Workbook
Name \A: '[1]טורים 98'!$HJ$133
Name \B: #REF!
Name \B: #REF!
Name \B: #REF!
Name \C: '[1]טורים 98'!$HJ$154
Name \D: '[1]טורים 98'!#REF!
Name \D: '[1]טורים 98'!#REF!
Name \D: '[1]טורים 98'!#REF!
Name \E: '[1]טורים 98'!$HJ$155
Name \F: '[1]טורים 98'!$GS$2
Name \H: '[1]טורים 98'!$B$336
Name \J: '[1]טורים 98'!$HJ$164
Name \K: '[1]טורים 98'!$HJ$166
Name \L: '[1]טורים 98'!$HJ$124
Name \M: '[1]טורים 98'!$HJ$121
Name \O: '[1]טורים 98'!$HJ$144
Name \P: '[1]טורים 98'!$GT$13
Name \Q: '[1]טורים 98'!$HJ$127
Name \R: '[1]טורים 98'!$HJ$118
Name \S: '[1]טורים 98'!$HJ$151
Name \U: '[1]טורים 98'!$HJ$116
Name \W: '[1]טורים 98'!$HJ$113
Name \X: '[1]טורים 98'!$HJ$146
Name \Y: '[1]טורים 98'!$GT$6
Name \Z: '[1]טורים 98'!$HJ$129
Name _______DAT1: #REF!
Name _______DAT1: #REF!
Name _______DAT1: #REF!
Name _______DAT10: #REF!
Name _______DAT10: #REF!
Name _______DAT10: #REF!
Name _______DAT11: #REF!
Name _______DAT11: #REF!
Name _______DAT11: #REF!
Name _______DAT12: #REF!
Name _______DAT12: #REF!
Name _______DAT12: #REF!
Name _______DAT13: #REF!
Name _______DAT13: #REF!
Name _______DAT13: #REF!
Name _______DAT14: #REF!
Name _______DAT14: #REF!
Name _______DAT14: #REF!
Name _______DAT15: #REF!
Name _______DAT15: #REF!
Name _______DAT15: #REF!
Name _______DAT2: #REF!
Name _______DAT2: #REF!
Name _______DAT2: #REF!
Name _______DAT3: #REF!
Name _______DAT3: #REF!
Name _______DAT3: #REF!
Name _______DAT4: #REF!
Name _______DAT4: #REF!
Name _______DAT4: #REF!
Name _______DAT5: #REF!
Name _______DAT5: #REF!
Name _______DAT5: #REF!
Name _______DAT6: #REF!
Name _______DAT6: #REF!

Sheet BS
B2: (IL) Ltd | C2: INC | D2: Consolidated | G2: s (IL) Ltd
B3: U S D O L L A R S | G3: Shekels | I3: הערת חשב
A4: Current Assets
A5: Cash & cash equivalents ISRAEL | B5: =SUMIF('TB - Ltd'!C:C,A5,'TB - Ltd'!J:J) -> 95452260 | C5: =SUMIF('TB - Inc'!C:C,A5,'TB - Inc'!F:F) -> 0 | D5: =SUM(B5:C5) -> 95452260 | G5: =SUMIF('TB - Ltd'!C:C,A5,'TB - Ltd'!G:G) -> 3.4620535e+08 | H5: =G5/B5 -> 3.627 | I5: אישורי יתרה
A6: Cash & cash equivalents US | B6: =SUMIF('TB - Ltd'!C:C,A6,'TB - Ltd'!J:J) -> 0 | C6: =SUMIF('TB - Inc'!C:C,A6,'TB - Inc'!F:F) -> 973689.67 | D6: =SUM(B6:C6) -> 973689.67 | G6: =SUMIF('TB - Ltd'!C:C,A6,'TB - Ltd'!G:G) -> 0
A7: Accounts receivable | B7: =SUMIF('TB - Ltd'!C:C,A7,'TB - Ltd'!J:J) -> 114017.44 | C7: =SUMIF('TB - Inc'!C:C,A7,'TB - Inc'!F:F) -> 808996.95 | D7: =SUM(B7:C7) -> 923014.39 | G7: =SUMIF('TB - Ltd'!C:C,A7,'TB - Ltd'!G:G) -> 413541.27 | H7: =G7/B7 -> 3.6270001 | I7: גיול לקוחות
A8: Accounts receivable - Sublease | B8: =SUMIF('TB - Ltd'!C:C,A8,'TB - Ltd'!J:J) -> 48986.45 | C8: =SUMIF('TB - Inc'!C:C,A8,'TB - Inc'!F:F) -> 0 | D8: =SUM(B8:C8) -> 48986.45 | G8: =SUMIF('TB - Ltd'!C:C,A8,'TB - Ltd'!G:G) -> 177673.86 | I8: יתרות משכירות משנה
A9: Prepaid Expenses | B9: =SUMIF('TB - Ltd'!C:C,A9,'TB - Ltd'!J:J) -> 362325.82 | C9: =SUMIF('TB - Inc'!C:C,A9,'TB - Inc'!F:F) -> 36085.73 | D9: =SUM(B9:C9) -> 398411.55 | G9: =SUMIF('TB - Ltd'!C:C,A9,'TB - Ltd'!G:G) -> 1365414.8 | H9: =G9/B9 -> 3.7684724 | I9: הרכב
A10: Intercompany | B10: =SUMIF('TB - Ltd'!C:C,A10,'TB - Ltd'!J:J) -> 531531.97 | C10: =SUMIF('TB - Inc'!C:C,A10,'TB - Inc'!F:F) -> -531532.06 | D10: =SUM(B10:C10) -> -0.088104535 | G10: =SUMIF('TB - Ltd'!C:C,A10,'TB - Ltd'!G:G) -> 1159373.9 | H10: =G10/B10 -> 2.1811931 | I10: מצורף חישוב בינחברתי
A11: Other Current Assets | B11: =SUMIF('TB - Ltd'!C:C,A11,'TB - Ltd'!J:J) -> 496783.84 | C11: =SUMIF('TB - Inc'!C:C,A11,'TB - Inc'!F:F) -> 0 | D11: =SUM(B11:C11) -> 496783.84 | G11: =SUMIF('TB - Ltd'!C:C,A11,'TB - Ltd'!G:G) -> 1801835 | H11: =G11/B11 -> 3.627 | I11: מע"מ - נובמבר+דצמבר ,מצורף אישור דיווח
A12: Total Current Assets | B12: =SUM(B5:B11) -> 97005905 | C12: =SUM(C5:C11) -> 1287240.3 | D12: =SUM(D5:D11) -> 98293145 | G12: =SUM(G5:G11) -> 3.5112318e+08 | I12: מצורף נייר ניכוי מס מפקדונות + פקדון DEEL
A14: Fixed Assets
A15: Short term bank credit | B15: =SUMIF('TB - Ltd'!#REF!,BS!#REF!,'TB - Ltd'!$J$4:$J$153) -> #REF! | C15: =SUMIF('TB - Inc'!#REF!,BS!#REF!,'TB - Inc'!#REF!) -> #REF! | D15: =SUM(B15:C15) -> #REF! | G15: =SUMIF('TB - Ltd'!#REF!,BS!#REF!,'TB - Ltd'!$G$4:$G$139) -> #REF!
A16: Computer equipment & software | B16: =SUMIF('TB - Ltd'!C:C,A16,'TB - Ltd'!J:J) -> 425011.87 | C16: =SUMIF('TB - Inc'!C:C,A16,'TB - Inc'!F:F) -> 57005.59 | D16: =SUM(B16:C16) -> 482017.46 | G16: =SUMIF('TB - Ltd'!C:C,A16,'TB - Ltd'!G:G) -> 1455299.6 | H16: =G16/B16 -> 3.4241388 | I16: טופס פחת מפורט
A17: Office furniture and equipment | B17: =SUMIF('TB - Ltd'!C:C,A17,'TB - Ltd'!J:J) -> 206676.16 | C17: =SUMIF('TB - Inc'!C:C,A17,'TB - Inc'!F:F) -> 0 | D17: =SUM(B17:C17) -> 206676.16 | G17: =SUMIF('TB - Ltd'!C:C,A17,'TB - Ltd'!G:G) -> 697676.2 | H17: =G17/B17 -> 3.3756975
A18: Lab equipments | B18: =SUMIF('TB - Ltd'!C:C,A18,'TB - Ltd'!J:J) -> 0 | C18: =SUMIF('TB - Inc'!C:C,A18,'TB - Inc'!F:F) -> 0 | D18: =SUM(B18:C18) -> 0 | G18: =SUMIF('TB - Ltd'!C:C,A18,'TB - Ltd'!G:G) -> 0
A19: Leasehold Improvements | B19: =SUMIF('TB - Ltd'!C:C,A19,'TB - Ltd'!J:J) -> 451119.09 | C19: =SUMIF('TB - Inc'!C:C,A19,'TB - Inc'!F:F) -> 0 | D19: =SUM(B19:C19) -> 451119.09 | G19: =SUMIF('TB - Ltd'!C:C,A19,'TB - Ltd'!G:G) -> 1529963.2 | H19: =G19/B19 -> 3.3914841
A20: Less accumulated depreciation | B20: =SUMIF('TB - Ltd'!C:C,A20,'TB - Ltd'!J:J) -> -281400.98 | C20: =SUMIF('TB - Inc'!C:C,A20,'TB - Inc'!F:F) -> -17730.99 | D20: =SUM(B20:C20) -> -299131.97 | G20: =SUMIF('TB - Ltd'!C:C,A20,'TB - Ltd'!G:G) -> -938083.8 | H20: =G20/B20 -> 3.3336195
A21: Total Fixed assets | B21: =SUM(B16:B20) -> 801406.14 | C21: =SUM(C16:C20) -> 39274.6 | D21: =SUM(D16:D20) -> 840680.74 | G21: =SUM(G16:G20) -> 2744855.2
A23: Other Long term Assets
A24: Operating lease ROU asset | B24: =SUMIF('TB - Ltd'!C:C,A24,'TB - Ltd'!J:J) -> 0 | C24: =SUMIF('TB - Inc'!C:C,A24,'TB - Inc'!F:F) -> 0 | D24: =SUM(B24:C24) -> 0 | G24: =SUMIF('TB - Ltd'!C:C,A24,'TB - Ltd'!G:G) -> 0
A25: Investment in subsidiary | B25: =SUMIF('TB - Ltd'!C:C,A25,'TB - Ltd'!J:J) -> 0 | C25: =SUMIF('TB - Inc'!C:C,A25,'TB - Inc'!F:F) -> 0 | D25: =SUM(B25:C25) -> 0
A26: Total Other Long term Assets | B26: =SUM(B24:B25) -> 0 | C26: =SUM(C24:C25) -> 0 | D26: =SUM(D24:D25) -> 0 | G26: =SUM(G24:G25) -> 0
A28: TOTAL ASSETS | B28: =B21+B12+B26 -> 97807311 | C28: =C21+C12+C26 -> 1326514.9 | D28: =D21+D12+D26 -> 99133826 | G28: =G21+G12+G26 -> 3.5386804e+08
A30: LIABILITIES & SHAREHOLDERS' EQUITY
A31: Current Liabilities
A32: Other short term loans | B32: =-SUMIF('TB - Ltd'!C:C,A32,'TB - Ltd'!J:J) -> 0 | C32: =-SUMIF('TB - Inc'!C:C,A32,'TB - Inc'!F:F) -> 0 | D32: =SUM(B32:C32) -> 0 | G32: =-SUMIF('TB - Ltd'!C:C,A32,'TB - Ltd'!G:G) -> 0
A33: Accounts payable | B33: =-SUMIF('TB - Ltd'!C:C,A33,'TB - Ltd'!J:J) -> -260809.43 | C33: =-SUMIF('TB - Inc'!C:C,A33,'TB - Inc'!F:F) -> 0 | D33: =SUM(B33:C33) -> -260809.43 | G33: =-SUMIF('TB - Ltd'!C:C,A33,'TB - Ltd'!G:G) -> -945955.84 | H33: =G33/B33 -> 3.6270001
A34: Accrued expenses | B34: =-SUMIF('TB - Ltd'!C:C,A34,'TB - Ltd'!J:J) -> 252626.47 | C34: =-SUMIF('TB - Inc'!C:C,A34,'TB - Inc'!F:F) -> 0 | D34: =SUM(B34:C34) -> 252626.47 | G34: =-SUMIF('TB - Ltd'!C:C,A34,'TB - Ltd'!G:G) -> 916277.88 | H34: =G34/B34 -> 3.6270066 | I34: הרכב
A35: Employee payables | B35: =-SUMIF('TB - Ltd'!C:C,A35,'TB - Ltd'!J:J) -> 690702.23 | C35: =-SUMIF('TB - Inc'!C:C,A35,'TB - Inc'!F:F) -> 169.6 | D35: =SUM(B35:C35) -> 690871.83 | G35: =-SUMIF('TB - Ltd'!C:C,A35,'TB - Ltd'!G:G) -> 2505177 | H35: =G35/B35 -> 3.627 | I35: פקודת שכר 12.23
A36: Employee institution | B36: =-SUMIF('TB - Ltd'!C:C,A36,'TB - Ltd'!J:J) -> 768178.1 | C36: =-SUMIF('TB - Inc'!C:C,A36,'TB - Inc'!F:F) -> 0 | D36: =SUM(B36:C36) -> 768178.1 | G36: =-SUMIF('TB - Ltd'!C:C,A36,'TB - Ltd'!G:G) -> 2786182 | H36: =G36/B36 -> 3.627 | I36: 102 + נייר עבודה
A37: Short term provisions - holiday accrual | B37: =-SUMIF('TB - Ltd'!C:C,A37,'TB - Ltd'!J:J) -> 504905.91 | C37: =-SUMIF('TB - Inc'!C:C,A37,'TB - Inc'!F:F) -> 0 | D37: =SUM(B37:C37) -> 504905.91 | G37: =-SUMIF('TB - Ltd'!C:C,A37,'TB - Ltd'!G:G) -> 1831293.7 | H37: =G37/B37 -> 3.627 | I37: דוח עתודה לחופשה והבראה
A38: Deffered revenues | B38: =-SUMIF('TB - Ltd'!C:C,A38,'TB - Ltd'!J:J) -> 131737 | C38: =-SUMIF('TB - Inc'!C:C,A38,'TB - Inc'!F:F) -> 1068361 | D38: =SUM(B38:C38) -> 1200098 | G38: =-SUMIF('TB - Ltd'!C:C,A38,'TB - Ltd'!G:G) -> 477810.46 | H38: =G38/B38 -> 3.6270027 | I38: נייר עבודה הכנסות נדחות
A39: Other short term liabilities | B39: =-SUMIF('TB - Ltd'!C:C,A39,'TB - Ltd'!J:J) -> 0 | C39: =-SUMIF('TB - Inc'!C:C,A39,'TB - Inc'!F:F) -> 0 | D39: =SUM(B39:C39) -> 0 | G39: =-SUMIF('TB - Ltd'!C:C,A39,'TB - Ltd'!G:G) -> 0
A40: Total Current Liabilities | B40: =SUM(B32:B39) -> 2087340.3 | C40: =SUM(C32:C39) -> 1068530.6 | D40: =SUM(D32:D39) -> 3155870.9 | G40: =SUM(G32:G39) -> 7570785.2
A42: Long term Liabilities
A43: Other long term liabilities | B43: =-SUMIF('TB - Ltd'!C:C,A43,'TB - Ltd'!J:J) -> 0 | C43: =-SUMIF('TB - Inc'!C:C,A43,'TB - Inc'!F:F) -> 0 | D43: =SUM(B43:C43) -> 0 | G43: =-SUMIF('TB - Ltd'!C:C,A43,'TB - Ltd'!G:G) -> 0
A45: Shareholders equity
A47: Preferred & Common Stock | B47: =-SUMIF('TB - Ltd'!C:C,A47,'TB - Ltd'!J:J) -> 0 | C47: =-SUMIF('TB - Inc'!C:C,A47,'TB - Inc'!F:F) -> 0 | D47: =SUM(B47:C47) -> 0 | G47: =-SUMIF('TB - Ltd'!C:C,A47,'TB - Ltd'!G:G) -> 0
A48: Additional paid in capital | B48: =-SUMIF('TB - Ltd'!C:C,A48,'TB - Ltd'!J:J) -> 1.3747636e+08 | C48: =-SUMIF('TB - Inc'!C:C,A48,'TB - Inc'!F:F) -> 1535 | D48: =SUM(B48:C48) -> 1.3747789e+08 | G48: =-SUMIF('TB - Ltd'!C:C,A48,'TB - Ltd'!G:G) -> 4.6306972e+08 | H48: =G48/B48 -> 3.368359
A49: Issuance Costs | B49: =-SUMIF('TB - Ltd'!C:C,A49,'TB - Ltd'!J:J) -> -73343.69 | C49: =-SUMIF('TB - Inc'!C:C,A49,'TB - Inc'!F:F) -> 0 | D49: =SUM(B49:C49) -> -73343.69 | G49: =-SUMIF('TB - Ltd'!C:C,A49,'TB - Ltd'!G:G) -> -253058.22 | H49: =G49/B49 -> 3.4503066
A50: Accumulated deficit | B50: =-SUMIF('TB - Ltd'!C:C,A50,'TB - Ltd'!J:J) -> -19986271 | C50: =-SUMIF('TB - Inc'!C:C,A50,'TB - Inc'!F:F) -> -5513.02 | D50: =SUM(B50:C50) -> -19991784 | G50: =-SUMIF('TB - Ltd'!C:C,A50,'TB - Ltd'!G:G) -> -51132568 | H50: =G50/B50 -> 2.5583846
A51: Profit (loss) - this year | B51: ='P&L'!B213 -> -21696771 | C51: ='P&L'!C213 -> 261962.31 | D51: ='P&L'!D213 -> -21434808 | G51: ='P&L'!G213 -> -65386837
A53: TOTAL LIABILITIES & SHAREHOLDERS' EQUITY | B53: =SUM(B47:B51)+B43+B40 -> 97807311 | C53: =SUM(C47:C51)+C43+C40 -> 1326514.9 | D53: =SUM(D47:D51)+D43+D40 -> 99133826 | E53: =SUM(E47:E51)+E43+E40 -> 0 | F53: =SUM(F47:F51)+F43+F40 -> 0 | G53: =SUM(G47:G51)+G43+G40 -> 3.5386804e+08
B55: =B53-B28 -> 0 | C55: =C53-C28 -> 0 | D55: =D53-D28 -> 0 | E55: =E53-E28 -> 0 | F55: =F53-F28 -> 0 | G55: =G53-G28 -> 0

Sheet P&L
B2: (IL) Ltd | C2: INC | D2: Consolidated | G2: s (IL) Ltd
B3: U S D O L L A R S | G3: Shekels
A5: Revenues - Income | B5: =-SUMIF('TB - Ltd'!C:C,A5,'TB - Ltd'!J:J) -> 204524.12 | C5: =-SUMIF('TB - Inc'!C:C,A5,'TB - Inc'!F:F) -> 964580.05 | D5: =SUM(B5:C5) -> 1169104.2 | G5: =-SUMIF('TB - Ltd'!C:C,A5,'TB - Ltd'!G:G) -> 770610.31
A6: Intercompany - P&L | B6: =-SUMIF('TB - Ltd'!C:C,A6,'TB - Ltd'!J:J) -> -8084166.7 | C6: =-SUMIF('TB - Inc'!C:C,A6,'TB - Inc'!F:F) -> 8084166.7 | D6: =SUM(B6:C6) -> 0 | G6: =-SUMIF('TB - Ltd'!C:C,A6,'TB - Ltd'!G:G) -> -30062412
B7: =SUM(B5:B6) -> -7879642.6 | C7: =SUM(C5:C6) -> 9048746.8 | D7: =SUM(D5:D6) -> 1169104.2 | G7: =SUM(G5:G6) -> -29291801
A10: Short term bank credit | B10: =SUMIF('TB - Ltd'!#REF!,'P&L'!#REF!,'TB - Ltd'!$J$4:$J$153) -> #REF! | C10: =SUMIF('TB - Inc'!#REF!,'P&L'!#REF!,'TB - Inc'!#REF!) -> #REF! | D10: =SUM(B10:C10) -> #REF! | G10: =SUMIF('TB - Ltd'!#REF!,'P&L'!#REF!,'TB - Ltd'!$G$4:$G$139) -> #REF!
A11: COS - Hosting | B11: =SUMIF('TB - Ltd'!C:C,A11,'TB - Ltd'!J:J) -> 164759.95 | C11: =SUMIF('TB - Inc'!C:C,A11,'TB - Inc'!F:F) -> 0 | D11: =SUM(B11:C11) -> 164759.95 | G11: =SUMIF('TB - Ltd'!C:C,A11,'TB - Ltd'!G:G) -> 597584.52
A12: COS - SW (product -variable) | B12: =SUMIF('TB - Ltd'!C:C,A12,'TB - Ltd'!J:J) -> 234738.46 | C12: =SUMIF('TB - Inc'!C:C,A12,'TB - Inc'!F:F) -> 0 | D12: =SUM(B12:C12) -> 234738.46 | G12: =SUMIF('TB - Ltd'!C:C,A12,'TB - Ltd'!G:G) -> 869455.83
A13: COS - SW (product-fixed) | B13: =SUMIF('TB - Ltd'!C:C,A13,'TB - Ltd'!J:J) -> 10944.46 | C13: =SUMIF('TB - Inc'!C:C,A13,'TB - Inc'!F:F) -> 0 | D13: =SUM(B13:C13) -> 10944.46 | G13: =SUMIF('TB - Ltd'!C:C,A13,'TB - Ltd'!G:G) -> 41182.09
A14: COS - Allocation from Support | B14: =SUMIF('TB - Ltd'!C:C,A14,'TB - Ltd'!J:J) -> 171469.77 | C14: =SUMIF('TB - Inc'!C:C,A14,'TB - Inc'!F:F) -> 0 | D14: =SUM(B14:C14) -> 171469.77 | G14: =SUMIF('TB - Ltd'!C:C,A14,'TB - Ltd'!G:G) -> 621921.69
A15: COS - Contingency (on expenses only) | B15: =SUMIF('TB - Ltd'!C:C,A15,'TB - Ltd'!J:J) -> 0 | C15: =SUMIF('TB - Inc'!C:C,A15,'TB - Inc'!F:F) -> 0 | D15: =SUM(B15:C15) -> 0 | G15: =SUMIF('TB - Ltd'!C:C,A15,'TB - Ltd'!G:G) -> 0
B16: =SUM(B11:B15) -> 581912.64 | C16: =SUM(C11:C15) -> 0 | D16: =SUM(D11:D15) -> 581912.64 | G16: =SUM(G11:G15) -> 2130144.1
B18: =B7-B16 -> -8461555.2 | C18: =C7-C16 -> 9048746.8 | D18: =D7-D16 -> 587191.53 | G18: =G7-G16 -> -31421946
B19: =B18/B7 -> 1.0738501 | C19: =C18/C7 -> 1 | D19: =D18/D7 -> 0.50225766 | G19: =G18/G7 -> 1.0727215
A21: Support
A22: Support - Salaries and social benefits | B22: =SUMIF('TB - Ltd'!C:C,A22,'TB - Ltd'!J:J) -> 164918.07 | C22: =SUMIF('TB - Inc'!C:C,A22,'TB - Inc'!F:F) -> 0 | D22: =SUM(B22:C22) -> 164918.07 | G22: =SUMIF('TB - Ltd'!C:C,A22,'TB - Ltd'!G:G) -> 610227.82
A23: Support - Recruiting | B23: =SUMIF('TB - Ltd'!C:C,A23,'TB - Ltd'!J:J) -> 0 | C23: =SUMIF('TB - Inc'!C:C,A23,'TB - Inc'!F:F) -> 0 | D23: =SUM(B23:C23) -> 0 | G23: =SUMIF('TB - Ltd'!C:C,A23,'TB - Ltd'!G:G) -> 0
A24: Support - Total Support MBO and social benefits ($) | B24: =SUMIF('TB - Ltd'!C:C,A24,'TB - Ltd'!J:J) -> 2403 | C24: =SUMIF('TB - Inc'!C:C,A24,'TB - Inc'!F:F) -> 0 | D24: =SUM(B24:C24) -> 2403 | G24: =SUMIF('TB - Ltd'!C:C,A24,'TB - Ltd'!G:G) -> 8715.681
A25: Support - Software Tools | B25: =SUMIF('TB - Ltd'!C:C,A25,'TB - Ltd'!J:J) -> 4148.4 | C25: =SUMIF('TB - Inc'!C:C,A25,'TB - Inc'!F:F) -> 0 | D25: =SUM(B25:C25) -> 4148.4 | G25: =SUMIF('TB - Ltd'!C:C,A25,'TB - Ltd'!G:G) -> 15737.38
A26: Support - Contingency | B26: =SUMIF('TB - Ltd'!C:C,A26,'TB - Ltd'!J:J) -> 12757.502 | C26: =SUMIF('TB - Inc'!C:C,A26,'TB - Inc'!F:F) -> 0 | D26: =SUM(B26:C26) -> 12757.502 | G26: =SUMIF('TB - Ltd'!C:C,A26,'TB - Ltd'!G:G) -> 37856.484
A27: Support - Allocation to COS | B27: =SUMIF('TB - Ltd'!C:C,A27,'TB - Ltd'!J:J) -> -171469.77 | C27: =SUMIF('TB - Inc'!C:C,A27,'TB - Inc'!F:F) -> 0 | D27: =SUM(B27:C27) -> -171469.77 | G27: =SUMIF('TB - Ltd'!C:C,A27,'TB - Ltd'!G:G) -> -621921.69
B28: =SUM(B22:B27) -> 12757.202 | C28: =SUM(C22:C27) -> 0 | D28: =SUM(D22:D27) -> 12757.202 | G28: =SUM(G22:G27) -> 50615.674
A30: Engineering | B30: `
A31: Engineering - Salaries and social benefits | B31: =SUMIF('TB - Ltd'!C:C,A31,'TB - Ltd'!J:J) -> 10085869 | C31: =SUMIF('TB - Inc'!C:C,A31,'TB - Inc'!F:F) -> 135469.86 | D31: =SUM(B31:C31) -> 10221339 | G31: =SUMIF('TB - Ltd'!C:C,A31,'TB - Ltd'!G:G) -> 37399383
A32: Engineering - Recruiting | B32: =SUMIF('TB - Ltd'!C:C,A32,'TB - Ltd'!J:J) -> 22237.83 | C32: =SUMIF('TB - Inc'!C:C,A32,'TB - Inc'!F:F) -> 0 | D32: =SUM(B32:C32) -> 22237.83 | G32: =SUMIF('TB - Ltd'!C:C,A32,'TB - Ltd'!G:G) -> 79000
A33: Engineering - Total Engineering MBO and social benefits ($) | B33: =SUMIF('TB - Ltd'!C:C,A33,'TB - Ltd'!J:J) -> 643 | C33: =SUMIF('TB - Inc'!C:C,A33,'TB - Inc'!F:F) -> 0 | D33: =SUM(B33:C33) -> 643 | G33: =SUMIF('TB - Ltd'!C:C,A33,'TB - Ltd'!G:G) -> 2332.161
A34: Engineering - Ongoing/random outsourced | B34: =SUMIF('TB - Ltd'!C:C,A34,'TB - Ltd'!J:J) -> 148951.75 | C34: =SUMIF('TB - Inc'!C:C,A34,'TB - Inc'!F:F) -> 0 | D34: =SUM(B34:C34) -> 148951.75 | G34: =SUMIF('TB - Ltd'!C:C,A34,'TB - Ltd'!G:G) -> 560627.71
A35: Engineering - Options | B35: =SUMIF('TB - Ltd'!C:C,A35,'TB - Ltd'!J:J) -> 384964.66 | C35: =SUMIF('TB - Inc'!C:C,A35,'TB - Inc'!F:F) -> 26607.4 | D35: =SUM(B35:C35) -> 411572.06 | G35: =SUMIF('TB - Ltd'!C:C,A35,'TB - Ltd'!G:G) -> 1395111.9
A36: Engineering - Hosting | B36: =SUMIF('TB - Ltd'!C:C,A36,'TB - Ltd'!J:J) -> 442474.5 | C36: =SUMIF('TB - Inc'!C:C,A36,'TB - Inc'!F:F) -> 40000 | D36: =SUM(B36:C36) -> 482474.5 | G36: =SUMIF('TB - Ltd'!C:C,A36,'TB - Ltd'!G:G) -> 1662016.5
A37: Engineering - Development software tools | B37: =SUMIF('TB - Ltd'!C:C,A37,'TB - Ltd'!J:J) -> 288287.64 | C37: =SUMIF('TB - Inc'!C:C,A37,'TB - Inc'!F:F) -> 4500 | D37: =SUM(B37:C37) -> 292787.64 | G37: =SUMIF('TB - Ltd'!C:C,A37,'TB - Ltd'!G:G) -> 1026197.1
A38: Engineering - Training / Professional courses | B38: =SUMIF('TB - Ltd'!C:C,A38,'TB - Ltd'!J:J) -> 7020.1 | C38: =SUMIF('TB - Inc'!C:C,A38,'TB - Inc'!F:F) -> 0 | D38: =SUM(B38:C38) -> 7020.1 | G38: =SUMIF('TB - Ltd'!C:C,A38,'TB - Ltd'!G:G) -> 25550
A39: Engineering - Guest/Client hospitality | B39: =SUMIF('TB - Ltd'!C:C,A39,'TB - Ltd'!J:J) -> 83.44 | C39: =SUMIF('TB - Inc'!C:C,A39,'TB - Inc'!F:F) -> 0 | D39: =SUM(B39:C39) -> 83.44 | G39: =SUMIF('TB - Ltd'!C:C,A39,'TB - Ltd'!G:G) -> 297
A40: Engineering - Travel | B40: =SUMIF('TB - Ltd'!C:C,A40,'TB - Ltd'!J:J) -> 20326.1 | C40: =SUMIF('TB - Inc'!C:C,A40,'TB - Inc'!F:F) -> 0 | D40: =SUM(B40:C40) -> 20326.1 | G40: =SUMIF('TB - Ltd'!C:C,A40,'TB - Ltd'!G:G) -> 77438.98
A41: Engineering - Contingency | B41: =SUMIF('TB - Ltd'!C:C,A41,'TB - Ltd'!J:J) -> 880267.65 | C41: =SUMIF('TB - Inc'!C:C,A41,'TB - Inc'!F:F) -> 0 | D41: =SUM(B41:C41) -> 880267.65 | G41: =SUMIF('TB - Ltd'!C:C,A41,'TB - Ltd'!G:G) -> 2612097.4
B42: =SUM(B31:B41) -> 12281126 | C42: =SUM(C31:C41) -> 206577.26 | D42: =SUM(D31:D41) -> 12487703 | G42: =SUM(G31:G41) -> 44840052
A44: Product
A45: Product - Salaries and social benefits | B45: =SUMIF('TB - Ltd'!C:C,A45,'TB - Ltd'!J:J) -> 2111370 | C45: =SUMIF('TB - Inc'!C:C,A45,'TB - Inc'!F:F) -> 0 | D45: =SUM(B45:C45) -> 2111370 | G45: =SUMIF('TB - Ltd'!C:C,A45,'TB - Ltd'!G:G) -> 7809642.5
A46: Product - Recruiting | B46: =SUMIF('TB - Ltd'!C:C,A46,'TB - Ltd'!J:J) -> 112.99 | C46: =SUMIF('TB - Inc'!C:C,A46,'TB - Inc'!F:F) -> 0 | D46: =SUM(B46:C46) -> 112.99 | G46: =SUMIF('TB - Ltd'!C:C,A46,'TB - Ltd'!G:G) -> 413.46
A47: Product - Ongoing/random outsourced | B47: =SUMIF('TB - Ltd'!C:C,A47,'TB - Ltd'!J:J) -> 6385.7 | C47: =SUMIF('TB - Inc'!C:C,A47,'TB - Inc'!F:F) -> 0 | D47: =SUM(B47:C47) -> 6385.7 | G47: =SUMIF('TB - Ltd'!C:C,A47,'TB - Ltd'!G:G) -> 24572.16
A48: Product - Product certification & compliance | B48: =SUMIF('TB - Ltd'!C:C,A48,'TB - Ltd'!J:J) -> 38687.72 | C48: =SUMIF('TB - Inc'!C:C,A48,'TB - Inc'!F:F) -> 0 | D48: =SUM(B48:C48) -> 38687.72 | G48: =SUMIF('TB - Ltd'!C:C,A48,'TB - Ltd'!G:G) -> 138112.29
A49: Product - Training / Professional courses | B49: =SUMIF('TB - Ltd'!C:C,A49,'TB - Ltd'!J:J) -> 694.02 | C49: =SUMIF('TB - Inc'!C:C,A49,'TB - Inc'!F:F) -> 0 | D49: =SUM(B49:C49) -> 694.02 | G49: =SUMIF('TB - Ltd'!C:C,A49,'TB - Ltd'!G:G) -> 2538.46
A50: Product - Software Tools | B50: =SUMIF('TB - Ltd'!C:C,A50,'TB - Ltd'!J:J) -> 58239.59 | C50: =SUMIF('TB - Inc'!C:C,A50,'TB - Inc'!F:F) -> 0 | D50: =SUM(B50:C50) -> 58239.59 | G50: =SUMIF('TB - Ltd'!C:C,A50,'TB - Ltd'!G:G) -> 217326.47
A51: Product - Travel | B51: =SUMIF('TB - Ltd'!C:C,A51,'TB - Ltd'!J:J) -> 40291.04 | C51: =SUMIF('TB - Inc'!C:C,A51,'TB - Inc'!F:F) -> 0 | D51: =SUM(B51:C51) -> 40291.04 | G51: =SUMIF('TB - Ltd'!C:C,A51,'TB - Ltd'!G:G) -> 150959.96
A52: Product - Contingency | B52: =SUMIF('TB - Ltd'!C:C,A52,'TB - Ltd'!J:J) -> 0 | C52: =SUMIF('TB - Inc'!C:C,A52,'TB - Inc'!F:F) -> 0 | D52: =SUM(B52:C52) -> 0 | G52: =SUMIF('TB - Ltd'!C:C,A52,'TB - Ltd'!G:G) -> 0
A53: Product - Options | B53: =SUMIF('TB - Ltd'!C:C,A53,'TB - Ltd'!J:J) -> 72510.852 | C53: =SUMIF('TB - Inc'!C:C,A53,'TB - Inc'!F:F) -> 0 | D53: =SUM(B53:C53) -> 72510.852 | G53: =SUMIF('TB - Ltd'!C:C,A53,'TB - Ltd'!G:G) -> 262779.33
B54: =SUM(B45:B53) -> 2328291.9 | C54: =SUM(C45:C53) -> 0 | D54: =SUM(D45:D53) -> 2328291.9 | G54: =SUM(G45:G53) -> 8606344.7
A56: IT
A57: IT - Salaries and social benefits | B57: =SUMIF('TB - Ltd'!C:C,A57,'TB - Ltd'!J:J) -> 39469.93 | C57: =SUMIF('TB - Inc'!C:C,A57,'TB - Inc'!F:F) -> 0 | D57: =SUM(B57:C57) -> 39469.93 | G57: =SUMIF('TB - Ltd'!C:C,A57,'TB - Ltd'!G:G) -> 149069.5
A58: IT - IT equipment | B58: =SUMIF('TB - Ltd'!C:C,A58,'TB - Ltd'!J:J) -> 26338.99 | C58: =SUMIF('TB - Inc'!C:C,A58,'TB - Inc'!F:F) -> 8966.13 | D58: =SUM(B58:C58) -> 35305.12 | G58: =SUMIF('TB - Ltd'!C:C,A58,'TB - Ltd'!G:G) -> 97232.73
A59: IT - Cyber protection tools | B59: =SUMIF('TB - Ltd'!C:C,A59,'TB - Ltd'!J:J) -> 35559.99 | C59: =SUMIF('TB - Inc'!C:C,A59,'TB - Inc'!F:F) -> 0 | D59: =SUM(B59:C59) -> 35559.99 | G59: =SUMIF('TB - Ltd'!C:C,A59,'TB - Ltd'!G:G) -> 127341.99
A60: IT - Company IT SW | B60: =SUMIF('TB - Ltd'!C:C,A60,'TB - Ltd'!J:J) -> 57595.68 | C60: =SUMIF('TB - Inc'!C:C,A60,'TB - Inc'!F:F) -> 1613.31 | D60: =SUM(B60:C60) -> 59208.99 | G60: =SUMIF('TB - Ltd'!C:C,A60,'TB - Ltd'!G:G) -> 216883.05
A61: IT - IT SW tools | B61: =SUMIF('TB - Ltd'!C:C,A61,'TB - Ltd'!J:J) -> 16477.55 | C61: =SUMIF('TB - Inc'!C:C,A61,'TB - Inc'!F:F) -> 0 | D61: =SUM(B61:C61) -> 16477.55 | G61: =SUMIF('TB - Ltd'!C:C,A61,'TB - Ltd'!G:G) -> 59393.65
A62: IT - Company wide certifications | B62: =SUMIF('TB - Ltd'!C:C,A62,'TB - Ltd'!J:J) -> 0 | C62: =SUMIF('TB - Inc'!C:C,A62,'TB - Inc'!F:F) -> 0 | D62: =SUM(B62:C62) -> 0 | G62: =SUMIF('TB - Ltd'!C:C,A62,'TB - Ltd'!G:G) -> 0
A63: IT - Communications expenses (internet, calls) | B63: =SUMIF('TB - Ltd'!C:C,A63,'TB - Ltd'!J:J) -> 19634.99 | C63: =SUMIF('TB - Inc'!C:C,A63,'TB - Inc'!F:F) -> 3269.47 | D63: =SUM(B63:C63) -> 22904.46 | G63: =SUMIF('TB - Ltd'!C:C,A63,'TB - Ltd'!G:G) -> 71644.72
A64: IT - Travel | B64: =SUMIF('TB - Ltd'!C:C,A64,'TB - Ltd'!J:J) -> 0 | C64: =SUMIF('TB - Inc'!C:C,A64,'TB - Inc'!F:F) -> 0 | D64: =SUM(B64:C64) -> 0 | G64: =SUMIF('TB - Ltd'!C:C,A64,'TB - Ltd'!G:G) -> 0
A65: IT - Contingency | B65: =SUMIF('TB - Ltd'!C:C,A65,'TB - Ltd'!J:J) -> 0 | C65: =SUMIF('TB - Inc'!C:C,A65,'TB - Inc'!F:F) -> 0 | D65: =SUM(B65:C65) -> 0 | G65: =SUMIF('TB - Ltd'!C:C,A65,'TB - Ltd'!G:G) -> 0
B66: =SUM(B57:B65) -> 195077.13 | C66: =SUM(C57:C65) -> 13848.91 | D66: =SUM(D57:D65) -> 208926.04 | G66: =SUM(G57:G65) -> 721565.64
A68: IP
A69: IP - Salaries and social benefits | B69: =SUMIF('TB - Ltd'!C:C,A69,'TB - Ltd'!J:J) -> 0 | C69: =SUMIF('TB - Inc'!C:C,A69,'TB - Inc'!F:F) -> 0 | D69: =SUM(B69:C69) -> 0 | G69: =SUMIF('TB - Ltd'!C:C,A69,'TB - Ltd'!G:G) -> 0
A70: IP - Recruiting | B70: =SUMIF('TB - Ltd'!C:C,A70,'TB - Ltd'!J:J) -> 0 | C70: =SUMIF('TB - Inc'!C:C,A70,'TB - Inc'!F:F) -> 0 | D70: =SUM(B70:C70) -> 0 | G70: =SUMIF('TB - Ltd'!C:C,A70,'TB - Ltd'!G:G) -> 0
A71: IP - Total IP MBO and social benefits ($) | B71: =SUMIF('TB - Ltd'!C:C,A71,'TB - Ltd'!J:J) -> 0 | C71: =SUMIF('TB - Inc'!C:C,A71,'TB - Inc'!F:F) -> 0 | D71: =SUM(B71:C71) -> 0 | G71: =SUMIF('TB - Ltd'!C:C,A71,'TB - Ltd'!G:G) -> 0
A72: IP - Longer term outsource compensation | B72: =SUMIF('TB - Ltd'!C:C,A72,'TB - Ltd'!J:J) -> 0 | C72: =SUMIF('TB - Inc'!C:C,A72,'TB - Inc'!F:F) -> 0 | D72: =SUM(B72:C72) -> 0 | G72: =SUMIF('TB - Ltd'!C:C,A72,'TB - Ltd'!G:G) -> 0
A73: IP - Ongoing/random outsourced | B73: =SUMIF('TB - Ltd'!C:C,A73,'TB - Ltd'!J:J) -> 0 | C73: =SUMIF('TB - Inc'!C:C,A73,'TB - Inc'!F:F) -> 0 | D73: =SUM(B73:C73) -> 0 | G73: =SUMIF('TB - Ltd'!C:C,A73,'TB - Ltd'!G:G) -> 0
A74: IP - Options | B74: =SUMIF('TB - Ltd'!C:C,A74,'TB - Ltd'!J:J) -> 0 | C74: =SUMIF('TB - Inc'!C:C,A74,'TB - Inc'!F:F) -> 0 | D74: =SUM(B74:C74) -> 0 | G74: =SUMIF('TB - Ltd'!C:C,A74,'TB - Ltd'!G:G) -> 0
A75: IP - Patent application fees & office action fees | B75: =SUMIF('TB - Ltd'!C:C,A75,'TB - Ltd'!J:J) -> 87147.56 | C75: =SUMIF('TB - Inc'!C:C,A75,'TB - Inc'!F:F) -> 0 | D75: =SUM(B75:C75) -> 87147.56 | G75: =SUMIF('TB - Ltd'!C:C,A75,'TB - Ltd'!G:G) -> 324562.17
A76: IP - Contingency | B76: =SUMIF('TB - Ltd'!C:C,A76,'TB - Ltd'!J:J) -> 0 | C76: =SUMIF('TB - Inc'!C:C,A76,'TB - Inc'!F:F) -> 0 | D76: =SUM(B76:C76) -> 0 | G76: =SUMIF('TB - Ltd'!C:C,A76,'TB - Ltd'!G:G) -> 0
B77: =SUM(B69:B76) -> 87147.56 | C77: =SUM(C69:C76) -> 0 | D77: =SUM(D69:D76) -> 87147.56 | G77: =SUM(G69:G76) -> 324562.17
A80: Customer Success
A81: Customer Success - Salaries and social benefits | B81: =SUMIF('TB - Ltd'!C:C,A81,'TB - Ltd'!J:J) -> 315968.5 | C81: =SUMIF('TB - Inc'!C:C,A81,'TB - Inc'!F:F) -> 984651.76 | D81: =SUM(B81:C81) -> 1300620.3 | G81: =SUMIF('TB - Ltd'!C:C,A81,'TB - Ltd'!G:G) -> 1164357.9
A82: Customer Success - Recruiting | B82: =SUMIF('TB - Ltd'!C:C,A82,'TB - Ltd'!J:J) -> 0 | C82: =SUMIF('TB - Inc'!C:C,A82,'TB - Inc'!F:F) -> 0 | D82: =SUM(B82:C82) -> 0 | G82: =SUMIF('TB - Ltd'!C:C,A82,'TB - Ltd'!G:G) -> 0
A83: Customer Success - Total Customer Success MBO and social benefits ($) | B83: =SUMIF('TB - Ltd'!C:C,A83,'TB - Ltd'!J:J) -> 3119 | C83: =SUMIF('TB - Inc'!C:C,A83,'TB - Inc'!F:F) -> 175479.81 | D83: =SUM(B83:C83) -> 178598.81 | G83: =SUMIF('TB - Ltd'!C:C,A83,'TB - Ltd'!G:G) -> 11312.613
A84: Customer Success - Longer term outsource compensation | B84: =SUMIF('TB - Ltd'!C:C,A84,'TB - Ltd'!J:J) -> 0 | C84: =SUMIF('TB - Inc'!C:C,A84,'TB - Inc'!F:F) -> 0 | D84: =SUM(B84:C84) -> 0 | G84: =SUMIF('TB - Ltd'!C:C,A84,'TB - Ltd'!G:G) -> 0
A85: Customer Success - Ongoing/random outsourced | B85: =SUMIF('TB - Ltd'!C:C,A85,'TB - Ltd'!J:J) -> 0 | C85: =SUMIF('TB - Inc'!C:C,A85,'TB - Inc'!F:F) -> 0 | D85: =SUM(B85:C85) -> 0 | G85: =SUMIF('TB - Ltd'!C:C,A85,'TB - Ltd'!G:G) -> 0
A86: Customer Success - Options | B86: =SUMIF('TB - Ltd'!C:C,A86,'TB - Ltd'!J:J) -> 21805.907 | C86: =SUMIF('TB - Inc'!C:C,A86,'TB - Inc'!F:F) -> 9107.2 | D86: =SUM(B86:C86) -> 30913.107 | G86: =SUMIF('TB - Ltd'!C:C,A86,'TB - Ltd'!G:G) -> 79024.608
A87: Customer Success - Software Tools | B87: =SUMIF('TB - Ltd'!C:C,A87,'TB - Ltd'!J:J) -> 23533.42 | C87: =SUMIF('TB - Inc'!C:C,A87,'TB - Inc'!F:F) -> 9720 | D87: =SUM(B87:C87) -> 33253.42 | G87: =SUMIF('TB - Ltd'!C:C,A87,'TB - Ltd'!G:G) -> 85711.19
A88: Customer Success - Training / Professional courses | B88: =SUMIF('TB - Ltd'!C:C,A88,'TB - Ltd'!J:J) -> 2325.58 | C88: =SUMIF('TB - Inc'!C:C,A88,'TB - Inc'!F:F) -> 0 | D88: =SUM(B88:C88) -> 2325.58 | G88: =SUMIF('TB - Ltd'!C:C,A88,'TB - Ltd'!G:G) -> 8400
A89: Customer Success - Travel | B89: =SUMIF('TB - Ltd'!C:C,A89,'TB - Ltd'!J:J) -> 14151.65 | C89: =SUMIF('TB - Inc'!C:C,A89,'TB - Inc'!F:F) -> 2779.38 | D89: =SUM(B89:C89) -> 16931.03 | G89: =SUMIF('TB - Ltd'!C:C,A89,'TB - Ltd'!G:G) -> 53031.1
A90: Customer Success - Contingency | B90: =SUMIF('TB - Ltd'!C:C,A90,'TB - Ltd'!J:J) -> 25515.004 | C90: =SUMIF('TB - Inc'!C:C,A90,'TB - Inc'!F:F) -> 0 | D90: =SUM(B90:C90) -> 25515.004 | G90: =SUMIF('TB - Ltd'!C:C,A90,'TB - Ltd'!G:G) -> 75712.968
B91: =SUM(B81:B90) -> 406419.06 | C91: =SUM(C81:C90) -> 1181738.1 | D91: =SUM(D81:D90) -> 1588157.2 | G91: =SUM(G81:G90) -> 1477550.3
A92: Marketing
A93: Marketing - Salaries and social benefits | B93: =SUMIF('TB - Ltd'!C:C,A93,'TB - Ltd'!J:J) -> 216246.86 | C93: =SUMIF('TB - Inc'!C:C,A93,'TB - Inc'!F:F) -> 1528683.5 | D93: =SUM(B93:C93) -> 1744930.4 | G93: =SUMIF('TB - Ltd'!C:C,A93,'TB - Ltd'!G:G) -> 806707.3
A94: Marketing - Total Marketing MBO and social benefits ($) | B94: =SUMIF('TB - Ltd'!C:C,A94,'TB - Ltd'!J:J) -> 0 | C94: =SUMIF('TB - Inc'!C:C,A94,'TB - Inc'!F:F) -> 273627.35 | D94: =SUM(B94:C94) -> 273627.35 | G94: =SUMIF('TB - Ltd'!C:C,A94,'TB - Ltd'!G:G) -> 0
A95: Marketing - Ongoing/random outsourced | B95: =SUMIF('TB - Ltd'!C:C,A95,'TB - Ltd'!J:J) -> 76255.02 | C95: =SUMIF('TB - Inc'!C:C,A95,'TB - Inc'!F:F) -> 61337.5 | D95: =SUM(B95:C95) -> 137592.52 | G95: =SUMIF('TB - Ltd'!C:C,A95,'TB - Ltd'!G:G) -> 278735.28
A96: Marketing - Software Tools | B96: =SUMIF('TB - Ltd'!C:C,A96,'TB - Ltd'!J:J) -> 52526.59 | C96: =SUMIF('TB - Inc'!C:C,A96,'TB - Inc'!F:F) -> 30899.16 | D96: =SUM(B96:C96) -> 83425.75 | G96: =SUMIF('TB - Ltd'!C:C,A96,'TB - Ltd'!G:G) -> 194245.8
A97: Marketing - Alliances | B97: =SUMIF('TB - Ltd'!C:C,A97,'TB - Ltd'!J:J) -> 3085.27 | C97: =SUMIF('TB - Inc'!C:C,A97,'TB - Inc'!F:F) -> 0 | D97: =SUM(B97:C97) -> 3085.27 | G97: =SUMIF('TB - Ltd'!C:C,A97,'TB - Ltd'!G:G) -> 11804.26
A98: Marketing - PR- Direct Cost | B98: =SUMIF('TB - Ltd'!C:C,A98,'TB - Ltd'!J:J) -> 0 | C98: =SUMIF('TB - Inc'!C:C,A98,'TB - Inc'!F:F) -> 0 | D98: =SUM(B98:C98) -> 0 | G98: =SUMIF('TB - Ltd'!C:C,A98,'TB - Ltd'!G:G) -> 0
A99: Marketing - Website | B99: =SUMIF('TB - Ltd'!C:C,A99,'TB - Ltd'!J:J) -> 158815.03 | C99: =SUMIF('TB - Inc'!C:C,A99,'TB - Inc'!F:F) -> 0 | D99: =SUM(B99:C99) -> 158815.03 | G99: =SUMIF('TB - Ltd'!C:C,A99,'TB - Ltd'!G:G) -> 581072.05
A100: Marketing - Digital Marketing_US | B100: =SUMIF('TB - Ltd'!C:C,A100,'TB - Ltd'!J:J) -> 184267.05 | C100: =SUMIF('TB - Inc'!C:C,A100,'TB - Inc'!F:F) -> 146348.56 | D100: =SUM(B100:C100) -> 330615.61 | G100: =SUMIF('TB - Ltd'!C:C,A100,'TB - Ltd'!G:G) -> 668660.19
A101: Marketing - Digital Marketing_ISRAEL | B101: =SUMIF('TB - Ltd'!C:C,A101,'TB - Ltd'!J:J) -> 20000 | C101: =SUMIF('TB - Inc'!C:C,A101,'TB - Inc'!F:F) -> 0 | D101: =SUM(B101:C101) -> 20000 | G101: =SUMIF('TB - Ltd'!C:C,A101,'TB - Ltd'!G:G) -> 74125
A102: Marketing - PR agency_US | B102: =SUMIF('TB - Ltd'!C:C,A102,'TB - Ltd'!J:J) -> 32474.77 | C102: =SUMIF('TB - Inc'!C:C,A102,'TB - Inc'!F:F) -> 27600 | D102: =SUM(B102:C102) -> 60074.77 | G102: =SUMIF('TB - Ltd'!C:C,A102,'TB - Ltd'!G:G) -> 119941.95
A103: Marketing - Branding Project | B103: =SUMIF('TB - Ltd'!C:C,A103,'TB - Ltd'!J:J) -> 1143.34 | C103: =SUMIF('TB - Inc'!C:C,A103,'TB - Inc'!F:F) -> 0 | D103: =SUM(B103:C103) -> 1143.34 | G103: =SUMIF('TB - Ltd'!C:C,A103,'TB - Ltd'!G:G) -> 4215.38
A104: Marketing - Swag- Employee | B104: =SUMIF('TB - Ltd'!C:C,A104,'TB - Ltd'!J:J) -> 58000.32 | C104: =SUMIF('TB - Inc'!C:C,A104,'TB - Inc'!F:F) -> 0 | D104: =SUM(B104:C104) -> 58000.32 | G104: =SUMIF('TB - Ltd'!C:C,A104,'TB - Ltd'!G:G) -> 212183.93
... A119: Marketing - Options | B119: =SUMIF('TB - Ltd'!C:C,A119,'TB - Ltd'!J:J) -> 2889.6321 | C119: =SUMIF('TB - Inc'!C:C,A119,'TB - Inc'!F:F) -> 38253 | D119: =SUM(B119:C119) -> 41142.632 | G119: =SUMIF('TB - Ltd'!C:C,A119,'TB - Ltd'!G:G) -> 10472.027
B120: =SUM(B93:B119) -> 1494873.4 | C120: =SUM(C93:C119) -> 2777347.6 | D120: =SUM(D93:D119) -> 4272221 | G120: =SUM(G93:G119) -> 5421265.1
A121: Sales
A122: Sales - Salaries and social benefits | B122: =SUMIF('TB - Ltd'!C:C,A122,'TB - Ltd'!J:J) -> 256205.5 | C122: =SUMIF('TB - Inc'!C:C,A122,'TB - Inc'!F:F) -> 2213752.1 | D122: =SUM(B122:C122) -> 2469957.6 | G122: =SUMIF('TB - Ltd'!C:C,A122,'TB - Ltd'!G:G) -> 944918.22
A123: Sales - Recruiting | B123: =SUMIF('TB - Ltd'!C:C,A123,'TB - Ltd'!J:J) -> 182.55 | C123: =SUMIF('TB - Inc'!C:C,A123,'TB - Inc'!F:F) -> 484.52 | D123: =SUM(B123:C123) -> 667.07 | G123: =SUMIF('TB - Ltd'!C:C,A123,'TB - Ltd'!G:G) -> 634
A124: Sales - Sales Commission | B124: =SUMIF('TB - Ltd'!C:C,A124,'TB - Ltd'!J:J) -> 4825 | C124: =SUMIF('TB - Inc'!C:C,A124,'TB - Inc'!F:F) -> 609393.1 | D124: =SUM(B124:C124) -> 614218.1 | G124: =SUMIF('TB - Ltd'!C:C,A124,'TB - Ltd'!G:G) -> 17500.275
A125: Sales - Total Sales MBO and social benefits ($) | B125: =SUMIF('TB - Ltd'!C:C,A125,'TB - Ltd'!J:J) -> 0 | C125: =SUMIF('TB - Inc'!C:C,A125,'TB - Inc'!F:F) -> 370837.08 | D125: =SUM(B125:C125) -> 370837.08 | G125: =SUMIF('TB - Ltd'!C:C,A125,'TB - Ltd'!G:G) -> 0
A126: Sales - Ongoing/random outsourced | B126: =SUMIF('TB - Ltd'!C:C,A126,'TB - Ltd'!J:J) -> 447973.82 | C126: =SUMIF('TB - Inc'!C:C,A126,'TB - Inc'!F:F) -> -95000 | D126: =SUM(B126:C126) -> 352973.82 | G126: =SUMIF('TB - Ltd'!C:C,A126,'TB - Ltd'!G:G) -> 1692183.2
...

Sheet TB - Ltd
E1: =SUM(E3:E537) -> -9.5560608e-08 | F1: =SUM(F3:F537) -> 1.8626451e-09 | G1: =SUM(G3:G537) -> 5.0295057e-09 | H1: =SUM(H3:H537) -> -2.0207381e-08 | I1: =SUM(I3:I537) -> 0 | J1: =SUM(J3:J537) -> -3.4435743e-09
A2: חשבון | B2: תאור החשבון | D2: BS/PL | E2: ספרים - ש"ח | F2: פ"נ ש"ח | G2: סופי - ש"ח | H2: ספרים - דולר | I2: פ"נ - דולר | J2: סופי - דולר
A3: 10001 | B3: בנק הפועלים 174/9550 $ | C3: Cash & cash equivalents ISRAEL | D3: BS | E3: 1.6487672e+08 | F3: =SUMIF('JE - LTD '!A:A,'TB - Ltd'!A3,'JE - LTD '!D:D) -> 0 | G3: =E3+F3 -> 1.6487672e+08 | H3: 45458154 | I3: =SUMIF('JE - LTD '!A:A,'TB - Ltd'!A3,'JE - LTD '!C:C) -> 0 | J3: =H3+I3 -> 45458154 | K3: =G3/J3 -> 3.627
A4: 10002 | B4: בנק הפועלים 174/9550 יורו | C4: Cash & cash equivalents ISRAEL | D4: BS | E4: -278046.44 | F4: =SUMIF('JE - LTD '!A:A,'TB - Ltd'!A4,'JE - LTD '!D:D) -> 0 | G4: =E4+F4 -> -278046.44 | H4: -76660.17 | I4: =SUMIF('JE - LTD '!A:A,'TB - Ltd'!A4,'JE - LTD '!C:C) -> 0 | J4: =H4+I4 -> -76660.17 | K4: =G4/J4 -> 3.627
A5: 10322 | B5: פקדון $ בנק הפועלים 356789013 | C5: Cash & cash equivalents ISRAEL | D5: BS | E5: 679272.29 | F5: =SUMIF('JE - LTD '!A:A,'TB - Ltd'!A5,'JE - LTD '!D:D) -> 0 | G5: =E5+F5 -> 679272.29 | H5: 187282.13 | I5: =SUMIF('JE - LTD '!A:A,'TB - Ltd'!A5,'JE - LTD '!C:C) -> 0 | J5: =H5+I5 -> 187282.13 | K5: =G5/J5 -> 3.627
A6: 10300 | B6: פקדון ש"ח בנק הפועלים | C6: Cash & cash equivalents ISRAEL | D6: BS | E6: 25401555 | F6: =SUMIF('JE - LTD '!A:A,'TB - Ltd'!A6,'JE - LTD '!D:D) -> 0 | G6: =E6+F6 -> 25401555 | H6: 7003461.4 | I6: =SUMIF('JE - LTD '!A:A,'TB - Ltd'!A6,'JE - LTD '!C:C) -> 0 | J6: =H6+I6 -> 7003461.4 | K6: =G6/J6 -> 3.627
A7: 10207 | B7: MESH | C7: Other Current Assets | D7: BS | E7: 480633.03 | F7: =SUMIF('JE - LTD '!A:A,'TB - Ltd'!A7,'JE - LTD '!D:D) -> 0 | G7: =E7+F7 -> 480633.03 | H7: 132515.31 | I7: =SUMIF('JE - LTD '!A:A,'TB - Ltd'!A7,'JE - LTD '!C:C) -> 0 | J7: =H7+I7 -> 132515.31 | K7: =G7/J7 -> 3.627
A8: 10200 | B8: כרטיס אשראי 1784 ש"ח | C8: Accounts payable | D8: BS | E8: -4936.29 | F8: =SUMIF('JE - LTD '!A:A,'TB - Ltd'!A8,'JE - LTD '!D:D) -> 0 | G8: =E8+F8 -> -4936.29 | H8: -1360.98 | I8: =SUMIF('JE - LTD '!A:A,'TB - Ltd'!A8,'JE - LTD '!C:C) -> 0 | J8: =H8+I8 -> -1360.98 | K8: =G8/J8 -> 3.6270114
A9: 10202 | B9: כרטיס אשראי 9518 MAX ש"ח | C9: Accounts payable | D9: BS | E9: -3559.12 | F9: =SUMIF('JE - LTD '!A:A,'TB - Ltd'!A9,'JE - LTD '!D:D) -> 0 | G9: =E9+F9 -> -3559.12 | H9: -981.28 | I9: =SUMIF('JE - LTD '!A:A,'TB - Ltd'!A9,'JE - LTD '!C:C) -> 0 | J9: =H9+I9 -> -981.28 | K9: =G9/J9 -> 3.6270178
A10: 10204 | B10: כרטיס אשראי 9419 MAX ש"ח | C10: Accounts payable | D10: BS | E10: -23565.61 | F10: =SUMIF('JE - LTD '!A:A,'TB - Ltd'!A10,'JE - LTD '!D:D) -> 0 | G10: =E10+F10 -> -23565.61 | H10: -6497.27 | I10: =SUMIF('JE - LTD '!A:A,'TB - Ltd'!A10,'JE - LTD '!C:C) -> 0 | J10: =H10+I10 -> -6497.27 | K10: =G10/J10 -> 3.6270018
A11: 10502 | B11: פקדון DEEL | C11: Other current assets | D11: BS | E11: 476733.37 | F11: =SUMIF('JE - LTD '!A:A,'TB - Ltd'!A11,'JE - LTD '!D:D) -> 0 | G11: =E11+F11 -> 476733.37 | H11: 131440.13 | I11: =SUMIF('JE - LTD '!A:A,'TB - Ltd'!A11,'JE - LTD '!C:C) -> 0 | J11: =H11+I11 -> 131440.13 | K11: =G11/J11 -> 3.6270001
A12: 106001 | B12: וויזור איי אי בע"מ | C12: Accounts receivable - Sublease | D12: BS | E12: -3494.79 | F12: =SUMIF('JE - LTD '!A:A,'TB - Ltd'!A12,'JE - LTD '!D:D) -> 0 | G12: =E12+F12 -> -3494.79 | H12: -963.55 | I12: =SUMIF('JE - LTD '!A:A,'TB - Ltd'!A12,'JE - LTD '!C:C) -> 0 | J12: =H12+I12 -> -963.55 | K12: =G12/J12 -> 3.6269939
A13: 106002 | B13: קופלי זיפ בע"מ | C13: Accounts receivable - Sublease | D13: BS | E13: 181168.65 | F13: =SUMIF('JE - LTD '!A:A,'TB - Ltd'!A13,'JE - LTD '!D:D) -> 0 | G13: =E13+F13 -> 181168.65 | H13: 49950 | I13: =SUMIF('JE - LTD '!A:A,'TB - Ltd'!A13,'JE - LTD '!C:C) -> 0 | J13: =H13+I13 -> 49950 | K13: =G13/J13 -> 3.627
A14: 106000 | B14: Location World Colombia S.A.S | C14: Accounts receivable | D14: BS | E14: 5386.09 | F14: =SUMIF('JE - LTD '!A:A,'TB - Ltd'!A14,'JE - LTD '!D:D) -> 0 | G14: =E14+F14 -> 5386.09 | H14: 1485 | I14: =SUMIF('JE - LTD '!A:A,'TB - Ltd'!A14,'JE - LTD '!C:C) -> 0 | J14: =H14+I14 -> 1485 | K14: =G14/J14 -> 3.6269966
... A18: 10800 | B18: הוצאות מראש | C18: Prepaid Expenses | D18: BS | E18: 1294552.8 | F18: =SUMIF('JE - LTD '!A:A,'TB - Ltd'!A18,'JE - LTD '!D:D) -> 70862.01 | G18: =E18+F18 -> 1365414.8 | H18: 365325.82 | I18: =SUMIF('JE - LTD '!A:A,'TB - Ltd'!A18,'JE - LTD '!C:C) -> -3000 | J18: =H18+I18 -> 362325.82 | K18: =G18/J18 -> 3.7684724
A19: 15001 | B19: ריהוט וציוד | C19: Office furniture and equipment | D19: BS | E19: 606307.32 | F19: =SUMIF('JE - LTD '!A:A,'TB - Ltd'!A20,'JE - LTD '!D:D) -> 0 | G19: =E19+F19 -> 606307.32 | H19: 180121.26 | I19: =SUMIF('JE - LTD '!A:A,'TB - Ltd'!A20,'JE - LTD '!C:C) -> 0 | J19: =H19+I19 -> 180121.26 | K19: =G19/J19 -> 3.3661064
A20: 15002 | B20: ציוד אלקטרוני | C20: Office furniture and equipment | D20: BS | E20: 91368.88 | F20: =SUMIF('JE - LTD '!A:A,'TB - Ltd'!A22,'JE - LTD '!D:D) -> 0 | G20: =E20+F20 -> 91368.88 | H20: 26554.9 | I20: =SUMIF('JE - LTD '!A:A,'TB - Ltd'!A22,'JE - LTD '!C:C) -> 0 | J20: =H20+I20 -> 26554.9 | K20: =G20/J20 -> 3.4407541
A21: 15003 | B21: שיפורים במושכר | C21: Leasehold Improvements | D21: BS | E21: 1529963.2 | F21: =SUMIF('JE - LTD '!A:A,'TB - Ltd'!A21,'JE - LTD '!D:D) -> 0 | G21: =E21+F21 -> 1529963.2 | H21: 451119.09 | I21: =SUMIF('JE - LTD '!A:A,'TB - Ltd'!A21,'JE - LTD '!C:C) -> 0 | J21: =H21+I21 -> 451119.09 | K21: =G21/J21 -> 3.3914841
A22: 15103 | B22: פחת נצבר שפורים במושכר | C22: Less accumulated depreciation | D22: BS | E22: -197360.14 | F22: =SUMIF('JE - LTD '!A:A,'TB - Ltd'!A26,'JE - LTD '!D:D) -> 0 | G22: =E22+F22 -> -197360.14 | H22: -59330.23 | I22: =SUMIF('JE - LTD '!A:A,'TB - Ltd'!A26,'JE - LTD '!C:C) -> 0 | J22: =H22+I22 -> -59330.23 | K22: =G22/J22 -> 3.3264685
A23: 15101 | B23: פחת נצבר ריהוט וציוד | C23: Less accumulated depreciation | D23: BS | E23: -59053.53 | F23: =SUMIF('JE - LTD '!A:A,'TB - Ltd'!A25,'JE - LTD '!D:D) -> 0 | G23: =E23+F23 -> -59053.53 | H23: -17661.48 | I23: =SUMIF('JE - LTD '!A:A,'TB - Ltd'!A25,'JE - LTD '!C:C) -> 0 | J23: =H23+I23 -> -17661.48 | K23: =G23/J23 -> 3.3436343
A24: 15102 | B24: פחת נצבר ציוד אלקטרוני | C24: Less accumulated depreciation | D24: BS | E24: -12800.94 | F24: =SUMIF('JE - LTD '!A:A,'TB - Ltd'!A23,'JE - LTD '!D:D) -> 0 | G24: =E24+F24 -> -12800.94 | H24: -3755.9 | I24: =SUMIF('JE - LTD '!A:A,'TB - Ltd'!A23,'JE - LTD '!C:C) -> 0 | J24: =H24+I24 -> -3755.9 | K24: =G24/J24 -> 3.4082217
A25: 15100 | B25: פחת נצבר מחשבים | C25: Less accumulated depreciation | D25: BS | E25: -668869.19 | F25: =SUMIF('JE - LTD '!A:A,'TB - Ltd'!A24,'JE - LTD '!D:D) -> 0 | G25: =E25+F25 -> -668869.19 | H25: -200653.37 | I25: =SUMIF('JE - LTD '!A:A,'TB - Ltd'!A24,'JE - LTD '!C:C) -> 0 | J25: =H25+I25 -> -200653.37 | K25: =G25/J25 -> 3.333456
A26: 15000 | B26: מחשבים ותוכנות | C26: Computer equipment & software | D26: BS | E26: 1455299.6 | F26: =SUMIF('JE - LTD '!A:A,'TB - Ltd'!A19,'JE - LTD '!D:D) -> 0 | G26: =E26+F26 -> 1455299.6 | H26: 425011.87 | I26: =SUMIF('JE - LTD '!A:A,'TB - Ltd'!A19,'JE - LTD '!C:C) -> 0 | J26: =H26+I26 -> 425011.87 | K26: =G26/J26 -> 3.4241388
A27: 200017 | B27: מטריקס אי.טי. אינטגרציה ותשתיות בע"מ | C27: Accounts payable | D27: BS | E27: 13381 | F27: =SUMIF('JE - LTD '!A:A,'TB - Ltd'!A27,'JE - LTD '!D:D) -> 0 | G27: =E27+F27 -> 13381 | H27: 3689.27 | I27: =SUMIF('JE - LTD '!A:A,'TB - Ltd'!A27,'JE - LTD '!C:C) -> 0 | J27: =H27+I27 -> 3689.27 | K27: =G27/J27 -> 3.6270048
A28: 200053 | B28: פון פלוס בע"מ | C28: Accounts payable | D28: BS | E28: 39 | F28: =SUMIF('JE - LTD '!A:A,'TB - Ltd'!A28,'JE - LTD '!D:D) -> 0 | G28: =E28+F28 -> 39 | H28: 10.75 | I28: =SUMIF('JE - LTD '!A:A,'TB - Ltd'!A28,'JE - LTD '!C:C) -> 0 | J28: =H28+I28 -> 10.75 | K28: =G28/J28 -> 3.627907
A29: 200126 | B29: אופיר טורס בע"מ | C29: Accounts payable | D29: BS | E29: -10455.22 | F29: =SUMIF('JE - LTD '!A:A,'TB - Ltd'!A29,'JE - LTD '!D:D) -> 0 | G29: =E29+F29 -> -10455.22 | H29: -2882.61 | I29: =SUMIF('JE - LTD '!A:A,'TB - Ltd'!A29,'JE - LTD '!C:C) -> 0 | J29: =H29+I29 -> -2882.61 | K29: =G29/J29 -> 3.6269978
A30: 200105 | B30: נאביטק בע"מ | C30: Accounts payable | D30: BS | E30: -35276 | F30: =SUMIF('JE - LTD '!A:A,'TB - Ltd'!A30,'JE - LTD '!D:D) -> 0 | G30: =E30+F30 -> -35276 | H30: -9725.94 | I30: =SUMIF('JE - LTD '!A:A,'TB - Ltd'!A30,'JE - LTD '!C:C) -> 0 | J30: =H30+I30 -> -9725.94 | K30: =G30/J30 -> 3.6270016
A31: 200130 | B31: אקורן נכסים והשקעות בע"מ | C31: Accounts payable | D31: BS | E31: 563037.11 | F31: =SUMIF('JE - LTD '!A:A,'TB - Ltd'!A31,'JE - LTD '!D:D) -> 0 | G31: =E31+F31 -> 563037.11 | H31: 155234.94 | I31: =SUMIF('JE - LTD '!A:A,'TB - Ltd'!A31,'JE - LTD '!C:C) -> 0 | J31: =H31+I31 -> 155234.94 | K31: =G31/J31 -> 3.6269999
A32: 200049 | B32: WOLT וואלט אנטרפריזס | C32: Accounts payable | D32: BS | E32: 1215.15 | F32: =SUMIF('JE - LTD '!A:A,'TB - Ltd'!A32,'JE - LTD '!D:D) -> 0 | G32: =E32+F32 -> 1215.15 | H32: 335.03 | I32: =SUMIF('JE - LTD '!A:A,'TB - Ltd'!A32,'JE - LTD '!C:C) -> 0 | J32: =H32+I32 -> 335.03 | K32: =G32/J32 -> 3.6269886
A33: 200148 | B33: פליקאן גרופ א.י. בע"מ | C33: Accounts payable | D33: BS | E33: 94862.92 | F33: =SUMIF('JE - LTD '!A:A,'TB - Ltd'!A33,'JE - LTD '!D:D) -> 0 | G33: =E33+F33 -> 94862.92 | H33: 26154.63 | I33: =SUMIF('JE - LTD '!A:A,'TB - Ltd'!A33,'JE - LTD '!C:C) -> 0 | J33: =H33+I33 -> 26154.63 | K33: =G33/J33 -> 3.6270029
A34: 20003 | B34: עירייה | C34: Accounts payable | D34: BS | E34: 111171.77 | F34: =SUMIF('JE - LTD '!A:A,'TB - Ltd'!A34,'JE - LTD '!D:D) -> 0 | G34: =E34+F34 -> 111171.77 | H34: 30651.16 | I34: =SUMIF('JE - LTD '!A:A,'TB - Ltd'!A34,'JE - LTD '!C:C) -> 0 | J34: =H34+I34 -> 30651.16 | K34: =G34/J34 -> 3.6270004
A35: 200118 | B35: תגמול סוכנות לביטוח חיים(2002) בע"מ | C35: Accounts payable | D35: BS | E35: 5884.59 | F35: =SUMIF('JE - LTD '!A:A,'TB - Ltd'!A35,'JE - LTD '!D:D) -> 0 | G35: =E35+F35 -> 5884.59 | H35: 1622.44 | I35: =SUMIF('JE - LTD '!A:A,'TB - Ltd'!A35,'JE - LTD '!C:C) -> 0 | J35: =H35+I35 -> 1622.44 | K35: =G35/J35 -> 3.6270001
A36: 200127 | B36: חברת פרטנר תקשורת בע"מ | C36: Accounts payable | D36: BS | E36: 4897.04 | F36: =SUMIF('JE - LTD '!A:A,'TB - Ltd'!A36,'JE - LTD '!D:D) -> 0 | G36: =E36+F36 -> 4897.04 | H36: 1350.16 | I36: =SUMIF('JE - LTD '!A:A,'TB - Ltd'!A36,'JE - LTD '!C:C) -> 0 | J36: =H36+I36 -> 1350.16 | K36: =G36/J36 -> 3.6270072
A37: 200160 | B37: ש.ר מודוס אופוס בע"מ | C37: Accounts payable | D37: BS | E37: 6435 | F37: =SUMIF('JE - LTD '!A:A,'TB - Ltd'!A37,'JE - LTD '!D:D) -> 0 | G37: =E37+F37 -> 6435 | H37: 1774.19 | I37: =SUMIF('JE - LTD '!A:A,'TB - Ltd'!A37,'JE - LTD '!C:C) -> 0 | J37: =H37+I37 -> 1774.19 | K37: =G37/J37 -> 3.6270073
A38: 200200 | B38: DEEL-LDEEL PROLL, S.L | C38: Accounts payable | D38: BS | E38: 90338.99 | F38: =SUMIF('JE - LTD '!A:A,'TB - Ltd'!A38,'JE - LTD '!D:D) -> 0 | G38: =E38+F38 -> 90338.99 | H38: 24907.36 | I38: =SUMIF('JE - LTD '!A:A,'TB - Ltd'!A38,'JE - LTD '!C:C) -> 0 | J38: =H38+I38 -> 24907.36 | K38: =G38/J38 -> 3.6269998
... A371: 1-11173027 | B371: עופר בן נון 2022.04 ארה"ב | C371: G&A - Travel | D371: P&L | E371: 1119 | F371: =SUMIF('JE - LTD '!A:A,'TB - Ltd'!A371,'JE - LTD '!D:D) -> 0 | G371: =E371+F371 -> 1119 | H371: 306 | I371: =SUMIF('JE - LTD '!A:A,'TB - Ltd'!A371,'JE - LTD '!C:C) -> 0 | J371: =H371+I371 -> 306 | K371: =G371/J371 -> 3.6568627
A372: 74003 | B372: הוצאות פחת שיפורים במושכר | C372: Non cash expense - Depreciation of fixed assets | D372: P&L | E372: 133592.26 | F372: =SUMIF('JE - LTD '!A:A,'TB - Ltd'!A374,'JE - LTD '!D:D) -> 0 | G372: =E372+F372 -> 133592.26 | H372: 39855.92 | I372: =SUMIF('JE - LTD '!A:A,'TB - Ltd'!A374,'JE - LTD '!C:C) -> 0 | J372: =H372+I372 -> 39855.92 | K372: =G372/J372 -> 3.35188
A373: 74001 | B373: הוצאות פחת ריהוט וציוד | C373: Non cash expense - Depreciation of fixed assets | D373: P&L | E373: 42376.21 | F373: =SUMIF('JE - LTD '!A:A,'TB - Ltd'!A373,'JE - LTD '!D:D) -> 0 | G373: =E373+F373 -> 42376.21 | H373: 12597.28 | I373: =SUMIF('JE - LTD '!A:A,'TB - Ltd'!A373,'JE - LTD '!C:C) -> 0 | J373: =H373+I373 -> 12597.28 | K373: =G373/J373 -> 3.3639174
A374: 74002 | B374: הוצאות פחת ציוד אלקטרוני | C374: Non cash expense - Depreciation of fixed assets | D374: P&L | E374: 11401.91 | F374: =SUMIF('JE - LTD '!A:A,'TB - Ltd'!A375,'JE - LTD '!D:D) -> 0 | G374: =E374+F374 -> 11401.91 | H374: 3355.57 | I374: =SUMIF('JE - LTD '!A:A,'TB - Ltd'!A375,'JE - LTD '!C:C) -> 0 | J374: =H374+I374 -> 3355.57 | K374: =G374/J374 -> 3.3979056
A375: 74000 | B375: הוצאות פחת מחשבים ותוכנה | C375: Non cash expense - Depreciation of fixed assets | D375: P&L | E375: 414864.93 | F375: =SUMIF('JE - LTD '!A:A,'TB - Ltd'!A372,'JE - LTD '!D:D) -> 0 | G375: =E375+F375 -> 414864.93 | H375: 122872.23 | I375: =SUMIF('JE - LTD '!A:A,'TB - Ltd'!A372,'JE - LTD '!C:C) -> 0 | J375: =H375+I375 -> 122872.23 | K375: =G375/J375 -> 3.3763929
A376: 99999 | B376: ביטולי יתרות | C376: Non cash expenses. - Net interest income (expense) | D376: P&L | E376: 72.65 | F376: =SUMIF('JE - LTD '!A:A,'TB - Ltd'!A376,'JE - LTD '!D:D) -> 0 | G376: =E376+F376 -> 72.65 | H376: -226.56 | I376: =SUMIF('JE - LTD '!A:A,'TB - Ltd'!A376,'JE - LTD '!C:C) -> 0 | J376: =H376+I376 -> -226.56 | K376: =G376/J376 -> -0.32066561
A377: 90000 | B377: עמלות בנק וריבית חובה | C377: Non cash expenses. - Net interest income (expense) | D377: P&L | E377: 40964.8 | F377: =SUMIF('JE - LTD '!A:A,'TB - Ltd'!A377,'JE - LTD '!D:D) -> 0 | G377: =E377+F377 -> 40964.8 | H377: 11123.41 | I377: =SUMIF('JE - LTD '!A:A,'TB - Ltd'!A377,'JE - LTD '!C:C) -> 0 | J377: =H377+I377 -> 11123.41 | K377: =G377/J377 -> 3.6827556
A378: 90001 | B378: הכנסות ריבית מפקדונות | C378: Non cash expenses. - Net interest income (expense) | D378: P&L | E378: -25316923 | F378: =SUMIF('JE - LTD '!A:A,'TB - Ltd'!A378,'JE - LTD '!D:D) -> 0 | G378: =E378+F378 -> -25316923 | H378: -6916928.3 | I378: =SUMIF('JE - LTD '!A:A,'TB - Ltd'!A378,'JE - LTD '!C:C) -> 0 | J378: =H378+I378 -> -6916928.3 | K378: =G378/J378 -> 3.6601396
A379: 90002 | B379: הפרשי שער | C379: Non cash expenses. - Currency difference | D379: P&L | E379: -14309148 | F379: =SUMIF('JE - LTD '!A:A,'TB - Ltd'!A379,'JE - LTD '!D:D) -> -11587.9 | G379: =E379+F379 -> -14320736 | H379: 30672.39 | I379: =SUMIF('JE - LTD '!A:A,'TB - Ltd'!A379,'JE - LTD '!C:C) -> 0 | J379: =H379+I379 -> 30672.39 | K379: =G379/J379 -> -466.8934
A380: 90006 | B380: עמלות כרטיס אשראי | C380: Non cash expenses. - Net interest income (expense) | D380: P&L | E380: 784.16 | F380: =SUMIF('JE - LTD '!A:A,'TB - Ltd'!A380,'JE - LTD '!D:D) -> 0 | G380: =E380+F380 -> 784.16 | H380: 210.04 | I380: =SUMIF('JE - LTD '!A:A,'TB - Ltd'!A380,'JE - LTD '!C:C) -> 0 | J380: =H380+I380 -> 210.04 | K380: =G380/J380 -> 3.7333841
A381: 90010 | B381: ריבית והצמדה - מוסדות (מ"ה ומע"מ) | C381: Non cash expenses. - Net interest income (expense) | D381: P&L | E381: -4920.78 | F381: =SUMIF('JE - LTD '!A:A,'TB - Ltd'!A381,'JE - LTD '!D:D) -> 0 | G381: =E381+F381 -> -4920.78 | H381: -1366.59 | I381: =SUMIF('JE - LTD '!A:A,'TB - Ltd'!A381,'JE - LTD '!C:C) -> 0 | J381: =H381+I381 -> -1366.59 | K381: =G381/J381 -> 3.6007727
A382: 90011 | B382: MESH CASH BACK | C382: Non cash expenses. - Net interest income (expense) | D382: P&L | E382: -51925.51 | F382: =SUMIF('JE - LTD '!A:A,'TB - Ltd'!A382,'JE - LTD '!D:D) -> 0 | G382: =E382+F382 -> -51925.51 | H382: -13981.96 | I382: =SUMIF('JE - LTD '!A:A,'TB - Ltd'!A382,'JE - LTD '!C:C) -> 0 | J382: =H382+I382 -> -13981.96 | K382: =G382/J382 -> 3.7137504
A383: 90012 | B383: ריביות קופות גמל | C383: Non cash expenses. - Net interest income (expense) | D383: P&L | E383: 33.78 | F383: =SUMIF('JE - LTD '!A:A,'TB - Ltd'!A383,'JE - LTD '!D:D) -> 0 | G383: =E383+F383 -> 33.78 | H383: 9.52 | I383: =SUMIF('JE - LTD '!A:A,'TB - Ltd'!A383,'JE - LTD '!C:C) -> 0 | J383: =H383+I383 -> 9.52 | K383: =G383/J383 -> 3.5483193
A384: new1242 | B384: COS - Allocation from Support | C384: COS - Allocation from Support | D384: P&L | E384: 0 | F384: =SUMIF('JE - LTD '!A:A,'TB - Ltd'!A384,'JE - LTD '!D:D) -> 621921.69 | G384: =E384+F384 -> 621921.69 | H384: 171469.77 | I384: =SUMIF('JE - LTD '!A:A,'TB - Ltd'!A384,'JE - LTD '!C:C) -> 0 | J384: =H384+I384 -> 171469.77 | K384: =G384/J384 -> 3.6270049
A385: new1243 | B385: Support - Allocation to CoS | C385: Support - Allocation to CoS | D385: P&L | E385: 0 | F385: =SUMIF('JE - LTD '!A:A,'TB - Ltd'!A385,'JE - LTD '!D:D) -> -621921.69 | G385: =E385+F385 -> -621921.69 | H385: -171469.77 | I385: =SUMIF('JE - LTD '!A:A,'TB - Ltd'!A385,'JE - LTD '!C:C) -> 0 | J385: =H385+I385 -> -171469.77 | K385: =G385/J385 -> 3.6270049
A386: 1-11170004 | B386: Software Licenses | C386: G&A - Software Tools | D386: P&L | E386: 2961.88 | F386: =SUMIF('JE - LTD '!A:A,'TB - Ltd'!A386,'JE - LTD '!D:D) -> 0 | G386: =E386+F386 -> 2961.88 | H386: 821.4 | I386: =SUMIF('JE - LTD '!A:A,'TB - Ltd'!A386,'JE - LTD '!C:C) -> 0 | J386: =H386+I386 -> 821.4 | K386: =G386/J386 -> 3.6058924
A387: 1-104700105 | B387: הוצאות א.ס.אנטיס | C387: IP - Patent application fees & office action fees | D387: P&L | E387: 322706.82 | F387: =SUMIF('JE - LTD '!A:A,'TB - Ltd'!A387,'JE - LTD '!D:D) -> 0 | G387: =E387+F387 -> 322706.82 | H387: 86622.56 | I387: =SUMIF('JE - LTD '!A:A,'TB - Ltd'!A387,'JE - LTD '!C:C) -> 0 | J387: =H387+I387 -> 86622.56 | K387: =G387/J387 -> 3.7254362
... A407: 1-11173035 | B407: עופר בן נון 30.3202 ארה"ב | C407: G&A - Travel | D407: P&L | E407: 13803.82 | F407: =SUMIF('JE - LTD '!A:A,'TB - Ltd'!A407,'JE - LTD '!D:D) -> 0 | G407: =E407+F407 -> 13803.82 | H407: 3746.54 | I407: =SUMIF('JE - LTD '!A:A,'TB - Ltd'!A407,'JE - LTD '!C:C) -> 0 | J407: =H407+I407 -> 3746.54 | K407: =G407/J407 -> 3.6844182
A408: 200397 | B408: מאיו ניב | C408: Accounts payable | D408: BS | E408: 1755 | F408: =SUMIF('JE - LTD '!A:A,'TB - Ltd'!A408,'JE - LTD '!D:D) -> 0 | G408: =E408+F408 -> 1755 | H408: 483.87 | I408: =SUMIF('JE - LTD '!A:A,'TB - Ltd'!A408,'JE - LTD '!C:C) -> 0 | J408: =H408+I408 -> 483.87 | K408: =G408/J408 -> 3.6270073
A409: 30077 | B409: Series A - NIBIN PHILIP | C409: Additional paid in capital | D409: BS | E409: -218162.51 | F409: =SUMIF('JE - LTD '!A:A,'TB - Ltd'!A409,'JE - LTD '!D:D) -> 0 | G409: =E409+F409 -> -218162.51 | H409: -60000.69 | I409: =SUMIF('JE - LTD '!A:A,'TB - Ltd'!A409,'JE - LTD '!C:C) -> 0 | J409: =H409+I409 -> -60000.69 | K409: =G409/J409 -> 3.636
A410: 1-11173028 | B410: עופר בן נון 2023.04.18-28 ארה"ב | C410: G&A - Travel | D410: P&L | E410: 20181.08 | F410: =SUMIF('JE - LTD '!A:A,'TB - Ltd'!A410,'JE - LTD '!D:D) -> 0 | G410: =E410+F410 -> 20181.08 | H410: 5593.74 | I410: =SUMIF('JE - LTD '!A:A,'TB - Ltd'!A410,'JE - LTD '!C:C) -> 0 | J410: =H410+I410 -> 5593.74 | K410: =G410/J410 -> 3.6077973
A411: 1-10473032 | B411: גיא חרפק 2023.04.23-28 ארה"ב | C411: Product - Travel | D411: P&L | E411: 5226.52 | F411: =SUMIF('JE - LTD '!A:A,'TB - Ltd'!A411,'JE - LTD '!D:D) -> 0 | G411: =E411+F411 -> 5226.52 | H411: 1498 | I411: =SUMIF('JE - LTD '!A:A,'TB - Ltd'!A411,'JE - LTD '!C:C) -> 0 | J411: =H411+I411 -> 1498 | K411: =G411/J411 -> 3.4889987
A412: 1-10773033 | B412: ראובן אליהו 2023.04.23-28 ארה"ב | C412: Customer Success - Travel | D412: P&L | E412: 5226.52 | F412: =SUMIF('JE - LTD '!A:A,'TB - Ltd'!A412,'JE - LTD '!D:D) -> 0 | G412: =E412+F412 -> 5226.52 | H412: 1498 | I412: =SUMIF('JE - LTD '!A:A,'TB - Ltd'!A412,'JE - LTD '!C:C) -> 0 | J412: =H412+I412 -> 1498 | K412: =G412/J412 -> 3.4889987
A413: 1-11073029 | B413: עמית רוזנוקס 2023.04.23-28 ארה"ב | C413: Business Development - Travel | D413: P&L | E413: 5226.52 | F413: =SUMIF('JE - LTD '!A:A,'TB - Ltd'!A413,'JE - LTD '!D:D) -> 0 | G413: =E413+F413 -> 5226.52 | H413: 1498 | I413: =SUMIF('JE - LTD '!A:A,'TB - Ltd'!A413,'JE - LTD '!C:C) -> 0 | J413: =H413+I413 -> 1498 | K413: =G413/J413 -> 3.4889987
A414: 1-10473030 | B414: אלעד גברא 2023.04.23-28 ארה"ב | C414: Product - Travel | D414: P&L | E414: 10780.38 | F414: =SUMIF('JE - LTD '!A:A,'TB - Ltd'!A414,'JE - LTD '!D:D) -> 0 | G414: =E414+F414 -> 10780.38 | H414: 2995.47 | I414: =SUMIF('JE - LTD '!A:A,'TB - Ltd'!A414,'JE - LTD '!C:C) -> 0 | J414: =H414+I414 -> 2995.47 | K414: =G414/J414 -> 3.5988943
A415: 1-10473031 | B415: אוהד בוברוב 2023.04.23-28 ארה"ב | C415: Product - Travel | D415: P&L | E415: 11911.94 | F415: =SUMIF('JE - LTD '!A:A,'TB - Ltd'!A415,'JE - LTD '!D:D) -> 0 | G415: =E415+F415 -> 11911.94 | H415: 3284.24 | I415: =SUMIF('JE - LTD '!A:A,'TB - Ltd'!A415,'JE - LTD '!C:C) -> 0 | J415: =H415+I415 -> 3284.24 | K415: =G415/J415 -> 3.6270005
A416: 1-100700114 | B416: Product SW- fixed | C416: COS - SW (product-fixed) | D416: P&L | E416: 41182.09 | F416: =SUMIF('JE - LTD '!A:A,'TB - Ltd'!A416,'JE - LTD '!D:D) -> 0 | G416: =E416+F416 -> 41182.09 | H416: 10944.46 | I416: =SUMIF('JE - LTD '!A:A,'TB - Ltd'!A416,'JE - LTD '!C:C) -> 0 | J416: =H416+I416 -> 10944.46 | K416: =G416/J416 -> 3.7628252
A417: 1-108700115 | B417: global analyst relations line | C417: Marketing - Market Analysis & Competition (Change to Analyst Relations) | D417: P&L | E417: 260212.63 | F417: =SUMIF('JE - LTD '!A:A,'TB - Ltd'!A417,'JE - LTD '!D:D) -> 0 | G417: =E417+F417 -> 260212.63 | H417: 73154.41 | I417: =SUMIF('JE - LTD '!A:A,'TB - Ltd'!A417,'JE - LTD '!C:C) -> 0 | J417: =H417+I417 -> 73154.41 | K417: =G417/J417 -> 3.5570327
A418: 30078 | B418: Series A - Mike Sullivan | C418: Additional paid in capital | D418: BS | E418: -1102501.3 | F418: =SUMIF('JE - LTD '!A:A,'TB - Ltd'!A418,'JE - LTD '!D:D) -> 0 | G418: =E418+F418 -> -1102501.3 | H418: -300000.36 | I418: =SUMIF('JE - LTD '!A:A,'TB - Ltd'!A418,'JE - LTD '!C:C) -> 0 | J418: =H418+I418 -> -300000.36 | K418: =G418/J418 -> 3.675
A419: 30096 | B419: MARIANNE BUDNI - אופציות | C419: Additional paid in capital | D419: BS | E419: -310483.13 | F419: =SUMIF('JE - LTD '!A:A,'TB - Ltd'!A419,'JE - LTD '!D:D) -> 0 | G419: =E419+F419 -> -310483.13 | H419: -84375 | I419: =SUMIF('JE - LTD '!A:A,'TB - Ltd'!A419,'JE - LTD '!C:C) -> 0 | J419: =H419+I419 -> -84375 | K419: =G419/J419 -> 3.6798001
A420: 1-108700116 | B420: Digital Marketing_US | C420: Marketing - Digital Marketing_US | D420: P&L | E420: 56904.59 | F420: =SUMIF('JE - LTD '!A:A,'TB - Ltd'!A420,'JE - LTD '!D:D) -> 0 | G420: =E420+F420 -> 56904.59 | H420: 15279.14 | I420: =SUMIF('JE - LTD '!A:A,'TB - Ltd'!A420,'JE - LTD '!C:C) -> 0 | J420: =H420+I420 -> 15279.14 | K420: =G420/J420 -> 3.724332
A421: 1-113700117 | B421: financial outsource - PFIC/CFC analysis | C421: Business Operations - Ongoing/random outsourced | D421: P&L | E421: 90000 | F421: =SUMIF('JE - LTD '!A:A,'TB - Ltd'!A421,'JE - LTD '!D:D) -> 0 | G421: =E421+F421 -> 90000 | H421: 24438.32 | I421: =SUMIF('JE - LTD '!A:A,'TB - Ltd'!A421,'JE - LTD '!C:C) -> 0 | J421: =H421+I421 -> 24438.32 | K421: =G421/J421 -> 3.6827409
... A537: 1-11270054 | B537: HR - Happy Hour | C537: HR - Happy Hour | D537: P&L | E537: 6301.6 | F537: =SUMIF('JE - LTD '!A:A,'TB - Ltd'!A537,'JE - LTD '!D:D) -> 0 | G537: =E537+F537 -> 6301.6 | H537: 1743.76 | I537: =SUMIF('JE - LTD '!A:A,'TB - Ltd'!A537,'JE - LTD '!C:C) -> 0 | J537: =H537+I537 -> 1743.76 | K537: =G537/J537 -> 3.6138001
A538: New1 | B538: אלוקציה מופ | C538: Engineering - Contingency | D538: P&L | F538: =SUMIF('JE - LTD '!A:A,'TB - Ltd'!A538,'JE - LTD '!D:D) -> 2612097.4 | G538: =E538+F538 -> 2612097.4 | I538: =SUMIF('JE - LTD '!A:A,'TB - Ltd'!A538,'JE - LTD '!C:C) -> 880267.65 | J538: =H538+I538 -> 880267.65 | K538: =G538/J538 -> 2.96739
A539: New2 | B539: אלוקציה הנהכ | C539: G&A - Contingency | D539: P&L | F539: =SUMIF('JE - LTD '!A:A,'TB - Ltd'!A539,'JE - LTD '!D:D) -> -2877092.8 | G539: =E539+F539 -> -2877092.8 | I539: =SUMIF('JE - LTD '!A:A,'TB - Ltd'!A539,'JE - LTD '!C:C) -> -969570.16 | J539: =H539+I539 -> -969570.16 | K539: =G539/J539 -> 2.96739
A540: New3 | B540: אלוקציה שיווק | C540: Marketing - Contingency | D540: P&L | F540: =SUMIF('JE - LTD '!A:A,'TB - Ltd'!A540,'JE - LTD '!D:D) -> 113569.45 | G540: =E540+F540 -> 113569.45 | I540: =SUMIF('JE - LTD '!A:A,'TB - Ltd'!A540,'JE - LTD '!C:C) -> 38272.506 | J540: =H540+I540 -> 38272.506 | K540: =G540/J540 -> 2.96739
A541: New4 | B541: אלוקציה מכירות | C541: Sales - Contingency | D541: P&L | F541: =SUMIF('JE - LTD '!A:A,'TB - Ltd'!A541,'JE - LTD '!D:D) -> 37856.484 | G541: =E541+F541 -> 37856.484 | I541: =SUMIF('JE - LTD '!A:A,'TB - Ltd'!A541,'JE - LTD '!C:C) -> 12757.502 | J541: =H541+I541 -> 12757.502 | K541: =G541/J541 -> 2.96739
A542: New5 | B542: אלוקציה CS | C542: Customer Success - Contingency | D542: P&L | F542: =SUMIF('JE - LTD '!A:A,'TB - Ltd'!A542,'JE - LTD '!D:D) -> 75712.968 | G542: =E542+F542 -> 75712.968 | I542: =SUMIF('JE - LTD '!A:A,'TB - Ltd'!A542,'JE - LTD '!C:C) -> 25515.004 | J542: =H542+I542 -> 25515.004 | K542: =G542/J542 -> 2.96739
A543: New6 | B543: אלוקציה SUPPORT | C543: Support - Contingency | D543: P&L | F543: =SUMIF('JE - LTD '!A:A,'TB - Ltd'!A543,'JE - LTD '!D:D) -> 37856.484 | G543: =E543+F543 -> 37856.484 | I543: =SUMIF('JE - LTD '!A:A,'TB - Ltd'!A543,'JE - LTD '!C:C) -> 12757.502 | J543: =H543+I543 -> 12757.502 | K543: =G543/J543 -> 2.96739

Sheet JE - LTD 
A2: Acc # | B2: Acc Name | C2: US$ | D2: NIS | E2: 3.627 | F2: מהות הפקודה
A4: 25100 | B4: =VLOOKUP(A4,'TB - Ltd'!A:B,2,0) -> ביטול הוצ שכירות יישום תקן ASC842 הקטנת התחייבות | C4: -1
A5: 25102 | B5: =VLOOKUP(A5,'TB - Ltd'!A:B,2,0) -> Owned asset | C5: -2687944 | D5: -8707035 | F5: ביטול יתרות חכירה
A6: 20202 | B6: =VLOOKUP(A6,'TB - Ltd'!A:B,2,0) -> Owned liability- short term | C6: 358997 | D6: 1302082.1
A7: 25101 | B7: =VLOOKUP(A7,'TB - Ltd'!A:B,2,0) -> Owned liability- long term | C7: 2004123 | D7: 7069213
A8: 1-11370005 | B8: =VLOOKUP(A8,'TB - Ltd'!A:B,2,0) -> Office rent | C8: =-SUM(C4:C7) -> 324825 | D8: =-SUM(D4:D7) -> 335739.88
A10: New64 | B10: =VLOOKUP(A10,'TB - Ltd'!A:B,2,0) -> הוצאות בגין אופציות- פיתוח | C10: 384964.66 | D10: =C10*$E$10 -> 1395111.9 | E10: 3.624 | F10: פקודת אופציות 27/12 ישראל
A11: New48 | B11: =VLOOKUP(A11,'TB - Ltd'!A:B,2,0) -> הוצאות בגין אופציות- Customer Success | C11: 21805.907 | D11: =C11*$E$10 -> 79024.608
A12: New61 | B12: =VLOOKUP(A12,'TB - Ltd'!A:B,2,0) -> הוצאות בגין אופציות- שיווק | C12: 2889.6321 | D12: =C12*$E$10 -> 10472.027
A13: New65 | B13: =VLOOKUP(A13,'TB - Ltd'!A:B,2,0) -> הוצאות בגין אופציות-מוצר | C13: 72510.852 | D13: =C13*$E$10 -> 262779.33
A14: New47 | B14: =VLOOKUP(A14,'TB - Ltd'!A:B,2,0) -> הוצאות בגין אופציות-פיתוח עסקי | C14: 9141.8349 | D14: =C14*$E$10 -> 33130.01
A15: New78 | B15: =VLOOKUP(A15,'TB - Ltd'!A:B,2,0) -> הוצאות בגין אופציות- מכירות | C15: 28650.655 | D15: =C15*$E$10 -> 103829.97
A16: New66 | B16: =VLOOKUP(A16,'TB - Ltd'!A:B,2,0) -> הוצאות בגין אופציות- משאבי אנוש | C16: 4109.5808 | D16: =C16*$E$10 -> 14893.121
A17: New79 | B17: =VLOOKUP(A17,'TB - Ltd'!A:B,2,0) -> הוצאות בגין אופציות- Business Operations | C17: 5253.5372 | D17: =C17*$E$10 -> 19038.819
A18: New46 | B18: =VLOOKUP(A18,'TB - Ltd'!A:B,2,0) -> הוצאות בגין אופציות- הנהכ | C18: 6693.9341 | D18: =C18*$E$10 -> 24258.817
A19: 30080 | B19: =VLOOKUP(A19,'TB - Ltd'!A:B,2,0) -> קרן הון בגין הוצ' בגין אופציות | C19: =-SUM(C10:C18) -> -536020.6 | D19: =C19*$E$10 -> -1942538.6
A21: 30080 | B21: =VLOOKUP(A21,'TB - Ltd'!A:B,2,0) -> קרן הון בגין הוצ' בגין אופציות | C21: =-C22 -> 5362.98 | D21: =C21*E2 -> 19451.528 | F21: פקודת אופציות INC
A22: 25200 | B22: =VLOOKUP(A22,'TB - Ltd'!A:B,2,0) -> חו"ז בינחברתי | C22: -5362.98 | D22: =-D21 -> -19451.528
A25: 700104 | B25: =VLOOKUP(A25,'TB - Ltd'!A:B,2,0) -> הוצאות בינחברתי | C25: 2586533.7 | D25: =C25*E2 -> 9381357.8 | F25: פקודה בינחברתית
A26: 25200 | B26: =VLOOKUP(A26,'TB - Ltd'!A:B,2,0) -> חו"ז בינחברתי | C26: =-C25 -> -2586533.7 | D26: =-D25 -> -9381357.8
A28: New1 | B28: =VLOOKUP(A28,'TB - Ltd'!A:B,2,0) -> אלוקציה מופ | C28: 880267.65 | D28: 2612097.4 | F28: פקודת אלוקציה
A29: New2 | B29: =VLOOKUP(A29,'TB - Ltd'!A:B,2,0) -> אלוקציה הנהכ | C29: =-C28-C30-C31-C32-C33 -> -969570.16 | D29: =-D28-D30-D31-D32-D33 -> -2877092.8
A30: New3 | B30: =VLOOKUP(A30,'TB - Ltd'!A:B,2,0) -> אלוקציה שיווק | C30: 38272.506 | D30: 113569.45
A31: New4 | B31: =VLOOKUP(A31,'TB - Ltd'!A:B,2,0) -> אלוקציה מכירות | C31: 12757.502 | D31: 37856.484
A32: New5 | B32: =VLOOKUP(A32,'TB - Ltd'!A:B,2,0) -> אלוקציה CS | C32: 25515.004 | D32: 75712.968
A33: New6 | B33: =VLOOKUP(A33,'TB - Ltd'!A:B,2,0) -> אלוקציה SUPPORT | C33: 12757.502 | D33: 37856.484
A36: 1-10870089 | B36: =VLOOKUP(A36,'TB - Ltd'!A:B,2,0) -> US EVENTS | C36: 3000 | F36: העמדת הוצאות מראש כראוי בגין מנוי Influ2
A37: 10800 | B37: =VLOOKUP(A37,'TB - Ltd'!A:B,2,0) -> הוצאות מראש | C37: =-C36 -> -3000
A39: 10800 | B39: =VLOOKUP(A39,'TB - Ltd'!A:B,2,0) -> הוצאות מראש | D39: =-D40-D41 -> 70862.01 | F39: פקודה שעברה רק בדולר, להעביר גם בשקל
A40: 1-10870089 | B40: =VLOOKUP(A40,'TB - Ltd'!A:B,2,0) -> US EVENTS | D40: -11601
A41: 1-108700131 | B41: =VLOOKUP(A41,'TB - Ltd'!A:B,2,0) -> Events - EMEA | D41: -59261.01
A43: 20200 | B43: =VLOOKUP(A43,'TB - Ltd'!A:B,2,0) -> הוצאות לשלם | D43: 9147.294 | F43: פקודה שעברה רק בדולר, להעביר גם בשקל
A44: 1-10870062 | B44: =VLOOKUP(A44,'TB - Ltd'!A:B,2,0) -> Swag- Employee | D44: =-D43 -> -9147.294 | F44: נטרול רכיב המע"מ מההפרשה לספק מיתוגון
A46: 20800 | B46: =VLOOKUP(A46,'TB - Ltd'!A:B,2,0) -> הכנסות נדחות | D46: 11587.9 | F46: הפרשי שער על הכנסות נדחות
A47: 90002 | B47: =VLOOKUP(A47,'TB - Ltd'!A:B,2,0) -> הפרשי שער | D47: =-D46 -> -11587.9
A49: 1-10070014 | B49: =VLOOKUP(A49,'TB - Ltd'!A:B,2,0) -> Hosting | D49: =164760*3.627 -> 597584.52 | F49: פקודה שעברה רק בדולר, להעביר גם בשקל
A50: 1-10270014 | B50: =VLOOKUP(A50,'TB - Ltd'!A:B,2,0) -> Hosting | D50: =-D49 -> -597584.52
A52: new1242 | B52: =VLOOKUP(A52,'TB - Ltd'!A:B,2,0) -> COS - Allocation from Support | D52: =171470*3.627 -> 621921.69 | F52: פקודה שעברה רק בדולר, להעביר גם בשקל
A53: new1243 | B53: =VLOOKUP(A53,'TB - Ltd'!A:B,2,0) -> Support - Allocation to CoS | D53: =-D52 -> -621921.69
A55: new70 | B55: =VLOOKUP(A55,'TB - Ltd'!A:B,2,0) -> בונוס | D55: =643*3.627 -> 2332.161 | F55: פקודה שעברה רק בדולר, להעביר גם בשקל
A56: 1-10271000 | B56: =VLOOKUP(A56,'TB - Ltd'!A:B,2,0) -> הוצאות משכורת | D56: =-D55 -> -2332.161
A58: 1-10771006 | B58: =VLOOKUP(A58,'TB - Ltd'!A:B,2,0) -> עמלות מכירה | D58: =3119*3.627 -> 11312.613 | F58: פקודה שעברה רק בדולר, להעביר גם בשקל
A59: 1-10771000 | B59: =VLOOKUP(A59,'TB - Ltd'!A:B,2,0) -> הוצאות משכורת | D59: =-D58 -> -11312.613
A61: 1-11071006 | B61: =VLOOKUP(A61,'TB - Ltd'!A:B,2,0) -> עמלות מכירה | D61: =760*3.627 -> 2756.52 | F61: פקודה שעברה רק בדולר, להעביר גם בשקל
A62: 1-11071000 | B62: =VLOOKUP(A62,'TB - Ltd'!A:B,2,0) -> הוצאות משכורת | D62: =-D61 -> -2756.52
A64: new71 | B64: =VLOOKUP(A64,'TB - Ltd'!A:B,2,0) -> בונוס | D64: =2403*3.627 -> 8715.681 | F64: פקודה שעברה רק בדולר, להעביר גם בשקל
A65: 1-10171000 | B65: =VLOOKUP(A65,'TB - Ltd'!A:B,2,0) -> הוצאות משכורת | D65: =-D64 -> -8715.681
A67: 1-10970086 | B67: =VLOOKUP(A67,'TB - Ltd'!A:B,2,0) -> Sales Commision | D67: =4825*3.627 -> 17500.275 | F67: פקודה שעברה רק בדולר, להעביר גם בשקל
A68: 1-10971000 | B68: =VLOOKUP(A68,'TB - Ltd'!A:B,2,0) -> הוצאות משכורת | D68: =-D67 -> -17500.275

Sheet TB - Inc
D1: =SUM(D3:D165) -> -7.7125151e-10 | E1: =SUM(E3:E166) -> 0 | F1: =SUM(F3:F166) -> -1.1641532e-09
A2: חשבון | B2: תאור החשבון | D2: ספרים - דולר | E2: פ"נ - דולר | F2: סופי - דולר
A3: 10000 | B3: Analysis Checking (8992) - 1 | C3: Cash & cash equivalents US | D3: 883967.03 | E3: =SUMIF('JE - Inc'!A:A,'TB - Inc'!A3,'JE - Inc'!D:D) -> 0 | F3: =IFERROR(E3+D3,0) -> 883967.03
A4: 12000 | B4: Account Receivable | C4: Accounts receivable | D4: 808996.95 | E4: =SUMIF('JE - Inc'!A:A,'TB - Inc'!A4,'JE - Inc'!D:D) -> 0 | F4: =IFERROR(E4+D4,0) -> 808996.95
A5: 13000 | B5: Prepaid Expenses | C5: Prepaid Expenses | D5: 36085.73 | E5: =SUMIF('JE - Inc'!A:A,'TB - Inc'!A5,'JE - Inc'!D:D) -> 0 | F5: =IFERROR(E5+D5,0) -> 36085.73
A6: 14500 | B6: Mesh Pay | C6: Cash & cash equivalents US | D6: 89722.64 | E6: =SUMIF('JE - Inc'!A:A,'TB - Inc'!A6,'JE - Inc'!D:D) -> 0 | F6: =IFERROR(E6+D6,0) -> 89722.64
A7: 16100 | B7: Fixed Assets:Fixed Assets - Computer | C7: Computer equipment & software | D7: 57005.59 | E7: =SUMIF('JE - Inc'!A:A,'TB - Inc'!A7,'JE - Inc'!D:D) -> 0 | F7: =IFERROR(E7+D7,0) -> 57005.59
A8: 16200 | B8: Fixed Assets:Accumulated Depreciation - Computer | C8: Less accumulated depreciation | D8: -17730.99 | E8: =SUMIF('JE - Inc'!A:A,'TB - Inc'!A8,'JE - Inc'!D:D) -> 0 | F8: =IFERROR(E8+D8,0) -> -17730.99
A9: 23500 | B9: Other current Liabilities:Employees Reimbursements | C9: Employee payables | D9: -99.6 | E9: =SUMIF('JE - Inc'!A:A,'TB - Inc'!A9,'JE - Inc'!D:D) -> 0 | F9: =IFERROR(E9+D9,0) -> -99.6
A10: 24000 | B10: Deferred Revenue | C10: Deffered revenues | D10: -1068361 | E10: =SUMIF('JE - Inc'!A:A,'TB - Inc'!A10,'JE - Inc'!D:D) -> 0 | F10: =IFERROR(E10+D10,0) -> -1068361
A11: 25000 | B11: Intercompany- Talon Cyber Security LTD | C11: Intercompany | D11: -5426998.8 | E11: =SUMIF('JE - Inc'!A:A,'TB - Inc'!A11,'JE - Inc'!D:D) -> 2591896.7 | F11: =IFERROR(E11+D11,0) -> -2835102.1
A12: 60110 | B12: Sales Expenses:Salaries and Related Expenses:Gross Salary | C12: Sales - Salaries and social benefits | D12: 1824047.4 | E12: =SUMIF('JE - Inc'!A:A,'TB - Inc'!A12,'JE - Inc'!D:D) -> 0 | F12: =IFERROR(E12+D12,0) -> 1824047.4
A13: 60120 | B13: Sales Expenses:Salaries and Related Expenses:Vacation/PTO Expenses | C13: Sales - Salaries and social benefits | D13: 2746.51 | E13: =SUMIF('JE - Inc'!A:A,'TB - Inc'!A13,'JE - Inc'!D:D) -> 0 | F13: =IFERROR(E13+D13,0) -> 2746.51
A14: 60130 | B14: Sales Expenses:Salaries and Related Expenses:Employer Taxes | C14: Sales - Salaries and social benefits | D14: 211656.28 | E14: =SUMIF('JE - Inc'!A:A,'TB - Inc'!A14,'JE - Inc'!D:D) -> 0 | F14: =IFERROR(E14+D14,0) -> 211656.28
... A165: new85 | B165: TASKRAY | C165: Customer Success - Software Tools | D165: 9720 | E165: =SUMIF('JE - Inc'!A:A,'TB - Inc'!A165,'JE - Inc'!D:D) -> 0 | F165: =IFERROR(E165+D165,0) -> 9720
A166: New49 | B166: Subcontractors & Consulting | C166: G&A - Ongoing/random outsourced | E166: =SUMIF('JE - Inc'!A:A,'TB - Inc'!A166,'JE - Inc'!D:D) -> 100000 | F166: =IFERROR(E166+D166,0) -> 100000

Sheet JE - Inc
A2: Acc # | B2: Acc Name | D2: US$ | E2: מהות הפקודה
A4: 100201 | B4: =VLOOKUP(A4,'TB - Inc'!A:B,2,0) -> Engineering Expenses:Options - Engineering | D4: -1443.6 | E4: פקודת אופציות
A5: 62195 | B5: =VLOOKUP(A5,'TB - Inc'!A:B,2,0) -> Sales Expenses:Other:Sales - Options | D5: -1751
A6: 66165 | B6: =VLOOKUP(A6,'TB - Inc'!A:B,2,0) -> Business Operations Expenses:Other:Business Operations - Options | D6: 11.42
A7: 72275 | B7: =VLOOKUP(A7,'TB - Inc'!A:B,2,0) -> Marketing Expenses:Other:Marketing - Options | D7: -5021
A8: 82165 | B8: =VLOOKUP(A8,'TB - Inc'!A:B,2,0) -> Customer Success Expenses:Other:Customer Success - Options | D8: 2841.2
A9: 25000 | B9: =VLOOKUP(A9,'TB - Inc'!A:B,2,0) -> Intercompany- Talon Cyber Security LTD | D9: =-SUM(D4:D8) -> 5362.98
A11: New49 | B11: =VLOOKUP(A11,'TB - Inc'!A:B,2,0) -> Subcontractors & Consulting | D11: 100000 | E11: מיון הוצאה - ייעוץ פטנטים מארה"ב
A12: 93140 | B12: =VLOOKUP(A12,'TB - Inc'!A:B,2,0) -> G&A Expenses:Consultants & Service Providers:Consulting Expenes | D12: -100000
A14: 25000 | B14: =VLOOKUP(A14,'TB - Inc'!A:B,2,0) -> Intercompany- Talon Cyber Security LTD | D14: 2586533.7 | E14: Intercompany Q4
A15: 40500 | B15: =VLOOKUP(A15,'TB - Inc'!A:B,2,0) -> Revenue:Intercompany Revenue | D15: =-D14 -> -2586533.7

Sheet נסיעות לחו"ל
E2: Sensible
E3: 2013
E4: קובץ חישוב הוצאות לא מוכרות לצורך מס - נסיעות לחו"ל
E5: ב - $ של ארה"ב
E6: ראה תקרות למטה
I9: Total | J9: Car | K9: Hotel | U9: meals/ | W9: Hotel | X9: other | Y9: car | Z9: car
A10: Card No. | C10: Name | D10: תעריפים רגילים או תוספת 25% | E10: Country | F10: Departure date | G10: Return date | I10: days | J10: days | K10: days | L10: Hotel $ | M10: Telephone | N10: Transportation | O10: Meals | P10: אירוח | Q10: Other | R10: Other - ALLOWED EXPENSES | S10: Car | T10: מיון | U10: other | V10: Total | W10: disa | X10: disa | Y10: diss | Z10: days | AA10: Ticket | AB10: Total | AC10: Total NIS
V11: =SUM(L11:T11) -> 0 | AB11: =+AA11+V11 -> 0
A12: ="81700" -> 81700 | D12: רגיל | E12: USA | F12: 41522 | G12: 41527 | I12: =G12-F12+1 -> 6 | K12: =+I12-1 -> 5 | R12: =#REF! -> #REF! | U12: =O12+Q12 -> 0 | V12: =SUM(L12:T12) -> #REF! | W12: =IF(F12>0,ROUND(IF(K12<=7,IF(L12/K12<=תקרת_מלון_ל___7_ראשונים,0,L12-K12*תקרת_מלון_ל___7_ראשונים),IF(L12/K12<=תקרת_מלון_נמוכה,0,IF(L12/K12<=תקרת_מלון_גבוה,L12-7*L12/K12-(K12-7)*MAXA(תקרת_מלון_נמוכה,75%*L12/K12),(L12-7*MINA(L12/K12,תקרת_מלון_ל___7_ראשונים)-(K12-7)*MINA(75%*L12/K12,תקרת_מלון_גבוה))))),0),0) -> 0 | X12: =IF(L12>0,IF(U12/I12<תקרת_אשל_ליום___עם_לינה,0,U12-I12*תקרת_אשל_ליום___עם_לינה),IF(U12/I12<תקרת_אשל_ליום___ללא_לינה,0,U12-I12*תקרת_אשל_ליום___ללא_לינה)) -> 0 | Y12: =IF((S12-($E$66*Z12))>0,(S12-($E$66*Z12)),0) -> 0 | Z12: =J12 -> 0 | AB12: =+AA12+V12 -> #REF! | AC12: 783 | AD12: =AC12/AB12 -> #REF!
D13: רגיל | E13: USA | F13: 41522 | G13: 41527 | I13: =G13-F13+1 -> 6 | K13: =+I13-1 -> 5 | Q13: =#REF! -> #REF! | U13: =O13+Q13 -> #REF! | V13: =SUM(L13:T13) -> #REF! | W13: =IF(F13>0,ROUND(IF(K13<=7,IF(L13/K13<=תקרת_מלון_ל___7_ראשונים,0,L13-K13*תקרת_מלון_ל___7_ראשונים),IF(L13/K13<=תקרת_מלון_נמוכה,0,IF(L13/K13<=תקרת_מלון_גבוה,L13-7*L13/K13-(K13-7)*MAXA(תקרת_מלון_נמוכה,75%*L13/K13),(L13-7*MINA(L13/K13,תקרת_מלון_ל___7_ראשונים)-(K13-7)*MINA(75%*L13/K13,תקרת_מלון_גבוה))))),0),0) -> 0 | X13: =IF(L13>0,IF(U13/I13<תקרת_אשל_ליום___עם_לינה,0,U13-I13*תקרת_אשל_ליום___עם_לינה),IF(U13/I13<תקרת_אשל_ליום___ללא_לינה,0,U13-I13*תקרת_אשל_ליום___ללא_לינה)) -> #REF! | Y13: =IF((S13-($E$66*Z13))>0,(S13-($E$66*Z13)),0) -> 0 | Z13: =J13 -> 0 | AA13: =#REF!+#REF! -> #REF! | AB13: =+AA13+V13 -> #REF! | AC13: 11567 | AD13: =AC13/AB13 -> #REF!
D14: 25% יותר | E14: Italy, Germany | F14: 41297 | G14: 41301 | I14: =G14-F14+1 -> 5 | K14: =+I14-1 -> 4 | N14: =#REF! -> #REF! | Q14: =#REF!+#REF! -> #REF! | R14: =#REF! -> #REF! | U14: =O14+Q14 -> #REF! | V14: =SUM(L14:T14) -> #REF! | W14: =IF(F14>0,ROUND(IF(K14<=7,IF(L14/K14<=תקרת_מלון_ל___7_ראשונים,0,L14-K14*תקרת_מלון_ל___7_ראשונים),IF(L14/K14<=תקרת_מלון_נמוכה,0,IF(L14/K14<=תקרת_מלון_גבוה,L14-7*L14/K14-(K14-7)*MAXA(תקרת_מלון_נמוכה,75%*L14/K14),(L14-7*MINA(L14/K14,תקרת_מלון_ל___7_ראשונים)-(K14-7)*MINA(75%*L14/K14,תקרת_מלון_גבוה))))),0),0) -> 0 | X14: =IF(L14>0,IF(U14/I14<תקרת_אשל_ליום___עם_לינה,0,U14-I14*תקרת_אשל_ליום___עם_לינה),IF(U14/I14<תקרת_אשל_ליום___ללא_לינה,0,U14-I14*תקרת_אשל_ליום___ללא_לינה)) -> #REF! | Y14: =IF((S14-($E$66*Z14))>0,(S14-($E$66*Z14)),0) -> 0 | Z14: =J14 -> 0 | AA14: =#REF! -> #REF! | AB14: =+AA14+V14 -> #REF! | AC14: 6416 | AD14: =AC14/AB14 -> #REF!
D15: 25% יותר | E15: Germany, Spain | F15: 41319 | G15: 41326 | I15: =G15-F15+1 -> 8 | K15: =+I15-1 -> 7 | L15: =#REF!+#REF!+#REF!+#REF!+#REF! -> #REF! | M15: =#REF! -> #REF! | N15: =#REF! -> #REF! | Q15: =#REF! -> #REF! | U15: =O15+Q15 -> #REF! | V15: =SUM(L15:T15) -> #REF! | W15: =IF(F15>0,ROUND(IF(K15<=7,IF(L15/K15<=תקרת_מלון_ל___7_ראשונים,0,L15-K15*תקרת_מלון_ל___7_ראשונים),IF(L15/K15<=תקרת_מלון_נמוכה,0,IF(L15/K15<=תקרת_מלון_גבוה,L15-7*L15/K15-(K15-7)*MAXA(תקרת_מלון_נמוכה,75%*L15/K15),(L15-7*MINA(L15/K15,תקרת_מלון_ל___7_ראשונים)-(K15-7)*MINA(75%*L15/K15,תקרת_מלון_גבוה))))),0),0) -> #REF! | X15: =IF(L15>0,IF(U15/I15<תקרת_אשל_ליום___עם_לינה,0,U15-I15*תקרת_אשל_ליום___עם_לינה),IF(U15/I15<תקרת_אשל_ליום___ללא_לינה,0,U15-I15*תקרת_אשל_ליום___ללא_לינה)) -> #REF! | Y15: =IF((S15-($E$66*Z15))>0,(S15-($E$66*Z15)),0) -> 0 | Z15: =J15 -> 0 | AA15: =#REF!+#REF! -> #REF! | AB15: =+AA15+V15 -> #REF! | AC15: 12151 | AD15: =AC15/AB15 -> #REF!
D16: 25% יותר | E16: Germany | F16: 41382 | G16: 41389 | I16: =G16-F16+1 -> 8 | J16: 7 | K16: =+I16-1 -> 7 | N16: =#REF! -> #REF! | Q16: =#REF! -> #REF! | S16: =#REF! -> #REF! | U16: =O16+Q16 -> #REF! | V16: =SUM(L16:T16) -> #REF! | W16: =IF(F16>0,ROUND(IF(K16<=7,IF(L16/K16<=תקרת_מלון_ל___7_ראשונים,0,L16-K16*תקרת_מלון_ל___7_ראשונים),IF(L16/K16<=תקרת_מלון_נמוכה,0,IF(L16/K16<=תקרת_מלון_גבוה,L16-7*L16/K16-(K16-7)*MAXA(תקרת_מלון_נמוכה,75%*L16/K16),(L16-7*MINA(L16/K16,תקרת_מלון_ל___7_ראשונים)-(K16-7)*MINA(75%*L16/K16,תקרת_מלון_גבוה))))),0),0) -> 0 | X16: =IF(L16>0,IF(U16/I16<תקרת_אשל_ליום___עם_לינה,0,U16-I16*תקרת_אשל_ליום___עם_לינה),IF(U16/I16<תקרת_אשל_ליום___ללא_לינה,0,U16-I16*תקרת_אשל_ליום___ללא_לינה)) -> #REF! | Y16: =IF((S16-($E$66*Z16))>0,(S16-($E$66*Z16)),0) -> #REF! | Z16: =J16 -> 7 | AA16: =#REF! -> #REF! | AB16: =+AA16+V16 -> #REF! | AC16: 7574 | AD16: =AC16/AB16 -> #REF!
D17: 25% יותר | E17: Germany | F17: 41441 | G17: 41445 | I17: =G17-F17+1 -> 5 | J17: 4 | K17: =+I17-1 -> 4 | L17: =#REF! -> #REF! | Q17: =#REF! -> #REF! | S17: =#REF!+#REF! -> #REF! | U17: =O17+Q17 -> #REF! | V17: =SUM(L17:T17) -> #REF! | W17: =IF(F17>0,ROUND(IF(K17<=7,IF(L17/K17<=תקרת_מלון_ל___7_ראשונים,0,L17-K17*תקרת_מלון_ל___7_ראשונים),IF(L17/K17<=תקרת_מלון_נמוכה,0,IF(L17/K17<=תקרת_מלון_גבוה,L17-7*L17/K17-(K17-7)*MAXA(תקרת_מלון_נמוכה,75%*L17/K17),(L17-7*MINA(L17/K17,תקרת_מלון_ל___7_ראשונים)-(K17-7)*MINA(75%*L17/K17,תקרת_מלון_גבוה))))),0),0) -> #REF! | X17: =IF(L17>0,IF(U17/I17<תקרת_אשל_ליום___עם_לינה,0,U17-I17*תקרת_אשל_ליום___עם_לינה),IF(U17/I17<תקרת_אשל_ליום___ללא_לינה,0,U17-I17*תקרת_אשל_ליום___ללא_לינה)) -> #REF! | Y17: =IF((S17-($E$66*Z17))>0,(S17-($E$66*Z17)),0) -> #REF! | Z17: =J17 -> 4 | AA17: =#REF! -> #REF! | AB17: =+AA17+V17 -> #REF! | AC17: 6689 | AD17: =AC17/AB17 -> #REF!
D18: 25% יותר | E18: Germany | F18: 41485 | G18: 41488 | I18: =G18-F18+1 -> 4 | J18: 3 | K18: =+I18-1 -> 3 | L18: =#REF! -> #REF! | N18: =#REF! -> #REF! | Q18: =#REF!+#REF!+#REF! -> #REF! | S18: =#REF!+#REF! -> #REF! | U18: =O18+Q18 -> #REF! | V18: =SUM(L18:T18) -> #REF! | W18: =IF(F18>0,ROUND(IF(K18<=7,IF(L18/K18<=תקרת_מלון_ל___7_ראשונים,0,L18-K18*תקרת_מלון_ל___7_ראשונים),IF(L18/K18<=תקרת_מלון_נמוכה,0,IF(L18/K18<=תקרת_מלון_גבוה,L18-7*L18/K18-(K18-7)*MAXA(תקרת_מלון_נמוכה,75%*L18/K18),(L18-7*MINA(L18/K18,תקרת_מלון_ל___7_ראשונים)-(K18-7)*MINA(75%*L18/K18,תקרת_מלון_גבוה))))),0),0) -> #REF! | X18: =IF(L18>0,IF(U18/I18<תקרת_אשל_ליום___עם_לינה,0,U18-I18*תקרת_אשל_ליום___עם_לינה),IF(U18/I18<תקרת_אשל_ליום___ללא_לינה,0,U18-I18*תקרת_אשל_ליום___ללא_לינה)) -> #REF! | Y18: =IF((S18-($E$66*Z18))>0,(S18-($E$66*Z18)),0) -> #REF! | Z18: =J18 -> 3 | AA18: =#REF! -> #REF! | AB18: =+AA18+V18 -> #REF! | AC18: 8995 | AD18: =AC18/AB18 -> #REF!
D19: 25% יותר | E19: Germany | F19: 41532 | G19: 41536 | I19: =G19-F19+1 -> 5 | K19: =+I19-1 -> 4 | L19: =#REF! -> #REF! | R19: =#REF! -> #REF! | U19: =O19+Q19 -> 0 | V19: =SUM(L19:T19) -> #REF! | W19: =IF(F19>0,ROUND(IF(K19<=7,IF(L19/K19<=תקרת_מלון_ל___7_ראשונים,0,L19-K19*תקרת_מלון_ל___7_ראשונים),IF(L19/K19<=תקרת_מלון_נמוכה,0,IF(L19/K19<=תקרת_מלון_גבוה,L19-7*L19/K19-(K19-7)*MAXA(תקרת_מלון_נמוכה,75%*L19/K19),(L19-7*MINA(L19/K19,תקרת_מלון_ל___7_ראשונים)-(K19-7)*MINA(75%*L19/K19,תקרת_מלון_גבוה))))),0),0) -> #REF! | X19: =IF(L19>0,IF(U19/I19<תקרת_אשל_ליום___עם_לינה,0,U19-I19*תקרת_אשל_ליום___עם_לינה),IF(U19/I19<תקרת_אשל_ליום___ללא_לינה,0,U19-I19*תקרת_אשל_ליום___ללא_לינה)) -> #REF! | Y19: =IF((S19-($E$66*Z19))>0,(S19-($E$66*Z19)),0) -> 0 | Z19: =J19 -> 0 | AA19: =#REF!+#REF! -> #REF! | AB19: =+AA19+V19 -> #REF! | AC19: 4497 | AD19: =AC19/AB19 -> #REF!
D20: רגיל | E20: USA | F20: 41545 | G20: 41554 | I20: =G20-F20+1 -> 10 | K20: =+I20-1 -> 9 | L20: =#REF! -> #REF! | N20: =#REF! -> #REF! | Q20: =#REF! -> #REF! | U20: =O20+Q20 -> #REF! | V20: =SUM(L20:T20) -> #REF! | W20: =IF(F20>0,ROUND(IF(K20<=7,IF(L20/K20<=תקרת_מלון_ל___7_ראשונים,0,L20-K20*תקרת_מלון_ל___7_ראשונים),IF(L20/K20<=תקרת_מלון_נמוכה,0,IF(L20/K20<=תקרת_מלון_גבוה,L20-7*L20/K20-(K20-7)*MAXA(תקרת_מלון_נמוכה,75%*L20/K20),(L20-7*MINA(L20/K20,תקרת_מלון_ל___7_ראשונים)-(K20-7)*MINA(75%*L20/K20,תקרת_מלון_גבוה))))),0),0) -> #REF! | X20: =IF(L20>0,IF(U20/I20<תקרת_אשל_ליום___עם_לינה,0,U20-I20*תקרת_אשל_ליום___עם_לינה),IF(U20/I20<תקרת_אשל_ליום___ללא_לינה,0,U20-I20*תקרת_אשל_ליום___ללא_לינה)) -> #REF! | Y20: =IF((S20-($E$66*Z20))>0,(S20-($E$66*Z20)),0) -> 0 | Z20: =J20 -> 0 | AA20: =#REF! -> #REF! | AB20: =+AA20+V20 -> #REF! | AC20: 12549 | AD20: =AC20/AB20 -> #REF!
D21: 25% יותר | E21: Austria | F21: 41622 | G21: 41627 | I21: =G21-F21+1 -> 6 | J21: 5 | K21: =+I21-1 -> 5 | L21: =#REF! -> #REF! | R21: 860.83 | S21: =#REF! -> #REF! | U21: =O21+Q21 -> 0 | V21: =SUM(L21:T21) -> #REF! | W21: =IF(F21>0,ROUND(IF(K21<=7,IF(L21/K21<=תקרת_מלון_ל___7_ראשונים,0,L21-K21*תקרת_מלון_ל___7_ראשונים),IF(L21/K21<=תקרת_מלון_נמוכה,0,IF(L21/K21<=תקרת_מלון_גבוה,L21-7*L21/K21-(K21-7)*MAXA(תקרת_מלון_נמוכה,75%*L21/K21),(L21-7*MINA(L21/K21,תקרת_מלון_ל___7_ראשונים)-(K21-7)*MINA(75%*L21/K21,תקרת_מלון_גבוה))))),0),0) -> #REF! | X21: =IF(L21>0,IF(U21/I21<תקרת_אשל_ליום___עם_לינה,0,U21-I21*תקרת_אשל_ליום___עם_לינה),IF(U21/I21<תקרת_אשל_ליום___ללא_לינה,0,U21-I21*תקרת_אשל_ליום___ללא_לינה)) -> #REF! | Y21: =IF((S21-($E$66*Z21))>0,(S21-($E$66*Z21)),0) -> #REF! | Z21: =J21 -> 5 | AB21: =+AA21+V21 -> #REF! | AC21: 4072 | AD21: =AC21/AB21 -> #REF!
D22: 25% יותר | E22: Germany | F22: 41619 | G22: 41625 | I22: =G22-F22+1 -> 7 | J22: 6 | K22: =+I22-1 -> 6 | L22: =#REF! -> #REF! | M22: =#REF! -> #REF! | Q22: =#REF!+#REF! -> #REF! | S22: =#REF!+#REF! -> #REF! | U22: =O22+Q22 -> #REF! | V22: =SUM(L22:T22) -> #REF! | W22: =IF(F22>0,ROUND(IF(K22<=7,IF(L22/K22<=תקרת_מלון_ל___7_ראשונים,0,L22-K22*תקרת_מלון_ל___7_ראשונים),IF(L22/K22<=תקרת_מלון_נמוכה,0,IF(L22/K22<=תקרת_מלון_גבוה,L22-7*L22/K22-(K22-7)*MAXA(תקרת_מלון_נמוכה,75%*L22/K22),(L22-7*MINA(L22/K22,תקרת_מלון_ל___7_ראשונים)-(K22-7)*MINA(75%*L22/K22,תקרת_מלון_גבוה))))),0),0) -> #REF! | X22: =IF(L22>0,IF(U22/I22<תקרת_אשל_ליום___עם_לינה,0,U22-I22*תקרת_אשל_ליום___עם_לינה),IF(U22/I22<תקרת_אשל_ליום___ללא_לינה,0,U22-I22*תקרת_אשל_ליום___ללא_לינה)) -> #REF! | Y22: =IF((S22-($E$66*Z22))>0,(S22-($E$66*Z22)),0) -> #REF! | Z22: =J22 -> 6 | AB22: =+AA22+V22 -> #REF! | AC22: 5143 | AD22: =AC22/AB22 -> #REF!
D23: רגיל | E23: USA | F23: 41287 | G23: 41288 | I23: =G23-F23+1 -> 2 | K23: =+I23-1 -> 1 | L23: =#REF! -> #REF! | N23: =#REF! -> #REF! | O23: =#REF! -> #REF! | Q23: =#REF! -> #REF! | U23: =O23+Q23 -> #REF! | V23: =SUM(L23:T23) -> #REF! | W23: =IF(F23>0,ROUND(IF(K23<=7,IF(L23/K23<=תקרת_מלון_ל___7_ראשונים,0,L23-K23*תקרת_מלון_ל___7_ראשונים),IF(L23/K23<=תקרת_מלון_נמוכה,0,IF(L23/K23<=תקרת_מלון_גבוה,L23-7*L23/K23-(K23-7)*MAXA(תקרת_מלון_נמוכה,75%*L23/K23),(L23-7*MINA(L23/K23,תקרת_מלון_ל___7_ראשונים)-(K23-7)*MINA(75%*L23/K23,תקרת_מלון_גבוה))))),0),0) -> #REF! | X23: =IF(L23>0,IF(U23/I23<תקרת_אשל_ליום___עם_לינה,0,U23-I23*תקרת_אשל_ליום___עם_לינה),IF(U23/I23<תקרת_אשל_ליום___ללא_לינה,0,U23-I23*תקרת_אשל_ליום___ללא_לינה)) -> #REF! | Y23: =IF((S23-($E$66*Z23))>0,(S23-($E$66*Z23)),0) -> 0 | Z23: =J23 -> 0 | AA23: =#REF! -> #REF! | AB23: =+AA23+V23 -> #REF! | AC23: 11782 | AD23: =AC23/AB23 -> #REF!
D24: רגיל | E24: USA | F24: 41368 | G24: 41375 | I24: =G24-F24+1 -> 8 | J24: 7 | K24: =+I24-1 -> 7 | L24: =#REF!+#REF!+#REF! -> #REF! | M24: =#REF! -> #REF! | Q24: =#REF!+#REF! -> #REF! | S24: =#REF! -> #REF! | U24: =O24+Q24 -> #REF! | V24: =SUM(L24:T24) -> #REF! | W24: =IF(F24>0,ROUND(IF(K24<=7,IF(L24/K24<=תקרת_מלון_ל___7_ראשונים,0,L24-K24*תקרת_מלון_ל___7_ראשונים),IF(L24/K24<=תקרת_מלון_נמוכה,0,IF(L24/K24<=תקרת_מלון_גבוה,L24-7*L24/K24-(K24-7)*MAXA(תקרת_מלון_נמוכה,75%*L24/K24),(L24-7*MINA(L24/K24,תקרת_מלון_ל___7_ראשונים)-(K24-7)*MINA(75%*L24/K24,תקרת_מלון_גבוה))))),0),0) -> #REF! | X24: =IF(L24>0,IF(U24/I24<תקרת_אשל_ליום___עם_לינה,0,U24-I24*תקרת_אשל_ליום___עם_לינה),IF(U24/I24<תקרת_אשל_ליום___ללא_לינה,0,U24-I24*תקרת_אשל_ליום___ללא_לינה)) -> #REF! | Y24: =IF((S24-($E$66*Z24))>0,(S24-($E$66*Z24)),0) -> #REF! | Z24: =J24 -> 7 | AA24: =#REF! -> #REF! | AB24: =+AA24+V24 -> #REF! | AC24: 15834 | AD24: =AC24/AB24 -> #REF!
D25: רגיל | E25: USA | F25: 41492 | G25: 41495 | I25: =G25-F25+1 -> 4 | K25: =+I25-1 -> 3 | L25: =#REF!+#REF! -> #REF! | O25: =#REF! -> #REF! | Q25: =#REF! -> #REF! | U25: =O25+Q25 -> #REF! | V25: =SUM(L25:T25) -> #REF! | W25: =IF(F25>0,ROUND(IF(K25<=7,IF(L25/K25<=תקרת_מלון_ל___7_ראשונים,0,L25-K25*תקרת_מלון_ל___7_ראשונים),IF(L25/K25<=תקרת_מלון_נמוכה,0,IF(L25/K25<=תקרת_מלון_גבוה,L25-7*L25/K25-(K25-7)*MAXA(תקרת_מלון_נמוכה,75%*L25/K25),(L25-7*MINA(L25/K25,תקרת_מלון_ל___7_ראשונים)-(K25-7)*MINA(75%*L25/K25,תקרת_מלון_גבוה))))),0),0) -> #REF! | X25: =IF(L25>0,IF(U25/I25<תקרת_אשל_ליום___עם_לינה,0,U25-I25*תקרת_אשל_ליום___עם_לינה),IF(U25/I25<תקרת_אשל_ליום___ללא_לינה,0,U25-I25*תקרת_אשל_ליום___ללא_לינה)) -> #REF! | Y25: =IF((S25-($E$66*Z25))>0,(S25-($E$66*Z25)),0) -> 0 | Z25: =J25 -> 0 | AA25: =#REF!+#REF!+#REF!+#REF! -> #REF! | AB25: =+AA25+V25 -> #REF! | AC25: 15204 | AD25: =AC25/AB25 -> #REF!
D26: רגיל | E26: USA | F26: 41602 | G26: 41605 | I26: =G26-F26+1 -> 4 | K26: =+I26-1 -> 3 | L26: =#REF! -> #REF! | N26: =#REF! -> #REF! | Q26: =#REF! -> #REF! | U26: =O26+Q26 -> #REF! | V26: =SUM(L26:T26) -> #REF! | W26: =IF(F26>0,ROUND(IF(K26<=7,IF(L26/K26<=תקרת_מלון_ל___7_ראשונים,0,L26-K26*תקרת_מלון_ל___7_ראשונים),IF(L26/K26<=תקרת_מלון_נמוכה,0,IF(L26/K26<=תקרת_מלון_גבוה,L26-7*L26/K26-(K26-7)*MAXA(תקרת_מלון_נמוכה,75%*L26/K26),(L26-7*MINA(L26/K26,תקרת_מלון_ל___7_ראשונים)-(K26-7)*MINA(75%*L26/K26,תקרת_מלון_גבוה))))),0),0) -> #REF! | X26: =IF(L26>0,IF(U26/I26<תקרת_אשל_ליום___עם_לינה,0,U26-I26*תקרת_אשל_ליום___עם_לינה),IF(U26/I26<תקרת_אשל_ליום___ללא_לינה,0,U26-I26*תקרת_אשל_ליום___ללא_לינה)) -> #REF! | Y26: =IF((S26-($E$66*Z26))>0,(S26-($E$66*Z26)),0) -> 0 | Z26: =J26 -> 0 | AA26: =#REF! -> #REF! | AB26: =+AA26+V26 -> #REF! | AC26: 10679 | AD26: =AC26/AB26 -> #REF!
D27: רגיל | E27: USA | F27: 41592 | G27: 41594 | I27: =G27-F27+1 -> 3 | K27: =+I27-1 -> 2 | R27: =#REF! -> #REF! | U27: =O27+Q27 -> 0 | V27: =SUM(L27:T27) -> #REF! | W27: =IF(F27>0,ROUND(IF(K27<=7,IF(L27/K27<=תקרת_מלון_ל___7_ראשונים,0,L27-K27*תקרת_מלון_ל___7_ראשונים),IF(L27/K27<=תקרת_מלון_נמוכה,0,IF(L27/K27<=תקרת_מלון_גבוה,L27-7*L27/K27-(K27-7)*MAXA(תקרת_מלון_נמוכה,75%*L27/K27),(L27-7*MINA(L27/K27,תקרת_מלון_ל___7_ראשונים)-(K27-7)*MINA(75%*L27/K27,תקרת_מלון_גבוה))))),0),0) -> 0 | X27: =IF(L27>0,IF(U27/I27<תקרת_אשל_ליום___עם_לינה,0,U27-I27*תקרת_אשל_ליום___עם_לינה),IF(U27/I27<תקרת_אשל_ליום___ללא_לינה,0,U27-I27*תקרת_אשל_ליום___ללא_לינה)) -> 0 | Y27: =IF((S27-($E$66*Z27))>0,(S27-($E$66*Z27)),0) -> 0 | Z27: =J27 -> 0 | AB27: =AA27+V27 -> #REF! | AC27: 3054.54 | AD27: =AC27/AB27 -> #REF!
D28: רגיל | E28: USA | F28: 41287 | G28: 41290 | I28: =G28-F28+1 -> 4 | K28: =+I28-1 -> 3 | L28: =#REF! -> #REF! | N28: =#REF!+#REF!+#REF! -> #REF! | O28: =#REF! -> #REF! | Q28: =#REF!+#REF!+#REF! -> #REF! | R28: =#REF!+#REF!+#REF! -> #REF! | U28: =O28+Q28 -> #REF! | V28: =SUM(L28:T28) -> #REF! | W28: =IF(F28>0,ROUND(IF(K28<=7,IF(L28/K28<=תקרת_מלון_ל___7_ראשונים,0,L28-K28*תקרת_מלון_ל___7_ראשונים),IF(L28/K28<=תקרת_מלון_נמוכה,0,IF(L28/K28<=תקרת_מלון_גבוה,L28-7*L28/K28-(K28-7)*MAXA(תקרת_מלון_נמוכה,75%*L28/K28),(L28-7*MINA(L28/K28,תקרת_מלון_ל___7_ראשונים)-(K28-7)*MINA(75%*L28/K28,תקרת_מלון_גבוה))))),0),0) -> #REF! | X28: =IF(L28>0,IF(U28/I28<תקרת_אשל_ליום___עם_לינה,0,U28-I28*תקרת_אשל_ליום___עם_לינה),IF(U28/I28<תקרת_אשל_ליום___ללא_לינה,0,U28-I28*תקרת_אשל_ליום___ללא_לינה)) -> #REF! | Y28: =IF((S28-($E$66*Z28))>0,(S28-($E$66*Z28)),0) -> 0 | Z28: =J28 -> 0 | AA28: =#REF! -> #REF! | AB28: =+AA28+V28 -> #REF! | AC28: 18233 | AD28: =AC28/AB28 -> #REF!
D29: 25% יותר | E29: Italy, Germany | F29: 41297 | G29: 41301 | I29: =G29-F29+1 -> 5 | J29: 4 | K29: =+I29-1 -> 4 | L29: =#REF!+#REF!+#REF!+#REF!+#REF! -> #REF! | N29: =#REF!+#REF! -> #REF! | O29: =#REF!+#REF!+#REF! -> #REF! | P29: =#REF! -> #REF! | Q29: =#REF! -> #REF! | R29: =#REF! -> #REF! | S29: =#REF! -> #REF! | U29: =O29+Q29 -> #REF! | V29: =SUM(L29:T29) -> #REF! | W29: =IF(F29>0,ROUND(IF(K29<=7,IF(L29/K29<=תקרת_מלון_ל___7_ראשונים,0,L29-K29*תקרת_מלון_ל___7_ראשונים),IF(L29/K29<=תקרת_מלון_נמוכה,0,IF(L29/K29<=תקרת_מלון_גבוה,L29-7*L29/K29-(K29-7)*MAXA(תקרת_מלון_נמוכה,75%*L29/K29),(L29-7*MINA(L29/K29,תקרת_מלון_ל___7_ראשונים)-(K29-7)*MINA(75%*L29/K29,תקרת_מלון_גבוה))))),0),0) -> #REF! | X29: =IF(L29>0,IF(U29/I29<תקרת_אשל_ליום___עם_לינה,0,U29-I29*תקרת_אשל_ליום___עם_לינה),IF(U29/I29<תקרת_אשל_ליום___ללא_לינה,0,U29-I29*תקרת_אשל_ליום___ללא_לינה)) -> #REF! | Y29: =IF((S29-($E$66*Z29))>0,(S29-($E$66*Z29)),0) -> #REF! | Z29: =J29 -> 4 | AA29: =#REF!+#REF! -> #REF! | AB29: =+AA29+V29 -> #REF! | AC29: 14562 | AD29: =AC29/AB29 -> #REF!
D30: 25% יותר | E30: Italy, Germany | F30: 41296 | G30: 41300 | I30: =G30-F30+1 -> 5 | J30: 4 | K30: =+I30-1 -> 4 | N30: =#REF! -> #REF! | Q30: =#REF!+#REF! -> #REF! | R30: =#REF! -> #REF! | S30: =#REF! -> #REF! | U30: =O30+Q30 -> #REF! | V30: =SUM(L30:T30) -> #REF! | W30: =IF(F30>0,ROUND(IF(K30<=7,IF(L30/K30<=תקרת_מלון_ל___7_ראשונים,0,L30-K30*תקרת_מלון_ל___7_ראשונים),IF(L30/K30<=תקרת_מלון_נמוכה,0,IF(L30/K30<=תקרת_מלון_גבוה,L30-7*L30/K30-(K30-7)*MAXA(תקרת_מלון_נמוכה,75%*L30/K30),(L30-7*MINA(L30/K30,תקרת_מלון_ל___7_ראשונים)-(K30-7)*MINA(75%*L30/K30,תקרת_מלון_גבוה))))),0),0) -> 0 | X30: =IF(L30>0,IF(U30/I30<תקרת_אשל_ליום___עם_לינה,0,U30-I30*תקרת_אשל_ליום___עם_לינה),IF(U30/I30<תקרת_אשל_ליום___ללא_לינה,0,U30-I30*תקרת_אשל_ליום___ללא_לינה)) -> #REF! | Y30: =IF((S30-($E$66*Z30))>0,(S30-($E$66*Z30)),0) -> #REF! | Z30: =J30 -> 4 | AA30: =#REF! -> #REF! | AB30: =+AA30+V30 -> #REF! | AC30: 6552 | AD30: =AC30/AB30 -> #REF!
D31: 25% יותר | E31: Italy, Germany | F31: 41319 | G31: 41327 | I31: =G31-F31+1 -> 9 | J31: 8 | K31: =+I31-1 -> 8 | L31: =#REF!+#REF!+#REF!+#REF! -> #REF! | N31: =#REF! -> #REF! | O31: =#REF! -> #REF! | P31: =#REF!+#REF!+#REF! -> #REF! | Q31: =#REF!+#REF!+#REF! -> #REF! | R31: =#REF! -> #REF! | S31: =#REF!+#REF!+#REF! -> #REF! | U31: =O31+Q31 -> #REF! | V31: =SUM(L31:T31) -> #REF! | W31: =IF(F31>0,ROUND(IF(K31<=7,IF(L31/K31<=תקרת_מלון_ל___7_ראשונים,0,L31-K31*תקרת_מלון_ל___7_ראשונים),IF(L31/K31<=תקרת_מלון_נמוכה,0,IF(L31/K31<=תקרת_מלון_גבוה,L31-7*L31/K31-(K31-7)*MAXA(תקרת_מלון_נמוכה,75%*L31/K31),(L31-7*MINA(L31/K31,תקרת_מלון_ל___7_ראשונים)-(K31-7)*MINA(75%*L31/K31,תקרת_מלון_גבוה))))),0),0) -> #REF! | X31: =IF(L31>0,IF(U31/I31<תקרת_אשל_ליום___עם_לינה,0,U31-I31*תקרת_אשל_ליום___עם_לינה),IF(U31/I31<תקרת_אשל_ליום___ללא_לינה,0,U31-I31*תקרת_אשל_ליום___ללא_לינה)) -> #REF! | Y31: =IF((S31-($E$66*Z31))>0,(S31-($E$66*Z31)),0) -> #REF! | Z31: =J31 -> 8 | AA31: =#REF!+#REF! -> #REF! | AB31: =+AA31+V31 -> #REF! | AC31: 17873 | AD31: =AC31/AB31 -> #REF!
D32: 25% יותר | E32: Germany, Spain | F32: 41319 | G32: 41327 | I32: =G32-F32+1 -> 9 | J32: 8 | K32: =+I32-1 -> 8 | L32: =#REF!+#REF!+#REF!+#REF! -> #REF! | Q32: =#REF! -> #REF! | R32: =#REF! -> #REF! | S32: =#REF! -> #REF! | U32: =O32+Q32 -> #REF! | V32: =SUM(L32:T32) -> #REF! | W32: =IF(F32>0,ROUND(IF(K32<=7,IF(L32/K32<=תקרת_מלון_ל___7_ראשונים,0,L32-K32*תקרת_מלון_ל___7_ראשונים),IF(L32/K32<=תקרת_מלון_נמוכה,0,IF(L32/K32<=תקרת_מלון_גבוה,L32-7*L32/K32-(K32-7)*MAXA(תקרת_מלון_נמוכה,75%*L32/K32),(L32-7*MINA(L32/K32,תקרת_מלון_ל___7_ראשונים)-(K32-7)*MINA(75%*L32/K32,תקרת_מלון_גבוה))))),0),0) -> #REF! | X32: =IF(L32>0,IF(U32/I32<תקרת_אשל_ליום___עם_לינה,0,U32-I32*תקרת_אשל_ליום___עם_לינה),IF(U32/I32<תקרת_אשל_ליום___ללא_לינה,0,U32-I32*תקרת_אשל_ליום___ללא_לינה)) -> #REF! | Y32: =IF((S32-($E$66*Z32))>0,(S32-($E$66*Z32)),0) -> #REF! | Z32: =J32 -> 8 | AA32: =#REF!+#REF! -> #REF! | AB32: =+AA32+V32 -> #REF! | AC32: 13118 | AD32: =AC32/AB32 -> #REF!
D33: 25% יותר | E33: Germany | F33: 41350 | G33: 41354 | I33: =G33-F33+1 -> 5 | K33: =+I33-1 -> 4 | L33: =#REF!+#REF! -> #REF! | U33: =O33+Q33 -> 0 | V33: =SUM(L33:T33) -> #REF! | W33: =IF(F33>0,ROUND(IF(K33<=7,IF(L33/K33<=תקרת_מלון_ל___7_ראשונים,0,L33-K33*תקרת_מלון_ל___7_ראשונים),IF(L33/K33<=תקרת_מלון_נמוכה,0,IF(L33/K33<=תקרת_מלון_גבוה,L33-7*L33/K33-(K33-7)*MAXA(תקרת_מלון_נמוכה,75%*L33/K33),(L33-7*MINA(L33/K33,תקרת_מלון_ל___7_ראשונים)-(K33-7)*MINA(75%*L33/K33,תקרת_מלון_גבוה))))),0),0) -> #REF! | X33: =IF(L33>0,IF(U33/I33<תקרת_אשל_ליום___עם_לינה,0,U33-I33*תקרת_אשל_ליום___עם_לינה),IF(U33/I33<תקרת_אשל_ליום___ללא_לינה,0,U33-I33*תקרת_אשל_ליום___ללא_לינה)) -> #REF! | Y33: =IF((S33-($E$66*Z33))>0,(S33-($E$66*Z33)),0) -> 0 | Z33: =J33 -> 0 | AA33: =#REF!+#REF! -> #REF! | AB33: =+AA33+V33 -> #REF! | AC33: 2097 | AD33: =AC33/AB33 -> #REF!
D34: רגיל | E34: USA | F34: 41382 | G34: 41389 | I34: =G34-F34+1 -> 8 | J34: 7 | K34: =+I34-1 -> 7 | L34: =#REF!+#REF!+#REF! -> #REF! | P34: =#REF!+#REF!+#REF! -> #REF! | Q34: =#REF! -> #REF! | S34: =#REF!+#REF!+#REF!+#REF!+#REF!+#REF! -> #REF! | U34: =O34+Q34 -> #REF! | V34: =SUM(L34:T34) -> #REF! | W34: =IF(F34>0,ROUND(IF(K34<=7,IF(L34/K34<=תקרת_מלון_ל___7_ראשונים,0,L34-K34*תקרת_מלון_ל___7_ראשונים),IF(L34/K34<=תקרת_מלון_נמוכה,0,IF(L34/K34<=תקרת_מלון_גבוה,L34-7*L34/K34-(K34-7)*MAXA(תקרת_מלון_נמוכה,75%*L34/K34),(L34-7*MINA(L34/K34,תקרת_מלון_ל___7_ראשונים)-(K34-7)*MINA(75%*L34/K34,תקרת_מלון_גבוה))))),0),0) -> #REF! | X34: =IF(L34>0,IF(U34/I34<תקרת_אשל_ליום___עם_לינה,0,U34-I34*תקרת_אשל_ליום___עם_לינה),IF(U34/I34<תקרת_אשל_ליום___ללא_לינה,0,U34-I34*תקרת_אשל_ליום___ללא_לינה)) -> #REF! | Y34: =IF((S34-($E$66*Z34))>0,(S34-($E$66*Z34)),0) -> #REF! | Z34: =J34 -> 7 | AA34: =#REF!+#REF! -> #REF! | AB34: =+AA34+V34 -> #REF! | AC34: 29639 | AD34: =AC34/AB34 -> #REF!
D35: 25% יותר | E35: Germany | F35: 41382 | G35: 41389 | I35: =G35-F35+1 -> 8 | J35: 7 | K35: =+I35-1 -> 7 | L35: =#REF! -> #REF! | N35: =#REF! -> #REF! | O35: =#REF! -> #REF! | Q35: =#REF! -> #REF! | U35: =O35+Q35 -> #REF! | V35: =SUM(L35:T35) -> #REF! | W35: =IF(F35>0,ROUND(IF(K35<=7,IF(L35/K35<=תקרת_מלון_ל___7_ראשונים,0,L35-K35*תקרת_מלון_ל___7_ראשונים),IF(L35/K35<=תקרת_מלון_נמוכה,0,IF(L35/K35<=תקרת_מלון_גבוה,L35-7*L35/K35-(K35-7)*MAXA(תקרת_מלון_נמוכה,75%*L35/K35),(L35-7*MINA(L35/K35,תקרת_מלון_ל___7_ראשונים)-(K35-7)*MINA(75%*L35/K35,תקרת_מלון_גבוה))))),0),0) -> #REF! | X35: =IF(L35>0,IF(U35/I35<תקרת_אשל_ליום___עם_לינה,0,U35-I35*תקרת_אשל_ליום___עם_לינה),IF(U35/I35<תקרת_אשל_ליום___ללא_לינה,0,U35-I35*תקרת_אשל_ליום___ללא_לינה)) -> #REF! | Y35: =IF((S35-($E$66*Z35))>0,(S35-($E$66*Z35)),0) -> 0 | Z35: =J35 -> 7 | AA35: =#REF! -> #REF! | AB35: =+AA35+V35 -> #REF! | AC35: 7295 | AD35: =AC35/AB35 -> #REF!
D36: רגיל | E36: USA | F36: 41373 | G36: 41375 | I36: =G36-F36+1 -> 3 | K36: =+I36-1 -> 2 | N36: =#REF! -> #REF! | O36: =#REF!+#REF! -> #REF! | P36: =#REF! -> #REF! | Q36: =#REF!+#REF! -> #REF! | U36: =O36+Q36 -> #REF! | V36: =SUM(L36:T36) -> #REF! | W36: =IF(F36>0,ROUND(IF(K36<=7,IF(L36/K36<=תקרת_מלון_ל___7_ראשונים,0,L36-K36*תקרת_מלון_ל___7_ראשונים),IF(L36/K36<=תקרת_מלון_נמוכה,0,IF(L36/K36<=תקרת_מלון_גבוה,L36-7*L36/K36-(K36-7)*MAXA(תקרת_מלון_נמוכה,75%*L36/K36),(L36-7*MINA(L36/K36,תקרת_מלון_ל___7_ראשונים)-(K36-7)*MINA(75%*L36/K36,תקרת_מלון_גבוה))))),0),0) -> 0 | X36: =IF(L36>0,IF(U36/I36<תקרת_אשל_ליום___עם_לינה,0,U36-I36*תקרת_אשל_ליום___עם_לינה),IF(U36/I36<תקרת_אשל_ליום___ללא_לינה,0,U36-I36*תקרת_אשל_ליום___ללא_לינה)) -> #REF! | Y36: =IF((S36-($E$66*Z36))>0,(S36-($E$66*Z36)),0) -> 0 | Z36: =J36 -> 0 | AB36: =+AA36+V36 -> #REF! | AC36: 2742 | AD36: =AC36/AB36 -> #REF!
D37: 25% יותר | E37: Germany | F37: 41468 | G37: 41482 | I37: =G37-F37+1 -> 15 | J37: 14 | K37: =+I37-1 -> 14 | L37: =#REF!+#REF!+#REF!+#REF!+#REF!+#REF! -> #REF! | N37: =#REF!+#REF!+#REF!+#REF!+#REF!+#REF!+#REF!+#REF!+#REF!+#REF!+#REF!+#REF!+#REF!+#REF!+#REF! -> #REF! | O37: =#REF!+#REF!+#REF!+#REF!+#REF! -> #REF! | P37: =#REF! -> #REF! | Q37: =#REF!+#REF!+#REF!+#REF! -> #REF! | S37: =#REF!+#REF!+#REF!+#REF!+#REF!+#REF!+#REF!+#REF! -> #REF! | U37: =O37+Q37 -> #REF! | V37: =SUM(L37:T37) -> #REF! | W37: =IF(F37>0,ROUND(IF(K37<=7,IF(L37/K37<=תקרת_מלון_ל___7_ראשונים,0,L37-K37*תקרת_מלון_ל___7_ראשונים),IF(L37/K37<=תקרת_מלון_נמוכה,0,IF(L37/K37<=תקרת_מלון_גבוה,L37-7*L37/K37-(K37-7)*MAXA(תקרת_מלון_נמוכה,75%*L37/K37),(L37-7*MINA(L37/K37,תקרת_מלון_ל___7_ראשונים)-(K37-7)*MINA(75%*L37/K37,תקרת_מלון_גבוה))))),0),0) -> #REF! | X37: =IF(L37>0,IF(U37/I37<תקרת_אשל_ליום___עם_לינה,0,U37-I37*תקרת_אשל_ליום___עם_לינה),IF(U37/I37<תקרת_אשל_ליום___ללא_לינה,0,U37-I37*תקרת_אשל_ליום___ללא_לינה)) -> #REF! | Y37: =IF((S37-($E$66*Z37))>0,(S37-($E$66*Z37)),0) -> #REF! | Z37: =J37 -> 14 | AA37: =#REF! -> #REF! | AB37: =+AA37+V37 -> #REF! | AC37: 22574 | AD37: =AC37/AB37 -> #REF!
D38: 25% יותר | E38: Germany | F38: 41441 | G38: 41445 | I38: =G38-F38+1 -> 5 | J38: 4 | K38: =+I38-1 -> 4 | L38: =#REF! -> #REF! | N38: =#REF!+#REF! -> #REF! | O38: =#REF! -> #REF! | Q38: =#REF!+#REF!+#REF! -> #REF! | S38: =#REF!+#REF! -> #REF! | U38: =O38+Q38 -> #REF! | V38: =SUM(L38:T38) -> #REF! | W38: =IF(F38>0,ROUND(IF(K38<=7,IF(L38/K38<=תקרת_מלון_ל___7_ראשונים,0,L38-K38*תקרת_מלון_ל___7_ראשונים),IF(L38/K38<=תקרת_מלון_נמוכה,0,IF(L38/K38<=תקרת_מלון_גבוה,L38-7*L38/K38-(K38-7)*MAXA(תקרת_מלון_נמוכה,75%*L38/K38),(L38-7*MINA(L38/K38,תקרת_מלון_ל___7_ראשונים)-(K38-7)*MINA(75%*L38/K38,תקרת_מלון_גבוה))))),0),0) -> #REF! | X38: =IF(L38>0,IF(U38/I38<תקרת_אשל_ליום___עם_לינה,0,U38-I38*תקרת_אשל_ליום___עם_לינה),IF(U38/I38<תקרת_אשל_ליום___ללא_לינה,0,U38-I38*תקרת_אשל_ליום___ללא_לינה)) -> #REF! | Y38: =IF((S38-($E$66*Z38))>0,(S38-($E$66*Z38)),0) -> #REF! | Z38: =J38 -> 4 | AA38: =#REF! -> #REF! | AB38: =+AA38+V38 -> #REF! | AC38: 7899 | AD38: =AC38/AB38 -> #REF!
D39: 25% יותר | E39: Germany | F39: 41479 | G39: 41485 | I39: =G39-F39+1 -> 7 | J39: 6 | K39: =+I39-1 -> 6 | L39: =#REF! -> #REF! | N39: =#REF!+#REF! -> #REF! | Q39: =#REF!+#REF!+#REF! -> #REF! | S39: =#REF!+#REF!+#REF! -> #REF! | U39: =O39+Q39 -> #REF! | V39: =SUM(L39:T39) -> #REF! | W39: =IF(F39>0,ROUND(IF(K39<=7,IF(L39/K39<=תקרת_מלון_ל___7_ראשונים,0,L39-K39*תקרת_מלון_ל___7_ראשונים),IF(L39/K39<=תקרת_מלון_נמוכה,0,IF(L39/K39<=תקרת_מלון_גבוה,L39-7*L39/K39-(K39-7)*MAXA(תקרת_מלון_נמוכה,75%*L39/K39),(L39-7*MINA(L39/K39,תקרת_מלון_ל___7_ראשונים)-(K39-7)*MINA(75%*L39/K39,תקרת_מלון_גבוה))))),0),0) -> #REF! | X39: =IF(L39>0,IF(U39/I39<תקרת_אשל_ליום___עם_לינה,0,U39-I39*תקרת_אשל_ליום___עם_לינה),IF(U39/I39<תקרת_אשל_ליום___ללא_לינה,0,U39-I39*תקרת_אשל_ליום___ללא_לינה)) -> #REF! | Y39: =IF((S39-($E$66*Z39))>0,(S39-($E$66*Z39)),0) -> #REF! | Z39: =J39 -> 6 | AA39: =#REF! -> #REF! | AB39: =+AA39+V39 -> #REF! | AC39: 9109 | AD39: =AC39/AB39 -> #REF!
D40: רגיל | E40: USA | F40: 41492 | G40: 41495 | I40: =G40-F40+1 -> 4 | J40: 3 | K40: =+I40-1 -> 3 | L40: =#REF!+#REF! -> #REF! | O40: =#REF!+#REF! -> #REF! | Q40: =#REF! -> #REF! | S40: =#REF! -> #REF! | U40: =O40+Q40 -> #REF! | V40: =SUM(L40:T40) -> #REF! | W40: =IF(F40>0,ROUND(IF(K40<=7,IF(L40/K40<=תקרת_מלון_ל___7_ראשונים,0,L40-K40*תקרת_מלון_ל___7_ראשונים),IF(L40/K40<=תקרת_מלון_נמוכה,0,IF(L40/K40<=תקרת_מלון_גבוה,L40-7*L40/K40-(K40-7)*MAXA(תקרת_מלון_נמוכה,75%*L40/K40),(L40-7*MINA(L40/K40,תקרת_מלון_ל___7_ראשונים)-(K40-7)*MINA(75%*L40/K40,תקרת_מלון_גבוה))))),0),0) -> #REF! | X40: =IF(L40>0,IF(U40/I40<תקרת_אשל_ליום___עם_לינה,0,U40-I40*תקרת_אשל_ליום___עם_לינה),IF(U40/I40<תקרת_אשל_ליום___ללא_לינה,0,U40-I40*תקרת_אשל_ליום___ללא_לינה)) -> #REF! | Y40: =IF((S40-($E$66*Z40))>0,(S40-($E$66*Z40)),0) -> #REF! | Z40: =J40 -> 3 | AA40: =#REF! -> #REF! | AB40: =+AA40+V40 -> #REF! | AC40: 3047 | AD40: =AC40/AB40 -> #REF!
D41: רגיל | E41: USA | F41: 41491 | G41: 41507 | I41: =G41-F41+1 -> 17 | K41: =+I41-1 -> 16 | O41: =#REF! -> #REF! | Q41: =#REF! -> #REF! | U41: =O41+Q41 -> #REF! | V41: =SUM(L41:T41) -> #REF! | W41: =IF(F41>0,ROUND(IF(K41<=7,IF(L41/K41<=תקרת_מלון_ל___7_ראשונים,0,L41-K41*תקרת_מלון_ל___7_ראשונים),IF(L41/K41<=תקרת_מלון_נמוכה,0,IF(L41/K41<=תקרת_מלון_גבוה,L41-7*L41/K41-(K41-7)*MAXA(תקרת_מלון_נמוכה,75%*L41/K41),(L41-7*MINA(L41/K41,תקרת_מלון_ל___7_ראשונים)-(K41-7)*MINA(75%*L41/K41,תקרת_מלון_גבוה))))),0),0) -> 0 | X41: =IF(L41>0,IF(U41/I41<תקרת_אשל_ליום___עם_לינה,0,U41-I41*תקרת_אשל_ליום___עם_לינה),IF(U41/I41<תקרת_אשל_ליום___ללא_לינה,0,U41-I41*תקרת_אשל_ליום___ללא_לינה)) -> #REF! | Y41: =IF((S41-($E$66*Z41))>0,(S41-($E$66*Z41)),0) -> 0 | Z41: =J41 -> 0 | AA41: =#REF!+#REF! -> #REF! | AB41: =+AA41+V41 -> #REF! | AC41: 11651 | AD41: =AC41/AB41 -> #REF!
D42: רגיל | E42: USA | F42: 41522 | G42: 41527 | I42: =G42-F42+1 -> 6 | K42: =+I42-1 -> 5 | L42: =#REF!+#REF!+#REF!+#REF! -> #REF! | N42: =#REF!+#REF!+#REF!+#REF!+#REF! -> #REF! | O42: =#REF!+#REF!+#REF!+#REF!+#REF! -> #REF! | Q42: =#REF!+#REF! -> #REF! | R42: =#REF! -> #REF! | U42: =O42+Q42 -> #REF! | V42: =SUM(L42:T42) -> #REF! | W42: =IF(F42>0,ROUND(IF(K42<=7,IF(L42/K42<=תקרת_מלון_ל___7_ראשונים,0,L42-K42*תקרת_מלון_ל___7_ראשונים),IF(L42/K42<=תקרת_מלון_נמוכה,0,IF(L42/K42<=תקרת_מלון_גבוה,L42-7*L42/K42-(K42-7)*MAXA(תקרת_מלון_נמוכה,75%*L42/K42),(L42-7*MINA(L42/K42,תקרת_מלון_ל___7_ראשונים)-(K42-7)*MINA(75%*L42/K42,תקרת_מלון_גבוה))))),0),0) -> #REF! | X42: =IF(L42>0,IF(U42/I42<תקרת_אשל_ליום___עם_לינה,0,U42-I42*תקרת_אשל_ליום___עם_לינה),IF(U42/I42<תקרת_אשל_ליום___ללא_לינה,0,U42-I42*תקרת_אשל_ליום___ללא_לינה)) -> #REF! | Y42: =IF((S42-($E$66*Z42))>0,(S42-($E$66*Z42)),0) -> 0 | Z42: =J42 -> 0 | AA42: =#REF!+#REF!+#REF! -> #REF! | AB42: =+AA42+V42 -> #REF! | AC42: 22494 | AD42: =AC42/AB42 -> #REF!
D43: 25% יותר | E43: France | F43: 41552 | G43: 41557 | I43: =G43-F43+1 -> 6 | K43: =+I43-1 -> 5 | L43: =#REF!+#REF!+#REF!+#REF!+#REF! -> #REF! | N43: =#REF! -> #REF! | O43: =#REF!+#REF!+#REF!+#REF! -> #REF! | Q43: =#REF!+#REF!+#REF! -> #REF! | U43: =O43+Q43 -> #REF! | V43: =SUM(L43:T43) -> #REF! | W43: =IF(F43>0,ROUND(IF(K43<=7,IF(L43/K43<=תקרת_מלון_ל___7_ראשונים,0,L43-K43*תקרת_מלון_ל___7_ראשונים),IF(L43/K43<=תקרת_מלון_נמוכה,0,IF(L43/K43<=תקרת_מלון_גבוה,L43-7*L43/K43-(K43-7)*MAXA(תקרת_מלון_נמוכה,75%*L43/K43),(L43-7*MINA(L43/K43,תקרת_מלון_ל___7_ראשונים)-(K43-7)*MINA(75%*L43/K43,תקרת_מלון_גבוה))))),0),0) -> #REF! | X43: =IF(L43>0,IF(U43/I43<תקרת_אשל_ליום___עם_לינה,0,U43-I43*תקרת_אשל_ליום___עם_לינה),IF(U43/I43<תקרת_אשל_ליום___ללא_לינה,0,U43-I43*תקרת_אשל_ליום___ללא_לינה)) -> #REF! | Y43: =IF((S43-($E$66*Z43))>0,(S43-($E$66*Z43)),0) -> 0 | Z43: =J43 -> 0 | AA43: =#REF! -> #REF! | AB43: =+AA43+V43 -> #REF! | AC43: 9815 | AD43: =AC43/AB43 -> #REF!
D44: רגיל | E44: USA | F44: 41545 | G44: 41550 | I44: =G44-F44+1 -> 6 | K44: =+I44-1 -> 5 | L44: =#REF! -> #REF! | N44: =#REF!+#REF!+#REF!+#REF!+#REF!+#REF!+#REF!+#REF!+#REF!+#REF! -> #REF! | O44: =#REF!+#REF!+#REF!+#REF! -> #REF! | Q44: =#REF! -> #REF! | U44: =O44+Q44 -> #REF! | V44: =SUM(L44:T44) -> #REF! | W44: =IF(F44>0,ROUND(IF(K44<=7,IF(L44/K44<=תקרת_מלון_ל___7_ראשונים,0,L44-K44*תקרת_מלון_ל___7_ראשונים),IF(L44/K44<=תקרת_מלון_נמוכה,0,IF(L44/K44<=תקרת_מלון_גבוה,L44-7*L44/K44-(K44-7)*MAXA(תקרת_מלון_נמוכה,75%*L44/K44),(L44-7*MINA(L44/K44,תקרת_מלון_ל___7_ראשונים)-(K44-7)*MINA(75%*L44/K44,תקרת_מלון_גבוה))))),0),0) -> #REF! | X44: =IF(L44>0,IF(U44/I44<תקרת_אשל_ליום___עם_לינה,0,U44-I44*תקרת_אשל_ליום___עם_לינה),IF(U44/I44<תקרת_אשל_ליום___ללא_לינה,0,U44-I44*תקרת_אשל_ליום___ללא_לינה)) -> #REF! | Y44: =IF((S44-($E$66*Z44))>0,(S44-($E$66*Z44)),0) -> 0 | Z44: =J44 -> 0 | AA44: =#REF! -> #REF! | AB44: =+AA44+V44 -> #REF! | AC44: 17297 | AD44: =AC44/AB44 -> #REF!
D45: רגיל | E45: USA | F45: 41602 | G45: 41605 | I45: =G45-F45+1 -> 4 | J45: 3 | K45: =+I45-1 -> 3 | L45: =#REF!+#REF! -> #REF! | O45: =#REF!+#REF!+#REF!+#REF! -> #REF! | P45: =#REF! -> #REF! | Q45: =#REF!+#REF! -> #REF! | S45: =#REF! -> #REF! | U45: =O45+Q45 -> #REF! | V45: =SUM(L45:T45) -> #REF! | W45: =IF(F45>0,ROUND(IF(K45<=7,IF(L45/K45<=תקרת_מלון_ל___7_ראשונים,0,L45-K45*תקרת_מלון_ל___7_ראשונים),IF(L45/K45<=תקרת_מלון_נמוכה,0,IF(L45/K45<=תקרת_מלון_גבוה,L45-7*L45/K45-(K45-7)*MAXA(תקרת_מלון_נמוכה,75%*L45/K45),(L45-7*MINA(L45/K45,תקרת_מלון_ל___7_ראשונים)-(K45-7)*MINA(75%*L45/K45,תקרת_מלון_גבוה))))),0),0) -> #REF! | X45: =IF(L45>0,IF(U45/I45<תקרת_אשל_ליום___עם_לינה,0,U45-I45*תקרת_אשל_ליום___עם_לינה),IF(U45/I45<תקרת_אשל_ליום___ללא_לינה,0,U45-I45*תקרת_אשל_ליום___ללא_לינה)) -> #REF! | Y45: =IF((S45-($E$66*Z45))>0,(S45-($E$66*Z45)),0) -> #REF! | Z45: =J45 -> 3 | AA45: =#REF! -> #REF! | AB45: =+AA45+V45 -> #REF! | AC45: 13613 | AD45: =AC45/AB45 -> #REF!
D46: 25% יותר | E46: Germany | F46: 41619 | G46: 41625 | I46: =G46-F46+1 -> 7 | K46: =+I46-1 -> 6 | L46: =#REF!+#REF! -> #REF! | N46: =#REF!+#REF! -> #REF! | O46: =#REF! -> #REF! | Q46: =#REF!+#REF!+#REF! -> #REF! | U46: =O46+Q46 -> #REF! | V46: =SUM(L46:T46) -> #REF! | W46: =IF(F46>0,ROUND(IF(K46<=7,IF(L46/K46<=תקרת_מלון_ל___7_ראשונים,0,L46-K46*תקרת_מלון_ל___7_ראשונים),IF(L46/K46<=תקרת_מלון_נמוכה,0,IF(L46/K46<=תקרת_מלון_גבוה,L46-7*L46/K46-(K46-7)*MAXA(תקרת_מלון_נמוכה,75%*L46/K46),(L46-7*MINA(L46/K46,תקרת_מלון_ל___7_ראשונים)-(K46-7)*MINA(75%*L46/K46,תקרת_מלון_גבוה))))),0),0) -> #REF! | X46: =IF(L46>0,IF(U46/I46<תקרת_אשל_ליום___עם_לינה,0,U46-I46*תקרת_אשל_ליום___עם_לינה),IF(U46/I46<תקרת_אשל_ליום___ללא_לינה,0,U46-I46*תקרת_אשל_ליום___ללא_לינה)) -> #REF! | Y46: =IF((S46-($E$66*Z46))>0,(S46-($E$66*Z46)),0) -> 0 | Z46: =J46 -> 0 | AB46: =+AA46+V46 -> #REF! | AC46: 7517 | AD46: =AC46/AB46 -> #REF!
I47: =G47-F47+1 -> 1 | K47: =+I47-1 -> 0 | U47: =O47+Q47 -> 0 | V47: =SUM(L47:T47) -> 0 | W47: =IF(F47>0,ROUND(IF(K47<=7,IF(L47/K47<=תקרת_מלון_ל___7_ראשונים,0,L47-K47*תקרת_מלון_ל___7_ראשונים),IF(L47/K47<=תקרת_מלון_נמוכה,0,IF(L47/K47<=תקרת_מלון_גבוה,L47-7*L47/K47-(K47-7)*MAXA(תקרת_מלון_נמוכה,75%*L47/K47),(L47-7*MINA(L47/K47,תקרת_מלון_ל___7_ראשונים)-(K47-7)*MINA(75%*L47/K47,תקרת_מלון_גבוה))))),0),0) -> 0 | X47: =IF(L47>0,IF(U47/I47<תקרת_אשל_ליום___עם_לינה,0,U47-I47*תקרת_אשל_ליום___עם_לינה),IF(U47/I47<תקרת_אשל_ליום___ללא_לינה,0,U47-I47*תקרת_אשל_ליום___ללא_לינה)) -> 0 | Y47: =IF((S47-($E$66*Z47))>0,(S47-($E$66*Z47)),0) -> 0 | Z47: =J47 -> 0 | AB47: =+AA47+V47 -> 0
C49: total | L49: =SUM(L11:L47) -> #REF! | M49: =SUM(M11:M47) -> #REF! | N49: =SUM(N11:N47) -> #REF! | O49: =SUM(O11:O47) -> #REF! | P49: =SUM(P11:P47) -> #REF! | Q49: =SUM(Q11:Q47) -> #REF! | R49: =SUM(R11:R47) -> #REF! | S49: =SUM(S11:S47) -> #REF! | U49: =SUM(U11:U47) -> #REF! | V49: =SUM(V11:V47) -> #REF! | W49: =SUM(W11:W47) -> #REF! | X49: =SUM(X11:X47) -> #REF! | Y49: =SUM(Y11:Y47) -> #REF! | Z49: =SUM(Z11:Z47) -> 100 | AA49: =SUM(AA11:AA47) -> #REF! | AB49: =SUM(AB11:AB47) -> #REF! | AC49: =SUM(AC11:AC47) -> 374116.54 | AD49: =AVERAGE(AD12:AD47) -> #REF!
C51: TOTAL DISSALL. EXP $ | G51: =SUM(W49:Y49) -> #REF!
C52: TOTAL DISSALL. EXP NIS | G52: =+G51*AD49 -> #REF! | AB52: =+AB49+AB50 -> #REF! | AC52: =+AC49+AC50 -> 374116.54
A56: Total expenses recorded (books) - | G56: 374106
A58: Differences - | G58: =+AC52-G56 -> 10.54 | I58: =+G58-H58 -> 10.54
E61: הגדרות
C62: תאור | E62: קלט ($) - רגיל | F62: קלט ($) - 25% יותר
A63: תקרת מלון ל - 7 ראשונים | E63: 259 | F63: =+E63*125% -> 323.75
A64: תקרת מלון נמוכה | E64: 114 | F64: =+E64*125% -> 142.5
A65: תקרת מלון גבוה | E65: 194.25 | F65: =+E65*125% -> 242.8125
A66: תקרת רכב שכור ליום | E66: 75 | F66: =+E66*125% -> 93.75
A67: תקרת אשל ליום , ללא לינה | E67: 122 | F67: =+E67*125% -> 152.5
A68: תקרת אשל ליום , עם לינה | E68: 73 | F68: =+E68*125% -> 91.25
A69: תקרת מתנה לתושב חול | E69: 15 | F69: =+E69 -> 15
C73: סטרליה
C74: אוסטריה
C75: איטליה | L75: \
C76: איסלנד
C77: אירלנד
C78: אנגולה
C79: בלגיה
C80: גרמניה
C81: דובאי
C82: דנמרק
C83: הולנד
C84: הונג-קונג
C85: בריטניה
C86: טיוואן
C87: יוון
... C100: שוויץ
