Workbook
Name \A: '[1]טורים 98'!$HJ$133
Name \A: '[2]טורים 98'!$HJ$133
Name \B: #REF!
Name \B: #REF!
Name \B: #REF!
Name \B: #REF!
Name \C: '[1]טורים 98'!$HJ$154
Name \C: '[2]טורים 98'!$HJ$154
Name \D: '[2]טורים 98'!#REF!
Name \D: '[1]טורים 98'!#REF!
Name \D: '[2]טורים 98'!#REF!
Name \E: '[1]טורים 98'!$HJ$155
Name \E: '[2]טורים 98'!$HJ$155
Name \F: '[1]טורים 98'!$GS$2
Name \F: '[2]טורים 98'!$GS$2
Name \H: '[1]טורים 98'!$B$336
Name \H: '[2]טורים 98'!$B$336
Name \J: '[1]טורים 98'!$HJ$164
Name \J: '[2]טורים 98'!$HJ$164
Name \K: '[1]טורים 98'!$HJ$166
Name \K: '[2]טורים 98'!$HJ$166
Name \L: '[1]טורים 98'!$HJ$124
Name \L: '[2]טורים 98'!$HJ$124
Name \M: '[1]טורים 98'!$HJ$121
Name \M: '[2]טורים 98'!$HJ$121
Name \O: '[1]טורים 98'!$HJ$144
Name \O: '[2]טורים 98'!$HJ$144
Name \P: '[1]טורים 98'!$GT$13
Name \P: '[2]טורים 98'!$GT$13
Name \Q: '[1]טורים 98'!$HJ$127
Name \Q: '[2]טורים 98'!$HJ$127
Name \R: '[1]טורים 98'!$HJ$118
Name \R: '[2]טורים 98'!$HJ$118
Name \S: '[1]טורים 98'!$HJ$151
Name \S: '[2]טורים 98'!$HJ$151
Name \t: #REF!
Name \t: #REF!
Name \t: #REF!
Name \t: #REF!
Name \U: '[1]טורים 98'!$HJ$116
Name \U: '[2]טורים 98'!$HJ$116
Name \W: '[1]טורים 98'!$HJ$113
Name \W: '[2]טורים 98'!$HJ$113
Name \X: '[1]טורים 98'!$HJ$146
Name \X: '[2]טורים 98'!$HJ$146
Name \Y: '[1]טורים 98'!$GT$6
Name \Y: '[2]טורים 98'!$GT$6
Name \Z: '[1]טורים 98'!$HJ$129
Name \Z: '[2]טורים 98'!$HJ$129
Name _____ICP1: #REF!
Name _____ICP1: #REF!
Name _____ICP1: #REF!
Name _____ICP1: #REF!
Name _____ND1: #REF!
Name _____ND1: #REF!
Name _____ND1: #REF!
Name _____ND1: #REF!
Name _____OM9: #REF!
Name _____OM9: #REF!
Name _____OM9: #REF!

Sheet Master Data (do not print)
A13: Company name | B13: Aurora Labs Consolidated
A19: Date | B19: 44926
A20: CompareDate | B20: 44561
A22: exchange rate
A23: USD/NIS | B23: 3.519
A24: Euro NIS | B24: 3.753
A27: Sanity check - בדיקת סך בקרות הסיכום בחוברת | B27: =SUM(BS!C46)+SUM('P&L'!D33:H33)+SUM(NotesBS!C13,NotesBS!C26,NotesBS!C36,NotesBS!C37,NotesBS!C45,NotesBS!C57,NotesBS!C58,NotesBS!C65)+SUM('NotesP&L'!B15,'NotesP&L'!F15,'NotesP&L'!B30,'NotesP&L'!F30,'NotesP&L'!B49,'NotesP&L'!F49,'NotesP&L'!B60,'NotesP&L'!F60) -> 29962875 | C27: חייב להיות אפס

Sheet COVER NEW
A1: =Companyname -> Aurora Labs Consolidated
A13: INTERNAL
A16: FINANCIAL
A18: STATEMENTS
A21: UNAUDITED
A35: =DATE -> 44926

Sheet BS
A1: =Companyname -> Aurora Labs Consolidated | E1: INDEX
A2: BALANCE SHEET
C4: =DATE -> 44926 | D4: 43830
C5: =DATE -> 44926 | D5: =CompareDATE -> 44561
C6: U.S. Dollars | D6: U.S. Dollars
C7: Unaudited | D7: Audited
A8: CURRENT ASSETS | B8: Note
A9: =VLOOKUP(E9,Index!A:B,2,0) -> Cash and cash equivalents | B9: 1 | C9: =-SUMIF(SAP!I:I,E9,SAP!F:F) -> 20779776 | D9: 13400932 | E9: 130
A10: =VLOOKUP(E10,Index!A:B,2,0) -> Short term deposit | C10: =-SUMIF(SAP!I:I,E10,SAP!F:F) -> 40710444 | D10: 0 | E10: 133
A11: =VLOOKUP(E11,Index!A:B,2,0) -> Accounts receivable | C11: =-SUMIF(SAP!I:I,E11,SAP!F:F) -> 1269967 | D11: 220165 | E11: 134
A12: =VLOOKUP(E12,Index!A:B,2,0) -> Other current assets | B12: 2 | C12: =-SUMIF(SAP!I:I,E12,SAP!F:F) -> 208930 | D12: 47343 | E12: 135
C13: =SUM(C9:C12) -> 62969117 | D13: =SUM(D9:D12) -> 13668440
C14: - - - - - - - - - | D14: - - - - - - - - -
A15: NON - CURRENT ASSETS
A16: =VLOOKUP(E16,Index!A:B,2,0) -> Leased property under capital lease | C16: =-SUMIF(SAP!I:I,E16,SAP!F:F) -> 225967 | D16: 0 | E16: 141
A18: FIXED ASSETS
A19: =VLOOKUP(E19,Index!A:B,2,0) -> Fixed assets, gross | B19: 3 | C19: =-SUMIF(SAP!I:I,E19,SAP!F:F) -> 386842 | D19: 286867 | E19: 190
A20: =VLOOKUP(E20,Index!A:B,2,0) -> Accumulated depreciation | C20: =-SUMIF(SAP!I:I,E20,SAP!F:F) -> -211237 | D20: -141400 | E20: 191
C21: =SUM(C19:C20) -> 175605 | D21: =SUM(D19:D20) -> 145467
C22: - - - - - - - | D22: - - - - - - -
C23: =SUM(C21,C16,C13) -> 63370689 | D23: =SUM(D21,,D13) -> 13813907
A25: CURRENT LIABILITIES
A26: =VLOOKUP(E26,Index!A:B,2,0) -> Short Term Loans | C26: =-SUMIF('SAP DRAFT'!K:K,E26,'SAP DRAFT'!H:H) -> 0 | D26: 0 | E26: 261
A27: =VLOOKUP(E27,Index!A:B,2,0) -> Current maturities of obligation under capital lease | C27: =SUMIF(SAP!I:I,E27,SAP!F:F) -> 149136 | D27: 0 | E27: 263
A28: =VLOOKUP(E28,Index!A:B,2,0) -> Accounts payable | B28: 4 | C28: =SUMIF(SAP!I:I,E28,SAP!F:F) -> 150071 | D28: 74466 | E28: 265
A29: =VLOOKUP(E29,Index!A:B,2,0) -> Other liabilities | B29: 5 | C29: =SUMIF(SAP!I:I,E29,SAP!F:F) -> 1319416 | D29: 1190612 | E29: 268
C30: =SUM(C26:C29) -> 1618623 | D30: =SUM(D26:D29) -> 1265078
C32: - - - - - - - - - | D32: - - - - - - - - -
A34: LONG TERM LIABILITIES
A35: =VLOOKUP(E35,Index!A:B,2,0) -> Long Term Lease | C35: =SUMIF(SAP!I:I,E35,SAP!F:F) -> 75354 | D35: 0 | E35: 301
C36: =SUM(C32:C35) -> 75354 | D36: =SUM(D32:D35) -> 0
A38: SHAREHOLDER'S EQUITY
A39: =VLOOKUP(E39,Index!A:B,2,0) -> Share capital | B39: 6 | C39: =SUMIF(SAP!I:I,E39,SAP!F:F) -> 2215 | D39: 1866 | E39: 372 | J39: =טבלה2[[#This Row],[עמודה3]]-טבלה2[[#This Row],[עמודה5]] -> 349 | L39: שינוי בהון
A40: =VLOOKUP(E40,Index!A:B,2,0) -> Additional paid-in capital | C40: =SUMIF(SAP!I:I,E40,SAP!F:F) -> 97198946 | D40: 35489172 | E40: 374 | J40: =טבלה2[[#This Row],[עמודה3]]-טבלה2[[#This Row],[עמודה5]] -> 61709774 | L40: שינוי בפרמיה
A41: =VLOOKUP(E41,Index!A:B,2,0) -> Accumulated Earnings | C41: ='P&L'!H31 -> -35524449 | D41: -22942209 | E41: 378
C42: =SUM(C39:C41) -> 61676712 | D42: =SUM(D39:D41) -> 12548829 | L42: הרכב שינוי בפרמיה:
C43: - - - - - - - | D43: - - - - - - - | J43: 1465364.9 | L43: תשלום במוסס מניות
C44: =SUM(C30,C36,C42) -> 63370689 | D44: =SUM(D30,,D42) -> 13813907 | J44: 63318262 | L44: גיוס 2022
J45: -3073504.9 | L45: הוצאות הנפקה
C46: =ROUND(C44-C23,0) -> 0 | D46: =ROUND(D44-D23,0) -> 0 | J46: -349 | L46: Preferred C Shares
J47: 1.04 | L47: מימוש אופציות
J48: =SUM(J43:J47) -> 61709774
A49: =Companyname &" Confidential" -> Aurora Labs Consolidated Confidential | J49: =J40-J48 -> -0.0027226731 | L49: הפרש

Sheet P&L
A1: =Companyname -> Aurora Labs Consolidated | J1: INDEX
A2: STATEMENT OF OPERATIONS
D5: MTD | F5: QTD | H5: YTD | I5: YTD | V5: YTD | X5: MTD | Y5: YTD | AA5: MTD | AB5: YTD | AE5: MTD | AF5: YTD | AH5: YTD | AI5: YTD | AJ5: MTD | AK5: YTD | AM5: MTD | AN5: QTD | AP5: MTD | AQ5: YTD | AT5: MTD | AU5: YTD | AX5: QTD | AY5: MTD | AZ5: YTD | BC5: MTD | BD5: YTD | BF5: MTD | BG5: YTD
D6: =DATE -> 44926 | F6: =DATE -> 44926 | H6: =DATE -> 44926 | I6: 43830 | V6: 44592 | X6: 44620 | Y6: 44620 | AA6: 44651 | AB6: 44742 | AE6: 44681 | AF6: 44681 | AH6: 44712 | AI6: 44742 | AJ6: 44712 | AK6: 44804 | AM6: 44742 | AN6: 44742 | AP6: 44773 | AQ6: 44773 | AT6: 44804 | AU6: 44804 | AX6: 44834 | AY6: 44834 | AZ6: 44834 | BC6: 44865 | BD6: 44865 | BF6: 44895 | BG6: 44895
D7: =DATE -> 44926 | F7: =DATE -> 44926 | H7: =DATE -> 44926 | I7: =CompareDATE -> 44561 | V7: 44592 | X7: 44620 | Y7: 44620 | AA7: 44651 | AB7: 44742 | AE7: 44681 | AF7: 44681 | AH7: 44712 | AI7: 44742 | AJ7: 44712 | AK7: 44804 | AM7: 44742 | AN7: 44742 | AP7: 44773 | AQ7: 44773 | AT7: 44804 | AU7: 44804 | AX7: 44834 | AY7: 44834 | AZ7: 44834 | BC7: 44865 | BD7: 44865 | BF7: 44895 | BG7: 44895
D8: U.S. Dollars | F8: U.S. Dollars | H8: U.S. Dollars | I8: U.S. Dollars | V8: U.S. Dollars | X8: U.S. Dollars | Y8: U.S. Dollars | AA8: U.S. Dollars | AB8: U.S. Dollars | AE8: U.S. Dollars | AF8: U.S. Dollars | AH8: U.S. Dollars | AI8: U.S. Dollars | AJ8: U.S. Dollars | AK8: U.S. Dollars | AM8: U.S. Dollars | AN8: U.S. Dollars | AP8: U.S. Dollars | AQ8: U.S. Dollars | AT8: U.S. Dollars | AU8: U.S. Dollars | AX8: U.S. Dollars | AY8: U.S. Dollars | AZ8: U.S. Dollars | BC8: U.S. Dollars | BD8: U.S. Dollars | BF8: U.S. Dollars | BG8: U.S. Dollars
C9: Note | D9: Unaudited | F9: Unaudited | H9: Unaudited | I9: Audited | V9: Unaudited | X9: Unaudited | Y9: Unaudited | AA9: Unaudited | AB9: Unaudited | AE9: Unaudited | AF9: Unaudited | AH9: Unaudited | AI9: Unaudited | AJ9: Unaudited | AK9: Unaudited | AM9: Unaudited | AN9: Unaudited | AP9: Unaudited | AQ9: Unaudited | AT9: Unaudited | AU9: Unaudited | AX9: Unaudited | AY9: Unaudited | AZ9: Unaudited | BC9: Unaudited | BD9: Unaudited | BF9: Unaudited | BG9: Unaudited
A12: =VLOOKUP(J12,Index!A:B,2,0) -> Revenues | D12: =H12-BG12 -> -37339 | F12: =טבלה3[[#This Row],[עמודה6]]-AZ12 -> 137873 | H12: =SUMIF(SAP!I:I,J12,SAP!F:F) -> 1219917 | I12: 852628 | J12: 420 | L12: =טבלה3[[#This Row],[עמודה6]]/1000 -> 1219.917 | M12: =טבלה3[[#This Row],[עמודה8]]/1000 -> 852.628 | V12: 0 | X12: 0 | Y12: 0 | AA12: 16290 | AB12: 16290 | AE12: 0 | AF12: 16290 | AH12: 16290 | AI12: 16290 | AJ12: 0 | AK12: 267290 | AM12: 0 | AN12: 0 | AP12: 0 | AQ12: 16290 | AT12: 251000 | AU12: 267290 | AX12: 1065754 | AY12: 814754 | AZ12: 1082044 | BC12: 59000 | BD12: 1141044 | BF12: 834261 | BG12: 1257256 | BL12: =טבלה3[[#This Row],[עמודה6]]/1000 -> 1219.917
L13: =טבלה3[[#This Row],[עמודה6]]/1000 -> 0 | M13: =טבלה3[[#This Row],[עמודה8]]/1000 -> 0
A14: =VLOOKUP(J14,Index!A:B,2,0) -> Cost of Goods Sold | D14: =H14-BG14 -> 975934 | F14: =טבלה3[[#This Row],[עמודה6]]-AZ14 -> 975934 | H14: =-SUMIF(SAP!I:I,J14,SAP!F:F) -> 975934 | I14: 681279 | J14: 472 | L14: =טבלה3[[#This Row],[עמודה6]]/1000 -> 975.934 | M14: =טבלה3[[#This Row],[עמודה8]]/1000 -> 681.279 | U14: =טבלה3[[#This Row],[עמודה6]]/H12 -> 0.80000033 | V14: 0 | X14: 0 | Y14: 0 | AA14: 0 | AB14: 0 | AE14: 0 | AF14: 0 | AH14: 0 | AI14: 0 | AJ14: 0 | AK14: 0 | AM14: 0 | AN14: 0 | AP14: 0 | AQ14: 0 | AT14: 0 | AU14: 0 | AX14: 0 | AY14: 0 | AZ14: 0 | BC14: 0 | BD14: 0 | BF14: 0 | BG14: 0
L15: =טבלה3[[#This Row],[עמודה6]]/1000 -> 0 | M15: =טבלה3[[#This Row],[עמודה8]]/1000 -> 0
A16: Gross profit | D16: =D12-D14 -> -1013273 | E16: =E12-E14 -> 0 | F16: =F12-F14 -> -838061 | G16: =G12-G14 -> 0 | H16: =H12-H14 -> 243983 | I16: =I12-I14 -> 171349 | L16: =טבלה3[[#This Row],[עמודה6]]/1000 -> 243.983 | M16: =טבלה3[[#This Row],[עמודה8]]/1000 -> 171.349 | V16: 0 | X16: 0 | Y16: 0 | AA16: 16290 | AB16: 16290 | AE16: 0 | AF16: 16290 | AH16: 16290 | AI16: 16290 | AJ16: 0 | AK16: 267290 | AM16: 0 | AN16: 0 | AP16: 0 | AQ16: 16290 | AT16: 251000 | AU16: 267290 | AX16: 1065754 | AY16: 814754 | AZ16: 1082044 | BC16: 59000 | BD16: 1141044 | BF16: 834261 | BG16: 1257256 | BJ16: =טבלה3[[#This Row],[עמודה6]]/H12 -> 0.19999967
L17: =טבלה3[[#This Row],[עמודה6]]/1000 -> 0 | M17: =טבלה3[[#This Row],[עמודה8]]/1000 -> 0
A18: Operating expenses | L18: =טבלה3[[#This Row],[עמודה6]]/1000 -> 0 | M18: =טבלה3[[#This Row],[עמודה8]]/1000 -> 0
A19: =VLOOKUP(J19,Index!A:B,2,0) -> Research & Development | C19: 7 | D19: =H19-BG19 -> 988994 | F19: =טבלה3[[#This Row],[עמודה6]]-AZ19 -> 2580362 | H19: =-SUMIF(SAP!I:I,J19,SAP!F:F) -> 9603573 | I19: 6319935 | J19: 700 | L19: =טבלה3[[#This Row],[עמודה6]]/1000 -> 9603.573 | M19: =טבלה3[[#This Row],[עמודה8]]/1000 -> 6319.935 | V19: 680328 | X19: 670718 | Y19: 1351046 | AA19: 834423 | AB19: 4474171 | AE19: 693251 | AF19: 2878720 | AH19: 3645784 | AI19: 4474171 | AJ19: 767064 | AK19: 6049875 | AM19: 828387 | AN19: 2288702 | AP19: 738353 | AQ19: 5212524 | AT19: 837351 | AU19: 6049875 | AX19: 2549040 | AY19: 973336 | AZ19: 7023211 | BC19: 698614 | BD19: 7721825 | BF19: 892754 | BG19: 8614579
A20: =VLOOKUP(J20,Index!A:B,2,0) -> Sales & Marketing | C20: 8 | D20: =H20-BG20 -> -21361 | F20: =טבלה3[[#This Row],[עמודה6]]-AZ20 -> 274362 | H20: =-SUMIF(SAP!I:I,J20,SAP!F:F) -> 1406393 | I20: 1322914 | J20: 702 | L20: =טבלה3[[#This Row],[עמודה6]]/1000 -> 1406.393 | M20: =טבלה3[[#This Row],[עמודה8]]/1000 -> 1322.914 | V20: 102942 | X20: 98084 | Y20: 201026 | AA20: 159649 | AB20: 756638 | AE20: 160352 | AF20: 521027 | AH20: 620248 | AI20: 756638 | AJ20: 99221 | AK20: 972585 | AM20: 136390 | AN20: 395963 | AP20: 103390 | AQ20: 860028 | AT20: 112557 | AU20: 972585 | AX20: 375393 | AY20: 159446 | AZ20: 1132031 | BC20: 120805 | BD20: 1252836 | BF20: 174918 | BG20: 1427754
A21: =VLOOKUP(J21,Index!A:B,2,0) -> General & Administrative | C21: 9 | D21: =H21-BG21 -> -80108 | F21: =טבלה3[[#This Row],[עמודה6]]-AZ21 -> 223230 | H21: =-SUMIF(SAP!I:I,J21,SAP!F:F) -> 2185950 | I21: 1859794 | J21: 705 | L21: =טבלה3[[#This Row],[עמודה6]]/1000 -> 2185.95 | M21: =טבלה3[[#This Row],[עמודה8]]/1000 -> 1859.794 | V21: 147583 | X21: 452715 | Y21: 600298 | AA21: 175162 | AB21: 1259969 | AE21: 156108 | AF21: 931568 | AH21: 1089656 | AI21: 1259969 | AJ21: 158088 | AK21: 1699531 | AM21: 170313 | AN21: 484509 | AP21: 262172 | AQ21: 1522141 | AT21: 177390 | AU21: 1699531 | AX21: 702751 | AY21: 263189 | AZ21: 1962720 | BC21: 148573 | BD21: 2111293 | BF21: 154765 | BG21: 2266058
A22: ="Total "&A18 -> Total Operating expenses | D22: =SUM(D19:D21) -> 887525 | F22: =SUM(F19:F21) -> 3077954 | G22: =SUM(G19:G21) -> 0 | H22: =SUM(H19:H21) -> 13195916 | I22: =SUM(I19:I21) -> 9502643 | L22: =טבלה3[[#This Row],[עמודה6]]/1000 -> 13195.916 | M22: =טבלה3[[#This Row],[עמודה8]]/1000 -> 9502.643 | V22: 930853 | X22: 1221517 | Y22: 2152370 | AA22: 1169234 | AB22: 6490778 | AE22: 1009711 | AF22: 4331315 | AH22: 5355688 | AI22: 6490778 | AJ22: 1024373 | AK22: 8721991 | AM22: 1135090 | AN22: 3169174 | AP22: 1103915 | AQ22: 7594693 | AT22: 1127298 | AU22: 8721991 | AX22: 3627184 | AY22: 1395971 | AZ22: 10117962 | BC22: 967992 | BD22: 11085954 | BF22: 1222437 | BG22: 12308391
D23: - - - - - - - - - | F23: - - - - - - - - - | H23: - - - - - - - - - | I23: - - - - - - - - - | V23: - - - - - - - - - | X23: - - - - - - - - - | Y23: - - - - - - - - - | AA23: - - - - - - - - - | AB23: - - - - - - - - - | AE23: - - - - - - - - - | AF23: - - - - - - - - - | AH23: - - - - - - - - - | AI23: - - - - - - - - - | AJ23: - - - - - - - - - | AK23: - - - - - - - - - | AM23: - - - - - - - - - | AN23: - - - - - - - - - | AP23: - - - - - - - - - | AQ23: - - - - - - - - - | AT23: - - - - - - - - - | AU23: - - - - - - - - - | AX23: - - - - - - - - - | AY23: - - - - - - - - - | AZ23: - - - - - - - - - | BC23: - - - - - - - - - | BD23: - - - - - - - - - | BF23: - - - - - - - - - | BG23: - - - - - - - - -
A24: PROFIT (LOSS) FROM OPERATIONS | D24: =D16-D22 -> -1900798 | F24: =F16-F22 -> -3916015 | G24: =G16-G22 -> 0 | H24: =H16-H22 -> -12951933 | I24: =I16-I22 -> -9331294 | L24: =טבלה3[[#This Row],[עמודה6]]/1000 -> -12951.933 | M24: =טבלה3[[#This Row],[עמודה8]]/1000 -> -9331.294 | V24: -930853 | X24: -1221517 | Y24: -2152370 | AA24: -1152944 | AB24: -6474488 | AE24: -1009711 | AF24: -4315025 | AH24: -5339398 | AI24: -6474488 | AJ24: -1024373 | AK24: -8454701 | AM24: -1135090 | AN24: -3169174 | AP24: -1103915 | AQ24: -7578403 | AT24: -876298 | AU24: -8454701 | AX24: -2561430 | AY24: -581217 | AZ24: -9035918 | BC24: -908992 | BD24: -9944910 | BF24: -388176 | BG24: -11051135
A25: =VLOOKUP(J25,Index!A:B,2,0) -> Financial | C25: 10 | D25: =H25-BG25 -> 54384 | F25: =טבלה3[[#This Row],[עמודה6]]-AZ25 -> -810451 | H25: =-SUMIF(SAP!I:I,J25,SAP!F:F) -> -369693 | I25: 18173 | J25: 790 | L25: =טבלה3[[#This Row],[עמודה6]]/1000 -> -369.693 | M25: =טבלה3[[#This Row],[עמודה8]]/1000 -> 18.173 | V25: 9761 | X25: -48730 | Y25: -38969 | AA25: -143247 | AB25: 546178 | AE25: 265543 | AF25: 83327 | AH25: 98028 | AI25: 546178 | AJ25: 14701 | AK25: -56126 | AM25: 448150 | AN25: 728394 | AP25: -364684 | AQ25: 181494 | AT25: -237620 | AU25: -56126 | AX25: -105420 | AY25: 496884 | AZ25: 440758 | BC25: -232699 | BD25: 208059 | BF25: -632136 | BG25: -424077
A26: =VLOOKUP(J26,Index!A:B,2,0) -> Other revenues | D26: =H26-AK26 -> 0 | F26: =טבלה3[[#This Row],[עמודה6]]-AZ26 -> 0 | H26: =-SUMIF(SAP!I:I,J26,SAP!F:F) -> 0 | I26: 0 | J26: 801 | L26: =טבלה3[[#This Row],[עמודה6]]/1000 -> 0 | M26: =טבלה3[[#This Row],[עמודה8]]/1000 -> 0 | V26: 0 | X26: 0 | Y26: 0 | AA26: 0 | AB26: 0 | AE26: 0 | AF26: 0 | AH26: 0 | AI26: 0 | AJ26: 0 | AK26: 0 | AM26: 0 | AN26: 0 | AP26: 0 | AQ26: 0 | AT26: 0 | AU26: 0 | AX26: 0 | AY26: 0 | AZ26: 0 | BC26: 0 | BD26: 0 | BF26: 0 | BG26: 0
A27: =VLOOKUP(J27,Index!A:B,2,0) -> Tax Expenses | D27: =H27-V27 -> 0 | F27: =טבלה3[[#This Row],[עמודה6]]-AA27 -> 0 | H27: =SUMIF(SAP!I:I,J27,SAP!F:F) -> 0 | I27: 0 | J27: 850 | L27: =טבלה3[[#This Row],[עמודה6]]/1000 -> 0 | M27: =טבלה3[[#This Row],[עמודה8]]/1000 -> 0 | V27: 0 | X27: 0 | Y27: 0 | AA27: 0 | AB27: 0 | AE27: 0 | AF27: 0 | AH27: 0 | AI27: 0 | AJ27: 0 | AK27: 0 | AM27: 0 | AN27: 0 | AP27: 0 | AQ27: 0 | AT27: 0 | AU27: 0 | AX27: 0 | AY27: 0 | AZ27: 0 | BC27: 0 | BD27: 0 | BF27: 0 | BG27: 0
A28: NET INCOME (LOSS) | D28: =D24-D25-D27-D26 -> -1955182 | E28: =E24-E25-E27-E26 -> 0 | F28: =F24-F25-F27-F26 -> -3105564 | G28: =G24-G25-G27-G26 -> 0 | H28: =H24-H25-H27-H26 -> -12582240 | I28: =I24-I25-I27-I26 -> -9349467 | L28: =טבלה3[[#This Row],[עמודה6]]/1000 -> -12582.24 | M28: =טבלה3[[#This Row],[עמודה8]]/1000 -> -9349.467 | V28: -940614 | X28: -1172787 | Y28: -2113401 | AA28: -1009697 | AB28: -7020666 | AE28: -1275254 | AF28: -4398352 | AH28: -5437426 | AI28: -7020666 | AJ28: -1039074 | AK28: -8398575 | AM28: -1583240 | AN28: -3897568 | AP28: -739231 | AQ28: -7759897 | AT28: -638678 | AU28: -8398575 | AX28: -2456010 | AY28: -1078101 | AZ28: -9476676 | BC28: -676293 | BD28: -10152969 | BF28: 243960 | BG28: -10627058
L29: =טבלה3[[#This Row],[עמודה6]]/1000 -> 0 | M29: =טבלה3[[#This Row],[עמודה8]]/1000 -> 0
A30: Opening Retained Earnings | D30: =BG31 -> -33569267 | F30: =AX31 -> -2456010 | H30: =SUMIF(SAP!I:I,J30,SAP!F:F) -> -22942209 | I30: -13592742 | J30: 941 | L30: =טבלה3[[#This Row],[עמודה6]]/1000 -> -22942.209 | M30: =טבלה3[[#This Row],[עמודה8]]/1000 -> -13592.742 | V30: -22651833 | X30: -23592447 | Y30: -22651833 | AA30: -24765234 | AB30: -22651833 | AE30: -25774931 | AF30: -22651833 | AH30: -22651833 | AI30: -22651833 | AJ30: -27050185 | AK30: -22651833 | AM30: -28089259 | AN30: -25774931 | AP30: -29672499 | AQ30: -22651833 | AT30: -30411730 | AU30: -22651833 | BH30: =L28+טבלה3[[#This Row],[Column4]] -> -35524.449
A31: ACCUMULATED EARNINGS (LOSS) | D31: =D28+D30 -> -35524449 | F31: =F28+F30 -> -5561574 | G31: =G28+G30 -> 0 | H31: =H28+H30 -> -35524449 | I31: =I28+I30 -> -22942209 | L31: =טבלה3[[#This Row],[עמודה6]]/1000 -> -35524.449 | M31: =טבלה3[[#This Row],[עמודה8]]/1000 -> -22942.209 | V31: -23592447 | X31: -24765234 | Y31: -24765234 | AA31: -25774931 | AB31: -29672499 | AE31: -27050185 | AF31: -27050185 | AH31: -28089259 | AI31: -29672499 | AJ31: -28089259 | AK31: -31050408 | AM31: -29672499 | AN31: -29672499 | AP31: -30411730 | AQ31: -30411730 | AT31: -31050408 | AU31: -31050408 | AX31: =AX28+AX30 -> -2456010 | AY31: =AY28+AY30 -> -1078101 | AZ31: =AZ28+AZ30 -> -9476676 | BC31: -32804802 | BD31: -32804802 | BF31: -33569267 | BG31: -33569267
L32: =טבלה3[[#This Row],[עמודה6]]/1000 -> 0 | M32: =טבלה3[[#This Row],[עמודה8]]/1000 -> 0
D33: =D31-H31 -> 0 | F33: =F31-H31 -> 29962875 | H33: =H30-I31 -> 0 | L33: =טבלה3[[#This Row],[עמודה6]]/1000 -> 0 | M33: =טבלה3[[#This Row],[עמודה8]]/1000 -> 0 | AB33: 0 | AE33: 0 | AF33: 0 | AH33: 0 | AI33: 0 | AJ33: 0 | AK33: 0 | AM33: 0 | AN33: 0 | AP33: 0 | AQ33: 0 | AT33: 0 | AU33: 0 | AX33: 0 | AY33: 0 | AZ33: 0 | BC33: 0 | BD33: 0 | BF33: 0 | BG33: 0
L34: =טבלה3[[#This Row],[עמודה6]]/1000 -> 0 | M34: =טבלה3[[#This Row],[עמודה8]]/1000 -> 0 | BD34: 290376
BD35: -33095178
A40: =Companyname &" Confidential" -> Aurora Labs Consolidated Confidential

Sheet CF
A1: =Companyname -> Aurora Labs Consolidated
A2: STATEMENT OF CASH FLOW
D4: QTD | E4: YTD | F4: YTD | H4: YTD | I4: YTD | J4: YTD | K4: YTD | L4: YTD
D5: =DATE -> 44926 | E5: =DATE -> 44926 | F5: 41639 | H5: 40908 | I5: 41364 | J5: 41455 | K5: 41547 | L5: 41639
D6: =DATE -> 44926 | E6: =DATE -> 44926 | F6: 41639 | H6: 41274 | I6: 41364 | J6: 41455 | K6: 41547 | L6: 41639
D7: U.S. Dollars | E7: U.S. Dollars | F7: U.S. Dollars | H7: NIS | I7: U.S. Dollars | J7: U.S. Dollars | K7: U.S. Dollars | L7: U.S. Dollars
A8: Cash flows from operating activities
A9: Net profit (Loss) | D9: =E9-O9 -> -12582240 | E9: ='P&L'!H28 -> -12582240 | F9: -1593533 | H9: -3883878 | I9: -382921 | J9: -826690 | K9: -990570 | L9: -1367620 | N9: =E9/1000 -> -12582.24
N10: =E10/1000 -> 0
A11: Expenses not involving cash flows: | N11: =E11/1000 -> 0
A12: Depreciation | D12: =E12-O12 -> 69837 | E12: =-(BS!C20-BS!D20) -> 69837 | F12: 14414 | H12: 24802 | I12: 3254 | J12: 6753 | K12: 10525 | L12: 14414 | N12: =E12/1000 -> 69.837
A13: Compensation charged in respect of options | N13: =E13/1000 -> 0
A14: granted to employee | D14: =E14-O14 -> 1465365 | E14: ='SAP DRAFT'!D166-1625923 -> 1465365 | F14: 128525.11 | H14: 67688.211 | I14: 0 | J14: 0 | K14: 0 | L14: 0 | N14: =E14/1000 -> 1465.365
N15: =E15/1000 -> 0
A16: Changes in operating asset and liability items: | N16: =E16/1000 -> 0
A17: (Increase) Decrease in Short term deposit | E17: =-(BS!C10-BS!D10) -> -40710444
A18: (Increase) Decrease in accounts receivable | D18: =E18-O18 -> -1049802 | E18: =-(BS!C11-BS!D11) -> -1049802 | F18: 0 | H18: 0 | I18: -33597 | J18: 0 | K18: -24921 | L18: 0 | N18: =E18/1000 -> -1049.802
A19: (Increase) Decrease in other current assets | D19: =E19-O19 -> -161587 | E19: =-(BS!C12-BS!D12) -> -161587 | F19: -91109 | H19: -139291 | I19: 7263 | J19: -10095 | K19: -21052 | L19: -52665 | N19: =E19/1000 -> -161.587
A20: (Increase) Decrease in Leased property under capital lease | D20: =E20-O20 -> -225967 | E20: =-(BS!C16-BS!D16) -> -225967 | F20: 13596 | H20: -50752 | I20: -363 | J20: -522 | K20: 13596 | L20: 13596 | N20: =E20/1000 -> -225.967
A21: Increase (Decrease) in accounts payable and accruals | D21: =E21-O21 -> 75605 | E21: =BS!C28-BS!D28 -> 75605 | F21: 21250 | H21: 72729 | I21: -14603 | J21: 4632 | K21: 23063 | L21: 21250 | N21: =E21/1000 -> 75.605
A22: Increase (Decrease) in obligation under capital lease | E22: =(BS!C27-BS!D27)+(BS!C35-BS!D35) -> 224490
A23: Increase (Decrease) in other liabilities | D23: =E23-O23 -> 128804 | E23: =(BS!C29-BS!D29) -> 128804 | F23: 36658 | H23: 515653 | I23: 8584 | J23: 25970 | K23: 15427 | L23: 36658 | N23: =E23/1000 -> 128.804
D24: =SUM(D9:D23) -> -12279985 | E24: =SUM(E9:E23) -> -52765939 | F24: -1470198.9 | H24: -3393048.8 | I24: -411781 | J24: -799952 | K24: -973932 | L24: -1334367 | N24: =E24/1000 -> -52765.939
D25: - - - - - - - - | E25: - - - - - - - - | F25: - - - - - - - - | H25: - - - - - - - - | I25: - - - - - - - - | J25: - - - - - - - - | K25: - - - - - - - - | L25: - - - - - - - -
A26: Cash flows from investing activities | N26: =E26/1000 -> 0
A27: Purchase of fixed assets | D27: =E27-O27 -> -99975 | E27: =-(BS!C19-BS!D19) -> -99975 | F27: -9766 | H27: -188915 | I27: 0 | J27: -6975 | K27: -9104 | L27: -9766 | N27: =E27/1000 -> -99.975
A28: (Increase)Decrease in Share capital | E28: =BS!C39-BS!D39 -> 349 | N28: =E28/1000 -> 0.349
D29: =SUM(D27:D27) -> -99975 | E29: =SUM(E27:E28) -> -99626 | F29: -9766 | H29: -188915 | I29: 0 | J29: -6975 | K29: -9104 | L29: -9766 | N29: =E29/1000 -> -99.626
D30: - - - - - - - - | E30: - - - - - - - - | F30: - - - - - - - - | H30: - - - - - - - - | I30: - - - - - - - - | J30: - - - - - - - - | K30: - - - - - - - - | L30: - - - - - - - -
A31: Total Cash Outflow before financing | D31: =D24-D29 -> -12180010 | E31: =E24-E29 -> -52666313 | F31: -1460432.9 | H31: -3204133.8 | I31: -411781 | J31: -792977 | K31: -964828 | L31: -1324601 | N31: =E31/1000 -> -52666.313
A33: Cash flows from financing activities | N33: =E33/1000 -> 0
A34: Proceeds from Additional paid-in capital | D34: =E34-O34 -> 60244409 | E34: =BS!C40-BS!D40-E14 -> 60244409 | F34: 2085661.9 | H34: 7539834.8 | I34: =1266776+602 -> 1267378 | J34: 1949830 | K34: 1949830 | L34: 1949830 | N34: =E34/1000 -> 60244.409
D35: =SUM(D34:D34) -> 60244409 | E35: =SUM(E34:E34) -> 60244409 | F35: 2085661.9 | H35: 7319834.8 | I35: 1266776 | J35: 1949830 | K35: 1949830 | L35: 1949830 | N35: =E35/1000 -> 60244.409
D36: - - - - - - - - | E36: - - - - - - - - | F36: - - - - - - - - | H36: - - - - - - - - | I36: - - - - - - - - | J36: - - - - - - - - | K36: - - - - - - - - | L36: - - - - - - - -
A37: Increase(decrease) in cash and cash equivalents | D37: =SUM(D35,D29,D24) -> 47864449 | E37: =SUM(E35,E29,E24) -> 7378844 | F37: 605697 | H37: 3737871 | I37: 854995 | J37: 1142903 | K37: 966794 | L37: 605697 | N37: =E37/1000 -> 7378.844
A38: Cash and cash equivalents at beginning of period | D38: =O39 -> 0 | E38: =BS!D9 -> 13400932 | F38: 1003375 | H38: 7725 | I38: 1003375 | J38: 1003375 | K38: 1003375 | L38: 1003375 | N38: =E38/1000 -> 13400.932
A39: Cash and cash equivalents at end of period | D39: =SUM(D37:D38) -> 47864449 | E39: =SUM(E37:E38) -> 20779776 | F39: 1609072 | H39: 3745596 | I39: 1858370 | J39: 2146278 | K39: 1970169 | L39: 1609072 | N39: =E39/1000 -> 20779.776
D40: =ROUND(D39-BS!$C$9,0) -> 27084673 | E40: =ROUND(E39-BS!$C$9,0) -> 0 | F40: =ROUND(F39-BS!#REF!,0) -> #REF! | N40: =E40/1000 -> 0
N41: =E41/1000 -> 0
N42: =E42/1000 -> 0
A43: =Companyname &" Confidential" -> Aurora Labs Consolidated Confidential

Sheet NotesBS
A1: =Companyname -> Aurora Labs Consolidated | E1: INDEX
A2: NOTES TO FINANCIAL STATEMENTS
A4: Note 1 - Cash and Cash Equivalents
C5: =DATE -> 44926 | D5: 43830 | G5: 44592 | I5: 44620 | K5: 44651 | M5: 44681 | Q5: 44712 | T5: 44742 | V5: 44773 | X5: 44804 | Z5: 44834 | AC5: 44865 | AF5: 44895
C6: =DATE -> 44926 | D6: =CompareDATE -> 44561 | G6: 44592 | I6: 44620 | K6: 44651 | M6: 44681 | Q6: 44712 | T6: 44742 | V6: 44773 | X6: 44804 | Z6: 44834 | AC6: 44865 | AF6: 44895
C7: U.S. Dollars | D7: U.S. Dollars | G7: U.S. Dollars | I7: U.S. Dollars | K7: U.S. Dollars | M7: U.S. Dollars | Q7: U.S. Dollars | T7: U.S. Dollars | V7: U.S. Dollars | X7: U.S. Dollars | Z7: U.S. Dollars | AC7: U.S. Dollars | AF7: U.S. Dollars
A9: =VLOOKUP(E9,Index!A:B,2,0) -> Israeli currency | C9: =-SUMIF(SAP!A:A,E9,SAP!F:F) -> 12486866 | D9: 71138 | E9: 1302 | G9: 1289860 | I9: 5084457 | K9: 6532473 | M9: 6433363 | Q9: 8394078 | T9: 12995838 | V9: 12635288 | X9: 11911901 | Z9: 13916155 | AC9: 14186857 | AF9: 13684763 | AI9: =C9/1000 -> 12486.866 | AJ9: =D9/1000 -> 71.138
A10: =VLOOKUP(E10,Index!A:B,2,0) -> USD currency | C10: =-SUMIF(SAP!A:A,E10,SAP!F:F) -> 8290712 | D10: 13327078 | E10: 1304 | G10: 11220739 | I10: 6553208 | K10: 4009069 | M10: 2717223 | Q10: 29571 | T10: 54347641 | V10: 56879436 | X10: 53932390 | Z10: 50288980 | AC10: 49245779 | AF10: 49106881 | AI10: =C10/1000 -> 8290.712 | AJ10: =D10/1000 -> 13327.078
A11: =VLOOKUP(E11,Index!A:B,2,0) -> EURO currency | C11: =-SUMIF(SAP!A:A,E11,SAP!F:F) -> 2198 | D11: 2716 | E11: 1307 | G11: 2677 | I11: 2688 | K11: 2662 | M11: 2541 | Q11: 2570 | T11: 2527 | V11: 2489 | X11: 6798 | Z11: 2133 | AC11: 2148 | AF11: 2245 | AI11: =C11/1000 -> 2.198 | AJ11: =D11/1000 -> 2.716
C12: =SUM(C9:C11) -> 20779776 | D12: =SUM(D9:D11) -> 13400932 | G12: 12513276 | I12: 11640353 | K12: 10544204 | M12: 9153127 | Q12: 8426219 | T12: 67346006 | V12: 69517213 | X12: 65851089 | Z12: 64207268 | AC12: 63434784 | AF12: 62793889 | AI12: =C12/1000 -> 20779.776 | AJ12: =D12/1000 -> 13400.932
C13: =C12-BS!C9 -> 0 | D13: =D12-BS!D9 -> 0 | I13: 0 | K13: 0 | M13: 0 | Q13: 0 | T13: 0 | V13: 0 | X13: 0 | Z13: 0 | AC13: 0 | AF13: 0 | AI13: =C13/1000 -> 0 | AJ13: =D13/1000 -> 0
AI14: =C14/1000 -> 0 | AJ14: =D14/1000 -> 0
A15: Note 2 - Other current assets | AI15: =C15/1000 -> 0 | AJ15: =D15/1000 -> 0
C16: =DATE -> 44926 | D16: 43830 | G16: 44592 | I16: 44620 | K16: 44651 | M16: 44681 | Q16: 44712 | T16: 44742 | V16: 44773 | X16: 44804 | Z16: 44834 | AC16: 44865 | AF16: 44895 | AI16: =C16/1000 -> 44.926 | AJ16: =D16/1000 -> 43.83
C17: =DATE -> 44926 | D17: =CompareDATE -> 44561 | G17: 44592 | I17: 44620 | K17: 44651 | M17: 44681 | Q17: 44712 | T17: 44742 | V17: 44773 | X17: 44804 | Z17: 44834 | AC17: 44865 | AF17: 44895 | AI17: =C17/1000 -> 44.926 | AJ17: =D17/1000 -> 44.561
C18: U.S. Dollars | D18: U.S. Dollars | G18: U.S. Dollars | I18: U.S. Dollars | K18: U.S. Dollars | M18: U.S. Dollars | Q18: U.S. Dollars | T18: U.S. Dollars | V18: U.S. Dollars | X18: U.S. Dollars | Z18: U.S. Dollars | AC18: U.S. Dollars | AF18: U.S. Dollars | AI18: =C18/1000 -> #VALUE! | AJ18: =D18/1000 -> #VALUE!
A19: =VLOOKUP(E19,Index!A:B,2,0) -> Related company | C19: =-SUMIF(SAP!A:A,E19,SAP!F:F) -> 0 | D19: 0 | E19: 1351 | G19: 0 | I19: 0 | K19: 0 | M19: 0 | Q19: 0 | T19: 0 | V19: 0 | X19: 0 | Z19: 0 | AC19: 0 | AF19: 0 | AI19: =C19/1000 -> 0 | AJ19: =D19/1000 -> 0
A20: =VLOOKUP(E20,Index!A:B,2,0) -> Prepaid expenses | C20: =-SUMIF(SAP!A:A,E20,SAP!F:F) -> 127522 | D20: 2991 | E20: 1354 | G20: 2243 | I20: 47900 | K20: 99389 | M20: 129793 | Q20: 118889 | T20: 104362 | V20: 176260 | X20: 162798 | Z20: 89627 | AC20: 121449 | AF20: 114876 | AI20: =C20/1000 -> 127.522 | AJ20: =D20/1000 -> 2.991
A21: =VLOOKUP(E21,Index!A:B,2,0) -> Guaranty deposits | C21: =-SUMIF(SAP!A:A,E21,SAP!F:F) -> 22131 | D21: 23879 | E21: 1355 | G21: 23244 | I21: 22935 | K21: 23383 | M21: 22389 | Q21: 22248 | T21: 21218 | V21: 22966 | X21: 23310 | Z21: 21981 | AC21: 22062 | AF21: 22633 | AI21: =C21/1000 -> 22.131 | AJ21: =D21/1000 -> 23.879
A22: =VLOOKUP(E22,Index!A:B,2,0) -> Income tax | C22: =-SUMIF(SAP!A:A,E22,SAP!F:F) -> 0 | D22: 660 | E22: 1356 | G22: 19430 | I22: 18893 | K22: 22401 | M22: 22954 | Q22: 22817 | T22: 24354 | V22: 26607 | X22: 28499 | Z22: 26877 | AC22: 26977 | AF22: 11625 | AI22: =C22/1000 -> 0 | AJ22: =D22/1000 -> 0.66
A23: =VLOOKUP(E23,Index!A:B,2,0) -> VAT | C23: =-SUMIF(SAP!A:A,E23,SAP!F:F) -> 55725 | D23: 19813 | E23: 1357 | G23: 32131 | I23: 40232 | K23: 31855 | M23: 45790 | Q23: 13889 | T23: 16151 | V23: 40821 | X23: 66206 | Z23: 62024 | AC23: 52789 | AF23: 42811 | AI23: =C23/1000 -> 55.725 | AJ23: =D23/1000 -> 19.813
A24: =VLOOKUP(E24,Index!A:B,2,0) -> Other | C24: =-SUMIF(SAP!A:A,E24,SAP!F:F) -> 3552 | D24: 0 | E24: 1358 | G24: 0 | I24: 13897 | K24: 11020 | M24: 10552 | Q24: 8987 | T24: 7143 | V24: 13270 | X24: 11223 | Z24: 351205 | AC24: 349112 | AF24: 4359 | AI24: =C24/1000 -> 3.552 | AJ24: =D24/1000 -> 0
C25: =SUM(C19:C24) -> 208930 | D25: =SUM(D20:D24) -> 47343 | G25: 77048 | I25: 143857 | K25: 188048 | M25: 231478 | Q25: 186830 | T25: 173228 | V25: 279924 | X25: 292036 | Z25: 551714 | AC25: 572389 | AF25: 196304 | AI25: =C25/1000 -> 208.93 | AJ25: =D25/1000 -> 47.343
C26: =C25-BS!C12 -> 0 | D26: =D25-BS!D12 -> 0 | M26: 0 | Q26: 0 | T26: 0 | V26: 0 | X26: 0 | Z26: 0 | AC26: 0 | AF26: 0 | AI26: =C26/1000 -> 0 | AJ26: =D26/1000 -> 0
AI27: =C27/1000 -> 0 | AJ27: =D27/1000 -> 0
A28: Note 3 - Fixed assets, gross | AI28: =C28/1000 -> 0 | AJ28: =D28/1000 -> 0
C29: =DATE -> 44926 | D29: 43830 | G29: 44592 | I29: 44620 | K29: 44651 | M29: 44681 | Q29: 44712 | T29: 44742 | V29: 44773 | X29: 44804 | Z29: 44834 | AC29: 44865 | AF29: 44895 | AI29: =C29/1000 -> 44.926 | AJ29: =D29/1000 -> 43.83
C30: =DATE -> 44926 | D30: =CompareDATE -> 44561 | G30: 44592 | I30: 44620 | K30: 44651 | M30: 44681 | Q30: 44712 | T30: 44742 | V30: 44773 | X30: 44804 | Z30: 44834 | AC30: 44865 | AF30: 44895 | AI30: =C30/1000 -> 44.926 | AJ30: =D30/1000 -> 44.561
C31: U.S. Dollars | D31: U.S. Dollars | G31: U.S. Dollars | I31: U.S. Dollars | K31: U.S. Dollars | M31: U.S. Dollars | Q31: U.S. Dollars | T31: U.S. Dollars | V31: U.S. Dollars | X31: U.S. Dollars | Z31: U.S. Dollars | AC31: U.S. Dollars | AF31: U.S. Dollars | AI31: =C31/1000 -> #VALUE! | AJ31: =D31/1000 -> #VALUE!
A32: =VLOOKUP(E32,Index!A:B,2,0) -> Furniture & Fixtures General | C32: =-SUMIF(SAP!A:A,E32,SAP!F:F) -> 17471 | D32: 14486 | E32: 1903 | G32: 15050 | I32: 15541 | K32: 15541 | M32: 15541 | Q32: 15541 | T32: 15541 | V32: 15555 | X32: 17471 | Z32: 17471 | AC32: 17471 | AF32: 17471 | AI32: =C32/1000 -> 17.471 | AJ32: =D32/1000 -> 14.486
A33: =VLOOKUP(E33,Index!A:B,2,0) -> Computers & Software | C33: =-SUMIF(SAP!A:A,E33,SAP!F:F) -> 344827 | D33: 253167 | E33: 1901 | G33: 265468 | I33: 269340 | K33: 286745 | M33: 286745 | Q33: 286745 | T33: 295539 | V33: 297342 | X33: 316555 | Z33: 318058 | AC33: 327092 | AF33: 327092 | AI33: =C33/1000 -> 344.827 | AJ33: =D33/1000 -> 253.167
A34: =VLOOKUP(E34,Index!A:B,2,0) -> Electronic equipment | C34: =-SUMIF(SAP!A:A,E34,SAP!F:F) -> 24544 | D34: 19214 | E34: 1904 | G34: 19214 | I34: 19216 | K34: 19216 | M34: 19216 | Q34: 19216 | T34: 19216 | V34: 20213 | X34: 23516 | Z34: 23516 | AC34: 23516 | AF34: 23516 | AI34: =C34/1000 -> 24.544 | AJ34: =D34/1000 -> 19.214
C35: =SUM(C31:C34) -> 386842 | D35: =SUM(D32:D34) -> 286867 | G35: 299732 | I35: 304097 | K35: 321502 | M35: 321502 | Q35: 321502 | T35: 330296 | V35: 333110 | X35: 357542 | Z35: 359045 | AC35: 368079 | AF35: 368079 | AI35: =C35/1000 -> 386.842 | AJ35: =D35/1000 -> 286.867
C36: =C35-BS!C19 -> 0 | D36: =D35-BS!D19 -> 0 | M36: 0 | Q36: 0 | T36: 0 | V36: 0 | X36: 0 | Z36: 0 | AC36: 0 | AF36: 0 | AI36: =C36/1000 -> 0 | AJ36: =D36/1000 -> 0
AI37: =C37/1000 -> 0 | AJ37: =D37/1000 -> 0
A38: Note 4 - Accounts payable | AI38: =C38/1000 -> 0 | AJ38: =D38/1000 -> 0
C39: =DATE -> 44926 | D39: 43830 | G39: 44592 | I39: 44620 | K39: 44651 | M39: 44681 | Q39: 44712 | T39: 44742 | V39: 44773 | X39: 44804 | Z39: 44834 | AC39: 44865 | AF39: 44895
C40: =DATE -> 44926 | D40: =CompareDATE -> 44561 | G40: 44592 | I40: 44620 | K40: 44651 | M40: 44681 | Q40: 44712 | T40: 44742 | V40: 44773 | X40: 44804 | Z40: 44834 | AC40: 44865 | AF40: 44895
C41: U.S. Dollars | D41: U.S. Dollars | G41: U.S. Dollars | I41: U.S. Dollars | K41: U.S. Dollars | M41: U.S. Dollars | Q41: U.S. Dollars | T41: U.S. Dollars | V41: U.S. Dollars | X41: U.S. Dollars | Z41: U.S. Dollars | AC41: U.S. Dollars | AF41: U.S. Dollars
A42: =VLOOKUP(E42,Index!A:B,2,0) -> Accounts payable | C42: =SUMIF(SAP!A:A,E42,SAP!F:F) -> 129249 | D42: 60901 | E42: 2652 | G42: 91049 | I42: 432673 | K42: 140429 | M42: 117470 | Q42: 56416 | T42: 61330 | V42: 2805995 | X42: 154647 | Z42: 166345 | AC42: 143862 | AF42: 88743 | AI42: =C42/1000 -> 129.249 | AJ42: =D42/1000 -> 60.901
A43: =VLOOKUP(E43,Index!A:B,2,0) -> Checks payable | C43: =SUMIF(SAP!A:A,E43,SAP!F:F) -> 20822 | D43: 13565 | E43: 2658 | G43: 10720 | I43: 9399 | K43: 12013 | M43: 12315 | Q43: 14899 | T43: 3240 | V43: 17855 | X43: 10309 | Z43: 15339 | AC43: 13072 | AF43: 5482 | AI43: =C43/1000 -> 20.822 | AJ43: =D43/1000 -> 13.565
C44: =SUM(C41:C43) -> 150071 | D44: =SUM(D41:D43) -> 74466 | G44: 101769 | I44: 442072 | K44: 152442 | M44: 129785 | Q44: 71315 | T44: 64570 | V44: 2823850 | X44: 164956 | Z44: 181684 | AC44: 156934 | AF44: 94225 | AI44: =C44/1000 -> 150.071 | AJ44: =D44/1000 -> 74.466
C45: =C44-BS!C28 -> 0 | D45: =D44-BS!D28 -> 0 | M45: 0 | Q45: 0 | T45: 0 | V45: 0 | X45: 0 | Z45: 0 | AC45: 0 | AF45: 0 | AI45: =C45/1000 -> 0 | AJ45: =D45/1000 -> 0
AI46: =C46/1000 -> 0 | AJ46: =D46/1000 -> 0
A47: Note 5 - Other liabilities | AI47: =C47/1000 -> 0 | AJ47: =D47/1000 -> 0
C48: =DATE -> 44926 | D48: 43830 | G48: 44592 | I48: 44620 | K48: 44651 | M48: 44681 | Q48: 44712 | T48: 44742 | V48: 44773 | X48: 44804 | Z48: 44834 | AC48: 44865 | AF48: 44895
C49: =DATE -> 44926 | D49: =CompareDATE -> 44561 | G49: 44592 | I49: 44620 | K49: 44651 | M49: 44681 | Q49: 44712 | T49: 44742 | V49: 44773 | X49: 44804 | Z49: 44834 | AC49: 44865 | AF49: 44895
C50: U.S. Dollars | D50: U.S. Dollars | G50: U.S. Dollars | I50: U.S. Dollars | K50: U.S. Dollars | M50: U.S. Dollars | Q50: U.S. Dollars | T50: U.S. Dollars | V50: U.S. Dollars | X50: U.S. Dollars | Z50: U.S. Dollars | AC50: U.S. Dollars | AF50: U.S. Dollars
A51: =VLOOKUP(E51,Index!A:B,2,0) -> Vacation & Convalescence | C51: =SUMIF(SAP!A:A,E51,SAP!F:F) -> 379770 | D51: 417475 | E51: 2681 | G51: 417797 | I51: 428853 | K51: 457253 | M51: 407467 | Q51: 425528 | T51: 413073 | V51: 421410 | X51: 406522 | Z51: 402201 | AC51: 352824 | AF51: 384479 | AI51: =C51/1000 -> 379.77 | AJ51: =D51/1000 -> 417.475
A52: =VLOOKUP(E52,Index!A:B,2,0) -> Employees | C52: =SUMIF(SAP!A:A,E52,SAP!F:F) -> 753251 | D52: 664338 | E52: 2685 | G52: 637305 | I52: 655320 | K52: 714977 | M52: 701060 | Q52: 855247 | T52: 680682 | V52: 758456 | X52: 775696 | Z52: 742545 | AC52: 749368 | AF52: 761732 | AI52: =C52/1000 -> 753.251 | AJ52: =D52/1000 -> 664.338
A53: =VLOOKUP(E53,Index!A:B,2,0) -> Related company | C53: =SUMIF(SAP!A:A,E53,SAP!F:F) -> 0 | D53: 0 | E53: 2686 | G53: 0 | I53: 0 | K53: 0 | M53: 0 | Q53: 0 | T53: 0 | V53: 0 | X53: 0 | Z53: 0 | AC53: 0 | AF53: 0 | AI53: =C53/1000 -> 0 | AJ53: =D53/1000 -> 0
A54: =VLOOKUP(E54,Index!A:B,2,0) -> Expenses Payable | C54: =SUMIF(SAP!A:A,E54,SAP!F:F) -> 174402 | D54: 108799 | E54: 2687 | G54: 127851 | I54: 126109 | K54: 145233 | M54: 129420 | Q54: 149018 | T54: 203695 | V54: 149532 | X54: 152804 | Z54: 151389 | AC54: 151542 | AF54: 203900 | AI54: =C54/1000 -> 174.402 | AJ54: =D54/1000 -> 108.799
A55: =VLOOKUP(E55,Index!A:B,2,0) -> Income tax | C55: =SUMIF(SAP!A:A,E55,SAP!F:F) -> 11993 | D55: 0 | E55: 2688 | G55: 3781 | I55: 3964 | K55: 597 | M55: 570 | Q55: 577 | T55: 560 | V55: 552 | X55: 538 | Z55: 530 | AC55: 534 | AF55: 558 | AI55: =C55/1000 -> 11.993 | AJ55: =D55/1000 -> 0
C56: =SUM(C51:C55) -> 1319416 | D56: =SUM(D51:D55) -> 1190612 | G56: 1186734 | I56: 1214246 | K56: 1318060 | M56: 1238517 | Q56: 1430370 | T56: 1298010 | V56: 1329950 | X56: 1335560 | Z56: 1296665 | AC56: 1254268 | AF56: 1350669 | AI56: =C56/1000 -> 1319.416 | AJ56: =D56/1000 -> 1190.612
AI57: =C57/1000 -> 0 | AJ57: =D57/1000 -> 0
C58: =C56-BS!C29 -> 0 | D58: =D56-BS!D29 -> 0 | M58: 0 | Q58: 0 | T58: 0 | V58: 0 | X58: 0 | Z58: 0 | AC58: 0 | AF58: 0 | AI58: =C58/1000 -> 0 | AJ58: =D58/1000 -> 0
A59: Note 6 - Share capital | AI59: =C59/1000 -> 0 | AJ59: =D59/1000 -> 0
C60: =DATE -> 44926 | D60: 43830 | G60: 44592 | I60: 44620 | K60: 44651 | M60: 44681 | Q60: 44712 | T60: 44742 | V60: 44773 | X60: 44804 | Z60: 44834 | AC60: 44865 | AF60: 44895 | AI60: =C60/1000 -> 44.926 | AJ60: =D60/1000 -> 43.83
C61: =DATE -> 44926 | D61: =CompareDATE -> 44561 | G61: 44592 | I61: 44620 | K61: 44651 | M61: 44681 | Q61: 44712 | T61: 44742 | V61: 44773 | X61: 44804 | Z61: 44834 | AC61: 44865 | AF61: 44895 | AI61: =C61/1000 -> 44.926 | AJ61: =D61/1000 -> 44.561
C62: U.S. Dollars | D62: U.S. Dollars | G62: U.S. Dollars | I62: U.S. Dollars | K62: U.S. Dollars | M62: U.S. Dollars | Q62: U.S. Dollars | T62: U.S. Dollars | V62: U.S. Dollars | X62: U.S. Dollars | Z62: U.S. Dollars | AC62: U.S. Dollars | AF62: U.S. Dollars | AI62: =C62/1000 -> #VALUE! | AJ62: =D62/1000 -> #VALUE!
A63: =VLOOKUP(E63,Index!A:B,2,0) -> Share capital | C63: =SUMIF(SAP!A:A,E63,SAP!F:F) -> 2215 | D63: 1866 | E63: 3721 | G63: 1866 | I63: 1866 | K63: 1866 | M63: 1866 | Q63: 1866 | T63: 1866 | V63: 2215 | X63: 2215 | Z63: 2215 | AC63: 2215 | AF63: 2215 | AI63: =C63/1000 -> 2.215 | AJ63: =D63/1000 -> 1.866
C64: =SUM(C63:C63) -> 2215 | D64: =SUM(D63:D63) -> 1866 | G64: 1866 | I64: 1866 | K64: 1866 | M64: 1866 | Q64: 1866 | T64: 1866 | V64: 2215 | X64: 2215 | Z64: 2215 | AC64: 2215 | AF64: 2215 | AI64: =C64/1000 -> 2.215 | AJ64: =D64/1000 -> 1.866
C65: =C64-BS!C39 -> 0 | D65: =D64-BS!D39 -> 0 | M65: 0 | Q65: 0 | T65: 0 | V65: 0 | X65: 0 | Z65: 0 | AC65: 0 | AF65: 0 | AI65: =C65/1000 -> 0 | AJ65: =D65/1000 -> 0

Sheet NotesP&L
A1: =Companyname -> Aurora Labs Consolidated | H1: INDEX
A2: NOTES TO FINANCIAL STATEMENTS
A4: Note 7 - Research & Development
B5: MTD | D5: QTD | F5: YTD | G5: YTD | J5: YTD | L5: MTD | M5: YTD | O5: MTD | P5: YTD | R5: MTD | S5: YTD | U5: YTD | V5: YTD | W5: MTD | X5: YTD | Y5: MTD | Z5: QTD | AC5: MTD | AD5: YTD | AF5: MTD | AG5: YTD | AH5: MTD | AI5: QTD | AJ5: YTD | AL5: MTD | AM5: YTD | AQ5: MTD | AR5: YTD
B6: =DATE -> 44926 | D6: =DATE -> 44926 | F6: =DATE -> 44926 | G6: 43830 | J6: 44592 | L6: 44620 | M6: 44620 | O6: 44651 | P6: 44742 | R6: 44681 | S6: 44681 | U6: 44712 | V6: 44742 | W6: 44712 | X6: 44804 | Y6: 44742 | Z6: 44742 | AC6: 44773 | AD6: 44773 | AF6: 44804 | AG6: 44804 | AH6: 44834 | AI6: 44834 | AJ6: 44834 | AL6: 44865 | AM6: 44865 | AQ6: 44895 | AR6: 44895
B7: =DATE -> 44926 | D7: =DATE -> 44926 | F7: =DATE -> 44926 | G7: =CompareDATE -> 44561 | J7: 44592 | L7: 44620 | M7: 44620 | O7: 44651 | P7: 44742 | R7: 44681 | S7: 44681 | U7: 44712 | V7: 44742 | W7: 44712 | X7: 44804 | Y7: 44742 | Z7: 44742 | AC7: 44773 | AD7: 44773 | AF7: 44804 | AG7: 44804 | AH7: 44834 | AI7: 44834 | AJ7: 44834 | AL7: 44865 | AM7: 44865 | AQ7: 44895 | AR7: 44895
B8: U.S. Dollars | D8: U.S. Dollars | F8: U.S. Dollars | G8: U.S. Dollars | J8: U.S. Dollars | L8: U.S. Dollars | M8: U.S. Dollars | O8: U.S. Dollars | P8: U.S. Dollars | R8: U.S. Dollars | S8: U.S. Dollars | U8: U.S. Dollars | V8: U.S. Dollars | W8: U.S. Dollars | X8: U.S. Dollars | Y8: U.S. Dollars | Z8: U.S. Dollars | AC8: U.S. Dollars | AD8: U.S. Dollars | AF8: U.S. Dollars | AG8: U.S. Dollars | AH8: U.S. Dollars | AI8: U.S. Dollars | AJ8: U.S. Dollars | AL8: U.S. Dollars | AM8: U.S. Dollars | AQ8: U.S. Dollars | AR8: U.S. Dollars
A10: =VLOOKUP(H10,Index!A:B,2,0) -> Salaries and social benefits | B10: =טבלה5[[#This Row],[עמודה4]]-AR10 -> 845679 | D10: =טבלה5[[#This Row],[עמודה4]]-AJ10 -> 2107456 | F10: =-SUMIF(SAP!A:A,H10,SAP!F:F) -> 7823748 | G10: 4719388 | H10: 7000 | J10: 556984 | L10: 555255 | M10: 1112239 | O10: 716439 | P10: 3683897 | R10: 547781 | S10: 2376459 | U10: 2999454 | V10: 3683897 | W10: 622995 | X10: 4959416 | Y10: 684443 | Z10: 1855219 | AC10: 617593 | AD10: 4301490 | AF10: 657926 | AG10: 4959416 | AH10: 756876 | AI10: 2032395 | AJ10: 5716292 | AL10: 588857 | AM10: 6305149 | AQ10: 672920 | AR10: 6978069 | AX10: =טבלה5[[#This Row],[עמודה4]]/1000 -> 7823.748 | AY10: =טבלה5[[#This Row],[עמודה4]]/1000 -> 7823.748
A11: =VLOOKUP(H11,Index!A:B,2,0) -> Outsourcing & Consultation | B11: =טבלה5[[#This Row],[עמודה4]]-AR11 -> 113996 | D11: =טבלה5[[#This Row],[עמודה4]]-AJ11 -> 351588 | F11: =-SUMIF(SAP!A:A,H11,SAP!F:F) -> 1267597 | G11: 1174376 | H11: 7001 | J11: 99768 | L11: 98284 | M11: 198052 | O11: 97146 | P11: 623169 | R11: 115746 | S11: 410944 | U11: 513602 | V11: 623169 | W11: 102658 | X11: 805805 | Y11: 109567 | Z11: 327971 | AC11: 80334 | AD11: 703503 | AF11: 102302 | AG11: 805805 | AH11: 110204 | AI11: 292840 | AJ11: 916009 | AL11: 88950 | AM11: 1004959 | AQ11: 148642 | AR11: 1153601 | AX11: =טבלה5[[#This Row],[עמודה4]]/1000 -> 1267.597 | AY11: =טבלה5[[#This Row],[עמודה4]]/1000 -> 1267.597
A12: =VLOOKUP(H12,Index!A:B,2,0) -> Communication & Computer Maintenance | B12: =טבלה5[[#This Row],[עמודה4]]-AR12 -> 29319 | D12: =טבלה5[[#This Row],[עמודה4]]-AJ12 -> 121318 | F12: =-SUMIF(SAP!A:A,H12,SAP!F:F) -> 512228 | G12: 426171 | H12: 7002 | J12: 23576 | L12: 17179 | M12: 40755 | O12: 20838 | P12: 167105 | R12: 29724 | S12: 91317 | U12: 132728 | V12: 167105 | W12: 41411 | X12: 284654 | Y12: 34377 | Z12: 105512 | AC12: 40426 | AD12: 207531 | AF12: 77123 | AG12: 284654 | AH12: 106256 | AI12: 223805 | AJ12: 390910 | AL12: 20807 | AM12: 411717 | AQ12: 71192 | AR12: 482909 | AX12: =טבלה5[[#This Row],[עמודה4]]/1000 -> 512.228 | AY12: =טבלה5[[#This Row],[עמודה4]]/1000 -> 512.228
A13: =VLOOKUP(H13,Index!A:B,2,0) -> Travel Abroad | B13: =F13-J13 -> 0 | F13: =-SUMIF(SAP!A:A,H13,SAP!F:F) -> 0 | H13: 7007 | J13: 0 | L13: 0 | M13: 0 | O13: 0 | P13: 0 | R13: 0 | S13: 0 | U13: 0 | V13: 0 | W13: 0 | X13: 0 | Y13: 0 | AC13: 0 | AD13: 0 | AF13: 0 | AG13: 0 | AH13: 0 | AJ13: 0 | AL13: 0 | AM13: 0 | AQ13: 0 | AR13: 0 | AX13: =טבלה5[[#This Row],[עמודה4]]/1000 -> 0 | AY13: =טבלה5[[#This Row],[עמודה4]]/1000 -> 0
B14: =SUM(B10:B13) -> 988994 | C14: =SUM(C10:C13) -> 0 | D14: =SUM(D10:D13) -> 2580362 | F14: =SUM(F10:F13) -> 9603573 | G14: =SUM(G10:G13) -> 6319935 | J14: 680328 | L14: 670718 | M14: 1351046 | O14: 834423 | P14: 4474171 | R14: 693251 | S14: 2878720 | U14: 3645784 | V14: 4474171 | W14: 767064 | X14: 6049875 | Y14: 828387 | Z14: 2288702 | AC14: 738353 | AD14: 5212524 | AF14: 837351 | AG14: 6049875 | AH14: 973336 | AI14: 2549040 | AJ14: 7023211 | AL14: 698614 | AM14: 7721825 | AQ14: 892754 | AR14: 8614579 | AX14: =טבלה5[[#This Row],[עמודה4]]/1000 -> 9603.573 | AY14: =טבלה5[[#This Row],[עמודה4]]/1000 -> 9603.573
B15: =B14-'P&L'!D19 -> 0 | D15: =D14-'P&L'!F19 -> 0 | F15: =F14-'P&L'!H19 -> 0 | G15: =G14-'P&L'!I19 -> 0 | P15: 0 | S15: 0 | U15: 0 | V15: 0 | W15: 0 | X15: 0 | Y15: 0 | Z15: 0 | AC15: 0 | AD15: 0 | AF15: 0 | AG15: 0 | AH15: 0 | AI15: 0 | AJ15: 0 | AL15: 0 | AM15: 0 | AQ15: 0 | AR15: 0 | AX15: =טבלה5[[#This Row],[עמודה4]]/1000 -> 0 | AY15: =טבלה5[[#This Row],[עמודה4]]/1000 -> 0
AX16: =טבלה5[[#This Row],[עמודה4]]/1000 -> 0 | AY16: =טבלה5[[#This Row],[עמודה4]]/1000 -> 0
A17: Note 8 - Sales & Marketing | AX17: =טבלה5[[#This Row],[עמודה4]]/1000 -> 0 | AY17: =טבלה5[[#This Row],[עמודה4]]/1000 -> 0
B18: =B5 -> MTD | D18: QTD | F18: YTD | G18: YTD | J18: YTD | L18: MTD | M18: YTD | O18: MTD | P18: YTD | R18: MTD | S18: YTD | U18: YTD | V18: YTD | W18: MTD | X18: YTD | Y18: MTD | Z18: QTD | AC18: MTD | AD18: YTD | AF18: MTD | AG18: YTD | AH18: MTD | AI18: QTD | AJ18: YTD | AL18: MTD | AM18: YTD | AQ18: MTD | AR18: YTD
B19: =DATE -> 44926 | D19: =DATE -> 44926 | F19: =DATE -> 44926 | G19: 43830 | J19: 44592 | L19: 44620 | M19: 44620 | O19: 44651 | P19: 44742 | R19: 44681 | S19: 44681 | U19: 44712 | V19: 44742 | W19: 44712 | X19: 44804 | Y19: 44742 | Z19: 44742 | AC19: 44773 | AD19: 44773 | AF19: 44804 | AG19: 44804 | AH19: 44834 | AI19: 44834 | AJ19: 44834 | AL19: 44865 | AM19: 44865 | AQ19: 44895 | AR19: 44895
B20: =DATE -> 44926 | D20: =DATE -> 44926 | F20: =DATE -> 44926 | G20: =CompareDATE -> 44561 | J20: 44592 | L20: 44620 | M20: 44620 | O20: 44651 | P20: 44742 | R20: 44681 | S20: 44681 | U20: 44712 | V20: 44742 | W20: 44712 | X20: 44804 | Y20: 44742 | Z20: 44742 | AC20: 44773 | AD20: 44773 | AF20: 44804 | AG20: 44804 | AH20: 44834 | AI20: 44834 | AJ20: 44834 | AL20: 44865 | AM20: 44865 | AQ20: 44895 | AR20: 44895
B21: U.S. Dollars | D21: U.S. Dollars | F21: U.S. Dollars | G21: U.S. Dollars | J21: U.S. Dollars | L21: U.S. Dollars | M21: U.S. Dollars | O21: U.S. Dollars | P21: U.S. Dollars | R21: U.S. Dollars | S21: U.S. Dollars | U21: U.S. Dollars | V21: U.S. Dollars | W21: U.S. Dollars | X21: U.S. Dollars | Y21: U.S. Dollars | Z21: U.S. Dollars | AC21: U.S. Dollars | AD21: U.S. Dollars | AF21: U.S. Dollars | AG21: U.S. Dollars | AH21: U.S. Dollars | AI21: U.S. Dollars | AJ21: U.S. Dollars | AL21: U.S. Dollars | AM21: U.S. Dollars | AQ21: U.S. Dollars | AR21: U.S. Dollars
A22: =VLOOKUP(H22,Index!A:B,2,0) -> Salaries and social benefits | B22: =טבלה5[[#This Row],[עמודה4]]-AR22 -> -136286 | D22: =טבלה5[[#This Row],[עמודה4]]-AJ22 -> 4244 | F22: =-SUMIF(SAP!A:A,H22,SAP!F:F) -> 639847 | G22: 873229 | H22: 7020 | J22: 57074 | L22: 57576 | M22: 114650 | O22: 104488 | P22: 423716 | R22: 52542 | S22: 271680 | U22: 321569 | V22: 423716 | W22: 49889 | X22: 522265 | Y22: 102147 | Z22: 204578 | AC22: 53348 | AD22: 477064 | AF22: 45201 | AG22: 522265 | AH22: 113338 | AI22: 211887 | AJ22: 635603 | AL22: 59805 | AM22: 695408 | AQ22: 80725 | AR22: 776133 | AX22: =טבלה5[[#This Row],[עמודה4]]/1000 -> 639.847 | AY22: =טבלה5[[#This Row],[עמודה4]]/1000 -> 639.847
A23: =VLOOKUP(H23,Index!A:B,2,0) -> Marketing exepences | B23: =טבלה5[[#This Row],[עמודה4]]-AR23 -> 48402 | D23: =טבלה5[[#This Row],[עמודה4]]-AJ23 -> 142440 | F23: =-SUMIF(SAP!A:A,H23,SAP!F:F) -> 471153 | G23: 327480 | H23: 7021 | J23: 34927 | L23: 31174 | M23: 66101 | O23: 46352 | P23: 196784 | R23: 33730 | S23: 146183 | U23: 181038 | V23: 196784 | W23: 34855 | X23: 295018 | Y23: 15746 | Z23: 84331 | AC23: 46614 | AD23: 243398 | AF23: 51620 | AG23: 295018 | AH23: 33695 | AI23: 131929 | AJ23: 328713 | AL23: 38444 | AM23: 367157 | AQ23: 55594 | AR23: 422751 | AX23: =טבלה5[[#This Row],[עמודה4]]/1000 -> 471.153 | AY23: =טבלה5[[#This Row],[עמודה4]]/1000 -> 471.153
A24: =VLOOKUP(H24,Index!A:B,2,0) -> Conference and shows | B24: =טבלה5[[#This Row],[עמודה4]]-AR24 -> 27054 | D24: =טבלה5[[#This Row],[עמודה4]]-AJ24 -> 49686 | F24: =-SUMIF(SAP!A:A,H24,SAP!F:F) -> 75712 | G24: 16541 | H24: 7022 | J24: =-SUMIF(SAP!E:E,L24,SAP!J:J) -> 0 | L24: 0 | M24: 0 | O24: 0 | P24: 24411 | R24: 16699 | S24: 16699 | U24: 17844 | V24: 24411 | W24: 1145 | X24: 25332 | Y24: 6567 | Z24: 24411 | AC24: -3838 | AD24: 20573 | AF24: 4759 | AG24: 25332 | AH24: 694 | AI24: 1615 | AJ24: 26026 | AL24: 9219 | AM24: 35245 | AQ24: 13413 | AR24: 48658 | AX24: =טבלה5[[#This Row],[עמודה4]]/1000 -> 75.712 | AY24: =טבלה5[[#This Row],[עמודה4]]/1000 -> 75.712
A25: =VLOOKUP(H25,Index!A:B,2,0) -> Subcontructors GMBH | B25: =טבלה5[[#This Row],[עמודה4]]-AR25 -> 0 | D25: =טבלה5[[#This Row],[עמודה4]]-AJ25 -> 0 | F25: =-SUMIF(SAP!A:A,H25,SAP!F:F) -> 0 | G25: 0 | H25: 7023 | J25: =-SUMIF(SAP!E:E,L25,SAP!J:J) -> 0 | L25: 0 | M25: 0 | O25: 0 | P25: 0 | R25: 0 | S25: 0 | U25: 0 | V25: 0 | W25: 0 | X25: 0 | Y25: 0 | Z25: 0 | AC25: 0 | AD25: 0 | AF25: 0 | AG25: 0 | AH25: 0 | AI25: 0 | AJ25: 0 | AL25: 0 | AM25: 0 | AQ25: 0 | AR25: 0 | AX25: =טבלה5[[#This Row],[עמודה4]]/1000 -> 0 | AY25: =טבלה5[[#This Row],[עמודה4]]/1000 -> 0
A26: =VLOOKUP(H26,Index!A:B,2,0) -> Other expenses | B26: =טבלה5[[#This Row],[עמודה4]]-AR26 -> 8635 | D26: =טבלה5[[#This Row],[עמודה4]]-AJ26 -> 8777 | F26: =-SUMIF(SAP!A:A,H26,SAP!F:F) -> 10194 | G26: 2566 | H26: 7028 | J26: =-SUMIF(SAP!E:E,L26,SAP!J:J) -> 0 | L26: 290 | M26: 290 | O26: 338 | P26: 4342 | R26: -29 | S26: 599 | U26: 971 | V26: 4342 | W26: 372 | X26: 1131 | Y26: 3371 | Z26: 3714 | AC26: 9973 | AD26: 14315 | AF26: -13184 | AG26: 1131 | AH26: 286 | AI26: -2925 | AJ26: 1417 | AL26: 10 | AM26: 1427 | AQ26: 132 | AR26: 1559 | AX26: =טבלה5[[#This Row],[עמודה4]]/1000 -> 10.194 | AY26: =טבלה5[[#This Row],[עמודה4]]/1000 -> 10.194
A27: =VLOOKUP(H27,Index!A:B,2,0) -> Travel Abroad | B27: =טבלה5[[#This Row],[עמודה4]]-AR27 -> 793 | D27: =טבלה5[[#This Row],[עמודה4]]-AJ27 -> 1088 | F27: =-SUMIF(SAP!A:A,H27,SAP!F:F) -> 6688 | G27: 2452 | H27: 7025 | J27: 0 | L27: 0 | M27: 0 | O27: 0 | P27: 0 | R27: 0 | S27: 0 | U27: 0 | V27: 0 | W27: 0 | X27: 5826 | Y27: 0 | Z27: 0 | AC27: 5826 | AD27: 5826 | AF27: 0 | AG27: 5826 | AH27: -226 | AI27: 5600 | AJ27: 5600 | AL27: 40 | AM27: 5640 | AQ27: 255 | AR27: 5895 | AX27: =טבלה5[[#This Row],[עמודה4]]/1000 -> 6.688 | AY27: =טבלה5[[#This Row],[עמודה4]]/1000 -> 6.688
A28: =VLOOKUP(H28,Index!A:B,2,0) -> Creative & branding | B28: =טבלה5[[#This Row],[עמודה4]]-AR28 -> 30041 | D28: =טבלה5[[#This Row],[עמודה4]]-AJ28 -> 68127 | F28: =-SUMIF(SAP!A:A,H28,SAP!F:F) -> 202799 | G28: 100646 | H28: 7026 | J28: 10941 | L28: 9044 | M28: 19985 | O28: 8471 | P28: 107385 | R28: 57410 | S28: 85866 | U28: 98826 | V28: 107385 | W28: 12960 | X28: 123013 | Y28: 8559 | Z28: 78929 | AC28: -8533 | AD28: 98852 | AF28: 24161 | AG28: 123013 | AH28: 11659 | AI28: 27287 | AJ28: 134672 | AL28: 13287 | AM28: 147959 | AQ28: 24799 | AR28: 172758 | AX28: =טבלה5[[#This Row],[עמודה4]]/1000 -> 202.799 | AY28: =טבלה5[[#This Row],[עמודה4]]/1000 -> 202.799
B29: =SUM(B22:B28) -> -21361 | C29: =SUM(C22:C28) -> 0 | D29: =SUM(D22:D28) -> 274362 | E29: =SUM(E22:E28) -> 0 | F29: =SUM(F22:F28) -> 1406393 | G29: =SUM(G22:G28) -> 1322914 | J29: 102942 | L29: 98084 | M29: 201026 | O29: 159649 | P29: 756638 | R29: 160352 | S29: 521027 | U29: 620248 | V29: 756638 | W29: 99221 | X29: 972585 | Y29: 136390 | Z29: 395963 | AC29: 103390 | AD29: 860028 | AF29: 112557 | AG29: 972585 | AH29: 159446 | AI29: 375393 | AJ29: 1132031 | AL29: 120805 | AM29: 1252836 | AQ29: 174918 | AR29: 1427754 | AX29: =טבלה5[[#This Row],[עמודה4]]/1000 -> 1406.393 | AY29: =טבלה5[[#This Row],[עמודה4]]/1000 -> 1406.393
B30: =B29-'P&L'!D20 -> 0 | D30: =D29-'P&L'!F20 -> 0 | F30: =F29-'P&L'!H20 -> 0 | G30: =G29-'P&L'!I20 -> 0 | P30: 0 | S30: 0 | U30: 0 | V30: 0 | W30: 0 | X30: 0 | Y30: 0 | Z30: 0 | AC30: 0 | AD30: 0 | AF30: 0 | AG30: 0 | AH30: 0 | AI30: 0 | AJ30: 0 | AL30: 0 | AM30: 0 | AQ30: 0 | AR30: 0 | AX30: =טבלה5[[#This Row],[עמודה4]]/1000 -> 0 | AY30: =טבלה5[[#This Row],[עמודה4]]/1000 -> 0
AX31: =טבלה5[[#This Row],[עמודה4]]/1000 -> 0 | AY31: =טבלה5[[#This Row],[עמודה4]]/1000 -> 0
AX32: =טבלה5[[#This Row],[עמודה4]]/1000 -> 0 | AY32: =טבלה5[[#This Row],[עמודה4]]/1000 -> 0
AX33: =טבלה5[[#This Row],[עמודה4]]/1000 -> 0 | AY33: =טבלה5[[#This Row],[עמודה4]]/1000 -> 0
A34: Note 9 - General & Administrative | AX34: =טבלה5[[#This Row],[עמודה4]]/1000 -> 0 | AY34: =טבלה5[[#This Row],[עמודה4]]/1000 -> 0
B35: =B18 -> MTD | D35: QTD | F35: YTD | G35: YTD | J35: YTD | L35: MTD | M35: YTD | O35: MTD | P35: YTD | R35: MTD | S35: YTD | U35: YTD | V35: YTD | W35: MTD | X35: YTD | Y35: MTD | Z35: QTD | AC35: MTD | AD35: YTD | AF35: MTD | AG35: YTD | AH35: MTD | AI35: QTD | AJ35: YTD | AL35: MTD | AM35: YTD | AQ35: MTD | AR35: YTD | AX35: =טבלה5[[#This Row],[עמודה4]]/1000 -> #VALUE! | AY35: =טבלה5[[#This Row],[עמודה4]]/1000 -> #VALUE!
B36: =DATE -> 44926 | D36: =DATE -> 44926 | F36: =DATE -> 44926 | G36: 43830 | J36: 44592 | L36: 44620 | M36: 44620 | O36: 44651 | P36: 44742 | R36: 44681 | S36: 44681 | U36: 44712 | V36: 44742 | W36: 44712 | X36: 44804 | Y36: 44742 | Z36: 44742 | AC36: 44773 | AD36: 44773 | AF36: 44804 | AG36: 44804 | AH36: 44834 | AI36: 44834 | AJ36: 44834 | AL36: 44865 | AM36: 44865 | AQ36: 44895 | AR36: 44895 | AX36: =טבלה5[[#This Row],[עמודה4]]/1000 -> 44.926 | AY36: =טבלה5[[#This Row],[עמודה4]]/1000 -> 44.926
B37: =DATE -> 44926 | D37: =DATE -> 44926 | F37: =DATE -> 44926 | G37: =CompareDATE -> 44561 | J37: 44592 | L37: 44620 | M37: 44620 | O37: 44651 | P37: 44742 | R37: 44681 | S37: 44681 | U37: 44712 | V37: 44742 | W37: 44712 | X37: 44804 | Y37: 44742 | Z37: 44742 | AC37: 44773 | AD37: 44773 | AF37: 44804 | AG37: 44804 | AH37: 44834 | AI37: 44834 | AJ37: 44834 | AL37: 44865 | AM37: 44865 | AQ37: 44895 | AR37: 44895 | AX37: =טבלה5[[#This Row],[עמודה4]]/1000 -> 44.926 | AY37: =טבלה5[[#This Row],[עמודה4]]/1000 -> 44.926
B38: U.S. Dollars | D38: U.S. Dollars | F38: U.S. Dollars | G38: U.S. Dollars | J38: U.S. Dollars | L38: U.S. Dollars | M38: U.S. Dollars | O38: U.S. Dollars | P38: U.S. Dollars | R38: U.S. Dollars | S38: U.S. Dollars | U38: U.S. Dollars | V38: U.S. Dollars | W38: U.S. Dollars | X38: U.S. Dollars | Y38: U.S. Dollars | Z38: U.S. Dollars | AC38: U.S. Dollars | AD38: U.S. Dollars | AF38: U.S. Dollars | AG38: U.S. Dollars | AH38: U.S. Dollars | AI38: U.S. Dollars | AJ38: U.S. Dollars | AL38: U.S. Dollars | AM38: U.S. Dollars | AQ38: U.S. Dollars | AR38: U.S. Dollars | AX38: =טבלה5[[#This Row],[עמודה4]]/1000 -> #VALUE! | AY38: =טבלה5[[#This Row],[עמודה4]]/1000 -> #VALUE!
A39: =VLOOKUP(H39,Index!A:B,2,0) -> Salaries and social benefits | B39: =טבלה5[[#This Row],[עמודה4]]-AR39 -> 62436 | D39: =טבלה5[[#This Row],[עמודה4]]-AJ39 -> 209618 | F39: =-SUMIF(SAP!A:A,H39,SAP!F:F) -> 933435 | G39: 820270 | H39: 7050 | J39: 73400 | L39: 77980 | M39: 151380 | O39: 92151 | P39: 485780 | R39: 76377 | S39: 319908 | U39: 398777 | V39: 485780 | W39: 78869 | X39: 640821 | Y39: 87003 | Z39: 242249 | AC39: 75887 | AD39: 561667 | AF39: 79154 | AG39: 640821 | AH39: 82996 | AI39: 238037 | AJ39: 723817 | AL39: 70714 | AM39: 794531 | AQ39: 76468 | AR39: 870999 | AX39: =טבלה5[[#This Row],[עמודה4]]/1000 -> 933.435 | AY39: =טבלה5[[#This Row],[עמודה4]]/1000 -> 933.435
A40: =VLOOKUP(H40,Index!A:B,2,0) -> Professional services | B40: =טבלה5[[#This Row],[עמודה4]]-AR40 -> 19171 | D40: =טבלה5[[#This Row],[עמודה4]]-AJ40 -> 40173 | F40: =-SUMIF(SAP!A:A,H40,SAP!F:F) -> 181013 | G40: 335179 | H40: 7051 | J40: 23816 | L40: 13870 | M40: 37686 | O40: 13841 | P40: 101072 | R40: 18263 | S40: 69790 | U40: 94169 | V40: 101072 | W40: 24379 | X40: 128359 | Y40: 6903 | Z40: 49545 | AC40: 8603 | AD40: 109675 | AF40: 18684 | AG40: 128359 | AH40: 12481 | AI40: 39768 | AJ40: 140840 | AL40: 9929 | AM40: 150769 | AQ40: 11073 | AR40: 161842 | AX40: =טבלה5[[#This Row],[עמודה4]]/1000 -> 181.013 | AY40: =טבלה5[[#This Row],[עמודה4]]/1000 -> 181.013
A41: =VLOOKUP(H41,Index!A:B,2,0) -> Depreciation | B41: =טבלה5[[#This Row],[עמודה4]]-AR41 -> 6997 | D41: =טבלה5[[#This Row],[עמודה4]]-AJ41 -> 20488 | F41: =-SUMIF(SAP!A:A,H41,SAP!F:F) -> 73303 | G41: 46356 | H41: 7052 | J41: 5276 | L41: 5371 | M41: 10647 | O41: 5463 | P41: 33657 | R41: 5807 | S41: 21917 | U41: 27671 | V41: 33657 | W41: 5754 | X41: 46243 | Y41: 5986 | Z41: 17547 | AC41: 6059 | AD41: 39716 | AF41: 6527 | AG41: 46243 | AH41: 6572 | AI41: 19158 | AJ41: 52815 | AL41: 6573 | AM41: 59388 | AQ41: 6918 | AR41: 66306 | AX41: =טבלה5[[#This Row],[עמודה4]]/1000 -> 73.303 | AY41: =טבלה5[[#This Row],[עמודה4]]/1000 -> 73.303
A42: =VLOOKUP(H42,Index!A:B,2,0) -> Insurance | B42: =טבלה5[[#This Row],[עמודה4]]-AR42 -> 3359 | D42: =טבלה5[[#This Row],[עמודה4]]-AJ42 -> 10060 | F42: =-SUMIF(SAP!A:A,H42,SAP!F:F) -> 124846 | G42: 12350 | H42: 7054 | J42: 2006 | L42: 1316 | M42: 3322 | O42: 1347 | P42: 7080 | R42: 1261 | S42: 5930 | U42: 6240 | V42: 7080 | W42: 310 | X42: 43402 | Y42: 840 | Z42: 2411 | AC42: 32811 | AD42: 39891 | AF42: 3511 | AG42: 43402 | AH42: 71384 | AI42: 107706 | AJ42: 114786 | AL42: 779 | AM42: 115565 | AQ42: 5922 | AR42: 121487 | AX42: =טבלה5[[#This Row],[עמודה4]]/1000 -> 124.846 | AY42: =טבלה5[[#This Row],[עמודה4]]/1000 -> 124.846
A43: =VLOOKUP(H43,Index!A:B,2,0) -> Vehicle expense | B43: =טבלה5[[#This Row],[עמודה4]]-AR43 -> 0 | D43: =טבלה5[[#This Row],[עמודה4]]-AJ43 -> 793 | F43: =-SUMIF(SAP!A:A,H43,SAP!F:F) -> 793 | G43: 6077 | H43: 7056 | J43: 0 | L43: 0 | M43: 0 | O43: 0 | P43: 0 | R43: 0 | S43: 0 | U43: 0 | V43: 0 | W43: 0 | X43: 0 | Y43: 0 | Z43: 0 | AC43: 0 | AD43: 0 | AF43: 0 | AG43: 0 | AH43: 0 | AI43: 0 | AJ43: 0 | AL43: 793 | AM43: 793 | AQ43: 0 | AR43: 793 | AX43: =טבלה5[[#This Row],[עמודה4]]/1000 -> 0.793 | AY43: =טבלה5[[#This Row],[עמודה4]]/1000 -> 0.793
A44: =VLOOKUP(H44,Index!A:B,2,0) -> Consulting | B44: =טבלה5[[#This Row],[עמודה4]]-AR44 -> -308510 | D44: =טבלה5[[#This Row],[עמודה4]]-AJ44 -> -291421 | F44: =-SUMIF(SAP!A:A,H44,SAP!F:F) -> 105442 | G44: 101458 | H44: 7053 | J44: 9401 | L44: 326935 | M44: 336336 | O44: 9204 | P44: 371960 | R44: 8755 | S44: 354295 | U44: 363189 | V44: 371960 | W44: 8894 | X44: 388717 | Y44: 8771 | Z44: 26420 | AC44: 8439 | AD44: 380399 | AF44: 8318 | AG44: 388717 | AH44: 8146 | AI44: 24903 | AJ44: 396863 | AL44: 8074 | AM44: 404937 | AQ44: 9015 | AR44: 413952 | AX44: =טבלה5[[#This Row],[עמודה4]]/1000 -> 105.442 | AY44: =טבלה5[[#This Row],[עמודה4]]/1000 -> 105.442
A45: =VLOOKUP(H45,Index!A:B,2,0) -> Office Maintenance | B45: =טבלה5[[#This Row],[עמודה4]]-AR45 -> 34438 | D45: =טבלה5[[#This Row],[עמודה4]]-AJ45 -> 91971 | F45: =-SUMIF(SAP!A:A,H45,SAP!F:F) -> 331046 | G45: 306316 | H45: 7055 | J45: 26898 | L45: 22301 | M45: 49199 | O45: 26600 | P45: 158378 | R45: 25395 | S45: 101194 | U45: 131406 | V45: 158378 | W45: 30212 | X45: 207309 | Y45: 26972 | Z45: 82579 | AC45: 22612 | AD45: 180990 | AF45: 26319 | AG45: 207309 | AH45: 31766 | AI45: 80697 | AJ45: 239075 | AL45: 27252 | AM45: 266327 | AQ45: 30281 | AR45: 296608 | AX45: =טבלה5[[#This Row],[עמודה4]]/1000 -> 331.046 | AY45: =טבלה5[[#This Row],[עמודה4]]/1000 -> 331.046
A46: =VLOOKUP(H46,Index!A:B,2,0) -> Travel Abroad | B46: =טבלה5[[#This Row],[עמודה4]]-AR46 -> 32789 | D46: =טבלה5[[#This Row],[עמודה4]]-AJ46 -> 56471 | F46: =-SUMIF(SAP!A:A,H46,SAP!F:F) -> 196840 | G46: 14258 | H46: 7057 | J46: -4310 | L46: 0 | M46: -4310 | O46: 4620 | P46: 28659 | R46: 9928 | S46: 10238 | U46: 10245 | V46: 28659 | W46: 7 | X46: 100296 | Y46: 18414 | Z46: 28349 | AC46: 66310 | AD46: 94969 | AF46: 5327 | AG46: 100296 | AH46: 40073 | AI46: 111710 | AJ46: 140369 | AL46: 20361 | AM46: 160730 | AQ46: 3321 | AR46: 164051 | AX46: =טבלה5[[#This Row],[עמודה4]]/1000 -> 196.84 | AY46: =טבלה5[[#This Row],[עמודה4]]/1000 -> 196.84
A47: =VLOOKUP(H47,Index!A:B,2,0) -> Other | B47: =טבלה5[[#This Row],[עמודה4]]-AR47 -> 69212 | D47: =טבלה5[[#This Row],[עמודה4]]-AJ47 -> 85077 | F47: =-SUMIF(SAP!A:A,H47,SAP!F:F) -> 239232 | G47: 217530 | H47: 7059 | J47: 11096 | L47: 4942 | M47: 16038 | O47: 21936 | P47: 73383 | R47: 10322 | S47: 48296 | U47: 57959 | V47: 73383 | W47: 9663 | X47: 144384 | Y47: 15424 | Z47: 35409 | AC47: 41451 | AD47: 114834 | AF47: 29550 | AG47: 144384 | AH47: 9771 | AI47: 80772 | AJ47: 154155 | AL47: 4098 | AM47: 158253 | AQ47: 11767 | AR47: 170020 | AX47: =טבלה5[[#This Row],[עמודה4]]/1000 -> 239.232 | AY47: =טבלה5[[#This Row],[עמודה4]]/1000 -> 239.232
B48: =SUM(B39:B47) -> -80108 | C48: =SUM(C39:C47) -> 0 | D48: =SUM(D39:D47) -> 223230 | E48: =SUM(E39:E47) -> 0 | F48: =SUM(F39:F47) -> 2185950 | G48: =SUM(G39:G47) -> 1859794 | J48: 147583 | L48: 452715 | M48: 600298 | O48: 175162 | P48: 1259969 | R48: 156108 | S48: 931568 | U48: 1089656 | V48: 1259969 | W48: 158088 | X48: 1699531 | Y48: 170313 | Z48: 484509 | AC48: 262172 | AD48: 1522141 | AF48: 177390 | AG48: 1699531 | AH48: 263189 | AI48: 702751 | AJ48: 1962720 | AL48: 148573 | AM48: 2111293 | AQ48: 154765 | AR48: 2266058 | AX48: =טבלה5[[#This Row],[עמודה4]]/1000 -> 2185.95 | AY48: =טבלה5[[#This Row],[עמודה4]]/1000 -> 2185.95
B49: =B48-'P&L'!D21 -> 0 | D49: =D48-'P&L'!F21 -> 0 | F49: =F48-'P&L'!H21 -> 0 | G49: =G48-'P&L'!I21 -> 0 | P49: 0 | S49: 0 | U49: 0 | V49: 0 | W49: 0 | X49: 0 | Y49: 0 | Z49: 0 | AC49: 0 | AD49: 0 | AF49: 0 | AG49: 0 | AH49: 0 | AI49: 0 | AJ49: 0 | AL49: 0 | AM49: 0 | AQ49: 0 | AR49: 0 | AX49: =טבלה5[[#This Row],[עמודה4]]/1000 -> 0 | AY49: =טבלה5[[#This Row],[עמודה4]]/1000 -> 0
AX50: =טבלה5[[#This Row],[עמודה4]]/1000 -> 0 | AY50: =טבלה5[[#This Row],[עמודה4]]/1000 -> 0
A51: Note 10 - Interest expenses (income) | AX51: =טבלה5[[#This Row],[עמודה4]]/1000 -> 0 | AY51: =טבלה5[[#This Row],[עמודה4]]/1000 -> 0
B52: =B35 -> MTD | D52: QTD | F52: YTD | G52: YTD | J52: YTD | L52: MTD | M52: YTD | O52: MTD | P52: YTD | R52: MTD | S52: YTD | U52: YTD | V52: YTD | W52: MTD | X52: YTD | Y52: MTD | Z52: QTD | AC52: MTD | AD52: YTD | AF52: MTD | AG52: YTD | AH52: MTD | AI52: QTD | AJ52: YTD | AL52: MTD | AM52: YTD | AQ52: MTD | AR52: YTD | AX52: =טבלה5[[#This Row],[עמודה4]]/1000 -> #VALUE! | AY52: =טבלה5[[#This Row],[עמודה4]]/1000 -> #VALUE!
B53: =DATE -> 44926 | D53: =DATE -> 44926 | F53: =DATE -> 44926 | G53: 43830 | J53: 44592 | L53: 44620 | M53: 44620 | O53: 44651 | P53: 44742 | R53: 44681 | S53: 44681 | U53: 44712 | V53: 44742 | W53: 44712 | X53: 44804 | Y53: 44742 | Z53: 44742 | AC53: 44773 | AD53: 44773 | AF53: 44804 | AG53: 44804 | AH53: 44834 | AI53: 44834 | AJ53: 44834 | AL53: 44865 | AM53: 44865 | AQ53: 44895 | AR53: 44895 | AX53: =טבלה5[[#This Row],[עמודה4]]/1000 -> 44.926 | AY53: =טבלה5[[#This Row],[עמודה4]]/1000 -> 44.926
B54: =DATE -> 44926 | D54: =DATE -> 44926 | F54: =DATE -> 44926 | G54: =CompareDATE -> 44561 | J54: 44592 | L54: 44620 | M54: 44620 | O54: 44651 | P54: 44742 | R54: 44681 | S54: 44681 | U54: 44712 | V54: 44742 | W54: 44712 | X54: 44804 | Y54: 44742 | Z54: 44742 | AC54: 44773 | AD54: 44773 | AF54: 44804 | AG54: 44804 | AH54: 44834 | AI54: 44834 | AJ54: 44834 | AL54: 44865 | AM54: 44865 | AQ54: 44895 | AR54: 44895 | AX54: =טבלה5[[#This Row],[עמודה4]]/1000 -> 44.926 | AY54: =טבלה5[[#This Row],[עמודה4]]/1000 -> 44.926
B55: U.S. Dollars | D55: U.S. Dollars | F55: U.S. Dollars | G55: U.S. Dollars | J55: U.S. Dollars | L55: U.S. Dollars | M55: U.S. Dollars | O55: U.S. Dollars | P55: U.S. Dollars | R55: U.S. Dollars | S55: U.S. Dollars | U55: U.S. Dollars | V55: U.S. Dollars | W55: U.S. Dollars | X55: U.S. Dollars | Y55: U.S. Dollars | Z55: U.S. Dollars | AC55: U.S. Dollars | AD55: U.S. Dollars | AF55: U.S. Dollars | AG55: U.S. Dollars | AH55: U.S. Dollars | AI55: U.S. Dollars | AJ55: U.S. Dollars | AL55: U.S. Dollars | AM55: U.S. Dollars | AQ55: U.S. Dollars | AR55: U.S. Dollars | AX55: =טבלה5[[#This Row],[עמודה4]]/1000 -> #VALUE! | AY55: =טבלה5[[#This Row],[עמודה4]]/1000 -> #VALUE!
A56: =VLOOKUP(H56,Index!A:B,2,0) -> Bank commission and interest | B56: =טבלה5[[#This Row],[עמודה4]]-AR56 -> -155766 | D56: =טבלה5[[#This Row],[עמודה4]]-AJ56 -> -466259 | F56: =-SUMIF(SAP!A:A,H56,SAP!F:F) -> -701518 | G56: 6284 | H56: 7900 | J56: 541 | L56: 403 | M56: 944 | O56: 607 | P56: 3459 | R56: 701 | S56: 2252 | U56: 2820 | V56: 3459 | W56: 568 | X56: -82607 | Y56: 639 | Z56: 1908 | AC56: -54 | AD56: 3405 | AF56: -86012 | AG56: -82607 | AH56: -152652 | AI56: -238718 | AJ56: -235259 | AL56: -157969 | AM56: -393228 | AQ56: -152524 | AR56: -545752 | AX56: =טבלה5[[#This Row],[עמודה4]]/1000 -> -701.518 | AY56: =טבלה5[[#This Row],[עמודה4]]/1000 -> -701.518
A57: =VLOOKUP(H57,Index!A:B,2,0) -> Exchange difference rate | B57: =טבלה5[[#This Row],[עמודה4]]-AR57 -> 204862 | D57: =טבלה5[[#This Row],[עמודה4]]-AJ57 -> -349480 | F57: =-SUMIF(SAP!A:A,H57,SAP!F:F) -> 326537 | G57: 12329 | H57: 7901 | J57: 9220 | L57: -49133 | M57: -39913 | O57: -143854 | P57: 542719 | R57: 264842 | S57: 81075 | U57: 95208 | V57: 542719 | W57: 14133 | X57: 26481 | Y57: 447511 | Z57: 726486 | AC57: -364630 | AD57: 178089 | AF57: -151608 | AG57: 26481 | AH57: 649536 | AI57: 133298 | AJ57: 676017 | AL57: -74730 | AM57: 601287 | AQ57: -479612 | AR57: 121675 | AX57: =טבלה5[[#This Row],[עמודה4]]/1000 -> 326.537 | AY57: =טבלה5[[#This Row],[עמודה4]]/1000 -> 326.537
A58: =VLOOKUP(H58,Index!A:B,2,0) -> Interest to (from) authorities | B58: =טבלה5[[#This Row],[עמודה4]]-X58 -> 5288 | D58: =טבלה5[[#This Row],[עמודה4]]-AJ58 -> 5288 | F58: =-SUMIF(SAP!A:A,H58,SAP!F:F) -> 5288 | G58: -440 | H58: 7903 | J58: 0 | L58: 0 | M58: 0 | O58: 0 | P58: 0 | R58: 0 | S58: 0 | U58: 0 | V58: 0 | W58: 0 | X58: 0 | Y58: 0 | Z58: 0 | AC58: 0 | AD58: 0 | AF58: 0 | AG58: 0 | AH58: 0 | AI58: 0 | AJ58: 0 | AL58: 0 | AM58: 0 | AQ58: 0 | AR58: 0 | AX58: =טבלה5[[#This Row],[עמודה4]]/1000 -> 5.288 | AY58: =טבלה5[[#This Row],[עמודה4]]/1000 -> 5.288
B59: =SUM(B56:B58) -> 54384 | C59: =SUM(C56:C58) -> 0 | D59: =SUM(D56:D58) -> -810451 | E59: =SUM(E56:E58) -> 0 | F59: =SUM(F56:F58) -> -369693 | G59: =SUM(G56:G58) -> 18173 | J59: 9761 | L59: -48730 | M59: -38969 | O59: -143247 | P59: 546178 | R59: 265543 | S59: 83327 | U59: 98028 | V59: 546178 | W59: 14701 | X59: -56126 | Y59: 448150 | Z59: 728394 | AC59: -364684 | AD59: 181494 | AF59: -237620 | AG59: -56126 | AH59: 496884 | AI59: -105420 | AJ59: 440758 | AL59: -232699 | AM59: 208059 | AQ59: -632136 | AR59: -424077 | AX59: =טבלה5[[#This Row],[עמודה4]]/1000 -> -369.693 | AY59: =טבלה5[[#This Row],[עמודה4]]/1000 -> -369.693
B60: =B59-'P&L'!D25 -> 0 | D60: =D59-'P&L'!F25 -> 0 | F60: =F59-'P&L'!H25 -> 0 | G60: =G59-'P&L'!I25 -> 0 | P60: 0 | S60: 0 | U60: 0 | V60: 0 | W60: 0 | X60: 0 | Y60: 0 | Z60: 0 | AC60: 0 | AD60: 0 | AF60: 0 | AG60: 0 | AH60: 0 | AI60: 0 | AJ60: 0 | AL60: 0 | AM60: 0 | AQ60: 0 | AR60: 0 | AX60: =טבלה5[[#This Row],[עמודה4]]/1000 -> 0 | AY60: =טבלה5[[#This Row],[עמודה4]]/1000 -> 0
AX61: =טבלה5[[#This Row],[עמודה4]]/1000 -> 0 | AY61: =טבלה5[[#This Row],[עמודה4]]/1000 -> 0
AX62: =טבלה5[[#This Row],[עמודה4]]/1000 -> 0 | AY62: =טבלה5[[#This Row],[עמודה4]]/1000 -> 0
AX63: =טבלה5[[#This Row],[עמודה4]]/1000 -> 0 | AY63: =טבלה5[[#This Row],[עמודה4]]/1000 -> 0
AX64: =טבלה5[[#This Row],[עמודה4]]/1000 -> 0 | AY64: =טבלה5[[#This Row],[עמודה4]]/1000 -> 0
AX65: =טבלה5[[#This Row],[עמודה4]]/1000 -> 0 | AY65: =טבלה5[[#This Row],[עמודה4]]/1000 -> 0
AX66: =טבלה5[[#This Row],[עמודה4]]/1000 -> 0 | AY66: =טבלה5[[#This Row],[עמודה4]]/1000 -> 0
AX67: =טבלה5[[#This Row],[עמודה4]]/1000 -> 0 | AY67: =טבלה5[[#This Row],[עמודה4]]/1000 -> 0
AX68: =טבלה5[[#This Row],[עמודה4]]/1000 -> 0 | AY68: =טבלה5[[#This Row],[עמודה4]]/1000 -> 0
AX69: =טבלה5[[#This Row],[עמודה4]]/1000 -> 0 | AY69: =טבלה5[[#This Row],[עמודה4]]/1000 -> 0
AX70: =טבלה5[[#This Row],[עמודה4]]/1000 -> #VALUE! | AY70: =טבלה5[[#This Row],[עמודה4]]/1000 -> #VALUE!
AX71: =טבלה5[[#This Row],[עמודה4]]/1000 -> #VALUE! | AY71: =טבלה5[[#This Row],[עמודה4]]/1000 -> #VALUE!
AX72: =טבלה5[[#This Row],[עמודה4]]/1000 -> #VALUE! | AY72: =טבלה5[[#This Row],[עמודה4]]/1000 -> #VALUE!
... AX89: =טבלה5[[#This Row],[עמודה4]]/1000 -> #VALUE! | AY89: =טבלה5[[#This Row],[עמודה4]]/1000 -> #VALUE!

Sheet Equity
I4: Evigilo
D6: Retained Earning
K8: LTD
K9: December 31, 2015
K10: $
D11: Stockholders' Equity | E11: Number of ordinary shares | F11: Number of series A-1 preferred shares | G11: Number of series A-2 preferred shares | H11: Number of series A-3 preferred shares | I11: Number of series B preferred shares | J11: Number of series C preferred shares | K11: Share capital | L11: Receivables on account of shares | M11: Additional paid in capital | N11: Accumulated deficit | O11: Total
D12: Opening balance | E12: 1000000 | F12: 6621798 | G12: 6709427 | H12: 155848 | I12: 5437857 | J12: 82347724 | K12: 255005.08 | L12: -26 | M12: 6579304.9 | N12: -6878314.8 | O12: -44030.808
D13: Conversion of convertible loan
D14: Investment
D15: Issuance of anti-dilution shares | F15: =6621798-F12 -> 0
D16: Share based payment
D17: profit for the year
D19: Total Stockholders' Equity | E19: =SUM(E12:E18) -> 1000000 | F19: =SUM(F12:F18) -> 6621798 | G19: =SUM(G12:G18) -> 6709427 | H19: =SUM(H12:H18) -> 155848 | I19: =SUM(I12:I18) -> 5437857 | J19: =SUM(J12:J18) -> 82347724 | K19: =SUM(K12:K18) -> 255005.08 | L19: =SUM(L12:L18) -> -26 | ... O19: =SUM(O12:O18) -> -44030.808
O21: =O19-[83]CONSBS!G44 -> -3.45
K23: ₪
D24: Stockholders' Equity | E24: Number of ordinary shares | F24: Number of series A-1 preferred shares | G24: Number of series A-2 preferred shares | H24: Number of series A-3 preferred shares | I24: Number of series B preferred shares | J24: Number of series C preferred shares | K24: Share capital | L24: Receivables on account of shares | M24: Additional paid in capital | N24: Accumulated deficit | O24: Total
D25: Opening balance | E25: 1000000 | F25: 6621798 | G25: 6709427 | H25: 155848 | I25: 5437857 | J25: 82347724 | K25: 990813 | L25: -100 | M25: 24181105 | N25: -25194620 | O25: -22802
D26: Conversion of convertible loan
D27: Investment
D28: Issuance of anti-dilution shares | F28: =6621798-F25 -> 0
D29: Share based payment | M29: 9751 | O29: =SUM(K29:N29) -> 9751
D30: profit for the year | N30: ='P&L'!#REF! -> #REF! | O30: =SUM(K30:N30) -> #REF!
O31: =SUM(K31:N31) -> 0
D32: Total Stockholders' Equity | E32: =SUM(E25:E31) -> 1000000 | F32: =SUM(F25:F31) -> 6621798 | G32: =SUM(G25:G31) -> 6709427 | H32: =SUM(H25:H31) -> 155848 | I32: =SUM(I25:I31) -> 5437857 | J32: =SUM(J25:J31) -> 82347724 | K32: =SUM(K25:K31) -> 990813 | L32: =SUM(L25:L31) -> -100 | ... O32: =SUM(O25:O31) -> #REF!
K34: =K32-BS!#REF! -> #REF! | M34: =Equity!M32+Equity!L32-BS!#REF! -> #REF! | O34: =O32-BS!#REF! -> #REF!

Sheet SAP
A1: קוד 4 ספרות | C1: LTD $ | D1: GMBH $ | E1: פקודות נוספות $ (-) חובה | F1: יתרה $ | G1: פקודות נוספות ש"ח (-) חובה | H1: יתרה ישראל - ₪ | I1: קוד 3 ספרות | J1: קוד 2 ספרות | K1: שער | L1: שער | M1: Details
A2: 1302 | B2: =VLOOKUP(A2,Index!A:B,2,0) -> Israeli currency | C2: =SUMIF('SAP DRAFT'!B:B,A2,'SAP DRAFT'!D:D) -> -12486866 | D2: =SUMIF('SAP DRAFT'!B:B,A2,'SAP DRAFT'!F:F) -> 0 | E2: =SUMIF(AE!$B$1:$B$1009,A2,AE!$E$1:$E$1009)-SUMIF(AE!$B$1:$B$1009,A2,AE!$D$1:$D$1009) -> 0 | F2: =ROUND(E2+C2+D2,0) -> -12486866 | G2: =SUMIF(AE!$B$1:$B$1009,#REF!,AE!$G$1:$G$1009)-SUMIF(AE!$B$1:$B$1009,#REF!,AE!$F$1:$F$1009) -> 0 | H2: =ROUND(G2+#REF!,0) -> #REF! | I2: =LEFT(A2,3) -> 130 | J2: =LEFT(A2,2) -> 13 | K2: =+#REF!/C2 -> #REF! | L2: =+H2/F2 -> #REF! | M2: תואם לריכוז יתרות 30.06.19 | N2: =VLOOKUP(A2,'SAP DRAFT'!A:B,1,0) -> #N/A
A3: 1304 | B3: =VLOOKUP(A3,Index!A:B,2,0) -> USD currency | C3: =SUMIF('SAP DRAFT'!B:B,A3,'SAP DRAFT'!D:D) -> -8290712 | D3: =SUMIF('SAP DRAFT'!B:B,A3,'SAP DRAFT'!F:F) -> 0 | E3: =SUMIF(AE!$B$1:$B$1009,A3,AE!$E$1:$E$1009)-SUMIF(AE!$B$1:$B$1009,A3,AE!$D$1:$D$1009) -> 0 | F3: =ROUND(E3+C3+D3,0) -> -8290712 | G3: =SUMIF(AE!$B$1:$B$1009,#REF!,AE!$G$1:$G$1009)-SUMIF(AE!$B$1:$B$1009,#REF!,AE!$F$1:$F$1009) -> 0 | H3: =ROUND(G3+#REF!,0) -> #REF! | I3: =LEFT(A3,3) -> 130 | J3: =LEFT(A3,2) -> 13 | K3: =+#REF!/C3 -> #REF! | L3: =+H3/F3 -> #REF! | M3: תואם לריכוז יתרות 30.06.19 | N3: =VLOOKUP(A3,'SAP DRAFT'!A:B,1,0) -> #N/A
A4: 1307 | B4: =VLOOKUP(A4,Index!A:B,2,0) -> EURO currency | C4: =SUMIF('SAP DRAFT'!B:B,A4,'SAP DRAFT'!D:D) -> 0 | D4: =SUMIF('SAP DRAFT'!B:B,A4,'SAP DRAFT'!F:F) -> -2198.2832 | E4: =SUMIF(AE!$B$1:$B$1009,A4,AE!$E$1:$E$1009)-SUMIF(AE!$B$1:$B$1009,A4,AE!$D$1:$D$1009) -> 0 | F4: =ROUND(E4+C4+D4,0) -> -2198 | G4: =SUMIF(AE!$B$1:$B$1009,#REF!,AE!$G$1:$G$1009)-SUMIF(AE!$B$1:$B$1009,#REF!,AE!$F$1:$F$1009) -> 0 | H4: =ROUND(G4+#REF!,0) -> #REF! | I4: =LEFT(A4,3) -> 130 | J4: =LEFT(A4,2) -> 13 | N4: =VLOOKUP(A4,'SAP DRAFT'!A:B,1,0) -> #N/A
A5: 1330 | B5: =VLOOKUP(A5,Index!A:B,2,0) -> Short term deposit | C5: =SUMIF('SAP DRAFT'!B:B,A5,'SAP DRAFT'!D:D) -> -40710444 | D5: =SUMIF('SAP DRAFT'!B:B,A5,'SAP DRAFT'!F:F) -> 0 | E5: =SUMIF(AE!$B$1:$B$1009,A5,AE!$E$1:$E$1009)-SUMIF(AE!$B$1:$B$1009,A5,AE!$D$1:$D$1009) -> 0 | F5: =ROUND(E5+C5+D5,0) -> -40710444 | I5: =LEFT(A5,3) -> 133 | J5: =LEFT(A5,2) -> 13
A6: 1351 | B6: =VLOOKUP(A6,Index!A:B,2,0) -> Related company | C6: =SUMIF('SAP DRAFT'!B:B,A6,'SAP DRAFT'!D:D) -> 0 | D6: =SUMIF('SAP DRAFT'!B:B,A6,'SAP DRAFT'!F:F) -> -238143.08 | E6: =SUMIF(AE!$B$1:$B$1009,A6,AE!$E$1:$E$1009)-SUMIF(AE!$B$1:$B$1009,A6,AE!$D$1:$D$1009) -> 238143.08 | F6: =ROUND(E6+C6+D6,0) -> 0 | G6: =SUMIF(AE!$B$1:$B$1009,#REF!,AE!$G$1:$G$1009)-SUMIF(AE!$B$1:$B$1009,#REF!,AE!$F$1:$F$1009) -> 0 | H6: =ROUND(G6+#REF!,0) -> #REF! | I6: =LEFT(A6,3) -> 135 | J6: =LEFT(A6,2) -> 13 | N6: =VLOOKUP(A6,'SAP DRAFT'!A:B,1,0) -> #N/A
A7: 1354 | B7: =VLOOKUP(A7,Index!A:B,2,0) -> Prepaid expenses | C7: =SUMIF('SAP DRAFT'!B:B,A7,'SAP DRAFT'!D:D) -> -128703 | D7: =SUMIF('SAP DRAFT'!B:B,A7,'SAP DRAFT'!F:F) -> 0 | E7: =SUMIF(AE!$B$1:$B$1009,A7,AE!$E$1:$E$1009)-SUMIF(AE!$B$1:$B$1009,A7,AE!$D$1:$D$1009) -> 1180.7232 | F7: =ROUND(E7+C7+D7,0) -> -127522 | G7: =SUMIF(AE!$B$1:$B$1009,#REF!,AE!$G$1:$G$1009)-SUMIF(AE!$B$1:$B$1009,#REF!,AE!$F$1:$F$1009) -> 0 | H7: =ROUND(G7+#REF!,0) -> #REF! | I7: =LEFT(A7,3) -> 135 | J7: =LEFT(A7,2) -> 13 | K7: =+#REF!/C7 -> #REF! | L7: =+H7/F7 -> #REF! | M7: תואם לנייר עבודה Q2 2019 | N7: =VLOOKUP(A7,'SAP DRAFT'!A:B,1,0) -> #N/A
A8: 1355 | B8: =VLOOKUP(A8,Index!A:B,2,0) -> Guaranty deposits | C8: =SUMIF('SAP DRAFT'!B:B,A8,'SAP DRAFT'!D:D) -> -22131 | D8: =SUMIF('SAP DRAFT'!B:B,A8,'SAP DRAFT'!F:F) -> 0 | E8: =SUMIF(AE!$B$1:$B$1009,A8,AE!$E$1:$E$1009)-SUMIF(AE!$B$1:$B$1009,A8,AE!$D$1:$D$1009) -> 0 | F8: =ROUND(E8+C8+D8,0) -> -22131 | G8: =SUMIF(AE!$B$1:$B$1009,#REF!,AE!$G$1:$G$1009)-SUMIF(AE!$B$1:$B$1009,#REF!,AE!$F$1:$F$1009) -> 0 | H8: =ROUND(G8+#REF!,0) -> #REF! | I8: =LEFT(A8,3) -> 135 | J8: =LEFT(A8,2) -> 13 | K8: =+#REF!/C8 -> #REF! | L8: =+H8/F8 -> #REF! | M8: ללא שינוי משנה קודמת. לקבל בסוף שנה אישור מהספק | N8: =VLOOKUP(A8,'SAP DRAFT'!A:B,1,0) -> #N/A
A9: 1356 | B9: =VLOOKUP(A9,Index!A:B,2,0) -> Income tax | C9: =SUMIF('SAP DRAFT'!B:B,A9,'SAP DRAFT'!D:D) -> 0 | D9: =SUMIF('SAP DRAFT'!B:B,A9,'SAP DRAFT'!F:F) -> 0 | E9: =SUMIF(AE!$B$1:$B$1009,A9,AE!$E$1:$E$1009)-SUMIF(AE!$B$1:$B$1009,A9,AE!$D$1:$D$1009) -> 0 | F9: =ROUND(E9+C9+D9,0) -> 0 | G9: =SUMIF(AE!$B$1:$B$1009,#REF!,AE!$G$1:$G$1009)-SUMIF(AE!$B$1:$B$1009,#REF!,AE!$F$1:$F$1009) -> 0 | H9: =ROUND(G9+#REF!,0) -> #REF! | I9: =LEFT(A9,3) -> 135 | J9: =LEFT(A9,2) -> 13 | K9: =+#REF!/C9 -> #REF! | L9: =+H9/F9 -> #REF! | M9: מקדמות בגין עודפות 2017. לסגור מול הפרשה בסוף שנה | N9: =VLOOKUP(A9,'SAP DRAFT'!A:B,1,0) -> #N/A
A10: 1357 | B10: =VLOOKUP(A10,Index!A:B,2,0) -> VAT | C10: =SUMIF('SAP DRAFT'!B:B,A10,'SAP DRAFT'!D:D) -> -50267 | D10: =SUMIF('SAP DRAFT'!B:B,A10,'SAP DRAFT'!F:F) -> -5458.0524 | E10: =SUMIF(AE!$B$1:$B$1009,A10,AE!$E$1:$E$1009)-SUMIF(AE!$B$1:$B$1009,A10,AE!$D$1:$D$1009) -> 0 | F10: =ROUND(E10+C10+D10,0) -> -55725 | G10: =SUMIF(AE!$B$1:$B$1009,#REF!,AE!$G$1:$G$1009)-SUMIF(AE!$B$1:$B$1009,#REF!,AE!$F$1:$F$1009) -> 0 | H10: =ROUND(G10+#REF!,0) -> #REF! | I10: =LEFT(A10,3) -> 135 | J10: =LEFT(A10,2) -> 13 | K10: =+#REF!/C10 -> #REF! | L10: =+H10/F10 -> #REF! | M10: תשומות בגין 5-6.2019. טרם הועברה פקודת מע"מ | N10: =VLOOKUP(A10,'SAP DRAFT'!A:B,1,0) -> #N/A
A11: 1358 | B11: =VLOOKUP(A11,Index!A:B,2,0) -> Other | C11: =SUMIF('SAP DRAFT'!B:B,A11,'SAP DRAFT'!D:D) -> -3552 | D11: =SUMIF('SAP DRAFT'!B:B,A11,'SAP DRAFT'!F:F) -> 0 | E11: =SUMIF(AE!$B$1:$B$1009,A11,AE!$E$1:$E$1009)-SUMIF(AE!$B$1:$B$1009,A11,AE!$D$1:$D$1009) -> 0 | F11: =ROUND(E11+C11+D11,0) -> -3552 | G11: =SUMIF(AE!$B$1:$B$1009,#REF!,AE!$G$1:$G$1009)-SUMIF(AE!$B$1:$B$1009,#REF!,AE!$F$1:$F$1009) -> 0 | H11: =ROUND(G11+#REF!,0) -> #REF! | I11: =LEFT(A11,3) -> 135 | J11: =LEFT(A11,2) -> 13 | N11: =VLOOKUP(A11,'SAP DRAFT'!A:B,1,0) -> #N/A
A12: 1900 | B12: =VLOOKUP(A12,Index!A:B,2,0) -> Other operating and office equipment | C12: =SUMIF('SAP DRAFT'!B:B,A12,'SAP DRAFT'!D:D) -> 0 | D12: =SUMIF('SAP DRAFT'!B:B,A12,'SAP DRAFT'!F:F) -> 0 | E12: =SUMIF(AE!$B$1:$B$1009,A12,AE!$E$1:$E$1009)-SUMIF(AE!$B$1:$B$1009,A12,AE!$D$1:$D$1009) -> 0 | F12: =ROUND(E12+C12+D12,0) -> 0 | I12: =LEFT(A12,3) -> 190 | J12: =LEFT(A12,2) -> 19 | N12: =VLOOKUP(A12,'SAP DRAFT'!A:B,1,0) -> #N/A
A13: 1901 | B13: =VLOOKUP(A13,Index!A:B,2,0) -> Computers & Software | C13: =SUMIF('SAP DRAFT'!B:B,A13,'SAP DRAFT'!D:D) -> -344827 | D13: =SUMIF('SAP DRAFT'!B:B,A13,'SAP DRAFT'!F:F) -> 0 | E13: =SUMIF(AE!$B$1:$B$1009,A13,AE!$E$1:$E$1009)-SUMIF(AE!$B$1:$B$1009,A13,AE!$D$1:$D$1009) -> 0 | F13: =ROUND(E13+C13+D13,0) -> -344827 | G13: =SUMIF(AE!$B$1:$B$1009,#REF!,AE!$G$1:$G$1009)-SUMIF(AE!$B$1:$B$1009,#REF!,AE!$F$1:$F$1009) -> 0 | H13: =ROUND(G13+#REF!,0) -> #REF! | I13: =LEFT(A13,3) -> 190 | J13: =LEFT(A13,2) -> 19 | K13: =+#REF!/C13 -> #REF! | L13: =+H13/F13 -> #REF! | N13: =VLOOKUP(A13,'SAP DRAFT'!A:B,1,0) -> #N/A
A14: 1903 | B14: =VLOOKUP(A14,Index!A:B,2,0) -> Furniture & Fixtures General | C14: =SUMIF('SAP DRAFT'!B:B,A14,'SAP DRAFT'!D:D) -> -17471 | D14: =SUMIF('SAP DRAFT'!B:B,A14,'SAP DRAFT'!F:F) -> 0 | E14: =SUMIF(AE!$B$1:$B$1009,A14,AE!$E$1:$E$1009)-SUMIF(AE!$B$1:$B$1009,A14,AE!$D$1:$D$1009) -> 0 | F14: =ROUND(E14+C14+D14,0) -> -17471 | G14: =SUMIF(AE!$B$1:$B$1009,#REF!,AE!$G$1:$G$1009)-SUMIF(AE!$B$1:$B$1009,#REF!,AE!$F$1:$F$1009) -> 0 | H14: =ROUND(G14+#REF!,0) -> #REF! | I14: =LEFT(A14,3) -> 190 | J14: =LEFT(A14,2) -> 19
A15: 1904 | B15: =VLOOKUP(A15,Index!A:B,2,0) -> Electronic equipment | C15: =SUMIF('SAP DRAFT'!B:B,A15,'SAP DRAFT'!D:D) -> -24543 | D15: =SUMIF('SAP DRAFT'!B:B,A15,'SAP DRAFT'!F:F) -> -1.0664962 | E15: =SUMIF(AE!$B$1:$B$1009,A15,AE!$E$1:$E$1009)-SUMIF(AE!$B$1:$B$1009,A15,AE!$D$1:$D$1009) -> 0 | F15: =ROUND(E15+C15+D15,0) -> -24544 | G15: =SUMIF(AE!$B$1:$B$1009,#REF!,AE!$G$1:$G$1009)-SUMIF(AE!$B$1:$B$1009,#REF!,AE!$F$1:$F$1009) -> 0 | H15: =ROUND(G15+#REF!,0) -> #REF! | I15: =LEFT(A15,3) -> 190 | J15: =LEFT(A15,2) -> 19 | K15: =+#REF!/C15 -> #REF! | L15: =+H15/F15 -> #REF! | M15: תואם לטופס פחת 30.06.19 | N15: =VLOOKUP(A15,'SAP DRAFT'!A:B,1,0) -> #N/A
A16: 1910 | B16: =VLOOKUP(A16,Index!A:B,2,0) -> Accumulated depreciation | C16: =SUMIF('SAP DRAFT'!B:B,A16,'SAP DRAFT'!D:D) -> 211237 | D16: =SUMIF('SAP DRAFT'!B:B,A16,'SAP DRAFT'!F:F) -> 0 | E16: =SUMIF(AE!$B$1:$B$1009,A16,AE!$E$1:$E$1009)-SUMIF(AE!$B$1:$B$1009,A16,AE!$D$1:$D$1009) -> 0 | F16: =ROUND(E16+C16+D16,0) -> 211237 | G16: =SUMIF(AE!$B$1:$B$1009,#REF!,AE!$G$1:$G$1009)-SUMIF(AE!$B$1:$B$1009,#REF!,AE!$F$1:$F$1009) -> 0 | H16: =ROUND(G16+#REF!,0) -> #REF! | I16: =LEFT(A16,3) -> 191 | J16: =LEFT(A16,2) -> 19 | K16: =+#REF!/C16 -> #REF! | L16: =+H16/F16 -> #REF! | N16: =VLOOKUP(A16,'SAP DRAFT'!A:B,1,0) -> #N/A
A17: 7052 | B17: =VLOOKUP(A17,Index!A:B,2,0) -> Depreciation | C17: =SUMIF('SAP DRAFT'!B:B,A17,'SAP DRAFT'!D:D) -> -73303 | D17: =SUMIF('SAP DRAFT'!B:B,A17,'SAP DRAFT'!F:F) -> 0 | E17: =SUMIF(AE!$B$1:$B$1009,A17,AE!$E$1:$E$1009)-SUMIF(AE!$B$1:$B$1009,A17,AE!$D$1:$D$1009) -> 0 | F17: =ROUND(E17+C17+D17,0) -> -73303 | G17: =SUMIF(AE!$B$1:$B$1009,#REF!,AE!$G$1:$G$1009)-SUMIF(AE!$B$1:$B$1009,#REF!,AE!$F$1:$F$1009) -> 0 | H17: =ROUND(G17+#REF!,0) -> #REF! | I17: =LEFT(A17,3) -> 705 | J17: =LEFT(A17,2) -> 70 | K17: =+#REF!/C17 -> #REF! | L17: =+H17/F17 -> #REF! | M17: תואם לטופס פחת 30.06.19 | N17: =VLOOKUP(A17,'SAP DRAFT'!A:B,1,0) -> #N/A
A18: 2652 | B18: =VLOOKUP(A18,Index!A:B,2,0) -> Accounts payable | C18: =SUMIF('SAP DRAFT'!B:B,A18,'SAP DRAFT'!D:D) -> 129249 | D18: =SUMIF('SAP DRAFT'!B:B,A18,'SAP DRAFT'!F:F) -> 0 | E18: =SUMIF(AE!$B$1:$B$1009,A18,AE!$E$1:$E$1009)-SUMIF(AE!$B$1:$B$1009,A18,AE!$D$1:$D$1009) -> 0 | F18: =ROUND(E18+C18+D18,0) -> 129249 | G18: =SUMIF(AE!$B$1:$B$1009,#REF!,AE!$G$1:$G$1009)-SUMIF(AE!$B$1:$B$1009,#REF!,AE!$F$1:$F$1009) -> 0 | H18: =ROUND(G18+#REF!,0) -> #REF! | I18: =LEFT(A18,3) -> 265 | J18: =LEFT(A18,2) -> 26 | K18: =+#REF!/C18 -> #REF! | L18: =+H18/F18 -> #REF! | M18: תואם לנייר עבודה Q2 2019 | N18: =VLOOKUP(A18,'SAP DRAFT'!A:B,1,0) -> #N/A
A19: 2658 | B19: =VLOOKUP(A19,Index!A:B,2,0) -> Checks payable | C19: =SUMIF('SAP DRAFT'!B:B,A19,'SAP DRAFT'!D:D) -> 20822 | D19: =SUMIF('SAP DRAFT'!B:B,A19,'SAP DRAFT'!F:F) -> 0 | E19: =SUMIF(AE!$B$1:$B$1009,A19,AE!$E$1:$E$1009)-SUMIF(AE!$B$1:$B$1009,A19,AE!$D$1:$D$1009) -> 0 | F19: =ROUND(E19+C19+D19,0) -> 20822 | G19: =SUMIF(AE!$B$1:$B$1009,#REF!,AE!$G$1:$G$1009)-SUMIF(AE!$B$1:$B$1009,#REF!,AE!$F$1:$F$1009) -> 0 | H19: =ROUND(G19+#REF!,0) -> #REF! | I19: =LEFT(A19,3) -> 265 | J19: =LEFT(A19,2) -> 26 | K19: =+#REF!/C19 -> #REF! | L19: =+H19/F19 -> #REF! | M19: תואם לפירוט כ"א | N19: =VLOOKUP(A19,'SAP DRAFT'!A:B,1,0) -> #N/A
A20: 2681 | B20: =VLOOKUP(A20,Index!A:B,2,0) -> Vacation & Convalescence | C20: =SUMIF('SAP DRAFT'!B:B,A20,'SAP DRAFT'!D:D) -> 379770 | D20: =SUMIF('SAP DRAFT'!B:B,A20,'SAP DRAFT'!F:F) -> 0 | E20: =SUMIF(AE!$B$1:$B$1009,A20,AE!$E$1:$E$1009)-SUMIF(AE!$B$1:$B$1009,A20,AE!$D$1:$D$1009) -> 0 | F20: =ROUND(E20+C20+D20,0) -> 379770 | G20: =SUMIF(AE!$B$1:$B$1009,#REF!,AE!$G$1:$G$1009)-SUMIF(AE!$B$1:$B$1009,#REF!,AE!$F$1:$F$1009) -> 0 | H20: =ROUND(G20+#REF!,0) -> #REF! | I20: =LEFT(A20,3) -> 268 | J20: =LEFT(A20,2) -> 26 | K20: =+#REF!/C20 -> #REF! | L20: =+H20/F20 -> #REF! | M20: תואם לנייר עבודה Q2 2019 | N20: =VLOOKUP(A20,'SAP DRAFT'!A:B,1,0) -> #N/A
A21: 2684 | B21: =VLOOKUP(A21,Index!A:B,2,0) -> Shareholders | C21: =SUMIF('SAP DRAFT'!B:B,A21,'SAP DRAFT'!D:D) -> 0 | D21: =SUMIF('SAP DRAFT'!B:B,A21,'SAP DRAFT'!F:F) -> 0 | E21: =SUMIF(AE!$B$1:$B$1009,A21,AE!$E$1:$E$1009)-SUMIF(AE!$B$1:$B$1009,A21,AE!$D$1:$D$1009) -> 0 | F21: =ROUND(E21+C21+D21,0) -> 0 | G21: =SUMIF(AE!$B$1:$B$1009,#REF!,AE!$G$1:$G$1009)-SUMIF(AE!$B$1:$B$1009,#REF!,AE!$F$1:$F$1009) -> 0 | H21: =ROUND(G21+#REF!,0) -> #REF! | I21: =LEFT(A21,3) -> 268 | J21: =LEFT(A21,2) -> 26 | N21: =VLOOKUP(A21,'SAP DRAFT'!A:B,1,0) -> #N/A
A22: 2685 | B22: =VLOOKUP(A22,Index!A:B,2,0) -> Employees | C22: =SUMIF('SAP DRAFT'!B:B,A22,'SAP DRAFT'!D:D) -> 746112 | D22: =SUMIF('SAP DRAFT'!B:B,A22,'SAP DRAFT'!F:F) -> 7139.4346 | E22: =SUMIF(AE!$B$1:$B$1009,A22,AE!$E$1:$E$1009)-SUMIF(AE!$B$1:$B$1009,A22,AE!$D$1:$D$1009) -> 0 | F22: =ROUND(E22+C22+D22,0) -> 753251 | G22: =SUMIF(AE!$B$1:$B$1009,#REF!,AE!$G$1:$G$1009)-SUMIF(AE!$B$1:$B$1009,#REF!,AE!$F$1:$F$1009) -> 0 | H22: =ROUND(G22+#REF!,0) -> #REF! | I22: =LEFT(A22,3) -> 268 | J22: =LEFT(A22,2) -> 26 | K22: =+#REF!/C22 -> #REF! | L22: =+H22/F22 -> #REF! | M22: בגין שכר 6.19. תואם לפקודת שכר | N22: =VLOOKUP(A22,'SAP DRAFT'!A:B,1,0) -> #N/A
A23: 2686 | B23: =VLOOKUP(A23,Index!A:B,2,0) -> Related company | C23: =SUMIF('SAP DRAFT'!B:B,A23,'SAP DRAFT'!D:D) -> 234727 | D23: =SUMIF('SAP DRAFT'!B:B,A23,'SAP DRAFT'!F:F) -> 0 | E23: =SUMIF(AE!$B$1:$B$1009,A23,AE!$E$1:$E$1009)-SUMIF(AE!$B$1:$B$1009,A23,AE!$D$1:$D$1009) -> -234727 | F23: =ROUND(E23+C23+D23,0) -> 0 | G23: =SUMIF(AE!$B$1:$B$1009,#REF!,AE!$G$1:$G$1009)-SUMIF(AE!$B$1:$B$1009,#REF!,AE!$F$1:$F$1009) -> 0 | H23: =ROUND(G23+#REF!,0) -> #REF! | I23: =LEFT(A23,3) -> 268 | J23: =LEFT(A23,2) -> 26 | N23: =VLOOKUP(A23,'SAP DRAFT'!A:B,1,0) -> #N/A
A24: 2687 | B24: =VLOOKUP(A24,Index!A:B,2,0) -> Expenses Payable | C24: =SUMIF('SAP DRAFT'!B:B,A24,'SAP DRAFT'!D:D) -> 174402 | D24: =SUMIF('SAP DRAFT'!B:B,A24,'SAP DRAFT'!F:F) -> 0 | E24: =SUMIF(AE!$B$1:$B$1009,A24,AE!$E$1:$E$1009)-SUMIF(AE!$B$1:$B$1009,A24,AE!$D$1:$D$1009) -> 0 | F24: =ROUND(E24+C24+D24,0) -> 174402 | G24: =SUMIF(AE!$B$1:$B$1009,#REF!,AE!$G$1:$G$1009)-SUMIF(AE!$B$1:$B$1009,#REF!,AE!$F$1:$F$1009) -> 0 | H24: =ROUND(G24+#REF!,0) -> #REF! | I24: =LEFT(A24,3) -> 268 | J24: =LEFT(A24,2) -> 26 | K24: =+#REF!/C24 -> #REF! | L24: =+H24/F24 -> #REF! | M24: תואם לנייר עבודה Q2 2019 | N24: =VLOOKUP(A24,'SAP DRAFT'!A:B,1,0) -> #N/A
A25: 2688 | B25: =VLOOKUP(A25,Index!A:B,2,0) -> Income tax | C25: =SUMIF('SAP DRAFT'!B:B,A25,'SAP DRAFT'!D:D) -> 0 | D25: =SUMIF('SAP DRAFT'!B:B,A25,'SAP DRAFT'!F:F) -> 11993.411 | E25: =SUMIF(AE!$B$1:$B$1009,A25,AE!$E$1:$E$1009)-SUMIF(AE!$B$1:$B$1009,A25,AE!$D$1:$D$1009) -> 0 | F25: =ROUND(E25+C25+D25,0) -> 11993 | G25: =SUMIF(AE!$B$1:$B$1009,#REF!,AE!$G$1:$G$1009)-SUMIF(AE!$B$1:$B$1009,#REF!,AE!$F$1:$F$1009) -> 0 | H25: =ROUND(G25+#REF!,0) -> #REF! | I25: =LEFT(A25,3) -> 268 | J25: =LEFT(A25,2) -> 26 | N25: =VLOOKUP(A25,'SAP DRAFT'!A:B,1,0) -> #N/A
A26: 2630 | B26: =VLOOKUP(A26,Index!A:B,2,0) -> Current maturities of obligation under capital lease | C26: =SUMIF('SAP DRAFT'!B:B,A26,'SAP DRAFT'!D:D) -> 0 | D26: =SUMIF('SAP DRAFT'!B:B,A26,'SAP DRAFT'!F:F) -> 0 | E26: =SUMIF(AE!$B$1:$B$1009,A26,AE!$E$1:$E$1009)-SUMIF(AE!$B$1:$B$1009,A26,AE!$D$1:$D$1009) -> 149136 | F26: =ROUND(E26+C26+D26,0) -> 149136 | G26: =SUMIF(AE!$B$1:$B$1009,#REF!,AE!$G$1:$G$1009)-SUMIF(AE!$B$1:$B$1009,#REF!,AE!$F$1:$F$1009) -> 0 | H26: =ROUND(G26+#REF!,0) -> #REF! | I26: =LEFT(A26,3) -> 263 | J26: =LEFT(A26,2) -> 26 | N26: =VLOOKUP(A26,'SAP DRAFT'!A:B,1,0) -> #N/A
A27: 3721 | B27: =VLOOKUP(A27,Index!A:B,2,0) -> Share capital | C27: =SUMIF('SAP DRAFT'!B:B,A27,'SAP DRAFT'!D:D) -> 2215 | D27: =SUMIF('SAP DRAFT'!B:B,A27,'SAP DRAFT'!F:F) -> 0 | E27: =SUMIF(AE!$B$1:$B$1009,A27,AE!$E$1:$E$1009)-SUMIF(AE!$B$1:$B$1009,A27,AE!$D$1:$D$1009) -> 0 | F27: =ROUND(E27+C27+D27,0) -> 2215 | G27: =SUMIF(AE!$B$1:$B$1009,#REF!,AE!$G$1:$G$1009)-SUMIF(AE!$B$1:$B$1009,#REF!,AE!$F$1:$F$1009) -> 0 | H27: =ROUND(G27+#REF!,0) -> #REF! | I27: =LEFT(A27,3) -> 372 | J27: =LEFT(A27,2) -> 37 | K27: =+#REF!/C27 -> #REF! | L27: =+H27/F27 -> #REF! | M27: ללא שינוי | N27: =VLOOKUP(A27,'SAP DRAFT'!A:B,1,0) -> #N/A
A28: 3740 | B28: =VLOOKUP(A28,Index!A:B,2,0) -> Warrants premium | C28: =SUMIF('SAP DRAFT'!B:B,A28,'SAP DRAFT'!D:D) -> -577 | D28: =SUMIF('SAP DRAFT'!B:B,A28,'SAP DRAFT'!F:F) -> 0 | E28: =SUMIF(AE!$B$1:$B$1009,A28,AE!$E$1:$E$1009)-SUMIF(AE!$B$1:$B$1009,A28,AE!$D$1:$D$1009) -> 0 | F28: =ROUND(E28+C28+D28,0) -> -577 | G28: =SUMIF(AE!$B$1:$B$1009,#REF!,AE!$G$1:$G$1009)-SUMIF(AE!$B$1:$B$1009,#REF!,AE!$F$1:$F$1009) -> 0 | H28: =ROUND(G28+#REF!,0) -> #REF! | I28: =LEFT(A28,3) -> 374 | J28: =LEFT(A28,2) -> 37 | K28: =+#REF!/C28 -> #REF! | L28: =+H28/F28 -> #REF! | M28: ללא שינוי | N28: =VLOOKUP(A28,'SAP DRAFT'!A:B,1,0) -> #N/A
A29: 3743 | B29: =VLOOKUP(A29,Index!A:B,2,0) -> Additional paid-in capital | C29: =SUMIF('SAP DRAFT'!B:B,A29,'SAP DRAFT'!D:D) -> 97199523 | D29: =SUMIF('SAP DRAFT'!B:B,A29,'SAP DRAFT'!F:F) -> 0 | E29: =SUMIF(AE!$B$1:$B$1009,A29,AE!$E$1:$E$1009)-SUMIF(AE!$B$1:$B$1009,A29,AE!$D$1:$D$1009) -> 0 | F29: =ROUND(E29+C29+D29,0) -> 97199523 | G29: =SUMIF(AE!$B$1:$B$1009,#REF!,AE!$G$1:$G$1009)-SUMIF(AE!$B$1:$B$1009,#REF!,AE!$F$1:$F$1009) -> 0 | H29: =ROUND(G29+#REF!,0) -> #REF! | I29: =LEFT(A29,3) -> 374 | J29: =LEFT(A29,2) -> 37 | K29: =+#REF!/C29 -> #REF! | L29: =+H29/F29 -> #REF! | M29: ללא שינוי | N29: =VLOOKUP(A29,'SAP DRAFT'!A:B,1,0) -> #N/A
A30: 4200 | B30: =VLOOKUP(A30,Index!A:B,2,0) -> Revenues | C30: =SUMIF('SAP DRAFT'!B:B,A30,'SAP DRAFT'!D:D) -> 1219917 | D30: =SUMIF('SAP DRAFT'!B:B,A30,'SAP DRAFT'!F:F) -> 0 | E30: =SUMIF(AE!$B$1:$B$1009,A30,AE!$E$1:$E$1009)-SUMIF(AE!$B$1:$B$1009,A30,AE!$D$1:$D$1009) -> 0 | F30: =ROUND(E30+C30+D30,0) -> 1219917 | G30: =SUMIF(AE!$B$1:$B$1009,#REF!,AE!$G$1:$G$1009)-SUMIF(AE!$B$1:$B$1009,#REF!,AE!$F$1:$F$1009) -> 0 | H30: =ROUND(G30+#REF!,0) -> #REF! | I30: =LEFT(A30,3) -> 420 | J30: =LEFT(A30,2) -> 42 | K30: =+#REF!/C30 -> #REF! | L30: =+H30/F30 -> #REF! | M30: Daimler AG - לקוח 20007 - | N30: =VLOOKUP(A30,'SAP DRAFT'!A:B,1,0) -> #N/A
A31: 7000 | B31: =VLOOKUP(A31,Index!A:B,2,0) -> Salaries and social benefits | C31: =SUMIF('SAP DRAFT'!B:B,A31,'SAP DRAFT'!D:D) -> -7823748 | D31: =SUMIF('SAP DRAFT'!B:B,A31,'SAP DRAFT'!F:F) -> 0 | E31: =SUMIF(AE!$B$1:$B$1009,A31,AE!$E$1:$E$1009)-SUMIF(AE!$B$1:$B$1009,A31,AE!$D$1:$D$1009) -> 0 | F31: =ROUND(E31+C31+D31,0) -> -7823748 | G31: =SUMIF(AE!$B$1:$B$1009,#REF!,AE!$G$1:$G$1009)-SUMIF(AE!$B$1:$B$1009,#REF!,AE!$F$1:$F$1009) -> 0 | H31: =ROUND(G31+#REF!,0) -> #REF! | I31: =LEFT(A31,3) -> 700 | J31: =LEFT(A31,2) -> 70 | K31: =+#REF!/C31 -> #REF! | L31: =+H31/F31 -> #REF! | N31: =VLOOKUP(A31,'SAP DRAFT'!A:B,1,0) -> #N/A
A32: 7001 | B32: =VLOOKUP(A32,Index!A:B,2,0) -> Outsourcing & Consultation | C32: =SUMIF('SAP DRAFT'!B:B,A32,'SAP DRAFT'!D:D) -> -1267597 | D32: =SUMIF('SAP DRAFT'!B:B,A32,'SAP DRAFT'!F:F) -> 0 | E32: =SUMIF(AE!$B$1:$B$1009,A32,AE!$E$1:$E$1009)-SUMIF(AE!$B$1:$B$1009,A32,AE!$D$1:$D$1009) -> 0 | F32: =ROUND(E32+C32+D32,0) -> -1267597 | G32: =SUMIF(AE!$B$1:$B$1009,#REF!,AE!$G$1:$G$1009)-SUMIF(AE!$B$1:$B$1009,#REF!,AE!$F$1:$F$1009) -> 0 | H32: =ROUND(G32+#REF!,0) -> #REF! | I32: =LEFT(A32,3) -> 700 | J32: =LEFT(A32,2) -> 70 | K32: =+#REF!/C32 -> #REF! | L32: =+H32/F32 -> #REF! | N32: =VLOOKUP(A32,'SAP DRAFT'!A:B,1,0) -> 7001
A33: 7002 | B33: =VLOOKUP(A33,Index!A:B,2,0) -> Communication & Computer Maintenance | C33: =SUMIF('SAP DRAFT'!B:B,A33,'SAP DRAFT'!D:D) -> -512228 | D33: =SUMIF('SAP DRAFT'!B:B,A33,'SAP DRAFT'!F:F) -> 0 | E33: =SUMIF(AE!$B$1:$B$1009,A33,AE!$E$1:$E$1009)-SUMIF(AE!$B$1:$B$1009,A33,AE!$D$1:$D$1009) -> 0 | F33: =ROUND(E33+C33+D33,0) -> -512228 | G33: =SUMIF(AE!$B$1:$B$1009,#REF!,AE!$G$1:$G$1009)-SUMIF(AE!$B$1:$B$1009,#REF!,AE!$F$1:$F$1009) -> 0 | H33: =ROUND(G33+#REF!,0) -> #REF! | I33: =LEFT(A33,3) -> 700 | J33: =LEFT(A33,2) -> 70 | K33: =+#REF!/C33 -> #REF! | L33: =+H33/F33 -> #REF! | N33: =VLOOKUP(A33,'SAP DRAFT'!A:B,1,0) -> #N/A
A34: 7007 | B34: =VLOOKUP(A34,Index!A:B,2,0) -> Travel Abroad | C34: =SUMIF('SAP DRAFT'!B:B,A34,'SAP DRAFT'!D:D) -> 0 | D34: =SUMIF('SAP DRAFT'!B:B,A34,'SAP DRAFT'!F:F) -> 0 | E34: =SUMIF(AE!$B$1:$B$1009,A34,AE!$E$1:$E$1009)-SUMIF(AE!$B$1:$B$1009,A34,AE!$D$1:$D$1009) -> 0 | F34: =ROUND(E34+C34+D34,0) -> 0 | G34: =SUMIF(AE!$B$1:$B$1009,#REF!,AE!$G$1:$G$1009)-SUMIF(AE!$B$1:$B$1009,#REF!,AE!$F$1:$F$1009) -> 0 | H34: =ROUND(G34+#REF!,0) -> #REF! | I34: =LEFT(A34,3) -> 700 | J34: =LEFT(A34,2) -> 70 | K34: =+#REF!/C34 -> #REF! | L34: =+H34/F34 -> #REF! | N34: =VLOOKUP(A34,'SAP DRAFT'!A:B,1,0) -> #N/A
A35: 7020 | B35: =VLOOKUP(A35,Index!A:B,2,0) -> Salaries and social benefits | C35: =SUMIF('SAP DRAFT'!B:B,A35,'SAP DRAFT'!D:D) -> -627386 | D35: =SUMIF('SAP DRAFT'!B:B,A35,'SAP DRAFT'!F:F) -> -322091.07 | E35: =SUMIF(AE!$B$1:$B$1009,A35,AE!$E$1:$E$1009)-SUMIF(AE!$B$1:$B$1009,A35,AE!$D$1:$D$1009) -> 309629.81 | F35: =ROUND(E35+C35+D35,0) -> -639847 | G35: =SUMIF(AE!$B$1:$B$1009,#REF!,AE!$G$1:$G$1009)-SUMIF(AE!$B$1:$B$1009,#REF!,AE!$F$1:$F$1009) -> 0 | H35: =ROUND(G35+#REF!,0) -> #REF! | I35: =LEFT(A35,3) -> 702 | J35: =LEFT(A35,2) -> 70 | K35: =+#REF!/C35 -> #REF! | L35: =+H35/F35 -> #REF! | N35: =VLOOKUP(A35,'SAP DRAFT'!A:B,1,0) -> #N/A
A36: 7021 | B36: =VLOOKUP(A36,Index!A:B,2,0) -> Marketing exepences | C36: =SUMIF('SAP DRAFT'!B:B,A36,'SAP DRAFT'!D:D) -> -458598 | D36: =SUMIF('SAP DRAFT'!B:B,A36,'SAP DRAFT'!F:F) -> -12554.995 | E36: =SUMIF(AE!$B$1:$B$1009,A36,AE!$E$1:$E$1009)-SUMIF(AE!$B$1:$B$1009,A36,AE!$D$1:$D$1009) -> 0 | F36: =ROUND(E36+C36+D36,0) -> -471153 | G36: =SUMIF(AE!$B$1:$B$1009,#REF!,AE!$G$1:$G$1009)-SUMIF(AE!$B$1:$B$1009,#REF!,AE!$F$1:$F$1009) -> 0 | H36: =ROUND(G36+#REF!,0) -> #REF! | I36: =LEFT(A36,3) -> 702 | J36: =LEFT(A36,2) -> 70 | K36: =+#REF!/C36 -> #REF! | L36: =+H36/F36 -> #REF! | N36: =VLOOKUP(A36,'SAP DRAFT'!A:B,1,0) -> #N/A
A37: 7022 | B37: =VLOOKUP(A37,Index!A:B,2,0) -> Conference and shows | C37: =SUMIF('SAP DRAFT'!B:B,A37,'SAP DRAFT'!D:D) -> -75712 | D37: =SUMIF('SAP DRAFT'!B:B,A37,'SAP DRAFT'!F:F) -> 0 | E37: =SUMIF(AE!$B$1:$B$1009,A37,AE!$E$1:$E$1009)-SUMIF(AE!$B$1:$B$1009,A37,AE!$D$1:$D$1009) -> 0 | F37: =ROUND(E37+C37+D37,0) -> -75712 | G37: =SUMIF(AE!$B$1:$B$1009,#REF!,AE!$G$1:$G$1009)-SUMIF(AE!$B$1:$B$1009,#REF!,AE!$F$1:$F$1009) -> 0 | H37: =ROUND(G37+#REF!,0) -> #REF! | I37: =LEFT(A37,3) -> 702 | J37: =LEFT(A37,2) -> 70 | K37: =+#REF!/C37 -> #REF! | L37: =+H37/F37 -> #REF! | N37: =VLOOKUP(A37,'SAP DRAFT'!A:B,1,0) -> #N/A
A38: 7023 | B38: =VLOOKUP(A38,Index!A:B,2,0) -> Subcontructors GMBH | C38: =SUMIF('SAP DRAFT'!B:B,A38,'SAP DRAFT'!D:D) -> -466078 | D38: =SUMIF('SAP DRAFT'!B:B,A38,'SAP DRAFT'!F:F) -> 477453.22 | E38: =SUMIF(AE!$B$1:$B$1009,A38,AE!$E$1:$E$1009)-SUMIF(AE!$B$1:$B$1009,A38,AE!$D$1:$D$1009) -> -11375.215 | F38: =ROUND(E38+C38+D38,0) -> 0 | G38: =SUMIF(AE!$B$1:$B$1009,#REF!,AE!$G$1:$G$1009)-SUMIF(AE!$B$1:$B$1009,#REF!,AE!$F$1:$F$1009) -> 0 | H38: =ROUND(G38+#REF!,0) -> #REF! | I38: =LEFT(A38,3) -> 702 | J38: =LEFT(A38,2) -> 70 | N38: =VLOOKUP(A38,'SAP DRAFT'!A:B,1,0) -> #N/A
A39: 7025 | B39: =VLOOKUP(A39,Index!A:B,2,0) -> Travel Abroad | C39: =SUMIF('SAP DRAFT'!B:B,A39,'SAP DRAFT'!D:D) -> 0 | D39: =SUMIF('SAP DRAFT'!B:B,A39,'SAP DRAFT'!F:F) -> -6687.8695 | E39: =SUMIF(AE!$B$1:$B$1009,A39,AE!$E$1:$E$1009)-SUMIF(AE!$B$1:$B$1009,A39,AE!$D$1:$D$1009) -> 0 | F39: =ROUND(E39+C39+D39,0) -> -6688 | G39: =SUMIF(AE!$B$1:$B$1009,#REF!,AE!$G$1:$G$1009)-SUMIF(AE!$B$1:$B$1009,#REF!,AE!$F$1:$F$1009) -> 0 | H39: =ROUND(G39+#REF!,0) -> #REF! | I39: =LEFT(A39,3) -> 702 | J39: =LEFT(A39,2) -> 70 | K39: =+#REF!/C39 -> #REF! | L39: =+H39/F39 -> #REF! | N39: =VLOOKUP(A39,'SAP DRAFT'!A:B,1,0) -> #N/A
A40: 7026 | B40: =VLOOKUP(A40,Index!A:B,2,0) -> Creative & branding | C40: =SUMIF('SAP DRAFT'!B:B,A40,'SAP DRAFT'!D:D) -> -202325 | D40: =SUMIF('SAP DRAFT'!B:B,A40,'SAP DRAFT'!F:F) -> -474.05754 | E40: =SUMIF(AE!$B$1:$B$1009,A40,AE!$E$1:$E$1009)-SUMIF(AE!$B$1:$B$1009,A40,AE!$D$1:$D$1009) -> 0 | F40: =ROUND(E40+C40+D40,0) -> -202799 | G40: =SUMIF(AE!$B$1:$B$1009,#REF!,AE!$G$1:$G$1009)-SUMIF(AE!$B$1:$B$1009,#REF!,AE!$F$1:$F$1009) -> 0 | H40: =ROUND(G40+#REF!,0) -> #REF! | I40: =LEFT(A40,3) -> 702 | J40: =LEFT(A40,2) -> 70 | K40: =+#REF!/C40 -> #REF! | L40: =+H40/F40 -> #REF! | N40: =VLOOKUP(A40,'SAP DRAFT'!A:B,1,0) -> #N/A
A41: 7050 | B41: =VLOOKUP(A41,Index!A:B,2,0) -> Salaries and social benefits | C41: =SUMIF('SAP DRAFT'!B:B,A41,'SAP DRAFT'!D:D) -> -933435 | D41: =SUMIF('SAP DRAFT'!B:B,A41,'SAP DRAFT'!F:F) -> 0 | E41: =SUMIF(AE!$B$1:$B$1009,A41,AE!$E$1:$E$1009)-SUMIF(AE!$B$1:$B$1009,A41,AE!$D$1:$D$1009) -> 0 | F41: =ROUND(E41+C41+D41,0) -> -933435 | G41: =SUMIF(AE!$B$1:$B$1009,#REF!,AE!$G$1:$G$1009)-SUMIF(AE!$B$1:$B$1009,#REF!,AE!$F$1:$F$1009) -> 0 | H41: =ROUND(G41+#REF!,0) -> #REF! | I41: =LEFT(A41,3) -> 705 | J41: =LEFT(A41,2) -> 70 | K41: =+#REF!/C41 -> #REF! | L41: =+H41/F41 -> #REF! | N41: =VLOOKUP(A41,'SAP DRAFT'!A:B,1,0) -> #N/A
A42: 7051 | B42: =VLOOKUP(A42,Index!A:B,2,0) -> Professional services | C42: =SUMIF('SAP DRAFT'!B:B,A42,'SAP DRAFT'!D:D) -> -181013 | D42: =SUMIF('SAP DRAFT'!B:B,A42,'SAP DRAFT'!F:F) -> 0 | E42: =SUMIF(AE!$B$1:$B$1009,A42,AE!$E$1:$E$1009)-SUMIF(AE!$B$1:$B$1009,A42,AE!$D$1:$D$1009) -> 0 | F42: =ROUND(E42+C42+D42,0) -> -181013 | G42: =SUMIF(AE!$B$1:$B$1009,#REF!,AE!$G$1:$G$1009)-SUMIF(AE!$B$1:$B$1009,#REF!,AE!$F$1:$F$1009) -> 0 | H42: =ROUND(G42+#REF!,0) -> #REF! | I42: =LEFT(A42,3) -> 705 | J42: =LEFT(A42,2) -> 70 | K42: =+#REF!/C42 -> #REF! | L42: =+H42/F42 -> #REF! | N42: =VLOOKUP(A42,'SAP DRAFT'!A:B,1,0) -> #N/A
A43: 7054 | B43: =VLOOKUP(A43,Index!A:B,2,0) -> Insurance | C43: =SUMIF('SAP DRAFT'!B:B,A43,'SAP DRAFT'!D:D) -> -17058 | D43: =SUMIF('SAP DRAFT'!B:B,A43,'SAP DRAFT'!F:F) -> -106606.96 | E43: =SUMIF(AE!$B$1:$B$1009,A43,AE!$E$1:$E$1009)-SUMIF(AE!$B$1:$B$1009,A43,AE!$D$1:$D$1009) -> -1180.7232 | F43: =ROUND(E43+C43+D43,0) -> -124846 | G43: =SUMIF(AE!$B$1:$B$1009,#REF!,AE!$G$1:$G$1009)-SUMIF(AE!$B$1:$B$1009,#REF!,AE!$F$1:$F$1009) -> 0 | H43: =ROUND(G43+#REF!,0) -> #REF! | I43: =LEFT(A43,3) -> 705 | J43: =LEFT(A43,2) -> 70 | K43: =+#REF!/C43 -> #REF! | L43: =+H43/F43 -> #REF! | N43: =VLOOKUP(A43,'SAP DRAFT'!A:B,1,0) -> #N/A
A44: 7053 | B44: =VLOOKUP(A44,Index!A:B,2,0) -> Consulting | C44: =SUMIF('SAP DRAFT'!B:B,A44,'SAP DRAFT'!D:D) -> -105442 | D44: =SUMIF('SAP DRAFT'!B:B,A44,'SAP DRAFT'!F:F) -> 0 | E44: =SUMIF(AE!$B$1:$B$1009,A44,AE!$E$1:$E$1009)-SUMIF(AE!$B$1:$B$1009,A44,AE!$D$1:$D$1009) -> 0 | F44: =ROUND(E44+C44+D44,0) -> -105442 | I44: =LEFT(A44,3) -> 705 | J44: =LEFT(A44,2) -> 70
A45: 7055 | B45: =VLOOKUP(A45,Index!A:B,2,0) -> Office Maintenance | C45: =SUMIF('SAP DRAFT'!B:B,A45,'SAP DRAFT'!D:D) -> -331046 | D45: =SUMIF('SAP DRAFT'!B:B,A45,'SAP DRAFT'!F:F) -> 0 | E45: =SUMIF(AE!$B$1:$B$1009,A45,AE!$E$1:$E$1009)-SUMIF(AE!$B$1:$B$1009,A45,AE!$D$1:$D$1009) -> 0 | F45: =ROUND(E45+C45+D45,0) -> -331046 | G45: =SUMIF(AE!$B$1:$B$1009,#REF!,AE!$G$1:$G$1009)-SUMIF(AE!$B$1:$B$1009,#REF!,AE!$F$1:$F$1009) -> 0 | H45: =ROUND(G45+#REF!,0) -> #REF! | I45: =LEFT(A45,3) -> 705 | J45: =LEFT(A45,2) -> 70 | K45: =+#REF!/C45 -> #REF! | L45: =+H45/F45 -> #REF! | M45: גידול בתעריף שכר דירה | N45: =VLOOKUP(A45,'SAP DRAFT'!A:B,1,0) -> #N/A
A46: 7056 | B46: =VLOOKUP(A46,Index!A:B,2,0) -> Vehicle expense | C46: =SUMIF('SAP DRAFT'!B:B,A46,'SAP DRAFT'!D:D) -> -793 | D46: =SUMIF('SAP DRAFT'!B:B,A46,'SAP DRAFT'!F:F) -> 0 | E46: =SUMIF(AE!$B$1:$B$1009,A46,AE!$E$1:$E$1009)-SUMIF(AE!$B$1:$B$1009,A46,AE!$D$1:$D$1009) -> 0 | F46: =ROUND(E46+C46+D46,0) -> -793 | G46: =SUMIF(AE!$B$1:$B$1009,#REF!,AE!$G$1:$G$1009)-SUMIF(AE!$B$1:$B$1009,#REF!,AE!$F$1:$F$1009) -> 0 | H46: =ROUND(G46+#REF!,0) -> #REF! | I46: =LEFT(A46,3) -> 705 | J46: =LEFT(A46,2) -> 70
A47: 7057 | B47: =VLOOKUP(A47,Index!A:B,2,0) -> Travel Abroad | C47: =SUMIF('SAP DRAFT'!B:B,A47,'SAP DRAFT'!D:D) -> -196840 | D47: =SUMIF('SAP DRAFT'!B:B,A47,'SAP DRAFT'!F:F) -> 0 | E47: =SUMIF(AE!$B$1:$B$1009,A47,AE!$E$1:$E$1009)-SUMIF(AE!$B$1:$B$1009,A47,AE!$D$1:$D$1009) -> 0 | F47: =ROUND(E47+C47+D47,0) -> -196840 | G47: =SUMIF(AE!$B$1:$B$1009,#REF!,AE!$G$1:$G$1009)-SUMIF(AE!$B$1:$B$1009,#REF!,AE!$F$1:$F$1009) -> 0 | H47: =ROUND(G47+#REF!,0) -> #REF! | I47: =LEFT(A47,3) -> 705 | J47: =LEFT(A47,2) -> 70 | K47: =+#REF!/C47 -> #REF! | L47: =+H47/F47 -> #REF! | N47: =VLOOKUP(A47,'SAP DRAFT'!A:B,1,0) -> #N/A
A48: 7059 | B48: =VLOOKUP(A48,Index!A:B,2,0) -> Other | C48: =SUMIF('SAP DRAFT'!B:B,A48,'SAP DRAFT'!D:D) -> -239232 | D48: =SUMIF('SAP DRAFT'!B:B,A48,'SAP DRAFT'!F:F) -> 0 | E48: =SUMIF(AE!$B$1:$B$1009,A48,AE!$E$1:$E$1009)-SUMIF(AE!$B$1:$B$1009,A48,AE!$D$1:$D$1009) -> 0 | F48: =ROUND(E48+C48+D48,0) -> -239232 | G48: =SUMIF(AE!$B$1:$B$1009,#REF!,AE!$G$1:$G$1009)-SUMIF(AE!$B$1:$B$1009,#REF!,AE!$F$1:$F$1009) -> 0 | H48: =ROUND(G48+#REF!,0) -> #REF! | I48: =LEFT(A48,3) -> 705 | J48: =LEFT(A48,2) -> 70 | K48: =+#REF!/C48 -> #REF! | L48: =+H48/F48 -> #REF! | N48: =VLOOKUP(A48,'SAP DRAFT'!A:B,1,0) -> #N/A
A49: 7900 | B49: =VLOOKUP(A49,Index!A:B,2,0) -> Bank commission and interest | C49: =SUMIF('SAP DRAFT'!B:B,A49,'SAP DRAFT'!D:D) -> 703418 | D49: =SUMIF('SAP DRAFT'!B:B,A49,'SAP DRAFT'!F:F) -> 0 | E49: =SUMIF(AE!$B$1:$B$1009,A49,AE!$E$1:$E$1009)-SUMIF(AE!$B$1:$B$1009,A49,AE!$D$1:$D$1009) -> -1900 | F49: =ROUND(E49+C49+D49,0) -> 701518 | G49: =SUMIF(AE!$B$1:$B$1009,#REF!,AE!$G$1:$G$1009)-SUMIF(AE!$B$1:$B$1009,#REF!,AE!$F$1:$F$1009) -> 0 | H49: =ROUND(G49+#REF!,0) -> #REF! | I49: =LEFT(A49,3) -> 790 | J49: =LEFT(A49,2) -> 79 | K49: =+#REF!/C49 -> #REF! | L49: =+H49/F49 -> #REF! | N49: =VLOOKUP(A49,'SAP DRAFT'!A:B,1,0) -> #N/A
A50: 7901 | B50: =VLOOKUP(A50,Index!A:B,2,0) -> Exchange difference rate | C50: =SUMIF('SAP DRAFT'!B:B,A50,'SAP DRAFT'!D:D) -> -332555 | D50: =SUMIF('SAP DRAFT'!B:B,A50,'SAP DRAFT'!F:F) -> -3237.8159 | E50: =SUMIF(AE!$B$1:$B$1009,A50,AE!$E$1:$E$1009)-SUMIF(AE!$B$1:$B$1009,A50,AE!$D$1:$D$1009) -> 9256.1357 | F50: =ROUND(E50+C50+D50,0) -> -326537 | G50: =SUMIF(AE!$B$1:$B$1009,#REF!,AE!$G$1:$G$1009)-SUMIF(AE!$B$1:$B$1009,#REF!,AE!$F$1:$F$1009) -> 0 | H50: =ROUND(G50+#REF!,0) -> #REF! | I50: =LEFT(A50,3) -> 790 | J50: =LEFT(A50,2) -> 79 | K50: =+#REF!/C50 -> #REF! | L50: =+H50/F50 -> #REF! | N50: =VLOOKUP(A50,'SAP DRAFT'!A:B,1,0) -> #N/A
A51: 7903 | B51: =VLOOKUP(A51,Index!A:B,2,0) -> Interest to (from) authorities | C51: =SUMIF('SAP DRAFT'!B:B,A51,'SAP DRAFT'!D:D) -> -5288 | D51: =SUMIF('SAP DRAFT'!B:B,A51,'SAP DRAFT'!F:F) -> 0 | E51: =SUMIF(AE!$B$1:$B$1009,A51,AE!$E$1:$E$1009)-SUMIF(AE!$B$1:$B$1009,A51,AE!$D$1:$D$1009) -> 0 | F51: =ROUND(E51+C51+D51,0) -> -5288 | G51: =SUMIF(AE!$B$1:$B$1009,#REF!,AE!$G$1:$G$1009)-SUMIF(AE!$B$1:$B$1009,#REF!,AE!$F$1:$F$1009) -> 0 | H51: =ROUND(G51+#REF!,0) -> #REF! | I51: =LEFT(A51,3) -> 790 | J51: =LEFT(A51,2) -> 79 | K51: =+#REF!/C51 -> #REF! | L51: =+H51/F51 -> #REF! | N51: =VLOOKUP(A51,'SAP DRAFT'!A:B,1,0) -> #N/A
A52: 9410 | B52: =VLOOKUP(A52,Index!A:B,2,0) -> Opening Retained Earnings (Deficit) | C52: =SUMIF('SAP DRAFT'!B:B,A52,'SAP DRAFT'!D:D) -> -22817667 | D52: =SUMIF('SAP DRAFT'!B:B,A52,'SAP DRAFT'!F:F) -> 28059 | E52: =SUMIF(AE!$B$1:$B$1009,A52,AE!$E$1:$E$1009)-SUMIF(AE!$B$1:$B$1009,A52,AE!$D$1:$D$1009) -> -152601 | F52: =ROUND(E52+C52+D52,0) -> -22942209 | G52: =SUMIF(AE!$B$1:$B$1009,#REF!,AE!$G$1:$G$1009)-SUMIF(AE!$B$1:$B$1009,#REF!,AE!$F$1:$F$1009) -> 0 | H52: =ROUND(G52+#REF!,0) -> #REF! | I52: =LEFT(A52,3) -> 941 | J52: =LEFT(A52,2) -> 94 | K52: =+#REF!/C52 -> #REF! | L52: =+H52/F52 -> #REF! | N52: =VLOOKUP(A52,'SAP DRAFT'!A:B,1,0) -> #N/A
A53: 1342 | B53: =VLOOKUP(A53,Index!A:B,2,0) -> Accounts receivable | C53: =SUMIF('SAP DRAFT'!B:B,A53,'SAP DRAFT'!D:D) -> -1269967 | D53: =SUMIF('SAP DRAFT'!B:B,A53,'SAP DRAFT'!F:F) -> 0 | E53: =SUMIF(AE!$B$1:$B$1009,A53,AE!$E$1:$E$1009)-SUMIF(AE!$B$1:$B$1009,A53,AE!$D$1:$D$1009) -> 0 | F53: =ROUND(E53+C53+D53,0) -> -1269967 | G53: =SUMIF(AE!$B$1:$B$1009,#REF!,AE!$G$1:$G$1009)-SUMIF(AE!$B$1:$B$1009,#REF!,AE!$F$1:$F$1009) -> 0 | H53: =ROUND(G53+#REF!,0) -> #REF! | I53: =LEFT(A53,3) -> 134 | J53: =LEFT(A53,2) -> 13 | K53: =+#REF!/C53 -> #REF! | L53: =+H53/F53 -> #REF! | N53: =VLOOKUP(A53,'SAP DRAFT'!A:B,1,0) -> #N/A
A54: 1842 | B54: =VLOOKUP(A54,Index!A:B,2,0) -> Investment in subsidiary | C54: =SUMIF('SAP DRAFT'!B:B,A54,'SAP DRAFT'!D:D) -> -28054 | D54: =SUMIF('SAP DRAFT'!B:B,A54,'SAP DRAFT'!F:F) -> 183001.81 | E54: =SUMIF(AE!$B$1:$B$1009,A54,AE!$E$1:$E$1009)-SUMIF(AE!$B$1:$B$1009,A54,AE!$D$1:$D$1009) -> -154947.81 | F54: =ROUND(E54+C54+D54,0) -> 0 | G54: =SUMIF(AE!$B$1:$B$1009,#REF!,AE!$G$1:$G$1009)-SUMIF(AE!$B$1:$B$1009,#REF!,AE!$F$1:$F$1009) -> 0 | H54: =ROUND(G54+#REF!,0) -> #REF! | I54: =LEFT(A54,3) -> 184 | J54: =LEFT(A54,2) -> 18 | K54: =+#REF!/C54 -> #REF! | L54: =+H54/F54 -> #REF! | N54: =VLOOKUP(A54,'SAP DRAFT'!A:B,1,0) -> #N/A
A55: 7028 | B55: =VLOOKUP(A55,Index!A:B,2,0) -> Other expenses | C55: =SUMIF('SAP DRAFT'!B:B,A55,'SAP DRAFT'!D:D) -> 0 | D55: =SUMIF('SAP DRAFT'!B:B,A55,'SAP DRAFT'!F:F) -> -10193.632 | E55: =SUMIF(AE!$B$1:$B$1009,A55,AE!$E$1:$E$1009)-SUMIF(AE!$B$1:$B$1009,A55,AE!$D$1:$D$1009) -> 0 | F55: =ROUND(E55+C55+D55,0) -> -10194 | G55: =SUMIF(AE!$B$1:$B$1009,#REF!,AE!$G$1:$G$1009)-SUMIF(AE!$B$1:$B$1009,#REF!,AE!$F$1:$F$1009) -> 0 | H55: =ROUND(G55+#REF!,0) -> #REF! | I55: =LEFT(A55,3) -> 702 | J55: =LEFT(A55,2) -> 70 | N55: =VLOOKUP(A55,'SAP DRAFT'!A:B,1,0) -> #N/A
A56: 8015 | B56: =VLOOKUP(A56,Index!A:B,2,0) -> Revenue from the sale of fixed assets | C56: =SUMIF('SAP DRAFT'!B:B,A56,'SAP DRAFT'!D:D) -> 0 | D56: =SUMIF('SAP DRAFT'!B:B,A56,'SAP DRAFT'!F:F) -> 0 | E56: =SUMIF(AE!$B$1:$B$1009,A56,AE!$E$1:$E$1009)-SUMIF(AE!$B$1:$B$1009,A56,AE!$D$1:$D$1009) -> 0 | F56: =ROUND(E56+C56+D56,0) -> 0 | I56: =LEFT(A56,3) -> 801 | J56: =LEFT(A56,2) -> 80
A57: 4720 | B57: Reclassification of R&D expenses | C57: =SUMIF('SAP DRAFT'!B:B,A57,'SAP DRAFT'!D:D) -> -975934 | D57: =SUMIF('SAP DRAFT'!B:B,A57,'SAP DRAFT'!F:F) -> 0 | E57: =SUMIF(AE!$B$1:$B$1009,A57,AE!$E$1:$E$1009)-SUMIF(AE!$B$1:$B$1009,A57,AE!$D$1:$D$1009) -> 0 | F57: =ROUND(E57+C57+D57,0) -> -975934 | I57: =LEFT(A57,3) -> 472 | J57: =LEFT(A57,2) -> 47
A58: 3010 | B58: =VLOOKUP(A58,Index!A:B,2,0) -> Long Term Lease | D58: =SUMIF('SAP DRAFT'!B:B,A58,'SAP DRAFT'!F:F) -> 0 | E58: =SUMIF(AE!$B$1:$B$1009,A58,AE!$E$1:$E$1009)-SUMIF(AE!$B$1:$B$1009,A58,AE!$D$1:$D$1009) -> 75354.055 | F58: =ROUND(E58+C58+D58,0) -> 75354 | I58: =LEFT(A58,3) -> 301 | J58: =LEFT(A58,2) -> 30
A59: 1410 | B59: =VLOOKUP(A59,Index!A:B,2,0) -> Leased property under capital lease, net | D59: =SUMIF('SAP DRAFT'!B:B,A59,'SAP DRAFT'!F:F) -> 0 | E59: =SUMIF(AE!$B$1:$B$1009,A59,AE!$E$1:$E$1009)-SUMIF(AE!$B$1:$B$1009,A59,AE!$D$1:$D$1009) -> -225967.05 | F59: =ROUND(E59+C59+D59,0) -> -225967 | I59: =LEFT(A59,3) -> 141 | J59: =LEFT(A59,2) -> 14
E60: =SUMIF(AE!$B$1:$B$1009,A60,AE!$E$1:$E$1009)-SUMIF(AE!$B$1:$B$1009,A60,AE!$D$1:$D$1009) -> 0 | F60: =ROUND(E60+C60+D60,0) -> 0 | I60: =LEFT(A60,3) | J60: =LEFT(A60,2)
E61: =SUMIF(AE!$B$1:$B$1009,A61,AE!$E$1:$E$1009)-SUMIF(AE!$B$1:$B$1009,A61,AE!$D$1:$D$1009) -> 0 | F61: =ROUND(E61+C61+D61,0) -> 0 | I61: =LEFT(A61,3) | J61: =LEFT(A61,2)
C65: =SUM(C2:C57) -> 0 | D65: =SUM(D2:D62) -> 0.00015089514 | E65: =SUM(E2:E62) -> 1 | F65: =SUM(F2:F62) -> 0 | G65: =SUM(G2:G55) -> 0 | H65: =SUM(H2:H55) -> #REF!
C66: .

Sheet SAP DRAFT
A1: קוד 4 ספרות | B1: קוד חשבון | D1: LTD $ | E1: יתרה ישראל - ₪ | F1: GMBH $ | G1: פקודות נוספות $ (-) חובה | H1: יתרה $ | I1: פקודות נוספות ש"ח (-) חובה | J1: יתרה ישראל - ₪ | K1: קוד 3 ספרות | L1: קוד 2 ספרות | M1: שער | N1: שער | O1: Details
A2: 1100 | B2: 1302 | C2: Bank Hapoalim NIS | D2: -12486866 | E2: -43941283 | H2: =ROUND(G2+D2+F2,0) -> -12486866 | I2: =SUMIF(AE!$B$1:$B$1009,B2,AE!$G$1:$G$1009)-SUMIF(AE!$B$1:$B$1009,B2,AE!$F$1:$F$1009) -> 0 | J2: =ROUND(I2+E2,0) -> -43941283 | K2: =LEFT(B2,3) -> 130 | L2: =LEFT(B2,2) -> 13 | M2: =+E2/D2 -> 3.5190001 | N2: =+J2/H2 -> 3.5190001 | O2: תואם לריכוז יתרות 30.06.19 | P2: =VLOOKUP(B2,SAP!A:A,1,0) -> 1302
A3: 1101 | B3: 1304 | C3: Bank Hapoalim $ | D3: -8290314 | E3: -29173614 | H3: =ROUND(G3+D3+F3,0) -> -8290314 | I3: =SUMIF(AE!$B$1:$B$1009,B3,AE!$G$1:$G$1009)-SUMIF(AE!$B$1:$B$1009,B3,AE!$F$1:$F$1009) -> 0 | J3: =ROUND(I3+E3,0) -> -29173614 | K3: =LEFT(B3,3) -> 130 | L3: =LEFT(B3,2) -> 13 | M3: =+E3/D3 -> 3.5189999 | N3: =+J3/H3 -> 3.5189999 | O3: תואם לריכוז יתרות 30.06.20 | P3: =VLOOKUP(B3,SAP!A:A,1,0) -> 1304
A4: 1102 | B4: 1304 | C4: Bank Hapoalim EURO | D4: -398 | E4: -1401 | H4: =ROUND(G4+D4+F4,0) -> -398 | I4: =SUMIF(AE!$B$1:$B$1009,B4,AE!$G$1:$G$1009)-SUMIF(AE!$B$1:$B$1009,B4,AE!$F$1:$F$1009) -> 0 | J4: =ROUND(I4+E4,0) -> -1401 | K4: =LEFT(B4,3) -> 130 | L4: =LEFT(B4,2) -> 13 | M4: =+E4/D4 -> 3.5201005 | N4: =+J4/H4 -> 3.5201005 | O4: תואם לריכוז יתרות 30.06.21 | P4: =VLOOKUP(B4,SAP!A:A,1,0) -> 1304
A5: 1120 | B5: 1330 | C5: Bank Hapoalim Deposit | D5: -40710444 | E5: -143260053 | H5: =ROUND(G5+D5+F5,0) -> -40710444 | I5: =SUMIF(AE!$B$1:$B$1009,B5,AE!$G$1:$G$1009)-SUMIF(AE!$B$1:$B$1009,B5,AE!$F$1:$F$1009) -> 0 | J5: =ROUND(I5+E5,0) -> -143260053 | K5: =LEFT(B5,3) -> 133 | L5: =LEFT(B5,2) -> 13 | M5: =+E5/D5 -> 3.519 | N5: =+J5/H5 -> 3.519 | O5: תואם לריכוז יתרות 30.06.22 | P5: =VLOOKUP(B5,SAP!A:A,1,0) -> 1330
A6: 20000 | B6: 1342 | C6: Customers | D6: -1269967 | E6: -4459328 | H6: =ROUND(G6+D6+F6,0) -> -1269967 | I6: =SUMIF(AE!$B$1:$B$1009,B6,AE!$G$1:$G$1009)-SUMIF(AE!$B$1:$B$1009,B6,AE!$F$1:$F$1009) -> 0 | J6: =ROUND(I6+E6,0) -> -4459328 | K6: =LEFT(B6,3) -> 134 | L6: =LEFT(B6,2) -> 13 | M6: =+E6/D6 -> 3.5113731 | N6: =+J6/H6 -> 3.5113731 | O6: תואם לריכוז יתרות 30.06.23 | P6: =VLOOKUP(B6,SAP!A:A,1,0) -> 1342
A7: 6000 | B7: 1342 | C7: Other Debtors | D7: 0 | E7: 0 | H7: =ROUND(G7+D7+F7,0) -> 0 | I7: =SUMIF(AE!$B$1:$B$1009,B7,AE!$G$1:$G$1009)-SUMIF(AE!$B$1:$B$1009,B7,AE!$F$1:$F$1009) -> 0 | J7: =ROUND(I7+E7,0) -> 0 | K7: =LEFT(B7,3) -> 134 | L7: =LEFT(B7,2) -> 13 | M7: =+E7/D7 -> #DIV/0! | N7: =+J7/H7 -> #DIV/0! | O7: תואם לריכוז יתרות 30.06.24 | P7: =VLOOKUP(B7,SAP!A:A,1,0) -> 1342
A8: 6003 | B8: 1354 | C8: Prepaid expense | D8: -128703 | E8: -452905 | H8: =ROUND(G8+D8+F8,0) -> -128703 | I8: =SUMIF(AE!$B$1:$B$1009,B8,AE!$G$1:$G$1009)-SUMIF(AE!$B$1:$B$1009,B8,AE!$F$1:$F$1009) -> 0 | J8: =ROUND(I8+E8,0) -> -452905 | K8: =LEFT(B8,3) -> 135 | L8: =LEFT(B8,2) -> 13 | M8: =+E8/D8 -> 3.5189933 | N8: =+J8/H8 -> 3.5189933 | O8: תואם לריכוז יתרות 30.06.25 | P8: =VLOOKUP(B8,SAP!A:A,1,0) -> 1354
A9: 6004 | B9: 1355 | C9: Deposit for Rent | D9: -22131 | E9: -77879 | H9: =ROUND(G9+D9+F9,0) -> -22131 | I9: =SUMIF(AE!$B$1:$B$1009,B9,AE!$G$1:$G$1009)-SUMIF(AE!$B$1:$B$1009,B9,AE!$F$1:$F$1009) -> 0 | J9: =ROUND(I9+E9,0) -> -77879 | K9: =LEFT(B9,3) -> 135 | L9: =LEFT(B9,2) -> 13 | M9: =+E9/D9 -> 3.5190005 | N9: =+J9/H9 -> 3.5190005 | O9: תואם לריכוז יתרות 30.06.26 | P9: =VLOOKUP(B9,SAP!A:A,1,0) -> 1355
A10: 4004 | B10: 1356 | C10: Income Tax Advances | D10: -14172 | E10: -49872 | H10: =ROUND(G10+D10+F10,0) -> -14172 | I10: =SUMIF(AE!$B$1:$B$1009,B10,AE!$G$1:$G$1009)-SUMIF(AE!$B$1:$B$1009,B10,AE!$F$1:$F$1009) -> 0 | J10: =ROUND(I10+E10,0) -> -49872 | K10: =LEFT(B10,3) -> 135 | L10: =LEFT(B10,2) -> 13 | M10: =+E10/D10 -> 3.5190517 | N10: =+J10/H10 -> 3.5190517 | O10: תואם לריכוז יתרות 30.06.27 | P10: =VLOOKUP(B10,SAP!A:A,1,0) -> 1356
A11: 4006 | B11: 1356 | C11: Deduction at Source Cust. | D11: -41036 | E11: -144406 | H11: =ROUND(G11+D11+F11,0) -> -41036 | I11: =SUMIF(AE!$B$1:$B$1009,B11,AE!$G$1:$G$1009)-SUMIF(AE!$B$1:$B$1009,B11,AE!$F$1:$F$1009) -> 0 | J11: =ROUND(I11+E11,0) -> -144406 | K11: =LEFT(B11,3) -> 135 | L11: =LEFT(B11,2) -> 13 | M11: =+E11/D11 -> 3.5190077 | N11: =+J11/H11 -> 3.5190077 | O11: תואם לריכוז יתרות 30.06.28 | P11: =VLOOKUP(B11,SAP!A:A,1,0) -> 1356
A12: 4008 | B12: 1356 | C12: Advances - Income Tax | D12: -22329 | E12: -78574 | H12: =ROUND(G12+D12+F12,0) -> -22329 | I12: =SUMIF(AE!$B$1:$B$1009,B12,AE!$G$1:$G$1009)-SUMIF(AE!$B$1:$B$1009,B12,AE!$F$1:$F$1009) -> 0 | J12: =ROUND(I12+E12,0) -> -78574 | K12: =LEFT(B12,3) -> 135 | L12: =LEFT(B12,2) -> 13 | M12: =+E12/D12 -> 3.5189216 | N12: =+J12/H12 -> 3.5189216 | O12: תואם לריכוז יתרות 30.06.29 | P12: =VLOOKUP(B12,SAP!A:A,1,0) -> 1356
A13: 4012 | B13: 1356 | C13: Accrual for non deductible expenses | D13: 142139 | E13: 500185 | H13: =ROUND(G13+D13+F13,0) -> 142139 | I13: =SUMIF(AE!$B$1:$B$1009,B13,AE!$G$1:$G$1009)-SUMIF(AE!$B$1:$B$1009,B13,AE!$F$1:$F$1009) -> 0 | J13: =ROUND(I13+E13,0) -> 500185 | K13: =LEFT(B13,3) -> 135 | L13: =LEFT(B13,2) -> 13 | M13: =+E13/D13 -> 3.5189849 | N13: =+J13/H13 -> 3.5189849 | O13: תואם לריכוז יתרות 30.06.30 | P13: =VLOOKUP(B13,SAP!A:A,1,0) -> 1356
... A165: 9932 | B165: 3743 | C165: TOYOTA TSUS | D165: 1450093 | E165: 4883914 | H165: =ROUND(G165+D165+F165,0) -> 1450093 | I165: =SUMIF(AE!$B$1:$B$1009,B165,AE!$G$1:$G$1009)-SUMIF(AE!$B$1:$B$1009,B165,AE!$F$1:$F$1009) -> 0 | J165: =ROUND(I165+E165,0) -> 4883914 | K165: =LEFT(B165,3) -> 374 | L165: =LEFT(B165,2) -> 37 | M165: =+E165/D165 -> 3.3680005 | N165: =+J165/H165 -> 3.3680005 | O165: תואם לריכוז יתרות 30.06.182 | P165: =VLOOKUP(B165,SAP!A:A,1,0) -> 3743
A166: 9934 | B166: 3743 | C166: Capital fund for share-based payment | D166: 3091288 | E166: 10535476 | K166: =LEFT(B166,3) -> 374 | L166: =LEFT(B166,2) -> 37 | M166: =+E166/D166 -> 3.4081186 | N166: =+J166/H166 -> #DIV/0! | O166: תואם לריכוז יתרות 30.06.183 | P166: =VLOOKUP(B166,SAP!A:A,1,0) -> 3743
A167: 9935 | B167: 3743 | C167: Exercise of Oren Ronit option | D167: 19336 | E167: 62687 | K167: =LEFT(B167,3) -> 374 | L167: =LEFT(B167,2) -> 37 | M167: =+E167/D167 -> 3.2419839 | N167: =+J167/H167 -> #DIV/0! | O167: תואם לריכוז יתרות 30.06.184 | P167: =VLOOKUP(B167,SAP!A:A,1,0) -> 3743
A168: 9936 | B168: 3743 | C168: Exercise of shgia option | D168: 14636 | E168: 47214 | K168: =LEFT(B168,3) -> 374 | L168: =LEFT(B168,2) -> 37 | M168: =+E168/D168 -> 3.2258814 | N168: =+J168/H168 -> #DIV/0! | O168: תואם לריכוז יתרות 30.06.185 | P168: =VLOOKUP(B168,SAP!A:A,1,0) -> 3743
A169: 9937 | B169: 3743 | C169: MOORE STRATEGI | D169: 40000163 | E169: 133600544 | K169: =LEFT(B169,3) -> 374 | L169: =LEFT(B169,2) -> 37 | M169: =+E169/D169 -> 3.34 | N169: =+J169/H169 -> #DIV/0! | O169: תואם לריכוז יתרות 30.06.186 | P169: =VLOOKUP(B169,SAP!A:A,1,0) -> 3743
A170: 9938 | B170: 3743 | C170: COLMOBIL LTD | D170: 7000124 | E170: 23373406 | K170: =LEFT(B170,3) -> 374 | L170: =LEFT(B170,2) -> 37 | M170: =+E170/D170 -> 3.3389989 | N170: =+J170/H170 -> #DIV/0! | O170: תואם לריכוז יתרות 30.06.187 | P170: =VLOOKUP(B170,SAP!A:A,1,0) -> 3743
A171: 9939 | B171: 3743 | C171: NANYAH CARS LT | D171: 1500027 | E171: 5007089 | K171: =LEFT(B171,3) -> 374 | L171: =LEFT(B171,2) -> 37 | M171: =+E171/D171 -> 3.3379992 | N171: =+J171/H171 -> #DIV/0! | O171: תואם לריכוז יתרות 30.06.188 | P171: =VLOOKUP(B171,SAP!A:A,1,0) -> 3743
A172: 9942 | B172: 3743 | C172: S.H.R. Motorization | D172: 5000089 | E172: 16690297 | K172: =LEFT(B172,3) -> 374 | L172: =LEFT(B172,2) -> 37 | M172: =+E172/D172 -> 3.338 | N172: =+J172/H172 -> #DIV/0! | O172: תואם לריכוז יתרות 30.06.189 | P172: =VLOOKUP(B172,SAP!A:A,1,0) -> 3743
A173: 9943 | B173: 3743 | C173: Exercise of Amos Rosemary option | D173: 1 | E173: 4 | K173: =LEFT(B173,3) -> 374 | L173: =LEFT(B173,2) -> 37 | M173: =+E173/D173 -> 4 | N173: =+J173/H173 -> #DIV/0! | O173: תואם לריכוז יתרות 30.06.190 | P173: =VLOOKUP(B173,SAP!A:A,1,0) -> 3743
A174: 7001 | B174: 4200 | C174: Exempt Local Sales | D174: 1219917 | E174: 4120082 | K174: =LEFT(B174,3) -> 420 | L174: =LEFT(B174,2) -> 42 | M174: =+E174/D174 -> 3.3773462 | N174: =+J174/H174 -> #DIV/0! | O174: תואם לריכוז יתרות 30.06.191 | P174: =VLOOKUP(B174,SAP!A:A,1,0) -> 4200
A175: 7010 | B175: 4200 | C175: Training Revenues | D175: 5200257 | E175: 17407820 | K175: =LEFT(B175,3) -> 420 | L175: =LEFT(B175,2) -> 42 | M175: =+E175/D175 -> 3.3474922 | N175: =+J175/H175 -> #DIV/0! | O175: תואם לריכוז יתרות 30.06.192 | P175: =VLOOKUP(B175,SAP!A:A,1,0) -> 4200
A176: 7011 | B176: 4200 | C176: Contracting Revenues | D176: -5200257 | E176: -17407820 | K176: =LEFT(B176,3) -> 420 | L176: =LEFT(B176,2) -> 42 | M176: =+E176/D176 -> 3.3474922 | N176: =+J176/H176 -> #DIV/0! | O176: תואם לריכוז יתרות 30.06.193 | P176: =VLOOKUP(B176,SAP!A:A,1,0) -> 4200
A177: 8047 | B177: 4200 | C177: Self-invoice | D177: 0 | E177: 0 | K177: =LEFT(B177,3) -> 420 | L177: =LEFT(B177,2) -> 42 | M177: =+E177/D177 -> #DIV/0! | N177: =+J177/H177 -> #DIV/0! | O177: תואם לריכוז יתרות 30.06.194 | P177: =VLOOKUP(B177,SAP!A:A,1,0) -> 4200
... A204: 8305 | B204: 7020 | C204: S&M Employer Training Fund | D204: -13063 | E204: -44236 | K204: =LEFT(B204,3) -> 702 | L204: =LEFT(B204,2) -> 70 | M204: =+E204/D204 -> 3.3863584 | N204: =+J204/H204 -> #DIV/0! | O204: תואם לריכוז יתרות 30.06.221 | P204: =VLOOKUP(B204,SAP!A:A,1,0) -> 7020
A205: 8306 | B205: 7020 | C205: S&M compensation | D205: -35261 | E205: -119381 | K205: =LEFT(B205,3) -> 702 | L205: =LEFT(B205,2) -> 70 | P205: =VLOOKUP(B205,SAP!A:A,1,0) -> 7020
A206: 8307 | B206: 7020 | C206: Miscellaneous S&M employer | D206: -3554 | E206: -12108 | K206: =LEFT(B206,3) -> 702 | L206: =LEFT(B206,2) -> 70 | P206: =VLOOKUP(B206,SAP!A:A,1,0) -> 7020
A207: 8309 | B207: 7020 | C207: S&M convalescence expenses | D207: 361 | E207: 1196 | K207: =LEFT(B207,3) -> 702 | L207: =LEFT(B207,2) -> 70 | P207: =VLOOKUP(B207,SAP!A:A,1,0) -> 7020
A208: 8311 | B208: 7020 | C208: S&M options expenses | D208: -93116 | E208: -327675 | K208: =LEFT(B208,3) -> 702 | L208: =LEFT(B208,2) -> 70 | P208: =VLOOKUP(B208,SAP!A:A,1,0) -> 7020
A209: 8025 | B209: 7021 | C209: PR & ABM | D209: -324156 | E209: -1096261 | K209: =LEFT(B209,3) -> 702 | L209: =LEFT(B209,2) -> 70 | P209: =VLOOKUP(B209,SAP!A:A,1,0) -> 7021
A210: 8080 | B210: 7021 | C210: Mary M. Maguire exp. | D210: -134442 | E210: -452827 | K210: =LEFT(B210,3) -> 702 | L210: =LEFT(B210,2) -> 70 | P210: =VLOOKUP(B210,SAP!A:A,1,0) -> 7021
A211: 8024 | B211: 7022 | C211: Conference | D211: -75712 | E211: -259728 | K211: =LEFT(B211,3) -> 702 | L211: =LEFT(B211,2) -> 70 | P211: =VLOOKUP(B211,SAP!A:A,1,0) -> 7022
A212: 8219 | B212: 7023 | C212: Subcontructors GMBH | D212: -466078 | E212: -1594663 | K212: =LEFT(B212,3) -> 702 | L212: =LEFT(B212,2) -> 70 | P212: =VLOOKUP(B212,SAP!A:A,1,0) -> 7023
A213: 8021 | B213: 7026 | C213: Graphic Design | D213: -77929 | E213: -257366 | K213: =LEFT(B213,3) -> 702 | L213: =LEFT(B213,2) -> 70 | P213: =VLOOKUP(B213,SAP!A:A,1,0) -> 7026
A214: 8076 | B214: 7026 | C214: Consulting S&M | D214: -124396 | E214: -418958 | K214: =LEFT(B214,3) -> 702 | L214: =LEFT(B214,2) -> 70 | P214: =VLOOKUP(B214,SAP!A:A,1,0) -> 7026
A215: 8032 | B215: 7050 | C215: G&A convalescence expenses | D215: -38 | E215: -156 | K215: =LEFT(B215,3) -> 705 | L215: =LEFT(B215,2) -> 70 | P215: =VLOOKUP(B215,SAP!A:A,1,0) -> 7050
A216: 8050 | B216: 7050 | C216: Wage/Salary | D216: -744139 | E216: -2510979 | K216: =LEFT(B216,3) -> 705 | L216: =LEFT(B216,2) -> 70 | P216: =VLOOKUP(B216,SAP!A:A,1,0) -> 7050
... A289: 9941 | B289: 9410 | C289: Surpluses 2021 | D289: -9311277 | E289: -31197052 | K289: =LEFT(B289,3) -> 941 | L289: =LEFT(B289,2) -> 94 | P289: =VLOOKUP(B289,SAP!A:A,1,0) -> 9410
A290: NEW2 | B290: 4720 | C290: Reclassification of R&D expenses | D290: -975934 | E290: -3296066 | K290: =LEFT(B290,3) -> 472 | L290: =LEFT(B290,2) -> 47 | P290: =VLOOKUP(B290,SAP!A:A,1,0) -> #N/A
A291: NEW1 | B291: 7000 | C291: COGS - Reclassification of expenses | D291: 975934 | E291: 3296066 | K291: =LEFT(B291,3) -> 700 | L291: =LEFT(B291,2) -> 70 | P291: =VLOOKUP(B291,SAP!A:A,1,0) -> 7000
C293: GMBH | K293: =LEFT(A293,3) | L293: =LEFT(B293,2) | M293: =+E293/D293 -> #DIV/0! | N293: =+J293/H293 -> #DIV/0! | O293: תואם לריכוז יתרות 30.06.196
K294: =LEFT(A294,3) | L294: =LEFT(B294,2) | M294: =+E294/D294 -> #DIV/0! | N294: =+J294/H294 -> #DIV/0! | O294: תואם לריכוז יתרות 30.06.197
A295: 490 | B295: 1904 | C295: Other operating and office equipment | F295: =-'GMBH BS 31.12.2022'!H13 -> -1.0664962 | H295: =ROUND(G295+F295+#REF!,0) -> #REF! | I295: =SUMIF(AE!$B$1:$B$1009,B295,AE!$G$1:$G$1009)-SUMIF(AE!$B$1:$B$1009,B295,AE!$F$1:$F$1009) -> 0 | J295: =ROUND(I295+E295,0) -> 0 | K295: =LEFT(B295,3) -> 190 | L295: =LEFT(B295,2) -> 19 | M295: =+E295/D295 -> #DIV/0! | N295: =+J295/H295 -> #REF! | O295: תואם לריכוז יתרות 30.06.198 | P295: =VLOOKUP(B295,SAP!A:A,1,0) -> 1904
A296: 1410 | B296: 1351 | C296: Trade receivables | F296: =-'GMBH BS 31.12.2022'!H16 -> -238143.08 | H296: =ROUND(G296+F296+#REF!,0) -> #REF! | I296: =SUMIF(AE!$B$1:$B$1009,B296,AE!$G$1:$G$1009)-SUMIF(AE!$B$1:$B$1009,B296,AE!$F$1:$F$1009) -> 0 | J296: =ROUND(I296+E296,0) -> 0 | K296: =LEFT(B296,3) -> 135 | L296: =LEFT(B296,2) -> 13 | M296: =+E296/D296 -> #DIV/0! | N296: =+J296/H296 -> #REF! | O296: תואם לריכוז יתרות 30.06.201 | P296: =VLOOKUP(B296,SAP!A:A,1,0) -> 1351
A297: 1548 | B297: 1357 | C297: Input tax ded. following period/year | F297: =-'GMBH BS 31.12.2022'!H21 -> -467.05066 | K297: =LEFT(B297,3) -> 135 | L297: =LEFT(B297,2) -> 13 | P297: =VLOOKUP(B297,SAP!A:A,1,0) -> 1357
A298: 1570 | B298: 1357 | C298: Deductible input tax | F298: =-'GMBH BS 31.12.2022'!H23 -> -159.39852 | H298: =ROUND(G298+F298+#REF!,0) -> #REF! | I298: =SUMIF(AE!$B$1:$B$1009,B298,AE!$G$1:$G$1009)-SUMIF(AE!$B$1:$B$1009,B298,AE!$F$1:$F$1009) -> 0 | J298: =ROUND(I298+E298,0) -> 0 | K298: =LEFT(B298,3) -> 135 | L298: =LEFT(B298,2) -> 13 | M298: =+E298/D298 -> #DIV/0! | N298: =+J298/H298 -> #REF! | O298: תואם לריכוז יתרות 30.06.205 | P298: =VLOOKUP(B298,SAP!A:A,1,0) -> 1357
A299: 1571 | B299: 1357 | C299: Deductible input tax, 7% | F299: =-'GMBH BS 31.12.2022'!H24 -> -87.335371 | K299: =LEFT(B299,3) -> 135 | L299: =LEFT(B299,2) -> 13 | M299: =+E299/D299 -> #DIV/0! | N299: =+J299/H299 -> #DIV/0! | O299: תואם לריכוז יתרות 30.06.206 | P299: =VLOOKUP(B299,SAP!A:A,1,0) -> 1357
A300: 1576 | B300: 1357 | C300: Deductible input tax 19% | F300: =-'GMBH BS 31.12.2022'!H25 -> -1852.7598 | H300: =ROUND(G300+F300+#REF!,0) -> #REF! | I300: =SUMIF(AE!$B$1:$B$1009,B300,AE!$G$1:$G$1009)-SUMIF(AE!$B$1:$B$1009,B300,AE!$F$1:$F$1009) -> 0 | J300: =ROUND(I300+E300,0) -> 0 | K300: =LEFT(B300,3) -> 135 | L300: =LEFT(B300,2) -> 13 | M300: =+E300/D300 -> #DIV/0! | N300: =+J300/H300 -> #REF! | O300: תואם לריכוז יתרות 30.06.206 | P300: =VLOOKUP(B300,SAP!A:A,1,0) -> 1357
A301: 1741 | B301: 1357 | C301: Wage and church tax payables | F301: =-'GMBH BS 31.12.2022'!H26 -> 0 | H301: =ROUND(G301+F301+#REF!,0) -> #REF! | I301: =SUMIF(AE!$B$1:$B$1009,B301,AE!$G$1:$G$1009)-SUMIF(AE!$B$1:$B$1009,B301,AE!$F$1:$F$1009) -> 0 | J301: =ROUND(I301+E301,0) -> 0 | K301: =LEFT(B301,3) -> 135 | L301: =LEFT(B301,2) -> 13 | M301: =+E301/D301 -> #DIV/0! | N301: =+J301/H301 -> #REF! | O301: תואם לריכוז יתרות 30.06.207 | P301: =VLOOKUP(B301,SAP!A:A,1,0) -> 1357
A302: 1742 | B302: 1357 | C302: Social security liabilities | F302: =-'GMBH BS 31.12.2022'!H27 -> 0 | H302: =ROUND(G302+F302+#REF!,0) -> #REF! | I302: =SUMIF(AE!$B$1:$B$1009,B302,AE!$G$1:$G$1009)-SUMIF(AE!$B$1:$B$1009,B302,AE!$F$1:$F$1009) -> 0 | J302: =ROUND(I302+E302,0) -> 0 | K302: =LEFT(B302,3) -> 135 | L302: =LEFT(B302,2) -> 13 | M302: =+E302/D302 -> #DIV/0! | N302: =+J302/H302 -> #REF! | O302: תואם לריכוז יתרות 30.06.208 | P302: =VLOOKUP(B302,SAP!A:A,1,0) -> 1357
A303: 1790 | B303: 1357 | C303: VAT, previous year | F303: =-'GMBH BS 31.12.2022'!H30 -> -3283.3471 | H303: =ROUND(G303+F303+#REF!,0) -> #REF! | I303: =SUMIF(AE!$B$1:$B$1009,B303,AE!$G$1:$G$1009)-SUMIF(AE!$B$1:$B$1009,B303,AE!$F$1:$F$1009) -> 0 | J303: =ROUND(I303+E303,0) -> 0 | K303: =LEFT(B303,3) -> 135 | L303: =LEFT(B303,2) -> 13 | M303: =+E303/D303 -> #DIV/0! | N303: =+J303/H303 -> #REF! | O303: תואם לריכוז יתרות 30.06.209 | P303: =VLOOKUP(B303,SAP!A:A,1,0) -> 1357
A304: 1200 | B304: 1307 | C304: Bank | F304: =-'GMBH BS 31.12.2022'!H34 -> -2198.2832 | K304: =LEFT(B304,3) -> 130 | L304: =LEFT(B304,2) -> 13 | M304: =+E304/D304 -> #DIV/0! | N304: =+J304/H304 -> #DIV/0! | O304: תואם לריכוז יתרות 30.06.210 | P304: =VLOOKUP(B304,SAP!A:A,1,0) -> 1307
A305: 980 | B305: 1356 | C305: Prepaid expenses | F305: =-'GMBH BS 31.12.2022'!H37 -> 0 | K305: =LEFT(B305,3) -> 135 | L305: =LEFT(B305,2) -> 13 | P305: =VLOOKUP(B305,SAP!A:A,1,0) -> 1356
A306: 800 | B306: 1842 | C306: Subscribed capital | F306: 28054 | K306: =LEFT(B306,3) -> 184 | L306: =LEFT(B306,2) -> 18 | M306: =+E306/D306 -> #DIV/0! | N306: =+J306/H306 -> #DIV/0! | O306: תואם לריכוז יתרות 30.06.216 | P306: =VLOOKUP(B306,SAP!A:A,1,0) -> 1842
A307: 860 | B307: 9410 | C307: Retained profits bef apprprtn net profit | F307: 28059 | K307: =LEFT(B307,3) -> 941 | L307: =LEFT(B307,2) -> 94 | M307: =+E307/D307 -> #DIV/0! | N307: =+J307/H307 -> #DIV/0! | O307: תואם לריכוז יתרות 30.06.217 | P307: =VLOOKUP(B307,SAP!A:A,1,0) -> 9410
A308: 956 | B308: 2688 | C308: Provision for trade tax, EStG s. 4(5b) | F308: ='GMBH BS 31.12.2022'!H57 -> 4975.2046 | H308: =ROUND(G308+D308+F308,0) -> 4975 | I308: =SUMIF(AE!$B$1:$B$1009,B308,AE!$G$1:$G$1009)-SUMIF(AE!$B$1:$B$1009,B308,AE!$F$1:$F$1009) -> 0 | J308: =ROUND(I308+E308,0) -> 0 | K308: =LEFT(B308,3) -> 268 | L308: =LEFT(B308,2) -> 26 | M308: =+E308/D308 -> #DIV/0! | N308: =+J308/H308 -> 0 | O308: תואם לריכוז יתרות 30.06.218 | P308: =VLOOKUP(B308,SAP!A:A,1,0) -> 2688
A309: 963 | B309: 2688 | C309: Provisions for corporate income tax | F309: ='GMBH BS 31.12.2022'!H58 -> 3285.4694 | K309: =LEFT(B309,3) -> 268 | L309: =LEFT(B309,2) -> 26 | P309: =VLOOKUP(B309,SAP!A:A,1,0) -> 2688
A310: 970 | B310: 2688 | C310: Other provisions | F310: ='GMBH BS 31.12.2022'!H61 -> 0 | K310: =LEFT(B310,3) -> 268 | L310: =LEFT(B310,2) -> 26 | M310: =+E310/D310 -> #DIV/0! | N310: =+J310/H310 -> #DIV/0! | O310: תואם לריכוז יתרות 30.06.220 | P310: =VLOOKUP(B310,SAP!A:A,1,0) -> 2688
A311: 977 | B311: 2688 | C311: Provsns period-end closing/ audit costs | F311: ='GMBH BS 31.12.2022'!H62 -> 3732.7366 | K311: =LEFT(B311,3) -> 268 | L311: =LEFT(B311,2) -> 26 | M311: =+E311/D311 -> #DIV/0! | N311: =+J311/H311 -> #DIV/0! | O311: תואם לריכוז יתרות 30.06.221 | P311: =VLOOKUP(B311,SAP!A:A,1,0) -> 2688
A312: 1610 | B312: 2652 | C312: Trade pybls, no sep. rec./pybls accntng | F312: ='GMBH BS 31.12.2022'!H65 -> 0 | K312: =LEFT(B312,3) -> 265 | L312: =LEFT(B312,2) -> 26 | M312: =+E312/D312 -> #DIV/0! | N312: =+J312/H312 -> #DIV/0! | O312: תואם לריכוז יתרות 30.06.222 | P312: =VLOOKUP(B312,SAP!A:A,1,0) -> 2652
A313: 1700 | B313: 2685 | C313: Other liabilities | F313: ='GMBH BS 31.12.2022'!H68 -> 3404.2877 | G313: ='GMBH BS 31.12.2022'!I68 -> 0 | H313: ='GMBH BS 31.12.2022'!J68 -> 0 | I313: ='GMBH BS 31.12.2022'!K68 -> 0 | J313: ='GMBH BS 31.12.2022'!L68 -> 0 | K313: =LEFT(B313,3) -> 268 | L313: =LEFT(B313,2) -> 26 | M313: =+E313/D313 -> #DIV/0! | N313: =+J313/H313 -> #DIV/0! | O313: תואם לריכוז יתרות 30.06.223 | P313: =VLOOKUP(B313,SAP!A:A,1,0) -> 2685
A314: 1705 | B314: 1842 | C314: Loans Related company | F314: ='GMBH BS 31.12.2022'!H69 -> 154947.81 | K314: =LEFT(B314,3) -> 184 | L314: =LEFT(B314,2) -> 18 | M314: =+E314/D314 -> #DIV/0! | N314: =+J314/H314 -> #DIV/0! | O314: תואם לריכוז יתרות 30.06.224 | P314: =VLOOKUP(B314,SAP!A:A,1,0) -> 1842
A315: 1740 | B315: 2685 | C315: Payroll liabilities | F315: ='GMBH BS 31.12.2022'!H70 -> 0 | K315: =LEFT(B315,3) -> 268 | L315: =LEFT(B315,2) -> 26 | M315: =+E315/D315 -> #DIV/0! | N315: =+J315/H315 -> #DIV/0! | O315: תואם לריכוז יתרות 30.06.224 | P315: =VLOOKUP(B315,SAP!A:A,1,0) -> 2685
A316: 1741 | B316: 2685 | C316: Wage and church tax payables | F316: ='GMBH BS 31.12.2022'!H71 -> 3735.1469 | K316: =LEFT(B316,3) -> 268 | L316: =LEFT(B316,2) -> 26 | P316: =VLOOKUP(B316,SAP!A:A,1,0) -> 2685
A317: 1736 | B317: 1357 | C317: Liabilities from taxes and levies | F317: 391.839 | H317: =ROUND(G317+F317+#REF!,0) -> #REF! | I317: =SUMIF(AE!$B$1:$B$1009,B317,AE!$G$1:$G$1009)-SUMIF(AE!$B$1:$B$1009,B317,AE!$F$1:$F$1009) -> 0 | J317: =ROUND(I317+E317,0) -> 0 | K317: =LEFT(B317,3) -> 135 | L317: =LEFT(B317,2) -> 13 | M317: =+E317/D317 -> #DIV/0! | N317: =+J317/H317 -> #REF! | O317: תואם לריכוז יתרות 30.06.204 | P317: =VLOOKUP(B317,SAP!A:A,1,0) -> 1357
A318: 1742 | B318: 2685 | C318: Social security liabilities | F318: ='GMBH BS 31.12.2022'!H72 -> 0 | K318: =LEFT(B318,3) -> 268 | L318: =LEFT(B318,2) -> 26 | P318: =VLOOKUP(B318,SAP!A:A,1,0) -> 2685
A319: 8338 | B319: 7023 | C319: Tax-exempt sales 3rd country | F319: ='GMBH P&L 12.2022'!H12 -> 477453.22 | K319: =LEFT(B319,3) -> 702 | L319: =LEFT(B319,2) -> 70 | P319: =VLOOKUP(B319,SAP!A:A,1,0) -> 7023
A320: 4100 | B320: 7020 | C320: Wages and salaries | F320: ='GMBH P&L 12.2022'!H18 -> -149096.16 | K320: =LEFT(B320,3) -> 702 | L320: =LEFT(B320,2) -> 70 | P320: =VLOOKUP(B320,SAP!A:A,1,0) -> 7020
A321: 4120 | B321: 7020 | C321: share-based payments | F321: ='GMBH P&L 12.2022'!H19 -> -154947.81 | K321: =LEFT(B321,3) -> 702 | L321: =LEFT(B321,2) -> 70 | P321: =VLOOKUP(B321,SAP!A:A,1,0) -> 7020
A322: 4130 | B322: 7020 | C322: Statutory social security expenses | F322: ='GMBH P&L 12.2022'!H22 -> -17758.654 | K322: =LEFT(B322,3) -> 702 | L322: =LEFT(B322,2) -> 70 | P322: =VLOOKUP(B322,SAP!A:A,1,0) -> 7020
A323: 4138 | B323: 7020 | C323: Contrb. to occup. health/safety agency | F323: ='GMBH P&L 12.2022'!H23 -> -108.96391 | K323: =LEFT(B323,3) -> 702 | L323: =LEFT(B323,2) -> 70 | P323: =VLOOKUP(B323,SAP!A:A,1,0) -> 7020
A324: 4360 | B324: 7054 | C324: Insurance premiums | F324: ='GMBH P&L 12.2022'!H37 -> -106606.96 | K324: =LEFT(B324,3) -> 705 | L324: =LEFT(B324,2) -> 70 | P324: =VLOOKUP(B324,SAP!A:A,1,0) -> 7054
A325: 4396 | B325: 7020 | C325: Late filing penalties/ admin. fines | F325: ='GMBH P&L 12.2022'!H38 -> -179.46997 | K325: =LEFT(B325,3) -> 702 | L325: =LEFT(B325,2) -> 70 | P325: =VLOOKUP(B325,SAP!A:A,1,0) -> 7020
A326: 4600 | B326: 7026 | C326: Advertising expenses | F326: ='GMBH P&L 12.2022'!H42 -> -469.25831 | K326: =LEFT(B326,3) -> 702 | L326: =LEFT(B326,2) -> 70 | P326: =VLOOKUP(B326,SAP!A:A,1,0) -> 7026
A327: 4655 | B327: 7026 | C327: Non-deductible business expenses | F327: ='GMBH P&L 12.2022'!H43 -> -4.7992327 | K327: =LEFT(B327,3) -> 702 | L327: =LEFT(B327,2) -> 70 | P327: =VLOOKUP(B327,SAP!A:A,1,0) -> 7026
A328: 4663 | B328: 7025 | C328: Employee travel expnses, cost of travel | F328: ='GMBH P&L 12.2022'!H45 -> -4175.4605 | K328: =LEFT(B328,3) -> 702 | L328: =LEFT(B328,2) -> 70 | P328: =VLOOKUP(B328,SAP!A:A,1,0) -> 7025
A329: 4666 | B329: 7025 | C329: Employee trav. expn, accommodation costs | F329: ='GMBH P&L 12.2022'!H47 -> -2512.409 | K329: =LEFT(B329,3) -> 702 | L329: =LEFT(B329,2) -> 70 | P329: =VLOOKUP(B329,SAP!A:A,1,0) -> 7025
A330: 4830 | B330: 7021 | C330: Depreciation of tangible fixed assets | F330: ='GMBH P&L 12.2022'!H30 -> -447.21384 | K330: =LEFT(B330,3) -> 702 | L330: =LEFT(B330,2) -> 70 | P330: =VLOOKUP(B330,SAP!A:A,1,0) -> 7021
A331: 4900 | B331: 7021 | C331: Other operating expenses | F331: ='GMBH P&L 12.2022'!H54 -> -1902.3199 | K331: =LEFT(B331,3) -> 702 | L331: =LEFT(B331,2) -> 70 | P331: =VLOOKUP(B331,SAP!A:A,1,0) -> 7021
A332: 4950 | B332: 7021 | C332: Legal and consulting expenses | F332: ='GMBH P&L 12.2022'!H57 -> -1301.5732 | K332: =LEFT(B332,3) -> 702 | L332: =LEFT(B332,2) -> 70 | P332: =VLOOKUP(B332,SAP!A:A,1,0) -> 7021
A333: 4955 | B333: 7021 | C333: Bookkeeping expenses | F333: ='GMBH P&L 12.2022'!H58 -> -4387.5652 | K333: =LEFT(B333,3) -> 702 | L333: =LEFT(B333,2) -> 70 | P333: =VLOOKUP(B333,SAP!A:A,1,0) -> 7021
A334: 4957 | B334: 7021 | C334: Period-end closing and audit costs | F334: ='GMBH P&L 12.2022'!H59 -> -4052.6854 | K334: =LEFT(B334,3) -> 702 | L334: =LEFT(B334,2) -> 70 | P334: =VLOOKUP(B334,SAP!A:A,1,0) -> 7021
A335: 4970 | B335: 7021 | C335: Incidental monetary transaction costs | F335: ='GMBH P&L 12.2022'!H60 -> -463.63788 | K335: =LEFT(B335,3) -> 702 | L335: =LEFT(B335,2) -> 70 | P335: =VLOOKUP(B335,SAP!A:A,1,0) -> 7021
A336: 9004 | B336: 7901 | C336: Exchange rate | F336: ='GMBH P&L 12.2022'!H66 -> -3237.8159 | K336: =LEFT(B336,3) -> 790 | L336: =LEFT(B336,2) -> 79 | P336: =VLOOKUP(B336,SAP!A:A,1,0) -> 7901
A337: 4320 | B337: 7028 | C337: Trade tax | F337: ='GMBH P&L 12.2022'!H75 -> -4975.2046 | K337: =LEFT(B337,3) -> 702 | L337: =LEFT(B337,2) -> 70 | P337: =VLOOKUP(B337,SAP!A:A,1,0) -> 7028
A338: 2200 | B338: 7028 | C338: Corporate income tax | F338: ='GMBH P&L 12.2022'!H72 -> -4355.5703 | K338: =LEFT(B338,3) -> 702 | L338: =LEFT(B338,2) -> 70 | P338: =VLOOKUP(B338,SAP!A:A,1,0) -> 7028
A339: 2208 | B339: 7028 | C339: Solidarity surcharge | F339: ='GMBH P&L 12.2022'!H73-1 -> -240.55637 | K339: =LEFT(B339,3) -> 702 | L339: =LEFT(B339,2) -> 70 | P339: =VLOOKUP(B339,SAP!A:A,1,0) -> 7028
A340: 2281 | B340: 7028 | C340: Backp/refunds trade tax pr yrs, s 4/5 | F340: ='GMBH P&L 12.2022'!H74 -> -622.30051 | K340: =LEFT(B340,3) -> 702 | L340: =LEFT(B340,2) -> 70
D348: =SUM(D2:D346) -> 0 | E348: =SUM(E2:E346) -> 0 | F348: =SUM(F2:F346) -> 0.00015089513
A368: 956
A369: 963
A372: 970
A373: 977
A376: 1610
A379: 1700
A380: 1740
A381: 1741
A382: 1742
...

Sheet GMBH BS 31.12.2022
B1: INTERIM BALANCE SHEET
B2: ACCOUNTS as at | J2: =DATE -> 44926
B3: Balance Sheet Accounts as at 31/12/2022 | I3: ='Master Data (do not print)'!B23 -> 3.519 | J3: שע"ח $
I4: ='Master Data (do not print)'!B24 -> 3.753 | J4: שע"ח יורו
B5: Aurora Labs Germany GmbH Entwicklung und Vertrieb von Software, München | I5: =I4/I3 -> 1.0664962 | J5: יחס
B7: ASSETS | I7: 1.1318006 | J7: יחס 31.12.2021
E9: Financial year | F9: Previous year | H9: $
B10: Account | C10: Description | D10: EUR | E10: EUR | F10: EUR
C12: Other equipment, operating and office equipment
A13: 1904 | B13: 490 | C13: Other operating and office equipment | E13: 1 | F13: 739.17 | H13: =E13*$I$5 -> 1.0664962
AU14: 0
C15: Trade receivables
A16: 1351 | B16: 1410 | C16: Trade receivables | E16: 223294.83 | F16: 50112.19 | H16: =E16*$I$5 -> 238143.08
C18: Other assets
A19: 1355 | B19: 1525 | C19: Security deposits | F19: 1119.62 | H19: =D19*$I$5 -> 0
A20: 1356 | B20: 1540 | C20: Receivables from trade tax overpaymts | F20: 0 | H20: =D20*$I$5 -> 0
A21: 1357 | B21: 1548 | C21: Input tax ded. following period/year | D21: 437.93 | F21: 165.72 | H21: =D21*$I$5 -> 467.05066
A22: 1357 | B22: 1736 | C22: Liabilities from taxes and levies | D22: 0 | F22: 209.4 | H22: =D22*$I$5 -> 0
A23: 1357 | B23: 1570 | C23: Deductible input tax | D23: 149.46 | F23: 0 | H23: =D23*$I$5 -> 159.39852
A24: 1357 | B24: 1571 | C24: Deductible input tax, 7% | D24: 81.89 | H24: =D24*$I$5 -> 87.335371
A25: 1357 | B25: 1576 | C25: Deductible input tax 19% | D25: 1737.24 | F25: 10262.01 | H25: =D25*$I$5 -> 1852.7598
A26: 1357 | B26: 1741 | C26: Wage and church tax payables | D26: 0 | H26: =D26*$I$5 -> 0
A27: 1357 | B27: 1742 | C27: Social security liabilities | D27: 0 | H27: =D27*$I$5 -> 0
A28: 1357 | B28: 1780 | C28: VAT prepayments | F28: -6442.09 | H28: =D28*$I$5 -> 0
A29: 1357 | B29: 1789 | C29: VAT, current year | H29: =D29*$I$5 -> 0
A30: 1357 | B30: 1790 | C30: VAT, previous year | D30: 3078.63 | F30: 536.28 | H30: =D30*$I$5 -> 3283.3471
A31: 1357 | B31: 1791 | C31: VAT, earlier years | H31: =D31*$I$5 -> 0
E32: =SUM(D19:D31) -> 5485.15 | H32: =SUM(H19:H31) -> 5849.8914 | AU32: 0
C33: Cash-in-hand, central bank balances, bank balances and cheques
A34: 1307 | B34: 1200 | C34: Bank | E34: 2061.22 | F34: 8432.45 | H34: =E34*$I$5 -> 2198.2832
C36: Other assets
A37: 1356 | B37: 980 | C37: Prepaid expenses | F37: 0 | H37: =E37*$I$5 -> 0
C40: Total assets | E40: =E34+E32+E16+E13+E37 -> 230842.2 | F40: 65134.75 | H40: =H34+H32+H16+H13+H37 -> 246192.32 | I40: =H37+H34+H32+H16+H13-H40 -> 0
B42: EQUITY AND LIABILITIES
E44: Financial year | F44: Previous year
B45: Account | C45: Description | D45: EUR | E45: EUR | F45: EUR
C47: Subscribed capital | I47: י.פ. | J47: הפרשי שער
A48: 1842 | B48: 800 | C48: Subscribed capital | E48: 25000 | F48: 25000 | H48: =E48*$I$5 -> 26662.404 | I48: 28054 | J48: =I48-H48 -> 1391.5959 | K48: הוצאה
C50: Retained profits brought forward | I50: י.פ.
A51: 9410 | B51: 860 | C51: Retained profits bef apprprtn net profit | E51: 24578.41 | F51: 6553.33 | H51: =E51*$I$5 -> 26212.78 | I51: 28059 | J51: =I51-H51 -> 1846.22 | K51: הוצאה | AU51: 0
C53: Net income for the financial year
C54: Net income for the financial year | E54: ='GMBH P&L 12.2022'!D79 -> 17670.61 | F54: 11407.34 | H54: =E54*$I$5 -> 18845.638 | I54: ='GMBH P&L 12.2022'!H79 -> 15607.822
C56: Provisions for taxes
A57: 2688 | B57: 956 | C57: Provision for trade tax, EStG s. 4(5b) | D57: 4665 | F57: 1040 | H57: =D57*$I$5 -> 4975.2046
A58: 2688 | B58: 963 | C58: Provisions for corporate income tax | D58: 3080.62 | E58: =SUM(D57:D58) -> 7745.62 | F58: 1436.91 | H58: =D58*$I$5 -> 3285.4694
H59: =SUM(H57:H58) -> 8260.674
C60: Other provisions
A61: 2688 | B61: 970 | C61: Other provisions | D61: 0 | H61: =D61*$I$5 -> 0
A62: 2688 | B62: 977 | C62: Provsns period-end closing/ audit costs | D62: 3500 | E62: =SUM(D61:D62) -> 3500 | F62: 2600 | H62: =D62*$I$5 -> 3732.7366
H63: =SUM(H61:H62) -> 3732.7366 | AU63: 0
C64: Trade payables
A65: 2652 | B65: 1610 | C65: Trade pybls, no sep. rec./pybls accntng | H65: =E65*$I$5 -> 0
C67: Other liabilities
A68: 2685 | B68: 1700 | C68: Other liabilities | D68: 3192.03 | H68: =D68*$I$5 -> 3404.2877
A69: 1842 | B69: 1705 | C69: Loans Related company | D69: 145286.8 | H69: =D69*$I$5 -> 154947.81
A70: 2685 | B70: 1740 | C70: Payroll liabilities | F70: 12940.04 | H70: =D70*$I$5 -> 0
A71: 2685 | B71: 1741 | C71: Wage and church tax payables | D71: 3502.26 | F71: 3332 | H71: =D71*$I$5 -> 3735.1469
A72: 2685 | B72: 1742 | C72: Social security liabilities | D72: 0 | F72: 825.13 | H72: =D72*$I$5 -> 0
A73: 2685 | B73: 1736 | C73: Liabilities from taxes and levies | D73: 366.47 | H73: =D73*$I$5 -> 390.83885
E74: =SUM(D68:D73) -> 152347.56 | H74: =SUM(H68:H73) -> 162478.09
C75: of which taxes EUR 0,00 (EUR 825,13)
B76: 1741 | C76: Wage and church tax payables
C78: of which due within one year EUR 4.697,08 (EUR 17.097,17)
B79: 1700 | C79: Other liabilities | D79: 0
B80: 1701 | C80: Other liabilities due w/in 1 year | D80: 0
E81: =SUM(D79:D80) -> 0 | H81: =E81*$I$5 -> 0
C83: Other equity and liabilities
A84: 2658 | B84: 1525 | C84: Security deposits | E84: 0 | H84: =E84*$I$5 -> 0
C86: Total equity and liabilities | E86: =E84+E74+E65+E62+E58+E51+E48+E54+E81 -> 230842.2 | F86: 65134.75 | H86: =H84+H74+H65+H63+H59+I51+I48+I54+H81 -> 246192.32 | I86: =H74+H59+I54+I51+I48-H86+H62+H65+H84+H61 -> 7.2759576e-12
E89: =E86-E40 -> 0 | H89: =H86-H40 -> 0

Sheet GMBH P&L 12.2022
B1: Income statement | L1: =DATE -> 44926
B2: ACCOUNTS from | K2: ='Master Data (do not print)'!B23 -> 3.519 | L2: שע"ח $
A3: Income Statement Accounts from 01/01/2022 to 31/12/2022 | K3: ='Master Data (do not print)'!B24 -> 3.753 | L3: שע"ח יורו
K4: =K3/K2 -> 1.0664962 | L4: יחס
B5: Aurora Labs Germany GmbH Entwicklung und Vertrieb von Software, München
E8: Financial year | F8: Previous year | H8: $
B9: Account | C9: Description | D9: EUR | E9: EUR | F9: EUR
C11: Sales
A12: 7023 | B12: 8338 | C12: Tax-exempt sales 3rd country | E12: 447,683.95 | F12: 153998.81 | H12: =E12*$K$4 -> 477453.22
C14: Income from reversal of provisions
A15: 7021 | B15: 2375 | C15: Income from reversal of provisions | F15: 0 | H15: =E15*$K$4 -> 0
C17: Wages and salaries
A18: 7020 | B18: 4100 | C18: Wages and salaries | D18: -139800 | H18: =D18*$K$4 -> -149096.16
A19: 7020 | B19: 4120 | C19: share-based payments | D19: -145286.8 | F19: -70333.31 | H19: =D19*$K$4 -> -154947.81
E20: =SUM(D18:D19) -> -285086.8 | H20: =SUM(H18:H19) -> -304043.98
C21: Social security, post-employment and other employee benefit costs
A22: 7020 | B22: 4130 | C22: Statutory social security expenses | D22: -16651.4 | F22: -11541.55 | H22: =D22*$K$4 -> -17758.654
A23: 7020 | B23: 4138 | C23: Contrb. to occup. health/safety agency | D23: -102.17 | F23: -156.2 | H23: =D23*$K$4 -> -108.96391
E24: =SUM(D22:D23) -> -16753.57 | H24: =SUM(H22:H23) -> -17867.618
C25: Depreciation, amortisation and write-downs
C28: Amortisation and write-downs of intangible fixed assets and depreciation and write downs of tangible fixed assets
A29: 7021 | B29: 4830 | C29: Depreciation of tangible fixed assets | E29: 0 | F29: -386.83 | H29: =E29*$K$4 -> 0
A30: 7021 | B30: 4855 | C30: Immediate write-off of low-value assets | D30: -419.33 | H30: =D30*$K$4 -> -447.21384
E31: =D30 -> -419.33
H32: =H30+H29 -> -447.21384
C33: Occupancy costs
A34: 7021 | B34: 4210 | C34: Rent (immovable property) | D34: 0 | F34: -5174.73 | H34: =D34*$K$4 -> 0
A35: 7021 | B35: 4260 | C35: Maintenance of operating premises | D35: 0 | E35: 0 | H35: =D35*$K$4 -> 0
C36: Insurance premiums, fees and contributions | H36: =SUM(H34:H35) -> 0
A37: 7054 | B37: 4360 | C37: Insurance premiums | D37: -99960 | H37: =D37*$K$4 -> -106606.96
A38: 7020 | B38: 4396 | C38: Late filing penalties/ admin. fines | D38: -168.28 | F38: 0 | H38: =D38*$K$4 -> -179.46997
A39: 7020 | B39: 4397 | C39: N-tx dedctbl l.filg. penlts/admin. fines | E39: 0 | H39: =E39*$K$4 -> 0
E40: =D37+D38 -> -100128.28 | H40: =H37+H38 -> -106786.43
C41: Advertising and travel expenses
A42: 7026 | B42: 4600 | C42: Advertising expenses | D42: -440 | F42: -27249.72 | H42: =D42*$K$4 -> -469.25831
A43: 7026 | B43: 4655 | C43: Non-deductible business expenses | D43: -4.5 | F43: -234.96 | H43: =D43*$K$4 -> -4.7992327
B44: 4660 | C44: Employee travel expenses | D44: 0 | F44: -937.19 | H44: =D44*$K$4 -> 0
A45: 7025 | B45: 4663 | C45: Employee travel expnses, cost of travel | D45: -3915.12 | F45: -1700.42 | H45: =D45*$K$4 -> -4175.4605
A46: 7025 | B46: 4664 | C46: Employee trav. expn, addnl substnc costs | D46: 0 | F46: -305 | H46: =D46*$K$4 -> 0
A47: 7025 | B47: 4666 | C47: Employee trav. expn, accommodation costs | D47: -2355.76 | F47: -2245.81 | H47: =D47*$K$4 -> -2512.409
B48: 4668 | C48: Employee mileage reimbursement | D48: 0 | E48: =SUM(D42:D48) -> -6715.38 | F48: -612.6 | H48: =D48*$K$4 -> 0
H49: =SUM(H42:H48) -> -7161.927
C50: Selling and distribution expenses
B51: 4780 | C51: Third-party services (distribution) | E51: 0 | F51: -17280
C53: Miscellaneous operating costs
A54: 7021 | B54: 4900 | C54: Other operating expenses | D54: -1783.71 | F54: -239.5 | H54: =D54*$K$4 -> -1902.3199
A55: 7021 | B55: 4920 | C55: Telephone | D55: 0 | F55: -648.57 | H55: =D55*$K$4 -> 0
A56: 7021 | B56: 4930 | C56: Office supplies | D56: 0 | F56: -131.9 | H56: =D56*$K$4 -> 0
A57: 7021 | B57: 4950 | C57: Legal and consulting expenses | D57: -1220.42 | F57: -820 | H57: =D57*$K$4 -> -1301.5732
A58: 7021 | B58: 4955 | C58: Bookkeeping expenses | D58: -4114 | H58: =D58*$K$4 -> -4387.5652
A59: 7021 | B59: 4957 | C59: Period-end closing and audit costs | D59: -3800 | F59: -2355.3 | H59: =D59*$K$4 -> -4052.6854
A60: 7021 | B60: 4970 | C60: Incidental monetary transaction costs | D60: -434.73 | E60: =SUM(D54:D60) -> -11352.86 | F60: -237.88 | H60: =D60*$K$4 -> -463.63788
H61: =SUM(H54:H60) -> -12107.782
C62: Other interest and similar income
A63: 7900 | B63: 2650 | C63: Other interest and similar income | E63: 0 | H63: =E63*$K$4 -> 0
A66: 7901 | B66: 9004 | C66: Exchange rate | H66: =-('GMBH BS 31.12.2022'!J48+'GMBH BS 31.12.2022'!J51) -> -3237.8159
C68: Interest and similar expenses
A69: 7901 | B69: 2105 | C69: Int. expns. sec 233a AO, non-deductible | E69: 0 | F69: 0 | H69: =E69*$K$4 -> 0
C71: Taxes on income
A72: 7028 | B72: 2200 | C72: Corporate income tax | D72: -4084 | F72: 0 | H72: =D72*$K$4 -> -4355.5703
A73: 7028 | B73: 2208 | C73: Solidarity surcharge | D73: -224.62 | H73: =D73*$K$4 -> -239.55637
A74: 7028 | B74: 2281 | C74: Backp/refunds trade tax pr yrs, s 4/5 | D74: -583.5 | H74: =D74*$K$4 -> -622.30051
A75: 7028 | B75: 4320 | C75: Trade tax | D75: -4665 | E75: =SUM(D72:D75) -> -9557.12 | H75: =D75*$K$4 -> -4975.2046
H76: =SUM(H72:H75) -> -10192.632
C78: Net income for the financial year
C79: Net income for the financial year | D79: =E12+E20+E24+E48+E60+E75+E40+E31 -> 17670.61 | F79: 11407.34 | H79: =H12+H15+H20+H24+H40+H49+H61+H63+H66+H76+H32 -> 15607.822 | I79: =D79*K4+H66-H79 -> 5.0931703e-11

Sheet AE
D1: =SUM(D3:D194) -> 1060950 | E1: =SUM(E3:E194) -> 1060951 | F1: =SUM(F3:F194) -> 2321 | G1: =SUM(G3:G194) -> 0
A2: AE # | B2: Code # | C2: Code name | D2: Debit | E2: Credit | F2: חובה ₪ | G2: זכות ₪ | H2: Details
AU3: U.S. Dollars
A4: 1 | B4: 9410 | C4: =VLOOKUP(B4,SAP!A:B,2,0) -> Opening Retained Earnings (Deficit) | E4: =2322-241 -> 2081 | F4: 2321
B5: 7901 | C5: =VLOOKUP(B5,SAP!A:B,2,0) -> Exchange difference rate | D5: =E4 -> 2081 | AU5: 52986
AU7: 15114299
AU8: 44500
A9: 2 | B9: 7023 | C9: =VLOOKUP(B9,SAP!A:B,2,0) -> Subcontructors GMBH | E9: =-SAP!C38-SAP!D38 -> -11375.215 | H9: I/C adjustment | AU9: U.S. Dollars
B10: 7901 | C10: =VLOOKUP(B10,SAP!A:B,2,0) -> Exchange difference rate | D10: =E9 -> -11375.215 | AU10: 0
AU11: 4276
A12: 3 | B12: 1351 | C12: =VLOOKUP(B12,SAP!A:B,2,0) -> Related company | E12: =-SAP!D6 -> 238143.08 | H12: I/C adjustment | AU12: 23516
B13: 2686 | C13: =VLOOKUP(B13,SAP!A:B,2,0) -> Related company | D13: =SAP!C23 -> 234727 | AU13: 14869
B14: 7901 | C14: =VLOOKUP(B14,SAP!A:B,2,0) -> Exchange difference rate | D14: =E12-D13 -> 3416.0796 | AU14: 26154
A17: 4 | B17: 7054 | C17: =VLOOKUP(B17,SAP!A:B,2,0) -> Insurance | E17: =D18 -> -1180.7232 | H17: Advance expenses for MARSH product insurance for the period of 09.15-21-09-15-24
B18: 1354 | C18: =VLOOKUP(B18,SAP!A:B,2,0) -> Prepaid expenses | D18: ='Prepaid expenses'!K9 -> -1180.7232
A21: 5 | B21: 7020 | C21: =VLOOKUP(B21,SAP!A:B,2,0) -> Salaries and social benefits | E21: 154682 | H21: Expenses for share-based payment 2019-2021 - GMBH | I21: לא לרשום פקודה במאוחד למחוק אותה ב2023
B22: 9410 | C22: =VLOOKUP(B22,SAP!A:B,2,0) -> Opening Retained Earnings (Deficit) | D22: =E21 -> 154682
B24: 7901 | C24: =VLOOKUP(B24,SAP!A:B,2,0) -> Exchange difference rate | D24: -1
B25: 2685 | C25: =VLOOKUP(B25,SAP!A:B,2,0) -> Employees
AU28: 0
AU29: 13953
A30: 6 | B30: 1842 | C30: =VLOOKUP(B30,SAP!A:B,2,0) -> Investment in subsidiary | D30: 154947.81 | H30: Cancel Expenses for share-based payment 2019-2021 - GMBH | I30: פקודה קבועה עד להעברה בספרים של GMBH | AU30: 253871
B31: 7020 | C31: =VLOOKUP(B31,SAP!A:B,2,0) -> Salaries and social benefits | E31: =D30 -> 154947.81
I32: ביטול הוצאות אופציות שנרשמו בכל השנים 2019-2021 | AU32: 44500
AU33: 44500
AU34: U.S. Dollars
H36: פקודות יומן בגין חכירה
A38: 7 | B38: 1410 | C38: =VLOOKUP(B38,SAP!A:B,2,0) -> Leased property under capital lease, net | D38: 300242.05 | H38: הקמת נכס והתחייבות בגין חכירה
B39: 3010 | C39: =VLOOKUP(B39,SAP!A:B,2,0) -> Long Term Lease | E39: =D38 -> 300242.05
A43: 8 | B43: 3010 | C43: =VLOOKUP(B43,SAP!A:B,2,0) -> Long Term Lease | D43: 149136 | H43: פקודה בגין חלויות שוטפות 2023 בגין התחייבות
B44: 2630 | C44: =VLOOKUP(B44,SAP!A:B,2,0) -> Current maturities of obligation under capital lease | E44: =D43 -> 149136 | AU44: 78285
AU45: 13689
AU46: 91974
A48: 9 | B48: 1410 | C48: =VLOOKUP(B48,SAP!A:B,2,0) -> Leased property under capital lease, net | E48: 74275 | H48: הפחתת נכס והפחת התחייבות חצי שנתית 2022 | I48: מ1.7.22-.31.12.22
B49: 3010 | C49: =VLOOKUP(B49,SAP!A:B,2,0) -> Long Term Lease | D49: 75752
B50: 7901 | C50: =VLOOKUP(B50,SAP!A:B,2,0) -> Exchange difference rate | D50: =E48-D49-D51 -> -3377
B51: 7900 | C51: =VLOOKUP(B51,SAP!A:B,2,0) -> Bank commission and interest | D51: 1900 | AU51: 0
AU54: 44500
AU55: 44500
AU56: U.S. Dollars
AU57: 351042
AU58: 569612
AU59: 0
AU60: 132452
AU61: 240
AU62: 0
AU63: 1053346
AU65: 0
AU67: 44500
AU68: 44500
AU69: U.S. Dollars
AU70: 1859
AU71: 1859
AU72: 0

Sheet GMBH BS 31.12.2022 (2)
B1: INTERIM BALANCE SHEET
B2: ACCOUNTS as at | J2: =DATE -> 44926
B3: Balance Sheet Accounts as at 31/10/2022 | I3: ='Master Data (do not print)'!B23 -> 3.519 | J3: שע"ח $
I4: ='Master Data (do not print)'!B24 -> 3.753 | J4: שע"ח יורו
B5: Aurora Labs Germany GmbH Entwicklung und Vertrieb von Software, München | I5: =I4/I3 -> 1.0664962 | J5: יחס
B7: ASSETS | I7: 1.1318006 | J7: יחס 31.12.2021
E9: Financial year | F9: Previous year | H9: $
B10: Account | C10: Description | D10: EUR | E10: EUR | F10: EUR | L10: 2022 changes | M10: difference 2022 | P10: 2022 changes V1 | Q10: difference 2022 V1
M11: euro | N11: $ | Q11: euro | R11: $
C12: Other equipment, operating and office equipment
A13: 1904 | B13: 490 | C13: Other operating and office equipment | E13: 1 | F13: 739.17 | H13: =E13*$I$5 -> 1.0664962
AU14: 0
C15: Trade receivables
A16: 1351 | B16: 1410 | C16: Trade receivables | E16: 223139.75 | F16: 50112.19 | H16: =E16*$I$5 -> 237977.69 | L16: 223294.83 | M16: =E16-L16 -> -155.08 | N16: =M16*$I$5 -> -165.39223 | P16: 223294.83 | Q16: =P16-E16 -> 155.08 | R16: =Q16*$I$5 -> 165.39223 | S16: =R16+N16 -> 0
C18: Other assets
A19: 1355 | B19: 1525 | C19: Security deposits | F19: 1119.62 | H19: =D19*$I$5 -> 0
A20: 1356 | B20: 1540 | C20: Receivables from trade tax overpaymts | F20: 0 | H20: =D20*$I$5 -> 0
A21: 2688 | B21: 1548 | C21: Input tax ded. following period/year | D21: 0 | F21: 165.72 | H21: =D21*$I$5 -> 0 | L21: 437.93 | M21: =D21-L21 -> -437.93 | N21: =M21*$I$5 -> -467.05066 | P21: 437.93 | Q21: =P21-D21 -> 437.93 | R21: =Q21*$I$5 -> 467.05066 | S21: =R21+N21 -> 0
A22: 1357 | B22: 1736 | C22: Liabilities from taxes and levies | D22: 155.08 | F22: 209.4 | H22: =D22*$I$5 -> 165.39223 | L22: 0 | M22: =D22-L22 -> 155.08 | N22: =M22*$I$5 -> 165.39223 | P22: 0 | Q22: =P22-D22 -> -155.08 | R22: =Q22*$I$5 -> -165.39223 | S22: =R22+N22 -> 0
A23: 1357 | B23: 1570 | C23: Deductible input tax | D23: 149.46 | F23: 0 | H23: =D23*$I$5 -> 159.39852
A24: 1357 | B24: 1571 | C24: Deductible input tax, 7% | D24: 81.89 | H24: =D24*$I$5 -> 87.335371
A25: 1357 | B25: 1576 | C25: Deductible input tax 19% | D25: 1722.7 | F25: 10262.01 | H25: =D25*$I$5 -> 1837.2529 | P25: 1737 | Q25: =P25-D25 -> 14.3 | R25: =Q25*$I$5 -> 15.250895 | S25: =R25+N25 -> 15.250895
A26: 1357 | B26: 1741 | C26: Wage and church tax payables | D26: 0 | H26: =D26*$I$5 -> 0
A27: 1357 | B27: 1742 | C27: Social security liabilities | D27: 0 | H27: =D27*$I$5 -> 0
A28: 1357 | B28: 1780 | C28: VAT prepayments | F28: -6442.09 | H28: =D28*$I$5 -> 0
A29: 1357 | B29: 1789 | C29: VAT, current year | H29: =D29*$I$5 -> 0
A30: 1357 | B30: 1790 | C30: VAT, previous year | D30: 3078.63 | F30: 536.28 | H30: =D30*$I$5 -> 3283.3471 | P30: 3078.63 | Q30: =P30-D30 -> 0 | R30: =Q30*$I$5 -> 0 | S30: =R30+N30 -> 0
A31: 1357 | B31: 1791 | C31: VAT, earlier years | H31: =D31*$I$5 -> 0
E32: =SUM(D19:D31) -> 5187.76 | H32: =SUM(H19:H31) -> 5532.7261 | AU32: 0
C33: Cash-in-hand, central bank balances, bank balances and cheques
A34: 1307 | B34: 1200 | C34: Bank | E34: 2167.72 | F34: 8432.45 | H34: =E34*$I$5 -> 2311.8651 | L34: 2061.22 | M34: =E34-L34 -> 106.5 | N34: =M34*$I$5 -> 113.58184 | P34: 2061 | Q34: =P34-E34 -> -106.72 | R34: =Q34*$I$5 -> -113.81647 | S34: =R34+N34 -> -0.23462916
C36: Other assets
A37: 1356 | B37: 980 | C37: Prepaid expenses | F37: 0 | H37: =E37*$I$5 -> 0
C40: Total assets | E40: =E34+E32+E16+E13+E37 -> 230496.23 | F40: 65134.75 | H40: =H34+H32+H16+H13+H37 -> 245823.35 | I40: =H37+H34+H32+H16+H13-H40 -> 0
B42: EQUITY AND LIABILITIES
E44: Financial year | F44: Previous year
B45: Account | C45: Description | D45: EUR | E45: EUR | F45: EUR
C47: Subscribed capital | I47: י.פ. | J47: הפרשי שער
A48: 1842 | B48: 800 | C48: Subscribed capital | E48: 25000 | F48: 25000 | H48: =E48*$I$5 -> 26662.404 | I48: 28054 | J48: =I48-H48 -> 1391.5959 | K48: הוצאה
C50: Retained profits brought forward | I50: י.פ.
A51: 9410 | B51: 860 | C51: Retained profits bef apprprtn net profit | E51: 24578.41 | F51: 6553.33 | H51: =E51*$I$5 -> 26212.78 | I51: =E51*I7 -> 27817.86 | J51: =I51-H51 -> 1605.0803 | K51: הוצאה | P51: 24578.41 | Q51: =P51-E51 -> 0 | AU51: 0
C53: Net income for the financial year
C54: Net income for the financial year | E54: ='GMBH P&L 12.2022'!D79 -> 17670.61 | F54: 11407.34 | H54: =E54*$I$5 -> 18845.638 | I54: ='GMBH P&L 12.2022'!H79 -> 15607.822 | L54: 25850 | M54: =E54-L54 -> -8179.39 | P54: 17670.61 | Q54: =P54-E54 -> 0 | S54: =Q54+M54 -> -8179.39
C56: Provisions for taxes
A57: 2688 | B57: 956 | C57: Provision for trade tax, EStG s. 4(5b) | D57: 73 | F57: 1040 | H57: =D57*$I$5 -> 77.85422 | L57: 0 | M57: =D57-L57 -> 73 | N57: =M57*$I$5 -> 77.85422 | P57: 4665 | Q57: =P57-D57 -> 4592 | R57: =Q57*$I$5 -> 4897.3504 | S57: =R57+N57 -> 4975.2046
A58: 2688 | B58: 963 | C58: Provisions for corporate income tax | D58: 293.47 | E58: =SUM(D57:D58) -> 366.47 | F58: 1436.91 | H58: =D58*$I$5 -> 312.98463 | L58: 0 | M58: =D58-L58 -> 293.47 | N58: =M58*$I$5 -> 312.98463 | P58: 3080.62 | Q58: =P58-D58 -> 2787.15 | R58: =Q58*$I$5 -> 2972.4848 | S58: =R58+N58 -> 3285.4694
H59: =SUM(H57:H58) -> 390.83885
C60: Other provisions
A61: 2688 | B61: 970 | C61: Other provisions | D61: 172 | H61: =D61*$I$5 -> 183.43734 | L61: 0 | M61: =D61-L61 -> 172 | N61: =M61*$I$5 -> 183.43734 | P61: 0 | Q61: =P61-D61 -> -172 | R61: =Q61*$I$5 -> -183.43734 | S61: =R61+N61 -> 0
A62: 2688 | B62: 977 | C62: Provsns period-end closing/ audit costs | D62: 0 | E62: =SUM(D61:D62) -> 172 | F62: 2600 | H62: =D62*$I$5 -> 0 | L62: 3500 | M62: =D62-L62 -> -3500 | N62: =M62*$I$5 -> -3732.7366 | P62: 3500 | Q62: =P62-D62 -> 3500 | R62: =Q62*$I$5 -> 3732.7366 | S62: =R62+N62 -> 0
H63: =SUM(H61:H62) -> 183.43734 | AU63: 0
C64: Trade payables
A65: 2652 | B65: 1610 | C65: Trade pybls, no sep. rec./pybls accntng | H65: =E65*$I$5 -> 0
C67: Other liabilities
A68: 2685 | B68: 1700 | C68: Other liabilities | D68: 0 | H68: =D68*$I$5 -> 0 | L68: 2742.83 | M68: =D68-L68 -> -2742.83 | N68: =M68*$I$5 -> -2925.2177 | P68: 3192 | Q68: =P68-D68 -> 3192 | R68: =Q68*$I$5 -> 3404.2558 | S68: =R68+N68 -> 479.03808
A69: 1842 | B69: 1705 | C69: Loans Related company | D69: 145286.8 | H69: =D69*$I$5 -> 154947.81
A70: 2685 | B70: 1740 | C70: Payroll liabilities | F70: 12940.04 | H70: =D70*$I$5 -> 0
A71: 2685 | B71: 1741 | C71: Wage and church tax payables | D71: 3742.26 | F71: 3332 | H71: =D71*$I$5 -> 3991.1059 | L71: 3502 | M71: =D71-L71 -> 240.26 | N71: =M71*$I$5 -> 256.23637 | P71: 3502 | Q71: =P71-D71 -> -240.26 | R71: =Q71*$I$5 -> -256.23637 | S71: =R71+N71 -> 0
A72: 2685 | B72: 1742 | C72: Social security liabilities | D72: 0 | F72: 825.13 | H72: =D72*$I$5 -> 0
A73: 2685 | B73: 1736 | C73: Liabilities from taxes and levies | H73: =D73*$I$5 -> 0 | L73: 366.47 | M73: =D73-L73 -> -366.47 | N73: =M73*$I$5 -> -390.83885 | P73: 366.47 | Q73: =P73-D73 -> 366.47 | R73: =Q73*$I$5 -> 390.83885 | S73: =R73+N73 -> 0
E74: =SUM(D68:D73) -> 149029.06 | H74: =SUM(H68:H73) -> 158938.92
C75: of which taxes EUR 0,00 (EUR 825,13)
B76: 1741 | C76: Wage and church tax payables
C78: of which due within one year EUR 4.697,08 (EUR 17.097,17)
B79: 1700 | C79: Other liabilities | D79: 0
B80: 1701 | C80: Other liabilities due w/in 1 year | D80: 0
E81: =SUM(D79:D80) -> 0 | H81: =E81*$I$5 -> 0
C83: Other equity and liabilities
A84: 2658 | B84: 1525 | C84: Security deposits | E84: 0 | H84: =E84*$I$5 -> 0
C86: Total equity and liabilities | E86: =E84+E74+E65+E62+E58+E51+E48+E54+E81 -> 216816.55 | F86: 65134.75 | H86: =H84+H74+H65+H63+H59+I51+I48+I54+H81 -> 230992.88 | I86: =H74+H59+I54+I51+I48-H86+H62+H65+H84+H61 -> 1.3244517e-11 | M86: =SUM(M16:M34)-SUM(M57:M73) -> 5499.14 | N86: =SUM(N16:N34)-SUM(N57:N73) -> 5864.8117 | Q86: =SUM(Q16:Q34)-SUM(Q57:Q73) -> -13679.85 | R86: =SUM(R16:R34)-SUM(R57:R73) -> -14589.508 | S86: =SUM(S16:S34)-SUM(S57:S73) -> -8724.6958
E89: =E86-E40 -> -13679.68 | H89: =H86-H40 -> -14830.466

Sheet GMBH P&L 12.2022 (2)
B1: Income statement | L1: =DATE -> 44926
B2: ACCOUNTS from | K2: ='Master Data (do not print)'!B23 -> 3.519 | L2: שע"ח $
A3: Income Statement Accounts from 01/01/2022 to 30/11/2022 | K3: ='Master Data (do not print)'!B24 -> 3.753 | L3: שע"ח יורו
K4: =K3/K2 -> 1.0664962 | L4: יחס
B5: Aurora Labs Germany GmbH Entwicklung und Vertrieb von Software, München
E8: Financial year | F8: Previous year | H8: $
B9: Account | C9: Description | D9: EUR | E9: EUR | F9: EUR
C11: Sales
A12: 7023 | B12: 8338 | C12: Tax-exempt sales 3rd country | E12: 447,683.95 | F12: 153998.81 | H12: =E12*$K$4 -> 477453.22
C14: Income from reversal of provisions
A15: 7021 | B15: 2375 | C15: Income from reversal of provisions | F15: 0 | H15: =E15*$K$4 -> 0
C17: Wages and salaries
A18: 7020 | B18: 4100 | C18: Wages and salaries | D18: -140100 | H18: =D18*$K$4 -> -149416.11
A19: 7020 | B19: 4120 | C19: share-based payments | D19: -145286.8 | F19: -70333.31 | H19: =D19*$K$4 -> -154947.81
E20: =SUM(D18:D19) -> -285386.8 | H20: =SUM(H18:H19) -> -304363.93
C21: Social security, post-employment and other employee benefit costs
A22: 7020 | B22: 4130 | C22: Statutory social security expenses | D22: -16651.4 | F22: -11541.55 | H22: =D22*$K$4 -> -17758.654
A23: 7020 | B23: 4138 | C23: Contrb. to occup. health/safety agency | D23: -274.17 | F23: -156.2 | H23: =D23*$K$4 -> -292.40125
E24: =SUM(D22:D23) -> -16925.57 | H24: =SUM(H22:H23) -> -18051.055
C25: Depreciation, amortisation and write-downs
C28: Amortisation and write-downs of intangible fixed assets and depreciation and write downs of tangible fixed assets
A29: 7021 | B29: 4830 | C29: Depreciation of tangible fixed assets | E29: 0 | F29: -386.83 | H29: =E29*$K$4 -> 0
A30: 7021 | B30: 4855 | C30: Immediate write-off of low-value assets | D30: -419.33 | H30: =D30*$K$4 -> -447.21384
E31: =D30 -> -419.33
H32: =H30+H29 -> -447.21384
C33: Occupancy costs
A34: 7021 | B34: 4210 | C34: Rent (immovable property) | D34: 0 | F34: -5174.73 | H34: =D34*$K$4 -> 0
A35: 7021 | B35: 4260 | C35: Maintenance of operating premises | D35: 0 | E35: 0 | H35: =D35*$K$4 -> 0
C36: Insurance premiums, fees and contributions | H36: =SUM(H34:H35) -> 0
A37: 7054 | B37: 4360 | C37: Insurance premiums | D37: -99960 | H37: =D37*$K$4 -> -106606.96
A38: 7020 | B38: 4396 | C38: Late filing penalties/ admin. fines | D38: -108.28 | F38: 0 | H38: =D38*$K$4 -> -115.4802
A39: 7020 | B39: 4397 | C39: N-tx dedctbl l.filg. penlts/admin. fines | E39: 0 | H39: =E39*$K$4 -> 0
E40: =D37+D38 -> -100068.28 | H40: =H37+H38 -> -106722.44
C41: Advertising and travel expenses
A42: 7026 | B42: 4600 | C42: Advertising expenses | D42: -440 | F42: -27249.72 | H42: =D42*$K$4 -> -469.25831
A43: 7026 | B43: 4655 | C43: Non-deductible business expenses | D43: -4.5 | F43: -234.96 | H43: =D43*$K$4 -> -4.7992327
B44: 4660 | C44: Employee travel expenses | D44: 0 | F44: -937.19 | H44: =D44*$K$4 -> 0
A45: 7025 | B45: 4663 | C45: Employee travel expnses, cost of travel | D45: -3480.46 | F45: -1700.42 | H45: =D45*$K$4 -> -3711.8972
A46: 7025 | B46: 4664 | C46: Employee trav. expn, addnl substnc costs | D46: 0 | F46: -305 | H46: =D46*$K$4 -> 0
A47: 7025 | B47: 4666 | C47: Employee trav. expn, accommodation costs | D47: -2355.76 | F47: -2245.81 | H47: =D47*$K$4 -> -2512.409
B48: 4668 | C48: Employee mileage reimbursement | D48: 0 | E48: =SUM(D42:D48) -> -6280.72 | F48: -612.6 | H48: =D48*$K$4 -> 0
H49: =SUM(H42:H48) -> -6698.3638
C50: Selling and distribution expenses
B51: 4780 | C51: Third-party services (distribution) | E51: 0 | F51: -17280
C53: Miscellaneous operating costs
A54: 7021 | B54: 4900 | C54: Other operating expenses | D54: -1783.71 | F54: -239.5 | H54: =D54*$K$4 -> -1902.3199
A55: 7021 | B55: 4920 | C55: Telephone | D55: 0 | F55: -648.57 | H55: =D55*$K$4 -> 0
A56: 7021 | B56: 4930 | C56: Office supplies | D56: 0 | F56: -131.9 | H56: =D56*$K$4 -> 0
A57: 7021 | B57: 4950 | C57: Legal and consulting expenses | D57: -1220.42 | F57: -820 | H57: =D57*$K$4 -> -1301.5732
A58: 7021 | B58: 4955 | C58: Bookkeeping expenses | D58: -1809.1 | H58: =D58*$K$4 -> -1929.3982
A59: 7021 | B59: 4957 | C59: Period-end closing and audit costs | D59: -300 | F59: -2355.3 | H59: =D59*$K$4 -> -319.94885
A60: 7021 | B60: 4970 | C60: Incidental monetary transaction costs | D60: -328.23 | E60: =SUM(D54:D60) -> -5441.46 | F60: -237.88 | H60: =D60*$K$4 -> -350.05604
H61: =SUM(H54:H60) -> -5803.2962
C62: Other interest and similar income
A63: 7900 | B63: 2650 | C63: Other interest and similar income | E63: 0 | H63: =E63*$K$4 -> 0
A66: 7901 | B66: 9004 | C66: Exchange rate | H66: =-('GMBH BS 31.12.2022'!J48+'GMBH BS 31.12.2022'!J51) -> -3237.8159
C68: Interest and similar expenses
A69: 7901 | B69: 2105 | C69: Int. expns. sec 233a AO, non-deductible | E69: 0 | F69: 0 | H69: =E69*$K$4 -> 0
C71: Taxes on income
A72: 7028 | B72: 2200 | C72: Corporate income tax | D72: -1164 | F72: 0 | H72: =D72*$K$4 -> -1241.4015
A73: 7028 | B73: 2208 | C73: Solidarity surcharge | D73: -64 | H73: =D73*$K$4 -> -68.255754
A74: 7028 | B74: 4320 | C74: Trade tax | D74: -583.5 | E74: =SUM(D72:D74) -> -1811.5 | H74: =D74*$K$4 -> -622.30051
H75: =SUM(H72:H74) -> -1931.9578
C77: Net income for the financial year
C78: Net income for the financial year | D78: =E12+E20+E24+E48+E60+E74+E40+E31 -> 31350.29 | F78: 11407.34 | H78: =H12+H15+H20+H24+H40+H49+H61+H63+H66+H75+H32 -> 30197.148 | I78: =D78*K4+H66-H78 -> 0 | L78: 25850.89 | M78: =D78-L78 -> 5499.4

Sheet Prepaid expenses
C1: =DATE -> 44926 | D1: ='Master Data (do not print)'!B23 -> 3.519 | E1: דולר
D2: ='Master Data (do not print)'!B24 -> 3.753 | E2: אירו
D3: ='GMBH P&L 12.2022'!K4 -> 1.0664962 | E3: יחס
A4: Prepaid expenses | J4: הרכב אחרי סגירת דוח שנתי
A5: פרטים | C5: תאריך תחילה | D5: תאריך סיום | E5: תאריך חתך | F5: סה"כ ימים | G5: יתרת ימים | H5: סכום מקורי דולר | I5: יתרת סגירה הוצאות מראש (מחושב, צ"ל) | J5: יתרה שנה קודמת + רישום שוטף (SAP) | K5: להפחתה החודש | L5: מס' חשבון
A6: MARSH | C6: 44454 | D6: 45550 | E6: =$C$1 -> 44926 | F6: =+D6-C6+1 -> 1097 | G6: =IF(D6<E6,0,D6-E6) -> 624 | H6: 99960 | I6: =IF(G6>0,H6*G6/F6,0) -> 56859.654 | J6: 59684.412 | K6: =J6-I6 -> 2824.7584 | L6: 8019 | N6: =SUM(K6:K6) -> 2824.7584 | O6: 8019
I7: =SUM(I6:I6) -> 56859.654 | J7: =SUM(J6:J6) -> 59684.412 | K7: =SUM(K6:K6) -> 2824.7584
I8: =I7*$D$3 -> 60640.602 | J8: 61821.326 | K8: =I8-J8 -> -1180.7232 | L8: 6003
K9: =I8-J8 -> -1180.7232
C11: הוצאות מראש בגין ביטוח מוצר של MARSH לתקופה של 15.09.21-15.09-24
A13: הוצאות הנפקה
A14: ספק-שבלת ושות'
I16: שע"ח
A17: חשבונת מס/קבלה | B17: תאריך | C17: סה"כ לפני הנחה | D17: מיוחס להוצאות הנפקה | E17: הוצאות הנפקה אחרי הנחה של 20% | F17: הפרשים | G17: סה"כ אחרי הנחה | H17: הערות
A18: 80394 | B18: 44116 | C18: 5282.5 | D18: 1725 | E18: =D18*0.8 -> 1380 | F18: 3000 | G18: =0.8*(C18-F18) -> 1826 | H18: הפרשי חודש ספטמבר-20 | I18: 3.383
A19: 80394 | B19: 44116 | C19: 24981.25 | D19: 24981.25 | E19: =D19*0.8 -> 19985 | F19: 3000 | G19: =0.8*(C19-F19) -> 17585 | H19: הפרשי חודש אוגוסט-20 | I19: 3.383
A20: 80394 | B20: 44116 | C20: 2000 | D20: - | F20: - | G20: =C20 -> 2000 | H20: רייטינר 9-20 | I20: 3.383
A21: 81223 | B21: 44143 | C21: 2000 | D21: - | F21: - | G21: =C21 -> 2000 | H21: רייטינר 10-20 | I21: 3.377
C23: =SUM(C18:C22) -> 34263.75 | D23: =SUM(D18:D22) -> 26706.25 | E23: =D23*0.8 -> 21365 | G23: =SUM(G18:G22) -> 23411
E25: =E23*I18 -> 72277.795

Sheet Kontennachweis zur Bilanz
A1: Interim Balance Sheet Accounts as at 31/03/2022
A3: Aurora Labs Germany GmbH Entwicklung und Vertrieb von Software, München
A6: ASSETS
A7: Account | B7: Description | C7: EUR | D7: Financial Year EUR | E7: Prior Year EUR
B13: Noncurrent assets
A14: 490 | B14: Other operating and office equipment | D14: 1.00 | E14: 211.75
B16: Current assets
A17: 1200 | B17: Bank | C17: 2,399.29 | E17: 1,285.12
A18: 1410 | B18: Trade receivables | C18: 45,754.26 | E18: 45,067.52
A19: 1540 | B19: Receivables from trade tax overpaymts | C19: 0.00 | E19: 324.50
A20: 1548 | B20: Input tax ded. following period/year | C20: 0.00 | E20: 171.32
A21: 1549 | B21: Reclaimed corporate income tax | C21: 0.00 | E21: 205.82
A22: 1736 | B22: Liabilities from taxes and levies | C22: 155.08 | E22: 0.00
A23: 1791 | B23: VAT, earlier years | C23: 0.00 | E23: 2,270.97
C24: 48,308.63 | E24: 49,325.25
A26: 1570 | B26: Deductible input tax | C26: 149.46 | E26: 0.00
A27: 1576 | B27: Deductible input tax 19% | C27: 638.97 | E27: 1,480.10
A28: 1790 | B28: VAT, previous year | C28: 3,078.63 | E28: 771.66
C29: 3,867.06 | E29: 2,251.76
D31: 52,175.69 | E31: 51,577.01
B33: Prepaid expenses
A34: 980 | B34: Prepaid expenses | D34: 324.50 | E34: 0.00
D36: 52,501.19 | E36: 51,788.76
A42: TOTAL EQUITY AND LIABILITIES
A43: Account | B43: Description | C43: EUR | D43: Financial Year EUR | E43: Prior Year EUR
B49: Equity
B50: Net income for the financial year | C50: 2,383.31 | E50: 2,425.06
A51: 800 | B51: Subscribed capital | C51: 25,000.00 | E51: 25,000.00
A52: 860 | B52: Retained profits bef apprprtn net profit | C52: 24,578.41 | E52: 17,586.45
D53: 51,961.72 | E53: 45,011.51
B55: Provisions
A56: 956 | B56: Provision for trade tax, EStG s. 4(5b) | C56: 73.00 | E56: 0.00
A57: 963 | B57: Provisions for corporate income tax | C57: 293.47 | E57: 1,187.93
A58: 970 | B58: Other provisions | C58: 172.00 | E58: 0.00
A59: 977 | B59: Provsns period-end closing/ audit costs | C59: 0.00 | E59: 3,250.00
D60: 538.47 | E60: 4,437.93
B62: Liabilities
A63: 1610 | B63: Trade pybls, no sep. rec./pybls accntng | C63: 0.00 | E63: 2,306.12
A64: 1741 | B64: Wage and church tax payables | C64: 1.00 | E64: 0.00
D65: 1.00 | E65: 2,306.12
B67: of which remaining term up to 1 year EUR 1.00 (EUR 2,306.12)
A68: 1610 | B68: Trade pybls, no sep. rec./pybls accntng
A69: 1741 | B69: Wage and church tax payables
B71: Other equity and liabilities
A72: 1525 | B72: Security deposits | D72: 0.00 | E72: 33.20
D74: 52,501.19 | E74: 51,788.76

Sheet GMBH BS 31.08.2020
B1: INTERIM BALANCE SHEET
B2: ACCOUNTS as at | I2: 3.362 | J2: שע"ח $ 31.07.20
B3: 31.08.2020 | I3: 4.0126 | J3: שע"ח יורו 31.07.20
I4: =I3/I2 -> 1.1935158 | J4: יחס
B5: Aurora Labs Germany GmbH Entwicklung und Vertrieb von Software, Unterschleißheim
B7: ASSETS
E9: Financial year | F9: Previous year
B10: Account | C10: Description | D10: EUR | E10: EUR | F10: EUR | H10: $
C12: Other equipment, operating and office equipment
A13: 1904 | B13: 490 | C13: Other operating and office equipment | E13: 457.84 | F13: 844.67 | H13: =E13*$I$4 -> 546.43926
C15: Trade receivables
A16: 1351 | B16: 1410 | C16: Trade receivables | E16: 41282.25 | F16: 24572.76 | H16: =E16*$I$4 -> 49271.016
C18: Other assets
A19: 1307 | B19: 1525 | C19: Security deposits | D19: 1119.62 | F19: 1119.62 | H19: =D19*$I$4 -> 1336.2841
B20: 1570 | C20: Deductible input tax | D20: 0 | F20: 165.72 | H20: =D20*$I$4 -> 0
B21: 1571 | C21: Deductible input tax, 7% | D21: 0 | F21: 156.27 | H21: =D21*$I$4 -> 0
A22: 1357 | B22: 1575 | D22: 97.75 | F22: 0 | H22: =D22*$I$4 -> 116.66617
A23: 1357 | B23: 1576 | C23: Deductible input tax, 19% | D23: 3152.25 | F23: 6120.1 | H23: =D23*$I$4 -> 3762.2601
A24: 1357 | B24: 1780 | C24: VAT prepayments | D24: -3136.8 | F24: -4184.05 | H24: =D24*$I$4 -> -3743.8202
A25: 1357 | B25: 1790 | C25: VAT, previous year | D25: 2270.97 | E25: 3503.79 | F25: 536.28 | H25: =D25*$I$4 -> 2710.4385
H26: =SUM(H19:H25) -> 4181.8286
C27: Cash-in-hand, central bank balances, bank balances and cheques
A28: 1307 | B28: 1200 | C28: Bank | E28: 381.77 | F28: 34082.9 | H28: =E28*$I$4 -> 455.64851
C30: Other assets
A31: 1358 | B31: 977 | C31: Provsns period-end closing/ audit costs | E31: 2959.4 | F31: 0 | H31: =E31*$I$4 -> 3532.0906
C34: Total assets | E34: 48585.05 | F34: 63414.27 | H34: =H31+H28+H26+H16+H13 -> 57987.023
B36: EQUITY AND LIABILITIES
E38: Financial year | F38: Previous year
B39: Account | C39: Description | D39: EUR | E39: EUR | F39: EUR
C41: Subscribed capital | I41: י.פ. | J41: הפרשי שער
A42: 1842 | B42: 800 | C42: Subscribed capital | E42: 25000 | F42: 25000 | H42: =E42*$I$4 -> 29837.894 | I42: 28054 | J42: =I42-H42 -> -1783.8941 | K42: הכנסות
C44: Retained profits brought forward | I44: י.פ. | J44: הפרשי שער
A45: 9410 | B45: 860 | C45: Retained profits bef apprprtn net profit | E45: 11943.69 | F45: 6553.33 | H45: =E45*$I$4 -> 14254.982 | I45: 13158 | J45: =I45-H45 -> -1096.9823 | K45: הכנסות
C47: Net income for the financial year
C48: Net income for the financial year | E48: 3851.35 | F48: 8184.88 | H48: =E48*$I$4 -> 4596.6469 | I48: ='GMBH P&L 31.08.2020'!H69 -> 7477.5234
C50: Provisions for taxes
A51: 2688 | B51: 956 | C51: Provision for trade tax, EStG s. 4(5b) | D51: 1905 | F51: 1040 | H51: =D51*$I$4 -> 2273.6475
A52: 2688 | B52: 963 | C52: Provisions for corporate income tax | D52: 1187.93 | E52: 3092.93 | F52: 1436.91 | H52: =D52*$I$4 -> 1417.8132
H53: =SUM(H51:H52) -> 3691.4607
C54: Other provisions
B55: 977 | C55: Provsns period-end closing/ audit costs | E55: 0 | F55: 2600
C57: Other liabilities
A58: 2689 | B58: 1700 | C58: Other liabilities | D58: 4697.08 | F58: 11776.42 | H58: =D58*$I$4 -> 5606.039
B59: 1701 | C59: Other liabilities due w/in 1 year | D59: 0 | F59: 5997.6 | H59: =D59*$I$4 -> 0
B60: 1741 | C60: Wage and church tax payables | D60: 0 | E60: 4697.08 | F60: 825.13 | H60: =D60*$I$4 -> 0
H61: =SUM(H58:H60) -> 5606.039
C62: of which taxes EUR 0,00 (EUR 825,13)
B63: 1741 | C63: Wage and church tax payables
C65: of which due within one year EUR 4.697,08 (EUR 18.599,15)
B66: 1700 | C66: Other liabilities
B67: 1701 | C67: Other liabilities due w/in 1 year
B68: 1741 | C68: Wage and church tax payables
C71: Total equity and liabilities | E71: 48585.05 | F71: 63414.27 | H71: =H61+H53+I48+I45+I42 -> 57987.023 | I71: =E71*I4-H71 -> 0
B76: 1

Sheet GMBH P&L 31.08.2020
B2: Income statement | I2: 3.362 | J2: שע"ח $ 31.07.20
B3: ACCOUNTS from | I3: 4.0126 | J3: שע"ח יורו 31.07.20
B4: 01.01.2020 to 31.08.2020 | I4: =I3/I2 -> 1.1935158 | J4: יחס
B6: Aurora Labs Germany GmbH Entwicklung und Vertrieb von Software, Unterschleißheim
E9: Financial year | F9: Previous year
B10: Account | C10: Description | D10: EUR | E10: EUR | F10: EUR | H10: $
C12: Sales
A13: 7023 | B13: 8338 | C13: Tax-exempt sales 3rd country | E13: 37165.57 | F13: 110495.71 | H13: =E13*$I$4 -> 44357.694
C15: Income from reversal of provisions
A16: 7021 | B16: 2735 | C16: Income from reversal of provisions | E16: 1479.7 | F16: 0 | H16: =E16*$I$4 -> 1766.0453
C18: Wages and salaries
A19: 7020 | B19: 4100 | C19: Wages and salaries | E19: -17333.32 | F19: -57333.32 | H19: =E19*$I$4 -> -20687.591
C21: Social security, post-employment and other employee benefit costs
A22: 7020 | B22: 4130 | C22: Statutory social security expenses | D22: -3848.88 | F22: -8661.4 | H22: =D22*$I$4 -> -4593.699
A23: 7020 | B23: 4138 | C23: Contrb. to occup. health/safety agency | D23: -171.23 | E23: -4020.11 | F23: 0 | H23: =D23*$I$4 -> -204.3657
H24: =SUM(H22:H23) -> -4798.0647
C25: Depreciation, amortisation and write-downs
C27: Amortisation and write-downs of intangible fixed assets and depreciation and write downs of tangible fixed assets
A28: 7021 | B28: 4830 | C28: Depreciation of tangible fixed assets | E28: -246.16 | F28: -281.33 | H28: =E28*$I$4 -> -293.79584
C30: Occupancy costs
A31: 7021 | B31: 4210 | C31: Rent (immovable property) | E31: -3293.01 | F31: -3763.44 | H31: =E31*$I$4 -> -3930.2593
C33: Insurance premiums, fees and contributions
A34: 7020 | B34: 4396 | C34: Late filing penalties/ admin. fines | E34: -25 | F34: 0 | H34: =E34*$I$4 -> -29.837894
C36: Advertising and travel expenses
A37: 7026 | B37: 4600 | C37: Advertising expenses | D37: -8400 | F37: -21279.72 | H37: =D37*$I$4 -> -10025.532
B38: 4650 | C38: Entertainment expenses | D38: 0 | F38: -234.96 | H38: =D38*$I$4 -> 0
B39: 4660 | C39: Employee travel expenses | D39: 0 | F39: -529.7 | H39: =D39*$I$4 -> 0
B40: 4663 | C40: Employee travel expnses, cost of travel | D40: 0 | F40: -596.11 | H40: =D40*$I$4 -> 0
B41: 4664 | C41: Employee trav. expn, addnl substnc costs | D41: 0 | F41: -137 | H41: =D41*$I$4 -> 0
B42: 4666 | C42: Employee trav. expn, accommodation costs | D42: 0 | F42: -1871.98 | H42: =D42*$I$4 -> 0
B43: 4668 | C43: Employee mileage reimbursement | D43: 0 | E43: -8400 | F43: -288 | H43: =D43*$I$4 -> 0
H44: =SUM(H37:H43) -> -10025.532
C45: Selling and distribution expenses
B46: 4780 | C46: Third-party services (distribution) | E46: 0 | F46: -5040
C48: Miscellaneous operating costs
B49: 4900 | C49: Other operating expenses | D49: 0 | F49: -239.5 | H49: =D49*$I$4 -> 0
A50: 7021 | B50: 4920 | C50: Telephone | D50: -583.51 | F50: -346.64 | H50: =D50*$I$4 -> -696.42838
A51: 7021 | B51: 4950 | C51: Legal and consulting expenses | D51: -232.1 | F51: -820 | H51: =D51*$I$4 -> -277.01501
A52: 7021 | B52: 4955 | C52: Bookkeeping expenses | D52: -33.4 | F52: -734 | H52: =D52*$I$4 -> -39.863427
A53: 7021 | B53: 4970 | C53: Incidental monetary transaction costs | D53: -251.42 | E53: -1100.43 | F53: -153.73 | H53: =D53*$I$4 -> -300.07373
H54: =SUM(H49:H53) -> -1313.3806
A57: 7901 | B57: 9004 | C57: Exchange rate | H57: =-('GMBH BS 31.08.2020'!J42+'GMBH BS 31.08.2020'!J45) -> 2880.8764
C64: Taxes on income
A65: 7028 | B65: 2200 | C65: Corporate income tax | E65: -375.89 | F65: 0 | H65: =E65*$I$4 -> -448.63064
C68: Net income for the financial year
C69: Net income for the financial year | E69: 3851.35 | F69: 8184.88 | H69: =H13+H16+H19+H24+H28+H31+H34+H44+H54+H65+H57 -> 7477.5234 | I69: =E69*I4-H69+H57 -> 3.6379788e-12

Sheet GMBH BS 31.10.2020
B2: INTERIM BALANCE SHEET
B3: ACCOUNTS as at | I3: 3.422 | J3: שע"ח $ 31.10.20
B4: 30.09.2020 | I4: 3.9938 | J4: שע"ח יורו 31.10.20
I5: 1.1935158 | J5: יחס
B6: Aurora Labs Germany GmbH Entwicklung und Vertrieb von Software, Unterschleißheim
B8: ASSETS
E10: Financial year | F10: Previous year
B11: Account | C11: Description | D11: EUR | E11: EUR | F11: EUR | H11: $
C13: Other equipment, operating and office equipment
A14: 1904 | B14: 490 | C14: Other operating and office equipment | E14: 352.34 | F14: 774.34 | H14: =E14*$I$5 -> 420.52334
C16: Trade receivables
A17: 1351 | B17: 1410 | C17: Trade receivables | E17: 38866.29 | F17: 58712.41 | H17: =E17*$I$5 -> 46387.53
C19: Other assets
A20: 1355 | B20: 1525 | C20: Security deposits | D20: 1119.62 | F20: 1119.62 | H20: =D20*$I$5 -> 1336.2841
A21: 2688 | B21: 1540 | C21: Receivables from trade tax overpaymts | D21: 173.5 | F21: 0 | H21: =D21*$I$5 -> 207.07499
B22: 1570 | C22: Deductible input tax | D22: 0 | F22: 165.72 | H22: =D22*$I$5 -> 0
B23: 1571 | C23: Deductible input tax, 7% | D23: 0 | F23: 209.4 | H23: =D23*$I$5 -> 0
A24: 1357 | B24: 1575 | C24: Deductible input tax 16% | D24: 343.8 | F24: 0 | H24: =D24*$I$5 -> 410.33072
A25: 1357 | B25: 1576 | C25: Deductible input tax 19% | D25: 3152.25 | F25: 9630.57 | H25: =D25*$I$5 -> 3762.2601
A26: 1357 | B26: 1780 | C26: VAT prepayments | D26: -3136.8 | F26: -6442.09 | H26: =D26*$I$5 -> -3743.8202
A27: 1357 | B27: 1790 | C27: VAT, previous year | D27: 2270.97 | E27: 3923.34 | F27: 536.28 | H27: =D27*$I$5 -> 2710.4385
H28: =SUM(H20:H27) -> 4682.5681
C29: Cash-in-hand, central bank balances, bank balances and cheques
A30: 1307 | B30: 1200 | C30: Bank | E30: 137.53 | F30: 4142.58 | H30: =E30*$I$5 -> 164.14422
C32: Other assets
A33: 1358 | B33: 977 | C33: Provsns period-end closing/ audit costs | E33: 2959.4 | F33: 0 | H33: =E33*$I$5 -> 3532.0906
C36: Total assets | E36: 46238.9 | F36: 68848.83 | H36: =H33+H30+H28+H17+H14 -> 55186.856 | I36: =E36*I5-H36 -> 0
B38: EQUITY AND LIABILITIES
E40: Financial year | F40: Previous year
B41: Account | C41: Description | D41: EUR | E41: EUR | F41: EUR
C43: Subscribed capital | I43: י.פ. | J43: הפרשי שער
A44: 1842 | B44: 800 | C44: Subscribed capital | E44: 25000 | F44: 25000 | H44: =E44*$I$5 -> 29837.894 | I44: 28054 | J44: =I44-H44 -> -1783.8941 | K44: הכנסות
I45: י.פ. | J45: הפרשי שער
C46: Retained profits brought forward
A47: 9410 | B47: 860 | C47: Retained profits bef apprprtn net profit | E47: 11943.69 | F47: 6553.33 | H47: =E47*$I$5 -> 14254.982 | I47: 13158 | J47: =I47-H47 -> -1096.9823 | K47: הכנסות
C49: Net income for the financial year
C50: Net income for the financial year | E50: 3410.2 | F50: 10713.75 | H50: =E50*$I$5 -> 4070.1275 | I50: ='GMBH P&L 31.10.2020'!H66 -> 6951.0039
C52: Provisions for taxes
B53: 956 | C53: Provision for trade tax, EStG s. 4(5b) | D53: 0 | F53: 1040 | H53: =D53*$I$5 -> 0
A54: 2688 | B54: 963 | C54: Provisions for corporate income tax | D54: 1187.93 | E54: 1187.93 | F54: 1436.91 | H54: =D54*$I$5 -> 1417.8132
H55: =SUM(H53:H54) -> 1417.8132
C56: Other provisions
B57: 977 | C57: Provsns period-end closing/ audit costs | E57: 0 | F57: 2600
C59: Other liabilities
A60: 2689 | B60: 1700 | C60: Other liabilities | D60: 4697.08 | F60: 13920.51 | H60: =D60*$I$5 -> 5606.039
B61: 1701 | C61: Other liabilities due w/in 1 year | D61: 0 | F61: 6759.2 | H61: =D61*$I$5 -> 0
B62: 1741 | C62: Wage and church tax payables | D62: 0 | E62: 4697.08 | F62: 825.13 | H62: =D62*$I$5 -> 0
H63: =SUM(H60:H62) -> 5606.039
C64: of which taxes EUR 0,00 (EUR 825,13)
B65: 1741 | C65: Wage and church tax payables
C67: of which due within one year EUR 4.697,08 (EUR 21.504,84)
B68: 1700 | C68: Other liabilities
B69: 1701 | C69: Other liabilities due w/in 1 year
B70: 1741 | C70: Wage and church tax payables
C73: Total equity and liabilities | E73: 46238.9 | F73: 68848.83 | H73: =H63+H55+I47+I50+I44 -> 55186.856 | I73: =E73*I5-H73 -> 0

Sheet GMBH P&L 31.10.2020
B1: Income statement
B2: ACCOUNTS from | H2: 3.441 | I2: שע"ח $ 30.09.20
B3: 01.01.2020 to 30.09.2020 | H3: 4.0258 | I3: שע"ח יורו 30.09.20
H4: 1.1935158 | I4: יחס
B5: Aurora Labs Germany GmbH Entwicklung und Vertrieb von Software, Unterschleißheim
E8: Financial year | F8: Previous year | H8: $
B9: Account | C9: Description | D9: EUR | E9: EUR | F9: EUR
C11: Sales
A12: 7023 | B12: 8338 | C12: Tax-exempt sales 3rd country | E12: 38510.21 | F12: 144635.36 | H12: =E12*$H$4 -> 45962.543
C14: Income from reversal of provisions
A15: 7021 | B15: 2735 | C15: Income from reversal of provisions | E15: 1479.7 | F15: 0 | H15: =E15*$H$4 -> 1766.0453
C17: Wages and salaries
A18: 7020 | B18: 4100 | C18: Wages and salaries | E18: -17333.32 | F18: -65999.98 | H18: =E18*$H$4 -> -20687.591
C20: Social security, post-employment and other employee benefit costs
A21: 7020 | B21: 4130 | C21: Statutory social security expenses | D21: -3848.88 | F21: -10581.5 | H21: =D21*$H$4 -> -4593.699
A22: 7020 | B22: 4138 | C22: Contrb. to occup. health/safety agency | D22: -171.23 | E22: -4020.11 | F22: -156.2 | H22: =D22*$H$4 -> -204.3657
H23: =SUM(H21:H22) -> -4798.0647
C24: Depreciation, amortisation and write-downs
C26: Amortisation and write-downs of intangible fixed assets and depreciation and write downs of tangible fixed assets
A27: 7021 | B27: 4830 | C27: Depreciation of tangible fixed assets | E27: -351.66 | F27: -351.66 | H27: =E27*$H$4 -> -419.71175
C29: Occupancy costs
A30: 7021 | B30: 4210 | C30: Rent (immovable property) | E30: -4704.3 | F30: -4704.3 | H30: =E30*$H$4 -> -5614.6562
C32: Insurance premiums, fees and contributions
A33: 7020 | B33: 4396 | C33: Late filing penalties/ admin. fines | E33: -50 | F33: 0 | H33: =E33*$H$4 -> -59.675788
C35: Advertising and travel expenses
A36: 7026 | B36: 4600 | C36: Advertising expenses | D36: -8400 | F36: -24449.72 | H36: =D36*$H$4 -> -10025.532
B37: 4650 | C37: Entertainment expenses | D37: 0 | F37: -234.96 | H37: =D37*$H$4 -> 0
B38: 4660 | C38: Employee travel expenses | D38: 0 | F38: -937.19 | H38: =D38*$H$4 -> 0
B39: 4663 | C39: Employee travel expnses, cost of travel | D39: 0 | F39: -1700.42 | H39: =D39*$H$4 -> 0
B40: 4664 | C40: Employee trav. expn, addnl substnc costs | D40: 0 | F40: -305 | H40: =D40*$H$4 -> 0
B41: 4666 | C41: Employee trav. expn, accommodation costs | D41: 0 | F41: -2245.81 | H41: =D41*$H$4 -> 0
B42: 4668 | C42: Employee mileage reimbursement | D42: 0 | E42: -8400 | F42: -612.6 | H42: =D42*$H$4 -> 0
H43: =SUM(H36:H42) -> -10025.532
C44: Selling and distribution expenses
B45: 4780 | C45: Third-party services (distribution) | E45: 0 | F45: -17280
C47: Miscellaneous operating costs
B48: 4900 | C48: Other operating expenses | D48: 0 | F48: -239.5 | H48: =D48*$H$4 -> 0
A49: 7021 | B49: 4920 | C49: Telephone | D49: -709.95 | F49: -595.64 | H49: =D49*$H$4 -> -847.33652
B50: 4930 | C50: Office supplies | D50: 0 | F50: -131.9 | H50: =D50*$H$4 -> 0
A51: 7021 | B51: 4950 | C51: Legal and consulting expenses | D51: -232.1 | F51: -820 | H51: =D51*$H$4 -> -277.01501
A52: 7021 | B52: 4955 | C52: Bookkeeping expenses | D52: -33.4 | F52: -2355.3 | H52: =D52*$H$4 -> -39.863427
A53: 7021 | B53: 4970 | C53: Incidental monetary transaction costs | D53: -348.98 | E53: -1324.43 | F53: -219.93 | H53: =D53*$H$4 -> -416.51313
H54: =SUM(H48:H53) -> -1580.7281
A56: 7901 | B56: 9004 | C56: Exchange rate | H56: =-('GMBH BS 31.10.2020'!J44+'GMBH BS 31.10.2020'!J47) -> 2880.8764
C58: Interest and similar expenses
A59: 7901 | B59: 2105 | C59: Int. expns. sec 233a AO, non-deductible | E59: -20 | F59: 0 | H59: =E59*$H$4 -> -23.870315
C61: Taxes on income
A62: 7028 | B62: 2200 | C62: Corporate income tax | E62: -375.89 | F62: 0 | H62: =E62*$H$4 -> -448.63064
C65: Net income for the financial year
C66: Net income for the financial year | E66: 3410.2 | F66: 10713.75 | H66: =H62+H54+H43+H33+H30+H27+H23+H18+H15+H12+H56+H59 -> 6951.0039 | I66: =E66*H4-H66+H56 -> 4.0927262e-12

Sheet GMBH BS 30.06.2020
B2: INTERIM BALANCE SHEET | I2: 3.466 | J2: שע"ח $ 31.05.20
B3: ACCOUNTS as at | I3: 3.8828 | J3: שע"ח יורו 31.05.20
B4: 30.06.2020 | I4: =I3/I2 -> 1.1202539 | J4: יחס
B6: Aurora Labs Germany GmbH Entwicklung und Vertrieb von Software, Unterschleißheim
B8: ASSETS
E10: Financial year | F10: Previous year
B11: Account | C11: Description | D11: EUR | E11: EUR | F11: EUR | H11: $
C13: Other equipment, operating and office equipment
A14: 1904 | B14: 490 | C14: Other operating and office equipment | E14: 493.01 | F14: 1126 | H14: =E14*$I$4 -> 552.29637
C16: Trade receivables
A17: 1351 | B17: 1410 | C17: Trade receivables | E17: 40440.25 | F17: 43511.19 | H17: =E17*I4 -> 45303.348 | I17: חו"ז בינחברתי
C19: Other assets
A20: 1307 | B20: 1525 | C20: Security deposits | D20: 1119.62 | F20: 1119.62 | H20: =D20*$I$4 -> 1254.2587
B21: 1570 | C21: Deductible input tax | D21: 0 | F21: 165.72 | H21: =D21*$I$4 -> 0
B22: 1571 | C22: Deductible input tax, 7% | D22: 0 | F22: 156.27 | H22: =D22*$I$4 -> 0
A23: 1357 | B23: 1576 | C23: Deductible input tax, 19% | D23: 3152.25 | F23: 3862.06 | H23: =D23*$I$4 -> 3531.3203
B24: 1590 | C24: Items in transit | D24: 0 | F24: 78.4 | H24: =D24*$I$4 -> 0
A25: 1357 | B25: 1780 | C25: VAT prepayments | D25: -2941.02 | F25: -2455.95 | H25: =D25*$I$4 -> -3294.6891
A26: 1357 | B26: 1790 | C26: VAT, previous year | D26: 2270.97 | E26: 3601.82 | F26: 2526.32 | H26: =D26*$I$4 -> 2544.063
H27: =SUM(H20:H26) -> 4034.9529
C28: Cash-in-hand, central bank balances, bank balances and cheques
A29: 1307 | B29: 1200 | C29: Bank | E29: 994.79 | F29: 5221.93 | H29: =E29*$I$4 -> 1114.4174
C31: Other assets
A32: 1358 | B32: 975 | D32: 66.8 | F32: 0 | H32: =D32*$I$4 -> 74.83296
A33: 1358 | B33: 977 | C33: Provsns period-end closing/ audit costs | D33: 2959.4 | E33: 3026.2 | F33: 0 | H33: =D33*$I$4 -> 3315.2794
H34: =SUM(H32:H33) -> 3390.1123
C36: Total assets | E36: 48556.07 | F36: 55311.56 | H36: =H34+H29+H27+H17+H14 -> 54395.127 | I36: =E36*I4-H36 -> 0
B38: EQUITY AND LIABILITIES
E40: Financial year | F40: Previous year
B41: Account | C41: Description | D41: EUR | E41: EUR | F41: EUR
C43: Subscribed capital | I43: י.פ. | J43: הפרשי שער
A44: 1842 | B44: 800 | C44: Subscribed capital | E44: 25000 | F44: 25000 | H44: =E44*$I$4 -> 28006.347 | I44: 28054 | J44: =I44-H44 -> 47.652626
C46: Retained profits brought forward | I46: י.פ. | J46: הפרשי שער
A47: 9410 | B47: 860 | C47: Retained profits bef apprprtn net profit | E47: 11943.69 | F47: 6553.33 | H47: =E47*$I$4 -> 13379.965 | I47: 13158 | J47: =I47-H47 -> -221.96524
C49: Net income for the financial year
C50: Net income for the financial year | E50: 3822.37 | F50: 6364.67 | H50: =E50*$I$4 -> 4282.0249 | I50: ='GMBH P&L 30.06.2020'!H59 -> 4456.3365
C52: Provisions for taxes
A53: 2688 | B53: 956 | C53: Provision for trade tax, EStG s. 4(5b) | D53: 1905 | F53: 1040 | H53: =D53*$I$4 -> 2134.0837
A54: 2688 | B54: 963 | C54: Provisions for corporate income tax | D54: 1187.93 | E54: 3092.93 | F54: 1436.91 | H54: =D54*$I$4 -> 1330.7832
H55: =SUM(H53:H54) -> 3464.8669
C56: Other provisions
B57: 977 | C57: Provsns period-end closing/ audit costs | E57: 0 | F57: 2600
C59: Other liabilities
A60: 2689 | B60: 1700 | C60: Other liabilities | D60: 4697.08 | F60: 10689.59 | H60: =D60*$I$4 -> 5261.9222
B61: 1701 | C61: Other liabilities due w/in 1 year | D61: 0 | F61: 1165.23 | H61: =D61*$I$4 -> 0
B62: 1741 | C62: Wage and church tax payables | D62: 0 | E62: 4697.08 | F62: 461.83 | H62: =D62*$I$4 -> 0
H63: =SUM(H60:H62) -> 5261.9222
C64: of which taxes EUR 0,00 (EUR 461,83)
B65: 1741 | C65: Wage and church tax payables
C67: of which due within one year EUR 4.697,08 (EUR 12.316,65)
B68: 1700 | C68: Other liabilities
B69: 1701 | C69: Other liabilities due w/in 1 year
B70: 1741 | C70: Wage and church tax payables
C73: Total equity and liabilities | E73: 48556.07 | F73: 55311.56 | H73: =I44+I47+I50+H55+H63 -> 54395.126 | I73: =E73*I4-H73 -> 0.0010364144
H76: =H73-H36 -> -0.0010364144

Sheet GMBH P&L 30.06.2020
B1: Income statement
B2: ACCOUNTS from | J2: 3.5092 | K2: שע"ח ממצוע $ 1-6.2020
B3: 01.01.2020 to 30.06.2020 | J3: 3.8616 | K3: שע"ח ממצוע יורו 1-6.2020
J4: =J3/J2 -> 1.1004217 | K4: יחס
B5: Aurora Labs Germany GmbH Entwicklung und Vertrieb von Software, Unterschleißheim
E8: Financial year | F8: Previous year
B9: Account | C9: Description | D9: EUR | E9: EUR | F9: EUR | H9: $
C11: Sales
A12: 7023 | B12: 8338 | C12: Tax-exempt sales 3rd country | E12: 36323.57 | F12: 85922.95 | H12: =E12*$J$4 -> 39971.246
C14: Income from reversal of provisions
A15: 7021 | B15: 2735 | C15: Income from reversal of provisions | E15: 1513.1 | F15: 0 | H15: =E15*$J$4 -> 1665.0481
C17: Wages and salaries
A18: 7020 | B18: 4100 | C18: Wages and salaries | E18: -17333.32 | F18: -48666.66 | H18: =E18*$J$4 -> -19073.962
C20: Social security, post-employment and other employee benefit costs
A21: 7020 | B21: 4130 | C21: Statutory social security expenses | D21: -3848.88 | F21: -6741.3 | H21: =D21*$J$4 -> -4235.3913
A22: 7020 | B22: 4138 | C22: Contrb. to occup. health/safety agency | D22: -171.23 | E22: -4020.11 | F22: 0 | H22: =D22*$J$4 -> -188.42522
H23: =SUM(H21:H22) -> -4423.8165
C24: Depreciation, amortisation and write-downs
C26: Amortisation and write-downs of intangible fixed assets and depreciation and write downs of tangible fixed assets
A27: 7021 | B27: 4830 | C27: Depreciation of tangible fixed assets | E27: -210.99 | F27: 0 | H27: =E27*$J$4 -> -232.17798
C29: Occupancy costs
A30: 7021 | B30: 4210 | C30: Rent (immovable property) | E30: -2822.58 | F30: -2822.58 | H30: =E30*$J$4 -> -3106.0284
C32: Insurance premiums, fees and contributions
A33: 7020 | B33: 4396 | C33: Late filing penalties/ admin. fines | E33: -25 | F33: 0 | H33: =E33*$J$4 -> -27.510544
C35: Advertising and travel expenses
A36: 7026 | B36: 4600 | C36: Advertising expenses | D36: -8400 | F36: -15429.72 | H36: =D36*$J$4 -> -9243.5427
B37: 4650 | C37: Entertainment expenses | D37: 0 | F37: -234.96 | H37: =D37*$J$4 -> 0
B38: 4660 | C38: Employee travel expenses | D38: 0 | F38: -529.7 | H38: =D38*$J$4 -> 0
B39: 4663 | C39: Employee travel expnses, cost of travel | D39: 0 | F39: -596.11 | H39: =D39*$J$4 -> 0
B40: 4664 | C40: Employee trav. expn, addnl substnc costs | D40: 0 | F40: -137 | H40: =D40*$J$4 -> 0
B41: 4666 | C41: Employee trav. expn, accommodation costs | D41: 0 | F41: -1871.98 | H41: =D41*$J$4 -> 0
B42: 4668 | C42: Employee mileage reimbursement | D42: 0 | E42: -8400 | F42: -288 | H42: =D42*$J$4 -> 0
H43: =SUM(H36:H42) -> -9243.5427
C44: Miscellaneous operating costs
B45: 4900 | C45: Other operating expenses | D45: 0 | F45: -239.5 | H45: =D45*$J$4 -> 0
A46: 7021 | B46: 4920 | C46: Telephone | D46: -443.02 | F46: -346.64 | H46: =D46*$J$4 -> -487.50884
A47: 7021 | B47: 4950 | C47: Legal and consulting expenses | D47: -232.1 | F47: -820 | H47: =D47*$J$4 -> -255.40789
B48: 4955 | C48: Bookkeeping expenses | D48: 0 | F48: -680.4 | H48: =D48*$J$4 -> 0
A49: 7021 | B49: 4970 | C49: Incidental monetary transaction costs | D49: -151.29 | E49: -826.41 | F49: -153.73 | H49: =D49*$J$4 -> -166.48281
H50: =SUM(H45:H49) -> -909.39954
A52: 7901 | B52: 9004 | C52: Exchange rate | H52: ='GMBH BS 30.06.2020'!J44+'GMBH BS 30.06.2020'!J47+424.43 -> 250.11738
C54: Taxes on income
A55: 7028 | B55: 2200 | C55: Corporate income tax | E55: -375.89 | F55: 0 | H55: =E55*$J$4 -> -413.63753
C58: Net income for the financial year
C59: Net income for the financial year | E59: 3822.37 | F59: 6364.67 | H59: =H12+H15+H18+H23+H27+H30+H33+H43+H50+H55+H52 -> 4456.3365 | I59: =E59*J4-H59+H52 -> 4.2632564e-12
K66: ;

Sheet GMBH BS 31.07.2020
B1: INTERIM BALANCE SHEET
B2: ACCOUNTS as at | I2: 3.408 | J2: שע"ח $ 31.07.20
B3: 31.07.2020 | I3: 4.0388 | J3: שע"ח יורו 31.07.20
I4: =I3/I2 -> 1.1850939 | J4: יחס
B5: Aurora Labs Germany GmbH Entwicklung und Vertrieb von Software, Unterschleißheim
B7: ASSETS
E9: Financial year | F9: Previous year
B10: Account | C10: Description | D10: EUR | E10: EUR | F10: EUR | H10: $
C12: Other equipment, operating and office equipment
A13: 1904 | B13: 490 | C13: Other operating and office equipment | E13: 457.84 | F13: 879.84 | H13: =E13*I4 -> 542.58339
C15: Trade receivables
A16: 1351 | B16: 1410 | C16: Trade receivables | E16: 41213.23 | F16: 31822.29 | H16: =E16*$I$4 -> 48841.547 | I16: חו"ז בינחברתי
C18: Other assets
A19: 1307 | B19: 1525 | C19: Security deposits | D19: 1119.62 | F19: 1119.62 | H19: =D19*$I$4 -> 1326.8548
B20: 1570 | C20: Deductible input tax | D20: 0 | F20: 165.72 | H20: =D20*$I$4 -> 0
B21: 1571 | C21: Deductible input tax, 7% | D21: 0 | F21: 156.27 | H21: =D21*$I$4 -> 0
A22: 1357 | B22: 1575 | D22: 87.63 | F22: 0 | H22: =D22*$I$4 -> 103.84978
A23: 1357 | B23: 1576 | C23: Deductible input tax, 19% | D23: 3152.25 | F23: 4530.94 | H23: =D23*$I$4 -> 3735.7122
B24: 1590 | C24: Items in transit | D24: 0 | F24: 78.4 | H24: =D24*$I$4 -> 0
A25: 1357 | B25: 1780 | C25: VAT prepayments | D25: -3049.17 | F25: -2455.95 | H25: =D25*$I$4 -> -3613.5528
A26: 1357 | B26: 1790 | C26: VAT, previous year | D26: 2270.97 | E26: 3581.3 | F26: 536.28 | H26: =D26*$I$4 -> 2691.3127
H27: =SUM(H19:H26) -> 4244.1768
C28: Cash-in-hand, central bank balances, bank balances and cheques
A29: 1307 | B29: 1200 | C29: Bank | E29: 368.16 | F29: 19567.97 | H29: =E29*$I$4 -> 436.30417
C31: Other assets
A32: 1358 | B32: 977 | C32: Provsns period-end closing/ audit costs | E32: 2959.4 | F32: 0 | H32: =E32*$I$4 -> 3507.1669
C35: Total assets | E35: 48579.93 | F35: 56401.38 | H35: =H32+H29+H27+H16+H13 -> 57571.779
B38: EQUITY AND LIABILITIES
E40: Financial year | F40: Previous year
B41: Account | C41: Description | D41: EUR | E41: EUR | F41: EUR
C43: Subscribed capital | I43: י.פ. | J43: הפרשי שער
A44: 1842 | B44: 800 | C44: Subscribed capital | E44: 25000 | F44: 25000 | H44: =E44*$I$4 -> 29627.347 | I44: 28054 | J44: =I44-H44 -> -1573.3474
C46: Retained profits brought forward | I46: י.פ. | J46: הפרשי שער
A47: 9410 | B47: 860 | C47: Retained profits bef apprprtn net profit | E47: 11943.69 | F47: 6553.33 | H47: =E47*$I$4 -> 14154.394 | I47: 13158 | J47: =I47-H47 -> -996.39412
C49: Net income for the financial year
C50: Net income for the financial year | E50: 3846.23 | F50: 7091.19 | H50: =E50*$I$4 -> 4558.1437 | I50: ='GMBH P&L 31.07.2020'!H59 -> 7127.8872
C52: Provisions for taxes
A53: 2688 | B53: 956 | C53: Provision for trade tax, EStG s. 4(5b) | D53: 1905 | F53: 1040 | H53: =D53*$I$4 -> 2257.6039
A54: 2688 | B54: 963 | C54: Provisions for corporate income tax | D54: 1187.93 | E54: 3092.93 | F54: 1436.91 | H54: =D54*$I$4 -> 1407.8086
H55: =SUM(H53:H54) -> 3665.4125
C56: Other provisions
B57: 977 | C57: Provsns period-end closing/ audit costs | E57: 0 | F57: 2600
C59: Other liabilities
A60: 2689 | B60: 1700 | C60: Other liabilities | D60: 4697.08 | F60: 10689.59 | H60: =D60*$I$4 -> 5566.4808
B61: 1701 | C61: Other liabilities due w/in 1 year | D61: 0 | F61: 1165.23 | H61: =D61*$I$4 -> 0
B62: 1741 | C62: Wage and church tax payables | D62: 0 | E62: 4697.08 | F62: 825.13 | H62: =D62*$I$4 -> 0
H63: =SUM(H60:H62) -> 5566.4808
C64: of which taxes EUR 0,00 (EUR 825,13)
B65: 1741 | C65: Wage and church tax payables
C67: of which due within one year EUR 4.697,08 (EUR 12.679,95)
B68: 1700 | C68: Other liabilities
B69: 1701 | C69: Other liabilities due w/in 1 year
B70: 1741 | C70: Wage and church tax payables
C73: Total equity and liabilities | E73: 48579.93 | F73: 56401.38 | H73: =H63+H55+I50+I47+I44 -> 57571.781
H77: =H73-H35 -> 0.0019951031

Sheet GMBH P&L 31.07.2020
B1: Income statement
B2: ACCOUNTS from | J2: 3.4984 | K2: שע"ח ממצוע $ 1-7.2020
B3: 01.01.2020 to 31.07.2020 | J3: 3.8714 | K3: שע"ח ממצוע יורו 1-7.2020
J4: =J3/J2 -> 1.1066202 | K4: יחס
B5: Aurora Labs Germany GmbH Entwicklung und Vertrieb von Software, Unterschleißheim
E8: Financial year | F8: Previous year | H8: $
B9: Account | C9: Description | D9: EUR | E9: EUR | F9: EUR
C11: Sales
A12: 7023 | B12: 8338 | C12: Tax-exempt sales 3rd country | E12: 37096.55 | F12: 95730.94 | H12: =E12*$J$4 -> 41051.79
C14: Income from reversal of provisions
A15: 7021 | B15: 2735 | C15: Income from reversal of provisions | E15: 1479.7 | F15: 0 | H15: =E15*$J$4 -> 1637.4659
C17: Wages and salaries
A18: 7020 | B18: 4100 | C18: Wages and salaries | E18: -17333.32 | F18: -52999.99 | H18: =E18*$J$4 -> -19181.402
C20: Social security, post-employment and other employee benefit costs
A21: 7020 | B21: 4130 | C21: Statutory social security expenses | D21: -3848.88 | F21: -7701.35 | H21: =D21*$J$4 -> -4259.2482
A22: 7020 | B22: 4138 | C22: Contrb. to occup. health/safety agency | D22: -171.23 | E22: -4020.11 | F22: 0 | H22: =D22*$J$4 -> -189.48657
H23: =SUM(H21:H22) -> -4448.7348
C24: Depreciation, amortisation and write-downs
C26: Amortisation and write-downs of intangible fixed assets and depreciation and write downs of tangible fixed assets
A27: 7021 | B27: 4830 | C27: Depreciation of tangible fixed assets | E27: -246.16 | F27: -246.16 | H27: =E27*$J$4 -> -272.40562
C29: Occupancy costs
A30: 7021 | B30: 4210 | C30: Rent (immovable property) | E30: -3293.01 | F30: -3293.01 | H30: =E30*$J$4 -> -3644.1113
C32: Insurance premiums, fees and contributions
A33: 7020 | B33: 4396 | C33: Late filing penalties/ admin. fines | E33: -25 | F33: 0 | H33: =E33*$J$4 -> -27.665504
C35: Advertising and travel expenses
A36: 7026 | B36: 4600 | C36: Advertising expenses | D36: -8400 | F36: -18479.72 | H36: =D36*$J$4 -> -9295.6094
B37: 4650 | C37: Entertainment expenses | D37: 0 | F37: -234.96 | H37: =D37*$J$4 -> 0
B38: 4660 | C38: Employee travel expenses | D38: 0 | F38: -529.7 | H38: =D38*$J$4 -> 0
B39: 4663 | C39: Employee travel expnses, cost of travel | D39: 0 | F39: -596.11 | H39: =D39*$J$4 -> 0
B40: 4664 | C40: Employee trav. expn, addnl substnc costs | D40: 0 | F40: -137 | H40: =D40*$J$4 -> 0
B41: 4666 | C41: Employee trav. expn, accommodation costs | D41: 0 | F41: -1871.98 | H41: =D41*$J$4 -> 0
B42: 4668 | C42: Employee mileage reimbursement | D42: 0 | E42: -8400 | F42: -288 | H42: =D42*$J$4 -> 0
H43: =SUM(H36:H42) -> -9295.6094
C44: Miscellaneous operating costs
B45: 4900 | C45: Other operating expenses | D45: 0 | F45: -239.5 | H45: =D45*$J$4 -> 0
A46: 7021 | B46: 4920 | C46: Telephone | D46: -520.29 | F46: -346.64 | H46: =D46*$J$4 -> -575.76341
A47: 7021 | B47: 4950 | C47: Legal and consulting expenses | D47: -232.1 | F47: -820 | H47: =D47*$J$4 -> -256.84654
A48: 7021 | B48: 4955 | C48: Bookkeeping expenses | D48: -33.4 | F48: -680.4 | H48: =D48*$J$4 -> -36.961114
A49: 7021 | B49: 4970 | C49: Incidental monetary transaction costs | D49: -250.74 | E49: -1036.53 | F49: -175.23 | H49: =D49*$J$4 -> -277.47394
H50: =SUM(H45:H49) -> -1147.045
A52: 7901 | B52: 9004 | C52: Exchange rate | H52: =-('GMBH BS 31.07.2020'!J44+'GMBH BS 31.07.2020'!J47)+301.83 -> 2871.5715
C54: Taxes on income
A55: 7028 | B55: 2200 | C55: Corporate income tax | E55: -375.89 | F55: 0 | H55: =E55*$J$4 -> -415.96746
C58: Net income for the financial year
C59: Net income for the financial year | E59: 3846.23 | F59: 7091.19 | H59: =H12+H15+H18+H23+H27+H30+H33+H43+H50+H55+H52 -> 7127.8872 | I59: =E59*J4-H59+H52 -> -1.1823431e-11

Sheet GMBH BS 31.03.2020
B1: INTERIM BALANCE SHEET
B2: ACCOUNTS as at
B3: 31.03.2020
L4: 3.565 | M4: שע"ח $ 31.03.20
B5: Aurora Labs Germany GmbH Entwicklung und Vertrieb von Software, Unterschleißheim | L5: 3.9003 | M5: שע"ח יורו 31.03.20
L6: =L5/L4 -> 1.0940533 | M6: יחס
B7: ASSETS
E9: Financial year | F9: Previous year
B10: Account | C10: Description | D10: EUR | E10: EUR | F10: EUR | H10: $
C12: Other equipment, operating and office equipment
A13: 1904 | B13: 490 | C13: Other operating and office equipment | E13: 633.67 | F13: 1126 | H13: =E13*$L$6 -> 693.26875
C15: Trade receivables
A16: 1351 | B16: 1410 | C16: Trade receivables | E16: 37554.05 | F16: 67588.24 | H16: =E16*$L$6 -> 41086.132 | I16: חוז בינחברתי
C18: Other assets
A19: 1307 | B19: 1525 | C19: Security deposits | D19: 1119.62 | F19: 1119.62 | H19: =D19*$L$6 -> 1224.924
B20: 1548 | C20: Input tax ded. following period/year | D20: 0 | F20: 165.72 | H20: =D20*$L$6 -> 0
B21: 1571 | C21: Deductible input tax, 7% | D21: 0 | F21: 130.11 | H21: =D21*$L$6 -> 0
A22: 1357 | B22: 1576 | C22: Deductible input tax, 19% | D22: 2836.34 | F22: 1538.74 | H22: =D22*$L$6 -> 3103.1071
A23: 1357 | B23: 1780 | C23: VAT prepayments | D23: -1296.15 | F23: 0 | H23: =D23*$L$6 -> -1418.0572
A24: 1357 | B24: 1790 | C24: VAT, previous year | D24: 2270.97 | F24: 3531.61 | H24: =D24*$L$6 -> 2484.5622
A25: 1357 | B25: 1791 | C25: VAT, earlier years | D25: 536.28 | E25: 5467.06 | F25: 0 | H25: =D25*$L$6 -> 586.7189
H26: =SUM(H19:H25) -> 5981.255
C27: Cash-in-hand, central bank balances, bank balances and cheques
A28: 1307 | B28: 1200 | C28: Bank | E28: 3965.33 | F28: 17136.27 | H28: =E28*$L$6 -> 4338.2824
C30: Deficit not covered by equity
C31: Equity deficit | E31: 0 | F31: 12977.4
C33: Other assets
A34: 1358 | B34: 975 | D34: 66.8 | F34: 0 | H34: =D34*$L$6 -> 73.08276
A35: 1358 | B35: 977 | C35: Provsns period-end closing/ audit costs | D35: 2959.4 | E35: 3026.2 | F35: 0 | H35: =D35*$L$6 -> 3237.7413
H36: =SUM(H34:H35) -> 3310.8241
C38: Total assets | E38: 50646.31 | F38: 105313.71 | H38: =H36+H28+H26+H16+H13 -> 55409.762 | I38: =E38*L6-H38 -> 0
B40: EQUITY AND LIABILITIES
E42: Financial year | F42: Previous year
B43: Account | C43: Description | D43: EUR | E43: EUR | F43: EUR
C45: Subscribed capital | I45: י.פ. | J45: הפרשי שער
A46: 1842 | B46: 800 | C46: Subscribed capital | E46: 25000 | F46: 25000 | H46: =E46*$L$6 -> 27351.332 | I46: 28054 | J46: =I46-H46 -> 702.6676
C48: Retained profits brought forward | J48: הפרשי שער
A49: 9410 | B49: 860 | C49: Retained profits bef apprprtn net profit | E49: 11943.69 | F49: 6553.33 | H49: =E49*$L$6 -> 13067.033 | I49: 13158 | J49: =I49-H49 -> 90.96659
C51: Net income for the financial year
C52: Net income for the financial year | E52: 3619.58 | F52: -44530.73 | H52: =E52*$L$6 -> 3960.0134 | I52: =H52-(J49+J46) -> 3166.3792
C54: Deficit not covered
C55: Equity deficit | E55: 0 | F55: 12977.4
C57: Provisions for taxes
A58: 2688 | B58: 956 | C58: Provision for trade tax, EStG s. 4(5b) | D58: 1905 | F58: 1040 | H58: =D58*$L$6 -> 2084.1715
A59: 2688 | B59: 963 | C59: Provisions for corporate income tax | D59: 2624.84 | E59: 4529.84 | F59: 1436.91 | H59: =D59*$L$6 -> 2871.7149
H60: =SUM(H58:H59) -> 4955.8864
C61: Other provisions
A62: 2687 | B62: 977 | C62: Provsns period-end closing/ audit costs | E62: 0 | F62: 2600
C64: Trade payables
B65: 1610 | C65: Trade pybls, no sep. rec./pybls accntng | E65: 0 | F65: 822.76
C67: of which due within one year EUR 0,00 (EUR 822,76)
B68: 1610 | C68: Trade pybls, no sep. rec./pybls accntng
C70: Other liabilities
B71: 1665 | C71: Liabilities to GmbH shareholders | D71: 0 | F71: 60000 | H71: =D71*$L$6 -> 0
A72: 2689 | B72: 1700 | C72: Other liabilities | D72: 4745.44 | F72: 10990.35 | H72: =D72*$L$6 -> 5191.7643
B73: 1705 | C73: Loans | D73: 0 | F73: 559.81 | H73: =D73*$L$6 -> 0
A74: 2685 | B74: 1741 | C74: Wage and church tax payables | D74: 807.76 | E74: 5553.2 | F74: 27863.88 | H74: =D74*$L$6 -> 883.73249
H75: =SUM(H71:H74) -> 6075.4968
C76: of which to shareholders EUR 0,00 (EUR 60.000,00)
B77: 1665 | C77: Liabilities to GmbH shareholders
C79: of which taxes EUR 807,76 (EUR 27.863,88)
B80: 1741 | C80: Wage and church tax payables
C82: of which due within one year EUR 5.553,20 (EUR 99.414,04)
B83: 1665 | C83: Liabilities to GmbH shareholders
B84: 1700 | C84: Other liabilities
B85: 1705 | C85: Loans
B86: 1741 | C86: Wage and church tax payables
C89: Total equity and liabilities | E89: 50646.31 | F89: 105313.71 | H89: =H75+H60+I52+I49+I46 -> 55409.762

Sheet GMBH P&L 31.03.2020
B1: Income statement
B2: ACCOUNTS from
B3: 01.01.2020 to 31.03.2020 | M3: 3.565 | N3: שע"ח $ 31.03.20
M4: 3.9003 | N4: שע"ח יורו 31.03.20
B5: Aurora Labs Germany GmbH Entwicklung und Vertrieb von Software, Unterschleißheim | M5: =M4/M3 -> 1.0940533 | N5: יחס
E8: Financial year | F8: Previous year
B9: Account | C9: Description | D9: EUR | E9: EUR | F9: EUR | H9: $
C11: Sales
A12: 7023 | B12: 8338 | C12: Tax-exempt sales 3rd country | E12: 28437.37 | F12: 0 | H12: =E12*$M$5 -> 31111.998 | J12: חש' COST+
C14: Income from reversal of provisions
A15: 7021 | B15: 2735 | C15: Income from reversal of provisions | E15: 1513.1 | F15: 0 | H15: =E15*$M$5 -> 1655.412
C17: Wages and salaries
A18: 7020 | B18: 4100 | C18: Wages and salaries | E18: -12999.99 | F18: -30000 | H18: =E18*$M$5 -> -14222.682
C20: Social security, post-employment and other employee benefit costs
A21: 7020 | B21: 4130 | C21: Statutory social security expenses | E21: -2886.66 | F21: -3615.9 | H21: =E21*$M$5 -> -3158.1599
C23: Depreciation, amortisation and write-downs
C25: Amortisation and write-downs of intangible fixed assets and depreciation and write downs of tangible fixed assets
A26: 7021 | B26: 4830 | C26: Depreciation of tangible fixed assets | E26: -70.33 | F26: 0 | H26: =E26*$M$5 -> -76.944768
C28: Occupancy costs
A29: 7021 | B29: 4210 | C29: Rent (immovable property) | E29: -1411.29 | F29: -1411.29 | H29: =E29*$M$5 -> -1544.0265
C31: Advertising and travel expenses
A32: 7026 | B32: 4600 | C32: Advertising expenses | D32: -8400 | F32: -6578.92 | H32: =D32*$M$5 -> -9190.0477
B33: 4650 | C33: Entertainment expenses | D33: 0 | F33: -234.96
B34: 4660 | C34: Employee travel expenses | D34: 0 | F34: -139.06
B35: 4663 | C35: Employee travel expnses, cost of travel | D35: 0 | F35: -330.29
B36: 4664 | C36: Employee trav. expn, addnl substnc costs | D36: 0 | F36: -77
B37: 4666 | C37: Employee trav. expn, accommodation costs | D37: 0 | E37: -8400 | F37: -1871.98
C39: Miscellaneous operating costs
B40: 4900 | C40: Other operating expenses | D40: 0 | F40: -177.95 | H40: =D40*$M$5 -> 0
A41: 7021 | B41: 4920 | C41: Telephone | D41: -227.39 | F41: -93.8 | H41: =D41*$M$5 -> -248.77678
A42: 7051 | B42: 4950 | C42: Legal and consulting expenses | D42: -196.3 | F42: 0 | H42: =D42*$M$5 -> -214.76266
