Workbook
Name _Hlk8837652: 'Payroll analytics'!$C$75
Name Account_num: 'Trial balance'!$B$4:$B$1762
Name balance_bbs_01: [1]BBS!$J$12:$J$70
Name balance_bbs_01: BBS!$J$12:$J$69
Name balance_bbs_02: [1]BBS!$K$12:$K$70
Name balance_bbs_02: BBS!$K$12:$K$69
Name balance_bbs_03: [1]BBS!$L$12:$L$70
Name balance_bbs_03: BBS!$L$12:$L$69
Name balance_bbs_04: [1]BBS!$M$12:$M$70
Name balance_bbs_04: BBS!$M$12:$M$69
Name balance_bbs_05: [1]BBS!$N$12:$N$70
Name balance_bbs_05: BBS!$N$12:$N$69
Name balance_bbs_06: [1]BBS!$O$12:$O$70
Name balance_bbs_06: BBS!$O$12:$O$69
Name balance_bbs_07: [1]BBS!$P$12:$P$70
Name balance_bbs_07: BBS!$P$12:$P$69
Name balance_bbs_08: [1]BBS!$Q$12:$Q$70
Name balance_bbs_08: BBS!$Q$12:$Q$69
Name balance_bbs_09: [1]BBS!$R$12:$R$70
Name balance_bbs_09: BBS!$R$12:$R$69
Name balance_bbs_10: [1]BBS!$S$12:$S$70
Name balance_bbs_10: BBS!$S$12:$S$69
Name balance_bbs_11: [1]BBS!$T$12:$T$70
Name balance_bbs_11: BBS!$T$12:$T$69
Name balance_bbs_12: [1]BBS!$U$12:$U$70
Name balance_bbs_12: BBS!$U$12:$U$69
Name Balance_bpl_01: '[1]P&L'!$BS$8:$BS$436
Name Balance_bpl_01: 'P&L'!$BS$8:$BS$277
Name Balance_bpl_02: '[1]P&L'!$BT$8:$BT$436
Name Balance_bpl_02: 'P&L'!$BT$8:$BT$277
Name Balance_bpl_03: '[1]P&L'!$BV$8:$BV$436
Name Balance_bpl_03: 'P&L'!$BV$8:$BV$277
Name Balance_bpl_04: '[1]P&L'!$BX$8:$BX$436
Name Balance_bpl_04: 'P&L'!$BX$8:$BX$277
Name Balance_bpl_05: '[1]P&L'!$BZ$8:$BZ$436
Name Balance_bpl_05: 'P&L'!$BZ$8:$BZ$277
Name Balance_bpl_06: '[1]P&L'!$CB$8:$CB$436
Name Balance_bpl_06: 'P&L'!$CB$8:$CB$277
Name Balance_bpl_07: '[1]P&L'!$CD$8:$CD$436
Name Balance_bpl_07: 'P&L'!$CD$8:$CD$277
Name Balance_bpl_08: '[1]P&L'!$CF$8:$CF$436
Name Balance_bpl_08: 'P&L'!$CF$8:$CF$277
Name Balance_bpl_09: '[1]P&L'!$CH$8:$CH$436
Name Balance_bpl_09: 'P&L'!$CH$8:$CH$277
Name Balance_bpl_10: '[1]P&L'!$CJ$8:$CJ$436
Name Balance_bpl_10: 'P&L'!$CJ$8:$CJ$277
Name Balance_bpl_11: '[1]P&L'!$CL$8:$CL$436
Name Balance_bpl_11: 'P&L'!$CL$8:$CL$277
Name Balance_bpl_12: '[1]P&L'!$CN$8:$CN$436
Name Balance_bpl_12: 'P&L'!$CN$8:$CN$277
Name Balance_bplm_01: 'P&L'!$BS$8:$BS$277
Name Balance_bplm_02: 'P&L'!$BU$8:$BU$277
Name Balance_bplm_03: '[1]P&L'!$BW$8:$BW$436
Name Balance_bplm_03: 'P&L'!$BW$8:$BW$277
Name Balance_bplm_04: 'P&L'!$BY$8:$BY$277
Name Balance_bplm_05: 'P&L'!$CA$8:$CA$277
Name Balance_bplm_06: '[1]P&L'!$CC$8:$CC$436
Name Balance_bplm_06: 'P&L'!$CC$8:$CC$277
Name Balance_bplm_07: 'P&L'!$CE$8:$CE$277
Name Balance_bplm_08: 'P&L'!$CG$8:$CG$277

Sheet Template version managment
B4: Version | C4: Release Date | D4: Type | E4: Modifications
B5: V4 | C5: 43139 | E5: Original
B6: V5 | C6: 43142 | E6: BBS (update the index) + (cashflow move the interst&currncie to finance) +(BS update the long term liabilities ) + (opex type updated)
B7: V6 | C7: 43143 | E7: Entity added to the JE Tab+BS Index fixed
B8: V6 | C8: 43143 | E8: Adding 'Inventory' to the BS index ( not added to the BS itself )
B9: V7 | C9: 43144 | E9: Changes in the charts' title+Update the balance sheet index & cashflow
B10: v8 | C10: 43149 | E10: expend the P&L Department in the index + change fourmula in cs

Sheet Executive summary
A2: ='Actual vs Budget'!A7 -> $ | C2: ='P&L'!E2 -> Pocket Pie Studios Ltd.
A3: =IF(A2="$",1,IF(A2="$k",1000,1000000)) -> 1 | C3: Executive Summary
C5: Executive summary | D5: =EOMONTH(E5,-2)+1 -> 43466 | E5: =EOMONTH(F5,-2)+1 -> 43497 | F5: 43525 | H5: =YEAR(F5) -> 2019
C6: =A2 -> $ | D6: Actual | E6: Actual | F6: Actual | H6: YTD
C7: KPI
C8: # of customers
C9: MRR
C10: ARR
C11: ACV
C13: P&L Summary
C14: Revenue | D14: =INDEX('Financial highlights'!$D$13:$Q$13,MATCH(D$5,'Financial highlights'!$D$5:$Q$5,0)) -> #N/A | E14: =INDEX('Financial highlights'!$D$13:$Q$13,MATCH(E$5,'Financial highlights'!$D$5:$Q$5,0)) -> #N/A | F14: =INDEX('Financial highlights'!$D$13:$Q$13,MATCH(F$5,'Financial highlights'!$D$5:$Q$5,0)) -> #N/A | H14: =INDEX('Financial highlights'!$D$13:$Q$13,MATCH(H$5&" "&H$6,'Financial highlights'!$D$5:$Q$5,0)) -> #N/A
C15: COS | D15: =INDEX('Financial highlights'!$D$14:$Q$14,,MATCH(D$5,'Financial highlights'!$D$5:$Q$5,0)) -> #N/A | E15: =INDEX('Financial highlights'!$D$14:$Q$14,,MATCH(E$5,'Financial highlights'!$D$5:$Q$5,0)) -> #N/A | F15: =INDEX('Financial highlights'!$D$14:$Q$14,,MATCH(F$5,'Financial highlights'!$D$5:$Q$5,0)) -> #N/A | H15: =INDEX('Financial highlights'!$D$14:$Q$14,MATCH(H$5&" "&H$6,'Financial highlights'!$D$5:$Q$5,0)) -> #N/A
C16: Gross Profit | D16: =D14-D15 -> #N/A | E16: =E14-E15 -> #N/A | F16: =F14-F15 -> #N/A | H16: =H14-H15 -> #N/A
C17: Gross margin | D17: =IFERROR(+D16/D14,0) -> 0 | E17: =IFERROR(+E16/E14,0) -> 0 | F17: =IFERROR(+F16/F14,0) -> 0 | H17: =IFERROR(+H16/H14,0) -> 0
C18: Opex | D18: =INDEX('Financial highlights'!$D$25:$Q$25,,MATCH(D$5,'Financial highlights'!$D$5:$Q$5,0)) -> #N/A | E18: =INDEX('Financial highlights'!$D$25:$Q$25,,MATCH(E$5,'Financial highlights'!$D$5:$Q$5,0)) -> #N/A | F18: =INDEX('Financial highlights'!$D$25:$Q$25,,MATCH(F$5,'Financial highlights'!$D$5:$Q$5,0)) -> #N/A | H18: =INDEX('Financial highlights'!$D$25:$Q$25,,MATCH(H$5&" "&H$6,'Financial highlights'!$D$5:$Q$5,0)) -> #N/A
C19: EBITDA | D19: =D16-D18 -> #N/A | E19: =E16-E18 -> #N/A | F19: =F16-F18 -> #N/A | H19: =H16-H18 -> #N/A
C21: Cash flow Summary
C22: Collection | D22: =(INDEX(BS!$P$13:$AB$68,MATCH("Accounts receivable",BS!$F$13:$F$68,0),MATCH(D$5,BS!$P$9:$AB$9,0)-1)-INDEX(BS!$P$13:$AB$68,MATCH("Accounts receivable",BS!$F$13:$F$68,0),MATCH(D$5,BS!$P$9:$AB$9,0))+INDEX('P&L'!$W$13:$AI$13,MATCH(D$5,'P&L'!$W$6:$AI$6,0))+INDEX(BS!$P$13:$AB$68,MATCH("Deferred revenues",BS!$F$13:$F$68,0),MATCH(D$5,BS!$P$9:$AB$9,0))-INDEX(BS!$P$13:$AB$68,MATCH("Deferred revenues",BS!$F$13:$F$68,0),MATCH(D$5,BS!$P$9:$AB$9,0)-1))/$A$3 -> #N/A | E22: =(INDEX(BS!$P$13:$AB$68,MATCH("Accounts receivable",BS!$F$13:$F$68,0),MATCH(E$5,BS!$P$9:$AB$9,0)-1)-INDEX(BS!$P$13:$AB$68,MATCH("Accounts receivable",BS!$F$13:$F$68,0),MATCH(E$5,BS!$P$9:$AB$9,0))+INDEX('P&L'!$W$13:$AI$13,MATCH(E$5,'P&L'!$W$6:$AI$6,0))+INDEX(BS!$P$13:$AB$68,MATCH("Deferred revenues",BS!$F$13:$F$68,0),MATCH(E$5,BS!$P$9:$AB$9,0))-INDEX(BS!$P$13:$AB$68,MATCH("Deferred revenues",BS!$F$13:$F$68,0),MATCH(E$5,BS!$P$9:$AB$9,0)-1))/$A$3 -> #N/A | F22: =(INDEX(BS!$P$13:$AB$68,MATCH("Accounts receivable",BS!$F$13:$F$68,0),MATCH(F$5,BS!$P$9:$AB$9,0)-1)-INDEX(BS!$P$13:$AB$68,MATCH("Accounts receivable",BS!$F$13:$F$68,0),MATCH(F$5,BS!$P$9:$AB$9,0))+INDEX('P&L'!$W$13:$AI$13,MATCH(F$5,'P&L'!$W$6:$AI$6,0))+INDEX(BS!$P$13:$AB$68,MATCH("Deferred revenues",BS!$F$13:$F$68,0),MATCH(F$5,BS!$P$9:$AB$9,0))-INDEX(BS!$P$13:$AB$68,MATCH("Deferred revenues",BS!$F$13:$F$68,0),MATCH(F$5,BS!$P$9:$AB$9,0)-1))/$A$3 -> #N/A | H22: =(INDEX(BS!$P$13:$P$70,MATCH("Accounts receivable",BS!$F$13:$F$70,0))-INDEX(BS!$J$13:$J$70,MATCH("Accounts receivable",BS!$F$13:$F$70,0))+'P&L'!P13+INDEX(BS!$P$13:$P$70,MATCH("Deferred revenues",BS!$F$13:$F$70,0))-INDEX(BS!$J$13:$J$70,MATCH("Deferred revenues",BS!$F$13:$F$70,0)))/$A$3 -> 0
C23: Payments Payroll | D23: =(-INDEX(BS!$P$13:$AB$68,MATCH("Employee payables",BS!$F$13:$F$68,0),MATCH(D$5,BS!$P$9:$AB$9,0)-1)+INDEX(BS!$P$13:$AB$68,MATCH("Employee payables",BS!$F$13:$F$68,0),MATCH(D$5,BS!$P$9:$AB$9,0))-INDEX(BS!$P$13:$AB$68,MATCH("Employee institution",BS!$F$13:$F$68,0),MATCH(D$5,BS!$P$9:$AB$9,0)-1)+INDEX(BS!$P$13:$AB$68,MATCH("Employee institution",BS!$F$13:$F$68,0),MATCH(D$5,BS!$P$9:$AB$9,0))-INDEX(BS!$P$13:$AB$68,MATCH("Short term provisions - holiday accrual",BS!$F$13:$F$68,0),MATCH(D$5,BS!$P$9:$AB$9,0)-1)+INDEX(BS!$P$13:$AB$68,MATCH("Short term provisions - holiday accrual",BS!$F$13:$F$68,0),MATCH(D$5,BS!$P$9:$AB$9,0))-SUMIFS(INDEX('P&L'!$V$8:$AI$277,,MATCH(D$5,'P&L'!$V$6:$AI$6,0)-1),'P&L'!$D$8:$D$277,"Payroll")-SUMIFS(INDEX('P&L'!$V$8:$AI$277,,MATCH(D$5,'P&L'!$V$6:$AI$6,0)-1),'P&L'!$D$8:$D$277,"Recruitment"))/$A$3 -> #N/A | E23: =(-INDEX(BS!$P$13:$AB$68,MATCH("Employee payables",BS!$F$13:$F$68,0),MATCH(E$5,BS!$P$9:$AB$9,0)-1)+INDEX(BS!$P$13:$AB$68,MATCH("Employee payables",BS!$F$13:$F$68,0),MATCH(E$5,BS!$P$9:$AB$9,0))-INDEX(BS!$P$13:$AB$68,MATCH("Employee institution",BS!$F$13:$F$68,0),MATCH(E$5,BS!$P$9:$AB$9,0)-1)+INDEX(BS!$P$13:$AB$68,MATCH("Employee institution",BS!$F$13:$F$68,0),MATCH(E$5,BS!$P$9:$AB$9,0))-INDEX(BS!$P$13:$AB$68,MATCH("Short term provisions - holiday accrual",BS!$F$13:$F$68,0),MATCH(E$5,BS!$P$9:$AB$9,0)-1)+INDEX(BS!$P$13:$AB$68,MATCH("Short term provisions - holiday accrual",BS!$F$13:$F$68,0),MATCH(E$5,BS!$P$9:$AB$9,0))-SUMIFS(INDEX('P&L'!$V$8:$AI$277,,MATCH(E$5,'P&L'!$V$6:$AI$6,0)-1),'P&L'!$D$8:$D$277,"Payroll")-SUMIFS(INDEX('P&L'!$V$8:$AI$277,,MATCH(E$5,'P&L'!$V$6:$AI$6,0)-1),'P&L'!$D$8:$D$277,"Recruitment"))/$A$3 -> #N/A | F23: =(-INDEX(BS!$P$13:$AB$68,MATCH("Employee payables",BS!$F$13:$F$68,0),MATCH(F$5,BS!$P$9:$AB$9,0)-1)+INDEX(BS!$P$13:$AB$68,MATCH("Employee payables",BS!$F$13:$F$68,0),MATCH(F$5,BS!$P$9:$AB$9,0))-INDEX(BS!$P$13:$AB$68,MATCH("Employee institution",BS!$F$13:$F$68,0),MATCH(F$5,BS!$P$9:$AB$9,0)-1)+INDEX(BS!$P$13:$AB$68,MATCH("Employee institution",BS!$F$13:$F$68,0),MATCH(F$5,BS!$P$9:$AB$9,0))-INDEX(BS!$P$13:$AB$68,MATCH("Short term provisions - holiday accrual",BS!$F$13:$F$68,0),MATCH(F$5,BS!$P$9:$AB$9,0)-1)+INDEX(BS!$P$13:$AB$68,MATCH("Short term provisions - holiday accrual",BS!$F$13:$F$68,0),MATCH(F$5,BS!$P$9:$AB$9,0))-SUMIFS(INDEX('P&L'!$V$8:$AI$277,,MATCH(F$5,'P&L'!$V$6:$AI$6,0)-1),'P&L'!$D$8:$D$277,"Payroll")-SUMIFS(INDEX('P&L'!$V$8:$AI$277,,MATCH(F$5,'P&L'!$V$6:$AI$6,0)-1),'P&L'!$D$8:$D$277,"Recruitment"))/$A$3 -> #N/A | H23: =(-INDEX(BS!$P$13:$AB$68,MATCH("Employee payables",BS!$F$13:$F$63,0),MATCH(BS!$P$9,BS!$P$9:$AB$9,0))+INDEX(BS!$J$13:$J$68,MATCH("Employee payables",BS!$F$13:$F$68,0))-INDEX(BS!$P$13:$AB$68,MATCH("Employee institution",BS!$F$13:$F$63,0),MATCH(BS!$P$9,BS!$P$9:$AB$9,0))+INDEX(BS!$J$13:$J$68,MATCH("Employee institution",BS!$F$13:$F$68,0))-INDEX(BS!$P$13:$AB$68,MATCH("Short term provisions - holiday accrual",BS!$F$13:$F$63,0),MATCH(BS!$P$9,BS!$P$9:$AB$9,0))+INDEX(BS!$J$13:$J$68,MATCH("Short term provisions - holiday accrual",BS!$F$13:$F$68,0))-SUMIFS('P&L'!$W$8:$W$277,'P&L'!$D$8:$D$277,"Payroll")-SUMIFS('P&L'!$W$8:$W$277,'P&L'!$D$8:$D$277,"Recruitment"))/$A$3 -> 208543.7
C24: Payments Vendors | D24: =(D26-D22-D23-D25)/$A$3 -> #N/A | E24: =(E26-E22-E23-E25)/$A$3 -> #N/A | F24: =(F26-F22-F23-F25)/$A$3 -> #N/A | H24: =(H26-H22-H23-H25)/$A$3 -> #N/A
C25: Financing | D25: =INDEX(CF!$Y$57:$AK$57,MATCH(D$5,CF!$Y$7:$AK$7,0))/$A$3 -> #N/A | E25: =INDEX(CF!$Y$57:$AK$57,MATCH(E$5,CF!$Y$7:$AK$7,0))/$A$3 -> #N/A | F25: =INDEX(CF!$Y$57:$AK$57,MATCH(F$5,CF!$Y$7:$AK$7,0))/$A$3 -> #N/A | H25: =CF!S57/$A$3 -> 8627433.5
C26: Net burn | D26: =INDEX('Financial highlights'!$D$36:$Q$36,MATCH(D$5,'Financial highlights'!$D$29:$Q$29,0)) -> #N/A | E26: =INDEX('Financial highlights'!$D$36:$Q$36,MATCH(E$5,'Financial highlights'!$D$29:$Q$29,0)) -> #N/A | F26: =INDEX('Financial highlights'!$D$36:$Q$36,MATCH(F$5,'Financial highlights'!$D$29:$Q$29,0)) -> #N/A | H26: =INDEX('Financial highlights'!$D$36:$Q$36,MATCH(H$5&" "&H$6,'Financial highlights'!$D$29:$Q$29,0)) -> #N/A
C27: Cash end of period | D27: =INDEX('Financial highlights'!$D$37:$Q$37,MATCH(D$5,'Financial highlights'!$D$5:$Q$5,0)) -> #N/A | E27: =INDEX('Financial highlights'!$D$37:$Q$37,MATCH(E$5,'Financial highlights'!$D$5:$Q$5,0)) -> #N/A | F27: =INDEX('Financial highlights'!$D$37:$Q$37,MATCH(F$5,'Financial highlights'!$D$5:$Q$5,0)) -> #N/A | H27: =INDEX('Financial highlights'!$D$37:$Q$37,MATCH(H$5&" "&H$6,'Financial highlights'!$D$5:$Q$5,0)) -> #N/A
C29: HC Summary
C30: HC | D30: =INDEX('Financial highlights'!$D$50:$Q$50,,MATCH(D$5,'Financial highlights'!$D$40:$Q$40,0)) -> #N/A | E30: =INDEX('Financial highlights'!$D$50:$Q$50,,MATCH(E$5,'Financial highlights'!$D$40:$Q$40,0)) -> #N/A | F30: =INDEX('Financial highlights'!$D$50:$Q$50,,MATCH(F$5,'Financial highlights'!$D$40:$Q$40,0)) -> #N/A | H30: =INDEX('Financial highlights'!$D$50:$Q$50,,MATCH(H$5&" "&H$6,'Financial highlights'!$D$40:$Q$40,0)) -> #N/A
C31: Opex + COS / HC | D31: =IFERROR((D15+D18)/D30,0) -> 0 | E31: =IFERROR((E15+E18)/E30,0) -> 0 | F31: =IFERROR((F15+F18)/F30,0) -> 0 | H31: =IFERROR((H15+H18)/H30,0) -> 0
C33: Balance Sheet Summary
C34: Net working capital | D34: =(INDEX(BS!$P$12:$AB$70,MATCH("Total Current Assets",BS!$E$12:$E$70,0),MATCH(D$5,BS!$P$9:$AB$9,0))-INDEX(BS!$P$12:$AB$70,MATCH("Total Current Liabilities",BS!$E$12:$E$70,0),MATCH(D$5,BS!$P$9:$AB$9,0)))/$A$3 -> #N/A | E34: =(INDEX(BS!$P$12:$AB$70,MATCH("Total Current Assets",BS!$E$12:$E$70,0),MATCH(E$5,BS!$P$9:$AB$9,0))-INDEX(BS!$P$12:$AB$70,MATCH("Total Current Liabilities",BS!$E$12:$E$70,0),MATCH(E$5,BS!$P$9:$AB$9,0)))/$A$3 -> #N/A | F34: =(INDEX(BS!$P$12:$AB$70,MATCH("Total Current Assets",BS!$E$12:$E$70,0),MATCH(F$5,BS!$P$9:$AB$9,0))-INDEX(BS!$P$12:$AB$70,MATCH("Total Current Liabilities",BS!$E$12:$E$70,0),MATCH(F$5,BS!$P$9:$AB$9,0)))/$A$3 -> #N/A | H34: =(INDEX(BS!$J$12:$J$70,MATCH("Total Current Assets",BS!$E$12:$E$70,0))-INDEX(BS!$J$12:$J$70,MATCH("Total Current Liabilities",BS!$E$12:$E$70,0)))/$A$3 -> 6524305.4
C35: Outstanding Loans / long term liabilities | D35: =INDEX(BS!$P$55:$AB$55,MATCH(D$5,BS!$P$9:$AB$9,0))/$A$3 -> #N/A | E35: =INDEX(BS!$P$55:$AB$55,MATCH(E$5,BS!$P$9:$AB$9,0))/$A$3 -> #N/A | F35: =INDEX(BS!$P$55:$AB$55,MATCH(F$5,BS!$P$9:$AB$9,0))/$A$3 -> #N/A | H35: =BS!J55/$A$3 -> 0

Sheet Actual vs Budget
A2: Errors in this sheet: | C2: ='P&L'!E2 -> Pocket Pie Studios Ltd.
A3: =COUNTIF(D28:O28,"error")+COUNTIF(D37:O37,"error")+COUNTIF(D50:O50,"error")+COUNTIF(D93:O93,"error") -> 0 | C3: Actual vs Budget
A4: General errors in file:
A5: =A3+'Financial highlights'!A3+'P&L'!CU2+'P&L'!M2+BS!J2+BS!AQ2+CF!AS2+CF!M2+JE!C1+'Trial balance'!C1 -> 5
A6: Scale | C6: ="Month "&$A$7 -> Month $ | D6: =month_of_report -> 44531 | H6: ="Quarter "&$A$7 -> Quarter $ | I6: ="Q"&ROUNDUP(MONTH(month_of_report)/3,0)&"-"&YEAR(month_of_report)-2000 -> Q4-21 | M6: =$A$7&" YTD "&YEAR(month_of_report) -> $ YTD 2021 | N6: =RIGHT(M6,4) -> 2021
A7: ='Financial highlights'!E3 -> $ | D7: Actual | E7: Budget | F7: Variance | I7: Actual | J7: Budget | K7: Variance | N7: Actual | O7: Budget | P7: Variance
A8: =IF(A7="$",1,IF(A7="$k",1000,1000000)) -> 1 | C8: KPI | H8: =C8 -> KPI | M8: =H8 -> KPI
C9: KPI | H9: =C9 -> KPI | M9: =H9 -> KPI
C10: MRR | H10: =C10 -> MRR | M10: =H10 -> MRR
C11: ARR | H11: =C11 -> ARR | M11: =H11 -> ARR
C13: ="P&L Summary "&$A$7 -> P&L Summary $ | H13: =C13 -> P&L Summary $ | M13: =H13 -> P&L Summary $
A14: 1 | C14: Revenues | D14: =IFERROR(INDEX('P&L'!H$8:H$278,MATCH($A14,'P&L'!$C$8:$C$278,0),),0)/$A$8 -> 0 | E14: =IFERROR(INDEX('P&L'!I$8:I$278,MATCH($A14,'P&L'!$C$8:$C$278,0),),0)/$A$8 -> 0 | F14: =IFERROR(INDEX('P&L'!J$8:J$278,MATCH($A14,'P&L'!$C$8:$C$278,0),),0)/$A$8 -> 0 | H14: =C14 -> Revenues | I14: =IFERROR(INDEX('P&L'!L$8:L$278,MATCH($A14,'P&L'!$C$8:$C$278,0),),0)/$A$8 -> 0 | J14: =IFERROR(INDEX('P&L'!M$8:M$278,MATCH($A14,'P&L'!$C$8:$C$278,0),),0)/$A$8 -> 0 | K14: =IFERROR(INDEX('P&L'!N$8:N$278,MATCH($A14,'P&L'!$C$8:$C$278,0),),0)/$A$8 -> 0 | M14: =H14 -> Revenues | N14: =IFERROR(INDEX('P&L'!P$8:P$278,MATCH($A14,'P&L'!$C$8:$C$278,0),),0)/$A$8 -> 0 | O14: =IFERROR(INDEX('P&L'!Q$8:Q$278,MATCH($A14,'P&L'!$C$8:$C$278,0),),0)/$A$8 -> 0 | P14: =IFERROR(INDEX('P&L'!R$8:R$278,MATCH($A14,'P&L'!$C$8:$C$278,0),),0)/$A$8 -> 0
A15: 2 | C15: Cost of Sales | D15: =IFERROR(INDEX('P&L'!H$8:H$278,MATCH($A15,'P&L'!$C$8:$C$278,0),),0)/$A$8 -> 0 | E15: =IFERROR(INDEX('P&L'!I$8:I$278,MATCH($A15,'P&L'!$C$8:$C$278,0),),0)/$A$8 -> 0 | F15: =IFERROR(INDEX('P&L'!J$8:J$278,MATCH($A15,'P&L'!$C$8:$C$278,0),),0)/$A$8 -> 0 | H15: =C15 -> Cost of Sales | I15: =IFERROR(INDEX('P&L'!L$8:L$278,MATCH($A15,'P&L'!$C$8:$C$278,0),),0)/$A$8 -> 0 | J15: =IFERROR(INDEX('P&L'!M$8:M$278,MATCH($A15,'P&L'!$C$8:$C$278,0),),0)/$A$8 -> 0 | K15: =IFERROR(INDEX('P&L'!N$8:N$278,MATCH($A15,'P&L'!$C$8:$C$278,0),),0)/$A$8 -> 0 | M15: =H15 -> Cost of Sales | N15: =IFERROR(INDEX('P&L'!P$8:P$278,MATCH($A15,'P&L'!$C$8:$C$278,0),),0)/$A$8 -> 0 | O15: =IFERROR(INDEX('P&L'!Q$8:Q$278,MATCH($A15,'P&L'!$C$8:$C$278,0),),0)/$A$8 -> 0 | P15: =IFERROR(INDEX('P&L'!R$8:R$278,MATCH($A15,'P&L'!$C$8:$C$278,0),),0)/$A$8 -> 0
C16: Gross profit | D16: =D14-D15 -> 0 | E16: =E14-E15 -> 0 | F16: =F14+F15 -> 0 | H16: =C16 -> Gross profit | I16: =I14-I15 -> 0 | J16: =J14-J15 -> 0 | K16: =K14+K15 -> 0 | M16: =H16 -> Gross profit | N16: =N14-N15 -> 0 | O16: =O14-O15 -> 0 | P16: =P14+P15 -> 0
C17: Gross margin | D17: =IFERROR(+D16/D14,0) -> 0 | E17: =IFERROR(+E16/E14,0) -> 0 | F17: =IFERROR(+F16/F14,0) -> 0 | H17: =C17 -> Gross margin | I17: =IFERROR(+I16/I14,0) -> 0 | J17: =IFERROR(+J16/J14,0) -> 0 | K17: =IFERROR(+K16/K14,0) -> 0 | M17: =H17 -> Gross margin | N17: =IFERROR(+N16/N14,0) -> 0 | O17: =IFERROR(+O16/O14,0) -> 0 | P17: =IFERROR(+P16/P14,0) -> 0
C18: Opex: | H18: =C18 -> Opex: | M18: =H18 -> Opex:
A19: 11 | C19: ='Financial highlights'!C18 -> R&D | D19: =IFERROR(INDEX('P&L'!H$8:H$278,MATCH($A19,'P&L'!$C$8:$C$278,0),),0)/$A$8 -> 669810.02 | E19: =IFERROR(INDEX('P&L'!I$8:I$278,MATCH($A19,'P&L'!$C$8:$C$278,0),),0)/$A$8 -> 77241.456 | F19: =IFERROR(INDEX('P&L'!J$8:J$278,MATCH($A19,'P&L'!$C$8:$C$278,0),),0)/$A$8 -> -592568.57 | H19: =C19 -> R&D | I19: =IFERROR(INDEX('P&L'!L$8:L$278,MATCH($A19,'P&L'!$C$8:$C$278,0),),0)/$A$8 -> 669810.02 | J19: =IFERROR(INDEX('P&L'!M$8:M$278,MATCH($A19,'P&L'!$C$8:$C$278,0),),0)/$A$8 -> 231724.37 | K19: =IFERROR(INDEX('P&L'!N$8:N$278,MATCH($A19,'P&L'!$C$8:$C$278,0),),0)/$A$8 -> -438085.66 | M19: =H19 -> R&D | N19: =IFERROR(INDEX('P&L'!P$8:P$278,MATCH($A19,'P&L'!$C$8:$C$278,0),),0)/$A$8 -> 669810.02 | O19: =IFERROR(INDEX('P&L'!Q$8:Q$278,MATCH($A19,'P&L'!$C$8:$C$278,0),),0)/$A$8 -> 654302.04 | P19: =IFERROR(INDEX('P&L'!R$8:R$278,MATCH($A19,'P&L'!$C$8:$C$278,0),),0)/$A$8 -> -15507.983
A20: 12 | C20: ='Financial highlights'!C19 -> Product | D20: =IFERROR(INDEX('P&L'!H$8:H$278,MATCH($A20,'P&L'!$C$8:$C$278,0),),0)/$A$8 -> 326761.88 | E20: =IFERROR(INDEX('P&L'!I$8:I$278,MATCH($A20,'P&L'!$C$8:$C$278,0),),0)/$A$8 -> 29147.848 | F20: =IFERROR(INDEX('P&L'!J$8:J$278,MATCH($A20,'P&L'!$C$8:$C$278,0),),0)/$A$8 -> -297614.03 | H20: =C20 -> Product | I20: =IFERROR(INDEX('P&L'!L$8:L$278,MATCH($A20,'P&L'!$C$8:$C$278,0),),0)/$A$8 -> 326761.88 | J20: =IFERROR(INDEX('P&L'!M$8:M$278,MATCH($A20,'P&L'!$C$8:$C$278,0),),0)/$A$8 -> 87443.544 | K20: =IFERROR(INDEX('P&L'!N$8:N$278,MATCH($A20,'P&L'!$C$8:$C$278,0),),0)/$A$8 -> -239318.33 | M20: =H20 -> Product | N20: =IFERROR(INDEX('P&L'!P$8:P$278,MATCH($A20,'P&L'!$C$8:$C$278,0),),0)/$A$8 -> 326761.88 | O20: =IFERROR(INDEX('P&L'!Q$8:Q$278,MATCH($A20,'P&L'!$C$8:$C$278,0),),0)/$A$8 -> 251033.92 | P20: =IFERROR(INDEX('P&L'!R$8:R$278,MATCH($A20,'P&L'!$C$8:$C$278,0),),0)/$A$8 -> -75727.952
A21: 13 | C21: ='Financial highlights'!C20 -> Art | D21: =IFERROR(INDEX('P&L'!H$8:H$278,MATCH($A21,'P&L'!$C$8:$C$278,0),),0)/$A$8 -> 664947.33 | E21: =IFERROR(INDEX('P&L'!I$8:I$278,MATCH($A21,'P&L'!$C$8:$C$278,0),),0)/$A$8 -> 53061.835 | F21: =IFERROR(INDEX('P&L'!J$8:J$278,MATCH($A21,'P&L'!$C$8:$C$278,0),),0)/$A$8 -> -611885.5 | H21: =C21 -> Art | I21: =IFERROR(INDEX('P&L'!L$8:L$278,MATCH($A21,'P&L'!$C$8:$C$278,0),),0)/$A$8 -> 664947.33 | J21: =IFERROR(INDEX('P&L'!M$8:M$278,MATCH($A21,'P&L'!$C$8:$C$278,0),),0)/$A$8 -> 159185.51 | K21: =IFERROR(INDEX('P&L'!N$8:N$278,MATCH($A21,'P&L'!$C$8:$C$278,0),),0)/$A$8 -> -505761.82 | M21: =H21 -> Art | N21: =IFERROR(INDEX('P&L'!P$8:P$278,MATCH($A21,'P&L'!$C$8:$C$278,0),),0)/$A$8 -> 664947.33 | O21: =IFERROR(INDEX('P&L'!Q$8:Q$278,MATCH($A21,'P&L'!$C$8:$C$278,0),),0)/$A$8 -> 577647.58 | P21: =IFERROR(INDEX('P&L'!R$8:R$278,MATCH($A21,'P&L'!$C$8:$C$278,0),),0)/$A$8 -> -87299.75
A22: 14 | C22: ='Financial highlights'!C21 -> Sales Costs | D22: =IFERROR(INDEX('P&L'!H$8:H$278,MATCH($A22,'P&L'!$C$8:$C$278,0),),0)/$A$8 -> 0 | E22: =IFERROR(INDEX('P&L'!I$8:I$278,MATCH($A22,'P&L'!$C$8:$C$278,0),),0)/$A$8 -> 0 | F22: =IFERROR(INDEX('P&L'!J$8:J$278,MATCH($A22,'P&L'!$C$8:$C$278,0),),0)/$A$8 -> 0 | H22: =C22 -> Sales Costs | I22: =IFERROR(INDEX('P&L'!L$8:L$278,MATCH($A22,'P&L'!$C$8:$C$278,0),),0)/$A$8 -> 0 | J22: =IFERROR(INDEX('P&L'!M$8:M$278,MATCH($A22,'P&L'!$C$8:$C$278,0),),0)/$A$8 -> 40000 | K22: =IFERROR(INDEX('P&L'!N$8:N$278,MATCH($A22,'P&L'!$C$8:$C$278,0),),0)/$A$8 -> 40000 | M22: =H22 -> Sales Costs | N22: =IFERROR(INDEX('P&L'!P$8:P$278,MATCH($A22,'P&L'!$C$8:$C$278,0),),0)/$A$8 -> 0 | O22: =IFERROR(INDEX('P&L'!Q$8:Q$278,MATCH($A22,'P&L'!$C$8:$C$278,0),),0)/$A$8 -> 128000 | P22: =IFERROR(INDEX('P&L'!R$8:R$278,MATCH($A22,'P&L'!$C$8:$C$278,0),),0)/$A$8 -> 128000
A23: 15 | C23: ='Financial highlights'!C22 -> Marketing Costs | D23: =IFERROR(INDEX('P&L'!H$8:H$278,MATCH($A23,'P&L'!$C$8:$C$278,0),),0)/$A$8 -> 6018.94 | E23: =IFERROR(INDEX('P&L'!I$8:I$278,MATCH($A23,'P&L'!$C$8:$C$278,0),),0)/$A$8 -> 39162.468 | F23: =IFERROR(INDEX('P&L'!J$8:J$278,MATCH($A23,'P&L'!$C$8:$C$278,0),),0)/$A$8 -> 33143.528 | H23: =C23 -> Marketing Costs | I23: =IFERROR(INDEX('P&L'!L$8:L$278,MATCH($A23,'P&L'!$C$8:$C$278,0),),0)/$A$8 -> 6018.94 | J23: =IFERROR(INDEX('P&L'!M$8:M$278,MATCH($A23,'P&L'!$C$8:$C$278,0),),0)/$A$8 -> 117487.41 | K23: =IFERROR(INDEX('P&L'!N$8:N$278,MATCH($A23,'P&L'!$C$8:$C$278,0),),0)/$A$8 -> 111468.47 | M23: =H23 -> Marketing Costs | N23: =IFERROR(INDEX('P&L'!P$8:P$278,MATCH($A23,'P&L'!$C$8:$C$278,0),),0)/$A$8 -> 6018.94 | O23: =IFERROR(INDEX('P&L'!Q$8:Q$278,MATCH($A23,'P&L'!$C$8:$C$278,0),),0)/$A$8 -> 199137.28 | P23: =IFERROR(INDEX('P&L'!R$8:R$278,MATCH($A23,'P&L'!$C$8:$C$278,0),),0)/$A$8 -> 193118.34
A24: 16 | C24: ='Financial highlights'!C23 -> G&A | D24: =IFERROR(INDEX('P&L'!H$8:H$278,MATCH($A24,'P&L'!$C$8:$C$278,0),),0)/$A$8 -> 265069.35 | E24: =IFERROR(INDEX('P&L'!I$8:I$278,MATCH($A24,'P&L'!$C$8:$C$278,0),),0)/$A$8 -> 25440.492 | F24: =IFERROR(INDEX('P&L'!J$8:J$278,MATCH($A24,'P&L'!$C$8:$C$278,0),),0)/$A$8 -> -239628.86 | H24: =C24 -> G&A | I24: =IFERROR(INDEX('P&L'!L$8:L$278,MATCH($A24,'P&L'!$C$8:$C$278,0),),0)/$A$8 -> 265069.35 | J24: =IFERROR(INDEX('P&L'!M$8:M$278,MATCH($A24,'P&L'!$C$8:$C$278,0),),0)/$A$8 -> 70030.337 | K24: =IFERROR(INDEX('P&L'!N$8:N$278,MATCH($A24,'P&L'!$C$8:$C$278,0),),0)/$A$8 -> -195039.01 | M24: =H24 -> G&A | N24: =IFERROR(INDEX('P&L'!P$8:P$278,MATCH($A24,'P&L'!$C$8:$C$278,0),),0)/$A$8 -> 265069.35 | O24: =IFERROR(INDEX('P&L'!Q$8:Q$278,MATCH($A24,'P&L'!$C$8:$C$278,0),),0)/$A$8 -> 254084.76 | P24: =IFERROR(INDEX('P&L'!R$8:R$278,MATCH($A24,'P&L'!$C$8:$C$278,0),),0)/$A$8 -> -10984.584
C25: ='Financial highlights'!C24 -> #N/A | D25: =IFERROR(INDEX('P&L'!H$8:H$278,MATCH($A25,'P&L'!$C$8:$C$278,0),),0)/$A$8 -> 0 | E25: =IFERROR(INDEX('P&L'!I$8:I$278,MATCH($A25,'P&L'!$C$8:$C$278,0),),0)/$A$8 -> 0 | F25: =IFERROR(INDEX('P&L'!J$8:J$278,MATCH($A25,'P&L'!$C$8:$C$278,0),),0)/$A$8 -> 0 | H25: =C25 -> #N/A | I25: =IFERROR(INDEX('P&L'!L$8:L$278,MATCH($A25,'P&L'!$C$8:$C$278,0),),0)/$A$8 -> 0 | J25: =IFERROR(INDEX('P&L'!M$8:M$278,MATCH($A25,'P&L'!$C$8:$C$278,0),),0)/$A$8 -> 0 | K25: =IFERROR(INDEX('P&L'!N$8:N$278,MATCH($A25,'P&L'!$C$8:$C$278,0),),0)/$A$8 -> 0 | M25: =H25 -> #N/A | N25: =IFERROR(INDEX('P&L'!P$8:P$278,MATCH($A25,'P&L'!$C$8:$C$278,0),),0)/$A$8 -> 0 | O25: =IFERROR(INDEX('P&L'!Q$8:Q$278,MATCH($A25,'P&L'!$C$8:$C$278,0),),0)/$A$8 -> 0 | P25: =IFERROR(INDEX('P&L'!R$8:R$278,MATCH($A25,'P&L'!$C$8:$C$278,0),),0)/$A$8 -> 0
C26: Total OPEX | D26: =SUM(D19:D25) -> 1932607.5 | E26: =SUM(E19:E25) -> 224054.1 | F26: =SUM(F19:F25) -> -1708553.4 | H26: =C26 -> Total OPEX | I26: =SUM(I19:I25) -> 1932607.5 | J26: =SUM(J19:J25) -> 705871.16 | K26: =SUM(K19:K25) -> -1226736.4 | M26: =H26 -> Total OPEX | N26: =SUM(N19:N25) -> 1932607.5 | O26: =SUM(O19:O25) -> 2064205.6 | P26: =SUM(P19:P25) -> 131598.07
C27: EBITDA | D27: =D16-D26 -> -1932607.5 | E27: =E16-E26 -> -224054.1 | F27: =F16+F26 -> -1708553.4 | H27: =C27 -> EBITDA | I27: =I16-I26 -> -1932607.5 | J27: =J16-J26 -> -705871.16 | K27: =K16+K26 -> -1226736.4 | M27: =H27 -> EBITDA | N27: =N16-N26 -> -1932607.5 | O27: =O16-O26 -> -2064205.6 | P27: =P16+P26 -> 131598.07
D28: =IF(ROUND(D26*$A$8,0)=ROUND('P&L'!H249,0),"","Error") | E28: =IF(ROUND(E26*$A$8,0)=ROUND('P&L'!I249,0),"","Error") | I28: =IF(ROUND(I26*$A$8,0)=ROUND('P&L'!L249,0),"","Error") | J28: =IF(ROUND(J26*$A$8,0)=ROUND('P&L'!M249,0),"","Error") | N28: =IF(ROUND(N26*$A$8,0)=ROUND('P&L'!P249,0),"","Error") | O28: =IF(ROUND(O26*$A$8,0)=ROUND('P&L'!Q249,0),"","Error")
C29: ="Cash flow "&$A$7 -> Cash flow $ | D29: =D7 -> Actual | E29: =E7 -> Budget | F29: =F7 -> Variance | H29: =C29 -> Cash flow $ | I29: =I7 -> Actual | J29: =J7 -> Budget | K29: =K7 -> Variance | M29: =H29 -> Cash flow $ | N29: =N7 -> Actual | O29: =O7 -> Budget | P29: =P7 -> Variance
C30: Cash at Beginning of Period | D30: =INDEX(CF!K$11:K$65,MATCH($C30,CF!$I$11:$I$65,0))/$A$8 -> 1663501.8 | E30: =INDEX(CF!L$11:L$65,MATCH($C30,CF!$I$11:$I$65,0))/$A$8 -> 3868873.2 | F30: =INDEX(CF!M$11:M$65,MATCH($C30,CF!$I$11:$I$65,0))/$A$8 -> -2205371.4 | H30: =C30 -> Cash at Beginning of Period | I30: =INDEX(CF!O$11:O$65,MATCH($C30,CF!$I$11:$I$65,0))/$A$8 -> 1663501.8 | J30: =INDEX(CF!P$11:P$65,MATCH($C30,CF!$I$11:$I$65,0))/$A$8 -> 4341021.4 | K30: =INDEX(CF!Q$11:Q$65,MATCH($C30,CF!$I$11:$I$65,0))/$A$8 -> -2677519.6 | M30: =H30 -> Cash at Beginning of Period | N30: =INDEX(CF!S$11:S$65,MATCH($C30,CF!$I$11:$I$65,0))/$A$8 -> 1663501.8 | O30: =INDEX(CF!T$11:T$65,MATCH($C30,CF!$I$11:$I$65,0))/$A$8 -> 1667734.9 | P30: =INDEX(CF!U$11:U$65,MATCH($C30,CF!$I$11:$I$65,0))/$A$8 -> -4233.1061
C31: Net Operating Cash Flow | D31: =INDEX(CF!K$11:K$65,MATCH($C31,CF!$I$11:$I$65,0))/$A$8 -> -1560685.8 | E31: =INDEX(CF!L$11:L$65,MATCH($C31,CF!$I$11:$I$65,0))/$A$8 -> -238402.53 | F31: =INDEX(CF!M$11:M$65,MATCH($C31,CF!$I$11:$I$65,0))/$A$8 -> -1322283.3 | H31: =C31 -> Net Operating Cash Flow | I31: =INDEX(CF!O$11:O$65,MATCH($C31,CF!$I$11:$I$65,0))/$A$8 -> -1560685.8 | J31: =INDEX(CF!P$11:P$65,MATCH($C31,CF!$I$11:$I$65,0))/$A$8 -> -704340.6 | K31: =INDEX(CF!Q$11:Q$65,MATCH($C31,CF!$I$11:$I$65,0))/$A$8 -> -856345.19 | M31: =H31 -> Net Operating Cash Flow | N31: =INDEX(CF!S$11:S$65,MATCH($C31,CF!$I$11:$I$65,0))/$A$8 -> -1560685.8 | O31: =INDEX(CF!T$11:T$65,MATCH($C31,CF!$I$11:$I$65,0))/$A$8 -> -1896076.1 | P31: =INDEX(CF!U$11:U$65,MATCH($C31,CF!$I$11:$I$65,0))/$A$8 -> 335390.27
C32: Total Capital Expenditure | D32: =INDEX(CF!K$11:K$65,MATCH($C32,CF!$I$11:$I$65,0))/$A$8 -> -106525.99 | E32: =INDEX(CF!L$11:L$65,MATCH($C32,CF!$I$11:$I$65,0))/$A$8 -> 0 | F32: =INDEX(CF!M$11:M$65,MATCH($C32,CF!$I$11:$I$65,0))/$A$8 -> -106525.99 | H32: =C32 -> Total Capital Expenditure | I32: =INDEX(CF!O$11:O$65,MATCH($C32,CF!$I$11:$I$65,0))/$A$8 -> -106525.99 | J32: =INDEX(CF!P$11:P$65,MATCH($C32,CF!$I$11:$I$65,0))/$A$8 -> -6210.1266 | K32: =INDEX(CF!Q$11:Q$65,MATCH($C32,CF!$I$11:$I$65,0))/$A$8 -> -100315.86 | M32: =H32 -> Total Capital Expenditure | N32: =INDEX(CF!S$11:S$65,MATCH($C32,CF!$I$11:$I$65,0))/$A$8 -> -106525.99 | O32: =INDEX(CF!T$11:T$65,MATCH($C32,CF!$I$11:$I$65,0))/$A$8 -> -74521.519 | P32: =INDEX(CF!U$11:U$65,MATCH($C32,CF!$I$11:$I$65,0))/$A$8 -> -32004.471
C33: Total Financing | D33: =INDEX(CF!K$11:K$65,MATCH($C33,CF!$I$11:$I$65,0))/$A$8 -> 8627433.5 | E33: =INDEX(CF!L$11:L$65,MATCH($C33,CF!$I$11:$I$65,0))/$A$8 -> -3.4924597e-10 | F33: =INDEX(CF!M$11:M$65,MATCH($C33,CF!$I$11:$I$65,0))/$A$8 -> 8627433.5 | H33: =C33 -> Total Financing | I33: =INDEX(CF!O$11:O$65,MATCH($C33,CF!$I$11:$I$65,0))/$A$8 -> 8627433.5 | J33: =INDEX(CF!P$11:P$65,MATCH($C33,CF!$I$11:$I$65,0))/$A$8 -> -1.0477379e-09 | K33: =INDEX(CF!Q$11:Q$65,MATCH($C33,CF!$I$11:$I$65,0))/$A$8 -> 8627433.5 | M33: =H33 -> Total Financing | N33: =INDEX(CF!S$11:S$65,MATCH($C33,CF!$I$11:$I$65,0))/$A$8 -> 8627433.5 | O33: =INDEX(CF!T$11:T$65,MATCH($C33,CF!$I$11:$I$65,0))/$A$8 -> 3933333.3 | P33: =INDEX(CF!U$11:U$65,MATCH($C33,CF!$I$11:$I$65,0))/$A$8 -> 4694100.1
C34: Taxation Paid | D34: =INDEX(CF!K$11:K$65,MATCH($C34,CF!$I$11:$I$65,0))/$A$8 -> 0 | E34: =INDEX(CF!L$11:L$65,MATCH($C34,CF!$I$11:$I$65,0))/$A$8 -> 0 | F34: =INDEX(CF!M$11:M$65,MATCH($C34,CF!$I$11:$I$65,0))/$A$8 -> 0 | H34: =C34 -> Taxation Paid | I34: =INDEX(CF!O$11:O$65,MATCH($C34,CF!$I$11:$I$65,0))/$A$8 -> 0 | J34: =INDEX(CF!P$11:P$65,MATCH($C34,CF!$I$11:$I$65,0))/$A$8 -> 0 | K34: =INDEX(CF!Q$11:Q$65,MATCH($C34,CF!$I$11:$I$65,0))/$A$8 -> 0 | M34: =H34 -> Taxation Paid | N34: =INDEX(CF!S$11:S$65,MATCH($C34,CF!$I$11:$I$65,0))/$A$8 -> 0 | O34: =INDEX(CF!T$11:T$65,MATCH($C34,CF!$I$11:$I$65,0))/$A$8 -> 0 | P34: =INDEX(CF!U$11:U$65,MATCH($C34,CF!$I$11:$I$65,0))/$A$8 -> 0
C35: Net Cash Inflow / (Outflow) | D35: =INDEX(CF!K$11:K$65,MATCH($C35,CF!$I$11:$I$65,0))/$A$8 -> 6960221.7 | E35: =INDEX(CF!L$11:L$65,MATCH($C35,CF!$I$11:$I$65,0))/$A$8 -> -238402.53 | F35: =INDEX(CF!M$11:M$65,MATCH($C35,CF!$I$11:$I$65,0))/$A$8 -> 7198624.2 | H35: =C35 -> Net Cash Inflow / (Outflow) | I35: =INDEX(CF!O$11:O$65,MATCH($C35,CF!$I$11:$I$65,0))/$A$8 -> 6960221.7 | J35: =INDEX(CF!P$11:P$65,MATCH($C35,CF!$I$11:$I$65,0))/$A$8 -> -710550.72 | K35: =INDEX(CF!Q$11:Q$65,MATCH($C35,CF!$I$11:$I$65,0))/$A$8 -> 7670772.4 | M35: =H35 -> Net Cash Inflow / (Outflow) | N35: =INDEX(CF!S$11:S$65,MATCH($C35,CF!$I$11:$I$65,0))/$A$8 -> 6960221.7 | O35: =INDEX(CF!T$11:T$65,MATCH($C35,CF!$I$11:$I$65,0))/$A$8 -> 1962735.8 | P35: =INDEX(CF!U$11:U$65,MATCH($C35,CF!$I$11:$I$65,0))/$A$8 -> 4997485.9
C36: Cash End Of Period | D36: =INDEX(CF!K$11:K$65,MATCH($C36,CF!$I$11:$I$65,0))/$A$8 -> 8623723.5 | E36: =INDEX(CF!L$11:L$65,MATCH($C36,CF!$I$11:$I$65,0))/$A$8 -> 3630470.6 | F36: =INDEX(CF!M$11:M$65,MATCH($C36,CF!$I$11:$I$65,0))/$A$8 -> 4993252.8 | H36: =C36 -> Cash End Of Period | I36: =INDEX(CF!O$11:O$65,MATCH($C36,CF!$I$11:$I$65,0))/$A$8 -> 8623723.5 | J36: =INDEX(CF!P$11:P$65,MATCH($C36,CF!$I$11:$I$65,0))/$A$8 -> 3630470.6 | K36: =INDEX(CF!Q$11:Q$65,MATCH($C36,CF!$I$11:$I$65,0))/$A$8 -> 4993252.8 | M36: =H36 -> Cash End Of Period | N36: =INDEX(CF!S$11:S$65,MATCH($C36,CF!$I$11:$I$65,0))/$A$8 -> 8623723.5 | O36: =INDEX(CF!T$11:T$65,MATCH($C36,CF!$I$11:$I$65,0))/$A$8 -> 3630470.6 | P36: =INDEX(CF!U$11:U$65,MATCH($C36,CF!$I$11:$I$65,0))/$A$8 -> 4993252.8
D37: =IF(ROUND(D36*$A$8,0)=ROUND(CF!K63,0),"","Error") | E37: =IF(ROUND(E36*$A$8,0)=ROUND(CF!L63,0),"","Error") | I37: =IF(ROUND(I36*$A$8,0)=ROUND(CF!O63,0),"","Error") | J37: =IF(ROUND(J36*$A$8,0)=ROUND(CF!P63,0),"","Error") | N37: =IF(ROUND(N36*$A$8,0)=ROUND(CF!S63,0),"","Error") | O37: =IF(ROUND(O36*$A$8,0)=ROUND(CF!T63,0),"","Error")
C39: HC | D39: =D6 -> 44531 | H39: =C39 -> HC | I39: =I6 -> Q4-21 | M39: =H39 -> HC | N39: =N6 -> 2021
D40: =D7 -> Actual | E40: =E7 -> Budget | F40: =F7 -> Variance | I40: =I7 -> Actual | J40: =J7 -> Budget | K40: =K7 -> Variance | N40: =N7 -> Actual | O40: =O7 -> Budget | P40: =P7 -> Variance
A41: 22302 | C41: =C15 -> Cost of Sales | D41: =IFERROR(INDEX('P&L'!H$8:H$278,MATCH($A41,'P&L'!$C$8:$C$278,0),),0) -> 0 | E41: =IFERROR(INDEX('P&L'!I$8:I$278,MATCH($A41,'P&L'!$C$8:$C$278,0),),0) -> 0 | F41: =IFERROR(INDEX('P&L'!J$8:J$278,MATCH($A41,'P&L'!$C$8:$C$278,0),),0) -> 0 | H41: =C41 -> Cost of Sales | I41: =IFERROR(INDEX('P&L'!L$8:L$278,MATCH($A41,'P&L'!$C$8:$C$278,0),),0) -> 0 | J41: =IFERROR(INDEX('P&L'!M$8:M$278,MATCH($A41,'P&L'!$C$8:$C$278,0),),0) -> 0 | K41: =IFERROR(INDEX('P&L'!N$8:N$278,MATCH($A41,'P&L'!$C$8:$C$278,0),),0) -> 0 | M41: =H41 -> Cost of Sales | N41: =IFERROR(INDEX('P&L'!P$8:P$278,MATCH($A41,'P&L'!$C$8:$C$278,0),),0) -> 0 | O41: =IFERROR(INDEX('P&L'!Q$8:Q$278,MATCH($A41,'P&L'!$C$8:$C$278,0),),0) -> 0 | P41: =IFERROR(INDEX('P&L'!R$8:R$278,MATCH($A41,'P&L'!$C$8:$C$278,0),),0) -> 0
A42: 23203 | C42: =C19 -> R&D | D42: =IFERROR(INDEX('P&L'!H$8:H$278,MATCH($A42,'P&L'!$C$8:$C$278,0),),0) -> 8 | E42: =IFERROR(INDEX('P&L'!I$8:I$278,MATCH($A42,'P&L'!$C$8:$C$278,0),),0) -> 9 | F42: =IFERROR(INDEX('P&L'!J$8:J$278,MATCH($A42,'P&L'!$C$8:$C$278,0),),0) -> 1 | H42: =C42 -> R&D | I42: =IFERROR(INDEX('P&L'!L$8:L$278,MATCH($A42,'P&L'!$C$8:$C$278,0),),0) -> 8 | J42: =IFERROR(INDEX('P&L'!M$8:M$278,MATCH($A42,'P&L'!$C$8:$C$278,0),),0) -> 9 | K42: =IFERROR(INDEX('P&L'!N$8:N$278,MATCH($A42,'P&L'!$C$8:$C$278,0),),0) -> 1 | M42: =H42 -> R&D | N42: =IFERROR(INDEX('P&L'!P$8:P$278,MATCH($A42,'P&L'!$C$8:$C$278,0),),0) -> 8 | O42: =IFERROR(INDEX('P&L'!Q$8:Q$278,MATCH($A42,'P&L'!$C$8:$C$278,0),),0) -> 9 | P42: =IFERROR(INDEX('P&L'!R$8:R$278,MATCH($A42,'P&L'!$C$8:$C$278,0),),0) -> 1
A43: 23208 | C43: =C20 -> Product | D43: =IFERROR(INDEX('P&L'!H$8:H$278,MATCH($A43,'P&L'!$C$8:$C$278,0),),0) -> 2 | E43: =IFERROR(INDEX('P&L'!I$8:I$278,MATCH($A43,'P&L'!$C$8:$C$278,0),),0) -> 3 | F43: =IFERROR(INDEX('P&L'!J$8:J$278,MATCH($A43,'P&L'!$C$8:$C$278,0),),0) -> 1 | H43: =C43 -> Product | I43: =IFERROR(INDEX('P&L'!L$8:L$278,MATCH($A43,'P&L'!$C$8:$C$278,0),),0) -> 2 | J43: =IFERROR(INDEX('P&L'!M$8:M$278,MATCH($A43,'P&L'!$C$8:$C$278,0),),0) -> 3 | K43: =IFERROR(INDEX('P&L'!N$8:N$278,MATCH($A43,'P&L'!$C$8:$C$278,0),),0) -> 1 | M43: =H43 -> Product | N43: =IFERROR(INDEX('P&L'!P$8:P$278,MATCH($A43,'P&L'!$C$8:$C$278,0),),0) -> 2 | O43: =IFERROR(INDEX('P&L'!Q$8:Q$278,MATCH($A43,'P&L'!$C$8:$C$278,0),),0) -> 3 | P43: =IFERROR(INDEX('P&L'!R$8:R$278,MATCH($A43,'P&L'!$C$8:$C$278,0),),0) -> 1
A44: 23217 | C44: =C21 -> Art | D44: =IFERROR(INDEX('P&L'!H$8:H$278,MATCH($A44,'P&L'!$C$8:$C$278,0),),0) -> 6 | E44: =IFERROR(INDEX('P&L'!I$8:I$278,MATCH($A44,'P&L'!$C$8:$C$278,0),),0) -> 6 | F44: =IFERROR(INDEX('P&L'!J$8:J$278,MATCH($A44,'P&L'!$C$8:$C$278,0),),0) -> 0 | H44: =C44 -> Art | I44: =IFERROR(INDEX('P&L'!L$8:L$278,MATCH($A44,'P&L'!$C$8:$C$278,0),),0) -> 6 | J44: =IFERROR(INDEX('P&L'!M$8:M$278,MATCH($A44,'P&L'!$C$8:$C$278,0),),0) -> 6 | K44: =IFERROR(INDEX('P&L'!N$8:N$278,MATCH($A44,'P&L'!$C$8:$C$278,0),),0) -> 0 | M44: =H44 -> Art | N44: =IFERROR(INDEX('P&L'!P$8:P$278,MATCH($A44,'P&L'!$C$8:$C$278,0),),0) -> 6 | O44: =IFERROR(INDEX('P&L'!Q$8:Q$278,MATCH($A44,'P&L'!$C$8:$C$278,0),),0) -> 6 | P44: =IFERROR(INDEX('P&L'!R$8:R$278,MATCH($A44,'P&L'!$C$8:$C$278,0),),0) -> 0
A45: 24206 | C45: =C22 -> Sales Costs | D45: =IFERROR(INDEX('P&L'!H$8:H$278,MATCH($A45,'P&L'!$C$8:$C$278,0),),0) -> 0 | E45: =IFERROR(INDEX('P&L'!I$8:I$278,MATCH($A45,'P&L'!$C$8:$C$278,0),),0) -> 0 | F45: =IFERROR(INDEX('P&L'!J$8:J$278,MATCH($A45,'P&L'!$C$8:$C$278,0),),0) -> 0 | H45: =C45 -> Sales Costs | I45: =IFERROR(INDEX('P&L'!L$8:L$278,MATCH($A45,'P&L'!$C$8:$C$278,0),),0) -> 0 | J45: =IFERROR(INDEX('P&L'!M$8:M$278,MATCH($A45,'P&L'!$C$8:$C$278,0),),0) -> 0 | K45: =IFERROR(INDEX('P&L'!N$8:N$278,MATCH($A45,'P&L'!$C$8:$C$278,0),),0) -> 0 | M45: =H45 -> Sales Costs | N45: =IFERROR(INDEX('P&L'!P$8:P$278,MATCH($A45,'P&L'!$C$8:$C$278,0),),0) -> 0 | O45: =IFERROR(INDEX('P&L'!Q$8:Q$278,MATCH($A45,'P&L'!$C$8:$C$278,0),),0) -> 0 | P45: =IFERROR(INDEX('P&L'!R$8:R$278,MATCH($A45,'P&L'!$C$8:$C$278,0),),0) -> 0
A46: 24207 | C46: =C23 -> Marketing Costs | D46: =IFERROR(INDEX('P&L'!H$8:H$278,MATCH($A46,'P&L'!$C$8:$C$278,0),),0) -> 0 | E46: =IFERROR(INDEX('P&L'!I$8:I$278,MATCH($A46,'P&L'!$C$8:$C$278,0),),0) -> 1 | F46: =IFERROR(INDEX('P&L'!J$8:J$278,MATCH($A46,'P&L'!$C$8:$C$278,0),),0) -> 1 | H46: =C46 -> Marketing Costs | I46: =IFERROR(INDEX('P&L'!L$8:L$278,MATCH($A46,'P&L'!$C$8:$C$278,0),),0) -> 0 | J46: =IFERROR(INDEX('P&L'!M$8:M$278,MATCH($A46,'P&L'!$C$8:$C$278,0),),0) -> 1 | K46: =IFERROR(INDEX('P&L'!N$8:N$278,MATCH($A46,'P&L'!$C$8:$C$278,0),),0) -> 1 | M46: =H46 -> Marketing Costs | N46: =IFERROR(INDEX('P&L'!P$8:P$278,MATCH($A46,'P&L'!$C$8:$C$278,0),),0) -> 0 | O46: =IFERROR(INDEX('P&L'!Q$8:Q$278,MATCH($A46,'P&L'!$C$8:$C$278,0),),0) -> 1 | P46: =IFERROR(INDEX('P&L'!R$8:R$278,MATCH($A46,'P&L'!$C$8:$C$278,0),),0) -> 1
A47: 25205 | C47: =C24 -> G&A | D47: =IFERROR(INDEX('P&L'!H$8:H$278,MATCH($A47,'P&L'!$C$8:$C$278,0),),0) -> 1 | E47: =IFERROR(INDEX('P&L'!I$8:I$278,MATCH($A47,'P&L'!$C$8:$C$278,0),),0) -> 1 | F47: =IFERROR(INDEX('P&L'!J$8:J$278,MATCH($A47,'P&L'!$C$8:$C$278,0),),0) -> 0 | H47: =C47 -> G&A | I47: =IFERROR(INDEX('P&L'!L$8:L$278,MATCH($A47,'P&L'!$C$8:$C$278,0),),0) -> 1 | J47: =IFERROR(INDEX('P&L'!M$8:M$278,MATCH($A47,'P&L'!$C$8:$C$278,0),),0) -> 1 | K47: =IFERROR(INDEX('P&L'!N$8:N$278,MATCH($A47,'P&L'!$C$8:$C$278,0),),0) -> 0 | M47: =H47 -> G&A | N47: =IFERROR(INDEX('P&L'!P$8:P$278,MATCH($A47,'P&L'!$C$8:$C$278,0),),0) -> 1 | O47: =IFERROR(INDEX('P&L'!Q$8:Q$278,MATCH($A47,'P&L'!$C$8:$C$278,0),),0) -> 1 | P47: =IFERROR(INDEX('P&L'!R$8:R$278,MATCH($A47,'P&L'!$C$8:$C$278,0),),0) -> 0
C48: =C25 -> #N/A | D48: =IFERROR(INDEX('P&L'!H$8:H$278,MATCH($A48,'P&L'!$C$8:$C$278,0),),0) -> 0 | E48: =IFERROR(INDEX('P&L'!I$8:I$278,MATCH($A48,'P&L'!$C$8:$C$278,0),),0) -> 0 | F48: =IFERROR(INDEX('P&L'!J$8:J$278,MATCH($A48,'P&L'!$C$8:$C$278,0),),0) -> 0 | H48: =C48 -> #N/A | I48: =IFERROR(INDEX('P&L'!L$8:L$278,MATCH($A48,'P&L'!$C$8:$C$278,0),),0) -> 0 | J48: =IFERROR(INDEX('P&L'!M$8:M$278,MATCH($A48,'P&L'!$C$8:$C$278,0),),0) -> 0 | K48: =IFERROR(INDEX('P&L'!N$8:N$278,MATCH($A48,'P&L'!$C$8:$C$278,0),),0) -> 0 | M48: =H48 -> #N/A | N48: =IFERROR(INDEX('P&L'!P$8:P$278,MATCH($A48,'P&L'!$C$8:$C$278,0),),0) -> 0 | O48: =IFERROR(INDEX('P&L'!Q$8:Q$278,MATCH($A48,'P&L'!$C$8:$C$278,0),),0) -> 0 | P48: =IFERROR(INDEX('P&L'!R$8:R$278,MATCH($A48,'P&L'!$C$8:$C$278,0),),0) -> 0
C49: Total Headcount | D49: =SUM(D41:D48) -> 17 | E49: =SUM(E41:E48) -> 20 | F49: =SUM(F41:F48) -> 3 | H49: =C49 -> Total Headcount | I49: =SUM(I41:I48) -> 17 | J49: =SUM(J41:J48) -> 20 | K49: =SUM(K41:K48) -> 3 | M49: =H49 -> Total Headcount | N49: =SUM(N41:N48) -> 17 | O49: =SUM(O41:O48) -> 20 | P49: =SUM(P41:P48) -> 3
D50: =IF(ROUND(D49,0)=ROUND('P&L'!H277,0),"","Error") | E50: =IF(ROUND(E49,0)=ROUND('P&L'!I277,0),"","Error") | I50: =IF(ROUND(I49,0)=ROUND('P&L'!L277,0),"","Error") | J50: =IF(ROUND(J49,0)=ROUND('P&L'!M277,0),"","Error") | N50: =IF(ROUND(N49,0)=ROUND('P&L'!P277,0),"","Error") | O50: =IF(ROUND(O49,0)=ROUND('P&L'!Q277,0),"","Error")
C51: ="Opex expense type "&$A$7 -> Opex expense type $ | D51: =D6 -> 44531 | H51: =C51 -> Opex expense type $ | I51: =I6 -> Q4-21 | M51: =H51 -> Opex expense type $ | N51: =N6 -> 2021
D52: =D7 -> Actual | E52: =E7 -> Budget | F52: =F7 -> Variance | I52: =I7 -> Actual | J52: =J7 -> Budget | K52: =K7 -> Variance | N52: =N7 -> Actual | O52: =O7 -> Budget | P52: =P7 -> Variance
C53: =IF(ISBLANK('Benchmark Index'!S7),"--",'Benchmark Index'!S7) -> Payroll | D53: =SUMIFS('P&L'!H$8:H$278,'P&L'!$D$8:$D$278,$C53)/$A$8 -> 1572528.5 | E53: =SUMIFS('P&L'!I$8:I$278,'P&L'!$D$8:$D$278,$C53)/$A$8 -> 180066.27 | F53: =SUMIFS('P&L'!J$8:J$278,'P&L'!$D$8:$D$278,$C53)/$A$8 -> -1392462.2 | H53: =C53 -> Payroll | I53: =SUMIFS('P&L'!L$8:L$278,'P&L'!$D$8:$D$278,$C53)/$A$8 -> 1572528.5 | J53: =SUMIFS('P&L'!M$8:M$278,'P&L'!$D$8:$D$278,$C53)/$A$8 -> 540198.8 | K53: =SUMIFS('P&L'!N$8:N$278,'P&L'!$D$8:$D$278,$C53)/$A$8 -> -1032329.7 | M53: =H53 -> Payroll | N53: =SUMIFS('P&L'!P$8:P$278,'P&L'!$D$8:$D$278,$C53)/$A$8 -> 1572528.5 | O53: =SUMIFS('P&L'!Q$8:Q$278,'P&L'!$D$8:$D$278,$C53)/$A$8 -> 1582402.7 | P53: =SUMIFS('P&L'!R$8:R$278,'P&L'!$D$8:$D$278,$C53)/$A$8 -> 9874.2535
C54: =IF(ISBLANK('Benchmark Index'!S8),"--",'Benchmark Index'!S8) -> Recruitment | D54: =SUMIFS('P&L'!H$8:H$278,'P&L'!$D$8:$D$278,$C54)/$A$8 -> 1089.9 | E54: =SUMIFS('P&L'!I$8:I$278,'P&L'!$D$8:$D$278,$C54)/$A$8 -> 0 | F54: =SUMIFS('P&L'!J$8:J$278,'P&L'!$D$8:$D$278,$C54)/$A$8 -> -1089.9 | H54: =C54 -> Recruitment | I54: =SUMIFS('P&L'!L$8:L$278,'P&L'!$D$8:$D$278,$C54)/$A$8 -> 1089.9 | J54: =SUMIFS('P&L'!M$8:M$278,'P&L'!$D$8:$D$278,$C54)/$A$8 -> 0 | K54: =SUMIFS('P&L'!N$8:N$278,'P&L'!$D$8:$D$278,$C54)/$A$8 -> -1089.9 | M54: =H54 -> Recruitment | N54: =SUMIFS('P&L'!P$8:P$278,'P&L'!$D$8:$D$278,$C54)/$A$8 -> 1089.9 | O54: =SUMIFS('P&L'!Q$8:Q$278,'P&L'!$D$8:$D$278,$C54)/$A$8 -> 0 | P54: =SUMIFS('P&L'!R$8:R$278,'P&L'!$D$8:$D$278,$C54)/$A$8 -> -1089.9
C55: =IF(ISBLANK('Benchmark Index'!S9),"--",'Benchmark Index'!S9) -> Travel | D55: =SUMIFS('P&L'!H$8:H$278,'P&L'!$D$8:$D$278,$C55)/$A$8 -> 0 | E55: =SUMIFS('P&L'!I$8:I$278,'P&L'!$D$8:$D$278,$C55)/$A$8 -> 0 | F55: =SUMIFS('P&L'!J$8:J$278,'P&L'!$D$8:$D$278,$C55)/$A$8 -> 0 | H55: =C55 -> Travel | I55: =SUMIFS('P&L'!L$8:L$278,'P&L'!$D$8:$D$278,$C55)/$A$8 -> 0 | J55: =SUMIFS('P&L'!M$8:M$278,'P&L'!$D$8:$D$278,$C55)/$A$8 -> 0 | K55: =SUMIFS('P&L'!N$8:N$278,'P&L'!$D$8:$D$278,$C55)/$A$8 -> 0 | M55: =H55 -> Travel | N55: =SUMIFS('P&L'!P$8:P$278,'P&L'!$D$8:$D$278,$C55)/$A$8 -> 0 | O55: =SUMIFS('P&L'!Q$8:Q$278,'P&L'!$D$8:$D$278,$C55)/$A$8 -> 0 | P55: =SUMIFS('P&L'!R$8:R$278,'P&L'!$D$8:$D$278,$C55)/$A$8 -> 0
C56: =IF(ISBLANK('Benchmark Index'!S10),"--",'Benchmark Index'!S10) -> COS | D56: =SUMIFS('P&L'!H$8:H$278,'P&L'!$D$8:$D$278,$C56)/$A$8 -> 0 | E56: =SUMIFS('P&L'!I$8:I$278,'P&L'!$D$8:$D$278,$C56)/$A$8 -> 0 | F56: =SUMIFS('P&L'!J$8:J$278,'P&L'!$D$8:$D$278,$C56)/$A$8 -> 0 | H56: =C56 -> COS | I56: =SUMIFS('P&L'!L$8:L$278,'P&L'!$D$8:$D$278,$C56)/$A$8 -> 0 | J56: =SUMIFS('P&L'!M$8:M$278,'P&L'!$D$8:$D$278,$C56)/$A$8 -> 0 | K56: =SUMIFS('P&L'!N$8:N$278,'P&L'!$D$8:$D$278,$C56)/$A$8 -> 0 | M56: =H56 -> COS | N56: =SUMIFS('P&L'!P$8:P$278,'P&L'!$D$8:$D$278,$C56)/$A$8 -> 0 | O56: =SUMIFS('P&L'!Q$8:Q$278,'P&L'!$D$8:$D$278,$C56)/$A$8 -> 0 | P56: =SUMIFS('P&L'!R$8:R$278,'P&L'!$D$8:$D$278,$C56)/$A$8 -> 0
C57: =IF(ISBLANK('Benchmark Index'!S11),"--",'Benchmark Index'!S11) -> Office admin | D57: =SUMIFS('P&L'!H$8:H$278,'P&L'!$D$8:$D$278,$C57)/$A$8 -> 0 | E57: =SUMIFS('P&L'!I$8:I$278,'P&L'!$D$8:$D$278,$C57)/$A$8 -> 0 | F57: =SUMIFS('P&L'!J$8:J$278,'P&L'!$D$8:$D$278,$C57)/$A$8 -> 0 | H57: =C57 -> Office admin | I57: =SUMIFS('P&L'!L$8:L$278,'P&L'!$D$8:$D$278,$C57)/$A$8 -> 0 | J57: =SUMIFS('P&L'!M$8:M$278,'P&L'!$D$8:$D$278,$C57)/$A$8 -> 0 | K57: =SUMIFS('P&L'!N$8:N$278,'P&L'!$D$8:$D$278,$C57)/$A$8 -> 0 | M57: =H57 -> Office admin | N57: =SUMIFS('P&L'!P$8:P$278,'P&L'!$D$8:$D$278,$C57)/$A$8 -> 0 | O57: =SUMIFS('P&L'!Q$8:Q$278,'P&L'!$D$8:$D$278,$C57)/$A$8 -> 0 | P57: =SUMIFS('P&L'!R$8:R$278,'P&L'!$D$8:$D$278,$C57)/$A$8 -> 0
C58: =IF(ISBLANK('Benchmark Index'!S12),"--",'Benchmark Index'!S12) -> Consultant | D58: =SUMIFS('P&L'!H$8:H$278,'P&L'!$D$8:$D$278,$C58)/$A$8 -> 0 | E58: =SUMIFS('P&L'!I$8:I$278,'P&L'!$D$8:$D$278,$C58)/$A$8 -> 0 | F58: =SUMIFS('P&L'!J$8:J$278,'P&L'!$D$8:$D$278,$C58)/$A$8 -> 0 | H58: =C58 -> Consultant | I58: =SUMIFS('P&L'!L$8:L$278,'P&L'!$D$8:$D$278,$C58)/$A$8 -> 0 | J58: =SUMIFS('P&L'!M$8:M$278,'P&L'!$D$8:$D$278,$C58)/$A$8 -> 0 | K58: =SUMIFS('P&L'!N$8:N$278,'P&L'!$D$8:$D$278,$C58)/$A$8 -> 0 | M58: =H58 -> Consultant | N58: =SUMIFS('P&L'!P$8:P$278,'P&L'!$D$8:$D$278,$C58)/$A$8 -> 0 | O58: =SUMIFS('P&L'!Q$8:Q$278,'P&L'!$D$8:$D$278,$C58)/$A$8 -> 0 | P58: =SUMIFS('P&L'!R$8:R$278,'P&L'!$D$8:$D$278,$C58)/$A$8 -> 0
C59: =IF(ISBLANK('Benchmark Index'!S13),"--",'Benchmark Index'!S13) -> Insurance | D59: =SUMIFS('P&L'!H$8:H$278,'P&L'!$D$8:$D$278,$C59)/$A$8 -> 7715.8 | E59: =SUMIFS('P&L'!I$8:I$278,'P&L'!$D$8:$D$278,$C59)/$A$8 -> 662.5 | F59: =SUMIFS('P&L'!J$8:J$278,'P&L'!$D$8:$D$278,$C59)/$A$8 -> -7053.3 | H59: =C59 -> Insurance | I59: =SUMIFS('P&L'!L$8:L$278,'P&L'!$D$8:$D$278,$C59)/$A$8 -> 7715.8 | J59: =SUMIFS('P&L'!M$8:M$278,'P&L'!$D$8:$D$278,$C59)/$A$8 -> 1987.5 | K59: =SUMIFS('P&L'!N$8:N$278,'P&L'!$D$8:$D$278,$C59)/$A$8 -> -5728.3 | M59: =H59 -> Insurance | N59: =SUMIFS('P&L'!P$8:P$278,'P&L'!$D$8:$D$278,$C59)/$A$8 -> 7715.8 | O59: =SUMIFS('P&L'!Q$8:Q$278,'P&L'!$D$8:$D$278,$C59)/$A$8 -> 7950 | P59: =SUMIFS('P&L'!R$8:R$278,'P&L'!$D$8:$D$278,$C59)/$A$8 -> 234.2
C60: =IF(ISBLANK('Benchmark Index'!S14),"--",'Benchmark Index'!S14) -> License | D60: =SUMIFS('P&L'!H$8:H$278,'P&L'!$D$8:$D$278,$C60)/$A$8 -> 0 | E60: =SUMIFS('P&L'!I$8:I$278,'P&L'!$D$8:$D$278,$C60)/$A$8 -> 0 | F60: =SUMIFS('P&L'!J$8:J$278,'P&L'!$D$8:$D$278,$C60)/$A$8 -> 0 | H60: =C60 -> License | I60: =SUMIFS('P&L'!L$8:L$278,'P&L'!$D$8:$D$278,$C60)/$A$8 -> 0 | J60: =SUMIFS('P&L'!M$8:M$278,'P&L'!$D$8:$D$278,$C60)/$A$8 -> 0 | K60: =SUMIFS('P&L'!N$8:N$278,'P&L'!$D$8:$D$278,$C60)/$A$8 -> 0 | M60: =H60 -> License | N60: =SUMIFS('P&L'!P$8:P$278,'P&L'!$D$8:$D$278,$C60)/$A$8 -> 0 | O60: =SUMIFS('P&L'!Q$8:Q$278,'P&L'!$D$8:$D$278,$C60)/$A$8 -> 0 | P60: =SUMIFS('P&L'!R$8:R$278,'P&L'!$D$8:$D$278,$C60)/$A$8 -> 0
C61: =IF(ISBLANK('Benchmark Index'!S15),"--",'Benchmark Index'!S15) -> Rent & Utilities | D61: =SUMIFS('P&L'!H$8:H$278,'P&L'!$D$8:$D$278,$C61)/$A$8 -> 50466.11 | E61: =SUMIFS('P&L'!I$8:I$278,'P&L'!$D$8:$D$278,$C61)/$A$8 -> 4936.7089 | F61: =SUMIFS('P&L'!J$8:J$278,'P&L'!$D$8:$D$278,$C61)/$A$8 -> -45529.401 | H61: =C61 -> Rent & Utilities | I61: =SUMIFS('P&L'!L$8:L$278,'P&L'!$D$8:$D$278,$C61)/$A$8 -> 50466.11 | J61: =SUMIFS('P&L'!M$8:M$278,'P&L'!$D$8:$D$278,$C61)/$A$8 -> 11518.987 | K61: =SUMIFS('P&L'!N$8:N$278,'P&L'!$D$8:$D$278,$C61)/$A$8 -> -38947.123 | M61: =H61 -> Rent & Utilities | N61: =SUMIFS('P&L'!P$8:P$278,'P&L'!$D$8:$D$278,$C61)/$A$8 -> 50466.11 | O61: =SUMIFS('P&L'!Q$8:Q$278,'P&L'!$D$8:$D$278,$C61)/$A$8 -> 41139.241 | P61: =SUMIFS('P&L'!R$8:R$278,'P&L'!$D$8:$D$278,$C61)/$A$8 -> -9326.8695
C62: =IF(ISBLANK('Benchmark Index'!S16),"--",'Benchmark Index'!S16) -> Marketing consultant | D62: =SUMIFS('P&L'!H$8:H$278,'P&L'!$D$8:$D$278,$C62)/$A$8 -> 0 | E62: =SUMIFS('P&L'!I$8:I$278,'P&L'!$D$8:$D$278,$C62)/$A$8 -> 0 | F62: =SUMIFS('P&L'!J$8:J$278,'P&L'!$D$8:$D$278,$C62)/$A$8 -> 0 | H62: =C62 -> Marketing consultant | I62: =SUMIFS('P&L'!L$8:L$278,'P&L'!$D$8:$D$278,$C62)/$A$8 -> 0 | J62: =SUMIFS('P&L'!M$8:M$278,'P&L'!$D$8:$D$278,$C62)/$A$8 -> 0 | K62: =SUMIFS('P&L'!N$8:N$278,'P&L'!$D$8:$D$278,$C62)/$A$8 -> 0 | M62: =H62 -> Marketing consultant | N62: =SUMIFS('P&L'!P$8:P$278,'P&L'!$D$8:$D$278,$C62)/$A$8 -> 0 | O62: =SUMIFS('P&L'!Q$8:Q$278,'P&L'!$D$8:$D$278,$C62)/$A$8 -> 0 | P62: =SUMIFS('P&L'!R$8:R$278,'P&L'!$D$8:$D$278,$C62)/$A$8 -> 0
C63: =IF(ISBLANK('Benchmark Index'!S17),"--",'Benchmark Index'!S17) -> Marketing general | D63: =SUMIFS('P&L'!H$8:H$278,'P&L'!$D$8:$D$278,$C63)/$A$8 -> 6018.94 | E63: =SUMIFS('P&L'!I$8:I$278,'P&L'!$D$8:$D$278,$C63)/$A$8 -> 25000 | F63: =SUMIFS('P&L'!J$8:J$278,'P&L'!$D$8:$D$278,$C63)/$A$8 -> 18981.06 | H63: =C63 -> Marketing general | I63: =SUMIFS('P&L'!L$8:L$278,'P&L'!$D$8:$D$278,$C63)/$A$8 -> 6018.94 | J63: =SUMIFS('P&L'!M$8:M$278,'P&L'!$D$8:$D$278,$C63)/$A$8 -> 115000 | K63: =SUMIFS('P&L'!N$8:N$278,'P&L'!$D$8:$D$278,$C63)/$A$8 -> 108981.06 | M63: =H63 -> Marketing general | N63: =SUMIFS('P&L'!P$8:P$278,'P&L'!$D$8:$D$278,$C63)/$A$8 -> 6018.94 | O63: =SUMIFS('P&L'!Q$8:Q$278,'P&L'!$D$8:$D$278,$C63)/$A$8 -> 228000 | P63: =SUMIFS('P&L'!R$8:R$278,'P&L'!$D$8:$D$278,$C63)/$A$8 -> 221981.06
C64: =IF(ISBLANK('Benchmark Index'!S18),"--",'Benchmark Index'!S18) -> Subcontractors & Consulting | D64: =SUMIFS('P&L'!H$8:H$278,'P&L'!$D$8:$D$278,$C64)/$A$8 -> 0 | E64: =SUMIFS('P&L'!I$8:I$278,'P&L'!$D$8:$D$278,$C64)/$A$8 -> 0 | F64: =SUMIFS('P&L'!J$8:J$278,'P&L'!$D$8:$D$278,$C64)/$A$8 -> 0 | H64: =C64 -> Subcontractors & Consulting | I64: =SUMIFS('P&L'!L$8:L$278,'P&L'!$D$8:$D$278,$C64)/$A$8 -> 0 | J64: =SUMIFS('P&L'!M$8:M$278,'P&L'!$D$8:$D$278,$C64)/$A$8 -> 0 | K64: =SUMIFS('P&L'!N$8:N$278,'P&L'!$D$8:$D$278,$C64)/$A$8 -> 0 | M64: =H64 -> Subcontractors & Consulting | N64: =SUMIFS('P&L'!P$8:P$278,'P&L'!$D$8:$D$278,$C64)/$A$8 -> 0 | O64: =SUMIFS('P&L'!Q$8:Q$278,'P&L'!$D$8:$D$278,$C64)/$A$8 -> 0 | P64: =SUMIFS('P&L'!R$8:R$278,'P&L'!$D$8:$D$278,$C64)/$A$8 -> 0
... C70: =IF(ISBLANK('Benchmark Index'!S24),"--",'Benchmark Index'!S24) -> Studies | D70: =SUMIFS('P&L'!H$8:H$278,'P&L'!$D$8:$D$278,$C70)/$A$8 -> 0 | E70: =SUMIFS('P&L'!I$8:I$278,'P&L'!$D$8:$D$278,$C70)/$A$8 -> 0 | F70: =SUMIFS('P&L'!J$8:J$278,'P&L'!$D$8:$D$278,$C70)/$A$8 -> 0 | H70: =C70 -> Studies | I70: =SUMIFS('P&L'!L$8:L$278,'P&L'!$D$8:$D$278,$C70)/$A$8 -> 0 | J70: =SUMIFS('P&L'!M$8:M$278,'P&L'!$D$8:$D$278,$C70)/$A$8 -> 0 | K70: =SUMIFS('P&L'!N$8:N$278,'P&L'!$D$8:$D$278,$C70)/$A$8 -> 0 | M70: =H70 -> Studies | N70: =SUMIFS('P&L'!P$8:P$278,'P&L'!$D$8:$D$278,$C70)/$A$8 -> 0 | O70: =SUMIFS('P&L'!Q$8:Q$278,'P&L'!$D$8:$D$278,$C70)/$A$8 -> 0 | P70: =SUMIFS('P&L'!R$8:R$278,'P&L'!$D$8:$D$278,$C70)/$A$8 -> 0
D71: =SUMIFS('P&L'!H$8:H$278,'P&L'!$D$8:$D$278,$C71)/$A$8 -> 0 | E71: =SUMIFS('P&L'!I$8:I$278,'P&L'!$D$8:$D$278,$C71)/$A$8 -> 0 | F71: =SUMIFS('P&L'!J$8:J$278,'P&L'!$D$8:$D$278,$C71)/$A$8 -> 0 | H71: =C71 -> 0 | I71: =SUMIFS('P&L'!L$8:L$278,'P&L'!$D$8:$D$278,$C71)/$A$8 -> 0 | J71: =SUMIFS('P&L'!M$8:M$278,'P&L'!$D$8:$D$278,$C71)/$A$8 -> 0 | K71: =SUMIFS('P&L'!N$8:N$278,'P&L'!$D$8:$D$278,$C71)/$A$8 -> 0 | M71: =H71 -> 0 | N71: =SUMIFS('P&L'!P$8:P$278,'P&L'!$D$8:$D$278,$C71)/$A$8 -> 0 | O71: =SUMIFS('P&L'!Q$8:Q$278,'P&L'!$D$8:$D$278,$C71)/$A$8 -> 0 | P71: =SUMIFS('P&L'!R$8:R$278,'P&L'!$D$8:$D$278,$C71)/$A$8 -> 0
C72: =IF(ISBLANK('Benchmark Index'!S26),"--",'Benchmark Index'!S26) -> BOM | D72: =SUMIFS('P&L'!H$8:H$278,'P&L'!$D$8:$D$278,$C72)/$A$8 -> 0 | E72: =SUMIFS('P&L'!I$8:I$278,'P&L'!$D$8:$D$278,$C72)/$A$8 -> 0 | F72: =SUMIFS('P&L'!J$8:J$278,'P&L'!$D$8:$D$278,$C72)/$A$8 -> 0 | H72: =C72 -> BOM | I72: =SUMIFS('P&L'!L$8:L$278,'P&L'!$D$8:$D$278,$C72)/$A$8 -> 0 | J72: =SUMIFS('P&L'!M$8:M$278,'P&L'!$D$8:$D$278,$C72)/$A$8 -> 0 | K72: =SUMIFS('P&L'!N$8:N$278,'P&L'!$D$8:$D$278,$C72)/$A$8 -> 0 | M72: =H72 -> BOM | N72: =SUMIFS('P&L'!P$8:P$278,'P&L'!$D$8:$D$278,$C72)/$A$8 -> 0 | O72: =SUMIFS('P&L'!Q$8:Q$278,'P&L'!$D$8:$D$278,$C72)/$A$8 -> 0 | P72: =SUMIFS('P&L'!R$8:R$278,'P&L'!$D$8:$D$278,$C72)/$A$8 -> 0
C73: =IF(ISBLANK('Benchmark Index'!S27),"--",'Benchmark Index'!S27) -> OCS | D73: =SUMIFS('P&L'!H$8:H$278,'P&L'!$D$8:$D$278,$C73)/$A$8 -> 0 | E73: =SUMIFS('P&L'!I$8:I$278,'P&L'!$D$8:$D$278,$C73)/$A$8 -> 0 | F73: =SUMIFS('P&L'!J$8:J$278,'P&L'!$D$8:$D$278,$C73)/$A$8 -> 0 | H73: =C73 -> OCS | I73: =SUMIFS('P&L'!L$8:L$278,'P&L'!$D$8:$D$278,$C73)/$A$8 -> 0 | J73: =SUMIFS('P&L'!M$8:M$278,'P&L'!$D$8:$D$278,$C73)/$A$8 -> 0 | K73: =SUMIFS('P&L'!N$8:N$278,'P&L'!$D$8:$D$278,$C73)/$A$8 -> 0 | M73: =H73 -> OCS | N73: =SUMIFS('P&L'!P$8:P$278,'P&L'!$D$8:$D$278,$C73)/$A$8 -> 0 | O73: =SUMIFS('P&L'!Q$8:Q$278,'P&L'!$D$8:$D$278,$C73)/$A$8 -> 0 | P73: =SUMIFS('P&L'!R$8:R$278,'P&L'!$D$8:$D$278,$C73)/$A$8 -> 0
C74: =IF(ISBLANK('Benchmark Index'!S28),"--",'Benchmark Index'!S28) -> Rev. Share | D74: =SUMIFS('P&L'!H$8:H$278,'P&L'!$D$8:$D$278,$C74)/$A$8 -> 0 | E74: =SUMIFS('P&L'!I$8:I$278,'P&L'!$D$8:$D$278,$C74)/$A$8 -> 0 | F74: =SUMIFS('P&L'!J$8:J$278,'P&L'!$D$8:$D$278,$C74)/$A$8 -> 0 | H74: =C74 -> Rev. Share | I74: =SUMIFS('P&L'!L$8:L$278,'P&L'!$D$8:$D$278,$C74)/$A$8 -> 0 | J74: =SUMIFS('P&L'!M$8:M$278,'P&L'!$D$8:$D$278,$C74)/$A$8 -> 0 | K74: =SUMIFS('P&L'!N$8:N$278,'P&L'!$D$8:$D$278,$C74)/$A$8 -> 0 | M74: =H74 -> Rev. Share | N74: =SUMIFS('P&L'!P$8:P$278,'P&L'!$D$8:$D$278,$C74)/$A$8 -> 0 | O74: =SUMIFS('P&L'!Q$8:Q$278,'P&L'!$D$8:$D$278,$C74)/$A$8 -> 0 | P74: =SUMIFS('P&L'!R$8:R$278,'P&L'!$D$8:$D$278,$C74)/$A$8 -> 0
C75: Office expenses | D75: =SUMIFS('P&L'!H$8:H$278,'P&L'!$D$8:$D$278,$C75)/$A$8 -> 70505.04 | E75: =SUMIFS('P&L'!I$8:I$278,'P&L'!$D$8:$D$278,$C75)/$A$8 -> 2044 | F75: =SUMIFS('P&L'!J$8:J$278,'P&L'!$D$8:$D$278,$C75)/$A$8 -> -68461.04 | H75: =C75 -> Office expenses | I75: =SUMIFS('P&L'!L$8:L$278,'P&L'!$D$8:$D$278,$C75)/$A$8 -> 70505.04 | J75: =SUMIFS('P&L'!M$8:M$278,'P&L'!$D$8:$D$278,$C75)/$A$8 -> 6132 | K75: =SUMIFS('P&L'!N$8:N$278,'P&L'!$D$8:$D$278,$C75)/$A$8 -> -64373.04 | M75: =H75 -> Office expenses | N75: =SUMIFS('P&L'!P$8:P$278,'P&L'!$D$8:$D$278,$C75)/$A$8 -> 70505.04 | O75: =SUMIFS('P&L'!Q$8:Q$278,'P&L'!$D$8:$D$278,$C75)/$A$8 -> 22056 | P75: =SUMIFS('P&L'!R$8:R$278,'P&L'!$D$8:$D$278,$C75)/$A$8 -> -48449.04
C76: =IF(ISBLANK('Benchmark Index'!S30),"--",'Benchmark Index'!S30) -> Cloud Computing | D76: =SUMIFS('P&L'!H$8:H$278,'P&L'!$D$8:$D$278,$C76)/$A$8 -> 0 | E76: =SUMIFS('P&L'!I$8:I$278,'P&L'!$D$8:$D$278,$C76)/$A$8 -> 0 | F76: =SUMIFS('P&L'!J$8:J$278,'P&L'!$D$8:$D$278,$C76)/$A$8 -> 0 | H76: =C76 -> Cloud Computing | I76: =SUMIFS('P&L'!L$8:L$278,'P&L'!$D$8:$D$278,$C76)/$A$8 -> 0 | J76: =SUMIFS('P&L'!M$8:M$278,'P&L'!$D$8:$D$278,$C76)/$A$8 -> 0 | K76: =SUMIFS('P&L'!N$8:N$278,'P&L'!$D$8:$D$278,$C76)/$A$8 -> 0 | M76: =H76 -> Cloud Computing | N76: =SUMIFS('P&L'!P$8:P$278,'P&L'!$D$8:$D$278,$C76)/$A$8 -> 0 | O76: =SUMIFS('P&L'!Q$8:Q$278,'P&L'!$D$8:$D$278,$C76)/$A$8 -> 0 | P76: =SUMIFS('P&L'!R$8:R$278,'P&L'!$D$8:$D$278,$C76)/$A$8 -> 0
C77: =IF(ISBLANK('Benchmark Index'!S31),"--",'Benchmark Index'!S31) -> Software | D77: =SUMIFS('P&L'!H$8:H$278,'P&L'!$D$8:$D$278,$C77)/$A$8 -> 0 | E77: =SUMIFS('P&L'!I$8:I$278,'P&L'!$D$8:$D$278,$C77)/$A$8 -> 0 | F77: =SUMIFS('P&L'!J$8:J$278,'P&L'!$D$8:$D$278,$C77)/$A$8 -> 0 | H77: =C77 -> Software | I77: =SUMIFS('P&L'!L$8:L$278,'P&L'!$D$8:$D$278,$C77)/$A$8 -> 0 | J77: =SUMIFS('P&L'!M$8:M$278,'P&L'!$D$8:$D$278,$C77)/$A$8 -> 0 | K77: =SUMIFS('P&L'!N$8:N$278,'P&L'!$D$8:$D$278,$C77)/$A$8 -> 0 | M77: =H77 -> Software | N77: =SUMIFS('P&L'!P$8:P$278,'P&L'!$D$8:$D$278,$C77)/$A$8 -> 0 | O77: =SUMIFS('P&L'!Q$8:Q$278,'P&L'!$D$8:$D$278,$C77)/$A$8 -> 0 | P77: =SUMIFS('P&L'!R$8:R$278,'P&L'!$D$8:$D$278,$C77)/$A$8 -> 0
C78: =IF(ISBLANK('Benchmark Index'!S32),"--",'Benchmark Index'!S32) -> Outsource | D78: =SUMIFS('P&L'!H$8:H$278,'P&L'!$D$8:$D$278,$C78)/$A$8 -> 52871.21 | E78: =SUMIFS('P&L'!I$8:I$278,'P&L'!$D$8:$D$278,$C78)/$A$8 -> 0 | F78: =SUMIFS('P&L'!J$8:J$278,'P&L'!$D$8:$D$278,$C78)/$A$8 -> -52871.21 | H78: =C78 -> Outsource | I78: =SUMIFS('P&L'!L$8:L$278,'P&L'!$D$8:$D$278,$C78)/$A$8 -> 52871.21 | J78: =SUMIFS('P&L'!M$8:M$278,'P&L'!$D$8:$D$278,$C78)/$A$8 -> 0 | K78: =SUMIFS('P&L'!N$8:N$278,'P&L'!$D$8:$D$278,$C78)/$A$8 -> -52871.21 | M78: =H78 -> Outsource | N78: =SUMIFS('P&L'!P$8:P$278,'P&L'!$D$8:$D$278,$C78)/$A$8 -> 52871.21 | O78: =SUMIFS('P&L'!Q$8:Q$278,'P&L'!$D$8:$D$278,$C78)/$A$8 -> 63000 | P78: =SUMIFS('P&L'!R$8:R$278,'P&L'!$D$8:$D$278,$C78)/$A$8 -> 10128.79
C79: =IF(ISBLANK('Benchmark Index'!S33),"--",'Benchmark Index'!S33) -> Professional | D79: =SUMIFS('P&L'!H$8:H$278,'P&L'!$D$8:$D$278,$C79)/$A$8 -> 44395.17 | E79: =SUMIFS('P&L'!I$8:I$278,'P&L'!$D$8:$D$278,$C79)/$A$8 -> 7544.625 | F79: =SUMIFS('P&L'!J$8:J$278,'P&L'!$D$8:$D$278,$C79)/$A$8 -> -36850.545 | H79: =C79 -> Professional | I79: =SUMIFS('P&L'!L$8:L$278,'P&L'!$D$8:$D$278,$C79)/$A$8 -> 44395.17 | J79: =SUMIFS('P&L'!M$8:M$278,'P&L'!$D$8:$D$278,$C79)/$A$8 -> 19633.875 | K79: =SUMIFS('P&L'!N$8:N$278,'P&L'!$D$8:$D$278,$C79)/$A$8 -> -24761.295 | M79: =H79 -> Professional | N79: =SUMIFS('P&L'!P$8:P$278,'P&L'!$D$8:$D$278,$C79)/$A$8 -> 44395.17 | O79: =SUMIFS('P&L'!Q$8:Q$278,'P&L'!$D$8:$D$278,$C79)/$A$8 -> 65607.625 | P79: =SUMIFS('P&L'!R$8:R$278,'P&L'!$D$8:$D$278,$C79)/$A$8 -> 21212.455
C80: =IF(ISBLANK('Benchmark Index'!S34),"--",'Benchmark Index'!S34) -> Welfare | D80: =SUMIFS('P&L'!H$8:H$278,'P&L'!$D$8:$D$278,$C80)/$A$8 -> 35569.44 | E80: =SUMIFS('P&L'!I$8:I$278,'P&L'!$D$8:$D$278,$C80)/$A$8 -> 2000 | F80: =SUMIFS('P&L'!J$8:J$278,'P&L'!$D$8:$D$278,$C80)/$A$8 -> -33569.44 | H80: =C80 -> Welfare | I80: =SUMIFS('P&L'!L$8:L$278,'P&L'!$D$8:$D$278,$C80)/$A$8 -> 35569.44 | J80: =SUMIFS('P&L'!M$8:M$278,'P&L'!$D$8:$D$278,$C80)/$A$8 -> 6000 | K80: =SUMIFS('P&L'!N$8:N$278,'P&L'!$D$8:$D$278,$C80)/$A$8 -> -29569.44 | M80: =H80 -> Welfare | N80: =SUMIFS('P&L'!P$8:P$278,'P&L'!$D$8:$D$278,$C80)/$A$8 -> 35569.44 | O80: =SUMIFS('P&L'!Q$8:Q$278,'P&L'!$D$8:$D$278,$C80)/$A$8 -> 18300 | P80: =SUMIFS('P&L'!R$8:R$278,'P&L'!$D$8:$D$278,$C80)/$A$8 -> -17269.44
C81: =IF(ISBLANK('Benchmark Index'!S35),"--",'Benchmark Index'!S35) -> Hosting | D81: =SUMIFS('P&L'!H$8:H$278,'P&L'!$D$8:$D$278,$C81)/$A$8 -> 88.59 | E81: =SUMIFS('P&L'!I$8:I$278,'P&L'!$D$8:$D$278,$C81)/$A$8 -> 0 | F81: =SUMIFS('P&L'!J$8:J$278,'P&L'!$D$8:$D$278,$C81)/$A$8 -> -88.59 | H81: =C81 -> Hosting | I81: =SUMIFS('P&L'!L$8:L$278,'P&L'!$D$8:$D$278,$C81)/$A$8 -> 88.59 | J81: =SUMIFS('P&L'!M$8:M$278,'P&L'!$D$8:$D$278,$C81)/$A$8 -> 0 | K81: =SUMIFS('P&L'!N$8:N$278,'P&L'!$D$8:$D$278,$C81)/$A$8 -> -88.59 | M81: =H81 -> Hosting | N81: =SUMIFS('P&L'!P$8:P$278,'P&L'!$D$8:$D$278,$C81)/$A$8 -> 88.59 | O81: =SUMIFS('P&L'!Q$8:Q$278,'P&L'!$D$8:$D$278,$C81)/$A$8 -> 20000 | P81: =SUMIFS('P&L'!R$8:R$278,'P&L'!$D$8:$D$278,$C81)/$A$8 -> 19911.41
C82: =IF(ISBLANK('Benchmark Index'!S36),"--",'Benchmark Index'!S36) -> Relocation Expenses | D82: =SUMIFS('P&L'!H$8:H$278,'P&L'!$D$8:$D$278,$C82)/$A$8 -> 0 | E82: =SUMIFS('P&L'!I$8:I$278,'P&L'!$D$8:$D$278,$C82)/$A$8 -> 0 | F82: =SUMIFS('P&L'!J$8:J$278,'P&L'!$D$8:$D$278,$C82)/$A$8 -> 0 | H82: =C82 -> Relocation Expenses | I82: =SUMIFS('P&L'!L$8:L$278,'P&L'!$D$8:$D$278,$C82)/$A$8 -> 0 | J82: =SUMIFS('P&L'!M$8:M$278,'P&L'!$D$8:$D$278,$C82)/$A$8 -> 0 | K82: =SUMIFS('P&L'!N$8:N$278,'P&L'!$D$8:$D$278,$C82)/$A$8 -> 0 | M82: =H82 -> Relocation Expenses | N82: =SUMIFS('P&L'!P$8:P$278,'P&L'!$D$8:$D$278,$C82)/$A$8 -> 0 | O82: =SUMIFS('P&L'!Q$8:Q$278,'P&L'!$D$8:$D$278,$C82)/$A$8 -> 0 | P82: =SUMIFS('P&L'!R$8:R$278,'P&L'!$D$8:$D$278,$C82)/$A$8 -> 0
C83: =IF(ISBLANK('Benchmark Index'!S37),"--",'Benchmark Index'!S37) -> Tools | D83: =SUMIFS('P&L'!H$8:H$278,'P&L'!$D$8:$D$278,$C83)/$A$8 -> 40734.05 | E83: =SUMIFS('P&L'!I$8:I$278,'P&L'!$D$8:$D$278,$C83)/$A$8 -> 1800 | F83: =SUMIFS('P&L'!J$8:J$278,'P&L'!$D$8:$D$278,$C83)/$A$8 -> -38934.05 | H83: =C83 -> Tools | I83: =SUMIFS('P&L'!L$8:L$278,'P&L'!$D$8:$D$278,$C83)/$A$8 -> 40734.05 | J83: =SUMIFS('P&L'!M$8:M$278,'P&L'!$D$8:$D$278,$C83)/$A$8 -> 5400 | K83: =SUMIFS('P&L'!N$8:N$278,'P&L'!$D$8:$D$278,$C83)/$A$8 -> -35334.05 | M83: =H83 -> Tools | N83: =SUMIFS('P&L'!P$8:P$278,'P&L'!$D$8:$D$278,$C83)/$A$8 -> 40734.05 | O83: =SUMIFS('P&L'!Q$8:Q$278,'P&L'!$D$8:$D$278,$C83)/$A$8 -> 15750 | P83: =SUMIFS('P&L'!R$8:R$278,'P&L'!$D$8:$D$278,$C83)/$A$8 -> -24984.05
C84: =IF(ISBLANK('Benchmark Index'!S38),"--",'Benchmark Index'!S38) -> Tapeout | D84: =SUMIFS('P&L'!H$8:H$278,'P&L'!$D$8:$D$278,$C84)/$A$8 -> 0 | E84: =SUMIFS('P&L'!I$8:I$278,'P&L'!$D$8:$D$278,$C84)/$A$8 -> 0 | F84: =SUMIFS('P&L'!J$8:J$278,'P&L'!$D$8:$D$278,$C84)/$A$8 -> 0 | H84: =C84 -> Tapeout | I84: =SUMIFS('P&L'!L$8:L$278,'P&L'!$D$8:$D$278,$C84)/$A$8 -> 0 | J84: =SUMIFS('P&L'!M$8:M$278,'P&L'!$D$8:$D$278,$C84)/$A$8 -> 0 | K84: =SUMIFS('P&L'!N$8:N$278,'P&L'!$D$8:$D$278,$C84)/$A$8 -> 0 | M84: =H84 -> Tapeout | N84: =SUMIFS('P&L'!P$8:P$278,'P&L'!$D$8:$D$278,$C84)/$A$8 -> 0 | O84: =SUMIFS('P&L'!Q$8:Q$278,'P&L'!$D$8:$D$278,$C84)/$A$8 -> 0 | P84: =SUMIFS('P&L'!R$8:R$278,'P&L'!$D$8:$D$278,$C84)/$A$8 -> 0
C85: =IF(ISBLANK('Benchmark Index'!S39),"--",'Benchmark Index'!S39) -> Hardware | D85: =SUMIFS('P&L'!H$8:H$278,'P&L'!$D$8:$D$278,$C85)/$A$8 -> 0 | E85: =SUMIFS('P&L'!I$8:I$278,'P&L'!$D$8:$D$278,$C85)/$A$8 -> 0 | F85: =SUMIFS('P&L'!J$8:J$278,'P&L'!$D$8:$D$278,$C85)/$A$8 -> 0 | H85: =C85 -> Hardware | I85: =SUMIFS('P&L'!L$8:L$278,'P&L'!$D$8:$D$278,$C85)/$A$8 -> 0 | J85: =SUMIFS('P&L'!M$8:M$278,'P&L'!$D$8:$D$278,$C85)/$A$8 -> 0 | K85: =SUMIFS('P&L'!N$8:N$278,'P&L'!$D$8:$D$278,$C85)/$A$8 -> 0 | M85: =H85 -> Hardware | N85: =SUMIFS('P&L'!P$8:P$278,'P&L'!$D$8:$D$278,$C85)/$A$8 -> 0 | O85: =SUMIFS('P&L'!Q$8:Q$278,'P&L'!$D$8:$D$278,$C85)/$A$8 -> 0 | P85: =SUMIFS('P&L'!R$8:R$278,'P&L'!$D$8:$D$278,$C85)/$A$8 -> 0
C86: =IF(ISBLANK('Benchmark Index'!S40),"--",'Benchmark Index'!S40) -> rental of lab equipment | D86: =SUMIFS('P&L'!H$8:H$278,'P&L'!$D$8:$D$278,$C86)/$A$8 -> 0 | E86: =SUMIFS('P&L'!I$8:I$278,'P&L'!$D$8:$D$278,$C86)/$A$8 -> 0 | F86: =SUMIFS('P&L'!J$8:J$278,'P&L'!$D$8:$D$278,$C86)/$A$8 -> 0 | H86: =C86 -> rental of lab equipment | I86: =SUMIFS('P&L'!L$8:L$278,'P&L'!$D$8:$D$278,$C86)/$A$8 -> 0 | J86: =SUMIFS('P&L'!M$8:M$278,'P&L'!$D$8:$D$278,$C86)/$A$8 -> 0 | K86: =SUMIFS('P&L'!N$8:N$278,'P&L'!$D$8:$D$278,$C86)/$A$8 -> 0 | M86: =H86 -> rental of lab equipment | N86: =SUMIFS('P&L'!P$8:P$278,'P&L'!$D$8:$D$278,$C86)/$A$8 -> 0 | O86: =SUMIFS('P&L'!Q$8:Q$278,'P&L'!$D$8:$D$278,$C86)/$A$8 -> 0 | P86: =SUMIFS('P&L'!R$8:R$278,'P&L'!$D$8:$D$278,$C86)/$A$8 -> 0
C87: =IF(ISBLANK('Benchmark Index'!S41),"--",'Benchmark Index'!S41) -> Manufacturing | D87: =SUMIFS('P&L'!H$8:H$278,'P&L'!$D$8:$D$278,$C87)/$A$8 -> 0 | E87: =SUMIFS('P&L'!I$8:I$278,'P&L'!$D$8:$D$278,$C87)/$A$8 -> 0 | F87: =SUMIFS('P&L'!J$8:J$278,'P&L'!$D$8:$D$278,$C87)/$A$8 -> 0 | H87: =C87 -> Manufacturing | I87: =SUMIFS('P&L'!L$8:L$278,'P&L'!$D$8:$D$278,$C87)/$A$8 -> 0 | J87: =SUMIFS('P&L'!M$8:M$278,'P&L'!$D$8:$D$278,$C87)/$A$8 -> 0 | K87: =SUMIFS('P&L'!N$8:N$278,'P&L'!$D$8:$D$278,$C87)/$A$8 -> 0 | M87: =H87 -> Manufacturing | N87: =SUMIFS('P&L'!P$8:P$278,'P&L'!$D$8:$D$278,$C87)/$A$8 -> 0 | O87: =SUMIFS('P&L'!Q$8:Q$278,'P&L'!$D$8:$D$278,$C87)/$A$8 -> 0 | P87: =SUMIFS('P&L'!R$8:R$278,'P&L'!$D$8:$D$278,$C87)/$A$8 -> 0
... C90: =IF(ISBLANK('Benchmark Index'!S44),"--",'Benchmark Index'!S44) -> CT Expenses | D90: =SUMIFS('P&L'!H$8:H$278,'P&L'!$D$8:$D$278,$C90)/$A$8 -> 0 | E90: =SUMIFS('P&L'!I$8:I$278,'P&L'!$D$8:$D$278,$C90)/$A$8 -> 0 | F90: =SUMIFS('P&L'!J$8:J$278,'P&L'!$D$8:$D$278,$C90)/$A$8 -> 0 | H90: =C90 -> CT Expenses | I90: =SUMIFS('P&L'!L$8:L$278,'P&L'!$D$8:$D$278,$C90)/$A$8 -> 0 | J90: =SUMIFS('P&L'!M$8:M$278,'P&L'!$D$8:$D$278,$C90)/$A$8 -> 0 | K90: =SUMIFS('P&L'!N$8:N$278,'P&L'!$D$8:$D$278,$C90)/$A$8 -> 0 | M90: =H90 -> CT Expenses | N90: =SUMIFS('P&L'!P$8:P$278,'P&L'!$D$8:$D$278,$C90)/$A$8 -> 0 | O90: =SUMIFS('P&L'!Q$8:Q$278,'P&L'!$D$8:$D$278,$C90)/$A$8 -> 0 | P90: =SUMIFS('P&L'!R$8:R$278,'P&L'!$D$8:$D$278,$C90)/$A$8 -> 0
C91: =IF(ISBLANK('Benchmark Index'!S54),"--",'Benchmark Index'!S54) -> Signing bonus | D91: =SUMIFS('P&L'!H$8:H$278,'P&L'!$D$8:$D$278,$C91)/$A$8 -> 15800.67 | E91: =SUMIFS('P&L'!I$8:I$278,'P&L'!$D$8:$D$278,$C91)/$A$8 -> 0 | F91: =SUMIFS('P&L'!J$8:J$278,'P&L'!$D$8:$D$278,$C91)/$A$8 -> -15800.67 | H91: =C91 -> Signing bonus | I91: =SUMIFS('P&L'!L$8:L$278,'P&L'!$D$8:$D$278,$C91)/$A$8 -> 15800.67 | J91: =SUMIFS('P&L'!M$8:M$278,'P&L'!$D$8:$D$278,$C91)/$A$8 -> 0 | K91: =SUMIFS('P&L'!N$8:N$278,'P&L'!$D$8:$D$278,$C91)/$A$8 -> -15800.67 | M91: =H91 -> Signing bonus | N91: =SUMIFS('P&L'!P$8:P$278,'P&L'!$D$8:$D$278,$C91)/$A$8 -> 15800.67 | O91: =SUMIFS('P&L'!Q$8:Q$278,'P&L'!$D$8:$D$278,$C91)/$A$8 -> 0 | P91: =SUMIFS('P&L'!R$8:R$278,'P&L'!$D$8:$D$278,$C91)/$A$8 -> -15800.67
C92: Total Opex | D92: =SUM(D53:D91) -> 1932607.5 | E92: =SUM(E53:E91) -> 224054.1 | F92: =SUM(F53:F91) -> -1708553.4 | H92: =C92 -> Total Opex | I92: =SUM(I53:I91) -> 1932607.5 | J92: =SUM(J53:J91) -> 705871.16 | K92: =SUM(K53:K91) -> -1226736.4 | M92: =H92 -> Total Opex | N92: =SUM(N53:N91) -> 1932607.5 | O92: =SUM(O53:O91) -> 2064205.6 | P92: =SUM(P53:P91) -> 131598.07
D93: =IF(ROUND(D92*$A$8,0)=ROUND(SUM(D15,D26)*$A$8,0),"","Error") | E93: =IF(ROUND(E92*$A$8,0)=ROUND(SUM(E15,E26)*$A$8,0),"","Error") | I93: =IF(ROUND(I92*$A$8,0)=ROUND(SUM(I15,I26)*$A$8,0),"","Error") | J93: =IF(ROUND(J92*$A$8,0)=ROUND(SUM(J15,J26)*$A$8,0),"","Error") | N93: =IF(ROUND(N92*$A$8,0)=ROUND(SUM(N15,N26)*$A$8,0),"","Error") | O93: =IF(ROUND(O92*$A$8,0)=ROUND(SUM(O15,O26)*$A$8,0),"","Error")

Sheet Financial highlights
A1: =IF(E3="$",1,IF(E3="$k",1000,1000000)) -> 1
A2: Errors in this sheet: | C2: ='P&L'!E2 -> Pocket Pie Studios Ltd.
A3: =COUNTIF(D28:R28,"error")+COUNTIF(D38:R38,"error")+COUNTIF(D51:R51,"error")+COUNTIF(D104:R104,"error") -> 0 | C3: Financial Highlights | E3: $
A4: General errors in file:
A5: ='Actual vs Budget'!A5 -> 5 | C5: Financial highlights | D5: 44197 | E5: 44228 | F5: 44256 | G5: 44287 | H5: 44317 | I5: 44348 | J5: 44378 | K5: 44409 | L5: 44440 | M5: 44470 | N5: 44501 | O5: 44531 | Q5: 2021 YTD
C6: $K | D6: Actual | E6: Actual | F6: Actual | G6: Actual | H6: Actual | I6: Actual | J6: Actual | K6: Actual | L6: Actual | M6: Actual | N6: Actual | O6: Actual | Q6: Actual | R6: Budget
C7: KPI
C8: # of customers
C9: MRR
C10: ARR
C12: P&L Summary
A13: 1 | C13: Revenues | D13: =SUMIFS('P&L'!X$8:X$276,'P&L'!$C$8:$C$276,$A13)/$A$1 -> 0 | E13: =SUMIFS('P&L'!Y$8:Y$276,'P&L'!$C$8:$C$276,$A13)/$A$1 -> 0 | F13: =SUMIFS('P&L'!Z$8:Z$276,'P&L'!$C$8:$C$276,$A13)/$A$1 -> 0 | H13: =SUMIFS('P&L'!AB$8:AB$276,'P&L'!$C$8:$C$276,$A13)/$A$1 -> 0 | I13: =SUMIFS('P&L'!AC$8:AC$276,'P&L'!$C$8:$C$276,$A13)/$A$1 -> 0 | J13: =SUMIFS('P&L'!AD$8:AD$276,'P&L'!$C$8:$C$276,$A13)/$A$1 -> 0 | K13: =SUMIFS('P&L'!AE$8:AE$276,'P&L'!$C$8:$C$276,$A13)/$A$1 -> 0 | L13: =SUMIFS('P&L'!AF$8:AF$276,'P&L'!$C$8:$C$276,$A13)/$A$1 -> 0 | M13: =SUMIFS('P&L'!AG$8:AG$276,'P&L'!$C$8:$C$276,$A13)/$A$1 -> 0 | N13: =SUMIFS('P&L'!AH$8:AH$276,'P&L'!$C$8:$C$276,$A13)/$A$1 -> 0 | O13: =SUMIFS('P&L'!AI$8:AI$276,'P&L'!$C$8:$C$276,$A13)/$A$1 -> 0 | Q13: =F13+I13+L13+O13 -> 0 | R13: =IFERROR(INDEX('P&L'!$Q$8:$Q$278,MATCH($A13,'P&L'!$C$8:$C$278,0)),0)/$A$1 -> 0
A14: 2 | C14: COS | D14: =SUMIFS('P&L'!X$8:X$276,'P&L'!$C$8:$C$276,$A14)/$A$1 -> 0 | E14: =SUMIFS('P&L'!Y$8:Y$276,'P&L'!$C$8:$C$276,$A14)/$A$1 -> 0 | F14: =SUMIFS('P&L'!Z$8:Z$276,'P&L'!$C$8:$C$276,$A14)/$A$1 -> 0 | G14: =SUMIFS('P&L'!AA$8:AA$276,'P&L'!$C$8:$C$276,$A14)/$A$1 -> 0 | H14: =SUMIFS('P&L'!AB$8:AB$276,'P&L'!$C$8:$C$276,$A14)/$A$1 -> 0 | I14: =SUMIFS('P&L'!AC$8:AC$276,'P&L'!$C$8:$C$276,$A14)/$A$1 -> 0 | J14: =SUMIFS('P&L'!AD$8:AD$276,'P&L'!$C$8:$C$276,$A14)/$A$1 -> 0 | K14: =SUMIFS('P&L'!AE$8:AE$276,'P&L'!$C$8:$C$276,$A14)/$A$1 -> 0 | ... O14: =SUMIFS('P&L'!AI$8:AI$276,'P&L'!$C$8:$C$276,$A14)/$A$1 -> 0 | Q14: =IFERROR(INDEX('P&L'!$P$8:$P$278,MATCH($A14,'P&L'!$C$8:$C$278,0)),0)/$A$1 -> 0 | R14: =IFERROR(INDEX('P&L'!$Q$8:$Q$278,MATCH($A14,'P&L'!$C$8:$C$278,0)),0)/$A$1 -> 0
C15: Gross Profit | D15: =D13-D14 -> 0 | E15: =E13-E14 -> 0 | F15: =F13-F14 -> 0 | G15: =G13-G14 -> 0 | H15: =H13-H14 -> 0 | I15: =I13-I14 -> 0 | J15: =J13-J14 -> 0 | K15: =K13-K14 -> 0 | ... O15: =O13-O14 -> 0 | Q15: =Q13-Q14 -> 0 | R15: =R13-R14 -> 0
C16: Gross margin | D16: =IFERROR(+D15/D13,0) -> 0 | E16: =IFERROR(+E15/E13,0) -> 0 | F16: =IFERROR(+F15/F13,0) -> 0 | G16: =IFERROR(+G15/G13,0) -> 0 | H16: =IFERROR(+H15/H13,0) -> 0 | I16: =IFERROR(+I15/I13,0) -> 0 | J16: =IFERROR(+J15/J13,0) -> 0 | K16: =IFERROR(+K15/K13,0) -> 0 | ... O16: =IFERROR(+O15/O13,0) -> 0 | Q16: =IFERROR(+Q15/Q13,0) -> 0 | R16: =IFERROR(+R15/R13,0) -> 0
C17: Operational costs
A18: 11 | C18: =RIGHT(INDEX('P&L'!$E$5:$E$275,MATCH($A18,'P&L'!$C$5:$C$275,0)),LEN(INDEX('P&L'!$E$5:$E$275,MATCH($A18,'P&L'!$C$5:$C$275,0)))-6) -> R&D | D18: =SUMIFS('P&L'!X$8:X$276,'P&L'!$C$8:$C$276,$A18)/$A$1 -> 0 | E18: =SUMIFS('P&L'!Y$8:Y$276,'P&L'!$C$8:$C$276,$A18)/$A$1 -> 0 | F18: =SUMIFS('P&L'!Z$8:Z$276,'P&L'!$C$8:$C$276,$A18)/$A$1 -> 0 | H18: =SUMIFS('P&L'!AB$8:AB$276,'P&L'!$C$8:$C$276,$A18)/$A$1 -> 0 | I18: =SUMIFS('P&L'!AC$8:AC$276,'P&L'!$C$8:$C$276,$A18)/$A$1 -> 0 | J18: =SUMIFS('P&L'!AD$8:AD$276,'P&L'!$C$8:$C$276,$A18)/$A$1 -> 0 | K18: =SUMIFS('P&L'!AE$8:AE$276,'P&L'!$C$8:$C$276,$A18)/$A$1 -> 0 | L18: =SUMIFS('P&L'!AF$8:AF$276,'P&L'!$C$8:$C$276,$A18)/$A$1 -> 0 | M18: =SUMIFS('P&L'!AG$8:AG$276,'P&L'!$C$8:$C$276,$A18)/$A$1 -> 0 | N18: =SUMIFS('P&L'!AH$8:AH$276,'P&L'!$C$8:$C$276,$A18)/$A$1 -> 0 | O18: =SUMIFS('P&L'!AI$8:AI$276,'P&L'!$C$8:$C$276,$A18)/$A$1 -> 669810.02 | Q18: =F18+I18+L18+O18 -> 669810.02 | R18: =IFERROR(INDEX('P&L'!$Q$8:$Q$278,MATCH($A18,'P&L'!$C$8:$C$278,0)),0)/$A$1 -> 654302.04
A19: 12 | C19: =RIGHT(INDEX('P&L'!$E$5:$E$275,MATCH($A19,'P&L'!$C$5:$C$275,0)),LEN(INDEX('P&L'!$E$5:$E$275,MATCH($A19,'P&L'!$C$5:$C$275,0)))-6) -> Product | D19: =SUMIFS('P&L'!X$8:X$276,'P&L'!$C$8:$C$276,$A19)/$A$1 -> 0 | E19: =SUMIFS('P&L'!Y$8:Y$276,'P&L'!$C$8:$C$276,$A19)/$A$1 -> 0 | F19: =SUMIFS('P&L'!Z$8:Z$276,'P&L'!$C$8:$C$276,$A19)/$A$1 -> 0 | H19: =SUMIFS('P&L'!AB$8:AB$276,'P&L'!$C$8:$C$276,$A19)/$A$1 -> 0 | I19: =SUMIFS('P&L'!AC$8:AC$276,'P&L'!$C$8:$C$276,$A19)/$A$1 -> 0 | J19: =SUMIFS('P&L'!AD$8:AD$276,'P&L'!$C$8:$C$276,$A19)/$A$1 -> 0 | K19: =SUMIFS('P&L'!AE$8:AE$276,'P&L'!$C$8:$C$276,$A19)/$A$1 -> 0 | L19: =SUMIFS('P&L'!AF$8:AF$276,'P&L'!$C$8:$C$276,$A19)/$A$1 -> 0 | M19: =SUMIFS('P&L'!AG$8:AG$276,'P&L'!$C$8:$C$276,$A19)/$A$1 -> 0 | N19: =SUMIFS('P&L'!AH$8:AH$276,'P&L'!$C$8:$C$276,$A19)/$A$1 -> 0 | O19: =SUMIFS('P&L'!AI$8:AI$276,'P&L'!$C$8:$C$276,$A19)/$A$1 -> 326761.88 | Q19: =F19+I19+L19+O19 -> 326761.88 | R19: =IFERROR(INDEX('P&L'!$Q$8:$Q$278,MATCH($A19,'P&L'!$C$8:$C$278,0)),0)/$A$1 -> 251033.92
A20: 13 | C20: =RIGHT(INDEX('P&L'!$E$5:$E$275,MATCH($A20,'P&L'!$C$5:$C$275,0)),LEN(INDEX('P&L'!$E$5:$E$275,MATCH($A20,'P&L'!$C$5:$C$275,0)))-6) -> Art | D20: =SUMIFS('P&L'!X$8:X$276,'P&L'!$C$8:$C$276,$A20)/$A$1 -> 0 | E20: =SUMIFS('P&L'!Y$8:Y$276,'P&L'!$C$8:$C$276,$A20)/$A$1 -> 0 | F20: =SUMIFS('P&L'!Z$8:Z$276,'P&L'!$C$8:$C$276,$A20)/$A$1 -> 0 | H20: =SUMIFS('P&L'!AB$8:AB$276,'P&L'!$C$8:$C$276,$A20)/$A$1 -> 0 | I20: =SUMIFS('P&L'!AC$8:AC$276,'P&L'!$C$8:$C$276,$A20)/$A$1 -> 0 | J20: =SUMIFS('P&L'!AD$8:AD$276,'P&L'!$C$8:$C$276,$A20)/$A$1 -> 0 | K20: =SUMIFS('P&L'!AE$8:AE$276,'P&L'!$C$8:$C$276,$A20)/$A$1 -> 0 | L20: =SUMIFS('P&L'!AF$8:AF$276,'P&L'!$C$8:$C$276,$A20)/$A$1 -> 0 | M20: =SUMIFS('P&L'!AG$8:AG$276,'P&L'!$C$8:$C$276,$A20)/$A$1 -> 0 | N20: =SUMIFS('P&L'!AH$8:AH$276,'P&L'!$C$8:$C$276,$A20)/$A$1 -> 0 | O20: =SUMIFS('P&L'!AI$8:AI$276,'P&L'!$C$8:$C$276,$A20)/$A$1 -> 664947.33 | Q20: =F20+I20+L20+O20 -> 664947.33 | R20: =IFERROR(INDEX('P&L'!$Q$8:$Q$278,MATCH($A20,'P&L'!$C$8:$C$278,0)),0)/$A$1 -> 577647.58
A21: 14 | C21: =RIGHT(INDEX('P&L'!$E$5:$E$275,MATCH($A21,'P&L'!$C$5:$C$275,0)),LEN(INDEX('P&L'!$E$5:$E$275,MATCH($A21,'P&L'!$C$5:$C$275,0)))-6) -> Sales Costs | D21: =SUMIFS('P&L'!X$8:X$276,'P&L'!$C$8:$C$276,$A21)/$A$1 -> 0 | E21: =SUMIFS('P&L'!Y$8:Y$276,'P&L'!$C$8:$C$276,$A21)/$A$1 -> 0 | F21: =SUMIFS('P&L'!Z$8:Z$276,'P&L'!$C$8:$C$276,$A21)/$A$1 -> 0 | H21: =SUMIFS('P&L'!AB$8:AB$276,'P&L'!$C$8:$C$276,$A21)/$A$1 -> 0 | I21: =SUMIFS('P&L'!AC$8:AC$276,'P&L'!$C$8:$C$276,$A21)/$A$1 -> 0 | J21: =SUMIFS('P&L'!AD$8:AD$276,'P&L'!$C$8:$C$276,$A21)/$A$1 -> 0 | K21: =SUMIFS('P&L'!AE$8:AE$276,'P&L'!$C$8:$C$276,$A21)/$A$1 -> 0 | L21: =SUMIFS('P&L'!AF$8:AF$276,'P&L'!$C$8:$C$276,$A21)/$A$1 -> 0 | M21: =SUMIFS('P&L'!AG$8:AG$276,'P&L'!$C$8:$C$276,$A21)/$A$1 -> 0 | N21: =SUMIFS('P&L'!AH$8:AH$276,'P&L'!$C$8:$C$276,$A21)/$A$1 -> 0 | O21: =SUMIFS('P&L'!AI$8:AI$276,'P&L'!$C$8:$C$276,$A21)/$A$1 -> 0 | Q21: =F21+I21+L21+O21 -> 0 | R21: =IFERROR(INDEX('P&L'!$Q$8:$Q$278,MATCH($A21,'P&L'!$C$8:$C$278,0)),0)/$A$1 -> 128000
A22: 15 | C22: =RIGHT(INDEX('P&L'!$E$5:$E$275,MATCH($A22,'P&L'!$C$5:$C$275,0)),LEN(INDEX('P&L'!$E$5:$E$275,MATCH($A22,'P&L'!$C$5:$C$275,0)))-6) -> Marketing Costs | D22: =SUMIFS('P&L'!X$8:X$276,'P&L'!$C$8:$C$276,$A22)/$A$1 -> 0 | E22: =SUMIFS('P&L'!Y$8:Y$276,'P&L'!$C$8:$C$276,$A22)/$A$1 -> 0 | F22: =SUMIFS('P&L'!Z$8:Z$276,'P&L'!$C$8:$C$276,$A22)/$A$1 -> 0 | G22: =SUMIFS('P&L'!AA$8:AA$276,'P&L'!$C$8:$C$276,$A22)/$A$1 -> 0 | H22: =SUMIFS('P&L'!AB$8:AB$276,'P&L'!$C$8:$C$276,$A22)/$A$1 -> 0 | I22: =SUMIFS('P&L'!AC$8:AC$276,'P&L'!$C$8:$C$276,$A22)/$A$1 -> 0 | J22: =SUMIFS('P&L'!AD$8:AD$276,'P&L'!$C$8:$C$276,$A22)/$A$1 -> 0 | K22: =SUMIFS('P&L'!AE$8:AE$276,'P&L'!$C$8:$C$276,$A22)/$A$1 -> 0 | ... O22: =SUMIFS('P&L'!AI$8:AI$276,'P&L'!$C$8:$C$276,$A22)/$A$1 -> 6018.94 | Q22: =IFERROR(INDEX('P&L'!$P$8:$P$278,MATCH($A22,'P&L'!$C$8:$C$278,0)),0)/$A$1 -> 6018.94 | R22: =IFERROR(INDEX('P&L'!$Q$8:$Q$278,MATCH($A22,'P&L'!$C$8:$C$278,0)),0)/$A$1 -> 199137.28
A23: 16 | C23: =RIGHT(INDEX('P&L'!$E$5:$E$275,MATCH($A23,'P&L'!$C$5:$C$275,0)),LEN(INDEX('P&L'!$E$5:$E$275,MATCH($A23,'P&L'!$C$5:$C$275,0)))-6) -> G&A | D23: =SUMIFS('P&L'!X$8:X$276,'P&L'!$C$8:$C$276,$A23)/$A$1 -> 0 | E23: =SUMIFS('P&L'!Y$8:Y$276,'P&L'!$C$8:$C$276,$A23)/$A$1 -> 0 | F23: =SUMIFS('P&L'!Z$8:Z$276,'P&L'!$C$8:$C$276,$A23)/$A$1 -> 0 | G23: =SUMIFS('P&L'!AA$8:AA$276,'P&L'!$C$8:$C$276,$A23)/$A$1 -> 0 | H23: =SUMIFS('P&L'!AB$8:AB$276,'P&L'!$C$8:$C$276,$A23)/$A$1 -> 0 | I23: =SUMIFS('P&L'!AC$8:AC$276,'P&L'!$C$8:$C$276,$A23)/$A$1 -> 0 | J23: =SUMIFS('P&L'!AD$8:AD$276,'P&L'!$C$8:$C$276,$A23)/$A$1 -> 0 | K23: =SUMIFS('P&L'!AE$8:AE$276,'P&L'!$C$8:$C$276,$A23)/$A$1 -> 0 | ... O23: =SUMIFS('P&L'!AI$8:AI$276,'P&L'!$C$8:$C$276,$A23)/$A$1 -> 265069.35 | Q23: =IFERROR(INDEX('P&L'!$P$8:$P$278,MATCH($A23,'P&L'!$C$8:$C$278,0)),0)/$A$1 -> 265069.35 | R23: =IFERROR(INDEX('P&L'!$Q$8:$Q$278,MATCH($A23,'P&L'!$C$8:$C$278,0)),0)/$A$1 -> 254084.76
C24: =RIGHT(INDEX('P&L'!$E$5:$E$275,MATCH($A24,'P&L'!$C$5:$C$275,0)),LEN(INDEX('P&L'!$E$5:$E$275,MATCH($A24,'P&L'!$C$5:$C$275,0)))-6) -> #N/A | D24: =SUMIFS('P&L'!X$8:X$276,'P&L'!$C$8:$C$276,$A24)/$A$1 -> 0 | E24: =SUMIFS('P&L'!Y$8:Y$276,'P&L'!$C$8:$C$276,$A24)/$A$1 -> 0 | F24: =SUMIFS('P&L'!Z$8:Z$276,'P&L'!$C$8:$C$276,$A24)/$A$1 -> 0 | G24: =SUMIFS('P&L'!AA$8:AA$276,'P&L'!$C$8:$C$276,$A24)/$A$1 -> 0 | H24: =SUMIFS('P&L'!AB$8:AB$276,'P&L'!$C$8:$C$276,$A24)/$A$1 -> 0 | I24: =SUMIFS('P&L'!AC$8:AC$276,'P&L'!$C$8:$C$276,$A24)/$A$1 -> 0 | J24: =SUMIFS('P&L'!AD$8:AD$276,'P&L'!$C$8:$C$276,$A24)/$A$1 -> 0 | K24: =SUMIFS('P&L'!AE$8:AE$276,'P&L'!$C$8:$C$276,$A24)/$A$1 -> 0 | ... O24: =SUMIFS('P&L'!AI$8:AI$276,'P&L'!$C$8:$C$276,$A24)/$A$1 -> 0 | Q24: =IFERROR(INDEX('P&L'!$P$8:$P$278,MATCH($A24,'P&L'!$C$8:$C$278,0)),0)/$A$1 -> 0 | R24: =IFERROR(INDEX('P&L'!$Q$8:$Q$278,MATCH($A24,'P&L'!$C$8:$C$278,0)),0)/$A$1 -> 0
C25: Total Opex | D25: =SUM(D18:D24) -> 0 | E25: =SUM(E18:E24) -> 0 | F25: =SUM(F18:F24) -> 0 | G25: =SUM(G18:G24) -> 0 | H25: =SUM(H18:H24) -> 0 | I25: =SUM(I18:I24) -> 0 | J25: =SUM(J18:J24) -> 0 | K25: =SUM(K18:K24) -> 0 | ... O25: =SUM(O18:O24) -> 1932607.5 | Q25: =SUM(Q18:Q24) -> 1932607.5 | R25: =SUM(R18:R24) -> 2064205.6
C27: EBITDA | D27: =D15-D25 -> 0 | E27: =E15-E25 -> 0 | F27: =F15-F25 -> 0 | G27: =G15-G25 -> 0 | H27: =H15-H25 -> 0 | I27: =I15-I25 -> 0 | J27: =J15-J25 -> 0 | K27: =K15-K25 -> 0 | ... O27: =O15-O25 -> -1932607.5 | Q27: =Q15-Q25 -> -1932607.5 | R27: =R15-R25 -> -2064205.6
F28: =IF(ROUND(F25*$A$1,0)=ROUND(INDEX('P&L'!$X$249:$AI$249,MATCH(F5,'P&L'!$X$6:$AI$6,0)),0),"","Error") | H28: =IF(ROUND(H25*$A$1,0)=ROUND(INDEX('P&L'!$X$249:$AI$249,MATCH(H5,'P&L'!$X$6:$AI$6,0)),0),"","Error") | I28: =IF(ROUND(I25*$A$1,0)=ROUND(INDEX('P&L'!$X$249:$AI$249,MATCH(I5,'P&L'!$X$6:$AI$6,0)),0),"","Error") | J28: =IF(ROUND(J25*$A$1,0)=ROUND(INDEX('P&L'!$X$249:$AI$249,MATCH(J5,'P&L'!$X$6:$AI$6,0)),0),"","Error") | K28: =IF(ROUND(K25*$A$1,0)=ROUND(INDEX('P&L'!$X$249:$AI$249,MATCH(K5,'P&L'!$X$6:$AI$6,0)),0),"","Error") | L28: =IF(ROUND(L25*$A$1,0)=ROUND(INDEX('P&L'!$X$249:$AI$249,MATCH(L5,'P&L'!$X$6:$AI$6,0)),0),"","Error") | M28: =IF(ROUND(M25*$A$1,0)=ROUND(INDEX('P&L'!$X$249:$AI$249,MATCH(M5,'P&L'!$X$6:$AI$6,0)),0),"","Error") | N28: =IF(ROUND(N25*$A$1,0)=ROUND(INDEX('P&L'!$X$249:$AI$249,MATCH(N5,'P&L'!$X$6:$AI$6,0)),0),"","Error") | O28: =IF(ROUND(O25*$A$1,0)=ROUND(INDEX('P&L'!$X$249:$AI$249,MATCH(O5,'P&L'!$X$6:$AI$6,0)),0),"","Error") | R28: =IF(ROUND(R25*$A$1,0)=ROUND('P&L'!Q249,0),"","Error")
C29: Cash Flow Summary | D29: =D5 -> 44197 | E29: =E5 -> 44228 | F29: =F5 -> 44256 | G29: =G5 -> 44287 | H29: =H5 -> 44317 | I29: =I5 -> 44348 | J29: =J5 -> 44378 | K29: =K5 -> 44409 | ... O29: =O5 -> 44531 | Q29: =Q5 -> 2021 YTD
D30: =D6 -> Actual | E30: =E6 -> Actual | F30: =F6 -> Actual | G30: =G6 -> Actual | H30: =H6 -> Actual | I30: =I6 -> Actual | J30: =J6 -> Actual | K30: =K6 -> Actual | ... O30: =O6 -> Actual | Q30: =Q6 -> Actual | R30: =$R$6 -> Budget
C31: Cash at Beginning of Period | D31: =BS!N13+BS!N14 -> 0 | E31: =BS!O13+BS!O14 -> 0 | F31: =BS!P13+BS!P14 -> 1663501.8 | G31: =INDEX(CF!$Y$61:$AK$61,MATCH(G$29,CF!$Y$7:$AK$7,0))/$A$1 -> 0 | H31: =INDEX(CF!$Y$61:$AK$61,MATCH(H$29,CF!$Y$7:$AK$7,0))/$A$1 -> 0 | I31: =INDEX(CF!$Y$61:$AK$61,MATCH(I$29,CF!$Y$7:$AK$7,0))/$A$1 -> 1663501.8 | J31: =INDEX(CF!$Y$61:$AK$61,MATCH(J$29,CF!$Y$7:$AK$7,0))/$A$1 -> 0 | K31: =INDEX(CF!$Y$61:$AK$61,MATCH(K$29,CF!$Y$7:$AK$7,0))/$A$1 -> 0 | L31: =INDEX(CF!$Y$61:$AK$61,MATCH(L$29,CF!$Y$7:$AK$7,0))/$A$1 -> 1663501.8 | M31: =INDEX(CF!$Y$61:$AK$61,MATCH(M$29,CF!$Y$7:$AK$7,0))/$A$1 -> 0 | N31: =INDEX(CF!$Y$61:$AK$61,MATCH(N$29,CF!$Y$7:$AK$7,0))/$A$1 -> 0 | O31: =L37 -> 1663501.8 | Q31: =CF!S61/$A$1 -> 1663501.8 | R31: =CF!T61/$A$1 -> 1667734.9
C32: Net Operating Cash Flow | D32: =INDEX(CF!$Y$27:$AK$27,MATCH(D$29,CF!$Y$7:$AK$7,0))/$A$1 -> 0 | E32: =INDEX(CF!$Y$27:$AK$27,MATCH(E$29,CF!$Y$7:$AK$7,0))/$A$1 -> 0 | F32: =INDEX(CF!$Y$27:$AK$27,MATCH(F$29,CF!$Y$7:$AK$7,0))/$A$1 -> 0 | G32: =INDEX(CF!$Y$27:$AK$27,MATCH(G$29,CF!$Y$7:$AK$7,0))/$A$1 -> 0 | H32: =INDEX(CF!$Y$27:$AK$27,MATCH(H$29,CF!$Y$7:$AK$7,0))/$A$1 -> 0 | I32: =CF!AE27 -> 0 | J32: =INDEX(CF!$Y$27:$AK$27,MATCH(J$29,CF!$Y$7:$AK$7,0))/$A$1 -> 0 | K32: =INDEX(CF!$Y$27:$AK$27,MATCH(K$29,CF!$Y$7:$AK$7,0))/$A$1 -> 0 | L32: =CF!AH27 -> 0 | M32: =INDEX(CF!$Y$27:$AK$27,MATCH(M$29,CF!$Y$7:$AK$7,0))/$A$1 -> 0 | N32: =INDEX(CF!$Y$27:$AK$27,MATCH(N$29,CF!$Y$7:$AK$7,0))/$A$1 -> 0 | O32: =CF!AK27 -> -1560685.8 | Q32: =F32+I32+L32+O32 -> -1560685.8 | R32: =CF!T27/$A$1 -> -1896076.1
C33: Total Capital Expenditure | D33: =INDEX(CF!$Y$47:$AK$47,MATCH(D$29,CF!$Y$7:$AK$7,0))/$A$1 -> 0 | E33: =INDEX(CF!$Y$47:$AK$47,MATCH(E$29,CF!$Y$7:$AK$7,0))/$A$1 -> 0 | F33: =INDEX(CF!$Y$47:$AK$47,MATCH(F$29,CF!$Y$7:$AK$7,0))/$A$1 -> 0 | G33: =INDEX(CF!$Y$47:$AK$47,MATCH(G$29,CF!$Y$7:$AK$7,0))/$A$1 -> 0 | H33: =INDEX(CF!$Y$47:$AK$47,MATCH(H$29,CF!$Y$7:$AK$7,0))/$A$1 -> 0 | I33: =INDEX(CF!$Y$47:$AK$47,MATCH(I$29,CF!$Y$7:$AK$7,0))/$A$1 -> 0 | J33: =INDEX(CF!$Y$47:$AK$47,MATCH(J$29,CF!$Y$7:$AK$7,0))/$A$1 -> 0 | K33: =INDEX(CF!$Y$47:$AK$47,MATCH(K$29,CF!$Y$7:$AK$7,0))/$A$1 -> 0 | L33: =CF!AH47 -> 0 | M33: =INDEX(CF!$Y$47:$AK$47,MATCH(M$29,CF!$Y$7:$AK$7,0))/$A$1 -> 0 | N33: =INDEX(CF!$Y$47:$AK$47,MATCH(N$29,CF!$Y$7:$AK$7,0))/$A$1 -> 0 | O33: =CF!AK47 -> -106525.99 | Q33: =F33+I33+L33+O33 -> -106525.99 | R33: =CF!T47/$A$1 -> -74521.519
C34: Total Financing | D34: =INDEX(CF!$Y$57:$AK$57,MATCH(D$29,CF!$Y$7:$AK$7,0))/$A$1 -> 0 | E34: =INDEX(CF!$Y$57:$AK$57,MATCH(E$29,CF!$Y$7:$AK$7,0))/$A$1 -> 0 | F34: =INDEX(CF!$Y$57:$AK$57,MATCH(F$29,CF!$Y$7:$AK$7,0))/$A$1 -> 0 | G34: =INDEX(CF!$Y$57:$AK$57,MATCH(G$29,CF!$Y$7:$AK$7,0))/$A$1 -> 0 | H34: =INDEX(CF!$Y$57:$AK$57,MATCH(H$29,CF!$Y$7:$AK$7,0))/$A$1 -> 0 | I34: =INDEX(CF!$Y$57:$AK$57,MATCH(I$29,CF!$Y$7:$AK$7,0))/$A$1 -> 0 | J34: =INDEX(CF!$Y$57:$AK$57,MATCH(J$29,CF!$Y$7:$AK$7,0))/$A$1 -> 0 | K34: =INDEX(CF!$Y$57:$AK$57,MATCH(K$29,CF!$Y$7:$AK$7,0))/$A$1 -> 0 | L34: =CF!AH57 -> 0 | M34: =INDEX(CF!$Y$47:$AK$47,MATCH(M$29,CF!$Y$7:$AK$7,0))/$A$1 -> 0 | N34: =INDEX(CF!$Y$47:$AK$47,MATCH(N$29,CF!$Y$7:$AK$7,0))/$A$1 -> 0 | O34: =CF!AK57 -> 8627433.5 | Q34: =F34+I34+L34+O34 -> 8627433.5 | R34: =CF!T57/$A$1 -> 3933333.3
C35: Taxation Paid | D35: =INDEX(CF!$Y$49:$AK$49,MATCH(D$29,CF!$Y$7:$AK$7,0))/$A$1 -> 0 | E35: =INDEX(CF!$Y$49:$AK$49,MATCH(E$29,CF!$Y$7:$AK$7,0))/$A$1 -> 0 | F35: =INDEX(CF!$Y$49:$AK$49,MATCH(F$29,CF!$Y$7:$AK$7,0))/$A$1 -> 0 | H35: =INDEX(CF!$Y$49:$AK$49,MATCH(H$29,CF!$Y$7:$AK$7,0))/$A$1 -> 0 | I35: =INDEX(CF!$Y$49:$AK$49,MATCH(I$29,CF!$Y$7:$AK$7,0))/$A$1 -> 0 | J35: =INDEX(CF!$Y$49:$AK$49,MATCH(J$29,CF!$Y$7:$AK$7,0))/$A$1 -> 0 | K35: =INDEX(CF!$Y$49:$AK$49,MATCH(K$29,CF!$Y$7:$AK$7,0))/$A$1 -> 0 | L35: =CF!AH49 -> 0 | M35: =INDEX(CF!$Y$49:$AK$49,MATCH(M$29,CF!$Y$7:$AK$7,0))/$A$1 -> 0 | N35: =INDEX(CF!$Y$49:$AK$49,MATCH(N$29,CF!$Y$7:$AK$7,0))/$A$1 -> 0 | O35: =CF!AK49 -> 0 | Q35: =F35+I35+L35+O35 -> 0 | R35: =CF!T49/$A$1 -> 0
C36: Net Cash Inflow / (Outflow) | D36: =INDEX(CF!$Y$59:$AK$59,MATCH(D$29,CF!$Y$7:$AK$7,0))/$A$1 -> 0 | E36: =INDEX(CF!$Y$59:$AK$59,MATCH(E$29,CF!$Y$7:$AK$7,0))/$A$1 -> 0 | F36: =INDEX(CF!$Y$59:$AK$59,MATCH(F$29,CF!$Y$7:$AK$7,0))/$A$1 -> 0 | H36: =INDEX(CF!$Y$59:$AK$59,MATCH(H$29,CF!$Y$7:$AK$7,0))/$A$1 -> 0 | I36: =SUM(I32:I35) -> 0 | J36: =INDEX(CF!$Y$59:$AK$59,MATCH(J$29,CF!$Y$7:$AK$7,0))/$A$1 -> 0 | K36: =INDEX(CF!$Y$59:$AK$59,MATCH(K$29,CF!$Y$7:$AK$7,0))/$A$1 -> 0 | L36: =SUM(L32:L35) -> 0 | M36: =INDEX(CF!$Y$59:$AK$59,MATCH(M$29,CF!$Y$7:$AK$7,0))/$A$1 -> 0 | N36: =INDEX(CF!$Y$59:$AK$59,MATCH(N$29,CF!$Y$7:$AK$7,0))/$A$1 -> 0 | O36: =SUM(O32:O35) -> 6960221.7 | Q36: =SUM(Q32:Q35) -> 6960221.7 | R36: =CF!T59/$A$1 -> 1962735.8
C37: Cash End Of Period | F37: =INDEX(CF!$Y$63:$AK$63,MATCH(F$29,CF!$Y$7:$AK$7,0))/$A$1 -> 1663501.8 | G37: =INDEX(CF!$Y$63:$AK$63,MATCH(G$29,CF!$Y$7:$AK$7,0))/$A$1 -> 0 | H37: =INDEX(CF!$Y$63:$AK$63,MATCH(H$29,CF!$Y$7:$AK$7,0))/$A$1 -> 0 | I37: =I31+I36 -> 1663501.8 | J37: =INDEX(CF!$Y$63:$AK$63,MATCH(J$29,CF!$Y$7:$AK$7,0))/$A$1 -> 0 | K37: =INDEX(CF!$Y$63:$AK$63,MATCH(K$29,CF!$Y$7:$AK$7,0))/$A$1 -> 0 | L37: =L31+L36 -> 1663501.8 | M37: =INDEX(CF!$Y$63:$AK$63,MATCH(M$29,CF!$Y$7:$AK$7,0))/$A$1 -> 0 | N37: =INDEX(CF!$Y$63:$AK$63,MATCH(N$29,CF!$Y$7:$AK$7,0))/$A$1 -> 0 | O37: =O31+O36 -> 8623723.5 | Q37: =Q31+Q36 -> 8623723.5 | R37: =CF!T63/$A$1 -> 3630470.6
F38: =IF(ABS(ROUND(F37*$A$1,0)=ROUND(INDEX(CF!$Z$63:$AK$63,MATCH(F29,CF!$Z$7:$AK$7,0)),0)),"","Error") | G38: =IF(ABS(ROUND(G37*$A$1,0)=ROUND(INDEX(CF!$Z$63:$AK$63,MATCH(G29,CF!$Z$7:$AK$7,0)),0)),"","Error") | H38: =IF(ABS(ROUND(H37*$A$1,0)=ROUND(INDEX(CF!$Z$63:$AK$63,MATCH(H29,CF!$Z$7:$AK$7,0)),0)),"","Error") | I38: =IF(ABS(ROUND(I37*$A$1,0)=ROUND(INDEX(CF!$Z$63:$AK$63,MATCH(I29,CF!$Z$7:$AK$7,0)),0)),"","Error") | J38: =IF(ABS(ROUND(J37*$A$1,0)=ROUND(INDEX(CF!$Z$63:$AK$63,MATCH(J29,CF!$Z$7:$AK$7,0)),0)),"","Error") | K38: =IF(ABS(ROUND(K37*$A$1,0)=ROUND(INDEX(CF!$Z$63:$AK$63,MATCH(K29,CF!$Z$7:$AK$7,0)),0)),"","Error") | M38: =IF(ABS(ROUND(M37*$A$1,0)=ROUND(INDEX(CF!$Z$63:$AK$63,MATCH(M29,CF!$Z$7:$AK$7,0)),0)),"","Error") | N38: =IF(ABS(ROUND(N37*$A$1,0)=ROUND(INDEX(CF!$Z$63:$AK$63,MATCH(N29,CF!$Z$7:$AK$7,0)),0)),"","Error") | O38: =IF(ABS(ROUND(O37*$A$1,0)=ROUND(INDEX(CF!$Z$63:$AK$63,MATCH(O29,CF!$Z$7:$AK$7,0)),0)),"","Error") | R38: =IF(ROUND(R37*$A$1,0)=ROUND(CF!T63,0),"","Error")
C40: HC summary | D40: =D5 -> 44197 | E40: =E5 -> 44228 | F40: =F5 -> 44256 | G40: =G5 -> 44287 | H40: =H5 -> 44317 | I40: =I5 -> 44348 | J40: =J5 -> 44378 | K40: =K5 -> 44409 | ... O40: =O5 -> 44531 | Q40: =Q29 -> 2021 YTD
D41: =D6 -> Actual | E41: =E6 -> Actual | F41: =F6 -> Actual | G41: =G6 -> Actual | H41: =H6 -> Actual | I41: =I6 -> Actual | J41: =J6 -> Actual | K41: =K6 -> Actual | ... O41: =O6 -> Actual | Q41: =Q6 -> Actual | R41: =$R$6 -> Budget
A42: 22302 | C42: =C14 -> COS | F42: =SUMIFS(INDEX('P&L'!$V$8:$AI$278,,MATCH(F$40,'P&L'!$V$6:$AI$6,0)),'P&L'!$C$8:$C$278,$A42) -> 0 | G42: =SUMIFS(INDEX('P&L'!$V$8:$AI$278,,MATCH(G$40,'P&L'!$V$6:$AI$6,0)),'P&L'!$C$8:$C$278,$A42) -> 0 | H42: =SUMIFS(INDEX('P&L'!$V$8:$AI$278,,MATCH(H$40,'P&L'!$V$6:$AI$6,0)),'P&L'!$C$8:$C$278,$A42) -> 0 | I42: =SUMIFS(INDEX('P&L'!$V$8:$AI$278,,MATCH(I$40,'P&L'!$V$6:$AI$6,0)),'P&L'!$C$8:$C$278,$A42) -> 0 | J42: =SUMIFS(INDEX('P&L'!$V$8:$AI$278,,MATCH(J$40,'P&L'!$V$6:$AI$6,0)),'P&L'!$C$8:$C$278,$A42) -> 0 | K42: =SUMIFS(INDEX('P&L'!$V$8:$AI$278,,MATCH(K$40,'P&L'!$V$6:$AI$6,0)),'P&L'!$C$8:$C$278,$A42) -> 0 | L42: =SUMIFS(INDEX('P&L'!$V$8:$AI$278,,MATCH(L$40,'P&L'!$V$6:$AI$6,0)),'P&L'!$C$8:$C$278,$A42) -> 0 | M42: =SUMIFS(INDEX('P&L'!$V$8:$AI$278,,MATCH(M$40,'P&L'!$V$6:$AI$6,0)),'P&L'!$C$8:$C$278,$A42) -> 0 | ... O42: =SUMIFS(INDEX('P&L'!$V$8:$AI$278,,MATCH(O$40,'P&L'!$V$6:$AI$6,0)),'P&L'!$C$8:$C$278,$A42) -> 0 | Q42: =IFERROR(INDEX('P&L'!$P$8:$P$278,MATCH($A42,'P&L'!$C$8:$C$278,0)),0) -> 0 | R42: =IFERROR(INDEX('P&L'!$Q$8:$Q$278,MATCH($A42,'P&L'!$C$8:$C$278,0)),0) -> 0
A43: 23203 | C43: =C18 -> R&D | F43: =SUMIFS(INDEX('P&L'!$V$8:$AI$278,,MATCH(F$40,'P&L'!$V$6:$AI$6,0)),'P&L'!$C$8:$C$278,$A43) -> 0 | G43: =SUMIFS(INDEX('P&L'!$V$8:$AI$278,,MATCH(G$40,'P&L'!$V$6:$AI$6,0)),'P&L'!$C$8:$C$278,$A43) -> 0 | H43: =SUMIFS(INDEX('P&L'!$V$8:$AI$278,,MATCH(H$40,'P&L'!$V$6:$AI$6,0)),'P&L'!$C$8:$C$278,$A43) -> 0 | I43: =SUMIFS(INDEX('P&L'!$V$8:$AI$278,,MATCH(I$40,'P&L'!$V$6:$AI$6,0)),'P&L'!$C$8:$C$278,$A43) -> 0 | J43: =SUMIFS(INDEX('P&L'!$V$8:$AI$278,,MATCH(J$40,'P&L'!$V$6:$AI$6,0)),'P&L'!$C$8:$C$278,$A43) -> 0 | K43: =SUMIFS(INDEX('P&L'!$V$8:$AI$278,,MATCH(K$40,'P&L'!$V$6:$AI$6,0)),'P&L'!$C$8:$C$278,$A43) -> 0 | L43: =SUMIFS(INDEX('P&L'!$V$8:$AI$278,,MATCH(L$40,'P&L'!$V$6:$AI$6,0)),'P&L'!$C$8:$C$278,$A43) -> 0 | M43: =SUMIFS(INDEX('P&L'!$V$8:$AI$278,,MATCH(M$40,'P&L'!$V$6:$AI$6,0)),'P&L'!$C$8:$C$278,$A43) -> 0 | ... O43: =SUMIFS(INDEX('P&L'!$V$8:$AI$278,,MATCH(O$40,'P&L'!$V$6:$AI$6,0)),'P&L'!$C$8:$C$278,$A43) -> 8 | Q43: =IFERROR(INDEX('P&L'!$P$8:$P$278,MATCH($A43,'P&L'!$C$8:$C$278,0)),0) -> 8 | R43: =IFERROR(INDEX('P&L'!$Q$8:$Q$278,MATCH($A43,'P&L'!$C$8:$C$278,0)),0) -> 9
A44: 23208 | C44: =C19 -> Product | F44: =SUMIFS(INDEX('P&L'!$V$8:$AI$278,,MATCH(F$40,'P&L'!$V$6:$AI$6,0)),'P&L'!$C$8:$C$278,$A44) -> 0 | G44: =SUMIFS(INDEX('P&L'!$V$8:$AI$278,,MATCH(G$40,'P&L'!$V$6:$AI$6,0)),'P&L'!$C$8:$C$278,$A44) -> 0 | H44: =SUMIFS(INDEX('P&L'!$V$8:$AI$278,,MATCH(H$40,'P&L'!$V$6:$AI$6,0)),'P&L'!$C$8:$C$278,$A44) -> 0 | I44: =SUMIFS(INDEX('P&L'!$V$8:$AI$278,,MATCH(I$40,'P&L'!$V$6:$AI$6,0)),'P&L'!$C$8:$C$278,$A44) -> 0 | J44: =SUMIFS(INDEX('P&L'!$V$8:$AI$278,,MATCH(J$40,'P&L'!$V$6:$AI$6,0)),'P&L'!$C$8:$C$278,$A44) -> 0 | K44: =SUMIFS(INDEX('P&L'!$V$8:$AI$278,,MATCH(K$40,'P&L'!$V$6:$AI$6,0)),'P&L'!$C$8:$C$278,$A44) -> 0 | L44: =SUMIFS(INDEX('P&L'!$V$8:$AI$278,,MATCH(L$40,'P&L'!$V$6:$AI$6,0)),'P&L'!$C$8:$C$278,$A44) -> 0 | M44: =SUMIFS(INDEX('P&L'!$V$8:$AI$278,,MATCH(M$40,'P&L'!$V$6:$AI$6,0)),'P&L'!$C$8:$C$278,$A44) -> 0 | ... O44: =SUMIFS(INDEX('P&L'!$V$8:$AI$278,,MATCH(O$40,'P&L'!$V$6:$AI$6,0)),'P&L'!$C$8:$C$278,$A44) -> 2 | Q44: =IFERROR(INDEX('P&L'!$P$8:$P$278,MATCH($A44,'P&L'!$C$8:$C$278,0)),0) -> 2 | R44: =IFERROR(INDEX('P&L'!$Q$8:$Q$278,MATCH($A44,'P&L'!$C$8:$C$278,0)),0) -> 3
A45: 23217 | C45: =C20 -> Art | F45: =SUMIFS(INDEX('P&L'!$V$8:$AI$278,,MATCH(F$40,'P&L'!$V$6:$AI$6,0)),'P&L'!$C$8:$C$278,$A45) -> 0 | G45: =SUMIFS(INDEX('P&L'!$V$8:$AI$278,,MATCH(G$40,'P&L'!$V$6:$AI$6,0)),'P&L'!$C$8:$C$278,$A45) -> 0 | H45: =SUMIFS(INDEX('P&L'!$V$8:$AI$278,,MATCH(H$40,'P&L'!$V$6:$AI$6,0)),'P&L'!$C$8:$C$278,$A45) -> 0 | I45: =SUMIFS(INDEX('P&L'!$V$8:$AI$278,,MATCH(I$40,'P&L'!$V$6:$AI$6,0)),'P&L'!$C$8:$C$278,$A45) -> 0 | J45: =SUMIFS(INDEX('P&L'!$V$8:$AI$278,,MATCH(J$40,'P&L'!$V$6:$AI$6,0)),'P&L'!$C$8:$C$278,$A45) -> 0 | K45: =SUMIFS(INDEX('P&L'!$V$8:$AI$278,,MATCH(K$40,'P&L'!$V$6:$AI$6,0)),'P&L'!$C$8:$C$278,$A45) -> 0 | L45: =SUMIFS(INDEX('P&L'!$V$8:$AI$278,,MATCH(L$40,'P&L'!$V$6:$AI$6,0)),'P&L'!$C$8:$C$278,$A45) -> 0 | M45: =SUMIFS(INDEX('P&L'!$V$8:$AI$278,,MATCH(M$40,'P&L'!$V$6:$AI$6,0)),'P&L'!$C$8:$C$278,$A45) -> 0 | ... O45: =SUMIFS(INDEX('P&L'!$V$8:$AI$278,,MATCH(O$40,'P&L'!$V$6:$AI$6,0)),'P&L'!$C$8:$C$278,$A45) -> 6 | Q45: =IFERROR(INDEX('P&L'!$P$8:$P$278,MATCH($A45,'P&L'!$C$8:$C$278,0)),0) -> 6 | R45: =IFERROR(INDEX('P&L'!$Q$8:$Q$278,MATCH($A45,'P&L'!$C$8:$C$278,0)),0) -> 6
A46: 24206 | C46: =C21 -> Sales Costs | F46: =SUMIFS(INDEX('P&L'!$V$8:$AI$278,,MATCH(F$40,'P&L'!$V$6:$AI$6,0)),'P&L'!$C$8:$C$278,$A46) -> 0 | G46: =SUMIFS(INDEX('P&L'!$V$8:$AI$278,,MATCH(G$40,'P&L'!$V$6:$AI$6,0)),'P&L'!$C$8:$C$278,$A46) -> 0 | H46: =SUMIFS(INDEX('P&L'!$V$8:$AI$278,,MATCH(H$40,'P&L'!$V$6:$AI$6,0)),'P&L'!$C$8:$C$278,$A46) -> 0 | I46: =SUMIFS(INDEX('P&L'!$V$8:$AI$278,,MATCH(I$40,'P&L'!$V$6:$AI$6,0)),'P&L'!$C$8:$C$278,$A46) -> 0 | J46: =SUMIFS(INDEX('P&L'!$V$8:$AI$278,,MATCH(J$40,'P&L'!$V$6:$AI$6,0)),'P&L'!$C$8:$C$278,$A46) -> 0 | K46: =SUMIFS(INDEX('P&L'!$V$8:$AI$278,,MATCH(K$40,'P&L'!$V$6:$AI$6,0)),'P&L'!$C$8:$C$278,$A46) -> 0 | L46: =SUMIFS(INDEX('P&L'!$V$8:$AI$278,,MATCH(L$40,'P&L'!$V$6:$AI$6,0)),'P&L'!$C$8:$C$278,$A46) -> 0 | M46: =SUMIFS(INDEX('P&L'!$V$8:$AI$278,,MATCH(M$40,'P&L'!$V$6:$AI$6,0)),'P&L'!$C$8:$C$278,$A46) -> 0 | ... O46: =SUMIFS(INDEX('P&L'!$V$8:$AI$278,,MATCH(O$40,'P&L'!$V$6:$AI$6,0)),'P&L'!$C$8:$C$278,$A46) -> 0 | Q46: =IFERROR(INDEX('P&L'!$P$8:$P$278,MATCH($A46,'P&L'!$C$8:$C$278,0)),0) -> 0 | R46: =IFERROR(INDEX('P&L'!$Q$8:$Q$278,MATCH($A46,'P&L'!$C$8:$C$278,0)),0) -> 0
A47: 24207 | C47: =C22 -> Marketing Costs | F47: =SUMIFS(INDEX('P&L'!$V$8:$AI$278,,MATCH(F$40,'P&L'!$V$6:$AI$6,0)),'P&L'!$C$8:$C$278,$A47) -> 0 | G47: =SUMIFS(INDEX('P&L'!$V$8:$AI$278,,MATCH(G$40,'P&L'!$V$6:$AI$6,0)),'P&L'!$C$8:$C$278,$A47) -> 0 | H47: =SUMIFS(INDEX('P&L'!$V$8:$AI$278,,MATCH(H$40,'P&L'!$V$6:$AI$6,0)),'P&L'!$C$8:$C$278,$A47) -> 0 | I47: =SUMIFS(INDEX('P&L'!$V$8:$AI$278,,MATCH(I$40,'P&L'!$V$6:$AI$6,0)),'P&L'!$C$8:$C$278,$A47) -> 0 | J47: =SUMIFS(INDEX('P&L'!$V$8:$AI$278,,MATCH(J$40,'P&L'!$V$6:$AI$6,0)),'P&L'!$C$8:$C$278,$A47) -> 0 | K47: =SUMIFS(INDEX('P&L'!$V$8:$AI$278,,MATCH(K$40,'P&L'!$V$6:$AI$6,0)),'P&L'!$C$8:$C$278,$A47) -> 0 | L47: =SUMIFS(INDEX('P&L'!$V$8:$AI$278,,MATCH(L$40,'P&L'!$V$6:$AI$6,0)),'P&L'!$C$8:$C$278,$A47) -> 0 | M47: =SUMIFS(INDEX('P&L'!$V$8:$AI$278,,MATCH(M$40,'P&L'!$V$6:$AI$6,0)),'P&L'!$C$8:$C$278,$A47) -> 0 | ... O47: =SUMIFS(INDEX('P&L'!$V$8:$AI$278,,MATCH(O$40,'P&L'!$V$6:$AI$6,0)),'P&L'!$C$8:$C$278,$A47) -> 0 | Q47: =IFERROR(INDEX('P&L'!$P$8:$P$278,MATCH($A47,'P&L'!$C$8:$C$278,0)),0) -> 0 | R47: =IFERROR(INDEX('P&L'!$Q$8:$Q$278,MATCH($A47,'P&L'!$C$8:$C$278,0)),0) -> 1
A48: 25205 | C48: =C23 -> G&A | F48: =SUMIFS(INDEX('P&L'!$V$8:$AI$278,,MATCH(F$40,'P&L'!$V$6:$AI$6,0)),'P&L'!$C$8:$C$278,$A48) -> 0 | G48: =SUMIFS(INDEX('P&L'!$V$8:$AI$278,,MATCH(G$40,'P&L'!$V$6:$AI$6,0)),'P&L'!$C$8:$C$278,$A48) -> 0 | H48: =SUMIFS(INDEX('P&L'!$V$8:$AI$278,,MATCH(H$40,'P&L'!$V$6:$AI$6,0)),'P&L'!$C$8:$C$278,$A48) -> 0 | I48: =SUMIFS(INDEX('P&L'!$V$8:$AI$278,,MATCH(I$40,'P&L'!$V$6:$AI$6,0)),'P&L'!$C$8:$C$278,$A48) -> 0 | J48: =SUMIFS(INDEX('P&L'!$V$8:$AI$278,,MATCH(J$40,'P&L'!$V$6:$AI$6,0)),'P&L'!$C$8:$C$278,$A48) -> 0 | K48: =SUMIFS(INDEX('P&L'!$V$8:$AI$278,,MATCH(K$40,'P&L'!$V$6:$AI$6,0)),'P&L'!$C$8:$C$278,$A48) -> 0 | L48: =SUMIFS(INDEX('P&L'!$V$8:$AI$278,,MATCH(L$40,'P&L'!$V$6:$AI$6,0)),'P&L'!$C$8:$C$278,$A48) -> 0 | M48: =SUMIFS(INDEX('P&L'!$V$8:$AI$278,,MATCH(M$40,'P&L'!$V$6:$AI$6,0)),'P&L'!$C$8:$C$278,$A48) -> 0 | ... O48: =SUMIFS(INDEX('P&L'!$V$8:$AI$278,,MATCH(O$40,'P&L'!$V$6:$AI$6,0)),'P&L'!$C$8:$C$278,$A48) -> 1 | Q48: =IFERROR(INDEX('P&L'!$P$8:$P$278,MATCH($A48,'P&L'!$C$8:$C$278,0)),0) -> 1 | R48: =IFERROR(INDEX('P&L'!$Q$8:$Q$278,MATCH($A48,'P&L'!$C$8:$C$278,0)),0) -> 1
C49: =C24 -> #N/A | F49: =SUMIFS(INDEX('P&L'!$V$8:$AI$278,,MATCH(F$40,'P&L'!$V$6:$AI$6,0)),'P&L'!$C$8:$C$278,$A49) -> 0 | G49: =SUMIFS(INDEX('P&L'!$V$8:$AI$278,,MATCH(G$40,'P&L'!$V$6:$AI$6,0)),'P&L'!$C$8:$C$278,$A49) -> 0 | H49: =SUMIFS(INDEX('P&L'!$V$8:$AI$278,,MATCH(H$40,'P&L'!$V$6:$AI$6,0)),'P&L'!$C$8:$C$278,$A49) -> 0 | I49: =SUMIFS(INDEX('P&L'!$V$8:$AI$278,,MATCH(I$40,'P&L'!$V$6:$AI$6,0)),'P&L'!$C$8:$C$278,$A49) -> 0 | J49: =SUMIFS(INDEX('P&L'!$V$8:$AI$278,,MATCH(J$40,'P&L'!$V$6:$AI$6,0)),'P&L'!$C$8:$C$278,$A49) -> 0 | K49: =SUMIFS(INDEX('P&L'!$V$8:$AI$278,,MATCH(K$40,'P&L'!$V$6:$AI$6,0)),'P&L'!$C$8:$C$278,$A49) -> 0 | L49: =SUMIFS(INDEX('P&L'!$V$8:$AI$278,,MATCH(L$40,'P&L'!$V$6:$AI$6,0)),'P&L'!$C$8:$C$278,$A49) -> 0 | M49: =SUMIFS(INDEX('P&L'!$V$8:$AI$278,,MATCH(M$40,'P&L'!$V$6:$AI$6,0)),'P&L'!$C$8:$C$278,$A49) -> 0 | ... O49: =SUMIFS(INDEX('P&L'!$V$8:$AI$278,,MATCH(O$40,'P&L'!$V$6:$AI$6,0)),'P&L'!$C$8:$C$278,$A49) -> 0 | Q49: =IFERROR(INDEX('P&L'!$P$8:$P$278,MATCH($A49,'P&L'!$C$8:$C$278,0)),0) -> 0 | R49: =IFERROR(INDEX('P&L'!$Q$8:$Q$278,MATCH($A49,'P&L'!$C$8:$C$278,0)),0) -> 0
C50: Total HC | F50: =SUM(F42:F49) -> 0 | G50: =SUM(G42:G49) -> 0 | H50: =SUM(H42:H49) -> 0 | I50: =SUM(I42:I49) -> 0 | J50: =SUM(J42:J49) -> 0 | K50: =SUM(K42:K49) -> 0 | L50: =SUM(L42:L49) -> 0 | M50: =SUM(M42:M49) -> 0 | ... O50: =SUM(O42:O49) -> 17 | Q50: =SUM(Q42:Q49) -> 17 | R50: =SUM(R42:R49) -> 20
F51: =IF(ROUND(F50,0)=ROUND(INDEX('P&L'!$X$277:$AI$277,MATCH(F29,'P&L'!$X$6:$AI$6,0)),0),"","Error") | G51: =IF(ROUND(G50,0)=ROUND(INDEX('P&L'!$X$277:$AI$277,MATCH(G29,'P&L'!$X$6:$AI$6,0)),0),"","Error") | H51: =IF(ROUND(H50,0)=ROUND(INDEX('P&L'!$X$277:$AI$277,MATCH(H29,'P&L'!$X$6:$AI$6,0)),0),"","Error") | I51: =IF(ROUND(I50,0)=ROUND(INDEX('P&L'!$X$277:$AI$277,MATCH(I29,'P&L'!$X$6:$AI$6,0)),0),"","Error") | J51: =IF(ROUND(J50,0)=ROUND(INDEX('P&L'!$X$277:$AI$277,MATCH(J29,'P&L'!$X$6:$AI$6,0)),0),"","Error") | K51: =IF(ROUND(K50,0)=ROUND(INDEX('P&L'!$X$277:$AI$277,MATCH(K29,'P&L'!$X$6:$AI$6,0)),0),"","Error") | L51: =IF(ROUND(L50,0)=ROUND(INDEX('P&L'!$X$277:$AI$277,MATCH(L29,'P&L'!$X$6:$AI$6,0)),0),"","Error") | M51: =IF(ROUND(M50,0)=ROUND(INDEX('P&L'!$X$277:$AI$277,MATCH(M29,'P&L'!$X$6:$AI$6,0)),0),"","Error") | ... O51: =IF(ROUND(O50,0)=ROUND(INDEX('P&L'!$X$277:$AI$277,MATCH(O29,'P&L'!$X$6:$AI$6,0)),0),"","Error") | Q51: =IF(ROUND(Q50,0)=ROUND('P&L'!P277,0),"","Error") | R51: =IF(ROUND(R50,0)=ROUND('P&L'!Q277,0),"","Error")
C53: Opex breakdown | D53: =D5 -> 44197 | E53: =E5 -> 44228 | F53: =F5 -> 44256 | G53: =G5 -> 44287 | H53: =H5 -> 44317 | I53: =I5 -> 44348 | J53: =J5 -> 44378 | K53: =K5 -> 44409 | ... O53: =O5 -> 44531 | Q53: =Q40 -> 2021 YTD
D54: =D6 -> Actual | E54: =E6 -> Actual | F54: =F6 -> Actual | G54: =G6 -> Actual | H54: =H6 -> Actual | I54: =I6 -> Actual | J54: =J6 -> Actual | K54: =K6 -> Actual | ... O54: =O6 -> Actual | Q54: =Q6 -> Actual | R54: =$R$6 -> Budget
C55: =IF(ISBLANK('Benchmark Index'!S7),"--",'Benchmark Index'!S7) -> Payroll | F55: =SUMIFS(INDEX('P&L'!$V$8:$AI$278,,MATCH(F$53,'P&L'!$V$6:$AI$6,0)),'P&L'!$D$8:$D$278,$C55)/$A$1 -> 0 | H55: =SUMIFS(INDEX('P&L'!$V$8:$AI$278,,MATCH(H$53,'P&L'!$V$6:$AI$6,0)),'P&L'!$D$8:$D$278,$C55)/$A$1 -> 0 | I55: =SUMIFS(INDEX('P&L'!$V$8:$AI$278,,MATCH(I$53,'P&L'!$V$6:$AI$6,0)),'P&L'!$D$8:$D$278,$C55)/$A$1 -> 0 | J55: =SUMIFS(INDEX('P&L'!$V$8:$AI$278,,MATCH(J$53,'P&L'!$V$6:$AI$6,0)),'P&L'!$D$8:$D$278,$C55)/$A$1 -> 0 | K55: =SUMIFS(INDEX('P&L'!$V$8:$AI$278,,MATCH(K$53,'P&L'!$V$6:$AI$6,0)),'P&L'!$D$8:$D$278,$C55)/$A$1 -> 0 | L55: =SUMIFS(INDEX('P&L'!$V$8:$AI$278,,MATCH(L$53,'P&L'!$V$6:$AI$6,0)),'P&L'!$D$8:$D$278,$C55)/$A$1 -> 0 | M55: =SUMIFS(INDEX('P&L'!$V$8:$AI$278,,MATCH(M$53,'P&L'!$V$6:$AI$6,0)),'P&L'!$D$8:$D$278,$C55)/$A$1 -> 0 | N55: =SUMIFS(INDEX('P&L'!$V$8:$AI$278,,MATCH(N$53,'P&L'!$V$6:$AI$6,0)),'P&L'!$D$8:$D$278,$C55)/$A$1 -> 0 | O55: =SUMIFS(INDEX('P&L'!$V$8:$AI$278,,MATCH(O$53,'P&L'!$V$6:$AI$6,0)),'P&L'!$D$8:$D$278,$C55)/$A$1 -> 1572528.5 | Q55: =F55+I55+L55+O55 -> 1572528.5 | R55: =SUMIFS('P&L'!Q$8:Q$278,'P&L'!$D$8:$D$278,$C55)/$A$1 -> 1582402.7
C56: =IF(ISBLANK('Benchmark Index'!S8),"--",'Benchmark Index'!S8) -> Recruitment | F56: =SUMIFS(INDEX('P&L'!$V$8:$AI$278,,MATCH(F$53,'P&L'!$V$6:$AI$6,0)),'P&L'!$D$8:$D$278,$C56)/$A$1 -> 0 | H56: =SUMIFS(INDEX('P&L'!$V$8:$AI$278,,MATCH(H$53,'P&L'!$V$6:$AI$6,0)),'P&L'!$D$8:$D$278,$C56)/$A$1 -> 0 | I56: =SUMIFS(INDEX('P&L'!$V$8:$AI$278,,MATCH(I$53,'P&L'!$V$6:$AI$6,0)),'P&L'!$D$8:$D$278,$C56)/$A$1 -> 0 | J56: =SUMIFS(INDEX('P&L'!$V$8:$AI$278,,MATCH(J$53,'P&L'!$V$6:$AI$6,0)),'P&L'!$D$8:$D$278,$C56)/$A$1 -> 0 | K56: =SUMIFS(INDEX('P&L'!$V$8:$AI$278,,MATCH(K$53,'P&L'!$V$6:$AI$6,0)),'P&L'!$D$8:$D$278,$C56)/$A$1 -> 0 | L56: =SUMIFS(INDEX('P&L'!$V$8:$AI$278,,MATCH(L$53,'P&L'!$V$6:$AI$6,0)),'P&L'!$D$8:$D$278,$C56)/$A$1 -> 0 | M56: =SUMIFS(INDEX('P&L'!$V$8:$AI$278,,MATCH(M$53,'P&L'!$V$6:$AI$6,0)),'P&L'!$D$8:$D$278,$C56)/$A$1 -> 0 | N56: =SUMIFS(INDEX('P&L'!$V$8:$AI$278,,MATCH(N$53,'P&L'!$V$6:$AI$6,0)),'P&L'!$D$8:$D$278,$C56)/$A$1 -> 0 | O56: =SUMIFS(INDEX('P&L'!$V$8:$AI$278,,MATCH(O$53,'P&L'!$V$6:$AI$6,0)),'P&L'!$D$8:$D$278,$C56)/$A$1 -> 1089.9 | Q56: =F56+I56+L56+O56 -> 1089.9 | R56: =SUMIFS('P&L'!Q$8:Q$278,'P&L'!$D$8:$D$278,$C56)/$A$1 -> 0
C57: =IF(ISBLANK('Benchmark Index'!S9),"--",'Benchmark Index'!S9) -> Travel | F57: =SUMIFS(INDEX('P&L'!$V$8:$AI$278,,MATCH(F$53,'P&L'!$V$6:$AI$6,0)),'P&L'!$D$8:$D$278,$C57)/$A$1 -> 0 | H57: =SUMIFS(INDEX('P&L'!$V$8:$AI$278,,MATCH(H$53,'P&L'!$V$6:$AI$6,0)),'P&L'!$D$8:$D$278,$C57)/$A$1 -> 0 | I57: =SUMIFS(INDEX('P&L'!$V$8:$AI$278,,MATCH(I$53,'P&L'!$V$6:$AI$6,0)),'P&L'!$D$8:$D$278,$C57)/$A$1 -> 0 | J57: =SUMIFS(INDEX('P&L'!$V$8:$AI$278,,MATCH(J$53,'P&L'!$V$6:$AI$6,0)),'P&L'!$D$8:$D$278,$C57)/$A$1 -> 0 | K57: =SUMIFS(INDEX('P&L'!$V$8:$AI$278,,MATCH(K$53,'P&L'!$V$6:$AI$6,0)),'P&L'!$D$8:$D$278,$C57)/$A$1 -> 0 | L57: =SUMIFS(INDEX('P&L'!$V$8:$AI$278,,MATCH(L$53,'P&L'!$V$6:$AI$6,0)),'P&L'!$D$8:$D$278,$C57)/$A$1 -> 0 | M57: =SUMIFS(INDEX('P&L'!$V$8:$AI$278,,MATCH(M$53,'P&L'!$V$6:$AI$6,0)),'P&L'!$D$8:$D$278,$C57)/$A$1 -> 0 | N57: =SUMIFS(INDEX('P&L'!$V$8:$AI$278,,MATCH(N$53,'P&L'!$V$6:$AI$6,0)),'P&L'!$D$8:$D$278,$C57)/$A$1 -> 0 | O57: =SUMIFS(INDEX('P&L'!$V$8:$AI$278,,MATCH(O$53,'P&L'!$V$6:$AI$6,0)),'P&L'!$D$8:$D$278,$C57)/$A$1 -> 0 | Q57: =F57+I57+L57+O57 -> 0 | R57: =SUMIFS('P&L'!Q$8:Q$278,'P&L'!$D$8:$D$278,$C57)/$A$1 -> 0
C58: =IF(ISBLANK('Benchmark Index'!S10),"--",'Benchmark Index'!S10) -> COS | F58: =SUMIFS(INDEX('P&L'!$V$8:$AI$278,,MATCH(F$53,'P&L'!$V$6:$AI$6,0)),'P&L'!$D$8:$D$278,$C58)/$A$1 -> 0 | H58: =SUMIFS(INDEX('P&L'!$V$8:$AI$278,,MATCH(H$53,'P&L'!$V$6:$AI$6,0)),'P&L'!$D$8:$D$278,$C58)/$A$1 -> 0 | I58: =SUMIFS(INDEX('P&L'!$V$8:$AI$278,,MATCH(I$53,'P&L'!$V$6:$AI$6,0)),'P&L'!$D$8:$D$278,$C58)/$A$1 -> 0 | J58: =SUMIFS(INDEX('P&L'!$V$8:$AI$278,,MATCH(J$53,'P&L'!$V$6:$AI$6,0)),'P&L'!$D$8:$D$278,$C58)/$A$1 -> 0 | K58: =SUMIFS(INDEX('P&L'!$V$8:$AI$278,,MATCH(K$53,'P&L'!$V$6:$AI$6,0)),'P&L'!$D$8:$D$278,$C58)/$A$1 -> 0 | L58: =SUMIFS(INDEX('P&L'!$V$8:$AI$278,,MATCH(L$53,'P&L'!$V$6:$AI$6,0)),'P&L'!$D$8:$D$278,$C58)/$A$1 -> 0 | M58: =SUMIFS(INDEX('P&L'!$V$8:$AI$278,,MATCH(M$53,'P&L'!$V$6:$AI$6,0)),'P&L'!$D$8:$D$278,$C58)/$A$1 -> 0 | N58: =SUMIFS(INDEX('P&L'!$V$8:$AI$278,,MATCH(N$53,'P&L'!$V$6:$AI$6,0)),'P&L'!$D$8:$D$278,$C58)/$A$1 -> 0 | O58: =SUMIFS(INDEX('P&L'!$V$8:$AI$278,,MATCH(O$53,'P&L'!$V$6:$AI$6,0)),'P&L'!$D$8:$D$278,$C58)/$A$1 -> 0 | Q58: =F58+I58+L58+O58 -> 0 | R58: =SUMIFS('P&L'!Q$8:Q$278,'P&L'!$D$8:$D$278,$C58)/$A$1 -> 0
C59: =IF(ISBLANK('Benchmark Index'!S11),"--",'Benchmark Index'!S11) -> Office admin | F59: =SUMIFS(INDEX('P&L'!$V$8:$AI$278,,MATCH(F$53,'P&L'!$V$6:$AI$6,0)),'P&L'!$D$8:$D$278,$C59)/$A$1 -> 0 | H59: =SUMIFS(INDEX('P&L'!$V$8:$AI$278,,MATCH(H$53,'P&L'!$V$6:$AI$6,0)),'P&L'!$D$8:$D$278,$C59)/$A$1 -> 0 | I59: =SUMIFS(INDEX('P&L'!$V$8:$AI$278,,MATCH(I$53,'P&L'!$V$6:$AI$6,0)),'P&L'!$D$8:$D$278,$C59)/$A$1 -> 0 | J59: =SUMIFS(INDEX('P&L'!$V$8:$AI$278,,MATCH(J$53,'P&L'!$V$6:$AI$6,0)),'P&L'!$D$8:$D$278,$C59)/$A$1 -> 0 | K59: =SUMIFS(INDEX('P&L'!$V$8:$AI$278,,MATCH(K$53,'P&L'!$V$6:$AI$6,0)),'P&L'!$D$8:$D$278,$C59)/$A$1 -> 0 | L59: =SUMIFS(INDEX('P&L'!$V$8:$AI$278,,MATCH(L$53,'P&L'!$V$6:$AI$6,0)),'P&L'!$D$8:$D$278,$C59)/$A$1 -> 0 | M59: =SUMIFS(INDEX('P&L'!$V$8:$AI$278,,MATCH(M$53,'P&L'!$V$6:$AI$6,0)),'P&L'!$D$8:$D$278,$C59)/$A$1 -> 0 | N59: =SUMIFS(INDEX('P&L'!$V$8:$AI$278,,MATCH(N$53,'P&L'!$V$6:$AI$6,0)),'P&L'!$D$8:$D$278,$C59)/$A$1 -> 0 | O59: =SUMIFS(INDEX('P&L'!$V$8:$AI$278,,MATCH(O$53,'P&L'!$V$6:$AI$6,0)),'P&L'!$D$8:$D$278,$C59)/$A$1 -> 0 | Q59: =F59+I59+L59+O59 -> 0 | R59: =SUMIFS('P&L'!Q$8:Q$278,'P&L'!$D$8:$D$278,$C59)/$A$1 -> 0
C60: =IF(ISBLANK('Benchmark Index'!S12),"--",'Benchmark Index'!S12) -> Consultant | F60: =SUMIFS(INDEX('P&L'!$V$8:$AI$278,,MATCH(F$53,'P&L'!$V$6:$AI$6,0)),'P&L'!$D$8:$D$278,$C60)/$A$1 -> 0 | H60: =SUMIFS(INDEX('P&L'!$V$8:$AI$278,,MATCH(H$53,'P&L'!$V$6:$AI$6,0)),'P&L'!$D$8:$D$278,$C60)/$A$1 -> 0 | I60: =SUMIFS(INDEX('P&L'!$V$8:$AI$278,,MATCH(I$53,'P&L'!$V$6:$AI$6,0)),'P&L'!$D$8:$D$278,$C60)/$A$1 -> 0 | J60: =SUMIFS(INDEX('P&L'!$V$8:$AI$278,,MATCH(J$53,'P&L'!$V$6:$AI$6,0)),'P&L'!$D$8:$D$278,$C60)/$A$1 -> 0 | K60: =SUMIFS(INDEX('P&L'!$V$8:$AI$278,,MATCH(K$53,'P&L'!$V$6:$AI$6,0)),'P&L'!$D$8:$D$278,$C60)/$A$1 -> 0 | L60: =SUMIFS(INDEX('P&L'!$V$8:$AI$278,,MATCH(L$53,'P&L'!$V$6:$AI$6,0)),'P&L'!$D$8:$D$278,$C60)/$A$1 -> 0 | M60: =SUMIFS(INDEX('P&L'!$V$8:$AI$278,,MATCH(M$53,'P&L'!$V$6:$AI$6,0)),'P&L'!$D$8:$D$278,$C60)/$A$1 -> 0 | N60: =SUMIFS(INDEX('P&L'!$V$8:$AI$278,,MATCH(N$53,'P&L'!$V$6:$AI$6,0)),'P&L'!$D$8:$D$278,$C60)/$A$1 -> 0 | O60: =SUMIFS(INDEX('P&L'!$V$8:$AI$278,,MATCH(O$53,'P&L'!$V$6:$AI$6,0)),'P&L'!$D$8:$D$278,$C60)/$A$1 -> 0 | Q60: =F60+I60+L60+O60 -> 0 | R60: =SUMIFS('P&L'!Q$8:Q$278,'P&L'!$D$8:$D$278,$C60)/$A$1 -> 0
C61: =IF(ISBLANK('Benchmark Index'!S13),"--",'Benchmark Index'!S13) -> Insurance | F61: =SUMIFS(INDEX('P&L'!$V$8:$AI$278,,MATCH(F$53,'P&L'!$V$6:$AI$6,0)),'P&L'!$D$8:$D$278,$C61)/$A$1 -> 0 | H61: =SUMIFS(INDEX('P&L'!$V$8:$AI$278,,MATCH(H$53,'P&L'!$V$6:$AI$6,0)),'P&L'!$D$8:$D$278,$C61)/$A$1 -> 0 | I61: =SUMIFS(INDEX('P&L'!$V$8:$AI$278,,MATCH(I$53,'P&L'!$V$6:$AI$6,0)),'P&L'!$D$8:$D$278,$C61)/$A$1 -> 0 | J61: =SUMIFS(INDEX('P&L'!$V$8:$AI$278,,MATCH(J$53,'P&L'!$V$6:$AI$6,0)),'P&L'!$D$8:$D$278,$C61)/$A$1 -> 0 | K61: =SUMIFS(INDEX('P&L'!$V$8:$AI$278,,MATCH(K$53,'P&L'!$V$6:$AI$6,0)),'P&L'!$D$8:$D$278,$C61)/$A$1 -> 0 | L61: =SUMIFS(INDEX('P&L'!$V$8:$AI$278,,MATCH(L$53,'P&L'!$V$6:$AI$6,0)),'P&L'!$D$8:$D$278,$C61)/$A$1 -> 0 | M61: =SUMIFS(INDEX('P&L'!$V$8:$AI$278,,MATCH(M$53,'P&L'!$V$6:$AI$6,0)),'P&L'!$D$8:$D$278,$C61)/$A$1 -> 0 | N61: =SUMIFS(INDEX('P&L'!$V$8:$AI$278,,MATCH(N$53,'P&L'!$V$6:$AI$6,0)),'P&L'!$D$8:$D$278,$C61)/$A$1 -> 0 | O61: =SUMIFS(INDEX('P&L'!$V$8:$AI$278,,MATCH(O$53,'P&L'!$V$6:$AI$6,0)),'P&L'!$D$8:$D$278,$C61)/$A$1 -> 7715.8 | Q61: =F61+I61+L61+O61 -> 7715.8 | R61: =SUMIFS('P&L'!Q$8:Q$278,'P&L'!$D$8:$D$278,$C61)/$A$1 -> 7950
C62: =IF(ISBLANK('Benchmark Index'!S14),"--",'Benchmark Index'!S14) -> License | F62: =SUMIFS(INDEX('P&L'!$V$8:$AI$278,,MATCH(F$53,'P&L'!$V$6:$AI$6,0)),'P&L'!$D$8:$D$278,$C62)/$A$1 -> 0 | H62: =SUMIFS(INDEX('P&L'!$V$8:$AI$278,,MATCH(H$53,'P&L'!$V$6:$AI$6,0)),'P&L'!$D$8:$D$278,$C62)/$A$1 -> 0 | I62: =SUMIFS(INDEX('P&L'!$V$8:$AI$278,,MATCH(I$53,'P&L'!$V$6:$AI$6,0)),'P&L'!$D$8:$D$278,$C62)/$A$1 -> 0 | J62: =SUMIFS(INDEX('P&L'!$V$8:$AI$278,,MATCH(J$53,'P&L'!$V$6:$AI$6,0)),'P&L'!$D$8:$D$278,$C62)/$A$1 -> 0 | K62: =SUMIFS(INDEX('P&L'!$V$8:$AI$278,,MATCH(K$53,'P&L'!$V$6:$AI$6,0)),'P&L'!$D$8:$D$278,$C62)/$A$1 -> 0 | L62: =SUMIFS(INDEX('P&L'!$V$8:$AI$278,,MATCH(L$53,'P&L'!$V$6:$AI$6,0)),'P&L'!$D$8:$D$278,$C62)/$A$1 -> 0 | M62: =SUMIFS(INDEX('P&L'!$V$8:$AI$278,,MATCH(M$53,'P&L'!$V$6:$AI$6,0)),'P&L'!$D$8:$D$278,$C62)/$A$1 -> 0 | N62: =SUMIFS(INDEX('P&L'!$V$8:$AI$278,,MATCH(N$53,'P&L'!$V$6:$AI$6,0)),'P&L'!$D$8:$D$278,$C62)/$A$1 -> 0 | O62: =SUMIFS(INDEX('P&L'!$V$8:$AI$278,,MATCH(O$53,'P&L'!$V$6:$AI$6,0)),'P&L'!$D$8:$D$278,$C62)/$A$1 -> 0 | Q62: =F62+I62+L62+O62 -> 0 | R62: =SUMIFS('P&L'!Q$8:Q$278,'P&L'!$D$8:$D$278,$C62)/$A$1 -> 0
C63: =IF(ISBLANK('Benchmark Index'!S15),"--",'Benchmark Index'!S15) -> Rent & Utilities | F63: =SUMIFS(INDEX('P&L'!$V$8:$AI$278,,MATCH(F$53,'P&L'!$V$6:$AI$6,0)),'P&L'!$D$8:$D$278,$C63)/$A$1 -> 0 | H63: =SUMIFS(INDEX('P&L'!$V$8:$AI$278,,MATCH(H$53,'P&L'!$V$6:$AI$6,0)),'P&L'!$D$8:$D$278,$C63)/$A$1 -> 0 | I63: =SUMIFS(INDEX('P&L'!$V$8:$AI$278,,MATCH(I$53,'P&L'!$V$6:$AI$6,0)),'P&L'!$D$8:$D$278,$C63)/$A$1 -> 0 | J63: =SUMIFS(INDEX('P&L'!$V$8:$AI$278,,MATCH(J$53,'P&L'!$V$6:$AI$6,0)),'P&L'!$D$8:$D$278,$C63)/$A$1 -> 0 | K63: =SUMIFS(INDEX('P&L'!$V$8:$AI$278,,MATCH(K$53,'P&L'!$V$6:$AI$6,0)),'P&L'!$D$8:$D$278,$C63)/$A$1 -> 0 | L63: =SUMIFS(INDEX('P&L'!$V$8:$AI$278,,MATCH(L$53,'P&L'!$V$6:$AI$6,0)),'P&L'!$D$8:$D$278,$C63)/$A$1 -> 0 | M63: =SUMIFS(INDEX('P&L'!$V$8:$AI$278,,MATCH(M$53,'P&L'!$V$6:$AI$6,0)),'P&L'!$D$8:$D$278,$C63)/$A$1 -> 0 | N63: =SUMIFS(INDEX('P&L'!$V$8:$AI$278,,MATCH(N$53,'P&L'!$V$6:$AI$6,0)),'P&L'!$D$8:$D$278,$C63)/$A$1 -> 0 | O63: =SUMIFS(INDEX('P&L'!$V$8:$AI$278,,MATCH(O$53,'P&L'!$V$6:$AI$6,0)),'P&L'!$D$8:$D$278,$C63)/$A$1 -> 50466.11 | Q63: =F63+I63+L63+O63 -> 50466.11 | R63: =SUMIFS('P&L'!Q$8:Q$278,'P&L'!$D$8:$D$278,$C63)/$A$1 -> 41139.241
C64: =IF(ISBLANK('Benchmark Index'!S16),"--",'Benchmark Index'!S16) -> Marketing consultant | F64: =SUMIFS(INDEX('P&L'!$V$8:$AI$278,,MATCH(F$53,'P&L'!$V$6:$AI$6,0)),'P&L'!$D$8:$D$278,$C64)/$A$1 -> 0 | H64: =SUMIFS(INDEX('P&L'!$V$8:$AI$278,,MATCH(H$53,'P&L'!$V$6:$AI$6,0)),'P&L'!$D$8:$D$278,$C64)/$A$1 -> 0 | I64: =SUMIFS(INDEX('P&L'!$V$8:$AI$278,,MATCH(I$53,'P&L'!$V$6:$AI$6,0)),'P&L'!$D$8:$D$278,$C64)/$A$1 -> 0 | J64: =SUMIFS(INDEX('P&L'!$V$8:$AI$278,,MATCH(J$53,'P&L'!$V$6:$AI$6,0)),'P&L'!$D$8:$D$278,$C64)/$A$1 -> 0 | K64: =SUMIFS(INDEX('P&L'!$V$8:$AI$278,,MATCH(K$53,'P&L'!$V$6:$AI$6,0)),'P&L'!$D$8:$D$278,$C64)/$A$1 -> 0 | L64: =SUMIFS(INDEX('P&L'!$V$8:$AI$278,,MATCH(L$53,'P&L'!$V$6:$AI$6,0)),'P&L'!$D$8:$D$278,$C64)/$A$1 -> 0 | M64: =SUMIFS(INDEX('P&L'!$V$8:$AI$278,,MATCH(M$53,'P&L'!$V$6:$AI$6,0)),'P&L'!$D$8:$D$278,$C64)/$A$1 -> 0 | N64: =SUMIFS(INDEX('P&L'!$V$8:$AI$278,,MATCH(N$53,'P&L'!$V$6:$AI$6,0)),'P&L'!$D$8:$D$278,$C64)/$A$1 -> 0 | O64: =SUMIFS(INDEX('P&L'!$V$8:$AI$278,,MATCH(O$53,'P&L'!$V$6:$AI$6,0)),'P&L'!$D$8:$D$278,$C64)/$A$1 -> 0 | Q64: =F64+I64+L64+O64 -> 0 | R64: =SUMIFS('P&L'!Q$8:Q$278,'P&L'!$D$8:$D$278,$C64)/$A$1 -> 0
C65: =IF(ISBLANK('Benchmark Index'!S17),"--",'Benchmark Index'!S17) -> Marketing general | F65: =SUMIFS(INDEX('P&L'!$V$8:$AI$278,,MATCH(F$53,'P&L'!$V$6:$AI$6,0)),'P&L'!$D$8:$D$278,$C65)/$A$1 -> 0 | H65: =SUMIFS(INDEX('P&L'!$V$8:$AI$278,,MATCH(H$53,'P&L'!$V$6:$AI$6,0)),'P&L'!$D$8:$D$278,$C65)/$A$1 -> 0 | I65: =SUMIFS(INDEX('P&L'!$V$8:$AI$278,,MATCH(I$53,'P&L'!$V$6:$AI$6,0)),'P&L'!$D$8:$D$278,$C65)/$A$1 -> 0 | J65: =SUMIFS(INDEX('P&L'!$V$8:$AI$278,,MATCH(J$53,'P&L'!$V$6:$AI$6,0)),'P&L'!$D$8:$D$278,$C65)/$A$1 -> 0 | K65: =SUMIFS(INDEX('P&L'!$V$8:$AI$278,,MATCH(K$53,'P&L'!$V$6:$AI$6,0)),'P&L'!$D$8:$D$278,$C65)/$A$1 -> 0 | L65: =SUMIFS(INDEX('P&L'!$V$8:$AI$278,,MATCH(L$53,'P&L'!$V$6:$AI$6,0)),'P&L'!$D$8:$D$278,$C65)/$A$1 -> 0 | M65: =SUMIFS(INDEX('P&L'!$V$8:$AI$278,,MATCH(M$53,'P&L'!$V$6:$AI$6,0)),'P&L'!$D$8:$D$278,$C65)/$A$1 -> 0 | N65: =SUMIFS(INDEX('P&L'!$V$8:$AI$278,,MATCH(N$53,'P&L'!$V$6:$AI$6,0)),'P&L'!$D$8:$D$278,$C65)/$A$1 -> 0 | O65: =SUMIFS(INDEX('P&L'!$V$8:$AI$278,,MATCH(O$53,'P&L'!$V$6:$AI$6,0)),'P&L'!$D$8:$D$278,$C65)/$A$1 -> 6018.94 | Q65: =F65+I65+L65+O65 -> 6018.94 | R65: =SUMIFS('P&L'!Q$8:Q$278,'P&L'!$D$8:$D$278,$C65)/$A$1 -> 228000
C66: =IF(ISBLANK('Benchmark Index'!S18),"--",'Benchmark Index'!S18) -> Subcontractors & Consulting | F66: =SUMIFS(INDEX('P&L'!$V$8:$AI$278,,MATCH(F$53,'P&L'!$V$6:$AI$6,0)),'P&L'!$D$8:$D$278,$C66)/$A$1 -> 0 | H66: =SUMIFS(INDEX('P&L'!$V$8:$AI$278,,MATCH(H$53,'P&L'!$V$6:$AI$6,0)),'P&L'!$D$8:$D$278,$C66)/$A$1 -> 0 | I66: =SUMIFS(INDEX('P&L'!$V$8:$AI$278,,MATCH(I$53,'P&L'!$V$6:$AI$6,0)),'P&L'!$D$8:$D$278,$C66)/$A$1 -> 0 | J66: =SUMIFS(INDEX('P&L'!$V$8:$AI$278,,MATCH(J$53,'P&L'!$V$6:$AI$6,0)),'P&L'!$D$8:$D$278,$C66)/$A$1 -> 0 | K66: =SUMIFS(INDEX('P&L'!$V$8:$AI$278,,MATCH(K$53,'P&L'!$V$6:$AI$6,0)),'P&L'!$D$8:$D$278,$C66)/$A$1 -> 0 | L66: =SUMIFS(INDEX('P&L'!$V$8:$AI$278,,MATCH(L$53,'P&L'!$V$6:$AI$6,0)),'P&L'!$D$8:$D$278,$C66)/$A$1 -> 0 | M66: =SUMIFS(INDEX('P&L'!$V$8:$AI$278,,MATCH(M$53,'P&L'!$V$6:$AI$6,0)),'P&L'!$D$8:$D$278,$C66)/$A$1 -> 0 | N66: =SUMIFS(INDEX('P&L'!$V$8:$AI$278,,MATCH(N$53,'P&L'!$V$6:$AI$6,0)),'P&L'!$D$8:$D$278,$C66)/$A$1 -> 0 | O66: =SUMIFS(INDEX('P&L'!$V$8:$AI$278,,MATCH(O$53,'P&L'!$V$6:$AI$6,0)),'P&L'!$D$8:$D$278,$C66)/$A$1 -> 0 | Q66: =F66+I66+L66+O66 -> 0 | R66: =SUMIFS('P&L'!Q$8:Q$278,'P&L'!$D$8:$D$278,$C66)/$A$1 -> 0
... C72: =IF(ISBLANK('Benchmark Index'!S24),"--",'Benchmark Index'!S24) -> Studies | F72: =SUMIFS(INDEX('P&L'!$V$8:$AI$278,,MATCH(F$53,'P&L'!$V$6:$AI$6,0)),'P&L'!$D$8:$D$278,$C72)/$A$1 -> 0 | H72: =SUMIFS(INDEX('P&L'!$V$8:$AI$278,,MATCH(H$53,'P&L'!$V$6:$AI$6,0)),'P&L'!$D$8:$D$278,$C72)/$A$1 -> 0 | I72: =SUMIFS(INDEX('P&L'!$V$8:$AI$278,,MATCH(I$53,'P&L'!$V$6:$AI$6,0)),'P&L'!$D$8:$D$278,$C72)/$A$1 -> 0 | J72: =SUMIFS(INDEX('P&L'!$V$8:$AI$278,,MATCH(J$53,'P&L'!$V$6:$AI$6,0)),'P&L'!$D$8:$D$278,$C72)/$A$1 -> 0 | K72: =SUMIFS(INDEX('P&L'!$V$8:$AI$278,,MATCH(K$53,'P&L'!$V$6:$AI$6,0)),'P&L'!$D$8:$D$278,$C72)/$A$1 -> 0 | L72: =SUMIFS(INDEX('P&L'!$V$8:$AI$278,,MATCH(L$53,'P&L'!$V$6:$AI$6,0)),'P&L'!$D$8:$D$278,$C72)/$A$1 -> 0 | M72: =SUMIFS(INDEX('P&L'!$V$8:$AI$278,,MATCH(M$53,'P&L'!$V$6:$AI$6,0)),'P&L'!$D$8:$D$278,$C72)/$A$1 -> 0 | N72: =SUMIFS(INDEX('P&L'!$V$8:$AI$278,,MATCH(N$53,'P&L'!$V$6:$AI$6,0)),'P&L'!$D$8:$D$278,$C72)/$A$1 -> 0 | O72: =SUMIFS(INDEX('P&L'!$V$8:$AI$278,,MATCH(O$53,'P&L'!$V$6:$AI$6,0)),'P&L'!$D$8:$D$278,$C72)/$A$1 -> 0 | Q72: =F72+I72+L72+O72 -> 0 | R72: =SUMIFS('P&L'!Q$8:Q$278,'P&L'!$D$8:$D$278,$C72)/$A$1 -> 0
C73: =IF(ISBLANK('Benchmark Index'!S26),"--",'Benchmark Index'!S26) -> BOM | F73: =SUMIFS(INDEX('P&L'!$V$8:$AI$278,,MATCH(F$53,'P&L'!$V$6:$AI$6,0)),'P&L'!$D$8:$D$278,$C73)/$A$1 -> 0 | H73: =SUMIFS(INDEX('P&L'!$V$8:$AI$278,,MATCH(H$53,'P&L'!$V$6:$AI$6,0)),'P&L'!$D$8:$D$278,$C73)/$A$1 -> 0 | I73: =SUMIFS(INDEX('P&L'!$V$8:$AI$278,,MATCH(I$53,'P&L'!$V$6:$AI$6,0)),'P&L'!$D$8:$D$278,$C73)/$A$1 -> 0 | J73: =SUMIFS(INDEX('P&L'!$V$8:$AI$278,,MATCH(J$53,'P&L'!$V$6:$AI$6,0)),'P&L'!$D$8:$D$278,$C73)/$A$1 -> 0 | K73: =SUMIFS(INDEX('P&L'!$V$8:$AI$278,,MATCH(K$53,'P&L'!$V$6:$AI$6,0)),'P&L'!$D$8:$D$278,$C73)/$A$1 -> 0 | L73: =SUMIFS(INDEX('P&L'!$V$8:$AI$278,,MATCH(L$53,'P&L'!$V$6:$AI$6,0)),'P&L'!$D$8:$D$278,$C73)/$A$1 -> 0 | M73: =SUMIFS(INDEX('P&L'!$V$8:$AI$278,,MATCH(M$53,'P&L'!$V$6:$AI$6,0)),'P&L'!$D$8:$D$278,$C73)/$A$1 -> 0 | N73: =SUMIFS(INDEX('P&L'!$V$8:$AI$278,,MATCH(N$53,'P&L'!$V$6:$AI$6,0)),'P&L'!$D$8:$D$278,$C73)/$A$1 -> 0 | O73: =SUMIFS(INDEX('P&L'!$V$8:$AI$278,,MATCH(O$53,'P&L'!$V$6:$AI$6,0)),'P&L'!$D$8:$D$278,$C73)/$A$1 -> 0 | Q73: =F73+I73+L73+O73 -> 0 | R73: =SUMIFS('P&L'!Q$8:Q$278,'P&L'!$D$8:$D$278,$C73)/$A$1 -> 0
C74: =IF(ISBLANK('Benchmark Index'!S27),"--",'Benchmark Index'!S27) -> OCS | F74: =SUMIFS(INDEX('P&L'!$V$8:$AI$278,,MATCH(F$53,'P&L'!$V$6:$AI$6,0)),'P&L'!$D$8:$D$278,$C74)/$A$1 -> 0 | H74: =SUMIFS(INDEX('P&L'!$V$8:$AI$278,,MATCH(H$53,'P&L'!$V$6:$AI$6,0)),'P&L'!$D$8:$D$278,$C74)/$A$1 -> 0 | I74: =SUMIFS(INDEX('P&L'!$V$8:$AI$278,,MATCH(I$53,'P&L'!$V$6:$AI$6,0)),'P&L'!$D$8:$D$278,$C74)/$A$1 -> 0 | J74: =SUMIFS(INDEX('P&L'!$V$8:$AI$278,,MATCH(J$53,'P&L'!$V$6:$AI$6,0)),'P&L'!$D$8:$D$278,$C74)/$A$1 -> 0 | K74: =SUMIFS(INDEX('P&L'!$V$8:$AI$278,,MATCH(K$53,'P&L'!$V$6:$AI$6,0)),'P&L'!$D$8:$D$278,$C74)/$A$1 -> 0 | L74: =SUMIFS(INDEX('P&L'!$V$8:$AI$278,,MATCH(L$53,'P&L'!$V$6:$AI$6,0)),'P&L'!$D$8:$D$278,$C74)/$A$1 -> 0 | M74: =SUMIFS(INDEX('P&L'!$V$8:$AI$278,,MATCH(M$53,'P&L'!$V$6:$AI$6,0)),'P&L'!$D$8:$D$278,$C74)/$A$1 -> 0 | N74: =SUMIFS(INDEX('P&L'!$V$8:$AI$278,,MATCH(N$53,'P&L'!$V$6:$AI$6,0)),'P&L'!$D$8:$D$278,$C74)/$A$1 -> 0 | O74: =SUMIFS(INDEX('P&L'!$V$8:$AI$278,,MATCH(O$53,'P&L'!$V$6:$AI$6,0)),'P&L'!$D$8:$D$278,$C74)/$A$1 -> 0 | Q74: =F74+I74+L74+O74 -> 0 | R74: =SUMIFS('P&L'!Q$8:Q$278,'P&L'!$D$8:$D$278,$C74)/$A$1 -> 0
C75: =IF(ISBLANK('Benchmark Index'!S28),"--",'Benchmark Index'!S28) -> Rev. Share | F75: =SUMIFS(INDEX('P&L'!$V$8:$AI$278,,MATCH(F$53,'P&L'!$V$6:$AI$6,0)),'P&L'!$D$8:$D$278,$C75)/$A$1 -> 0 | H75: =SUMIFS(INDEX('P&L'!$V$8:$AI$278,,MATCH(H$53,'P&L'!$V$6:$AI$6,0)),'P&L'!$D$8:$D$278,$C75)/$A$1 -> 0 | I75: =SUMIFS(INDEX('P&L'!$V$8:$AI$278,,MATCH(I$53,'P&L'!$V$6:$AI$6,0)),'P&L'!$D$8:$D$278,$C75)/$A$1 -> 0 | J75: =SUMIFS(INDEX('P&L'!$V$8:$AI$278,,MATCH(J$53,'P&L'!$V$6:$AI$6,0)),'P&L'!$D$8:$D$278,$C75)/$A$1 -> 0 | K75: =SUMIFS(INDEX('P&L'!$V$8:$AI$278,,MATCH(K$53,'P&L'!$V$6:$AI$6,0)),'P&L'!$D$8:$D$278,$C75)/$A$1 -> 0 | L75: =SUMIFS(INDEX('P&L'!$V$8:$AI$278,,MATCH(L$53,'P&L'!$V$6:$AI$6,0)),'P&L'!$D$8:$D$278,$C75)/$A$1 -> 0 | M75: =SUMIFS(INDEX('P&L'!$V$8:$AI$278,,MATCH(M$53,'P&L'!$V$6:$AI$6,0)),'P&L'!$D$8:$D$278,$C75)/$A$1 -> 0 | N75: =SUMIFS(INDEX('P&L'!$V$8:$AI$278,,MATCH(N$53,'P&L'!$V$6:$AI$6,0)),'P&L'!$D$8:$D$278,$C75)/$A$1 -> 0 | O75: =SUMIFS(INDEX('P&L'!$V$8:$AI$278,,MATCH(O$53,'P&L'!$V$6:$AI$6,0)),'P&L'!$D$8:$D$278,$C75)/$A$1 -> 0 | Q75: =F75+I75+L75+O75 -> 0 | R75: =SUMIFS('P&L'!Q$8:Q$278,'P&L'!$D$8:$D$278,$C75)/$A$1 -> 0
C76: =IF(ISBLANK('Benchmark Index'!S29),"--",'Benchmark Index'!S29) -> Office exp. | F76: =SUMIFS(INDEX('P&L'!$V$8:$AI$278,,MATCH(F$53,'P&L'!$V$6:$AI$6,0)),'P&L'!$D$8:$D$278,$C76)/$A$1 -> 0 | H76: =SUMIFS(INDEX('P&L'!$V$8:$AI$278,,MATCH(H$53,'P&L'!$V$6:$AI$6,0)),'P&L'!$D$8:$D$278,$C76)/$A$1 -> 0 | I76: =SUMIFS(INDEX('P&L'!$V$8:$AI$278,,MATCH(I$53,'P&L'!$V$6:$AI$6,0)),'P&L'!$D$8:$D$278,$C76)/$A$1 -> 0 | J76: =SUMIFS(INDEX('P&L'!$V$8:$AI$278,,MATCH(J$53,'P&L'!$V$6:$AI$6,0)),'P&L'!$D$8:$D$278,$C76)/$A$1 -> 0 | K76: =SUMIFS(INDEX('P&L'!$V$8:$AI$278,,MATCH(K$53,'P&L'!$V$6:$AI$6,0)),'P&L'!$D$8:$D$278,$C76)/$A$1 -> 0 | L76: =SUMIFS(INDEX('P&L'!$V$8:$AI$278,,MATCH(L$53,'P&L'!$V$6:$AI$6,0)),'P&L'!$D$8:$D$278,$C76)/$A$1 -> 0 | M76: =SUMIFS(INDEX('P&L'!$V$8:$AI$278,,MATCH(M$53,'P&L'!$V$6:$AI$6,0)),'P&L'!$D$8:$D$278,$C76)/$A$1 -> 0 | N76: =SUMIFS(INDEX('P&L'!$V$8:$AI$278,,MATCH(N$53,'P&L'!$V$6:$AI$6,0)),'P&L'!$D$8:$D$278,$C76)/$A$1 -> 0 | O76: =SUMIFS(INDEX('P&L'!$V$8:$AI$278,,MATCH(O$53,'P&L'!$V$6:$AI$6,0)),'P&L'!$D$8:$D$278,$C76)/$A$1 -> 0 | Q76: =F76+I76+L76+O76 -> 0 | R76: =SUMIFS('P&L'!Q$8:Q$278,'P&L'!$D$8:$D$278,$C76)/$A$1 -> 0
C77: =IF(ISBLANK('Benchmark Index'!S30),"--",'Benchmark Index'!S30) -> Cloud Computing | F77: =SUMIFS(INDEX('P&L'!$V$8:$AI$278,,MATCH(F$53,'P&L'!$V$6:$AI$6,0)),'P&L'!$D$8:$D$278,$C77)/$A$1 -> 0 | H77: =SUMIFS(INDEX('P&L'!$V$8:$AI$278,,MATCH(H$53,'P&L'!$V$6:$AI$6,0)),'P&L'!$D$8:$D$278,$C77)/$A$1 -> 0 | I77: =SUMIFS(INDEX('P&L'!$V$8:$AI$278,,MATCH(I$53,'P&L'!$V$6:$AI$6,0)),'P&L'!$D$8:$D$278,$C77)/$A$1 -> 0 | J77: =SUMIFS(INDEX('P&L'!$V$8:$AI$278,,MATCH(J$53,'P&L'!$V$6:$AI$6,0)),'P&L'!$D$8:$D$278,$C77)/$A$1 -> 0 | K77: =SUMIFS(INDEX('P&L'!$V$8:$AI$278,,MATCH(K$53,'P&L'!$V$6:$AI$6,0)),'P&L'!$D$8:$D$278,$C77)/$A$1 -> 0 | L77: =SUMIFS(INDEX('P&L'!$V$8:$AI$278,,MATCH(L$53,'P&L'!$V$6:$AI$6,0)),'P&L'!$D$8:$D$278,$C77)/$A$1 -> 0 | M77: =SUMIFS(INDEX('P&L'!$V$8:$AI$278,,MATCH(M$53,'P&L'!$V$6:$AI$6,0)),'P&L'!$D$8:$D$278,$C77)/$A$1 -> 0 | N77: =SUMIFS(INDEX('P&L'!$V$8:$AI$278,,MATCH(N$53,'P&L'!$V$6:$AI$6,0)),'P&L'!$D$8:$D$278,$C77)/$A$1 -> 0 | O77: =SUMIFS(INDEX('P&L'!$V$8:$AI$278,,MATCH(O$53,'P&L'!$V$6:$AI$6,0)),'P&L'!$D$8:$D$278,$C77)/$A$1 -> 0 | Q77: =F77+I77+L77+O77 -> 0 | R77: =SUMIFS('P&L'!Q$8:Q$278,'P&L'!$D$8:$D$278,$C77)/$A$1 -> 0
C78: =IF(ISBLANK('Benchmark Index'!S31),"--",'Benchmark Index'!S31) -> Software | F78: =SUMIFS(INDEX('P&L'!$V$8:$AI$278,,MATCH(F$53,'P&L'!$V$6:$AI$6,0)),'P&L'!$D$8:$D$278,$C78)/$A$1 -> 0 | H78: =SUMIFS(INDEX('P&L'!$V$8:$AI$278,,MATCH(H$53,'P&L'!$V$6:$AI$6,0)),'P&L'!$D$8:$D$278,$C78)/$A$1 -> 0 | I78: =SUMIFS(INDEX('P&L'!$V$8:$AI$278,,MATCH(I$53,'P&L'!$V$6:$AI$6,0)),'P&L'!$D$8:$D$278,$C78)/$A$1 -> 0 | J78: =SUMIFS(INDEX('P&L'!$V$8:$AI$278,,MATCH(J$53,'P&L'!$V$6:$AI$6,0)),'P&L'!$D$8:$D$278,$C78)/$A$1 -> 0 | K78: =SUMIFS(INDEX('P&L'!$V$8:$AI$278,,MATCH(K$53,'P&L'!$V$6:$AI$6,0)),'P&L'!$D$8:$D$278,$C78)/$A$1 -> 0 | L78: =SUMIFS(INDEX('P&L'!$V$8:$AI$278,,MATCH(L$53,'P&L'!$V$6:$AI$6,0)),'P&L'!$D$8:$D$278,$C78)/$A$1 -> 0 | M78: =SUMIFS(INDEX('P&L'!$V$8:$AI$278,,MATCH(M$53,'P&L'!$V$6:$AI$6,0)),'P&L'!$D$8:$D$278,$C78)/$A$1 -> 0 | N78: =SUMIFS(INDEX('P&L'!$V$8:$AI$278,,MATCH(N$53,'P&L'!$V$6:$AI$6,0)),'P&L'!$D$8:$D$278,$C78)/$A$1 -> 0 | O78: =SUMIFS(INDEX('P&L'!$V$8:$AI$278,,MATCH(O$53,'P&L'!$V$6:$AI$6,0)),'P&L'!$D$8:$D$278,$C78)/$A$1 -> 0 | Q78: =F78+I78+L78+O78 -> 0 | R78: =SUMIFS('P&L'!Q$8:Q$278,'P&L'!$D$8:$D$278,$C78)/$A$1 -> 0
C79: =IF(ISBLANK('Benchmark Index'!S32),"--",'Benchmark Index'!S32) -> Outsource | F79: =SUMIFS(INDEX('P&L'!$V$8:$AI$278,,MATCH(F$53,'P&L'!$V$6:$AI$6,0)),'P&L'!$D$8:$D$278,$C79)/$A$1 -> 0 | H79: =SUMIFS(INDEX('P&L'!$V$8:$AI$278,,MATCH(H$53,'P&L'!$V$6:$AI$6,0)),'P&L'!$D$8:$D$278,$C79)/$A$1 -> 0 | I79: =SUMIFS(INDEX('P&L'!$V$8:$AI$278,,MATCH(I$53,'P&L'!$V$6:$AI$6,0)),'P&L'!$D$8:$D$278,$C79)/$A$1 -> 0 | J79: =SUMIFS(INDEX('P&L'!$V$8:$AI$278,,MATCH(J$53,'P&L'!$V$6:$AI$6,0)),'P&L'!$D$8:$D$278,$C79)/$A$1 -> 0 | K79: =SUMIFS(INDEX('P&L'!$V$8:$AI$278,,MATCH(K$53,'P&L'!$V$6:$AI$6,0)),'P&L'!$D$8:$D$278,$C79)/$A$1 -> 0 | L79: =SUMIFS(INDEX('P&L'!$V$8:$AI$278,,MATCH(L$53,'P&L'!$V$6:$AI$6,0)),'P&L'!$D$8:$D$278,$C79)/$A$1 -> 0 | M79: =SUMIFS(INDEX('P&L'!$V$8:$AI$278,,MATCH(M$53,'P&L'!$V$6:$AI$6,0)),'P&L'!$D$8:$D$278,$C79)/$A$1 -> 0 | N79: =SUMIFS(INDEX('P&L'!$V$8:$AI$278,,MATCH(N$53,'P&L'!$V$6:$AI$6,0)),'P&L'!$D$8:$D$278,$C79)/$A$1 -> 0 | O79: =SUMIFS(INDEX('P&L'!$V$8:$AI$278,,MATCH(O$53,'P&L'!$V$6:$AI$6,0)),'P&L'!$D$8:$D$278,$C79)/$A$1 -> 52871.21 | Q79: =F79+I79+L79+O79 -> 52871.21 | R79: =SUMIFS('P&L'!Q$8:Q$278,'P&L'!$D$8:$D$278,$C79)/$A$1 -> 63000
C80: =IF(ISBLANK('Benchmark Index'!S33),"--",'Benchmark Index'!S33) -> Professional | F80: =SUMIFS(INDEX('P&L'!$V$8:$AI$278,,MATCH(F$53,'P&L'!$V$6:$AI$6,0)),'P&L'!$D$8:$D$278,$C80)/$A$1 -> 0 | H80: =SUMIFS(INDEX('P&L'!$V$8:$AI$278,,MATCH(H$53,'P&L'!$V$6:$AI$6,0)),'P&L'!$D$8:$D$278,$C80)/$A$1 -> 0 | I80: =SUMIFS(INDEX('P&L'!$V$8:$AI$278,,MATCH(I$53,'P&L'!$V$6:$AI$6,0)),'P&L'!$D$8:$D$278,$C80)/$A$1 -> 0 | J80: =SUMIFS(INDEX('P&L'!$V$8:$AI$278,,MATCH(J$53,'P&L'!$V$6:$AI$6,0)),'P&L'!$D$8:$D$278,$C80)/$A$1 -> 0 | K80: =SUMIFS(INDEX('P&L'!$V$8:$AI$278,,MATCH(K$53,'P&L'!$V$6:$AI$6,0)),'P&L'!$D$8:$D$278,$C80)/$A$1 -> 0 | L80: =SUMIFS(INDEX('P&L'!$V$8:$AI$278,,MATCH(L$53,'P&L'!$V$6:$AI$6,0)),'P&L'!$D$8:$D$278,$C80)/$A$1 -> 0 | M80: =SUMIFS(INDEX('P&L'!$V$8:$AI$278,,MATCH(M$53,'P&L'!$V$6:$AI$6,0)),'P&L'!$D$8:$D$278,$C80)/$A$1 -> 0 | N80: =SUMIFS(INDEX('P&L'!$V$8:$AI$278,,MATCH(N$53,'P&L'!$V$6:$AI$6,0)),'P&L'!$D$8:$D$278,$C80)/$A$1 -> 0 | O80: =SUMIFS(INDEX('P&L'!$V$8:$AI$278,,MATCH(O$53,'P&L'!$V$6:$AI$6,0)),'P&L'!$D$8:$D$278,$C80)/$A$1 -> 44395.17 | Q80: =F80+I80+L80+O80 -> 44395.17 | R80: =SUMIFS('P&L'!Q$8:Q$278,'P&L'!$D$8:$D$278,$C80)/$A$1 -> 65607.625
C81: =IF(ISBLANK('Benchmark Index'!S34),"--",'Benchmark Index'!S34) -> Welfare | D81: =SUMIFS(INDEX('P&L'!$V$8:$AI$278,,MATCH(D$53,'P&L'!$V$6:$AI$6,0)),'P&L'!$D$8:$D$278,$C81)/$A$1 -> 0 | E81: =SUMIFS(INDEX('P&L'!$V$8:$AI$278,,MATCH(E$53,'P&L'!$V$6:$AI$6,0)),'P&L'!$D$8:$D$278,$C81)/$A$1 -> 0 | F81: =SUMIFS(INDEX('P&L'!$V$8:$AI$278,,MATCH(F$53,'P&L'!$V$6:$AI$6,0)),'P&L'!$D$8:$D$278,$C81)/$A$1 -> 0 | G81: =SUMIFS(INDEX('P&L'!$V$8:$AI$278,,MATCH(G$53,'P&L'!$V$6:$AI$6,0)),'P&L'!$D$8:$D$278,$C81)/$A$1 -> 0 | H81: =SUMIFS(INDEX('P&L'!$V$8:$AI$278,,MATCH(H$53,'P&L'!$V$6:$AI$6,0)),'P&L'!$D$8:$D$278,$C81)/$A$1 -> 0 | I81: =SUMIFS(INDEX('P&L'!$V$8:$AI$278,,MATCH(I$53,'P&L'!$V$6:$AI$6,0)),'P&L'!$D$8:$D$278,$C81)/$A$1 -> 0 | J81: =SUMIFS(INDEX('P&L'!$V$8:$AI$278,,MATCH(J$53,'P&L'!$V$6:$AI$6,0)),'P&L'!$D$8:$D$278,$C81)/$A$1 -> 0 | K81: =SUMIFS(INDEX('P&L'!$V$8:$AI$278,,MATCH(K$53,'P&L'!$V$6:$AI$6,0)),'P&L'!$D$8:$D$278,$C81)/$A$1 -> 0 | ... O81: =SUMIFS(INDEX('P&L'!$V$8:$AI$278,,MATCH(O$53,'P&L'!$V$6:$AI$6,0)),'P&L'!$D$8:$D$278,$C81)/$A$1 -> 35569.44 | Q81: =SUMIFS('P&L'!P$8:P$278,'P&L'!$D$8:$D$278,$C81)/$A$1 -> 35569.44 | R81: =SUMIFS('P&L'!Q$8:Q$278,'P&L'!$D$8:$D$278,$C81)/$A$1 -> 18300
C82: =IF(ISBLANK('Benchmark Index'!S35),"--",'Benchmark Index'!S35) -> Hosting | D82: =SUMIFS(INDEX('P&L'!$V$8:$AI$278,,MATCH(D$53,'P&L'!$V$6:$AI$6,0)),'P&L'!$D$8:$D$278,$C82)/$A$1 -> 0 | E82: =SUMIFS(INDEX('P&L'!$V$8:$AI$278,,MATCH(E$53,'P&L'!$V$6:$AI$6,0)),'P&L'!$D$8:$D$278,$C82)/$A$1 -> 0 | F82: =SUMIFS(INDEX('P&L'!$V$8:$AI$278,,MATCH(F$53,'P&L'!$V$6:$AI$6,0)),'P&L'!$D$8:$D$278,$C82)/$A$1 -> 0 | G82: =SUMIFS(INDEX('P&L'!$V$8:$AI$278,,MATCH(G$53,'P&L'!$V$6:$AI$6,0)),'P&L'!$D$8:$D$278,$C82)/$A$1 -> 0 | H82: =SUMIFS(INDEX('P&L'!$V$8:$AI$278,,MATCH(H$53,'P&L'!$V$6:$AI$6,0)),'P&L'!$D$8:$D$278,$C82)/$A$1 -> 0 | I82: =SUMIFS(INDEX('P&L'!$V$8:$AI$278,,MATCH(I$53,'P&L'!$V$6:$AI$6,0)),'P&L'!$D$8:$D$278,$C82)/$A$1 -> 0 | J82: =SUMIFS(INDEX('P&L'!$V$8:$AI$278,,MATCH(J$53,'P&L'!$V$6:$AI$6,0)),'P&L'!$D$8:$D$278,$C82)/$A$1 -> 0 | K82: =SUMIFS(INDEX('P&L'!$V$8:$AI$278,,MATCH(K$53,'P&L'!$V$6:$AI$6,0)),'P&L'!$D$8:$D$278,$C82)/$A$1 -> 0 | ... O82: =SUMIFS(INDEX('P&L'!$V$8:$AI$278,,MATCH(O$53,'P&L'!$V$6:$AI$6,0)),'P&L'!$D$8:$D$278,$C82)/$A$1 -> 88.59 | Q82: =SUMIFS('P&L'!P$8:P$278,'P&L'!$D$8:$D$278,$C82)/$A$1 -> 88.59 | R82: =SUMIFS('P&L'!Q$8:Q$278,'P&L'!$D$8:$D$278,$C82)/$A$1 -> 20000
C83: =IF(ISBLANK('Benchmark Index'!S36),"--",'Benchmark Index'!S36) -> Relocation Expenses | D83: =SUMIFS(INDEX('P&L'!$V$8:$AI$278,,MATCH(D$53,'P&L'!$V$6:$AI$6,0)),'P&L'!$D$8:$D$278,$C83)/$A$1 -> 0 | E83: =SUMIFS(INDEX('P&L'!$V$8:$AI$278,,MATCH(E$53,'P&L'!$V$6:$AI$6,0)),'P&L'!$D$8:$D$278,$C83)/$A$1 -> 0 | F83: =SUMIFS(INDEX('P&L'!$V$8:$AI$278,,MATCH(F$53,'P&L'!$V$6:$AI$6,0)),'P&L'!$D$8:$D$278,$C83)/$A$1 -> 0 | G83: =SUMIFS(INDEX('P&L'!$V$8:$AI$278,,MATCH(G$53,'P&L'!$V$6:$AI$6,0)),'P&L'!$D$8:$D$278,$C83)/$A$1 -> 0 | H83: =SUMIFS(INDEX('P&L'!$V$8:$AI$278,,MATCH(H$53,'P&L'!$V$6:$AI$6,0)),'P&L'!$D$8:$D$278,$C83)/$A$1 -> 0 | I83: =SUMIFS(INDEX('P&L'!$V$8:$AI$278,,MATCH(I$53,'P&L'!$V$6:$AI$6,0)),'P&L'!$D$8:$D$278,$C83)/$A$1 -> 0 | J83: =SUMIFS(INDEX('P&L'!$V$8:$AI$278,,MATCH(J$53,'P&L'!$V$6:$AI$6,0)),'P&L'!$D$8:$D$278,$C83)/$A$1 -> 0 | K83: =SUMIFS(INDEX('P&L'!$V$8:$AI$278,,MATCH(K$53,'P&L'!$V$6:$AI$6,0)),'P&L'!$D$8:$D$278,$C83)/$A$1 -> 0 | ... O83: =SUMIFS(INDEX('P&L'!$V$8:$AI$278,,MATCH(O$53,'P&L'!$V$6:$AI$6,0)),'P&L'!$D$8:$D$278,$C83)/$A$1 -> 0 | Q83: =SUMIFS('P&L'!P$8:P$278,'P&L'!$D$8:$D$278,$C83)/$A$1 -> 0 | R83: =SUMIFS('P&L'!Q$8:Q$278,'P&L'!$D$8:$D$278,$C83)/$A$1 -> 0
C84: =IF(ISBLANK('Benchmark Index'!S37),"--",'Benchmark Index'!S37) -> Tools | D84: =SUMIFS(INDEX('P&L'!$V$8:$AI$278,,MATCH(D$53,'P&L'!$V$6:$AI$6,0)),'P&L'!$D$8:$D$278,$C84)/$A$1 -> 0 | E84: =SUMIFS(INDEX('P&L'!$V$8:$AI$278,,MATCH(E$53,'P&L'!$V$6:$AI$6,0)),'P&L'!$D$8:$D$278,$C84)/$A$1 -> 0 | F84: =SUMIFS(INDEX('P&L'!$V$8:$AI$278,,MATCH(F$53,'P&L'!$V$6:$AI$6,0)),'P&L'!$D$8:$D$278,$C84)/$A$1 -> 0 | G84: =SUMIFS(INDEX('P&L'!$V$8:$AI$278,,MATCH(G$53,'P&L'!$V$6:$AI$6,0)),'P&L'!$D$8:$D$278,$C84)/$A$1 -> 0 | H84: =SUMIFS(INDEX('P&L'!$V$8:$AI$278,,MATCH(H$53,'P&L'!$V$6:$AI$6,0)),'P&L'!$D$8:$D$278,$C84)/$A$1 -> 0 | I84: =SUMIFS(INDEX('P&L'!$V$8:$AI$278,,MATCH(I$53,'P&L'!$V$6:$AI$6,0)),'P&L'!$D$8:$D$278,$C84)/$A$1 -> 0 | J84: =SUMIFS(INDEX('P&L'!$V$8:$AI$278,,MATCH(J$53,'P&L'!$V$6:$AI$6,0)),'P&L'!$D$8:$D$278,$C84)/$A$1 -> 0 | K84: =SUMIFS(INDEX('P&L'!$V$8:$AI$278,,MATCH(K$53,'P&L'!$V$6:$AI$6,0)),'P&L'!$D$8:$D$278,$C84)/$A$1 -> 0 | ... O84: =SUMIFS(INDEX('P&L'!$V$8:$AI$278,,MATCH(O$53,'P&L'!$V$6:$AI$6,0)),'P&L'!$D$8:$D$278,$C84)/$A$1 -> 40734.05 | Q84: =SUMIFS('P&L'!P$8:P$278,'P&L'!$D$8:$D$278,$C84)/$A$1 -> 40734.05 | R84: =SUMIFS('P&L'!Q$8:Q$278,'P&L'!$D$8:$D$278,$C84)/$A$1 -> 15750
C85: =IF(ISBLANK('Benchmark Index'!S38),"--",'Benchmark Index'!S38) -> Tapeout | D85: =SUMIFS(INDEX('P&L'!$V$8:$AI$278,,MATCH(D$53,'P&L'!$V$6:$AI$6,0)),'P&L'!$D$8:$D$278,$C85)/$A$1 -> 0 | E85: =SUMIFS(INDEX('P&L'!$V$8:$AI$278,,MATCH(E$53,'P&L'!$V$6:$AI$6,0)),'P&L'!$D$8:$D$278,$C85)/$A$1 -> 0 | F85: =SUMIFS(INDEX('P&L'!$V$8:$AI$278,,MATCH(F$53,'P&L'!$V$6:$AI$6,0)),'P&L'!$D$8:$D$278,$C85)/$A$1 -> 0 | G85: =SUMIFS(INDEX('P&L'!$V$8:$AI$278,,MATCH(G$53,'P&L'!$V$6:$AI$6,0)),'P&L'!$D$8:$D$278,$C85)/$A$1 -> 0 | H85: =SUMIFS(INDEX('P&L'!$V$8:$AI$278,,MATCH(H$53,'P&L'!$V$6:$AI$6,0)),'P&L'!$D$8:$D$278,$C85)/$A$1 -> 0 | I85: =SUMIFS(INDEX('P&L'!$V$8:$AI$278,,MATCH(I$53,'P&L'!$V$6:$AI$6,0)),'P&L'!$D$8:$D$278,$C85)/$A$1 -> 0 | J85: =SUMIFS(INDEX('P&L'!$V$8:$AI$278,,MATCH(J$53,'P&L'!$V$6:$AI$6,0)),'P&L'!$D$8:$D$278,$C85)/$A$1 -> 0 | K85: =SUMIFS(INDEX('P&L'!$V$8:$AI$278,,MATCH(K$53,'P&L'!$V$6:$AI$6,0)),'P&L'!$D$8:$D$278,$C85)/$A$1 -> 0 | ... O85: =SUMIFS(INDEX('P&L'!$V$8:$AI$278,,MATCH(O$53,'P&L'!$V$6:$AI$6,0)),'P&L'!$D$8:$D$278,$C85)/$A$1 -> 0 | Q85: =SUMIFS('P&L'!P$8:P$278,'P&L'!$D$8:$D$278,$C85)/$A$1 -> 0 | R85: =SUMIFS('P&L'!Q$8:Q$278,'P&L'!$D$8:$D$278,$C85)/$A$1 -> 0
C86: =IF(ISBLANK('Benchmark Index'!S39),"--",'Benchmark Index'!S39) -> Hardware | D86: =SUMIFS(INDEX('P&L'!$V$8:$AI$278,,MATCH(D$53,'P&L'!$V$6:$AI$6,0)),'P&L'!$D$8:$D$278,$C86)/$A$1 -> 0 | E86: =SUMIFS(INDEX('P&L'!$V$8:$AI$278,,MATCH(E$53,'P&L'!$V$6:$AI$6,0)),'P&L'!$D$8:$D$278,$C86)/$A$1 -> 0 | F86: =SUMIFS(INDEX('P&L'!$V$8:$AI$278,,MATCH(F$53,'P&L'!$V$6:$AI$6,0)),'P&L'!$D$8:$D$278,$C86)/$A$1 -> 0 | G86: =SUMIFS(INDEX('P&L'!$V$8:$AI$278,,MATCH(G$53,'P&L'!$V$6:$AI$6,0)),'P&L'!$D$8:$D$278,$C86)/$A$1 -> 0 | H86: =SUMIFS(INDEX('P&L'!$V$8:$AI$278,,MATCH(H$53,'P&L'!$V$6:$AI$6,0)),'P&L'!$D$8:$D$278,$C86)/$A$1 -> 0 | I86: =SUMIFS(INDEX('P&L'!$V$8:$AI$278,,MATCH(I$53,'P&L'!$V$6:$AI$6,0)),'P&L'!$D$8:$D$278,$C86)/$A$1 -> 0 | J86: =SUMIFS(INDEX('P&L'!$V$8:$AI$278,,MATCH(J$53,'P&L'!$V$6:$AI$6,0)),'P&L'!$D$8:$D$278,$C86)/$A$1 -> 0 | K86: =SUMIFS(INDEX('P&L'!$V$8:$AI$278,,MATCH(K$53,'P&L'!$V$6:$AI$6,0)),'P&L'!$D$8:$D$278,$C86)/$A$1 -> 0 | ... O86: =SUMIFS(INDEX('P&L'!$V$8:$AI$278,,MATCH(O$53,'P&L'!$V$6:$AI$6,0)),'P&L'!$D$8:$D$278,$C86)/$A$1 -> 0 | Q86: =SUMIFS('P&L'!P$8:P$278,'P&L'!$D$8:$D$278,$C86)/$A$1 -> 0 | R86: =SUMIFS('P&L'!Q$8:Q$278,'P&L'!$D$8:$D$278,$C86)/$A$1 -> 0
C87: =IF(ISBLANK('Benchmark Index'!S40),"--",'Benchmark Index'!S40) -> rental of lab equipment | D87: =SUMIFS(INDEX('P&L'!$V$8:$AI$278,,MATCH(D$53,'P&L'!$V$6:$AI$6,0)),'P&L'!$D$8:$D$278,$C87)/$A$1 -> 0 | E87: =SUMIFS(INDEX('P&L'!$V$8:$AI$278,,MATCH(E$53,'P&L'!$V$6:$AI$6,0)),'P&L'!$D$8:$D$278,$C87)/$A$1 -> 0 | F87: =SUMIFS(INDEX('P&L'!$V$8:$AI$278,,MATCH(F$53,'P&L'!$V$6:$AI$6,0)),'P&L'!$D$8:$D$278,$C87)/$A$1 -> 0 | G87: =SUMIFS(INDEX('P&L'!$V$8:$AI$278,,MATCH(G$53,'P&L'!$V$6:$AI$6,0)),'P&L'!$D$8:$D$278,$C87)/$A$1 -> 0 | H87: =SUMIFS(INDEX('P&L'!$V$8:$AI$278,,MATCH(H$53,'P&L'!$V$6:$AI$6,0)),'P&L'!$D$8:$D$278,$C87)/$A$1 -> 0 | I87: =SUMIFS(INDEX('P&L'!$V$8:$AI$278,,MATCH(I$53,'P&L'!$V$6:$AI$6,0)),'P&L'!$D$8:$D$278,$C87)/$A$1 -> 0 | J87: =SUMIFS(INDEX('P&L'!$V$8:$AI$278,,MATCH(J$53,'P&L'!$V$6:$AI$6,0)),'P&L'!$D$8:$D$278,$C87)/$A$1 -> 0 | K87: =SUMIFS(INDEX('P&L'!$V$8:$AI$278,,MATCH(K$53,'P&L'!$V$6:$AI$6,0)),'P&L'!$D$8:$D$278,$C87)/$A$1 -> 0 | ... O87: =SUMIFS(INDEX('P&L'!$V$8:$AI$278,,MATCH(O$53,'P&L'!$V$6:$AI$6,0)),'P&L'!$D$8:$D$278,$C87)/$A$1 -> 0 | Q87: =SUMIFS('P&L'!P$8:P$278,'P&L'!$D$8:$D$278,$C87)/$A$1 -> 0 | R87: =SUMIFS('P&L'!Q$8:Q$278,'P&L'!$D$8:$D$278,$C87)/$A$1 -> 0
C88: =IF(ISBLANK('Benchmark Index'!S41),"--",'Benchmark Index'!S41) -> Manufacturing | D88: =SUMIFS(INDEX('P&L'!$V$8:$AI$278,,MATCH(D$53,'P&L'!$V$6:$AI$6,0)),'P&L'!$D$8:$D$278,$C88)/$A$1 -> 0 | E88: =SUMIFS(INDEX('P&L'!$V$8:$AI$278,,MATCH(E$53,'P&L'!$V$6:$AI$6,0)),'P&L'!$D$8:$D$278,$C88)/$A$1 -> 0 | F88: =SUMIFS(INDEX('P&L'!$V$8:$AI$278,,MATCH(F$53,'P&L'!$V$6:$AI$6,0)),'P&L'!$D$8:$D$278,$C88)/$A$1 -> 0 | G88: =SUMIFS(INDEX('P&L'!$V$8:$AI$278,,MATCH(G$53,'P&L'!$V$6:$AI$6,0)),'P&L'!$D$8:$D$278,$C88)/$A$1 -> 0 | H88: =SUMIFS(INDEX('P&L'!$V$8:$AI$278,,MATCH(H$53,'P&L'!$V$6:$AI$6,0)),'P&L'!$D$8:$D$278,$C88)/$A$1 -> 0 | I88: =SUMIFS(INDEX('P&L'!$V$8:$AI$278,,MATCH(I$53,'P&L'!$V$6:$AI$6,0)),'P&L'!$D$8:$D$278,$C88)/$A$1 -> 0 | J88: =SUMIFS(INDEX('P&L'!$V$8:$AI$278,,MATCH(J$53,'P&L'!$V$6:$AI$6,0)),'P&L'!$D$8:$D$278,$C88)/$A$1 -> 0 | K88: =SUMIFS(INDEX('P&L'!$V$8:$AI$278,,MATCH(K$53,'P&L'!$V$6:$AI$6,0)),'P&L'!$D$8:$D$278,$C88)/$A$1 -> 0 | ... O88: =SUMIFS(INDEX('P&L'!$V$8:$AI$278,,MATCH(O$53,'P&L'!$V$6:$AI$6,0)),'P&L'!$D$8:$D$278,$C88)/$A$1 -> 0 | Q88: =SUMIFS('P&L'!P$8:P$278,'P&L'!$D$8:$D$278,$C88)/$A$1 -> 0 | R88: =SUMIFS('P&L'!Q$8:Q$278,'P&L'!$D$8:$D$278,$C88)/$A$1 -> 0
C89: =IF(ISBLANK('Benchmark Index'!S42),"--",'Benchmark Index'!S42) -> IP | D89: =SUMIFS(INDEX('P&L'!$V$8:$AI$278,,MATCH(D$53,'P&L'!$V$6:$AI$6,0)),'P&L'!$D$8:$D$278,$C89)/$A$1 -> 0 | E89: =SUMIFS(INDEX('P&L'!$V$8:$AI$278,,MATCH(E$53,'P&L'!$V$6:$AI$6,0)),'P&L'!$D$8:$D$278,$C89)/$A$1 -> 0 | F89: =SUMIFS(INDEX('P&L'!$V$8:$AI$278,,MATCH(F$53,'P&L'!$V$6:$AI$6,0)),'P&L'!$D$8:$D$278,$C89)/$A$1 -> 0 | G89: =SUMIFS(INDEX('P&L'!$V$8:$AI$278,,MATCH(G$53,'P&L'!$V$6:$AI$6,0)),'P&L'!$D$8:$D$278,$C89)/$A$1 -> 0 | H89: =SUMIFS(INDEX('P&L'!$V$8:$AI$278,,MATCH(H$53,'P&L'!$V$6:$AI$6,0)),'P&L'!$D$8:$D$278,$C89)/$A$1 -> 0 | I89: =SUMIFS(INDEX('P&L'!$V$8:$AI$278,,MATCH(I$53,'P&L'!$V$6:$AI$6,0)),'P&L'!$D$8:$D$278,$C89)/$A$1 -> 0 | J89: =SUMIFS(INDEX('P&L'!$V$8:$AI$278,,MATCH(J$53,'P&L'!$V$6:$AI$6,0)),'P&L'!$D$8:$D$278,$C89)/$A$1 -> 0 | K89: =SUMIFS(INDEX('P&L'!$V$8:$AI$278,,MATCH(K$53,'P&L'!$V$6:$AI$6,0)),'P&L'!$D$8:$D$278,$C89)/$A$1 -> 0 | ... O89: =SUMIFS(INDEX('P&L'!$V$8:$AI$278,,MATCH(O$53,'P&L'!$V$6:$AI$6,0)),'P&L'!$D$8:$D$278,$C89)/$A$1 -> 0 | Q89: =SUMIFS('P&L'!P$8:P$278,'P&L'!$D$8:$D$278,$C89)/$A$1 -> 0 | R89: =SUMIFS('P&L'!Q$8:Q$278,'P&L'!$D$8:$D$278,$C89)/$A$1 -> 0
C90: =IF(ISBLANK('Benchmark Index'!S43),"--",'Benchmark Index'!S43) -> Regulatory | D90: =SUMIFS(INDEX('P&L'!$V$8:$AI$278,,MATCH(D$53,'P&L'!$V$6:$AI$6,0)),'P&L'!$D$8:$D$278,$C90)/$A$1 -> 0 | E90: =SUMIFS(INDEX('P&L'!$V$8:$AI$278,,MATCH(E$53,'P&L'!$V$6:$AI$6,0)),'P&L'!$D$8:$D$278,$C90)/$A$1 -> 0 | F90: =SUMIFS(INDEX('P&L'!$V$8:$AI$278,,MATCH(F$53,'P&L'!$V$6:$AI$6,0)),'P&L'!$D$8:$D$278,$C90)/$A$1 -> 0 | G90: =SUMIFS(INDEX('P&L'!$V$8:$AI$278,,MATCH(G$53,'P&L'!$V$6:$AI$6,0)),'P&L'!$D$8:$D$278,$C90)/$A$1 -> 0 | H90: =SUMIFS(INDEX('P&L'!$V$8:$AI$278,,MATCH(H$53,'P&L'!$V$6:$AI$6,0)),'P&L'!$D$8:$D$278,$C90)/$A$1 -> 0 | I90: =SUMIFS(INDEX('P&L'!$V$8:$AI$278,,MATCH(I$53,'P&L'!$V$6:$AI$6,0)),'P&L'!$D$8:$D$278,$C90)/$A$1 -> 0 | J90: =SUMIFS(INDEX('P&L'!$V$8:$AI$278,,MATCH(J$53,'P&L'!$V$6:$AI$6,0)),'P&L'!$D$8:$D$278,$C90)/$A$1 -> 0 | K90: =SUMIFS(INDEX('P&L'!$V$8:$AI$278,,MATCH(K$53,'P&L'!$V$6:$AI$6,0)),'P&L'!$D$8:$D$278,$C90)/$A$1 -> 0 | ... O90: =SUMIFS(INDEX('P&L'!$V$8:$AI$278,,MATCH(O$53,'P&L'!$V$6:$AI$6,0)),'P&L'!$D$8:$D$278,$C90)/$A$1 -> 0 | Q90: =SUMIFS('P&L'!P$8:P$278,'P&L'!$D$8:$D$278,$C90)/$A$1 -> 0 | R90: =SUMIFS('P&L'!Q$8:Q$278,'P&L'!$D$8:$D$278,$C90)/$A$1 -> 0
C91: =IF(ISBLANK('Benchmark Index'!S44),"--",'Benchmark Index'!S44) -> CT Expenses | D91: =SUMIFS(INDEX('P&L'!$V$8:$AI$278,,MATCH(D$53,'P&L'!$V$6:$AI$6,0)),'P&L'!$D$8:$D$278,$C91)/$A$1 -> 0 | E91: =SUMIFS(INDEX('P&L'!$V$8:$AI$278,,MATCH(E$53,'P&L'!$V$6:$AI$6,0)),'P&L'!$D$8:$D$278,$C91)/$A$1 -> 0 | F91: =SUMIFS(INDEX('P&L'!$V$8:$AI$278,,MATCH(F$53,'P&L'!$V$6:$AI$6,0)),'P&L'!$D$8:$D$278,$C91)/$A$1 -> 0 | G91: =SUMIFS(INDEX('P&L'!$V$8:$AI$278,,MATCH(G$53,'P&L'!$V$6:$AI$6,0)),'P&L'!$D$8:$D$278,$C91)/$A$1 -> 0 | H91: =SUMIFS(INDEX('P&L'!$V$8:$AI$278,,MATCH(H$53,'P&L'!$V$6:$AI$6,0)),'P&L'!$D$8:$D$278,$C91)/$A$1 -> 0 | I91: =SUMIFS(INDEX('P&L'!$V$8:$AI$278,,MATCH(I$53,'P&L'!$V$6:$AI$6,0)),'P&L'!$D$8:$D$278,$C91)/$A$1 -> 0 | J91: =SUMIFS(INDEX('P&L'!$V$8:$AI$278,,MATCH(J$53,'P&L'!$V$6:$AI$6,0)),'P&L'!$D$8:$D$278,$C91)/$A$1 -> 0 | K91: =SUMIFS(INDEX('P&L'!$V$8:$AI$278,,MATCH(K$53,'P&L'!$V$6:$AI$6,0)),'P&L'!$D$8:$D$278,$C91)/$A$1 -> 0 | ... O91: =SUMIFS(INDEX('P&L'!$V$8:$AI$278,,MATCH(O$53,'P&L'!$V$6:$AI$6,0)),'P&L'!$D$8:$D$278,$C91)/$A$1 -> 0 | Q91: =SUMIFS('P&L'!P$8:P$278,'P&L'!$D$8:$D$278,$C91)/$A$1 -> 0 | R91: =SUMIFS('P&L'!Q$8:Q$278,'P&L'!$D$8:$D$278,$C91)/$A$1 -> 0
C92: =IF(ISBLANK('Benchmark Index'!S45),"--",'Benchmark Index'!S45) -> RT Cost | D92: =SUMIFS(INDEX('P&L'!$V$8:$AI$278,,MATCH(D$53,'P&L'!$V$6:$AI$6,0)),'P&L'!$D$8:$D$278,$C92)/$A$1 -> 0 | E92: =SUMIFS(INDEX('P&L'!$V$8:$AI$278,,MATCH(E$53,'P&L'!$V$6:$AI$6,0)),'P&L'!$D$8:$D$278,$C92)/$A$1 -> 0 | F92: =SUMIFS(INDEX('P&L'!$V$8:$AI$278,,MATCH(F$53,'P&L'!$V$6:$AI$6,0)),'P&L'!$D$8:$D$278,$C92)/$A$1 -> 0 | G92: =SUMIFS(INDEX('P&L'!$V$8:$AI$278,,MATCH(G$53,'P&L'!$V$6:$AI$6,0)),'P&L'!$D$8:$D$278,$C92)/$A$1 -> 0 | H92: =SUMIFS(INDEX('P&L'!$V$8:$AI$278,,MATCH(H$53,'P&L'!$V$6:$AI$6,0)),'P&L'!$D$8:$D$278,$C92)/$A$1 -> 0 | I92: =SUMIFS(INDEX('P&L'!$V$8:$AI$278,,MATCH(I$53,'P&L'!$V$6:$AI$6,0)),'P&L'!$D$8:$D$278,$C92)/$A$1 -> 0 | J92: =SUMIFS(INDEX('P&L'!$V$8:$AI$278,,MATCH(J$53,'P&L'!$V$6:$AI$6,0)),'P&L'!$D$8:$D$278,$C92)/$A$1 -> 0 | K92: =SUMIFS(INDEX('P&L'!$V$8:$AI$278,,MATCH(K$53,'P&L'!$V$6:$AI$6,0)),'P&L'!$D$8:$D$278,$C92)/$A$1 -> 0 | ... O92: =SUMIFS(INDEX('P&L'!$V$8:$AI$278,,MATCH(O$53,'P&L'!$V$6:$AI$6,0)),'P&L'!$D$8:$D$278,$C92)/$A$1 -> 0 | Q92: =SUMIFS('P&L'!P$8:P$278,'P&L'!$D$8:$D$278,$C92)/$A$1 -> 0 | R92: =SUMIFS('P&L'!Q$8:Q$278,'P&L'!$D$8:$D$278,$C92)/$A$1 -> 0
... C98: =IF(ISBLANK('Benchmark Index'!S51),"--",'Benchmark Index'!S51) -> Finance | D98: =SUMIFS(INDEX('P&L'!$V$8:$AI$278,,MATCH(D$53,'P&L'!$V$6:$AI$6,0)),'P&L'!$D$8:$D$278,$C98)/$A$1 -> 0 | E98: =SUMIFS(INDEX('P&L'!$V$8:$AI$278,,MATCH(E$53,'P&L'!$V$6:$AI$6,0)),'P&L'!$D$8:$D$278,$C98)/$A$1 -> 0 | F98: =SUMIFS(INDEX('P&L'!$V$8:$AI$278,,MATCH(F$53,'P&L'!$V$6:$AI$6,0)),'P&L'!$D$8:$D$278,$C98)/$A$1 -> 0 | G98: =SUMIFS(INDEX('P&L'!$V$8:$AI$278,,MATCH(G$53,'P&L'!$V$6:$AI$6,0)),'P&L'!$D$8:$D$278,$C98)/$A$1 -> 0 | H98: =SUMIFS(INDEX('P&L'!$V$8:$AI$278,,MATCH(H$53,'P&L'!$V$6:$AI$6,0)),'P&L'!$D$8:$D$278,$C98)/$A$1 -> 0 | I98: =SUMIFS(INDEX('P&L'!$V$8:$AI$278,,MATCH(I$53,'P&L'!$V$6:$AI$6,0)),'P&L'!$D$8:$D$278,$C98)/$A$1 -> 0 | J98: =SUMIFS(INDEX('P&L'!$V$8:$AI$278,,MATCH(J$53,'P&L'!$V$6:$AI$6,0)),'P&L'!$D$8:$D$278,$C98)/$A$1 -> 0 | K98: =SUMIFS(INDEX('P&L'!$V$8:$AI$278,,MATCH(K$53,'P&L'!$V$6:$AI$6,0)),'P&L'!$D$8:$D$278,$C98)/$A$1 -> 0 | ... O98: =SUMIFS(INDEX('P&L'!$V$8:$AI$278,,MATCH(O$53,'P&L'!$V$6:$AI$6,0)),'P&L'!$D$8:$D$278,$C98)/$A$1 -> 0 | Q98: =SUMIFS('P&L'!P$8:P$278,'P&L'!$D$8:$D$278,$C98)/$A$1 -> 0 | R98: =SUMIFS('P&L'!Q$8:Q$278,'P&L'!$D$8:$D$278,$C98)/$A$1 -> 0
C99: =IF(ISBLANK('Benchmark Index'!S53),"--",'Benchmark Index'!S53) -> Bonus | D99: =SUMIFS(INDEX('P&L'!$V$8:$AI$278,,MATCH(D$53,'P&L'!$V$6:$AI$6,0)),'P&L'!$D$8:$D$278,$C99)/$A$1 -> 0 | E99: =SUMIFS(INDEX('P&L'!$V$8:$AI$278,,MATCH(E$53,'P&L'!$V$6:$AI$6,0)),'P&L'!$D$8:$D$278,$C99)/$A$1 -> 0 | F99: =SUMIFS(INDEX('P&L'!$V$8:$AI$278,,MATCH(F$53,'P&L'!$V$6:$AI$6,0)),'P&L'!$D$8:$D$278,$C99)/$A$1 -> 0 | G99: =SUMIFS(INDEX('P&L'!$V$8:$AI$278,,MATCH(G$53,'P&L'!$V$6:$AI$6,0)),'P&L'!$D$8:$D$278,$C99)/$A$1 -> 0 | H99: =SUMIFS(INDEX('P&L'!$V$8:$AI$278,,MATCH(H$53,'P&L'!$V$6:$AI$6,0)),'P&L'!$D$8:$D$278,$C99)/$A$1 -> 0 | I99: =SUMIFS(INDEX('P&L'!$V$8:$AI$278,,MATCH(I$53,'P&L'!$V$6:$AI$6,0)),'P&L'!$D$8:$D$278,$C99)/$A$1 -> 0 | J99: =SUMIFS(INDEX('P&L'!$V$8:$AI$278,,MATCH(J$53,'P&L'!$V$6:$AI$6,0)),'P&L'!$D$8:$D$278,$C99)/$A$1 -> 0 | K99: =SUMIFS(INDEX('P&L'!$V$8:$AI$278,,MATCH(K$53,'P&L'!$V$6:$AI$6,0)),'P&L'!$D$8:$D$278,$C99)/$A$1 -> 0 | ... O99: =SUMIFS(INDEX('P&L'!$V$8:$AI$278,,MATCH(O$53,'P&L'!$V$6:$AI$6,0)),'P&L'!$D$8:$D$278,$C99)/$A$1 -> 0 | Q99: =SUMIFS('P&L'!P$8:P$278,'P&L'!$D$8:$D$278,$C99)/$A$1 -> 0 | R99: =SUMIFS('P&L'!Q$8:Q$278,'P&L'!$D$8:$D$278,$C99)/$A$1 -> 0
C100: =IF(ISBLANK('Benchmark Index'!S54),"--",'Benchmark Index'!S54) -> Signing bonus | D100: =SUMIFS(INDEX('P&L'!$V$8:$AI$278,,MATCH(D$53,'P&L'!$V$6:$AI$6,0)),'P&L'!$D$8:$D$278,$C100)/$A$1 -> 0 | E100: =SUMIFS(INDEX('P&L'!$V$8:$AI$278,,MATCH(E$53,'P&L'!$V$6:$AI$6,0)),'P&L'!$D$8:$D$278,$C100)/$A$1 -> 0 | F100: =SUMIFS(INDEX('P&L'!$V$8:$AI$278,,MATCH(F$53,'P&L'!$V$6:$AI$6,0)),'P&L'!$D$8:$D$278,$C100)/$A$1 -> 0 | G100: =SUMIFS(INDEX('P&L'!$V$8:$AI$278,,MATCH(G$53,'P&L'!$V$6:$AI$6,0)),'P&L'!$D$8:$D$278,$C100)/$A$1 -> 0 | H100: =SUMIFS(INDEX('P&L'!$V$8:$AI$278,,MATCH(H$53,'P&L'!$V$6:$AI$6,0)),'P&L'!$D$8:$D$278,$C100)/$A$1 -> 0 | I100: =SUMIFS(INDEX('P&L'!$V$8:$AI$278,,MATCH(I$53,'P&L'!$V$6:$AI$6,0)),'P&L'!$D$8:$D$278,$C100)/$A$1 -> 0 | J100: =SUMIFS(INDEX('P&L'!$V$8:$AI$278,,MATCH(J$53,'P&L'!$V$6:$AI$6,0)),'P&L'!$D$8:$D$278,$C100)/$A$1 -> 0 | K100: =SUMIFS(INDEX('P&L'!$V$8:$AI$278,,MATCH(K$53,'P&L'!$V$6:$AI$6,0)),'P&L'!$D$8:$D$278,$C100)/$A$1 -> 0 | ... O100: =SUMIFS(INDEX('P&L'!$V$8:$AI$278,,MATCH(O$53,'P&L'!$V$6:$AI$6,0)),'P&L'!$D$8:$D$278,$C100)/$A$1 -> 15800.67 | Q100: =SUMIFS('P&L'!P$8:P$278,'P&L'!$D$8:$D$278,$C100)/$A$1 -> 15800.67 | R100: =SUMIFS('P&L'!Q$8:Q$278,'P&L'!$D$8:$D$278,$C100)/$A$1 -> 0
C101: =IF(ISBLANK('Benchmark Index'!S55),"--",'Benchmark Index'!S55) -> -- | D101: =SUMIFS(INDEX('P&L'!$V$8:$AI$278,,MATCH(D$53,'P&L'!$V$6:$AI$6,0)),'P&L'!$D$8:$D$278,$C101)/$A$1 -> 0 | E101: =SUMIFS(INDEX('P&L'!$V$8:$AI$278,,MATCH(E$53,'P&L'!$V$6:$AI$6,0)),'P&L'!$D$8:$D$278,$C101)/$A$1 -> 0 | F101: =SUMIFS(INDEX('P&L'!$V$8:$AI$278,,MATCH(F$53,'P&L'!$V$6:$AI$6,0)),'P&L'!$D$8:$D$278,$C101)/$A$1 -> 0 | G101: =SUMIFS(INDEX('P&L'!$V$8:$AI$278,,MATCH(G$53,'P&L'!$V$6:$AI$6,0)),'P&L'!$D$8:$D$278,$C101)/$A$1 -> 0 | H101: =SUMIFS(INDEX('P&L'!$V$8:$AI$278,,MATCH(H$53,'P&L'!$V$6:$AI$6,0)),'P&L'!$D$8:$D$278,$C101)/$A$1 -> 0 | I101: =SUMIFS(INDEX('P&L'!$V$8:$AI$278,,MATCH(I$53,'P&L'!$V$6:$AI$6,0)),'P&L'!$D$8:$D$278,$C101)/$A$1 -> 0 | J101: =SUMIFS(INDEX('P&L'!$V$8:$AI$278,,MATCH(J$53,'P&L'!$V$6:$AI$6,0)),'P&L'!$D$8:$D$278,$C101)/$A$1 -> 0 | K101: =SUMIFS(INDEX('P&L'!$V$8:$AI$278,,MATCH(K$53,'P&L'!$V$6:$AI$6,0)),'P&L'!$D$8:$D$278,$C101)/$A$1 -> 0 | ... O101: =SUMIFS(INDEX('P&L'!$V$8:$AI$278,,MATCH(O$53,'P&L'!$V$6:$AI$6,0)),'P&L'!$D$8:$D$278,$C101)/$A$1 -> 0 | Q101: =SUMIFS('P&L'!P$8:P$278,'P&L'!$D$8:$D$278,$C101)/$A$1 -> 0 | R101: =SUMIFS('P&L'!Q$8:Q$278,'P&L'!$D$8:$D$278,$C101)/$A$1 -> 0
C102: =IF(ISBLANK('Benchmark Index'!S56),"--",'Benchmark Index'!S56) -> -- | D102: =SUMIFS(INDEX('P&L'!$V$8:$AI$278,,MATCH(D$53,'P&L'!$V$6:$AI$6,0)),'P&L'!$D$8:$D$278,$C102)/$A$1 -> 0 | E102: =SUMIFS(INDEX('P&L'!$V$8:$AI$278,,MATCH(E$53,'P&L'!$V$6:$AI$6,0)),'P&L'!$D$8:$D$278,$C102)/$A$1 -> 0 | F102: =SUMIFS(INDEX('P&L'!$V$8:$AI$278,,MATCH(F$53,'P&L'!$V$6:$AI$6,0)),'P&L'!$D$8:$D$278,$C102)/$A$1 -> 0 | G102: =SUMIFS(INDEX('P&L'!$V$8:$AI$278,,MATCH(G$53,'P&L'!$V$6:$AI$6,0)),'P&L'!$D$8:$D$278,$C102)/$A$1 -> 0 | H102: =SUMIFS(INDEX('P&L'!$V$8:$AI$278,,MATCH(H$53,'P&L'!$V$6:$AI$6,0)),'P&L'!$D$8:$D$278,$C102)/$A$1 -> 0 | I102: =SUMIFS(INDEX('P&L'!$V$8:$AI$278,,MATCH(I$53,'P&L'!$V$6:$AI$6,0)),'P&L'!$D$8:$D$278,$C102)/$A$1 -> 0 | J102: =SUMIFS(INDEX('P&L'!$V$8:$AI$278,,MATCH(J$53,'P&L'!$V$6:$AI$6,0)),'P&L'!$D$8:$D$278,$C102)/$A$1 -> 0 | K102: =SUMIFS(INDEX('P&L'!$V$8:$AI$278,,MATCH(K$53,'P&L'!$V$6:$AI$6,0)),'P&L'!$D$8:$D$278,$C102)/$A$1 -> 0 | ... O102: =SUMIFS(INDEX('P&L'!$V$8:$AI$278,,MATCH(O$53,'P&L'!$V$6:$AI$6,0)),'P&L'!$D$8:$D$278,$C102)/$A$1 -> 0 | Q102: =SUMIFS('P&L'!P$8:P$278,'P&L'!$D$8:$D$278,$C102)/$A$1 -> 0 | R102: =SUMIFS('P&L'!Q$8:Q$278,'P&L'!$D$8:$D$278,$C102)/$A$1 -> 0
C103: Total Opex | F103: =SUM(F55:F102) -> 0 | G103: =SUM(G55:G102) -> 0 | H103: =SUM(H55:H102) -> 0 | I103: =SUM(I55:I102) -> 0 | J103: =SUM(J55:J102) -> 0 | K103: =SUM(K55:K102) -> 0 | L103: =SUM(L55:L102) -> 0 | M103: =SUM(M55:M102) -> 0 | ... O103: =SUM(O55:O102) -> 1932607.5 | Q103: =SUM(Q55:Q102) -> 1932607.5 | R103: =SUM(R55:R102) -> 2064205.6
D104: =IF(ROUND(D103*$A$1,0)=ROUND(SUM(D14,D25)*$A$1,0),"","Error") | E104: =IF(ROUND(E103*$A$1,0)=ROUND(SUM(E14,E25)*$A$1,0),"","Error") | F104: =IF(ROUND(F103*$A$1,0)=ROUND(SUM(F14,F25)*$A$1,0),"","Error") | G104: =IF(ROUND(G103*$A$1,0)=ROUND(SUM(G14,G25)*$A$1,0),"","Error") | H104: =IF(ROUND(H103*$A$1,0)=ROUND(SUM(H14,H25)*$A$1,0),"","Error") | I104: =IF(ROUND(I103*$A$1,0)=ROUND(SUM(I14,I25)*$A$1,0),"","Error") | J104: =IF(ROUND(J103*$A$1,0)=ROUND(SUM(J14,J25)*$A$1,0),"","Error") | K104: =IF(ROUND(K103*$A$1,0)=ROUND(SUM(K14,K25)*$A$1,0),"","Error") | ... O104: =IF(ROUND(O103*$A$1,0)=ROUND(SUM(O14,O25)*$A$1,0),"","Error") | Q104: =IF(ROUND(Q103*$A$1,0)=ROUND(SUM(Q14,Q25)*$A$1,0),"","Error") | R104: =IF(ROUND(R103*$A$1,0)=ROUND(SUM(R14,R25)*$A$1,0),"","Error")

Sheet Charts
B2: KPIs:
B22: 43466 | C22: 43466 | D22: 43497 | E22: 43525 | F22: 43556 | G22: 43586 | H22: 43617 | I22: 43647 | J22: 43678 | K22: 43709 | L22: 43739 | M22: 43770 | N22: 43800
B23: # of customers - Actual | C23: ='Financial highlights'!D8 -> 0 | D23: ='Financial highlights'!E8 -> 0 | E23: ='Financial highlights'!F8 -> 0 | F23: ='Financial highlights'!G8 -> 0 | G23: ='Financial highlights'!H8 -> 0 | H23: ='Financial highlights'!I8 -> 0 | I23: ='Financial highlights'!J8 -> 0 | J23: ='Financial highlights'!K8 -> 0 | ... N23: ='Financial highlights'!O8 -> 0
B24: # of customers - Budget
B26: MRR - Actual | C26: ='Financial highlights'!D9 -> 0
B27: MRR - Budget
B29: ARR - Actual | C29: =C26*12 -> 0
B30: ARR - Budget
B34: Financial Highlights:
B56: 43466 | C56: 43466 | D56: 43497 | E56: 43525 | F56: 43556 | G56: 43586 | H56: 43617 | I56: 43647 | J56: 43678 | K56: 43709 | L56: 43739 | M56: 43770 | N56: 43800
B57: Opex - Actual | C57: ='Financial highlights'!D25 -> 0 | D57: ='Financial highlights'!E25 -> 0 | E57: ='Financial highlights'!F25 -> 0 | F57: ='Financial highlights'!G25 -> 0 | G57: ='Financial highlights'!H25 -> 0 | H57: ='Financial highlights'!I25 -> 0 | I57: ='Financial highlights'!J25 -> 0 | J57: ='Financial highlights'!K25 -> 0 | ... N57: ='Financial highlights'!O25 -> 1932607.5
B58: Opex - Budget
B60: EBITDA - Actual | C60: ='Financial highlights'!D27 -> 0 | D60: ='Financial highlights'!E27 -> 0 | E60: ='Financial highlights'!F27 -> 0 | F60: ='Financial highlights'!G27 -> 0 | G60: ='Financial highlights'!H27 -> 0 | H60: ='Financial highlights'!I27 -> 0 | I60: ='Financial highlights'!J27 -> 0 | J60: ='Financial highlights'!K27 -> 0 | ... N60: ='Financial highlights'!O27 -> -1932607.5
B61: EBITDA - Budget
B63: Cost per emp. - Actual (K$) | C63: =IFERROR(('Financial highlights'!D14+'Financial highlights'!D25)/'Financial highlights'!D50,0)/1000 -> 0 | D63: =IFERROR(('Financial highlights'!E14+'Financial highlights'!E25)/'Financial highlights'!E50,0)/1000 -> 0 | E63: =IFERROR(('Financial highlights'!F14+'Financial highlights'!F25)/'Financial highlights'!F50,0)/1000 -> 0 | F63: =IFERROR(('Financial highlights'!G14+'Financial highlights'!G25)/'Financial highlights'!G50,0)/1000 -> 0 | G63: =IFERROR(('Financial highlights'!H14+'Financial highlights'!H25)/'Financial highlights'!H50,0)/1000 -> 0 | H63: =IFERROR(('Financial highlights'!I14+'Financial highlights'!I25)/'Financial highlights'!I50,0)/1000 -> 0 | I63: =IFERROR(('Financial highlights'!J14+'Financial highlights'!J25)/'Financial highlights'!J50,0)/1000 -> 0 | J63: =IFERROR(('Financial highlights'!K14+'Financial highlights'!K25)/'Financial highlights'!K50,0)/1000 -> 0 | ... N63: =IFERROR(('Financial highlights'!O14+'Financial highlights'!O25)/'Financial highlights'!O50,0)/1000 -> 113.6828
B65: Cash End Of Period - Actual | C65: ='Financial highlights'!D37 -> 0 | D65: ='Financial highlights'!E37 -> 0 | E65: ='Financial highlights'!F37 -> 1663501.8 | F65: ='Financial highlights'!G37 -> 0 | G65: ='Financial highlights'!H37 -> 0 | H65: ='Financial highlights'!I37 -> 1663501.8 | I65: ='Financial highlights'!J37 -> 0 | J65: ='Financial highlights'!K37 -> 0 | ... N65: ='Financial highlights'!O37 -> 8623723.5
B66: Cash End Of Period - Budget
B88: * The Opex by type % is calculated as a percentage of the total Opex amount
B89: HC:

Sheet External Reporting Scheme
B1: ='P&L'!E2 -> Pocket Pie Studios Ltd.
B2: CONSOLIDSTED FINANCIAL STATEMENT
B3: AS OF | C3: =month_of_report -> 44531
B7: CONSOLIDATED STATEMENTS OF OPERATIONS
G8: =C3 -> 44531 | I8: ="Q"&ROUNDUP(MONTH(G8)/3,0)&"-"&RIGHT(YEAR(G8),2) -> Q4-21 | K8: YTD
G9: UNAUDITED | I9: UNAUDITED | K9: UNAUDITED
G10: ACTUAL | I10: ACTUAL | K10: ACTUAL
B11: Gross Revenues | G11: ='P&L'!H13 -> 0 | I11: ='P&L'!L13 -> 0 | K11: ='P&L'!P13 -> 0
B12: Cost of goods | G12: ='P&L'!H26 -> 0 | I12: ='P&L'!L26 -> 0 | K12: ='P&L'!P26 -> 0
B13: Net Revenues | G13: =G11-G12 -> 0 | I13: =I11-I12 -> 0 | K13: =K11-K12 -> 0
B15: Operating expenses:
B16: R&D | G16: ='P&L'!H44 -> 669810.02 | I16: ='P&L'!L44 -> 669810.02 | K16: ='P&L'!P44 -> 669810.02
B17: Product | G17: ='P&L'!H61 -> 326761.88 | I17: ='P&L'!L61 -> 326761.88 | K17: ='P&L'!P61 -> 326761.88
B18: Art | G18: ='P&L'!H81 -> 664947.33 | I18: ='P&L'!L81 -> 664947.33 | K18: ='P&L'!P81 -> 664947.33
B19: Sales | G19: ='P&L'!Z99 -> 0 | I19: ='P&L'!L99 -> 0 | K19: ='P&L'!P99 -> 0
B20: Marketing | G20: ='P&L'!H121 -> 6018.94 | I20: ='P&L'!L121 -> 6018.94 | K20: ='P&L'!P121 -> 6018.94
B21: G&A | G21: ='P&L'!H152 -> 265069.35 | I21: ='P&L'!L152 -> 265069.35 | K21: ='P&L'!P152 -> 265069.35
B22: Total OPEX | G22: =SUM(G16:G21) -> 1932607.5 | I22: ='P&L'!L249 -> 1932607.5 | K22: =SUM(K16:K21) -> 1932607.5
B24: Net Loss before finance and Depreciation | G24: =G13-G22 -> -1932607.5 | I24: ='P&L'!L251 -> -1932607.5 | K24: =K13-K22 -> -1932607.5
B25: Financial expenses, net | G25: =-'P&L'!H266 -> -109458.15 | I25: =-'P&L'!L266 -> -109458.15 | K25: =-'P&L'!P266 -> -109458.15
B26: Taxation provision | G26: =-'P&L'!H268 -> 0 | K26: =-'P&L'!P268 -> 0
B27: Amortization of other intangibles
B28: Depreciation of fixed assets | G28: ='P&L'!H254 -> 0 | I28: ='P&L'!L258 -> 0 | K28: ='P&L'!P258 -> 0
B30: Net loss | G30: =G24-G25-G28-G26-G27 -> -1823149.4 | I30: =I24-I25-I28-I26-I27 -> -1823149.4 | K30: =K24-K25-K28-K26-K27 -> -1823149.4
B34: =B1 -> Pocket Pie Studios Ltd.
B35: CONSOLIDATED BALANCE SHEETS
G38: ="As of"&" "&TEXT(G8,"[$-409]MMMM - YYYY") -> As of December - 2021
G39: UNAUDITED
B40: ASSETS | G40: ACTUAL
B42: CURRENT ASSETS:
C43: Cash and cash equivalents | G43: =SUM(BS!J13:J14) -> 6785753.3
C44: Accounts receivables | G44: =BS!J15 -> 0
C45: Prepaid expenses and other current assets | G45: =SUM(BS!J16:J18) -> 36990.88
C47: Total current assets | G47: =SUM(G43:G46) -> 6822744.2
B49: Long-Term deposits | G49: =BS!J34 -> 0
B51: PROPERTY AND EQUIPMENT, NET | G51: =BS!J26 -> 83603.31
C54: Total assets | G54: =SUM(G51,G49,G47) -> 6906347.5
B57: LIABILITIES AND STOCKHOLDERS' EQUITY
B59: CURRENT LIABILITIES:
C61: Trade payables and Accrued expenses | G61: =SUM(BS!J42:J43) -> 11276.58
C62: Employees and payroll accruals and insistution | G62: =SUM(BS!J44:J46) -> 287162.25
C63: Other Current terms liabilities | G63: =BS!J50-G61-G62 -> 0
C65: Total current liabilities | G65: =SUM(G61:G63) -> 298438.83
B68: LONG TERM LIABILITY | G68: =BS!J55 -> 0
B70: SHAREHOLDERS' EQUITY
C71: Total Shareholders' equity | G71: =BS!J64 -> 6607908.7
C74: Total liabilities and Shareholders' equity | G74: =G71+G65+G68 -> 6906347.5
G76: =G54-G74 -> 0
B78: =B1 -> Pocket Pie Studios Ltd.
B79: CONSOLIDATED STATEMENTS OF CASH FLOWS
G81: =C3 -> 44531 | I81: =I8 -> Q4-21 | K81: YTD
G82: UNAUDITED | I82: =I9 -> UNAUDITED | K82: UNAUDITED
G83: ACTUAL | I83: =I10 -> ACTUAL | K83: ACTUAL
C84: Cash flows from operating activities:
C85: Net loss | G85: =CF!K11 -> -1932607.5 | I85: =CF!O11 -> -1932607.5 | K85: =CF!S11 -> -1932607.5
C87: Working Capital Movements
C88: Account Receivable | G88: =CF!K14 -> 0 | I88: =CF!O14 -> 0 | K88: =CF!S14 -> 0
C89: Accounts payable & accrued expenses | G89: =CF!K16 -> 11276.58 | I89: =CF!O16 -> 11276.58 | K89: =CF!S16 -> 11276.58
C90: Employee payables and accruals | G90: =SUM(CF!K17:K18) -> 287162.25 | I90: =SUM(CF!M17:O18) -> 571818.5 | K90: =SUM(CF!S17:S18) -> 287162.25
C91: Other working capital items | G91: =CF!K19 -> -36990.88 | I91: =CF!O19 -> -36990.88 | K91: =CF!S19 -> -36990.88
C92: Other current liabilities | G92: =CF!K22 -> 0 | I92: =CF!O22 -> 0 | K92: =CF!S22 -> 0
C93: Interest received / (paid) | G93: =CF!K21 -> 110473.78 | I93: =CF!O21 -> 110473.78 | K93: =CF!S21 -> 110473.78
C94: Total Working Capital Movements | G94: =SUM(G88:G93) -> 371921.73 | I94: =SUM(I88:I93) -> 656577.98 | K94: =SUM(K88:K93) -> 371921.73
C96: Net Operating Cash Flow | G96: =CF!K27 -> -1560685.8 | I96: =CF!O27 -> -1560685.8 | K96: =CF!S27 -> -1560685.8
C98: Total Capital Expenditure | G98: =CF!K47 -> -106525.99 | I98: =CF!O47 -> -106525.99 | K98: =CF!S47 -> -106525.99
C100: Total Cash Outflow before financing & Tax | G100: =G96+G98 -> -1667211.8 | I100: =I96+I98 -> -1667211.8 | K100: =K96+K98 -> -1667211.8
C102: Total Financing & Tax | G102: =CF!K57+CF!K49 -> 8627433.5 | I102: =CF!O57+CF!O49 -> 8627433.5 | K102: =CF!S57+CF!S49 -> 8627433.5
C104: Net Cash Inflow / (Outflow) | G104: =G100+G102 -> 6960221.7 | I104: =I100+I102 -> 6960221.7 | K104: =K100+K102 -> 6960221.7
C106: Cash at Beginning of Month/Year | G106: =CF!K61 -> 1663501.8 | I106: =CF!O61 -> 1663501.8 | K106: =CF!S61 -> 1663501.8
C108: Net Cash at End of Month | G108: =G104+G106 -> 8623723.5 | I108: =I104+I106 -> 8623723.5 | K108: =K104+K106 -> 8623723.5
G110: =G108-G43 -> 1837970.1 | I110: =I108-G43 -> 1837970.1 | K110: =K108-G43 -> 1837970.1

Sheet P&L
E2: Pocket Pie Studios Ltd. | H2: end month: | I2: 44531 | L2: # of Errors: | M2: =COUNTIF(H250:AN250,"error")+COUNTIF(H281:AI281,"error") -> 0 | CT2: # of Errors: | CU2: =COUNTIF(CW250:ER250,"error")+COUNTIF(CW280:ER280,"error") -> 0
E3: Profit & Loss - US$ | H3: start month: | I3: 44470
Z5: Q1 2021 | AC5: Q2 2021 | AF5: Q3 2021 | AI5: Q4 2021
H6: =month_of_report -> 44531 | L6: ="Q"&ROUNDUP(MONTH(H6)/3,0)&"-"&YEAR(H6)&" QTD" -> Q4-2021 QTD | P6: YTD | V6: 2020Total | W6: 44166 | X6: 44197 | Y6: 44228 | Z6: 44256 | AA6: 44287 | AB6: 44317 | AC6: 44348 | AD6: 44378 | AE6: 44409 | AF6: 44440 | AG6: 44470 | AH6: 44501 | AI6: 44531 | AM6: YTD | AX6: 2020 Total | AY6: 44166 | AZ6: 44197 | BA6: 44228 | BB6: 44256 | BC6: Q1-21 | BD6: 44287 | BE6: 44317 | BF6: 44348 | BG6: Q2-21 | BH6: 44378 | BI6: 44409 | BJ6: 44440 | BK6: Q3-21 | BL6: 44470 | BM6: 44501 | BN6: 44531 | BO6: Q4-21 | BP6: Total 2021 | BS6: 44197 | BT6: 44228 | BU6: Feb-21 - Accumulated | BV6: 44256 | BW6: Mar-21 - Accumulated | BX6: 44287 | BY6: Apr-21 - Accumulated | BZ6: 44317 | CA6: May-21 - Accumulated | CB6: 44348 | CC6: Jun-21 - Accumulated | CD6: 44378 | CE6: Jul-21 - Accumulated | CF6: 44409 | CG6: Aug-21 - Accumulated | CH6: 44440 | CI6: Sep-21 - Accumulated | CJ6: 44470 | CK6: Oct-21 - Accumulated | CL6: 44501 | CM6: Nov-21 - Accumulated | CN6: 44531 | CO6: Dec-21 - Accumulated | CW6: 44197 | CX6: 44197 | CY6: 44197 | CZ6: 44228 | DA6: 44228 | DB6: 44228 | DC6: 44256 | DD6: 44256 | DE6: 44256 | DF6: Q1-21 | DG6: Q1-21 | DH6: Q1-21 | DI6: 44287 | DJ6: 44287 | DK6: 44287 | DL6: 44317 | DM6: 44317 | DN6: 44317 | DO6: 44348 | DP6: 44348 | DQ6: 44348 | DR6: Q2-21 | DS6: Q2-21 | DT6: Q2-21 | DU6: 44378 | DV6: 44378 | DW6: 44378 | DX6: 44409 | DY6: 44409 | DZ6: 44409 | EA6: 44440 | EB6: 44440 | EC6: 44440 | ED6: Q3-21 | EE6: Q3-21 | EF6: Q3-21 | EG6: 44470 | EH6: 44470 | EI6: 44470 | EJ6: 44501 | EK6: 44501 | EL6: 44501 | EM6: 44531 | EN6: 44531 | EO6: 44531 | EP6: Q4-21 | EQ6: Q4-21 | ER6: Q4-21
C7: Index | D7: Opex type | F7: Description | H7: Actual | I7: Budget | J7: Variance | L7: Actual | M7: Budget | N7: Variance | P7: Actual | Q7: Budget | R7: Variance | V7: Actual | W7: Actual | X7: Actual | Y7: Actual | Z7: Actual | AA7: Actual | AB7: Actual | AC7: Actual | AD7: Actual | AE7: Actual | AF7: Actual | AG7: Actual | AH7: Actual | AI7: Actual | AM7: Actual USD | AN7: Actual NIS | AR7: =IF(B7="","",B7) | AS7: =IF(C7="","",C7) -> Index | AT7: =IF(D7="","",D7) -> Opex type | AU7: =IF(E7="","",E7) | AV7: =IF(F7="","",F7) -> Description | AX7: Budget | AY7: Budget | AZ7: Budget | BA7: Budget | BB7: Budget | BC7: Budget | BD7: Budget | BE7: Budget | BF7: Budget | BG7: Budget | BH7: Budget | BI7: Budget | BJ7: Budget | BK7: Budget | BL7: Budget | BM7: Budget | BN7: Budget | BO7: Budget | BP7: Budget | CQ7: =AR7 | CR7: =AS7 -> Index | CS7: =AT7 -> Opex type | CT7: =AU7 | CU7: =AV7 -> Description | CW7: INC | CX7: LTD | CY7: Consolidated | CZ7: INC | DA7: LTD | DB7: Consolidated | DC7: INC | DD7: LTD | DE7: Consolidated | DF7: INC | DG7: LTD | DH7: Consolidated | DI7: INC | DJ7: LTD | DK7: Consolidated | DL7: INC | DM7: LTD | DN7: Consolidated | DO7: INC | DP7: LTD | DQ7: Consolidated | DR7: INC | DS7: LTD | DT7: Consolidated | DU7: INC | DV7: LTD | DW7: Consolidated | DX7: INC | DY7: LTD | DZ7: Consolidated | EA7: INC | EB7: LTD | EC7: Consolidated | ED7: INC | EE7: LTD | EF7: Consolidated | EG7: INC | EH7: LTD | EI7: Consolidated | EJ7: INC | EK7: LTD | EL7: Consolidated | EM7: INC | EN7: LTD | EO7: Consolidated | EP7: INC | EQ7: LTD | ER7: Consolidated
D8: =IF($C8<=30,"",INDEX(Opex_expense_Type,MATCH($C8,Index_card_code,0))) | F8: =IFERROR(INDEX(Index_Card_name,MATCH($C8,Index_card_code,0)),"") | H8: =INDEX($X8:$AI8,,MATCH($H$6,$X$6:$AI$6,0)) -> 0 | I8: =SUMIF(Cards_selection_BPL,$C8,INDIRECT(Index!$P$16)) -> 0 | J8: =+H8-I8 -> 0 | L8: =IF(LEFT($L$6,2)="Q1",SUMIFS($X8:$Z8,$X$6:$Z$6,"<="&month_of_report),IF(LEFT($L$6,2)="Q2",SUMIFS($AA8:$AC8,$AA$6:$AC$6,"<="&month_of_report),IF(LEFT($L$6,2)="Q3",SUMIFS($AD8:$AF8,$AD$6:$AF$6,"<="&month_of_report),IF(LEFT($L$6,2)="Q4",SUMIFS($AG8:$AI8,$AG$6:$AI$6,"<="&month_of_report),0)))) -> 0 | M8: =IF(LEFT($L$6,2)="Q1",SUMIF(Cards_selection_BPL,$C8,INDIRECT(Index!$Q$16)),IF(LEFT($L$6,2)="Q2",SUMIF(Cards_selection_BPL,$C8,INDIRECT(Index!$Q$16))-SUMIF(Cards_selection_BPL,$C8,Balance_bplm_03),IF(LEFT($L$6,2)="Q3",SUMIF(Cards_selection_BPL,$C8,INDIRECT(Index!$Q$16))-SUMIF(Cards_selection_BPL,$C8,Balance_bplm_06),IF(LEFT($L$6,2)="Q4",SUMIF(Cards_selection_BPL,$C8,INDIRECT(Index!$Q$16))-SUMIF(Cards_selection_BPL,$C8,Balance_bplm_09),0)))) -> 0 | N8: =+L8-M8 -> 0 | P8: =SUMIFS($X8:$AI8,$X$6:$AI$6,"<="&month_of_report) -> 0 | Q8: =SUMIF(Cards_selection_BPL,$C8,INDIRECT(Index!$Q$16)) -> 0 | R8: =+P8-Q8 -> 0 | X8: =-IF(X$6<=month_of_report,(SUMIF(Cards_Selection,$C8,TB_Balance_01)),0) -> 0 | Y8: =-IF(Y$6<=month_of_report,(SUMIF(Cards_Selection,$C8,TB_Balance_02)-SUMIF(Cards_Selection,$C8,TB_Balance_01)),0) -> 0 | Z8: =-IF(Z$6<=month_of_report,(SUMIF(Cards_Selection,$C8,TB_Balance_03)-SUMIF(Cards_Selection,$C8,TB_Balance_02)),0) -> 0 | AA8: =-IF(AA$6<=month_of_report,(SUMIF(Cards_Selection,$C8,TB_Balance_04)-SUMIF(Cards_Selection,$C8,TB_Balance_03)),0) -> 0 | AB8: =-IF(AB$6<=month_of_report,(SUMIF(Cards_Selection,$C8,TB_Balance_05)-SUMIF(Cards_Selection,$C8,TB_Balance_04)),0) -> 0 | AC8: =-IF(AC$6<=month_of_report,(SUMIF(Cards_Selection,$C8,TB_Balance_06)-SUMIF(Cards_Selection,$C8,TB_Balance_05)),0) -> 0 | AD8: =-IF(AD$6<=month_of_report,(SUMIF(Cards_Selection,$C8,TB_Balance_07)-SUMIF(Cards_Selection,$C8,TB_Balance_06)),0) -> 0 | AE8: =-IF(AE$6<=month_of_report,(SUMIF(Cards_Selection,$C8,TB_Balance_08)-SUMIF(Cards_Selection,$C8,TB_Balance_07)),0) -> 0 | AF8: =-IF(AF$6<=month_of_report,(SUMIF(Cards_Selection,$C8,TB_Balance_09)-SUMIF(Cards_Selection,$C8,TB_Balance_08)),0) -> 0 | AG8: =-IF(AG$6<=month_of_report,(SUMIF(Cards_Selection,$C8,TB_Balance_10)-SUMIF(Cards_Selection,$C8,TB_Balance_09)),0) -> 0 | AH8: =-IF(AH$6<=month_of_report,(SUMIF(Cards_Selection,$C8,TB_Balance_11)-SUMIF(Cards_Selection,$C8,TB_Balance_10)),0) -> 0 | AI8: =-IF(AI$6<=month_of_report,(SUMIF(Cards_Selection,$C8,TB_Balance_12)-SUMIF(Cards_Selection,$C8,TB_Balance_09)),0) -> 0 | AM8: =P8 -> 0 | AN8: =-IF(AN$6<=month_of_report,SUMIF(Cards_Selection,$C8,TB_Balance_12_Nis),0) -> 0 | AR8: =IF(B8="","",B8) | AS8: =IF(C8="","",C8) | AT8: =IFERROR(IF($AS8<=30,"",INDEX(Opex_expense_Type,MATCH($AS8,Index_card_code,0))),"") | AU8: =IF(E8="","",E8) | AV8: =IF(F8="","",F8) | BC8: =SUM(AZ8:BB8) -> 0 | BG8: =SUM(BD8:BF8) -> 0 | BK8: =SUM(BH8:BJ8) -> 0 | BO8: =SUM(BL8:BN8) -> 0 | BP8: =BO8+BK8+BG8+BC8 -> 0 | BS8: =INDEX($AZ8:$BN8,MATCH(BS$6,$AZ$6:$BN$6,0)) -> 0 | BT8: =INDEX($AZ8:$BN8,MATCH(BT$6,$AZ$6:$BN$6,0)) -> 0 | BU8: =SUM(BS8:BT8) -> 0 | BV8: =INDEX($AZ8:$BN8,MATCH(BV$6,$AZ$6:$BN$6,0)) -> 0 | BW8: =SUM(BU8:BV8) -> 0 | BX8: =INDEX($AZ8:$BN8,MATCH(BX$6,$AZ$6:$BN$6,0)) -> 0 | BY8: =SUM(BW8:BX8) -> 0 | BZ8: =INDEX($AZ8:$BN8,MATCH(BZ$6,$AZ$6:$BN$6,0)) -> 0 | CA8: =SUM(BY8:BZ8) -> 0 | CB8: =INDEX($AZ8:$BN8,MATCH(CB$6,$AZ$6:$BN$6,0)) -> 0 | CC8: =SUM(CA8:CB8) -> 0 | CD8: =INDEX($AZ8:$BN8,MATCH(CD$6,$AZ$6:$BN$6,0)) -> 0 | CE8: =SUM(CC8:CD8) -> 0 | CF8: =INDEX($AZ8:$BN8,MATCH(CF$6,$AZ$6:$BN$6,0)) -> 0 | CG8: =SUM(CE8:CF8) -> 0 | CH8: =INDEX($AZ8:$BN8,MATCH(CH$6,$AZ$6:$BN$6,0)) -> 0 | CI8: =SUM(CG8:CH8) -> 0 | CJ8: =INDEX($AZ8:$BN8,MATCH(CJ$6,$AZ$6:$BN$6,0)) -> 0 | CK8: =SUM(CI8:CJ8) -> 0 | CL8: =INDEX($AZ8:$BN8,MATCH(CL$6,$AZ$6:$BN$6,0)) -> 0 | CM8: =SUM(CK8:CL8) -> 0 | CN8: =INDEX($AZ8:$BN8,MATCH(CN$6,$AZ$6:$BN$6,0)) -> 0 | CO8: =SUM(CM8:CN8) -> 0 | CQ8: =AR8 | CR8: =AS8 | CS8: =IFERROR(IF($CR8<=30,"",INDEX(Opex_expense_Type,MATCH($CR8,Index_card_code,0))),"") | CT8: =AU8 | CU8: =AV8 | CW8: =IF(CW$6>month_of_report,0,-SUMIFS(TB_Balance_01,TB_Entity,CW$7,Cards_Selection,$CR8)) -> 0 | CX8: =IF(CX$6>month_of_report,0,-SUMIFS(TB_Balance_01,TB_Entity,CX$7,Cards_Selection,$CR8)) -> 0 | CY8: =IF(CY$6<=month_of_report,(IFERROR(INDEX($X$8:$AI$277,MATCH($CR8,$C$8:$C$277,0),MATCH(CY$6,$X$6:$AI$6,0)),0)),0) -> 0 | CZ8: =IF(CZ$6>month_of_report,0,-(SUMIFS(TB_Balance_02,TB_Entity,CZ$7,Cards_Selection,$CR8)-SUMIFS(TB_Balance_01,TB_Entity,CZ$7,Cards_Selection,$CR8))) -> 0 | DA8: =IF(DA$6>month_of_report,0,-(SUMIFS(TB_Balance_02,TB_Entity,DA$7,Cards_Selection,$CR8)-SUMIFS(TB_Balance_01,TB_Entity,DA$7,Cards_Selection,$CR8))) -> 0 | DB8: =IF(DB$6<=month_of_report,(IFERROR(INDEX($X$8:$AI$277,MATCH($CR8,$C$8:$C$277,0),MATCH(DB$6,$X$6:$AI$6,0)),0)),0) -> 0 | DC8: =IF(DC$6>month_of_report,0,-(SUMIFS(TB_Balance_03,TB_Entity,DC$7,Cards_Selection,$CR8)-SUMIFS(TB_Balance_02,TB_Entity,DC$7,Cards_Selection,$CR8))) -> 0 | DD8: =IF(DD$6>month_of_report,0,-(SUMIFS(TB_Balance_03,TB_Entity,DD$7,Cards_Selection,$CR8)-SUMIFS(TB_Balance_02,TB_Entity,DD$7,Cards_Selection,$CR8))) -> 0 | DE8: =IF(DE$6<=month_of_report,(IFERROR(INDEX($X$8:$AI$277,MATCH($CR8,$C$8:$C$277,0),MATCH(DE$6,$X$6:$AI$6,0)),0)),0) -> 0 | DF8: =SUM(DC8,CZ8,CW8) -> 0 | DG8: =SUM(DD8,DA8,CX8) -> 0 | DH8: =SUM(DE8,DB8,CY8) -> 0 | DI8: =IF(DI$6>month_of_report,0,-(SUMIFS(TB_Balance_04,TB_Entity,DI$7,Cards_Selection,$CR8)-SUMIFS(TB_Balance_03,TB_Entity,DI$7,Cards_Selection,$CR8))) -> 0 | DJ8: =IF(DJ$6>month_of_report,0,-(SUMIFS(TB_Balance_04,TB_Entity,DJ$7,Cards_Selection,$CR8)-SUMIFS(TB_Balance_03,TB_Entity,DJ$7,Cards_Selection,$CR8))) -> 0 | DK8: =IF(DK$6<=month_of_report,(IFERROR(INDEX($X$8:$AI$277,MATCH($CR8,$C$8:$C$277,0),MATCH(DK$6,$X$6:$AI$6,0)),0)),0) -> 0 | DL8: =IF(DL$6>month_of_report,0,-(SUMIFS(TB_Balance_05,TB_Entity,DL$7,Cards_Selection,$CR8)-SUMIFS(TB_Balance_04,TB_Entity,DL$7,Cards_Selection,$CR8))) -> 0 | DM8: =IF(DM$6>month_of_report,0,-(SUMIFS(TB_Balance_05,TB_Entity,DM$7,Cards_Selection,$CR8)-SUMIFS(TB_Balance_04,TB_Entity,DM$7,Cards_Selection,$CR8))) -> 0 | DN8: =IF(DN$6<=month_of_report,(IFERROR(INDEX($X$8:$AI$277,MATCH($CR8,$C$8:$C$277,0),MATCH(DN$6,$X$6:$AI$6,0)),0)),0) -> 0 | DO8: =IF(DO$6>month_of_report,0,-(SUMIFS(TB_Balance_06,TB_Entity,DO$7,Cards_Selection,$CR8)-SUMIFS(TB_Balance_05,TB_Entity,DO$7,Cards_Selection,$CR8))) -> 0 | DP8: =IF(DP$6>month_of_report,0,-(SUMIFS(TB_Balance_06,TB_Entity,DP$7,Cards_Selection,$CR8)-SUMIFS(TB_Balance_05,TB_Entity,DP$7,Cards_Selection,$CR8))) -> 0 | DQ8: =IF(DQ$6<=month_of_report,(IFERROR(INDEX($X$8:$AI$277,MATCH($CR8,$C$8:$C$277,0),MATCH(DQ$6,$X$6:$AI$6,0)),0)),0) -> 0 | DR8: =SUM(DO8,DL8,DI8) -> 0 | DS8: =SUM(DP8,DM8,DJ8) -> 0 | DT8: =SUM(DQ8,DN8,DK8) -> 0 | DU8: =IF(DU$6>month_of_report,0,-(SUMIFS(TB_Balance_07,TB_Entity,DU$7,Cards_Selection,$CR8)-SUMIFS(TB_Balance_06,TB_Entity,DU$7,Cards_Selection,$CR8))) -> 0 | DV8: =IF(DV$6>month_of_report,0,-(SUMIFS(TB_Balance_07,TB_Entity,DV$7,Cards_Selection,$CR8)-SUMIFS(TB_Balance_06,TB_Entity,DV$7,Cards_Selection,$CR8))) -> 0 | DW8: =IF(DW$6<=month_of_report,(IFERROR(INDEX($X$8:$AI$277,MATCH($CR8,$C$8:$C$277,0),MATCH(DW$6,$X$6:$AI$6,0)),0)),0) -> 0 | DX8: =IF(DX$6>month_of_report,0,-(SUMIFS(TB_Balance_08,TB_Entity,DX$7,Cards_Selection,$CR8)-SUMIFS(TB_Balance_07,TB_Entity,DX$7,Cards_Selection,$CR8))) -> 0 | DY8: =IF(DY$6>month_of_report,0,-(SUMIFS(TB_Balance_08,TB_Entity,DY$7,Cards_Selection,$CR8)-SUMIFS(TB_Balance_07,TB_Entity,DY$7,Cards_Selection,$CR8))) -> 0 | DZ8: =IF(DZ$6<=month_of_report,(IFERROR(INDEX($X$8:$AI$277,MATCH($CR8,$C$8:$C$277,0),MATCH(DZ$6,$X$6:$AI$6,0)),0)),0) -> 0 | EA8: =IF(EA$6>month_of_report,0,-(SUMIFS(TB_Balance_09,TB_Entity,EA$7,Cards_Selection,$CR8)-SUMIFS(TB_Balance_08,TB_Entity,EA$7,Cards_Selection,$CR8))) -> 0 | EB8: =IF(EB$6>month_of_report,0,-(SUMIFS(TB_Balance_09,TB_Entity,EB$7,Cards_Selection,$CR8)-SUMIFS(TB_Balance_08,TB_Entity,EB$7,Cards_Selection,$CR8))) -> 0 | EC8: =IF(EC$6<=month_of_report,(IFERROR(INDEX($X$8:$AI$277,MATCH($CR8,$C$8:$C$277,0),MATCH(EC$6,$X$6:$AI$6,0)),0)),0) -> 0 | ED8: =SUM(EA8,DX8,DU8) -> 0 | EE8: =SUM(EB8,DY8,DV8) -> 0 | EF8: =SUM(EC8,DZ8,DW8) -> 0 | EG8: =IF(EG$6>month_of_report,0,-(SUMIFS(TB_Balance_10,TB_Entity,EG$7,Cards_Selection,$CR8)-SUMIFS(TB_Balance_09,TB_Entity,EG$7,Cards_Selection,$CR8))) -> 0 | EH8: =IF(EH$6>month_of_report,0,-(SUMIFS(TB_Balance_10,TB_Entity,EH$7,Cards_Selection,$CR8)-SUMIFS(TB_Balance_09,TB_Entity,EH$7,Cards_Selection,$CR8))) -> 0 | EI8: =IF(EI$6<=month_of_report,(IFERROR(INDEX($X$8:$AI$277,MATCH($CR8,$C$8:$C$277,0),MATCH(EI$6,$X$6:$AI$6,0)),0)),0) -> 0 | EJ8: =IF(EJ$6>month_of_report,0,-(SUMIFS(TB_Balance_11,TB_Entity,EJ$7,Cards_Selection,$CR8)-SUMIFS(TB_Balance_10,TB_Entity,EJ$7,Cards_Selection,$CR8))) -> 0 | EK8: =IF(EK$6>month_of_report,0,-(SUMIFS(TB_Balance_11,TB_Entity,EK$7,Cards_Selection,$CR8)-SUMIFS(TB_Balance_10,TB_Entity,EK$7,Cards_Selection,$CR8))) -> 0 | EL8: =IF(EL$6<=month_of_report,(IFERROR(INDEX($X$8:$AI$277,MATCH($CR8,$C$8:$C$277,0),MATCH(EL$6,$X$6:$AI$6,0)),0)),0) -> 0 | EM8: =IF(EM$6>month_of_report,0,-(SUMIFS(TB_Balance_12,TB_Entity,EM$7,Cards_Selection,$CR8)-SUMIFS(TB_Balance_11,TB_Entity,EM$7,Cards_Selection,$CR8))) -> 0 | EN8: =IF(EN$6>month_of_report,0,-(SUMIFS(TB_Balance_12,TB_Entity,EN$7,Cards_Selection,$CR8)-SUMIFS(TB_Balance_11,TB_Entity,EN$7,Cards_Selection,$CR8))) -> 0 | EO8: =IF(EO$6<=month_of_report,(IFERROR(INDEX($X$8:$AI$277,MATCH($CR8,$C$8:$C$277,0),MATCH(EO$6,$X$6:$AI$6,0)),0)),0) -> 0 | EP8: =SUM(EM8,EJ8,EG8) -> 0 | EQ8: =SUM(EN8,EK8,EH8) -> 0 | ER8: =SUM(EO8,EL8,EI8) -> 0
C9: 111 | D9: =IF($C9<=30,"",INDEX(Opex_expense_Type,MATCH($C9,Index_card_code,0))) -> -- | F9: =IFERROR(INDEX(Index_Card_name,MATCH($C9,Index_card_code,0)),"") -> Revenues - Income | H9: =INDEX($X9:$AI9,,MATCH($H$6,$X$6:$AI$6,0)) -> 0 | I9: =SUMIF(Cards_selection_BPL,$C9,INDIRECT(Index!$P$16)) -> 0 | J9: =+H9-I9 -> 0 | L9: =IF(LEFT($L$6,2)="Q1",SUMIFS($X9:$Z9,$X$6:$Z$6,"<="&month_of_report),IF(LEFT($L$6,2)="Q2",SUMIFS($AA9:$AC9,$AA$6:$AC$6,"<="&month_of_report),IF(LEFT($L$6,2)="Q3",SUMIFS($AD9:$AF9,$AD$6:$AF$6,"<="&month_of_report),IF(LEFT($L$6,2)="Q4",SUMIFS($AG9:$AI9,$AG$6:$AI$6,"<="&month_of_report),0)))) -> 0 | M9: =IF(LEFT($L$6,2)="Q1",SUMIF(Cards_selection_BPL,$C9,INDIRECT(Index!$Q$16)),IF(LEFT($L$6,2)="Q2",SUMIF(Cards_selection_BPL,$C9,INDIRECT(Index!$Q$16))-SUMIF(Cards_selection_BPL,$C9,Balance_bplm_03),IF(LEFT($L$6,2)="Q3",SUMIF(Cards_selection_BPL,$C9,INDIRECT(Index!$Q$16))-SUMIF(Cards_selection_BPL,$C9,Balance_bplm_06),IF(LEFT($L$6,2)="Q4",SUMIF(Cards_selection_BPL,$C9,INDIRECT(Index!$Q$16))-SUMIF(Cards_selection_BPL,$C9,Balance_bplm_09),0)))) -> 0 | N9: =+L9-M9 -> 0 | P9: =SUMIFS($X9:$AI9,$X$6:$AI$6,"<="&month_of_report) -> 0 | Q9: =SUMIF(Cards_selection_BPL,$C9,INDIRECT(Index!$Q$16)) -> 0 | R9: =+P9-Q9 -> 0 | X9: =-IF(X$6<=month_of_report,(SUMIF(Cards_Selection,$C9,TB_Balance_01)),0) -> 0 | Y9: =-IF(Y$6<=month_of_report,(SUMIF(Cards_Selection,$C9,TB_Balance_02)-SUMIF(Cards_Selection,$C9,TB_Balance_01)),0) -> 0 | Z9: =-IF(Z$6<=month_of_report,(SUMIF(Cards_Selection,$C9,TB_Balance_03)-SUMIF(Cards_Selection,$C9,TB_Balance_02)),0) -> 0 | AB9: =-IF(AB$6<=month_of_report,(SUMIF(Cards_Selection,$C9,TB_Balance_05)-SUMIF(Cards_Selection,$C9,TB_Balance_04)),0) -> 0 | AC9: =-IF(AC$6<=month_of_report,(SUMIF(Cards_Selection,$C9,TB_Balance_06)-SUMIF(Cards_Selection,$C9,TB_Balance_03)),0) -> 0 | AE9: =-IF(AE$6<=month_of_report,(SUMIF(Cards_Selection,$C9,TB_Balance_08)-SUMIF(Cards_Selection,$C9,TB_Balance_07)),0) -> 0 | AF9: =-IF(AF$6<=month_of_report,(SUMIF(Cards_Selection,$C9,TB_Balance_09)-SUMIF(Cards_Selection,$C9,TB_Balance_06)),0) -> 0 | AH9: =-IF(AH$6<=month_of_report,(SUMIF(Cards_Selection,$C9,TB_Balance_11)-SUMIF(Cards_Selection,$C9,TB_Balance_10)),0) -> 0 | AI9: =-IF(AI$6<=month_of_report,(SUMIF(Cards_Selection,$C9,TB_Balance_12)-SUMIF(Cards_Selection,$C9,TB_Balance_09)),0) -> 0 | AM9: =P9 -> 0 | AN9: =-IF(AN$6<=month_of_report,SUMIF(Cards_Selection,$C9,TB_Balance_12_Nis),0) -> 0 | AR9: =IF(B9="","",B9) | AS9: =IF(C9="","",C9) -> 111 | AT9: =IFERROR(IF($AS9<=30,"",INDEX(Opex_expense_Type,MATCH($AS9,Index_card_code,0))),"") -> -- | AU9: =IF(E9="","",E9) | AV9: =IF(F9="","",F9) -> Revenues - Income | BC9: =SUM(AZ9:BB9) -> 0 | BG9: =SUM(BD9:BF9) -> 0 | BK9: =SUM(BH9:BJ9) -> 0 | BO9: =SUM(BL9:BN9) -> 0 | BP9: =BO9+BK9+BG9+BC9 -> 0 | BS9: =INDEX($AZ9:$BN9,MATCH(BS$6,$AZ$6:$BN$6,0)) -> 0 | BT9: =INDEX($AZ9:$BN9,MATCH(BT$6,$AZ$6:$BN$6,0)) -> 0 | BU9: =SUM(BS9:BT9) -> 0 | BV9: =INDEX($AZ9:$BN9,MATCH(BV$6,$AZ$6:$BN$6,0)) -> 0 | BW9: =SUM(BU9:BV9) -> 0 | BX9: =INDEX($AZ9:$BN9,MATCH(BX$6,$AZ$6:$BN$6,0)) -> 0 | BY9: =SUM(BW9:BX9) -> 0 | BZ9: =INDEX($AZ9:$BN9,MATCH(BZ$6,$AZ$6:$BN$6,0)) -> 0 | CA9: =SUM(BY9:BZ9) -> 0 | CB9: =INDEX($AZ9:$BN9,MATCH(CB$6,$AZ$6:$BN$6,0)) -> 0 | CC9: =SUM(CA9:CB9) -> 0 | CD9: =INDEX($AZ9:$BN9,MATCH(CD$6,$AZ$6:$BN$6,0)) -> 0 | CE9: =SUM(CC9:CD9) -> 0 | CF9: =INDEX($AZ9:$BN9,MATCH(CF$6,$AZ$6:$BN$6,0)) -> 0 | CG9: =SUM(CE9:CF9) -> 0 | CH9: =INDEX($AZ9:$BN9,MATCH(CH$6,$AZ$6:$BN$6,0)) -> 0 | CI9: =SUM(CG9:CH9) -> 0 | CJ9: =INDEX($AZ9:$BN9,MATCH(CJ$6,$AZ$6:$BN$6,0)) -> 0 | CK9: =SUM(CI9:CJ9) -> 0 | CL9: =INDEX($AZ9:$BN9,MATCH(CL$6,$AZ$6:$BN$6,0)) -> 0 | CM9: =SUM(CK9:CL9) -> 0 | CN9: =INDEX($AZ9:$BN9,MATCH(CN$6,$AZ$6:$BN$6,0)) -> 0 | CO9: =SUM(CM9:CN9) -> 0 | CQ9: =AR9 | CR9: =AS9 -> 111 | CS9: =IFERROR(IF($CR9<=30,"",INDEX(Opex_expense_Type,MATCH($CR9,Index_card_code,0))),"") -> -- | CT9: =AU9 | CU9: =AV9 -> Revenues - Income | CW9: =IF(CW$6>month_of_report,0,-SUMIFS(TB_Balance_01,TB_Entity,CW$7,Cards_Selection,$CR9)) -> 0 | CX9: =IF(CX$6>month_of_report,0,-SUMIFS(TB_Balance_01,TB_Entity,CX$7,Cards_Selection,$CR9)) -> 0 | CY9: =IF(CY$6<=month_of_report,(IFERROR(INDEX($X$8:$AI$277,MATCH($CR9,$C$8:$C$277,0),MATCH(CY$6,$X$6:$AI$6,0)),0)),0) -> 0 | CZ9: =IF(CZ$6>month_of_report,0,-(SUMIFS(TB_Balance_02,TB_Entity,CZ$7,Cards_Selection,$CR9)-SUMIFS(TB_Balance_01,TB_Entity,CZ$7,Cards_Selection,$CR9))) -> 0 | DA9: =IF(DA$6>month_of_report,0,-(SUMIFS(TB_Balance_02,TB_Entity,DA$7,Cards_Selection,$CR9)-SUMIFS(TB_Balance_01,TB_Entity,DA$7,Cards_Selection,$CR9))) -> 0 | DB9: =IF(DB$6<=month_of_report,(IFERROR(INDEX($X$8:$AI$277,MATCH($CR9,$C$8:$C$277,0),MATCH(DB$6,$X$6:$AI$6,0)),0)),0) -> 0 | DC9: =IF(DC$6>month_of_report,0,-(SUMIFS(TB_Balance_03,TB_Entity,DC$7,Cards_Selection,$CR9)-SUMIFS(TB_Balance_02,TB_Entity,DC$7,Cards_Selection,$CR9))) -> 0 | DD9: =IF(DD$6>month_of_report,0,-(SUMIFS(TB_Balance_03,TB_Entity,DD$7,Cards_Selection,$CR9)-SUMIFS(TB_Balance_02,TB_Entity,DD$7,Cards_Selection,$CR9))) -> 0 | DE9: =IF(DE$6<=month_of_report,(IFERROR(INDEX($X$8:$AI$277,MATCH($CR9,$C$8:$C$277,0),MATCH(DE$6,$X$6:$AI$6,0)),0)),0) -> 0 | DF9: =SUM(DC9,CZ9,CW9) -> 0 | DG9: =SUM(DD9,DA9,CX9) -> 0 | DH9: =SUM(DE9,DB9,CY9) -> 0 | DI9: =IF(DI$6>month_of_report,0,-(SUMIFS(TB_Balance_04,TB_Entity,DI$7,Cards_Selection,$CR9)-SUMIFS(TB_Balance_03,TB_Entity,DI$7,Cards_Selection,$CR9))) -> 0 | DJ9: =IF(DJ$6>month_of_report,0,-(SUMIFS(TB_Balance_04,TB_Entity,DJ$7,Cards_Selection,$CR9)-SUMIFS(TB_Balance_03,TB_Entity,DJ$7,Cards_Selection,$CR9))) -> 0 | DK9: =IF(DK$6<=month_of_report,(IFERROR(INDEX($X$8:$AI$277,MATCH($CR9,$C$8:$C$277,0),MATCH(DK$6,$X$6:$AI$6,0)),0)),0) -> 0 | DL9: =IF(DL$6>month_of_report,0,-(SUMIFS(TB_Balance_05,TB_Entity,DL$7,Cards_Selection,$CR9)-SUMIFS(TB_Balance_04,TB_Entity,DL$7,Cards_Selection,$CR9))) -> 0 | DM9: =IF(DM$6>month_of_report,0,-(SUMIFS(TB_Balance_05,TB_Entity,DM$7,Cards_Selection,$CR9)-SUMIFS(TB_Balance_04,TB_Entity,DM$7,Cards_Selection,$CR9))) -> 0 | DN9: =IF(DN$6<=month_of_report,(IFERROR(INDEX($X$8:$AI$277,MATCH($CR9,$C$8:$C$277,0),MATCH(DN$6,$X$6:$AI$6,0)),0)),0) -> 0 | DO9: =IF(DO$6>month_of_report,0,-(SUMIFS(TB_Balance_06,TB_Entity,DO$7,Cards_Selection,$CR9)-SUMIFS(TB_Balance_05,TB_Entity,DO$7,Cards_Selection,$CR9))) -> 0 | DP9: =IF(DP$6>month_of_report,0,-(SUMIFS(TB_Balance_06,TB_Entity,DP$7,Cards_Selection,$CR9)-SUMIFS(TB_Balance_05,TB_Entity,DP$7,Cards_Selection,$CR9))) -> 0 | DQ9: =IF(DQ$6<=month_of_report,(IFERROR(INDEX($X$8:$AI$277,MATCH($CR9,$C$8:$C$277,0),MATCH(DQ$6,$X$6:$AI$6,0)),0)),0) -> 0 | DR9: =SUM(DO9,DL9,DI9) -> 0 | DS9: =SUM(DP9,DM9,DJ9) -> 0 | DT9: =SUM(DQ9,DN9,DK9) -> 0 | DU9: =IF(DU$6>month_of_report,0,-(SUMIFS(TB_Balance_07,TB_Entity,DU$7,Cards_Selection,$CR9)-SUMIFS(TB_Balance_06,TB_Entity,DU$7,Cards_Selection,$CR9))) -> 0 | DV9: =IF(DV$6>month_of_report,0,-(SUMIFS(TB_Balance_07,TB_Entity,DV$7,Cards_Selection,$CR9)-SUMIFS(TB_Balance_06,TB_Entity,DV$7,Cards_Selection,$CR9))) -> 0 | DW9: =IF(DW$6<=month_of_report,(IFERROR(INDEX($X$8:$AI$277,MATCH($CR9,$C$8:$C$277,0),MATCH(DW$6,$X$6:$AI$6,0)),0)),0) -> 0 | DX9: =IF(DX$6>month_of_report,0,-(SUMIFS(TB_Balance_08,TB_Entity,DX$7,Cards_Selection,$CR9)-SUMIFS(TB_Balance_07,TB_Entity,DX$7,Cards_Selection,$CR9))) -> 0 | DY9: =IF(DY$6>month_of_report,0,-(SUMIFS(TB_Balance_08,TB_Entity,DY$7,Cards_Selection,$CR9)-SUMIFS(TB_Balance_07,TB_Entity,DY$7,Cards_Selection,$CR9))) -> 0 | DZ9: =IF(DZ$6<=month_of_report,(IFERROR(INDEX($X$8:$AI$277,MATCH($CR9,$C$8:$C$277,0),MATCH(DZ$6,$X$6:$AI$6,0)),0)),0) -> 0 | EA9: =IF(EA$6>month_of_report,0,-(SUMIFS(TB_Balance_09,TB_Entity,EA$7,Cards_Selection,$CR9)-SUMIFS(TB_Balance_08,TB_Entity,EA$7,Cards_Selection,$CR9))) -> 0 | EB9: =IF(EB$6>month_of_report,0,-(SUMIFS(TB_Balance_09,TB_Entity,EB$7,Cards_Selection,$CR9)-SUMIFS(TB_Balance_08,TB_Entity,EB$7,Cards_Selection,$CR9))) -> 0 | EC9: =IF(EC$6<=month_of_report,(IFERROR(INDEX($X$8:$AI$277,MATCH($CR9,$C$8:$C$277,0),MATCH(EC$6,$X$6:$AI$6,0)),0)),0) -> 0 | ED9: =SUM(EA9,DX9,DU9) -> 0 | EE9: =SUM(EB9,DY9,DV9) -> 0 | EF9: =SUM(EC9,DZ9,DW9) -> 0 | EG9: =IF(EG$6>month_of_report,0,-(SUMIFS(TB_Balance_10,TB_Entity,EG$7,Cards_Selection,$CR9)-SUMIFS(TB_Balance_09,TB_Entity,EG$7,Cards_Selection,$CR9))) -> 0 | EH9: =IF(EH$6>month_of_report,0,-(SUMIFS(TB_Balance_10,TB_Entity,EH$7,Cards_Selection,$CR9)-SUMIFS(TB_Balance_09,TB_Entity,EH$7,Cards_Selection,$CR9))) -> 0 | EI9: =IF(EI$6<=month_of_report,(IFERROR(INDEX($X$8:$AI$277,MATCH($CR9,$C$8:$C$277,0),MATCH(EI$6,$X$6:$AI$6,0)),0)),0) -> 0 | EJ9: =IF(EJ$6>month_of_report,0,-(SUMIFS(TB_Balance_11,TB_Entity,EJ$7,Cards_Selection,$CR9)-SUMIFS(TB_Balance_10,TB_Entity,EJ$7,Cards_Selection,$CR9))) -> 0 | EK9: =IF(EK$6>month_of_report,0,-(SUMIFS(TB_Balance_11,TB_Entity,EK$7,Cards_Selection,$CR9)-SUMIFS(TB_Balance_10,TB_Entity,EK$7,Cards_Selection,$CR9))) -> 0 | EL9: =IF(EL$6<=month_of_report,(IFERROR(INDEX($X$8:$AI$277,MATCH($CR9,$C$8:$C$277,0),MATCH(EL$6,$X$6:$AI$6,0)),0)),0) -> 0 | EM9: =IF(EM$6>month_of_report,0,-(SUMIFS(TB_Balance_12,TB_Entity,EM$7,Cards_Selection,$CR9)-SUMIFS(TB_Balance_11,TB_Entity,EM$7,Cards_Selection,$CR9))) -> 0 | EN9: =IF(EN$6>month_of_report,0,-(SUMIFS(TB_Balance_12,TB_Entity,EN$7,Cards_Selection,$CR9)-SUMIFS(TB_Balance_11,TB_Entity,EN$7,Cards_Selection,$CR9))) -> 0 | EO9: =IF(EO$6<=month_of_report,(IFERROR(INDEX($X$8:$AI$277,MATCH($CR9,$C$8:$C$277,0),MATCH(EO$6,$X$6:$AI$6,0)),0)),0) -> 0 | EP9: =SUM(EM9,EJ9,EG9) -> 0 | EQ9: =SUM(EN9,EK9,EH9) -> 0 | ER9: =SUM(EO9,EL9,EI9) -> 0
C10: 112 | D10: =IF($C10<=30,"",INDEX(Opex_expense_Type,MATCH($C10,Index_card_code,0))) -> -- | F10: =IFERROR(INDEX(Index_Card_name,MATCH($C10,Index_card_code,0)),"") -> Revenues - Income | H10: =INDEX($X10:$AI10,,MATCH($H$6,$X$6:$AI$6,0)) -> 0 | I10: =SUMIF(Cards_selection_BPL,$C10,INDIRECT(Index!$P$16)) -> 0 | J10: =+H10-I10 -> 0 | L10: =IF(LEFT($L$6,2)="Q1",SUMIFS($X10:$Z10,$X$6:$Z$6,"<="&month_of_report),IF(LEFT($L$6,2)="Q2",SUMIFS($AA10:$AC10,$AA$6:$AC$6,"<="&month_of_report),IF(LEFT($L$6,2)="Q3",SUMIFS($AD10:$AF10,$AD$6:$AF$6,"<="&month_of_report),IF(LEFT($L$6,2)="Q4",SUMIFS($AG10:$AI10,$AG$6:$AI$6,"<="&month_of_report),0)))) -> 0 | M10: =IF(LEFT($L$6,2)="Q1",SUMIF(Cards_selection_BPL,$C10,INDIRECT(Index!$Q$16)),IF(LEFT($L$6,2)="Q2",SUMIF(Cards_selection_BPL,$C10,INDIRECT(Index!$Q$16))-SUMIF(Cards_selection_BPL,$C10,Balance_bplm_03),IF(LEFT($L$6,2)="Q3",SUMIF(Cards_selection_BPL,$C10,INDIRECT(Index!$Q$16))-SUMIF(Cards_selection_BPL,$C10,Balance_bplm_06),IF(LEFT($L$6,2)="Q4",SUMIF(Cards_selection_BPL,$C10,INDIRECT(Index!$Q$16))-SUMIF(Cards_selection_BPL,$C10,Balance_bplm_09),0)))) -> 0 | N10: =+L10-M10 -> 0 | P10: =SUMIFS($X10:$AI10,$X$6:$AI$6,"<="&month_of_report) -> 0 | Q10: =SUMIF(Cards_selection_BPL,$C10,INDIRECT(Index!$Q$16)) -> 0 | R10: =+P10-Q10 -> 0 | X10: =-IF(X$6<=month_of_report,(SUMIF(Cards_Selection,$C10,TB_Balance_01)),0) -> 0 | Y10: =-IF(Y$6<=month_of_report,(SUMIF(Cards_Selection,$C10,TB_Balance_02)-SUMIF(Cards_Selection,$C10,TB_Balance_01)),0) -> 0 | Z10: =-IF(Z$6<=month_of_report,(SUMIF(Cards_Selection,$C10,TB_Balance_03)-SUMIF(Cards_Selection,$C10,TB_Balance_02)),0) -> 0 | AA10: =-IF(AA$6<=month_of_report,(SUMIF(Cards_Selection,$C10,TB_Balance_04)-SUMIF(Cards_Selection,$C10,TB_Balance_03)),0) -> 0 | AB10: =-IF(AB$6<=month_of_report,(SUMIF(Cards_Selection,$C10,TB_Balance_05)-SUMIF(Cards_Selection,$C10,TB_Balance_04)),0) -> 0 | AC10: =-IF(AC$6<=month_of_report,(SUMIF(Cards_Selection,$C10,TB_Balance_06)-SUMIF(Cards_Selection,$C10,TB_Balance_05)),0) -> 0 | AD10: =-IF(AD$6<=month_of_report,(SUMIF(Cards_Selection,$C10,TB_Balance_07)-SUMIF(Cards_Selection,$C10,TB_Balance_06)),0) -> 0 | AE10: =-IF(AE$6<=month_of_report,(SUMIF(Cards_Selection,$C10,TB_Balance_08)-SUMIF(Cards_Selection,$C10,TB_Balance_07)),0) -> 0 | AF10: =-IF(AF$6<=month_of_report,(SUMIF(Cards_Selection,$C10,TB_Balance_09)-SUMIF(Cards_Selection,$C10,TB_Balance_08)),0) -> 0 | AG10: =-IF(AG$6<=month_of_report,(SUMIF(Cards_Selection,$C10,TB_Balance_10)-SUMIF(Cards_Selection,$C10,TB_Balance_09)),0) -> 0 | AH10: =-IF(AH$6<=month_of_report,(SUMIF(Cards_Selection,$C10,TB_Balance_11)-SUMIF(Cards_Selection,$C10,TB_Balance_10)),0) -> 0 | AI10: =-IF(AI$6<=month_of_report,(SUMIF(Cards_Selection,$C10,TB_Balance_12)-SUMIF(Cards_Selection,$C10,TB_Balance_09)),0) -> 0 | AM10: =P10 -> 0 | AN10: =-IF(AN$6<=month_of_report,SUMIF(Cards_Selection,$C10,TB_Balance_12_Nis),0) -> 0 | AR10: =IF(B10="","",B10) | AS10: =IF(C10="","",C10) -> 112 | AT10: =IFERROR(IF($AS10<=30,"",INDEX(Opex_expense_Type,MATCH($AS10,Index_card_code,0))),"") -> -- | AU10: =IF(E10="","",E10) | AV10: =IF(F10="","",F10) -> Revenues - Income | BC10: =SUM(AZ10:BB10) -> 0 | BG10: =SUM(BD10:BF10) -> 0 | BK10: =SUM(BH10:BJ10) -> 0 | BO10: =SUM(BL10:BN10) -> 0 | BP10: =BO10+BK10+BG10+BC10 -> 0 | BS10: =INDEX($AZ10:$BN10,MATCH(BS$6,$AZ$6:$BN$6,0)) -> 0 | BT10: =INDEX($AZ10:$BN10,MATCH(BT$6,$AZ$6:$BN$6,0)) -> 0 | BU10: =SUM(BS10:BT10) -> 0 | BV10: =INDEX($AZ10:$BN10,MATCH(BV$6,$AZ$6:$BN$6,0)) -> 0 | BW10: =SUM(BU10:BV10) -> 0 | BX10: =INDEX($AZ10:$BN10,MATCH(BX$6,$AZ$6:$BN$6,0)) -> 0 | BY10: =SUM(BW10:BX10) -> 0 | BZ10: =INDEX($AZ10:$BN10,MATCH(BZ$6,$AZ$6:$BN$6,0)) -> 0 | CA10: =SUM(BY10:BZ10) -> 0 | CB10: =INDEX($AZ10:$BN10,MATCH(CB$6,$AZ$6:$BN$6,0)) -> 0 | CC10: =SUM(CA10:CB10) -> 0 | CD10: =INDEX($AZ10:$BN10,MATCH(CD$6,$AZ$6:$BN$6,0)) -> 0 | CE10: =SUM(CC10:CD10) -> 0 | CF10: =INDEX($AZ10:$BN10,MATCH(CF$6,$AZ$6:$BN$6,0)) -> 0 | CG10: =SUM(CE10:CF10) -> 0 | CH10: =INDEX($AZ10:$BN10,MATCH(CH$6,$AZ$6:$BN$6,0)) -> 0 | CI10: =SUM(CG10:CH10) -> 0 | CJ10: =INDEX($AZ10:$BN10,MATCH(CJ$6,$AZ$6:$BN$6,0)) -> 0 | CK10: =SUM(CI10:CJ10) -> 0 | CL10: =INDEX($AZ10:$BN10,MATCH(CL$6,$AZ$6:$BN$6,0)) -> 0 | CM10: =SUM(CK10:CL10) -> 0 | CN10: =INDEX($AZ10:$BN10,MATCH(CN$6,$AZ$6:$BN$6,0)) -> 0 | CO10: =SUM(CM10:CN10) -> 0 | CQ10: =AR10 | CR10: =AS10 -> 112 | CS10: =IFERROR(IF($CR10<=30,"",INDEX(Opex_expense_Type,MATCH($CR10,Index_card_code,0))),"") -> -- | CT10: =AU10 | CU10: =AV10 -> Revenues - Income | CW10: =IF(CW$6>month_of_report,0,-SUMIFS(TB_Balance_01,TB_Entity,CW$7,Cards_Selection,$CR10)) -> 0 | CX10: =IF(CX$6>month_of_report,0,-SUMIFS(TB_Balance_01,TB_Entity,CX$7,Cards_Selection,$CR10)) -> 0 | CY10: =IF(CY$6<=month_of_report,(IFERROR(INDEX($X$8:$AI$277,MATCH($CR10,$C$8:$C$277,0),MATCH(CY$6,$X$6:$AI$6,0)),0)),0) -> 0 | CZ10: =IF(CZ$6>month_of_report,0,-(SUMIFS(TB_Balance_02,TB_Entity,CZ$7,Cards_Selection,$CR10)-SUMIFS(TB_Balance_01,TB_Entity,CZ$7,Cards_Selection,$CR10))) -> 0 | DA10: =IF(DA$6>month_of_report,0,-(SUMIFS(TB_Balance_02,TB_Entity,DA$7,Cards_Selection,$CR10)-SUMIFS(TB_Balance_01,TB_Entity,DA$7,Cards_Selection,$CR10))) -> 0 | DB10: =IF(DB$6<=month_of_report,(IFERROR(INDEX($X$8:$AI$277,MATCH($CR10,$C$8:$C$277,0),MATCH(DB$6,$X$6:$AI$6,0)),0)),0) -> 0 | DC10: =IF(DC$6>month_of_report,0,-(SUMIFS(TB_Balance_03,TB_Entity,DC$7,Cards_Selection,$CR10)-SUMIFS(TB_Balance_02,TB_Entity,DC$7,Cards_Selection,$CR10))) -> 0 | DD10: =IF(DD$6>month_of_report,0,-(SUMIFS(TB_Balance_03,TB_Entity,DD$7,Cards_Selection,$CR10)-SUMIFS(TB_Balance_02,TB_Entity,DD$7,Cards_Selection,$CR10))) -> 0 | DE10: =IF(DE$6<=month_of_report,(IFERROR(INDEX($X$8:$AI$277,MATCH($CR10,$C$8:$C$277,0),MATCH(DE$6,$X$6:$AI$6,0)),0)),0) -> 0 | DF10: =SUM(DC10,CZ10,CW10) -> 0 | DG10: =SUM(DD10,DA10,CX10) -> 0 | DH10: =SUM(DE10,DB10,CY10) -> 0 | DI10: =IF(DI$6>month_of_report,0,-(SUMIFS(TB_Balance_04,TB_Entity,DI$7,Cards_Selection,$CR10)-SUMIFS(TB_Balance_03,TB_Entity,DI$7,Cards_Selection,$CR10))) -> 0 | DJ10: =IF(DJ$6>month_of_report,0,-(SUMIFS(TB_Balance_04,TB_Entity,DJ$7,Cards_Selection,$CR10)-SUMIFS(TB_Balance_03,TB_Entity,DJ$7,Cards_Selection,$CR10))) -> 0 | DK10: =IF(DK$6<=month_of_report,(IFERROR(INDEX($X$8:$AI$277,MATCH($CR10,$C$8:$C$277,0),MATCH(DK$6,$X$6:$AI$6,0)),0)),0) -> 0 | DL10: =IF(DL$6>month_of_report,0,-(SUMIFS(TB_Balance_05,TB_Entity,DL$7,Cards_Selection,$CR10)-SUMIFS(TB_Balance_04,TB_Entity,DL$7,Cards_Selection,$CR10))) -> 0 | DM10: =IF(DM$6>month_of_report,0,-(SUMIFS(TB_Balance_05,TB_Entity,DM$7,Cards_Selection,$CR10)-SUMIFS(TB_Balance_04,TB_Entity,DM$7,Cards_Selection,$CR10))) -> 0 | DN10: =IF(DN$6<=month_of_report,(IFERROR(INDEX($X$8:$AI$277,MATCH($CR10,$C$8:$C$277,0),MATCH(DN$6,$X$6:$AI$6,0)),0)),0) -> 0 | DO10: =IF(DO$6>month_of_report,0,-(SUMIFS(TB_Balance_06,TB_Entity,DO$7,Cards_Selection,$CR10)-SUMIFS(TB_Balance_05,TB_Entity,DO$7,Cards_Selection,$CR10))) -> 0 | DP10: =IF(DP$6>month_of_report,0,-(SUMIFS(TB_Balance_06,TB_Entity,DP$7,Cards_Selection,$CR10)-SUMIFS(TB_Balance_05,TB_Entity,DP$7,Cards_Selection,$CR10))) -> 0 | DQ10: =IF(DQ$6<=month_of_report,(IFERROR(INDEX($X$8:$AI$277,MATCH($CR10,$C$8:$C$277,0),MATCH(DQ$6,$X$6:$AI$6,0)),0)),0) -> 0 | DR10: =SUM(DO10,DL10,DI10) -> 0 | DS10: =SUM(DP10,DM10,DJ10) -> 0 | DT10: =SUM(DQ10,DN10,DK10) -> 0 | DU10: =IF(DU$6>month_of_report,0,-(SUMIFS(TB_Balance_07,TB_Entity,DU$7,Cards_Selection,$CR10)-SUMIFS(TB_Balance_06,TB_Entity,DU$7,Cards_Selection,$CR10))) -> 0 | DV10: =IF(DV$6>month_of_report,0,-(SUMIFS(TB_Balance_07,TB_Entity,DV$7,Cards_Selection,$CR10)-SUMIFS(TB_Balance_06,TB_Entity,DV$7,Cards_Selection,$CR10))) -> 0 | DW10: =IF(DW$6<=month_of_report,(IFERROR(INDEX($X$8:$AI$277,MATCH($CR10,$C$8:$C$277,0),MATCH(DW$6,$X$6:$AI$6,0)),0)),0) -> 0 | DX10: =IF(DX$6>month_of_report,0,-(SUMIFS(TB_Balance_08,TB_Entity,DX$7,Cards_Selection,$CR10)-SUMIFS(TB_Balance_07,TB_Entity,DX$7,Cards_Selection,$CR10))) -> 0 | DY10: =IF(DY$6>month_of_report,0,-(SUMIFS(TB_Balance_08,TB_Entity,DY$7,Cards_Selection,$CR10)-SUMIFS(TB_Balance_07,TB_Entity,DY$7,Cards_Selection,$CR10))) -> 0 | DZ10: =IF(DZ$6<=month_of_report,(IFERROR(INDEX($X$8:$AI$277,MATCH($CR10,$C$8:$C$277,0),MATCH(DZ$6,$X$6:$AI$6,0)),0)),0) -> 0 | EA10: =IF(EA$6>month_of_report,0,-(SUMIFS(TB_Balance_09,TB_Entity,EA$7,Cards_Selection,$CR10)-SUMIFS(TB_Balance_08,TB_Entity,EA$7,Cards_Selection,$CR10))) -> 0 | EB10: =IF(EB$6>month_of_report,0,-(SUMIFS(TB_Balance_09,TB_Entity,EB$7,Cards_Selection,$CR10)-SUMIFS(TB_Balance_08,TB_Entity,EB$7,Cards_Selection,$CR10))) -> 0 | EC10: =IF(EC$6<=month_of_report,(IFERROR(INDEX($X$8:$AI$277,MATCH($CR10,$C$8:$C$277,0),MATCH(EC$6,$X$6:$AI$6,0)),0)),0) -> 0 | ED10: =SUM(EA10,DX10,DU10) -> 0 | EE10: =SUM(EB10,DY10,DV10) -> 0 | EF10: =SUM(EC10,DZ10,DW10) -> 0 | EG10: =IF(EG$6>month_of_report,0,-(SUMIFS(TB_Balance_10,TB_Entity,EG$7,Cards_Selection,$CR10)-SUMIFS(TB_Balance_09,TB_Entity,EG$7,Cards_Selection,$CR10))) -> 0 | EH10: =IF(EH$6>month_of_report,0,-(SUMIFS(TB_Balance_10,TB_Entity,EH$7,Cards_Selection,$CR10)-SUMIFS(TB_Balance_09,TB_Entity,EH$7,Cards_Selection,$CR10))) -> 0 | EI10: =IF(EI$6<=month_of_report,(IFERROR(INDEX($X$8:$AI$277,MATCH($CR10,$C$8:$C$277,0),MATCH(EI$6,$X$6:$AI$6,0)),0)),0) -> 0 | EJ10: =IF(EJ$6>month_of_report,0,-(SUMIFS(TB_Balance_11,TB_Entity,EJ$7,Cards_Selection,$CR10)-SUMIFS(TB_Balance_10,TB_Entity,EJ$7,Cards_Selection,$CR10))) -> 0 | EK10: =IF(EK$6>month_of_report,0,-(SUMIFS(TB_Balance_11,TB_Entity,EK$7,Cards_Selection,$CR10)-SUMIFS(TB_Balance_10,TB_Entity,EK$7,Cards_Selection,$CR10))) -> 0 | EL10: =IF(EL$6<=month_of_report,(IFERROR(INDEX($X$8:$AI$277,MATCH($CR10,$C$8:$C$277,0),MATCH(EL$6,$X$6:$AI$6,0)),0)),0) -> 0 | EM10: =IF(EM$6>month_of_report,0,-(SUMIFS(TB_Balance_12,TB_Entity,EM$7,Cards_Selection,$CR10)-SUMIFS(TB_Balance_11,TB_Entity,EM$7,Cards_Selection,$CR10))) -> 0 | EN10: =IF(EN$6>month_of_report,0,-(SUMIFS(TB_Balance_12,TB_Entity,EN$7,Cards_Selection,$CR10)-SUMIFS(TB_Balance_11,TB_Entity,EN$7,Cards_Selection,$CR10))) -> 0 | EO10: =IF(EO$6<=month_of_report,(IFERROR(INDEX($X$8:$AI$277,MATCH($CR10,$C$8:$C$277,0),MATCH(EO$6,$X$6:$AI$6,0)),0)),0) -> 0 | EP10: =SUM(EM10,EJ10,EG10) -> 0 | EQ10: =SUM(EN10,EK10,EH10) -> 0 | ER10: =SUM(EO10,EL10,EI10) -> 0
C11: 113 | D11: =IF($C11<=30,"",INDEX(Opex_expense_Type,MATCH($C11,Index_card_code,0))) -> -- | F11: =IFERROR(INDEX(Index_Card_name,MATCH($C11,Index_card_code,0)),"") -> Revenues - Income | H11: =INDEX($X11:$AI11,,MATCH($H$6,$X$6:$AI$6,0)) -> 0 | I11: =SUMIF(Cards_selection_BPL,$C11,INDIRECT(Index!$P$16)) -> 0 | J11: =+H11-I11 -> 0 | L11: =IF(LEFT($L$6,2)="Q1",SUMIFS($X11:$Z11,$X$6:$Z$6,"<="&month_of_report),IF(LEFT($L$6,2)="Q2",SUMIFS($AA11:$AC11,$AA$6:$AC$6,"<="&month_of_report),IF(LEFT($L$6,2)="Q3",SUMIFS($AD11:$AF11,$AD$6:$AF$6,"<="&month_of_report),IF(LEFT($L$6,2)="Q4",SUMIFS($AG11:$AI11,$AG$6:$AI$6,"<="&month_of_report),0)))) -> 0 | M11: =IF(LEFT($L$6,2)="Q1",SUMIF(Cards_selection_BPL,$C11,INDIRECT(Index!$Q$16)),IF(LEFT($L$6,2)="Q2",SUMIF(Cards_selection_BPL,$C11,INDIRECT(Index!$Q$16))-SUMIF(Cards_selection_BPL,$C11,Balance_bplm_03),IF(LEFT($L$6,2)="Q3",SUMIF(Cards_selection_BPL,$C11,INDIRECT(Index!$Q$16))-SUMIF(Cards_selection_BPL,$C11,Balance_bplm_06),IF(LEFT($L$6,2)="Q4",SUMIF(Cards_selection_BPL,$C11,INDIRECT(Index!$Q$16))-SUMIF(Cards_selection_BPL,$C11,Balance_bplm_09),0)))) -> 0 | N11: =+L11-M11 -> 0 | P11: =SUMIFS($X11:$AI11,$X$6:$AI$6,"<="&month_of_report) -> 0 | Q11: =SUMIF(Cards_selection_BPL,$C11,INDIRECT(Index!$Q$16)) -> 0 | R11: =+P11-Q11 -> 0 | X11: =-IF(X$6<=month_of_report,(SUMIF(Cards_Selection,$C11,TB_Balance_01)),0) -> 0 | Y11: =-IF(Y$6<=month_of_report,(SUMIF(Cards_Selection,$C11,TB_Balance_02)-SUMIF(Cards_Selection,$C11,TB_Balance_01)),0) -> 0 | Z11: =-IF(Z$6<=month_of_report,(SUMIF(Cards_Selection,$C11,TB_Balance_03)-SUMIF(Cards_Selection,$C11,TB_Balance_02)),0) -> 0 | AA11: =-IF(AA$6<=month_of_report,(SUMIF(Cards_Selection,$C11,TB_Balance_04)-SUMIF(Cards_Selection,$C11,TB_Balance_03)),0) -> 0 | AB11: =-IF(AB$6<=month_of_report,(SUMIF(Cards_Selection,$C11,TB_Balance_05)-SUMIF(Cards_Selection,$C11,TB_Balance_04)),0) -> 0 | AC11: =-IF(AC$6<=month_of_report,(SUMIF(Cards_Selection,$C11,TB_Balance_06)-SUMIF(Cards_Selection,$C11,TB_Balance_05)),0) -> 0 | AD11: =-IF(AD$6<=month_of_report,(SUMIF(Cards_Selection,$C11,TB_Balance_07)-SUMIF(Cards_Selection,$C11,TB_Balance_06)),0) -> 0 | AE11: =-IF(AE$6<=month_of_report,(SUMIF(Cards_Selection,$C11,TB_Balance_08)-SUMIF(Cards_Selection,$C11,TB_Balance_07)),0) -> 0 | AF11: =-IF(AF$6<=month_of_report,(SUMIF(Cards_Selection,$C11,TB_Balance_09)-SUMIF(Cards_Selection,$C11,TB_Balance_08)),0) -> 0 | AG11: =-IF(AG$6<=month_of_report,(SUMIF(Cards_Selection,$C11,TB_Balance_10)-SUMIF(Cards_Selection,$C11,TB_Balance_09)),0) -> 0 | AH11: =-IF(AH$6<=month_of_report,(SUMIF(Cards_Selection,$C11,TB_Balance_11)-SUMIF(Cards_Selection,$C11,TB_Balance_10)),0) -> 0 | AI11: =-IF(AI$6<=month_of_report,(SUMIF(Cards_Selection,$C11,TB_Balance_12)-SUMIF(Cards_Selection,$C11,TB_Balance_09)),0) -> 0 | AM11: =P11 -> 0 | AN11: =-IF(AN$6<=month_of_report,SUMIF(Cards_Selection,$C11,TB_Balance_12_Nis),0) -> 0 | AR11: =IF(B11="","",B11) | AS11: =IF(C11="","",C11) -> 113 | AT11: =IFERROR(IF($AS11<=30,"",INDEX(Opex_expense_Type,MATCH($AS11,Index_card_code,0))),"") -> -- | AU11: =IF(E11="","",E11) | AV11: =IF(F11="","",F11) -> Revenues - Income | BC11: =SUM(AZ11:BB11) -> 0 | BG11: =SUM(BD11:BF11) -> 0 | BK11: =SUM(BH11:BJ11) -> 0 | BO11: =SUM(BL11:BN11) -> 0 | BP11: =BO11+BK11+BG11+BC11 -> 0 | BS11: =INDEX($AZ11:$BN11,MATCH(BS$6,$AZ$6:$BN$6,0)) -> 0 | BT11: =INDEX($AZ11:$BN11,MATCH(BT$6,$AZ$6:$BN$6,0)) -> 0 | BU11: =SUM(BS11:BT11) -> 0 | BV11: =INDEX($AZ11:$BN11,MATCH(BV$6,$AZ$6:$BN$6,0)) -> 0 | BW11: =SUM(BU11:BV11) -> 0 | BX11: =INDEX($AZ11:$BN11,MATCH(BX$6,$AZ$6:$BN$6,0)) -> 0 | BY11: =SUM(BW11:BX11) -> 0 | BZ11: =INDEX($AZ11:$BN11,MATCH(BZ$6,$AZ$6:$BN$6,0)) -> 0 | CA11: =SUM(BY11:BZ11) -> 0 | CB11: =INDEX($AZ11:$BN11,MATCH(CB$6,$AZ$6:$BN$6,0)) -> 0 | CC11: =SUM(CA11:CB11) -> 0 | CD11: =INDEX($AZ11:$BN11,MATCH(CD$6,$AZ$6:$BN$6,0)) -> 0 | CE11: =SUM(CC11:CD11) -> 0 | CF11: =INDEX($AZ11:$BN11,MATCH(CF$6,$AZ$6:$BN$6,0)) -> 0 | CG11: =SUM(CE11:CF11) -> 0 | CH11: =INDEX($AZ11:$BN11,MATCH(CH$6,$AZ$6:$BN$6,0)) -> 0 | CI11: =SUM(CG11:CH11) -> 0 | CJ11: =INDEX($AZ11:$BN11,MATCH(CJ$6,$AZ$6:$BN$6,0)) -> 0 | CK11: =SUM(CI11:CJ11) -> 0 | CL11: =INDEX($AZ11:$BN11,MATCH(CL$6,$AZ$6:$BN$6,0)) -> 0 | CM11: =SUM(CK11:CL11) -> 0 | CN11: =INDEX($AZ11:$BN11,MATCH(CN$6,$AZ$6:$BN$6,0)) -> 0 | CO11: =SUM(CM11:CN11) -> 0 | CQ11: =AR11 | CR11: =AS11 -> 113 | CS11: =IFERROR(IF($CR11<=30,"",INDEX(Opex_expense_Type,MATCH($CR11,Index_card_code,0))),"") -> -- | CT11: =AU11 | CU11: =AV11 -> Revenues - Income | CW11: =IF(CW$6>month_of_report,0,-SUMIFS(TB_Balance_01,TB_Entity,CW$7,Cards_Selection,$CR11)) -> 0 | CX11: =IF(CX$6>month_of_report,0,-SUMIFS(TB_Balance_01,TB_Entity,CX$7,Cards_Selection,$CR11)) -> 0 | CY11: =IF(CY$6<=month_of_report,(IFERROR(INDEX($X$8:$AI$277,MATCH($CR11,$C$8:$C$277,0),MATCH(CY$6,$X$6:$AI$6,0)),0)),0) -> 0 | CZ11: =IF(CZ$6>month_of_report,0,-(SUMIFS(TB_Balance_02,TB_Entity,CZ$7,Cards_Selection,$CR11)-SUMIFS(TB_Balance_01,TB_Entity,CZ$7,Cards_Selection,$CR11))) -> 0 | DA11: =IF(DA$6>month_of_report,0,-(SUMIFS(TB_Balance_02,TB_Entity,DA$7,Cards_Selection,$CR11)-SUMIFS(TB_Balance_01,TB_Entity,DA$7,Cards_Selection,$CR11))) -> 0 | DB11: =IF(DB$6<=month_of_report,(IFERROR(INDEX($X$8:$AI$277,MATCH($CR11,$C$8:$C$277,0),MATCH(DB$6,$X$6:$AI$6,0)),0)),0) -> 0 | DC11: =IF(DC$6>month_of_report,0,-(SUMIFS(TB_Balance_03,TB_Entity,DC$7,Cards_Selection,$CR11)-SUMIFS(TB_Balance_02,TB_Entity,DC$7,Cards_Selection,$CR11))) -> 0 | DD11: =IF(DD$6>month_of_report,0,-(SUMIFS(TB_Balance_03,TB_Entity,DD$7,Cards_Selection,$CR11)-SUMIFS(TB_Balance_02,TB_Entity,DD$7,Cards_Selection,$CR11))) -> 0 | DE11: =IF(DE$6<=month_of_report,(IFERROR(INDEX($X$8:$AI$277,MATCH($CR11,$C$8:$C$277,0),MATCH(DE$6,$X$6:$AI$6,0)),0)),0) -> 0 | DF11: =SUM(DC11,CZ11,CW11) -> 0 | DG11: =SUM(DD11,DA11,CX11) -> 0 | DH11: =SUM(DE11,DB11,CY11) -> 0 | DI11: =IF(DI$6>month_of_report,0,-(SUMIFS(TB_Balance_04,TB_Entity,DI$7,Cards_Selection,$CR11)-SUMIFS(TB_Balance_03,TB_Entity,DI$7,Cards_Selection,$CR11))) -> 0 | DJ11: =IF(DJ$6>month_of_report,0,-(SUMIFS(TB_Balance_04,TB_Entity,DJ$7,Cards_Selection,$CR11)-SUMIFS(TB_Balance_03,TB_Entity,DJ$7,Cards_Selection,$CR11))) -> 0 | DK11: =IF(DK$6<=month_of_report,(IFERROR(INDEX($X$8:$AI$277,MATCH($CR11,$C$8:$C$277,0),MATCH(DK$6,$X$6:$AI$6,0)),0)),0) -> 0 | DL11: =IF(DL$6>month_of_report,0,-(SUMIFS(TB_Balance_05,TB_Entity,DL$7,Cards_Selection,$CR11)-SUMIFS(TB_Balance_04,TB_Entity,DL$7,Cards_Selection,$CR11))) -> 0 | DM11: =IF(DM$6>month_of_report,0,-(SUMIFS(TB_Balance_05,TB_Entity,DM$7,Cards_Selection,$CR11)-SUMIFS(TB_Balance_04,TB_Entity,DM$7,Cards_Selection,$CR11))) -> 0 | DN11: =IF(DN$6<=month_of_report,(IFERROR(INDEX($X$8:$AI$277,MATCH($CR11,$C$8:$C$277,0),MATCH(DN$6,$X$6:$AI$6,0)),0)),0) -> 0 | DO11: =IF(DO$6>month_of_report,0,-(SUMIFS(TB_Balance_06,TB_Entity,DO$7,Cards_Selection,$CR11)-SUMIFS(TB_Balance_05,TB_Entity,DO$7,Cards_Selection,$CR11))) -> 0 | DP11: =IF(DP$6>month_of_report,0,-(SUMIFS(TB_Balance_06,TB_Entity,DP$7,Cards_Selection,$CR11)-SUMIFS(TB_Balance_05,TB_Entity,DP$7,Cards_Selection,$CR11))) -> 0 | DQ11: =IF(DQ$6<=month_of_report,(IFERROR(INDEX($X$8:$AI$277,MATCH($CR11,$C$8:$C$277,0),MATCH(DQ$6,$X$6:$AI$6,0)),0)),0) -> 0 | DR11: =SUM(DO11,DL11,DI11) -> 0 | DS11: =SUM(DP11,DM11,DJ11) -> 0 | DT11: =SUM(DQ11,DN11,DK11) -> 0 | DU11: =IF(DU$6>month_of_report,0,-(SUMIFS(TB_Balance_07,TB_Entity,DU$7,Cards_Selection,$CR11)-SUMIFS(TB_Balance_06,TB_Entity,DU$7,Cards_Selection,$CR11))) -> 0 | DV11: =IF(DV$6>month_of_report,0,-(SUMIFS(TB_Balance_07,TB_Entity,DV$7,Cards_Selection,$CR11)-SUMIFS(TB_Balance_06,TB_Entity,DV$7,Cards_Selection,$CR11))) -> 0 | DW11: =IF(DW$6<=month_of_report,(IFERROR(INDEX($X$8:$AI$277,MATCH($CR11,$C$8:$C$277,0),MATCH(DW$6,$X$6:$AI$6,0)),0)),0) -> 0 | DX11: =IF(DX$6>month_of_report,0,-(SUMIFS(TB_Balance_08,TB_Entity,DX$7,Cards_Selection,$CR11)-SUMIFS(TB_Balance_07,TB_Entity,DX$7,Cards_Selection,$CR11))) -> 0 | DY11: =IF(DY$6>month_of_report,0,-(SUMIFS(TB_Balance_08,TB_Entity,DY$7,Cards_Selection,$CR11)-SUMIFS(TB_Balance_07,TB_Entity,DY$7,Cards_Selection,$CR11))) -> 0 | DZ11: =IF(DZ$6<=month_of_report,(IFERROR(INDEX($X$8:$AI$277,MATCH($CR11,$C$8:$C$277,0),MATCH(DZ$6,$X$6:$AI$6,0)),0)),0) -> 0 | EA11: =IF(EA$6>month_of_report,0,-(SUMIFS(TB_Balance_09,TB_Entity,EA$7,Cards_Selection,$CR11)-SUMIFS(TB_Balance_08,TB_Entity,EA$7,Cards_Selection,$CR11))) -> 0 | EB11: =IF(EB$6>month_of_report,0,-(SUMIFS(TB_Balance_09,TB_Entity,EB$7,Cards_Selection,$CR11)-SUMIFS(TB_Balance_08,TB_Entity,EB$7,Cards_Selection,$CR11))) -> 0 | EC11: =IF(EC$6<=month_of_report,(IFERROR(INDEX($X$8:$AI$277,MATCH($CR11,$C$8:$C$277,0),MATCH(EC$6,$X$6:$AI$6,0)),0)),0) -> 0 | ED11: =SUM(EA11,DX11,DU11) -> 0 | EE11: =SUM(EB11,DY11,DV11) -> 0 | EF11: =SUM(EC11,DZ11,DW11) -> 0 | EG11: =IF(EG$6>month_of_report,0,-(SUMIFS(TB_Balance_10,TB_Entity,EG$7,Cards_Selection,$CR11)-SUMIFS(TB_Balance_09,TB_Entity,EG$7,Cards_Selection,$CR11))) -> 0 | EH11: =IF(EH$6>month_of_report,0,-(SUMIFS(TB_Balance_10,TB_Entity,EH$7,Cards_Selection,$CR11)-SUMIFS(TB_Balance_09,TB_Entity,EH$7,Cards_Selection,$CR11))) -> 0 | EI11: =IF(EI$6<=month_of_report,(IFERROR(INDEX($X$8:$AI$277,MATCH($CR11,$C$8:$C$277,0),MATCH(EI$6,$X$6:$AI$6,0)),0)),0) -> 0 | EJ11: =IF(EJ$6>month_of_report,0,-(SUMIFS(TB_Balance_11,TB_Entity,EJ$7,Cards_Selection,$CR11)-SUMIFS(TB_Balance_10,TB_Entity,EJ$7,Cards_Selection,$CR11))) -> 0 | EK11: =IF(EK$6>month_of_report,0,-(SUMIFS(TB_Balance_11,TB_Entity,EK$7,Cards_Selection,$CR11)-SUMIFS(TB_Balance_10,TB_Entity,EK$7,Cards_Selection,$CR11))) -> 0 | EL11: =IF(EL$6<=month_of_report,(IFERROR(INDEX($X$8:$AI$277,MATCH($CR11,$C$8:$C$277,0),MATCH(EL$6,$X$6:$AI$6,0)),0)),0) -> 0 | EM11: =IF(EM$6>month_of_report,0,-(SUMIFS(TB_Balance_12,TB_Entity,EM$7,Cards_Selection,$CR11)-SUMIFS(TB_Balance_11,TB_Entity,EM$7,Cards_Selection,$CR11))) -> 0 | EN11: =IF(EN$6>month_of_report,0,-(SUMIFS(TB_Balance_12,TB_Entity,EN$7,Cards_Selection,$CR11)-SUMIFS(TB_Balance_11,TB_Entity,EN$7,Cards_Selection,$CR11))) -> 0 | EO11: =IF(EO$6<=month_of_report,(IFERROR(INDEX($X$8:$AI$277,MATCH($CR11,$C$8:$C$277,0),MATCH(EO$6,$X$6:$AI$6,0)),0)),0) -> 0 | EP11: =SUM(EM11,EJ11,EG11) -> 0 | EQ11: =SUM(EN11,EK11,EH11) -> 0 | ER11: =SUM(EO11,EL11,EI11) -> 0
D12: =IF($C12<=30,"",INDEX(Opex_expense_Type,MATCH($C12,Index_card_code,0))) | F12: =IFERROR(INDEX(Index_Card_name,MATCH($C12,Index_card_code,0)),"") | H12: =INDEX($X12:$AI12,,MATCH($H$6,$X$6:$AI$6,0)) -> 0 | I12: =SUMIF(Cards_selection_BPL,$C12,INDIRECT(Index!$P$16)) -> 0 | J12: =+H12-I12 -> 0 | L12: =IF(LEFT($L$6,2)="Q1",SUMIFS($X12:$Z12,$X$6:$Z$6,"<="&month_of_report),IF(LEFT($L$6,2)="Q2",SUMIFS($AA12:$AC12,$AA$6:$AC$6,"<="&month_of_report),IF(LEFT($L$6,2)="Q3",SUMIFS($AD12:$AF12,$AD$6:$AF$6,"<="&month_of_report),IF(LEFT($L$6,2)="Q4",SUMIFS($AG12:$AI12,$AG$6:$AI$6,"<="&month_of_report),0)))) -> 0 | M12: =IF(LEFT($L$6,2)="Q1",SUMIF(Cards_selection_BPL,$C12,INDIRECT(Index!$Q$16)),IF(LEFT($L$6,2)="Q2",SUMIF(Cards_selection_BPL,$C12,INDIRECT(Index!$Q$16))-SUMIF(Cards_selection_BPL,$C12,Balance_bplm_03),IF(LEFT($L$6,2)="Q3",SUMIF(Cards_selection_BPL,$C12,INDIRECT(Index!$Q$16))-SUMIF(Cards_selection_BPL,$C12,Balance_bplm_06),IF(LEFT($L$6,2)="Q4",SUMIF(Cards_selection_BPL,$C12,INDIRECT(Index!$Q$16))-SUMIF(Cards_selection_BPL,$C12,Balance_bplm_09),0)))) -> 0 | N12: =+L12-M12 -> 0 | P12: =SUMIFS($X12:$AI12,$X$6:$AI$6,"<="&month_of_report) -> 0 | Q12: =SUMIF(Cards_selection_BPL,$C12,INDIRECT(Index!$Q$16)) -> 0 | R12: =+P12-Q12 -> 0 | X12: =-IF(X$6<=month_of_report,(SUMIF(Cards_Selection,$C12,TB_Balance_01)),0) -> 0 | Y12: =-IF(Y$6<=month_of_report,(SUMIF(Cards_Selection,$C12,TB_Balance_02)-SUMIF(Cards_Selection,$C12,TB_Balance_01)),0) -> 0 | Z12: =-IF(Z$6<=month_of_report,(SUMIF(Cards_Selection,$C12,TB_Balance_03)-SUMIF(Cards_Selection,$C12,TB_Balance_02)),0) -> 0 | AA12: =-IF(AA$6<=month_of_report,(SUMIF(Cards_Selection,$C12,TB_Balance_04)-SUMIF(Cards_Selection,$C12,TB_Balance_03)),0) -> 0 | AB12: =-IF(AB$6<=month_of_report,(SUMIF(Cards_Selection,$C12,TB_Balance_05)-SUMIF(Cards_Selection,$C12,TB_Balance_04)),0) -> 0 | AC12: =-IF(AC$6<=month_of_report,(SUMIF(Cards_Selection,$C12,TB_Balance_06)-SUMIF(Cards_Selection,$C12,TB_Balance_05)),0) -> 0 | AD12: =-IF(AD$6<=month_of_report,(SUMIF(Cards_Selection,$C12,TB_Balance_07)-SUMIF(Cards_Selection,$C12,TB_Balance_06)),0) -> 0 | AE12: =-IF(AE$6<=month_of_report,(SUMIF(Cards_Selection,$C12,TB_Balance_08)-SUMIF(Cards_Selection,$C12,TB_Balance_07)),0) -> 0 | AF12: =-IF(AF$6<=month_of_report,(SUMIF(Cards_Selection,$C12,TB_Balance_09)-SUMIF(Cards_Selection,$C12,TB_Balance_08)),0) -> 0 | AG12: =-IF(AG$6<=month_of_report,(SUMIF(Cards_Selection,$C12,TB_Balance_10)-SUMIF(Cards_Selection,$C12,TB_Balance_09)),0) -> 0 | AH12: =-IF(AH$6<=month_of_report,(SUMIF(Cards_Selection,$C12,TB_Balance_11)-SUMIF(Cards_Selection,$C12,TB_Balance_10)),0) -> 0 | AI12: =-IF(AI$6<=month_of_report,(SUMIF(Cards_Selection,$C12,TB_Balance_12)-SUMIF(Cards_Selection,$C12,TB_Balance_09)),0) -> 0 | AM12: =P12 -> 0 | AN12: =-IF(AN$6<=month_of_report,SUMIF(Cards_Selection,$C12,TB_Balance_12_Nis),0) -> 0 | AR12: =IF(B12="","",B12) | AS12: =IF(C12="","",C12) | AT12: =IFERROR(IF($AS12<=30,"",INDEX(Opex_expense_Type,MATCH($AS12,Index_card_code,0))),"") | AU12: =IF(E12="","",E12) | AV12: =IF(F12="","",F12) | BC12: =SUM(AZ12:BB12) -> 0 | BG12: =SUM(BD12:BF12) -> 0 | BK12: =SUM(BH12:BJ12) -> 0 | BO12: =SUM(BL12:BN12) -> 0 | BP12: =BO12+BK12+BG12+BC12 -> 0 | BS12: =INDEX($AZ12:$BN12,MATCH(BS$6,$AZ$6:$BN$6,0)) -> 0 | BT12: =INDEX($AZ12:$BN12,MATCH(BT$6,$AZ$6:$BN$6,0)) -> 0 | BU12: =SUM(BS12:BT12) -> 0 | BV12: =INDEX($AZ12:$BN12,MATCH(BV$6,$AZ$6:$BN$6,0)) -> 0 | BW12: =SUM(BU12:BV12) -> 0 | BX12: =INDEX($AZ12:$BN12,MATCH(BX$6,$AZ$6:$BN$6,0)) -> 0 | BY12: =SUM(BW12:BX12) -> 0 | BZ12: =INDEX($AZ12:$BN12,MATCH(BZ$6,$AZ$6:$BN$6,0)) -> 0 | CA12: =SUM(BY12:BZ12) -> 0 | CB12: =INDEX($AZ12:$BN12,MATCH(CB$6,$AZ$6:$BN$6,0)) -> 0 | CC12: =SUM(CA12:CB12) -> 0 | CD12: =INDEX($AZ12:$BN12,MATCH(CD$6,$AZ$6:$BN$6,0)) -> 0 | CE12: =SUM(CC12:CD12) -> 0 | CF12: =INDEX($AZ12:$BN12,MATCH(CF$6,$AZ$6:$BN$6,0)) -> 0 | CG12: =SUM(CE12:CF12) -> 0 | CH12: =INDEX($AZ12:$BN12,MATCH(CH$6,$AZ$6:$BN$6,0)) -> 0 | CI12: =SUM(CG12:CH12) -> 0 | CJ12: =INDEX($AZ12:$BN12,MATCH(CJ$6,$AZ$6:$BN$6,0)) -> 0 | CK12: =SUM(CI12:CJ12) -> 0 | CL12: =INDEX($AZ12:$BN12,MATCH(CL$6,$AZ$6:$BN$6,0)) -> 0 | CM12: =SUM(CK12:CL12) -> 0 | CN12: =INDEX($AZ12:$BN12,MATCH(CN$6,$AZ$6:$BN$6,0)) -> 0 | CO12: =SUM(CM12:CN12) -> 0 | CQ12: =AR12 | CR12: =AS12 | CS12: =IFERROR(IF($CR12<=30,"",INDEX(Opex_expense_Type,MATCH($CR12,Index_card_code,0))),"") | CT12: =AU12 | CU12: =AV12 | CW12: =IF(CW$6>month_of_report,0,-SUMIFS(TB_Balance_01,TB_Entity,CW$7,Cards_Selection,$CR12)) -> 0 | CX12: =IF(CX$6>month_of_report,0,-SUMIFS(TB_Balance_01,TB_Entity,CX$7,Cards_Selection,$CR12)) -> 0 | CY12: =IF(CY$6<=month_of_report,(IFERROR(INDEX($X$8:$AI$277,MATCH($CR12,$C$8:$C$277,0),MATCH(CY$6,$X$6:$AI$6,0)),0)),0) -> 0 | CZ12: =IF(CZ$6>month_of_report,0,-(SUMIFS(TB_Balance_02,TB_Entity,CZ$7,Cards_Selection,$CR12)-SUMIFS(TB_Balance_01,TB_Entity,CZ$7,Cards_Selection,$CR12))) -> 0 | DA12: =IF(DA$6>month_of_report,0,-(SUMIFS(TB_Balance_02,TB_Entity,DA$7,Cards_Selection,$CR12)-SUMIFS(TB_Balance_01,TB_Entity,DA$7,Cards_Selection,$CR12))) -> 0 | DB12: =IF(DB$6<=month_of_report,(IFERROR(INDEX($X$8:$AI$277,MATCH($CR12,$C$8:$C$277,0),MATCH(DB$6,$X$6:$AI$6,0)),0)),0) -> 0 | DC12: =IF(DC$6>month_of_report,0,-(SUMIFS(TB_Balance_03,TB_Entity,DC$7,Cards_Selection,$CR12)-SUMIFS(TB_Balance_02,TB_Entity,DC$7,Cards_Selection,$CR12))) -> 0 | DD12: =IF(DD$6>month_of_report,0,-(SUMIFS(TB_Balance_03,TB_Entity,DD$7,Cards_Selection,$CR12)-SUMIFS(TB_Balance_02,TB_Entity,DD$7,Cards_Selection,$CR12))) -> 0 | DE12: =IF(DE$6<=month_of_report,(IFERROR(INDEX($X$8:$AI$277,MATCH($CR12,$C$8:$C$277,0),MATCH(DE$6,$X$6:$AI$6,0)),0)),0) -> 0 | DF12: =SUM(DC12,CZ12,CW12) -> 0 | DG12: =SUM(DD12,DA12,CX12) -> 0 | DH12: =SUM(DE12,DB12,CY12) -> 0 | DI12: =IF(DI$6>month_of_report,0,-(SUMIFS(TB_Balance_04,TB_Entity,DI$7,Cards_Selection,$CR12)-SUMIFS(TB_Balance_03,TB_Entity,DI$7,Cards_Selection,$CR12))) -> 0 | DJ12: =IF(DJ$6>month_of_report,0,-(SUMIFS(TB_Balance_04,TB_Entity,DJ$7,Cards_Selection,$CR12)-SUMIFS(TB_Balance_03,TB_Entity,DJ$7,Cards_Selection,$CR12))) -> 0 | DK12: =IF(DK$6<=month_of_report,(IFERROR(INDEX($X$8:$AI$277,MATCH($CR12,$C$8:$C$277,0),MATCH(DK$6,$X$6:$AI$6,0)),0)),0) -> 0 | DL12: =IF(DL$6>month_of_report,0,-(SUMIFS(TB_Balance_05,TB_Entity,DL$7,Cards_Selection,$CR12)-SUMIFS(TB_Balance_04,TB_Entity,DL$7,Cards_Selection,$CR12))) -> 0 | DM12: =IF(DM$6>month_of_report,0,-(SUMIFS(TB_Balance_05,TB_Entity,DM$7,Cards_Selection,$CR12)-SUMIFS(TB_Balance_04,TB_Entity,DM$7,Cards_Selection,$CR12))) -> 0 | DN12: =IF(DN$6<=month_of_report,(IFERROR(INDEX($X$8:$AI$277,MATCH($CR12,$C$8:$C$277,0),MATCH(DN$6,$X$6:$AI$6,0)),0)),0) -> 0 | DO12: =IF(DO$6>month_of_report,0,-(SUMIFS(TB_Balance_06,TB_Entity,DO$7,Cards_Selection,$CR12)-SUMIFS(TB_Balance_05,TB_Entity,DO$7,Cards_Selection,$CR12))) -> 0 | DP12: =IF(DP$6>month_of_report,0,-(SUMIFS(TB_Balance_06,TB_Entity,DP$7,Cards_Selection,$CR12)-SUMIFS(TB_Balance_05,TB_Entity,DP$7,Cards_Selection,$CR12))) -> 0 | DQ12: =IF(DQ$6<=month_of_report,(IFERROR(INDEX($X$8:$AI$277,MATCH($CR12,$C$8:$C$277,0),MATCH(DQ$6,$X$6:$AI$6,0)),0)),0) -> 0 | DR12: =SUM(DO12,DL12,DI12) -> 0 | DS12: =SUM(DP12,DM12,DJ12) -> 0 | DT12: =SUM(DQ12,DN12,DK12) -> 0 | DU12: =IF(DU$6>month_of_report,0,-(SUMIFS(TB_Balance_07,TB_Entity,DU$7,Cards_Selection,$CR12)-SUMIFS(TB_Balance_06,TB_Entity,DU$7,Cards_Selection,$CR12))) -> 0 | DV12: =IF(DV$6>month_of_report,0,-(SUMIFS(TB_Balance_07,TB_Entity,DV$7,Cards_Selection,$CR12)-SUMIFS(TB_Balance_06,TB_Entity,DV$7,Cards_Selection,$CR12))) -> 0 | DW12: =IF(DW$6<=month_of_report,(IFERROR(INDEX($X$8:$AI$277,MATCH($CR12,$C$8:$C$277,0),MATCH(DW$6,$X$6:$AI$6,0)),0)),0) -> 0 | DX12: =IF(DX$6>month_of_report,0,-(SUMIFS(TB_Balance_08,TB_Entity,DX$7,Cards_Selection,$CR12)-SUMIFS(TB_Balance_07,TB_Entity,DX$7,Cards_Selection,$CR12))) -> 0 | DY12: =IF(DY$6>month_of_report,0,-(SUMIFS(TB_Balance_08,TB_Entity,DY$7,Cards_Selection,$CR12)-SUMIFS(TB_Balance_07,TB_Entity,DY$7,Cards_Selection,$CR12))) -> 0 | DZ12: =IF(DZ$6<=month_of_report,(IFERROR(INDEX($X$8:$AI$277,MATCH($CR12,$C$8:$C$277,0),MATCH(DZ$6,$X$6:$AI$6,0)),0)),0) -> 0 | EA12: =IF(EA$6>month_of_report,0,-(SUMIFS(TB_Balance_09,TB_Entity,EA$7,Cards_Selection,$CR12)-SUMIFS(TB_Balance_08,TB_Entity,EA$7,Cards_Selection,$CR12))) -> 0 | EB12: =IF(EB$6>month_of_report,0,-(SUMIFS(TB_Balance_09,TB_Entity,EB$7,Cards_Selection,$CR12)-SUMIFS(TB_Balance_08,TB_Entity,EB$7,Cards_Selection,$CR12))) -> 0 | EC12: =IF(EC$6<=month_of_report,(IFERROR(INDEX($X$8:$AI$277,MATCH($CR12,$C$8:$C$277,0),MATCH(EC$6,$X$6:$AI$6,0)),0)),0) -> 0 | ED12: =SUM(EA12,DX12,DU12) -> 0 | EE12: =SUM(EB12,DY12,DV12) -> 0 | EF12: =SUM(EC12,DZ12,DW12) -> 0 | EG12: =IF(EG$6>month_of_report,0,-(SUMIFS(TB_Balance_10,TB_Entity,EG$7,Cards_Selection,$CR12)-SUMIFS(TB_Balance_09,TB_Entity,EG$7,Cards_Selection,$CR12))) -> 0 | EH12: =IF(EH$6>month_of_report,0,-(SUMIFS(TB_Balance_10,TB_Entity,EH$7,Cards_Selection,$CR12)-SUMIFS(TB_Balance_09,TB_Entity,EH$7,Cards_Selection,$CR12))) -> 0 | EI12: =IF(EI$6<=month_of_report,(IFERROR(INDEX($X$8:$AI$277,MATCH($CR12,$C$8:$C$277,0),MATCH(EI$6,$X$6:$AI$6,0)),0)),0) -> 0 | EJ12: =IF(EJ$6>month_of_report,0,-(SUMIFS(TB_Balance_11,TB_Entity,EJ$7,Cards_Selection,$CR12)-SUMIFS(TB_Balance_10,TB_Entity,EJ$7,Cards_Selection,$CR12))) -> 0 | EK12: =IF(EK$6>month_of_report,0,-(SUMIFS(TB_Balance_11,TB_Entity,EK$7,Cards_Selection,$CR12)-SUMIFS(TB_Balance_10,TB_Entity,EK$7,Cards_Selection,$CR12))) -> 0 | EL12: =IF(EL$6<=month_of_report,(IFERROR(INDEX($X$8:$AI$277,MATCH($CR12,$C$8:$C$277,0),MATCH(EL$6,$X$6:$AI$6,0)),0)),0) -> 0 | EM12: =IF(EM$6>month_of_report,0,-(SUMIFS(TB_Balance_12,TB_Entity,EM$7,Cards_Selection,$CR12)-SUMIFS(TB_Balance_11,TB_Entity,EM$7,Cards_Selection,$CR12))) -> 0 | EN12: =IF(EN$6>month_of_report,0,-(SUMIFS(TB_Balance_12,TB_Entity,EN$7,Cards_Selection,$CR12)-SUMIFS(TB_Balance_11,TB_Entity,EN$7,Cards_Selection,$CR12))) -> 0 | EO12: =IF(EO$6<=month_of_report,(IFERROR(INDEX($X$8:$AI$277,MATCH($CR12,$C$8:$C$277,0),MATCH(EO$6,$X$6:$AI$6,0)),0)),0) -> 0 | EP12: =SUM(EM12,EJ12,EG12) -> 0 | EQ12: =SUM(EN12,EK12,EH12) -> 0 | ER12: =SUM(EO12,EL12,EI12) -> 0
