Workbook

Sheet BS USD
C1: Wematch.live
C2: USD
E5: EQD | F5: WUS- LLC | G5: WIR | H5: WSF- LTD [IL] | I5: WSF (UK) | J5: WUS- INC | K5: R&D | L5: WTSE | M5: Elimination | N5: Elimination US | P5: JE'S | Q5: Total
E6: =+'BS ILS'!$E$6 -> 31.12.2023 | F6: =+'BS ILS'!$E$6 -> 31.12.2023 | G6: =+'BS ILS'!$E$6 -> 31.12.2023 | H6: =+'BS ILS'!$E$6 -> 31.12.2023 | I6: =+'BS ILS'!$E$6 -> 31.12.2023 | J6: =+'BS ILS'!$E$6 -> 31.12.2023 | K6: =+'BS ILS'!$E$6 -> 31.12.2023 | L6: =+'BS ILS'!$E$6 -> 31.12.2023 | Q6: =+'BS ILS'!$E$6 -> 31.12.2023 | S6: in 000' | U6: NOTE
B7: INDEX
C8: Assets | S8: =+Q8/1000 -> 0
C10: Current Assets: | S10: =+Q10/1000 -> 0
B11: 10 | C11: Cash and cash equivalent | E11: =+SUMIF('Full BS-USD'!$M:$M,B11,'Full BS-USD'!$D:$D) -> 20694.27 | F11: =+SUMIF('Full BS-USD'!$M:$M,B11,'Full BS-USD'!$G:$G) -> 1183093.2 | G11: =+SUMIF('Full BS-USD'!$M:$M,B11,'Full BS-USD'!$E:$E) -> 21.14 | H11: =+SUMIF('Full BS-USD'!$M:$M,B11,'Full BS-USD'!$F:$F) -> 299.37 | I11: =+SUMIF('Full BS-USD'!$M:$M,B11,'Full BS-USD'!$H:$H) -> 195757.56 | J11: =+SUMIF('Full BS-USD'!$M:$M,B11,'Full BS-USD'!$I:$I) -> 490094.22 | K11: =+SUMIF('Full BS-USD'!$M:$M,B11,'Full BS-USD'!$J:$J) -> 3193193.2 | L11: =+SUMIF('Full BS-USD'!$M:$M,B11,'Full BS-USD'!$K:$K) -> 208398.82 | M11: =+SUMIF('Full BS-USD'!$M:$M,B11,'Full BS-USD'!$B:$B) -> 0 | N11: =+SUMIF('Full BS-USD'!$M:$M,B11,'Full BS-USD'!$C:$C) -> 0 | Q11: =+SUMIF('Full BS-USD'!$M:$M,B11,'Full BS-USD'!$L:$L) -> 5291551.8 | R11: =+Q11-SUM(E11:N11) -> 0 | S11: =+ROUND((Q11/1000),0) -> 5292
B12: 11 | C12: Short term restricted deposits | E12: =+SUMIF('Full BS-USD'!$M:$M,B12,'Full BS-USD'!$D:$D) -> 0 | F12: =+SUMIF('Full BS-USD'!$M:$M,B12,'Full BS-USD'!$G:$G) -> 0 | G12: =+SUMIF('Full BS-USD'!$M:$M,B12,'Full BS-USD'!$E:$E) -> 0 | H12: =+SUMIF('Full BS-USD'!$M:$M,B12,'Full BS-USD'!$F:$F) -> 0 | I12: =+SUMIF('Full BS-USD'!$M:$M,B12,'Full BS-USD'!$H:$H) -> 0 | J12: =+SUMIF('Full BS-USD'!$M:$M,B12,'Full BS-USD'!$I:$I) -> 0 | K12: =+SUMIF('Full BS-USD'!$M:$M,B12,'Full BS-USD'!$J:$J) -> 7718871.7 | L12: =+SUMIF('Full BS-USD'!$M:$M,B12,'Full BS-USD'!$K:$K) -> 607156 | M12: =+SUMIF('Full BS-USD'!$M:$M,B12,'Full BS-USD'!$B:$B) -> 0 | N12: =+SUMIF('Full BS-USD'!$M:$M,B12,'Full BS-USD'!$C:$C) -> 0 | Q12: =+SUMIF('Full BS-USD'!$M:$M,B12,'Full BS-USD'!$L:$L) -> 8326027.7 | R12: =+Q12-SUM(E12:N12) -> 0 | S12: =+ROUND((Q12/1000),0) -> 8326
B13: 12 | C13: Trade recievables | E13: =+SUMIF('Full BS-USD'!$M:$M,B13,'Full BS-USD'!$D:$D) -> 0 | F13: =+SUMIF('Full BS-USD'!$M:$M,B13,'Full BS-USD'!$G:$G) -> 0 | G13: =+SUMIF('Full BS-USD'!$M:$M,B13,'Full BS-USD'!$E:$E) -> 0 | H13: =+SUMIF('Full BS-USD'!$M:$M,B13,'Full BS-USD'!$F:$F) -> 0 | I13: =+SUMIF('Full BS-USD'!$M:$M,B13,'Full BS-USD'!$H:$H) -> 0 | J13: =+SUMIF('Full BS-USD'!$M:$M,B13,'Full BS-USD'!$I:$I) -> 0 | K13: =+SUMIF('Full BS-USD'!$M:$M,B13,'Full BS-USD'!$J:$J) -> 658882.12 | L13: =+SUMIF('Full BS-USD'!$M:$M,B13,'Full BS-USD'!$K:$K) -> 0 | M13: =+SUMIF('Full BS-USD'!$M:$M,B13,'Full BS-USD'!$B:$B) -> 0 | N13: =+SUMIF('Full BS-USD'!$M:$M,B13,'Full BS-USD'!$C:$C) -> 0 | Q13: =+SUMIF('Full BS-USD'!$M:$M,B13,'Full BS-USD'!$L:$L) -> 658882.12 | R13: =+Q13-SUM(E13:N13) -> 0 | S13: =+ROUND((Q13/1000),0) -> 659 | U13: =+'NOTES-Conso'!B5 -> 3
B14: 13 | C14: other recievables and prepaid expenses | E14: =+SUMIF('Full BS-USD'!$M:$M,B14,'Full BS-USD'!$D:$D) -> 4101.54 | F14: =+SUMIF('Full BS-USD'!$M:$M,B14,'Full BS-USD'!$G:$G) -> 1359.83 | G14: =+SUMIF('Full BS-USD'!$M:$M,B14,'Full BS-USD'!$E:$E) -> 491.94 | H14: =+SUMIF('Full BS-USD'!$M:$M,B14,'Full BS-USD'!$F:$F) -> 48261.82 | I14: =+SUMIF('Full BS-USD'!$M:$M,B14,'Full BS-USD'!$H:$H) -> 2433115 | J14: =+SUMIF('Full BS-USD'!$M:$M,B14,'Full BS-USD'!$I:$I) -> 546686.67 | K14: =+SUMIF('Full BS-USD'!$M:$M,B14,'Full BS-USD'!$J:$J) -> 5432383.5 | L14: =+SUMIF('Full BS-USD'!$M:$M,B14,'Full BS-USD'!$K:$K) -> 975458.86 | M14: =+SUMIF('Full BS-USD'!$M:$M,B14,'Full BS-USD'!$B:$B) -> -8791437.7 | N14: =+SUMIF('Full BS-USD'!$M:$M,B14,'Full BS-USD'!$C:$C) -> 8338.78 | Q14: =+SUMIF('Full BS-USD'!$M:$M,B14,'Full BS-USD'!$L:$L) -> 658760.23 | R14: =+Q14-SUM(E14:N14) -> -1.3969839e-09 | S14: =+ROUND((Q14/1000),0) -> 659 | U14: =+'NOTES-Conso'!B10 -> 4
R15: =+Q15-SUM(E15:N15) -> 0 | S15: =+Q15/1000 -> 0
C16: Total cerrent assets | E16: =+SUM(E11:E14) -> 24795.81 | F16: =+SUM(F11:F14) -> 1184453 | G16: =+SUM(G11:G14) -> 513.08 | H16: =+SUM(H11:H14) -> 48561.19 | I16: =+SUM(I11:I14) -> 2628872.6 | J16: =+SUM(J11:J14) -> 1036780.9 | K16: =+SUM(K11:K14) -> 17003331 | L16: =+SUM(L11:L14) -> 1791013.7 | ... N16: =+SUM(N11:N14) -> 8338.78 | Q16: =+SUM(Q11:Q14) -> 14935222 | R16: =+Q16-SUM(E16:N16) -> 0 | S16: =+SUM(S11:S14) -> 14936
R17: =+Q17-SUM(E17:N17) -> 0 | S17: =+Q17/1000 -> 0
R18: =+Q18-SUM(E18:N18) -> 0
C19: Long-Term assets: | R19: =+Q19-SUM(E19:N19) -> 0
B20: 14 | C20: loans to employees | E20: =+SUMIF('Full BS-USD'!$M:$M,B20,'Full BS-USD'!$D:$D) -> 38487.03 | F20: =+SUMIF('Full BS-USD'!$M:$M,B20,'Full BS-USD'!$G:$G) -> 0 | G20: =+SUMIF('Full BS-USD'!$M:$M,B20,'Full BS-USD'!$E:$E) -> 0 | H20: =+SUMIF('Full BS-USD'!$M:$M,B20,'Full BS-USD'!$F:$F) -> 0 | I20: =+SUMIF('Full BS-USD'!$M:$M,B20,'Full BS-USD'!$H:$H) -> 0 | J20: =+SUMIF('Full BS-USD'!$M:$M,B20,'Full BS-USD'!$I:$I) -> 0 | K20: =+SUMIF('Full BS-USD'!$M:$M,B20,'Full BS-USD'!$J:$J) -> 261263.83 | L20: =+SUMIF('Full BS-USD'!$M:$M,B20,'Full BS-USD'!$K:$K) -> 0 | M20: =+SUMIF('Full BS-USD'!$M:$M,B20,'Full BS-USD'!$B:$B) -> -261263.83 | N20: =+SUMIF('Full BS-USD'!$M:$M,B20,'Full BS-USD'!$C:$C) -> 0 | Q20: =+SUMIF('Full BS-USD'!$M:$M,B20,'Full BS-USD'!$L:$L) -> 38487.03 | R20: =+Q20-SUM(E20:N20) -> 0 | S20: =+ROUND((Q20/1000),0) -> 38
B21: 15 | C21: property and equipment | E21: =+SUMIF('Full BS-USD'!$M:$M,B21,'Full BS-USD'!$D:$D) -> 0 | F21: =+SUMIF('Full BS-USD'!$M:$M,B21,'Full BS-USD'!$G:$G) -> 279.12 | G21: =+SUMIF('Full BS-USD'!$M:$M,B21,'Full BS-USD'!$E:$E) -> 0 | H21: =+SUMIF('Full BS-USD'!$M:$M,B21,'Full BS-USD'!$F:$F) -> 0 | I21: =+SUMIF('Full BS-USD'!$M:$M,B21,'Full BS-USD'!$H:$H) -> 46935.5 | J21: =+SUMIF('Full BS-USD'!$M:$M,B21,'Full BS-USD'!$I:$I) -> 4503.67 | K21: =+SUMIF('Full BS-USD'!$M:$M,B21,'Full BS-USD'!$J:$J) -> 53053.19 | L21: =+SUMIF('Full BS-USD'!$M:$M,B21,'Full BS-USD'!$K:$K) -> 16549.81 | M21: =+SUMIF('Full BS-USD'!$M:$M,B21,'Full BS-USD'!$B:$B) -> 0 | N21: =+SUMIF('Full BS-USD'!$M:$M,B21,'Full BS-USD'!$C:$C) -> 0 | Q21: =+SUMIF('Full BS-USD'!$M:$M,B21,'Full BS-USD'!$L:$L) -> 121321.29 | R21: =+Q21-SUM(E21:N21) -> 0 | S21: =+ROUND((Q21/1000),0) -> 121 | U21: 5
R22: =+Q22-SUM(E22:N22) -> 0
R23: =+Q23-SUM(E23:N23) -> 0
C24: Total Long-term assets | E24: =+E20+E21 -> 38487.03 | F24: =+F20+F21 -> 279.12 | G24: =+G20+G21 -> 0 | H24: =+H20+H21 -> 0 | I24: =+I20+I21 -> 46935.5 | J24: =+J20+J21 -> 4503.67 | K24: =+K20+K21 -> 314317.02 | L24: =+L20+L21 -> 16549.81 | ... N24: =+N20+N21 -> 0 | Q24: =+Q20+Q21 -> 159808.32 | R24: =+Q24-SUM(E24:N24) -> 0 | S24: =+ROUND(Q24/1000,0) -> 160
R25: =+Q25-SUM(E25:N25) -> 0
R26: =+Q26-SUM(E26:N26) -> 0
C27: Total assets | E27: =+E24+E16 -> 63282.84 | F27: =+F24+F16 -> 1184732.1 | G27: =+G24+G16 -> 513.08 | H27: =+H24+H16 -> 48561.19 | I27: =+I24+I16 -> 2675808.1 | J27: =+J24+J16 -> 1041284.6 | K27: =+K24+K16 -> 17317648 | L27: =+L24+L16 -> 1807563.5 | ... N27: =+N24+N16 -> 8338.78 | Q27: =+Q24+Q16 -> 15095030 | R27: =+Q27-SUM(E27:N27) -> 0 | S27: =+S24+S16 -> 15096
R28: =+Q28-SUM(E28:N28) -> 0
R29: =+Q29-SUM(E29:N29) -> 0 | S29: =+Q29/1000 -> 0
C30: Liabilities and shareholders' equity | R30: =+Q30-SUM(E30:N30) -> 0
R31: =+Q31-SUM(E31:N31) -> 0
C32: Current Liabilities: | R32: =+Q32-SUM(E32:N32) -> 0
R33: =+Q33-SUM(E33:N33) -> 0
B34: 16 | C34: Trade payables | E34: =+SUMIF('Full BS-USD'!$M:$M,B34,'Full BS-USD'!$D:$D) -> 0 | F34: =+SUMIF('Full BS-USD'!$M:$M,B34,'Full BS-USD'!$G:$G)+'Full BS-USD'!G157 -> 8115.99 | G34: =+SUMIF('Full BS-USD'!$M:$M,B34,'Full BS-USD'!$E:$E)+'Full BS-USD'!E157 -> 0 | H34: =+SUMIF('Full BS-USD'!$M:$M,B34,'Full BS-USD'!$F:$F)+'Full BS-USD'!F157 -> 0 | I34: =+SUMIF('Full BS-USD'!$M:$M,B34,'Full BS-USD'!$H:$H)+'Full BS-USD'!H157 -> 30952.4 | J34: =+SUMIF('Full BS-USD'!$M:$M,B34,'Full BS-USD'!$I:$I)+'Full BS-USD'!I157 -> 5746.28 | K34: =+SUMIF('Full BS-USD'!$M:$M,B34,'Full BS-USD'!$J:$J)+'Full BS-USD'!J157 -> 93784.12 | L34: =+SUMIF('Full BS-USD'!$M:$M,B34,'Full BS-USD'!$K:$K)+'Full BS-USD'!K157 -> 28738.66 | M34: =+SUMIF('Full BS-USD'!$M:$M,B34,'Full BS-USD'!$B:$B)+'Full BS-USD'!B157 -> 0.01 | N34: =+SUMIF('Full BS-USD'!$M:$M,B34,'Full BS-USD'!$C:$C) -> 0 | Q34: =+SUMIF('Full BS-USD'!$M:$M,B34,'Full BS-USD'!$L:$L)+'Full BS-USD'!L157 -> 167337.46 | R34: =+Q34-SUM(E34:N34) -> 0 | S34: =+ROUND((Q34/1000),0) -> 167
B35: 17 | C35: Accrued expenses and other liabilities | E35: =+SUMIF('Full BS-USD'!$M:$M,B35,'Full BS-USD'!$D:$D) -> 320.38 | F35: =+SUMIF('Full BS-USD'!$M:$M,B35,'Full BS-USD'!$G:$G) -> 21787.94 | G35: =+SUMIF('Full BS-USD'!$M:$M,B35,'Full BS-USD'!$E:$E) -> 320.38 | H35: =+SUMIF('Full BS-USD'!$M:$M,B35,'Full BS-USD'!$F:$F) -> 8858.12 | I35: =+SUMIF('Full BS-USD'!$M:$M,B35,'Full BS-USD'!$H:$H) -> 2128996.9 | J35: =+SUMIF('Full BS-USD'!$M:$M,B35,'Full BS-USD'!$I:$I) -> 346957.74 | K35: =+SUMIF('Full BS-USD'!$M:$M,B35,'Full BS-USD'!$J:$J) -> 4359939.4 | L35: =+SUMIF('Full BS-USD'!$M:$M,B35,'Full BS-USD'!$K:$K) -> 1432154.3 | M35: =+SUMIF('Full BS-USD'!$M:$M,B35,'Full BS-USD'!$B:$B) -> -8789619.4 | N35: =+SUMIF('Full BS-USD'!$M:$M,B35,'Full BS-USD'!$C:$C) -> 1608338.8 | Q35: =+SUMIF('Full BS-USD'!$M:$M,B35,'Full BS-USD'!$L:$L) -> 1118054.6 | R35: =+Q35-SUM(E35:N35) -> 0 | S35: =+ROUND((Q35/1000),0) -> 1118 | U35: =+'NOTES-Conso'!B27 -> 6
R36: =+Q36-SUM(E36:N36) -> 0
C37: Total current liabilities | E37: =+E35+E34 -> 320.38 | F37: =+F35+F34 -> 29903.93 | G37: =+G35+G34 -> 320.38 | H37: =+H35+H34 -> 8858.12 | I37: =+I35+I34 -> 2159949.3 | J37: =+J35+J34 -> 352704.02 | K37: =+K35+K34 -> 4453723.5 | L37: =+L35+L34 -> 1460893 | ... N37: =+N35+N34 -> 1608338.8 | Q37: =+Q35+Q34 -> 1285392 | R37: =+Q37-SUM(E37:N37) -> 0 | S37: =+S35+S34 -> 1285
R38: =+Q38-SUM(E38:N38) -> 0
R39: =+Q39-SUM(E39:N39) -> 0
C40: Non current Liabilities: | R40: =+Q40-SUM(E40:N40) -> 0
R41: =+Q41-SUM(E41:N41) -> 0
B42: 18 | C42: Long-Term liabilities: | E42: =+SUMIF('Full BS-USD'!$M:$M,B42,'Full BS-USD'!$D:$D) -> 0 | F42: =+SUMIF('Full BS-USD'!$M:$M,B42,'Full BS-USD'!$G:$G) -> 0 | G42: =+SUMIF('Full BS-USD'!$M:$M,B42,'Full BS-USD'!$E:$E) -> 261263.83 | H42: =+SUMIF('Full BS-USD'!$M:$M,B42,'Full BS-USD'!$F:$F) -> 0 | I42: =+SUMIF('Full BS-USD'!$M:$M,B42,'Full BS-USD'!$H:$H) -> 0 | J42: =+SUMIF('Full BS-USD'!$M:$M,B42,'Full BS-USD'!$I:$I) -> 0 | K42: =+SUMIF('Full BS-USD'!$M:$M,B42,'Full BS-USD'!$J:$J) -> 44955.43 | L42: =+SUMIF('Full BS-USD'!$M:$M,B42,'Full BS-USD'!$K:$K) -> 50.78 | M42: =+SUMIF('Full BS-USD'!$M:$M,B42,'Full BS-USD'!$B:$B) -> -261263.83 | N42: =+SUMIF('Full BS-USD'!$M:$M,B42,'Full BS-USD'!$C:$C) -> 0 | Q42: =+SUMIF('Full BS-USD'!$M:$M,B42,'Full BS-USD'!$L:$L) -> 45006.21 | R42: =+Q42-SUM(E42:N42) -> 0 | S42: =+ROUND(Q42/1000,0)-1 -> 44
R43: =+Q43-SUM(E43:N43) -> 0
C44: Shareholders equity | R44: =+Q44-SUM(E44:N44) -> 0
R45: =+Q45-SUM(E45:N45) -> 0
B46: 19 | C46: additrional paid in capital | E46: =+SUMIF('Full BS-USD'!$M:$M,B46,'Full BS-USD'!$D:$D) -> 600244.31 | F46: =+SUMIF('Full BS-USD'!$M:$M,B46,'Full BS-USD'!$G:$G) -> 0 | G46: =+SUMIF('Full BS-USD'!$M:$M,B46,'Full BS-USD'!$E:$E) -> 27.32 | H46: =+SUMIF('Full BS-USD'!$M:$M,B46,'Full BS-USD'!$F:$F) -> 1000280.6 | I46: =+SUMIF('Full BS-USD'!$M:$M,B46,'Full BS-USD'!$H:$H) -> 0 | J46: =+SUMIF('Full BS-USD'!$M:$M,B46,'Full BS-USD'!$I:$I) -> 0 | K46: =+SUMIF('Full BS-USD'!$M:$M,B46,'Full BS-USD'!$J:$J) -> 40818892 | L46: =+SUMIF('Full BS-USD'!$M:$M,B46,'Full BS-USD'!$K:$K) -> 1227 | M46: =+SUMIF('Full BS-USD'!$M:$M,B46,'Full BS-USD'!$B:$B) -> 0 | N46: =+SUMIF('Full BS-USD'!$M:$M,B46,'Full BS-USD'!$C:$C) -> 0 | Q46: =+SUMIF('Full BS-USD'!$M:$M,B46,'Full BS-USD'!$L:$L) -> 42420672 | R46: =+Q46-SUM(E46:N46) -> 0 | S46: =+'Change in Equity'!L26 -> 42141.364 | T46: =+S46-'Change in Equity'!L26 -> 0
B47: 20 | C47: Recievable on share account | E47: =+SUMIF('Full BS-USD'!$M:$M,B47,'Full BS-USD'!$D:$D) -> 0 | F47: =+SUMIF('Full BS-USD'!$M:$M,B47,'Full BS-USD'!$G:$G) -> 0 | G47: =+SUMIF('Full BS-USD'!$M:$M,B47,'Full BS-USD'!$E:$E) -> 0 | H47: =+SUMIF('Full BS-USD'!$M:$M,B47,'Full BS-USD'!$F:$F) -> 0 | I47: =+SUMIF('Full BS-USD'!$M:$M,B47,'Full BS-USD'!$H:$H) -> 0 | J47: =+SUMIF('Full BS-USD'!$M:$M,B47,'Full BS-USD'!$I:$I) -> 0 | K47: =+SUMIF('Full BS-USD'!$M:$M,B47,'Full BS-USD'!$J:$J) -> 0 | L47: =+SUMIF('Full BS-USD'!$M:$M,B47,'Full BS-USD'!$K:$K) -> 0 | M47: =+SUMIF('Full BS-USD'!$M:$M,B47,'Full BS-USD'!$B:$B) -> 0 | N47: =+SUMIF('Full BS-USD'!$M:$M,B47,'Full BS-USD'!$C:$C) -> 0 | Q47: =+SUMIF('Full BS-USD'!$M:$M,B47,'Full BS-USD'!$L:$L) -> 0 | R47: =+Q47-SUM(E47:N47) -> 0 | S47: =+ROUND((Q47/1000),0) -> 0
B48: 22 | C48: Other Equity | E48: =+SUMIF('Full BS-USD'!$M:$M,B48,'Full BS-USD'!$D:$D) -> 0 | F48: =+SUMIF('Full BS-USD'!$M:$M,B48,'Full BS-USD'!$G:$G) -> 1600000 | G48: =+SUMIF('Full BS-USD'!$M:$M,B48,'Full BS-USD'!$E:$E) -> 0 | H48: =+SUMIF('Full BS-USD'!$M:$M,B48,'Full BS-USD'!$F:$F) -> 0 | I48: =+SUMIF('Full BS-USD'!$M:$M,B48,'Full BS-USD'!$H:$H) -> 0 | J48: =+SUMIF('Full BS-USD'!$M:$M,B48,'Full BS-USD'!$I:$I) -> 0 | K48: =+SUMIF('Full BS-USD'!$M:$M,B48,'Full BS-USD'!$J:$J) -> 0 | L48: =+SUMIF('Full BS-USD'!$M:$M,B48,'Full BS-USD'!$K:$K) -> 0 | M48: =+SUMIF('Full BS-USD'!$M:$M,B48,'Full BS-USD'!$B:$B) -> -1818.35 | N48: =+SUMIF('Full BS-USD'!$M:$M,B48,'Full BS-USD'!$C:$C) -> -1600000 | Q48: =+SUMIF('Full BS-USD'!$M:$M,B48,'Full BS-USD'!$L:$L) -> -1818.35 | R48: =+Q48-SUM(E48:N48) -> 0
B49: 21 | C49: Accumulated deficit | E49: =+SUMIF('Full BS-USD'!$M:$M,B49,'Full BS-USD'!$D:$D) -> -537281.85 | F49: =+SUMIF('Full BS-USD'!$M:$M,B49,'Full BS-USD'!$G:$G) -> -445171.81 | G49: =+SUMIF('Full BS-USD'!$M:$M,B49,'Full BS-USD'!$E:$E) -> -261098.45 | H49: =+SUMIF('Full BS-USD'!$M:$M,B49,'Full BS-USD'!$F:$F) -> -960577.55 | I49: =+SUMIF('Full BS-USD'!$M:$M,B49,'Full BS-USD'!$H:$H) -> 515858.79 | J49: =+SUMIF('Full BS-USD'!$M:$M,B49,'Full BS-USD'!$I:$I) -> 688580.54 | K49: =+SUMIF('Full BS-USD'!$M:$M,B49,'Full BS-USD'!$J:$J) -> -27999924 | L49: =+SUMIF('Full BS-USD'!$M:$M,B49,'Full BS-USD'!$K:$K) -> 345392.74 | M49: =+SUMIF('Full BS-USD'!$M:$M,B49,'Full BS-USD'!$B:$B) -> 1.1641532e-10 | N49: =+SUMIF('Full BS-USD'!$M:$M,B49,'Full BS-USD'!$C:$C) -> 0 | Q49: =+SUMIF('Full BS-USD'!$M:$M,B49,'Full BS-USD'!$L:$L) -> -28654221 | R49: =+Q49-SUM(E49:N49) -> 0 | S49: =+ROUND((Q49/1000),0)+ROUND(Q46/1000,0)-S46 -> -28374.364
R50: =+Q50-SUM(E50:N50) -> 0
C51: Total shareholders equity | E51: =+SUM(E46:E49) -> 62962.46 | F51: =+SUM(F46:F49) -> 1154828.2 | G51: =+SUM(G46:G49) -> -261071.13 | H51: =+SUM(H46:H49) -> 39703.07 | I51: =+SUM(I46:I49) -> 515858.79 | J51: =+SUM(J46:J49) -> 688580.54 | K51: =+SUM(K46:K49) -> 12818969 | L51: =+SUM(L46:L49) -> 346619.74 | ... N51: =+SUM(N46:N49) -> -1600000 | Q51: =+SUM(Q46:Q49) -> 13764632 | R51: =+Q51-SUM(E51:N51) -> 0 | S51: =+SUM(S46:S49) -> 13767
R52: =+Q52-SUM(E52:N52) -> 0
C53: Total liabilities and shareholders' equity | E53: =+E51+E42+E37 -> 63282.84 | F53: =+F51+F42+F37 -> 1184732.1 | G53: =+G51+G42+G37 -> 513.08 | H53: =+H51+H42+H37 -> 48561.19 | I53: =+I51+I42+I37 -> 2675808.1 | J53: =+J51+J42+J37 -> 1041284.6 | K53: =+K51+K42+K37 -> 17317648 | L53: =+L51+L42+L37 -> 1807563.5 | ... N53: =+N51+N42+N37 -> 8338.78 | Q53: =+Q51+Q42+Q37 -> 15095030 | R53: =+Q53-SUM(E53:N53) -> 0 | S53: =+S51+S42+S37 -> 15096
C55: check | E55: =+E53-E27 -> 8.0035534e-11 | F55: =+F53-F27 -> 0 | G55: =+G53-G27 -> -1.7507773e-11 | H55: =+H53-H27 -> 5.8207661e-11 | I55: =+I53-I27 -> 0 | J55: =+J53-J27 -> 0 | K55: =+K53-K27 -> 0 | L55: =+L53-L27 -> 0 | ... N55: =+N53-N27 -> 2.910383e-11 | Q55: =+Q53-Q27 -> 0 | S55: =+S53-S27 -> 0

Sheet P&L
C1: Wematch.live
C2: USD
B5: INDEX | E5: EQD | F5: WIR | G5: WSF- LTD [IL] | H5: WUS LLC | I5: WSF LTD | J5: WUS INC | K5: R&D | L5: WTSE | N5: Total
E6: =+'P&L ILS'!$E$6 -> 2023 | F6: =+'P&L ILS'!$E$6 -> 2023 | G6: =+'P&L ILS'!$E$6 -> 2023 | H6: =+'P&L ILS'!$E$6 -> 2023 | I6: =+'P&L ILS'!$E$6 -> 2023 | J6: =+'P&L ILS'!$E$6 -> 2023 | K6: =+'P&L ILS'!$E$6 -> 2023 | L6: =+'P&L ILS'!$E$6 -> 2023 | N6: =+'P&L ILS'!$E$6 -> 2023 | P6: in 000' | R6: NOTE
B8: 1 | C8: Revenues | E8: =+SUMIF('Full P&L-USD'!$K:$K,B8,'Full P&L-USD'!$B:$B) -> 0 | F8: =+SUMIF('Full P&L-USD'!$K:$K,B8,'Full P&L-USD'!$C:$C) -> 0 | G8: =+SUMIF('Full P&L-USD'!$K:$K,B8,'Full P&L-USD'!$D:$D) -> 0 | H8: =+SUMIF('Full P&L-USD'!$K:$K,B8,'Full P&L-USD'!$E:$E) -> 0 | I8: =+SUMIF('Full P&L-USD'!$K:$K,B8,'Full P&L-USD'!$F:$F) -> 0 | J8: =+SUMIF('Full P&L-USD'!$K:$K,B8,'Full P&L-USD'!$G:$G) -> 0 | K8: =+SUMIF('Full P&L-USD'!$K:$K,B8,'Full P&L-USD'!$H:$H) -> 9466029.3 | L8: =+SUMIF('Full P&L-USD'!$K:$K,B8,'Full P&L-USD'!$I:$I) -> 0 | N8: =+SUMIF('Full P&L-USD'!$K:$K,B8,'Full P&L-USD'!$J:$J) -> 9466029.3 | O8: =+N8-SUM(E8:L8) -> 0 | P8: =+ROUND(N8/1000,0) -> 9466 | R8: =+'NOTES-Conso'!B50 -> 9
O9: =+N9-SUM(E9:L9) -> 0
B10: 2 | C10: Cost of Revenues | E10: =+SUMIF('Full P&L-USD'!$K:$K,B10,'Full P&L-USD'!$B:$B) -> 0 | F10: =+SUMIF('Full P&L-USD'!$K:$K,B10,'Full P&L-USD'!$C:$C) -> 0 | G10: =+SUMIF('Full P&L-USD'!$K:$K,B10,'Full P&L-USD'!$D:$D) -> 0 | H10: =+SUMIF('Full P&L-USD'!$K:$K,B10,'Full P&L-USD'!$E:$E) -> -71276.44 | I10: =+SUMIF('Full P&L-USD'!$K:$K,B10,'Full P&L-USD'!$F:$F) -> -20466.03 | J10: =+SUMIF('Full P&L-USD'!$K:$K,B10,'Full P&L-USD'!$G:$G) -> -27322.1 | K10: =+SUMIF('Full P&L-USD'!$K:$K,B10,'Full P&L-USD'!$H:$H) -> -2824601.4 | L10: =+SUMIF('Full P&L-USD'!$K:$K,B10,'Full P&L-USD'!$I:$I) -> -133042.18 | N10: =+SUMIF('Full P&L-USD'!$K:$K,B10,'Full P&L-USD'!$J:$J) -> -3076708.1 | O10: =+N10-SUM(E10:L10) -> 0 | P10: =+ROUND(N10/1000,0) -> -3077 | R10: =+'NOTES-Conso'!B59 -> 10
O11: =+N11-SUM(E11:L11) -> 0
B12: 3 | C12: Gross profit | E12: =+E8+E10 -> 0 | F12: =+F8+F10 -> 0 | G12: =+G8+G10 -> 0 | H12: =+H8+H10 -> -71276.44 | I12: =+I8+I10 -> -20466.03 | J12: =+J8+J10 -> -27322.1 | K12: =+K8+K10 -> 6641427.9 | L12: =+L8+L10 -> -133042.18 | N12: =+N8+N10 -> 6389321.2 | O12: =+N12-SUM(E12:L12) -> 0 | P12: =+P8+P10 -> 6389
O13: =+N13-SUM(E13:L13) -> 0
C14: Operating expenses: | O14: =+N14-SUM(E14:L14) -> 0
A15: Total - R&D | B15: 4.1 | C15: R&D | E15: =+SUMIF('Full P&L-USD'!$K:$K,B15,'Full P&L-USD'!$B:$B) -> 0 | F15: =+SUMIF('Full P&L-USD'!$K:$K,B15,'Full P&L-USD'!$C:$C) -> 0 | G15: =+SUMIF('Full P&L-USD'!$K:$K,B15,'Full P&L-USD'!$D:$D) -> 0 | H15: =+SUMIF('Full P&L-USD'!$K:$K,B15,'Full P&L-USD'!$E:$E)+'Full P&L-USD'!E222 -> 8957.16 | I15: =+SUMIF('Full P&L-USD'!$K:$K,B15,'Full P&L-USD'!$F:$F)+'Full P&L-USD'!F222 -> 1513589.8 | J15: =+SUMIF('Full P&L-USD'!$K:$K,B15,'Full P&L-USD'!$G:$G)+'Full P&L-USD'!G222 -> 528752.56 | K15: =+SUMIF('Full P&L-USD'!$K:$K,B15,'Full P&L-USD'!$H:$H)+'Full P&L-USD'!H222 -> 2699383.3 | L15: =+SUMIF('Full P&L-USD'!$K:$K,B15,'Full P&L-USD'!$I:$I)+'Full P&L-USD'!I222 -> 789404.87 | N15: =+'Full P&L-USD'!J405+'Full P&L-USD'!J222 -> 5540087.6 | O15: =+N15-SUM(E15:L15) -> 0 | P15: =+ROUND(N15/1000,0) -> 5540
A16: Total - S&M | B16: 4.2 | C16: S&M | E16: =+SUMIF('Full P&L-USD'!$K:$K,B16,'Full P&L-USD'!$B:$B) -> 0 | F16: =+SUMIF('Full P&L-USD'!$K:$K,B16,'Full P&L-USD'!$C:$C) -> 0 | G16: =+SUMIF('Full P&L-USD'!$K:$K,B16,'Full P&L-USD'!$D:$D) -> 0 | H16: =+SUMIF('Full P&L-USD'!$K:$K,B16,'Full P&L-USD'!$E:$E) -> 281115.73 | I16: =+SUMIF('Full P&L-USD'!$K:$K,B16,'Full P&L-USD'!$F:$F) -> 1391589.7 | J16: =+SUMIF('Full P&L-USD'!$K:$K,B16,'Full P&L-USD'!$G:$G) -> 825110.41 | K16: =+SUMIF('Full P&L-USD'!$K:$K,B16,'Full P&L-USD'!$H:$H) -> 1892920.5 | L16: =+SUMIF('Full P&L-USD'!$K:$K,B16,'Full P&L-USD'!$I:$I) -> 365308.16 | N16: =+'Full P&L-USD'!J581 -> 4756044.5 | O16: =+N16-SUM(E16:L16) -> 0 | P16: =+ROUND(N16/1000,0) -> 4756
A17: Total - G&A | B17: 4.3 | C17: G&A | E17: =+SUMIF('Full P&L-USD'!$K:$K,B17,'Full P&L-USD'!$B:$B) -> 0 | F17: =+SUMIF('Full P&L-USD'!$K:$K,B17,'Full P&L-USD'!$C:$C) -> 0 | G17: =+SUMIF('Full P&L-USD'!$K:$K,B17,'Full P&L-USD'!$D:$D) -> 0 | H17: =+SUMIF('Full P&L-USD'!$K:$K,B17,'Full P&L-USD'!$E:$E) -> 128130.87 | I17: =+SUMIF('Full P&L-USD'!$K:$K,B17,'Full P&L-USD'!$F:$F) -> 1113905.1 | J17: =+SUMIF('Full P&L-USD'!$K:$K,B17,'Full P&L-USD'!$G:$G) -> 741036.55 | K17: =+SUMIF('Full P&L-USD'!$K:$K,B17,'Full P&L-USD'!$H:$H) -> 1411783.6 | L17: =+SUMIF('Full P&L-USD'!$K:$K,B17,'Full P&L-USD'!$I:$I) -> 129771.13 | N17: =+'Full P&L-USD'!J942 -> 3524627.3 | O17: =+N17-SUM(E17:L17)+'Full P&L-USD'!J798 -> 4.6566129e-10 | P17: =+ROUND(N17/1000,0) -> 3525
O18: =+N18-SUM(E18:L18) -> 0
A19: Total Operation Expense | B19: 4 | C19: Total Operatiing Expense | E19: =+SUM(E15:E17) -> 0 | F19: =+SUM(F15:F17) -> 0 | G19: =+SUM(G15:G17) -> 0 | H19: =+SUM(H15:H17) -> 418203.76 | I19: =+SUM(I15:I17) -> 4019084.6 | J19: =+SUM(J15:J17) -> 2094899.5 | K19: =+SUM(K15:K17) -> 6004087.4 | L19: =+SUM(L15:L17) -> 1284484.2 | N19: =+SUM(N15:N17) -> 13820759 | O19: =+N19-SUM(E19:L19) -> 0 | P19: =+SUM(P15:P17) -> 13821
O20: =+N20-SUM(E20:L20) -> 0
C21: Operating Loss | E21: =+E12-E19 -> 0 | F21: =+F12-F19 -> 0 | G21: =+G12-G19 -> 0 | H21: =+H12-H19 -> -489480.2 | I21: =+I12-I19 -> -4039550.6 | J21: =+J12-J19 -> -2122221.6 | K21: =+K12-K19 -> 637340.5 | L21: =+L12-L19 -> -1417526.3 | N21: =+N12-N19 -> -7431438.3 | P21: =+P12-P19 -> -7432
B23: 5 | C23: Earning/(Loss) Before Interest & Tax | E23: =+E12-E19 -> 0 | F23: =+F12-F19 -> 0 | G23: =+G12-G19 -> 0 | H23: =+H12-H19 -> -489480.2 | I23: =+I12-I19 -> -4039550.6 | J23: =+J12-J19 -> -2122221.6 | K23: =+K12-K19 -> 637340.5 | L23: =+L12-L19 -> -1417526.3 | N23: =+N12-N19 -> -7431438.3 | O23: =+N23-SUM(E23:L23) -> 0 | P23: =+P12-P19 -> -7432
O24: =+N24-SUM(E24:L24) -> 0
B25: 6 | C25: Financial expenses, net | E25: =+SUMIF('Full P&L-USD'!$K:$K,B25,'Full P&L-USD'!$B:$B) -> 5.15 | F25: =+SUMIF('Full P&L-USD'!$K:$K,B25,'Full P&L-USD'!$C:$C) -> 9.56 | G25: =+SUMIF('Full P&L-USD'!$K:$K,B25,'Full P&L-USD'!$D:$D) -> -429.43 | H25: =+SUMIF('Full P&L-USD'!$K:$K,B25,'Full P&L-USD'!$E:$E) -> 44408.39 | I25: =+SUMIF('Full P&L-USD'!$K:$K,B25,'Full P&L-USD'!$F:$F) -> 12561.62 | J25: =+SUMIF('Full P&L-USD'!$K:$K,B25,'Full P&L-USD'!$G:$G) -> -625.11 | K25: =+SUMIF('Full P&L-USD'!$K:$K,B25,'Full P&L-USD'!$H:$H) -> 509470.73 | L25: =+SUMIF('Full P&L-USD'!$K:$K,B25,'Full P&L-USD'!$I:$I) -> 13097.9 | N25: =+SUMIF('Full P&L-USD'!$K:$K,B25,'Full P&L-USD'!$J:$J) -> 578498.81 | O25: =+N25-SUM(E25:L25) -> 0 | P25: =+ROUND(N25/1000,0) -> 578 | R25: =+'NOTES-Conso'!B67 -> 11
O26: =+N26-SUM(E26:L26) -> 0
B27: 7 | C27: Loss Before Taxes On Income | E27: =+E25+E23 -> 5.15 | F27: =+F25+F23 -> 9.56 | G27: =+G25+G23 -> -429.43 | H27: =+H25+H23 -> -445071.81 | I27: =+I25+I23 -> -4026989 | J27: =+J25+J23 -> -2122846.7 | K27: =+K25+K23 -> 1146811.2 | L27: =+L25+L23 -> -1404428.4 | N27: =+N25+N23 -> -6852939.5 | O27: =+N27-SUM(E27:L27) -> 0 | P27: =+P25+P23 -> -6854
O28: =+N28-SUM(E28:L28) -> 0
B29: 8 | C29: Tax on Income | E29: =+SUMIF('Full P&L-USD'!$K:$K,B29,'Full P&L-USD'!$B:$B) -> 0 | F29: =+SUMIF('Full P&L-USD'!$K:$K,B29,'Full P&L-USD'!$C:$C) -> 0 | G29: =+SUMIF('Full P&L-USD'!$K:$K,B29,'Full P&L-USD'!$D:$D) -> 0 | H29: =+SUMIF('Full P&L-USD'!$K:$K,B29,'Full P&L-USD'!$E:$E) -> -100 | I29: =+SUMIF('Full P&L-USD'!$K:$K,B29,'Full P&L-USD'!$F:$F) -> -72806.3 | J29: =+SUMIF('Full P&L-USD'!$K:$K,B29,'Full P&L-USD'!$G:$G) -> -47086.07 | K29: =+SUMIF('Full P&L-USD'!$K:$K,B29,'Full P&L-USD'!$H:$H) -> 200 | L29: =+SUMIF('Full P&L-USD'!$K:$K,B29,'Full P&L-USD'!$I:$I) -> 59189.74 | N29: =+SUMIF('Full P&L-USD'!$K:$K,B29,'Full P&L-USD'!$J:$J) -> -60602.63 | O29: =+N29-SUM(E29:L29) -> 0 | P29: =+ROUND(N29/1000,0) -> -61
O30: =+N30-SUM(E30:L30) -> 0
C31: Net Loss | E31: =+E27+E29 -> 5.15 | F31: =+F27+F29 -> 9.56 | G31: =+G27+G29 -> -429.43 | H31: =+H27+H29 -> -445171.81 | I31: =+I27+I29 -> -4099795.3 | J31: =+J27+J29 -> -2169932.8 | K31: =+K27+K29 -> 1147011.2 | L31: =+L27+L29 -> -1345238.7 | N31: =+N27+N29 -> -6913542.1 | O31: =+N31-SUM(E31:L31) -> 0 | P31: =+P27+P29 -> -6915

Sheet CF
A4: Cash flows from operating activities:
C5: As of December 31, 2023
C7: US thousand
A9: Net loss | C9: =-E96 -> -6915
A11: Adjustments to reconcile net loss to net cash provided by operating activities:
A14: Depreciation and amortization and impermanent | C14: =-E83 -> 43.221
A15: Share-based compensation expense | C15: =-E93 -> 292.364
A16: Change in employee long term loans | C16: =-E82 -> -4
A17: Change in long time employee benefit | C17: =-E89 -> -370
A19: Change in SAFE fair value | C19: =-E88 -> 0
A21: Changes in operating assets and liabilities:
A22: Accounts receivable | C22: =-E80 -> 1378
A23: Prepaid expenses and other assets | C23: =-E81 -> 117
A24: Accounts payable | C24: =-E84 -> -35
A25: Accrued expenses and other liabilities | C25: =-E85 -> 326
A26: Change in Deferred revenue | C26: =-E86 -> 0
A28: Net cash provided by operating activities | C28: =SUM(C9:C27) -> -5167.415
A30: Cash flows from investing activities:
A32: Change in short term restricted deposit | C32: =-F79-284 -> 2553
A33: Purchases of property and equipment | C33: =-F83 -> -41.221
A35: Net cash used in investing activities | C35: =-F97 -> 2795.779
A37: Cash flows from financing activities:
A39: Proceeds from issuance of Sample agreement for future equity ("SAFE") | C39: 0
A40: Proceeds from opsions excersize | C40: =-G91 -> 4
A41: Issuance of Preferred B shares, net of issuance cost
A42: Proceeds from issuance of convertible preferred shares, net of issuance costs
A44: Net cash provided by financing activities | C44: =+C42+C41+C39+C40 -> 4
A46: Net increase (decrease) in cash, cash equivalents, and restricted cash | C46: =+C44+C28+C35 -> -2367.636
A47: Cash, cash equivalents, and restricted cash—beginning of period | C47: =+D78 -> 7660
A49: Cash, cash equivalents, and restricted cash—end of period | C49: =+C46+C47 -> 5292.364 | D49: =+J78 -> 5292 | E49: =+C49-D49 -> 0.364
E55: אם הפקדונות משמשים לפעילות השוטפת או נזילים תוך פחות מ-3 חודשים הם מסווגים כמזומן ושווי מזומן
E56: .
F71: Working peper for cash flow
D75: Closing balance as | E75: Cash flow from | F75: Cash flow from | G75: Cash flow from | J75: Closing balance as
D76: 44926 | E76: Opeartion | F76: Investing | G76: Financing | H76: Non-cash activites | I76: Change in cash | J76: 45291 | L76: Check
B78: 10 | C78: Cash and cash equivalents | D78: 7660 | I78: =J78-D78-E78 -> -2368 | J78: =+'BS USD'!S11 -> 5292 | K78: =+J78-'BS USD'!$S11 -> 0 | L78: =SUM(D78:I78)-J78 -> 0
B79: 11 | C79: Restricted Bank Deposit | D79: 11163 | F79: =J79-D79 -> -2837 | J79: =+'BS USD'!S12 -> 8326 | K79: =+J79-'BS USD'!$S12 -> 0 | L79: =SUM(D79:I79)-J79 -> 0
B80: 12 | C80: Account Receivable | D80: 2037 | E80: =J80-D80 -> -1378 | J80: =+'BS USD'!S13 -> 659 | K80: =+J80-'BS USD'!$S13 -> 0 | L80: =SUM(D80:I80)-J80 -> 0
B81: 13 | C81: Prepaid expenses and other current assets | D81: 776 | E81: =J81-D81 -> -117 | J81: =+'BS USD'!S14 -> 659 | K81: =+J81-'BS USD'!$S14 -> 0 | L81: =SUM(D81:I81)-J81 -> 0
B82: 14 | C82: Other long term accounts receivables | D82: 34 | E82: =J82-D82 -> 4 | J82: =+'BS USD'!S20 -> 38 | K82: =+J82-'BS USD'!$S20 -> 0 | L82: =SUM(D82:I82)-J82 -> 0
B83: 15 | C83: Property & Equipment, Net | D83: 123 | E83: =-43221/1000 -> -43.221 | F83: =+J83-D83-E83 -> 41.221 | J83: =+'BS USD'!S21 -> 121 | K83: =+J83-'BS USD'!$S21 -> 0 | L83: =SUM(D83:I83)-J83 -> 0
A84: Total Credit Card- add manualy | B84: 16 | C84: Account Payable | D84: -202 | E84: =J84-D84 -> 35 | J84: =-'BS USD'!S34 -> -167 | K84: =+J84+'BS USD'!$S34 -> 0 | L84: =SUM(D84:I84)-J84 -> 0
B85: 17 | C85: Accrued expenses and other current liabilities | D85: -792 | E85: =J85-D85 -> -326 | J85: =-'BS USD'!S35 -> -1118 | K85: =+J85+'BS USD'!$S35 -> 0 | L85: =SUM(D85:I85)-J85 -> 0
B86: 17.4 | C86: Deferred Revenues | E86: =J86-D86 -> 0 | L86: =SUM(D86:I86)-J86 -> 0
C87: Warrants | D87: 0 | E87: =J87-D87 -> 0 | J87: =+ROUND(SUMIF('BS USD'!$B$7:$B$55,B87,'BS USD'!$S$7:$S$55),0) -> 0 | L87: =SUM(D87:I87)-J87 -> 0
C88: Safe agreement | D88: 0 | E88: =J88-D88 -> 0 | J88: =+ROUND(SUMIF('BS USD'!$B$7:$B$55,B88,'BS USD'!$S$7:$S$55),0) -> 0 | L88: =SUM(D88:I88)-J88 -> 0
B89: 18 | C89: Provision for post employment benefits | D89: -414 | E89: =J89-D89 -> 370 | J89: =-'BS USD'!S42 -> -44 | K89: =+J89+'BS USD'!S42 -> 0 | L89: =SUM(D89:I89)-J89 -> 0
C90: Ordinary shares | D90: 0 | J90: =+ROUND(SUMIF('BS USD'!$B$7:$B$55,B90,'BS USD'!$S$7:$S$55),0) -> 0 | K90: Capital and Reserves | L90: =SUM(D90:I90)-J90 -> 0
C91: Option exercise by employees | D91: -7 | G91: -4 | J91: =+G91+D91 -> -11 | L91: =SUM(D91:I91)-J91 -> 0
B92: 19.1 | C92: Preferred shares | D92: -31124.706 | G92: =+J92-D92 -> 0 | J92: =-ROUND(SUMIF('Full BS-USD'!M:M,B92,'Full BS-USD'!L:L),0)/1000 -> -31124.706 | L92: =SUM(D92:I92)-J92 -> 0
B93: 19.2 | C93: Additional paid in capital-Share based compensation | D93: -1654.137 | E93: =J93-D93 -> -292.364 | J93: =-ROUND(SUMIF('Full BS-USD'!M:M,B93,'Full BS-USD'!L:L),0)/1000-1 -> -1946.501 | L93: =SUM(D93:I93)-J93 -> 0 | M93: 31005
B94: 19.3 | C94: Additional paid in capital | D94: -9339.464 | J94: =-ROUND(SUMIF('Full BS-USD'!M:M,B94,'Full BS-USD'!L:L),0)/1000-J91 -> -9339.464
C95: Retained Earnings | D95: =14349.72+7391 -> 21740.72 | J95: =-ROUND(SUMIF('Full BS-USD'!A:A,C95,'Full BS-USD'!L:L),0)/1000 -> 21740.692
C96: Current year Profit (loss) | E96: =+J96 -> 6915 | J96: =-'P&L'!P31 -> 6915 | L96: =SUM(D96:I96)-J96 -> 0
C97: Check | D97: =SUM(D78:D96) -> 0.413 | E97: =SUM(E78:E96) -> 5167.415 | F97: =SUM(F77:F96) -> -2795.779 | G97: =SUM(G77:G96) -> -4 | I97: =SUM(I78:I96) -> -2368 | J97: =SUM(J78:J96) -> 0.021 | L97: =SUM(E97:I97)-J97 -> -0.385
L98: =SUM(D98:I98)-J98 -> 0
E99: =+E97+C28 -> 0

Sheet Change in Equity
D3: Ordinary shares | H3: Preferred Shares | L3: Additional | N3: Receivable on | P3: Accumulated | R3: Total shareholders' equity
L4: paid-in
D5: Number | F5: Amount | H5: Number | J5: Amount | L5: capital | N5: Shares account | P5: deficit | R5: (deficit)
B7: Balance as of January 1, 2021 | D7: 1401739 | F7: 4 | H7: 1481702 | J7: 5 | L7: 41580 | N7: 0 | P7: -14078 | R7: 27511
B9: Net loss and other comprehensive loss | D9: 0 | F9: 0 | H9: 0 | J9: 0 | L9: 0 | N9: 0 | P9: -7391 | R9: =+P9+F9+L9+J9 -> -7391
B10: Option exercise | D10: 2600 | L10: 8 | R10: =+P10+F10+L10+J10+N10 -> 8
B11: Share based compensation | D11: 0 | F11: 0 | H11: 0 | J11: 0 | L11: 257 | N11: 0 | P11: 0 | R11: =+P11+F11+L11+J11 -> 257
B12: Warrant exercise | H12: 127247 | J12: (*)
B13: SAFE exercise | D13: 0 | F13: 0 | N13: - | P13: 0 | R13: =+P13+F13+L13+J13 -> 0
B14: Issuance of preferred B Shares, net of issuance cost | D14: 0 | F14: 0 | P14: 0 | R14: =+P14+J14+L14+N14 -> 0 | S14: =+H14+'NOTES-Conso'!H41 -> 0
B16: Balance as of December 31, 2021 | D16: =SUM(D7:D15) -> 1404339 | F16: =SUM(F7:F15) -> 4 | H16: =SUM(H7:H15) -> 1608949 | J16: =SUM(J7:J15) -> 5 | L16: =SUM(L7:L15) -> 41845 | N16: =SUM(N7:N15) -> 0 | P16: =SUM(P7:P15) -> -21469 | R16: =+P16+F16+L16+N16+J16 -> 20385
B18: Net loss and other comprehensive loss | D18: 0 | F18: 0 | H18: 0 | J18: 0 | L18: 0 | N18: 0 | P18: =+'P&L'!P31 -> -6915 | R18: =SUM(J18:P18,F18) -> -6915
B19: Option exercise | R19: =SUM(J19:P19,F19) -> 0
B20: Share based compensation | L20: =-CF!E93+4 -> 296.364 | R20: =SUM(J20:P20,F20) -> 296.364
B21: SAFE exercise | R21: =SUM(J21:P21,F21) -> 0
B22: Warrant exercise | J22: (*) | R22: =SUM(J22:P22,F22) -> 0
B23: Issuance of preferred A Shares, net of issuance cost
B24: Issuance of ordinary stocks, net of issuance cost | F24: 0 | P24: 0 | R24: =SUM(J24:P24,F24) -> 0
B26: Balance as of December 31, 2022 | D26: =SUM(D16:D24) -> 1404339 | F26: =SUM(F16:F24) -> 4 | H26: =SUM(H16:H24) -> 1608949 | J26: =SUM(J16:J24) -> 5 | L26: =SUM(L16:L24) -> 42141.364 | N26: =SUM(N16:N24) -> 0 | P26: =SUM(P16:P24) -> -28384 | R26: =+R16+R18+R20 -> 13766.364
D28: =+D16+D19+D20-D26 -> 0 | H28: =+H16+H22-H26 -> 0 | L28: =+L16+L20-L26 -> 0 | P28: =+P16+P18-P26 -> 0 | Q28: =+Q16+Q18-Q26 -> 0
R29: =+'BS USD'!S51-R26 -> 0.636
L30: =+L26-'BS USD'!S46 -> 0

Sheet JE'S
B5: 1 | D5: AR-DR Offset | G5: JEIL-01719
C9: D | D9: 12002 AR OFFSET | E9: 47763.9
C10: C | D10: 26002 DR OFFSET | E10: 47763.9
B14: 2
B35: 3 | D35: Rent paid upfront- wework | G35: JEIL-03339
G36: ILS
C37: D | D37: 67101 Rent | G37: 53520
C38: C | D38: 20001 AP | G38: =+G37 -> 53520

Sheet NOTES-Conso
D3: Balance Sheet Notes
B5: 3 | D5: Trade recievables | E5: =+SUMIF('Full BS-USD'!$M$9:$M$226,F5,'Full BS-USD'!$L$9:$L$226)/1000 -> 424.62305 | F5: 12.1 | I5: See WP AR Breakdown
D6: Unbilled revenue | E6: =SUMIF('Full BS-USD'!$M$9:$M$226,F6,'Full BS-USD'!$L$9:$L$226)/1000-E5-1 -> 233.25907 | F6: 12
E7: =SUM(E5:E6) -> 657.88212
E8: =+E7-'BS USD'!S13 -> -1.11788
B10: 4 | D10: Prepaid expenses | E10: =+SUMIF('Full BS-USD'!$M$9:$M$226,F10,'Full BS-USD'!$L$9:$L$226)/1000 -> 273.23526 | F10: 13.1 | I10: See WP Prepaid expenses
D11: Government institutions | E11: =+SUMIF('Full BS-USD'!$M$9:$M$226,F11,'Full BS-USD'!$L$9:$L$226)/1000 -> 162.24782 | F11: 13.2
D12: Other current assts | E12: =SUMIF('Full BS-USD'!$M$9:$M$226,F12,'Full BS-USD'!$L$9:$L$226)/1000-E11-E10 -> 223.27715 | F12: 13
E13: =SUM(E10:E12) -> 658.76023
E14: =+E13-'BS USD'!S14 -> -0.23977
B15: 5 | D15: Cost:
D16: Computers & Software | E16: =+SUMIF('Full BS-USD'!$M$9:$M$226,F16,'Full BS-USD'!$L$9:$L$226)/1000 -> 233.65423 | F16: 15.1
D17: Office furniture | E17: =+SUMIF('Full BS-USD'!$M$9:$M$226,F17,'Full BS-USD'!$L$9:$L$226)/1000 -> 28.00532 | F17: 15.2
D18: Leasehold improvements | E18: =SUMIF('Full BS-USD'!$M$9:$M$226,F18,'Full BS-USD'!$L$9:$L$226)/1000 -> 2.65233 | F18: 15.3
E19: =SUM(E16:E18) -> 264.31188
D21: Accumulated depritiation | E21: =SUMIF('Full BS-USD'!$M$9:$M$226,F21,'Full BS-USD'!$L$9:$L$226)/1000 -> -142.99059 | F21: 15.4
D23: Preperty and equipment, net | E23: =+E19+E21 -> 121.32129
E24: =+E23-'BS USD'!S21 -> 0.32129
I26: See WP : Accruals Breakdown
B27: 6 | D27: Accrued employee compensation and benefits | E27: =+SUMIF('Full BS-USD'!$M$9:$M$226,F27,'Full BS-USD'!$L$9:$L$226)/1000 -> 592.20807 | F27: 17.1
D28: Accrued expenses | E28: =+SUMIF('Full BS-USD'!$M$9:$M$226,F28,'Full BS-USD'!$L$9:$L$226)/1000 -> 211.29614 | F28: 17.2
D29: Income and indirect tax payable | E29: =+SUMIF('Full BS-USD'!$M$9:$M$226,F29,'Full BS-USD'!$L$9:$L$226)/1000-E28-E27 -> 314.55034 | F29: 17 | G29: includes DR
E30: =SUM(E27:E29) -> 1118.0546
E31: =+E30-'BS USD'!S35 -> 0.05455
B33: 8 | D33: Share capital: | O33: Shareholders' equity
O35: 2022
E36: Authorized | F36: issued and outstanding | J36: Authorized | K36: issued and outstanding | O36: number of options | P36: weightes average excersise price
E37: December 31,2023 | J37: December 31,2022 | N37: Balance as of December 31,2021
D38: ordinary shares | E38: 3074000 | F38: 1223458 | J38: 3074000 | K38: 1223458 | N38: Granted
D39: ordinary A Shares | E39: 205000 | F39: 180881 | J39: 205000 | K39: 180881 | N39: Balance as of December 31,2022
D40: Preferred A shares (*) | E40: 651000 | F40: 641271 | J40: 651000 | K40: 641271 | N40: Excercisable as of December 31,2021
D41: preferred B shares (*) | E41: 1070000 | F41: 967678 | J41: 1070000 | K41: 967678
E42: =SUM(E38:E41) -> 5000000 | F42: =SUM(F38:F41) -> 3013288 | J42: =SUM(J38:J41) -> 5000000 | K42: =SUM(K38:K41) -> 3013288
K45: The information is taken from Carta- "Summery Cap Table" report
D48: P&L Notes
B50: 9
D51: Subscription fees | F51: From rev File | I51: See WP: Revenue File
D52: Variable Fees | F52: From rev File
E53: =SUM(E51:E52) -> 0
E54: =+'P&L'!P8 -> 9466 | F54: NS
E55: =+E53-E54 -> -9466 | F55: DIFF
B59: 10 | D59: Revenues shared with third parties | E59: =-SUMIF('Full P&L-USD'!$K$8:$K$808,F59,'Full P&L-USD'!$J$8:$J$808)/1000 -> 1752.497 | F59: 2.1
D60: Other cost of sales | E60: =-SUMIF('Full P&L-USD'!$A$8:$A$808,G60,'Full P&L-USD'!$J$8:$J$808)/1000 -> 1324.2111 | F60: 2.2 | G60: Total - Cost Of Sales
E61: =+E60+E59 -> 3076.7081
E62: =+E61+'P&L'!P10 -> -0.29185
B67: 11 | D67: Bank fees | E67: =-SUMIF('Full P&L-USD'!$K$8:$K$1000,F67,'Full P&L-USD'!$J$8:$J$1000)/1000 -> -28.4887 | F67: 6.1
D68: Revaluation expenses | E68: =-SUMIF('Full P&L-USD'!$K$8:$K$1000,F68,'Full P&L-USD'!$J$8:$J$1000)/1000 -> 92.54814 | F68: 6.2
D69: Exchange difference | E69: =-SUMIF('Full P&L-USD'!$K$8:$K$1000,F69,'Full P&L-USD'!$J$8:$J$1000)/1000 -> 0 | F69: 6.3
D70: Interest income | E70: =SUMIF('Full P&L-USD'!$K$8:$K$1000,F70,'Full P&L-USD'!$J$8:$J$1000)/1000 -> 514.44097 | F70: 6.4
E71: =SUM(E67:E70) -> 578.50041
E72: =+E71-'P&L'!P25 -> 0.50041

Sheet Options -Outstanding Awards
B5: Number of Awards | C5: Weighted Average Exercise Price | D5: Weighted Average Share Price on Date of Exercise | E5: Weighted Average Remaining Contractual Life | F5: Aggregate Intrinsic Value
A6: Outstanding, beginning of period | B6: 146702 | C6: 8.431322 | F6: 3604274.2
A7: Granted | B7: 23750 | C7: 21.18
A8: Exercised/Released | B8: -2600 | C8: 4.3474829 | D8: 4.3474829
A9: Cancelled/Forfeited | B9: -5752 | C9: 13.90386
A10: Expired | B10: -765 | C10: 12.5
A11: Outstanding, End of period | B11: 161335 | C11: 10.159456 | E11: 7.7855858 | F11: 3684979.2
A12: Exercisable, End of period | B12: 89352 | C12: 4.9935285 | E12: 6.9678835 | F12: 2502434.2
B18: 2022
B19: Number of options | C19: Weightes average exercise price | E19: *
A20: Balance as of December 31,2021 | B20: 105702 | C20: 5.47 | E20: =+B20/B22 -> 0.81653431 | F20: =+C20*E20 -> 4.4664427 | L20: From Carta
A21: Granted | B21: =+B7 -> 23750 | C21: =+C7 -> 21.18 | E21: =+B21/B22 -> 0.18346569 | F21: =+E21*C21 -> 3.8858032 | L21: Wematch.live R&D LTD Options Exercised & RSUs Settled
A22: Balance as of December 31,2022 | B22: =+B21+B20 -> 129452 | C22: 8.35 | D22: * | F22: =+F21+F20 -> 8.3522459 | L22: As of 12/31/2022 • Generated by Hila Eliasi (hila.eliasi@wematch.live) at 08/10/2023 06:10:37
A23: Excercisable as of December 31,2022 | B23: =+B12 -> 89352 | C23: =+C12 -> 4.9935285
L24: ID | M24: Optionholder | N24: Employee ID | O24: Shares Exercised | P24: Grant Date | Q24: Exercise Request Date | R24: Off System Transaction | S24: Exercise Price | T24: Total Exercise Price
L25: ES-1008 | M25: Rudy Perez | O25: 1216 | P25: 43586 | Q25: 44650 | S25: 0.002783 | T25: =O25*S25 -> 3.384128
L26: ES-1019 | M26: Eitan Katz | O26: 800 | P26: 43952 | Q26: 44921 | S26: 5 | T26: =O26*S26 -> 4000
L27: ES-1054 | M27: Rudy Perez | O27: 584 | P27: 44317 | Q27: 44650 | S27: 12.5 | T27: =O27*S27 -> 7300
A28: Grant date | B28: number of options granted during 2023 | C28: number of options excercised during 2023 | D28: Options outstanding as of December 31, 2023 | E28: Exercise price | F28: Options excercisable as of December 31,2023 | G28: Excercisable through
A29: 43647 | B29: 14900 | C29: =+O25 -> 1216 | D29: =+C29+B29 -> 16116 | E29: 0.001 | F29: 7450 | G29: =+A29+365*10+3 -> 47300
A30: 43952 | B30: 9500 | C30: =+O26 -> 800 | E30: 5 | G30: =+A30+365*10+2 -> 47604
A31: 44317 | B31: 300 | C31: =+O27 -> 584 | D31: =+C31+B31 -> 884 | E31: 12.5 | F31: 100 | G31: =+A31+365*10+2 -> 47969
A32: 01/05/2022 | B32: 11800 | C32: - | E32: =+C7 -> 21.18 | F32: =+F33 -> 89352 | G32: =+A32+365*10+3 -> 48335
A33: 22/09/2022 | B33: 11950 | C33: - | D33: =+B11 -> 161335 | E33: =+E32 -> 21.18 | F33: =+B12 -> 89352 | G33: =+A33+365*10+3 -> 48479
E39: December 31,
E40: 2023 | F40: 2022
D41: CogS | E41: 2 | F41: 2 | J41: CogS | L41: 1607
D42: R&D | E42: 80 | F42: 80 | J42: R&D | K42: Product | L42: 60098
D43: S&M | E43: 44 | F43: 44 | K43: Technology | L43: 19839
D44: G&A | E44: 131 | F44: 131 | J44: S&M | K44: Sales | L44: 57149
E45: =SUM(E41:E44) -> 257 | F45: 257 | K45: Marketing | L45: -13087
J46: G&A | L46: =97986+19940+1135+12277 -> 131338
E47: 257 | L47: =SUM(L41:L46) -> 256944
B53: 01/08/2023 from Carta | C53: 66288
B54: Niv Sabag | C54: -800
B55: Shane Martin | C55: -2000
B56: Christine Lowe | C56: -1000
B57: Jason Hunter | C57: -750
B58: Jason Hunter | C58: -1500
B59: Shane Martin | C59: -2000
B60: Michael Sabbah | C60: -1100
B61: 2023 grants | C61: 5000
B62: Michael Sabbah | C62: -11000
B63: Rudy Perez | C63: 1216
B64: Eitan Katz | C64: 800
C65: =SUM(C53:C64) -> 53154
C69: 53144
B70: Diff | C70: =+C65-C69 -> 10

Sheet Full BS-USD
A1: Wematch.live R&D LTD
A2: Wematch.live R&D LTD (Consolidated)
A3: Balance Sheet
A4: End of Dec 2023
A7: Financial Row | B7: Elimination | C7: Elimination US | D7: Wematch EQD LTD | E7: Wematch Interest rate LTD | F7: Wematch Securities. Financing LTD [IL] | G7: Wematch.Live LLC | H7: Wematch.SecuritiesFinancing LTD | I7: Wematch.Support US INC. | J7: Wematch.live R&D LTD | K7: Wematch.live Tech Support Europe | L7: Total | M7: INDEX
B8: Amount | C8: Amount | D8: Amount | E8: Amount | F8: Amount | G8: Amount | H8: Amount | I8: Amount | J8: Amount | K8: Amount | L8: Amount
A9: Current Assets
A10: Bank
A11: 100 - DUMMY USD | B11: 0 | C11: 0 | D11: 0 | E11: 0 | F11: 0 | G11: 0 | H11: 0 | I11: 0 | J11: -2039.05 | K11: 0 | L11: =SUM(B11:K11) -> -2039.05 | M11: 10
A12: 10000 - Cash and Cash Equivalent (WRD-IL)
A13: 10001 - Bank Fibi 327492 NIS | B13: 0 | C13: 0 | D13: 0 | E13: 0 | F13: 0 | G13: 0 | H13: 0 | I13: 0 | J13: 95130.17 | K13: 0 | L13: =SUM(B13:K13) -> 95130.17
A14: 10002 - Bank Hapoalim 120737 NIS | B14: 0 | C14: 0 | D14: 0 | E14: 0 | F14: 0 | G14: 0 | H14: 0 | I14: 0 | J14: 281335.24 | K14: 0 | L14: =SUM(B14:K14) -> 281335.24
A15: 10003 - Bank Hapoalim 120737 USD | B15: 0 | C15: 0 | D15: 0 | E15: 0 | F15: 0 | G15: 0 | H15: 0 | I15: 0 | J15: 2680320.9 | K15: 0 | L15: =SUM(B15:K15) -> 2680320.9
A16: 10004 - Bank Hapoalim 120737 GBP | B16: 0 | C16: 0 | D16: 0 | E16: 0 | F16: 0 | G16: 0 | H16: 0 | I16: 0 | J16: 3012.11 | K16: 0 | L16: =SUM(B16:K16) -> 3012.11
A17: 10005 - Bank Hapoalim 120737 EUR | B17: 0 | C17: 0 | D17: 0 | E17: 0 | F17: 0 | G17: 0 | H17: 0 | I17: 0 | J17: 125756.42 | K17: 0 | L17: =SUM(B17:K17) -> 125756.42
A18: 10006 - Bank Hapoalim 120737 CAD | B18: 0 | C18: 0 | D18: 0 | E18: 0 | F18: 0 | G18: 0 | H18: 0 | I18: 0 | J18: 9468.65 | K18: 0 | L18: =SUM(B18:K18) -> 9468.65
A19: 10007 - Bank Hapoalim 120737 SGD | B19: 0 | C19: 0 | D19: 0 | E19: 0 | F19: 0 | G19: 0 | H19: 0 | I19: 0 | J19: 208.81 | K19: 0 | L19: =SUM(B19:K19) -> 208.81
A20: Total - 10000 - Cash and Cash Equivalent (WRD-IL) | B20: =SUM(B13:B19) -> 0 | C20: =SUM(C13:C19) -> 0 | D20: =SUM(D13:D19) -> 0 | E20: =SUM(E13:E19) -> 0 | F20: =SUM(F13:F19) -> 0 | G20: =SUM(G13:G19) -> 0 | H20: =SUM(H13:H19) -> 0 | I20: =SUM(I13:I19) -> 0 | ... L20: =SUM(L13:L19) -> 3195232.3 | M20: 10
A21: 10100 - Cash and Cash Equivalent (WIR-IL)
A22: 10101 - Bank Hapoalim 120720 NIS | B22: 0 | C22: 0 | D22: 0 | E22: 21.14 | F22: 0 | G22: 0 | H22: 0 | I22: 0 | J22: 0 | K22: 0 | L22: =SUM(B22:K22) -> 21.14
A23: Total - 10100 - Cash and Cash Equivalent (WIR-IL) | B23: =SUM(B22) -> 0 | C23: =SUM(C22) -> 0 | D23: =SUM(D22) -> 0 | E23: =SUM(E22) -> 21.14 | F23: =SUM(F22) -> 0 | G23: =SUM(G22) -> 0 | H23: =SUM(H22) -> 0 | I23: =SUM(I22) -> 0 | ... L23: =SUM(L22) -> 21.14 | M23: 10
A24: 102 - DUMMY - FR | B24: 0 | C24: 0 | D24: 0 | E24: 0 | F24: 0 | G24: 0 | H24: 0 | I24: 0 | J24: 0 | K24: 18.74 | L24: =SUM(B24:K24) -> 18.74 | M24: 10
A25: 10200 - Cash and Cash Equivalent (WSF-IL)
A26: 10201 - Bank Hapoalim 120729 NIS | B26: 0 | C26: 0 | D26: 0 | E26: 0 | F26: 45.87 | G26: 0 | H26: 0 | I26: 0 | J26: 0 | K26: 0 | L26: =SUM(B26:K26) -> 45.87
A27: 10202 - Bank Hapoalim 120729 USD | B27: 0 | C27: 0 | D27: 0 | E27: 0 | F27: 24.67 | G27: 0 | H27: 0 | I27: 0 | J27: 0 | K27: 0 | L27: =SUM(B27:K27) -> 24.67
A28: 10203 - Bank Hapoalim 120729 EUR | B28: 0 | C28: 0 | D28: 0 | E28: 0 | F28: 228.83 | G28: 0 | H28: 0 | I28: 0 | J28: 0 | K28: 0 | L28: =SUM(B28:K28) -> 228.83
A29: Total - 10200 - Cash and Cash Equivalent (WSF-IL) | B29: =SUM(B26:B28) -> 0 | C29: =SUM(C26:C28) -> 0 | D29: =SUM(D26:D28) -> 0 | E29: =SUM(E26:E28) -> 0 | F29: =SUM(F26:F28) -> 299.37 | G29: =SUM(G26:G28) -> 0 | H29: =SUM(H26:H28) -> 0 | I29: =SUM(I26:I28) -> 0 | ... L29: =SUM(L26:L28) -> 299.37 | M29: 10
A30: 10300 - Cash and Cash Equivalent (WEQD-IL)
A31: 10301 - Bank Hapoalim 120702 NIS | B31: 0 | C31: 0 | D31: 19 | E31: 0 | F31: 0 | G31: 0 | H31: 0 | I31: 0 | J31: 0 | K31: 0 | L31: =SUM(B31:K31) -> 19
A32: 10302 - Bank Hapoalim 120702 USD | B32: 0 | C32: 0 | D32: 6438.02 | E32: 0 | F32: 0 | G32: 0 | H32: 0 | I32: 0 | J32: 0 | K32: 0 | L32: =SUM(B32:K32) -> 6438.02
A33: 10303 - Bank BIA | B33: 0 | C33: 0 | D33: 14237.25 | E33: 0 | F33: 0 | G33: 0 | H33: 0 | I33: 0 | J33: 0 | K33: 0 | L33: =SUM(B33:K33) -> 14237.25
A34: Total - 10300 - Cash and Cash Equivalent (WEQD-IL) | B34: =SUM(B31:B33) -> 0 | C34: =SUM(C31:C33) -> 0 | D34: =SUM(D31:D33) -> 20694.27 | E34: =SUM(E31:E33) -> 0 | F34: =SUM(F31:F33) -> 0 | G34: =SUM(G31:G33) -> 0 | H34: =SUM(H31:H33) -> 0 | I34: =SUM(I31:I33) -> 0 | ... L34: =SUM(L31:L33) -> 20694.27 | M34: 10
A35: 10400 - Cash and Cash Equivalent (WSF-UK)
A36: 10401 - Bank Netwest 27557405 £ | B36: 0 | C36: 0 | D36: 0 | E36: 0 | F36: 0 | G36: 0 | H36: 166161.23 | I36: 0 | J36: 0 | K36: 0 | L36: =SUM(B36:K36) -> 166161.23
A37: 70942471 - Soldo UK Wallet | B37: 0 | C37: 0 | D37: 0 | E37: 0 | F37: 0 | G37: 0 | H37: 29596.33 | I37: 0 | J37: 0 | K37: 0 | L37: =SUM(B37:K37) -> 29596.33
A38: Total - 10400 - Cash and Cash Equivalent (WSF-UK) | B38: =SUM(B36:B37) -> 0 | C38: =SUM(C36:C37) -> 0 | D38: =SUM(D36:D37) -> 0 | E38: =SUM(E36:E37) -> 0 | F38: =SUM(F36:F37) -> 0 | G38: =SUM(G36:G37) -> 0 | H38: =SUM(H36:H37) -> 195757.56 | I38: =SUM(I36:I37) -> 0 | ... L38: =SUM(L36:L37) -> 195757.56 | M38: 10
A39: 10500 - Cash and Cash Equivalent (WTSE-FR)
A40: 10501 - Bank SG 20020671 EUR | B40: 0 | C40: 0 | D40: 0 | E40: 0 | F40: 0 | G40: 0 | H40: 0 | I40: 0 | J40: 0 | K40: 198122.7 | L40: =SUM(B40:K40) -> 198122.7
A41: 70424674 - Soldo FR Wallet € | B41: 0 | C41: 0 | D41: 0 | E41: 0 | F41: 0 | G41: 0 | H41: 0 | I41: 0 | J41: 0 | K41: 10257.38 | L41: =SUM(B41:K41) -> 10257.38
A42: Total - 10500 - Cash and Cash Equivalent (WTSE-FR) | B42: =SUM(B40:B41) -> 0 | C42: =SUM(C40:C41) -> 0 | D42: =SUM(D40:D41) -> 0 | E42: =SUM(E40:E41) -> 0 | F42: =SUM(F40:F41) -> 0 | G42: =SUM(G40:G41) -> 0 | H42: =SUM(H40:H41) -> 0 | I42: =SUM(I40:I41) -> 0 | ... L42: =SUM(L40:L41) -> 208380.08 | M42: 10
A43: 10600 - Cash and Cash Equivalent (WUS-US)
A44: 10601 - Bank Hapoalim 542 Saving USD | B44: 0 | C44: 0 | D44: 0 | E44: 0 | F44: 0 | G44: 0 | H44: 0 | I44: 451223.9 | J44: 0 | K44: 0 | L44: =SUM(B44:K44) -> 451223.9
A45: 10602 - Bank Hapoalim 0700 Checking USD | B45: 0 | C45: 0 | D45: 0 | E45: 0 | F45: 0 | G45: 0 | H45: 0 | I45: 33151.29 | J45: 0 | K45: 0 | L45: =SUM(B45:K45) -> 33151.29
A46: 10603 - Bank Hapoalim 2845 Checking USD | B46: 0 | C46: 0 | D46: 0 | E46: 0 | F46: 0 | G46: 19813.74 | H46: 0 | I46: 0 | J46: 0 | K46: 0 | L46: =SUM(B46:K46) -> 19813.74
A47: 10604 - Bank Hapoalim 3800 Saving USD | B47: 0 | C47: 0 | D47: 0 | E47: 0 | F47: 0 | G47: 1154849.1 | H47: 0 | I47: 0 | J47: 0 | K47: 0 | L47: =SUM(B47:K47) -> 1154849.1
A48: 14251668 - Soldo US LLC Wallet $ | B48: 0 | C48: 0 | D48: 0 | E48: 0 | F48: 0 | G48: 7928.46 | H48: 0 | I48: 0 | J48: 0 | K48: 0 | L48: =SUM(B48:K48) -> 7928.46
A49: 14251669 - Soldo US INC Wallet £ | B49: 0 | C49: 0 | D49: 0 | E49: 0 | F49: 0 | G49: 0 | H49: 0 | I49: 421.68 | J49: 0 | K49: 0 | L49: =SUM(B49:K49) -> 421.68
A50: 37940705 - Soldo US LLC Wallet £ | B50: 0 | C50: 0 | D50: 0 | E50: 0 | F50: 0 | G50: 501.84 | H50: 0 | I50: 0 | J50: 0 | K50: 0 | L50: =SUM(B50:K50) -> 501.84
A51: 65554811 - Soldo US INC Wallet $ | B51: 0 | C51: 0 | D51: 0 | E51: 0 | F51: 0 | G51: 0 | H51: 0 | I51: 5297.35 | J51: 0 | K51: 0 | L51: =SUM(B51:K51) -> 5297.35
A52: Total - 10600 - Cash and Cash Equivalent (WUS-US) | B52: =SUM(B44:B51) -> 0 | C52: =SUM(C44:C51) -> 0 | D52: =SUM(D44:D51) -> 0 | E52: =SUM(E44:E51) -> 0 | F52: =SUM(F44:F51) -> 0 | G52: =SUM(G44:G51) -> 1183093.2 | H52: =SUM(H44:H51) -> 0 | I52: =SUM(I44:I51) -> 490094.22 | ... L52: =SUM(L44:L51) -> 1673187.4 | M52: 10
A53: 11000 - Short-term Restricted cash
A54: 11001 - Bank Hapoalim Deposit NIS | B54: 0 | C54: 0 | D54: 0 | E54: 0 | F54: 0 | G54: 0 | H54: 0 | I54: 0 | J54: 16744.01 | K54: 0 | L54: =SUM(B54:K54) -> 16744.01
A55: 11002 - Bank FIBI Deposit NIS | B55: 0 | C55: 0 | D55: 0 | E55: 0 | F55: 0 | G55: 0 | H55: 0 | I55: 0 | J55: 2767.89 | K55: 0 | L55: =SUM(B55:K55) -> 2767.89
A56: 11003 - Bank FIBI Deposit EUR | B56: 0 | C56: 0 | D56: 0 | E56: 0 | F56: 0 | G56: 0 | H56: 0 | I56: 0 | J56: 8345.64 | K56: 0 | L56: =SUM(B56:K56) -> 8345.64
A57: Total - 11000 - Short-term Restricted cash | B57: =SUM(B54:B56) -> 0 | C57: =SUM(C54:C56) -> 0 | D57: =SUM(D54:D56) -> 0 | E57: =SUM(E54:E56) -> 0 | F57: =SUM(F54:F56) -> 0 | G57: =SUM(G54:G56) -> 0 | H57: =SUM(H54:H56) -> 0 | I57: =SUM(I54:I56) -> 0 | ... L57: =SUM(L54:L56) -> 27857.54 | M57: 11
A58: 11100 - Short term Bank Deposit
A59: 11101 - Short term Bank Deposit [BANK HAPOALIM] | B59: 0 | C59: 0 | D59: 0 | E59: 0 | F59: 0 | G59: 0 | H59: 0 | I59: 0 | J59: 7249271.4 | K59: 0 | L59: =SUM(B59:K59) -> 7249271.4
A60: 11102 - Short term Bank Deposit [HAPOALIM EUR] | B60: 0 | C60: 0 | D60: 0 | E60: 0 | F60: 0 | G60: 0 | H60: 0 | I60: 0 | J60: 441742.78 | K60: 0 | L60: =SUM(B60:K60) -> 441742.78
A61: 11103 - Soc Gen Deposit 2258E2376200016 | B61: 0 | C61: 0 | D61: 0 | E61: 0 | F61: 0 | G61: 0 | H61: 0 | I61: 0 | J61: 0 | K61: 441568 | L61: =SUM(B61:K61) -> 441568
A62: 11104 - Soc Gen Deposit 2258E2376200024 | B62: 0 | C62: 0 | D62: 0 | E62: 0 | F62: 0 | G62: 0 | H62: 0 | I62: 0 | J62: 0 | K62: 165588 | L62: =SUM(B62:K62) -> 165588
A63: Total - 11100 - Short term Bank Deposit | B63: =SUM(B59:B62) -> 0 | C63: =SUM(C59:C62) -> 0 | D63: =SUM(D59:D62) -> 0 | E63: =SUM(E59:E62) -> 0 | F63: =SUM(F59:F62) -> 0 | G63: =SUM(G59:G62) -> 0 | H63: =SUM(H59:H62) -> 0 | I63: =SUM(I59:I62) -> 0 | ... L63: =SUM(L59:L62) -> 8298170.1 | M63: 11
A64: Total Bank | B64: =SUM(B11,B20,B23:B24,B29,B34,B38,B42,B52,B57,B63) -> 0 | C64: =SUM(C11,C20,C23:C24,C29,C34,C38,C42,C52,C57,C63) -> 0 | D64: =SUM(D11,D20,D23:D24,D29,D34,D38,D42,D52,D57,D63) -> 20694.27 | E64: =SUM(E11,E20,E23:E24,E29,E34,E38,E42,E52,E57,E63) -> 21.14 | F64: =SUM(F11,F20,F23:F24,F29,F34,F38,F42,F52,F57,F63) -> 299.37 | G64: =SUM(G11,G20,G23:G24,G29,G34,G38,G42,G52,G57,G63) -> 1183093.2 | H64: =SUM(H11,H20,H23:H24,H29,H34,H38,H42,H52,H57,H63) -> 195757.56 | I64: =SUM(I11,I20,I23:I24,I29,I34,I38,I42,I52,I57,I63) -> 490094.22 | ... L64: =SUM(L11,L20,L23:L24,L29,L34,L38,L42,L52,L57,L63) -> 13617579
A65: Accounts Receivable
A66: 12000 - Accounts Receivable
A67: 12001 - Accounts Receivable | B67: 0 | C67: 0 | D67: 0 | E67: 0 | F67: 0 | G67: 0 | H67: 0 | I67: 0 | J67: 424623.05 | K67: 0 | L67: =SUM(B67:K67) -> 424623.05 | M67: 12
A68: Total - 12000 - Accounts Receivable | B68: =SUM(B67) -> 0 | C68: =SUM(C67) -> 0 | D68: =SUM(D67) -> 0 | E68: =SUM(E67) -> 0 | F68: =SUM(F67) -> 0 | G68: =SUM(G67) -> 0 | H68: =SUM(H67) -> 0 | I68: =SUM(I67) -> 0 | ... L68: =SUM(L67) -> 424623.05 | M68: 12.1
A69: Total Accounts Receivable | B69: =SUM(B68) -> 0 | C69: =SUM(C68) -> 0 | D69: =SUM(D68) -> 0 | E69: =SUM(E68) -> 0 | F69: =SUM(F68) -> 0 | G69: =SUM(G68) -> 0 | H69: =SUM(H68) -> 0 | I69: =SUM(I68) -> 0 | ... L69: =SUM(L68) -> 424623.05
A70: Unbilled Receivable
A71: 12003 - Unbilled Receivable | B71: 0 | C71: 0 | D71: 0 | E71: 0 | F71: 0 | G71: 0 | H71: 0 | I71: 0 | J71: 20816.79 | K71: 0 | L71: =SUM(B71:K71) -> 20816.79
A72: Total Unbilled Receivable | B72: =SUM(B71) -> 0 | C72: =SUM(C71) -> 0 | D72: =SUM(D71) -> 0 | E72: =SUM(E71) -> 0 | F72: =SUM(F71) -> 0 | G72: =SUM(G71) -> 0 | H72: =SUM(H71) -> 0 | I72: =SUM(I71) -> 0 | ... L72: =SUM(L71) -> 20816.79 | M72: 12
A73: Other Current Asset
A74: 12004 - Unbilled Revenue | B74: 0 | C74: 0 | D74: 0 | E74: 0 | F74: 0 | G74: 0 | H74: 0 | I74: 0 | J74: 213442.28 | K74: 0 | L74: =SUM(B74:K74) -> 213442.28 | M74: 12
A75: 12600 - Intercompany (O.C Assets)
A76: 12601 - WeMatch.Securitiesfinancing Ltd. [P] | B76: -4197205.6 | C76: 0 | D76: 0 | E76: 0 | F76: 0 | G76: 0 | H76: 2290955.5 | I76: 0 | J76: 1906250.1 | K76: 0 | L76: =SUM(B76:K76) -> 0
A77: 12602 - WeMatch.Live Tech Support Europe [P] | B77: -2131357.1 | C77: 0 | D77: 0 | E77: 0 | F77: 0 | G77: 0 | H77: 0 | I77: 0 | J77: 1302084.4 | K77: 829272.76 | L77: =SUM(B77:K77) -> 0
A78: 12603 - WeMatch Securities Financing Ltd. [P] | B78: -48502.45 | C78: 0 | D78: 0 | E78: 0 | F78: 48177.9 | G78: 0 | H78: 0 | I78: -636.59 | J78: 961.14 | K78: 0 | L78: =SUM(B78:K78) -> 4.3200998e-12
A79: 12605 - WeMatch EQD Ltd. [P] | B79: -4417.64 | C79: 0 | D79: 4417.64 | E79: 0 | F79: 0 | G79: 0 | H79: 0 | I79: 0 | J79: 0 | K79: 0 | L79: =SUM(B79:K79) -> 0
A80: 12606 - Wematch.Support US INC [P] | B80: -2406220 | C80: 1000 | D80: 0 | E80: 0 | F80: 0 | G80: -1000 | H80: 15878.25 | I80: 478909.01 | J80: 1911432.7 | K80: 0 | L80: =SUM(B80:K80) -> -2.3283064e-10
A81: 12607 - Wematch.Support US LLC [P] | B81: -3734.99 | C81: 7338.78 | D81: 0 | E81: 0 | F81: 0 | G81: -10370.79 | H81: 3250 | I81: 0 | J81: 3517 | K81: 0 | L81: =SUM(B81:K81) -> -9.094947e-13
A82: Total - 12600 - Intercompany (O.C Assets) | B82: =SUM(B76:B81) -> -8791437.7 | C82: =SUM(C76:C81) -> 8338.78 | D82: =SUM(D76:D81) -> 4417.64 | E82: =SUM(E76:E81) -> 0 | F82: =SUM(F76:F81) -> 48177.9 | G82: =SUM(G76:G81) -> -11370.79 | H82: =SUM(H76:H81) -> 2310083.7 | I82: =SUM(I76:I81) -> 478272.42 | ... L82: =SUM(L76:L81) -> -2.2942004e-10 | M82: 13
A83: 13000 - Prepaid Exp.
A84: 13001 - Prepaid Expenses | B84: 0 | C84: 0 | D84: 0 | E84: 0 | F84: 0 | G84: 12730.62 | H84: 12158.82 | I84: 24121.45 | J84: 181028.76 | K84: 8599.91 | L84: =SUM(B84:K84) -> 238639.56 | M84: 13.1
A85: 13002 - Prepaid rent | B85: 0 | C85: 0 | D85: 0 | E85: 0 | F85: 0 | G85: 0 | H85: 26219.86 | I85: 5400 | J85: 2975.84 | K85: 0 | L85: =SUM(B85:K85) -> 34595.7 | M85: 13.1
A86: Total - 13000 - Prepaid Exp. | B86: =SUM(B84:B85) -> 0 | C86: =SUM(C84:C85) -> 0 | D86: =SUM(D84:D85) -> 0 | E86: =SUM(E84:E85) -> 0 | F86: =SUM(F84:F85) -> 0 | G86: =SUM(G84:G85) -> 12730.62 | H86: =SUM(H84:H85) -> 38378.68 | I86: =SUM(I84:I85) -> 29521.45 | ... L86: =SUM(L84:L85) -> 273235.26 | M86: 13
A87: 13009 - Government Institutions
A88: 13100 - VAT Assets
A89: 13101 - VAT on FA Purchases IL | B89: 0 | C89: 0 | D89: 0 | E89: 0 | F89: 0 | G89: 0 | H89: 0 | I89: 0 | J89: -627 | K89: 0 | L89: =SUM(B89:K89) -> -627
A90: 13102 - VAT on Purchases IL | B90: 0 | C90: 0 | D90: 0 | E90: 0 | F90: 0 | G90: 0 | H90: 0 | I90: 0 | J90: -5460.9 | K90: 0 | L90: =SUM(B90:K90) -> -5460.9
A91: 13103 - VAT Proforma IL | B91: 0 | C91: 0 | D91: 0 | E91: 0 | F91: 0 | G91: 0 | H91: 0 | I91: 0 | J91: 4733.06 | K91: 0 | L91: =SUM(B91:K91) -> 4733.06
A92: 13107 - VAT D/C | B92: 0 | C92: 0 | D92: 0 | E92: 0 | F92: 0 | G92: 0 | H92: 0 | I92: 0 | J92: 26305.05 | K92: 0 | L92: =SUM(B92:K92) -> 26305.05
A93: 13122 - VAT on FA Purchases FR | B93: 0 | C93: 0 | D93: 0 | E93: 0 | F93: 0 | G93: 0 | H93: 0 | I93: 0 | J93: 0 | K93: 5870.77 | L93: =SUM(B93:K93) -> 5870.77
A94: 13123 - VAT on Purchases FR | B94: 0 | C94: 0 | D94: 0 | E94: 0 | F94: 0 | G94: 0 | H94: 0 | I94: 0 | J94: 0 | K94: 16566.87 | L94: =SUM(B94:K94) -> 16566.87
A95: 13124 - VAT deductible on goods and services | B95: 0 | C95: 0 | D95: 0 | E95: 0 | F95: 0 | G95: 0 | H95: 0 | I95: 0 | J95: 0 | K95: 875.41 | L95: =SUM(B95:K95) -> 875.41
A96: 13202 - VAT on Purchases UK | B96: 0 | C96: 0 | D96: 0 | E96: 0 | F96: 0 | G96: 0 | H96: 17208.32 | I96: 0 | J96: 0 | K96: 0 | L96: =SUM(B96:K96) -> 17208.32
A97: Total - 13100 - VAT Assets | B97: =SUM(B89:B96) -> 0 | C97: =SUM(C89:C96) -> 0 | D97: =SUM(D89:D96) -> 0 | E97: =SUM(E89:E96) -> 0 | F97: =SUM(F89:F96) -> 0 | G97: =SUM(G89:G96) -> 0 | H97: =SUM(H89:H96) -> 17208.32 | I97: =SUM(I89:I96) -> 0 | ... L97: =SUM(L89:L96) -> 65471.58 | M97: 13.2
A98: 13300 - TAX Assets
A99: 13301 - Advances for Odfot | B99: 0 | C99: 0 | D99: 0 | E99: 0 | F99: 0 | G99: 0 | H99: 0 | I99: 0 | J99: 17204.02 | K99: 0 | L99: =SUM(B99:K99) -> 17204.02
A100: 13302 - Reversal for Exceed expenses | B100: 0 | C100: 0 | D100: 0 | E100: 0 | F100: 0 | G100: 0 | H100: 0 | I100: 0 | J100: -17204.02 | K100: 0 | L100: =SUM(B100:K100) -> -17204.02
A101: 13303 - Tax Benefits | B101: 0 | C101: 0 | D101: -433.98 | E101: 0 | F101: 0 | G101: 0 | H101: 0 | I101: 0 | J101: 0 | K101: 93942.34 | L101: =SUM(B101:K101) -> 93508.36
A102: 13304 - Other current tax asset | B102: 0 | C102: 0 | D102: 0 | E102: 0 | F102: 0 | G102: 0 | H102: 3267.88 | I102: 0 | J102: 0 | K102: 0 | L102: =SUM(B102:K102) -> 3267.88
...

Sheet Full P&L-USD
A1: Wematch.live R&D LTD
A2: Wematch.live R&D LTD (Consolidated)
A3: WM INCOME STATEMENT for budget -Oren
A4: From Jan 2023 to Dec 2023
A7: Financial Row | B7: Wematch EQD LTD | C7: Wematch Interest rate LTD | D7: Wematch Securities. Financing LTD [IL] | E7: Wematch.Live LLC | F7: Wematch.SecuritiesFinancing LTD | G7: Wematch.Support US INC. | H7: Wematch.live R&D LTD | I7: Wematch.live Tech Support Europe | J7: Total | K7: INDEX | L7: note
B8: Amount | C8: Amount | D8: Amount | E8: Amount | F8: Amount | G8: Amount | H8: Amount | I8: Amount | J8: Amount
A9: Gross Revenue
A10: Securities Financing
A11: TRS | B11: 0 | C11: 0 | D11: 0 | E11: 0 | F11: 0 | G11: 0 | H11: 8244447.1 | I11: 0 | J11: =SUM(B11:I11) -> 8244447.1
A12: SBL | B12: 0 | C12: 0 | D12: 0 | E12: 0 | F12: 0 | G12: 0 | H12: 528827.37 | I12: 0 | J12: =SUM(B12:I12) -> 528827.37
A13: Total - Securities Financing | B13: =SUM(B11:B12) -> 0 | C13: =SUM(C11:C12) -> 0 | D13: =SUM(D11:D12) -> 0 | E13: =SUM(E11:E12) -> 0 | F13: =SUM(F11:F12) -> 0 | G13: =SUM(G11:G12) -> 0 | H13: =SUM(H11:H12) -> 8773274.4 | I13: =SUM(I11:I12) -> 0 | J13: =SUM(J11:J12) -> 8773274.4
A14: Equity Derivative | B14: 0 | C14: 0 | D14: 0 | E14: 0 | F14: 0 | G14: 0 | H14: 272800.02 | I14: 0 | J14: =SUM(B14:I14) -> 272800.02
A15: Interest rate | B15: 0 | C15: 0 | D15: 0 | E15: 0 | F15: 0 | G15: 0 | H15: 419954.86 | I15: 0 | J15: =SUM(B15:I15) -> 419954.86
A16: Total Gross Revenue | B16: =SUM(B13:B15) -> 0 | C16: =SUM(C13:C15) -> 0 | D16: =SUM(D13:D15) -> 0 | E16: =SUM(E13:E15) -> 0 | F16: =SUM(F13:F15) -> 0 | G16: =SUM(G13:G15) -> 0 | H16: =SUM(H13:H15) -> 9466029.3 | I16: =SUM(I13:I15) -> 0 | J16: =SUM(J13:J15) -> 9466029.3 | K16: 1 | L16: 9
A17: Revenue Shared With Regulated Broker Dealer
A18: 45000 - Revenues shared to third parties
A19: 45002 - Commission Shared with third party | B19: 0 | C19: 0 | D19: 0 | E19: 0 | F19: 0 | G19: 0 | H19: -1311204.7 | I19: 0 | J19: =SUM(B19:I19) -> -1311204.7 | K19: 2.1
A20: 45001 - ISIN | B20: 0 | C20: 0 | D20: 0 | E20: 0 | F20: 0 | G20: 0 | H20: -36045.01 | I20: 0 | J20: =SUM(B20:I20) -> -36045.01 | K20: 2.1
A21: 45003 - Non Reclaimable VAT | B21: 0 | C21: 0 | D21: 0 | E21: 0 | F21: 0 | G21: 0 | H21: -405247.27 | I21: 0 | J21: =SUM(B21:I21) -> -405247.27 | K21: 2.1
A22: Total - 45000 - Revenues shared to third parties | B22: =SUM(B19:B21) -> 0 | C22: =SUM(C19:C21) -> 0 | D22: =SUM(D19:D21) -> 0 | E22: =SUM(E19:E21) -> 0 | F22: =SUM(F19:F21) -> 0 | G22: =SUM(G19:G21) -> 0 | H22: =SUM(H19:H21) -> -1752497 | I22: =SUM(I19:I21) -> 0 | J22: =SUM(J19:J21) -> -1752497 | K22: 2
A23: Total Revenue Shared With Regulated Broker Dealer | B23: =SUM(B22) -> 0 | C23: =SUM(C22) -> 0 | D23: =SUM(D22) -> 0 | E23: =SUM(E22) -> 0 | F23: =SUM(F22) -> 0 | G23: =SUM(G22) -> 0 | H23: =SUM(H22) -> -1752497 | I23: =SUM(I22) -> 0 | J23: =SUM(J22) -> -1752497
A24: Net Revenue | B24: =+B16+B23 -> 0 | C24: =+C16+C23 -> 0 | D24: =+D16+D23 -> 0 | E24: =+E16+E23 -> 0 | F24: =+F16+F23 -> 0 | G24: =+G16+G23 -> 0 | H24: =+H16+H23 -> 7713532.3 | I24: =+I16+I23 -> 0 | J24: =+J16+J23 -> 7713532.3
A25: Cost Of Sales
A26: CoS
A27: Platform Operation
A28: 50000 - COGS expenses
A29: 50100 - Payroll and Related expenses [COGS]
A30: 50101 - COGS Gross Salaries | B30: 0 | C30: 0 | D30: 0 | E30: -57460.16 | F30: -10363.15 | G30: -18764.36 | H30: -512355.68 | I30: 0 | J30: =SUM(B30:I30) -> -598943.35
A31: 50106 - COGS Workers Compensation | B31: 0 | C31: 0 | D31: 0 | E31: -273.16 | F31: 0 | G31: 0 | H31: 0 | I31: 0 | J31: =SUM(B31:I31) -> -273.16
A32: 50107 - COGS Benefits | B32: 0 | C32: 0 | D32: 0 | E32: 0 | F32: 47.61 | G32: 0 | H32: 0 | I32: 0 | J32: =SUM(B32:I32) -> 47.61
A33: 50108 - COGS Employee stock-based compensation | B33: 0 | C33: 0 | D33: 0 | E33: -288 | F33: -3697.56 | G33: -459 | H33: 0 | I33: -811 | J33: =SUM(B33:I33) -> -5255.56
A34: 50109 - COGS Payroll processing fees | B34: 0 | C34: 0 | D34: 0 | E34: 0 | F34: 0 | G34: 0 | H34: -2073.97 | I34: 0 | J34: =SUM(B34:I34) -> -2073.97
A35: 50112 - COGS Employee Life Insurance | B35: 0 | C35: 0 | D35: 0 | E35: 0 | F35: -41.94 | G35: 0 | H35: 0 | I35: 0 | J35: =SUM(B35:I35) -> -41.94
A36: 50114 - COGS Gym membership | B36: 0 | C36: 0 | D36: 0 | E36: 0 | F36: -828.44 | G36: 0 | H36: 0 | I36: 0 | J36: =SUM(B36:I36) -> -828.44
A37: 51003 - COGS Medical Insurance | B37: 0 | C37: 0 | D37: 0 | E37: -646.9 | F37: -1379.36 | G37: 577.49 | H37: -693.86 | I37: 0 | J37: =SUM(B37:I37) -> -2142.63
A38: Total - 50100 - Payroll and Related expenses [COGS] | B38: =SUM(B30:B37) -> 0 | C38: =SUM(C30:C37) -> 0 | D38: =SUM(D30:D37) -> 0 | E38: =SUM(E30:E37) -> -58668.22 | F38: =SUM(F30:F37) -> -16262.84 | G38: =SUM(G30:G37) -> -18645.87 | H38: =SUM(H30:H37) -> -515123.51 | I38: =SUM(I30:I37) -> -811 | J38: =SUM(J30:J37) -> -609511.44
A39: 50200 - COGS Travel and Entertainment
A40: 50201 - COGS Airfare | B40: 0 | C40: 0 | D40: 0 | E40: 0 | F40: 0 | G40: 0 | H40: -992.96 | I40: 0 | J40: =SUM(B40:I40) -> -992.96
A41: 50202 - COGS Lodging | B41: 0 | C41: 0 | D41: 0 | E41: 0 | F41: 0 | G41: 0 | H41: -992.96 | I41: 0 | J41: =SUM(B41:I41) -> -992.96
A42: Total - 50200 - COGS Travel and Entertainment | B42: =SUM(B40:B41) -> 0 | C42: =SUM(C40:C41) -> 0 | D42: =SUM(D40:D41) -> 0 | E42: =SUM(E40:E41) -> 0 | F42: =SUM(F40:F41) -> 0 | G42: =SUM(G40:G41) -> 0 | H42: =SUM(H40:H41) -> -1985.92 | I42: =SUM(I40:I41) -> 0 | J42: =SUM(J40:J41) -> -1985.92
A43: 50300 - COGS Tools/ Systems
A44: 50301 - COGS Tools | B44: 0 | C44: 0 | D44: 0 | E44: -6779.01 | F44: -179.85 | G44: -621.22 | H44: -187942.97 | I44: 0 | J44: =SUM(B44:I44) -> -195523.05
A45: Total - 50300 - COGS Tools/ Systems | B45: =SUM(B44) -> 0 | C45: =SUM(C44) -> 0 | D45: =SUM(D44) -> 0 | E45: =SUM(E44) -> -6779.01 | F45: =SUM(F44) -> -179.85 | G45: =SUM(G44) -> -621.22 | H45: =SUM(H44) -> -187942.97 | I45: =SUM(I44) -> 0 | J45: =SUM(J44) -> -195523.05
A46: 51000 - Payroll Taxes [COGS]
A47: 51001 - Social Security | B47: 0 | C47: 0 | D47: 0 | E47: -4039.42 | F47: -2101.14 | G47: -1427.02 | H47: -544.48 | I47: 0 | J47: =SUM(B47:I47) -> -8112.06
A48: 51103 - COGS Car value - Debit | B48: 0 | C48: 0 | D48: 0 | E48: 0 | F48: 0 | G48: 192.49 | H48: 0 | I48: 0 | J48: =SUM(B48:I48) -> 192.49
A49: Total - 51000 - Payroll Taxes [COGS] | B49: =SUM(B47:B48) -> 0 | C49: =SUM(C47:C48) -> 0 | D49: =SUM(D47:D48) -> 0 | E49: =SUM(E47:E48) -> -4039.42 | F49: =SUM(F47:F48) -> -2101.14 | G49: =SUM(G47:G48) -> -1234.53 | H49: =SUM(H47:H48) -> -544.48 | I49: =SUM(I47:I48) -> 0 | J49: =SUM(J47:J48) -> -7919.57
A50: 51100 - Other Payroll related cost [COGS]
A51: 51101 - Pension Contribution [COGS] | B51: 0 | C51: 0 | D51: 0 | E51: -1729.79 | F51: -386.28 | G51: -746.13 | H51: -2936.43 | I51: 0 | J51: =SUM(B51:I51) -> -5798.63
A52: Total - 51100 - Other Payroll related cost [COGS] | B52: =SUM(B51) -> 0 | C52: =SUM(C51) -> 0 | D52: =SUM(D51) -> 0 | E52: =SUM(E51) -> -1729.79 | F52: =SUM(F51) -> -386.28 | G52: =SUM(G51) -> -746.13 | H52: =SUM(H51) -> -2936.43 | I52: =SUM(I51) -> 0 | J52: =SUM(J51) -> -5798.63
A53: 51110 - Recruiting Fees | B53: 0 | C53: 0 | D53: 0 | E53: 0 | F53: 0 | G53: 0 | H53: -11748.07 | I53: 0 | J53: =SUM(B53:I53) -> -11748.07
A54: Total - 50000 - COGS expenses | B54: =SUM(B38,B42,B45,B49,B52:B53) -> 0 | C54: =SUM(C38,C42,C45,C49,C52:C53) -> 0 | D54: =SUM(D38,D42,D45,D49,D52:D53) -> 0 | E54: =SUM(E38,E42,E45,E49,E52:E53) -> -71216.44 | F54: =SUM(F38,F42,F45,F49,F52:F53) -> -18930.11 | G54: =SUM(G38,G42,G45,G49,G52:G53) -> -21247.75 | H54: =SUM(H38,H42,H45,H49,H52:H53) -> -720281.38 | I54: =SUM(I38,I42,I45,I49,I52:I53) -> -811 | J54: =SUM(J38,J42,J45,J49,J52:J53) -> -832486.68 | K54: 2.2
A55: 61000 - Salaries & Wages
A56: 61700 - Team Events & Welfare
A57: 61703 - Employee meals | B57: 0 | C57: 0 | D57: 0 | E57: 0 | F57: 0 | G57: 0 | H57: 0 | I57: -178.79 | J57: =SUM(B57:I57) -> -178.79
A58: Total - 61700 - Team Events & Welfare | B58: =SUM(B57) -> 0 | C58: =SUM(C57) -> 0 | D58: =SUM(D57) -> 0 | E58: =SUM(E57) -> 0 | F58: =SUM(F57) -> 0 | G58: =SUM(G57) -> 0 | H58: =SUM(H57) -> 0 | I58: =SUM(I57) -> -178.79 | J58: =SUM(J57) -> -178.79
A59: Total - 61000 - Salaries & Wages | B59: =SUM(B58) -> 0 | C59: =SUM(C58) -> 0 | D59: =SUM(D58) -> 0 | E59: =SUM(E58) -> 0 | F59: =SUM(F58) -> 0 | G59: =SUM(G58) -> 0 | H59: =SUM(H58) -> 0 | I59: =SUM(I58) -> -178.79 | J59: =SUM(J58) -> -178.79
A60: 62000 - Travel and Entertainment
A61: 62100 - Travel & Entertainment
A62: 62103 - Ground Transportation | B62: 0 | C62: 0 | D62: 0 | E62: -60 | F62: 0 | G62: 0 | H62: 0 | I62: 0 | J62: =SUM(B62:I62) -> -60
A63: Total - 62100 - Travel & Entertainment | B63: =SUM(B62) -> 0 | C63: =SUM(C62) -> 0 | D63: =SUM(D62) -> 0 | E63: =SUM(E62) -> -60 | F63: =SUM(F62) -> 0 | G63: =SUM(G62) -> 0 | H63: =SUM(H62) -> 0 | I63: =SUM(I62) -> 0 | J63: =SUM(J62) -> -60
A64: Total - 62000 - Travel and Entertainment | B64: =SUM(B63) -> 0 | C64: =SUM(C63) -> 0 | D64: =SUM(D63) -> 0 | E64: =SUM(E63) -> -60 | F64: =SUM(F63) -> 0 | G64: =SUM(G63) -> 0 | H64: =SUM(H63) -> 0 | I64: =SUM(I63) -> 0 | J64: =SUM(J63) -> -60
A65: 67000 - IT, Rent, & Office Expenses
A66: 67100 - Rent Expenses
A67: 67101 - Office rent | B67: 0 | C67: 0 | D67: 0 | E67: 0 | F67: -1266.01 | G67: 0 | H67: 0 | I67: -3506.36 | J67: =SUM(B67:I67) -> -4772.37
A68: Total - 67100 - Rent Expenses | B68: =SUM(B67) -> 0 | C68: =SUM(C67) -> 0 | D68: =SUM(D67) -> 0 | E68: =SUM(E67) -> 0 | F68: =SUM(F67) -> -1266.01 | G68: =SUM(G67) -> 0 | H68: =SUM(H67) -> 0 | I68: =SUM(I67) -> -3506.36 | J68: =SUM(J67) -> -4772.37
A69: 67300 - Software & Equipment
A70: 62105 - Communication | B70: 0 | C70: 0 | D70: 0 | E70: 0 | F70: -4.04 | G70: 0 | H70: 0 | I70: 0 | J70: =SUM(B70:I70) -> -4.04
A71: 67301 - IT Equipment (non-capitalizable) | B71: 0 | C71: 0 | D71: 0 | E71: 0 | F71: -28.89 | G71: -97.2 | H71: 0 | I71: -27.2 | J71: =SUM(B71:I71) -> -153.29
A72: 67303 - IT services | B72: 0 | C72: 0 | D72: 0 | E72: 0 | F72: -7.22 | G72: 0 | H72: 0 | I72: -18.77 | J72: =SUM(B72:I72) -> -25.99
A73: Total - 67300 - Software & Equipment | B73: =SUM(B70:B72) -> 0 | C73: =SUM(C70:C72) -> 0 | D73: =SUM(D70:D72) -> 0 | E73: =SUM(E70:E72) -> 0 | F73: =SUM(F70:F72) -> -40.15 | G73: =SUM(G70:G72) -> -97.2 | H73: =SUM(H70:H72) -> 0 | I73: =SUM(I70:I72) -> -45.97 | J73: =SUM(J70:J72) -> -183.32
A74: 67400 - Other Office Expenses
A75: 67401 - Office Supplies | B75: 0 | C75: 0 | D75: 0 | E75: 0 | F75: -6.1 | G75: 0 | H75: 0 | I75: -34.24 | J75: =SUM(B75:I75) -> -40.34
A76: 67402 - Office Food | B76: 0 | C76: 0 | D76: 0 | E76: 0 | F76: -73.86 | G76: 0 | H76: 0 | I76: -137.24 | J76: =SUM(B76:I76) -> -211.1
A77: Total - 67400 - Other Office Expenses | B77: =SUM(B75:B76) -> 0 | C77: =SUM(C75:C76) -> 0 | D77: =SUM(D75:D76) -> 0 | E77: =SUM(E75:E76) -> 0 | F77: =SUM(F75:F76) -> -79.96 | G77: =SUM(G75:G76) -> 0 | H77: =SUM(H75:H76) -> 0 | I77: =SUM(I75:I76) -> -171.48 | J77: =SUM(J75:J76) -> -251.44
A78: 67500 - Insurance
A79: 67504 - Life / Risk insurance | B79: 0 | C79: 0 | D79: 0 | E79: 0 | F79: -7.88 | G79: 0 | H79: 0 | I79: 0 | J79: =SUM(B79:I79) -> -7.88
A80: Total - 67500 - Insurance | B80: =SUM(B79) -> 0 | C80: =SUM(C79) -> 0 | D80: =SUM(D79) -> 0 | E80: =SUM(E79) -> 0 | F80: =SUM(F79) -> -7.88 | G80: =SUM(G79) -> 0 | H80: =SUM(H79) -> 0 | I80: =SUM(I79) -> 0 | J80: =SUM(J79) -> -7.88
A81: Total - 67000 - IT, Rent, & Office Expenses | B81: =SUM(B68,B73,B77,B80) -> 0 | C81: =SUM(C68,C73,C77,C80) -> 0 | D81: =SUM(D68,D73,D77,D80) -> 0 | E81: =SUM(E68,E73,E77,E80) -> 0 | F81: =SUM(F68,F73,F77,F80) -> -1394 | G81: =SUM(G68,G73,G77,G80) -> -97.2 | H81: =SUM(H68,H73,H77,H80) -> 0 | I81: =SUM(I68,I73,I77,I80) -> -3723.81 | J81: =SUM(J68,J73,J77,J80) -> -5215.01
A82: 69000 - Depreciation & Amortization
A83: 69001 - Depr. - Computers & Software Licenses | B83: 0 | C83: 0 | D83: 0 | E83: 0 | F83: -32.28 | G83: -599.65 | H83: 0 | I83: -75.23 | J83: =SUM(B83:I83) -> -707.16
A84: 69002 - Depr. - Furniture and Fixtures | B84: 0 | C84: 0 | D84: 0 | E84: 0 | F84: -4.43 | G84: 0 | H84: 0 | I84: 0 | J84: =SUM(B84:I84) -> -4.43
A85: 69003 - Depr. - Electric & Office Equipment | B85: 0 | C85: 0 | D85: 0 | E85: 0 | F85: -3.21 | G85: -27.79 | H85: 0 | I85: -15.27 | J85: =SUM(B85:I85) -> -46.27
A86: Total - 69000 - Depreciation & Amortization | B86: =SUM(B83:B85) -> 0 | C86: =SUM(C83:C85) -> 0 | D86: =SUM(D83:D85) -> 0 | E86: =SUM(E83:E85) -> 0 | F86: =SUM(F83:F85) -> -39.92 | G86: =SUM(G83:G85) -> -627.44 | H86: =SUM(H83:H85) -> 0 | I86: =SUM(I83:I85) -> -90.5 | J86: =SUM(J83:J85) -> -757.86
A87: Total - Platform Operation | B87: =SUM(B54,B59,B64,B81,B86) -> 0 | C87: =SUM(C54,C59,C64,C81,C86) -> 0 | D87: =SUM(D54,D59,D64,D81,D86) -> 0 | E87: =SUM(E54,E59,E64,E81,E86) -> -71276.44 | F87: =SUM(F54,F59,F64,F81,F86) -> -20364.03 | G87: =SUM(G54,G59,G64,G81,G86) -> -21972.39 | H87: =SUM(H54,H59,H64,H81,H86) -> -720281.38 | I87: =SUM(I54,I59,I64,I81,I86) -> -4804.1 | J87: =SUM(J54,J59,J64,J81,J86) -> -838698.34
A88: Tech. Support
A89: 50000 - COGS expenses
A90: 50100 - Payroll and Related expenses [COGS]
A91: 50101 - COGS Gross Salaries | B91: 0 | C91: 0 | D91: 0 | E91: 0 | F91: 0 | G91: -3171.4 | H91: -26563.61 | I91: -79853.65 | J91: =SUM(B91:I91) -> -109588.66
A92: 50105 - COGS Employer taxes | B92: 0 | C92: 0 | D92: 0 | E92: 0 | F92: 0 | G92: 0 | H92: 0 | I92: -788.86 | J92: =SUM(B92:I92) -> -788.86
A93: 50106 - COGS Workers Compensation | B93: 0 | C93: 0 | D93: 0 | E93: 0 | F93: 0 | G93: -18.55 | H93: 0 | I93: 0 | J93: =SUM(B93:I93) -> -18.55
A94: 50107 - COGS Benefits | B94: 0 | C94: 0 | D94: 0 | E94: 0 | F94: 0 | G94: 0 | H94: 0 | I94: -835.13 | J94: =SUM(B94:I94) -> -835.13
A95: 50108 - COGS Employee stock-based compensation | B95: 0 | C95: 0 | D95: 0 | E95: 0 | F95: -102 | G95: 0 | H95: -1895 | I95: -3820 | J95: =SUM(B95:I95) -> -5817
A96: 50110 - COGS Employee's housing | B96: 0 | C96: 0 | D96: 0 | E96: 0 | F96: 0 | G96: -162 | H96: 0 | I96: 0 | J96: =SUM(B96:I96) -> -162
A97: 50111 - COGS Keren Hishtalmut | B97: 0 | C97: 0 | D97: 0 | E97: 0 | F97: 0 | G97: 0 | H97: -1713.33 | I97: 0 | J97: =SUM(B97:I97) -> -1713.33
A98: 50112 - COGS Employee Life Insurance | B98: 0 | C98: 0 | D98: 0 | E98: 0 | F98: 0 | G98: 0 | H98: 0 | I98: -28.89 | J98: =SUM(B98:I98) -> -28.89
A99: 50115 - COGS Employee meals | B99: 0 | C99: 0 | D99: 0 | E99: 0 | F99: 0 | G99: 0 | H99: -764.23 | I99: -62.87 | J99: =SUM(B99:I99) -> -827.1
A100: 50117 - COGS Vacation expenses | B100: 0 | C100: 0 | D100: 0 | E100: 0 | F100: 0 | G100: 0 | H100: 1314.06 | I100: 0 | J100: =SUM(B100:I100) -> 1314.06
A101: 51003 - COGS Medical Insurance | B101: 0 | C101: 0 | D101: 0 | E101: 0 | F101: 0 | G101: 0 | H101: 0 | I101: 83.54 | J101: =SUM(B101:I101) -> 83.54
A102: Total - 50100 - Payroll and Related expenses [COGS] | B102: =SUM(B91:B101) -> 0 | C102: =SUM(C91:C101) -> 0 | D102: =SUM(D91:D101) -> 0 | E102: =SUM(E91:E101) -> 0 | F102: =SUM(F91:F101) -> -102 | G102: =SUM(G91:G101) -> -3351.95 | H102: =SUM(H91:H101) -> -29622.11 | I102: =SUM(I91:I101) -> -85305.86 | J102: =SUM(J91:J101) -> -118381.92
...

Sheet Solo--->

Sheet Change in Equity ILS
D3: הון | F3: חייבים על חשבון מניות | H3: פרמיה | J3: עודפים | L3: סה"כ
D4: המניות
D5: אלפי ש"ח
B7: יתרה ליום 1 בינואר, 2021 | D7: 16 | F7: -163 | H7: 38957 | J7: -31471 | L7: 7339
B9: הנפקת מניות | D9: 12 | F9: 163 | H9: 89852 | L9: =SUM(D9:K9) -> 90027
B10: קרן הון בגין אופציות | D10: - | H10: 1757 | L10: =SUM(D10:K10) -> 1757
B11: הפסד נקי | D11: - | F11: - | H11: - | J11: -13588 | L11: =SUM(D11:K11) -> -13588
B13: יתרה ליום 31 בדצמבר, 2021 | D13: =SUM(D7:D12) -> 28 | F13: - | H13: =SUM(H7:H12) -> 130566 | J13: =SUM(J7:J12) -> -45059 | L13: =SUM(L7:L12) -> 85535
L14: =SUM(D14:K14) -> 0
B15: מימוש אופציות | F15: =+'WRD Solo BS'!B146/1000-1 -> 22.17112 | L15: =SUM(D15:K15) -> 22.17112
B16: קרן הון בגין אופציות | H16: =+'WRD Solo BS'!E147/1000-1 -> 823.74508 | L16: =SUM(D16:K16) -> 823.74508
B17: הפסד נקי | D17: - | F17: - | H17: - | J17: =+'P&L ILS'!G31 -> -17338 | L17: =+J17 -> -17338
B19: יתרה ליום 31 בדצמבר, 2022 | D19: =SUM(D13:D17) -> 28 | F19: =SUM(F13:F17) -> 22.17112 | H19: =SUM(H13:H17) -> 131389.75 | J19: =SUM(J13:J18) -> -62397 | L19: =SUM(L13:L18) -> 69042.916
L21: =+'BS ILS'!E51/1000-L19 -> 0.27307

Sheet P&L ILS
C1: Wematch.live
C2: USD
B5: INDEX | E5: R&D
E6: 2023 | G6: in 000' | I6: NOTE
B8: 1 | C8: Revenues | E8: =+SUMIF('WRD Solo P&L'!$C$7:$C$674,B8,'WRD Solo P&L'!$B$7:$B$674) -> 22654854 | G8: =+ROUND(E8/1000,0) -> 22655 | I8: =+'NOTES-Conso'!B50 -> 9
B10: 2 | C10: Cost of Revenues | E10: =+SUMIF('WRD Solo P&L'!$C$7:$C$674,B10,'WRD Solo P&L'!$B$7:$B$674) -> -5998216.2 | G10: =+ROUND(E10/1000,0) -> -5998 | I10: =+'NOTES-Conso'!B59 -> 10
B12: 3 | C12: Gross profit | E12: =+E8+E10 -> 16656638 | G12: =+G8+G10 -> 16657
C14: Operating expenses:
A15: Total - R&D | B15: 4.1 | C15: R&D | E15: =+SUMIF('WRD Solo P&L'!$C$7:$C$674,B15,'WRD Solo P&L'!$B$7:$B$674)+'WRD Solo P&L'!E680 -> 19092521 | G15: =+ROUND(E15/1000,0) -> 19093
A16: Total - S&M | B16: 4.2 | C16: S&M | E16: =+SUMIF('WRD Solo P&L'!$C$7:$C$674,B16,'WRD Solo P&L'!$B$7:$B$674)+'WRD Solo P&L'!E681 -> 13490588 | G16: =+ROUND(E16/1000,0) -> 13491
A17: Total - G&A | B17: 4.3 | C17: G&A | E17: =+SUMIF('WRD Solo P&L'!$C$7:$C$674,B17,'WRD Solo P&L'!$B$7:$B$674)+'WRD Solo P&L'!E682 -> 12234312 | G17: =+ROUND(E17/1000,0) -> 12234
A19: Total Operation Expense | B19: 4 | C19: Total Operatiing Expense | E19: =+SUMIF('WRD Solo P&L'!$C$7:$C$674,B19,'WRD Solo P&L'!$B$7:$B$674)+'WRD Solo P&L'!B676 -> 44817421 | G19: =+SUM(G15:G17) -> 44818 | H19: =+E19-E17-E16-E15 -> 0
C21: Operating Loss | E21: =+E12-E19 -> -28160782 | G21: =+G12-G19 -> -28161
B23: 5 | C23: Earning/(Loss) Before Interest & Tax | E23: =+E12-E19 -> -28160782 | G23: =+G12-G19 -> -28161
B25: 6 | C25: Financial expenses, net | E25: =+SUMIF('WRD Solo P&L'!$C$7:$C$674,B25,'WRD Solo P&L'!$B$7:$B$674) -> 10822974 | G25: =+ROUND(E25/1000,0) -> 10823 | I25: =+'NOTES-Conso'!B67 -> 11
B27: 7 | C27: Loss Before Taxes On Income | E27: =+E25+E23 -> -17337808 | G27: =+G25+G23 -> -17338
B29: 8 | C29: Tax on Income | E29: =+SUMIF('WRD Solo P&L'!$C$7:$C$674,B29,'WRD Solo P&L'!$B$7:$B$674) -> 0 | G29: =+ROUND(E29/1000,0) -> 0
C31: Net Loss | E31: =+E27+E29 -> -17337808 | G31: =+G27+G29 -> -17338

Sheet BS ILS
C1: Wematch.live
C2: USD
E5: R&D
E6: 31.12.2023 | G6: in 000' | I6: NOTE
B7: INDEX
C8: Assets | G8: =+E8/1000 -> 0
C10: Current Assets: | G10: =+E10/1000 -> 0
B11: 10 | C11: Cash and cash equivalent | E11: =+SUMIF('WRD Solo BS'!$C$7:$C$154,B11,'WRD Solo BS'!$B$7:$B$154) -> 22763397 | G11: =+ROUND((E11/1000),0)+1 -> 22764
B12: 11 | C12: Short term restricted deposits | E12: =+SUMIF('WRD Solo BS'!$C$7:$C$154,B12,'WRD Solo BS'!$B$7:$B$154) -> 39137419 | G12: =+ROUND((E12/1000),0)+1 -> 39138
B13: 12 | C13: Trade recievables | E13: =+SUMIF('WRD Solo BS'!$C$7:$C$154,B13,'WRD Solo BS'!$B$7:$B$154) -> 6718863.5 | G13: =+ROUND((E13/1000),0)-1 -> 6718 | I13: =+'NOTES-Conso'!B5 -> 3
B14: 13 | C14: other recievables and prepaid expenses | E14: =+SUMIF('WRD Solo BS'!$C$7:$C$154,B14,'WRD Solo BS'!$B$7:$B$154) -> 1047905.9 | G14: =+ROUND((E14/1000),0)-1 -> 1047
B15: 13.5 | C15: intercompany | E15: =+SUMIF('WRD Solo BS'!$C$7:$C$154,B15,'WRD Solo BS'!$B$7:$B$154) -> 16483008 | G15: =+'NOTES-Solo'!E69 -> 3620 | I15: =+'NOTES-Conso'!B10 -> 4
G16: =+E16/1000 -> 0
C17: Total cerrent assets | E17: =+SUM(E11:E15) -> 86150593 | G17: =+SUM(G11:G15) -> 73287
G18: =+E18/1000 -> 0
C20: Long-Term assets:
B21: 14 | C21: loans to employees | E21: =+SUMIF('WRD Solo BS'!$C$7:$C$154,B21,'WRD Solo BS'!$B$7:$B$154) -> 0 | G21: =+ROUND((E21/1000),0) -> 0
B22: 15 | C22: property and equipment | E22: =+SUMIF('WRD Solo BS'!$C$7:$C$154,B22,'WRD Solo BS'!$B$7:$B$154) -> 183362.48 | G22: =+ROUND((E22/1000),0) -> 183 | I22: =+'NOTES-Solo'!B15 -> 5
C25: Total Long-term assets | E25: =+E21+E22 -> 183362.48 | G25: =+ROUND(E25/1000,0) -> 183
C28: Total assets | E28: =+E25+E17 -> 86333955 | G28: =+G25+G17 -> 73470
G30: =+E30/1000 -> 0
C31: Liabilities and shareholders' equity
C33: Current Liabilities:
B35: 16 | C35: Trade payables | E35: =+SUMIF('WRD Solo BS'!$C$7:$C$154,B35,'WRD Solo BS'!$B$7:$B$154) -> 510409.23 | G35: =+ROUND((E35/1000),0) -> 510
B36: 16.1 | C36: Intercompany | E36: =+SUMIF('WRD Solo BS'!$C$7:$C$154,B36,'WRD Solo BS'!$B$7:$B$154)/1000 -> 13044.607 | G36: =-'NOTES-Solo'!E76 -> 181.51692 | I36: =+'NOTES-Conso'!B27 -> 6
B37: 17 | C37: Accrued expenses and other liabilities | E37: =+SUMIF('WRD Solo BS'!$C$7:$C$154,B37,'WRD Solo BS'!$B$7:$B$154) -> 2278915.2 | G37: =+ROUND((E37/1000),0) -> 2279
C39: Total current liabilities | E39: =+E37+E35+E36 -> 2802369.1 | G39: =+G37+G35+G36 -> 2970.5169
C41: Non current Liabilities:
B43: 18 | C43: Long-Term liabilities: | E43: =+SUMIF('WRD Solo BS'!$C$7:$C$154,B43,'WRD Solo BS'!$B$7:$B$154) -> 1456834.9 | G43: =+SUMIF('WRD Solo BS'!$C$7:$C$154,B43,'WRD Solo BS'!$B$7:$B$154)/1000 -> 1456.8349
C45: Shareholders equity
B47: 19 | C47: additrional paid in capital | E47: =+SUMIF('WRD Solo BS'!$C$7:$C$154,B47,'WRD Solo BS'!$B$7:$B$154) -> 1.3144118e+08 | G47: =+ROUND((E47/1000),0) -> 131441 | H47: =+G47-'Change in Equity ILS'!H19 -> 51.25492
B48: 20 | C48: Recievable on share account | E48: =+SUMIF('WRD Solo BS'!$C$7:$C$154,B48,'WRD Solo BS'!$B$7:$B$154) -> 0 | G48: =+ROUND((E48/1000),0) -> 0
B49: 21 | C49: Accumulated deficit | E49: =+SUMIF('WRD Solo BS'!$C$7:$C$154,B49,'WRD Solo BS'!$B$7:$B$154) -> -62397988 | G49: =+ROUND((E49/1000),0)+ROUND(E47/1000,0)-G47 -> -62398
C51: Total shareholders equity | E51: =+SUM(E47:E49) -> 69043189 | G51: =+SUM(G47:G49) -> 69043
C53: Total liabilities and shareholders' equity | E53: =+E51+E43+E39 -> 73302393 | G53: =+G51+G43+G39 -> 73470.352
C55: check | E55: =+E53-E28 -> -13031562 | G55: =+G53-G28 -> 0.35185

Sheet WRD Solo P&L
A1: Wematch.live R&D LTD
A2: Wematch.live R&D LTD
A3: WM INCOME STATEMENT | H3: This report doesn't include intercompany transactions
A4: From Jan 2022 to Dec 2022 | H4: download them from report: Income statement-->Account 60002
A7: Financial Row | B7: Amount
A8: Gross Income
A9: - No Class - | B9: -291319.42
A10: TRS | B10: 19366160
A11: SBL | B11: 1316300.2
A12: Securities Financing | B12: -289116.71
A13: Interest rate | B13: 1566131
A14: Equity Derivative | B14: 986699.3
A15: Total Gross Income | B15: =SUM(B9:B14) -> 22654854 | C15: 1
A16: Revenue Shared With Regulated Broker Dealer
A17: 45000 - Revenues shared to third parties
A18: 45002 - Commission Shared with third party | B18: -2291594.3 | C18: 2.1
A19: 45001 - IS IN | B19: -217430.61 | C19: 2.1
A20: 45003 - Non Reclaimable VAT | B20: -566840.57 | C20: 2.1
A21: Total - 45000 - Revenues shared to third parties | B21: =SUM(B18:B20) -> -3075865.5 | C21: 2
A22: Total Revenue Shared With Regulated Broker Dealer | B22: =SUM(B21) -> -3075865.5
A23: Net Income | B23: =+B15+B22 -> 19578989
A24: Cost Of Sales
A25: 50000 - COGS expenses
A26: 50100 - Payroll and Related expenses [COGS]
A27: 50101 - COGS Gross Salaries | B27: -1418426.1
A28: 50108 - COGS Employee stock-based compensation | B28: -5096.32
A29: Total - 50100 - Payroll and Related expenses [COGS] | B29: =SUM(B27:B28) -> -1423522.4 | C29: 2.2
A30: 50400 - COGS Hosting
A31: 50402 - AWS | B31: -732235.83
A32: 50401 - COGS Hosting exp. | B32: -207326.05
A33: Total - 50400 - COGS Hosting | B33: =SUM(B31:B32) -> -939561.88 | C33: 2.2
A34: 50300 - COGS Tools/ Systems
A35: 50301 - COGS Tools | B35: -547331.41
A36: Total - 50300 - COGS Tools/ Systems | B36: =SUM(B35) -> -547331.41 | C36: 2.2
A37: 51110 - Recruiting Fees
A38: 51110 - Recruiting Fees | B38: -11935.02
A39: Total - 51110 - Recruiting Fees | B39: =SUM(B38) -> -11935.02 | C39: 2.2
A40: Total - 50000 - COGS expenses | B40: =SUM(B29,B33,B36,B39) -> -2922350.7
A41: Total - Cost Of Sales | B41: =SUM(B40) -> -2922350.7 | C41: 2
A42: Gross Profit | B42: =B23+B41 -> 16656638
A43: Gross Profit as % of Gross Income | B43: =B42/B15*100 -> 73.523484
A44: Operation Expense
A45: - No Department -
A46: 299997 - Conversion payable account | B46: -5406.73
A47: 61000 - Salaries & Wages
A48: 61700 - Team Events & Welfare
A49: 61705 - Team events | B49: -958.28
A50: Total - 61700 - Team Events & Welfare | B50: =SUM(B49) -> -958.28
A51: Total - 61000 - Salaries & Wages | B51: =SUM(B50) -> -958.28
A52: 61400 - Payroll Services
A53: 61401 - Payroll processing fees | B53: -435.86
A54: Total - 61400 - Payroll Services | B54: =SUM(B53) -> -435.86
A55: 62000 - Travel and Entertainment
A56: 62100 - Travel & Entertainment
A57: 62101 - Airfare | B57: -2833.27
A58: 62102 - Lodging | B58: -2819
A59: 62103 - Ground Transportation | B59: -775.26
A60: 62106 - Other Travel expenses | B60: -1994.9
A61: Total - 62100 - Travel & Entertainment | B61: =SUM(B57:B60) -> -8422.43
A62: Total - 62000 - Travel and Entertainment | B62: =SUM(B61) -> -8422.43
A63: 66000 - Professional Services
A64: 66100 - Consulting
A65: 66101 - Reccuring Consultants & Subcontractors | B65: -82273.34
A66: Total - 66100 - Consulting | B66: =SUM(B65) -> -82273.34
A67: Total - 66000 - Professional Services | B67: =SUM(B66) -> -82273.34
A68: 67000 - IT, Rent, & Office Expenses
A69: 67300 - Software & Equipment
A70: 67301 - IT Equipment (non-capitalizable) | B70: -16388.33
A71: 67302 - Cloud services | B71: 2557.57
A72: Total - 67300 - Software & Equipment | B72: =SUM(B70:B71) -> -13830.76
A73: 67400 - Other Office Expenses
A74: 67401 - Office Supplies | B74: 1382.65
A75: 67402 - Office Food | B75: -477.62
A76: Total - 67400 - Other Office Expenses | B76: =SUM(B74:B75) -> 905.03
A77: Total - 67000 - IT, Rent, & Office Expenses | B77: =SUM(B72,B76) -> -12925.73
A78: Total - No Department - | B78: =SUM(B46,B51,B54,B62,B67,B77) -> -110422.37 | C78: 4.1 | D78: (Most are R&D)
A79: R&D
A80: Product
A81: 61000 - Salaries & Wages
A82: 61001 - Gross Salaries | B82: 1463786.7
A83: 61003 - Vacation expenses | B83: 77512.06
A84: 61700 - Team Events & Welfare
A85: 61701 - Employee gifts | B85: 3676.2
A86: 61703 - Employee meals | B86: 28172.94
A87: 61704 - Onboarding new employee | B87: 323.49
A88: 61705 - Team events | B88: 2662.75
A89: Total - 61700 - Team Events & Welfare | B89: =SUM(B85:B88) -> 34835.38
A90: Total - 61000 - Salaries & Wages | B90: =SUM(B82:B83,B89) -> 1576134.1
A91: 61100 - Payroll Taxes
A92: 61105 - Gift value - Debit | B92: 1560
A93: 61106 - Gift value - Credit | B93: -1560
A94: 61107 - Imputation of benefits - Debit | B94: 7526.4
A95: 61108 - Imputation of benefits - Credit | B95: -7526.4
A96: 61109 - Education fund Imputation - Debit | B96: 1906.48
A97: 61110 - Education fund Imputation - Credit | B97: -1906.48
A98: 61111 - Meals value - Debit | B98: 24878.46
A99: 61112 - Meals value - Credit | B99: -24878.44
A100: 61113 - Social Security | B100: 73342.18
A101: Total - 61100 - Payroll Taxes | B101: =SUM(B92:B100) -> 73342.2
A102: 61200 - Benefits - Financial
...

Sheet WRD Solo BS
A1: Wematch.live R&D LTD
A2: Wematch.live R&D LTD
A3: Balance Sheet
A4: End of Dec 2022
A7: Financial Row | B7: Amount
A8: Current Assets
A9: Bank
A10: 10000 - Cash and Cash Equivalent (WRD-IL)
A11: 10001 - Bank Fibi 327492 NIS | B11: 347754.07
A12: 10002 - Bank Hapoalim 120737 NIS | B12: 648131.34
A13: 10003 - Bank Hapoalim 120737 USD | B13: 21568727
A14: 10004 - Bank Hapoalim 120737 GBP | B14: 41070.08
A15: 10005 - Bank Hapoalim 120737 EUR | B15: 59093.11
A16: Total - 10000 - Cash and Cash Equivalent (WRD-IL) | B16: =SUM(B11:B15) -> 22664776 | C16: 10
A17: 11000 - Short-term Restricted cash
A18: 11001 - Bank Hapoalim Deposit NIS | B18: 60130.82
A19: 11002 - Bank FIBI Deposit NIS | B19: 10054.45
A20: 11003 - Bank FIBI Deposit EUR | B20: 28435.63
A21: Total - 11000 - Short-term Restricted cash | B21: =SUM(B18:B20) -> 98620.9 | C21: 10
A22: 11100 - Short term Bank Deposit
A23: 11101 - Short term Bank Deposit [BANK HAPOALIM] | B23: 39137419 | C23: 11
A24: Total - 11100 - Short term Bank Deposit | B24: =SUM(B23) -> 39137419
A25: Total Bank | B25: =SUM(B16,B21,B24) -> 61900816
A26: Accounts Receivable
A27: 12000 - Accounts Receivable
A28: 12001 - Accounts Receivable | B28: 5733182.8
A29: 12002 - Accounts Receivable - Customers offset | B29: -166571.4
A30: Total - 12000 - Accounts Receivable | B30: =SUM(B28:B29) -> 5566611.4 | C30: 12
A31: Total Accounts Receivable | B31: =SUM(B30) -> 5566611.4
A32: Other Current Asset
A33: 12004 - Unbilled Revenue | B33: 1152252.1 | C33: 12
A34: 12600 - Intercompany (O.C Assets)
A35: 12601 - WeMatch.Securitiesfinancing Ltd. [P] | B35: 9554851.5 | C35: 13.5.1
A36: 12602 - WeMatch.Live Tech Support Europe [P] | B36: 3041990.8 | C36: 13.5.2
A37: 12603 - WeMatch Securities Financing Ltd. [P] | B37: 3486 | C37: 13.5.3
A38: 12606 - Wematch.Support US INC [P] | B38: 2964415.6 | C38: 13.5.4
A39: Total - 12600 - Intercompany (O.C Assets) | B39: =SUM(B35:B38) -> 15564744 | C39: 13.5
A40: 13000 - Prepaid Exp.
A41: 13001 - Prepaid Expenses | B41: 454510.24
A42: 13003 - Deferred Customer acquisition cost | B42: 329537.48
A43: Total - 13000 - Prepaid Exp. | B43: =SUM(B41:B42) -> 784047.72 | C43: 13
A44: 13009 - Government Institutions
A45: 13100 - VAT Assets
A46: 13101 - VAT on FA Purchases IL | B46: 80.9 | C46: 13.2
A47: 13102 - VAT on Purchases IL | B47: 295.78 | C47: 13.2
A48: 13107 - VAT D/C | B48: 102491.64 | C48: 13.2
A49: Total - 13100 - VAT Assets | B49: =SUM(B46:B48) -> 102868.32 | C49: 13
A50: 13300 - TAX Assets
A51: 13301 - Advances for Odfot | B51: 53504.51
A52: 13302 - Reversal for Exceed expenses | B52: -53504.51
A53: Total - 13300 - TAX Assets | B53: =SUM(B51:B52) -> 0
A54: Total - 13009 - Government Institutions | B54: =SUM(B49,B53) -> 102868.32
A55: 16000 - Other Current Asset
A56: 16001 - Rent deposit | B56: 118236.95
A57: 16002 - Other Deposits | B57: 38480.99
A58: Total - 16000 - Other Current Asset | B58: =SUM(B56:B57) -> 156717.94 | C58: 13
A59: 16100 - other current asset | B59: -1 | C59: 13
A60: 17000 - Other long term assets
A61: 17001 - Interco Loans | B61: 918263.98 | C61: 13.5 | D61: WIR
A62: Total - 17000 - Other long term assets | B62: =SUM(B61) -> 918263.98
A63: Advances Paid | B63: 4275.39 | C63: 13
A64: Undeposited Funds | B64: -2.45 | C64: 13
A65: Total Other Current Asset | B65: =SUM(B33,B39,B43,B54,B58:B59,B62:B64) -> 18683166
A66: Total Current Assets | B66: =B25+B31+0+B65 -> 86150593
A67: Fixed Assets
A68: 15000 - FA Cost
A69: 15001 - Cost - Computers & Software | B69: 369615.79 | C69: 15.1
A70: 15002 - Cost - Leasehold Improvements | B70: 9200 | C70: 15.3
A71: 15003 - Cost - Furniture and Fixtures | B71: 6807 | C71: 15.2
A72: 15004 - Cost - Electronic equipment | B72: 27440 | C72: 15.1
A73: Total - 15000 - FA Cost | B73: =SUM(B69:B72) -> 413062.79 | C73: 15
A74: 15100 - Accumulated Depr.
A75: 15101 - AD - Computers & Software | B75: -198146.83 | C75: 15.4
A76: 15102 - AD - Leasehold Improvements | B76: -9200 | C76: 15.4
A77: 15103 - AD - Furniture and Fixtures | B77: -2538.72 | C77: 15.4
A78: 15104 - AD - Electronic equipments | B78: -19814.76 | C78: 15.4
A79: Total - 15100 - Accumulated Depr. | B79: =SUM(B75:B78) -> -229700.31 | C79: 15
A80: Total Fixed Assets | B80: =SUM(B73,B79) -> 183362.48
A81: Current Liabilities
A82: Accounts Payable
A83: 20000 - AP
A84: 20001 - Accounts Payable | B84: 417013.46 | C84: 16
A85: Total - 20000 - AP | B85: =SUM(B84) -> 417013.46
A86: 20050 - Intercompany Liabilities
A87: 20052 - WeMatch.Live Tech Support Europe | B87: 99731.57 | C87: 16
A88: Total - 20050 - Intercompany Liabilities | B88: =SUM(B87) -> 99731.57
A89: Total Accounts Payable | B89: =SUM(B85,B88) -> 516745.03
A90: Credit Card
A91: 20100 - Credit Cards
A92: 20101 - BH CC 7544 | B92: -5731.49
A93: 20102 - BH CC 0070 | B93: -15337.24
A94: 20103 - BH CC 4700 | B94: -10444.77
A95: 20105 - FIBI CC 6491 | B95: -117
A96: 20106 - FIBI CC 7644 | B96: 2909.93
A97: 20110 - BH CC 7544 ILS | B97: 12777.51
A98: 20111 - BH CC 0070 ILS | B98: 12190.66
A99: 20113 - BH CC 7544 EURO | B99: -7.15
A100: 20114 - BH CC 0070 EURO | B100: -2576.25
A101: Total - 20100 - Credit Cards | B101: =SUM(B92:B100) -> -6335.8 | C101: 16
A102: Total Credit Card | B102: =SUM(B101) -> -6335.8
...

Sheet NOTES-Solo
D3: Balance Sheet Notes
B5: 3 | D5: Trade recievables | E5: =+SUMIF('Full BS-USD'!$M$9:$M$226,F5,'Full BS-USD'!$L$9:$L$226)/1000 -> 424.62305 | F5: 12.1
D6: Unbilled revenue | E6: =SUMIF('Full BS-USD'!$M$9:$M$226,F6,'Full BS-USD'!$L$9:$L$226)/1000-E5-1 -> 233.25907 | F6: 12
E7: =SUM(E5:E6) -> 657.88212
E8: =+E7-'BS USD'!S13 -> -1.11788
B10: 4 | D10: Prepaid expenses | E10: =+SUMIF('Full BS-USD'!$M$9:$M$226,F10,'Full BS-USD'!$L$9:$L$226)/1000 -> 273.23526 | F10: 13.1
D11: Government institutions | E11: =+SUMIF('Full BS-USD'!$M$9:$M$226,F11,'Full BS-USD'!$L$9:$L$226)/1000 -> 162.24782 | F11: 13.2
D12: Other current assts | E12: =SUMIF('Full BS-USD'!$M$9:$M$226,F12,'Full BS-USD'!$L$9:$L$226)/1000-E11-E10-'Full BS-USD'!L157/1000 -> 201.69305 | F12: 13
E13: =SUM(E10:E12) -> 637.17613
E14: =+E13-'BS USD'!S14 -> -21.82387
B15: 5 | D15: Cost:
D16: Computers & Software | E16: =+SUMIF('WRD Solo BS'!C7:C154,F16,'WRD Solo BS'!B7:B154)/1000 -> 397.05579 | F16: 15.1
D17: Office furniture | E17: =+SUMIF('WRD Solo BS'!C8:C155,F17,'WRD Solo BS'!B8:B155)/1000 -> 6.807 | F17: 15.2
D18: Leasehold improvements | E18: =+SUMIF('WRD Solo BS'!C9:C156,F18,'WRD Solo BS'!B9:B156)/1000 -> 9.2 | F18: 15.3
E19: =SUM(E16:E18) -> 413.06279
D21: Accumulated depritiation | E21: =+SUMIF('WRD Solo BS'!C12:C159,F21,'WRD Solo BS'!B12:B159)/1000 -> -229.70031 | F21: 15.4
D23: Preperty and equipment, net | E23: =+E19+E21 -> 183.36248
E24: =+E23-'BS ILS'!G22 -> 0.36248
B27: 6 | D27: Accrued employee compensation and benefits | E27: =+SUMIF('WRD Solo BS'!C18:C165,F27,'WRD Solo BS'!B18:B165)/1000 -> 1656.894 | F27: 17.1
C28: 23501 - Other Current Liability | D28: Accrued expenses | E28: =+SUMIF('WRD Solo BS'!C19:C166,F28,'WRD Solo BS'!B19:B166)/1000+VLOOKUP(C28,'WRD Solo BS'!$A$73:$B$136,2,0)/1000 -> 227.3206 | F28: 17.2
D29: Income and indirect tax payable | E29: =+SUMIF('WRD Solo BS'!C20:C167,F29,'WRD Solo BS'!B20:B167)/1000 -> 394.70063 | F29: 17.4
E30: =SUM(E27:E29) -> 2278.9152
E31: =+E30-'BS ILS'!G37 -> -0.08478
B33: 8 | D33: Share capital: | O33: Shareholders' equity
O35: 2022
E36: Authorized | F36: issued and outstanding | J36: Authorized | K36: issued and outstanding | O36: number of options | P36: weightes average excersise price
E37: December 31,2022 | J37: December 31,2021 | N37: Balance as of December 31,2021
D38: ordinary shares | E38: 3074000 | F38: 1223458 | J38: 3074000 | K38: 1220858 | N38: Granted
D39: ordinary A Shares | E39: 205000 | F39: 180881 | J39: 205000 | K39: 180881 | N39: Balance as of December 31,2022
D40: Preferred A shares (*) | E40: 651000 | F40: 641271 | J40: 651000 | K40: 514024 | N40: Excercisable as of December 31,2021
D41: preferred B shares (*) | E41: 1070000 | F41: 967678 | G41: =+K41 -> 967678 | H41: =+F41-G41 -> 0 | J41: 1070000 | K41: 967678 | L41: different from 2021 signed report
E42: =SUM(E38:E41) -> 5000000 | F42: =SUM(F38:F41) -> 3013288 | J42: =SUM(J38:J41) -> 5000000 | K42: =SUM(K38:K41) -> 2883441
K45: The information is taken from Carta- "Summery Cap Table" report
B47: 9 | D47: 12600 - Intercompany (O.C Assets)
D48: 12601 - WeMatch.Securitiesfinancing Ltd. [P] | E48: =+SUMIF('WRD Solo BS'!C7:C153,F48,'WRD Solo BS'!B7:B153)/1000 -> 9554.8515 | F48: 13.5.1
D49: 12602 - WeMatch.Live Tech Support Europe [P] | E49: =+SUMIF('WRD Solo BS'!C8:C154,F49,'WRD Solo BS'!B8:B154)/1000 -> 3041.9908 | F49: 13.5.2
D50: 12603 - WeMatch Securities Financing Ltd. [P] | E50: =+SUMIF('WRD Solo BS'!C9:C155,F50,'WRD Solo BS'!B9:B155)/1000 -> 3.486 | F50: 13.5.3
D51: 12606 - Wematch.Support US INC [P] | E51: =+SUMIF('WRD Solo BS'!C10:C156,F51,'WRD Solo BS'!B10:B156)/1000 -> 2964.4156 | F51: 13.5.4
C52: WIR | D52: 17001 - Interco Loans | E52: =918263.98/1000 -> 918.26398
E53: =SUM(E47:E52) -> 16483.008 | I53: =+E53-E61 -> 3438.4013
D55: 20060 - Intercompany (O.C Liability)
D56: 20061 - WeMatch.Securitiesfinancing Ltd. [PL] | E56: =+SUMIF('WRD Solo BS'!C47:C194,F56,'WRD Solo BS'!B47:B194)/1000 -> 8030.9138 | F56: 16.1.1
D57: 20062 - WeMatch.Live Tech Support Europe [PL] | E57: =+SUMIF('WRD Solo BS'!C48:C195,F57,'WRD Solo BS'!B48:B195)/1000 -> 2808.9979 | F57: 16.1.2
D58: 20063 - WeMatch Securities Financing Ltd. [PL] | E58: =+SUMIF('WRD Solo BS'!C49:C196,F58,'WRD Solo BS'!B49:B196)/1000 -> 169.33087 | F58: 16.1.3
D59: 20065 - WeMatch EQD Ltd. [PL] | E59: =+SUMIF('WRD Solo BS'!C50:C197,F59,'WRD Solo BS'!B50:B197)/1000 -> 15.67205 | F59: 16.1.4
D60: 20066 - Wematch.Support US INC [PL] | E60: =+SUMIF('WRD Solo BS'!C51:C198,F60,'WRD Solo BS'!B51:B198)/1000 -> 2019.692 | F60: 16.1.5
E61: =SUM(E56:E60) -> 13044.607
D63: NET-For Financial Statements
D64: 12600 - Intercompany (O.C Assets)
D65: 12601 - WeMatch.Securitiesfinancing Ltd. [P] | E65: =+E48-E56 -> 1523.9377
D66: 12602 - WeMatch.Live Tech Support Europe [P] | E66: =+E49-E57 -> 232.99288
D67: WIR | E67: =+E52 -> 918.26398
D68: 12606 - Wematch.Support US INC [P] | E68: =+E51-E60 -> 944.72363
E69: 3620 | I69: =+E69+E76 -> 3438.4831
D70: 20060 - Intercompany (O.C Liability)
D71: 20061 - WeMatch.Securitiesfinancing Ltd. [PL]
D72: 20062 - WeMatch.Live Tech Support Europe [PL]
D73: 20063 - WeMatch Securities Financing Ltd. [PL] | E73: =-E58+E50 -> -165.84487
D74: 20065 - WeMatch EQD Ltd. [PL] | E74: =-E59 -> -15.67205
D75: 20066 - Wematch.Support US INC [PL]
E76: =SUM(E71:E75) -> -181.51692
E77: =+E53-E61-E69-E76 -> -0.08183
D79: P&L Notes
B81: 9
N85: 592386
N86: 41895
N87: 459304
N88: 124518
N89: 751867
B90: 10 | N90: =SUM(N85:N89) -> 1969970
B98: 11 | D98: הוצאות (הכנסות) הפרשי שער | E98: =-SUMIF('WRD Solo P&L'!C7:C673,F98,'WRD Solo P&L'!B7:B673)/1000 -> 9766.2999 | F98: 6.1 | G98: expense
D99: הוצאות עמלות בנקים | E99: =-SUMIF('WRD Solo P&L'!C8:C674,F99,'WRD Solo P&L'!B8:B674)/1000 -> -47.92491 | F99: 6.2 | G99: expense
D100: הוצאות בגין שערוך התחייבות לזמן ארוך | E100: =+SUMIF('WRD Solo P&L'!C10:C676,F100,'WRD Solo P&L'!B10:B676)/1000 -> 1104.5992 | F100: 6.4 | G100: income
E101: =SUM(E98:E100) -> 10822.974
E102: =+E101-'P&L ILS'!G25 -> -0.02589
E108: 9766
E109: -48
E110: 1105
E111: =SUM(E108:E110) -> 10823

Sheet Full BS-USD (2)
A1: Wematch.live R&D LTD
A2: Wematch.live R&D LTD (Consolidated)
A3: Balance Sheet
A4: End of FY 2022
A7: Financial Row | B7: Elimination | C7: WEMATCH.SUPPORT US INC. | D7: Wematch EQD LTD | E7: Wematch Interest rate LTD | F7: Wematch Securities. Financing LTD [IL] | G7: Wematch.Securities Financing LTD | H7: Wematch.live R&D LTD | I7: Wematch.live Tech Support Europe | J7: Total | K7: INDEX
B8: Amount | C8: Amount | D8: Amount | E8: Amount | F8: Amount | G8: Amount | H8: Amount | I8: Amount | J8: Amount
A9: Current Assets
A10: Bank
A11: 10000 - Cash and Cash Equivalent (WRD-IL)
A12: 10001 - Bank Fibi 327492 NIS | B12: 0 | C12: 0 | D12: 0 | E12: 0 | F12: 0 | G12: 0 | H12: 98925.39 | I12: 0 | J12: =+IFERROR(VLOOKUP(A12,[1]BalanceSheet!A$8:B$154,2,0),0) -> 26151.22
A13: 10002 - Bank Hapoalim 120737 NIS | B13: 0 | C13: 0 | D13: 0 | E13: 0 | F13: 0 | G13: 0 | H13: 184319.33 | I13: 0 | J13: =+IFERROR(VLOOKUP(A13,[1]BalanceSheet!A$8:B$154,2,0),0) -> 344.4
A14: 10003 - Bank Hapoalim 120737 USD | B14: 0 | C14: 0 | D14: 0 | E14: 0 | F14: 0 | G14: 0 | H14: 6136719.3 | I14: 0 | J14: =+IFERROR(VLOOKUP(A14,[1]BalanceSheet!A$8:B$154,2,0),0) -> 26906064
A15: 10004 - Bank Hapoalim 120737 GBP | B15: 0 | C15: 0 | D15: 0 | E15: 0 | F15: 0 | G15: 0 | H15: 11685.56 | I15: 0 | J15: =+IFERROR(VLOOKUP(A15,[1]BalanceSheet!A$8:B$154,2,0),0) -> 5309.75
A16: 10005 - Bank Hapoalim 120737 EUR | B16: 0 | C16: 0 | D16: 0 | E16: 0 | F16: 0 | G16: 0 | H16: 16813.13 | I16: 0 | J16: =+IFERROR(VLOOKUP(A16,[1]BalanceSheet!A$8:B$154,2,0),0) -> 367423.66
A17: Total - 10000 - Cash and Cash Equivalent (WRD-IL) | B17: =SUM(B12:B16) -> 0 | C17: =SUM(C12:C16) -> 0 | D17: =SUM(D12:D16) -> 0 | E17: =SUM(E12:E16) -> 0 | F17: =SUM(F12:F16) -> 0 | G17: =SUM(G12:G16) -> 0 | H17: =SUM(H12:H16) -> 6448462.7 | I17: =SUM(I12:I16) -> 0 | J17: =+IFERROR(VLOOKUP(A17,[1]BalanceSheet!A$8:B$154,2,0),0) -> 27305293 | K17: 10
A18: 101 - Dummy USD [UK] | B18: 0 | C18: 0 | D18: 0 | E18: 0 | F18: 0 | G18: -0.01 | H18: 0 | I18: 0 | J18: =+IFERROR(VLOOKUP(A18,[1]BalanceSheet!A$8:B$154,2,0),0) -> 0
A19: 10100 - Cash and Cash Equivalent (WIR-IL) | J19: =+IFERROR(VLOOKUP(A19,[1]BalanceSheet!A$8:B$154,2,0),0) -> 0
A20: 10101 - Bank Hapoalim 120720 NIS | B20: 0 | C20: 0 | D20: 0 | E20: 21.81 | F20: 0 | G20: 0 | H20: 0 | I20: 0 | J20: =+IFERROR(VLOOKUP(A20,[1]BalanceSheet!A$8:B$154,2,0),0) -> 156.37
A21: Total - 10100 - Cash and Cash Equivalent (WIR-IL) | B21: =SUM(B20) -> 0 | C21: =SUM(C20) -> 0 | D21: =SUM(D20) -> 0 | E21: =SUM(E20) -> 21.81 | F21: =SUM(F20) -> 0 | G21: =SUM(G20) -> 0 | H21: =SUM(H20) -> 0 | I21: =SUM(I20) -> 0 | J21: =+IFERROR(VLOOKUP(A21,[1]BalanceSheet!A$8:B$154,2,0),0) -> 156.37 | K21: 10
A22: 10200 - Cash and Cash Equivalent (WSF-IL) | J22: =+IFERROR(VLOOKUP(A22,[1]BalanceSheet!A$8:B$154,2,0),0) -> 0
A23: 10201 - Bank Hapoalim 120729 NIS | B23: 0 | C23: 0 | D23: 0 | E23: 0 | F23: 124.45 | G23: 0 | H23: 0 | I23: 0 | J23: =+IFERROR(VLOOKUP(A23,[1]BalanceSheet!A$8:B$154,2,0),0) -> 422.32
A24: 10202 - Bank Hapoalim 120729 USD | B24: 0 | C24: 0 | D24: 0 | E24: 0 | F24: 24.67 | G24: 0 | H24: 0 | I24: 0 | J24: =+IFERROR(VLOOKUP(A24,[1]BalanceSheet!A$8:B$154,2,0),0) -> 24.67
A25: 10203 - Bank Hapoalim 120729 EUR | B25: 0 | C25: 0 | D25: 0 | E25: 0 | F25: 327.43 | G25: 0 | H25: 0 | I25: 0 | J25: =+IFERROR(VLOOKUP(A25,[1]BalanceSheet!A$8:B$154,2,0),0) -> 346.29
A26: Total - 10200 - Cash and Cash Equivalent (WSF-IL) | B26: =SUM(B23:B25) -> 0 | C26: =SUM(C23:C25) -> 0 | D26: =SUM(D23:D25) -> 0 | E26: =SUM(E23:E25) -> 0 | F26: =SUM(F23:F25) -> 476.55 | G26: =SUM(G23:G25) -> 0 | H26: =SUM(H23:H25) -> 0 | I26: =SUM(I23:I25) -> 0 | J26: =+IFERROR(VLOOKUP(A26,[1]BalanceSheet!A$8:B$154,2,0),0) -> 793.28 | K26: 10
A27: 10300 - Cash and Cash Equivalent (WEQD-IL) | J27: =+IFERROR(VLOOKUP(A27,[1]BalanceSheet!A$8:B$154,2,0),0) -> 0
A28: 10301 - Bank Hapoalim 120702 NIS | B28: 0 | C28: 0 | D28: -3.42 | E28: 0 | F28: 0 | G28: 0 | H28: 0 | I28: 0 | J28: =+IFERROR(VLOOKUP(A28,[1]BalanceSheet!A$8:B$154,2,0),0) -> 3.88
A29: 10302 - Bank Hapoalim 120702 USD | B29: 0 | C29: 0 | D29: 6438.02 | E29: 0 | F29: 0 | G29: 0 | H29: 0 | I29: 0 | J29: =+IFERROR(VLOOKUP(A29,[1]BalanceSheet!A$8:B$154,2,0),0) -> 6563.41
A30: Total - 10300 - Cash and Cash Equivalent (WEQD-IL) | B30: =SUM(B28:B29) -> 0 | C30: =SUM(C28:C29) -> 0 | D30: =SUM(D28:D29) -> 6434.6 | E30: =SUM(E28:E29) -> 0 | F30: =SUM(F28:F29) -> 0 | G30: =SUM(G28:G29) -> 0 | H30: =SUM(H28:H29) -> 0 | I30: =SUM(I28:I29) -> 0 | J30: =+IFERROR(VLOOKUP(A30,[1]BalanceSheet!A$8:B$154,2,0),0) -> 6567.29 | K30: 10
A31: 10400 - Cash and Cash Equivalent (WSF-UK) | J31: =+IFERROR(VLOOKUP(A31,[1]BalanceSheet!A$8:B$154,2,0),0) -> 0
A32: 10401 - Bank Netwest 27557405 GBP | B32: 0 | C32: 0 | D32: 0 | E32: 0 | F32: 0 | G32: 671354.25 | H32: 0 | I32: 0 | J32: =+IFERROR(VLOOKUP(A32,[1]BalanceSheet!A$8:B$154,2,0),0) -> 25648.28
A33: Total - 10400 - Cash and Cash Equivalent (WSF-UK) | B33: =SUM(B32) -> 0 | C33: =SUM(C32) -> 0 | D33: =SUM(D32) -> 0 | E33: =SUM(E32) -> 0 | F33: =SUM(F32) -> 0 | G33: =SUM(G32) -> 671354.25 | H33: =SUM(H32) -> 0 | I33: =SUM(I32) -> 0 | J33: =+IFERROR(VLOOKUP(A33,[1]BalanceSheet!A$8:B$154,2,0),0) -> 25648.28 | K33: 10
A34: 10500 - Cash and Cash Equivalent (WTSE-FR) | J34: =+IFERROR(VLOOKUP(A34,[1]BalanceSheet!A$8:B$154,2,0),0) -> 0
A35: 10501 - Bank SG 20020671 EUR | B35: 0 | C35: 0 | D35: 0 | E35: 0 | F35: 0 | G35: 0 | H35: 0 | I35: 294780.88 | J35: =+IFERROR(VLOOKUP(A35,[1]BalanceSheet!A$8:B$154,2,0),0) -> 49912.93
A36: Total - 10500 - Cash and Cash Equivalent (WTSE-FR) | B36: =SUM(B35) -> 0 | C36: =SUM(C35) -> 0 | D36: =SUM(D35) -> 0 | E36: =SUM(E35) -> 0 | F36: =SUM(F35) -> 0 | G36: =SUM(G35) -> 0 | H36: =SUM(H35) -> 0 | I36: =SUM(I35) -> 294780.88 | J36: =+IFERROR(VLOOKUP(A36,[1]BalanceSheet!A$8:B$154,2,0),0) -> 49912.93 | K36: 10
A37: 10600 - Cash and Cash Equivalent (WUS-US) | J37: =+IFERROR(VLOOKUP(A37,[1]BalanceSheet!A$8:B$154,2,0),0) -> 0
A38: 10601 - Bank Hapoalim 542 Saving USD | B38: 0 | C38: 180344.74 | D38: 0 | E38: 0 | F38: 0 | G38: 0 | H38: 0 | I38: 0 | J38: =+IFERROR(VLOOKUP(A38,[1]BalanceSheet!A$8:B$154,2,0),0) -> 0
A39: 10602 - Bank Hapoalim 0700 Checking USD | B39: 0 | C39: 42295.73 | D39: 0 | E39: 0 | F39: 0 | G39: 0 | H39: 0 | I39: 0 | J39: =+IFERROR(VLOOKUP(A39,[1]BalanceSheet!A$8:B$154,2,0),0) -> 0
A40: Total - 10600 - Cash and Cash Equivalent (WUS-US) | B40: =SUM(B38:B39) -> 0 | C40: =SUM(C38:C39) -> 222640.47 | D40: =SUM(D38:D39) -> 0 | E40: =SUM(E38:E39) -> 0 | F40: =SUM(F38:F39) -> 0 | G40: =SUM(G38:G39) -> 0 | H40: =SUM(H38:H39) -> 0 | I40: =SUM(I38:I39) -> 0 | J40: =+IFERROR(VLOOKUP(A40,[1]BalanceSheet!A$8:B$154,2,0),0) -> 0 | K40: 10
A41: 11000 - Short-term Restricted cash | J41: =+IFERROR(VLOOKUP(A41,[1]BalanceSheet!A$8:B$154,2,0),0) -> 0
A42: 11001 - Bank Hapoalim Deposit NIS | B42: 0 | C42: 0 | D42: 0 | E42: 0 | F42: 0 | G42: 0 | H42: 17071.92 | I42: 0 | J42: =+IFERROR(VLOOKUP(A42,[1]BalanceSheet!A$8:B$154,2,0),0) -> 19293.46
A43: 11002 - Bank FIBI Deposit NIS | B43: 0 | C43: 0 | D43: 0 | E43: 0 | F43: 0 | G43: 0 | H43: 2845.19 | I43: 0 | J43: =+IFERROR(VLOOKUP(A43,[1]BalanceSheet!A$8:B$154,2,0),0) -> 3215.43
A44: 11003 - Bank FIBI Deposit EUR | B44: 0 | C44: 0 | D44: 0 | E44: 0 | F44: 0 | G44: 0 | H44: 8090.49 | I44: 0 | J44: =+IFERROR(VLOOKUP(A44,[1]BalanceSheet!A$8:B$154,2,0),0) -> 8556.41
A45: Total - 11000 - Short-term Restricted cash | B45: =SUM(B42:B44) -> 0 | C45: =SUM(C42:C44) -> 0 | D45: =SUM(D42:D44) -> 0 | E45: =SUM(E42:E44) -> 0 | F45: =SUM(F42:F44) -> 0 | G45: =SUM(G42:G44) -> 0 | H45: =SUM(H42:H44) -> 28007.6 | I45: =SUM(I42:I44) -> 0 | J45: =+IFERROR(VLOOKUP(A45,[1]BalanceSheet!A$8:B$154,2,0),0) -> 31065.3 | K45: 11
A46: 11100 - Short term Bank Deposit | J46: =+IFERROR(VLOOKUP(A46,[1]BalanceSheet!A$8:B$154,2,0),0) -> 0
A47: 11101 - Short term Bank Deposit [BANK HAPOALIM] | B47: 0 | C47: 0 | D47: 0 | E47: 0 | F47: 0 | G47: 0 | H47: 11135351 | I47: 0 | J47: =+IFERROR(VLOOKUP(A47,[1]BalanceSheet!A$8:B$154,2,0),0) -> 0 | K47: 11
A48: Total - 11100 - Short term Bank Deposit | B48: =SUM(B47) -> 0 | C48: =SUM(C47) -> 0 | D48: =SUM(D47) -> 0 | E48: =SUM(E47) -> 0 | F48: =SUM(F47) -> 0 | G48: =SUM(G47) -> 0 | H48: =SUM(H47) -> 11135351 | I48: =SUM(I47) -> 0 | J48: =+IFERROR(VLOOKUP(A48,[1]BalanceSheet!A$8:B$154,2,0),0) -> 0
A49: Total Bank | B49: =SUM(B17:B18,B21,B26,B30,B33,B36,B40,B45,B48) -> 0 | C49: =SUM(C17:C18,C21,C26,C30,C33,C36,C40,C45,C48) -> 222640.47 | D49: =SUM(D17:D18,D21,D26,D30,D33,D36,D40,D45,D48) -> 6434.6 | E49: =SUM(E17:E18,E21,E26,E30,E33,E36,E40,E45,E48) -> 21.81 | F49: =SUM(F17:F18,F21,F26,F30,F33,F36,F40,F45,F48) -> 476.55 | G49: =SUM(G17:G18,G21,G26,G30,G33,G36,G40,G45,G48) -> 671354.24 | H49: =SUM(H17:H18,H21,H26,H30,H33,H36,H40,H45,H48) -> 17611821 | I49: =SUM(I17:I18,I21,I26,I30,I33,I36,I40,I45,I48) -> 294780.88 | J49: =+IFERROR(VLOOKUP(A49,[1]BalanceSheet!A$8:B$154,2,0),0) -> 27419436
A50: Accounts Receivable | J50: =+IFERROR(VLOOKUP(A50,[1]BalanceSheet!A$8:B$154,2,0),0) -> 0
A51: 12000 - Accounts Receivable | J51: =+IFERROR(VLOOKUP(A51,[1]BalanceSheet!A$8:B$154,2,0),0) -> 0
A52: 12001 - Accounts Receivable | B52: 0 | C52: 0 | D52: 0 | E52: 0 | F52: 0 | G52: 0 | H52: 1631201.2 | I52: 0 | J52: =+IFERROR(VLOOKUP(A52,[1]BalanceSheet!A$8:B$154,2,0),0) -> 867787
A53: 12002 - Accounts Receivable - Customers offset | B53: 0 | C53: 0 | D53: 0 | E53: 0 | F53: 0 | G53: 0 | H53: -20670 | I53: 0 | J53: =+IFERROR(VLOOKUP(A53,[1]BalanceSheet!A$8:B$154,2,0),0) -> -43969.38
A54: Total - 12000 - Accounts Receivable | B54: =SUM(B52:B53) -> 0 | C54: =SUM(C52:C53) -> 0 | D54: =SUM(D52:D53) -> 0 | E54: =SUM(E52:E53) -> 0 | F54: =SUM(F52:F53) -> 0 | G54: =SUM(G52:G53) -> 0 | H54: =SUM(H52:H53) -> 1610531.2 | I54: =SUM(I52:I53) -> 0 | J54: =+IFERROR(VLOOKUP(A54,[1]BalanceSheet!A$8:B$154,2,0),0) -> 823817.62 | K54: 12.1
A55: 12500 - Intercompany (Receviable) | J55: =+IFERROR(VLOOKUP(A55,[1]BalanceSheet!A$8:B$154,2,0),0) -> 0
A56: 12502 - WeMatch.Live Tech Support Europe | B56: -28375.56 | C56: 0 | D56: 0 | E56: 0 | F56: 0 | G56: 0 | H56: 0 | I56: 28375.56 | J56: =+IFERROR(VLOOKUP(A56,[1]BalanceSheet!A$8:B$154,2,0),0) -> 0
A57: Total - 12500 - Intercompany (Receviable) | B57: =SUM(B56) -> -28375.56 | C57: =SUM(C56) -> 0 | D57: =SUM(D56) -> 0 | E57: =SUM(E56) -> 0 | F57: =SUM(F56) -> 0 | G57: =SUM(G56) -> 0 | H57: =SUM(H56) -> 0 | I57: =SUM(I56) -> 28375.56 | J57: =+IFERROR(VLOOKUP(A57,[1]BalanceSheet!A$8:B$154,2,0),0) -> 0 | K57: 12.1
A58: Total Accounts Receivable | B58: =SUM(B54,B57) -> -28375.56 | C58: =SUM(C54,C57) -> 0 | D58: =SUM(D54,D57) -> 0 | E58: =SUM(E54,E57) -> 0 | F58: =SUM(F54,F57) -> 0 | G58: =SUM(G54,G57) -> 0 | H58: =SUM(H54,H57) -> 1610531.2 | I58: =SUM(I54,I57) -> 28375.56 | J58: =+IFERROR(VLOOKUP(A58,[1]BalanceSheet!A$8:B$154,2,0),0) -> 823817.62 | K58: 12
A59: Unbilled Receivable | J59: =+IFERROR(VLOOKUP(A59,[1]BalanceSheet!A$8:B$154,2,0),0) -> 0
A60: Unbilled Receivable | B60: 0 | C60: 0 | D60: 0 | E60: 0 | F60: 0 | G60: 0 | H60: 126335.77 | I60: 0 | J60: =+IFERROR(VLOOKUP(A60,[1]BalanceSheet!A$8:B$154,2,0),0) -> 0
A61: Total Unbilled Receivable | B61: =SUM(B60) -> 0 | C61: =SUM(C60) -> 0 | D61: =SUM(D60) -> 0 | E61: =SUM(E60) -> 0 | F61: =SUM(F60) -> 0 | G61: =SUM(G60) -> 0 | H61: =SUM(H60) -> 126335.77 | I61: =SUM(I60) -> 0 | J61: =+IFERROR(VLOOKUP(A61,[1]BalanceSheet!A$8:B$154,2,0),0) -> 0 | K61: 12
A62: Other Current Asset | J62: =+IFERROR(VLOOKUP(A62,[1]BalanceSheet!A$8:B$154,2,0),0) -> 0
A63: 12004 - Unbilled Revenue | B63: 0 | C63: 0 | D63: 0 | E63: 0 | F63: 0 | G63: 0 | H63: 327837.96 | I63: 0 | J63: =+IFERROR(VLOOKUP(A63,[1]BalanceSheet!A$8:B$154,2,0),0) -> 192570.33 | K63: 12
A64: 12600 - Intercompany (O.C Assets) | J64: =+IFERROR(VLOOKUP(A64,[1]BalanceSheet!A$8:B$154,2,0),0) -> 0
A65: 12601 - WeMatch.Securitiesfinancing Ltd. [P] | B65: -4619805.9 | C65: 0 | D65: 0 | E65: 0 | F65: 0 | G65: 2284953.2 | H65: 2334852.7 | I65: 0 | J65: =+IFERROR(VLOOKUP(A65,[1]BalanceSheet!A$8:B$154,2,0),0) -> 0
A66: 12602 - WeMatch.Live Tech Support Europe [P] | B66: -1664719.2 | C66: 0 | D66: 0 | E66: 0 | F66: 0 | G66: 0 | H66: 865505.1 | I66: 799214.12 | J66: =+IFERROR(VLOOKUP(A66,[1]BalanceSheet!A$8:B$154,2,0),0) -> 0
A67: 12603 - WeMatch Securities Financing Ltd. [P] | B67: -49169.73 | C67: 0 | D67: 0 | E67: 0 | F67: 48177.9 | G67: 0 | H67: 991.83 | I67: 0 | J67: =+IFERROR(VLOOKUP(A67,[1]BalanceSheet!A$8:B$154,2,0),0) -> 0
A68: 12605 - WeMatch EQD Ltd. [P] | B68: -4459 | C68: 0 | D68: 4459 | E68: 0 | F68: 0 | G68: 0 | H68: 0 | I68: 0 | J68: =+IFERROR(VLOOKUP(A68,[1]BalanceSheet!A$8:B$154,2,0),0) -> 0
A69: 12606 - Wematch.Support US INC [P] | B69: -1396757.1 | C69: 537445.42 | D69: 0 | E69: 0 | F69: 0 | G69: 15878.25 | H69: 843433.48 | I69: 0 | J69: =+IFERROR(VLOOKUP(A69,[1]BalanceSheet!A$8:B$154,2,0),0) -> 0
A70: Total - 12600 - Intercompany (O.C Assets) | B70: -7734911 | C70: 537445.42 | D70: 4459 | E70: 0 | F70: 48177.9 | G70: 2300831.5 | H70: 4044783.1 | I70: 799214.12 | J70: =+IFERROR(VLOOKUP(A70,[1]BalanceSheet!A$8:B$154,2,0),0) -> 0 | K70: 13
A71: 13000 - Prepaid Exp. | J71: =+IFERROR(VLOOKUP(A71,[1]BalanceSheet!A$8:B$154,2,0),0) -> 0
A72: 13001 - Prepaid Expenses | B72: 0 | C72: 143307.18 | D72: 0 | E72: 0 | F72: 0 | G72: 15354.25 | H72: 129071.74 | I72: 4547.06 | J72: =+IFERROR(VLOOKUP(A72,[1]BalanceSheet!A$8:B$154,2,0),0) -> 37005.61 | K72: 13.1
A73: 13002 - Prepaid rent | B73: 0 | C73: 0 | D73: 0 | E73: 0 | F73: 0 | G73: 11711.35 | H73: 0 | I73: 0 | J73: =+IFERROR(VLOOKUP(A73,[1]BalanceSheet!A$8:B$154,2,0),0) -> 0 | K73: 13.1
A74: 13003 - Deferred Customer acquisition cost | B74: 0 | C74: 0 | D74: 0 | E74: 0 | F74: 0 | G74: 0 | H74: 99340.48 | I74: 0 | J74: =+IFERROR(VLOOKUP(A74,[1]BalanceSheet!A$8:B$154,2,0),0) -> 0 | K74: 13.1
A75: Total - 13000 - Prepaid Exp. | B75: 0 | C75: 143307.18 | D75: 0 | E75: 0 | F75: 0 | G75: 27065.6 | H75: 228412.22 | I75: 4547.06 | J75: =+IFERROR(VLOOKUP(A75,[1]BalanceSheet!A$8:B$154,2,0),0) -> 37005.61 | K75: 13
A76: 13009 - Government Institutions | J76: =+IFERROR(VLOOKUP(A76,[1]BalanceSheet!A$8:B$154,2,0),0) -> 0
A77: 13100 - VAT Assets | J77: =+IFERROR(VLOOKUP(A77,[1]BalanceSheet!A$8:B$154,2,0),0) -> 0
A78: 13101 - VAT on FA Purchases IL | B78: 0 | C78: 0 | D78: 0 | E78: 0 | F78: 0 | G78: 0 | H78: -84.05 | I78: 0 | J78: =+IFERROR(VLOOKUP(A78,[1]BalanceSheet!A$8:B$154,2,0),0) -> 0
A79: 13102 - VAT on Purchases IL | B79: 0 | C79: 0 | D79: 0 | E79: 0 | F79: 0 | G79: 0 | H79: 655.96 | I79: 0 | J79: =+IFERROR(VLOOKUP(A79,[1]BalanceSheet!A$8:B$154,2,0),0) -> 32.8
A80: 13103 - VAT Proforma IL | B80: 0 | C80: 0 | D80: 0 | E80: 0 | F80: 0 | G80: 0 | H80: 3165.33 | I80: 0 | J80: =+IFERROR(VLOOKUP(A80,[1]BalanceSheet!A$8:B$154,2,0),0) -> 80072.82
A81: 13107 - VAT D/C | B81: 0 | C81: 0 | D81: 0 | E81: 0 | F81: 0 | G81: 0 | H81: 31238.41 | I81: 0 | J81: =+IFERROR(VLOOKUP(A81,[1]BalanceSheet!A$8:B$154,2,0),0) -> 0
A82: 13122 - VAT on FA Purchases FR | B82: 0 | C82: 0 | D82: 0 | E82: 0 | F82: 0 | G82: 0 | H82: 0 | I82: 5870.77 | J82: =+IFERROR(VLOOKUP(A82,[1]BalanceSheet!A$8:B$154,2,0),0) -> 5870.77
A83: 13123 - VAT on Purchases FR | B83: 0 | C83: 0 | D83: 0 | E83: 0 | F83: 0 | G83: 0 | H83: 0 | I83: 38437.97 | J83: =+IFERROR(VLOOKUP(A83,[1]BalanceSheet!A$8:B$154,2,0),0) -> 11696.16
A84: 13124 - VAT deductible on goods and services | B84: 0 | C84: 0 | D84: 0 | E84: 0 | F84: 0 | G84: 0 | H84: 0 | I84: 848.64 | J84: =+IFERROR(VLOOKUP(A84,[1]BalanceSheet!A$8:B$154,2,0),0) -> 899.79
A85: 13202 - VAT on Purchases UK | B85: 0 | C85: 0 | D85: 0 | E85: 0 | F85: 0 | G85: 39429.68 | H85: 0 | I85: 0 | J85: =+IFERROR(VLOOKUP(A85,[1]BalanceSheet!A$8:B$154,2,0),0) -> 0
A86: Total - 13100 - VAT Assets | B86: 0 | C86: 0 | D86: 0 | E86: 0 | F86: 0 | G86: 39429.68 | H86: 34975.65 | I86: 45157.38 | J86: =+IFERROR(VLOOKUP(A86,[1]BalanceSheet!A$8:B$154,2,0),0) -> 98572.34 | K86: 13.2
A87: 13300 - TAX Assets | J87: =+IFERROR(VLOOKUP(A87,[1]BalanceSheet!A$8:B$154,2,0),0) -> 0
A88: 13301 - Advances for Odfot | B88: 0 | C88: 0 | D88: 0 | E88: 0 | F88: 0 | G88: 0 | H88: 17204.02 | I88: 0 | J88: =+IFERROR(VLOOKUP(A88,[1]BalanceSheet!A$8:B$154,2,0),0) -> 17204.02
A89: 13302 - Reversal for Exceed expenses | B89: 0 | C89: 0 | D89: 0 | E89: 0 | F89: 0 | G89: 0 | H89: -17204.02 | I89: 0 | J89: =+IFERROR(VLOOKUP(A89,[1]BalanceSheet!A$8:B$154,2,0),0) -> -17204.02
A90: 13303 - Tax Benefits | B90: 0 | C90: 0 | D90: -447.84 | E90: 0 | F90: 0 | G90: 0 | H90: 0 | I90: 75511.06 | J90: =+IFERROR(VLOOKUP(A90,[1]BalanceSheet!A$8:B$154,2,0),0) -> 76473.19
A91: 13304 - Other current tax asset | B91: 0 | C91: 0 | D91: 0 | E91: 0 | F91: 0 | G91: 3267.88 | H91: 0 | I91: 0 | J91: =+IFERROR(VLOOKUP(A91,[1]BalanceSheet!A$8:B$154,2,0),0) -> 3267.88
A92: Total - 13300 - TAX Assets | B92: 0 | C92: 0 | D92: -447.84 | E92: 0 | F92: 0 | G92: 3267.88 | H92: 0 | I92: 75511.06 | J92: =+IFERROR(VLOOKUP(A92,[1]BalanceSheet!A$8:B$154,2,0),0) -> 79741.07 | K92: 13.2
A93: Total - 13009 - Government Institutions | B93: 0 | C93: 0 | D93: -447.84 | E93: 0 | F93: 0 | G93: 42697.56 | H93: 34975.65 | I93: 120668.44 | J93: =+IFERROR(VLOOKUP(A93,[1]BalanceSheet!A$8:B$154,2,0),0) -> 178313.41 | K93: 13
A94: 16000 - Other Current Asset | J94: =+IFERROR(VLOOKUP(A94,[1]BalanceSheet!A$8:B$154,2,0),0) -> 0
A95: 16001 - Rent deposit | B95: 0 | C95: 36775 | D95: 0 | E95: 0 | F95: 0 | G95: 68850.34 | H95: 37820.53 | I95: 14750.69 | J95: =+IFERROR(VLOOKUP(A95,[1]BalanceSheet!A$8:B$154,2,0),0) -> 36888.95 | K95: 13.3
A96: 16002 - Other Deposits | B96: 0 | C96: 0 | D96: 0 | E96: 0 | F96: 0 | G96: 0 | H96: 11921 | I96: 0 | J96: =+IFERROR(VLOOKUP(A96,[1]BalanceSheet!A$8:B$154,2,0),0) -> 0 | K96: 13.3
A97: Total - 16000 - Other Current Asset | B97: 0 | C97: 36775 | D97: 0 | E97: 0 | F97: 0 | G97: 68850.34 | H97: 49741.53 | I97: 14750.69 | J97: =+IFERROR(VLOOKUP(A97,[1]BalanceSheet!A$8:B$154,2,0),0) -> 36888.95 | K97: 13
A98: 16100 - other current asset | B98: 0 | C98: 0 | D98: 117.88 | E98: 491.94 | F98: 83.92 | G98: 0 | H98: 26.53 | I98: 0 | J98: =+IFERROR(VLOOKUP(A98,[1]BalanceSheet!A$8:B$154,2,0),0) -> 693.74 | K98: 13 | L98: 13.3
A99: 17000 - Other long term assets | J99: =+IFERROR(VLOOKUP(A99,[1]BalanceSheet!A$8:B$154,2,0),0) -> 0
A100: 17001 - Interco Loans | B100: -261263.83 | C100: 0 | D100: 0 | E100: 0 | F100: 0 | G100: 0 | H100: 261263.83 | I100: 0 | J100: =+IFERROR(VLOOKUP(A100,[1]BalanceSheet!A$8:B$154,2,0),0) -> 0
A101: 17002 - Employee Loans | B101: 0 | C101: 0 | D101: 37427.66 | E101: 0 | F101: 0 | G101: 0 | H101: 0 | I101: 0 | J101: =+IFERROR(VLOOKUP(A101,[1]BalanceSheet!A$8:B$154,2,0),0) -> 37427.66
A102: Total - 17000 - Other long term assets | B102: -261263.83 | C102: 0 | D102: 37427.66 | E102: 0 | F102: 0 | G102: 0 | H102: 261263.83 | I102: 0 | J102: =+IFERROR(VLOOKUP(A102,[1]BalanceSheet!A$8:B$154,2,0),0) -> 37427.66 | K102: 14
...
