Workbook

Sheet Summary
B6: GetCtrl LTD
B7: Unaudited Managerial Financial Report for the Month ended - | J7: 45291
B8: Profit & Loss Summary
G11: YTD
G12: 45291 | H12: =G12 -> 45291
G13: NIS | H13: USD
B15: Revenues | G15: ='P&L'!E15 -> 0 | H15: ='P&L'!F15 -> 0
B16: Cost of revenues | G16: ='P&L'!E21 -> 0 | H16: ='P&L'!F21 -> 0
B17: Gross profit | G17: =G15-G16 -> 0 | H17: =H15-H16 -> 0
B19: Operating expenses
C20: R&D expenses | G20: ='P&L'!E35 -> 4940779.5 | H20: ='P&L'!F35 -> 1343306.1 | J20: =H20/$H$23 -> 0.53528066
C21: S&M expenses | G21: ='P&L'!E46 -> 2228851.2 | H21: ='P&L'!F46 -> 612473.45 | J21: =H21/$H$23 -> 0.24405845
C22: G&A expenses | G22: ='P&L'!E63 -> 2012572.7 | H22: ='P&L'!F63 -> 553756.44 | J22: =H22/$H$23 -> 0.22066089
B23: Total Operating Expenses | G23: =SUM(G20:G22) -> 9182203.4 | H23: =SUM(H20:H22) -> 2509536
B25: (*) EBITDA | G25: ='P&L'!E76 -> -9100727.4 | H25: ='P&L'!F76 -> -2484756
B27: (*) Earnings Before Interest, Tax, Depreciation and Amortization
B30: Cash Status as of | E30: =J7 -> 45291 | G30: =BS!E16 -> 2798941.6 | H30: =BS!G16 -> 771696.05
B33: Monthly average Burn Rate(K$)
G36: YTD
G37: =G12 -> 45291 | H37: =H12 -> 45291
G38: NIS | H38: USD
C39: EBITDA | G39: =G25/9 -> -1011191.9 | H39: =H25/9 -> -276084
C40: CAPEX | G40: 0 | H40: 0
C42: Burn rate for period | G42: =G39+G40 -> -1011191.9 | H42: =H39+H40 -> -276084
B46: Head Count
H49: Month ended
G50: 43190 | H50: 43465
C51: Cogs | G51: 0.05 | H51: 0.4
C52: R&D | G52: 8.3 | H52: 5.6
C53: M&S | G53: 1.05 | H53: 0.7
C54: G&A | G54: 1.6 | H54: 1.3
C55: Total head count | G55: =SUM(G52:G54) -> 10.95 | H55: =SUM(H52:H54) -> 7.6

Sheet BS
B6: =Summary!B6 -> GetCtrl LTD
B7: Unaudited Managerial Financial Report as of - | I7: =Summary!J7 -> 45291
B8: Profit & Loss Summary
E11: =I7 -> 45291 | G11: =I7 -> 45291 | K11: 45199 | M11: 45199 | O11: 45107 | Q11: 45107 | S11: 45016 | U11: 45016 | W11: 44926 | Y11: 44926 | AA11: 44561 | AC11: 44561
E12: NIS | G12: USD | K12: NIS | M12: USD | O12: NIS | Q12: USD | S12: NIS | U12: USD | W12: NIS | Y12: USD | AA12: NIS | AC12: USD
B13: ASSETS
C15: Current Assets
D16: Cash and cash equivalents | E16: =SUMIF(TB!$J$2:$J$121,D16,TB!$F$2:$F$121) -> 2798941.6 | G16: =SUMIF(TB!$J$2:$J$121,D16,TB!$I$2:$I121) -> 771696.05 | K16: 4215848.2 | M16: 1101246.7 | O16: 5701783.6 | Q16: 1541050 | S16: 10315135 | U16: 2852307.3 | W16: 7141709.9 | Y16: 2029479.2 | AA16: 3333096.3 | AC16: 1071735.1
D17: Accounts receivable | E17: =SUMIF(TB!$J$2:$J$121,D17,TB!$F$2:$F$121) -> 0 | G17: =SUMIF(TB!$J$2:$J$121,D17,TB!$I$2:$I122) -> 0 | K17: 0 | M17: 0 | O17: 0 | Q17: 0 | S17: 0 | U17: 0 | W17: 0 | Y17: 0 | AA17: 0 | AC17: 0
D18: Prepaid expenses | E18: =SUMIF(TB!$J$2:$J$121,D18,TB!$F$2:$F$121) -> 0 | G18: =SUMIF(TB!$J$2:$J$121,D18,TB!$I$2:$I123) -> 0 | K18: 0 | M18: 0 | O18: 0 | Q18: 0 | S18: 0 | U18: 0 | W18: 0 | Y18: 0 | AA18: 0 | AC18: 0
D19: Account Receivable-VAT+TAX | E19: =SUMIF(TB!$J$2:$J$121,D19,TB!$F$2:$F$121) -> 111434.76 | G19: =SUMIF(TB!$J$2:$J$121,D19,TB!$I$2:$I124) -> 30723.68 | K19: 113888.95 | M19: 29782.67 | O19: 104315.43 | Q19: 28193.35 | S19: 87603.37 | U19: 24233.31 | W19: 104029.47 | Y19: 29562.23 | AA19: 53258.19 | AC19: 17124.82
D20: Deposit | E20: =SUMIF(TB!$J$2:$J$121,D20,TB!$F$2:$F$121) -> 0 | G20: =SUMIF(TB!$J$2:$J$121,D20,TB!$I$2:$I125) -> 0
D21: Related party Debit | E21: =SUMIF(TB!$J$2:$J$121,D21,TB!$F$2:$F$121) -> 0 | G21: =SUMIF(TB!$J$2:$J$121,D21,TB!$I$2:$I125) -> 0 | K21: 0 | M21: 0 | O21: 0 | Q21: 0 | S21: 0 | U21: 0 | W21: 0 | Y21: 0 | AA21: 445173.54 | AC21: 143142.62
D22: Other current assets | E22: =SUMIF(TB!$J$2:$J$121,D22,TB!$F$2:$F$121) -> 100360.02 | G22: =SUMIF(TB!$J$2:$J$121,D22,TB!$I$2:$I125) -> 27670.25 | K22: 30673.79 | M22: 8021.39 | O22: 38921.41 | Q22: 10519.3 | S22: 27957.46 | U22: 7733.74 | W22: 27957.46 | Y22: 7944.72 | AA22: 1240.75 | AC22: 398.95
C23: Total current assets | E23: =SUM(E16:E22) -> 3010736.4 | G23: =SUM(G16:G22) -> 830089.98 | K23: 4360410.9 | M23: 1139050.8 | O23: 5845020.4 | Q23: 1579762.7 | S23: 10430696 | U23: 2884274.3 | W23: 7273696.9 | Y23: 2066986.2 | AA23: 3832768.7 | AC23: 1232401.5
C25: Non current assets
D26: Restricted cash | E26: =SUMIF(TB!$J$2:$J$121,D26,TB!$F$2:$F$121) -> 145977.02 | G26: =SUMIF(TB!$J$2:$J$121,D26,TB!$I$2:$I129) -> 40247.32 | K26: 144210 | M26: 38975.676 | O26: 144210 | Q26: 38975.676 | S26: 144210 | U26: 40980.392 | W26: 144210 | Y26: 40980.392 | AA26: 144216.47 | AC26: 46371.85
D27: Property and Equipment, Net | E27: =SUMIF(TB!$J$2:$J$121,D27,TB!$F$2:$F$121) -> 288898.85 | G27: =SUMIF(TB!$J$2:$J$121,D27,TB!$I$2:$I130) -> 87591.02 | K27: 363026.13 | M27: 110528.31 | O27: 336124.8 | Q27: 103326.65 | S27: 336124.8 | U27: 103326.65 | W27: 336124.8 | Y27: 103326.65 | AA27: 357746.04 | AC27: 110861.09
D28: Other Long term Assets | E28: =SUMIF(TB!$J$2:$J$121,D28,TB!$F$2:$F$121) -> 563565 | G28: =SUMIF(TB!$J$2:$J$121,D28,TB!$I$2:$I131) -> 160149.19 | K28: 563565 | M28: 160149.19 | O28: 563565 | Q28: 160149.19 | W28: 563565 | Y28: 160149.19
C29: Total Non current assets | E29: =SUM(E26:E28) -> 998440.87 | G29: =SUM(G26:G28) -> 287987.53 | K29: 1070801.1 | M29: 309653.18 | O29: 1043899.8 | Q29: 302451.52 | S29: 480334.8 | U29: 144307.04 | W29: 1043899.8 | Y29: 304456.23 | AA29: 501962.51 | AC29: 157232.94
B32: TOTAL ASSETS | E32: =E23+E29 -> 4009177.2 | G32: =G23+G29 -> 1118077.5 | K32: 5431212 | M32: 1448704 | O32: 6888920.2 | Q32: 1882214.2 | S32: 10911031 | U32: 3028581.4 | W32: 8317596.7 | Y32: 2371442.4 | AA32: 4334731.2 | AC32: 1389634.5
B34: LIABILITIES AND SHAREHOLDERS' EQUITY
C36: Current Liabilities
D37: Short term loans | E37: =-SUMIF(TB!$J$2:$J$121,D37,TB!$F$2:$F$121) -> 0 | G37: =-SUMIF(TB!$J$2:$J$121,D37,TB!$I$2:$I135) -> 0 | K37: 0 | M37: 0 | O37: 0 | Q37: 0 | S37: 0 | U37: 0 | W37: 0 | Y37: 0 | AA37: 0 | AC37: 0
D38: Accounts payable | E38: =-SUMIF(TB!$J$2:$J$121,D38,TB!$F$2:$F$121) -> 267533.76 | G38: =-SUMIF(TB!$J$2:$J$121,D38,TB!$I$2:$I135) -> 73761.726 | K38: 128163.42 | M38: 33515.522 | O38: 119881.81 | Q38: 33696.817 | S38: 179452.29 | U38: 49641.002 | W38: 220909.19 | Y38: 62776.033 | AA38: 47369.14 | AC38: 15231.23
D39: Accrued expenses | E39: =-SUMIF(TB!$J$2:$J$121,D39,TB!$F$2:$F$121) -> 32627.41 | G39: =-SUMIF(TB!$J$2:$J$121,D39,TB!$I$2:$I135) -> 8995.7018 | K39: 32000 | M39: 8648.6486 | O39: 40800 | Q39: 11027.027 | S39: 75555 | U39: 20610.909 | W39: 75555 | Y39: 20610.909 | AA39: 66937.5 | AC39: 21523.31
D40: Employee payables & institutions | E40: =-SUMIF(TB!$J$2:$J$121,D40,TB!$F$2:$F$121) -> 320113.73 | G40: =-SUMIF(TB!$J$2:$J$121,D40,TB!$I$2:$I135) -> 93603.46 | K40: 460536.81 | M40: 128578.28 | O40: 342373.27 | Q40: 98950.6 | S40: 441473.87 | U40: 127287.27 | W40: 478198.82 | Y40: 139567.34 | AA40: 516508.38 | AC40: 166079.88
D41: Related party | E41: =-SUMIF(TB!$J$2:$J$121,D41,TB!$F$2:$F$121) -> 5507655.5 | G41: =-SUMIF(TB!$J$2:$J$121,D41,TB!$I$2:$I135) -> 1534943.1 | K41: 2767370.9 | M41: 810205.3 | O41: 47328011 | Q41: 13988401 | S41: 28930967 | U41: 8188365.7 | W41: 814859.54 | Y41: 253055.79 | AA41: 7884283.4 | AC41: 2535139.3
D42: Other short term liabilities | E42: =-SUMIF(TB!$J$2:$J$121,D42,TB!$F$2:$F$121) -> 0 | G42: =-SUMIF(TB!$J$2:$J$121,D42,TB!$I$2:$I135) -> 0 | K42: 0 | M42: 0 | O42: 0 | Q42: 0 | S42: 0 | U42: 0 | W42: 369893 | Y42: 105113.1 | AA42: 0 | AC42: 0
C43: Total Current Liabilities | E43: =SUM(E37:E42) -> 6127930.4 | G43: =SUM(G37:G42) -> 1711304 | K43: 3388071.1 | M43: 980947.75 | O43: 47831066 | Q43: 14132076 | S43: 29627448 | U43: 8385904.9 | W43: 1959415.6 | Y43: 581123.17 | AA43: 8515098.4 | AC43: 2737973.8
C45: Long Term Liabilities
D46: Severance, Net | E46: =-SUMIF(TB!$J$2:$J$121,D46,TB!$F$2:$F$121) -> 0 | G46: =-SUMIF(TB!$J$2:$J$121,D46,TB!$I$2:$I135) -> 0 | K46: 0 | M46: 0 | O46: 0 | Q46: 0 | S46: 0 | U46: 0 | W46: 0 | Y46: 0 | AA46: 0 | AC46: 0
D47: Other Long term liabilities | E47: =-SUMIF(TB!$J$2:$J$121,D47,TB!$F$2:$F$121) -> 569697 | G47: =-SUMIF(TB!$J$2:$J$121,D47,TB!$I$2:$I136) -> 161891.73 | K47: 569697 | M47: 161891.73 | O47: 569697 | Q47: 161891.73 | S47: 0 | U47: 0 | W47: 199804 | Y47: 56778.63 | AA47: 0 | AC47: 0
C48: Total Long Term Liabilities | E48: =SUM(E46:E47) -> 569697 | G48: =SUM(G46:G47) -> 161891.73 | K48: 569697 | M48: 161891.73 | O48: 569697 | Q48: 161891.73 | S48: 0 | U48: 0 | W48: 199804 | Y48: 56778.63 | AA48: 0 | AC48: 0
C50: Shareholders' Equity
D51: Share capital | E51: =-SUMIF(TB!$J$2:$J$121,D51,TB!$F$2:$F$121) -> 0 | G51: =-SUMIF(TB!$J$2:$J$121,D51,TB!$I$2:$I140) -> 0 | K51: 0 | M51: 0 | O51: 0 | Q51: 0 | S51: 0 | U51: 0 | W51: 0 | Y51: 0 | AA51: 0 | AC51: 0
D52: Additional paid-in capital | E52: =-SUMIF(TB!$J$2:$J$121,D52,TB!$F$2:$F$121) -> 0 | G52: =-SUMIF(TB!$J$2:$J$121,D52,TB!$I$2:$I141) -> 0 | K52: 0 | M52: 0 | O52: 0 | Q52: 0 | S52: 0 | U52: 0 | W52: 0 | Y52: 0 | AA52: 0 | AC52: 0
D53: Capital note | E53: =-SUMIF(TB!$J$2:$J$121,D53,TB!$F$2:$F$121) -> 22281920 | G53: =-SUMIF(TB!$J$2:$J$121,D53,TB!$I$2:$I142) -> 6600000 | K53: 22281920 | M53: 6600000 | O53: -22281920 | Q53: -6600000 | S53: 0 | U53: 0 | W53: 22281920 | Y53: 6600000
D54: Equity expenses | E54: =-SUMIF(TB!$J$2:$J$121,D54,TB!$F$2:$F$121) -> 0 | G54: =-SUMIF(TB!$J$2:$J$121,D54,TB!$I$2:$I142) -> 0 | K54: 0 | M54: 0 | O54: 0 | Q54: 0 | S54: 0 | U54: 0 | W54: 0 | Y54: 0 | AA54: 0 | AC54: 0
D55: Capital reserve | E55: =-SUMIF(TB!$J$2:$J$121,D55,TB!$F$2:$F$121) -> 0 | G55: =-SUMIF(TB!$J$2:$J$121,D55,TB!$I$2:$I143) -> 0 | K55: 0 | M55: 0 | O55: 0 | Q55: 0 | W55: 0 | Y55: 0 | AA55: 0 | AC55: 0
D56: Accumulated deficit | E56: =-SUMIF(TB!$J$2:$J$121,D56,TB!$F$2:$F$121) -> -16123543 | G56: =-SUMIF(TB!$J$2:$J$121,D56,TB!$I$2:$I141) -> -4866459.4 | I56: מתאים לדוח | K56: -16123543 | M56: -4866459.4 | O56: -16123543 | Q56: -4866459.4 | S56: -17060469 | U56: -4864716.9 | W56: -4180367.1 | Y56: -1348339.3 | AA56: 0 | AC56: 0
D57: Profit (loss) this year | E57: ='P&L'!E73 -> -8846827.3 | G57: ='P&L'!F73 -> -2488658.8 | K57: -4684933.2 | M57: -1427676.1 | O57: -3106379.5 | Q57: -945293.86 | S57: -1655948 | U57: -492606.63 | W57: -11943176 | Y57: -3518120.1 | AA57: -4180367.1 | AC57: -1348339.3
C58: Total Shareholders' Equity | E58: =SUM(E51:E57) -> -2688450.1 | G58: =SUM(G51:G57) -> -755118.21 | K58: 1473443.9 | M58: 305864.48 | O58: -41511842 | Q58: -12411753 | S58: -18716417 | U58: -5357323.5 | W58: 6158377.1 | Y58: 1733540.6 | AA58: -4180367.1 | AC58: -1348339.3
B60: TOTAL LIABILITIES AND
B61: SHAREHOLDERS' EQUITY | E61: =E43+E58+E48 -> 4009177.2 | G61: =G43+G58+G48 -> 1118077.5 | K61: 5431212 | M61: 1448704 | O61: 6888920.2 | Q61: 1882214.2 | S61: 10911031 | U61: 3028581.4 | W61: 8317596.7 | Y61: 2371442.4 | AA61: 4334731.2 | AC61: 1389634.5
C64: Notes | AE64: Capital note
C66: (1) | D66: The above mentioned balance sheet is based on unaudited ledger
C68: (2)
C70: (3)
W74: 0 | Y74: 0 | AA74: 0 | AC74: 0
E75: =E32-E61 -> 0 | G75: =G32-G61 -> 0 | K75: 0 | M75: 0 | O75: 0 | Q75: 0

Sheet CF
B6: =Summary!B6 -> GetCtrl LTD
B7: Unaudited Consilidated Managerial Financial Report for the Month ended - | K7: =Summary!J7 -> 45291
B8: Cash Flow (K$)
E11: =K7 -> 45291 | G11: YTD
C14: Cash Flows from Operating Activities
D15: Net Income (Loss)
C16: Adjustments to reconcile loss to net cash flow-
D17: Expenses not involving cash flow:
D18: Decrease (Increase) in Receivables
D19: Increase (Decrease) in Liabilities
D20: Increase (Decrease) in deferred revenue
D21: Depreciation
C22: Total Adjustments | E22: =SUM(E18:E21) -> 0
C23: Net cash used in operating activities | E23: =E15+E22 -> 0 | G23: =G15+G22 -> 0
D25: Purchase of fixed assets
D26: Increase in restricted cash
C27: Net cash used in investment activities | E27: =E25 -> 0 | G27: =SUM(G25:G26) -> 0
C29: Cash Flows from Financing Activities
D30: Receipt of loans
D31: Issuance of share capital
C32: Net cash provided by financing activities | E32: =SUM(E30:E31) -> 0 | G32: =SUM(G30:G31) -> 0
C34: Increase (decrease) in cash | E34: =E23+E27+E32 -> 0 | G34: =G23+G27+G32 -> 0
C36: Cash at beginning of period
C38: Cash at end of the period | G38: =G34+G36 -> 0
C42: Notes
C44: (1) | D44: The above mentioned cash flow is based on unaudited ledger
C46: (2)
C48: (3)

Sheet P&L
B6: =Summary!B6 -> GetCtrl LTD
B7: Unaudited Managerial Financial Report for the Month ended - | H7: =Summary!J7 -> 45291
B8: Profit & Loss Summary
E11: YTD | N11: YTD | Q11: YTD | T11: YTD | W11: YTD | Z11: YTD
E12: =H7 -> 45291 | F12: =E12 -> 45291 | G12: Note | N12: 45199 | O12: 45199 | Q12: 45107 | R12: 45107 | T12: 45016 | U12: 45016 | W12: 44926 | X12: 44926 | Z12: 44561 | AA12: 44561
E13: NIS | F13: USD | N13: NIS | O13: USD | Q13: NIS | R13: USD | T13: NIS | U13: USD | W13: NIS | X13: USD | Z13: NIS | AA13: USD
B15: Revenues | E15: =-SUMIF(TB!$J$2:$J$121,B15,TB!$F$2:$F$121) -> 0 | F15: =-SUMIF(TB!$J$2:$J$121,B15,TB!$I$2:$I$121) -> 0 | N15: 0 | O15: 0 | Q15: 0 | R15: 0 | T15: 0 | U15: 0 | W15: 0 | X15: 0 | Z15: 0 | AA15: 0
B17: Cost of revenues
B18: Cost of sales | E18: =SUMIF(TB!$J$2:$J$121,B18,TB!$F$2:$F$121) -> 0 | F18: =SUMIF(TB!$J$2:$J$121,B18,TB!$I$2:$I$121) -> 0 | N18: 0 | O18: 0 | Q18: 0 | R18: 0 | T18: 0 | U18: 0 | W18: 0 | X18: 0 | Z18: 0 | AA18: 0
B19: Cogs Payroll and social benefits | E19: =SUMIF(TB!$J$2:$J$121,B19,TB!$F$2:$F$121) -> 0 | F19: =SUMIF(TB!$J$2:$J$121,B19,TB!$I$2:$I$121) -> 0 | N19: 0 | O19: 0 | Q19: 0 | R19: 0 | T19: 0 | U19: 0 | W19: 0 | X19: 0 | Z19: 0 | AA19: 0
B20: Allocation cogs | E20: =SUMIF(TB!$J$2:$J$121,B20,TB!$F$2:$F$121) -> 0 | F20: =SUMIF(TB!$J$2:$J$121,B20,TB!$I$2:$I$121) -> 0 | N20: 0 | O20: 0 | Q20: 0 | R20: 0 | T20: 0 | U20: 0 | W20: 0 | X20: 0 | Z20: 0 | AA20: 0
B21: Total Cost of revenues | E21: =SUM(E18:E20) -> 0 | F21: =SUM(F18:F20) -> 0 | N21: 0 | O21: 0 | Q21: 0 | R21: 0 | T21: 0 | U21: 0 | W21: 0 | X21: 0 | Z21: 0 | AA21: 0
B23: Gross profit | E23: =E15-E21 -> 0 | F23: =F15-F21 -> 0 | N23: 0 | O23: 0 | Q23: 0 | R23: 0 | T23: 0 | U23: 0 | W23: 0 | X23: 0 | Z23: 0 | AA23: 0
B25: Operating expenses
B27: Research and development-
C28: Salaries and social benefits - R&D | E28: =SUMIF(TB!$J$2:$J$121,C28,TB!$F$2:$F$121) -> 3412007.6 | F28: =SUMIF(TB!$J$2:$J$121,C28,TB!$I$2:$I$121) -> 926825.31 | G28: (1) | I28: =E28-N28 -> 391919.24 | J28: =N28-Q28 -> 827827.16 | K28: =Q28-T28 -> 901590.74 | L28: =T28 -> 1290670.5 | N28: 3020088.4 | O28: 826546.87 | Q28: 2192261.2 | R28: 607213 | T28: 1290670.5 | U28: 359538.79 | W28: 4223891.8 | X28: 1248097.7 | Z28: 1852803.5 | AA28: 582341.96
C29: Subcontractors | E29: =SUMIF(TB!$J$2:$J$121,C29,TB!$F$2:$F$121) -> -35550 | F29: =SUMIF(TB!$J$2:$J$121,C29,TB!$I$2:$I$121) -> -10104.27 | I29: =E29-N29 -> 0 | J29: =N29-Q29 -> 0 | K29: =Q29-T29 -> -38000 | L29: =T29 -> 2450 | N29: -35550 | O29: -10104.27 | Q29: -35550 | R29: -10104.27 | T29: 2450 | U29: 694.25 | W29: 152000 | X29: 44337.642 | Z29: 121000 | AA29: 37501.49
C30: IIA Expenses | E30: =SUMIF(TB!$J$2:$J$121,C30,TB!$F$2:$F$121) -> 0 | F30: =SUMIF(TB!$J$2:$J$121,C30,TB!$I$2:$I$121) -> 0 | I30: =E30-N30 -> 0 | J30: =N30-Q30 -> 0 | K30: =Q30-T30 -> 0 | L30: =T30 -> 0 | N30: 0 | O30: 0 | Q30: 0 | R30: 0 | T30: 0 | U30: 0 | W30: 0 | X30: 0 | Z30: 0 | AA30: 0
C31: Recrutment | E31: =SUMIF(TB!$J$2:$J$121,C31,TB!$F$2:$F$121) -> 0 | F31: =SUMIF(TB!$J$2:$J$121,C31,TB!$I$2:$I$121) -> 0 | I31: =E31-N31 -> 0 | J31: =N31-Q31 -> 0 | K31: =Q31-T31 -> 0 | L31: =T31 -> 0 | N31: 0 | O31: 0 | Q31: 0 | R31: 0 | T31: 0 | U31: 0 | W31: 67097.05 | X31: 20502.54 | Z31: 32000 | AA31: 9959.54
C32: Travel R&D | E32: =SUMIF(TB!$J$2:$J$121,C32,TB!$F$2:$F$121) -> 0 | F32: =SUMIF(TB!$J$2:$J$121,C32,TB!$I$2:$I$121) -> 0 | I32: =E32-N32 -> 0 | J32: =N32-Q32 -> 0 | K32: =Q32-T32 -> 0 | L32: =T32 -> 0 | N32: 0 | O32: 0 | Q32: 0 | R32: 0 | T32: 0 | U32: 0 | W32: 0 | X32: 0 | Z32: 0 | AA32: 0
C33: G&A overhead | E33: =SUMIF(TB!$J$2:$J$121,C33,TB!$F$2:$F$121) -> 640307.23 | F33: =SUMIF(TB!$J$2:$J$121,C33,TB!$I$2:$I$121) -> 176539.08 | I33: =E33-N33 -> 172514.14 | J33: =N33-Q33 -> 155085.98 | K33: =Q33-T33 -> 154689.05 | L33: =T33 -> 158018.06 | N33: 467793.09 | O33: 126430.56 | Q33: 312707.1 | R33: 84515.434 | T33: 158018.06 | U33: 44904.25 | W33: 743604.89 | X33: 211311.42
C34: R&D expenses | E34: =SUMIF(TB!$J$2:$J$121,C34,TB!$F$2:$F$121) -> 924014.67 | F34: =SUMIF(TB!$J$2:$J$121,C34,TB!$I$2:$I$121) -> 250045.97 | I34: =E34-N34 -> 149498.25 | J34: =N34-Q34 -> 395690.46 | K34: =Q34-T34 -> 190928.5 | L34: =T34 -> 187897.46 | N34: 774516.42 | O34: 209029.29 | Q34: 378825.96 | R34: 104747.08 | T34: 187897.46 | U34: 52530.292 | W34: 1557440.5 | X34: 473461.24 | Z34: 488245.56 | AA34: 153274.96
B35: Total R&D | E35: =SUM(E28:E34) -> 4940779.5 | F35: =SUM(F28:F34) -> 1343306.1 | I35: =E35-N35 -> 713931.63 | J35: =N35-Q35 -> 1378603.6 | K35: =Q35-T35 -> 1209208.3 | L35: =T35 -> 1639036 | N35: 4226847.9 | O35: 1151902.5 | Q35: 2848244.3 | R35: 786371.24 | T35: 1639036 | U35: 457667.59 | W35: 6744034.2 | X35: 1997710.6 | Z35: 2494049 | AA35: 783077.95
I36: =E36-N36 -> 0 | J36: =N36-Q36 -> 0 | K36: =Q36-T36 -> 0 | L36: =T36 -> 0
B37: Sales and marketing- | I37: =E37-N37 -> 0 | J37: =N37-Q37 -> 0 | K37: =Q37-T37 -> 0 | L37: =T37 -> 0
C38: Salaries and social benefits - S&M | E38: =SUMIF(TB!$J$2:$J$121,C38,TB!$F$2:$F$121) -> 0 | F38: =SUMIF(TB!$J$2:$J$121,C38,TB!$I$2:$I$121) -> 0 | I38: =E38-N38 -> 0 | J38: =N38-Q38 -> 0 | K38: =Q38-T38 -> 0 | L38: =T38 -> 0 | N38: 0 | O38: 0 | Q38: 0 | R38: 0 | T38: 0 | U38: 0 | W38: 0 | X38: 0 | Z38: 0 | AA38: 0
C39: Travel | E39: =SUMIF(TB!$J$2:$J$121,C39,TB!$F$2:$F$121) -> 52909.86 | F39: =SUMIF(TB!$J$2:$J$121,C39,TB!$I$2:$I$121) -> 14359.73 | G39: (2) | I39: =E39-N39 -> 3147.04 | J39: =N39-Q39 -> 40036.86 | K39: =Q39-T39 -> 1704.61 | L39: =T39 -> 8021.35 | N39: 49762.82 | O39: 13367.507 | Q39: 9725.96 | R39: 2747.1174 | T39: 8021.35 | U39: 2275.6199 | W39: 132562.63 | X39: 39325.25 | Z39: 55859.74 | AA39: 17708.34
C40: PR | E40: =SUMIF(TB!$J$2:$J$121,C40,TB!$F$2:$F$121) -> 10000 | F40: =SUMIF(TB!$J$2:$J$121,C40,TB!$I$2:$I$121) -> 2721.08 | I40: =E40-N40 -> 0 | J40: =N40-Q40 -> 0 | K40: =Q40-T40 -> 10000 | L40: =T40 -> 0 | N40: 10000 | O40: 2721.08 | Q40: 10000 | R40: 2721.08 | T40: 0 | U40: 0 | W40: 0 | X40: 0 | Z40: 0 | AA40: 0
C41: Other S&M | E41: =SUMIF(TB!$J$2:$J$121,C41,TB!$F$2:$F$121) -> 455176.75 | F41: =SUMIF(TB!$J$2:$J$121,C41,TB!$I$2:$I$121) -> 123717.83 | I41: =E41-N41 -> 231053.62 | J41: =N41-Q41 -> 66739.55 | K41: =Q41-T41 -> 93045.63 | L41: =T41 -> 64337.95 | N41: 224123.13 | O41: 58746.774 | Q41: 157383.58 | R41: 43563.375 | T41: 64337.95 | U41: 17837.889 | W41: 67732.15 | X41: 19971.69 | Z41: 3031.68 | AA41: 950.68981
C42: Marketing | E42: =SUMIF(TB!$J$2:$J$121,C42,TB!$F$2:$F$121) -> 0 | F42: =SUMIF(TB!$J$2:$J$121,C42,TB!$I$2:$I$121) -> 0 | I42: =E42-N42 -> 0 | J42: =N42-Q42 -> 0 | K42: =Q42-T42 -> 0 | L42: =T42 -> 0 | N42: 0 | O42: 0 | Q42: 0 | R42: 0 | T42: 0 | U42: 0 | W42: 0 | X42: 0 | Z42: 0 | AA42: 0
C43: Recrutment S&M | E43: =SUMIF(TB!$J$2:$J$121,C43,TB!$F$2:$F$121) -> 0 | F43: =SUMIF(TB!$J$2:$J$121,C43,TB!$I$2:$I$121) -> 0 | I43: =E43-N43 -> 0 | J43: =N43-Q43 -> 0 | K43: =Q43-T43 -> 0 | L43: =T43 -> 0 | N43: 0 | O43: 0 | Q43: 0 | R43: 0 | T43: 0 | U43: 0 | W43: 0 | X43: 0 | Z43: 0 | AA43: 0
C44: Consultants S&M | E44: =SUMIF(TB!$J$2:$J$121,C44,TB!$F$2:$F$121) -> 0 | F44: =SUMIF(TB!$J$2:$J$121,C44,TB!$I$2:$I$121) -> 0 | I44: =E44-N44 -> 0 | J44: =N44-Q44 -> 0 | K44: =Q44-T44 -> 0 | L44: =T44 -> 0 | N44: 0 | O44: 0 | Q44: 0 | R44: 0 | T44: 0 | U44: 0 | W44: 0 | X44: 0 | Z44: 0 | AA44: 0
C45: COST + UK S&M | E45: =SUMIF(TB!$J$2:$J$121,C45,TB!$F$2:$F$121) -> 1710764.6 | F45: =SUMIF(TB!$J$2:$J$121,C45,TB!$I$2:$I$121) -> 471674.81 | I45: =E45-N45 -> 1710764.6 | J45: =N45-Q45 -> 0 | K45: =Q45-T45 -> 0 | L45: =T45 -> 0 | N45: 0 | O45: 0 | Q45: 0 | R45: 0 | T45: 0 | U45: 0 | W45: 1810051.1 | X45: 510162.46 | Z45: 0 | AA45: 0
B46: Total S&M | E46: =SUM(E38:E45) -> 2228851.2 | F46: =SUM(F38:F45) -> 612473.45 | I46: =E46-N46 -> 1944965.2 | J46: =N46-Q46 -> 106776.41 | K46: =Q46-T46 -> 104750.24 | L46: =T46 -> 72359.3 | N46: 283885.95 | O46: 74835.361 | Q46: 177109.54 | R46: 49031.572 | T46: 72359.3 | U46: 20113.509 | W46: 2010345.9 | X46: 569459.4 | Z46: 58891.42 | AA46: 18659.03
I47: =E47-N47 -> 0 | J47: =N47-Q47 -> 0 | K47: =Q47-T47 -> 0 | L47: =T47 -> 0
B48: General and administrative- | I48: =E48-N48 -> 0 | J48: =N48-Q48 -> 0 | K48: =Q48-T48 -> 0 | L48: =T48 -> 0
C49: Salaries and social benefits - G&A | E49: =SUMIF(TB!$J$2:$J$121,C49,TB!$F$2:$F$121) -> 564006 | F49: =SUMIF(TB!$J$2:$J$121,C49,TB!$I$2:$I$121) -> 153711.53 | I49: =E49-N49 -> 87564.77 | J49: =N49-Q49 -> 142413.17 | K49: =Q49-T49 -> 167013.31 | L49: =T49 -> 167014.75 | N49: 476441.23 | O49: 128767.9 | Q49: 334028.06 | R49: 90277.854 | T49: 167014.75 | U49: 47460.855 | W49: 1448994.8 | X49: 411763.22 | Z49: 84405.93 | AA49: 27148.9
C50: Accounting & Financial Services | E50: =SUMIF(TB!$J$2:$J$121,C50,TB!$F$2:$F$121) -> 147200 | F50: =SUMIF(TB!$J$2:$J$121,C50,TB!$I$2:$I$121) -> 40385.611 | I50: =E50-N50 -> 28800 | J50: =N50-Q50 -> 19700 | K50: =Q50-T50 -> 54200 | L50: =T50 -> 44500 | N50: 118400 | O50: 33157.109 | Q50: 98700 | R50: 27901.327 | T50: 44500 | U50: 12513.12 | W50: 120800 | X50: 34546.75 | Z50: 46461.18 | AA50: 14665.111
C51: Legal & Professional Services | E51: =SUMIF(TB!$J$2:$J$121,C51,TB!$F$2:$F$121) -> 101137.93 | F51: =SUMIF(TB!$J$2:$J$121,C51,TB!$I$2:$I$121) -> 27086.2 | I51: =E51-N51 -> 19315.14 | J51: =N51-Q51 -> 27567.84 | K51: =Q51-T51 -> 38699.33 | L51: =T51 -> 15555.62 | N51: 81822.79 | O51: 22134.87 | Q51: 54254.95 | R51: 14896.11 | T51: 15555.62 | U51: 4561.77 | W51: 367189.51 | X51: 107912.78 | Z51: 49337.62 | AA51: 15337.12
C52: Insurance | E52: =SUMIF(TB!$J$2:$J$121,C52,TB!$F$2:$F$121) -> 5349.75 | F52: =SUMIF(TB!$J$2:$J$121,C52,TB!$I$2:$I$121) -> 1474.03 | I52: =E52-N52 -> 5349.75 | J52: =N52-Q52 -> 0 | K52: =Q52-T52 -> 0 | L52: =T52 -> 0 | N52: 0 | O52: 0 | Q52: 0 | R52: 0 | T52: 0 | U52: 0 | W52: 0 | X52: 0 | Z52: 1754.25 | AA52: 540
C53: IT& communications | E53: =SUMIF(TB!$J$2:$J$121,C53,TB!$F$2:$F$121) -> 43957.04 | F53: =SUMIF(TB!$J$2:$J$121,C53,TB!$I$2:$I$121) -> 11946.89 | I53: =E53-N53 -> 17766.3 | J53: =N53-Q53 -> 8908.62 | K53: =Q53-T53 -> 8375.95 | L53: =T53 -> 8906.17 | N53: 26190.74 | O53: 7176.85 | Q53: 17282.12 | R53: 4801.61 | T53: 8906.17 | U53: 2514.36 | W53: 81487.21 | X53: 23473.807 | Z53: 22194.15 | AA53: 6989.37
C54: Recruiting & HR | E54: =SUMIF(TB!$J$2:$J$121,C54,TB!$F$2:$F$121) -> 0 | F54: =SUMIF(TB!$J$2:$J$121,C54,TB!$I$2:$I$121) -> 0 | I54: =E54-N54 -> 0 | J54: =N54-Q54 -> 0 | K54: =Q54-T54 -> 0 | L54: =T54 -> 0 | N54: 0 | O54: 0 | Q54: 0 | R54: 0 | T54: 0 | U54: 0 | W54: 0 | X54: 0 | Z54: 0 | AA54: 0
C55: Rent (Inc. Tax) | E55: =SUMIF(TB!$J$2:$J$121,C55,TB!$F$2:$F$121) -> 450797.15 | F55: =SUMIF(TB!$J$2:$J$121,C55,TB!$I$2:$I$121) -> 122403.24 | I55: =E55-N55 -> 119019.86 | J55: =N55-Q55 -> 111464.8 | K55: =Q55-T55 -> 107088.37 | L55: =T55 -> 113224.12 | N55: 331777.29 | O55: 91669.08 | Q55: 220312.49 | R55: 61648.79 | T55: 113224.12 | U55: 32082.66 | W55: 399362.08 | X55: 119570.52 | Z55: 254926.66 | AA55: 80220.491
C56: Maintenance | E56: =SUMIF(TB!$J$2:$J$121,C56,TB!$F$2:$F$121) -> 45477.34 | F56: =SUMIF(TB!$J$2:$J$121,C56,TB!$I$2:$I$121) -> 12435.96 | I56: =E56-N56 -> -6056.85 | J56: =N56-Q56 -> 19995.62 | K56: =Q56-T56 -> 17687.3 | L56: =T56 -> 13851.27 | N56: 51534.19 | O56: 14066.935 | Q56: 31538.57 | R56: 8866.6828 | T56: 13851.27 | U56: 3966.06 | W56: 57118.11 | X56: 18394.993 | Z56: 37382.42 | AA56: 11687.779
C57: Welfare | E57: =SUMIF(TB!$J$2:$J$121,C57,TB!$F$2:$F$121) -> 138368.52 | F57: =SUMIF(TB!$J$2:$J$121,C57,TB!$I$2:$I$121) -> 37571.74 | I57: =E57-N57 -> 26484.53 | J57: =N57-Q57 -> 35301.89 | K57: =Q57-T57 -> 39577.1 | L57: =T57 -> 37005 | N57: 111883.99 | O57: 30443.978 | Q57: 76582.1 | R57: 21106.925 | T57: 37005 | U57: 10310.381 | W57: 174781.92 | X57: 51728.16 | Z57: 56597 | AA57: 17804.73
C58: Car maintenance | E58: =SUMIF(TB!$J$2:$J$121,C58,TB!$F$2:$F$121) -> 9112.91 | F58: =SUMIF(TB!$J$2:$J$121,C58,TB!$I$2:$I$121) -> 2482.01 | I58: =E58-N58 -> 1986.61 | J58: =N58-Q58 -> 1069.75 | K58: =Q58-T58 -> 3605.13 | L58: =T58 -> 2451.42 | N58: 7126.3 | O58: 1949.96 | Q58: 6056.55 | R58: 1666.37 | T58: 2451.42 | U58: 697.2 | W58: 17927.87 | X58: 5288.01 | Z58: 2988.97 | AA58: 933.69
C59: COST + UK G&A | E59: =SUMIF(TB!$J$2:$J$121,C59,TB!$F$2:$F$121) -> 1000407.6 | F59: =SUMIF(TB!$J$2:$J$121,C59,TB!$I$2:$I$121) -> 277890.99 | I59: =E59-N59 -> 1000407.6 | J59: =N59-Q59 -> 0 | K59: =Q59-T59 -> 0 | L59: =T59 -> 0 | N59: 0 | O59: 0 | Q59: 0 | R59: 0 | T59: 0 | U59: 0 | W59: 849838.94 | X59: 238660.25 | Z59: 0 | AA59: 0
C60: Overhead set off | E60: =SUMIF(TB!$J$2:$J$121,C60,TB!$F$2:$F$121) -> -640307.23 | F60: =SUMIF(TB!$J$2:$J$121,C60,TB!$I$2:$I$121) -> -176539.08 | I60: =E60-N60 -> -172514.14 | J60: =N60-Q60 -> -155085.98 | K60: =Q60-T60 -> -154689.05 | L60: =T60 -> -158018.06 | N60: -467793.09 | O60: -126430.56 | Q60: -312707.1 | R60: -84515.434 | T60: -158018.06 | U60: -44904.25 | W60: -743604.89 | X60: -211311.42 | Z60: 0 | AA60: 0
... C62: Other - G&A | E62: =SUMIF(TB!$J$2:$J$121,C62,TB!$F$2:$F$121) -> 65589.66 | F62: =SUMIF(TB!$J$2:$J$121,C62,TB!$I$2:$I$121) -> 18127.31 | I62: =E62-N62 -> 2234.51 | J62: =N62-Q62 -> 18186.55 | K62: =Q62-T62 -> 20632.59 | L62: =T62 -> 24536.01 | N62: 63355.15 | O62: 17490.038 | Q62: 45168.6 | R62: 12723.019 | T62: 24536.01 | U62: 7005.7767 | W62: 128720.92 | X62: 38475.08 | Z62: 48568.79 | AA62: 15090.824
B63: Total G&A | E63: =SUM(E49:E62) -> 2012572.7 | F63: =SUM(F49:F62) -> 553756.44 | I63: =E63-N63 -> 1211834.1 | J63: =N63-Q63 -> 229522.26 | K63: =Q63-T63 -> 302190.03 | L63: =T63 -> 269026.3 | N63: 800738.59 | O63: 220426.16 | Q63: 571216.34 | R63: 159373.25 | T63: 269026.3 | U63: 76207.933 | W63: 2972724.5 | X63: 860329.15 | Z63: 604616.97 | AA63: 190418.02
I64: =E64-N64 -> 0 | J64: =N64-Q64 -> 0 | K64: =Q64-T64 -> 0 | L64: =T64 -> 0
B65: Total Operating Expenses | E65: =+E46+E63+E35 -> 9182203.4 | F65: =+F46+F63+F35 -> 2509536 | I65: =E65-N65 -> 3870730.9 | J65: =N65-Q65 -> 1714902.3 | K65: =Q65-T65 -> 1616148.6 | L65: =T65 -> 1980421.6 | N65: 5311472.5 | O65: 1447164 | Q65: 3596570.2 | R65: 994776.06 | T65: 1980421.6 | U65: 553989.03 | W65: 11727105 | X65: 3427499.1 | Z65: 3157557.4 | AA65: 992154.99
I66: =E66-N66 -> 0 | J66: =N66-Q66 -> 0 | K66: =Q66-T66 -> 0 | L66: =T66 -> 0
C67: Financial expenses (income) | E67: =SUMIF(TB!$J$2:$J$121,C67,TB!$F$2:$F$121) -> -335376.1 | F67: =SUMIF(TB!$J$2:$J$121,C67,TB!$I$2:$I$121) -> -20877.18 | I67: =E67-N67 -> 291163.12 | J67: =N67-Q67 -> -136348.55 | K67: =Q67-T67 -> -165717 | L67: =T67 -> -324473.67 | N67: -626539.22 | O67: -19487.86 | Q67: -490190.67 | R67: -49482.2 | T67: -324473.67 | U67: -61382.4 | W67: 216071.21 | X67: 90620.989 | Z67: -43293.01 | AA67: 15192.84
I68: =E68-N68 -> 0 | J68: =N68-Q68 -> 0 | K68: =Q68-T68 -> 0 | L68: =T68 -> 0
B69: Income (loss) before taxes | E69: =E23-E65-E67 -> -8846827.3 | F69: =F23-F65-F67 -> -2488658.8 | I69: =E69-N69 -> -4161894 | J69: =N69-Q69 -> -1578553.7 | K69: =Q69-T69 -> -1450431.6 | L69: =T69 -> -1655948 | N69: -4684933.2 | O69: -1427676.1 | Q69: -3106379.5 | R69: -945293.86 | T69: -1655948 | U69: -492606.63 | W69: -11943176 | X69: -3518120.1 | Z69: -3114264.4 | AA69: -1007347.8
I70: =E70-N70 -> 0 | J70: =N70-Q70 -> 0 | K70: =Q70-T70 -> 0 | L70: =T70 -> 0
B71: Tax expenses (income) | E71: =SUMIF(TB!$J$2:$J$121,C71,TB!$F$2:$F$121) -> 0 | F71: =SUMIF(TB!$J$2:$J$121,C71,TB!$I$2:$I$121) -> 0 | I71: =E71-N71 -> 0 | J71: =N71-Q71 -> 0 | K71: =Q71-T71 -> 0 | L71: =T71 -> 0 | N71: 0 | O71: 0 | Q71: 0 | R71: 0 | T71: 0 | U71: 0 | W71: 0 | X71: 0 | Z71: 0 | AA71: 0
I72: =E72-N72 -> 0 | J72: =N72-Q72 -> 0 | K72: =Q72-T72 -> 0 | L72: =T72 -> 0
B73: Net Income (loss) | E73: =E69-E71 -> -8846827.3 | F73: =F69-F71 -> -2488658.8 | I73: =E73-N73 -> -4161894 | J73: =N73-Q73 -> -1578553.7 | K73: =Q73-T73 -> -1450431.6 | L73: =T73 -> -1655948 | N73: -4684933.2 | O73: -1427676.1 | Q73: -3106379.5 | R73: -945293.86 | T73: -1655948 | U73: -492606.63 | W73: -11943176 | X73: -3518120.1 | Z73: -3114264.4 | AA73: -1007347.8
I74: =E74-N74 -> 0 | J74: =N74-Q74 -> 0 | K74: =Q74-T74 -> 0 | L74: =T74 -> 0
I75: =E75-N75 -> 0 | J75: =N75-Q75 -> 0 | K75: =Q75-T75 -> 0 | L75: =T75 -> 0
B76: EBITDA | E76: =E23-E65+E61 -> -9100727.4 | F76: =F23-F65+F61 -> -2484756 | I76: =E76-N76 -> -3789254.9 | J76: =N76-Q76 -> -1714902.3 | K76: =Q76-T76 -> -1616148.6 | L76: =T76 -> -1980421.6 | N76: -5311472.5 | O76: -1447164 | Q76: -3596570.2 | R76: -994776.06 | T76: -1980421.6 | U76: -553989.03 | W76: -11656997 | X76: -3405672.1 | Z76: -3157557.4 | AA76: -992154.99
B79: Notes
B81: (1) | C81: The above mentioned P&L is based on unaudited ledger
B86: Average Expenses for mont in the peroid | F86: =(F69+F67)/12 -> -209128 | I86: =(I69+I67)/3/3.6 -> -358401.01 | J86: =(J69+J67)/3/3.6 -> -158787.25 | K86: =(K69+K67)/3/3.6 -> -149643.39 | L86: =(L69+L67)/3/3.6 -> -183372.37 | O86: -160796 | R86: -165796.01 | X86: -569671.49 | AA86: -110239.44

Sheet TB
A1: סעיף; | B1: חשבון | C1: תאור החשבון | D1: יתרה בשקלים | E1: AJE | F1: Total NIS | G1: יתרה בדולרים | H1: AJE | I1: Total USD
A2: ="100.מזומנים ושווי מזומנים" -> 100.מזומנים ושווי מזומנים | B2: 1000 | C2: ="בנק לאומי שח 864/01880046" -> בנק לאומי שח 864/01880046 | D2: =VLOOKUP(B2,[1]DataSheet!$E$2:$H$112,3,0) -> 130855.81 | E2: =SUMIF(AJE!$B$8:$B$36,B2,AJE!$D$8:$D$36)-SUMIF(AJE!$G$8:$G$36,B2,AJE!$I$8:$I$36) -> 0 | F2: =D2+E2 -> 130855.81 | G2: =VLOOKUP(B2,[1]DataSheet!$E$2:$H$112,4,0) -> 36078.25 | H2: =SUMIF(AJE!$B$8:$B$36,B2,AJE!$E$8:$E$36)-SUMIF(AJE!$G$8:$G$36,B2,AJE!$J$8:$J$36) -> 0 | I2: =G2+H2 -> 36078.25 | J2: Cash and cash equivalents | K2: =D2/G2 -> 3.6269999 | L2: מתאים לבנק
A3: ="100.מזומנים ושווי מזומנים" -> 100.מזומנים ושווי מזומנים | B3: 1001 | C3: ="בנק לאומי 864/01880046 $$" -> בנק לאומי 864/01880046 $$ | D3: =VLOOKUP(B3,[1]DataSheet!$E$2:$H$112,3,0) -> 1019378.2 | E3: =SUMIF(AJE!$B$8:$B$36,B3,AJE!$D$8:$D$36)-SUMIF(AJE!$G$8:$G$36,B3,AJE!$I$8:$I$36) -> 0 | F3: =D3+E3 -> 1019378.2 | G3: =VLOOKUP(B3,[1]DataSheet!$E$2:$H$112,4,0) -> 281052.72 | H3: =SUMIF(AJE!$B$8:$B$36,B3,AJE!$E$8:$E$36)-SUMIF(AJE!$G$8:$G$36,B3,AJE!$J$8:$J$36) -> 0 | I3: =G3+H3 -> 281052.72 | J3: Cash and cash equivalents | K3: =F3/I3 -> 3.627 | L3: מתאים לבנק
A4: ="100.מזומנים ושווי מזומנים" -> 100.מזומנים ושווי מזומנים | B4: 1003 | C4: ="כ""א ויזה 9519 ש""ח" -> כ"א ויזה 9519 ש"ח | D4: =VLOOKUP(B4,[1]DataSheet!$E$2:$H$112,3,0) -> -15738.04 | E4: =SUMIF(AJE!$B$8:$B$36,B4,AJE!$D$8:$D$36)-SUMIF(AJE!$G$8:$G$36,B4,AJE!$I$8:$I$36) -> 0 | F4: =D4+E4 -> -15738.04 | G4: =VLOOKUP(B4,[1]DataSheet!$E$2:$H$112,4,0) -> -4339.13 | H4: =SUMIF(AJE!$B$8:$B$36,B4,AJE!$E$8:$E$36)-SUMIF(AJE!$G$8:$G$36,B4,AJE!$J$8:$J$36) -> 0 | I4: =G4+H4 -> -4339.13 | J4: Accounts payable | K4: =D4/G4 -> 3.6270036
A5: ="100.מזומנים ושווי מזומנים" -> 100.מזומנים ושווי מזומנים | B5: 1004 | C5: ="כ""א ויזה 9311 ש""ח" -> כ"א ויזה 9311 ש"ח | D5: =VLOOKUP(B5,[1]DataSheet!$E$2:$H$112,3,0) -> -2121.21 | E5: =SUMIF(AJE!$B$8:$B$36,B5,AJE!$D$8:$D$36)-SUMIF(AJE!$G$8:$G$36,B5,AJE!$I$8:$I$36) -> 0 | F5: =D5+E5 -> -2121.21 | G5: =VLOOKUP(B5,[1]DataSheet!$E$2:$H$112,4,0) -> -584.84 | H5: =SUMIF(AJE!$B$8:$B$36,B5,AJE!$E$8:$E$36)-SUMIF(AJE!$G$8:$G$36,B5,AJE!$J$8:$J$36) -> 0 | I5: =G5+H5 -> -584.84 | J5: Accounts payable | K5: =D5/G5 -> 3.626992
A6: ="100.מזומנים ושווי מזומנים" -> 100.מזומנים ושווי מזומנים | B6: 1005 | C6: ="כ""א ויזה 7413 ש""ח" -> כ"א ויזה 7413 ש"ח | D6: =VLOOKUP(B6,[1]DataSheet!$E$2:$H$112,3,0) -> -664.38 | E6: =SUMIF(AJE!$B$8:$B$36,B6,AJE!$D$8:$D$36)-SUMIF(AJE!$G$8:$G$36,B6,AJE!$I$8:$I$36) -> 0 | F6: =D6+E6 -> -664.38 | G6: =VLOOKUP(B6,[1]DataSheet!$E$2:$H$112,4,0) -> -183.18 | H6: =SUMIF(AJE!$B$8:$B$36,B6,AJE!$E$8:$E$36)-SUMIF(AJE!$G$8:$G$36,B6,AJE!$J$8:$J$36) -> 0 | I6: =G6+H6 -> -183.18 | J6: Accounts payable | K6: =D6/G6 -> 3.6269243
A7: ="100.מזומנים ושווי מזומנים" -> 100.מזומנים ושווי מזומנים | B7: 1006 | C7: ="בנק לאומי GBP 864/01880046" -> בנק לאומי GBP 864/01880046 | D7: =VLOOKUP(B7,[1]DataSheet!$E$2:$H$112,3,0) -> 0.42 | E7: =SUMIF(AJE!$B$8:$B$36,B7,AJE!$D$8:$D$36)-SUMIF(AJE!$G$8:$G$36,B7,AJE!$I$8:$I$36) -> 0 | F7: =D7+E7 -> 0.42 | G7: =VLOOKUP(B7,[1]DataSheet!$E$2:$H$112,4,0) -> 0.11 | H7: =SUMIF(AJE!$B$8:$B$36,B7,AJE!$E$8:$E$36)-SUMIF(AJE!$G$8:$G$36,B7,AJE!$J$8:$J$36) -> 0 | I7: =G7+H7 -> 0.11 | J7: Cash and cash equivalents | K7: =D7/G7 -> 3.8181818 | L7: מתאים לבנק
A8: ="100.מזומנים ושווי מזומנים" -> 100.מזומנים ושווי מזומנים | B8: 1007 | C8: ="כ""א ויזה 7413 $" -> כ"א ויזה 7413 $ | D8: =VLOOKUP(B8,[1]DataSheet!$E$2:$H$112,3,0) -> -15236.05 | E8: =SUMIF(AJE!$B$8:$B$36,B8,AJE!$D$8:$D$36)-SUMIF(AJE!$G$8:$G$36,B8,AJE!$I$8:$I$36) -> 0 | F8: =D8+E8 -> -15236.05 | G8: =VLOOKUP(B8,[1]DataSheet!$E$2:$H$112,4,0) -> -4200.73 | H8: =SUMIF(AJE!$B$8:$B$36,B8,AJE!$E$8:$E$36)-SUMIF(AJE!$G$8:$G$36,B8,AJE!$J$8:$J$36) -> 0 | I8: =G8+H8 -> -4200.73 | J8: Accounts payable | K8: =D8/G8 -> 3.6270005
B9: 1008 | C9: כ"א ויזה 9519 $ | D9: =VLOOKUP(B9,[1]DataSheet!$E$2:$H$112,3,0) -> -18669.98 | E9: =SUMIF(AJE!$B$8:$B$36,B9,AJE!$D$8:$D$36)-SUMIF(AJE!$G$8:$G$36,B9,AJE!$I$8:$I$36) -> 0 | F9: =D9+E9 -> -18669.98 | G9: =VLOOKUP(B9,[1]DataSheet!$E$2:$H$112,4,0) -> -5147.5 | H9: =SUMIF(AJE!$B$8:$B$36,B9,AJE!$E$8:$E$36)-SUMIF(AJE!$G$8:$G$36,B9,AJE!$J$8:$J$36) -> 0 | I9: =G9+H9 -> -5147.5 | J9: Accounts payable | K9: =D9/G9 -> 3.6269995
A10: ="100.מזומנים ושווי מזומנים" -> 100.מזומנים ושווי מזומנים | B10: 1011 | C10: ="פקדון בנק לאומי פק""מ" -> פקדון בנק לאומי פק"מ | D10: =VLOOKUP(B10,[1]DataSheet!$E$2:$H$112,3,0) -> 145977.02 | E10: =SUMIF(AJE!$B$8:$B$36,B10,AJE!$D$8:$D$36)-SUMIF(AJE!$G$8:$G$36,B10,AJE!$I$8:$I$36) -> 0 | F10: =D10+E10 -> 145977.02 | G10: =VLOOKUP(B10,[1]DataSheet!$E$2:$H$112,4,0) -> 40247.32 | H10: =SUMIF(AJE!$B$8:$B$36,B10,AJE!$E$8:$E$36)-SUMIF(AJE!$G$8:$G$36,B10,AJE!$J$8:$J$36) -> 0 | I10: =G10+H10 -> 40247.32 | J10: Restricted cash | K10: =D10/G10 -> 3.6269998 | L10: מתאים לבנק
B11: 1012 | C11: פקדון בנק לאומי $$ | D11: =VLOOKUP(B11,[1]DataSheet!$E$2:$H$112,3,0) -> 1648707.1 | E11: =SUMIF(AJE!$B$8:$B$36,B11,AJE!$D$8:$D$36)-SUMIF(AJE!$G$8:$G$36,B11,AJE!$I$8:$I$36) -> 0 | F11: =D11+E11 -> 1648707.1 | G11: =VLOOKUP(B11,[1]DataSheet!$E$2:$H$112,4,0) -> 454564.97 | H11: =SUMIF(AJE!$B$8:$B$36,B11,AJE!$E$8:$E$36)-SUMIF(AJE!$G$8:$G$36,B11,AJE!$J$8:$J$36) -> 0 | I11: =G11+H11 -> 454564.97 | J11: Cash and cash equivalents | K11: =D11/G11 -> 3.627 | L11: הוכנס ב 31/10 נפרע ב 31/1/24
B12: 1701 | C12: מראש | D12: =VLOOKUP(B12,[1]DataSheet!$E$2:$H$112,3,0) -> 100360.02 | E12: =SUMIF(AJE!$B$8:$B$36,B12,AJE!$D$8:$D$36)-SUMIF(AJE!$G$8:$G$36,B12,AJE!$I$8:$I$36) -> 0 | F12: =D12+E12 -> 100360.02 | G12: =VLOOKUP(B12,[1]DataSheet!$E$2:$H$112,4,0) -> 27670.25 | H12: =SUMIF(AJE!$B$8:$B$36,B12,AJE!$E$8:$E$36)-SUMIF(AJE!$G$8:$G$36,B12,AJE!$J$8:$J$36) -> 0 | I12: =G12+H12 -> 27670.25 | J12: Other current assets | L12: נייר פרוט
A13: ="150.עלות" -> 150.עלות | B13: 1500 | C13: ="מחשבים ותוכנות" -> מחשבים ותוכנות | D13: =VLOOKUP(B13,[1]DataSheet!$E$2:$H$112,3,0) -> 200238.09 | E13: =SUMIF(AJE!$B$8:$B$36,B13,AJE!$D$8:$D$36)-SUMIF(AJE!$G$8:$G$36,B13,AJE!$I$8:$I$36) -> 0 | F13: =D13+E13 -> 200238.09 | G13: =VLOOKUP(B13,[1]DataSheet!$E$2:$H$112,4,0) -> 60215.91 | H13: =SUMIF(AJE!$B$8:$B$36,B13,AJE!$E$8:$E$36)-SUMIF(AJE!$G$8:$G$36,B13,AJE!$J$8:$J$36) -> 0 | I13: =G13+H13 -> 60215.91 | J13: Property and Equipment, Net | K13: =D13/G13 -> 3.3253353 | L13: טופס פחת
A14: ="150.עלות" -> 150.עלות | B14: 1501 | C14: ="ריהוט וציוד" -> ריהוט וציוד | D14: =VLOOKUP(B14,[1]DataSheet!$E$2:$H$112,3,0) -> 152525.54 | E14: =SUMIF(AJE!$B$8:$B$36,B14,AJE!$D$8:$D$36)-SUMIF(AJE!$G$8:$G$36,B14,AJE!$I$8:$I$36) -> 0 | F14: =D14+E14 -> 152525.54 | G14: =VLOOKUP(B14,[1]DataSheet!$E$2:$H$112,4,0) -> 46915.77 | H14: =SUMIF(AJE!$B$8:$B$36,B14,AJE!$E$8:$E$36)-SUMIF(AJE!$G$8:$G$36,B14,AJE!$J$8:$J$36) -> 0 | I14: =G14+H14 -> 46915.77 | J14: Property and Equipment, Net | K14: =D14/G14 -> 3.2510506 | L14: טופס פחת
A15: ="150.עלות" -> 150.עלות | B15: 1502 | C15: ="שיפורים במושכר" -> שיפורים במושכר | D15: =VLOOKUP(B15,[1]DataSheet!$E$2:$H$112,3,0) -> 113554.22 | E15: =SUMIF(AJE!$B$8:$B$36,B15,AJE!$D$8:$D$36)-SUMIF(AJE!$G$8:$G$36,B15,AJE!$I$8:$I$36) -> 0 | F15: =D15+E15 -> 113554.22 | G15: =VLOOKUP(B15,[1]DataSheet!$E$2:$H$112,4,0) -> 35016.34 | H15: =SUMIF(AJE!$B$8:$B$36,B15,AJE!$E$8:$E$36)-SUMIF(AJE!$G$8:$G$36,B15,AJE!$J$8:$J$36) -> 0 | I15: =G15+H15 -> 35016.34 | J15: Property and Equipment, Net | K15: =D15/G15 -> 3.2428923 | L15: טופס פחת
B16: 1550 | C16: פחת נצבר | D16: =VLOOKUP(B16,[1]DataSheet!$E$2:$H$112,3,0) -> -177419 | E16: =SUMIF(AJE!$B$8:$B$36,B16,AJE!$D$8:$D$36)-SUMIF(AJE!$G$8:$G$36,B16,AJE!$I$8:$I$36) -> 0 | F16: =D16+E16 -> -177419 | G16: =VLOOKUP(B16,[1]DataSheet!$E$2:$H$112,4,0) -> -54557 | H16: =SUMIF(AJE!$B$8:$B$36,B16,AJE!$E$8:$E$36)-SUMIF(AJE!$G$8:$G$36,B16,AJE!$J$8:$J$36) -> 0 | I16: =G16+H16 -> -54557 | J16: Property and Equipment, Net | K16: =D16/G16 -> 3.2519933 | L16: טופס פחת
A17: ="250.מע'מ חו'ז" -> 250.מע'מ חו'ז | B17: 2500 | C17: ="מע'מ חו'ז" -> מע'מ חו'ז | D17: =VLOOKUP(B17,[1]DataSheet!$E$2:$H$112,3,0) -> 61128.31 | E17: =SUMIF(AJE!$B$8:$B$36,B17,AJE!$D$8:$D$36)-SUMIF(AJE!$G$8:$G$36,B17,AJE!$I$8:$I$36) -> 0 | F17: =D17+E17 -> 61128.31 | G17: =VLOOKUP(B17,[1]DataSheet!$E$2:$H$112,4,0) -> 16853.68 | H17: =SUMIF(AJE!$B$8:$B$36,B17,AJE!$E$8:$E$36)-SUMIF(AJE!$G$8:$G$36,B17,AJE!$J$8:$J$36) -> 0 | I17: =G17+H17 -> 16853.68 | J17: Account Receivable-VAT+TAX | K17: =D17/G17 -> 3.6270007
A18: ="250.מע'מ חו'ז" -> 250.מע'מ חו'ז | B18: 2502 | C18: ="מע'מ תשומות" -> מע'מ תשומות | D18: =VLOOKUP(B18,[1]DataSheet!$E$2:$H$112,3,0) -> 2237.45 | E18: =SUMIF(AJE!$B$8:$B$36,B18,AJE!$D$8:$D$36)-SUMIF(AJE!$G$8:$G$36,B18,AJE!$I$8:$I$36) -> 0 | F18: =D18+E18 -> 2237.45 | G18: =VLOOKUP(B18,[1]DataSheet!$E$2:$H$112,4,0) -> 616.89 | H18: =SUMIF(AJE!$B$8:$B$36,B18,AJE!$E$8:$E$36)-SUMIF(AJE!$G$8:$G$36,B18,AJE!$J$8:$J$36) -> 0 | I18: =G18+H18 -> 616.89 | J18: Account Receivable-VAT+TAX | K18: =D18/G18 -> 3.6269837
A19: ="250.מע'מ חו'ז" -> 250.מע'מ חו'ז | B19: 2503 | C19: ="מע'מ תשומות לנכסים" -> מע'מ תשומות לנכסים | E19: =SUMIF(AJE!$B$8:$B$36,B19,AJE!$D$8:$D$36)-SUMIF(AJE!$G$8:$G$36,B19,AJE!$I$8:$I$36) -> 0 | F19: =D19+E19 -> 0 | H19: =SUMIF(AJE!$B$8:$B$36,B19,AJE!$E$8:$E$36)-SUMIF(AJE!$G$8:$G$36,B19,AJE!$J$8:$J$36) -> 0 | I19: =G19+H19 -> 0 | J19: Account Receivable-VAT+TAX | K19: =D19/G19 -> #DIV/0!
B20: 2610 | C20: עודפות 2021 | D20: =VLOOKUP(B20,[1]DataSheet!$E$2:$H$112,3,0) -> 7038 | E20: =SUMIF(AJE!$B$8:$B$36,B20,AJE!$D$8:$D$36)-SUMIF(AJE!$G$8:$G$36,B20,AJE!$I$8:$I$36) -> 0 | F20: =D20+E20 -> 7038 | G20: =VLOOKUP(B20,[1]DataSheet!$E$2:$H$112,4,0) -> 1940.45 | H20: =SUMIF(AJE!$B$8:$B$36,B20,AJE!$E$8:$E$36)-SUMIF(AJE!$G$8:$G$36,B20,AJE!$J$8:$J$36) -> 0 | I20: =G20+H20 -> 1940.45 | J20: Account Receivable-VAT+TAX | K20: =D20/G20 -> 3.6269937
B21: 2611 | C21: עודפות 2022 | D21: =VLOOKUP(B21,[1]DataSheet!$E$2:$H$112,3,0) -> 41031 | E21: =SUMIF(AJE!$B$8:$B$36,B21,AJE!$D$8:$D$36)-SUMIF(AJE!$G$8:$G$36,B21,AJE!$I$8:$I$36) -> 0 | F21: =D21+E21 -> 41031 | G21: =VLOOKUP(B21,[1]DataSheet!$E$2:$H$112,4,0) -> 11312.66 | H21: =SUMIF(AJE!$B$8:$B$36,B21,AJE!$E$8:$E$36)-SUMIF(AJE!$G$8:$G$36,B21,AJE!$J$8:$J$36) -> 0 | I21: =G21+H21 -> 11312.66 | J21: Account Receivable-VAT+TAX
B22: 2701 | C22: לשלם | E22: =SUMIF(AJE!$B$8:$B$36,B22,AJE!$D$8:$D$36)-SUMIF(AJE!$G$8:$G$36,B22,AJE!$I$8:$I$36) -> -32627.41 | F22: =D22+E22 -> -32627.41 | H22: =SUMIF(AJE!$B$8:$B$36,B22,AJE!$E$8:$E$36)-SUMIF(AJE!$G$8:$G$36,B22,AJE!$J$8:$J$36) -> -8995.7018 | I22: =G22+H22 -> -8995.7018 | J22: Accrued expenses | L22: פרוט בפקודת יומן גיליון AJE , חסר לי הפרשה ל EY
A23: ="280.צדדים קשורים" -> 280.צדדים קשורים | B23: 2801 | C23: ="GETCTRL INC חו""ז" -> GETCTRL INC חו"ז | D23: =VLOOKUP(B23,[1]DataSheet!$E$2:$H$112,3,0) -> -5156583.3 | E23: =SUMIF(AJE!$B$8:$B$36,B23,AJE!$D$8:$D$36)-SUMIF(AJE!$G$8:$G$36,B23,AJE!$I$8:$I$36) -> 0 | F23: =D23+E23 -> -5156583.3 | G23: =VLOOKUP(B23,[1]DataSheet!$E$2:$H$112,4,0) -> -1434999.3 | H23: =SUMIF(AJE!$B$8:$B$36,B23,AJE!$E$8:$E$36)-SUMIF(AJE!$G$8:$G$36,B23,AJE!$J$8:$J$36) -> 0 | I23: =G23+H23 -> -1434999.3 | J23: Related party | K23: =D23/G23 -> 3.5934395
B24: 2803 | C24: UK Getctrl LTD | D24: =VLOOKUP(B24,[1]DataSheet!$E$2:$H$112,3,0) -> 2360100 | E24: =SUMIF(AJE!$B$8:$B$36,B24,AJE!$D$8:$D$36)-SUMIF(AJE!$G$8:$G$36,B24,AJE!$I$8:$I$36) -> -2711172.1 | F24: =D24+E24 -> -351072.18 | G24: =VLOOKUP(B24,[1]DataSheet!$E$2:$H$112,4,0) -> 650703.05 | H24: =SUMIF(AJE!$B$8:$B$36,B24,AJE!$E$8:$E$36)-SUMIF(AJE!$G$8:$G$36,B24,AJE!$J$8:$J$36) -> -750646.81 | I24: =G24+H24 -> -99943.758 | J24: Related party | K24: =D24/G24 -> 3.627 | L24: היתרה בלישט | M24: -164258 | N24: מתאים לספרי אנגליה
B25: 2804 | C25: שטר הון USA GETCTRL | D25: =VLOOKUP(B25,[1]DataSheet!$E$2:$H$112,3,0) -> -22281920 | E25: =SUMIF(AJE!$B$8:$B$36,B25,AJE!$D$8:$D$36)-SUMIF(AJE!$G$8:$G$36,B25,AJE!$I$8:$I$36) -> 0 | F25: =D25+E25 -> -22281920 | G25: =VLOOKUP(B25,[1]DataSheet!$E$2:$H$112,4,0) -> -6600000 | H25: =SUMIF(AJE!$B$8:$B$36,B25,AJE!$E$8:$E$36)-SUMIF(AJE!$G$8:$G$36,B25,AJE!$J$8:$J$36) -> 0 | I25: =G25+H25 -> -6600000 | J25: Capital note | L25: ללא תזוזה משנה שעברה
B26: 1704 | C26: נכס בגין תקן שכירות | D26: =VLOOKUP(B26,[1]DataSheet!$E$2:$H$112,3,0) -> 563565 | E26: =SUMIF(AJE!$B$8:$B$36,B26,AJE!$D$8:$D$36)-SUMIF(AJE!$G$8:$G$36,B26,AJE!$I$8:$I$36) -> 0 | F26: =D26+E26 -> 563565 | G26: =VLOOKUP(B26,[1]DataSheet!$E$2:$H$112,4,0) -> 160149.19 | H26: =SUMIF(AJE!$B$8:$B$36,B26,AJE!$E$8:$E$36)-SUMIF(AJE!$G$8:$G$36,B26,AJE!$J$8:$J$36) -> 0 | I26: =G26+H26 -> 160149.19 | J26: Other Long term Assets
B27: 2704 | C27: התחייבות בגין שכירות | D27: =VLOOKUP(B27,[1]DataSheet!$E$2:$H$112,3,0) -> -569697 | E27: =SUMIF(AJE!$B$8:$B$36,B27,AJE!$D$8:$D$36)-SUMIF(AJE!$G$8:$G$36,B27,AJE!$I$8:$I$36) -> 0 | F27: =D27+E27 -> -569697 | G27: =VLOOKUP(B27,[1]DataSheet!$E$2:$H$112,4,0) -> -161891.73 | H27: =SUMIF(AJE!$B$8:$B$36,B27,AJE!$E$8:$E$36)-SUMIF(AJE!$G$8:$G$36,B27,AJE!$J$8:$J$36) -> 0 | I27: =G27+H27 -> -161891.73 | J27: Other Long term liabilities
A28: ="300.ספקים" -> 300.ספקים | B28: 3003 | C28: ="סודקסו פאס ישראל בע""מ CIBUS" -> סודקסו פאס ישראל בע"מ CIBUS | D28: =VLOOKUP(B28,[1]DataSheet!$E$2:$H$112,3,0) -> -6571 | E28: =SUMIF(AJE!$B$8:$B$36,B28,AJE!$D$8:$D$36)-SUMIF(AJE!$G$8:$G$36,B28,AJE!$I$8:$I$36) -> 0 | F28: =D28+E28 -> -6571 | G28: =VLOOKUP(B28,[1]DataSheet!$E$2:$H$112,4,0) -> -1811.69 | H28: =SUMIF(AJE!$B$8:$B$36,B28,AJE!$E$8:$E$36)-SUMIF(AJE!$G$8:$G$36,B28,AJE!$J$8:$J$36) -> 0 | I28: =G28+H28 -> -1811.69 | J28: Accounts payable | K28: =D28/G28 -> 3.6270002
A29: ="300.ספקים" -> 300.ספקים | B29: 3017 | C29: ="תכן חברה כלכלית של הקיבוץ הארצי בע""מ" -> תכן חברה כלכלית של הקיבוץ הארצי בע"מ | D29: =VLOOKUP(B29,[1]DataSheet!$E$2:$H$112,3,0) -> -5868 | E29: =SUMIF(AJE!$B$8:$B$36,B29,AJE!$D$8:$D$36)-SUMIF(AJE!$G$8:$G$36,B29,AJE!$I$8:$I$36) -> 0 | F29: =D29+E29 -> -5868 | G29: =VLOOKUP(B29,[1]DataSheet!$E$2:$H$112,4,0) -> -1617.87 | H29: =SUMIF(AJE!$B$8:$B$36,B29,AJE!$E$8:$E$36)-SUMIF(AJE!$G$8:$G$36,B29,AJE!$J$8:$J$36) -> 0 | I29: =G29+H29 -> -1617.87 | J29: Accounts payable | K29: =D29/G29 -> 3.626991
A30: ="300.ספקים" -> 300.ספקים | B30: 3026 | C30: ="נ.פ.א סוכנות לביטוח (2001) בע""מ" -> נ.פ.א סוכנות לביטוח (2001) בע"מ | D30: =VLOOKUP(B30,[1]DataSheet!$E$2:$H$112,3,0) -> -350 | E30: =SUMIF(AJE!$B$8:$B$36,B30,AJE!$D$8:$D$36)-SUMIF(AJE!$G$8:$G$36,B30,AJE!$I$8:$I$36) -> 0 | F30: =D30+E30 -> -350 | G30: =VLOOKUP(B30,[1]DataSheet!$E$2:$H$112,4,0) -> -96.5 | H30: =SUMIF(AJE!$B$8:$B$36,B30,AJE!$E$8:$E$36)-SUMIF(AJE!$G$8:$G$36,B30,AJE!$J$8:$J$36) -> 0 | I30: =G30+H30 -> -96.5 | J30: Accounts payable | K30: =D30/G30 -> 3.626943
A31: ="305.ספקים חו""ל" -> 305.ספקים חו"ל | B31: 3120 | C31: ="GOOGLE" -> GOOGLE | D31: =VLOOKUP(B31,[1]DataSheet!$E$2:$H$112,3,0) -> -25.82 | E31: =SUMIF(AJE!$B$8:$B$36,B31,AJE!$D$8:$D$36)-SUMIF(AJE!$G$8:$G$36,B31,AJE!$I$8:$I$36) -> 0 | F31: =D31+E31 -> -25.82 | G31: =VLOOKUP(B31,[1]DataSheet!$E$2:$H$112,4,0) -> -7.12 | H31: =SUMIF(AJE!$B$8:$B$36,B31,AJE!$E$8:$E$36)-SUMIF(AJE!$G$8:$G$36,B31,AJE!$J$8:$J$36) -> 0 | I31: =G31+H31 -> -7.12 | J31: Accounts payable | K31: =D31/G31 -> 3.6264045
B32: 3099 | C32: אוטומט איט מלם תים בע"מ | D32: =VLOOKUP(B32,[1]DataSheet!$E$2:$H$112,3,0) -> 15461.12 | E32: =SUMIF(AJE!$B$8:$B$36,B32,AJE!$D$8:$D$36)-SUMIF(AJE!$G$8:$G$36,B32,AJE!$I$8:$I$36) -> -15461.12 | F32: =D32+E32 -> 0 | G32: =VLOOKUP(B32,[1]DataSheet!$E$2:$H$112,4,0) -> 4262.78 | H32: =SUMIF(AJE!$B$8:$B$36,B32,AJE!$E$8:$E$36)-SUMIF(AJE!$G$8:$G$36,B32,AJE!$J$8:$J$36) -> -4262.7847 | I32: =G32+H32 -> -0.0046705266 | J32: Accounts payable | K32: =D32/G32 -> 3.627004
B33: 3180 | C33: FullStory,Inc. | D33: =VLOOKUP(B33,[1]DataSheet!$E$2:$H$112,3,0) -> -27933.99 | E33: =SUMIF(AJE!$B$8:$B$36,B33,AJE!$D$8:$D$36)-SUMIF(AJE!$G$8:$G$36,B33,AJE!$I$8:$I$36) -> 0 | F33: =D33+E33 -> -27933.99 | G33: =VLOOKUP(B33,[1]DataSheet!$E$2:$H$112,4,0) -> -7701.68 | H33: =SUMIF(AJE!$B$8:$B$36,B33,AJE!$E$8:$E$36)-SUMIF(AJE!$G$8:$G$36,B33,AJE!$J$8:$J$36) -> 0 | I33: =G33+H33 -> -7701.68 | J33: Accounts payable | K33: =D33/G33 -> 3.6269996
B34: 3245 | C34: LinkedIN -ש"ח | D34: =VLOOKUP(B34,[1]DataSheet!$E$2:$H$112,3,0) -> 7273.84 | E34: =SUMIF(AJE!$B$8:$B$36,B34,AJE!$D$8:$D$36)-SUMIF(AJE!$G$8:$G$36,B34,AJE!$I$8:$I$36) -> -7273.84 | F34: =D34+E34 -> 0 | G34: =VLOOKUP(B34,[1]DataSheet!$E$2:$H$112,4,0) -> 2005.47 | H34: =SUMIF(AJE!$B$8:$B$36,B34,AJE!$E$8:$E$36)-SUMIF(AJE!$G$8:$G$36,B34,AJE!$J$8:$J$36) -> -2005.4701 | I34: =G34+H34 -> -8.5470086e-05 | J34: Accounts payable | K34: =D34/G34 -> 3.6270002
B35: 3016 | C35: GETT ג'יטי גטאקסי | D35: =VLOOKUP(B35,[1]DataSheet!$E$2:$H$112,3,0) -> -125 | E35: =SUMIF(AJE!$B$8:$B$36,B35,AJE!$D$8:$D$36)-SUMIF(AJE!$G$8:$G$36,B35,AJE!$I$8:$I$36) -> 0 | F35: =D35+E35 -> -125 | G35: =VLOOKUP(B35,[1]DataSheet!$E$2:$H$112,4,0) -> -34.46 | H35: =SUMIF(AJE!$B$8:$B$36,B35,AJE!$E$8:$E$36)-SUMIF(AJE!$G$8:$G$36,B35,AJE!$J$8:$J$36) -> 0 | I35: =G35+H35 -> -34.46 | J35: Accounts payable | K35: =D35/G35 -> 3.6273941
B36: 3139 | C36: Amazon.co.UK | D36: =VLOOKUP(B36,[1]DataSheet!$E$2:$H$112,3,0) -> 1669.21 | E36: =SUMIF(AJE!$B$8:$B$36,B36,AJE!$D$8:$D$36)-SUMIF(AJE!$G$8:$G$36,B36,AJE!$I$8:$I$36) -> -1669.21 | F36: =D36+E36 -> 0 | G36: =VLOOKUP(B36,[1]DataSheet!$E$2:$H$112,4,0) -> 460.22 | H36: =SUMIF(AJE!$B$8:$B$36,B36,AJE!$E$8:$E$36)-SUMIF(AJE!$G$8:$G$36,B36,AJE!$J$8:$J$36) -> -460.21781 | I36: =G36+H36 -> 0.002189137 | J36: Accounts payable | K36: =D36/G36 -> 3.6269827
B37: 3191 | C37: GBP-SKYPE.COM/GO/BILL Luxembourg | D37: =VLOOKUP(B37,[1]DataSheet!$E$2:$H$112,3,0) -> -10.63 | E37: =SUMIF(AJE!$B$8:$B$36,B37,AJE!$D$8:$D$36)-SUMIF(AJE!$G$8:$G$36,B37,AJE!$I$8:$I$36) -> 0 | F37: =D37+E37 -> -10.63 | G37: =VLOOKUP(B37,[1]DataSheet!$E$2:$H$112,4,0) -> -2.93 | H37: =SUMIF(AJE!$B$8:$B$36,B37,AJE!$E$8:$E$36)-SUMIF(AJE!$G$8:$G$36,B37,AJE!$J$8:$J$36) -> 0 | I37: =G37+H37 -> -2.93 | J37: Accounts payable | K37: =D37/G37 -> 3.6279863
B38: 3277 | C38: HubSpot Ireland Ltd | D38: =VLOOKUP(B38,[1]DataSheet!$E$2:$H$112,3,0) -> 1813.5 | E38: =SUMIF(AJE!$B$8:$B$36,B38,AJE!$D$8:$D$36)-SUMIF(AJE!$G$8:$G$36,B38,AJE!$I$8:$I$36) -> -1813.5 | F38: =D38+E38 -> 0 | G38: =VLOOKUP(B38,[1]DataSheet!$E$2:$H$112,4,0) -> 500 | H38: =SUMIF(AJE!$B$8:$B$36,B38,AJE!$E$8:$E$36)-SUMIF(AJE!$G$8:$G$36,B38,AJE!$J$8:$J$36) -> -500 | I38: =G38+H38 -> 0 | J38: Accounts payable | K38: =D38/G38 -> 3.627
B39: 3302 | C39: Nickolay Ribal | D39: =VLOOKUP(B39,[1]DataSheet!$E$2:$H$112,3,0) -> -37478.08 | E39: =SUMIF(AJE!$B$8:$B$36,B39,AJE!$D$8:$D$36)-SUMIF(AJE!$G$8:$G$36,B39,AJE!$I$8:$I$36) -> 0 | F39: =D39+E39 -> -37478.08 | G39: =VLOOKUP(B39,[1]DataSheet!$E$2:$H$112,4,0) -> -10333.08 | H39: =SUMIF(AJE!$B$8:$B$36,B39,AJE!$E$8:$E$36)-SUMIF(AJE!$G$8:$G$36,B39,AJE!$J$8:$J$36) -> 0 | I39: =G39+H39 -> -10333.08 | J39: Accounts payable | K39: =D39/G39 -> 3.6269999
B40: 3303 | C40: Tricentis | D40: =VLOOKUP(B40,[1]DataSheet!$E$2:$H$112,3,0) -> -25362.16 | E40: =SUMIF(AJE!$B$8:$B$36,B40,AJE!$D$8:$D$36)-SUMIF(AJE!$G$8:$G$36,B40,AJE!$I$8:$I$36) -> 0 | F40: =D40+E40 -> -25362.16 | G40: =VLOOKUP(B40,[1]DataSheet!$E$2:$H$112,4,0) -> -6992.6 | H40: =SUMIF(AJE!$B$8:$B$36,B40,AJE!$E$8:$E$36)-SUMIF(AJE!$G$8:$G$36,B40,AJE!$J$8:$J$36) -> 0 | I40: =G40+H40 -> -6992.6 | J40: Accounts payable | K40: =D40/G40 -> 3.627
B41: 3109 | C41: PRODUCTBOARD, INC | D41: =VLOOKUP(B41,[1]DataSheet!$E$2:$H$112,3,0) -> 217.62 | E41: =SUMIF(AJE!$B$8:$B$36,B41,AJE!$D$8:$D$36)-SUMIF(AJE!$G$8:$G$36,B41,AJE!$I$8:$I$36) -> 0 | F41: =D41+E41 -> 217.62 | G41: =VLOOKUP(B41,[1]DataSheet!$E$2:$H$112,4,0) -> 60 | H41: =SUMIF(AJE!$B$8:$B$36,B41,AJE!$E$8:$E$36)-SUMIF(AJE!$G$8:$G$36,B41,AJE!$J$8:$J$36) -> 0 | I41: =G41+H41 -> 60 | J41: Accounts payable | K41: =D41/G41 -> 3.627
B42: 3110 | C42: LINKEDIN | D42: =VLOOKUP(B42,[1]DataSheet!$E$2:$H$112,3,0) -> 147034.74 | E42: =SUMIF(AJE!$B$8:$B$36,B42,AJE!$D$8:$D$36)-SUMIF(AJE!$G$8:$G$36,B42,AJE!$I$8:$I$36) -> -147034.74 | F42: =D42+E42 -> 0 | G42: =VLOOKUP(B42,[1]DataSheet!$E$2:$H$112,4,0) -> 40538.94 | H42: =SUMIF(AJE!$B$8:$B$36,B42,AJE!$E$8:$E$36)-SUMIF(AJE!$G$8:$G$36,B42,AJE!$J$8:$J$36) -> -40538.941 | I42: =G42+H42 -> -0.00127378 | J42: Accounts payable | K42: =D42/G42 -> 3.6270001
B43: 3125 | C43: ATLASSIAN | D43: =VLOOKUP(B43,[1]DataSheet!$E$2:$H$112,3,0) -> 906.75 | E43: =SUMIF(AJE!$B$8:$B$36,B43,AJE!$D$8:$D$36)-SUMIF(AJE!$G$8:$G$36,B43,AJE!$I$8:$I$36) -> 0 | F43: =D43+E43 -> 906.75 | G43: =VLOOKUP(B43,[1]DataSheet!$E$2:$H$112,4,0) -> 250 | H43: =SUMIF(AJE!$B$8:$B$36,B43,AJE!$E$8:$E$36)-SUMIF(AJE!$G$8:$G$36,B43,AJE!$J$8:$J$36) -> 0 | I43: =G43+H43 -> 250 | J43: Accounts payable | K43: =D43/G43 -> 3.627
... B53: 3347 | C53: אייל אדרעי בע"מ | D53: =VLOOKUP(B53,[1]DataSheet!$E$2:$H$112,3,0) -> 210 | E53: =SUMIF(AJE!$B$8:$B$36,B53,AJE!$D$8:$D$36)-SUMIF(AJE!$G$8:$G$36,B53,AJE!$I$8:$I$36) -> 0 | F53: =D53+E53 -> 210 | G53: =VLOOKUP(B53,[1]DataSheet!$E$2:$H$112,4,0) -> 57.9 | H53: =SUMIF(AJE!$B$8:$B$36,B53,AJE!$E$8:$E$36)-SUMIF(AJE!$G$8:$G$36,B53,AJE!$J$8:$J$36) -> 0 | I53: =G53+H53 -> 57.9 | J53: Accounts payable | K53: =D53/G53 -> 3.626943
B54: 4000 | C54: הפרשה לחופשה והבראה | D54: =VLOOKUP(B54,[1]DataSheet!$E$2:$H$112,3,0) -> -119009 | E54: =SUMIF(AJE!$B$8:$B$36,B54,AJE!$D$8:$D$36)-SUMIF(AJE!$G$8:$G$36,B54,AJE!$I$8:$I$36) -> 0 | F54: =D54+E54 -> -119009 | G54: =VLOOKUP(B54,[1]DataSheet!$E$2:$H$112,4,0) -> -38156.88 | H54: =SUMIF(AJE!$B$8:$B$36,B54,AJE!$E$8:$E$36)-SUMIF(AJE!$G$8:$G$36,B54,AJE!$J$8:$J$36) -> 0 | I54: =G54+H54 -> -38156.88 | J54: Employee payables & institutions | K54: =D54/G54 -> 3.1189395 | L54: מתאים לנייר עבודה
A55: ="400.עובדים ומוסדות בגין שכר" -> 400.עובדים ומוסדות בגין שכר | B55: 4100 | C55: ="ביטוח לאומי" -> ביטוח לאומי | D55: =VLOOKUP(B55,[1]DataSheet!$E$2:$H$112,3,0) -> -27832.06 | E55: =SUMIF(AJE!$B$8:$B$36,B55,AJE!$D$8:$D$36)-SUMIF(AJE!$G$8:$G$36,B55,AJE!$I$8:$I$36) -> 0 | F55: =D55+E55 -> -27832.06 | G55: =VLOOKUP(B55,[1]DataSheet!$E$2:$H$112,4,0) -> -7673.58 | H55: =SUMIF(AJE!$B$8:$B$36,B55,AJE!$E$8:$E$36)-SUMIF(AJE!$G$8:$G$36,B55,AJE!$J$8:$J$36) -> 0 | I55: =G55+H55 -> -7673.58 | J55: Employee payables & institutions | K55: =D55/G55 -> 3.6269981 | L55: מתאים לפקודת שכר\ | O55: 4100 | P55: ="ביטוח לאומי" -> ביטוח לאומי | Q55: =D55 -> -27832.06 | R55: 27832 | S55: =Q55+R55 -> -0.06
A56: ="400.עובדים ומוסדות בגין שכר" -> 400.עובדים ומוסדות בגין שכר | B56: 4101 | C56: ="מס הכנסה עובדים" -> מס הכנסה עובדים | D56: =VLOOKUP(B56,[1]DataSheet!$E$2:$H$112,3,0) -> -30983 | E56: =SUMIF(AJE!$B$8:$B$36,B56,AJE!$D$8:$D$36)-SUMIF(AJE!$G$8:$G$36,B56,AJE!$I$8:$I$36) -> 0 | F56: =D56+E56 -> -30983 | G56: =VLOOKUP(B56,[1]DataSheet!$E$2:$H$112,4,0) -> -8542.32 | H56: =SUMIF(AJE!$B$8:$B$36,B56,AJE!$E$8:$E$36)-SUMIF(AJE!$G$8:$G$36,B56,AJE!$J$8:$J$36) -> 0 | I56: =G56+H56 -> -8542.32 | J56: Employee payables & institutions | K56: =D56/G56 -> 3.6270006 | L56: מתאים לפקודת שכר\ | O56: 4101 | P56: ="מס הכנסה עובדים" -> מס הכנסה עובדים | Q56: =D56 -> -30983 | R56: 30580 | S56: =Q56+R56 -> -403
A57: ="400.עובדים ומוסדות בגין שכר" -> 400.עובדים ומוסדות בגין שכר | B57: 4510 | C57: ="חו""ז קופות גמל עובדים" -> חו"ז קופות גמל עובדים | D57: =VLOOKUP(B57,[1]DataSheet!$E$2:$H$112,3,0) -> -47527.98 | E57: =SUMIF(AJE!$B$8:$B$36,B57,AJE!$D$8:$D$36)-SUMIF(AJE!$G$8:$G$36,B57,AJE!$I$8:$I$36) -> 0 | F57: =D57+E57 -> -47527.98 | G57: =VLOOKUP(B57,[1]DataSheet!$E$2:$H$112,4,0) -> -13103.94 | H57: =SUMIF(AJE!$B$8:$B$36,B57,AJE!$E$8:$E$36)-SUMIF(AJE!$G$8:$G$36,B57,AJE!$J$8:$J$36) -> 0 | I57: =G57+H57 -> -13103.94 | J57: Employee payables & institutions | K57: =D57/G57 -> 3.6269992 | L57: מתאים לפקודת שכר\ | O57: 4510 | P57: ="חו""ז קופות גמל עובדים" -> חו"ז קופות גמל עובדים | Q57: =D57 -> -47527.98 | R57: 47527.98 | S57: =Q57+R57 -> 0
A58: ="400.עובדים ומוסדות בגין שכר" -> 400.עובדים ומוסדות בגין שכר | B58: 5001 | C58: ="חו""ז עובדים" -> חו"ז עובדים | D58: =VLOOKUP(B58,[1]DataSheet!$E$2:$H$112,3,0) -> -94761.69 | E58: =SUMIF(AJE!$B$8:$B$36,B58,AJE!$D$8:$D$36)-SUMIF(AJE!$G$8:$G$36,B58,AJE!$I$8:$I$36) -> 0 | F58: =D58+E58 -> -94761.69 | G58: =VLOOKUP(B58,[1]DataSheet!$E$2:$H$112,4,0) -> -26126.74 | H58: =SUMIF(AJE!$B$8:$B$36,B58,AJE!$E$8:$E$36)-SUMIF(AJE!$G$8:$G$36,B58,AJE!$J$8:$J$36) -> 0 | I58: =G58+H58 -> -26126.74 | J58: Employee payables & institutions | K58: =D58/G58 -> 3.6270002 | L58: מתאים לפקודת שכר\ | O58: 5001 | P58: ="חו""ז עובדים" -> חו"ז עובדים | Q58: =D58 -> -94761.69 | R58: =44823.25+58045.84 -> 102869.09 | S58: =Q58+R58 -> 8107.4 | T58: בגין עובדת בשם יעל נמצאת בחופשת לידה | V58: =2255.8+2255.8+2246.8+1349 -> 8107.4
B59: 6100 | C59: יתרת רווח שנים קודמות | D59: =VLOOKUP(B59,[1]DataSheet!$E$2:$H$112,3,0) -> 16123543 | E59: =SUMIF(AJE!$B$8:$B$36,B59,AJE!$D$8:$D$36)-SUMIF(AJE!$G$8:$G$36,B59,AJE!$I$8:$I$36) -> 0 | F59: =D59+E59 -> 16123543 | G59: =VLOOKUP(B59,[1]DataSheet!$E$2:$H$112,4,0) -> 4866459.4 | H59: =SUMIF(AJE!$B$8:$B$36,B59,AJE!$E$8:$E$36)-SUMIF(AJE!$G$8:$G$36,B59,AJE!$J$8:$J$36) -> 0 | I59: =G59+H59 -> 4866459.4 | J59: Accumulated deficit
B60: 6502 | C60: הכנסות מחשבונית עצמית | D60: =VLOOKUP(B60,[1]DataSheet!$E$2:$H$112,3,0) -> -1190888 | E60: =SUMIF(AJE!$B$8:$B$36,B60,AJE!$D$8:$D$36)-SUMIF(AJE!$G$8:$G$36,B60,AJE!$I$8:$I$36) -> 0 | F60: =D60+E60 -> -1190888 | G60: =VLOOKUP(B60,[1]DataSheet!$E$2:$H$112,4,0) -> -321084.36 | H60: =SUMIF(AJE!$B$8:$B$36,B60,AJE!$E$8:$E$36)-SUMIF(AJE!$G$8:$G$36,B60,AJE!$J$8:$J$36) -> 0 | I60: =G60+H60 -> -321084.36 | J60: Revenues
B61: 6503 | C61: קיזוז הכנסות מחשבונית עצמית | D61: =VLOOKUP(B61,[1]DataSheet!$E$2:$H$112,3,0) -> 1190888 | E61: =SUMIF(AJE!$B$8:$B$36,B61,AJE!$D$8:$D$36)-SUMIF(AJE!$G$8:$G$36,B61,AJE!$I$8:$I$36) -> 0 | F61: =D61+E61 -> 1190888 | G61: =VLOOKUP(B61,[1]DataSheet!$E$2:$H$112,4,0) -> 321084.36 | H61: =SUMIF(AJE!$B$8:$B$36,B61,AJE!$E$8:$E$36)-SUMIF(AJE!$G$8:$G$36,B61,AJE!$J$8:$J$36) -> 0 | I61: =G61+H61 -> 321084.36 | J61: Revenues
B62: 7103 | C62: תגמולי מילואים | D62: =VLOOKUP(B62,[1]DataSheet!$E$2:$H$112,3,0) -> -88935 | E62: =SUMIF(AJE!$B$8:$B$36,B62,AJE!$D$8:$D$36)-SUMIF(AJE!$G$8:$G$36,B62,AJE!$I$8:$I$36) -> 0 | F62: =D62+E62 -> -88935 | G62: =VLOOKUP(B62,[1]DataSheet!$E$2:$H$112,4,0) -> -24111.36 | H62: =SUMIF(AJE!$B$8:$B$36,B62,AJE!$E$8:$E$36)-SUMIF(AJE!$G$8:$G$36,B62,AJE!$J$8:$J$36) -> 0 | I62: =G62+H62 -> -24111.36 | J62: Salaries and social benefits - R&D | K62: =D62/G62 -> 3.6885103
A63: ="720.שכר עבודה ונלוות מופ" -> 720.שכר עבודה ונלוות מופ | B63: 7200 | C63: ="שכר עבודה מופ" -> שכר עבודה מופ | D63: =VLOOKUP(B63,[1]DataSheet!$E$2:$H$112,3,0) -> 2745021.1 | E63: =SUMIF(AJE!$B$8:$B$36,B63,AJE!$D$8:$D$36)-SUMIF(AJE!$G$8:$G$36,B63,AJE!$I$8:$I$36) -> 0 | F63: =D63+E63 -> 2745021.1 | G63: =VLOOKUP(B63,[1]DataSheet!$E$2:$H$112,4,0) -> 746043.59 | H63: =SUMIF(AJE!$B$8:$B$36,B63,AJE!$E$8:$E$36)-SUMIF(AJE!$G$8:$G$36,B63,AJE!$J$8:$J$36) -> 0 | I63: =G63+H63 -> 746043.59 | J63: Salaries and social benefits - R&D | K63: =D63/G63 -> 3.6794379
A64: ="720.שכר עבודה ונלוות מופ" -> 720.שכר עבודה ונלוות מופ | B64: 7201 | C64: ="הכנסות זקופות חובה מופ" -> הכנסות זקופות חובה מופ | D64: =VLOOKUP(B64,[1]DataSheet!$E$2:$H$112,3,0) -> 126732.19 | E64: =SUMIF(AJE!$B$8:$B$36,B64,AJE!$D$8:$D$36)-SUMIF(AJE!$G$8:$G$36,B64,AJE!$I$8:$I$36) -> 0 | F64: =D64+E64 -> 126732.19 | G64: =VLOOKUP(B64,[1]DataSheet!$E$2:$H$112,4,0) -> 34224.71 | H64: =SUMIF(AJE!$B$8:$B$36,B64,AJE!$E$8:$E$36)-SUMIF(AJE!$G$8:$G$36,B64,AJE!$J$8:$J$36) -> 0 | I64: =G64+H64 -> 34224.71 | J64: Salaries and social benefits - R&D | K64: =D64/G64 -> 3.7029442
A65: ="720.שכר עבודה ונלוות מופ" -> 720.שכר עבודה ונלוות מופ | B65: 7202 | C65: ="הכנסות זקופות זכות מופ" -> הכנסות זקופות זכות מופ | D65: =VLOOKUP(B65,[1]DataSheet!$E$2:$H$112,3,0) -> -126732.19 | E65: =SUMIF(AJE!$B$8:$B$36,B65,AJE!$D$8:$D$36)-SUMIF(AJE!$G$8:$G$36,B65,AJE!$I$8:$I$36) -> 0 | F65: =D65+E65 -> -126732.19 | G65: =VLOOKUP(B65,[1]DataSheet!$E$2:$H$112,4,0) -> -34224.71 | H65: =SUMIF(AJE!$B$8:$B$36,B65,AJE!$E$8:$E$36)-SUMIF(AJE!$G$8:$G$36,B65,AJE!$J$8:$J$36) -> 0 | I65: =G65+H65 -> -34224.71 | J65: Salaries and social benefits - R&D | K65: =D65/G65 -> 3.7029442
A66: ="720.שכר עבודה ונלוות מופ" -> 720.שכר עבודה ונלוות מופ | B66: 7203 | C66: ="הוצאות ביטוח לאומי מעביד מופ" -> הוצאות ביטוח לאומי מעביד מופ | D66: =VLOOKUP(B66,[1]DataSheet!$E$2:$H$112,3,0) -> 222186.71 | E66: =SUMIF(AJE!$B$8:$B$36,B66,AJE!$D$8:$D$36)-SUMIF(AJE!$G$8:$G$36,B66,AJE!$I$8:$I$36) -> 0 | F66: =D66+E66 -> 222186.71 | G66: =VLOOKUP(B66,[1]DataSheet!$E$2:$H$112,4,0) -> 60396.29 | H66: =SUMIF(AJE!$B$8:$B$36,B66,AJE!$E$8:$E$36)-SUMIF(AJE!$G$8:$G$36,B66,AJE!$J$8:$J$36) -> 0 | I66: =G66+H66 -> 60396.29 | J66: Salaries and social benefits - R&D | K66: =D66/G66 -> 3.6788139
A67: ="720.שכר עבודה ונלוות מופ" -> 720.שכר עבודה ונלוות מופ | B67: 7204 | C67: ="הוצאות גמל מעביד מופ" -> הוצאות גמל מעביד מופ | D67: =VLOOKUP(B67,[1]DataSheet!$E$2:$H$112,3,0) -> 210148.88 | E67: =SUMIF(AJE!$B$8:$B$36,B67,AJE!$D$8:$D$36)-SUMIF(AJE!$G$8:$G$36,B67,AJE!$I$8:$I$36) -> 0 | F67: =D67+E67 -> 210148.88 | G67: =VLOOKUP(B67,[1]DataSheet!$E$2:$H$112,4,0) -> 57052.6 | H67: =SUMIF(AJE!$B$8:$B$36,B67,AJE!$E$8:$E$36)-SUMIF(AJE!$G$8:$G$36,B67,AJE!$J$8:$J$36) -> 0 | I67: =G67+H67 -> 57052.6 | J67: Salaries and social benefits - R&D | K67: =D67/G67 -> 3.6834234
A68: ="720.שכר עבודה ונלוות מופ" -> 720.שכר עבודה ונלוות מופ | B68: 7205 | C68: ="הוצאות קרן השתלמות מעביד מופ" -> הוצאות קרן השתלמות מעביד מופ | D68: =VLOOKUP(B68,[1]DataSheet!$E$2:$H$112,3,0) -> 136458.75 | E68: =SUMIF(AJE!$B$8:$B$36,B68,AJE!$D$8:$D$36)-SUMIF(AJE!$G$8:$G$36,B68,AJE!$I$8:$I$36) -> 0 | F68: =D68+E68 -> 136458.75 | G68: =VLOOKUP(B68,[1]DataSheet!$E$2:$H$112,4,0) -> 36991.4 | H68: =SUMIF(AJE!$B$8:$B$36,B68,AJE!$E$8:$E$36)-SUMIF(AJE!$G$8:$G$36,B68,AJE!$J$8:$J$36) -> 0 | I68: =G68+H68 -> 36991.4 | J68: Salaries and social benefits - R&D | K68: =D68/G68 -> 3.6889318
A69: ="720.שכר עבודה ונלוות מופ" -> 720.שכר עבודה ונלוות מופ | B69: 7206 | C69: ="הוצאות פיצויים מעביד מופ" -> הוצאות פיצויים מעביד מופ | D69: =VLOOKUP(B69,[1]DataSheet!$E$2:$H$112,3,0) -> 272579.77 | E69: =SUMIF(AJE!$B$8:$B$36,B69,AJE!$D$8:$D$36)-SUMIF(AJE!$G$8:$G$36,B69,AJE!$I$8:$I$36) -> 0 | F69: =D69+E69 -> 272579.77 | G69: =VLOOKUP(B69,[1]DataSheet!$E$2:$H$112,4,0) -> 74014.07 | H69: =SUMIF(AJE!$B$8:$B$36,B69,AJE!$E$8:$E$36)-SUMIF(AJE!$G$8:$G$36,B69,AJE!$J$8:$J$36) -> 0 | I69: =G69+H69 -> 74014.07 | J69: Salaries and social benefits - R&D | K69: =D69/G69 -> 3.6828102
A70: ="720.שכר עבודה ונלוות מופ" -> 720.שכר עבודה ונלוות מופ | B70: 7207 | C70: ="הוצאות ביטוח א.כ.ע מעביד מופ" -> הוצאות ביטוח א.כ.ע מעביד מופ | D70: =VLOOKUP(B70,[1]DataSheet!$E$2:$H$112,3,0) -> 2548.44 | E70: =SUMIF(AJE!$B$8:$B$36,B70,AJE!$D$8:$D$36)-SUMIF(AJE!$G$8:$G$36,B70,AJE!$I$8:$I$36) -> 0 | F70: =D70+E70 -> 2548.44 | G70: =VLOOKUP(B70,[1]DataSheet!$E$2:$H$112,4,0) -> 701.47 | H70: =SUMIF(AJE!$B$8:$B$36,B70,AJE!$E$8:$E$36)-SUMIF(AJE!$G$8:$G$36,B70,AJE!$J$8:$J$36) -> 0 | I70: =G70+H70 -> 701.47 | J70: Salaries and social benefits - R&D | K70: =D70/G70 -> 3.6329993
B71: 7208 | C71: חופשה והבאה מופ | D71: =VLOOKUP(B71,[1]DataSheet!$E$2:$H$112,3,0) -> -88001 | E71: =SUMIF(AJE!$B$8:$B$36,B71,AJE!$D$8:$D$36)-SUMIF(AJE!$G$8:$G$36,B71,AJE!$I$8:$I$36) -> 0 | F71: =D71+E71 -> -88001 | G71: =VLOOKUP(B71,[1]DataSheet!$E$2:$H$112,4,0) -> -24262.75 | H71: =SUMIF(AJE!$B$8:$B$36,B71,AJE!$E$8:$E$36)-SUMIF(AJE!$G$8:$G$36,B71,AJE!$J$8:$J$36) -> 0 | I71: =G71+H71 -> -24262.75 | J71: Salaries and social benefits - R&D | K71: =D71/G71 -> 3.6270002
B72: 7700 | C72: שכר הנהלה | D72: =VLOOKUP(B72,[1]DataSheet!$E$2:$H$112,3,0) -> 554135 | E72: =SUMIF(AJE!$B$8:$B$36,B72,AJE!$D$8:$D$36)-SUMIF(AJE!$G$8:$G$36,B72,AJE!$I$8:$I$36) -> 0 | F72: =D72+E72 -> 554135 | G72: =VLOOKUP(B72,[1]DataSheet!$E$2:$H$112,4,0) -> 150990 | H72: =SUMIF(AJE!$B$8:$B$36,B72,AJE!$E$8:$E$36)-SUMIF(AJE!$G$8:$G$36,B72,AJE!$J$8:$J$36) -> 0 | I72: =G72+H72 -> 150990 | J72: Salaries and social benefits - G&A | K72: =D72/G72 -> 3.6700113
B73: 7708 | C73: חופשה והבאה הנהלה | D73: =VLOOKUP(B73,[1]DataSheet!$E$2:$H$112,3,0) -> 9871 | E73: =SUMIF(AJE!$B$8:$B$36,B73,AJE!$D$8:$D$36)-SUMIF(AJE!$G$8:$G$36,B73,AJE!$I$8:$I$36) -> 0 | F73: =D73+E73 -> 9871 | G73: =VLOOKUP(B73,[1]DataSheet!$E$2:$H$112,4,0) -> 2721.53 | H73: =SUMIF(AJE!$B$8:$B$36,B73,AJE!$E$8:$E$36)-SUMIF(AJE!$G$8:$G$36,B73,AJE!$J$8:$J$36) -> 0 | I73: =G73+H73 -> 2721.53 | J73: Salaries and social benefits - G&A | K73: =D73/G73 -> 3.6270039
A74: ="730.הוצאות מחקר ופיתוח" -> 730.הוצאות מחקר ופיתוח | B74: 7301 | C74: ="פיתוח אחר" -> פיתוח אחר | D74: =VLOOKUP(B74,[1]DataSheet!$E$2:$H$112,3,0) -> 131271.6 | E74: =SUMIF(AJE!$B$8:$B$36,B74,AJE!$D$8:$D$36)-SUMIF(AJE!$G$8:$G$36,B74,AJE!$I$8:$I$36) -> 22591.33 | F74: =D74+E74 -> 153862.93 | G74: =VLOOKUP(B74,[1]DataSheet!$E$2:$H$112,4,0) -> 35583.86 | H74: =SUMIF(AJE!$B$8:$B$36,B74,AJE!$E$8:$E$36)-SUMIF(AJE!$G$8:$G$36,B74,AJE!$J$8:$J$36) -> 6228.6545 | I74: =G74+H74 -> 41812.515 | J74: R&D expenses | K74: =D74/G74 -> 3.689077
A75: ="730.הוצאות מחקר ופיתוח" -> 730.הוצאות מחקר ופיתוח | B75: 7303 | C75: ="אירוח שרתים" -> אירוח שרתים | D75: =VLOOKUP(B75,[1]DataSheet!$E$2:$H$112,3,0) -> 20529 | E75: =SUMIF(AJE!$B$8:$B$36,B75,AJE!$D$8:$D$36)-SUMIF(AJE!$G$8:$G$36,B75,AJE!$I$8:$I$36) -> 0 | F75: =D75+E75 -> 20529 | G75: =VLOOKUP(B75,[1]DataSheet!$E$2:$H$112,4,0) -> 5400 | H75: =SUMIF(AJE!$B$8:$B$36,B75,AJE!$E$8:$E$36)-SUMIF(AJE!$G$8:$G$36,B75,AJE!$J$8:$J$36) -> 0 | I75: =G75+H75 -> 5400 | J75: R&D expenses | K75: =D75/G75 -> 3.8016667
A76: ="730.הוצאות מחקר ופיתוח" -> 730.הוצאות מחקר ופיתוח | B76: 7305 | C76: ="פיתוח תוכנה" -> פיתוח תוכנה | D76: =VLOOKUP(B76,[1]DataSheet!$E$2:$H$112,3,0) -> 689442.52 | E76: =SUMIF(AJE!$B$8:$B$36,B76,AJE!$D$8:$D$36)-SUMIF(AJE!$G$8:$G$36,B76,AJE!$I$8:$I$36) -> 6882.42 | F76: =D76+E76 -> 696324.94 | G76: =VLOOKUP(B76,[1]DataSheet!$E$2:$H$112,4,0) -> 186864.06 | H76: =SUMIF(AJE!$B$8:$B$36,B76,AJE!$E$8:$E$36)-SUMIF(AJE!$G$8:$G$36,B76,AJE!$J$8:$J$36) -> 1897.5517 | I76: =G76+H76 -> 188761.61 | J76: R&D expenses | K76: =D76/G76 -> 3.6895405
A77: ="730.הוצאות מחקר ופיתוח" -> 730.הוצאות מחקר ופיתוח | B77: 7306 | C77: ="עיצוב גרפי" -> עיצוב גרפי | D77: =VLOOKUP(B77,[1]DataSheet!$E$2:$H$112,3,0) -> 16324.31 | E77: =SUMIF(AJE!$B$8:$B$36,B77,AJE!$D$8:$D$36)-SUMIF(AJE!$G$8:$G$36,B77,AJE!$I$8:$I$36) -> 0 | F77: =D77+E77 -> 16324.31 | G77: =VLOOKUP(B77,[1]DataSheet!$E$2:$H$112,4,0) -> 4341 | H77: =SUMIF(AJE!$B$8:$B$36,B77,AJE!$E$8:$E$36)-SUMIF(AJE!$G$8:$G$36,B77,AJE!$J$8:$J$36) -> 0 | I77: =G77+H77 -> 4341 | J77: R&D expenses | K77: =D77/G77 -> 3.7604953
A78: ="730.הוצאות מחקר ופיתוח" -> 730.הוצאות מחקר ופיתוח | B78: 7307 | C78: ="יעוץ פיתוח מוצר" -> יעוץ פיתוח מוצר | D78: =VLOOKUP(B78,[1]DataSheet!$E$2:$H$112,3,0) -> 36752.34 | E78: =SUMIF(AJE!$B$8:$B$36,B78,AJE!$D$8:$D$36)-SUMIF(AJE!$G$8:$G$36,B78,AJE!$I$8:$I$36) -> 0 | F78: =D78+E78 -> 36752.34 | G78: =VLOOKUP(B78,[1]DataSheet!$E$2:$H$112,4,0) -> 9671.44 | H78: =SUMIF(AJE!$B$8:$B$36,B78,AJE!$E$8:$E$36)-SUMIF(AJE!$G$8:$G$36,B78,AJE!$J$8:$J$36) -> 0 | I78: =G78+H78 -> 9671.44 | J78: R&D expenses | K78: =D78/G78 -> 3.8000897
B79: 7308 | C79: תוכנות מחשב R&D | D79: =VLOOKUP(B79,[1]DataSheet!$E$2:$H$112,3,0) -> 221.15 | E79: =SUMIF(AJE!$B$8:$B$36,B79,AJE!$D$8:$D$36)-SUMIF(AJE!$G$8:$G$36,B79,AJE!$I$8:$I$36) -> 0 | F79: =D79+E79 -> 221.15 | G79: =VLOOKUP(B79,[1]DataSheet!$E$2:$H$112,4,0) -> 59.4 | H79: =SUMIF(AJE!$B$8:$B$36,B79,AJE!$E$8:$E$36)-SUMIF(AJE!$G$8:$G$36,B79,AJE!$J$8:$J$36) -> 0 | I79: =G79+H79 -> 59.4 | J79: R&D expenses | K79: =D79/G79 -> 3.723064
A80: ="740.שכר עבודה ונלוות מכירה ושיווק" -> 740.שכר עבודה ונלוות מכירה ושיווק | B80: 7450 | C80: ="שיווק ומכירות" -> שיווק ומכירות | D80: =VLOOKUP(B80,[1]DataSheet!$E$2:$H$112,3,0) -> 283743.5 | E80: =SUMIF(AJE!$B$8:$B$36,B80,AJE!$D$8:$D$36)-SUMIF(AJE!$G$8:$G$36,B80,AJE!$I$8:$I$36) -> 171385.25 | F80: =D80+E80 -> 455128.75 | G80: =VLOOKUP(B80,[1]DataSheet!$E$2:$H$112,4,0) -> 76452.06 | H80: =SUMIF(AJE!$B$8:$B$36,B80,AJE!$E$8:$E$36)-SUMIF(AJE!$G$8:$G$36,B80,AJE!$J$8:$J$36) -> 47252.619 | I80: =G80+H80 -> 123704.68 | J80: Other S&M | K80: =D80/G80 -> 3.7113912
B81: 7501 | C81: הוצאות פרסום | D81: =VLOOKUP(B81,[1]DataSheet!$E$2:$H$112,3,0) -> 48 | E81: =SUMIF(AJE!$B$8:$B$36,B81,AJE!$D$8:$D$36)-SUMIF(AJE!$G$8:$G$36,B81,AJE!$I$8:$I$36) -> 0 | F81: =D81+E81 -> 48 | G81: =VLOOKUP(B81,[1]DataSheet!$E$2:$H$112,4,0) -> 13.15 | H81: =SUMIF(AJE!$B$8:$B$36,B81,AJE!$E$8:$E$36)-SUMIF(AJE!$G$8:$G$36,B81,AJE!$J$8:$J$36) -> 0 | I81: =G81+H81 -> 13.15 | J81: Other S&M | K81: =D81/G81 -> 3.6501901
B82: 7560 | C82: COST+אנגליה שיווק | E82: =SUMIF(AJE!$B$8:$B$36,B82,AJE!$D$8:$D$36)-SUMIF(AJE!$G$8:$G$36,B82,AJE!$I$8:$I$36) -> 1710764.6 | F82: =D82+E82 -> 1710764.6 | H82: =SUMIF(AJE!$B$8:$B$36,B82,AJE!$E$8:$E$36)-SUMIF(AJE!$G$8:$G$36,B82,AJE!$J$8:$J$36) -> 471674.81 | I82: =G82+H82 -> 471674.81 | J82: COST + UK S&M
A83: ="750.הוצאות מכירה ושיווק" -> 750.הוצאות מכירה ושיווק | B83: 7600 | C83: ="נסיעות לחול" -> נסיעות לחול | D83: =VLOOKUP(B83,[1]DataSheet!$E$2:$H$112,3,0) -> 31869.44 | E83: =SUMIF(AJE!$B$8:$B$36,B83,AJE!$D$8:$D$36)-SUMIF(AJE!$G$8:$G$36,B83,AJE!$I$8:$I$36) -> 0 | F83: =D83+E83 -> 31869.44 | G83: =VLOOKUP(B83,[1]DataSheet!$E$2:$H$112,4,0) -> 8677.19 | H83: =SUMIF(AJE!$B$8:$B$36,B83,AJE!$E$8:$E$36)-SUMIF(AJE!$G$8:$G$36,B83,AJE!$J$8:$J$36) -> 0 | I83: =G83+H83 -> 8677.19 | J83: Travel | K83: =D83/G83 -> 3.6727835
B84: 7801 | C84: ביטוח | D84: =VLOOKUP(B84,[1]DataSheet!$E$2:$H$112,3,0) -> 5349.75 | E84: =SUMIF(AJE!$B$8:$B$36,B84,AJE!$D$8:$D$36)-SUMIF(AJE!$G$8:$G$36,B84,AJE!$I$8:$I$36) -> 0 | F84: =D84+E84 -> 5349.75 | G84: =VLOOKUP(B84,[1]DataSheet!$E$2:$H$112,4,0) -> 1474.03 | H84: =SUMIF(AJE!$B$8:$B$36,B84,AJE!$E$8:$E$36)-SUMIF(AJE!$G$8:$G$36,B84,AJE!$J$8:$J$36) -> 0 | I84: =G84+H84 -> 1474.03 | J84: Insurance | K84: =D84/G84 -> 3.6293359
B85: 7805 | C85: ארנונה | D85: =VLOOKUP(B85,[1]DataSheet!$E$2:$H$112,3,0) -> 27306.17 | E85: =SUMIF(AJE!$B$8:$B$36,B85,AJE!$D$8:$D$36)-SUMIF(AJE!$G$8:$G$36,B85,AJE!$I$8:$I$36) -> 4671 | F85: =D85+E85 -> 31977.17 | G85: =VLOOKUP(B85,[1]DataSheet!$E$2:$H$112,4,0) -> 7676.81 | H85: =SUMIF(AJE!$B$8:$B$36,B85,AJE!$E$8:$E$36)-SUMIF(AJE!$G$8:$G$36,B85,AJE!$J$8:$J$36) -> 1287.8412 | I85: =G85+H85 -> 8964.6512 | J85: Rent (Inc. Tax) | K85: =D85/G85 -> 3.5569683
B86: 7814 | C86: אירוח בחו"ל | E86: =SUMIF(AJE!$B$8:$B$36,B86,AJE!$D$8:$D$36)-SUMIF(AJE!$G$8:$G$36,B86,AJE!$I$8:$I$36) -> 0 | F86: =D86+E86 -> 0 | H86: =SUMIF(AJE!$B$8:$B$36,B86,AJE!$E$8:$E$36)-SUMIF(AJE!$G$8:$G$36,B86,AJE!$J$8:$J$36) -> 0 | I86: =G86+H86 -> 0 | J86: Other - G&A | K86: =D86/G86 -> #DIV/0!
A87: ="780.הנהלה וכלליות" -> 780.הנהלה וכלליות | B87: 7806 | C87: ="אחזקת מחשבים" -> אחזקת מחשבים | D87: =VLOOKUP(B87,[1]DataSheet!$E$2:$H$112,3,0) -> 3105.57 | E87: =SUMIF(AJE!$B$8:$B$36,B87,AJE!$D$8:$D$36)-SUMIF(AJE!$G$8:$G$36,B87,AJE!$I$8:$I$36) -> 0 | F87: =D87+E87 -> 3105.57 | G87: =VLOOKUP(B87,[1]DataSheet!$E$2:$H$112,4,0) -> 853.32 | H87: =SUMIF(AJE!$B$8:$B$36,B87,AJE!$E$8:$E$36)-SUMIF(AJE!$G$8:$G$36,B87,AJE!$J$8:$J$36) -> 0 | I87: =G87+H87 -> 853.32 | J87: IT& communications | K87: =D87/G87 -> 3.6393967
A88: ="780.הנהלה וכלליות" -> 780.הנהלה וכלליות | B88: 7807 | C88: ="טלפון ותקשורת" -> טלפון ותקשורת | D88: =VLOOKUP(B88,[1]DataSheet!$E$2:$H$112,3,0) -> 38878.17 | E88: =SUMIF(AJE!$B$8:$B$36,B88,AJE!$D$8:$D$36)-SUMIF(AJE!$G$8:$G$36,B88,AJE!$I$8:$I$36) -> 0 | F88: =D88+E88 -> 38878.17 | G88: =VLOOKUP(B88,[1]DataSheet!$E$2:$H$112,4,0) -> 10563.46 | H88: =SUMIF(AJE!$B$8:$B$36,B88,AJE!$E$8:$E$36)-SUMIF(AJE!$G$8:$G$36,B88,AJE!$J$8:$J$36) -> 0 | I88: =G88+H88 -> 10563.46 | J88: IT& communications | K88: =D88/G88 -> 3.680439
B89: 7808 | C89: פחת | D89: =VLOOKUP(B89,[1]DataSheet!$E$2:$H$112,3,0) -> 81476 | E89: =SUMIF(AJE!$B$8:$B$36,B89,AJE!$D$8:$D$36)-SUMIF(AJE!$G$8:$G$36,B89,AJE!$I$8:$I$36) -> 0 | F89: =D89+E89 -> 81476 | G89: =VLOOKUP(B89,[1]DataSheet!$E$2:$H$112,4,0) -> 24780 | H89: =SUMIF(AJE!$B$8:$B$36,B89,AJE!$E$8:$E$36)-SUMIF(AJE!$G$8:$G$36,B89,AJE!$J$8:$J$36) -> 0 | I89: =G89+H89 -> 24780 | J89: Depreciation
A90: ="780.הנהלה וכלליות" -> 780.הנהלה וכלליות | B90: 7809 | C90: ="משפטיות" -> משפטיות | D90: =VLOOKUP(B90,[1]DataSheet!$E$2:$H$112,3,0) -> 101137.93 | E90: =SUMIF(AJE!$B$8:$B$36,B90,AJE!$D$8:$D$36)-SUMIF(AJE!$G$8:$G$36,B90,AJE!$I$8:$I$36) -> 0 | F90: =D90+E90 -> 101137.93 | G90: =VLOOKUP(B90,[1]DataSheet!$E$2:$H$112,4,0) -> 27086.2 | H90: =SUMIF(AJE!$B$8:$B$36,B90,AJE!$E$8:$E$36)-SUMIF(AJE!$G$8:$G$36,B90,AJE!$J$8:$J$36) -> 0 | I90: =G90+H90 -> 27086.2 | J90: Legal & Professional Services | K90: =D90/G90 -> 3.7339283
A91: ="780.הנהלה וכלליות" -> 780.הנהלה וכלליות | B91: 7810 | C91: ="הנהלת חשבונות וביקורת" -> הנהלת חשבונות וביקורת | D91: =VLOOKUP(B91,[1]DataSheet!$E$2:$H$112,3,0) -> 131000 | E91: =SUMIF(AJE!$B$8:$B$36,B91,AJE!$D$8:$D$36)-SUMIF(AJE!$G$8:$G$36,B91,AJE!$I$8:$I$36) -> 16200 | F91: =D91+E91 -> 147200 | G91: =VLOOKUP(B91,[1]DataSheet!$E$2:$H$112,4,0) -> 35919.11 | H91: =SUMIF(AJE!$B$8:$B$36,B91,AJE!$E$8:$E$36)-SUMIF(AJE!$G$8:$G$36,B91,AJE!$J$8:$J$36) -> 4466.5012 | I91: =G91+H91 -> 40385.611 | J91: Accounting & Financial Services | K91: =D91/G91 -> 3.6470837
A92: ="780.הנהלה וכלליות" -> 780.הנהלה וכלליות | B92: 7811 | C92: ="ביטולי יתרות" -> ביטולי יתרות | D92: =VLOOKUP(B92,[1]DataSheet!$E$2:$H$112,3,0) -> 14.33 | E92: =SUMIF(AJE!$B$8:$B$36,B92,AJE!$D$8:$D$36)-SUMIF(AJE!$G$8:$G$36,B92,AJE!$I$8:$I$36) -> 0 | F92: =D92+E92 -> 14.33 | G92: =VLOOKUP(B92,[1]DataSheet!$E$2:$H$112,4,0) -> 4.04 | H92: =SUMIF(AJE!$B$8:$B$36,B92,AJE!$E$8:$E$36)-SUMIF(AJE!$G$8:$G$36,B92,AJE!$J$8:$J$36) -> 0 | I92: =G92+H92 -> 4.04 | J92: Other - G&A | K92: =D92/G92 -> 3.5470297
A93: ="780.הנהלה וכלליות" -> 780.הנהלה וכלליות | B93: 7812 | C93: ="כיבודים" -> כיבודים | D93: =VLOOKUP(B93,[1]DataSheet!$E$2:$H$112,3,0) -> 49159.6 | E93: =SUMIF(AJE!$B$8:$B$36,B93,AJE!$D$8:$D$36)-SUMIF(AJE!$G$8:$G$36,B93,AJE!$I$8:$I$36) -> 0 | F93: =D93+E93 -> 49159.6 | G93: =VLOOKUP(B93,[1]DataSheet!$E$2:$H$112,4,0) -> 13452.08 | H93: =SUMIF(AJE!$B$8:$B$36,B93,AJE!$E$8:$E$36)-SUMIF(AJE!$G$8:$G$36,B93,AJE!$J$8:$J$36) -> 0 | I93: =G93+H93 -> 13452.08 | J93: Other - G&A | K93: =D93/G93 -> 3.6544237
A94: ="780.הנהלה וכלליות" -> 780.הנהלה וכלליות | B94: 7813 | C94: ="אירוח בארץ" -> אירוח בארץ | D94: =VLOOKUP(B94,[1]DataSheet!$E$2:$H$112,3,0) -> 9552.9 | E94: =SUMIF(AJE!$B$8:$B$36,B94,AJE!$D$8:$D$36)-SUMIF(AJE!$G$8:$G$36,B94,AJE!$I$8:$I$36) -> 0 | F94: =D94+E94 -> 9552.9 | G94: =VLOOKUP(B94,[1]DataSheet!$E$2:$H$112,4,0) -> 2788.56 | H94: =SUMIF(AJE!$B$8:$B$36,B94,AJE!$E$8:$E$36)-SUMIF(AJE!$G$8:$G$36,B94,AJE!$J$8:$J$36) -> 0 | I94: =G94+H94 -> 2788.56 | J94: Other - G&A | K94: =D94/G94 -> 3.4257466
A95: ="780.הנהלה וכלליות" -> 780.הנהלה וכלליות | B95: 7821 | C95: ="ארוחות עובדים" -> ארוחות עובדים | D95: =VLOOKUP(B95,[1]DataSheet!$E$2:$H$112,3,0) -> 107442 | E95: =SUMIF(AJE!$B$8:$B$36,B95,AJE!$D$8:$D$36)-SUMIF(AJE!$G$8:$G$36,B95,AJE!$I$8:$I$36) -> 0 | F95: =D95+E95 -> 107442 | G95: =VLOOKUP(B95,[1]DataSheet!$E$2:$H$112,4,0) -> 29133.07 | H95: =SUMIF(AJE!$B$8:$B$36,B95,AJE!$E$8:$E$36)-SUMIF(AJE!$G$8:$G$36,B95,AJE!$J$8:$J$36) -> 0 | I95: =G95+H95 -> 29133.07 | J95: Welfare | K95: =D95/G95 -> 3.6879738
A96: ="780.הנהלה וכלליות" -> 780.הנהלה וכלליות | B96: 7822 | C96: ="דמי שכירות" -> דמי שכירות | D96: =VLOOKUP(B96,[1]DataSheet!$E$2:$H$112,3,0) -> 418819.98 | E96: =SUMIF(AJE!$B$8:$B$36,B96,AJE!$D$8:$D$36)-SUMIF(AJE!$G$8:$G$36,B96,AJE!$I$8:$I$36) -> 0 | F96: =D96+E96 -> 418819.98 | G96: =VLOOKUP(B96,[1]DataSheet!$E$2:$H$112,4,0) -> 113438.59 | H96: =SUMIF(AJE!$B$8:$B$36,B96,AJE!$E$8:$E$36)-SUMIF(AJE!$G$8:$G$36,B96,AJE!$J$8:$J$36) -> 0 | I96: =G96+H96 -> 113438.59 | J96: Rent (Inc. Tax) | K96: =D96/G96 -> 3.6920415
A97: ="780.הנהלה וכלליות" -> 780.הנהלה וכלליות | B97: 7823 | C97: ="יעוץ מקצועי" -> יעוץ מקצועי | D97: =VLOOKUP(B97,[1]DataSheet!$E$2:$H$112,3,0) -> -35550 | E97: =SUMIF(AJE!$B$8:$B$36,B97,AJE!$D$8:$D$36)-SUMIF(AJE!$G$8:$G$36,B97,AJE!$I$8:$I$36) -> 0 | F97: =D97+E97 -> -35550 | G97: =VLOOKUP(B97,[1]DataSheet!$E$2:$H$112,4,0) -> -10104.27 | H97: =SUMIF(AJE!$B$8:$B$36,B97,AJE!$E$8:$E$36)-SUMIF(AJE!$G$8:$G$36,B97,AJE!$J$8:$J$36) -> 0 | I97: =G97+H97 -> -10104.27 | J97: Subcontractors | K97: =D97/G97 -> 3.5183145 | L97: ביטול הפרשה של אביב בן יוסף בסך 38 אלף ₪ - הם לא עובדים איתו יותר . בעיקורן לא הייתי צריכה לעשות הפרשה
A98: ="780.הנהלה וכלליות" -> 780.הנהלה וכלליות | B98: 7824 | C98: ="אחזקת משרד" -> אחזקת משרד | D98: =VLOOKUP(B98,[1]DataSheet!$E$2:$H$112,3,0) -> 44175.6 | E98: =SUMIF(AJE!$B$8:$B$36,B98,AJE!$D$8:$D$36)-SUMIF(AJE!$G$8:$G$36,B98,AJE!$I$8:$I$36) -> 0 | F98: =D98+E98 -> 44175.6 | G98: =VLOOKUP(B98,[1]DataSheet!$E$2:$H$112,4,0) -> 12067.96 | H98: =SUMIF(AJE!$B$8:$B$36,B98,AJE!$E$8:$E$36)-SUMIF(AJE!$G$8:$G$36,B98,AJE!$J$8:$J$36) -> 0 | I98: =G98+H98 -> 12067.96 | J98: Maintenance | K98: =D98/G98 -> 3.660569
A99: ="780.הנהלה וכלליות" -> 780.הנהלה וכלליות | B99: 7825 | C99: ="נסיעות ומוניות" -> נסיעות ומוניות | D99: =VLOOKUP(B99,[1]DataSheet!$E$2:$H$112,3,0) -> 4949.74 | E99: =SUMIF(AJE!$B$8:$B$36,B99,AJE!$D$8:$D$36)-SUMIF(AJE!$G$8:$G$36,B99,AJE!$I$8:$I$36) -> 0 | F99: =D99+E99 -> 4949.74 | G99: =VLOOKUP(B99,[1]DataSheet!$E$2:$H$112,4,0) -> 1337.12 | H99: =SUMIF(AJE!$B$8:$B$36,B99,AJE!$E$8:$E$36)-SUMIF(AJE!$G$8:$G$36,B99,AJE!$J$8:$J$36) -> 0 | I99: =G99+H99 -> 1337.12 | J99: Car maintenance | K99: =D99/G99 -> 3.7017919
B100: 7827 | C100: מתנות לעובדים | D100: =VLOOKUP(B100,[1]DataSheet!$E$2:$H$112,3,0) -> 16279.02 | E100: =SUMIF(AJE!$B$8:$B$36,B100,AJE!$D$8:$D$36)-SUMIF(AJE!$G$8:$G$36,B100,AJE!$I$8:$I$36) -> 0 | F100: =D100+E100 -> 16279.02 | G100: =VLOOKUP(B100,[1]DataSheet!$E$2:$H$112,4,0) -> 4426.9 | H100: =SUMIF(AJE!$B$8:$B$36,B100,AJE!$E$8:$E$36)-SUMIF(AJE!$G$8:$G$36,B100,AJE!$J$8:$J$36) -> 0 | I100: =G100+H100 -> 4426.9 | J100: Welfare | K100: =D100/G100 -> 3.6772956
B101: 7836 | C101: אירועי חברה | D101: =VLOOKUP(B101,[1]DataSheet!$E$2:$H$112,3,0) -> 14647.5 | E101: =SUMIF(AJE!$B$8:$B$36,B101,AJE!$D$8:$D$36)-SUMIF(AJE!$G$8:$G$36,B101,AJE!$I$8:$I$36) -> 0 | F101: =D101+E101 -> 14647.5 | G101: =VLOOKUP(B101,[1]DataSheet!$E$2:$H$112,4,0) -> 4011.77 | H101: =SUMIF(AJE!$B$8:$B$36,B101,AJE!$E$8:$E$36)-SUMIF(AJE!$G$8:$G$36,B101,AJE!$J$8:$J$36) -> 0 | I101: =G101+H101 -> 4011.77 | J101: Welfare | K101: =D101/G101 -> 3.6511315
A102: ="780.הנהלה וכלליות" -> 780.הנהלה וכלליות | B102: 7829 | C102: ="משרדיות" -> משרדיות | D102: =VLOOKUP(B102,[1]DataSheet!$E$2:$H$112,3,0) -> 1301.74 | E102: =SUMIF(AJE!$B$8:$B$36,B102,AJE!$D$8:$D$36)-SUMIF(AJE!$G$8:$G$36,B102,AJE!$I$8:$I$36) -> 0 | F102: =D102+E102 -> 1301.74 | G102: =VLOOKUP(B102,[1]DataSheet!$E$2:$H$112,4,0) -> 368 | H102: =SUMIF(AJE!$B$8:$B$36,B102,AJE!$E$8:$E$36)-SUMIF(AJE!$G$8:$G$36,B102,AJE!$J$8:$J$36) -> 0 | I102: =G102+H102 -> 368 | J102: Maintenance | K102: =D102/G102 -> 3.537337
A103: ="780.הנהלה וכלליות" -> 780.הנהלה וכלליות | B103: 7831 | C103: ="אגרות" -> אגרות | D103: =VLOOKUP(B103,[1]DataSheet!$E$2:$H$112,3,0) -> 1215 | E103: =SUMIF(AJE!$B$8:$B$36,B103,AJE!$D$8:$D$36)-SUMIF(AJE!$G$8:$G$36,B103,AJE!$I$8:$I$36) -> 0 | F103: =D103+E103 -> 1215 | G103: =VLOOKUP(B103,[1]DataSheet!$E$2:$H$112,4,0) -> 346.94 | H103: =SUMIF(AJE!$B$8:$B$36,B103,AJE!$E$8:$E$36)-SUMIF(AJE!$G$8:$G$36,B103,AJE!$J$8:$J$36) -> 0 | I103: =G103+H103 -> 346.94 | J103: Other - G&A | K103: =D103/G103 -> 3.5020465
A104: ="780.הנהלה וכלליות" -> 780.הנהלה וכלליות | B104: 7832 | C104: ="דמי סליקה/שירות פנסיוני" -> דמי סליקה/שירות פנסיוני | D104: =VLOOKUP(B104,[1]DataSheet!$E$2:$H$112,3,0) -> 5647.83 | E104: =SUMIF(AJE!$B$8:$B$36,B104,AJE!$D$8:$D$36)-SUMIF(AJE!$G$8:$G$36,B104,AJE!$I$8:$I$36) -> 0 | F104: =D104+E104 -> 5647.83 | G104: =VLOOKUP(B104,[1]DataSheet!$E$2:$H$112,4,0) -> 1535.69 | H104: =SUMIF(AJE!$B$8:$B$36,B104,AJE!$E$8:$E$36)-SUMIF(AJE!$G$8:$G$36,B104,AJE!$J$8:$J$36) -> 0 | I104: =G104+H104 -> 1535.69 | J104: Other - G&A | K104: =D104/G104 -> 3.6777149
A105: ="780.הנהלה וכלליות" -> 780.הנהלה וכלליות | B105: 7833 | C105: ="חניה" -> חניה | D105: =VLOOKUP(B105,[1]DataSheet!$E$2:$H$112,3,0) -> 4163.17 | E105: =SUMIF(AJE!$B$8:$B$36,B105,AJE!$D$8:$D$36)-SUMIF(AJE!$G$8:$G$36,B105,AJE!$I$8:$I$36) -> 0 | F105: =D105+E105 -> 4163.17 | G105: =VLOOKUP(B105,[1]DataSheet!$E$2:$H$112,4,0) -> 1144.89 | H105: =SUMIF(AJE!$B$8:$B$36,B105,AJE!$E$8:$E$36)-SUMIF(AJE!$G$8:$G$36,B105,AJE!$J$8:$J$36) -> 0 | I105: =G105+H105 -> 1144.89 | J105: Car maintenance | K105: =D105/G105 -> 3.6363057
B106: 7838 | C106: תוכנות מחשב GA | D106: =VLOOKUP(B106,[1]DataSheet!$E$2:$H$112,3,0) -> 1973.3 | E106: =SUMIF(AJE!$B$8:$B$36,B106,AJE!$D$8:$D$36)-SUMIF(AJE!$G$8:$G$36,B106,AJE!$I$8:$I$36) -> 0 | F106: =D106+E106 -> 1973.3 | G106: =VLOOKUP(B106,[1]DataSheet!$E$2:$H$112,4,0) -> 530.11 | H106: =SUMIF(AJE!$B$8:$B$36,B106,AJE!$E$8:$E$36)-SUMIF(AJE!$G$8:$G$36,B106,AJE!$J$8:$J$36) -> 0 | I106: =G106+H106 -> 530.11 | J106: IT& communications | K106: =D106/G106 -> 3.722435
B107: 7861 | C107: COST+אנגליה | E107: =SUMIF(AJE!$B$8:$B$36,B107,AJE!$D$8:$D$36)-SUMIF(AJE!$G$8:$G$36,B107,AJE!$I$8:$I$36) -> 1000407.6 | F107: =D107+E107 -> 1000407.6 | H107: =SUMIF(AJE!$B$8:$B$36,B107,AJE!$E$8:$E$36)-SUMIF(AJE!$G$8:$G$36,B107,AJE!$J$8:$J$36) -> 277890.99 | I107: =G107+H107 -> 277890.99 | J107: COST + UK G&A
B108: 7862 | C108: יחסי ציבור | D108: =VLOOKUP(B108,[1]DataSheet!$E$2:$H$112,3,0) -> 10000 | E108: =SUMIF(AJE!$B$8:$B$36,B108,AJE!$D$8:$D$36)-SUMIF(AJE!$G$8:$G$36,B108,AJE!$I$8:$I$36) -> 0 | F108: =D108+E108 -> 10000 | G108: =VLOOKUP(B108,[1]DataSheet!$E$2:$H$112,4,0) -> 2721.08 | H108: =SUMIF(AJE!$B$8:$B$36,B108,AJE!$E$8:$E$36)-SUMIF(AJE!$G$8:$G$36,B108,AJE!$J$8:$J$36) -> 0 | I108: =G108+H108 -> 2721.08 | J108: PR
B109: 3 | C109: אלוקציות הנהלה | E109: =SUMIF(AJE!$B$8:$B$36,B109,AJE!$D$8:$D$36)-SUMIF(AJE!$G$8:$G$36,B109,AJE!$I$8:$I$36) -> -640307.23 | F109: =D109+E109 -> -640307.23 | H109: =SUMIF(AJE!$B$8:$B$36,B109,AJE!$E$8:$E$36)-SUMIF(AJE!$G$8:$G$36,B109,AJE!$J$8:$J$36) -> -176539.08 | I109: =G109+H109 -> -176539.08 | J109: Overhead set off
...

Sheet AJE
G2: 45291 | H2: 3.627
B3: Additional Entries | G3: Averge | H3: 3.6
E4: 929080.21
B6: Debit | G6: Credit | L6: Description
B7: Account # | C7: Account name | D7: ₪ | E7: $ | G7: Account # | H7: Account name | I7: ₪ | J7: $
L10: לשלם
B11: 7810 | D11: =8100*2 -> 16200 | E11: =D11/$H$2 -> 4466.5012 | G11: 2701 | H11: =VLOOKUP(G11,TB!$B$2:$C$121,2,0) -> לשלם | I11: =D11 -> 16200 | J11: =E11 -> 4466.5012 | L11: הוצ לשלם שינדלר 11+12
B12: 7805 | D12: 4671 | E12: =D12/$H$2 -> 1287.8412 | G12: 2701 | H12: =VLOOKUP(G12,TB!$B$2:$C$121,2,0) -> לשלם | I12: =D12 -> 4671 | J12: =E12 -> 1287.8412 | L12: ארנונה 11+12
B13: 7450 | D13: =13755/1.17 -> 11756.41 | E13: =D13/$H$2 -> 3241.3593 | G13: 2701 | H13: =VLOOKUP(G13,TB!$B$2:$C$121,2,0) -> לשלם | I13: =D13 -> 11756.41 | J13: =E13 -> 3241.3593 | L13: רוני מסיאנו 12-23
L18: הפרשה לספקים בחובה
B19: 7450 | D19: 147034.74 | E19: =D19/$H$2 -> 40538.941 | G19: 3110 | H19: LINKEDIN | I19: =D19 -> 147034.74 | J19: =E19 -> 40538.941
B20: 7450 | D20: 7273.84 | E20: =D20/$H$2 -> 2005.4701 | G20: 3245 | H20: LinkedIN -ש"ח | I20: =D20 -> 7273.84 | J20: =E20 -> 2005.4701
B21: 7450 | D21: 1813.5 | E21: =D21/$H$2 -> 500 | G21: 3277 | H21: HubSpot Ireland Ltd | I21: =D21 -> 1813.5 | J21: =E21 -> 500
B22: 7301 | D22: 15461.12 | E22: =D22/$H$2 -> 4262.7847 | G22: 3099 | H22: אוטומט איט מלם תים בע"מ | I22: =D22 -> 15461.12 | J22: =E22 -> 4262.7847
B23: 7301 | D23: 5461 | E23: =D23/$H$2 -> 1505.6521 | G23: 3314 | H23: דורקם סהר | I23: =D23 -> 5461 | J23: =E23 -> 1505.6521
B24: 7305 | D24: 5787.57 | E24: =D24/$H$2 -> 1595.6907 | G24: 3119 | H24: NOTION LABS INC | I24: =D24 -> 5787.57 | J24: =E24 -> 1595.6907
B25: 7305 | D25: 1094.85 | E25: =D25/$H$2 -> 301.86104 | G25: 3123 | H25: GITHUB | I25: =D25 -> 1094.85 | J25: =E25 -> 301.86104
B26: 7301 | D26: 1669.21 | E26: =D26/$H$2 -> 460.21781 | G26: 3139 | H26: Amazon.co.UK | I26: =D26 -> 1669.21 | J26: =E26 -> 460.21781
B27: 7450 | D27: 3506.76 | E27: =D27/$H$2 -> 966.84864 | G27: 3338 | H27: מיסאנו רוני | I27: =D27 -> 3506.76 | J27: =E27 -> 966.84864
N29: סכומים בלישט
B30: 7560 | C30: COST+אנגליה שיווק | D30: =E30*H2 -> 1710764.6 | E30: ='TB UK'!E74 -> 471674.81 | G30: 2803 | I30: =D30 -> 1710764.6 | J30: =E30 -> 471674.81 | L30: COST + סכום בלישט 370484 | N30: 370487.32
B31: 7861 | C31: COST+אנגליה | D31: =E31*H3 -> 1000407.6 | E31: ='TB UK'!E75 -> 277890.99 | G31: 2803 | I31: =D31 -> 1000407.6 | J31: =E31 -> 277890.99 | L31: COST +סכום בלישט 218276 | N31: 218275.57
B32: 9002 | E32: 1081 | G32: 2803 | J32: =E32 -> 1081 | L32: הפרשי שער רק בדולרים
B35: 4 | C35: =VLOOKUP(B35,TB!$B$2:$C$121,2,0) -> אלוקציות RD | D35: ='אלוקציה הוצ'!C13 -> 640307.23 | E35: =D35/$H$2 -> 176539.08 | G35: 3 | H35: =VLOOKUP(G35,TB!$B$2:$C$121,2,0) -> אלוקציות הנהלה | I35: =D35 -> 640307.23 | J35: =E35 -> 176539.08 | L35: אלוקציות הוצאות RD

Sheet TB UK
A1: Currency | D1: GBP | E1: AJE | F1: Total GPB | G1: USD | H1: AJE | I1: Total USD
A2: Account Code | B2: Account | C2: Account Type | D2: 45291 | E2: 45291 | F2: 45291 | G2: 45291 | H2: 45291 | I2: 45291 | Q2: Currency | T2: GBP | U2: USD
A3: 200 | B3: S&M Cost plus revenue | C3: Revenue | D3: =VLOOKUP(A3,$Q$4:$U$67,4,0) -> -370487 | F3: =D3+E3 -> -370487 | G3: =VLOOKUP(A3,$Q$4:$U$67,5,0) -> -471674.41 | I3: =G3+H3 -> -471674.41 | J3: COST + UK S&M | Q3: Account Code | R3: Account | S3: Account Type | T3: 45291 | U3: 45291
A4: 200a | B4: G&A Cost plus revenue | C4: Revenue | D4: =VLOOKUP(A4,$Q$4:$U$67,4,0) -> -218276 | F4: =D4+E4 -> -218276 | G4: =VLOOKUP(A4,$Q$4:$U$67,5,0) -> -277891.54 | I4: =G4+H4 -> -277891.54 | J4: COST + UK G&A | Q4: 200 | R4: S&M Cost plus revenue | S4: Revenue | T4: -370487 | U4: -471674.41 | V4: =VLOOKUP(Q4,$A$3:$A$63,1,0) -> 200
A5: 270 | B5: Interest Income | C5: Overhead | D5: =VLOOKUP(A5,$Q$4:$U$67,4,0) -> -556.5 | F5: =D5+E5 -> -556.5 | G5: =VLOOKUP(A5,$Q$4:$U$67,5,0) -> -708.49128 | I5: =G5+H5 -> -708.49128 | J5: Financial expenses (income) | Q5: 200a | R5: G&A Cost plus revenue | S5: Revenue | T5: -218276 | U5: -277891.54 | V5: =VLOOKUP(Q5,$A$3:$A$63,1,0) -> 200a
A6: 310 | B6: Cost of Goods Sold | C6: Overhead | D6: =VLOOKUP(A6,$Q$4:$U$67,4,0) -> 103.2 | F6: =D6+E6 -> 103.2 | G6: =VLOOKUP(A6,$Q$4:$U$67,5,0) -> 131.38598 | I6: =G6+H6 -> 131.38598 | J6: Other - G&A | Q6: 270 | R6: Interest Income | S6: Revenue | T6: -556.5 | U6: -708.49128 | V6: =VLOOKUP(Q6,$A$3:$A$63,1,0) -> 270
A7: 400 | B7: G&A - Marketing | C7: Overhead | D7: =VLOOKUP(A7,$Q$4:$U$67,4,0) -> 8690 | F7: =D7+E7 -> 8690 | G7: =VLOOKUP(A7,$Q$4:$U$67,5,0) -> 11063.413 | I7: =G7+H7 -> 11063.413 | J7: Marketing | Q7: 310 | R7: Cost of Goods Sold | S7: Direct Costs | T7: 103.2 | U7: 131.38598 | V7: =VLOOKUP(Q7,$A$3:$A$63,1,0) -> 310
A8: 401 | B8: G&A - Audit and Accounting | C8: Overhead | D8: =VLOOKUP(A8,$Q$4:$U$67,4,0) -> 38064.35 | F8: =D8+E8 -> 38064.35 | G8: =VLOOKUP(A8,$Q$4:$U$67,5,0) -> 48460.485 | I8: =G8+H8 -> 48460.485 | J8: Accounting & Financial Services | Q8: 400 | R8: G&A - Marketing | S8: Overhead | T8: 8690 | U8: 11063.413 | V8: =VLOOKUP(Q8,$A$3:$A$63,1,0) -> 400
A9: 404 | B9: Finance - Bank Charges And Fees | C9: Overhead | D9: =VLOOKUP(A9,$Q$4:$U$67,4,0) -> 82.62 | F9: =D9+E9 -> 82.62 | G9: =VLOOKUP(A9,$Q$4:$U$67,5,0) -> 105.18517 | I9: =G9+H9 -> 105.18517 | J9: Financial expenses (income) | Q9: 401 | R9: G&A - Audit and Accounting | S9: Overhead | T9: 38064.35 | U9: 48460.485 | V9: =VLOOKUP(Q9,$A$3:$A$63,1,0) -> 401
A10: 412 | B10: Consulting | C10: Overhead | D10: =VLOOKUP(A10,$Q$4:$U$67,4,0) -> 0 | F10: =D10+E10 -> 0 | G10: =VLOOKUP(A10,$Q$4:$U$67,5,0) -> 0 | I10: =G10+H10 -> 0 | J10: Legal & Professional Services | Q10: 404 | R10: Finance - Bank Charges And Fees | S10: Overhead | T10: 82.62 | U10: 105.18517 | V10: =VLOOKUP(Q10,$A$3:$A$63,1,0) -> 404
A11: 416 | B11: G&A - Depreciation Expenses | C11: Overhead | D11: =VLOOKUP(A11,$Q$4:$U$67,4,0) -> 330 | F11: =D11+E11 -> 330 | G11: =VLOOKUP(A11,$Q$4:$U$67,5,0) -> 420.1296 | I11: =G11+H11 -> 420.1296 | J11: Depreciation | Q11: 412 | R11: Consulting | S11: Overhead | T11: 0 | U11: 0 | V11: =VLOOKUP(Q11,$A$3:$A$63,1,0) -> 412
A12: 418 | B12: Charitable and Political Donations | C12: Overhead | D12: =VLOOKUP(A12,$Q$4:$U$67,4,0) -> 1315 | F12: =D12+E12 -> 1315 | G12: =VLOOKUP(A12,$Q$4:$U$67,5,0) -> 1674.1528 | I12: =G12+H12 -> 1674.1528 | J12: Other - G&A | Q12: 416 | R12: G&A - Depreciation Expenses | S12: Overhead | T12: 330 | U12: 420.1296 | V12: =VLOOKUP(Q12,$A$3:$A$63,1,0) -> 416
A13: 420 | B13: Entertainment-100% business | C13: Overhead | D13: =VLOOKUP(A13,$Q$4:$U$67,4,0) -> 3066.62 | F13: =D13+E13 -> 3066.62 | G13: =VLOOKUP(A13,$Q$4:$U$67,5,0) -> 3904.1753 | I13: =G13+H13 -> 3904.1753 | J13: Welfare | Q13: 418 | R13: Charitable and Political Donations | S13: Overhead | T13: 1315 | U13: 1674.1528 | V13: =VLOOKUP(Q13,$A$3:$A$63,1,0) -> 418
A14: 426 | B14: G&A - Fines and penalties | C14: Overhead | D14: =VLOOKUP(A14,$Q$4:$U$67,4,0) -> 701.07 | F14: =D14+E14 -> 701.07 | G14: =VLOOKUP(A14,$Q$4:$U$67,5,0) -> 892.54624 | I14: =G14+H14 -> 892.54624 | J14: Financial expenses (income) | Q14: 420 | R14: Entertainment-100% business | S14: Overhead | T14: 3066.62 | U14: 3904.1753 | V14: =VLOOKUP(Q14,$A$3:$A$63,1,0) -> 420
A15: 429 | B15: G&A - Office Equipment And Miscellaneous | C15: Overhead | D15: =VLOOKUP(A15,$Q$4:$U$67,4,0) -> 542.71 | F15: =D15+E15 -> 542.71 | G15: =VLOOKUP(A15,$Q$4:$U$67,5,0) -> 690.93496 | I15: =G15+H15 -> 690.93496 | J15: Maintenance | Q15: 426 | R15: G&A - Fines and penalties | S15: Overhead | T15: 701.07 | U15: 892.54624 | V15: =VLOOKUP(Q15,$A$3:$A$63,1,0) -> 426
A16: 433 | B16: G&A - Insurance | C16: Overhead | D16: =VLOOKUP(A16,$Q$4:$U$67,4,0) -> 1545 | F16: =D16+E16 -> 1545 | G16: =VLOOKUP(A16,$Q$4:$U$67,5,0) -> 1966.9704 | I16: =G16+H16 -> 1966.9704 | J16: Insurance | Q16: 429 | R16: G&A - Office Equipment And Miscellaneous | S16: Overhead | T16: 542.71 | U16: 690.93496 | V16: =VLOOKUP(Q16,$A$3:$A$63,1,0) -> 429
A17: 437 | B17: Finance - Interest | C17: Overhead | D17: =VLOOKUP(A17,$Q$4:$U$67,4,0) -> -173.43 | F17: =D17+E17 -> -173.43 | G17: =VLOOKUP(A17,$Q$4:$U$67,5,0) -> -220.7972 | I17: =G17+H17 -> -220.7972 | J17: Financial expenses (income) | Q17: 433 | R17: G&A - Insurance | S17: Overhead | T17: 1545 | U17: 1966.9704 | V17: =VLOOKUP(Q17,$A$3:$A$63,1,0) -> 433
... A21: 477 | B21: S&M - Base Salary | C21: Overhead | D21: =VLOOKUP(A21,$Q$4:$U$67,4,0) -> 299089.7 | F21: =D21+E21 -> 299089.7 | G21: =VLOOKUP(A21,$Q$4:$U$67,5,0) -> 380777.08 | I21: =G21+H21 -> 380777.08 | J21: Salaries and social benefits - R&D | Q21: 469 | R21: G&A - Rent Expenses | S21: Overhead | T21: 13371.92 | U21: 17024.059 | V21: =VLOOKUP(Q21,$A$3:$A$63,1,0) -> 469
A22: 477a | B22: G&A - Base Salary | C22: Overhead | D22: =VLOOKUP(A22,$Q$4:$U$67,4,0) -> 105000 | F22: =D22+E22 -> 105000 | G22: =VLOOKUP(A22,$Q$4:$U$67,5,0) -> 133677.6 | I22: =G22+H22 -> 133677.6 | J22: Salaries and social benefits - G&A | Q22: 477 | R22: S&M - Base Salary | S22: Overhead | T22: 299089.7 | U22: 380777.08 | V22: =VLOOKUP(Q22,$A$3:$A$63,1,0) -> 477
A23: 477b | B23: S&M - Vacation Expenses | C23: Overhead | D23: =VLOOKUP(A23,$Q$4:$U$67,4,0) -> 509.28 | F23: =D23+E23 -> 509.28 | G23: =VLOOKUP(A23,$Q$4:$U$67,5,0) -> 648.37455 | I23: =G23+H23 -> 648.37455 | J23: Salaries and social benefits - R&D | Q23: 477a | R23: G&A - Base Salary | S23: Overhead | T23: 105000 | U23: 133677.6 | V23: =VLOOKUP(Q23,$A$3:$A$63,1,0) -> 477a
A24: 479 | B24: S&M - Employer Taxes | C24: Overhead | D24: =VLOOKUP(A24,$Q$4:$U$67,4,0) -> 37717.97 | F24: =D24+E24 -> 37717.97 | G24: =VLOOKUP(A24,$Q$4:$U$67,5,0) -> 48019.502 | I24: =G24+H24 -> 48019.502 | J24: Salaries and social benefits - R&D | Q24: 477b | R24: S&M - Vacation Expenses | S24: Overhead | T24: 509.28 | U24: 648.37455 | V24: =VLOOKUP(Q24,$A$3:$A$63,1,0) -> 477b
A25: 479a | B25: G&A - National Insurance | C25: Overhead | D25: =VLOOKUP(A25,$Q$4:$U$67,4,0) -> 13287.02 | F25: =D25+E25 -> 13287.02 | G25: =VLOOKUP(A25,$Q$4:$U$67,5,0) -> 16915.971 | I25: =G25+H25 -> 16915.971 | J25: Salaries and social benefits - G&A | Q25: 479 | R25: S&M - Employer Taxes | S25: Overhead | T25: 37717.97 | U25: 48019.502 | V25: =VLOOKUP(Q25,$A$3:$A$63,1,0) -> 479
A26: 481 | B26: Recruitment | C26: Overhead | D26: =VLOOKUP(A26,$Q$4:$U$67,4,0) -> 0 | F26: =D26+E26 -> 0 | G26: =VLOOKUP(A26,$Q$4:$U$67,5,0) -> 0 | I26: =G26+H26 -> 0 | Q26: 479a | R26: G&A - National Insurance | S26: Overhead | T26: 13287.02 | U26: 16915.971 | V26: =VLOOKUP(Q26,$A$3:$A$63,1,0) -> 479a
A27: 482 | B27: S&M - Pension | C27: Overhead | D27: =VLOOKUP(A27,$Q$4:$U$67,4,0) -> 8932.88 | F27: =D27+E27 -> 8932.88 | G27: =VLOOKUP(A27,$Q$4:$U$67,5,0) -> 11372.628 | I27: =G27+H27 -> 11372.628 | J27: Salaries and social benefits - R&D | Q27: 481 | R27: Recruitment | S27: Overhead | T27: 0 | U27: 0 | V27: =VLOOKUP(Q27,$A$3:$A$63,1,0) -> 481
A28: 482a | B28: G&A - Pension | C28: Overhead | D28: =VLOOKUP(A28,$Q$4:$U$67,4,0) -> 3113.65 | F28: =D28+E28 -> 3113.65 | G28: =VLOOKUP(A28,$Q$4:$U$67,5,0) -> 3964.0501 | I28: =G28+H28 -> 3964.0501 | J28: Salaries and social benefits - G&A | Q28: 482 | R28: S&M - Pension | S28: Overhead | T28: 8932.88 | U28: 11372.628 | V28: =VLOOKUP(Q28,$A$3:$A$63,1,0) -> 482
A29: 483 | B29: Medical Insurance | C29: Overhead | D29: =VLOOKUP(A29,$Q$4:$U$67,4,0) -> 3766.14 | F29: =D29+E29 -> 3766.14 | G29: =VLOOKUP(A29,$Q$4:$U$67,5,0) -> 4794.7482 | I29: =G29+H29 -> 4794.7482 | J29: Salaries and social benefits - G&A | M29: זה בטעות לא נכנס לחישוב של COST + לא מהותי | Q29: 482a | R29: G&A - Pension | S29: Overhead | T29: 3113.65 | U29: 3964.0501 | V29: =VLOOKUP(Q29,$A$3:$A$63,1,0) -> 482a
A30: 485 | B30: Subscriptions | C30: Overhead | D30: =VLOOKUP(A30,$Q$4:$U$67,4,0) -> 3429.08 | F30: =D30+E30 -> 3429.08 | G30: =VLOOKUP(A30,$Q$4:$U$67,5,0) -> 4365.6303 | I30: =G30+H30 -> 4365.6303 | J30: Maintenance | Q30: 483 | R30: Medical Insurance | S30: Overhead | T30: 3766.14 | U30: 4794.7482 | V30: =VLOOKUP(Q30,$A$3:$A$63,1,0) -> 483
A31: 486 | B31: G&A - Refreshments | C31: Overhead | D31: =VLOOKUP(A31,$Q$4:$U$67,4,0) -> 470.4 | F31: =D31+E31 -> 470.4 | G31: =VLOOKUP(A31,$Q$4:$U$67,5,0) -> 598.87565 | I31: =G31+H31 -> 598.87565 | J31: Welfare | Q31: 485 | R31: Subscriptions | S31: Overhead | T31: 3429.08 | U31: 4365.6303 | V31: =VLOOKUP(Q31,$A$3:$A$63,1,0) -> 485
A32: 493 | B32: G&A - Travel | C32: Overhead | D32: =VLOOKUP(A32,$Q$4:$U$67,4,0) -> 2727.52 | F32: =D32+E32 -> 2727.52 | G32: =VLOOKUP(A32,$Q$4:$U$67,5,0) -> 3472.4603 | I32: =G32+H32 -> 3472.4603 | J32: Other - G&A | Q32: 486 | R32: G&A - Refreshments | S32: Overhead | T32: 470.4 | U32: 598.87565 | V32: =VLOOKUP(Q32,$A$3:$A$63,1,0) -> 486
A33: 494 | B33: S&M - Travel Abroad | C33: Overhead | D33: =VLOOKUP(A33,$Q$4:$U$67,4,0) -> 1952.52 | F33: =D33+E33 -> 1952.52 | G33: =VLOOKUP(A33,$Q$4:$U$67,5,0) -> 2485.7923 | I33: =G33+H33 -> 2485.7923 | J33: Travel | Q33: 493 | R33: G&A - Travel | S33: Overhead | T33: 2727.52 | U33: 3472.4603 | V33: =VLOOKUP(Q33,$A$3:$A$63,1,0) -> 493
A34: 494a | B34: G&A - Travel Abroad | C34: Overhead | D34: =VLOOKUP(A34,$Q$4:$U$67,4,0) -> 3678.11 | F34: =D34+E34 -> 3678.11 | G34: =VLOOKUP(A34,$Q$4:$U$67,5,0) -> 4682.6754 | I34: =G34+H34 -> 4682.6754 | J34: Travel G&A | Q34: 494 | R34: S&M - Travel Abroad | S34: Overhead | T34: 1952.52 | U34: 2485.7923 | V34: =VLOOKUP(Q34,$A$3:$A$63,1,0) -> 494
A35: 497 | B35: Bank Revaluations | C35: Expense | D35: =VLOOKUP(A35,$Q$4:$U$67,4,0) -> -2944.96 | F35: =D35+E35 -> -2944.96 | G35: =VLOOKUP(A35,$Q$4:$U$67,5,0) -> -3749.2875 | I35: =G35+H35 -> -3749.2875 | J35: Other - G&A | Q35: 494a | R35: G&A - Travel Abroad | S35: Overhead | T35: 3678.11 | U35: 4682.6754 | V35: =VLOOKUP(Q35,$A$3:$A$63,1,0) -> 494a
A36: 498 | B36: Unrealised Currency Gains | C36: Expense | D36: =VLOOKUP(A36,$Q$4:$U$67,4,0) -> 17.1 | F36: =D36+E36 -> 17.1 | G36: =VLOOKUP(A36,$Q$4:$U$67,5,0) -> 29376.728 | I36: =G36+H36 -> 29376.728 | J36: Financial expenses (income) | Q36: 497 | R36: Bank Revaluations | S36: Expense | T36: -2944.96 | U36: -3749.2875 | V36: =VLOOKUP(Q36,$A$3:$A$63,1,0) -> 497
A37: 499 | B37: Finance - Exchange Rate Differences | C37: Expense | D37: =VLOOKUP(A37,$Q$4:$U$67,4,0) -> -6068.91 | F37: =D37+E37 -> -6068.91 | G37: =VLOOKUP(A37,$Q$4:$U$67,5,0) -> -7726.4507 | I37: =G37+H37 -> -7726.4507 | J37: Financial expenses (income) | Q37: 498 | R37: Unrealised Currency Gains | S37: Expense | T37: 17.1 | U37: 29376.728 | V37: =VLOOKUP(Q37,$A$3:$A$63,1,0) -> 498
A38: Deposit account- 0401 | B38: Deposit Account | C38: Bank | D38: =VLOOKUP(A38,$Q$4:$U$67,4,0) -> 241139.88 | F38: =D38+E38 -> 241139.88 | G38: =VLOOKUP(A38,$Q$4:$U$67,5,0) -> 307000 | I38: =G38+H38 -> 307000 | J38: Cash and cash equivalents | Q38: 499 | R38: Finance - Exchange Rate Differences | S38: Expense | T38: -6068.91 | U38: -7726.4507 | V38: =VLOOKUP(Q38,$A$3:$A$63,1,0) -> 499
A39: Cash Bank Deposits | B39: Cash Bank Deposits | C39: Bank | D39: =VLOOKUP(A39,$Q$4:$U$67,4,0) -> 0 | F39: =D39+E39 -> 0 | G39: =VLOOKUP(A39,$Q$4:$U$67,5,0) -> 0 | I39: =G39+H39 -> 0 | J39: Cash and cash equivalents | K39: Name of the bank | L39: In TB | M39: In the bank | N39: Diffrences | Q39: 500 | R39: Corporation Tax | S39: Overhead | T39: 0 | U39: 0 | V39: =VLOOKUP(Q39,$A$3:$A$63,1,0) -> #N/A
A40: GetCtrl UK Ltd | B40: GetCtrl UK Ltd | C40: Bank | D40: =VLOOKUP(A40,$Q$4:$U$67,4,0) -> 78089.08 | F40: =D40+E40 -> 78089.08 | G40: =VLOOKUP(A40,$Q$4:$U$67,5,0) -> 99416.77 | I40: =G40+H40 -> 99416.77 | J40: Cash and cash equivalents | K40: GetCtrl UK Ltd HSBC GPB | L40: =D40 -> 78089.08 | M40: 78089.08 | N40: =L40-M40 -> 0 | Q40: Deposit Account | R40: Deposit Account | S40: Bank | T40: 0 | U40: 0 | V40: =VLOOKUP(Q40,$A$3:$A$63,1,0) -> #N/A
A41: Wise Bank USD | B41: Wise Bank USD | C41: Bank | D41: =VLOOKUP(A41,$Q$4:$U$67,4,0) -> 21.17 | F41: =D41+E41 -> 21.17 | G41: =VLOOKUP(A41,$Q$4:$U$67,5,0) -> 26.95195 | I41: =G41+H41 -> 26.95195 | J41: Cash and cash equivalents | K41: Wise Bank USD | L41: =G41 -> 26.95195 | M41: 26.95 | N41: =L41-M41 -> 0.0019504 | Q41: Intercompany USA. | R41: Intercompany USA. | S41: Bank | T41: -286260.37 | U41: -364443.8 | V41: =VLOOKUP(Q41,$A$3:$A$63,1,0) -> Intercompany USA.
A42: Wise Bank GBP | B42: Wise Bank GBP | C42: Bank | D42: =VLOOKUP(A42,$Q$4:$U$67,4,0) -> 4496.56 | F42: =D42+E42 -> 4496.56 | G42: =VLOOKUP(A42,$Q$4:$U$67,5,0) -> 5724.6605 | I42: =G42+H42 -> 5724.6605 | J42: Cash and cash equivalents | K42: Wise Bank GBP | L42: =D42 -> 4496.56 | M42: 4496.56 | N42: =L42-M42 -> 0 | Q42: Cash Bank Deposits | R42: Cash Bank Deposits | S42: Bank | T42: 0 | U42: 0 | V42: =VLOOKUP(Q42,$A$3:$A$63,1,0) -> Cash Bank Deposits
A43: SVB GBP 20251475 | B43: SVB GBP 20251475 | C43: Bank | D43: =VLOOKUP(A43,$Q$4:$U$67,4,0) -> 0 | F43: =D43+E43 -> 0 | G43: =VLOOKUP(A43,$Q$4:$U$67,5,0) -> 0 | I43: =G43+H43 -> 0 | J43: Cash and cash equivalents | K43: SVB GBP 20251475 | N43: =L43-M43 -> 0 | Q43: GetCtrl UK Ltd | R43: GetCtrl UK Ltd | S43: Bank | T43: 78089.08 | U43: 99416.77 | V43: =VLOOKUP(Q43,$A$3:$A$63,1,0) -> GetCtrl UK Ltd
A44: GetCtrl UK Ltd USD | B44: GetCtrl UK Ltd USD | C44: Bank | D44: =VLOOKUP(A44,$Q$4:$U$67,4,0) -> 806.51 | F44: =D44+E44 -> 806.51 | G44: =VLOOKUP(A44,$Q$4:$U$67,5,0) -> 1026.784 | I44: =G44+H44 -> 1026.784 | J44: Cash and cash equivalents | K44: GetCtrl UK Ltd USD HSBC | L44: =G44 -> 1026.784 | M44: 1026.78 | N44: =L44-M44 -> 0.0040112 | Q44: Deposit account- 0401 | R44: Deposit account- 0401 | S44: Bank | T44: 241139.88 | U44: 307000 | V44: =VLOOKUP(Q44,$A$3:$A$63,1,0) -> Deposit account- 0401
A45: 610 | B45: Accounts Receivable | C45: Current Asset | D45: =VLOOKUP(A45,$Q$4:$U$67,4,0) -> 588763 | F45: =D45+E45 -> 588763 | G45: =VLOOKUP(A45,$Q$4:$U$67,5,0) -> 749565.95 | I45: =G45+H45 -> 749565.95 | J45: Related party | Q45: Wise Bank USD | R45: Wise Bank USD | S45: Bank | T45: 21.17 | U45: 26.95195
A46: 620 | B46: Prepayments | C46: Current Asset | D46: =VLOOKUP(A46,$Q$4:$U$67,4,0) -> 4310.55 | F46: =D46+E46 -> 4310.55 | G46: =VLOOKUP(A46,$Q$4:$U$67,5,0) -> 5487.8474 | I46: =G46+H46 -> 5487.8474 | J46: Prepaid expenses | K46: Cash Bank Deposits | L46: =G38 -> 307000 | M46: 307000 | N46: =L46-M46 -> 0.0040256 | Q46: Wise Bank GBP | R46: Wise Bank GBP | S46: Bank | T46: 4496.56 | U46: 5724.6605 | V46: =VLOOKUP(Q46,$A$3:$A$63,1,0) -> Wise Bank GBP
A47: 621 | B47: Rent Deposit | C47: Current Asset | D47: =VLOOKUP(A47,$Q$4:$U$67,4,0) -> 2616.72 | F47: =D47+E47 -> 2616.72 | G47: =VLOOKUP(A47,$Q$4:$U$67,5,0) -> 3331.3986 | I47: =G47+H47 -> 3331.3986 | J47: Prepaid expenses | Q47: SVB GBP 20251475 | R47: SVB GBP 20251475 | S47: Bank | T47: 0 | U47: 0 | V47: =VLOOKUP(Q47,$A$3:$A$63,1,0) -> SVB GBP 20251475
A48: 710 | B48: Office Equipment | C48: Fixed Asset | D48: =VLOOKUP(A48,$Q$4:$U$67,4,0) -> 2016.5 | F48: =D48+E48 -> 2016.5 | G48: =VLOOKUP(A48,$Q$4:$U$67,5,0) -> 2567.2465 | I48: =G48+H48 -> 2567.2465 | J48: Property and Equipment, Net | Q48: GetCtrl UK Ltd USD | R48: GetCtrl UK Ltd USD | S48: Bank | T48: 806.51 | U48: 1026.784 | V48: =VLOOKUP(Q48,$A$3:$A$63,1,0) -> GetCtrl UK Ltd USD
A49: 711 | B49: Less Accumulated Depreciation on Office Equipment | C49: Fixed Asset | D49: =VLOOKUP(A49,$Q$4:$U$67,4,0) -> -1035.96 | F49: =D49+E49 -> -1035.96 | G49: =VLOOKUP(A49,$Q$4:$U$67,5,0) -> -1318.9014 | I49: =G49+H49 -> -1318.9014 | J49: Property and Equipment, Net | Q49: 610 | R49: Accounts Receivable | S49: Current Asset | T49: 588763 | U49: 749565.95 | V49: =VLOOKUP(Q49,$A$3:$A$63,1,0) -> 610
A50: 802 | B50: Intercompany Israel | C50: Current Asset | D50: =VLOOKUP(A50,$Q$4:$U$67,4,0) -> -510259.26 | F50: =D50+E50 -> -510259.26 | G50: =VLOOKUP(A50,$Q$4:$U$67,5,0) -> -649621.27 | I50: =G50+H50 -> -649621.27 | J50: Related party | Q50: 620 | R50: Prepayments | S50: Current Asset | T50: 4310.55 | U50: 5487.8474 | V50: =VLOOKUP(Q50,$A$3:$A$63,1,0) -> 620
A51: 800 | B51: Accounts Payable | C51: Current Liability | D51: =VLOOKUP(A51,$Q$4:$U$67,4,0) -> -16775.09 | F51: =D51+E51 -> -16775.09 | G51: =VLOOKUP(A51,$Q$4:$U$67,5,0) -> -21356.703 | I51: =G51+H51 -> -21356.703 | J51: Accounts payable | Q51: 621 | R51: Rent Deposit | S51: Current Asset | T51: 2616.72 | U51: 3331.3986 | V51: =VLOOKUP(Q51,$A$3:$A$63,1,0) -> 621
A52: Intercompany USA. | B52: Intercompany USA | C52: Current Liability | D52: =VLOOKUP(A52,$Q$4:$U$67,4,0) -> -286260.37 | F52: =D52+E52 -> -286260.37 | G52: =VLOOKUP(A52,$Q$4:$U$67,5,0) -> -364443.8 | I52: =G52+H52 -> -364443.8 | J52: Related party | Q52: 710 | R52: Office Equipment | S52: Fixed Asset | T52: 2016.5 | U52: 2567.2465 | V52: =VLOOKUP(Q52,$A$3:$A$63,1,0) -> 710
A53: 806 | B53: Employees Reimbursment | C53: Current Liability | D53: =VLOOKUP(A53,$Q$4:$U$67,4,0) -> 361.06 | F53: =D53+E53 -> 361.06 | G53: =VLOOKUP(A53,$Q$4:$U$67,5,0) -> 459.67271 | I53: =G53+H53 -> 459.67271 | J53: Employee payables & institutions | Q53: 711 | R53: Less Accumulated Depreciation on Office Equipment | S53: Fixed Asset | T53: -1035.96 | U53: -1318.9014 | V53: =VLOOKUP(Q53,$A$3:$A$63,1,0) -> 711
A54: 811 | B54: Credit Cards | C54: Current Liability | D54: =VLOOKUP(A54,$Q$4:$U$67,4,0) -> 275.06 | F54: =D54+E54 -> 275.06 | G54: =VLOOKUP(A54,$Q$4:$U$67,5,0) -> 350.18439 | I54: =G54+H54 -> 350.18439 | J54: Accounts payable | Q54: 802 | R54: Intercompany Israel | S54: Current Asset | T54: -510259.26 | U54: -649621.27 | V54: =VLOOKUP(Q54,$A$3:$A$63,1,0) -> 802
A55: 814 | B55: Salary | C55: Current Liability | D55: =VLOOKUP(A55,$Q$4:$U$67,4,0) -> 400.4 | F55: =D55+E55 -> 400.4 | G55: =VLOOKUP(A55,$Q$4:$U$67,5,0) -> 509.75725 | I55: =G55+H55 -> 509.75725 | J55: Employee payables & institutions | Q55: 800 | R55: Accounts Payable | S55: Current Liability | T55: -16775.09 | U55: -21356.703 | V55: =VLOOKUP(Q55,$A$3:$A$63,1,0) -> 800
A56: 820 | B56: Input VAT | C56: Current Liability | D56: =VLOOKUP(A56,$Q$4:$U$67,4,0) -> 2845.44 | F56: =D56+E56 -> 2845.44 | G56: =VLOOKUP(A56,$Q$4:$U$67,5,0) -> 3622.5866 | I56: =G56+H56 -> 3622.5866 | J56: Account Receivable-VAT+TAX | Q56: 806 | R56: Employees Reimbursment | S56: Current Liability | T56: 361.06 | U56: 459.67271 | V56: =VLOOKUP(Q56,$A$3:$A$63,1,0) -> 806
A57: 825 | B57: Payroll Income Tax | C57: Current Liability | D57: =VLOOKUP(A57,$Q$4:$U$67,4,0) -> -12217.17 | F57: =D57+E57 -> -12217.17 | G57: =VLOOKUP(A57,$Q$4:$U$67,5,0) -> -15553.923 | I57: =G57+H57 -> -15553.923 | J57: Employee payables & institutions | Q57: 811 | R57: Credit Cards | S57: Current Liability | T57: 275.06 | U57: 350.18439 | V57: =VLOOKUP(Q57,$A$3:$A$63,1,0) -> 811
A58: 830 | B58: Provision for Corporation Tax | C58: Current Liability | D58: =VLOOKUP(A58,$Q$4:$U$67,4,0) -> -10363 | F58: =D58+E58 -> -10363 | G58: =VLOOKUP(A58,$Q$4:$U$67,5,0) -> -13193.343 | I58: =G58+H58 -> -13193.343 | J58: Account Receivable-VAT+TAX | Q58: 814 | R58: Salary | S58: Current Liability | T58: 400.4 | U58: 509.75725 | V58: =VLOOKUP(Q58,$A$3:$A$63,1,0) -> 814
A59: 858 | B59: Pension | C59: Current Liability | D59: =VLOOKUP(A59,$Q$4:$U$67,4,0) -> -1797.84 | F59: =D59+E59 -> -1797.84 | G59: =VLOOKUP(A59,$Q$4:$U$67,5,0) -> -2288.8661 | I59: =G59+H59 -> -2288.8661 | J59: Employee payables & institutions | Q59: 820 | R59: Input VAT | S59: Current Liability | T59: 2845.44 | U59: 3622.5866 | V59: =VLOOKUP(Q59,$A$3:$A$63,1,0) -> 820
A60: 850 | B60: Suspense | C60: Current Liability | D60: =VLOOKUP(A60,$Q$4:$U$67,4,0) -> 0.03 | F60: =D60+E60 -> 0.03 | G60: =VLOOKUP(A60,$Q$4:$U$67,5,0) -> 0.0381936 | I60: =G60+H60 -> 0.0381936 | J60: Accounts payable | Q60: 825 | R60: Payroll Income Tax | S60: Current Liability | T60: -12217.17 | U60: -15553.923 | V60: =VLOOKUP(Q60,$A$3:$A$63,1,0) -> 825
A61: 920 | B61: Deferred Tax | C61: Non-current Liability | D61: =VLOOKUP(A61,$Q$4:$U$67,4,0) -> 275 | F61: =D61+E61 -> 275 | G61: =VLOOKUP(A61,$Q$4:$U$67,5,0) -> 350.108 | I61: =G61+H61 -> 350.108 | J61: Accumulated deficit | Q61: 830 | R61: Provision for Corporation Tax | S61: Current Liability | T61: -10363 | U61: -13193.343 | V61: =VLOOKUP(Q61,$A$3:$A$63,1,0) -> 830
A62: 950 | B62: Capital - x,xxx Ordinary Shares | C62: Equity | D62: =VLOOKUP(A62,$Q$4:$U$67,4,0) -> -1 | F62: =D62+E62 -> -1 | G62: =VLOOKUP(A62,$Q$4:$U$67,5,0) -> -1.27312 | I62: =G62+H62 -> -1.27312 | J62: Accumulated deficit | Q62: 850 | R62: Suspense | S62: Current Liability | T62: 0.03 | U62: 0.0381936 | V62: =VLOOKUP(Q62,$A$3:$A$63,1,0) -> 850
A63: 960 | B63: Retained Earnings | C63: Equity | D63: =VLOOKUP(A63,$Q$4:$U$67,4,0) -> -43959.33 | F63: =D63+E63 -> -43959.33 | G63: =VLOOKUP(A63,$Q$4:$U$67,5,0) -> -85320.46 | I63: =G63+H63 -> -85320.46 | J63: Accumulated deficit | K63: מתאים דוחות 2022 | Q63: 858 | R63: Pension | S63: Current Liability | T63: -1797.84 | U63: -2288.8661 | V63: =VLOOKUP(Q63,$A$3:$A$63,1,0) -> 858
D64: =SUM(D3:D63) -> -2.0372681e-10 | E64: =SUM(E3:E63) -> 0 | F64: =SUM(F3:F63) -> -2.0372681e-10 | G64: =SUM(G3:G63) -> -1.7462298e-10 | H64: =SUM(H3:H63) -> 0 | I64: =SUM(I3:I63) -> -1.7462298e-10 | Q64: 920 | R64: Deferred Tax | S64: Non-current Liability | T64: 275 | U64: 350.108 | V64: =VLOOKUP(Q64,$A$3:$A$63,1,0) -> 920
Q65: 950 | R65: Capital - x,xxx Ordinary Shares | S65: Equity | T65: -1 | U65: -1.27312 | V65: =VLOOKUP(Q65,$A$3:$A$63,1,0) -> 950
C66: PL | D66: =SUM(D3:D37) -> -43747.94 | E66: =SUM(E3:E37) -> 0 | F66: =SUM(F3:F37) -> -43747.94 | G66: =SUM(G3:G37) -> -26341.42 | H66: =SUM(H3:H37) -> 0 | I66: =SUM(I3:I37) -> -26341.42 | Q66: 960 | R66: Retained Earnings | S66: Equity | T66: -43959.33 | U66: -85320.46 | V66: =VLOOKUP(Q66,$A$3:$A$63,1,0) -> 960
C68: Cost + Calculation | D68: GPB | E68: USD | R68: Total | T68: =SUM(T4:T67) -> -1.7462298e-10 | U68: =SUM(U4:U67) -> 0
C69: All eepenses without finance | D69: =SUM(F5:F37)-F37-F35-F36-F29 -> 550245.69 | E69: =SUM(G5:G37)-G37-G35-G36-G29 -> 700528.79
C70: S&M expnses | D70: =+D21+D23+D24+D27 -> 346249.83 | E70: =+I21+I23+I24+I27 -> 440817.58
C71: G&A expnses | D71: =D69-D70 -> 203995.86 | E71: =E69-E70 -> 259711.21
C74: Expenses with additional cost +7% for S&M | D74: =D70*1.07 -> 370487.32 | E74: =E70*1.07 -> 471674.81
C75: Expenses with additional cost +7% for G&A | D75: =D71*1.07 -> 218275.57 | E75: =E71*1.07 -> 277890.99
D76: =SUM(D74:D75) -> 588762.89 | E76: =SUM(E74:E75) -> 749565.81
C80: Total payroll | D80: =D21+D22+D23+D24+D25+D27 -> 464536.85
C84: S&M - Base Salary | D84: Overhead | E84: 299089.7
C85: G&A - Base Salary | D85: Overhead | E85: 105000
C86: S&M - Employer Taxes | D86: Overhead | E86: 37717.97
C87: G&A - National Insurance | D87: Overhead | E87: 13287.02
C88: S&M - Pension | D88: Overhead | E88: 8932.88
C89: G&A - Pension | D89: Overhead | E89: 3113.65
E90: =SUM(E84:E89) -> 467141.22
D95: GPB | E95: USD
D96: 588762.89 | E96: 749565.81

Sheet TB US
B1: TB us 31.12.23
B3: 102 · Cash-Operating | C3: =1420500.3-1400000+C36-75021-8797.5-46442.34 -> 0 | D3: Cash and cash equivalents
B4: 125 · Due from Getctrl Ltd Israel Sub | C4: =6635139.34+1400000 -> 8035139.3 | D4: Related party
B5: 126 · Due from Getctrl UK Ltd | C5: =232986.58+75021+46442.34+10000 -> 364449.92 | D5: Related party
B6: 400 · Capital Stock | C6: =-8345043.34-C36-10000 -> -8464803.9 | D6: Additional paid-in capital | M6: סכום של 10 אלף השקעה התקבל ב 31/5/23 בח WISE וUSD חשבון ששייך לחברה באנגליה
B7: 410 · Equity Expenses | C7: =55000 -> 55000 | D7: Equity expenses
B8: Accumulated deficit | C8: 1417.12 | D8: Accumulated deficit | H8: מתאים לדוח שנה קודמת
B9: 849 · Legal and Accounting | C9: =-L25 -> 5862.5 | D9: Legal & Professional Services
B10: 863 · Outside Service | C10: =-L15 -> 1900 | D10: Legal & Professional Services
B11: 882 · State Franchise Tax | C11: =-L23 -> 1045 | D11: Other - G&A | G11: 8797.5
B12: 809 · Bank Charges | C12: =-L19 -> -10 | D12: Other - G&A
C13: =SUM(C3:C12) -> 8.1854523e-10 | L13: תנועות בבנק
L14: 1420500.3
L15: -1900
L16: 17501.09
L17: -75021
F18: השקעות שבוצעו השנה בבנק | L18: 14970
L19: 10
L20: 19999.06
C21: 490000 | D21: INVEST | L21: 24990.1
C22: 147977 | D22: INVEST | L22: 12301.23
C23: 409463.33 | D23: INVEST | L23: -1045
C24: 3800000.1 | D24: INVEST | L24: 19999.06
C25: 10002.03 | D25: INVEST | L25: -5862.5
L26: -1400000
L27: -46442.34
L28: =SUM(L14:L27) -> 3.2014214e-10
F29: השקעות ב 2023
C30: 17501.09
C31: 14970
C32: 19999.06
C33: 24990.1
C34: 12301.23
C35: 19999.06
C36: =SUM(C30:C35) -> 109760.54
C38: 10000 | F38: סכום של 10 אלף השקעה התקבל ב 31/5/23 בח WISE וUSD חשבון ששייך לחברה באנגליה
C40: =C36+C38 -> 119760.54

Sheet BS (consolidate)
B6: =Summary!B6 -> GetCtrl LTD
B7: Unaudited Consolidated Managerial Financial Report as of - | J7: =Summary!J7 -> 45291
B8: Balance Sheet (K$)
E11: =$J$7 -> 45291 | F11: =$J$7 -> 45291 | G11: =$J$7 -> 45291 | H11: AJE | I11: =$J$7 -> 45291 | N11: 45199 | O11: 45107 | P11: 45016 | Q11: 44926
E12: Israel | F12: UK | G12: US | I12: Consolidated | N12: Consolidated | O12: Consolidated | P12: Consolidated | Q12: Consolidated
E13: USD | F13: USD | G13: USD | I13: USD | N13: USD | O13: USD | P13: USD | Q13: USD
B14: ASSETS
C16: Current Assets
D17: Cash and cash equivalents | E17: =SUMIF(TB!$J$2:$J$121,D17,TB!$I$2:$I121) -> 771696.05 | F17: =SUMIF('TB UK'!$J$2:$J$63,D17,'TB UK'!$I$2:$I$64) -> 413195.17 | G17: ='TB US'!C3 -> 0 | I17: =SUM(E17:G17) -> 1184891.2 | N17: 1661133.9 | O17: 2268299.2 | P17: 2947698.8 | Q17: 3536756.1
D18: Accounts receivable | E18: =SUMIF(TB!$J$2:$J$121,D18,TB!$I$2:$I122) -> 0 | F18: =SUMIF('TB UK'!$J$2:$J$63,D18,'TB UK'!$I$2:$I$64) -> 0 | I18: =SUM(E18:G18) -> 0 | N18: 0 | O18: 0 | P18: 0 | Q18: 0
D19: Prepaid expenses | E19: =SUMIF(TB!$J$2:$J$121,D19,TB!$I$2:$I123) -> 0 | F19: =SUMIF('TB UK'!$J$2:$J$63,D19,'TB UK'!$I$2:$I$64) -> 8819.246 | I19: =SUM(E19:G19) -> 8819.246 | N19: 8450.8538 | O19: 0 | P19: 0 | Q19: 0
D20: Account Receivable-VAT+TAX | E20: =SUMIF(TB!$J$2:$J$121,D20,TB!$I$2:$I124) -> 30723.68 | F20: =SUMIF('TB UK'!$J$2:$J$63,D20,'TB UK'!$I$2:$I$64) -> -9570.756 | I20: =SUM(E20:G20) -> 21152.924 | N20: 34155.972 | O20: 33030.42 | P20: 54259.04 | Q20: 58083.46
D21: Other current assets | E21: =SUMIF(TB!$J$2:$J$121,D21,TB!$I$2:$I125) -> 27670.25 | F21: =SUMIF('TB UK'!$J$2:$J$63,D21,'TB UK'!$I$2:$I$64) -> 0 | I21: =SUM(E21:G21) -> 27670.25 | N21: 8021.39 | O21: 19238.39 | P21: 14904.8 | Q21: 15863.04
C22: Total current assets | E22: =SUM(E17:E21) -> 830089.98 | F22: =SUM(F17:F21) -> 412443.66 | G22: =SUM(G17:G21) -> 0 | I22: =SUM(I17:I21) -> 1242533.6 | N22: 1711762.1 | O22: 2320568 | P22: 3016862.7 | Q22: 3610702.6
C24: Non current assets
D25: Restricted cash | E25: =SUMIF(TB!$J$2:$J$121,D25,TB!$I$2:$I129) -> 40247.32 | F25: =SUMIF('TB UK'!$J$2:$J$63,D25,'TB UK'!$I$2:$I$64) -> 0 | I25: =SUM(E25:G25) -> 40247.32 | N25: 38975.676 | O25: 38975.676 | P25: 40980.392 | Q25: 65064.502
D26: Property and Equipment, Net | E26: =SUMIF(TB!$J$2:$J$121,D26,TB!$I$2:$I130) -> 87591.02 | F26: =SUMIF('TB UK'!$J$2:$J$63,D26,'TB UK'!$I$2:$I$64) -> 1248.3451 | I26: =SUM(E26:G26) -> 88839.365 | N26: 111724.51 | O26: 104560.78 | P26: 104743.38 | Q26: 104904.81
D27: Other Long term Assets | E27: =SUMIF(TB!$J$2:$J$121,D27,TB!$I$2:$I131) -> 160149.19 | I27: =SUM(E27:G27) -> 160149.19 | N27: 160149.19 | O27: 160149.19 | Q27: 160149.19
C28: Total Non current assets | E28: =SUM(E25:E27) -> 287987.53 | F28: =SUM(F25:F27) -> 1248.3451 | G28: =SUM(G25:G27) -> 0 | I28: =SUM(I25:I27) -> 289235.88 | N28: 310849.38 | O28: 303685.65 | P28: 145723.77 | Q28: 330118.5
B31: TOTAL ASSETS | E31: =E22+E28 -> 1118077.5 | F31: =F22+F28 -> 413692.01 | G31: =G22+G28 -> 0 | I31: =I22+I28 -> 1531769.5 | N31: 2022611.5 | O31: 2624253.7 | P31: 3162586.4 | Q31: 3940821.1
B33: LIABILITIES AND SHAREHOLDERS' EQUITY
C35: Current Liabilities
D36: Short term loans | E36: =-SUMIF(TB!$J$2:$J$121,D36,TB!$I$2:$I135) -> 0 | F36: =-SUMIF('TB UK'!$J$2:$J$63,D36,'TB UK'!$I$2:$I$64) -> 0 | I36: =SUM(E36:G36) -> 0 | N36: 0 | O36: 0 | P36: 0 | Q36: 0 | R36: הפרש | S36: ישראל | T36: ארהב | U36: אנגליה | V36: ספרים | W36: מטבע
D37: Accounts payable | E37: =-SUMIF(TB!$J$2:$J$121,D37,TB!$I$2:$I135) -> 73761.726 | F37: =-SUMIF('TB UK'!$J$2:$J$63,D37,'TB UK'!$I$2:$I$64) -> 21006.48 | I37: =SUM(E37:G37) -> 94768.206 | N37: 52317.408 | O37: 36805.547 | P37: 63510.972 | Q37: 69130.883 | R37: =U37+T37 -> 6.1177456 | T37: ='TB US'!C5 -> 364449.92 | U37: ='TB UK'!G52 -> -364443.8 | V37: אנגליה ארה"ב | W37: USD
D38: Accrued expenses | E38: =-SUMIF(TB!$J$2:$J$121,D38,TB!$I$2:$I135) -> 8995.7018 | F38: =-SUMIF('TB UK'!$J$2:$J$63,D38,'TB UK'!$I$2:$I$64) -> 0 | I38: =SUM(E38:G38) -> 8995.7018 | N38: 8648.6486 | O38: 11027.027 | P38: 20610.909 | Q38: 20610.909 | R38: =U38+S38 -> 485.5017 | S38: =510744.65-AJE!N30-AJE!N31 -> -78018.238 | U38: ='TB UK'!F50+'TB UK'!F45 -> 78503.74 | V38: אנגליה ישראל | W38: GPB
D39: Employee payables & institutions | E39: =-SUMIF(TB!$J$2:$J$121,D39,TB!$I$2:$I135) -> 93603.46 | F39: =-SUMIF('TB UK'!$J$2:$J$63,D39,'TB UK'!$I$2:$I$64) -> 16873.36 | I39: =SUM(E39:G39) -> 110476.82 | N39: 167532.72 | O39: 122256.08 | P39: 151006.47 | Q39: 181822.17 | R39: =S39+T39 -> 140 | S39: =TB!I23+TB!G25 -> -8034999.3 | T39: ='TB US'!C4 -> 8035139.3 | V39: ישראל ארה"ב | W39: USD
D40: Related party | E40: =-SUMIF(TB!$J$2:$J$121,D40,TB!$I$2:$I135) -> 1534943.1 | F40: =-SUMIF('TB UK'!$J$2:$J$63,D40,'TB UK'!$I$2:$I$64) -> 264499.12 | G40: =-'TB US'!C4-'TB US'!C5 -> -8399589.3 | H40: 6600000 | I40: =SUM(E40:H40) -> -147.04086 | N40: -140.19063 | O40: -5743.91 | P40: -150.75 | Q40: -121.86
D41: Other short term liabilities | E41: =-SUMIF(TB!$J$2:$J$121,D41,TB!$I$2:$I135) -> 0 | F41: =-SUMIF('TB UK'!$J$2:$J$63,D41,'TB UK'!$I$2:$I$64) -> 0 | I41: =SUM(E41:G41) -> 0 | N41: 0 | O41: 0 | P41: 0 | Q41: 105113.1 | R41: =U41+S41 -> 0.9231163 | S41: =TB!I24 -> -99943.758 | U41: ='TB UK'!I50+'TB UK'!I45 -> 99944.681 | V41: אנגליה ישראל | W41: USD
C42: Total Current Liabilities | E42: =SUM(E36:E41) -> 1711304 | F42: =SUM(F36:F41) -> 302378.96 | G42: =SUM(G36:G41) -> -8399589.3 | H42: =SUM(H36:H41) -> 6600000 | I42: =SUM(I36:I41) -> 214093.69 | N42: 228358.59 | O42: 164344.74 | P42: 234977.6 | Q42: 376555.2
C44: Long Term Liabilities
D45: Severance, Net | E45: =-SUMIF(TB!$J$2:$J$121,D45,TB!$I$2:$I135) -> 0 | F45: =-SUMIF('TB UK'!$J$2:$J$63,D45,'TB UK'!$I$2:$I$64) -> 0 | Q45: 0
D46: Other Long term liabilities | E46: =-SUMIF(TB!$J$2:$J$121,D46,TB!$I$2:$I136) -> 161891.73 | F46: =-SUMIF('TB UK'!$J$2:$J$63,D46,'TB UK'!$I$2:$I$64) -> 0 | I46: =SUM(E46:G46) -> 161891.73 | N46: 161891.73 | O46: 161891.73 | Q46: 56778.63
C47: Total Long Term Liabilities | E47: =SUM(E45:E46) -> 161891.73 | F47: =SUM(F45:F46) -> 0 | G47: =SUM(G45:G46) -> 0 | H47: =SUM(H45:H46) -> 0 | I47: =SUM(I45:I46) -> 161891.73 | N47: 161891.73 | O47: 161891.73 | P47: 0 | Q47: 56778.63
C49: Shareholders' Equity
D50: Share capital | E50: =-SUMIF(TB!$J$2:$J$121,D50,TB!$I$2:$I140) -> 0 | F50: =-SUMIF('TB UK'!$J$2:$J$63,D50,'TB UK'!$I$2:$I$64) -> 0 | I50: =SUM(E50:H50) -> 0 | N50: 0 | O50: 0 | P50: 0 | Q50: 0
D51: Additional paid-in capital | E51: =-SUMIF(TB!$J$2:$J$121,D51,TB!$I$2:$I141) -> 0 | F51: =-SUMIF('TB UK'!$J$2:$J$63,D51,'TB UK'!$I$2:$I$64) -> 0 | G51: =-'TB US'!C6 -> 8464803.9 | I51: =SUM(E51:H51) -> 8464803.9 | N51: 8464794.3 | O51: 8464794.3 | P51: 8454794.3 | Q51: 8345043.3 | R51: =Q51-I51 -> -119760.54
D52: Capital note | E52: =-SUMIF(TB!$J$2:$J$121,D52,TB!$I$2:$I142) -> 6600000 | F52: =-SUMIF('TB UK'!$J$2:$J$63,D52,'TB UK'!$I$2:$I$64) -> 0 | H52: -6600000 | I52: =SUM(E52:H52) -> 0 | N52: 0 | O52: 0
D53: Equity expenses | E53: =-SUMIF(TB!$J$2:$J$121,D53,TB!$I$2:$I142) -> 0 | F53: =-SUMIF('TB UK'!$J$2:$J$63,D53,'TB UK'!$I$2:$I$64) -> 0 | G53: =-'TB US'!C7 -> -55000 | I53: =SUM(E53:H53) -> -55000 | N53: -55000 | O53: -55000 | P53: -55000 | Q53: -55000
D54: Capital reserve | E54: =-SUMIF(TB!$J$2:$J$121,D54,TB!$I$2:$I143) -> 0 | F54: =-SUMIF('TB UK'!$J$2:$J$63,D54,'TB UK'!$I$2:$I$64) -> 0 | I54: =SUM(E54:H54) -> 0 | N54: 0 | O54: 0 | P54: 0 | Q54: 0
D55: Accumulated deficit | E55: =-SUMIF(TB!$J$2:$J$121,D55,TB!$I$2:$I141) -> -4866459.4 | F55: =-SUMIF('TB UK'!$J$2:$J$63,D55,'TB UK'!$I$2:$I$64) -> 84971.625 | G55: -1417 | I55: =SUM(E55:H55) -> -4782904.8 | N55: -4801942.7 | O55: -4799851.9 | P55: -4799346.3 | Q55: -1344275.4
D56: Profit (loss) this year | E56: ='P&L'!F73 -> -2488658.8 | F56: ='P&L (consolidate)'!F75 -> 26341.42 | G56: ='P&L (consolidate)'!G75 -> -8797.5 | I56: =SUM(E56:H56) -> -2471114.9 | N56: -1975490.3 | O56: -1311925.2 | P56: -672839.13 | Q56: -3438280.7
C57: Total Shareholders' Equity | E57: =SUM(E50:E56) -> -755118.21 | F57: =SUM(F50:F56) -> 111313.04 | G57: =SUM(G50:G56) -> 8399589.4 | H57: =SUM(H50:H56) -> -6600000 | I57: =SUM(I50:I56) -> 1155784.2 | N57: 1632361.3 | O57: 2298017.3 | P57: 2927608.9 | Q57: 3507487.3
B59: TOTAL LIABILITIES AND
B60: SHAREHOLDERS' EQUITY | E60: =E42+E57+E47 -> 1118077.5 | F60: =F42+F57+F47 -> 413692.01 | G60: =G42+G57+G47 -> 0.12 | H60: =H42+H57+H47 -> 0 | I60: =I42+I57+I47 -> 1531769.6 | N60: 2022611.6 | O60: 2624253.8 | P60: 3162586.6 | Q60: 3940821.1
C63: Notes
C65: (1) | D65: The above mentioned balance sheet is based on unaudited ledger
C67: (2)
C69: (3)
Q72: 0
E74: =E31-E60 -> 0 | F74: =F31-F60 -> 0 | G74: =G31-G60 -> -0.12 | H74: =H31-H60 -> 0 | I74: =I31-I60 -> -0.12 | N74: -0.12 | O74: -0.12
D76: בדיקת עודפים
E77: -1348339.3 | F77: 4063.93 | G77: 0
E78: -3518120.1 | F78: 81256.53 | G78: -1417.12
D79: עודפים מבוקרים 31.12.22 | E79: =SUM(E77:E78) -> -4866459.4 | F79: =SUM(F77:F78) -> 85320.46 | G79: =SUM(G77:G78) -> -1417.12
D80: הפרש | E80: =E55-E79 -> 0.0027450975 | F80: =F55-F79 -> -348.83488 | G80: =G55-G79 -> 0.12

Sheet P&L (consolidate)
B6: =Summary!B6 -> GetCtrl LTD
B7: Unaudited Consolidated Managerial Financial Report for the Month ended - | H7: =Summary!J7 -> 45291
B8: Profit & Loss Summary
E11: =$H$7 -> 45291 | F11: =$H$7 -> 45291 | G11: =$H$7 -> 45291 | H11: =$H$7 -> 45291 | K11: Q4 2023 | L11: Q3 2023 | M11: Q2 2023 | N11: Q1 2023 | O11: 44926
E12: Israel | F12: UK | G12: US | H12: Consolidated | K12: Consolidated | L12: Consolidated | M12: Consolidated | N12: Consolidated | O12: Consolidated
E13: USD | F13: USD | G13: USD | H13: USD | K13: USD | L13: USD | M13: USD | N13: USD | O13: USD
B15: Revenues | E15: =-SUMIF(TB!$J$2:$J$121,B15,TB!$I$2:$I$121) -> 0
B17: Cost of revenues
B18: Cost of sales | E18: =SUMIF(TB!$J$2:$J$121,B18,TB!$I$2:$I$121) -> 0
B19: Cogs Payroll and social benefits | E19: =SUMIF(TB!$J$2:$J$121,B19,TB!$I$2:$I$121) -> 0
B20: Allocation cogs | E20: =SUMIF(TB!$J$2:$J$121,B20,TB!$I$2:$I$121) -> 0
B21: Total Cost of revenues | E21: =SUM(E18:E20) -> 0 | F21: =SUM(F18:F20) -> 0 | G21: =SUM(G18:G20) -> 0 | H21: =SUM(H18:H20) -> 0 | N21: 0 | O21: 0
B23: Gross profit | E23: =E15-E21 -> 0 | F23: =F15-F21 -> 0 | G23: =G15-G21 -> 0 | H23: =H15-H21 -> 0 | N23: 0 | O23: 0
B25: Operating expenses
B27: Research and development-
C28: Salaries and social benefits - R&D | E28: =SUMIF(TB!$J$2:$J$121,C28,TB!$I$2:$I$121) -> 926825.31 | F28: =SUMIF('TB UK'!$J$2:$J$63,C28,'TB UK'!$I$2:$I$64) -> 440817.58 | H28: =SUM(E28:G28) -> 1367642.9 | K28: =H28-N28-M28-L28 -> 190802.88 | L28: 266332.65 | M28: 398915.18 | N28: 511592.18 | O28: 1778094.5
C29: Subcontractors | E29: =SUMIF(TB!$J$2:$J$121,C29,TB!$I$2:$I$121) -> -10104.27 | F29: =SUMIF('TB UK'!$J$2:$J$63,C29,'TB UK'!$I$2:$I$64) -> 0 | H29: =SUM(E29:G29) -> -10104.27 | K29: =H29-N29-M29-L29 -> 0 | L29: 0 | M29: -10798.52 | N29: 694.25 | O29: 134443.92
C30: IIA Expenses | E30: =SUMIF(TB!$J$2:$J$121,C30,TB!$I$2:$I$121) -> 0 | F30: =SUMIF('TB UK'!$J$2:$J$63,C30,'TB UK'!$I$2:$I$64) -> 0 | H30: =SUM(E30:G30) -> 0 | K30: =H30-N30-M30-L30 -> 0 | L30: 0 | M30: 0 | N30: 0 | O30: 0
C31: Recrutment | E31: =SUMIF(TB!$J$2:$J$121,C31,TB!$I$2:$I$121) -> 0 | F31: =SUMIF('TB UK'!$J$2:$J$63,C31,'TB UK'!$I$2:$I$64) -> 0 | H31: =SUM(E31:G31) -> 0 | K31: =H31-N31-M31-L31 -> 0 | L31: 0 | M31: 0 | N31: 0 | O31: 48064.79
C32: Travel R&D | E32: =SUMIF(TB!$J$2:$J$121,C32,TB!$I$2:$I$121) -> 0 | F32: =SUMIF('TB UK'!$J$2:$J$63,C32,'TB UK'!$I$2:$I$64) -> 0 | H32: =SUM(E32:G32) -> 0 | K32: =H32-N32-M32-L32 -> 0 | L32: 0 | M32: 0 | N32: 0 | O32: 0
C33: G&A overhead | E33: =SUMIF(TB!$J$2:$J$121,C33,TB!$I$2:$I$121) -> 176539.08 | F33: =SUMIF('TB UK'!$J$2:$J$63,C33,'TB UK'!$I$2:$I$64) -> 0 | H33: =SUM(E33:G33) -> 176539.08 | K33: =H33-N33-M33-L33 -> 50108.511 | L33: 41915.131 | M33: 39611.183 | N33: 44904.25 | O33: 211311.42
C34: R&D expenses | E34: =SUMIF(TB!$J$2:$J$121,C34,TB!$I$2:$I$121) -> 250045.97 | F34: =SUMIF('TB UK'!$J$2:$J$63,C34,'TB UK'!$I$2:$I$64) -> 0 | H34: =SUM(E34:G34) -> 250045.97 | K34: =H34-N34-M34-L34 -> 41016.675 | L34: 104282.21 | M34: 52216.785 | N34: 52530.292 | O34: 473557.24
B35: Total R&D | E35: =SUM(E28:E34) -> 1343306.1 | F35: =SUM(F28:F34) -> 440817.58 | G35: =SUM(G28:G34) -> 0 | H35: =SUM(H28:H34) -> 1784123.7 | K35: =SUM(K28:K34) -> 281928.07 | L35: 412529.99 | M35: 479944.63 | N35: 609720.98 | O35: 2645471.9
B37: Sales and marketing-
C38: Salaries and social benefits - S&M | E38: =SUMIF(TB!$J$2:$J$121,C38,TB!$I$2:$I$121) -> 0 | F38: =SUMIF('TB UK'!$J$2:$J$63,C38,'TB UK'!$I$2:$I$64) -> 0 | H38: =SUM(E38:G38) -> 0 | K38: =H38-N38-M38-L38 -> 0 | L38: 0 | M38: 0 | N38: 0 | O38: 0
C39: Travel | E39: =SUMIF(TB!$J$2:$J$121,C39,TB!$I$2:$I$121) -> 14359.73 | F39: =SUMIF('TB UK'!$J$2:$J$63,C39,'TB UK'!$I$2:$I$64) -> 2485.7923 | H39: =SUM(E39:G39) -> 16845.522 | K39: =H39-N39-M39-L39 -> 2538.7954 | L39: 10804.429 | M39: 1226.6775 | N39: 2275.6199 | O39: 39325.25
C40: PR | E40: =SUMIF(TB!$J$2:$J$121,C40,TB!$I$2:$I$121) -> 2721.08 | F40: =SUMIF('TB UK'!$J$2:$J$63,C40,'TB UK'!$I$2:$I$64) -> 0 | H40: =SUM(E40:G40) -> 2721.08 | K40: =H40-N40-M40-L40 -> 0 | L40: 0 | M40: 2721.08 | N40: 0 | O40: 0
C41: Other S&M | E41: =SUMIF(TB!$J$2:$J$121,C41,TB!$I$2:$I$121) -> 123717.83 | F41: =SUMIF('TB UK'!$J$2:$J$63,C41,'TB UK'!$I$2:$I$64) -> 0 | H41: =SUM(E41:G41) -> 123717.83 | K41: =H41-N41-M41-L41 -> 64971.056 | L41: 15183.399 | M41: 25725.485 | N41: 17837.889 | O41: 19971.69
C42: Marketing | E42: =SUMIF(TB!$J$2:$J$121,C42,TB!$I$2:$I$121) -> 0 | F42: =SUMIF('TB UK'!$J$2:$J$63,C42,'TB UK'!$I$2:$I$64) -> 11063.413 | H42: =SUM(E42:G42) -> 11063.413 | K42: =H42-N42-M42-L42 -> 462.1342 | L42: 10601.279 | M42: 0 | N42: 0 | O42: 0
C43: Advertising | E43: =SUMIF(TB!$J$2:$J$121,C43,TB!$I$2:$I$121) -> 0 | F43: =SUMIF('TB UK'!$J$2:$J$63,C43,'TB UK'!$I$2:$I$64) -> 0 | H43: =SUM(E43:G43) -> 0 | K43: =H43-N43-M43-L43 -> 0 | L43: 0 | M43: 0 | N43: 0 | O43: 0
C44: Recrutment S&M | E44: =SUMIF(TB!$J$2:$J$121,C44,TB!$I$2:$I$121) -> 0 | F44: =SUMIF('TB UK'!$J$2:$J$63,C44,'TB UK'!$I$2:$I$64) -> 0 | H44: =SUM(E44:G44) -> 0 | K44: =H44-N44-M44-L44 -> 0 | L44: 0 | M44: 0 | N44: 0 | O44: 0
C45: Consultants S&M | E45: =SUMIF(TB!$J$2:$J$121,C45,TB!$I$2:$I$121) -> 0 | F45: =SUMIF('TB UK'!$J$2:$J$63,C45,'TB UK'!$I$2:$I$64) -> 0 | H45: =SUM(E45:G45) -> 0 | K45: =H45-N45-M45-L45 -> 0 | L45: 0 | M45: 0 | N45: 0 | O45: 0
C46: COST + UK S&M | E46: =SUMIF(TB!$J$2:$J$121,C46,TB!$I$2:$I$121) -> 471674.81 | F46: =SUMIF('TB UK'!$J$2:$J$63,C46,'TB UK'!$I$2:$I$64) -> -471674.41 | H46: =SUM(E46:G46) -> 0.40497947 | K46: =H46-N46-M46-L46 -> 0.40497947 | L46: 0 | M46: 0 | N46: 0 | O46: 0.02
B47: Total S&M | E47: =SUM(E38:E46) -> 612473.45 | F47: =SUM(F38:F46) -> -458125.2 | G47: =SUM(G38:G46) -> 0 | H47: =SUM(H38:H46) -> 154348.25 | K47: =SUM(K38:K46) -> 67972.39 | L47: 36589.107 | M47: 29673.243 | N47: 20113.509 | O47: 59296.96
B49: General and administrative-
C50: Salaries and social benefits - G&A | E50: =SUMIF(TB!$J$2:$J$121,C50,TB!$I$2:$I$121) -> 153711.53 | F50: =SUMIF('TB UK'!$J$2:$J$63,C50,'TB UK'!$I$2:$I$64) -> 159352.37 | H50: =SUM(E50:G50) -> 313063.9 | K50: =H50-N50-M50-L50 -> 73215.009 | L50: 149571.04 | M50: 42816.999 | N50: 47460.855 | O50: 411763.22
C51: Accounting & Financial Services | E51: =SUMIF(TB!$J$2:$J$121,C51,TB!$I$2:$I$121) -> 40385.611 | F51: =SUMIF('TB UK'!$J$2:$J$63,C51,'TB UK'!$I$2:$I$64) -> 48460.485 | H51: =SUM(E51:G51) -> 88846.097 | K51: =H51-N51-M51-L51 -> 17124.245 | L51: 18763.315 | M51: 28149.227 | N51: 24809.31 | O51: 50797.74
C52: Legal & Professional Services | E52: =SUMIF(TB!$J$2:$J$121,C52,TB!$I$2:$I$121) -> 27086.2 | F52: =SUMIF('TB UK'!$J$2:$J$63,C52,'TB UK'!$I$2:$I$64) -> 2501.6808 | G52: ='TB US'!C9+'TB US'!C10 -> 7762.5 | H52: =SUM(E52:G52) -> 37350.381 | K52: =H52-N52-M52-L52 -> 13971.172 | L52: 7204.7488 | M52: 11612.69 | N52: 4561.77 | O52: 109803.58
C53: Insurance | E53: =SUMIF(TB!$J$2:$J$121,C53,TB!$I$2:$I$121) -> 1474.03 | F53: =SUMIF('TB UK'!$J$2:$J$63,C53,'TB UK'!$I$2:$I$64) -> 1966.9704 | H53: =SUM(E53:G53) -> 3441.0004 | K53: =H53-N53-M53-L53 -> 1556.1931 | L53: 45.2073 | M53: 919.8 | N53: 919.8 | O53: 2879.81
C54: IT& communications | E54: =SUMIF(TB!$J$2:$J$121,C54,TB!$I$2:$I$121) -> 11946.89 | F54: =SUMIF('TB UK'!$J$2:$J$63,C54,'TB UK'!$I$2:$I$64) -> 1642.3248 | H54: =SUM(E54:G54) -> 13589.215 | K54: =H54-N54-M54-L54 -> 4838.6422 | L54: 3948.9626 | M54: 2287.25 | N54: 2514.36 | O54: 23473.807
C55: Recruiting & HR | E55: =SUMIF(TB!$J$2:$J$121,C55,TB!$I$2:$I$121) -> 0 | F55: =SUMIF('TB UK'!$J$2:$J$63,C55,'TB UK'!$I$2:$I$64) -> 0 | H55: =SUM(E55:G55) -> 0 | K55: =H55-N55-M55-L55 -> 0 | L55: 0 | M55: 0 | N55: 0 | O55: 0
C56: Rent (Inc. Tax) | E56: =SUMIF(TB!$J$2:$J$121,C56,TB!$I$2:$I$121) -> 122403.24 | F56: =SUMIF('TB UK'!$J$2:$J$63,C56,'TB UK'!$I$2:$I$64) -> 17024.059 | H56: =SUM(E56:G56) -> 139427.3 | K56: =H56-N56-M56-L56 -> 32064.973 | L56: 29924.757 | M56: 35177.98 | N56: 42259.59 | O56: 157960.68
C57: Maintenance | E57: =SUMIF(TB!$J$2:$J$121,C57,TB!$I$2:$I$121) -> 12435.96 | F57: =SUMIF('TB UK'!$J$2:$J$63,C57,'TB UK'!$I$2:$I$64) -> 5056.5653 | H57: =SUM(E57:G57) -> 17492.525 | K57: =H57-N57-M57-L57 -> -4276.7566 | L57: 12308.079 | M57: 5395.0528 | N57: 4066.15 | O57: 21155.253
C58: Welfare | E58: =SUMIF(TB!$J$2:$J$121,C58,TB!$I$2:$I$121) -> 37571.74 | F58: =SUMIF('TB UK'!$J$2:$J$63,C58,'TB UK'!$I$2:$I$64) -> 4503.0509 | H58: =SUM(E58:G58) -> 42074.791 | K58: =H58-N58-M58-L58 -> 10996.297 | L58: 9725.9381 | M58: 10903.554 | N58: 10449.001 | O58: 52854.57
C59: Travel G&A | E59: =SUMIF(TB!$J$2:$J$121,C59,TB!$I$2:$I$121) -> 0 | F59: =SUMIF('TB UK'!$J$2:$J$63,C59,'TB UK'!$I$2:$I$64) -> 4682.6754 | H59: =SUM(E59:G59) -> 4682.6754 | K59: =H59-N59-M59-L59 -> 195.60189 | L59: 175.27351 | M59: 4311.8 | N59: 0 | O59: 13696.03
C60: Car maintenance | E60: =SUMIF(TB!$J$2:$J$121,C60,TB!$I$2:$I$121) -> 2482.01 | F60: =SUMIF('TB UK'!$J$2:$J$63,C60,'TB UK'!$I$2:$I$64) -> 0 | H60: =SUM(E60:G60) -> 2482.01 | K60: =H60-N60-M60-L60 -> 532.05 | L60: 283.59 | M60: 969.17 | N60: 697.2 | O60: 5288.01
C61: Overhead set off | E61: =SUMIF(TB!$J$2:$J$121,C61,TB!$I$2:$I$121) -> -176539.08 | F61: =SUMIF('TB UK'!$J$2:$J$63,C61,'TB UK'!$I$2:$I$64) -> 0 | H61: =SUM(E61:G61) -> -176539.08 | K61: =H61-N61-M61-L61 -> -50108.511 | L61: -41915.131 | M61: -39611.183 | N61: -44904.25 | O61: -211311.42
C62: COST + UK G&A | E62: =SUMIF(TB!$J$2:$J$121,C62,TB!$I$2:$I$121) -> 277890.99 | F62: =SUMIF('TB UK'!$J$2:$J$63,C62,'TB UK'!$I$2:$I$64) -> -277891.54 | H62: =SUM(E62:G62) -> -0.54718698 | K62: =H62-N62-M62-L62 -> -0.54718698 | L62: 0 | M62: 0 | N62: 0 | O62: 0.32
C63: Depreciation | E63: =SUMIF(TB!$J$2:$J$121,C63,TB!$I$2:$I$121) -> 24780 | F63: =SUMIF('TB UK'!$J$2:$J$63,C63,'TB UK'!$I$2:$I$64) -> 420.1296 | H63: =SUM(E63:G63) -> 25200.13 | K63: =H63-N63-M63-L63 -> 24797.549 | L63: -15.3998 | M63: 210.15 | N63: 207.83 | O63: 22400.89
C64: Other - G&A | E64: =SUMIF(TB!$J$2:$J$121,C64,TB!$I$2:$I$121) -> 18127.31 | F64: =SUMIF('TB UK'!$J$2:$J$63,C64,'TB UK'!$I$2:$I$64) -> 1528.7116 | G64: ='TB US'!C11+'TB US'!C12 -> 1035 | H64: =SUM(E64:G64) -> 20691.022 | K64: =H64-N64-M64-L64 -> 7974.0627 | L64: -17588.39 | M64: 14239.513 | N64: 16065.837 | O64: 39892.2
B65: Total G&A | E65: =SUM(E50:E64) -> 553756.44 | F65: =SUM(F50:F64) -> -30752.519 | G65: =SUM(G50:G64) -> 8797.5 | H65: =SUM(H50:H64) -> 531801.42 | K65: =SUM(K50:K64) -> 132879.98 | L65: 172431.99 | M65: 117382 | N65: 109107.45 | O65: 700654.69
K66: =H66-N66-M66-L66 -> 0 | L66: 0 | M66: 0
B67: Total Operating Expenses | E67: =+E47+E65+E35 -> 2509536 | F67: =+F47+F65+F35 -> -48060.14 | G67: =+G47+G65+G35 -> 8797.5 | H67: =+H47+H65+H35 -> 2470273.3 | K67: =+K47+K65+K35 -> 482780.44 | L67: 621551.09 | M67: 626999.87 | N67: 738941.94 | O67: 3405423.5
C69: Financial expenses (income) | E69: =SUMIF(TB!$J$2:$J$121,C69,TB!$I$2:$I$121) -> -20877.18 | F69: =SUMIF('TB UK'!$J$2:$J$63,C69,'TB UK'!$I$2:$I$64) -> 21718.72 | H69: =SUM(E69:G69) -> 841.54037 | K69: =H69-N69-M69-L69 -> 12844.164 | L69: 42014.036 | M69: 12086.15 | N69: -66102.81 | O69: 32857.199
B71: Income (loss) before taxes | E71: =E23-E67-E69 -> -2488658.8 | F71: =F23-F67-F69 -> 26341.42 | G71: =G23-G67-G69 -> -8797.5 | H71: =H23-H67-H69 -> -2471114.9 | K71: =K23-K67-K69 -> -495624.6 | L71: -663565.12 | M71: -639086.02 | N71: -672839.13 | O71: -3438280.7
B73: Tax expenses (income) | E73: =SUMIF(TB!$J$2:$J$121,C73,TB!$I$2:$I$121) -> 0 | F73: =SUMIF('TB UK'!$J$2:$J$63,C73,'TB UK'!$I$2:$I$64) -> 0 | G73: =SUMIF(TB!$J$2:$J$121,E73,TB!$I$2:$I$121) -> 0 | H73: =SUM(E73:G73) -> 0 | K73: =H73-N73-M73-L73 -> 0 | L73: 0 | M73: 0 | N73: 0 | O73: 0
B75: Net Income (loss) | E75: =E71-E73 -> -2488658.8 | F75: =F71-F73 -> 26341.42 | G75: =G71-G73 -> -8797.5 | H75: =H71-H73 -> -2471114.9 | K75: =K71-K73 -> -495624.6 | L75: -663565.12 | M75: -639086.02 | N75: -672839.13 | O75: -3438280.7
M76: 0
K77: =H77-N77-M77-L77 -> 0 | L77: 0 | M77: 0
B78: EBITDA | E78: =E23-E67+E63 -> -2484756 | F78: =F23-F67+F63 -> 48480.27 | G78: =G23-G67+G63 -> -8797.5 | H78: =H23-H67+H63 -> -2445073.2 | K78: =K23-K67+K63 -> -457982.89 | L78: -621566.49 | M78: -626789.72 | N78: -738734.11 | O78: -3383022.6
B81: Notes
B83: (1) | C83: The above mentioned P&L is based on unaudited ledger
B88: Average Expenses for month in the peroid | E88: =(E71+E69)/12 -> -209128 | F88: =(F71+F69)/12 -> 4005.0117 | G88: =(G71+G69)/12 -> -733.125 | H88: =(H71+H69)/12 -> -205856.11 | K88: =(K71+K69)/3 -> -160926.81 | L88: =(L71+L69)/3 -> -207183.7 | M88: =(M71+M69)/3 -> -208999.96 | N88: =(N71+N69)/3 -> -246313.98 | O88: =(O71+O69)/12 -> -283785.29

Sheet Payroll Israel + allocation
A1: מחלקה: 000 -
A2: מספר | B2: שם העובד | C2: תשלומים | D2: תגמולי מעסיק | E2: קרן השתלמות | F2: פצויים | G2: שונות | H2: ב.לאומי מעסיק | I2: מס מעסיקים | J2: מס שכר | K2: סה"כ עלות | M2: זמן עבודה לאורך השנה
A3: 1 | B3: נחום אביב | C3: 380073 | D3: 24375 | E3: 14140.8 | F3: 31237.5 | H3: 26755.44 | K3: 476581.74 | L3: RD | M3: 1
A4: 2 | B4: המר ליאור | C4: 928500.03 | D4: 11700 | E4: 7070.4 | F4: 14994 | H4: 23140.75 | K4: 985405.18 | L4: GA | M4: =7/12 -> 0.58333333
A5: 3 | B5: יונגר זיו | C5: 456199.42 | D5: 28210 | E5: 14140.8 | F5: 36152.2 | H5: 32858.08 | K5: 567560.5 | L5: RD | M5: 1
A6: 4 | B6: שולדנפרי יפית | C6: 174084 | D6: 9785.88 | E6: 12175.2 | F6: 14094.36 | G6: 1212.12 | H6: 11025.74 | K6: 222377.3 | L6: RD | M6: 1
A7: 5 | B7: שלוסברג אליאן | C7: 184608.06 | D7: 11700 | E7: 13327.2 | F7: 14994 | H7: 11867.63 | K7: 236496.89 | L7: GA | M7: 1
A8: 7 | B8: לכטמן ליטל | C8: 565874.88 | D8: 31974.12 | E8: 14140.8 | F8: 45981.6 | G8: 3905.88 | H8: 38041.42 | K8: 699918.7 | L8: RD | M8: 1
A9: 8 | B9: לויטן סביאטוסלב אורי | C9: 386616 | D9: 24960 | E9: 14140.8 | F9: 31987.2 | H9: 27160.02 | K9: 484864.02 | L9: RD | M9: 1
A10: 9 | B10: מור אורן | C10: 8752.3 | D10: 400.4 | F10: 513.13 | H10: 289.58 | K10: 9955.41 | L10: RD | M10: =1/12 -> 0.083333333
A11: 10 | B11: רוטברג שרית | C11: 224265.1 | D11: 14407.19 | E11: 14140.8 | F11: 18463.37 | H11: 14776.2 | K11: 286052.66 | L11: RD | M11: 1
A12: 11 | B12: קדרון תומר | C12: 270598.51 | D12: 17484.35 | E12: 8998.05 | F12: 22406.87 | H12: 19446.83 | K12: 338934.61 | L12: RD | M12: =8/12 -> 0.66666667
A13: 12 | B13: קליסקי אברהם יעקב | C13: 308884 | D13: 19760 | E13: 9427.2 | F13: 25323.2 | H13: 22436.4 | K13: 385830.8 | L13: RD | M13: =8/12 -> 0.66666667
A14: 13 | B14: ריבל ניקולאי | C14: 205318.3 | D14: 12000.75 | E14: 9355.05 | F14: 15806.18 | G14: 333.01 | H14: 13583.24 | K14: 256396.53 | L14: RD | M14: =8/12 -> 0.66666667
A15: 14 | B15: חולוב ברנתן יעל | C15: 179964.23 | D15: 11600.88 | E15: 8248.8 | F15: 14866.97 | H15: 12411.83 | K15: 227092.71 | L15: GA | M15: =7/12 -> 0.58333333
A16: 15 | B16: שטרן גילי | C16: 208710 | D16: 12733.62 | E16: 7070.4 | F16: 17273.08 | G16: 744.78 | H16: 14445.12 | K16: 260977 | L16: RD | M16: =6/12 -> 0.5
A17: 16 | B17: ברקאי זלדיס שי | C17: 114900 | D17: 7131.64 | E17: 4713.6 | F17: 9496.2 | G17: 278.36 | H17: 7975.71 | K17: 144495.51 | L17: RD | M17: =4/12 -> 0.33333333
A18: 15 | B18: סך למחל. | C18: 4597347.8 | D18: 238223.83 | E18: 151089.9 | F18: 313589.86 | G18: 6474.15 | H18: 276213.99 | K18: 5582939.6 | M18: =SUM(M3:M17) -> 11.083333
A19: 15 | B19: סה"כ לחברה | C19: 4597347.8 | D19: 238223.83 | E19: 151089.9 | F19: 313589.86 | G19: 6474.15 | H19: 276213.99 | K19: 5582939.6
J22: שכר ל GA | K22: =K4+K7+K15 -> 1448994.8 | M22: =(M4+M7+M15)/M18 -> 0.19548872 | N22: אלוקציה GA
M23: =1-M22 -> 0.80451128
A25: מספר | B25: שם העובד | C25: תשלומים | D25: תגמולי מעסיק | E25: קרן השתלמות | F25: פצויים | G25: שונות | H25: ב.לאומי מעסיק | I25: מס מעסיקים | J25: מס שכר | K25: סה"כ עלות
A26: 1 | B26: נחום אביב | C26: 105675 | D26: 6825 | E26: 3535.2 | F26: 8746.5 | H26: 7392.73 | K26: 132174.43 | L26: RD
A27: 3 | B27: יונגר זיו | C27: 116175 | D27: 7507.5 | E27: 3535.2 | F27: 9621.15 | H27: 8246.65 | K27: 145085.5 | L27: RD
A28: 4 | B28: שולדנפרי יפית | C28: 54675 | D28: 3384 | E28: 3535.2 | F28: 4498.2 | G28: 126 | H28: 3502.8 | K28: 69721.2 | L28: RD
A29: 5 | B29: שלוסברג אליאן | C29: 48675 | D29: 3120 | E29: 3535.2 | F29: 3998.4 | H29: 3060.87 | K29: 62389.47 | L29: GA
A30: 7 | B30: לכטמן ליטל | C30: 141000 | D30: 8060.51 | E30: 3535.2 | F30: 11495.4 | G30: 909.49 | H30: 9957.99 | K30: 174958.59 | L30: RD
A31: 8 | B31: לויטן סביאטוסלב אורי | C31: 96675 | D31: 6240 | E31: 3535.2 | F31: 7996.8 | H31: 6662.23 | K31: 121109.23 | L31: RD
A32: 10 | B32: רוטברג שרית | C32: 55875 | D32: 3588 | E32: 3535.2 | F32: 4598.16 | H32: 3608.51 | K32: 71204.87 | L32: RD
A33: 11 | B33: קדרון תומר | C33: 111675 | D33: 7215 | E33: 3535.2 | F33: 9246.3 | H33: 7860.83 | K33: 139532.33 | L33: RD
A34: 12 | B34: קליסקי אברהם יעקב | C34: 115831.5 | D34: 7410 | E34: 3535.2 | F34: 9496.2 | H34: 8166.6 | K34: 144439.5 | L34: RD
A35: 13 | B35: ריבל ניקולאי | C35: 33173.79 | D35: 1586.91 | E35: 1178.4 | F35: 2082.5 | G35: 38.09 | H35: 1628.29 | K35: 39687.98 | L35: RD
A36: 14 | B36: חולוב ברנתן יעל | C36: 83175 | D36: 5362.5 | E36: 3535.2 | F36: 6872.25 | H36: 5680.33 | K36: 104625.28 | L36: GA
A37: 15 | B37: שטרן גילי | C37: 108675 | D37: 6655.47 | E37: 3535.2 | F37: 8996.4 | G37: 364.53 | H37: 7421.13 | K37: 135647.73 | L37: RD
A38: 16 | B38: ברקאי זלדיס שי | C38: 98669.21 | D38: 5321.82 | E38: 3535.2 | F38: 7012.59 | G38: 150.2 | H38: 6164.12 | K38: 120853.14 | L38: RD
A39: 13 | B39: סך למחל. | C39: 1169949.5 | D39: 72276.71 | E39: 43600.8 | F39: 94660.85 | G39: 1588.31 | H39: 79353.08 | K39: 1461429.2
A40: 13 | B40: סה"כ לחברה | C40: 1169949.5 | D40: 72276.71 | E40: 43600.8 | F40: 94660.85 | G40: 1588.31 | H40: 79353.08 | K40: 1461429.2
J43: שכר ל GA | K43: =K29+K36 -> 167014.75
A46: 2023 | B46: עד דצמבר 2023
A48: מספר | B48: שם העובד | C48: תשלומים | D48: תגמולי מעסיק | E48: קרן השתלמות | F48: פצויים | G48: שונות | H48: ב.לאומי מעסיק | I48: מס מעסיקים | J48: מס שכר | K48: סה"כ עלות
A49: 1 | B49: נחום אביב | C49: 425208 | D49: 27300 | E49: 14140.8 | F49: 34986 | H49: 29787.74 | K49: 531422.54
A50: 3 | B50: יונגר זיו | C50: 274492.2 | D50: 17549.7 | E50: 10369.95 | F50: 22490.61 | H50: 18934.84 | K50: 343837.3
A51: 4 | B51: שולדנפרי יפית | C51: 221208 | D51: 13536 | E51: 14140.8 | F51: 17992.8 | G51: 504 | H51: 14231.5 | K51: 281613.1
A52: 5 | B52: שלוסברג אליאן | C52: 197208 | D52: 12480 | E52: 14140.8 | F52: 15993.6 | H52: 12430.68 | K52: 252253.08 | L52: GA
A53: 7 | B53: לכטמן ליטל | C53: 226383.4 | D53: 10470.91 | E53: 4713.6 | F53: 14867.38 | G53: 1130.29 | H53: 12937.6 | K53: 270503.18
A54: 8 | B54: לויטן סביאטוסלב אורי | C54: 390859.1 | D54: 24960 | E54: 14140.8 | F54: 31987.2 | H54: 26896.14 | K54: 488843.24
A55: 10 | B55: רוטברג שרית | C55: 229996.92 | D55: 14531.4 | E55: 14140.8 | F55: 18622.55 | H55: 14878.09 | K55: 292169.76
A56: 11 | B56: קדרון תומר | C56: 257650.4 | D56: 16498.3 | E56: 8248.8 | F56: 21143.2 | H56: 18134.71 | K56: 321675.41
A57: 12 | B57: קליסקי אברהם יעקב | C57: 466043 | D57: 29640 | E57: 14140.8 | F57: 37984.8 | H57: 33008.51 | K57: 580817.11
A58: 13 | B58: ריבל ניקולאי | C58: 33173.79 | D58: 1586.91 | E58: 1178.4 | F58: 2082.5 | G58: 38.09 | H58: 1628.29 | K58: 39687.98
A59: 14 | B59: חולוב ברנתן יעל | C59: 224232.76 | D59: 20770.75 | E59: 14140.8 | F59: 26618.52 | H59: 16119.2 | K59: 301882.03 | L59: GA
A60: 15 | B60: שטרן גילי | C60: 254031.31 | D60: 15503.09 | E60: 9427.2 | F60: 20798.02 | G60: 725.86 | H60: 17035.29 | K60: 317520.77
A61: 16 | B61: ברקאי זלדיס שי | C61: 98669.21 | D61: 5321.82 | E61: 3535.2 | F61: 7012.59 | G61: 150.2 | H61: 6164.12 | K61: 120853.14
A62: 13 | B62: סך למחל. | C62: 3299156.1 | D62: 210148.88 | E62: 136458.75 | F62: 272579.77 | G62: 2548.44 | H62: 222186.71 | K62: 4143078.6
A63: 13 | B63: סה"כ לחברה | C63: 3299156.1 | D63: 210148.88 | E63: 136458.75 | F63: 272579.77 | G63: 2548.44 | H63: 222186.71 | K63: 4143078.6

Sheet אלוקציה הוצ
C2: יתרות
A3: IT& communications | C3: ='P&L'!E53 -> 43957.04
A4: Rent (Inc. Tax) | C4: ='P&L'!E55 -> 450797.15
A5: Maintenance | C5: ='P&L'!E56 -> 45477.34
A6: Welfare | C6: ='P&L'!E57 -> 138368.52
A7: Car maintenance | C7: ='P&L'!E58 -> 9112.91
A8: Other - G&A | C8: ='P&L'!E62 -> 65589.66
C9: =SUM(C3:C8) -> 753302.62
C11: 0.85 | G11: אחוז העמסת RD מתוך גיליון תמחיר מצטבר
C13: =C9*C11 -> 640307.23
