Workbook
Name __1: #REF!
Name __2: #REF!
Name _2017_Exp: '[1]Report data 2017'!$AG$18:$AG$635
Name _2B_9: #REF!
Name _ACK1: #REF!
Name _ACK2: #REF!
Name _Grp12: #REF!
Name _Grp13: #REF!
Name _Grp14: #REF!
Name _Grp15: #REF!
Name _Grp2: #REF!
Name _Pg1: #REF!
Name _PG10: #REF!
Name _Sch10: '[2]Schedules PL'!#REF!
Name _Sch11: '[2]Schedules PL'!#REF!
Name _Sch12: '[2]Schedules PL'!#REF!
Name _Sch13: '[2]Schedules PL'!#REF!
Name _Sch14: '[2]Schedules PL'!#REF!
Name _Sch15: '[2]Schedules PL'!#REF!
Name _Sch2: '[2]Schedules PL'!#REF!
Name _Sch4: '[2]Schedules PL'!#REF!
Name _Sch5: '[2]Schedules PL'!#REF!
Name _Sch6: '[2]Schedules PL'!#REF!
Name _Sch7: '[2]Schedules PL'!#REF!
Name _Sch8: '[2]Schedules PL'!#REF!
Name _Sch9: '[2]Schedules BS'!#REF!
Name ADTL: [2]BS!$A$1
Name Annexure: #REF!
Name Annexure1: #REF!
Name area1: #REF!
Name area2: #REF!
Name area3: #REF!
Name BABL: [3]TB!#REF!
Name Banks: #REF!
Name Category_List: #REF!
Name COMP: #REF!
Name compu1: #REF!
Name computation: #REF!
Name Continuation: #REF!
Name da: '[4]FORM-16'!#REF!
Name data: #REF!
Name Date: [2]BS!$C$1
Name days: #REF!
Name days_jj: #REF!
Name db: '[4]FORM-16'!#REF!
Name DEP: #REF!
Name Dep: '[1]Report data 2017'!$A$18:$A$635
Name DRUCKBEREI03: #REF!
Name Elim: #REF!
Name endofdoh: 'מאזן בוחן Australia'!#REF!
Name endofdoh: 'מאזן בוחן EUROPE'!$A$516
Name endofdoh: 'מאזן בוחן הודו'!#REF!
Name endofdoh: 'מאזן בוחן צרפת'!#REF!
Name endofdoh: 'מאזן בוחן'!$A$1018
Name Entity: '[1]Report data 2017'!$B$18:$B$635
Name Excel_BuiltIn_Print_Area_5: #REF!
Name Excel_BuiltIn_Print_Area_6: #REF!
Name far: #REF!
Name ga: '[4]FORM-16'!#REF!
Name gb: '[4]FORM-16'!#REF!

Sheet דוחות
A1: Algosec System Ltd | H1: Algosec System Ltd | N1: Algosec System Ltd
P3: רווח והפסד - חברה
J4: מאזן - חברה - פאסיב
C5: ='נתונים לשינוי'!$C$1 -> 44561 | F5: =L5 -> דצמבר 2007 | G5: =F5 -> דצמבר 2007 | L5: דצמבר 2007 | M5: דצמבר 2007 | T5: מחושב לפי ממוצע חודשי X 12
C6: נומינלי | F6: נומינלי | G6: $ | J6: נומינלי | L6: נומינלי | M6: $ | P6: LTD | Q6: LTD | S6: ממוצע חודשי | T6: דוח שנתי משוער
A7: רכוש שוטף | C7: LTD | D7: LTD | H7: התחייבויות שוטפות | J7: LTD | K7: LTD | P7: ₪ | Q7: $ | S7: $ | T7: $
A8: מזומנים ושווי מזומנים | C8: ₪ | D8: $ | H8: אשראי מתאגידים בנקאיים | J8: ₪ | K8: $ | N8: הכנסות בספרים עד 12/08 | R8: =P8/Q8 -> #DIV/0!
A9: מזומנים בש"ח | B9: =IF(C9=0,"",C9/D9) -> 3.1099992 | C9: =ROUND(('מאזן בוחן'!J10),0) -> 5177110 | D9: =ROUND(('מאזן בוחן'!K10),0) -> 1664666 | H9: משיכות יתר | J9: =-ROUND('מאזן בוחן'!J195,0) -> 0 | L9: 275737.65 | M9: 62440.591 | N9: הכרה בהכנסות שנדחו ש.ק. | R9: =P10/Q9 -> #DIV/0!
A10: מזומנים במט"ח | B10: =IF(C10=0,"",C10/D10) -> 3.11 | C10: =ROUND(('מאזן בוחן'!J22),0) -> 12489113 | D10: =ROUND(('מאזן בוחן'!K22),0) -> 4015792 | H10: הלוואות לז"ק- לא צמודות | J10: =ROUND((0),0) -> 0 | K10: =ROUND((0),0) -> 0 | L10: 0 | M10: 0 | N10: דחיית הכנסות השנה | R10: =#REF!/Q10 -> #REF! | S10: לא נעשה על 2008
A11: פקדונות בש"ח | B11: =IF(C11=0,"",C11/D11) | C11: =ROUND(('מאזן בוחן'!J14),0) -> 0 | D11: =ROUND(('מאזן בוחן'!K14),0) -> 0 | J11: =SUM(J9:J10) -> 0 | K11: =SUM(K9:K10) -> 0 | L11: 275737.65 | M11: 62440.591 | N11: סה"כ הכנסות לדוח כספי | P11: =SUM(P8:P10) -> 0 | Q11: =SUM(Q8:Q10) -> 0
A12: פקדונות במט"ח | B12: =IF(C12=0,"",C12/D12) | C12: 0 | D12: 0 | H12: זכאים ויתרות זכות | N12: הכנסות | O12: =IF(P12=0,"",P12/Q12) -> 3.2708073 | P12: =-'מאזן בוחן'!J564 -> 1.4157395e+08 | Q12: =-'מאזן בוחן'!K564 -> 43284099 | S12: =Q12/12 -> 3607008.3 | T12: =S12*12 -> 43284099
A13: סה"כ קופות קטנות | B13: =IF(C13=0,"",C13/D13) | C13: =ROUND(('מאזן בוחן'!J29),0) -> 0 | D13: =ROUND(('מאזן בוחן'!K29),0) -> 0 | H13: ספקים ונותני שירותים | I13: =IF(J13=0,"",J13/K13) -> 3.1099993 | J13: =ROUND((-SUM('מאזן בוחן'!J199:J447)),0) -> 7089940 | K13: =ROUND((-SUM('מאזן בוחן'!K199:K447)),0) -> 2279724 | O13: =IF(P13=0,"",P13/Q13) | S13: =Q13/10 -> 0
B14: =IF(C14=0,"",C14/D14) -> 3.1099998 | C14: =SUM(C9:C13) -> 17666223 | D14: =SUM(D9:D13) -> 5680458 | H14: מוסדות שכר | I14: =IF(J14=0,"",J14/K14) -> 3.1099997 | J14: =ROUND((-'מאזן בוחן'!J464),0) -> 3564523 | K14: =ROUND((-'מאזן בוחן'!K464),0) -> 1146149 | L14: 444746 | M14: 100712 | N14: הוצאות מו"פ | O14: =IF(P14=0,"",P14/Q14) | S14: =Q14/10 -> 0
B15: =IF(C15=0,"",C15/D15) | H15: הפרשה לחופשה | I15: =IF(J15=0,"",J15/K15) -> 3.1099993 | J15: =ROUND((-'מאזן בוחן'!J468),0) -> 5748162 | K15: =ROUND((-'מאזן בוחן'!K468),0) -> 1848284 | L15: 250806 | M15: 56795 | N15: הוצאות שכר | O15: =IF(P15=0,"",P15/Q15) -> 3.2291752 | P15: =ROUND('מאזן בוחן'!J595,0) -> 65829395 | Q15: =ROUND('מאזן בוחן'!K595,0) -> 20385823 | S15: =Q15/12 -> 1698818.6 | T15: =S15*12 -> 20385823
B16: =IF(C16=0,"",C16/D16) | H16: זכאים אחרים | I16: =IF(J16=0,"",J16/K16) | J16: =ROUND((-'מאזן בוחן'!J492),0)+ROUND((-'מאזן בוחן'!J491),0) -> 0 | K16: =ROUND((-'מאזן בוחן'!K492),0)+ROUND((-'מאזן בוחן'!K491),0) -> 0 | N16: אחרות | O16: =IF(P16=0,"",P16/Q16) -> 3.2331617 | P16: =ROUND('מאזן בוחן'!J618,0) -> 7058380 | Q16: =ROUND('מאזן בוחן'!K618,0) -> 2183120 | S16: =Q16/12 -> 181926.67 | T16: =S16*12 -> 2183120
B17: =IF(C17=0,"",C17/D17) | H17: עובדים | I17: =IF(J17=0,"",J17/K17) -> 3.1099996 | J17: =ROUND((-'מאזן בוחן'!J474),0) -> 8524170 | K17: =ROUND((-'מאזן בוחן'!K474),0) -> 2740891 | L17: 249122.97 | M17: 56413.716 | N17: הוצאות פחת | O17: =IF(P17=0,"",P17/Q17) | P17: =ROUND(('מאזן בוחן'!J623),0) -> 0 | Q17: =ROUND(('מאזן בוחן'!K623),0) -> 0 | S17: =Q17/12 -> 0 | T17: =S17*12 -> 0
A18: חייבים ויתרות חובה | B18: =IF(C18=0,"",C18/D18) | H18: הוצאות לשלם | I18: =IF(J18=0,"",J18/K18) -> 3.1100015 | J18: =ROUND((-SUM('מאזן בוחן'!J449:J456)),0) -> 1371803 | K18: =ROUND((-SUM('מאזן בוחן'!K449:K456)),0) -> 441094 | L18: 0 | M18: 0 | N18: פטנטים | O18: =IF(P18=0,"",P18/Q18) | P18: 0 | Q18: 0 | S18: =Q18/12 -> 0 | T18: =S18*12 -> 0
A19: לקוחות | B19: =IF(C19=0,"",C19/D19) -> 3.11 | C19: ='מאזן בוחן'!J75 -> 13916870 | D19: ='מאזן בוחן'!K75 -> 4474877.7 | H19: חברה אם | I19: =IF(J19=0,"",J19/K19) | L19: =ROUND((-'מאזן בוחן'!L505-'מאזן בוחן'!L456),0) -> 0 | M19: =ROUND((-'מאזן בוחן'!M505-'מאזן בוחן'!M456),0) -> 14641424 | N19: הוצאות מו"פ | O19: =IF(P19=0,"",P19/Q19) | P19: =ROUND(('מאזן בוחן'!J627),0) -> 0 | Q19: =ROUND(('מאזן בוחן'!K627),0) -> 0 | S19: =Q19/12 -> 0 | T19: =S19*12 -> 0
H20: הכנסות מראש חברה בת | J20: =-ROUND(SUM('מאזן בוחן'!J490),0) -> 35665055 | K20: =-ROUND(SUM('מאזן בוחן'!K490),0) -> 11467863
A21: מוסדות | B21: =IF(C21=0,"",C21/D21) -> 3.1235921 | C21: =ROUND(('מאזן בוחן'!J123),0) -> 1970996 | D21: =ROUND((ROUND('מאזן בוחן'!K123,0)),0) -> 631003 | H21: הכנסות מראש | J21: =-ROUND(SUM('מאזן בוחן'!J476:J486),0) -> 14833943 | K21: =-ROUND(SUM('מאזן בוחן'!K476:K486),0) -> 4237920 | L21: 1737092 | M21: 393362.72 | N21: אחזקת רכב | O21: =IF(P21=0,"",P21/Q21) | P21: 0 | Q21: 0 | S21: =Q21/12 -> 0 | T21: =S21*12 -> 0
A22: עובדים | B22: =IF(C22=0,"",C22/D22) | C22: =ROUND(('מאזן בוחן'!J126),0) -> 0 | D22: =ROUND((ROUND('מאזן בוחן'!K126,0)),0) -> 0 | I22: =IF(J22=0,"",J22/K22) -> 3.1784552 | J22: =SUM(J13:J21) -> 76797596 | K22: =SUM(K13:K21) -> 24161925 | N22: העמסת הוצאות | O22: =IF(P22=0,"",P22/Q22) -> 3.313031 | P22: ='מאזן בוחן'!J629 -> 6956062 | Q22: ='מאזן בוחן'!K629 -> 2099606.7 | S22: =Q22/12 -> 174967.22 | T22: =S22*12 -> 2099606.7
A23: הוצאות מראש | B23: =IF(C23=0,"",C23/D23) -> 3.3010847 | C23: =ROUND(('מאזן בוחן'!J141),0) -> 2658720 | D23: =ROUND(('מאזן בוחן'!K141),0) -> 805408 | I23: =IF(J23=0,"",J23/K23) | O23: =IF(P23=0,"",P23/Q23) -> 3.2366652 | P23: =SUM(P15:P22) -> 79843837 | Q23: =SUM(Q15:Q22) -> 24668550 | S23: =SUM(S15:S22) -> 2055712.5 | T23: =SUM(T15:T22) -> 24668550
A24: מסים נדחים זמן קצר | B24: =IF(C24=0,"",C24/D24) | H24: סה"כ התחייבויות שוטפות | I24: =IF(J24=0,"",J24/K24) -> 3.1784552 | J24: =J22+J11 -> 76797596 | K24: =K22+K11 -> 24161925 | L24: 2012829.6 | M24: 455803.31 | N24: עלות מכר | O24: =IF(P24=0,"",P24/Q24) | S24: =Q24/10 -> 0
A25: חברת האם | B25: =IF(C25=0,"",C25/D25) -> 3.11 | C25: =('מאזן בוחן'!J501+'מאזן בוחן'!J503) -> -16043024 | D25: =('מאזן בוחן'!K501+'מאזן בוחן'!K503) -> -5158528.6 | I25: =IF(J25=0,"",J25/K25) | N25: שכר ונלוות | O25: =IF(P31=0,"",P31/Q31) -> 3.2756524 | P25: ='מאזן בוחן'!J659 -> 9664382.5 | Q25: ='מאזן בוחן'!K659 -> 2988267.9 | S25: =Q25/12 -> 249022.32 | T25: =S25*12 -> 2988267.9
A26: חברות בנות | B26: =IF(C26=0,"",C26/D26) -> 3.1100295 | C26: ='מאזן בוחן'!J502+'מאזן בוחן'!J504+'מאזן בוחן'!J498+'מאזן בוחן'!J499+'מאזן בוחן'!J500+'מאזן בוחן'!J496+'מאזן בוחן'!J497 -> 52520370 | D26: ='מאזן בוחן'!K502+'מאזן בוחן'!K504+'מאזן בוחן'!K498+'מאזן בוחן'!K499+'מאזן בוחן'!K500+'מאזן בוחן'!K496+'מאזן בוחן'!K497 -> 16887419 | H26: התחיבויות לזמן ארוך- הכנסות מראש ז.א | I26: =IF(J26=0,"",J26/K26) -> 3.1100004 | J26: =-'מאזן בוחן'!J488 -> 10470146 | K26: =-'מאזן בוחן'!K488 -> 3366606 | N26: תמלוגים ועמלות מכירה | P26: =+SUM('מאזן בוחן'!J710:J710) -> 0 | Q26: =+SUM('מאזן בוחן'!K710:K710) -> 0 | S26: =Q26/12 -> 0 | T26: =S26*12 -> 0
B27: =IF(C27=0,"",C27/D27) -> 3.1192389 | C27: =SUM(C19:C26) -> 55023932 | D27: =SUM(D19:D26) -> 17640179 | H27: התחיבויות לזמן ארוך- הכנסות מראש ז.א TP | I27: =IF(J27=0,"",J27/K27) -> 3.11 | J27: =-'מאזן בוחן'!J494 -> 21497741 | K27: =-'מאזן בוחן'!K494 -> 6912456.9 | L27: 8258008.3 | M27: 1870020 | N27: חשבונית בינחברתית | P27: ='מאזן בוחן'!J706 -> 9389680.8 | Q27: ='מאזן בוחן'!K706 -> 2876821.8 | S27: =Q29/12 -> 186308.53 | T27: =S27*12 -> 2235702.4
H28: התחיבויות לזמן ארוך- מיסים | J28: =-'מאזן בוחן'!J507 -> 245221.47 | K28: =-'מאזן בוחן'!K507 -> 78849.346
B29: =IF(C29=0,"",C29/D29) | H29: עתודה לפיצויים | I29: =IF(J29=0,"",J29/K29) -> 3.1099991 | J29: =ROUND((-'מאזן בוחן'!J508),0) -> 5367790 | K29: =ROUND((-'מאזן בוחן'!K508),0) -> 1725978 | N29: אחרות | P29: ='מאזן בוחן'!J708-P27 -> 7470489.3 | Q29: ='מאזן בוחן'!K708-Q27 -> 2235702.4 | S29: =SUM(S25:S27) -> 435330.85 | T29: =SUM(T25:T27) -> 5223970.3
B30: =IF(C30=0,"",C30/D30) | H30: סה"כ התחייבויות ז.א | I30: =IF(J30=0,"",J30/K30) -> 3.11 | J30: =SUM(J26:J29) -> 37580898 | K30: =SUM(K26:K29) -> 12083890 | L30: =SUM(L26:L29) -> 8258008.3 | M30: =SUM(M26:M29) -> 1870020 | N30: העמסת הוצאות | P30: ='מאזן בוחן'!J711 -> 1101733.7 | Q30: ='מאזן בוחן'!K711 -> 333035.2
A31: סה"כ רכוש שוטף | B31: =IF(C31=0,"",C31/D31) -> 3.1169884 | C31: =C27+C14 -> 72690155 | D31: =D27+D14 -> 23320637 | H31: הון עצמי | I31: =IF(J31=0,"",J31/K31) | P31: =SUM(P25:P30) -> 27626286 | Q31: =SUM(Q25:Q30) -> 8433827.3 | S31: =Q32/10 -> 0
B32: =IF(C32=0,"",C32/D32) | H32: הון מניות | I32: =IF(J32=0,"",J32/K32) | L32: 0 | M32: 0 | S32: =Q33/10 -> 0
A33: פקדון לזמן ארוך | B33: =IF(C33=0,"",C33/D33) -> 3.1129797 | C33: =ROUND(('מאזן בוחן'!J153),0)-C37-C38 -> 543695.08 | D33: =ROUND(('מאזן בוחן'!K153),0)-D37-D38 -> 174654.23 | I33: =IF(J33=0,"",J33/K33) | L33: 0 | M33: 0 | N33: הוצאות הנהלה וכלליות | O33: =IF(P33=0,"",P33/Q33) | S33: =Q34/12 -> 12746.25 | T33: =S33*12 -> 152955
B34: =IF(C34=0,"",C34/D34) | H34: קרן הון | I34: =IF(J34=0,"",J34/K34) | L34: 0 | M34: 0 | N34: שרותים מקצועיים | O34: =IF(P34=0,"",P34/Q34) -> 3.209238 | P34: =ROUND(('מאזן בוחן'!J755),0) -> 490869 | Q34: =ROUND(('מאזן בוחן'!K755),0) -> 152955 | S34: =Q35/12 -> 64103.444 | T34: =S34*12 -> 769241.33
A35: רכוש קבוע | B35: =IF(C35=0,"",C35/D35) -> 3.5267315 | C35: =ROUND(('מאזן בוחן'!J182),0) -> 5696814 | D35: =ROUND(('מאזן בוחן'!K182),0) -> 1615324 | I35: =IF(J35=0,"",J35/K35) | L35: -6541461.3 | M35: -1471612 | N35: שכר דירה ואחזקת משרד | O35: =IF(P35=0,"",P35/Q35) -> 3.2516065 | P35: =SUM('מאזן בוחן'!$J$759:$J$762) -> 2501270.1 | Q35: =SUM('מאזן בוחן'!$K$759:$K$762) -> 769241.33 | S35: =Q36/12 -> 463809.67 | T35: =S35*12 -> 5565716
B36: =IF(C36=0,"",C36/D36) | H36: יתרת רווח לתחילת השנה | I36: =IF(J36=0,"",J36/K36) -> 3.2094039 | J36: =-SUM('מאזן בוחן'!J523) -> -19946063 | K36: =-SUM('מאזן בוחן'!K523) -> -6214880.9 | L36: =E40-L24-L30-L32-L34-L35-L27-L33 -> -11987385 | M36: =F40-M24-M30-M32-M34-M35-M27-M33 -> -2724231.3 | N36: הוצאות שכר | O36: =IF(P36=0,"",P36/Q36) -> 3.2355772 | P36: =ROUND(('מאזן בוחן'!J746),0) -> 18008304 | Q36: =ROUND(('מאזן בוחן'!K746),0) -> 5565716 | S36: =Q37/12 -> 0 | T36: =S36*12 -> 0
A37: יעודה לפיצויים | B37: =IF(C37=0,"",C37/D37) -> 3.11 | C37: ='מאזן בוחן'!J148 -> 786662 | D37: ='מאזן בוחן'!K148 -> 252945.98 | H37: רווח(הפסד) השנה | I37: =IF(J37=0,"",J37/K37) -> 3.1247894 | J37: =P65 -> -13597399 | K37: =Q65 -> -4351460.8 | N37: אחזקת רכב | O37: =IF(P37=0,"",P37/Q37) | P37: =ROUND(('מאזן בוחן'!J859),0) -> 0 | Q37: =ROUND(('מאזן בוחן'!K859),0) -> 0 | S37: =Q38/12 -> 55628.135 | T37: =S37*12 -> 667537.62
A38: הוצ' מראש זמן ארוך | B38: =IF(C38=0,"",C38/D38) -> 3.4963225 | C38: ='מאזן בוחן'!J149 -> 25997.92 | D38: ='מאזן בוחן'!K149 -> 7435.79 | I38: =IF(J38=0,"",J38/K38) -> 3.1745577 | J38: =SUM(J32:J37) -> -33543461 | K38: =SUM(K32:K37) -> -10566342 | N38: ארוח מתנות וכיבודים | O38: =IF(P38=0,"",P38/Q38) -> 3.2195802 | P38: ='מאזן בוחן'!J866-P40 -> 2149190.9 | Q38: ='מאזן בוחן'!K866-Q40 -> 667537.62 | S38: =Q39/12 -> 1367.5867 | T38: =S38*12 -> 16411.04
A39: מסים נדחים זמן ארוך וחייבית אחרים | B39: =IF(C39=0,"",C39/D39) -> 3.5390288 | C39: =ROUND(('מאזן בוחן'!J188),0) -> 1091709 | D39: =ROUND(('מאזן בוחן'!K188),0) -> 308477 | I39: =IF(J39=0,"",J39/K39) | N39: נסיעות לחו"ל | O39: =IF(P39=0,"",P39/Q39) -> 3.1945745 | P39: =SUM('מאזן בוחן'!J817:J836) -> 52426.29 | Q39: =SUM('מאזן בוחן'!K817:K836) -> 16411.04 | S39: =Q40/12 -> 0 | T39: =S39*12 -> 0
A40: סך הכל אקטיב | B40: =IF(C40=0,"",C40/D40) -> 3.1478462 | C40: =C35+C31+C37+C39+C33+C38 -> 80835033 | D40: =D35+D31+D37+D39+D33+D38 -> 25679474 | H40: סך הכל פאסיב | I40: =IF(J40=0,"",J40/K40) -> 3.1478462 | J40: =J24+J30+J38 -> 80835033 | K40: =K24+K30+K38 -> 25679474 | L40: 3743484.7 | M40: 857406.26 | N40: ארוח חו"ל | O40: =IF(P40=0,"",P40/Q40) | P40: =ROUND(('מאזן בוחן'!J865),0) -> 0 | Q40: =ROUND(('מאזן בוחן'!K865),0) -> 0 | S40: =Q41/12 -> 0 | T40: =S40*12 -> 0
B41: =IF(C41=0,"",C41/D41) | J41: =J40-C40 -> -0.29910055 | K41: =K40-D40 -> -0.28108458 | L41: 0 | M41: 0 | O41: =IF(P41=0,"",P41/Q41) | S41: =Q42/12 -> 42947.5 | T41: =S41*12 -> 515370
B42: =IF(C42=0,"",C42/D42) | N42: פחת | O42: =IF(P42=0,"",P42/Q42) -> 3.6682112 | P42: =ROUND(('מאזן בוחן'!J749),0) -> 1890486 | Q42: =ROUND(('מאזן בוחן'!K749),0) -> 515370 | S42: =Q43/12 -> 84083.809 | T42: =S42*12 -> 1009005.7
N43: הוצאות שונות | O43: =IF(P43=0,"",P43/Q43) -> 3.2621295 | P43: ='מאזן בוחן'!J852-P35-P39 -> 3291507.3 | Q43: ='מאזן בוחן'!K852-Q35-Q39 -> 1009005.7 | S43: =Q44/12 -> -247467.57 | T43: =S43*12 -> -2969610.8
N44: בניכוי הוצאות הנכ"ל שהועמסו | O44: =IF(P44=0,"",P44/Q44) -> 3.3076231 | P44: ='מאזן בוחן'!J855 -> -9822353.4 | Q44: ='מאזן בוחן'!K855 -> -2969610.8 | S44: =SUM(S33:S43) -> 477218.82 | T44: =SUM(T33:T43) -> 5726625.9
O45: =IF(P45=0,"",P45/Q45) -> 3.2412979 | P45: =SUM(P34:P44) -> 18561700 | Q45: =SUM(Q34:Q44) -> 5726625.9 | S45: =Q46/10 -> 0
S46: =Q47/10 -> 0
N47: הוצאות שיווק ומכירות | O47: =IF(P47=0,"",P47/Q47) | S47: =Q48/12 -> 316766.75 | T47: =S47*12 -> 3801201
N48: הוצאות שכר | O48: =IF(P48=0,"",P48/Q48) -> 3.2468446 | P48: =ROUND(('מאזן בוחן'!J919),0)-P49 -> 12341909 | Q48: =ROUND(('מאזן בוחן'!K919),0)-Q49 -> 3801201 | S48: =Q49/12 -> 0 | T48: =S48*12 -> 0
N49: תמלוגים למפיצים | O49: =IF(P49=0,"",P49/Q49) | S49: =Q50/12 -> 0 | T49: =S49*12 -> 0
N50: אחזקת רכב | O50: =IF(P50=0,"",P50/Q50) | P50: ='מאזן בוחן'!J981 -> 0 | Q50: ='מאזן בוחן'!K981 -> 0 | S50: =Q51/12 -> 14075.228 | T50: =S50*12 -> 168902.74
N51: נסיעות לחו"ל | O51: =IF(P51=0,"",P51/Q51) -> 3.2360911 | P51: =SUM('מאזן בוחן'!J928:J932,'מאזן בוחן'!J951:J956,'מאזן בוחן'!J967:J975) -> 546584.66 | Q51: =SUM('מאזן בוחן'!K928:K932,'מאזן בוחן'!K951:K956,'מאזן בוחן'!K967:K975) -> 168902.74 | S51: =Q52/12 -> 154327.66 | T51: =S51*12 -> 1851931.9
N52: אחרות | O52: =IF(P52=0,"",P52/Q52) -> 3.2432187 | P52: ='מאזן בוחן'!J977-P51-P53 -> 6006220.3 | Q52: ='מאזן בוחן'!K977-Q51-Q53 -> 1851931.9 | S52: =Q53/12 -> 19350.007 | T52: =S52*12 -> 232200.08
N53: תערוכות ופרסום | O53: =IF(P53=0,"",P53/Q53) -> 3.1899499 | P53: ='מאזן בוחן'!J933+'מאזן בוחן'!J942 -> 740706.63 | Q53: ='מאזן בוחן'!K933+'מאזן בוחן'!K942 -> 232200.08 | S53: =Q54/12 -> 0 | T53: =S53*12 -> 0
N54: פחת | O54: =IF(P54=0,"",P54/Q54) | P54: ='מאזן בוחן'!J922 -> 0 | Q54: ='מאזן בוחן'!K922 -> 0 | S54: =Q55/12 -> 44747.417 | T54: =S54*12 -> 536969
N55: הנכ"ל שהועמסו | O55: =IF(P55=0,"",P55/Q55) -> 3.286145 | P55: =ROUND(('מאזן בוחן'!J985),0) -> 1764558 | Q55: =ROUND(('מאזן בוחן'!K985),0) -> 536969 | S55: =SUM(S47:S54) -> 549267.06 | T55: =SUM(T47:T54) -> 6591204.7
O56: =IF(P56=0,"",P56/Q56) -> 3.2467477 | P56: =SUM(P48:P55) -> 21399979 | Q56: =SUM(Q48:Q55) -> 6591204.7 | S56: =Q57/10 -> 0
O57: =IF(P57=0,"",P57/Q57) | S57: =S12-S23-S29-S44-S55 -> 89479.065 | T57: =T12-T23-T29-T44-T55 -> 1073748.8
N58: רווח לפני הכנסות מימון,נטו | O58: =IF(P58=0,"",P58/Q58) -> 2.7423017 | P58: =P12-P23-P31-P45-P56 -> -5857853.2 | Q58: =Q12-Q23-Q31-Q45-Q56 -> -2136108.3 | S58: =Q59/10 -> 0
O59: =IF(P59=0,"",P59/Q59) | S59: =Q60/12 -> 122406.5
N60: הוצאות (הכנסות) מימון ,נטו | P60: =ROUND(('מאזן בוחן'!J1007),0)-P62 -> 5381126.3 | Q60: =ROUND(('מאזן בוחן'!K1007),0)-Q62+2 -> 1468878 | S60: =Q61/10 -> 0
N61: הפרשי תרגום (הוצאות/(הכנסות) | O61: =IF(P61=0,"",P61/Q61) | S61: =Q62/10 -> 398.804
N62: הפסד ממימוש רכוש קבוע | P62: ='מאזן בוחן'!J1005 -> 20327.74 | Q62: ='מאזן בוחן'!K1005 -> 3988.04 | S62: =S57-S59-S61 -> -33326.236 | T62: =T57-T59-T61 -> 1073748.8
N63: רווח לפני מסים על ההכנסה | P63: =P58-P60-P62 -> -11259307 | Q63: =Q58-Q60-Q62 -> -3608974.3 | S63: =Q64/12 -> 61873.88 | T63: =T62*#REF! -> #REF!
N64: מיסים על ההכנסה | P64: ='מאזן בוחן'!J996 -> 2338091.6 | Q64: ='מאזן בוחן'!K996 -> 742486.56 | S64: =S62-S63 -> -95200.115 | T64: =T62-T63 -> #REF!
N65: רווח לשנה | P65: =P63-P64 -> -13597399 | Q65: =Q63-Q64 -> -4351460.8

Sheet מאזן בוחן
E1: =E1010 -> 1.3969839e-08 | F1: =F1010/2 -> 0 | G1: =G1010/2 -> 0 | H1: =H1010/2 -> 0 | I1: =I1010/2 -> 0 | J1: =J1010 -> 1.9557774e-08 | K1: =K1010 -> -4.1909516e-09 | M1: =M1010 -> 0
B2: Algosec System Ltd | M2: שע"ח סוף תקופה | N2: ='נתונים לשינוי'!B7 -> 3.11
E3: ='נתונים לשינוי'!C1 -> 44561 | M3: שע"ח ממוצע | N3: ='נתונים לשינוי'!D8 -> 3.2293
E4: NIS | J4: NIS | K4: USD | M4: USD | N4: Rates
E5: יתרה לפי | F5: פקודות | G5: פקודות | H5: פקודות | I5: פקודות | J5: יתרה לאחר | K5: יתרה לאחר | M5: יתרה לפי
D6: סעיף | E6: מאזן | F6: נוספות | G6: נוספות | H6: נוספות | I6: נוספות | J6: נומינלי | K6: דולרי | M6: מאזן
E7: בוחן | F7: ח'(ז') | G7: ח'(ז') | H7: 'ח | I7: ('ז) | J7: ח'(ז') | K7: ח'(ז') | M7: בוחן | AB7: 01/2021 | AC7: 02/2021 | AD7: 03/2021 | AE7: 04/2021 | AF7: 05/2021 | AG7: 06/2021 | AH7: 07/2021 | AI7: 08/2021 | AJ7: 09/2021 | AK7: 10/2021 | AL7: 11/2021 | AM7: 12/2021
D8: Cash & Cash Equivalents
B9: 100.בנקים ומזומנים | C9: 1000020 | D9: בנק לאומי 522600/83 עו"ש שקל | E9: =VLOOKUP(C9,'פקודות נוספות'!$D$274:$F$797,3,0) -> 5177110 | F9: =SUMIF('פקודות נוספות'!C:C,C:C,'פקודות נוספות'!E:E) -> 0 | J9: =SUM(E9:I9) -> 5177110 | K9: =M9+SUMIF('פקודות נוספות'!C:C,'מאזן בוחן'!C9,'פקודות נוספות'!F:F) -> 1664665.6 | M9: =VLOOKUP(C9,'פקודות נוספות'!$D$273:$G$797,4,0) -> 1664665.6 | N9: =IF(K9=0,"-",J9/K9) -> 3.11
D10: סה"כ מזומנים בש"ח | E10: =SUM(E9:E9) -> 5177110 | F10: =SUM(F9:F9) -> 0 | G10: =SUM(G9:G9) -> 0 | H10: =SUM(H9:H9) -> 0 | I10: =SUM(I9:I9) -> 0 | J10: =SUM(J9:J9) -> 5177110 | K10: =SUM(K9:K9) -> 1664665.6 | M10: =SUM(M9:M9) -> 1664665.6 | N10: =IF(K10=0,"-",J10/K10) -> 3.11
D14: סה"כ פקדונות בש"ח | E14: =SUM(E11:E13) -> 0 | F14: =SUM(F11:F13) -> 0 | G14: =SUM(G11:G13) -> 0 | H14: =SUM(H11:H13) -> 0 | I14: =SUM(I11:I13) -> 0 | J14: =SUM(J11:J13) -> 0 | K14: =SUM(K11:K13) -> 0 | M14: =SUM(M11:M13) -> 0
B15: 100.בנקים ומזומנים | C15: 1000021 | D15: בנק לאומי דולר 522600/83 $ | E15: =IFERROR(VLOOKUP(C15,'פקודות נוספות'!$D$274:$F$797,3,0),0) -> 7928899 | F15: =SUMIF('פקודות נוספות'!C:C,C:C,'פקודות נוספות'!E:E) -> 0 | J15: =SUM(E15:I15) -> 7928899 | K15: =M15+SUMIF('פקודות נוספות'!C:C,'מאזן בוחן'!C15,'פקודות נוספות'!F:F) -> 2549485.2 | M15: =IFERROR(VLOOKUP(C15,'פקודות נוספות'!$D$273:$G$797,4,0),0) -> 2549485.2 | N15: =IF(K15=0,"-",J15/K15) -> 3.11
B16: 100.בנקים ומזומנים | C16: 1000024 | D16: בנק לאומי ליש"ט 522600/83 | E16: =IFERROR(VLOOKUP(C16,'פקודות נוספות'!$D$274:$F$797,3,0),0) -> 2942170 | F16: =SUMIF('פקודות נוספות'!C:C,C:C,'פקודות נוספות'!E:E) -> 0 | J16: =SUM(E16:I16) -> 2942170 | K16: =M16+SUMIF('פקודות נוספות'!C:C,'מאזן בוחן'!C16,'פקודות נוספות'!F:F) -> 946035.37 | L16: =J16/'נתונים לשינוי'!$C$20-700000 -> 0 | M16: =IFERROR(VLOOKUP(C16,'פקודות נוספות'!$D$273:$G$797,4,0),0) -> 946035.37 | N16: =IF(K16=0,"-",J16/K16) -> 3.11
B17: 100.בנקים ומזומנים | C17: 1000022 | D17: בנק לאומי ארה"ב חשבון 0768660918 | E17: =IFERROR(VLOOKUP(C17,'פקודות נוספות'!$D$274:$F$797,3,0),0) -> 1092819.3 | F17: =SUMIF('פקודות נוספות'!C:C,C:C,'פקודות נוספות'!E:E) -> 0 | J17: =SUM(E17:I17) -> 1092819.3 | K17: =M17+SUMIF('פקודות נוספות'!C:C,'מאזן בוחן'!C17,'פקודות נוספות'!F:F) -> 351388.83 | M17: =IFERROR(VLOOKUP(C17,'פקודות נוספות'!$D$273:$G$797,4,0),0) -> 351388.83 | N17: =IF(K17=0,"-",J17/K17) -> 3.11
B18: 100.בנקים ומזומנים | C18: 1000023 | D18: בנק לאומי יורו 522600/83 | E18: =IFERROR(VLOOKUP(C18,'פקודות נוספות'!$D$274:$F$797,3,0),0) -> 524796.36 | F18: =SUMIF('פקודות נוספות'!C:C,C:C,'פקודות נוספות'!E:E) -> 0 | J18: =SUM(E18:I18) -> 524796.36 | K18: =M18+SUMIF('פקודות נוספות'!C:C,'מאזן בוחן'!C18,'פקודות נוספות'!F:F) -> 168744.81 | L18: =J18/'נתונים לשינוי'!$C$21-149094 -> 0.11062814 | M18: =IFERROR(VLOOKUP(C18,'פקודות נוספות'!$D$273:$G$797,4,0),0) -> 168744.81 | N18: =IF(K18=0,"-",J18/K18) -> 3.11
B19: 100.בנקים ומזומנים | C19: 10010 | D19: בנק לאומי דולר אוסטרלי | E19: =IFERROR(VLOOKUP(C19,'פקודות נוספות'!$D$274:$F$797,3,0),0) -> 0 | F19: =SUMIF('פקודות נוספות'!C:C,C:C,'פקודות נוספות'!E:E) -> 0 | J19: =SUM(E19:I19) -> 0 | K19: =M19+SUMIF('פקודות נוספות'!C:C,'מאזן בוחן'!C19,'פקודות נוספות'!F:F) -> 0 | L19: =K19/'נתונים לשינוי'!C23*'נתונים לשינוי'!C22-0 -> 0 | M19: =IFERROR(VLOOKUP(C19,'פקודות נוספות'!$D$273:$G$797,4,0),0) -> 0 | N19: =IF(K19=0,"-",J19/K19) -> -
B20: 100.בנקים ומזומנים | C20: 1000030 | D20: קופה קטנה משרד | E20: =IFERROR(VLOOKUP(C20,'פקודות נוספות'!$D$274:$F$797,3,0),0) -> 428.02 | F20: =SUMIF('פקודות נוספות'!C:C,C:C,'פקודות נוספות'!E:E) -> 0 | J20: =SUM(E20:I20) -> 428.02 | K20: =M20+SUMIF('פקודות נוספות'!C:C,'מאזן בוחן'!C20,'פקודות נוספות'!F:F) -> 137.63 | L20: =428-J20 -> -0.02 | M20: =IFERROR(VLOOKUP(C20,'פקודות נוספות'!$D$273:$G$797,4,0),0) -> 137.63 | N20: =IF(K20=0,"-",J20/K20) -> 3.1099324
D22: סה"כ מזומנים במט"ח | E22: =SUM(E15:E21) -> 12489113 | F22: =SUM(F15:F21) -> 0 | G22: =SUM(G15:G21) -> 0 | H22: =SUM(H15:H21) -> 0 | I22: =SUM(I15:I21) -> 0 | J22: =SUM(J15:J21) -> 12489113 | K22: =SUM(K15:K21) -> 4015791.8 | M22: =SUM(M15:M21) -> 4015791.8
D26: סה"כ פקדונות במט"ח | E26: =SUM(E24:E25) -> 0 | F26: =SUM(F24:F25) -> 0 | G26: =SUM(G24:G25) -> 0 | H26: =SUM(H24:H25) -> 0 | I26: =SUM(I24:I25) -> 0 | J26: =SUM(J24:J25) -> 0 | K26: =SUM(K24:K25) -> 0 | M26: =SUM(M24:M25) -> 0
D29: סה"כ קופות קטנות | E29: =SUM(E28:E28) -> 0 | F29: =SUM(F28:F28) -> 0 | G29: =SUM(G28:G28) -> 0 | H29: =SUM(H28:H28) -> 0 | I29: =SUM(I28:I28) -> 0 | J29: =SUM(J28:J28) -> 0 | K29: =SUM(K28:K28) -> 0 | M29: =SUM(M28:M28) -> 0
D31: סה"כ מזומנים וש"מ | E31: =E29+E26+E22+E14+E10 -> 17666223 | F31: =F29+F26+F22+F14+F10 -> 0 | G31: =G29+G26+G22+G14+G10 -> 0 | H31: =H29+H26+H22+H14+H10 -> 0 | I31: =I29+I26+I22+I14+I10 -> 0 | J31: =J29+J26+J22+J14+J10 -> 17666223 | K31: =K29+K26+K22+K14+K10 -> 5680457.4 | M31: =M29+M26+M22+M14+M10 -> 5680457.4
D33: לקוחות
B35: 130.לקוחות ILS | C35: 207978 | D35: Security4IT | E35: =IFERROR(VLOOKUP(C35,'פקודות נוספות'!$D$274:$F$797,3,0),0) -> 0 | F35: =SUMIF('פקודות נוספות'!C:C,C:C,'פקודות נוספות'!E:E) -> 0 | J35: =SUM(E35:I35) -> 0 | K35: =M35+SUMIF('פקודות נוספות'!C:C,'מאזן בוחן'!C35,'פקודות נוספות'!F:F) -> 0 | M35: =IFERROR(VLOOKUP(C35,'פקודות נוספות'!$D$273:$G$797,4,0),0) -> 0 | N35: =IF(K35=0,"-",J35/K35) -> -
B36: 130.לקוחות ILS | C36: 201267 | D36: Bezeq Intl | E36: =IFERROR(VLOOKUP(C36,'פקודות נוספות'!$D$274:$F$797,3,0),0) -> 267932.14 | F36: =SUMIF('פקודות נוספות'!C:C,C:C,'פקודות נוספות'!E:E) -> 0 | J36: =SUM(E36:I36) -> 267932.14 | K36: =M36+SUMIF('פקודות נוספות'!C:C,'מאזן בוחן'!C36,'פקודות נוספות'!F:F) -> 86151.81 | M36: =IFERROR(VLOOKUP(C36,'פקודות נוספות'!$D$273:$G$797,4,0),0) -> 86151.81 | N36: =IF(K36=0,"-",J36/K36) -> 3.1100001
B37: 130.לקוחות ILS | C37: 209280 | D37: TrustNet | E37: =IFERROR(VLOOKUP(C37,'פקודות נוספות'!$D$274:$F$797,3,0),0) -> 82957.7 | F37: =SUMIF('פקודות נוספות'!C:C,C:C,'פקודות נוספות'!E:E) -> 0 | J37: =SUM(E37:I37) -> 82957.7 | K37: =M37+SUMIF('פקודות נוספות'!C:C,'מאזן בוחן'!C37,'פקודות נוספות'!F:F) -> 26674.5 | M37: =IFERROR(VLOOKUP(C37,'פקודות נוספות'!$D$273:$G$797,4,0),0) -> 26674.5 | N37: =IF(K37=0,"-",J37/K37) -> 3.1100002
B38: 130.לקוחות ILS | C38: 226550 | D38: Perion Solution Co., Ltd | E38: =IFERROR(VLOOKUP(C38,'פקודות נוספות'!$D$274:$F$797,3,0),0) -> 99271.2 | F38: =SUMIF('פקודות נוספות'!C:C,C:C,'פקודות נוספות'!E:E) -> 0 | J38: =SUM(E38:I38) -> 99271.2 | K38: =M38+SUMIF('פקודות נוספות'!C:C,'מאזן בוחן'!C38,'פקודות נוספות'!F:F) -> 31920 | M38: =IFERROR(VLOOKUP(C38,'פקודות נוספות'!$D$273:$G$797,4,0),0) -> 31920 | N38: =IF(K38=0,"-",J38/K38) -> 3.11
B39: 131.לקוחות $ | C39: 206364 | D39: ScanSource Brasil Distribuidora de Tecnologias L | E39: =IFERROR(VLOOKUP(C39,'פקודות נוספות'!$D$274:$F$797,3,0),0) -> 30135.9 | F39: =SUMIF('פקודות נוספות'!C:C,C:C,'פקודות נוספות'!E:E) -> 0 | J39: =SUM(E39:I39) -> 30135.9 | K39: =M39+SUMIF('פקודות נוספות'!C:C,'מאזן בוחן'!C39,'פקודות נוספות'!F:F) -> 9690 | M39: =IFERROR(VLOOKUP(C39,'פקודות נוספות'!$D$273:$G$797,4,0),0) -> 9690 | N39: =IF(K39=0,"-",J39/K39) -> 3.11
B40: 131.לקוחות $ | C40: 231045 | D40: Tech Mahindra (Singapore) Pte Ltd | E40: =IFERROR(VLOOKUP(C40,'פקודות נוספות'!$D$274:$F$797,3,0),0) -> 1754002.7 | F40: =SUMIF('פקודות נוספות'!C:C,C:C,'פקודות נוספות'!E:E) -> 0 | J40: =SUM(E40:I40) -> 1754002.7 | K40: =M40+SUMIF('פקודות נוספות'!C:C,'מאזן בוחן'!C40,'פקודות נוספות'!F:F) -> 563988 | M40: =IFERROR(VLOOKUP(C40,'פקודות נוספות'!$D$273:$G$797,4,0),0) -> 563988 | N40: =IF(K40=0,"-",J40/K40) -> 3.11
B41: 130.לקוחות ILS | C41: 201599 | D41: Bynet Data Communications ltd | E41: =IFERROR(VLOOKUP(C41,'פקודות נוספות'!$D$274:$F$797,3,0),0) -> 23153.27 | F41: =SUMIF('פקודות נוספות'!C:C,C:C,'פקודות נוספות'!E:E) -> 0 | J41: =SUM(E41:I41) -> 23153.27 | K41: =M41+SUMIF('פקודות נוספות'!C:C,'מאזן בוחן'!C41,'פקודות נוספות'!F:F) -> 7444.78 | M41: =IFERROR(VLOOKUP(C41,'פקודות נוספות'!$D$273:$G$797,4,0),0) -> 7444.78 | N41: =IF(K41=0,"-",J41/K41) -> 3.1100006
B42: 130.לקוחות ILS | C42: 217664 | D42: 10Secure Infinity Information Security Ltd. | E42: =IFERROR(VLOOKUP(C42,'פקודות נוספות'!$D$274:$F$797,3,0),0) -> 22330.62 | F42: =SUMIF('פקודות נוספות'!C:C,C:C,'פקודות נוספות'!E:E) -> 0 | J42: =SUM(E42:I42) -> 22330.62 | K42: =M42+SUMIF('פקודות נוספות'!C:C,'מאזן בוחן'!C42,'פקודות נוספות'!F:F) -> 7180.26 | M42: =IFERROR(VLOOKUP(C42,'פקודות נוספות'!$D$273:$G$797,4,0),0) -> 7180.26 | N42: =IF(K42=0,"-",J42/K42) -> 3.1100016
B43: 130.לקוחות ILS | C43: 232189 | D43: Exclusive Networks Singapore | E43: =IFERROR(VLOOKUP(C43,'פקודות נוספות'!$D$274:$F$797,3,0),0) -> 429804.55 | F43: =SUMIF('פקודות נוספות'!C:C,C:C,'פקודות נוספות'!E:E) -> 0 | J43: =SUM(E43:I43) -> 429804.55 | K43: =M43+SUMIF('פקודות נוספות'!C:C,'מאזן בוחן'!C43,'פקודות נוספות'!F:F) -> 138200.82 | M43: =IFERROR(VLOOKUP(C43,'פקודות נוספות'!$D$273:$G$797,4,0),0) -> 138200.82 | N43: =IF(K43=0,"-",J43/K43) -> 3.11 | O43: Waiting for payment confirmation
B44: 131.לקוחות $ | C44: 206331 | D44: Netpoleon Solutions Pte Ltd | E44: =IFERROR(VLOOKUP(C44,'פקודות נוספות'!$D$274:$F$797,3,0),0) -> 29382.38 | F44: =SUMIF('פקודות נוספות'!C:C,C:C,'פקודות נוספות'!E:E) -> 0 | J44: =SUM(E44:I44) -> 29382.38 | K44: =M44+SUMIF('פקודות נוספות'!C:C,'מאזן בוחן'!C44,'פקודות נוספות'!F:F) -> 9447.71 | M44: =IFERROR(VLOOKUP(C44,'פקודות נוספות'!$D$273:$G$797,4,0),0) -> 9447.71 | N44: =IF(K44=0,"-",J44/K44) -> 3.1100002
B45: 130.לקוחות ILS | C45: 232025 | D45: iValue InfoSolutions Pvt Ltd. - Singapore Branch | E45: =IFERROR(VLOOKUP(C45,'פקודות נוספות'!$D$274:$F$797,3,0),0) -> 67919.2 | F45: =SUMIF('פקודות נוספות'!C:C,C:C,'פקודות נוספות'!E:E) -> 0 | J45: =SUM(E45:I45) -> 67919.2 | K45: =M45+SUMIF('פקודות נוספות'!C:C,'מאזן בוחן'!C45,'פקודות נוספות'!F:F) -> 21838.97 | M45: =IFERROR(VLOOKUP(C45,'פקודות נוספות'!$D$273:$G$797,4,0),0) -> 21838.97 | N45: =IF(K45=0,"-",J45/K45) -> 3.1100002
B46: 131.לקוחות $ | C46: 202339 | D46: Contacta Seguranca em Conectividade LTDA | E46: =IFERROR(VLOOKUP(C46,'פקודות נוספות'!$D$274:$F$797,3,0),0) -> 35507.8 | F46: =SUMIF('פקודות נוספות'!C:C,C:C,'פקודות נוספות'!E:E) -> 0 | J46: =SUM(E46:I46) -> 35507.8 | K46: =M46+SUMIF('פקודות נוספות'!C:C,'מאזן בוחן'!C46,'פקודות נוספות'!F:F) -> 11417.3 | M46: =IFERROR(VLOOKUP(C46,'פקודות נוספות'!$D$273:$G$797,4,0),0) -> 11417.3 | N46: =IF(K46=0,"-",J46/K46) -> 3.1099997
B47: 131.לקוחות $ | C47: 209952 | D47: Westcon Solutions China | E47: =IFERROR(VLOOKUP(C47,'פקודות נוספות'!$D$274:$F$797,3,0),0) -> 0 | F47: =SUMIF('פקודות נוספות'!C:C,C:C,'פקודות נוספות'!E:E) -> 0 | J47: =SUM(E47:I47) -> 0 | K47: =M47+SUMIF('פקודות נוספות'!C:C,'מאזן בוחן'!C47,'פקודות נוספות'!F:F) -> 0 | M47: =IFERROR(VLOOKUP(C47,'פקודות נוספות'!$D$273:$G$797,4,0),0) -> 0 | N47: =IF(K47=0,"-",J47/K47) -> -
B48: 131.לקוחות $ | C48: 202629 | D48: Datalink Business Solutions Ltd. | E48: =IFERROR(VLOOKUP(C48,'פקודות נוספות'!$D$274:$F$797,3,0),0) -> 0 | F48: =SUMIF('פקודות נוספות'!C:C,C:C,'פקודות נוספות'!E:E) -> 0 | J48: =SUM(E48:I48) -> 0 | K48: =M48+SUMIF('פקודות נוספות'!C:C,'מאזן בוחן'!C48,'פקודות נוספות'!F:F) -> 0 | M48: =IFERROR(VLOOKUP(C48,'פקודות נוספות'!$D$273:$G$797,4,0),0) -> 0 | N48: =IF(K48=0,"-",J48/K48) -> -
B49: 131.לקוחות $ | C49: 209224 | D49: Exclusive Networks Asia Pte Ltd | E49: =IFERROR(VLOOKUP(C49,'פקודות נוספות'!$D$274:$F$797,3,0),0) -> 178617.63 | F49: =SUMIF('פקודות נוספות'!C:C,C:C,'פקודות נוספות'!E:E) -> 0 | J49: =SUM(E49:I49) -> 178617.63 | K49: =M49+SUMIF('פקודות נוספות'!C:C,'מאזן בוחן'!C49,'פקודות נוספות'!F:F) -> 57433.32 | M49: =IFERROR(VLOOKUP(C49,'פקודות נוספות'!$D$273:$G$797,4,0),0) -> 57433.32 | N49: =IF(K49=0,"-",J49/K49) -> 3.1100001
B50: 130.לקוחות ILS | C50: 208844 | D50: Tech Mahindra Ltd. | E50: =IFERROR(VLOOKUP(C50,'פקודות נוספות'!$D$274:$F$797,3,0),0) -> 0 | F50: =SUMIF('פקודות נוספות'!C:C,C:C,'פקודות נוספות'!E:E) -> 0 | J50: =SUM(E50:I50) -> 0 | K50: =M50+SUMIF('פקודות נוספות'!C:C,'מאזן בוחן'!C50,'פקודות נוספות'!F:F) -> 0 | M50: =IFERROR(VLOOKUP(C50,'פקודות נוספות'!$D$273:$G$797,4,0),0) -> 0 | N50: =IF(K50=0,"-",J50/K50) -> -
B51: 131.לקוחות $ | C51: 205457 | D51: Licencias On Line S.A.S | E51: =IFERROR(VLOOKUP(C51,'פקודות נוספות'!$D$274:$F$797,3,0),0) -> 23004.67 | F51: =SUMIF('פקודות נוספות'!C:C,C:C,'פקודות נוספות'!E:E) -> 0 | J51: =SUM(E51:I51) -> 23004.67 | K51: =M51+SUMIF('פקודות נוספות'!C:C,'מאזן בוחן'!C51,'פקודות נוספות'!F:F) -> 7397 | M51: =IFERROR(VLOOKUP(C51,'פקודות נוספות'!$D$273:$G$797,4,0),0) -> 7397 | N51: =IF(K51=0,"-",J51/K51) -> 3.11
B52: 130.לקוחות ILS | C52: 228871 | D52: Software Sources | E52: =IFERROR(VLOOKUP(C52,'פקודות נוספות'!$D$274:$F$797,3,0),0) -> 0 | F52: =SUMIF('פקודות נוספות'!C:C,C:C,'פקודות נוספות'!E:E) -> 0 | J52: =SUM(E52:I52) -> 0 | K52: =M52+SUMIF('פקודות נוספות'!C:C,'מאזן בוחן'!C52,'פקודות נוספות'!F:F) -> 0 | M52: =IFERROR(VLOOKUP(C52,'פקודות נוספות'!$D$273:$G$797,4,0),0) -> 0 | N52: =IF(K52=0,"-",J52/K52) -> -
B53: 131.לקוחות $ | C53: 205984 | D53: Misoft JSC | E53: =IFERROR(VLOOKUP(C53,'פקודות נוספות'!$D$274:$F$797,3,0),0) -> 0 | F53: =SUMIF('פקודות נוספות'!C:C,C:C,'פקודות נוספות'!E:E) -> 0 | J53: =SUM(E53:I53) -> 0 | K53: =M53+SUMIF('פקודות נוספות'!C:C,'מאזן בוחן'!C53,'פקודות נוספות'!F:F) -> 0 | M53: =IFERROR(VLOOKUP(C53,'פקודות נוספות'!$D$273:$G$797,4,0),0) -> 0 | N53: =IF(K53=0,"-",J53/K53) -> -
B54: 130.לקוחות ILS | C54: 202129 | D54: CLM Software Comercio Importação e Exportação Lt | E54: =IFERROR(VLOOKUP(C54,'פקודות נוספות'!$D$274:$F$797,3,0),0) -> 0 | F54: =SUMIF('פקודות נוספות'!C:C,C:C,'פקודות נוספות'!E:E) -> 0 | J54: =SUM(E54:I54) -> 0 | K54: =M54+SUMIF('פקודות נוספות'!C:C,'מאזן בוחן'!C54,'פקודות נוספות'!F:F) -> 0 | M54: =IFERROR(VLOOKUP(C54,'פקודות נוספות'!$D$273:$G$797,4,0),0) -> 0 | N54: =IF(K54=0,"-",J54/K54) -> -
B55: 130.לקוחות ILS | C55: 206964 | D55: PCS Security Pte Ltd | E55: =IFERROR(VLOOKUP(C55,'פקודות נוספות'!$D$274:$F$797,3,0),0) -> 0 | F55: =SUMIF('פקודות נוספות'!C:C,C:C,'פקודות נוספות'!E:E) -> 0 | J55: =SUM(E55:I55) -> 0 | K55: =M55+SUMIF('פקודות נוספות'!C:C,'מאזן בוחן'!C55,'פקודות נוספות'!F:F) -> 0 | M55: =IFERROR(VLOOKUP(C55,'פקודות נוספות'!$D$273:$G$797,4,0),0) -> 0 | N55: =IF(K55=0,"-",J55/K55) -> -
B56: 130.לקוחות ILS | C56: 207734 | D56: Safeway Data Protection Solutions Ltd. | E56: =IFERROR(VLOOKUP(C56,'פקודות נוספות'!$D$274:$F$797,3,0),0) -> 7146.82 | F56: =SUMIF('פקודות נוספות'!C:C,C:C,'פקודות נוספות'!E:E) -> 0 | J56: =SUM(E56:I56) -> 7146.82 | K56: =M56+SUMIF('פקודות נוספות'!C:C,'מאזן בוחן'!C56,'פקודות נוספות'!F:F) -> 2298.01 | M56: =IFERROR(VLOOKUP(C56,'פקודות נוספות'!$D$273:$G$797,4,0),0) -> 2298.01 | N56: =IF(K56=0,"-",J56/K56) -> 3.1100039
B57: 130.לקוחות ILS | C57: 221716 | D57: Comgene Ltd. | E57: =IFERROR(VLOOKUP(C57,'פקודות נוספות'!$D$274:$F$797,3,0),0) -> 293490.11 | F57: =SUMIF('פקודות נוספות'!C:C,C:C,'פקודות נוספות'!E:E) -> 0 | J57: =SUM(E57:I57) -> 293490.11 | K57: =M57+SUMIF('פקודות נוספות'!C:C,'מאזן בוחן'!C57,'פקודות נוספות'!F:F) -> 94369.81 | M57: =IFERROR(VLOOKUP(C57,'פקודות נוספות'!$D$273:$G$797,4,0),0) -> 94369.81 | N57: =IF(K57=0,"-",J57/K57) -> 3.11 | O57: Payment will be made by end of December 2021
B58: 130.לקוחות ILS | C58: 228747 | D58: NTT Brasil Comercio e Servicos de Tecnologia Ltd | E58: =IFERROR(VLOOKUP(C58,'פקודות נוספות'!$D$274:$F$797,3,0),0) -> 512643.75 | F58: =SUMIF('פקודות נוספות'!C:C,C:C,'פקודות נוספות'!E:E) -> 0 | J58: =SUM(E58:I58) -> 512643.75 | K58: =M58+SUMIF('פקודות נוספות'!C:C,'מאזן בוחן'!C58,'פקודות נוספות'!F:F) -> 164837.22 | M58: =IFERROR(VLOOKUP(C58,'פקודות נוספות'!$D$273:$G$797,4,0),0) -> 164837.22 | N58: =IF(K58=0,"-",J58/K58) -> 3.11 | O58: יכוי במקור
B59: 131.לקוחות $ | C59: 221670 | D59: Inventivo Pte Ltd | E59: =IFERROR(VLOOKUP(C59,'פקודות נוספות'!$D$274:$F$797,3,0),0) -> 0 | F59: =SUMIF('פקודות נוספות'!C:C,C:C,'פקודות נוספות'!E:E) -> 0 | J59: =SUM(E59:I59) -> 0 | K59: =M59+SUMIF('פקודות נוספות'!C:C,'מאזן בוחן'!C59,'פקודות נוספות'!F:F) -> 0 | M59: =IFERROR(VLOOKUP(C59,'פקודות נוספות'!$D$273:$G$797,4,0),0) -> 0 | N59: =IF(K59=0,"-",J59/K59) -> -
B60: 131.לקוחות $ | C60: 226481 | D60: Revel Tech (SG) Holdings Pte Ltd | E60: =IFERROR(VLOOKUP(C60,'פקודות נוספות'!$D$274:$F$797,3,0),0) -> 0 | F60: =SUMIF('פקודות נוספות'!C:C,C:C,'פקודות נוספות'!E:E) -> 0 | J60: =SUM(E60:I60) -> 0 | K60: =M60+SUMIF('פקודות נוספות'!C:C,'מאזן בוחן'!C60,'פקודות נוספות'!F:F) -> 0 | M60: =IFERROR(VLOOKUP(C60,'פקודות נוספות'!$D$273:$G$797,4,0),0) -> 0 | N60: =IF(K60=0,"-",J60/K60) -> -
B61: 130.לקוחות ILS | C61: 200022 | D61: 2BSecure Ltd | E61: =IFERROR(VLOOKUP(C61,'פקודות נוספות'!$D$274:$F$797,3,0),0) -> 591176.61 | F61: =SUMIF('פקודות נוספות'!C:C,C:C,'פקודות נוספות'!E:E) -> 0 | J61: =SUM(E61:I61) -> 591176.61 | K61: =M61+SUMIF('פקודות נוספות'!C:C,'מאזן בוחן'!C61,'פקודות נוספות'!F:F) -> 190088.94 | M61: =IFERROR(VLOOKUP(C61,'פקודות נוספות'!$D$273:$G$797,4,0),0) -> 190088.94 | N61: =IF(K61=0,"-",J61/K61) -> 3.11
B62: 131.לקוחות $ | C62: 212681 | D62: IISI - International Integrated Systems Inc | E62: =IFERROR(VLOOKUP(C62,'פקודות נוספות'!$D$274:$F$797,3,0),0) -> 663666.26 | F62: =SUMIF('פקודות נוספות'!C:C,C:C,'פקודות נוספות'!E:E) -> 0 | J62: =SUM(E62:I62) -> 663666.26 | K62: =M62+SUMIF('פקודות נוספות'!C:C,'מאזן בוחן'!C62,'פקודות נוספות'!F:F) -> 213397.51 | M62: =IFERROR(VLOOKUP(C62,'פקודות נוספות'!$D$273:$G$797,4,0),0) -> 213397.51 | N62: =IF(K62=0,"-",J62/K62) -> 3.11
B63: 131.לקוחות $ | C63: 202272 | D63: Compugraf Com?rcio de Tecnol?gia | E63: =IFERROR(VLOOKUP(C63,'פקודות נוספות'!$D$274:$F$797,3,0),0) -> 231213.29 | F63: =SUMIF('פקודות נוספות'!C:C,C:C,'פקודות נוספות'!E:E) -> 0 | J63: =SUM(E63:I63) -> 231213.29 | K63: =M63+SUMIF('פקודות נוספות'!C:C,'מאזן בוחן'!C63,'פקודות נוספות'!F:F) -> 74345.11 | M63: =IFERROR(VLOOKUP(C63,'פקודות נוספות'!$D$273:$G$797,4,0),0) -> 74345.11 | N63: =IF(K63=0,"-",J63/K63) -> 3.11
B64: 131.לקוחות $ | C64: 204961 | D64: iValue InfoSolutions Pvt. Ltd | E64: =VLOOKUP(C64,'פקודות נוספות'!$D$274:$F$797,3,0) -> 352948.68 | F64: =SUMIF('פקודות נוספות'!C:C,C:C,'פקודות נוספות'!E:E) -> 0 | J64: =SUM(E64:I64) -> 352948.68 | K64: =M64+SUMIF('פקודות נוספות'!C:C,'מאזן בוחן'!C64,'פקודות נוספות'!F:F) -> 113488.32 | M64: =VLOOKUP(C64,'פקודות נוספות'!$D$273:$G$797,4,0) -> 113488.32 | N64: =IF(K64=0,"-",J64/K64) -> 3.11 | O64: לקוח הודי - לוקח להם זמן להעביר ניכוי מס במקור 10%.
B65: 131.לקוחות $ | C65: 205455 | D65: Licencias Online Mexico (LOL) | E65: =VLOOKUP(C65,'פקודות נוספות'!$D$274:$F$797,3,0) -> 211069.32 | F65: =SUMIF('פקודות נוספות'!C:C,C:C,'פקודות נוספות'!E:E) -> 0 | J65: =SUM(E65:I65) -> 211069.32 | K65: =M65+SUMIF('פקודות נוספות'!C:C,'מאזן בוחן'!C65,'פקודות נוספות'!F:F) -> 67867.95 | M65: =VLOOKUP(C65,'פקודות נוספות'!$D$273:$G$797,4,0) -> 67867.95 | N65: =IF(K65=0,"-",J65/K65) -> 3.1099999
B66: 131.לקוחות $ | C66: 222011 | D66: INFOCZ | E66: =IFERROR(VLOOKUP(C66,'פקודות נוספות'!$D$274:$F$797,3,0),0) -> 217620.94 | F66: =SUMIF('פקודות נוספות'!C:C,C:C,'פקודות נוספות'!E:E) -> 0 | J66: =SUM(E66:I66) -> 217620.94 | K66: =M66+SUMIF('פקודות נוספות'!C:C,'מאזן בוחן'!C66,'פקודות נוספות'!F:F) -> 69974.58 | M66: =IFERROR(VLOOKUP(C66,'פקודות נוספות'!$D$273:$G$797,4,0),0) -> 69974.58 | N66: =IF(K66=0,"-",J66/K66) -> 3.1099999 | O66: תשלום חלקי, היתרה בבירור.
B67: 131.לקוחות $ | C67: 203122 | D67: EGUARDIAN LANKA PVT LTD | E67: =IFERROR(VLOOKUP(C67,'פקודות נוספות'!$D$274:$F$797,3,0),0) -> 3200.81 | F67: =SUMIF('פקודות נוספות'!C:C,C:C,'פקודות נוספות'!E:E) -> 0 | J67: =SUM(E67:I67) -> 3200.81 | K67: =M67+SUMIF('פקודות נוספות'!C:C,'מאזן בוחן'!C67,'פקודות נוספות'!F:F) -> 1029.2 | M67: =IFERROR(VLOOKUP(C67,'פקודות נוספות'!$D$273:$G$797,4,0),0) -> 1029.2 | N67: =IF(K67=0,"-",J67/K67) -> 3.1099981 | O67: לקוח הודי - לוקח להם זמן להעביר ניכוי מס במקור 10%.
B68: 131.לקוחות $ | C68: 209223 | D68: Exclusive Networks Sales India P | E68: =IFERROR(VLOOKUP(C68,'פקודות נוספות'!$D$274:$F$797,3,0),0) -> 2554788.4 | F68: =SUMIF('פקודות נוספות'!C:C,C:C,'פקודות נוספות'!E:E) -> 0 | J68: =SUM(E68:I68) -> 2554788.4 | K68: =M68+SUMIF('פקודות נוספות'!C:C,'מאזן בוחן'!C68,'פקודות נוספות'!F:F) -> 821475.38 | M68: =IFERROR(VLOOKUP(C68,'פקודות נוספות'!$D$273:$G$797,4,0),0) -> 821475.38 | N68: =IF(K68=0,"-",J68/K68) -> 3.11 | O68: לקוח הודי - לוקח להם זמן להעביר ניכוי מס במקור 10%
B69: 131.לקוחות $ | C69: 207238 | D69: PTLS SERVIÇOS DE TECNOLOGIA E ASSES | E69: =IFERROR(VLOOKUP(C69,'פקודות נוספות'!$D$274:$F$797,3,0),0) -> 4731602.2 | F69: =SUMIF('פקודות נוספות'!C:C,C:C,'פקודות נוספות'!E:E) -> 0 | J69: =SUM(E69:I69) -> 4731602.2 | K69: =M69+SUMIF('פקודות נוספות'!C:C,'מאזן בוחן'!C69,'פקודות נוספות'!F:F) -> 1521415.5 | M69: =IFERROR(VLOOKUP(C69,'פקודות נוספות'!$D$273:$G$797,4,0),0) -> 1521415.5 | N69: =IF(K69=0,"-",J69/K69) -> 3.11 | O69: ניכוי במקור.
B71: 135.לקוחות אחרים | C71: 1150001 | D71: הכנסות לקבל | E71: =IFERROR(VLOOKUP(C71,'פקודות נוספות'!$D$274:$F$797,3,0),0) -> 502282.7 | F71: =SUMIF('פקודות נוספות'!C:C,C:C,'פקודות נוספות'!E:E) -> 0 | J71: =SUM(E71:I71) -> 502282.7 | K71: =M71+SUMIF('פקודות נוספות'!C:C,'מאזן בוחן'!C71,'פקודות נוספות'!F:F) -> 161505.69 | L71: =SUM([10]Ltd!$C$5)-K71 -> 0.0012730594 | M71: =IFERROR(VLOOKUP(C71,'פקודות נוספות'!$D$273:$G$797,4,0),0) -> 161505.69 | N71: =IF(K71=0,"-",J71/K71) -> 3.11
B72: 135.לקוחות אחרים | C72: 2500204 | D72: הפרשה לחובות מסופקים | E72: =IFERROR(VLOOKUP(C72,'פקודות נוספות'!$D$274:$F$797,3,0),0) -> 0 | F72: =SUMIF('פקודות נוספות'!C:C,C:C,'פקודות נוספות'!E:E) -> 0 | J72: =SUM(E72:I72) -> 0 | K72: =M72+SUMIF('פקודות נוספות'!C:C,'מאזן בוחן'!C72,'פקודות נוספות'!F:F) -> 0 | M72: =IFERROR(VLOOKUP(C72,'פקודות נוספות'!$D$273:$G$797,4,0),0) -> 0 | N72: =IF(K72=0,"-",J72/K72) -> -
B73: 135.לקוחות אחרים | C73: 2090001 | D73: הכנסות מראש - מיון לקוחות בזכות | E73: =IFERROR(VLOOKUP(C73,'פקודות נוספות'!$D$274:$F$797,3,0),0) -> 0 | F73: =SUMIF('פקודות נוספות'!C:C,C:C,'פקודות נוספות'!E:E) -> 0 | J73: =SUM(E73:I73) -> 0 | K73: =M73+SUMIF('פקודות נוספות'!C:C,'מאזן בוחן'!C73,'פקודות נוספות'!F:F) -> 0 | M73: =IFERROR(VLOOKUP(C73,'פקודות נוספות'!$D$273:$G$797,4,0),0) -> 0 | N73: =IF(K73=0,"-",J73/K73) -> -
D75: סה"כ לקוחות | E75: =SUM(E35:E74) -> 13916870 | F75: =SUM(F35:F74) -> 0 | G75: =SUM(G35:G74) -> 0 | H75: =SUM(H35:H74) -> 0 | I75: =SUM(I35:I74) -> 0 | J75: =SUM(J35:J74) -> 13916870 | K75: =SUM(K35:K74) -> 4474877.7 | M75: =SUM(M35:M74) -> 4474877.7
D77: Accounts receivable and debit balances
D78: Government Institutions
B79: 250.מוסדות זכאים | C79: 2500001 | D79: מע"מ תשומות | E79: =IFERROR(VLOOKUP(C79,'פקודות נוספות'!$D$274:$H$808,3,0),0) -> 57528.99 | F79: =SUMIF('פקודות נוספות'!C:C,C:C,'פקודות נוספות'!E:E) -> 0 | J79: =SUM(E79:I79) -> 57528.99 | K79: =M79+SUMIF('פקודות נוספות'!C:C,'מאזן בוחן'!C79,'פקודות נוספות'!F:F) -> 18498.07 | M79: =VLOOKUP(C79,'פקודות נוספות'!$D$273:$G$797,4,0) -> 18498.07 | N79: =IF(K79=0,"-",J79/K79) -> 3.1099996 | O79: שוטף
B80: 250.מוסדות זכאים | C80: 2500002 | D80: מע"מ עסקאות | E80: =IFERROR(VLOOKUP(C80,'פקודות נוספות'!$D$274:$H$808,3,0),0) -> 0 | F80: =SUMIF('פקודות נוספות'!C:C,C:C,'פקודות נוספות'!E:E) -> 0 | J80: =SUM(E80:I80) -> 0 | K80: =M80+SUMIF('פקודות נוספות'!C:C,'מאזן בוחן'!C80,'פקודות נוספות'!F:F) -> 0 | M80: =IFERROR(VLOOKUP(C80,'פקודות נוספות'!$D$273:$G$797,4,0),0) -> 0 | N80: =IF(K80=0,"-",J80/K80) -> - | O80: שוטף
B81: 250.מוסדות זכאים | C81: חדש250 | D81: מע"מ ספקים בחובה לצורך מאזן בלבד | E81: =IFERROR(VLOOKUP(C81,'פקודות נוספות'!$D$274:$H$808,3,0),0) -> 0 | F81: =SUMIF('פקודות נוספות'!C:C,C:C,'פקודות נוספות'!E:E) -> 0 | J81: =SUM(E81:I81) -> 0 | K81: =M81+SUMIF('פקודות נוספות'!C:C,'מאזן בוחן'!C81,'פקודות נוספות'!F:F) -> 0 | M81: =IFERROR(VLOOKUP(C81,'פקודות נוספות'!$D$273:$G$797,4,0),0) -> 0 | N81: =IF(K81=0,"-",J81/K81) -> -
B82: 250.מוסדות זכאים | C82: 2500005 | D82: מע"מ מרשימון יבוא | E82: =IFERROR(VLOOKUP(C82,'פקודות נוספות'!$D$274:$H$808,3,0),0) -> 0 | F82: =SUMIF('פקודות נוספות'!C:C,C:C,'פקודות נוספות'!E:E) -> 0 | J82: =SUM(E82:I82) -> 0 | K82: =M82+SUMIF('פקודות נוספות'!C:C,'מאזן בוחן'!C82,'פקודות נוספות'!F:F) -> 0 | M82: =IFERROR(VLOOKUP(C82,'פקודות נוספות'!$D$273:$G$797,4,0),0) -> 0 | N82: =IF(K82=0,"-",J82/K82) -> -
B83: 250.מוסדות זכאים | C83: 2500003 | D83: מע"מ רכוש קבוע | E83: =IFERROR(VLOOKUP(C83,'פקודות נוספות'!$D$274:$H$808,3,0),0) -> -1186.66 | F83: =SUMIF('פקודות נוספות'!C:C,C:C,'פקודות נוספות'!E:E) -> 0 | J83: =SUM(E83:I83) -> -1186.66 | K83: =M83+SUMIF('פקודות נוספות'!C:C,'מאזן בוחן'!C83,'פקודות נוספות'!F:F) -> -381.56 | M83: =IFERROR(VLOOKUP(C83,'פקודות נוספות'!$D$273:$G$797,4,0),0) -> -381.56 | N83: =IF(K83=0,"-",J83/K83) -> 3.110022
B84: 250.מוסדות זכאים | C84: 2500004 | D84: מע"מ חו"ז | E84: =VLOOKUP(C84,'פקודות נוספות'!$D$274:$H$808,3,0) -> 797939.14 | F84: =SUMIF('פקודות נוספות'!C:C,C:C,'פקודות נוספות'!E:E) -> 0 | J84: =SUM(E84:I84) -> 797939.14 | K84: =M84+SUMIF('פקודות נוספות'!C:C,'מאזן בוחן'!C84,'פקודות נוספות'!F:F) -> 256572.07 | M84: =VLOOKUP(C84,'פקודות נוספות'!$D$273:$G$797,4,0) -> 256572.07 | N84: =IF(K84=0,"-",J84/K84) -> 3.11 | O84: שוטף
B85: 250.מוסדות זכאים | C85: 2500007 | D85: ניכוי במקור מכלל 2015 | E85: =VLOOKUP(C85,'פקודות נוספות'!$D$274:$F$797,3,0) -> 19981.24 | F85: =SUMIF('פקודות נוספות'!C:C,C:C,'פקודות נוספות'!E:E) -> 0 | J85: =SUM(E85:I85) -> 19981.24 | K85: =M85+SUMIF('פקודות נוספות'!C:C,'מאזן בוחן'!C85,'פקודות נוספות'!F:F) -> 6424.84 | M85: =VLOOKUP(C85,'פקודות נוספות'!$D$273:$G$797,4,0) -> 6424.84 | N85: =IF(K85=0,"-",J85/K85) -> 3.1099981 | O85: מקדמות בגין עודפות 2016:
B86: 250.מוסדות זכאים | C86: 2500027 | D86: מקדמות מס הכנסה 2015 | E86: =VLOOKUP(C86,'פקודות נוספות'!$D$274:$F$797,3,0) -> 269741 | F86: =SUMIF('פקודות נוספות'!C:C,C:C,'פקודות נוספות'!E:E) -> 0 | J86: =SUM(E86:I86) -> 269741 | K86: =M86+SUMIF('פקודות נוספות'!C:C,'מאזן בוחן'!C86,'פקודות נוספות'!F:F) -> 86733.44 | M86: =VLOOKUP(C86,'פקודות נוספות'!$D$273:$G$797,4,0) -> 86733.44 | N86: =IF(K86=0,"-",J86/K86) -> 3.11 | O86: =SUM(J85:J91) -> 0.27
B87: 250.מוסדות זכאים | C87: 2500023 | D87: ניכוי מס מלקוחות 2015 | E87: =VLOOKUP(C87,'פקודות נוספות'!$D$274:$F$797,3,0) -> 574795.76 | F87: =SUMIF('פקודות נוספות'!C:C,C:C,'פקודות נוספות'!E:E) -> 0 | J87: =SUM(E87:I87) -> 574795.76 | K87: =M87+SUMIF('פקודות נוספות'!C:C,'מאזן בוחן'!C87,'פקודות נוספות'!F:F) -> 184821.79 | M87: =VLOOKUP(C87,'פקודות נוספות'!$D$273:$G$797,4,0) -> 184821.79 | N87: =IF(K87=0,"-",J87/K87) -> 3.11
B88: 250.מוסדות זכאים | C88: 2500117 | D88: החזר מס הכנסה בגין שנת 2015 | E88: =VLOOKUP(C88,'פקודות נוספות'!$D$274:$F$797,3,0) -> -192540 | F88: =SUMIF('פקודות נוספות'!C:C,C:C,'פקודות נוספות'!E:E) -> 0 | J88: =SUM(E88:I88) -> -192540 | K88: =M88+SUMIF('פקודות נוספות'!C:C,'מאזן בוחן'!C88,'פקודות נוספות'!F:F) -> -61909.97 | M88: =VLOOKUP(C88,'פקודות נוספות'!$D$273:$G$797,4,0) -> -61909.97 | N88: =IF(K88=0,"-",J88/K88) -> 3.1099999 | O88: =[11]עודפות!$J$5 -> 37543.211
B89: 250.מוסדות זכאים | C89: 2502015 | D89: סגירת מיסים 2015 | E89: =VLOOKUP(C89,'פקודות נוספות'!$D$274:$F$797,3,0) -> -550036.73 | F89: =SUMIF('פקודות נוספות'!C:C,C:C,'פקודות נוספות'!E:E) -> 0 | J89: =SUM(E89:I89) -> -550036.73 | K89: =M89+SUMIF('פקודות נוספות'!C:C,'מאזן בוחן'!C89,'פקודות נוספות'!F:F) -> -176860.68 | M89: =VLOOKUP(C89,'פקודות נוספות'!$D$273:$G$797,4,0) -> -176860.68 | N89: =IF(K89=0,"-",J89/K89) -> 3.1100001
B90: 250.מוסדות זכאים | C90: 2500037-1 | D90: הפרשה למס 2015 | E90: =VLOOKUP(C90,'פקודות נוספות'!$D$274:$F$797,3,0) -> -189441 | F90: =SUMIF('פקודות נוספות'!C:C,C:C,'פקודות נוספות'!E:E) -> 0 | J90: =SUM(E90:I90) -> -189441 | K90: =M90+SUMIF('פקודות נוספות'!C:C,'מאזן בוחן'!C90,'פקודות נוספות'!F:F) -> -60913.5 | M90: =VLOOKUP(C90,'פקודות נוספות'!$D$273:$G$797,4,0) -> -60913.5 | N90: =IF(K90=0,"-",J90/K90) -> 3.1100002
B91: 250.מוסדות זכאים | C91: 2500028 | D91: עודפות 2015 | E91: =VLOOKUP(C91,'פקודות נוספות'!$D$274:$F$797,3,0) -> 67500 | F91: =SUMIF('פקודות נוספות'!C:C,C:C,'פקודות נוספות'!E:E) -> 0 | J91: =SUM(E91:I91) -> 67500 | K91: =M91+SUMIF('פקודות נוספות'!C:C,'מאזן בוחן'!C91,'פקודות נוספות'!F:F) -> 21704.18 | M91: =VLOOKUP(C91,'פקודות נוספות'!$D$273:$G$797,4,0) -> 21704.18 | N91: =IF(K91=0,"-",J91/K91) -> 3.11
B92: 250.מוסדות זכאים | C92: 2500024 | D92: ניכוי מס מלקוחות 2016 | E92: =IFERROR(VLOOKUP(C92,'פקודות נוספות'!$D$274:$F$797,3,0),0) -> 803750.86 | F92: =SUMIF('פקודות נוספות'!C:C,C:C,'פקודות נוספות'!E:E) -> 0 | J92: =SUM(E92:I92) -> 803750.86 | K92: =M92+SUMIF('פקודות נוספות'!C:C,'מאזן בוחן'!C92,'פקודות נוספות'!F:F) -> 258440.79 | M92: =IFERROR(VLOOKUP(C92,'פקודות נוספות'!$D$273:$G$797,4,0),0) -> 258440.79 | N92: =IF(K92=0,"-",J92/K92) -> 3.11 | O92: מקדמות בגין עודפות 2016:
B93: 250.מוסדות זכאים | C93: 2500029 | D93: מקדמות מס הכנסה 2016 | E93: =VLOOKUP(C93,'פקודות נוספות'!$D$274:$F$797,3,0) -> 106032 | F93: =SUMIF('פקודות נוספות'!C:C,C:C,'פקודות נוספות'!E:E) -> 0 | J93: =SUM(E93:I93) -> 106032 | K93: =M93+SUMIF('פקודות נוספות'!C:C,'מאזן בוחן'!C93,'פקודות נוספות'!F:F) -> 34093.89 | M93: =VLOOKUP(C93,'פקודות נוספות'!$D$273:$G$797,4,0) -> 34093.89 | N93: 3.4670004 | O93: =SUM(J92:J97) -> -0.14
B94: 250.מוסדות זכאים | C94: 2500116 | D94: החזר מס הכנסה בגין שנת 2016 | E94: =VLOOKUP(C94,'פקודות נוספות'!$D$274:$F$797,3,0) -> -106032 | F94: =SUMIF('פקודות נוספות'!C:C,C:C,'פקודות נוספות'!E:E) -> 0 | J94: =SUM(E94:I94) -> -106032 | K94: =M94+SUMIF('פקודות נוספות'!C:C,'מאזן בוחן'!C94,'פקודות נוספות'!F:F) -> -34093.89 | M94: =VLOOKUP(C94,'פקודות נוספות'!$D$273:$G$797,4,0) -> -34093.89 | N94: 4.4670004
B95: 250.מוסדות זכאים | C95: 2502016 | D95: סגירת מיסים 2016 | E95: =VLOOKUP(C95,'פקודות נוספות'!$D$274:$F$797,3,0) -> -774608 | F95: =SUMIF('פקודות נוספות'!C:C,C:C,'פקודות נוספות'!E:E) -> 0 | J95: =SUM(E95:I95) -> -774608 | K95: =M95+SUMIF('פקודות נוספות'!C:C,'מאזן בוחן'!C95,'פקודות נוספות'!F:F) -> -249070.1 | M95: =VLOOKUP(C95,'פקודות נוספות'!$D$273:$G$797,4,0) -> -249070.1 | N95: 5.4670004 | O95: =[11]עודפות!$J$7 -> 78751
B96: 250.מוסדות זכאים | C96: 2500030 | D96: עודפות 2016 | E96: =VLOOKUP(C96,'פקודות נוספות'!$D$274:$F$797,3,0) -> 78751 | F96: 0 | J96: =SUM(E96:I96) -> 78751 | K96: =M96+SUMIF('פקודות נוספות'!C:C,'מאזן בוחן'!C96,'פקודות נוספות'!F:F) -> 25321.86 | M96: =VLOOKUP(C96,'פקודות נוספות'!$D$273:$G$797,4,0) -> 25321.86 | N96: 3.4670001
B97: 250.מוסדות זכאים | C97: 2500037 | D97: הפרשה למס 2016 | E97: =VLOOKUP(C97,'פקודות נוספות'!$D$274:$F$797,3,0) -> -107894 | F97: 0 | J97: =SUM(E97:I97) -> -107894 | K97: =M97+SUMIF('פקודות נוספות'!C:C,'מאזן בוחן'!C97,'פקודות נוספות'!F:F) -> -34692.6 | M97: =VLOOKUP(C97,'פקודות נוספות'!$D$273:$G$797,4,0) -> -34692.6 | N97: 3.4669999
B98: 250.מוסדות זכאים | C98: 2500025 | D98: ניכוי מס מלקוחות 2017 | E98: =IFERROR(VLOOKUP(C98,'פקודות נוספות'!$D$274:$F$797,3,0),0) -> 1250940.8 | F98: =SUMIF('פקודות נוספות'!C:C,C:C,'פקודות נוספות'!E:E) -> 0 | J98: =SUM(E98:I98) -> 1250940.8 | K98: =M98+SUMIF('פקודות נוספות'!C:C,'מאזן בוחן'!C98,'פקודות נוספות'!F:F) -> 402231.77 | M98: =IFERROR(VLOOKUP(C98,'פקודות נוספות'!$D$273:$G$797,4,0),0) -> 402231.77 | N98: =IF(K98=0,"-",J98/K98) -> 3.11 | O98: מקדמות בגין עודפות 2017:
B99: 250.מוסדות זכאים | C99: 2500016 | D99: ניכוי מס מלקוחות ללא אישורים | E99: =VLOOKUP(C99,'פקודות נוספות'!$D$274:$F$797,3,0) -> -0.35 | F99: =SUMIF('פקודות נוספות'!C:C,C:C,'פקודות נוספות'!E:E) -> 0 | J99: =SUM(E99:I99) -> -0.35 | K99: =M99+SUMIF('פקודות נוספות'!C:C,'מאזן בוחן'!C99,'פקודות נוספות'!F:F) -> 0.31 | M99: =VLOOKUP(C99,'פקודות נוספות'!$D$273:$G$797,4,0) -> 0.31 | N99: =IF(K99=0,"-",J99/K99) -> -1.1290323 | O99: =SUM(J98:J103) -> 0.46
B100: 250.מוסדות זכאים | C100: 2500118 | D100: החזר מקדמות בגין שנת 2017 | E100: =VLOOKUP(C100,'פקודות נוספות'!$D$274:$F$797,3,0) -> -598426 | F100: =SUMIF('פקודות נוספות'!C:C,C:C,'פקודות נוספות'!E:E) -> 0 | J100: =SUM(E100:I100) -> -598426 | K100: =M100+SUMIF('פקודות נוספות'!C:C,'מאזן בוחן'!C100,'פקודות נוספות'!F:F) -> -192419.94 | M100: =VLOOKUP(C100,'פקודות נוספות'!$D$273:$G$797,4,0) -> -192419.94 | N100: =IF(K100=0,"-",J100/K100) -> 3.1099999
B101: 250.מוסדות זכאים | C101: 2502017 | D101: סגירת מיסים 2017 | E101: =VLOOKUP(C101,'פקודות נוספות'!$D$274:$F$797,3,0) -> -1364340 | F101: =SUMIF('פקודות נוספות'!C:C,C:C,'פקודות נוספות'!E:E) -> 0 | J101: =SUM(E101:I101) -> -1364340 | K101: =M101+SUMIF('פקודות נוספות'!C:C,'מאזן בוחן'!C101,'פקודות נוספות'!F:F) -> -438694.53 | M101: =VLOOKUP(C101,'פקודות נוספות'!$D$273:$G$797,4,0) -> -438694.53 | N101: =IF(K101=0,"-",J101/K101) -> 3.11 | O101: =[11]עודפות!$J$9 -> 113400
B102: 250.מוסדות זכאים | C102: 2500031 | D102: מקדמות מס הכנסה 2017 | E102: =VLOOKUP(C102,'פקודות נוספות'!$D$274:$F$797,3,0) -> 598426 | F102: =SUMIF('פקודות נוספות'!C:C,C:C,'פקודות נוספות'!E:E) -> 0 | J102: =SUM(E102:I102) -> 598426 | K102: =M102+SUMIF('פקודות נוספות'!C:C,'מאזן בוחן'!C102,'פקודות נוספות'!F:F) -> 192419.94 | M102: =VLOOKUP(C102,'פקודות נוספות'!$D$273:$G$797,4,0) -> 192419.94 | N102: =IF(K102=0,"-",J102/K102) -> 3.1099999
B103: 250.מוסדות זכאים | C103: 2500032 | D103: עודפות 2017 | E103: =VLOOKUP(C103,'פקודות נוספות'!$D$274:$F$797,3,0) -> 113400 | F103: =SUMIF('פקודות נוספות'!C:C,C:C,'פקודות נוספות'!E:E) -> 0 | J103: =SUM(E103:I103) -> 113400 | K103: =M103+SUMIF('פקודות נוספות'!C:C,'מאזן בוחן'!C103,'פקודות נוספות'!F:F) -> 36463.02 | M103: =VLOOKUP(C103,'פקודות נוספות'!$D$273:$G$797,4,0) -> 36463.02 | N103: =IF(K103=0,"-",J103/K103) -> 3.1100002
B104: 250.מוסדות זכאים | C104: 2500038 | D104: מקדמות מס הכנסה 2018 | E104: =IFERROR(VLOOKUP(C104,'פקודות נוספות'!$D$274:$F$797,3,0),0) -> 243521 | F104: =SUMIF('פקודות נוספות'!C:C,C:C,'פקודות נוספות'!E:E) -> 0 | J104: =SUM(E104:I104) -> 243521 | K104: =M104+SUMIF('פקודות נוספות'!C:C,'מאזן בוחן'!C104,'פקודות נוספות'!F:F) -> 78302.57 | M104: =IFERROR(VLOOKUP(C104,'פקודות נוספות'!$D$273:$G$797,4,0),0) -> 78302.57 | N104: =IF(K104=0,"-",J104/K104) -> 3.1100001 | O104: נמ"ב + מקדמות עודפות 2018:
B105: 250.מוסדות זכאים | C105: 2500119 | D105: החזר מקדמות בגין שנת 2018 | E105: =VLOOKUP(C105,'פקודות נוספות'!$D$274:$F$797,3,0) -> -243521 | F105: =SUMIF('פקודות נוספות'!C:C,C:C,'פקודות נוספות'!E:E) -> 0 | J105: =SUM(E105:I105) -> -243521 | K105: =M105+SUMIF('פקודות נוספות'!C:C,'מאזן בוחן'!C105,'פקודות נוספות'!F:F) -> -78302.57 | M105: =VLOOKUP(C105,'פקודות נוספות'!$D$273:$G$797,4,0) -> -78302.57 | N105: =IF(K105=0,"-",J105/K105) -> 3.1100001 | O105: =SUM(J104:J108)-O106 -> -180000.2
B106: 250.מוסדות זכאים | C106: 2502018 | D106: סגירת מיסים 2018 | E106: =VLOOKUP(C106,'פקודות נוספות'!$D$274:$F$797,3,0) -> -1268905.2 | F106: =SUMIF('פקודות נוספות'!C:C,C:C,'פקודות נוספות'!E:E) -> 0 | J106: =SUM(E106:I106) -> -1268905.2 | K106: =M106+SUMIF('פקודות נוספות'!C:C,'מאזן בוחן'!C106,'פקודות נוספות'!F:F) -> -408008.11 | M106: =VLOOKUP(C106,'פקודות נוספות'!$D$273:$G$797,4,0) -> -408008.11 | N106: =IF(K106=0,"-",J106/K106) -> 3.11 | O106: =J108 -> 180000
B107: 250.מוסדות זכאים | C107: 2500040 | D107: ניכוי מס מלקוחות 2018 | E107: =VLOOKUP(C107,'פקודות נוספות'!$D$274:$F$797,3,0) -> 1088905 | F107: =SUMIF('פקודות נוספות'!C:C,C:C,'פקודות נוספות'!E:E) -> 0 | J107: =SUM(E107:I107) -> 1088905 | K107: =M107+SUMIF('פקודות נוספות'!C:C,'מאזן בוחן'!C107,'פקודות נוספות'!F:F) -> 350130.23 | M107: =VLOOKUP(C107,'פקודות נוספות'!$D$273:$G$797,4,0) -> 350130.23 | N107: =IF(K107=0,"-",J107/K107) -> 3.11 | O107: =SUM(O105:O106) -> -0.2
B108: 250.מוסדות זכאים | C108: 2500033 | D108: עודפות 2018 | E108: =VLOOKUP(C108,'פקודות נוספות'!$D$274:$F$797,3,0) -> 180000 | F108: =SUMIF('פקודות נוספות'!C:C,C:C,'פקודות נוספות'!E:E) -> 0 | J108: =SUM(E108:I108) -> 180000 | K108: =M108+SUMIF('פקודות נוספות'!C:C,'מאזן בוחן'!C108,'פקודות נוספות'!F:F) -> 57877.81 | M108: =VLOOKUP(C108,'פקודות נוספות'!$D$273:$G$797,4,0) -> 57877.81 | N108: =IF(K108=0,"-",J108/K108) -> 3.1100002 | O108: =+[11]עודפות!$J$11 -> 180000
B109: 250.מוסדות זכאים | C109: 2500041 | D109: ניכוי מס מלקוחות 2019 | E109: =IFERROR(VLOOKUP(C109,'פקודות נוספות'!$D$274:$F$797,3,0),0) -> 985319.1 | F109: =SUMIF('פקודות נוספות'!C:C,C:C,'פקודות נוספות'!E:E) -> 0 | J109: =SUM(E109:I109) -> 985319.1 | K109: =M109+SUMIF('פקודות נוספות'!C:C,'מאזן בוחן'!C109,'פקודות נוספות'!F:F) -> 316822.86 | M109: =IFERROR(VLOOKUP(C109,'פקודות נוספות'!$D$273:$G$797,4,0),0) -> 316822.86 | N109: =IF(K109=0,"-",J109/K109) -> 3.11 | O109: נמ"ב + מקדמות בגין עודפות 2019
B110: 250.מוסדות זכאים | C110: 2500042 | D110: מקדמות מס הכנסה 2019 | E110: =VLOOKUP(C110,'פקודות נוספות'!$D$274:$F$797,3,0) -> 2980 | F110: =SUMIF('פקודות נוספות'!C:C,C:C,'פקודות נוספות'!E:E) -> 0 | J110: =SUM(E110:I110) -> 2980 | K110: =M110+SUMIF('פקודות נוספות'!C:C,'מאזן בוחן'!C110,'פקודות נוספות'!F:F) -> 862.27 | M110: =VLOOKUP(C110,'פקודות נוספות'!$D$273:$G$797,4,0) -> 862.27 | N110: =IF(K110=0,"-",J110/K110) -> 3.4559941 | O110: =[11]עודפות!$J$13 -> 84416
B111: 250.מוסדות זכאים | C111: 2500043 | D111: עודפות 2019 | E111: =VLOOKUP(C111,'פקודות נוספות'!$D$274:$F$797,3,0) -> 84416 | F111: =SUMIF('פקודות נוספות'!C:C,C:C,'פקודות נוספות'!E:E) -> 0 | J111: =SUM(E111:I111) -> 84416 | K111: =M111+SUMIF('פקודות נוספות'!C:C,'מאזן בוחן'!C111,'פקודות נוספות'!F:F) -> 27143.41 | M111: =VLOOKUP(C111,'פקודות נוספות'!$D$273:$G$797,4,0) -> 27143.41 | N111: =IF(K111=0,"-",J111/K111) -> 3.1099998 | O111: =[11]נמב!$R$86 -> 992981.08
B112: 250.מוסדות זכאים | C112: 2502019 | D112: סגירת מיסים 2019 | E112: =IFERROR(VLOOKUP(C112,'פקודות נוספות'!$D$274:$F$797,3,0),0) -> -1072714.8 | F112: =SUMIF('פקודות נוספות'!C:C,C:C,'פקודות נוספות'!E:E) -> 0 | J112: =SUM(E112:I112) -> -1072714.8 | K112: =M112+SUMIF('פקודות נוספות'!C:C,'מאזן בוחן'!C112,'פקודות נוספות'!F:F) -> -344924.39 | M112: =VLOOKUP(C112,'פקודות נוספות'!$D$273:$G$797,4,0) -> -344924.39 | N112: =IF(K112=0,"-",J112/K112) -> 3.11 | O112: =SUM(O110:O111) -> 1077397.1
B113: 250.מוסדות זכאים | C113: 2500044 | D113: עודפות 2020 | E113: =IFERROR(VLOOKUP(C113,'פקודות נוספות'!$D$274:$F$797,3,0),0) -> 78000 | F113: =SUMIF('פקודות נוספות'!C:C,C:C,'פקודות נוספות'!E:E) -> 0 | J113: =SUM(E113:I113) -> 78000 | K113: =M113+SUMIF('פקודות נוספות'!C:C,'מאזן בוחן'!C113,'פקודות נוספות'!F:F) -> 25080.39 | M113: =IFERROR(VLOOKUP(C113,'פקודות נוספות'!$D$273:$G$797,4,0),0) -> 25080.39 | N113: =IF(K113=0,"-",J113/K113) -> 3.1099995 | O113: =SUM(J109:J112) -> 0.26
B114: 250.מוסדות זכאים | C114: 2500047 | D114: מקדמות מס הכנסה 2020 | E114: =IFERROR(VLOOKUP(C114,'פקודות נוספות'!$D$274:$F$797,3,0),0) -> 196207.05 | F114: =SUMIF('פקודות נוספות'!C:C,C:C,'פקודות נוספות'!E:E) -> 0 | J114: =SUM(E114:I114) -> 196207.05 | K114: =M114+SUMIF('פקודות נוספות'!C:C,'מאזן בוחן'!C114,'פקודות נוספות'!F:F) -> 60427.18 | M114: =IFERROR(VLOOKUP(C114,'פקודות נוספות'!$D$273:$G$797,4,0),0) -> 60427.18 | N114: =IF(K114=0,"-",J114/K114) -> 3.2469999 | O114: המקדמות מורכבות מעיקול של מע"מ פברואר 2021 - לאחר הגשת דוח מס לשנת 2020 יבוצע החזר.
B115: 250.מוסדות זכאים | C115: 2500045 | D115: ניכוי מס מלקוחות 2020 | E115: =IFERROR(VLOOKUP(C115,'פקודות נוספות'!$D$274:$F$797,3,0),0) -> 1173839.5 | F115: =SUMIF('פקודות נוספות'!C:C,C:C,'פקודות נוספות'!E:E) -> 0 | J115: =SUM(E115:I115) -> 1173839.5 | K115: =M115+SUMIF('פקודות נוספות'!C:C,'מאזן בוחן'!C115,'פקודות נוספות'!F:F) -> 377440.36 | M115: =IFERROR(VLOOKUP(C115,'פקודות נוספות'!$D$273:$G$797,4,0),0) -> 377440.36 | N115: =IF(K115=0,"-",J115/K115) -> 3.11
...

Sheet פקודות נוספות
B1: Algosec System Ltd
B2: ='נתונים לשינוי'!C1 -> 44561
B3: פקודות נוספות לדו"חות הכספיים
B4: מספר | C4: מיון | D4: כרטיס | E4: סכום בש"ח | F4: סכום בדולר
E5: =SUM(E6:E238) -> 0 | F5: =SUM(F6:F238) -> 0
B6: 1 | C6: מיון לקוחות בזכות | E6: ILS | F6: USD | G6: ברבעון - להעביר ולהפוך
C7: 2090001 | D7: =VLOOKUP(C7,'מאזן בוחן'!C:D,2,0) -> הכנסות מראש - מיון לקוחות בזכות
C8: 53602 | D8: =VLOOKUP(C8,'מאזן בוחן'!C:D,2,0) -> הכנסות מראש - מיון לקוחות בזכות | E8: =-E7 -> 0 | F8: =-F7 -> 0
B9: 2 | C9: היפוך הכנסות לקבל בגין תשלום 2 Wipro | E9: ILS | F9: USD | G9: להעביר
C10: 1150001 | D10: =VLOOKUP(C10,'מאזן בוחן'!C:D,2,0) -> הכנסות לקבל | E10: =F10*'מאזן בוחן'!$N$2 -> 0 | F10: =-F12 -> 0
C11: 9010002 | D11: =VLOOKUP(C11,'מאזן בוחן'!C:D,2,0) -> הפרשי שער | E11: =-E12-E10 -> 0 | F11: 0
C12: 53581 | D12: =VLOOKUP(C12,'מאזן בוחן'!C:D,2,0) -> הכנסות מראש מטח Subsription פטורות חדש
B13: =B9+1 -> 3 | C13: היפוך הוצאות לשלם סקירה Q3 + דוח מס 2020 | E13: ILS | F13: USD | G13: להעביר
C14: 2200001 | D14: =VLOOKUP(C14,'מאזן בוחן'!C:D,2,0) -> הוצאות לשלם | F14: =E14/'מאזן בוחן'!$N$2 -> 0
C15: 9010002 | D15: =VLOOKUP(C15,'מאזן בוחן'!C:D,2,0) -> הפרשי שער | E15: 0 | F15: =-F16-F14 -> 0
C16: 8410068 | D16: =VLOOKUP(C16,'מאזן בוחן'!C:D,2,0) -> ביקורת ויעוץ רו"ח | E16: =-E14 -> 0 | F16: =E16/'נתונים לשינוי'!$D$8 -> 0
B17: =B13+1 -> 4 | C17: עמלות On-Hold Q4.2021 | E17: ILS | F17: USD | G17: מרכז רווח:
C18: 7110003 | D18: =VLOOKUP(C18,'מאזן בוחן'!C:D,2,0) -> שכר מכירות- עמלות למאזן בלבד | E18: =F18*'מאזן בוחן'!$N$2 -> 0 | G18: APAC
C19: 2400001 | D19: =VLOOKUP(C19,'מאזן בוחן'!C:D,2,0) -> הוצאות לשלם עובדים | E19: =-E18 -> 0 | F19: =-F18 -> 0 | G19: להעביר
B20: =B17+1 -> 5 | C20: Income receivable due renewals | E20: ILS | F20: USD | G20: להעביר ולהפוך
C21: 1150001 | D21: =VLOOKUP(C21,'מאזן בוחן'!C:D,2,0) -> הכנסות לקבל | E21: =F21*'מאזן בוחן'!N2 -> 0
C22: 80105-2 | D22: =VLOOKUP(C22,'מאזן בוחן'!C:D,2,0) -> הכנסות פטורות תחזוקה לצורך מאזן בלבד | E22: =-E21 -> 0 | F22: =-F21 -> 0
B23: =B20+1 -> 6 | C23: מיון הוצאות מראש לזמן ארוך | E23: ILS | F23: USD | G23: ברבעון - להעביר ולהפוך
C24: 2600003 | D24: =VLOOKUP(C24,'מאזן בוחן'!C:D,2,0) -> הוצ' מראש זמן ארוך
C25: 1100001 | D25: =VLOOKUP(C25,'מאזן בוחן'!C:D,2,0) -> הוצאות מראש
B26: =B23+1 -> 7 | C26: העמסת הוצאות הנה"כ | E26: ILS | F26: USD | G26: ברבעון - להעביר | H26: להעביר להנה"ח בסוף
C27: 6030001 | D27: =VLOOKUP(C27,'מאזן בוחן'!C:D,2,0) -> העמסת הנכ"כ למחלקת מו"פ | E27: ='העמסת הנה"כ'!I5 -> -0.0010582013 | F27: ='העמסת הנה"כ'!J5 -> 0.000178413
C28: 7030001 | D28: =VLOOKUP(C28,'מאזן בוחן'!C:D,2,0) -> העמסת הוצאות הנה"כ על השיווק | E28: ='העמסת הנה"כ'!I6 -> 0.00089947088 | F28: ='העמסת הנה"כ'!J6 -> -0.0010845719
C29: 5120001 | D29: =VLOOKUP(C29,'מאזן בוחן'!C:D,2,0) -> העמסת הנה"כ לעלות המכר | E29: ='העמסת הנה"כ'!I7 -> 0.0038095235 | F29: ='העמסת הנה"כ'!J7 -> 0.00075840688
C30: 93100 | D30: =VLOOKUP(C30,'מאזן בוחן'!C:D,2,0) -> העמסת הוצאות הנה"כ למחלקות אחרות | E30: =-SUM(E27:E29) -> -0.0036507931 | F30: =-SUM(F27:F29) -> 0.00014775206
B31: =B26+1 -> 8 | C31: עמלות Q4.2021 | E31: ILS | F31: USD | G31: מרכז רווח:
C32: 7110003 | D32: =VLOOKUP(C32,'מאזן בוחן'!C:D,2,0) -> שכר מכירות- עמלות למאזן בלבד | E32: =F32*'מאזן בוחן'!$N$2 -> 0 | F32: 0 | G32: EMEA
C33: 7110003 | D33: =VLOOKUP(C33,'מאזן בוחן'!C:D,2,0) -> שכר מכירות- עמלות למאזן בלבד | E33: =F33*'מאזן בוחן'!$N$2 -> 0 | G33: APAC
C34: 7110003 | D34: =VLOOKUP(C34,'מאזן בוחן'!C:D,2,0) -> שכר מכירות- עמלות למאזן בלבד | E34: =F34*'מאזן בוחן'!$N$2 -> 0 | F34: 0 | G34: LATAM
C35: 2400001 | D35: =VLOOKUP(C35,'מאזן בוחן'!C:D,2,0) -> הוצאות לשלם עובדים | E35: =F35*'מאזן בוחן'!$N$2 -> 0 | F35: =-SUM(F32:F34) -> 0 | G35: להעביר ולהפוך
B36: =B31+1 -> 9 | C36: חשבונית בינחברתית - אלגוסק מערכות ישראל-אלגוסק Inc | E36: ILS | F36: USD | G36: ברבעון - להעביר
C37: 1130001 | D37: =VLOOKUP(C37,'מאזן בוחן'!C:D,2,0) -> אלגוסק INC
C38: 80093 | D38: =VLOOKUP(C38,'מאזן בוחן'!C:D,2,0) -> הכנסות בין חברתיות-תיקון/ביטול שנים קודמות
B39: 9A | C39: חשבונית בינחברתית - אלגוסק מערכות ישראל-אלגוסק Inc | E39: ILS | F39: USD | G39: ברבעון - להעביר
C40: 1130001 | D40: =VLOOKUP(C40,'מאזן בוחן'!C:D,2,0) -> אלגוסק INC
C41: 80093 | D41: =VLOOKUP(C41,'מאזן בוחן'!C:D,2,0) -> הכנסות בין חברתיות-תיקון/ביטול שנים קודמות
B42: =B36+1 -> 10 | C42: IC charge Australia | E42: ILS | F42: USD | G42: AUD | H42: ברבעון - להעביר
C43: 1130005 | D43: =VLOOKUP(C43,'מאזן בוחן'!C:D,2,0) -> אלגוסק אוסטרליה
C44: 9010002 | D44: =VLOOKUP(C44,'מאזן בוחן'!C:D,2,0) -> הפרשי שער
C45: 80093 | D45: =VLOOKUP(C45,'מאזן בוחן'!C:D,2,0) -> הכנסות בין חברתיות-תיקון/ביטול שנים קודמות
B46: =B42+1 -> 11 | C46: IC income AUS LT/ST | E46: ILS | F46: USD | G46: AUD | H46: ברבעון - להעביר ולהפוך
C47: 80093 | D47: =VLOOKUP(C47,'מאזן בוחן'!C:D,2,0) -> הכנסות בין חברתיות-תיקון/ביטול שנים קודמות | E47: =F47*'מאזן בוחן'!$N$2 -> 0
C48: 53699 | D48: =VLOOKUP(C48,'מאזן בוחן'!C:D,2,0) -> מיון הכנסות מראש מז"ק לז"א TP | E48: =F48*'מאזן בוחן'!$N$2 -> 0
C49: 53588 | D49: =VLOOKUP(C49,'מאזן בוחן'!C:D,2,0) -> הכנסות מראש TP | E49: =F49*'מאזן בוחן'!$N$2 -> 0
B50: =B46+1 -> 12 | C50: IC charge Europe | E50: ILS | F50: USD | G50: GBP | H50: ברבעון - להעביר
C51: 1130002 | D51: =VLOOKUP(C51,'מאזן בוחן'!C:D,2,0) -> אלגוסק UK
C52: 9010002 | D52: =VLOOKUP(C52,'מאזן בוחן'!C:D,2,0) -> הפרשי שער
C53: 80093 | D53: =VLOOKUP(C53,'מאזן בוחן'!C:D,2,0) -> הכנסות בין חברתיות-תיקון/ביטול שנים קודמות
B54: =B50+1 -> 13 | C54: IC income EUR LT/ST | E54: ILS | F54: USD | G54: GBP | H54: להעביר ולהפוך
C55: 80093 | D55: =VLOOKUP(C55,'מאזן בוחן'!C:D,2,0) -> הכנסות בין חברתיות-תיקון/ביטול שנים קודמות | E55: =F55*'מאזן בוחן'!$N$2 -> 0 | F55: =-'פ.נ. EUROPE'!F31 -> 0 | G55: =-'פ.נ. EUROPE'!E31 -> 0
C56: 53699 | D56: =VLOOKUP(C56,'מאזן בוחן'!C:D,2,0) -> מיון הכנסות מראש מז"ק לז"א TP | E56: =F56*'מאזן בוחן'!$N$2 -> 0 | F56: =-'פ.נ. EUROPE'!F33 -> 0 | G56: =-'פ.נ. EUROPE'!E33 -> 0
C57: 53588 | D57: =VLOOKUP(C57,'מאזן בוחן'!C:D,2,0) -> הכנסות מראש TP | E57: =F57*'מאזן בוחן'!$N$2 -> 0 | F57: =-'פ.נ. EUROPE'!F32 -> 0 | G57: =-'פ.נ. EUROPE'!E32 -> 0
B58: =B54+1 -> 14 | C58: Def rev. appliance | E58: ILS | F58: USD | G58: אסמכתא | H58: להעביר ולהפוך
C59: 80103-1 | D59: =VLOOKUP(C59,'מאזן בוחן'!C:D,2,0) -> מיון הכנסות מוצר (רוה"ס) | E59: =F59*'מאזן בוחן'!$N$2 -> 0 | G59: IL218000293
C60: 53599 | D60: =VLOOKUP(C60,'מאזן בוחן'!C:D,2,0) -> מיון מהכנסות | E60: =-E59 -> 0 | F60: =-F59 -> 0
B61: =B58+1 -> 15 | C61: מיון בונוס עובדי מטריקס | E61: ILS | F61: USD
C62: 6010008 | D62: =VLOOKUP(C62,'מאזן בוחן'!C:D,2,0) -> שרותי פיתוח מטריקס
C63: 6010010 | D63: =VLOOKUP(C63,'מאזן בוחן'!C:D,2,0) -> בונוסים מטריקס
B64: =B61+1 -> 16 | C64: IC charge France | E64: ILS | F64: USD | G64: EUR | H64: להעביר
C65: 1130008 | D65: =VLOOKUP(C65,'מאזן בוחן'!C:D,2,0) -> אלגוסק צרפת | E65: =F65*'מאזן בוחן'!$N$2 -> 0
C66: 9010002 | D66: =VLOOKUP(C66,'מאזן בוחן'!C:D,2,0) -> הפרשי שער | E66: =-E67-E65 -> 0
C67: 80093 | D67: =VLOOKUP(C67,'מאזן בוחן'!C:D,2,0) -> הכנסות בין חברתיות-תיקון/ביטול שנים קודמות | E67: =F67*'מאזן בוחן'!$N$2 -> 0
B68: =B64+1 -> 17 | C68: IC charge France ST/LT | E68: ILS | F68: USD | G68: EUR | H68: להעביר ולהפוך
C69: 80093 | D69: =VLOOKUP(C69,'מאזן בוחן'!C:D,2,0) -> הכנסות בין חברתיות-תיקון/ביטול שנים קודמות | E69: =F69*'מאזן בוחן'!$N$2 -> 0 | F69: =-'פ.נ. צרפת'!F14 -> 0 | G69: =-'פ.נ. צרפת'!E14 -> 0
C70: 53699 | D70: =VLOOKUP(C70,'מאזן בוחן'!C:D,2,0) -> מיון הכנסות מראש מז"ק לז"א TP | E70: =-E71-E69 -> 0 | F70: =-F71-F69 -> 0 | G70: =-G71-G69 -> 0
C71: 53588 | D71: =VLOOKUP(C71,'מאזן בוחן'!C:D,2,0) -> הכנסות מראש TP | E71: =F71*'מאזן בוחן'!$N$2 -> 0 | F71: =-'פ.נ. צרפת'!F16 -> 0 | G71: =-'פ.נ. צרפת'!E16 -> 0
B72: =B68+1 -> 18 | C72: FAS 123 - Q4 | E72: ILS | F72: USD
C73: 5100013-1 | D73: תשלום מבוסס מניות עלות המכר | E73: =F73*'מאזן בוחן'!$N$2 -> 0 | G73: ברבעון להעביר
C74: 6010004 | D74: תשלום מבוסס מניות פיתוח | E74: =F74*'מאזן בוחן'!$N$2 -> 0
C75: 6110004 | D75: תשלום מבוסס מניות ניהול מוצר | E75: =F75*'מאזן בוחן'!$N$2 -> 0
C76: 7110006 | D76: תשלום מבוסס מניות - מכירות | E76: =F76*'מאזן בוחן'!$N$2 -> 0
C77: 70100025 | D77: תשלום מבוסס מניות שיווק | E77: =F77*'מאזן בוחן'!$N$2 -> 0
C78: 90102 | D78: תשלום מבוסס מניות הנה"כ | E78: =F78*'מאזן בוחן'!$N$2 -> 0
C79: 1130001 | D79: אלגוסק INC | E79: =F79*'מאזן בוחן'!$N$2 -> 0 | F79: =-SUM(F73:F78) -> 0
B80: =B72+1 -> 19 | C80: Arrow December arrow sell | E80: ILS | F80: USD | G80: להעביר
C81: 5800002 | D81: =VLOOKUP(C81,'מאזן בוחן'!C:D,2,0) -> רכיבים-ארו רפק ARROW | E81: =-E82 -> 0
C82: 1100005 | D82: =VLOOKUP(C82,'מאזן בוחן'!C:D,2,0) -> הוצ' מראש ARROW | E82: =F82*'מאזן בוחן'!$N$2 -> 0 | F82: =-F81 -> 0
B83: =B80+1 -> 20 | C83: Arrow December stock | E83: ILS | F83: USD | G83: להעביר
C84: 1100005 | D84: =VLOOKUP(C84,'מאזן בוחן'!C:D,2,0) -> הוצ' מראש ARROW | E84: =F84*'מאזן בוחן'!$N$2 -> 0
C85: 5800002 | D85: =VLOOKUP(C85,'מאזן בוחן'!C:D,2,0) -> רכיבים-ארו רפק ARROW | E85: =-E84 -> 0 | F85: =-F84 -> 0
B86: =B83+1 -> 21 | C86: חיוב ניכוי ביטוח לאומי | E86: ILS | F86: USD | G86: להעביר
C87: 9010004 | D87: =VLOOKUP(C87,'מאזן בוחן'!C:D,2,0) -> ריבית והפרשי הצמדה ממוסדות | E87: =-E88 -> 0 | F87: =E87/'מאזן בוחן'!$N$2 -> 0
C88: 8410300 | D88: =VLOOKUP(C88,'מאזן בוחן'!C:D,2,0) -> שכר לגילום | F88: =-F87 -> 0
B89: =B86+1 -> 22 | C89: ביטוח לאומי בגין עמלות | E89: ILS | F89: USD | G89: מרכז רווח:
C90: 7110010 | D90: =VLOOKUP(C90,'מאזן בוחן'!C:D,2,0) -> הוצאות ביטוח לאומי מעביד - למאזן בלבד | F90: =-F91 -> 0 | G90: EMEA
C91: 2400001 | D91: =VLOOKUP(C91,'מאזן בוחן'!C:D,2,0) -> הוצאות לשלם עובדים | E91: =-E90 -> 0 | F91: =E91/'מאזן בוחן'!$N$2 -> 0 | G91: להעביר ולהפוך
B92: =B89+1 -> 23 | C92: מיון לצורך הצגה בדוחות בין ז"ק לז"א | E92: ILS | F92: USD | G92: ברבעון - להעביר ולהפוך
C93: 53600 | D93: =VLOOKUP(C93,'מאזן בוחן'!C:D,2,0) -> מיון הכנסות מראש מז"ק לז"א | E93: =F93*'מאזן בוחן'!$N$2 -> 0
C94: 53500-1 | D94: הכנסות מראש שקל | E94: =-E93 -> 0 | F94: =-F93 -> 0
B95: =B92+1 -> 24 | C95: Reclass to LT | E95: ILS | F95: USD
C96: 1610005 | D96: =VLOOKUP(C96,'מאזן בוחן'!C:D,2,0) -> Prepaid Comm 606 - Long term | G96: ='מאזן בוחן'!N2 -> 3.11
C97: 1100099 | D97: =VLOOKUP(C97,'מאזן בוחן'!C:D,2,0) -> Prepaid Comm
B98: =B95+1 -> 25 | C98: AMORTIZATION of old comm - 606 | E98: ILS | F98: USD
C99: 1100099 | D99: =VLOOKUP(C99,'מאזן בוחן'!C:D,2,0) -> Prepaid Comm | E99: =F99*$G$99 -> 0 | F99: =-F100 -> 0 | G99: 3.748
C100: 7110044 | D100: =VLOOKUP(C100,'מאזן בוחן'!C:D,2,0) -> עמלות - תקן 606 | E100: =-E99 -> 0
...

Sheet מיסים שוטפים 2021
A1: הפרשה למס 2021 | G1: חופשה | H1: NIS | I1: פיצויים | J1: NIS
A2: מחזור הכנסות | D2: =דוחות!$P$12 -> 1.4157395e+08 | G2: הפרשה לחופשה י.פ. | H2: ='[44]מיסים שוטפים 2020'!$H$4 -> 5748419 | I2: פיצויים י.פ. | J2: ='[44]מיסים שוטפים 2020'!$J$4 -> 4572193
A3: רווח(הפסד) לפני מיסים לפי דו"ח | D3: =דוחות!$P$63 -> -11259307 | G3: הוצאות חופשה | H3: =H4-H2 -> -257 | I3: הוצאות חופשה | J3: =J4-J2 -> 8935
A4: הוסף: | G4: הפרשה לחופשה י.ס. | H4: =דוחות!$J$15 -> 5748162 | I4: פיצויים י.ס. | J4: =דוחות!$J$29-דוחות!$C$37 -> 4581128
A5: התחייבות בשל סיום יחסי עובד מעביד, נטו | C5: =J3 -> 8935
A6: הפרשה לחופשה | C6: =H3 -> -257
A7: קנסות | C7: 100532.8
A8: תשלום מבוסס מניות | C8: =+'מאזן בוחן'!$J$916+'מאזן בוחן'!$J$584+'מאזן בוחן'!$J$591+'מאזן בוחן'!$J$657+'מאזן בוחן'!$J$743+'מאזן בוחן'!$J$881 -> 5573718.3
A9: פחת לפי ספרים | C9: =FA!$G$15 -> 2889374
A10: הוצאות מו"פ שלא שולמו במזומן | C10: =-D66 -> 1183657.2
A11: הפקדות לבעש"ט | C11: ='[45]בדיקת הפקדה לבעל שליטה'!$E$47 -> 25223.52
A12: חלק ברווחי שותפות תושבת ההודית - 99% - דוח 31/03/2022 - שע"ח ממוצע לתקופה | C12: =16837084*0.99*'[46]Reference Rates (2)'!$K$15/9*12 -> 1006380.9
A13: הפסד הון ממכירת רכוש קבוע בספרים | C13: ='מאזן בוחן'!$J$1005 -> 20327.74
A14: עמלות 606 (לפני 2019) | C14: ='מאזן בוחן'!$J$912 -> 430510.49
A15: התאמה למחירי העברה [בגין הכנסות נדחות] - 2021 - MKT Prpjection | C15: =SUM('Tax - Inc'!F50)*'מאזן בוחן'!N2 -> 759209.36
A16: הוצאות מו"פ 2/3 שנדחים בגין 2021 | C16: =+D76 -> 5636927.6
A17: הוצאות עודפות | C17: =SUM('[47]חישוב עודפות'!$F$13) -> 149649.82
D18: =SUM(C5:C17) -> 17784190
A19: הורד:
A20: פחת לפי מס הכנסה | B20: לעדכן סוף שנה לפי טופס פחת לצורכי מס | C20: 3544478
A21: הוצאות מו"פ 1/3 מוכר משנת 2019 | C21: =D82 -> 2504275
A22: הוצאות מו"פ 1/3 מוכר משנת 2020 | C22: =D86 -> 2596973.8
A23: הוצאות מו"פ שלא שולמו במזומן ב- 2020, השנה מוכרות | C23: =D65 -> 1183657.2
A24: התאמות בגין ביקורת ניכויים 2016-2019 | C24: =[48]מרכז!$R$31 -> 377286
D26: =SUM(C20:C25) -> 10206670
A28: סה"כ | D28: =D3+D18-D26 -> -3681787.4
A30: הפרש הנובע מאישור המדען | D30: 0
A31: ניכוי בשל פחת | B31: לעדכן סוף שנה לפי טופס פחת לצורכי מס | D31: -72
A33: סה"כ הפסד להעברה
A34: הכנסה חייבת לצורכי מס (הפסד להעברה) | D34: =SUM($D$28:$D$32) -> -3681859.4
A35: הפסדים מועברים משנים קודמות | D35: 0
A36: סה"כ הכנסה חייבת | D36: =SUM(D34:D35) -> -3681859.4
A37: שיעור מס מועדף טכנוולוגי | B37: 0.12 | D37: =D36*B37 -> -441823.13
A38: הכנסה חייבת בשיעור מס חברות | B38: 0.265
A40: מס לתשלום לפני קיזוז בגין זיכויים
A41: זיכוי משנים קודמות | D41: ='[49]מיסים שוטפים 2020'!$D$48 -> 3146824.8
A42: זיכוי בגין תשלום המס בגין תקופה 2021-22 - שע"ח ממוצע לתקופת הדוח בהודו | D42: =(1755380+2105000+1643000+575157)*'[46]Reference Rates (2)'!$K$15 -> 275245.77
A43: זיכוי השנה | D43: =SUM('מאזן בוחן'!$J$118) -> 1708397.1
A44: קיזוז השנה - בגלל מפעל מועדף טכנולוגי אפשר לקזז רק 12% מההכנסה החייבת בחו"ל (הכנ' חייבת בחו"ל זה 98% לפי הטופס 901 השנה) | D44: =-D36*B37*G45 -> 438996.79 | G44: =[50]Main!$F$3 -> 0.006396993
A45: זיכוי מס מועבר לשנים הבאות | D45: =SUM(D41:D44) -> 5569464.4 | G45: =1-G44 -> 0.99360301
A47: הפסד הון מועבר לשנים הבאות | D47: =-C13 -> -20327.74
A52: מקדמות לנצל ב- 2020 | D52: =D44+D37 -> -2826.3395
A53: מקדמות עודפות שנים קודמות - לא ממודד | D53: =SUM([11]עודפות!$D$5:$F$15) -> 572110.21
A54: מקדמות ששולמו 2021 | D54: ='מאזן בוחן'!$J$121 -> 920507
A55: סה"כ מקדמות מס ששולמו | D55: =D52+D53+D54 -> 1489790.9
D56: =SUM([11]עודפות!$J$5:$J$15)-D55 -> -917680.66
A58: נספח ג' - הוצאות מו"פ לפי סעיף 20א' - השנה
A60: הוצאות מו"פ ברוטו | D60: =דוחות!$P$23 -> 79843837
A61: הוצאות שכר מעבר לתקרה - בהתאם לחישוב של הגשת 20א בגין 2019 | D61: 0
A62: בניכוי פחת | D62: =-'העמסת הנה"כ'!$H$33*'העמסת הנה"כ'!$C$19 -> -1210310.9
A63: בניכוי תשלום מבוסס מניות | D63: =-'מאזן בוחן'!$J$584-'מאזן בוחן'!$J$591 -> -1810399.4
A64: בניכוי הוצאות חופשה ופיצויים | D64: =-'מאזן בוחן'!J585-'מאזן בוחן'!J593 -> 44067.58
A65: תוספת הוצאות מו"פ שלא שולמו במזומן ב- 2020 | D65: =-'[49]מיסים שוטפים 2020'!$D$69 -> 1183657.2
A66: בניכוי הוצאות מו"פ שלא שולמו במזומן ב- 2021 | D66: =-D65 -> -1183657.2
A68: הוצאות מו"פ שהועברו לאישור המדען | D68: =SUM(D60:D66) -> 76867194
A70: החלק שיוכר מיידית 2020 - 89% - על בסיס אישור מדען של 2020 | B70: 0.89 | D70: =D68*B70 -> 68411803 | G70: ='[51]מופ מוכר (2019)'!$B$11 -> 0.88711006 | H70: נייר מופ מוכר 2019
A72: החלק שיוכר ע"פ 3 שנים | D72: =D68-D70 -> 8455391.4
D73: =-D61 -> 0
D74: =SUM(D72:D73) -> 8455391.4
A76: סך של 2/3 מהוצאות מו"פ לפריסה | D76: =+D74*2/3 -> 5636927.6
A79: נספח ד' - הוצאות מו"פ לפי סעיף 20א' בגין שנים קודמות
A81: שנת 2019:
A82: סך של 1/3 מהוצאות מו"פ בשנת 2019 המוכרות לצורך 20א' | D82: ='[52]מופ מוכר (2019)'!$E$46 -> 2504275
A85: שנת 2020:
A86: סך של 1/3 מהוצאות מו"פ בשנת 2020 המוכרות לצורך 20א' | D86: =SUM('[49]מיסים שוטפים 2020'!$D$79)/2 -> 2596973.8
H98: בפועל מה שקרה | I98: 2017 | J98: 2018 | K98: 2019
H99: הקדמת הוצאות
H100: הכרה בדוח | I100: =+C21 -> 2504275 | J100: =+I100 -> 2504275 | K100: =+J100 -> 2504275
H101: הכרה בכל שנה | I101: =SUM(I99:I100) -> 2504275 | J101: =SUM(J99:J100) -> 2504275 | K101: =SUM(K99:K100) -> 2504275
H102: הכרה מצטברת | I102: =+I101 -> 2504275 | J102: =+J101+I102 -> 5008550 | K102: =+K101+J102 -> 7512824.9
H105: מה היה צריך להיות
H107: הכרה בכל שנה | I107: =3116481/3 -> 1038827 | J107: =+I107 -> 1038827 | K107: =+J107 -> 1038827
H108: הכרה מצטברת | I108: =+I107 -> 1038827 | J108: =+J107+I108 -> 2077654 | K108: =+K107+J108 -> 3116481
H110: בעקבות התיקון
H111: הקדמת הוצאות | I111: =50086046-48811445 -> 1274601 | J111: =-K111 -> -424867 | K111: =I111/3 -> 424867
H112: הכרה בדוח | I112: =+I100 -> 2504275 | J112: =+I112 -> 2504275 | K112: =J112 -> 2504275
H113: הכרה בכל שנה | I113: =SUM(I111:I112) -> 3778876 | J113: =SUM(J111:J112) -> 2079408 | K113: =SUM(K111:K112) -> 2929142
H114: הכרה מצטברת | I114: =+I113 -> 3778876 | J114: =+J113+I114 -> 5858284 | K114: =+K113+J114 -> 8787425.9
J117: כך רואים שב-2018 אנחנו במצטבר עומדים ברמת הכרה התואמת את אישור המדען ל- 2017

Sheet העמסת הנה"כ
A2: G&A Loading - Brosh Building
G3: recorded
B4: תמחיר Q4 2021 | E4: פקודה להעמסת הוצאות הנה"כ | G4: ₪ | H4: $ | I4: ₪ | J4: $ | L4: לוודא שמתאפס
A5: Department | B5: # of employees | E5: 6030001 | F5: העמסת הנכ"ל למחלקת מו"פ | G5: =VLOOKUP(E5,'מאזן בוחן'!C:M,3,0) -> 6956062 | H5: =VLOOKUP(E5,'מאזן בוחן'!$C:$N,11,0) -> 2099606.7 | I5: =E15+E16+G15+G16+E66-G5 -> -0.0010582013 | J5: =F15+F16+H15+H16+F66-H5 -> 0.000178413
A6: G&A | B6: =2+12+4+9+3 -> 30 | E6: 7030001 | F6: העמסת הוצאות הנכ"ל על השיווק | G6: =VLOOKUP(E6,'מאזן בוחן'!C:M,3,0) -> 1764557.7 | H6: =VLOOKUP(E6,'מאזן בוחן'!C:N,11,0) -> 536968.96 | I6: =E17+G17+E68-G6 -> 0.00089947088 | J6: =F17+H17+F68-H6 -> -0.0010845719
A7: R&D | B7: =3+106+12 -> 121 | E7: 5120001 | F7: העמסת הנכ"ל ושכר למחלקת עלות המכר | G7: =VLOOKUP(E7,'מאזן בוחן'!C:M,3,0) -> 1101733.7 | H7: =VLOOKUP(E7,'מאזן בוחן'!C:N,11,0) -> 333035.2 | I7: =E13+E14+G13+G14+E70-G7 -> 0.0038095235 | J7: =F13+F14+H13+H14+F70-H7 -> 0.00075840688
A8: S&M | B8: =2/2+2+15+2 -> 20 | E8: 93100 | F8: העמסת הוצאות הנה"כ למחלקות אחרות | G8: =VLOOKUP(E8,'מאזן בוחן'!C:M,3,0) -> -9822353.4 | H8: =VLOOKUP(E8,'מאזן בוחן'!C:N,11,0) -> -2969610.8 | I8: =-SUM(I5:I7) -> -0.0036507931 | J8: =-SUM(J5:J7) -> 0.00014775206
A9: Support | B9: =2/2+5+5+7 -> 18 | G9: =SUM(G5:G8) -> 0 | H9: =SUM(H5:H8) -> 0 | I9: =SUM(E13:E17)+SUM(G13:G17)+SUM(E66:E70)+I8+G8 -> 0 | J9: =SUM(F13:F17)+SUM(H13:H17)+SUM(F59:F70)+J8+H8 -> 0
B10: =SUM(B6:B9) -> 189
E11: Rent | F11: Rent | G11: G&A | H11: G&A
E12: ש"ח | F12: USD | G12: ש"ח | H12: USD
E13: =+$G$27*C17 -> 237589.82 | F13: =+$H$27*C17 -> 73054.372 | G13: =$H$55*C17 -> 612297.88 | H13: =$I$55*C17 -> 182121.11
E14: =+$G$27*C18 -> 0 | F14: =+$H$27*C18 -> 0 | G14: =$H$55*C18 -> 0 | H14: =$I$55*C18 -> 0
E15: =+$G$27*C19 -> 1597131.6 | F15: =+$H$27*C19 -> 491087.73 | G15: =$H$55*C19 -> 4116002.4 | H15: =$I$55*C19 -> 1224258.6
B16: # of employees | C16: Key allocation | E16: =+$G$27*C20 -> 0 | F16: =+$H$27*C20 -> 0 | G16: =$H$55*C20 -> 0 | H16: =$I$55*C20 -> 0
A17: Technical support | B17: =B9 -> 18 | C17: =B17/$B$23 -> 0.095238095 | E17: =+$G$27*C21 -> 263988.69 | F17: =+$H$27*C21 -> 81171.525 | G17: =$H$55*C21 -> 680330.98 | H17: =$I$55*C21 -> 202356.79
A18: Professional services | E18: =+$G$27*C22 -> 395983.03 | F18: =+$H$27*C22 -> 121757.29 | G18: =$H$55*C22 -> 1020496.5 | H18: =$I$55*C22 -> 303535.19
A19: R&D | B19: =B7 -> 121 | C19: =B19/$B$23 -> 0.64021164 | E19: =SUM(E13:E18) -> 2494693.1 | F19: =SUM(F13:F18) -> 767070.91 | G19: =SUM(G13:G18) -> 6429127.8 | H19: =SUM(H13:H18) -> 1912271.7
A20: Product Management | E20: =G27-E19 -> 0 | F20: =H27-F19 -> 0 | G20: =G19-H55 -> 0 | H20: =H19-I55 -> 0
A21: Sales & Marketing | B21: =B8 -> 20 | C21: =B21/$B$23 -> 0.10582011
A22: G&A | B22: =B6 -> 30 | C22: =B22/$B$23 -> 0.15873016
B23: =SUM(B17:B22) -> 189 | C23: =SUM(C17:C22) -> 1 | G23: בש"ח | H23: USD
B24: =+B10-B23 -> 0 | E24: 8030001 | F24: שכר דירה | G24: =VLOOKUP(E24,'מאזן בוחן'!C:K,8,0) -> 1819066.4 | H24: =VLOOKUP(E24,'מאזן בוחן'!C:K,9,0) -> 557731.58 | I24: =G24/H24 -> 3.2615445
E25: 8030002 | F25: חשמל | G25: =VLOOKUP(E25,'מאזן בוחן'!C:K,8,0) -> 332476.92 | H25: =VLOOKUP(E25,'מאזן בוחן'!C:K,9,0) -> 103078.12 | I25: =G25/H25 -> 3.2254849
E26: 8030003 | F26: ארנונה ומים | G26: =VLOOKUP(E26,'מאזן בוחן'!C:K,8,0) -> 343149.8 | H26: =VLOOKUP(E26,'מאזן בוחן'!C:K,9,0) -> 106261.21 | I26: =G26/H26 -> 3.2293045
F27: Rent to allocate | G27: =SUM(G24:G26) -> 2494693.1 | H27: =SUM(H24:H26) -> 767070.91
G28: =SUM('מאזן בוחן'!J759:J761)-G27 -> 0 | H28: =SUM('מאזן בוחן'!K759:K761)-H27 -> 0
G30: G&A to allocate :
H32: בש"ח | I32: USD
F33: 8030020 | G33: פחת | H33: =VLOOKUP(F33,'מאזן בוחן'!C:K,8,0) -> 1890485.7 | I33: =VLOOKUP(F33,'מאזן בוחן'!C:K,9,0) -> 515370.41 | J33: =H33/I33 -> 3.6682076
F34: 8030004 | G34: טלפון, תקשורת ואינטרנט | H34: =VLOOKUP(F34,'מאזן בוחן'!C:K,8,0) -> 189274.77 | I34: =VLOOKUP(F34,'מאזן בוחן'!C:K,9,0) -> 58559.31 | J34: =H34/I34 -> 3.2321892
F35: 8030005 | G35: סלולרי | H35: =VLOOKUP(F35,'מאזן בוחן'!C:K,8,0) -> 4934.87 | I35: =VLOOKUP(F35,'מאזן בוחן'!C:K,9,0) -> 1528.78 | J35: =H35/I35 -> 3.2279792
F36: 8030006 | G36: משרדיות | H36: =VLOOKUP(F36,'מאזן בוחן'!C:K,8,0) -> 43089.95 | I36: =VLOOKUP(F36,'מאזן בוחן'!C:K,9,0) -> 13348.02 | J36: =H36/I36 -> 3.2281904
F37: 8030008 | G37: תחזוקת כללית | H37: =VLOOKUP(F37,'מאזן בוחן'!C:K,8,0) -> 6577 | I37: =VLOOKUP(F37,'מאזן בוחן'!C:K,9,0) -> 2170.42 | J37: =H37/I37 -> 3.0302891
F38: 8030009 | G38: אחזקת משרד | H38: =VLOOKUP(F38,'מאזן בוחן'!C:K,8,0) -> 265441.56 | I38: =VLOOKUP(F38,'מאזן בוחן'!C:K,9,0) -> 81422.72 | J38: =H38/I38 -> 3.2600429
F39: 8030010 | G39: שליחויות | H39: =VLOOKUP(F39,'מאזן בוחן'!C:K,8,0) -> 14714.53 | I39: =VLOOKUP(F39,'מאזן בוחן'!C:K,9,0) -> 4557.28 | J39: =H39/I39 -> 3.2287966
F40: 8030011 | G40: אגרות ודמי חבר | H40: =VLOOKUP(F40,'מאזן בוחן'!C:K,8,0) -> 19860.52 | I40: =VLOOKUP(F40,'מאזן בוחן'!C:K,9,0) -> 6132.12 | J40: =H40/I40 -> 3.238769
F41: 8030012 | G41: מצרכים למשרד ולישיבות | H41: =VLOOKUP(F41,'מאזן בוחן'!C:K,8,0) -> 99742.86 | I41: =VLOOKUP(F41,'מאזן בוחן'!C:K,9,0) -> 31012.99 | J41: =H41/I41 -> 3.2161639
F42: 8030013 | G42: נסיעות כללי, מוניות, (עובדים ללא רכב) וחניה | H42: =VLOOKUP(F42,'מאזן בוחן'!C:K,8,0) -> 3358.69 | I42: =VLOOKUP(F42,'מאזן בוחן'!C:K,9,0) -> 1039.14 | J42: =H42/I42 -> 3.2321824
F43: 8030014 | G43: השתלמויות וספרות מקצועית הנה"כ | H43: =VLOOKUP(F43,'מאזן בוחן'!C:K,8,0) -> 40497.46 | I43: =VLOOKUP(F43,'מאזן בוחן'!C:K,9,0) -> 12597.79 | J43: =H43/I43 -> 3.214648
F44: 8030015 | G44: אחזקת מחשבים | H44: =VLOOKUP(F44,'מאזן בוחן'!C:K,8,0) -> 391387.86 | I44: =VLOOKUP(F44,'מאזן בוחן'!C:K,9,0) -> 120291.86 | J44: =H44/I44 -> 3.2536521
F45: 8410066 | G45: ביטוח עסק | H45: =VLOOKUP(F45,'מאזן בוחן'!C:K,8,0) -> 23991.75 | I45: =VLOOKUP(F45,'מאזן בוחן'!C:K,9,0) -> 7212.49 | J45: =H45/I45 -> 3.3264171
F46: 8030015-1 | G46: אחזקת מחשבים | H46: =VLOOKUP(F46,'מאזן בוחן'!C:K,8,0) -> 32399 | I46: =VLOOKUP(F46,'מאזן בוחן'!C:K,9,0) -> 10454.76 | J46: =H46/I46 -> 3.0989712
F47: 8030017 | G47: פעילויות צוות /חברה | H47: =VLOOKUP(F47,'מאזן בוחן'!C:K,8,0) -> 97577.92 | I47: =VLOOKUP(F47,'מאזן בוחן'!C:K,9,0) -> 30950.35 | J47: =H47/I47 -> 3.1527243
F48: 8030018 | G48: ארוחות לעובדים | H48: =VLOOKUP(F48,'מאזן בוחן'!C:K,8,0) -> 1302335.7 | I48: =VLOOKUP(F48,'מאזן בוחן'!C:K,9,0) -> 405190.74 | J48: =H48/I48 -> 3.21413
F49: 8030022 | G49: מתנות לעובדים | H49: =VLOOKUP(F49,'מאזן בוחן'!C:K,8,0) -> 199002.25 | I49: =VLOOKUP(F49,'מאזן בוחן'!C:K,9,0) -> 61038.46 | J49: =H49/I49 -> 3.2602764
F50: 8030023 | G50: כיבודים | H50: =VLOOKUP(F50,'מאזן בוחן'!C:K,8,0) -> 99828.97 | I50: =VLOOKUP(F50,'מאזן בוחן'!C:K,9,0) -> 31045.07 | J50: =H50/I50 -> 3.2156143
F51: 8030025 | G51: אירועי חברה | H51: =VLOOKUP(F51,'מאזן בוחן'!C:K,8,0) -> 548024 | I51: =VLOOKUP(F51,'מאזן בוחן'!C:K,9,0) -> 170263.35 | J51: =H51/I51 -> 3.2186845
F52: 8030026 | G52: אירוח חו"ל | H52: =VLOOKUP(F52,'מאזן בוחן'!C:K,8,0) -> 0 | I52: =VLOOKUP(F52,'מאזן בוחן'!C:K,9,0) -> 0 | J52: =H52/I52 -> #DIV/0!
F53: 8410048 | G53: רשיונות תוכנה הנה"כ | H53: =VLOOKUP(F53,'מאזן בוחן'!C:K,8,0) -> 1156602.5 | I53: =VLOOKUP(F53,'מאזן בוחן'!C:K,9,0) -> 348085.63 | J53: =H53/I53 -> 3.3227527
H55: =SUM(H33:H53) -> 6429127.8 | I55: =SUM(I33:I53) -> 1912271.7
H56: =SUM('מאזן בוחן'!J748,'מאזן בוחן'!J762,'מאזן בוחן'!J765:J778,'מאזן בוחן'!J861:J865) -> 6429127.8 | I56: =SUM('מאזן בוחן'!K748,'מאזן בוחן'!K762,'מאזן בוחן'!K765:K778,'מאזן בוחן'!K861:K865) -> 1912271.7
H57: =H56-H55 -> 0 | I57: =I56-I55 -> 0
I58: =I55+H27 -> 2679342.6
C63: 1-3/2021
C64: ₪ | D64: $
A66: IT TEAM - FOR R&D LAB | B66: =C66/D66 -> 3.334 | C66: =111963+116606+86397 -> 314966 | D66: =C66/3.334 -> 94470.906 | E66: =C66+C75+C84+C93 -> 1242928 | F66: =D66+D75+D84+D93 -> 384260.35 | G66: =E66/F66 -> 3.2345986
A68: YAIR & GERSHON FOR SALES | B68: =C68/D68 -> 3.334 | C68: =65340+117864+56340 -> 239544 | D68: =C68/3.334 -> 71848.83 | E68: =C68+C77+C86+C95 -> 820238 | F68: =D68+D77+D86+D95 -> 253440.64 | G68: =E68/F68 -> 3.2364107
A70: SALES OPERATION - 50% FOR COGS | B70: =C70/D70 -> 3.334 | C70: =(40793+62147+37912)/2 -> 70426 | D70: =C70/3.334 -> 21123.575 | E70: =C70+C79+C88+C97 -> 251846 | F70: =D70+D79+D88+D97 -> 77859.715 | G70: =E70/F70 -> 3.2346124
C72: 4-6/2021
C73: ₪ | D73: $
A75: IT TEAM - FOR R&D LAB | B75: =C75/D75 -> 3.26 | C75: =61746+102303+90714+29891 -> 284654 | D75: =C75/3.26 -> 87317.178
A77: YAIR & GERSHON FOR SALES | B77: =C77/D77 -> 3.26 | C77: =115113+77156 -> 192269 | D77: =C77/3.26 -> 58978.221
A79: SALES OPERATION - 50% FOR COGS | B79: =C79/D79 -> 3.26 | C79: =(66672+52866)/2 -> 59769 | D79: =C79/3.26 -> 18334.049
C81: 7-9/2021
C82: ₪ | D82: $
A84: IT TEAM - FOR R&D LAB | B84: =C84/D84 -> 3.229 | C84: =61842+102432+100911+104366 -> 369551 | D84: =C84/3.229 -> 114447.51
A86: YAIR & GERSHON FOR SALES | B86: =C86/D86 -> 3.229 | C86: =115288+77278 -> 192566 | D86: =C86/3.229 -> 59636.42
A88: SALES OPERATION - 50% FOR COGS | B88: =C88/D88 -> 3.229 | C88: =(67146+53358)/2 -> 60252 | D88: =C88/3.229 -> 18659.647
C90: 10-12/2021
C91: ₪ | D91: $
A93: IT TEAM - FOR R&D LAB | B93: =C93/D93 -> 3.11 | C93: =63286+104437+106034 -> 273757 | D93: =C93/'מאזן בוחן'!$N$2 -> 88024.759
A95: YAIR & GERSHON FOR SALES | B95: =C95/D95 -> 3.11 | C95: =116909+78950 -> 195859 | D95: =C95/'מאזן בוחן'!$N$2 -> 62977.17
A97: SALES OPERATION - 50% FOR COGS | B97: =C97/D97 -> 3.11 | C97: =(68336+54462)/2 -> 61399 | D97: =C97/'מאזן בוחן'!$N$2 -> 19742.444

Sheet 606-Prepaid Comm&DR SUB
A9: 606-Prepaid Comm
A11: ='נתונים לשינוי'!C4 -> As at December 31, 2021
I12: ='נתונים לשינוי'!C4 -> As at December 31, 2021
A13: History | B13: Algosec System Ltd | C13: Algosec Inc | D13: Algosec Australia | E13: Algosec Europe | F13: Consolidated | I13: history | J13: Q1 | K13: Q2 | L13: Q3 | M13: Q4 | N13: Q1 2020 | O13: Q2 2020 | P13: Q3 2020 | Q13: Q4 2020 | R13: Q1 2021 | S13: Q2 2021 | T13: Q3 2021 | U13: Q4 2021 | V13: TOTAL
A14: Prepaid Comm 606- Short term | B14: =SUM('[53]Final '!$AU$3:$AX$3) -> 40175.612 | C14: =SUM('[53]Final '!$AU$4:$AX$4) -> 57347.494 | D14: =SUM('[53]Final '!$AU$6:$AX$6) -> 3377.4106 | E14: =SUM('[53]Final '!$AU$5:$AX$5) -> 21011.968 | F14: =SUM(B14:E14) -> 121912.48 | I14: =SUM('[53]Final '!$AU$7:$AX$7) -> 121912.48 | J14: =SUM([54]ALL!$AE$33:$AM$33) -> 40569.147 | K14: =SUM([55]ALL!$AE$33:$AO$33) -> 53574.646 | L14: =SUM([56]ALL!$AE$33:$AR$33) -> 63690.213 | M14: =SUM([57]ALL!$AE$33:$BB$33) -> 243232.28 | N14: =SUM([58]ALL!$AE$33:$AAA$33) -> 99933.598 | O14: =SUM([59]ALL!$AE$33:$BD$33) -> 361759.59 | P14: =SUM([60]ALL!$AE$33:$BE$33) -> 237161.32 | Q14: =SUM([61]ALL!$AE$33:$XFD$33) -> 444351.64 | R14: =SUM([62]ALL!$AE$33:$BC$33) -> 235967.46 | S14: =SUM([63]ALL!$AE$33:$BJ$33) -> 351483.73 | T14: =SUM([64]ALL!$AE$33:$BJ$33) -> 520656.6 | U14: =SUM([65]ALL!$AE$33:$BC$33) -> 869751.94 | V14: =SUM(I14:U14) -> 3644044.6
A15: Prepaid Comm 606- Long term | F15: =SUM(B15:E15) -> 0 | G15: =Consolidation!N19-דוחות!D38-F15-F18-F21-F24-F27-F30-F33-F36-F39-F42-F45-F48-F51 -> -0.25093654 | H15: Check | V15: =V14-F54 -> -0.0062177964
A16: Q1
A17: Prepaid Comm 606- Short term | B17: =SUM([54]ALL!$AE$29:$AH$29) -> 8658.8668 | C17: =SUM([54]ALL!$AE$30:$AH$30) -> 10782.009 | D17: =SUM([54]ALL!$AE$32:$AH$32) -> 8843.5168 | E17: =SUM([54]ALL!$AE$31:$AH$31) -> 5424.5611 | F17: =SUM(B17:E17) -> 33708.954
A18: Prepaid Comm 606- Long term | B18: =SUM([54]ALL!$AL$29:$AM$29) -> 2138.2381 | C18: =SUM([54]ALL!$AL$30:$AO$30) -> 2398.595 | D18: =SUM([54]ALL!$AL$32:$AO$32) -> 1040.5725 | E18: =SUM([54]ALL!$AL$31:$AL$31) -> 1282.7875 | F18: =SUM(B18:E18) -> 6860.1931
A19: Q2
A20: Prepaid Comm 606- Short term | B20: =SUM([55]ALL!$AE$29:$AH$29) -> 4313.8013 | C20: =SUM([55]ALL!$AE$30:$AH$30) -> 22988.81 | D20: =SUM([55]ALL!$AE$32:$AH$32) -> 2081.3175 | E20: =SUM([55]ALL!$AE$31:$AH$31) -> 9260.482 | F20: =SUM(B20:E20) -> 38644.411 | I20: LT TP PREPAID | K20: INC | L20: ='New TB INC'!J270 -> 1152543.5
A21: Prepaid Comm 606- Long term | B21: =SUM([55]ALL!$AL$29:$AO$29) -> 2045.6612 | C21: =SUM([55]ALL!$AL$30:$AO$30) -> 8706.3988 | D21: =SUM([55]ALL!$AL$32:$AO$32) -> 1040.6587 | E21: =SUM([55]ALL!$AL$31:$AO$31) -> 3137.5162 | F21: =SUM(B21:E21) -> 14930.235 | K21: UK | L21: ='FS EU'!C15 -> 377994.78
A22: Q3 | K22: AUD | L22: ='FS AU'!C15 -> 121809.95
A23: Prepaid Comm 606- Short term | B23: =SUM([56]ALL!$AE$29:$AH$29) -> 5399.3376 | C23: =SUM([56]ALL!$AE$30:$AH$30) -> 10725.209 | D23: =SUM([56]ALL!$AE$32:$AH$32) -> 9409.0007 | E23: =SUM([56]ALL!$AE$31:$AH$31) -> 22800.671 | F23: =SUM(B23:E23) -> 48334.218 | K23: LTD | L23: ='מאזן בוחן'!K186 -> 308476.88
A24: Prepaid Comm 606- Long term | B24: =SUM([56]ALL!$AL$29:$AO$29) -> 4003.9219 | C24: =SUM([56]ALL!$AL$30:$AO$30) -> 7098.3337 | D24: =SUM([56]ALL!$AL$32:$AO$32) -> 1081.1325 | E24: =SUM([56]ALL!$AL$31:$AO$31) -> 3172.6069 | F24: =SUM(B24:E24) -> 15355.995 | L24: =SUM(L20:L23) -> 1960825.2
A25: Q4 | L25: =F24+F21+F18+F15+F27+F30+F33+F36-L24+F39+F42+F45+F48+F51 -> 0.37093654
A26: Prepaid Comm 606- Short term | B26: =SUM([57]ALL!$AE$29:$AH$29) -> 25424.768 | C26: =SUM([57]ALL!$AE$30:$AH$30) -> 102986.69 | D26: =SUM([57]ALL!$AE$32:$AH$32) -> 395.9525 | E26: =SUM([57]ALL!$AE$31:$AH$31) -> 48205.005 | F26: =SUM(B26:E26) -> 177012.41
A27: Prepaid Comm 606- Long term | B27: =SUM([57]ALL!$AL$29:$AV$29) -> 11372.778 | C27: =SUM([57]ALL!$AL$30:$AV$30) -> 31262.833 | D27: =SUM([57]ALL!$AL$32:$AV$32) -> 395.9525 | E27: =SUM([57]ALL!$AL$31:$AX$31) -> 23188.305 | F27: =SUM(B27:E27) -> 66219.867
A28: Q1 2020
A29: Prepaid Comm 606- Short term | B29: =SUM([58]ALL!$AE$29:$AH$29) -> 15384.79 | C29: =SUM([58]ALL!$AE$30:$AH$30) -> 30607.92 | D29: =SUM([58]ALL!$AE$32:$AH$32) -> 355.785 | E29: =SUM([58]ALL!$AE$31:$AH$31) -> 6966.5323 | F29: =SUM(B29:E29) -> 53315.027
A30: Prepaid Comm 606- Long term | B30: =SUM([58]ALL!$AL$29:$BC$29) -> 14694.111 | C30: =SUM([58]ALL!$AL$30:$AV$30) -> 23275.078 | D30: =SUM([58]ALL!$AL$32:$AV$32) -> 444.73125 | E30: =SUM([58]ALL!$AL$31:$BC$31) -> 8204.6497 | F30: =SUM(B30:E30) -> 46618.57
A31: Q2 2020
A32: Prepaid Comm 606- Short term | B32: =SUM([59]ALL!$AE$29:$AH$29) -> 10553.229 | C32: =SUM([59]ALL!$AE$30:$AH$30) -> 192165.4 | D32: =SUM([59]ALL!$AE$32:$AH$32) -> 4011.3547 | E32: =SUM([59]ALL!$AE$31:$AH$31) -> 11784.303 | F32: =SUM(B32:E32) -> 218514.29
A33: Prepaid Comm 606- Long term | B33: =SUM([59]ALL!$AL$29:$AU$29) -> 13402.968 | C33: =SUM([59]ALL!$AL$30:$AT$30) -> 114569.92 | D33: =SUM([59]ALL!$AL$32:$AT$32) -> 2814.6024 | E33: =SUM([59]ALL!$AL$31:$AV$31) -> 12457.81 | F33: =SUM(B33:E33) -> 143245.3
A34: Q3 2020
A35: Prepaid Comm 606- Short term | B35: =SUM([60]ALL!$AE$29:$AH$29) -> 17463.033 | C35: =SUM([60]ALL!$AE$30:$AH$30) -> 53001.142 | D35: =SUM([60]ALL!$AE$32:$AH$32) -> 3176.1848 | E35: =SUM([60]ALL!$AE$31:$AH$31) -> 39039.65 | F35: =SUM(B35:E35) -> 112680.01
A36: Prepaid Comm 606- Long term | B36: =SUM([60]ALL!$AL$29:$BE$29) -> 23457.262 | C36: =SUM([60]ALL!$AL$30:$BE$30) -> 60053.506 | D36: =SUM([60]ALL!$AL$32:$BE$32) -> 5026.9005 | E36: =SUM([60]ALL!$AL$31:$BC$31) -> 35943.644 | F36: =SUM(B36:E36) -> 124481.31
A37: Q4 2020
A38: Prepaid Comm 606- Short term | B38: =SUM([66]ALL!$AE$29:$AH$29) -> 25378.056 | C38: =SUM([61]ALL!$AE$30:$AH$30) -> 104530.39 | D38: =SUM([61]ALL!$AE$32:$AH$32) -> 22518.372 | E38: =SUM([61]ALL!$AE$31:$AH$31) -> 17805.689 | F38: =SUM(B38:E38) -> 170232.51
A39: Prepaid Comm 606- Long term | B39: =SUM([66]ALL!$AL$29:$BE$29) -> 43996.643 | C39: =SUM([61]ALL!$AL$30:$BE$30) -> 147086.31 | D39: =SUM([61]ALL!$AL$32:$BE$32) -> 42488.48 | E39: =SUM([61]ALL!$AL$31:$BC$31) -> 40547.697 | F39: =SUM(B39:E39) -> 274119.13
A40: Q1 2021
A41: Prepaid Comm 606- Short term | B41: =SUM([67]ALL!$AE$29:$AH$29) -> 20202.476 | C41: =SUM([62]ALL!$AE$30:$AH$30) -> 50235.018 | D41: =SUM([67]ALL!$AE$32:$AH$32) -> 2522.2239 | E41: =SUM([67]ALL!$AE$31:$AH$31) -> 21046.902 | F41: =SUM(B41:E41) -> 94006.62
A42: Prepaid Comm 606- Long term | B42: =SUM([67]ALL!$AL$29:$BC$29) -> 43015.802 | C42: =SUM([62]ALL!$AL$30:$BF$30) -> 63863.149 | D42: =SUM([67]ALL!$AL$32:$BC$32) -> 5400.9948 | E42: =SUM([67]ALL!$AL$31:$BC$31) -> 29680.897 | F42: =SUM(B42:E42) -> 141960.84
A43: Q2 2021
A44: Prepaid Comm 606- Short term | B44: =SUM([68]ALL!$AE$29:$AH$29) -> 19590.473 | C44: =SUM([63]ALL!$AE$30:$AH$30) -> 79192.503 | D44: =SUM([68]ALL!$AE$32:$AH$32) -> 421.72507 | E44: =SUM([63]ALL!$AE$31:$AH$31) -> 25034.472 | F44: =SUM(B44:E44) -> 124239.17
A45: Prepaid Comm 606- Long term | B45: =SUM([68]ALL!$AL$29:$BJ$29) -> 41279.444 | C45: =SUM([63]ALL!$AL$30:$BJ$30) -> 130926.54 | D45: =SUM([68]ALL!$AL$32:$BJ$32) -> 1021.0562 | E45: =SUM([63]ALL!$AL$31:$BJ$31) -> 54017.52 | F45: =SUM(B45:E45) -> 227244.56
A46: Q3 2021
A47: Prepaid Comm 606- Short term | B47: =SUM([64]ALL!$AE$29:$AH$29) -> 18843.223 | C47: =SUM([64]ALL!$AE$30:$AH$30) -> 129805.67 | D47: =SUM([64]ALL!$AE$32:$AH$32) -> 23710.028 | E47: =SUM([64]ALL!$AE$31:$AH$31) -> 14065.337 | F47: =SUM(B47:E47) -> 186424.25
A48: Prepaid Comm 606- Long term | B48: =SUM([64]ALL!$AL$29:$BJ$29) -> 39400.357 | C48: =SUM([64]ALL!$AL$30:$BJ$30) -> 237263.35 | D48: =SUM([64]ALL!$AL$32:$BJ$32) -> 44506.746 | E48: =SUM([64]ALL!$AL$31:$BJ$31) -> 13061.888 | F48: =SUM(B48:E48) -> 334232.34
A49: Q4 2021
A50: Prepaid Comm 606- Short term | B50: =SUM([65]ALL!$AE$29:$AH$29) -> 52263.779 | C50: =SUM([65]ALL!$AE$30:$AH$30) -> 165885.52 | D50: =SUM([65]ALL!$AE$32:$AH$32) -> 6702.0895 | E50: =SUM([65]ALL!$AE$31:$AH$31) -> 79343.374 | F50: =SUM(B50:E50) -> 304194.76
A51: Prepaid Comm 606- Long term | B51: =SUM([65]ALL!$AL$29:$BJ$29) -> 69669.699 | C51: =SUM([65]ALL!$AL$30:$BJ$30) -> 326039.9 | D51: =SUM([65]ALL!$AL$32:$BJ$32) -> 16548.127 | E51: =SUM([65]ALL!$AL$31:$BJ$31) -> 153299.45 | F51: =SUM(B51:E51) -> 565557.18
B54: =SUM(B14:B53) -> 572128.33 | C54: =SUM(C14:C53) -> 2162797.7 | D54: =SUM(D14:D53) -> 209334.92 | E54: =SUM(E14:E53) -> 699783.72 | F54: =SUM(F14:F53) -> 3644044.7
B55: ='מאזן בוחן'!K138+'מאזן בוחן'!K186-B54 -> -1.1372469 | C55: ='New TB INC'!J242+'New TB INC'!J270-C54 -> 0.49068139 | D55: ='מאזן בוחן Australia'!K35+'מאזן בוחן Australia'!K64-D54 -> 0.60456324 | E55: ='מאזן בוחן EUROPE'!K186+'מאזן בוחן EUROPE'!K212-E54 -> 40.717416
A57: ST | B57: =B14+B17+B20+B23+B26+B29+B32+B35+B38+B41+B44+B47+B50 -> 263651.44 | C57: =C14+C17+C20+C23+C26+C29+C32+C35+C38+C41+C44+C47+C50 -> 1010253.8 | D57: =D14+D17+D20+D23+D26+D29+D32+D35+D38+D41+D44+D47+D50 -> 87524.961 | E57: =E14+E17+E20+E23+E26+E29+E32+E35+E38+E41+E44+E47+E50 -> 321788.95
A58: LT | B58: =B15+B18+B21+B24+B27+B30+B33+B36+B39+B42+B45+B48+B51 -> 308476.88 | C58: =C15+C18+C21+C24+C27+C30+C33+C36+C39+C42+C45+C48+C51 -> 1152543.9 | D58: =D15+D18+D21+D24+D27+D30+D33+D36+D39+D42+D45+D48+D51 -> 121809.95 | E58: =E15+E18+E21+E24+E27+E30+E33+E36+E39+E42+E45+E48+E51 -> 377994.78
A59: TB | B59: ='מאזן בוחן'!$M$186 -> 308476.88 | C59: ='New TB INC'!$E$270 -> 1152543.5 | D59: ='מאזן בוחן Australia'!$M$64 -> 121809.95 | E59: ='מאזן בוחן EUROPE'!$M$212 -> 377994.78
A61: Open balance | C61: 0
A62: Capitalization up to Dec 31, 2018 - Short Term | C62: =+'[69]Final '!$P$112 -> 607841.21
A63: Capitalization up to Dec 31, 2018 - Long Term | C63: =+'[69]Final '!$Q$112 -> 981166.65
A64: Amortization Q1-2019 (for Capitalization up to Dec 31, 2018) | C64: =-'[69]Final '!$BG$7 -> -151960.3
A65: Amortization Q2-2019 (for Capitalization up to Dec 31, 2018) | C65: =-'[69]Final '!$BM$7 -> -151960.3
A66: Amortization Q3-2019 (for Capitalization up to Dec 31, 2018) | C66: =-'[69]Final '!$BS$7 -> -151960.3
A67: Amortization Q4-2019 (for Capitalization up to Dec 31, 2018) | C67: =-'[69]Final '!$BG$7 -> -151960.3
A68: Amortization Q1-2020 (for Capitalization up to Dec 31, 2018) | C68: =-'[69]Final '!$CE$7 -> -151960.3
A69: Amortization Q2-2020 (for Capitalization up to Dec 31, 2018) | C69: =-'[69]Final '!$CK$7 -> -139273.22
A70: Amortization Q3-2020 (for Capitalization up to Dec 31, 2018) | C70: =-'[53]Final '!$CQ$7 -> -126586.15
A71: Amortization Q4-2020 (for Capitalization up to Dec 31, 2018) | C71: =-'[53]Final '!$CW$7 -> -113899.07
A72: Amortization Q1-2021 (for Capitalization up to Dec 31, 2018) | C72: =-'[53]Final '!$AO$7 -> -101211.99
A73: Amortization Q2-2021 (for Capitalization up to Dec 31, 2018) | C73: =-'[53]Final '!$AP$7 -> -88326.568
A74: Amortization Q3-2021 (for Capitalization up to Dec 31, 2018) | C74: =-'[53]Final '!$AQ$7 -> -75441.146
A75: Amortization Q4-2021 (for Capitalization up to Dec 31, 2018) | C75: =-'[53]Final '!$AR$7 -> -62555.724
A77: Capitalization Q1 2019 commissions | C77: =+[70]ALL!$C$33 -> 214076.19
A78: Amortization Q2-2019 (for Capitalization Q1 2019) | C78: =-[71]ALL!$K$33 -> -18179.416
A79: Amortization Q3-2019 (for Capitalization Q1 2019) | C79: =-[72]ALL!$L$33 -> -18088.838
A80: Amortization Q4-2019 (for Capitalization Q1 2019) | C80: -17935.644
A81: Amortization Q1-2020 (for Capitalization Q1 2019) | C81: -17667.946
A82: Amortization Q2-2020 (for Capitalization Q1 2019) | C82: -15562.519
A83: Amortization Q3-2020 (for Capitalization Q1 2019) | C83: =-[54]ALL!$S$33 -> -15562.519
A84: Amortization Q4-2020 (for Capitalization Q1 2019) | C84: =-[54]ALL!$T$33 -> -15562.519
A85: Amortization Q1-2021 (for Capitalization Q1 2019) | C85: =-[54]ALL!$X$33 -> -15562.519
A86: Amortization Q2-2021 (for Capitalization Q1 2019) | C86: =-[54]ALL!$Y$33 -> -13128.374
A87: Amortization Q3-2021 (for Capitalization Q1 2019) | C87: =-[54]ALL!$Z$33 -> -13128.374
A88: Amortization Q4-2021 (for Capitalization Q1 2019) | C88: =-[54]ALL!$AA$33 -> -13128.374
A90: Capitalization Q2 2019 commissions | C90: =[73]ALL!$D$33 -> 182639.23
A91: Amortization Q3-2019 (for Capitalization Q2 2019) | C91: =-[73]ALL!$L$33 -> -15206.258
A92: Amortization Q4-2019 (for Capitalization Q2 2019) | C92: -15006.217
A93: Amortization Q1-2020 (for Capitalization Q2 2019) | C93: -14997.396
A94: Amortization Q2-2020 (for Capitalization Q2 2019) | C94: -14993.357
A95: Amortization Q3-2020 (for Capitalization Q2 2019) | C95: -11476.925
A96: Amortization Q4-2020 (for Capitalization Q2 2019) | C96: -11476.925
A97: Amortization Q1-2021 (for Capitalization Q2 2019) | C97: -11476.925
A98: Amortization Q2-2021 (for Capitalization Q2 2019) | C98: -11476.925
A99: Amortization Q3-2021 (for Capitalization Q2 2019) | C99: =-[55]ALL!$Z$33 -> -11476.925
A100: Amortization Q4-2021 (for Capitalization Q2 2019) | C100: =-[55]ALL!$AA$33 -> -11476.925
A102: Capitalization Q3 2019 commissions | C102: =SUM([74]ALL!$E$33) -> 224681.82
A103: Amortization Q4-2019 (for Capitalization Q3 2019) | C103: -21713.882
A104: Amortization Q1-2020 (for Capitalization Q3 2019) | C104: -22224.548
A105: Amortization Q2-2020 (for Capitalization Q3 2019) | C105: -21881.773
A106: Amortization Q3-2020 (for Capitalization Q3 2019) | C106: =-[56]ALL!$S$33 -> -22706.027
A107: Amortization Q4-2020 (for Capitalization Q3 2019) | C107: =-[56]ALL!$T$33 -> -14539.519
A108: Amortization Q1-2021 (for Capitalization Q3 2019) | C108: =-[56]ALL!$X$33 -> -14511.248
A109: Amortization Q2-2021 (for Capitalization Q3 2019) | C109: =-[56]ALL!$Y$33 -> -14504.708
A110: Amortization Q3-2021 (for Capitalization Q3 2019) | C110: =-[56]ALL!$Z$33 -> -14504.708
A111: Amortization Q4-2021 (for Capitalization Q3 2019) | C111: =-[56]ALL!$AA$33 -> -14405.184
A113: Capitalization Q4 2019 commissions | C113: 680643.42
A114: Amortization Q1-2020 (for Capitalization Q4 2019) | C114: -62062.347
A115: Amortization Q2-2020 (for Capitalization Q4 2019) | C115: -62006.83
A116: Amortization Q3-2020 (for Capitalization Q4 2019) | C116: =-[57]ALL!$S$33 -> -59256.516
A117: Amortization Q4-2020 (for Capitalization Q4 2019) | C117: =-[57]ALL!$T$33 -> -59244.736
...

Sheet ביאורים לדוחות הכספיים
A2: FAS123 Check
A4: INC | B4: =SUM('New TB INC'!J445) -> -11488368
A5: UK | B5: =SUM('מאזן בוחן EUROPE'!K303,'מאזן בוחן EUROPE'!K305) -> -354154.95
B6: =SUM(B4:B5) -> -11842523
A8: ALTSHULER | B8: =SUM('[90]Expense Amortization'!$X$1190) -> 11837803
A9: NON SIGNIFICANT | B9: =SUM(B6:B8) -> -4720.39
A11: תנועה בקרן הון בארצות הברית
A12: Opening Balance | B12: -9290163.5
A13: Q1 | B13: -619693
A14: Q2 | B14: -511584
A15: Q3 | B15: -533569
A16: Q4 | B16: =-SUM('[91]Department & Entity'!$H$19)+'[91]Department & Entity'!$C$19 -> -533357.86
A17: Closing Balance | B17: =SUM(B12:B16) -> -11488367
B18: =-'New TB INC'!J445+B17 -> 0.59
A19: תנועה בקרן הון באירופה
A20: Opening Balance | B20: -156149
A21: Q1 | B21: -11611.039
A22: Q2 | B22: -11441.95
A23: Q3 | B23: -9406.68
A24: Q4 | B24: =-'[92]99911'!$D$16 -> -12752.05
A25: RECLASS TO A.E. | B25: =-'[92]99911'!$D$17 -> 93551.54
B26: =SUM(B20:B25) -> -107809.18
B27: ='מאזן בוחן EUROPE'!J303-'ביאורים לדוחות הכספיים'!B26 -> 0.56949265
A29: Social security UK | B29: Provision for commissions | C29: UK | D29: Germany | E29: Netherlands | F29: Sweden | G29: Denmark | H29: Switzerland - C. Graf/Payrollplus issues payslip for him | I29: Subcontractor | J29: Total
A30: one time bonus | B30: ='[93]One-Time Bonus '!$C$21*0.73993005162856 -> 12318.126 | C30: ='[93]One-Time Bonus '!$C$46*0.73993005162856 -> 8095.3083 | D30: ='[93]One-Time Bonus '!$C$34*0.73993005162856 -> 4222.8178 | E30: 0 | F30: 0 | G30: 0 | H30: 0 | I30: 0 | J30: =I30+H30+G30+F30+E30+D30+C30-B30 -> 0
C31: =SUM(C30:C30) -> 8095.3083 | D31: =SUM(D30:D30) -> 4222.8178 | E31: =SUM(E30:E30) -> 0 | F31: =SUM(F30:F30) -> 0 | G31: =SUM(G30:G30) -> 0 | I31: =SUM(I30:I30) -> 0
A32: Employer contribution | C32: 0.11 | D32: 0 | E32: 0 | F32: 0.3142 | G32: 0 | H32: 0.2 | I32: 0
A33: Social security | C33: =C31*C32 -> 890.48392 | D33: =D31*D32 -> 0 | E33: =E31*E32 -> 0 | F33: =F31*F32 -> 0 | G33: =G31*G32 -> 0 | I33: =I31*I32 -> 0 | J33: =SUM(C33:I33) -> 890.48392
A35: Social security Ltd | B35: Provision for commissions | C35: Israel | D35: Singapore | E35: Subcontractors | F35: Total
A36: Commisions | B36: =[94]Main!$E$7+[94]Main!$E$16+[94]Main!$E$24 -> 115868.39 | C36: =[94]Main!$E$7 -> 9524.0832 | D36: =[94]Main!$E$16 -> 28945.27 | E36: =[94]Main!$E$24 -> 77399.038 | F36: =SUM($C$36:$E$36)-$B$36 -> 0
A37: Rate | C37: 0.05 | D37: Above SGD 6,000 fixed rate of 1,020 - 3 employees
C38: =$C$36*$C$37 -> 476.20416 | D38: =3*1020 -> 3060 | F38: =SUM(C38:E38) -> 3536.2042
A40: Social security guidance:
D41: לבדוק האם בונוסים לבלרוס, פולין ואוקראינה כוללים בחשבונית העמסה של סוציאליות - במידה ולא אין צורך להוסיף.
A42: Denmark:
A43: Employer contribution based on a fixed amount per year.
A45: USA:
A46: The employee tax rate up to an yearly salary of $142k is 6.2%, each USD above this amount will bear a 1.45% - Most of our employees base salary pass the $142k yearly therefore the emploee tax provision due commissions is immaterial.
K47: גרמניה
K48: מעל שכר של 7,100 יורו לא חלות עלויות מעביד.
K49: ברמות השכר אצל העובדים שלנו תוספת עלות מעביד כשיש תשלום עמלה בגרמניה תהיה מזערית, אם בכלל
K51: אוקראינה
K52: עובדים דרך ספק, אין סוציאליות ישירות, משלמים לספק סכום קבוע של 1,400 דולר בחודש בעד הסוציאליות.
K54: שבדיה
K55: בהתאם לבדיקה שנעשתה במאי, 2021 הסוצילאיות בשבדיה הן 31% מהשכר ברוטו כולל תוספות (עמלות, בונוסים וכו').
K57: הולנד
K58: בהתאם לבדיקה שנעשתה במאי, 2021 הסוצילאיות בשבדיה הן 4% מהשכר ברוטו כולל תוספות (עמלות, בונוסים וכו').
A61: MBO
A63: LTD | B63: ='Accrued expenses'!$O$60/'מאזן בוחן'!$N$2 -> 993509.07
A64: INC | B64: ='Accrued expenses'!$O$132 -> 361328.25
A65: FRA | B65: ='Accrued expenses'!$O$91/'מאזן בוחן צרפת'!$O$2 -> 37696.559
A66: UK | B66: ='Accrued expenses'!$O$155/'מאזן בוחן EUROPE'!$N$2 -> 76806.885
A67: IND | B67: ='Accrued expenses'!$O$221/'מאזן בוחן הודו'!$O$2 -> 24339.002
A68: AU | B68: ='Accrued expenses'!$O$192/'מאזן בוחן Australia'!$O$2 -> 31447.791
B69: =SUM(B63:B68) -> 1525127.6
A71: MBO FILE | B71: =SUM([95]Sheet1!$H$22-[95]Sheet1!$E$22)+[96]Sheet1!$B$24 -> 1525536.6
B72: =B71-B69 -> 409 | C72: עקב הפרשי שער
A74: Income
A76: Component | B76: USD | C76: %
A77: Perpetual - Product | B77: =-SUM('מאזן בוחן EUROPE'!$K$342:$K$343,'מאזן בוחן'!$K$556,'מאזן בוחן'!$K$530:$K$531,'מאזן בוחן EUROPE'!$K$314:$K$315,'מאזן בוחן Australia'!$K$156:$K$157,'מאזן בוחן Australia'!$K$178,'New TB INC'!$J$457:$J$458,'מאזן בוחן צרפת'!$K$182) -> 15420087 | C77: =B77/$B$85 -> 0.20999439
A78: Appliance - Product | B78: =-SUM('מאזן בוחן EUROPE'!$K$317:$K$318,'מאזן בוחן Australia'!$K$159,'New TB INC'!$J$460:$J$462,'מאזן בוחן צרפת'!K184,'מאזן בוחן'!$K$533:$K$534) -> 1640770 | C78: =B78/$B$85 -> 0.022344393
A79: Perpetual - Support | B79: =-SUM('מאזן בוחן צרפת'!$K$186:$K$188,'New TB INC'!$J$464:$J$466,'מאזן בוחן Australia'!$K$163:$K$165,'מאזן בוחן EUROPE'!$K$324:$K$326,'מאזן בוחן'!$K$536:$K$538) -> 28542152 | C79: =B79/$B$85 -> 0.38869377
A80: Appliance - Support | B80: =-SUM('New TB INC'!$J$468:$J$470,'מאזן בוחן Australia'!$K$161,'מאזן בוחן EUROPE'!$K$320:$K$322,'מאזן בוחן'!$K$546:$K$548) -> 1196200.2 | C80: =B80/$B$85 -> 0.016290137
A81: Training | B81: =-SUM('מאזן בוחן צרפת'!K193,'New TB INC'!$J$472:$J$473,'מאזן בוחן Australia'!$K$176:$K$177,'מאזן בוחן EUROPE'!$K$328:$K$329,'מאזן בוחן'!$K$550:$K$551) -> 517780.83 | C81: =B81/$B$85 -> 0.0070512617
A82: PS | B82: =-SUM('מאזן בוחן צרפת'!$K$196,'New TB INC'!$J$475:$J$476,'מאזן בוחן Australia'!$K$167:$K$168,'מאזן בוחן EUROPE'!$K$331:$K$333,'מאזן בוחן'!$K$553:$K$554) -> 4632737.3 | C82: =B82/$B$85 -> 0.063089711
A83: Subscription | B83: =-SUM('מאזן בוחן'!$K$540:$K$544,'מאזן בוחן צרפת'!$K$190:$K$191,'New TB INC'!$J$478:$J$482,'מאזן בוחן Australia'!$K$170:$K$174,'מאזן בוחן EUROPE'!$K$335:$K$340) -> 21481221 | C83: =B83/$B$85 -> 0.29253634
A84: Other | C84: =B84/$B$85 -> 0
B85: =SUM(B77:B84) -> 73430948
B86: =B85-Consolidation!N64 -> 0
A90: Bank management fees due line of credit 2021 - | C90: ='מאזן בוחן'!K1003 -> 57200
A93: Deferrrd Revenue:
A95: Inc
A97: Appliance
A98: US215000637 | B98: 117996.75 | C98: Delivered in January.
A99: US215000574 | B99: 133729.8 | C99: Delivered in January.
A100: US215000564 | B100: 42967.5 | C100: Delivered in January.
A101: US215000564 | B101: 214837.5 | C101: Delivered in January.
B102: =SUM(B98:B101) -> 509531.55
A104: Ltd
A106: Appliance
A107: IL218000293 | B107: 55605 | C107: Delivered in January.
A108: IL218000241 | B108: 60660 | C108: Delivered in January.
B109: =SUM(B107:B108) -> 116265
A110: Australia
A112: Appliance
A115: Europe
A116: UK218000428 | B116: 16513 | C116: Delivered in January.
B119: =B116+B109+B102 -> 642309.55
A121: Inc
A122: Product
A123: US215000647 | B123: 147000 | C123: Delivered in January.
B125: =SUM(B123:B124) -> 147000
A129: Rent expense:
C130: Q1.2021 | D130: Q2.2021 | E130: Q3.2021 | F130: Q4.2021
A131: Ltd | B131: 8030001 | C131: 112861.93 | D131: 255784.22 | E131: 405012.58 | F131: =VLOOKUP(B131,'מאזן בוחן'!$C:$K,9,0) -> 557731.58
A132: Inc | B132: 8030001 | C132: 38380.88 | D132: 77121.5 | E132: 108252.41 | F132: =VLOOKUP(B132,'New TB INC'!$C:$J,8,0) -> 148030.57
A133: India | B133: 8030001 | C133: 16149.77 | D133: 32251.25 | E133: 48265.24 | F133: =VLOOKUP(B133,'מאזן בוחן הודו'!$C:$M,9,0) -> 64099.48
C134: 167392.58 | D134: 365156.97 | E134: 561530.23 | F134: =SUM(F131:F133) -> 769861.63
D135: 197764.39 | E135: 196373.26 | F135: =F134-E134 -> 208331.4
A137: Other account receivable: | B137: =Consolidation!C4 -> Algosec System Ltd | C137: =Consolidation!D4 -> Algosec Inc | D137: =Consolidation!E4 -> Algosec Europe | E137: =Consolidation!F4 -> Algosec Australia | F137: =Consolidation!G4 -> Algosec India | G137: =Consolidation!H4 -> Algosec France | H137: total
...

Sheet יתרות בינחברתיות
A2: Related Parties Reconsilation :
A4: BS | C4: usd | D4: GBP | E4: AUD | F4: EUR | G4: INR
A5: LTD
A6: 1130001 | B6: Algosec Inc | C6: ='מאזן בוחן'!K501 -> -5158528.6
A7: 1130002 | B7: Algosec Europe | C7: ='מאזן בוחן'!K502 -> 5177719.8 | D7: =C7*'נתונים לשינוי'!C22/'נתונים לשינוי'!C20 -> 3831150.5
A8: 1130004 | B8: Algosec INC- CREDIT CARD CHARGES | C8: ='מאזן בוחן'!K503 -> 0
A9: 1130005 | B9: אלגוסק אוסטרליה | C9: ='מאזן בוחן'!K504 -> 6775705.6 | E9: =C9*'מאזן בוחן Australia'!O2 -> 9324915.7
A10: 1130009 | B10: Algosec India | C10: ='מאזן בוחן'!K497 -> 0 | G10: =C10*'מאזן בוחן הודו'!$O$2 -> 0
A12: INC
A13: 1130001 | B13: Intercompany LTD Account | C13: ='New TB INC'!J271 -> 5158528.6
A14: 1130003 | B14: Intercompany Europe | C14: ='New TB INC'!J272 -> 0
A15: 1130004 | B15: Algosec INC- CREDIT CARD CHARGES | C15: ='New TB INC'!J432 -> 0
A16: New4 | B16: Algosec Australia | C16: =+'New TB INC'!J275 -> 14383.75
A17: 1130012 | B17: Algosec India | C17: =+'New TB INC'!J273 -> 40926.91 | G17: =C17*'נתונים לשינוי'!$B$17 -> 3040971.7
A19: EUR
A20: 1130002 | B20: Algosec Israel | C20: ='מאזן בוחן EUROPE'!K171 -> -5177719.8 | D20: ='מאזן בוחן EUROPE'!J171 -> -3831150.5
A21: 1130003 | B21: Algosec INC | C21: ='מאזן בוחן EUROPE'!K172 -> 0
A22: 1130007 | B22: אלגוסק אוסטרליה | C22: ='מאזן בוחן EUROPE'!K177 -> 0 | E22: =C22*'נתונים לשינוי'!C22/'נתונים לשינוי'!C23 -> 0
B23: Algosec France | C23: ='מאזן בוחן צרפת'!K164 -> 0 | F23: =C23*'מאזן בוחן צרפת'!$O$2 -> 0
A25: Australia
A26: 1130007 | B26: אלגוסק אנגליה | C26: 0 | E26: 0
A27: 1130005 | B27: אלגוסק ישראל | C27: ='מאזן בוחן Australia'!K44 -> -6775705.6 | E27: ='מאזן בוחן Australia'!J44 -> -9324921.8
A28: 1130003 | B28: Algosec INC | C28: =+'מאזן בוחן Australia'!K116 -> -14384.38
A30: France
A31: 1130010 | B31: Algosec Europe | C31: ='מאזן בוחן EUROPE'!K173 -> 0 | F31: =C31*'מאזן בוחן צרפת'!$O$2 -> 0
A33: India
B34: Algosec Israel | C34: ='מאזן בוחן הודו'!K47 -> 0 | G34: ='מאזן בוחן הודו'!J47 -> 0
A35: 1130012 | B35: Algosec Inc | C35: ='מאזן בוחן הודו'!K159 -> -40926.87 | G35: ='מאזן בוחן הודו'!J159 -> -3040968.8
D40: usd check | F40: main currency check
D41: =C6+C13 -> 0.05 | F41: =E6+E13 -> 0
D42: =C14+C21 -> 0 | F42: =E14+E21 -> 0
D43: =C15+C8 -> 0 | F43: =E15+E8 -> 0
D44: =C7+C20 -> 0 | F44: =D20+D7 -> 0.0037308177
D45: =C22+C26 -> 0 | F45: =E26+E22 -> 0
D46: =C9+C27 -> 0 | F46: =E9+E27 -> -6.1153801
D47: =C31+C23 -> 0 | F47: =F31+F23 -> 0
D48: =C34+C10+C35+C17 -> 0.04 | F48: =G34+G10+G35+G17 -> 2.9721
D49: =+C28+C16 -> -0.63 | F49: =+E28+E16 -> 0
A50: Income IC | D50: =SUM(D41:D49) -> -0.54 | F50: =SUM(F41:F49) -> -3.1395493
A52: India
A53: 80094 | B53: Cost+ income | C53: ='מאזן בוחן הודו'!K175 -> -2876820.1
A55: LTD
A56: ="80090" -> 80090 | B56: IC Inc | C56: ='מאזן בוחן'!K559 -> -16359278
A57: ="80091" -> 80091 | B57: IC UK | C57: ='מאזן בוחן'!K560 -> -20438093
A58: 80093 | B58: IC AJE | C58: =+'מאזן בוחן'!K562 -> 11491701
A59: ='מאזן בוחן'!C561 -> 80092 | B59: IC AUD | C59: ='מאזן בוחן'!K561 -> -7526271.3
F61: בדיקת איזון רווח והפסד בינחברתי:
A62: COGS IC | F62: =C56+C71+C73 -> 1921915.4
F63: =C53 -> -2876820.1
A64: EUR | F64: =C57+C65+C58 -> 4924445.4
A65: 5900001 | B65: Cogs Ltd | C65: ='מאזן בוחן EUROPE'!K368 -> 13870838 | F65: =C59+C69+C67 -> -3969539.9
A66: France | F66: =SUM(F62:F65) -> 0.7930455
A67: 5900001 | B67: Cogs Ltd | C67: =VLOOKUP(A67,'מאזן בוחן צרפת'!$C:$M,9) -> 899576.43
A68: Australia
A69: 5900001 | B69: Cogs Ltd | C69: ='מאזן בוחן Australia'!K192 -> 2657155
A70: INC
A71: ="5900001" -> 5900001 | B71: Cogs Ltd | C71: ='New TB INC'!J578 -> 15404372
A72: Ltd
A73: 5900001 | B73: Cogs India | C73: ='מאזן בוחן'!K706 -> 2876821.8

Sheet Accrued expenses
A13: Algosec Israel
A15: 2200001 | B15: ='מאזן בוחן'!D456 -> הוצאות לשלם
D16: ILS
D17: 44166 | E17: 44197 | F17: 44228 | G17: 44256 | H17: 44287 | I17: 44317 | J17: 44348 | K17: 44378 | L17: 44409 | M17: 44440 | N17: 44470 | O17: 44501 | P17: 44531 | S17: 2021
A18: 8410068 | B18: ביקורת2021 | C18: דוח מס $8k, דוח שנתי $17, שלוש סקירות $18k. | D18: 0 | E18: =(5+18+17)/12*3.291*1000 -> 10970 | F18: =E18+11*1000 -> 21970 | G18: =F18+11*1000-1140 -> 31830 | H18: =G18+10970+3247 -> 46047 | I18: =H18+10970+814 -> 57831 | J18: =I18+10970+814 -> 69615 | K18: =J18+10970+814 -> 81399 | L18: =K18+10970+814 -> 93183 | M18: =L18+10970+814-6000*'מאזן בוחן'!$N$2-180 -> 86127 | N18: =85839+10970+815 -> 97624 | O18: =N18+10970+815 -> 109409 | P18: 77750 | S18: =8000/12*12*3.11 -> 24880 | T18: דוח מס
A19: 8410068 | B19: ביקורת 2020 | C19: דוח מס | D19: 97142 | E19: 97142 | F19: =E19 -> 97142 | G19: =F19-6000*'נתונים לשינוי'!$C$22 -> 78482 | H19: =G19 -> 78482 | I19: =H19 -> 78482 | J19: =I19 -> 78482 | K19: =J19 -> 78482 | L19: =5000*'מאזן בוחן'!$N$2 -> 15550 | M19: =L19 -> 15550 | N19: 15790 | O19: 15790 | P19: 0 | S19: =17000/12*12*3.11 -> 52870 | T19: דוח שנתי
A20: 6020008 | B20: זיו האפט | D20: 31247 | E20: 0 | F20: 0 | G20: =F20 -> 0 | H20: 21950 | I20: 0 | M20: 45690 | N20: 0 | O20: 0 | P20: 0 | R20: שולם | S20: 0 | T20: רבעון 1
A21: 8410068 | B21: EY | C21: דוח מדען | D21: 10931 | E21: 0 | F21: 0 | G21: =F21 -> 0 | I21: =H21 -> 0 | M21: 0 | N21: 0 | O21: 0 | P21: 0 | R21: שולם | S21: 0 | T21: רבעון 2
A22: 8410068 | B22: אלטשולר שחם בנפיטס Q.2020-Q2.2021 | C22: הערכת שווי אופציות | D22: 7957.13 | E22: 7957.13 | F22: =E22 -> 7957.13 | G22: 0 | I22: =H22 -> 0 | M22: 0 | N22: 0 | O22: 0 | P22: 0 | R22: שולם | T22: רבעון 3
B23: הפרשה לכ.אשראי | D23: 35313 | E23: 40289 | F23: 70051 | G23: 84046 | H23: 123886 | I23: 158411 | J23: 117013 | K23: 153350 | L23: 141069 | M23: 136368 | N23: 141146 | O23: 111656 | P23: 180587 | S23: =SUM(S18:S22) -> 77750
A24: 8020013 | B24: mivtah saimon | D24: 8500 | E24: 8500 | F24: =E24 -> 8500 | G24: =F24 -> 8500 | H24: =G24 -> 8500 | I24: =H24 -> 8500 | J24: =I24 -> 8500 | K24: =J24 -> 8500 | L24: =K24 -> 8500 | M24: =L24 -> 8500 | N24: 8500 | O24: 8500 | P24: 8500 | S24: =P18 -> 77750
A25: 6020008 | B25: אולקלאוד | D25: 28000 | E25: =28000+D25 -> 56000 | F25: 0 | G25: =F25 -> 0 | H25: 24578 | M25: 0 | N25: 0 | O25: 0 | P25: 0 | S25: =S23-S24 -> 0
A26: 6010008 | B26: שרותי פיתוח מטריקס | D26: 0 | E26: 148148.49 | F26: 151161.86 | G26: 151355.21 | H26: 181985.61 | I26: 188666.35 | J26: 209436.6 | K26: 140387.58 | L26: 96576.17 | M26: 97724.55 | N26: 29423.23 | O26: 26850.25 | P26: 0
A27: 5420007 | B27: cloudshare | D27: 23668.83 | E27: 0 | F27: 0 | G27: =F27 -> 0 | I27: =H27 -> 0 | M27: 0 | N27: 0 | O27: 0 | P27: 0
A28: 6020014 | B28: אול קלאוד AWS | E28: =85360 -> 85360 | F28: 0 | G28: =F28 -> 0 | H28: 264837 | M28: 0 | N28: 333722 | O28: 359016.64 | P28: 0
A29: 8030020 | B29: Depriciation | D29: 0 | E29: 230000 | F29: =E29+230000 -> 460000 | G29: 0 | H29: 200000 | I29: 400000 | K29: 200000 | L29: =K29+200000 -> 400000 | M29: 200000 | N29: 200000 | O29: 400000 | P29: 0
A30: 8030009 | B30: נקיון | D30: 36594 | E30: 36594 | F30: 0 | G30: =F30 -> 0 | I30: =H30 -> 0 | M30: 0 | N30: 0 | P30: 0
A31: 7120042 | B31: יעוץ APAC | D31: 8287.52 | E31: 0 | F31: 0 | G31: =F31 -> 0 | I31: =H31 -> 0 | M31: 0 | N31: 0 | O31: 0 | P31: 0
A32: 7020026 | B32: Facebook | O32: 51221.24 | P32: 0
A33: 7020026 | B33: קודרס קלאן | D33: 23625 | E33: 0 | F33: 34144.8 | G33: 0 | I33: =H33 -> 0 | M33: 0 | N33: 14211 | P33: =40437+24880 -> 65317
A34: 8410048 | B34: רשיונות תוכנה הנה"כ | C34: בזק בינלאומי | F34: 45260.43 | G34: 0 | I34: =H34 -> 0 | M34: 0 | N34: 0 | O34: 0 | P34: 0
A35: 8220010 | B35: רופטופ פרטנרס | H35: 6125 | M35: 0 | N35: 0 | O35: 0 | P35: 0
A36: 8220010 | B36: אש מהירה | H36: 2200 | M36: 0 | N36: 0 | O36: 0 | P36: 0
A37: 8030012 | B37: אגם שיווק 4/21 | H37: 5000 | M37: 0 | N37: 0 | O37: 0 | P37: 0
A38: 7020038 | B38: הפרשה- איי טי סנטרל | J38: 4970 | K38: =J38+4970 -> 9940 | L38: =K38+4970 -> 14910 | M38: =L38+4970 -> 19880 | N38: =19880+4970 -> 24850 | O38: =4970+24850 -> 29820 | P38: =4970+29820 -> 34790
A39: 6010007 | B39: השמת עובדים -מו"פ | C39: גוטפרנדס | D39: 30392 | E39: 0 | F39: 0 | G39: =F39 -> 0 | I39: =H39 -> 0 | K39: 41500 | L39: =K39 -> 41500 | M39: 28000 | N39: 0 | O39: 0 | P39: 45000
A40: 6010022 | B40: שירותי פיתוח בבלרוס Belisoft International | J40: 712360 | K40: =J40 -> 712360 | L40: =K40 -> 712360 | M40: =L40 -> 712360 | N40: 712360 | O40: 712360 | P40: 712360
A41: 6020014 | B41: אוטומט איט | C41: אוטומט איט | M41: =8595+49111 -> 57706 | N41: =49111+135794 -> 184905 | O41: =15119+184905+12946 -> 212970 | P41: 0
A42: 6020008 | B42: יעוץ ויועצים פיתוח | C42: אברא | M42: 45650 | N42: 0 | O42: 0 | P42: 0
A43: 6020014 | B43: רשיונות ושירותי ענן - פיתוח | C43: שטרן IT | M43: 21000 | P43: 0
A44: 6020014 | B44: ניוווי | O44: 40177 | P44: 0
A45: 6120006 | B45: דובל | K45: 14180 | L45: 0 | M45: 0 | N45: 0 | O45: 29050 | P45: 0
A46: 7020038 | B46: Marketing Demand Generation | M46: 0 | N46: 72634 | O46: 80000 | P46: 0
A47: 5800001 | B47: פדקס | O47: 0 | P47: 0
A48: 5110007 | B48: מתודה | K48: 22227 | L48: =K48 -> 22227 | M48: =L48 -> 22227 | N48: 0 | O48: 0 | P48: 0
A49: 6010007 | B49: השמת עובדים -מו"פ | M49: 9638 | N49: 0 | O49: 26500 | P49: 26500
A50: 6010007 | B50: פעילויות צוות /חברה | C50: ליאור סושארד | M50: 35100 | N50: 0 | O50: 0 | P50: 21000
A51: 8410048 | B51: בזק | L51: 46544.87 | M51: =L51+46544.87 -> 93089.74 | N51: =93089.74+46544.87 -> 139634.61 | O51: =139634.61-46544.87*3 -> 0 | P51: 0
A52: 8030002 | B52: חשמל | D52: 27000 | E52: 27000 | F52: =E52 -> 27000 | G52: =F52 -> 27000 | H52: =G52 -> 27000 | I52: =H52 -> 27000 | J52: =I52 -> 27000 | K52: =J52 -> 27000 | L52: =K52 -> 27000 | M52: =L52 -> 27000 | N52: 27000 | O52: 27000 | P52: 27000
D53: =SUM(D18:D52) -> 368657.48 | E53: =SUM(E18:E52) -> 747960.62 | F53: =SUM(F18:F52) -> 923187.22 | G53: =SUM(G18:G52) -> 381213.21 | H53: =SUM(H18:H52) -> 990590.61 | I53: =SUM(I18:I52) -> 918890.35 | J53: =SUM(J18:J52) -> 1227376.6 | K53: =SUM(K18:K52) -> 1489325.6 | ... P53: =SUM(P18:P52) -> 1198804
P54: ='מאזן בוחן'!$J$456+P53 -> 0
A57: ='מאזן בוחן'!C471 -> 2400001 | B57: ='מאזן בוחן'!D471 -> הוצאות לשלם עובדים | C57: ILS
C58: 44166 | D58: 44197 | E58: 44228 | F58: 44256 | G58: 44287 | H58: 44317 | I58: 44348 | J58: 44378 | K58: 44409 | L58: 44440 | M58: 44470 | N58: 44501 | O58: 44531
B59: MBO 2020 | C59: 3368348.5 | D59: =C59 -> 3368348.5 | E59: 0 | F59: 0 | G59: 0 | L59: 0 | M59: 0 | N59: 0 | O59: 0
B60: MBO 2021 | D60: 287000 | E60: =D60+287000 -> 574000 | F60: 945422.38 | G60: =F60+306349.04 -> 1251771.4 | H60: =G60+306349.04 -> 1558120.5 | I60: =H60+306349.04 -> 1864469.5 | J60: =I60+306349.04 -> 2170818.5 | K60: =J60+306349.04 -> 2477167.6 | L60: =K60+306349.04 -> 2783516.6 | M60: =L60+306349.04 -> 3089865.7 | N60: =M60+306349.04 -> 3396214.7 | O60: =[43]Sheet1!$G$22*'מאזן בוחן'!$N$2 -> 3089813.2
B61: One time Bonus socials | O61: 0 | Q61: לא מהותי - 7,105 דולר
B62: Commissions 2021 | F62: =[98]Ltd!$D$12*'נתונים לשינוי'!$C$22 -> 459437.29 | G62: 0 | I62: 201867.73 | J62: 0 | L62: 374139.03 | M62: 0 | N62: 0 | O62: =([99]Main!$G$8+[99]Main!$G$12+[99]Main!$G$17)*'מאזן בוחן'!$N$2 -> 691990.82
B63: Socials due commissions 2021 | F63: ='ביאורים לדוחות הכספיים'!F38*'נתונים לשינוי'!$C$22 -> 10997.595 | G63: 0 | I63: 11465.79 | J63: 0 | L63: 11418.4 | M63: 0 | N63: 0 | O63: =[99]Main!$O$23 -> 1632.36
B64: One time Bonus | C64: 174500 | D64: =C64 -> 174500 | E64: 0 | F64: 0 | G64: 0 | L64: 0 | M64: 0 | N64: 0 | O64: ='[93]One-Time Bonus '!$G$21*'מאזן בוחן'!$N$2 -> 1321529.5
B65: One time Bonus socials | N65: 0 | O65: ='[100]Israel one time bonus'!$I$27 -> 43538.333
B66: MBO אבישי | C66: 30101 | D66: 30101 | E66: 30101 | F66: 0 | G66: 0 | L66: 0 | M66: 0 | N66: 0 | O66: 0
B67: הפרשי שכר אבישי | C67: =82277-C66 -> 52176 | D67: =C67 -> 52176 | E67: 0 | F67: 0 | G67: 0 | L67: 0 | M67: 0 | N67: 0 | O67: 0
B68: Commission On-hold | C68: 615413.26 | D68: 94576 | E68: 94576 | F68: 0 | G68: 0 | L68: 0 | M68: 0 | N68: 0 | O68: =([99]Main!$G$34+[99]Main!$G$41)*'מאזן בוחן'!$N$2 -> 122116.05
C69: =SUM(C59:C68) -> 4240538.8 | D69: =SUM(D59:D68) -> 4006701.5 | E69: =SUM(E59:E68) -> 698677 | F69: =SUM(F59:F68) -> 1415857.3 | G69: =SUM(G59:G68) -> 1251771.4 | H69: =SUM(H59:H68) -> 1558120.5 | I69: =SUM(I59:I68) -> 2077803 | J69: =SUM(J59:J68) -> 2170818.5 | ... O69: =SUM(O59:O68) -> 5270620.3
O70: ='מאזן בוחן'!$J$471+O69 -> -219.2755
A75: Algosec France SAAS
A77: 2200001 | C77: EUR
B78: Accrued expenses | C78: 44166 | D78: 44197 | E78: 44228 | F78: 44256 | G78: 44287 | H78: 44317 | I78: 44348 | J78: 44378 | K78: 44409 | L78: 44440 | M78: 44470 | N78: 44501 | O78: 44531
B79: Audit 2020 - A. Legoux | C79: 2400 | D79: =C79 -> 2400 | E79: =D79 -> 2400 | F79: =E79 -> 2400 | G79: =F79 -> 2400 | H79: =G79 -> 2400 | I79: =H79 -> 2400 | J79: =I79 -> 2400 | K79: =J79-900 -> 1500 | L79: =K79 -> 1500 | M79: =L79 -> 1500 | N79: =M79 -> 1500 | O79: 0
B80: Audit 2021 - A. Legoux | D80: 300 | E80: =D80+300 -> 600 | F80: =E80+300 -> 900 | G80: =F80+300 -> 1200 | H80: =G80+300 -> 1500 | I80: =H80+300 -> 1800 | J80: =I80+300 -> 2100 | K80: =J80+300 -> 2400 | L80: =K80+300 -> 2700 | ... N80: =M80+300 -> 3300 | O80: 5725
B81: Bookkeeping - NLE | O81: 0
B82: Salary - NLE | O82: 0
C83: 2400 | D83: =SUM(D79:D82) -> 2700 | E83: =SUM(E79:E82) -> 3000 | F83: =SUM(F79:F82) -> 3300 | G83: =SUM(G79:G82) -> 3600 | H83: =SUM(H79:H82) -> 3900 | I83: =SUM(I79:I82) -> 4200 | J83: =SUM(J79:J82) -> 4500 | K83: =SUM(K79:K82) -> 3900 | ... O83: =SUM(O79:O82) -> 5725
O84: =+'מאזן בוחן צרפת'!$J$145+O83 -> 0
A86: 2400001 | B86: Accrued Exp Employee Related | C86: 44166 | D86: 44197 | E86: 44228 | F86: 44256 | G86: 44287 | H86: 44317 | I86: 44348 | J86: 44378 | K86: 44409 | L86: 44440 | M86: 44470 | N86: 44501 | O86: 44531
B87: Commision accrual - On hold | C87: 0 | D87: 0 | E87: 0 | G87: 0 | J87: 0 | K87: 0 | L87: 0 | M87: 0 | N87: 0 | O87: ='[101]YTD Comm. Report '!$Q$155 -> 7539.87
B88: Comm. On-hold social exp (~42%) | O88: ='[102] EMEA Summary data 21'!$I$52 -> 3166.7454
B89: GP Commission | O89: 0
B90: Vacation Bonus | I90: 7913.01 | J90: 0 | K90: 0 | L90: 0 | M90: 0 | N90: 0 | O90: 0
B91: MBO 2021 | F91: 12840 | G91: =F91 -> 12840 | H91: =G91 -> 12840 | I91: =H91*2 -> 25680 | J91: =I91 -> 25680 | K91: =J91 -> 25680 | L91: =K91/2*3 -> 38520 | M91: =L91 -> 38520 | N91: =M91 -> 38520 | O91: =([43]Sheet1!$F$31)*'מאזן בוחן צרפת'!$O$2 -> 33306.713
B92: MBO payable in March 2022 | O92: ='פ.נ. צרפת'!E103 -> 0
B93: Commission 2021 | F93: 45380.4 | G93: 0 | I93: 28446.05 | J93: 0 | K93: 0 | L93: ='[103] EMEA Summary data 21'!$J$10+'[103] EMEA Summary data 21'!$J$23 -> 33249.418 | M93: 0 | N93: 0 | O93: ='[102] EMEA Summary data 21'!$H$50 -> 113990.96
B94: Commision 2020 | C94: 68417 | D94: 0 | E94: 0 | G94: 0 | J94: 0 | K94: 0 | L94: 0 | M94: 0 | N94: 0 | O94: 0
B95: Social due commission correction | O95: -23130.672
B96: One time bonus | C96: 20000 | D96: =C96-15000 -> 5000 | E96: 0 | G96: 0 | J96: 0 | K96: 0 | L96: 0 | M96: 0 | N96: 0 | O96: ='[104]One-Time Bonus '!$D$21*'מאזן בוחן צרפת'!$O$2 -> 16135.845
B97: OT bonus social exp (~42%) | C97: 8363 | D97: 1934.93 | E97: 0 | G97: 0 | J97: 0 | K97: 0 | L97: 0 | M97: 0 | N97: 0 | O97: =O96*'פ.נ. צרפת'!$I$62 -> 6777.055
B98: Commissions social exp (~42%) | C98: 24353 | D98: 0 | E98: 0 | F98: 20807 | G98: 0 | I98: 12623.85 | J98: 0 | K98: 0 | L98: =('[103] EMEA Summary data 21'!$J$6+'[103] EMEA Summary data 21'!$J$10+'[103] EMEA Summary data 21'!$J$23)*0.42 -> 25496.095 | M98: 0 | N98: 0 | O98: ='[102] EMEA Summary data 21'!$I$50 -> 57489.344
B99: Delivery - MBO 2021 Upda | O99: 2450.15
B100: MBO social expenses (~42%) | C100: 16051 | D100: =C100-4275/9977*5000 -> 13908.572 | E100: 0 | G100: 0 | J100: 0 | K100: 0 | L100: 0 | M100: 0 | N100: 0 | O100: =([43]Sheet1!$F$31)*'פ.נ. צרפת'!I62*'מאזן בוחן צרפת'!$O$2 -> 13988.819
B101: MBO provision update | C101: 37586 | D101: =C101-5000 -> 32586 | E101: 0 | G101: 0 | J101: 0 | K101: 0 | L101: 0 | M101: 0 | N101: 0 | O101: 0
C102: =SUM(C87:C101) -> 174770 | D102: =SUM(D87:D101) -> 53429.502 | E102: =SUM(E101) -> 0 | F102: =SUM(F87:F101) -> 79027.4 | G102: =SUM(G87:G101) -> 12840 | H102: =SUM(H87:H101) -> 12840 | I102: =SUM(I87:I101) -> 74662.91 | J102: =SUM(J87:J101) -> 25680 | K102: =SUM(K87:K101) -> 25680 | L102: =SUM(L87:L101) -> 97265.513 | M102: =SUM(M87:M101) -> 38520 | ... O102: =SUM(O87:O101) -> 231714.83
O103: ='מאזן בוחן צרפת'!$J$140+O102 -> -4.440332
A105: ='New TB INC'!B2 -> Algosec Inc
A107: ='New TB INC'!C427 -> 2200001 | B107: ='New TB INC'!D427 -> Accrued expenses
C108: USD
C109: 44166 | D109: 44197 | E109: 44228 | F109: 44256 | G109: 44287 | H109: 44317 | I109: 44348 | J109: 44378 | K109: 44409 | L109: 44440 | M109: 44470 | N109: 44501 | O109: 44531
B110: 2021 USA TR fees | D110: 2000 | E110: =D110+2000 -> 4000 | F110: =E110+2000 -> 6000 | G110: =6000+2000 -> 8000 | H110: 10000 | I110: 12000 | J110: =I110-5088 -> 6912 | K110: =J110+2000 -> 8912 | L110: =K110 -> 8912 | M110: =L110+2000 -> 10912 | N110: =10912-5088-2564.67+2000 -> 5259.33 | O110: =5259.33+2000 -> 7259.33
B111: ON 24-AlgoSum 2020 exp | C111: 26606 | D111: 26606 | E111: 26606 | F111: 26606 | G111: 0 | H111: 0 | I111: 0 | J111: 0 | K111: 0 | M111: 0 | N111: 0 | O111: 0
B112: Spiff card | C112: 10000 | D112: =C112 -> 10000 | E112: 0 | F112: 0 | G112: 0 | H112: 0 | I112: 0 | J112: 0 | K112: 0 | M112: 0 | N112: 0 | O112: 0
B113: founders interest | C113: 0 | D113: 0 | E113: 0 | F113: 0 | G113: 0 | H113: 0 | I113: 0 | J113: 0 | K113: 0 | M113: 0 | N113: 0 | O113: 0
B114: ="USA TR fees 2020 -MTK" -> USA TR fees 2020 -MTK | C114: 22915 | D114: =C114 -> 22915 | E114: =D114 -> 22915 | F114: =E114-5088 -> 17827 | G114: =17827-5088 -> 12739 | H114: 12739 | I114: =H114 -> 12739 | J114: =I114 -> 12739 | K114: =J114 -> 12739 | L114: =K114 -> 12739 | M114: =L114 -> 12739 | N114: 12739 | O114: 12739
B115: 2018 GILTI amendment fee | C115: 6000 | D115: =C115 -> 6000 | E115: =D115 -> 6000 | F115: 3000 | G115: 3000 | H115: 3000 | I115: =H115 -> 3000 | J115: =I115 -> 3000 | K115: =J115 -> 3000 | L115: =K115 -> 3000 | M115: =L115 -> 3000 | N115: 3000 | O115: 3000
B116: Fuller Canada | C116: 2000 | D116: 2000 | E116: =D116 -> 2000 | F116: =E116 -> 2000 | G116: 2000 | H116: 2000 | I116: =H116 -> 2000 | J116: =I116*2 -> 4000 | K116: =J116 -> 4000 | L116: =K116 -> 4000 | M116: =L116 -> 4000 | N116: 4000 | O116: =3000+4000 -> 7000
C117: =SUM(C110:C116) -> 67521 | D117: =SUM(D110:D116) -> 69521 | E117: =SUM(E110:E116) -> 61521 | F117: =SUM(F110:F116) -> 55433 | G117: =SUM(G110:G116) -> 25739 | H117: =SUM(H110:H116) -> 27739 | I117: =SUM(I110:I116) -> 29739 | J117: =SUM(J110:J116) -> 26651 | ... O117: =SUM(O110:O116) -> 29998.33
O118: ='New TB INC'!$J$427+O117 -> -0.19
A120: ='New TB INC'!C349 -> 2400001 | B120: ='New TB INC'!D349 -> Accrued Exp Employee Related | C120: USD
C121: 44166 | D121: 44197 | E121: 44228 | F121: 44256 | G121: 44287 | H121: 44317 | I121: 44348 | J121: 44378 | K121: 44409 | L121: 44440 | M121: 44470 | N121: 44501 | O121: 44531
B122: GP Bonus | C122: 86400 | D122: =C122 -> 86400 | E122: 0 | F122: 0 | G122: 0 | H122: =G122 -> 0 | J122: 0 | K122: 0 | L122: 0 | M122: 0 | N122: 0 | O122: 0
B123: Commision prov- Lowes | C123: 609441.47 | D123: =C123 -> 609441.47 | E123: =D123 -> 609441.47 | F123: 609441.47 | G123: =F123 -> 609441.47 | H123: =G123 -> 609441.47 | I123: =H123 -> 609441.47 | J123: =I123 -> 609441.47 | K123: 0 | L123: 0 | M123: 0 | N123: 0 | O123: 0
B124: Commision prov Q3.2020 | C124: 30445 | D124: 30444 | E124: =21963+8481 -> 30444 | F124: 30444 | G124: 21963.46 | H124: =G124 -> 21963.46 | I124: =H124 -> 21963.46 | J124: =I124 -> 21963.46 | K124: =J124 -> 21963.46 | L124: =K124 -> 21963.46 | M124: =L124 -> 21963.46 | N124: =M124 -> 21963.46 | O124: =N124 -> 21963.46
...

Sheet FA
A1: רכוש קבוע
A3: LTD - NIS
B4: עלות | F4: פחנ"צ | J4: עלות מופחתת
B5: י.פ. | C5: תוספות | D5: גריעות | E5: י.ס. | F5: י.פ. | G5: תוספות | H5: גריעות | I5: י.ס.
A6: מחשבים פיתוח | B6: =10431367+368811 -> 10800178 | C6: =684264 -> 684264 | D6: 368811 | E6: =C6+B6-D6 -> 11115631 | F6: =8988229+368811 -> 9357040 | G6: 960142 | H6: 368811 | I6: =G6+F6-H6 -> 9948371 | J6: =E6-I6 -> 1167260 | K6: =-'מאזן בוחן'!J159+E6 -> -349.78
A7: שיפורים במושכר | B7: 1843756 | C7: 0 | D7: 0 | E7: =C7+B7-D7 -> 1843756 | F7: 1165244 | G7: 215159 | H7: 0 | I7: =G7+F7-H7 -> 1380403 | J7: =E7-I7 -> 463353 | K7: =E7-'מאזן בוחן'!J164 -> -0.79
A8: ריהוט משרדי | B8: =1310965+52977 -> 1363942 | C8: 12893 | D8: 52977 | E8: =C8+B8-D8 -> 1323858 | F8: =387198+10674 -> 397872 | G8: 79888 | H8: 11686 | I8: =G8+F8-H8 -> 466074 | J8: =E8-I8 -> 857784 | K8: =E8-'מאזן בוחן'!J162 -> -0.84
A9: ציוד אלקטרוני | B9: 776891 | C9: 0 | D9: 23588 | E9: =C9+B9-D9 -> 753303 | F9: 484143 | G9: 87357 | H9: 15782 | I9: =G9+F9-H9 -> 555718 | J9: =E9-I9 -> 197585 | K9: =E9-'מאזן בוחן'!J161 -> -712.49
A10: ציוד תערוכה | B10: 14336 | C10: 0 | D10: 0 | E10: =C10+B10-D10 -> 14336 | F10: 14158 | G10: 180 | H10: 0 | I10: =G10+F10-H10 -> 14338 | J10: =E10-I10 -> -2 | K10: =E10-'מאזן בוחן'!J163 -> -0.4
A11: מחשבים למעבדה | B11: 1693270 | C11: 626614 | D11: 0 | E11: =C11+B11-D11 -> 2319884 | F11: 854508 | G11: 539825 | H11: 0 | I11: =G11+F11-H11 -> 1394333 | J11: =E11-I11 -> 925551 | K11: =E11-'מאזן בוחן'!J160 -> 0.45
A12: ציוד אלקטרוני - עבודה מהבית | B12: 18566 | C12: 25036 | D12: 0 | E12: =C12+B12-D12 -> 43602 | F12: 282 | G12: 5287 | H12: 0 | I12: =G12+F12-H12 -> 5569 | J12: =E12-I12 -> 38033 | K12: =E12-'מאזן בוחן'!J165 -> 916.41
A13: ריהוט משרדי - עבודה מהבית | B13: 23065 | C13: 26890 | D13: 0 | E13: =C13+B13-D13 -> 49955 | F13: 106 | G13: 2478 | H13: 0 | I13: =G13+F13-H13 -> 2584 | J13: =E13-I13 -> 47371 | K13: =E13-'מאזן בוחן'!J166 -> 1.19
A14: VNT | B14: 4995289 | C14: 0 | D14: 0 | E14: =C14+B14-D14 -> 4995289 | F14: 1998116 | G14: 999058 | H14: 0 | I14: =G14+F14-H14 -> 2997174 | J14: =E14-I14 -> 1998115 | K14: =E14-'מאזן בוחן'!J167 -> 0
A15: סה"כ בטופס פחת | B15: 21529292 | C15: =SUM(C6:C14) -> 1375697 | D15: =SUM(D6:D14) -> 445376 | E15: =SUM(E6:E14) -> 22459614 | F15: 14271488 | G15: =SUM(G6:G14) -> 2889374 | H15: =SUM(H6:H14) -> 396279 | I15: =SUM(I6:I14) -> 16764564 | J15: =SUM(J6:J14) -> 5695050
A17: סה"כ בספרים | E17: ='מאזן בוחן'!J169 -> 22459760 | I17: ='מאזן בוחן'!J180 -> -16762946 | J17: =E17+I17 -> 5696814.2
A18: הפרש | E18: =E17-E15 -> 146.25 | I18: =I17+I15 -> 1618 | J18: =J17-J15 -> 1764.25 | K18: הפרשים נגררים משנים קודמות.
A20: LTD - USD
B21: עלות | F21: פחנ"צ | J21: עלות מופחתת
B22: י.פ. | C22: תוספות | D22: גריעות | E22: י.ס. | F22: י.פ. | G22: תוספות | H22: גריעות | I22: י.ס.
A23: מחשבים פיתוח | B23: 2986246 | C23: 210854 | D23: 103264 | E23: =C23+B23-D23 -> 3093836 | F23: 2574192 | G23: 274120 | H23: 103264 | I23: =G23+F23-H23 -> 2745048 | J23: =E23-I23 -> 348788 | K23: ='מאזן בוחן'!K159-FA!E23 -> 1233.88
A24: שיפורים במושכר | B24: 515279 | C24: 0 | D24: 0 | E24: =C24+B24-D24 -> 515279 | F24: 320843 | G24: 61614 | H24: 0 | I24: =G24+F24-H24 -> 382457 | J24: =E24-I24 -> 132822 | K24: ='מאזן בוחן'!K164-FA!E24 -> -107.29
A25: ריהוט משרדי | B25: 376314 | C25: 4005 | D25: 14910 | E25: =C25+B25-D25 -> 365409 | F25: 108146 | G25: 22037 | H25: 3254 | I25: =G25+F25-H25 -> 126929 | J25: =E25-I25 -> 238480 | K25: ='מאזן בוחן'!K162-FA!E25 -> 146.69
A26: ציוד אלקטרוני | B26: 215327 | C26: 0 | D26: 6227 | E26: =C26+B26-D26 -> 209100 | F26: 132783 | G26: 24440 | H26: 4165 | I26: =G26+F26-H26 -> 153058 | J26: =E26-I26 -> 56042 | K26: ='מאזן בוחן'!K161-FA!E26 -> 193.15
A27: ציוד תערוכה | B27: 3741 | C27: 0 | D27: 0 | E27: =C27+B27-D27 -> 3741 | F27: 3690 | G27: 50 | H27: 0 | I27: =G27+F27-H27 -> 3740 | J27: =E27-I27 -> 1 | K27: ='מאזן בוחן'!K163-FA!E27 -> 0.56
A28: מחשבים למעבדה | B28: 479041 | C28: 193199 | D28: 0 | E28: =C28+B28-D28 -> 672240 | F28: 239572 | G28: 154415 | H28: 0 | I28: =G28+F28-H28 -> 393987 | J28: =E28-I28 -> 278253 | K28: ='מאזן בוחן'!K160-FA!E28 -> -936.99
A29: ציוד אלקטרוני - עבודה מהבית | B29: 5574 | C29: 7715 | D29: 0 | E29: =C29+B29-D29 -> 13289 | F29: 84 | G29: 1607 | H29: 0 | I29: =G29+F29-H29 -> 1691 | J29: =E29-I29 -> 11598 | K29: ='מאזן בוחן'!K165-FA!E29 -> -383.97
A30: ריהוט משרדי - עבודה מהבית | B30: 6982 | C30: 8300 | D30: 0 | E30: =C30+B30-D30 -> 15282 | F30: 32 | G30: 757 | H30: 0 | I30: =G30+F30-H30 -> 789 | J30: =E30-I30 -> 14493 | K30: ='מאזן בוחן'!K166-FA!E30 -> -158.31
A31: VNT | B31: 1332788 | C31: 0 | D31: 0 | E31: =C31+B31-D31 -> 1332788 | F31: 533115 | G31: 266558 | H31: 0 | I31: =G31+F31-H31 -> 799673 | J31: =E31-I31 -> 533115 | K31: ='מאזן בוחן'!K167-FA!E31 -> -628.84
A32: סה"כ בטופס פחת | B32: =SUM(B23:B31) -> 5921292 | C32: =SUM(C23:C31) -> 424073 | D32: =SUM(D23:D31) -> 124401 | E32: =SUM(E23:E31) -> 6220964 | F32: =SUM(F23:F31) -> 3912457 | G32: =SUM(G23:G31) -> 805598 | H32: =SUM(H23:H31) -> 110683 | I32: =SUM(I23:I31) -> 4607372 | J32: =SUM(J23:J31) -> 1613592
A34: סה"כ בספרים | E34: ='מאזן בוחן'!K169 -> 6220322.9 | I34: ='מאזן בוחן'!$K$180 -> -4604998.4 | J34: =E34+I34 -> 1615324.4
A35: הפרש | E35: =E34-E32 -> -641.12 | I35: =I34+I32 -> 2373.56 | J35: =J34-J32 -> 1732.44 | K35: הפרשים נגררים משנים קודמות.
A38: INC - USD
B39: עלות | F39: פחנ"צ | J39: עלות מופחתת
B40: י.פ. | C40: תוספות | D40: גריעות | E40: י.ס. | F40: י.פ. | G40: תוספות | H40: גריעות | I40: י.ס.
A41: מחשבים ותוכנות | B41: 246846 | C41: 47145 | D41: 2065 | E41: =B41+C41-D41 -> 291926 | F41: =192934+2065 -> 194999 | G41: 42384 | H41: 2065 | I41: =F41+G41-H41 -> 235318 | J41: =E41-I41 -> 56608
A42: ריהוט | B42: 96502 | C42: 1889 | E42: =B42+C42-D42 -> 98391 | F42: 55718 | G42: 13865 | I42: =F42+G42-H42 -> 69583 | J42: =E42-I42 -> 28808
A43: שיפורים במושכר | B43: 129754 | C43: 2039 | E43: =B43+C43-D43 -> 131793 | F43: 64404 | G43: 31701 | I43: =F43+G43-H43 -> 96105 | J43: =E43-I43 -> 35688
A44: סה"כ בטופס פחת | B44: =SUM(B41:B43) -> 473102 | C44: =SUM(C41:C43) -> 51073 | D44: =SUM(D41:D43) -> 2065 | E44: =SUM(E41:E43) -> 522110 | F44: =SUM(F41:F43) -> 315121 | G44: =SUM(G41:G43) -> 87950 | H44: =SUM(H41:H43) -> 2065 | I44: =SUM(I41:I43) -> 401006 | J44: =SUM(J41:J43) -> 121104
A46: סה"כ בספרים | E46: ='New TB INC'!J259 -> 522212.74 | I46: ='New TB INC'!J261 -> -401006 | J46: =E46+I46 -> 121206.74
A47: הפרש | E47: =E46-E44 -> 102.74 | I47: =I46+I44 -> 0 | J47: =J46-J44 -> 102.74 | K47: הפרשים נגררים משנים קודמות.
A49: Australia - AUD
A50: Group | B50: עלות | E50: פחנ"צ | H50: עלות מופחתת
B51: י.פ. | C51: רכישות השנה | D51: י.ס. | E51: י.פ. | F51: תנועה השנה | G51: י.ס. | H51: י.ס.
A52: מחשבים ותוכנות | B52: 2235 | C52: 13290.25 | D52: =C52+B52 -> 15525.25 | E52: 735 | F52: 3097 | G52: =F52+E52 -> 3832 | H52: =D52-G52 -> 11693.25
A53: סה"כ בטופס פחת | B53: =SUM(B52:B52) -> 2235 | C53: =SUM(C52:C52) -> 13290.25 | D53: =SUM(D52:D52) -> 15525.25 | E53: =SUM(E52:E52) -> 735 | F53: =SUM(F52:F52) -> 3097 | G53: =SUM(G52:G52) -> 3832 | H53: =SUM(H52:H52) -> 11693.25
A55: סה"כ בספרים | D55: ='מאזן בוחן Australia'!J55 -> 15525.25 | G55: ='מאזן בוחן Australia'!J59 -> -3832 | H55: =D55+G55 -> 11693.25
A56: הפרש | D56: =D55-D53 -> 0 | G56: =G55+G53 -> 0 | H56: =H55-H53 -> 0
A58: Australia - USD
A59: Group | B59: עלות | E59: פחנ"צ | H59: עלות מופחתת
B60: י.פ. | C60: רכישות השנה | D60: י.ס. | E60: י.פ. | F60: תנועה השנה | G60: י.ס. | H60: י.ס.
A61: מחשבים ותוכנות | B61: 1564 | C61: 9994 | D61: =C61+B61 -> 11558 | E61: 515 | F61: 2298 | G61: =F61+E61 -> 2813 | H61: =D61-G61 -> 8745
A62: סה"כ בטופס פחת | B62: =SUM(B61:B61) -> 1564 | C62: =SUM(C61:C61) -> 9994 | D62: =SUM(D61:D61) -> 11558 | E62: =SUM(E61:E61) -> 515 | F62: =SUM(F61:F61) -> 2298 | G62: =SUM(G61:G61) -> 2813 | H62: =SUM(H61:H61) -> 8745
A64: סה"כ בספרים | D64: ='מאזן בוחן Australia'!K54 -> 11553.08 | G64: ='מאזן בוחן Australia'!K58 -> -2813 | H64: =D64+G64 -> 8740.08
A65: הפרש | D65: =D64-D62 -> -4.92 | G65: =G64+G62 -> 0 | H65: =H64-H62 -> -4.92
A67: India - INR
B68: עלות | F68: פחנ"צ | J68: עלות מופחתת
B69: י.פ. | C69: תוספות | D69: גריעות | E69: י.ס. | F69: י.פ. | G69: תוספות | H69: גריעות | I69: י.ס.
A70: מחשבים ותוכנות | B70: 1931000 | C70: 4015000 | E70: =C70+B70-D70 -> 5946000 | F70: 160946.12 | G70: 1391845.6 | I70: =G70+F70-H70 -> 1552791.7 | J70: =E70-I70 -> 4393208.3
A71: ריהוט | B71: 0 | E71: =C71+B71-D71 -> 0 | F71: 0 | I71: =G71+F71-H71 -> 0 | J71: =E71-I71 -> 0
A72: שיפורים במושכר | B72: 0 | E72: =C72+B72-D72 -> 0 | F72: 0 | I72: =G72+F72-H72 -> 0 | J72: =E72-I72 -> 0
A73: סה"כ בטופס פחת | B73: =SUM(B70:B72) -> 1931000 | C73: =SUM(C70:C72) -> 4015000 | D73: =SUM(D70:D72) -> 0 | E73: =SUM(E70:E72) -> 5946000 | F73: =SUM(F70:F72) -> 160946.12 | G73: =SUM(G70:G72) -> 1391845.6 | H73: =SUM(H70:H72) -> 0 | I73: =SUM(I70:I72) -> 1552791.7 | J73: =SUM(J70:J72) -> 4393208.3
A75: סה"כ בספרים | E75: ='מאזן בוחן הודו'!J68 -> 5946000 | I75: ='מאזן בוחן הודו'!J72 -> -1552791.7 | J75: =E75+I75 -> 4393208.3
A76: הפרש | E76: =E75-E73 -> 0 | I76: =I75+I73 -> 0 | J76: =J75-J73 -> 0
A78: Europe - GBP
B79: עלות | F79: פחנ"צ | J79: עלות מופחתת
B80: י.פ. | C80: תוספות | D80: גריעות | E80: י.ס. | F80: י.פ. | G80: תוספות | H80: גריעות | I80: י.ס.
A81: מחשבים ותוכנות | B81: 4446 | C81: 24985 | E81: =C81+B81-D81 -> 29431 | F81: 479 | G81: 4691 | I81: =G81+F81-H81 -> 5170 | J81: =E81-I81 -> 24261
A82: ריהוט | E82: =C82+B82-D82 -> 0 | I82: =G82+F82-H82 -> 0 | J82: =E82-I82 -> 0
A83: שיפורים במושכר | E83: =C83+B83-D83 -> 0 | I83: =G83+F83-H83 -> 0 | J83: =E83-I83 -> 0
A84: סה"כ בטופס פחת | B84: =SUM(B81:B83) -> 4446 | C84: =SUM(C81:C83) -> 24985 | D84: =SUM(D81:D83) -> 0 | E84: =SUM(E81:E83) -> 29431 | F84: =SUM(F81:F83) -> 479 | G84: =SUM(G81:G83) -> 4691 | H84: =SUM(H81:H83) -> 0 | I84: =SUM(I81:I83) -> 5170 | J84: =SUM(J81:J83) -> 24261
A86: סה"כ בספרים | E86: ='מאזן בוחן EUROPE'!J199 -> 29430.23 | I86: ='מאזן בוחן EUROPE'!J203 -> -5170 | J86: =E86+I86 -> 24260.23
A87: הפרש | E87: =E86-E84 -> -0.77 | I87: =I86+I84 -> 0 | J87: =J86-J84 -> -0.77
A89: Europe - USD
B90: עלות | F90: פחנ"צ | J90: עלות מופחתת
B91: י.פ. | C91: תוספות | D91: גריעות | E91: י.ס. | F91: י.פ. | G91: תוספות | H91: גריעות | I91: י.ס.
A92: מחשבים ותוכנות | B92: 6012 | C92: 34266 | E92: =C92+B92-D92 -> 40278 | F92: 644 | G92: 6434 | I92: =G92+F92-H92 -> 7078 | J92: =E92-I92 -> 33200
A93: ריהוט | E93: =C93+B93-D93 -> 0 | I93: =G93+F93-H93 -> 0 | J93: =E93-I93 -> 0
A94: שיפורים במושכר | E94: =C94+B94-D94 -> 0 | I94: =G94+F94-H94 -> 0 | J94: =E94-I94 -> 0
A95: סה"כ בטופס פחת | B95: =SUM(B92:B94) -> 6012 | C95: =SUM(C92:C94) -> 34266 | D95: =SUM(D92:D94) -> 0 | E95: =SUM(E92:E94) -> 40278 | F95: =SUM(F92:F94) -> 644 | G95: =SUM(G92:G94) -> 6434 | H95: =SUM(H92:H94) -> 0 | I95: =SUM(I92:I94) -> 7078 | J95: =SUM(J92:J94) -> 33200
A97: סה"כ בספרים | E97: ='מאזן בוחן EUROPE'!K199 -> 40258.06 | I97: ='מאזן בוחן EUROPE'!K203 -> -7078 | J97: =E97+I97 -> 33180.06
A98: הפרש | E98: =E97-E95 -> -19.94 | I98: =I97+I95 -> 0 | J98: =J97-J95 -> -19.94
A100: Group - USD | B100: open balance | C100: additions 2021 | D100: deduction | E100: closing balance - cost | I100: closing balance - depreciated | J100: total
A101: מחשבים | B101: =B92+B61+B41+B23+B28+B31+26042 -> 5078539 | C101: =C92+C61+C41+C23+C28+C31+54112 -> 549570 | D101: =+D41+D23+D28+D31 -> 105329 | E101: =E92+D61+E41+E23+E28+E31+'מאזן בוחן הודו'!K68 -> 5522780.7 | I101: =I92+G61+I41+I23+I28+I31-'מאזן בוחן הודו'!K74 -> 4204921 | J101: =J92+H61+J41+J23+J28+J31+'מאזן בוחן הודו'!K76 -> 1317859.8
A102: ציוד אלקטרוני | B102: =B26+B29 -> 220901 | C102: =C26+C29 -> 7715 | D102: =D26+D29 -> 6227 | E102: =E26+E29 -> 222389 | I102: =I26+I29 -> 154749 | J102: =J26+J29 -> 67640
A103: ציוד משרדי | B103: =B27+B25+B30+B42 -> 483539 | C103: =C27+C25+C30+C42 -> 14194 | D103: =D27+D25+D30+D42 -> 14910 | E103: =E27+E25+E30+E42 -> 482823 | I103: =I27+I25+I30+I42 -> 201041 | J103: =J27+J25+J30+J42 -> 281782
A104: שיפורים | B104: =B24+B43 -> 645033 | C104: =C43+C24 -> 2039 | D104: =D43+D24 -> 0 | E104: =E43+E24 -> 647072 | I104: =I43+I24 -> 478562 | J104: =J43+J24 -> 168510
B107: =SUM(B101:B106) -> 6428012 | C107: =SUM(C101:C106) -> 573518 | D107: =SUM(D101:D106) -> 126466 | E107: =SUM(E101:E106) -> 6875064.7 | I107: =SUM(I101:I106) -> 5039273 | J107: =SUM(J101:J106) -> 1835791.8
A109: כולל הודו - דולר | B109: =B95+B62+B44+B32+26042 -> 6428012 | C109: =C95+C62+C44+C32+54112 -> 573518 | D109: =D95+D44+D32 -> 126466 | E109: =E95+D62+E44+E32+26042+54112 -> 6875064 | I109: =I95+G62+I44+I32-'מאזן בוחן הודו'!K74 -> 5039273 | J109: =J95+H62+J44+J32+'מאזן בוחן הודו'!K70+'מאזן בוחן הודו'!K74 -> 1835791.8
B110: =B109-B107 -> 0 | C110: =C109-C107 -> 0 | E110: =E109-E107 -> -0.74 | I110: =I109-I107 -> 0 | J110: =J109-J107 -> 0
D113: change in 2021 | E113: =C109-D109 -> 447052

Sheet Consolidation
B2: Consolidated financial statements
B3: $
C4: Algosec System Ltd | D4: Algosec Inc | E4: Algosec Europe | F4: Algosec Australia | G4: Algosec India | H4: Algosec France | J4: Consolidated Balance Sheet | Y4: 7 | Z4: to fill based on the final
C5: ='נתונים לשינוי'!C1 -> 44561 | D5: =$C$5 -> 44561 | E5: =$C$5 -> 44561 | F5: =$C$5 -> 44561 | G5: =$C$5 -> 44561 | H5: =$C$5 -> 44561 | J5: =$C$5 -> 44561 | K5: Journal Entries | L5: Journal Entries | M5: Journal Entries | N5: =$C$5 -> 44561 | Q5: =N5 -> 44561 | R5: 44469 | S5: 44377 | T5: 44286 | U5: 44196 | V5: 44104 | W5: 44012 | X5: 43921 | Y5: 43830 | Z5: 43738 | AA5: 43646 | AB5: 43555 | AC5: 43465 | AD5: 43373 | AE5: 43281 | AF5: 43190 | AG5: 43100 | AH5: 42735 | AI5: Difference | AJ5: Change in % | AK5: Explanations
B6: BALANCE SHEETS | C6: $ | D6: $ | E6: $ | F6: $ | G6: $ | H6: $ | J6: $ | K6: $ | L6: $ | N6: $ | Q6: $ | R6: $ | S6: $ | T6: $ | V6: $ | W6: $ | X6: $ | Y6: $ | Z6: $ | AA6: $ | AB6: $ | AC6: $ | AD6: $ | AE6: $ | AF6: $ | AG6: $ | AH6: $ | AI6: $ | AJ6: $
B9: Current assets
A10: Cash | B10: Cash and Cash Equivalents | C10: =+דוחות!D14 -> 5680458 | D10: ='New TB INC'!J13 -> 20867138 | E10: ='מאזן בוחן EUROPE'!K32 -> 4751031.3 | F10: ='מאזן בוחן Australia'!K13 -> 1530354.3 | G10: ='FS India'!D7 -> 1148700 | H10: ='FS France'!C7 -> 1183805.6 | J10: =SUM(C10:I10) -> 35161487 | N10: =SUM(J10:M10) -> 35161487 | Q10: =ROUND(N10/1000,0) -> 35161 | R10: 34003 | S10: 33397 | T10: 35570 | U10: 31701 | V10: 26439 | W10: =[120]Consolidation!$O$10 -> 26031 | X10: 22939 | Y10: 19555 | Z10: 14514 | AA10: 16698 | AB10: 19025 | AC10: 18177 | AD10: 18617 | AE10: 21685 | AF10: 57088 | AG10: 61911 | AH10: 22961 | AI10: =W10-AH10 -> 3070 | AJ10: =AI10/AH10 -> 0.13370498
A11: Trade receivable | B11: Trade receivable | C11: =+דוחות!D19 -> 4474877.7 | D11: ='New TB INC'!J213 -> 12278443 | E11: ='מאזן בוחן EUROPE'!K163 -> 6047284.5 | F11: ='מאזן בוחן Australia'!K31 -> 4402731.5 | G11: ='FS India'!D8 -> 0 | H11: ='FS France'!C8 -> 1664700.7 | J11: =SUM(C11:I11) -> 28868037 | N11: =SUM(J11:M11) -> 28868037 | Q11: =ROUND(N11/1000,0) -> 28868 | R11: 20275 | S11: 19779 | T11: 17037 | U11: 25035 | V11: 19572 | W11: =[120]Consolidation!$O$11 -> 14787 | X11: 11770 | Y11: 22572 | Z11: 11670 | AA11: 10897 | AB11: 4791 | AC11: 8539 | AD11: 5147 | AE11: 5329 | AF11: 3634 | AG11: 5607 | AH11: 6643 | AI11: =W11-AH11 -> 8144 | AJ11: =AI11/AH11 -> 1.2259521
B12: Defered Tax | C12: 0 | D12: ='New TB INC'!J268 -> 0.24 | G12: ='FS India'!D9 -> 0 | H12: ='FS France'!C9 -> 0 | J12: =SUM(C12:I12) -> 0.24 | N12: =SUM(J12:M12) -> 0.24 | Q12: =ROUND(N12/1000,0) -> 0 | R12: 0 | S12: 0 | T12: 0 | U12: 0 | V12: 0 | W12: =[121]Consolidation!O12 -> 0 | X12: 0 | Y12: 0 | Z12: 0 | AA12: 0 | AB12: 0 | AC12: 0 | AD12: 0 | AE12: 0 | AF12: 0 | AG12: 0 | AH12: 0 | AI12: =W12-AH12 -> 0 | AJ12: 0
A13: Other accounts receivable | B13: Other accounts receivable | C13: =+דוחות!D27-דוחות!D19-דוחות!D24-דוחות!D25-דוחות!D26+דוחות!D24 -> 1436411 | D13: ='New TB INC'!J249+'New TB INC'!J221 -> 1475804 | E13: ='מאזן בוחן EUROPE'!K169+'מאזן בוחן EUROPE'!K187+'מאזן בוחן EUROPE'!K193-'מאזן בוחן EUROPE'!K185 -> 845523.05 | F13: =SUM('מאזן בוחן Australia'!K35:K37) -> 240514.69 | G13: ='FS India'!D10 -> 136344.27 | H13: ='FS France'!C10 -> 1308.58 | J13: =SUM(C13:I13) -> 4135905.5 | N13: =SUM(J13:M13) -> 4135905.5 | Q13: =ROUND(N13/1000,0) -> 4136 | R13: 3824 | S13: 3855 | T13: 3502 | U13: 3404 | V13: 3509 | W13: =[120]Consolidation!$O$13 -> 3335 | X13: 3792 | Y13: 4030 | Z13: 2451 | AA13: 2299 | AB13: 2775 | AC13: 1988 | AD13: 3113 | AE13: 2939 | AF13: 2838 | AG13: 2681 | AH13: 1722 | AI13: =W13-AH13 -> 1613 | AJ13: =AI13/AH13 -> 0.93670151
A14: I/C | B14: Related Parties | C14: =+דוחות!D26+דוחות!D25 -> 11728890 | D14: ='New TB INC'!J271+'New TB INC'!J275+'New TB INC'!J273+'New TB INC'!J274 -> 5220131.4 | E14: ='מאזן בוחן EUROPE'!K178+'מאזן בוחן EUROPE'!K185 -> 965998.81 | F14: ='מאזן בוחן Australia'!K44+'מאזן בוחן Australia'!K38 -> -3629093.8 | G14: ='FS India'!D11 -> 0 | H14: ='FS France'!C11 -> 2178645.5 | J14: =SUM(C14:I14) -> 16464572 | K14: =-J14-L14 -> -16464572 | N14: =SUM(J14:L14) -> 0 | Q14: =ROUND(N14/1000,0) -> 0 | R14: 0 | S14: 0 | T14: 0 | U14: 0 | V14: 0 | W14: =[121]Consolidation!O14 -> 0 | X14: 0 | Y14: 0 | Z14: 0 | AA14: 0 | AB14: 0 | AC14: 0 | AD14: 0 | AE14: 0 | AF14: 0 | AG14: 0 | AH14: 0 | AI14: =W14-AH14 -> 0 | AJ14: 0
C15: =SUM(C10:C14) -> 23320637 | D15: =SUM(D10:D14) -> 39841516 | E15: =SUM(E10:E14) -> 12609838 | F15: =SUM(F10:F14) -> 2544506.8 | G15: =SUM(G10:G14) -> 1285044.3 | H15: =SUM(H10:H14) -> 5028460.3 | J15: =SUM(J10:J14) -> 84630002 | K15: =SUM(K10:K14) -> -16464572 | L15: =SUM(L10:L14) -> 0 | M15: =SUM(M10:M14) -> 0 | N15: =SUM(N10:N14) -> 68165430 | P15: =ROUND(N15/1000,0)-Q15 -> 0 | Q15: =SUM(Q10:Q14) -> 68165 | R15: 58102 | S15: 57031 | T15: 56109 | U15: 60140 | V15: 49520 | W15: =SUM(W10:W14) -> 44153 | X15: 38501 | Y15: 46157 | Z15: 28635 | AA15: =SUM(AA10:AA14) -> 29894 | AB15: =SUM(AB10:AB14) -> 26591 | AC15: 28704 | AD15: 26877 | AE15: 29953 | AF15: 63560 | AG15: 70199 | AH15: =SUM(AH10:AH14) -> 31326 | AI15: =W15-AH15 -> 12827 | AJ15: =AI15/AH15 -> 0.40946817
Y16: 0 | AD16: 0 | AE16: 0
B17: Long term assets | Y17: 0 | AD17: 0 | AE17: 0
B18: Long term deposits | C18: =+דוחות!D33 -> 174654.23 | D18: ='New TB INC'!J282 -> 7898.27 | G18: 0 | H18: 0 | J18: =SUM(C18:I18) -> 182552.5 | N18: =SUM(J18:K18) -> 182552.5 | Q18: =ROUND(N18/1000,0) -> 183 | R18: 136 | S18: 143 | T18: 143 | U18: 447 | V18: 447 | W18: =[120]Consolidation!$O$18 -> 438 | X18: 431 | Y18: 439 | Z18: 439 | AA18: 439 | AB18: 1234 | AC18: 410 | AD18: 152 | AE18: 133 | AF18: 133 | AG18: 103 | AH18: 14 | AI18: =W18-AH18 -> 424 | AJ18: =AI18/AH18 -> 30.285714
B19: LT Receivables | C19: =+דוחות!D39+דוחות!D38 -> 315912.79 | D19: ='New TB INC'!J270 -> 1152543.5 | E19: ='מאזן בוחן EUROPE'!K212+'מאזן בוחן EUROPE'!K213 -> 3529707.7 | F19: ='מאזן בוחן Australia'!K64+'מאזן בוחן Australia'!K65 -> 2503486.1 | G19: 0 | H19: ='FS France'!C16 -> 1379067.9 | J19: =SUM(C19:I19) -> 8880718 | K19: =K42 -> -6912456.9 | N19: =SUM(J19:K19) -> 1968261.1 | Q19: =ROUND(N19/1000,0) -> 1968 | R19: 1721 | S19: 1621 | T19: 1623 | U19: 1707 | V19: 1527 | W19: =[120]Consolidation!$O$19 -> 1509 | X19: 1275 | Y19: 1379 | Z19: 922 | AA19: 939 | AB19: 0 | AC19: 0 | AD19: 0 | AE19: 0 | AF19: 0 | AG19: 0 | AH19: 0 | AI19: =W19-AH19 -> 1509 | AJ19: 0
B20: Severance pay fund | C20: =דוחות!D37 -> 252945.98 | G20: 0 | H20: 0 | J20: =SUM(C20:I20) -> 252945.98 | K20: =+K40 -> 0 | N20: =SUM(J20:K20) -> 252945.98 | Q20: =ROUND(N20/1000,0) -> 253 | R20: 242 | S20: 352 | T20: 338 | U20: 367 | V20: 322 | W20: =[120]Consolidation!$O$20 -> 309 | X20: 287 | Y20: 312 | Z20: 294 | AA20: 279 | AB20: 265 | AC20: 250 | AD20: 295 | AE20: 284 | AF20: 283 | AG20: 286 | AH20: 274 | AI20: =W20-AH20 -> 35 | AJ20: =AI20/AH20 -> 0.12773723
B21: Defered Tax | D21: ='New TB INC'!J269 -> 45550.53 | E21: ='מאזן בוחן EUROPE'!K211 -> 28884.22 | G21: 0 | H21: 0 | J21: =SUM(C21:I21) -> 74434.75 | N21: =SUM(J21:K21) -> 74434.75 | O21: =K14-K36-K48 -> 1.2530455 | Q21: =ROUND(N21/1000,0) -> 74 | R21: 98 | S21: 85 | T21: 86 | U21: 89 | V21: 90 | W21: =[120]Consolidation!$O$21 -> 93 | X21: 96 | Y21: 95 | Z21: 97 | AA21: 74 | AB21: 63 | AC21: 51 | AD21: 1240 | AE21: 1252 | AF21: 1288 | AG21: 1278 | AH21: 577 | AI21: =W21-AH21 -> -484 | AJ21: =AI21/AH21 -> -0.83882149
C22: =SUM(C18:C21) -> 743513 | D22: =SUM(D18:D21) -> 1205992.3 | E22: =SUM(E18:E21) -> 3558591.9 | F22: =SUM(F18:F21) -> 2503486.1 | G22: =SUM(G18:G21) -> 0 | H22: =SUM(H18:H21) -> 1379067.9 | J22: =SUM(J18:J21) -> 9390651.2 | K22: =SUM(K18:K21) -> -6912456.9 | L22: =SUM(L18:L21) -> 0 | N22: =SUM(N18:N21) -> 2478194.3 | P22: =ROUND(N22/1000,0)-Q22 -> 0 | Q22: =SUM(Q18:Q21) -> 2478 | R22: 2197 | S22: 2201 | T22: 2190 | U22: 2610 | V22: 2386 | W22: =SUM(W18:W21) -> 2349 | X22: 2089 | Y22: 2225 | Z22: 1753 | AA22: =SUM(AA18:AA21) -> 1731 | AB22: =SUM(AB18:AB21) -> 1562 | AC22: 711 | AD22: 1687 | AE22: 1669 | AF22: 1704 | AG22: 1667 | AH22: =SUM(AH18:AH21) -> 865 | AI22: =W22-AH22 -> 1484 | AJ22: =AI22/AH22 -> 1.7156069
AD23: 0 | AE23: 0
AD24: 0 | AE24: 0
A25: Fixed assets | B25: Fixed assets ,net | C25: =+דוחות!D35 -> 1615324 | D25: ='New TB INC'!J265 -> 121206.74 | E25: ='FS EU'!C20 -> 33180.06 | F25: ='מאזן בוחן Australia'!K61 -> 8740.08 | G25: ='FS India'!D20 -> 59150.77 | H25: ='FS France'!C20 -> 0 | J25: =SUM(C25:I25) -> 1837601.7 | N25: =SUM(J25:L25) -> 1837601.7 | P25: =ROUND(N25/1000,0)-Q25 -> 0 | Q25: =ROUND(N25/1000,0) -> 1838 | R25: 1852 | S25: 1933 | T25: 2026 | U25: 2126 | V25: 2347 | W25: =[120]Consolidation!$O$25 -> 2510 | X25: 2732 | Y25: 2911 | Z25: 3219 | AA25: 3465 | AB25: 3458 | AC25: 2248 | AD25: 2309 | AE25: 2259 | AF25: 2270 | AG25: 2082 | AH25: 814 | AI25: =W25-AH25 -> 1696 | AJ25: =AI25/AH25 -> 2.0835381
AD26: 0 | AE26: 0
AD27: 0 | AE27: 0
B28: Total assets | C28: =+C15+C22+C25 -> 25679474 | D28: =+D15+D22+D25 -> 41168715 | E28: =+E15+E22+E25 -> 16201610 | F28: =+F15+F22+F25 -> 5056732.9 | G28: =+G15+G22+G25 -> 1344195 | H28: =+H15+H22+H25 -> 6407528.2 | J28: =+J15+J22+J25 -> 95858255 | K28: =+K15+K22+K25+1 -> -23377028 | L28: =+L15+L22+L25 -> 0 | M28: =+M15+M22+M25 -> 0 | N28: =+N15+N22+N25 -> 72481226 | P28: =ROUND(N28/1000,0)-Q28 -> 0 | Q28: =+Q15+Q22+Q25 -> 72481 | R28: 62151 | S28: 61165 | T28: 60325 | U28: 64876 | V28: 54253 | W28: =W25+W22+W15 -> 49012 | X28: 43322 | Y28: 51293 | Z28: 33607 | AA28: =+AA15+AA22+AA25 -> 35090 | AB28: =+AB15+AB22+AB25 -> 31611 | AC28: 31663 | AD28: 30874 | AE28: 33880 | AF28: 67534 | AG28: 73948 | AH28: =+AH15+AH22+AH25 -> 33005 | AI28: =W28-AH28 -> 16007 | AJ28: =AI28/AH28 -> 0.48498712
Y29: 0 | AD29: 0 | AE29: 0 | AF29: 0
AD30: 0
B31: Current liabilities | AD31: 0
A32: Trade payables | B32: Trade payables | C32: =+דוחות!K13 -> 2279724 | D32: =-'New TB INC'!J343 -> 207159.09 | E32: =-'מאזן בוחן EUROPE'!K241+'מאזן בוחן EUROPE'!K239 -> 63650.75 | F32: =-'מאזן בוחן Australia'!K86 -> 13011.77 | G32: ='FS India'!D27 -> -477.42 | H32: ='FS France'!C27 -> 10549.35 | J32: =SUM(C32:I32) -> 2573617.5 | N32: =SUM(J32:M32) -> 2573617.5 | Q32: =ROUND(N32/1000,0)+1 -> 2575 | R32: 1155 | S32: 1500 | T32: 1590 | U32: 1521 | V32: 1017 | W32: =[120]Consolidation!O32 -> 1415 | X32: 1140 | Y32: 1540 | Z32: 1263 | AA32: 1587 | AB32: 1194 | AC32: 1817 | AD32: 1257 | AE32: 1392 | AF32: 955 | AG32: 3205 | AH32: 1051 | AI32: =W32-AH32 -> 364 | AJ32: =AI32/AH32 -> 0.34633682
A33: Other accounts payable | B33: Accrued expenses and other liabilities | C33: =+דוחות!K22-דוחות!K13-דוחות!K19-דוחות!K21-דוחות!K20 -> 6176418 | D33: =-('New TB INC'!J392+SUM('New TB INC'!J409:J428)) -> 1703449.1 | E33: =-('מאזן בוחן EUROPE'!K265+'מאזן בוחן EUROPE'!K276)-'מאזן בוחן EUROPE'!K239 -> 1091689.9 | F33: =-'מאזן בוחן Australia'!K113-'מאזן בוחן Australia'!K117-'מאזן בוחן Australia'!K104 -> 273814.74 | G33: ='FS India'!D28 -> 262524.44 | H33: ='FS France'!C28 -> 817783.51 | J33: =SUM(C33:I33) -> 10325680 | N33: =SUM(J33:M33) -> 10325680 | Q33: =ROUND(N33/1000,0) -> 10326 | R33: 8563 | S33: 8141 | T33: 7991 | U33: 10922 | V33: 7826 | W33: =[120]Consolidation!O33 -> 7293 | X33: 4855 | Y33: 8268 | Z33: 6531 | AA33: 6848 | AB33: 6454 | AC33: 6598 | AD33: 5725 | AE33: 5316 | AF33: 4870 | AG33: 7541 | AH33: 9167 | AI33: =W33-AH33 -> -1874 | AJ33: =AI33/AH33 -> -0.20442893
B34: Liability for Treasury shares and founders ST | D34: =-'New TB INC'!J431 -> 5835921 | H34: 0 | J34: =SUM(C34:I34) -> 5835921 | N34: =SUM(J34:M34) -> 5835921 | Q34: =ROUND(N34/1000,0) -> 5836 | R34: 7500 | S34: 9133 | T34: 9001 | U34: 8868 | V34: 11710 | W34: =[120]Consolidation!O34 -> 11552 | X34: 10702 | Y34: 10702 | Z34: 10702 | AA34: 10702 | AB34: 10702 | AC34: 10702 | AD34: 10702 | AE34: 11842 | AF34: 41550 | AG34: 41550
A35: Deferred revenues | B35: Deferred revenues | C35: =+דוחות!K21 -> 4237920 | D35: =-SUM('New TB INC'!J394:J404) -> 17139054 | E35: =-SUM('מאזן בוחן EUROPE'!K278:K290) -> 7842201.5 | F35: =-SUM('מאזן בוחן Australia'!K119:K131) -> 2663254.9 | G35: ='FS India'!$D$29 -> 0 | H35: ='FS France'!C29 -> 1033965.9 | J35: =SUM(C35:I35) -> 32916396 | N35: =SUM(J35:M35) -> 32916396 | P35: =N35/(N35+N43) -> 0.63123567 | Q35: =ROUND(N35/1000,0) -> 32916 | R35: 29633 | S35: 28933 | T35: 28600 | U35: 29430 | V35: 24868 | W35: =[120]Consolidation!O35 -> 23816 | X35: 23769 | Y35: 24893 | Z35: 20284 | AA35: 21268 | AB35: 16447 | AC35: 19897 | AD35: 19657 | AE35: 19519 | AF35: 17066 | AG35: 14884 | AH35: 11480 | AI35: =W35-AH35 -> 12336 | AJ35: =AI35/AH35 -> 1.0745645
A36: I/C | B36: Related Parties | C36: =+דוחות!K20 -> 11467863 | D36: =-'New TB INC'!J432-'New TB INC'!J272 -> 0 | E36: 0 | F36: =-'מאזן בוחן Australia'!K116 -> 14384.38 | G36: ='FS India'!D30 -> 742762.38 | H36: ='FS France'!C30 -> 4236822.2 | J36: =SUM(C36:I36) -> 16461832 | K36: =-J36 -> -16461832 | N36: =SUM(J36:L36) -> 0 | W36: =[120]Consolidation!O36 -> 0 | Z36: 0 | AA36: 0 | AB36: 0 | AC36: 0 | AD36: 0 | AE36: 0 | AI36: =W36-AH36 -> 0 | AJ36: =AI36/AH36 -> #DIV/0!
B37: Total current liabilities | C37: =SUM(C32:C36) -> 24161925 | D37: =SUM(D32:D36) -> 24885583 | E37: =SUM(E32:E36) -> 8997542.1 | F37: =SUM(F32:F36) -> 2964465.8 | G37: =SUM(G32:G36) -> 1004809.4 | H37: =SUM(H32:H36) -> 6099121 | J37: =SUM(J32:J36) -> 68113446 | K37: =SUM(K32:K36) -> -16461832 | L37: =SUM(L32:L36) -> 0 | M37: =SUM(M32:M36) -> 0 | N37: =SUM(N32:N36) -> 51651614 | P37: =ROUND(N37/1000,0)-Q37 -> -1 | Q37: =SUM(Q32:Q36) -> 51653 | R37: 46851 | S37: 47707 | T37: 47182 | U37: 50741 | V37: 45421 | W37: =SUM(W32:W36) -> 44076 | X37: 40466 | Y37: 45403 | Z37: 38779 | AA37: =SUM(AA32:AA36) -> 40405 | AB37: =SUM(AB32:AB36) -> 34797 | AC37: 39014 | AD37: 37341 | AE37: 38069 | AF37: =SUM(AF32:AF36) -> 64441 | AG37: =SUM(AG32:AG35) -> 67180 | AH37: =SUM(AH32:AH36) -> 21698 | AI37: =W37-AH37 -> 22378 | AJ37: =AI37/AH37 -> 1.0313393
AD38: 0 | AE38: 0 | AF38: 0 | AG38: 0
B39: Long term liabilities | AD39: 0 | AE39: 0
A40: Accrued severance | B40: Accrued severance pay, net | C40: =+דוחות!K29 -> 1725978 | D40: 0 | E40: 0 | G40: 0 | H40: 0 | J40: =SUM(C40:I40) -> 1725978 | N40: =SUM(J40:K40) -> 1725978 | Q40: =ROUND(N40/1000,0) -> 1726 | R40: 1643 | S40: 1719 | T40: 1685 | U40: 1789 | V40: 1651 | W40: =[120]Consolidation!O40 -> 1619 | X40: 1555 | Y40: 1605 | Z40: 1575 | AA40: 1518 | AB40: 1459 | AC40: 1388 | AD40: 1474 | AE40: 1441 | AF40: 1470 | AG40: 1430 | AH40: 688 | AI40: =W40-AH40 -> 931 | AJ40: =AI40/AH40 -> 1.3531977
B41: Liability for Uncertain Tax exp | C41: =דוחות!K28 -> 78849.346 | D41: =-'New TB INC'!J429 -> 12844.785 | G41: 0 | H41: 0 | J41: =SUM(C41:I41) -> 91694.131 | N41: =SUM(J41:K41) -> 91694.131 | Q41: =ROUND(N41/1000,0) -> 92 | R41: 0 | S41: 0 | T41: 0 | U41: 0 | V41: 0 | W41: =[120]Consolidation!O41 -> 0 | X41: 0 | Y41: 0 | Z41: 0 | AA41: 0 | AB41: 0 | AC41: 0 | AD41: 0 | AE41: 0 | AF41: 6000 | AG41: 6000
B42: Deferred revenuesTP | C42: =דוחות!K27 -> 6912456.9 | G42: 0 | H42: 0 | J42: =SUM(C42:I42) -> 6912456.9 | K42: =-J42 -> -6912456.9 | N42: =SUM(J42:L42) -> 0 | Q42: =ROUND(N42/1000,0) -> 0 | R42: 0 | S42: 0 | T42: 0 | U42: 0 | V42: 0 | W42: =[120]Consolidation!O42 -> 0 | X42: 0 | Y42: 0 | Z42: 0 | AA42: 0
A43: Deferred revenues Long | B43: Deferred revenues | C43: =+דוחות!K26 -> 3366606 | D43: =-'New TB INC'!J406 -> 9061564.2 | E43: =-'מאזן בוחן EUROPE'!K297 -> 4131087.1 | F43: =-SUM('מאזן בוחן Australia'!K139) -> 2015822.7 | G43: 0 | H43: ='FS France'!C35 -> 654493.46 | J43: =SUM(C43:I43) -> 19229573 | N43: =SUM(J43:M43) -> 19229573 | Q43: =ROUND(N43/1000,0) -> 19230 | R43: 17243 | S43: 15464 | T43: 15155 | U43: 15049 | V43: 13490 | W43: =[120]Consolidation!O43 -> 12077 | X43: 11253 | Y43: 12193 | Z43: 8320 | AA43: 9567 | AB43: 9734 | AC43: 8247 | AD43: 9147 | AE43: 9700 | AF43: 7314 | AG43: 7198 | AH43: 5063 | AI43: =W43-AH43 -> 7014 | AJ43: =AI43/AH43 -> 1.3853447
C44: =SUM(C40:C43) -> 12083890 | D44: =SUM(D40:D43) -> 9074409 | E44: =SUM(E40:E43) -> 4131087.1 | F44: =SUM(F40:F43) -> 2015822.7 | G44: =SUM(G40:G43) -> 0 | H44: =SUM(H40:H43) -> 654493.46 | J44: =SUM(J40:J43) -> 27959702 | K44: =SUM(K40:K43) -> -6912456.9 | L44: =SUM(L40:L43) -> 0 | M44: =SUM(M40:M43) -> 0 | N44: =SUM(N40:N43) -> 21047246 | P44: =ROUND(N44/1000,0)-Q44 -> -1 | Q44: =SUM(Q40:Q43) -> 21048 | R44: 18886 | S44: 17183 | T44: 16840 | U44: 16838 | V44: 15141 | W44: =SUM(W40:W43) -> 13696 | X44: 12808 | Y44: 13798 | Z44: 9895 | AA44: =SUM(AA40:AA43) -> 11085 | AB44: =SUM(AB40:AB43) -> 11193 | AC44: 9635 | AD44: 10621 | AE44: 11141 | AF44: =SUM(AF40:AF43) -> 14784 | AG44: =SUM(AG40:AG43) -> 14628 | AH44: =SUM(AH40:AH43) -> 5751 | AI44: =W44-AH44 -> 7945 | AJ44: =AI44/AH44 -> 1.3814989
AD45: 0 | AE45: 0 | AF45: 0 | AG45: 0
AD46: 0 | AE46: 0 | AF46: 0 | AG46: 0
B47: Share holder's equity/deficiency | AD47: 0 | AE47: 0 | AF47: 0 | AG47: 0
A48: capital | B48: Share capital | C48: =+דוחות!K32 -> 0 | D48: =-'New TB INC'!J438-'New TB INC'!J439 -> 3518.95 | E48: =-'מאזן בוחן EUROPE'!K302 -> 128 | G48: =-'מאזן בוחן הודו'!K164 -> 1513.67 | H48: =-'מאזן בוחן צרפת'!K170 -> 1099.66 | J48: =SUM(C48:I48) -> 6260.28 | K48: =-E48-H48-G48 -> -2741.33 | N48: =SUM(J48:L48) -> 3518.95 | Q48: =ROUND(N48/1000,0) -> 4 | R48: 4 | S48: 4 | T48: 4 | U48: 4 | V48: 4 | W48: =[120]Consolidation!O48 -> 4 | X48: 4 | Y48: 4 | Z48: 4 | AA48: 4 | AB48: 4 | AC48: 4 | AD48: 3 | AE48: 3 | AF48: 4 | AG48: 4 | AH48: 3 | AI48: =W48-AH48 -> 1 | AJ48: =AI48/AH48 -> 0.33333333
B49: Capital fund | C49: =+דוחות!K34 -> 0 | D49: =-('New TB INC'!J444+'New TB INC'!J445) -> 12992836 | E49: =-'מאזן בוחן EUROPE'!K303-'מאזן בוחן EUROPE'!K305 -> 354154.95 | G49: 0 | H49: 0 | J49: =SUM(C49:I49) -> 13346991 | N49: =SUM(J49:L49) -> 13346991 | Q49: =ROUND(N49/1000,0) -> 13347 | R49: 12623 | S49: 11967 | T49: 11395 | U49: 10694 | V49: 10268 | W49: =[120]Consolidation!O49 -> 9593 | X49: 8885 | Y49: 8340 | Z49: 7822 | AA49: 7205 | AB49: 6731 | AC49: 6274 | AD49: 5682 | AE49: 5174 | AF49: 4694 | AG49: 4565 | AH49: 0 | AI49: =W49-AH49 -> 9593 | AJ49: 0
A50: Additional Paid in Capital | B50: Additional Paid in Capital | D50: =-('New TB INC'!J440+'New TB INC'!J441+'New TB INC'!J443+'New TB INC'!J442) -> 402373.74 | G50: 0 | H50: 0 | J50: =SUM(C50:I50) -> 402373.74 | N50: =SUM(J50:L50) -> 402373.74 | Q50: =ROUND(N50/1000,0) -> 402 | R50: 402 | S50: 402 | T50: 402 | U50: 402 | V50: -10503 | W50: =[120]Consolidation!O50 -> -10503 | X50: -10299 | Y50: -10300 | Z50: -10299 | AA50: -10299 | AB50: -10299 | AC50: -10299 | AD50: -10299 | AE50: -11439 | AF50: -11353 | AG50: -11369 | AH50: 3799 | AI50: =W50-AH50 -> -14302 | AJ50: =AI50/AH50 -> -3.7646749
A51: Retained earnings | B51: Retained earnings | C51: =+דוחות!K36 -> -6214880.9 | D51: =-'New TB INC'!J447-'New TB INC'!J448-'New TB INC'!J446 -> -9315216.8 | E51: =-'מאזן בוחן EUROPE'!K306-'מאזן בוחן EUROPE'!K304 -> 2331466.8 | F51: =-'מאזן בוחן Australia'!K148 -> -177557.41 | G51: ='FS India'!D42 -> 102989.66 | H51: ='FS France'!C42 -> -528889.95 | J51: =SUM(C51:I51) -> -13802089 | N51: =SUM(J51:L51) -> -13802089 | Q51: =ROUND(N51/1000,0)-1 -> -13803 | R51: -13802 | S51: -13802 | T51: -13803 | U51: -16857 | V51: -5952 | W51: =[120]Consolidation!O51 -> -5952 | X51: -5952 | Y51: -7202 | Z51: -7169 | AA51: -7203 | AB51: -7203 | AC51: -1059 | AD51: -1059 | AE51: -1059 | AF51: -1059 | AG51: 1754 | AH51: 1340 | AI51: =W51-AH51 -> -7292 | AJ51: =AI51/AH51 -> -5.441791
B52: Net profit for the year | C52: =+C77 -> -4351460.8 | D52: =D77 -> 3125212.1 | E52: =+E77 -> 387230.71 | F52: =+F77 -> 254001.86 | G52: ='FS India'!D44 -> 234882.29 | H52: ='FS France'!C44 -> 181704.01 | J52: =SUM(C52:I52) -> -168429.86 | K52: =+K77 -> 0.79304549 | L52: =+L77 -> 0 | N52: =SUM(J52:L52) -> -168429.06 | Q52: =+Q77 -> -169 | R52: -2813 | S52: -2296 | T52: -1695 | U52: 3054 | V52: -126 | W52: =[120]Consolidation!O52 -> -1902 | X52: -2590 | Y52: 1250 | Z52: -5425 | AA52: -6106 | AB52: -3611 | AC52: -11906 | AD52: -11413 | AE52: -8009 | AF52: -3977 | AG52: -2814 | AH52: =AH77 -> 414 | AI52: =W52-AH52 -> -2316 | AJ52: =AI52/AH52 -> -5.5942029
B53: Total Shareholder's (deficiency) Equity | C53: =SUM(C48:C52) -> -10566342 | D53: =SUM(D48:D52) -> 7208723.6 | E53: =SUM(E48:E52) -> 3072980.5 | F53: =SUM(F48:F52) -> 76444.45 | G53: =SUM(G48:G52) -> 339385.62 | H53: =SUM(H48:H52) -> -346086.28 | J53: =SUM(J48:J52) -> -214893.8 | K53: =SUM(K48:K52) -> -2740.537 | L53: =SUM(L48:L52) -> 0 | N53: =SUM(N48:N52) -> -217634.33 | P53: =ROUND(N53/1000,0)-Q53 -> 1 | Q53: =SUM(Q48:Q52) -> -219 | R53: -3586 | S53: -3725 | T53: -3697 | U53: -2703 | V53: -6309 | W53: =SUM(W48:W52) -> -8760 | X53: -9952 | Y53: -7908 | Z53: -15067 | AA53: =SUM(AA48:AA52)-1 -> -16400 | AB53: =SUM(AB48:AB52)-1 -> -14379 | AC53: -16986 | AD53: -17088 | AE53: -15330 | AF53: -11691 | AG53: -7860 | AH53: =SUM(AH48:AH52) -> 5556 | AI53: =W53-AH53 -> -14316 | AJ53: =AI53/AH53 -> -2.5766739
X54: 0 | Z54: 0 | AC54: 0 | AD54: 0 | AE54: 0 | AF54: 0 | AG54: 0
B55: Total liabilities | C55: =+C37+C44+C53 -> 25679474 | D55: =+D37+D44+D53 -> 41168715 | E55: =+E37+E44+E53 -> 16201610 | F55: =+F37+F44+F53 -> 5056732.9 | G55: =+G37+G44+G53 -> 1344195 | H55: =+H37+H44+H53 -> 6407528.2 | J55: =+J37+J44+J53 -> 95858255 | K55: =+K37+K44+K53 -> -23377029 | L55: =+L37+L44+L53 -> 0 | M55: =+M37+M44+M53 -> 0 | N55: =+N37+N44+N53 -> 72481225 | P55: =ROUND(N55/1000,0)-Q55 -> -1 | Q55: =+Q37+Q44+Q53 -> 72482 | R55: 62151 | S55: 61165 | T55: 60325 | U55: 64876 | V55: 54253 | W55: =W53+W44+W37 -> 49012 | X55: 43322 | Y55: 51293 | Z55: 33607 | AA55: =+AA37+AA44+AA53 -> 35090 | AB55: =+AB37+AB44+AB53 -> 31611 | AC55: 31663 | AD55: 30874 | AE55: 33880 | AF55: 67534 | AG55: 73948 | AH55: =+AH37+AH44+AH53 -> 33005 | AI55: =W55-AH55 -> 16007 | AJ55: =AI55/AH55 -> 0.48498712
C56: =C55-C28 -> -0.28108457 | D56: =D55-D28 -> 0 | E56: =E55-E28 -> 0 | F56: =F55-F28 -> 0 | G56: =G55-G28 -> -0.01 | H56: =H55-H28 -> 0 | J56: =J55-J28 -> -0.29108459 | K56: =K55-K28 -> -1.46 | L56: =L55-L28 -> 0 | M56: =M55-M28 -> 0 | N56: =N55-N28 -> -0.75108461 | Q56: =Q55-Q28 -> 1 | R56: 0 | S56: 0 | T56: 0 | U56: 1 | V56: 0 | W56: =W55-W28 -> 0 | Y56: 0 | Z56: 0 | AA56: =AA55-AA28 -> 0 | AC56: =AC55-AC28 -> 0 | AD56: 0 | AE56: 0 | AF56: 0 | AH56: =AH55-AH28 -> 0
AF57: 0 | AH57: 1
T58: 0
C60: =+C4 -> Algosec System Ltd | D60: =+D4 -> Algosec Inc | E60: =+E4 -> Algosec Europe | F60: =+F4 -> Algosec Australia | G60: Algosec India | H60: Algosec France | J60: Consolidated P&L
B61: STATEMENTS OF OPERATIONS | C61: =C5 -> 44561 | D61: =C61 -> 44561 | E61: =D61 -> 44561 | F61: =E61 -> 44561 | G61: =F61 -> 44561 | H61: =G61 -> 44561 | J61: =G61 -> 44561 | K61: Journal Entries | L61: Journal Entries | N61: =J61 -> 44561 | Q61: =N61 -> 44561 | R61: 44469 | S61: 44377 | T61: 44286 | U61: 44196 | V61: 44104 | W61: 44012 | X61: 43921 | Y61: 43830 | Z61: 43738 | AA61: 43646 | AB61: 43555 | AC61: 43465 | AD61: 43373 | AE61: 43281 | AF61: =AF5 -> 43190 | AG61: =AG5 -> 43100 | AH61: 42735 | AI61: Difference | AJ61: Change in % | AK61: Explanations
C62: $ | D62: $ | E62: $ | F62: $ | G62: $ | H62: $ | J62: $ | K62: $ | L62: $ | N62: $ | Q62: $ | R62: $ | S62: $ | T62: $ | U62: $ | V62: $ | W62: $ | X62: $ | Y62: $ | Z62: $ | AA62: $ | AB62: $ | AC62: $ | AD62: $ | AE62: $ | AF62: $ | AG62: $ | AH62: $ | AI62: $ | AJ62: $
X63: 0
A64: Income | B64: Revenues | C64: =+דוחות!Q12 -> 43284099 | D64: =-'New TB INC'!J484 -> 35909314 | E64: =-'מאזן בוחן EUROPE'!K345 -> 19220396 | F64: =-'מאזן בוחן Australia'!K179 -> 5012328.8 | G64: ='FS India'!D52 -> 2876820.1 | H64: ='FS France'!C52 -> 2836751 | J64: =SUM(C64:I64) -> 1.0913971e+08 | K64: =SUM('יתרות בינחברתיות'!$C$53:$C$59) -> -35708762 | N64: =SUM(J64:L64) -> 73430948 | P64: =Q64-R64 -> 24100 | Q64: =ROUND(N64/1000,0) -> 73431 | R64: 49331 | S64: 31569 | T64: 15243 | U64: 68194 | V64: 47711 | W64: =[120]Consolidation!$O$64 -> 31000 | X64: 14047 | Y64: 64562 | Z64: 41381 | AA64: 26397 | AB64: 12401 | AC64: 54118 | AD64: 36265 | AE64: 23492 | AF64: 10417 | AG64: 51027 | AH64: 42053 | AI64: =W64-AH64 -> -11053 | AJ64: =AI64/AH64 -> -0.26283499
A65: COGS | B65: COGS | C65: =+דוחות!Q31 -> 8433827.3 | D65: ='New TB INC'!J581+'New TB INC'!J623*0 -> 19472457 | E65: =+'מאזן בוחן EUROPE'!K370 -> 14407494 | F65: ='מאזן בוחן Australia'!K194 -> 3066115.7 | G65: ='FS India'!D53 -> 1342077.4 | H65: ='FS France'!C53 -> 1392203.3 | J65: =SUM(C65:I65) -> 48114175 | K65: =-SUM('יתרות בינחברתיות'!$C$73,'יתרות בינחברתיות'!$C$71,'יתרות בינחברתיות'!$C$65,'יתרות בינחברתיות'!$C$69,'יתרות בינחברתיות'!$C$67) -> -35708763 | N65: =SUM(J65:L65) -> 12405412 | P65: =Q65-R65 -> 3510 | Q65: =ROUND(N65/1000,0) -> 12405 | R65: 8895 | S65: 5726 | T65: 2815 | U65: 11065 | V65: 8209 | W65: =[120]Consolidation!$O$65 -> 5639 | X65: 2686 | Y65: 11634 | Z65: 8643 | AA65: 6210 | AB65: 3046 | AC65: 11455 | AD65: 8504 | AE65: 5757 | AF65: 2975 | AG65: 8062 | AH65: 5518 | AI65: =W65-AH65 -> 121 | AJ65: =AI65/AH65 -> 0.021928235
B66: Gross profit | C66: =+C64-C65 -> 34850272 | D66: =+D64-D65 -> 16436857 | E66: =+E64-E65 -> 4812902.3 | F66: =+F64-F65 -> 1946213.1 | G66: =+G64-G65 -> 1534742.8 | H66: =+H64-H65 -> 1444547.7 | J66: =+J64-J65 -> 61025535 | K66: =+K64-K65 -> 0.79304549 | L66: =+L64-L65 -> 0 | N66: =+N64-N65 -> 61025536 | P66: =Q66-R66 -> 20590 | Q66: =+Q64-Q65 -> 61026 | R66: 40436 | S66: 25843 | T66: 12428 | U66: 57129 | V66: 39502 | W66: =[120]Consolidation!$O$66 -> 25361 | X66: 11361 | Y66: 52928 | Z66: 32738 | AA66: =+AA64-AA65 -> 20187 | AB66: 9355 | AC66: 42663 | AD66: 27761 | AE66: 17735 | AF66: 7442 | AG66: 42965 | AH66: =+AH64-AH65 -> 36535 | AI66: =W66-AH66 -> -11174 | AJ66: =AI66/AH66 -> -0.30584371
B67: =SUM(D68)/SUM(C65:H65) -> 0.025566513 | P67: =Q67-R67 -> 0.011378481 | Q67: =Q66/Q64 -> 0.8310659 | R67: 0.81968742 | S67: 0.81861953 | T67: 0.81532507 | U67: 0.83774232 | V67: 0.82794324 | W67: =[121]Consolidation!O67 -> 0.81809677 | X67: 0.80878479 | Y67: 0.81980112 | Z67: 0.79113603 | AA67: =AA66/AA64 -> 0.76474599 | AB67: 0.75437465 | AC67: 0.7883329 | AD67: 0 | AE67: 0 | AF67: 0 | AG67: =AG66/AG64 -> 0.84200521
A68: R&D | B68: Research and development | C68: =+דוחות!Q23 -> 24668550 | D68: =+'New TB INC'!J623*1 -> 1230111.7 | F68: ='מאזן בוחן Australia'!K200 -> 0 | G68: ='FS India'!D56 -> 480687.22 | H68: ='FS France'!C56 -> 0 | J68: =SUM(C68:I68) -> 26379349 | N68: =SUM(J68:L68) -> 26379349 | P68: =Q68-R68 -> 7261 | Q68: =ROUND(N68/1000,0) -> 26379 | R68: 19118 | S68: 12897 | T68: 6306 | U68: 23328 | V68: 17181 | W68: =[120]Consolidation!$O$68 -> 11332 | X68: 5638 | Y68: 20905 | Z68: 15809 | AA68: 11024 | AB68: 5429 | AC68: 19869 | AD68: 14945 | AE68: 10135 | AF68: 4901 | AG68: 15507 | AH68: 10236 | AI68: =W68-AH68 -> 1096 | AJ68: =AI68/AH68 -> 0.10707308
A69: S&M | B69: Sales and marketing | C69: =+דוחות!Q56 -> 6591204.7 | D69: ='New TB INC'!J1002 -> 11127891 | E69: =+'מאזן בוחן EUROPE'!K488 -> 4397191.5 | F69: ='מאזן בוחן Australia'!K265 -> 1856889.1 | G69: ='FS India'!D57 -> 601389.73 | H69: ='FS France'!C57 -> 1358165.9 | J69: =SUM(C69:I69) -> 25932732 | N69: =SUM(J69:L69) -> 25932732 | P69: =Q69-R69 -> 8386 | Q69: =ROUND(N69/1000,0) -> 25933 | R69: 17547 | S69: 11136 | T69: 5506 | U69: 23613 | V69: 16988 | W69: =[120]Consolidation!$O$69 -> 11766 | X69: 6276 | Y69: 24644 | Z69: 17187 | AA69: 11851 | AB69: 5811 | AC69: 24998 | AD69: 18050 | AE69: 11782 | AF69: 5311 | AG69: 21994 | AH69: 18409 | AI69: =W69-AH69 -> -6643 | AJ69: =AI69/AH69 -> -0.3608561
A70: G&A | B70: General and administrative | C70: =+דוחות!Q45 -> 5726625.9 | D70: ='New TB INC'!J727 -> 435735.67 | E70: =+'מאזן בוחן EUROPE'!K402 -> -78501.44 | F70: ='מאזן בוחן Australia'!K208 -> 16080.6 | G70: ='FS India'!D58 -> 53985.02 | H70: ='FS France'!C58 -> 28671.15 | J70: =SUM(C70:I70) -> 6182596.9 | N70: =SUM(J70:L70) -> 6182596.9 | P70: =Q70-R70 -> 1632 | Q70: =ROUND(N70/1000,0) -> 6183 | R70: 4551 | S70: 2996 | T70: 1506 | U70: 5868 | V70: 4467 | W70: =[120]Consolidation!$O$70 -> 2989 | X70: 1519 | Y70: 5714 | Z70: 4415 | AA70: 2983 | AB70: 1475 | AC70: 6545 | AD70: 5549 | AE70: 3387 | AF70: 1606 | AG70: 9425 | AH70: 6528 | AI70: =W70-AH70 -> -3539 | AJ70: =AI70/AH70 -> -0.54212623
C71: =SUM(C68:C70) -> 36986380 | D71: =SUM(D68:D70) -> 12793739 | E71: =SUM(E68:E70) -> 4318690 | F71: =SUM(F68:F70) -> 1872969.7 | G71: =SUM(G68:G70) -> 1136062 | H71: =SUM(H68:H70) -> 1386837.1 | J71: =SUM(J68:J70) -> 58494678 | K71: =+K66-K69 -> 0.79304549 | L71: =SUM(L68:L70) -> 0 | N71: =SUM(N68:N70) -> 58494678 | P71: =Q71-R71 -> 17279 | Q71: =SUM(Q68:Q70) -> 58495 | R71: 41216 | S71: 27029 | T71: 13318 | U71: 52809 | V71: 38636 | W71: =[120]Consolidation!$O$71 -> 26087 | X71: 13433 | Y71: 51263 | Z71: 37411 | AA71: =SUM(AA68:AA70) -> 25858 | AB71: 12715 | AC71: 51412 | AD71: 38544 | AE71: 25304 | AF71: 11818 | AG71: 46926 | AH71: =SUM(AH68:AH70) -> 35173 | AI71: =W71-AH71 -> -9086 | AJ71: =AI71/AH71 -> -0.25832315
P72: =Q72-T72 -> 0 | Z72: 0 | AA72: 0 | AB72: 0 | AC72: 0 | AD72: 0 | AE72: 0 | AF72: 0 | AG72: 0
B73: Total operating profit | C73: =+C66-C71 -> -2136108.3 | D73: =+D66-D71 -> 3643118.5 | E73: =+E66-E71 -> 494212.26 | F73: =+F66-F71 -> 73243.37 | G73: =+G66-G71 -> 398680.81 | H73: =+H66-H71 -> 57710.67 | J73: =SUM(C73:I73) -> 2530857.4 | K73: =+K71 -> 0.79304549 | L73: =L66-L71 -> 0 | N73: =SUM(J73:L73) -> 2530858.2 | P73: =Q73-R73 -> 3311 | Q73: =ROUND(N73/1000,0) -> 2531 | R73: -780 | S73: -1186 | T73: -890 | U73: 4320 | V73: 866 | W73: =[120]Consolidation!$O$73 -> -726 | X73: -2071 | Y73: 1665 | Z73: -4673 | AA73: -5671 | AB73: -3360 | AC73: -8748 | AD73: -10783 | AE73: -7570 | AF73: -4376 | AG73: -3961 | AH73: =+AH66-AH71 -> 1362 | AI73: =W73-AH73 -> -2088 | AJ73: =AI73/AH73 -> -1.5330396
A74: finance | B74: Financial exp (Income) | C74: =+דוחות!Q60+דוחות!Q62 -> 1472866 | D74: ='New TB INC'!J1030 -> 507224.42 | E74: =+'מאזן בוחן EUROPE'!K504 -> 46118.41 | F74: ='מאזן בוחן Australia'!K278 -> -180758.49 | G74: =-'FS India'!D62 -> 22115.34 | H74: ='FS France'!C62 -> -131063.7 | J74: =SUM(C74:I74) -> 1736502 | N74: =SUM(J74:L74) -> 1736502 | P74: =Q74-R74 -> 183 | Q74: =ROUND(N74/1000,0) -> 1737 | R74: 1554 | S74: 824 | T74: 685 | U74: 109 | V74: 693 | W74: =[120]Consolidation!$O$74 -> 939 | X74: 464 | Y74: 249 | Z74: 617 | AA74: 275 | AB74: 154 | AC74: -436 | AD74: 343 | AE74: 253 | AF74: -432 | AG74: -856 | AH74: 588 | AI74: =W74-AH74 -> 351 | AJ74: =AI74/AH74 -> 0.59693878
B75: Profit (loss) before taxes: | C75: =+C73-C74 -> -3608974.3 | D75: =+D73-D74 -> 3135894.1 | E75: =+E73-E74 -> 448093.85 | F75: =+F73-F74 -> 254001.86 | G75: =+G73-G74 -> 376565.47 | H75: =+H73-H74 -> 188774.37 | J75: =+J73-J74 -> 794355.41 | K75: =+K73-K74 -> 0.79304549 | L75: =+L73-L74 -> 0 | N75: =SUM(J75:L75) -> 794356.2 | P75: =Q75-R75 -> 3128 | Q75: =+Q73-Q74 -> 794 | R75: -2334 | S75: -2010 | T75: -1575 | U75: 4211 | V75: 173 | W75: =[120]Consolidation!$O$75 -> -1665 | X75: -2535 | Y75: 1416 | Z75: -5290 | AA75: =+AA73-AA74 -> -5946 | AB75: -3514 | AC75: -9184 | AD75: -11126 | AE75: -7823 | AF75: -3944 | AG75: -3105 | AH75: =+AH73-AH74 -> 774 | AI75: =W75-AH75 -> -2439 | AJ75: =AI75/AH75 -> -3.1511628
A76: Tax | B76: Taxes on income (Tax benefit) | C76: =+דוחות!Q64 -> 742486.56 | D76: =+'New TB INC'!J1019 -> 10682.025 | E76: =+'מאזן בוחן EUROPE'!K496 -> 60863.14 | F76: ='מאזן בוחן Australia'!K271 -> 0 | G76: ='FS India'!D65 -> 141683.18 | H76: ='FS France'!C65 -> 7070.36 | J76: =SUM(C76:I76) -> 962785.26 | N76: =SUM(J76:L76) -> 962785.26 | P76: =Q76-R76 -> 484 | Q76: =ROUND(N76/1000,0) -> 963 | R76: 479 | S76: 286 | T76: 120 | U76: 1157 | V76: 299 | W76: =[120]Consolidation!$O$76 -> 237 | X76: 55 | Y76: 166 | Z76: 135 | AA76: 160 | AB76: 98 | AC76: -2721 | AD76: 287 | AE76: 186 | AF76: 33 | AG76: -291 | AH76: 360 | AI76: =W76-AH76 -> -123 | AJ76: =AI76/AH76 -> -0.34166667
B77: Net profit (loss) for the period | C77: =+C75-C76 -> -4351460.8 | D77: =+D75-D76 -> 3125212.1 | E77: =+E75-E76 -> 387230.71 | F77: =+F75-F76 -> 254001.86 | G77: =+G75-G76 -> 234882.29 | H77: =+H75-H76 -> 181704.01 | J77: =+J75-J76 -> -168429.86 | K77: =+K75-K76 -> 0.79304549 | L77: =+L75-L76 -> 0 | N77: =+N75-N76 -> -168429.06 | P77: =Q77-R77 -> 2644 | Q77: =+Q75-Q76 -> -169 | R77: -2813 | S77: -2296 | T77: -1695 | U77: 3054 | V77: -126 | W77: =[120]Consolidation!$O$77 -> -1902 | X77: -2590 | Y77: 1250 | Z77: =+Z75-Z76 -> -5425 | AA77: =+AA75-AA76 -> -6106 | AB77: -3612 | AC77: -11905 | AD77: -11413 | AE77: -8009 | AF77: -3977 | AG77: -2814 | AH77: =+AH75-AH76 -> 414 | AI77: =W77-AH77 -> -2316 | AJ77: =AI77/AH77 -> -5.5942029
C78: =C77-C52 -> 0 | D78: =D77-D52 -> 0 | E78: =E77-E52 -> 0 | F78: =F77-F52 -> 0 | G78: =G77-G52 -> 0 | H78: =H77-H52 -> 0 | J78: =J77-J52 -> 0 | K78: =K77-K52 -> 0 | N78: =N77-N52 -> 0 | P78: =Q78-R78 -> 0 | Q78: =Q77-Q52 -> 0 | R78: 0 | S78: 0 | T78: 0 | U78: 0 | V78: 0 | W78: =W77-W52 -> 0 | AG78: 0
B80: בדיקת עודפים:
B81: י.ס 31.12.20 | C81: =SUM([122]Consolidation!C51:C52) -> -6214880.3 | D81: =SUM([122]Consolidation!D51:D52) -> -9315216.8 | E81: =SUM([122]Consolidation!E51:E52) -> 2331466.8 | F81: =SUM([122]Consolidation!F51:F52) -> -177557.41 | G81: =SUM([122]Consolidation!G51:G52) -> 102989.66 | H81: =SUM([122]Consolidation!H51:H52) -> -528889.95 | J81: =SUM(C81:H81) -> -13802088
B82: reclass - UK GAAP - Share based paymt | J82: =SUM(C82:H82) -> 0
J83: =SUM(C83:H83) -> 0 | N83: QUICK RATIO | P83: =P85/P86 -> 4.9631036
B84: רווח\הפסד הרבעון | C84: =C77 -> -4351460.8 | D84: =D77 -> 3125212.1 | E84: =E77 -> 387230.71 | F84: =F77 -> 254001.86 | G84: =G77 -> 234882.29 | H84: =H77 -> 181704.01 | J84: =N77 -> -168429.06
B85: י.ס. ע"פ חישוב | C85: =C81+C84+C83 -> -10566341 | D85: =D81+D84+D83 -> -6190004.7 | E85: =E81+E84+E83 -> 2718697.5 | F85: =F81+F84+F83 -> 76444.45 | G85: =G81+G84+G83 -> 337871.95 | H85: =H81+H84+H83 -> -347185.94 | J85: =J81+J84+J83+J82 -> -13970517 | N85: CURRENT ASSETS | P85: =Q10+Q11 -> 64029
B86: י.ס. בפועל | C86: =C51+C52 -> -10566342 | D86: =D51+D52 -> -6190004.7 | E86: =E51+E52 -> 2718697.5 | F86: =F51+F52 -> 76444.45 | G86: =G51+G52 -> 337871.95 | H86: =H51+H52 -> -347185.94 | J86: =N51+N52 -> -13970518 | N86: CURRENT LIAB(LEUMI) | P86: =Q32+Q33 -> 12901
B87: הפרש | C87: =C85-C86 -> 0.55794323 | D87: =D85-D86 -> -1.4901161e-08 | E87: =E85-E86 -> 0 | F87: =F85-F86 -> -5.5297278e-10 | G87: =G85-G86 -> 0 | H87: =H85-H86 -> 0 | J87: =J86-J85 -> -0.55794322
B89: implementation | C89: -754469.93 | D89: -1201484.1 | E89: -3645687.8 | F89: -159485.69
B90: tp invoice | C90: =-SUM(D90:H90) -> -4881491.2 | D90: =-D89*0.975 -> 1171447 | E90: =-E89*0.975 -> 3554545.6 | F90: =-F89*0.975 -> 155498.55
C91: =SUM(C89:C90) -> -5635961.1 | D91: =SUM(D89:D90) -> -30037.103 | E91: =SUM(E89:E90) -> -91142.195 | F91: =SUM(F89:F90) -> -3987.1423
C92: =C91+C83 -> -5635961.1 | D92: =D91+D83 -> -30037.103 | E92: =E91+E83 -> -91142.195 | F92: =F91+F83 -> -3987.1423

Sheet Prepaid expenses
B1: 1100001 | D1: 44197 | E1: 44228 | F1: 44256 | G1: 44287 | H1: 44317 | I1: 44348 | J1: 44378 | K1: 44409 | L1: 44440 | M1: 44470 | N1: 44501 | O1: 44531 | P1: 44562 | Q1: 44593 | R1: 44621 | S1: 44652 | T1: 44682 | U1: 44713 | V1: 44743 | W1: 44774 | X1: 44805 | Y1: 44835 | Z1: 44866 | AA1: 44896 | AB1: 44927 | AC1: 44958 | AD1: 44986 | AE1: 45017 | AF1: 45047 | AG1: 45078 | AH1: 45108 | AI1: 45139 | AJ1: 45170 | AK1: 45200 | AL1: 45231
B2: INC
D4: USD
D5: 44197 | E5: 44228 | F5: 44256 | G5: 44287 | H5: 44317 | I5: 44348 | J5: 44378 | K5: 44409 | L5: 44440 | M5: 44470 | N5: 44501 | O5: 44531 | P5: 44197 | Q5: 44228 | R5: 44256 | S5: 44287 | T5: 44317 | U5: 44348 | V5: 44378 | W5: 44409 | X5: 44440 | Y5: 44470 | Z5: 44501
B6: Chris T SKO 2022 | C6: =SUM(D6:AX6) -> 4803.53 | P6: 4803.53
B7: GovSpend- Paid By Cindy | C7: =SUM(D7:AX7) -> 3591.85 | P7: 699.97 | Q7: 699.97 | R7: 699.97 | S7: 699.97 | T7: 699.97 | U7: 92
B8: Kelsey B -SKO Flight | C8: =SUM(D8:AX8) -> 179.63 | P8: 179.63
B9: Tony C -Cancelled Flight | C9: =SUM(D9:AX9) -> 312.55 | P9: 312.55
B10: COM+Umbrella 2021 | C10: =SUM(D10:AX10) -> 306.02 | P10: 306.02
B11: Aval Feb20-Feb21 (AMEX) | C11: =SUM(D11:AX11) -> 1315.09 | P11: 482.9 | Q11: 482.9 | R11: 349.29
B12: YesLogic- R&D CSO Licens | C12: =SUM(D12:AX12) -> 2750 | P12: 253.34 | Q12: 253.34 | R12: 253.34 | S12: 253.34 | T12: 253.34 | U12: 253.34 | V12: 253.34 | W12: 253.34 | X12: 253.34 | Y12: 253.34 | Z12: 216.6
B13: Kyle W -Jan 2021 SKO | C13: =SUM(D13:AX13) -> 688.6 | P13: 688.6
B14: Robert V -Jan 2021 SKO | C14: =SUM(D14:AX14) -> 249.01 | P14: 249.01
B15: Cindy G-Jan 2021 SKO | C15: =SUM(D15:AX15) -> 237.95 | P15: 237.95
B16: Lee H- SNS Jan/22-Dec 22 | C16: =SUM(D16:AX16) -> 1289.45 | P16: 1289.45
B17: MyFSA Canada Q1 | C17: =SUM(D17:AX17) -> 396.11 | P17: 396.11
B18: NETWORKS-Paid Amex | C18: =SUM(D18:AX18) -> 1233.7 | P18: 122.97 | Q18: 122.97 | R18: 122.97 | S18: 122.97 | T18: 122.97 | U18: 122.97 | V18: 122.97 | W18: 122.97 | X18: 122.97 | Y18: 122.97 | Z18: 4
C19: =SUM(C6:C18) -> 17353.49
C20: =-'New TB INC'!J241+C19 -> -7.01
B22: Europe
D24: GBP
D25: 44197 | E25: 44228 | F25: 44256 | G25: 44287 | H25: 44317 | I25: 44348 | J25: 44378 | K25: 44409 | L25: 44440 | M25: 44470 | N25: 44501 | O25: 44531 | P25: 44562 | Q25: 44593 | R25: 44621 | S25: 44652 | T25: 44682 | U25: 44713 | V25: 44743 | W25: 44774 | X25: 44805 | Y25: 44835 | Z25: 44866
B26: Ahmed Al-N - insurance | C26: =SUM(D26:AO26) -> 3657.12 | P26: 457.14 | Q26: 457.14 | R26: 457.14 | S26: 457.14 | T26: 457.14 | U26: 457.14 | V26: 457.14 | W26: 457.14
B27: Elsayed - insurance | C27: =SUM(D27:AO27) -> 8786.4 | P27: 1098.3 | Q27: 1098.3 | R27: 1098.3 | S27: 1098.3 | T27: 1098.3 | U27: 1098.3 | V27: 1098.3 | W27: 1098.3
B28: insurance | C28: =SUM(D28:AO28) -> 1027.62 | P28: 97.5 | Q28: 97.5 | R28: 97.5 | S28: 97.5 | T28: 97.5 | U28: 97.5 | V28: 97.5 | W28: 97.5 | X28: 97.5 | Y28: 97.5 | Z28: 52.62
B29: Twenty Three Aps Q4/21 | C29: =SUM(D29:AO29) -> 241.26 | P29: 241.26
B30: Office box | C30: =SUM(D30:AO30) -> 99 | P30: 99
B31: Amiviz - Saudia | C31: =SUM(D31:AO31) -> 504.86 | P31: 252.43 | Q31: 252.43
C32: =SUM(C26:C31) -> 14316.26
C33: =-'מאזן בוחן EUROPE'!J183+C32 -> -0.05
B35: Israel
C36: ILS
B37: ='מאזן בוחן'!C135 -> 1100001 | D37: 44197 | E37: 44228 | F37: 44256 | G37: 44287 | H37: 44317 | I37: 44348 | J37: 44378 | K37: 44409 | L37: 44440 | M37: 44470 | N37: 44501 | O37: 44531 | P37: 44562 | Q37: 44593 | R37: 44621 | S37: 44652 | T37: 44682 | U37: 44713 | V37: 44743 | W37: 44774 | X37: 44805 | Y37: 44835 | Z37: 44866 | AA37: 44896 | AB37: 44927 | AC37: 44958 | AD37: 44986 | AE37: 45017 | AF37: 45047 | AG37: 45078 | AH37: 45108 | AI37: 45139 | AJ37: 45170 | AK37: 45200 | AL37: 45231 | AM37: 45261 | AN37: 45292
B38: 6sense Insights, Inc | C38: =SUM(D38:AX38) -> 139085.35 | P38: 23180.9 | Q38: 23180.9 | R38: 23180.9 | S38: 23180.9 | T38: 23180.9 | U38: 23180.85
B39: 9\21-22 SNAPENGAGE CHAT | C39: =SUM(D39:AX39) -> 6783.07 | P39: 797.36 | Q39: 797.36 | R39: 797.36 | S39: 797.36 | T39: 797.36 | U39: 797.36 | V39: 797.36 | W39: 797.36 | X39: 404.19
B40: Aha 12/21-12/22 | C40: =SUM(D40:AX40) -> 35917.71 | P40: 3098.55 | Q40: 3098.55 | R40: 3098.55 | S40: 3098.55 | T40: 3098.55 | U40: 3098.55 | V40: 3098.55 | W40: 3098.55 | X40: 3098.55 | Y40: 3098.55 | Z40: 3098.55 | AA40: 1833.66
B41: Calendly 6/21-6/22 | C41: =SUM(D41:AX41) -> 8426.85 | P41: 1404.47 | Q41: 1404.47 | R41: 1404.47 | S41: 1404.47 | T41: 1404.47 | U41: 1404.5
B42: Cato Networks | C42: =SUM(D42:AX42) -> 571.24 | P42: 571.24
B43: Cato VPN
B44: Chili Piper | C44: =SUM(D44:AX44) -> 12238.36 | P44: 1104.6 | Q44: 1104.6 | R44: 1104.6 | S44: 1104.6 | T44: 1104.6 | U44: 1104.6 | V44: 1104.6 | W44: 1104.6 | X44: 1104.6 | Y44: 1104.6 | Z44: 1104.6 | AA44: 87.76
B45: CIS Renewal 7\21-7/22 | C45: =SUM(D45:AX45) -> 26047.01 | P45: 4064.62 | Q45: 4064.62 | R45: 4064.62 | S45: 4064.62 | T45: 4064.62 | U45: 4064.62 | V45: 1659.29
B46: Comeet Technolodies Inc | C46: =SUM(D46:AX46) -> 27231.48 | P46: 6807.88 | Q46: 6807.88 | R46: 6807.88 | S46: 6807.84
B47: Conga 11/21-10/22 | C47: =SUM(D47:AX47) -> 15363.85 | P47: 1536.39 | Q47: 1536.39 | R47: 1536.39 | S47: 1536.39 | T47: 1536.39 | U47: 1536.39 | V47: 1536.39 | W47: 1536.39 | X47: 1536.39 | Y47: 1536.34
B48: Docebo licence 5/21-5/22 | C48: =SUM(D48:AX48) -> 63822.45 | P48: 12849 | Q48: 12849 | R48: 12849 | S48: 12849 | T48: 12426.45
B49: Everpost, Inc | C49: =SUM(D49:AX49) -> 13366.82 | P49: 13366.82
B50: Gartner 10/21-3/22 | C50: =SUM(D50:AX50) -> 65299.99 | P50: 21766.67 | Q50: 21766.67 | R50: 21766.65
B51: GO Daddy | C51: =SUM(D51:AX51) -> 441.99 | P51: 103.33 | Q51: 103.33 | R51: 103.33 | S51: 103.33 | T51: 28.67
B52: GoDaddy | C52: =SUM(D52:AX52) -> 80.84 | P52: 18.76 | Q52: 18.76 | R52: 18.76 | S52: 18.76 | T52: 5.8
B53: Gurock 1-12/22 | C53: =SUM(D53:AX53) -> 56219.61 | P53: 6246.63 | Q53: 6246.63 | R53: 6246.63 | S53: 6246.63 | T53: 6246.63 | U53: 6246.63 | V53: 6246.63 | W53: 6246.63 | X53: 6246.57
B54: Hotjar- מנוי שנתי | C54: =SUM(D54:AX54) -> 723.83 | P54: 230.13 | Q54: 230.13 | R54: 230.13 | S54: 33.44
B55: IntelliJ license | C55: =SUM(D55:AX55) -> 3085.95 | P55: 514.32 | Q55: 514.32 | R55: 514.32 | S55: 514.32 | T55: 514.32 | U55: 514.35
B56: IRON MOUNTAIN | C56: =SUM(D56:AX56) -> 319.92 | P56: 319.92
B57: iStock | C57: =SUM(D57:AX57) -> 327.29 | P57: 327.29
B58: JET BRAINS | C58: =SUM(D58:AX58) -> 54197.18 | P58: 9032.86 | Q58: 9032.86 | R58: 9032.86 | S58: 9032.86 | T58: 9032.86 | U58: 9032.88
B59: Kahoot | C59: =SUM(D59:AX59) -> 698.07 | P59: 191.87 | Q59: 191.87 | R59: 191.87 | S59: 122.46
B60: Kovai 12/21-12/22 | C60: =SUM(D60:AX60) -> 57764.34 | P60: 5235.66 | Q60: 5235.66 | R60: 5235.66 | S60: 5235.66 | T60: 5235.66 | U60: 5235.66 | V60: 5235.66 | W60: 5235.66 | X60: 5235.66 | Y60: 5235.66 | Z60: 5235.66 | AA60: 172.08
B61: LeadGnome Inc | C61: =SUM(D61:AX61) -> 5577.58 | P61: 1773.36 | Q61: 1773.36 | R61: 1773.36 | S61: 257.5
B62: Linkpoint | C62: =SUM(D62:AX62) -> 3616.93 | P62: 534.27 | Q62: 534.27 | R62: 534.27 | S62: 534.27 | T62: 534.27 | U62: 534.27 | V62: 411.31
B63: Loopio Inc | C63: =SUM(D63:AX63) -> 336.16 | P63: 336.16
B64: MadCap 2022 | C64: =SUM(D64:AX64) -> 3623.38 | P64: 304.45 | Q64: 304.45 | R64: 304.45 | S64: 304.45 | T64: 304.45 | U64: 304.45 | V64: 304.45 | W64: 304.45 | X64: 304.45 | Y64: 304.45 | Z64: 304.45 | AA64: 274.43
B65: Marketo Bizible | C65: =SUM(D65:AX65) -> 5927.86 | P65: 5927.86
B66: Marketo inc | C66: =SUM(D66:AX66) -> 12619.93 | P66: 12619.93
B67: NCC Group | C67: =SUM(D67:AX67) -> 3750 | P67: 10.27 | Q67: 312.5 | R67: 312.5 | S67: 312.5 | T67: 312.5 | U67: 312.5 | V67: 312.5 | W67: 312.5 | X67: 312.5 | Y67: 312.5 | Z67: 312.5 | AA67: 312.5 | AB67: 302.23
B68: OKTOPOST | C68: =SUM(D68:AX68) -> 8421.32 | P68: 4210.67 | Q68: 4210.65
B69: PCI SECURITY SANDARDS | C69: =SUM(D69:AX69) -> 11954.94 | P69: 1106.66 | Q69: 1106.66 | R69: 1106.66 | S69: 1106.66 | T69: 1106.66 | U69: 1106.66 | V69: 1106.66 | W69: 1106.66 | X69: 1106.66 | Y69: 1106.66 | Z69: 888.34
B70: PFL Tech, Inc - Printing | C70: =SUM(D70:AX70) -> 1379.06 | P70: 1379.06
B71: Postman | C71: =SUM(D71:AX71) -> 6629.17 | P71: 567.06 | Q71: 567.06 | R71: 567.06 | S71: 567.06 | T71: 567.06 | U71: 567.06 | V71: 567.06 | W71: 567.06 | X71: 567.06 | Y71: 567.06 | Z71: 567.06 | AA71: 391.51
B72: Rapid 7 scanner הרשת שלי | C72: =SUM(D72:AX72) -> 8821.51 | P72: 1254.33 | Q72: 1254.33 | R72: 1254.33 | S72: 1254.33 | T72: 1254.33 | U72: 1254.33 | V72: 1254.33 | W72: 41.2
B73: Sales 4/21-3/22 | C73: =SUM(D73:AX73) -> 14850.58 | P73: 4950.2 | Q73: 4950.2 | R73: 4950.18
B74: Salesforce | C74: =SUM(D74:AX74) -> 6669.88 | P74: 1244 | Q74: 1244 | R74: 1244 | S74: 1244 | T74: 1244 | U74: 449.88
B75: Salesforce.com | C75: =SUM(D75:AX75) -> 257518.47 | P75: 47907.36 | Q75: 47907.36 | R75: 47907.36 | S75: 47907.36 | T75: 47907.36 | U75: 17981.67
B76: SalesLoft 7/21-6/22 | C76: =SUM(D76:AX76) -> 18066.24 | P76: 3011.04 | Q76: 3011.04 | R76: 3011.04 | S76: 3011.04 | T76: 3011.04 | U76: 3011.04
B77: Servicenow | C77: =SUM(D77:AX77) -> 10620.51 | P77: 1355.42 | Q77: 1355.42 | R77: 1355.42 | S77: 1355.42 | T77: 1355.42 | U77: 1355.42 | V77: 1355.42 | W77: 1132.57
B78: Shutterstock | C78: =SUM(D78:AX78) -> 316.99 | P78: 269.06 | Q78: 47.93
B79: Storage support renewal | C79: =SUM(D79:AX79) -> 14517.4 | P79: 1572.82 | Q79: 1572.82 | R79: 1572.82 | S79: 1572.82 | T79: 1572.82 | U79: 1572.82 | V79: 155.18 | W79: 206.84 | X79: 1572.82 | Y79: 1572.82 | Z79: 1572.82
B80: Taralex | C80: =SUM(D80:AX80) -> 179.07 | P80: 136.73 | Q80: 42.34
B81: TaskRay 8/21-8/22 | C81: =SUM(D81:AX81) -> 9366.56 | P81: 1185.43 | Q81: 1185.43 | R81: 1185.43 | S81: 1185.43 | T81: 1185.43 | U81: 1185.43 | V81: 1185.43 | W81: 1068.55
B82: Teamviewer | C82: =SUM(D82:AX82) -> 1628.95 | P82: 549 | Q82: 549 | R82: 530.95
B83: Yearly 24\7 support
B84: YourKit 9/21-9/22 | C84: =SUM(D84:AX84) -> 4459 | P84: 526.2 | Q84: 526.2 | R84: 526.2 | S84: 526.2 | T84: 526.2 | U84: 526.2 | V84: 526.2 | W84: 526.2 | X84: 249.4
B85: YWORKS 10/21-10/23 | C85: =SUM(D85:AX85) -> 19018.84 | P85: 872.31 | Q85: 872.31 | R85: 872.31 | S85: 872.31 | T85: 872.31 | U85: 872.31 | V85: 872.31 | W85: 872.31 | X85: 872.31 | Y85: 872.31 | Z85: 872.31 | AA85: 872.31 | AB85: 872.31 | AC85: 872.31 | AD85: 872.31 | AE85: 872.31 | AF85: 872.31 | AG85: 872.31 | AH85: 872.31 | AI85: 872.31 | AJ85: 872.31 | AK85: 700.33
B86: Zapier Futur Charge | C86: =SUM(D86:AX86) -> 1939.81 | S86: 1939.81
B87: Zeplin Inc -לא לשלם שול | C87: =SUM(D87:AX87) -> 373.38 | P87: 373.38
B88: אגרת מכון התקנים 2022 | C88: =SUM(D88:AX88) -> 11492.99 | P88: 957.75 | Q88: 957.75 | R88: 957.75 | S88: 957.75 | T88: 957.75 | U88: 957.75 | V88: 957.75 | W88: 957.75 | X88: 957.75 | Y88: 957.75 | Z88: 957.75 | AA88: 957.74
B89: אואזיס טכנולוגיות תקשורת | C89: =SUM(D89:AX89) -> 4008.98 | P89: 445.44 | Q89: 445.44 | R89: 445.44 | S89: 445.44 | T89: 445.44 | U89: 445.44 | V89: 445.44 | W89: 445.44 | X89: 445.46
B90: אוברליין בע"מ | C90: =SUM(D90:AX90) -> 38799.87 | P90: 2155.55 | Q90: 2155.55 | R90: 2155.55 | S90: 2155.55 | T90: 2155.55 | U90: 2155.55 | V90: 2155.55 | W90: 2155.55 | X90: 2155.55 | Y90: 2155.55 | Z90: 2155.55 | AA90: 2155.55 | AB90: 2155.55 | AC90: 2155.55 | AD90: 2155.55 | AE90: 2155.55 | AF90: 2155.55 | AG90: 2155.52
B91: אונבקאפ בע"מ | C91: =SUM(D91:AX91) -> 17392.32 | P91: 1449.36 | Q91: 1449.36 | R91: 1449.36 | S91: 1449.36 | T91: 1449.36 | U91: 1449.36 | V91: 1449.36 | W91: 1449.36 | X91: 1449.36 | Y91: 1449.36 | Z91: 1449.36 | AA91: 972.86 | AB91: 476.5
B92: איי טי סנטרל סטיישין בע" | C92: =SUM(D92:AX92) -> 105.12 | P92: 105.12
B93: איירונסקיילס 11/21-22 | C93: =SUM(D93:AX93) -> 33699.08 | P93: 3177.52 | Q93: 3177.52 | R93: 3177.52 | S93: 3177.52 | T93: 3177.52 | U93: 3177.52 | V93: 3177.52 | W93: 3177.52 | X93: 3177.52 | Y93: 3177.52 | Z93: 1923.88
B94: אלטשולר שחם | C94: =SUM(D94:AX94) -> 5134.61 | P94: 855.77 | Q94: 855.77 | R94: 855.77 | S94: 855.77 | T94: 855.77 | U94: 855.76
B95: ביטוח 12/21-11/22 | C95: =SUM(D95:AX95) -> 195078.85 | P95: 17734.45 | Q95: 17734.45 | R95: 17734.45 | S95: 17734.45 | T95: 17734.45 | U95: 17734.45 | V95: 17734.45 | W95: 17734.45 | X95: 17734.45 | Y95: 17734.45 | Z95: 17734.35
B96: ביטוח עסק 8/21-7/22 | C96: =SUM(D96:AX96) -> 13046.85 | P96: 1863.83 | Q96: 1863.83 | R96: 1863.83 | S96: 1863.83 | T96: 1863.83 | U96: 1863.83 | V96: 1863.87
B97: דמי חבר 2022 | C97: =SUM(D97:AX97) -> 837.61 | P97: 69.8 | Q97: 69.8 | R97: 69.8 | S97: 69.8 | T97: 69.8 | U97: 69.8 | V97: 69.8 | W97: 69.8 | X97: 69.8 | Y97: 69.8 | Z97: 69.8 | AA97: 69.81
B98: היי בוב 18.12.21-18.1.22 | C98: =SUM(D98:AX98) -> 4018.65 | P98: 4018.65
B99: הרשת שלי פתרונות מחשוב ב | C99: =SUM(D99:AX99) -> 4025.59 | P99: 175.02 | Q99: 175.02 | R99: 175.02 | S99: 175.02 | T99: 175.02 | U99: 175.02 | V99: 175.02 | W99: 175.02 | X99: 175.02 | Y99: 175.02 | Z99: 175.02 | AA99: 175.02 | AB99: 175.02 | AC99: 175.02 | AD99: 175.02 | AE99: 175.02 | AF99: 175.02 | AG99: 175.02 | AH99: 175.02 | AI99: 175.02 | AJ99: 175.02 | AK99: 175.02 | AL99: 175.15
B100: השמה 6/21-6/22 | C100: =SUM(D100:AX100) -> 23203.67 | P100: 4188.6 | Q100: 4188.6 | R100: 4188.6 | S100: 4188.6 | T100: 4188.6 | U100: 2260.67
B101: ויזה - רינת פז | C101: =SUM(D101:AX101) -> 808.12 | P101: 808.12
B102: זיכוי 22.12.21-22.1.21 | C102: =SUM(D102:AX102) -> -3629.46 | P102: -3629.46
B103: חוזה שירות שנתי 2022 | C103: =SUM(D103:AX103) -> 9543.2 | P103: 795.27 | Q103: 795.27 | R103: 795.27 | S103: 795.27 | T103: 795.27 | U103: 795.27 | V103: 795.27 | W103: 795.27 | X103: 795.27 | Y103: 795.27 | Z103: 795.27 | AA103: 795.23
B104: חוזה תמיכה לשנה | C104: =SUM(D104:AX104) -> 7333.32 | P104: 916.67 | Q104: 916.67 | R104: 916.67 | S104: 916.67 | T104: 916.67 | U104: 916.67 | V104: 916.67 | W104: 916.63
...

Sheet Post-Closing Withdrawl Updated
B4: Cash status
C6: 43100 | E6: 43100
D7: Adjustments: | E7: Final
B9: Cash in the bank | C9: =61911000-36400000 -> 25511000 | D9: =C65+C67 -> -232544.27 | E9: =SUM(C9:D9) -> 25278456
B10: Trade receivables Gross | C10: =+C21+10787782 -> 16395782 | D10: =C69+C73+C71 -> -238652.4 | E10: =SUM(C10:D10) -> 16157130
B11: Other accounts receivable | C11: 2681000 | E11: =SUM(C11:D11) -> 2681000
D12: =C75 -> -669000 | E12: =SUM(C12:D12) -> -669000
C13: =SUM(C9:C12) -> 44587782 | E13: =SUM(E9:E12) -> 43447585
B14: Short-term liabilities excluding deferred revenues | C14: =3205000+7541000 -> 10746000 | E14: =SUM(C14:D14) -> 10746000
B15: "Non-GAAP Net Working Capital" | C15: =+C13-C14 -> 33841782 | E15: =+E13-E14 -> 32701585
B20: Cash in the bank | C20: =++C9 -> 25511000 | E20: =SUM(C20:D20) -> 25511000
B21: Trade receivables | C21: 5608000 | E21: =SUM(C21:D21) -> 5608000
B22: Other accounts receivable | C22: =+C11 -> 2681000 | E22: =SUM(C22:D22) -> 2681000
D23: =C75 -> -669000 | E23: =SUM(C23:D23) -> -669000
C24: =SUM(C20:C23) -> 33800000 | E24: =SUM(E20:E23) -> 33131000
B25: Short-term liabilities excluding deferred revenues | C25: =+C14 -> 10746000 | E25: =SUM(C25:D25) -> 10746000
B26: "GAAP - Working capital" | C26: =+C24-C25 -> 23054000 | E26: =+E24-E25 -> 22385000
B30: Trail Balance Net Working Capital Threshold | C30: 22000000 | E30: 22000000
B32: Net Unrestricted Cash Threshold | C32: 15000000 | E32: 15000000
B34: Escrow for indemnification | C34: 6000000 | E34: 6000000
C38: =+C15 -> 33841782 | E38: =+E15 -> 32701585
C39: 22000000 | E39: 22000000
B40: Post-Closing Withdrawl | C40: =+C38-C39 -> 11841782 | E40: =+E38-E39 -> 10701585
C43: FY 2020
C45: Post-Closing Withdrawl updated | D45: 10905008
C47: 2018-2019 Interest | D47: 372000
C49: 1-12.2020 Interest | D49: ='[123]Q4 2020'!$C$20 -> 590958.18
C51: Repayment | D51: =-'[123]3M Payment'!$C$54 -> -3000000
C53: Post-Closing Withdrawl | D53: =SUM(D45:D52) -> 8867966.2
D54: ='New TB INC'!J431+D53 -> 3032045.2
B64: CI proposed adjustments:
B65: 1. Amounts required to be deposited in respect of lease agreements | C65: =-919357/3.4716 -> -264822.27 | E65: Obligation of deposit re new offices as per rent agreement (VDR item "6.3.2.9 שכירות הסכם ברוש- חתום 6.9.2017"), the total deposit amounts to NIS 919,357
C67: 32278 | E67: Deposit in 2017 balance Sheet account #1510001
B69: 2. Amounts required to be deposited in respect of lease agreements | C69: =-(17622.96+8050+3010.08) -> -28683.04 | E69: $29k deposits recorded in Other Receivables (US and UK)
B71: 3. Deferred revenues error | C71: -206636 | E71: Error confirmed by company
B73: 4. Receivables from shareholders, directors, employees | C73: -3333.36 | E73: "Loan to Employees", on-balance sheet, included in Other Receivables
B75: 4. Investment bonus | C75: -669000 | E75: Bonus of $3,000 per employee

Sheet נתונים לשינוי
B1: תאריך הדו"ח | C1: 44561
B2: מספרי השוואה | C2: 44196
B3: לתקופה שהסתיימה | C3: =C1 -> 44561
C4: As at December 31, 2021
B6: =+C1 -> 44561
B7: =C22 -> 3.11 | C7: NIS/USD | D7: שע"ח ממוצע לשנה
B8: =C20 -> 4.2031 | C8: NIS/GBP | D8: 3.2293
B9: =C23 -> 2.2598 | C9: NIS/Aus $
B10: =+$B$7/$B$8 -> 0.73993005 | C10: USD/GBP
B11: =C21 -> 3.5199 | C11: NIS/EUR
B12: =+B11/B8 -> 0.83745331 | C12: Euro/GBP
B13: =+B7/B9 -> 1.376228 | C13: USD/Aus $
B14: =+$B$7/$B$11 -> 0.88354783 | C14: USD/EUR
B15: =+$B$8/$B$9 -> 1.8599434 | C15: GBP/AUD
B17: 74.3025 | C17: USD/Rupee | D17: https://www.fbil.org.in/#/home
C18: =C1 -> 44561
B20: NIS/GBP | C20: 4.2031
B21: NIS/EUR | C21: 3.5199
B22: NIS/USD | C22: 3.11
B23: NIS/AUD | C23: 2.2598
B24: NIS/DKK | C24: 0.4732
B25: NIS/SEK | C25: 0.3436
B26: NIS/CHF | C26: 3.4045
B27: NIS/CAD | C27: 2.4424
B28: USD/SGD | C28: 0.73721
B30: Exchange rates:
B31: SEK | C31: to GBP | D31: =C25/C20 -> 0.081749185
B32: EUR | C32: to GBP | D32: =$C$21/$C$20 -> 0.83745331
B33: DKK | C33: to GBP | D33: =$C$24/$C$20 -> 0.11258357
B34: CHF | C34: to GBP | D34: =C26/C20 -> 0.80999738
B35: USD | C35: to GBP | D35: =C22/C20 -> 0.73993005
B36: CAD | C36: to USD | D36: =$C$27/$C$22 -> 0.78533762
B37: GBP | C37: to USD | D37: =$C$20/$C$22 -> 1.3514791
B38: AUD | C38: to USD | D38: =$C$22/$C$23 -> 1.376228

Sheet תזרים Algosec LTD בש"ח
D2: דו"ח על תזרימי מזומנים - ישראל
D4: י. פתיחה | F4: שנוי | G4: פעילות | H4: פעילות | I4: פעילות | K4: י. סגירה
D5: ='נתונים לשינוי'!$C$2 -> 44196 | F5: במזומנים | G5: שוטפת | H5: מימון | I5: השקעה | J5: טור עזר | K5: ='נתונים לשינוי'!$C$1 -> 44561
A6: מזומנים ושווי מזומנים | D6: 11959 | F6: =K6-D6 -> 5707 | K6: =ROUND(דוחות!C14/1000,0) -> 17666 | L6: =K6-+SUM(D6:J6) -> 0
A7: לקוחות | D7: 4856 | G7: =K7-D7 -> 9061 | K7: =ROUND(דוחות!C19/1000,0) -> 13917 | L7: =K7-+SUM(D7:J7) -> 0
A8: פקדון לזמן קצר | D8: 0 | I8: =K8-D8 -> 0 | L8: =K8-+SUM(D8:J8) -> 0
A9: חייבים ויתרות חובה | D9: 5570 | G9: =K9-D9 -> -1763.2996 | K9: =ROUND((דוחות!C27)/1000,0)+ROUND((דוחות!C39/1000),0)-K7-K14-K10 -> 3806.7004 | L9: =K9-+SUM(D9:J9) -> 0
A10: חייבים ויתרות חובה 606 | D10: =1966 -> 1966 | G10: =K10-D10 -> -50.70043 | K10: ='מאזן בוחן'!J138/1000+ROUND(דוחות!C39/1000,0) -> 1915.2996 | L10: =K10-+SUM(D10:J10) -> 0
A11: פקדון לזמן ארוך | D11: 1529 | I11: =K11-D11 -> -985 | K11: =ROUND(דוחות!C33/1000,0) -> 544 | L11: =K11-+SUM(D11:J11) -> 0
A12: מסים נדחים ויתרות חובה | D12: 0 | G12: =K12-D12 -> 0 | L12: =K12-+SUM(D12:J12) -> 0
A13: רכוש קבוע , נטו | D13: 7224 | G13: =-FA!G15/1000-3 -> -2892.374 | I13: =FA!C15/1000 -> 1375.697 | K13: =ROUND(דוחות!C35/1000,0) -> 5697 | L13: =K13-+SUM(D13:J13) -> -10.323
A14: חברת אם ובנות | D14: 20948 | G14: =K14-D14-J14 -> 15529 | J14: =-J15 -> 0 | K14: =ROUND(דוחות!C26/1000,0)+ROUND(דוחות!C25/1000,0) -> 36477 | L14: =K14-+SUM(D14:J14) -> 0
A15: תשלום מבוסס מניות | D15: 0 | J15: =-G15 -> 0 | K15: 0 | L15: =K15-+SUM(D15:J15) -> 0
A16: בעלי עניין | D16: 0 | G16: =K16-D16 -> 0 | L16: =K16-+SUM(D16:J16) -> 0
A17: ספקים | D17: -5647 | G17: =K17-D17 -> -1443 | K17: =-ROUND(דוחות!J13/1000,0) -> -7090 | L17: =K17-+SUM(D17:J17) -> 0
A18: זכאים ויתרות זכות | D18: -65471 | G18: =K18-D18 -> 10597 | K18: =-ROUND(דוחות!J22/1000,0)-K17-K19 -> -54874 | L18: =K18-+SUM(D18:J18) -> 0
A19: הכנסות נדחות-ז"ק | D19: -5296 | G19: =K19-D19-D20 -> -9538 | K19: =-ROUND(דוחות!J21/1000,0) -> -14834 | L19: =K19-+SUM(D19:J19) -> 0
A20: הכנסות נדחות 606 | L20: =K20-+SUM(D20:J20) -> 0
A21: הכנסות נדחות-ז"א | D21: -3489 | G21: =K21-D21 -> -28479 | K21: =-ROUND(דוחות!J26/1000,0)-ROUND(דוחות!J27/1000,0) -> -31968 | L21: =K21-+SUM(D21:J21) -> 0
A22: עתודה לפצויים | D22: -4262 | G22: =K22-D22-J22 -> -319 | K22: =-ROUND(דוחות!J29/1000,0)+ROUND(דוחות!C37/1000,0) -> -4581 | L22: =K22-+SUM(D22:J22) -> 0
A23: הון מניות | D23: 0 | K23: =-ROUND(דוחות!J32/1000,0) -> 0 | L23: =K23-+SUM(D23:J23) -> 0
A24: קרן הון | D24: 0 | K24: 0 | L24: =K24-+SUM(D24:J24) -> 0
A25: עודפים נסתרים | D25: ='מאזן בוחן'!J520/1000 -> -20037.608 | K25: 0 | L25: =K25-+SUM(D25:J25) -> 20037.608
A26: יתרת הפסד | D26: 51230 | G26: =K26-D26-J26-D25 -> 2350.608 | K26: =-ROUND(דוחות!J38/1000,0)-K23-K24-K25 -> 33543 | L26: =K26-+SUM(D26:J26) -> -20037.608
B27: =SUM(B6:B22) -> 0 | C27: =SUM(C6:C22) -> 0 | D27: =SUM(D6:D26) -> 1079.392 | E27: =SUM(E6:E26) -> 0 | F27: =SUM(F6:F26) -> 5707 | G27: =SUM(G6:G26) -> -6947.766 | H27: =SUM(H6:H26) -> 0 | I27: =SUM(I6:I26) -> 390.697 | J27: =SUM(J6:J26) -> 0 | K27: =SUM(K6:K26) -> 219 | L27: =SUM(L6:L26) -> -10.323
G28: =G26+דוחות!P65/1000 -> -11246.791
D36: =דוחות!A1 -> Algosec System Ltd
D38: דו"ח על תזרימי מזומנים - חברה
D39: Nis
A41: רווח לפי דו"ח רווח והפסד | D41: =-G26 -> -2350.608
A43: נספח א:התאמות הדרושות
A46: פחת והפחתות | D46: =-G13 -> 2892.374
A47: שינוי במיסים נדחים | D47: =-G12 -> 0
A48: הפסד הון ממכירת רכוש קבוע
A49: גידול בלקוחות | D49: =-G7 -> -9061
A50: גידול בספקים | D50: =-G17 -> 1443
A51: שנוי בעתודה לפצויים | D51: =-G22 -> 319
A52: גדול בחיבים ויתרות חובה | D52: =-G9-G14-G10 -> -13715
A53: קיטון בזכאים ויתרות זכות | D53: =-G18 -> -10597
A54: גידול בהתחייבויות לז"ק | D54: =-G19 -> 9538
A55: גידול בהתחייבויות לז"א | D55: =-G21 -> 28479
D56: =SUM(D44:D55) -> 9298.374
A58: הפסד מפעילות שוטפת | D58: =D56+D41 -> 6947.766
A60: פעילות השקעה
A61: השקעה ברכוש אחר - רכישת פטנטים
A62: פקדון לזמן ארוך/קצר | D62: =ROUND(-I11,0)-I8 -> 985
A63: רכישת רכוש קבוע | D63: =-I13 -> -1375.697
D64: =SUM(D61:D63) -> -390.697
A66: פעילות מימון
A67: קיטון באשראי מתאגידים בנקאיים | D67: =-H13 -> 0
A68: התחייבויות לז"א | D68: =-H17 -> 0
A69: הנפקת מניות
A70: הוצאות הנפקת מניות | D70: 0
D71: =SUM(D67:D70) -> 0
A74: שנוי במזומנים | D74: =D71+D64+D58 -> 6557.069
A75: מזומנים לתחילת שנה | D75: =D6 -> 11959
A76: מזומנים לסוף שנה לפי דוח תזרים | D76: =SUM(D74:D75) -> 18516.069
A77: מזומנים לסוף שנה לפי מאזן | D77: ='מאזן בוחן'!J31/1000 -> 17666.223
A78: הפרש | D78: =D76-D77 -> 849.84636

Sheet תזרים מאוחד ב-$
B2: דו"ח על תזרימי מזומנים - מאוחד | M2: מעגל רכוש קבוע - $:
M3: יתרת פתיחה, נטו | N3: =C13 -> 2126
C4: י. פתיחה | D4: שנוי | E4: פעילות | F4: פעילות | G4: פעילות | H4: תנועה שלא | I4: י. סגירה | M4: בתוספת: עלות רכישת רכוש קבוע | N4: =SUM(N17)/1000 -> 573.51864 | O4: =N4+N6-G13-H13 -> -0.3878
C5: ='תזרים Algosec LTD בש"ח'!D5 -> 44196 | D5: במזומנים | E5: שוטפת | F5: מימון | G5: השקעה | H5: במזומן | I5: ='תזרים Algosec LTD בש"ח'!K5 -> 44561 | M5: בניכוי: הוצאות פחת | N5: =-N26/1000 -> -849.60136 | O5: =N5+N7-E13 -> 0
B6: מזומנים ושווי מזומנים | C6: 31701 | D6: =I6-C6 -> 3460 | I6: =ROUND(Consolidation!N10/1000,0) -> 35161 | J6: =I6-+SUM(C6:H6) -> 0 | M6: בניכוי: תמורה שתקבלה ממכירת רכוש קבוע | N6: =-'מאזן בוחן'!$K$556/1000-'New TB INC'!J1027/1000 -> -8.61704
B7: לקוחות | C7: 25035 | E7: =I7-C7 -> 3833 | I7: =ROUND(Consolidation!N11/1000,0) -> 28868 | J7: =I7-+SUM(C7:H7) -> 0 | M7: בתוספת (בניכוי) רווח (הפסד) הון: | N7: =-'מאזן בוחן'!$K$1005/1000-'New TB INC'!J1027/1000 -> -3.68804
B8: חייבים ויתרות חובה | C8: 3404 | E8: =I8-C8 -> 732 | I8: =ROUND(Consolidation!N13/1000,0) -> 4136 | J8: =I8-+SUM(C8:H8) -> 0 | N8: =SUM(N3:N7) -> 1837.6122
B9: פקדון לזמן ארוך | C9: 447 | E9: =I9-C9 -> -264 | I9: =ROUND(Consolidation!N18/1000,0) -> 183 | J9: =I9-+SUM(C9:H9) -> 0 | N9: =N8-I13 -> -0.3878
B10: חייבים זמן ארוך | C10: 1707 | E10: =I10-C10 -> 261 | I10: =+ROUND(Consolidation!N19/1000,0) -> 1968 | J10: =I10-+SUM(C10:H10) -> 0
B11: יעודה לפיצויים | C11: 367 | E11: =I11-C11 -> -114 | I11: =ROUND(Consolidation!N20/1000,0) -> 253 | J11: =I11-+SUM(C11:H11) -> 0 | M11: תוספות לרכוש קבוע:
B12: רכוש אחר-מסים נדחים ז"א | C12: 89 | E12: =I12-C12 -> -15 | I12: =ROUND(Consolidation!N21/1000,0) -> 74 | J12: =I12-+SUM(C12:H12) -> 0 | M12: ישראל | N12: =FA!C32 -> 424073
B13: רכוש קבוע , נטו | C13: 2126 | E13: =N5+N7 -> -853.2894 | G13: =I13-E13-C13-H13 -> 504.37675 | H13: =N29/1000 -> 60.91265 | I13: =ROUND(Consolidation!N25/1000,0) -> 1838 | J13: =I13-+SUM(C13:H13) -> 0 | M13: ארה"ב | N13: =FA!C44 -> 51073
B14: ספקים | C14: -1521 | E14: =I14-C14-H14 -> -992.08735 | H14: =-H13 -> -60.91265 | I14: =-ROUND(Consolidation!N32/1000,0) -> -2574 | J14: =I14-+SUM(C14:H14) -> 0 | M14: אוסטרליה | N14: =FA!C61 -> 9994
B15: זכאים ויתרות זכות | C15: -10922 | E15: =I15-C15 -> 596 | I15: =-ROUND(Consolidation!N33/1000,0) -> -10326 | J15: =I15-+SUM(C15:H15) -> 0 | M15: אירופה | N15: =FA!C92 -> 34266
B16: התחייבות לבעלי מניות | C16: -8868 | E16: =I16-C16 -> 3032 | I16: =-ROUND(Consolidation!N34/1000,0) -> -5836 | J16: =I16-+SUM(C16:H16) -> 0 | M16: הודו | N16: ='מאזן בוחן הודו'!K68-'[19]מאזן בוחן הודו'!$K$62 -> 54112.64
B17: הכנסות נדחות-ז"ק | C17: -29430 | E17: =I17-C17 -> -3486 | I17: =-ROUND(Consolidation!N35/1000,0) -> -32916 | J17: =I17-+SUM(C17:H17) -> 0 | N17: =SUM(N12:N16) -> 573518.64
B18: הכנסות נדחות-ז"א | C18: -15049 | E18: =I18-C18 -> -4181 | I18: =-ROUND(Consolidation!N43/1000,0) -> -19230 | J18: =I18-+SUM(C18:H18) -> 0
B19: עתודה לfin48 | E19: =I19-C19 -> -92 | I19: =-ROUND(Consolidation!N41/1000,0) -> -92 | J19: =I19-+SUM(C19:H19) -> 0
B20: עתודה לפצויים | C20: -1789 | E20: =I20-C20 -> 63 | I20: =-ROUND(Consolidation!N40/1000,0) -> -1726 | J20: =I20-+SUM(C20:H20) -> 0 | M20: הוצאות פחת:
B21: הון מניות | C21: -4 | F21: =I21-C21 -> 0 | I21: =ROUND(-4,0) -> -4 | J21: =I21-+SUM(C21:H21) -> 0 | M21: ישראל | N21: ='מאזן בוחן'!$K$748+'מאזן בוחן'!$K$704 -> 734094.69
B22: Additional paid-in capital | C22: -402.374 | E22: =I22-C22 -> 0 | I22: =ROUND('New TB INC'!J440+'New TB INC'!J441+'New TB INC'!J443,0)/1000 -> -402.374 | J22: =I22-+SUM(C22:H22) -> 0 | M22: ארה"ב | N22: ='New TB INC'!$J$661 -> 87952
B23: Share based compensation | C23: =-10694.298+1 -> -10693.298 | E23: =I23-C23-F23 -> -2260.91 | F23: =-ROUND(SUM('Employee Stock Option Exercised'!C7:C45),0)/1000 -> -392.783 | I23: =ROUND('New TB INC'!J444+'New TB INC'!J445+'מאזן בוחן EUROPE'!K303+'מאזן בוחן EUROPE'!K305,0)/1000 -> -13346.991 | J23: =I23-+SUM(C23:H23) -> 0 | M23: אוסטרליה | N23: ='מאזן בוחן Australia'!$K$223 -> 2302.06
B24: Capital Reserve to Founders | C24: 0 | E24: =I24-C24 -> 0 | I24: =ROUND('New TB INC'!J442/1000,0) -> 0 | J24: =I24-+SUM(C24:H24) -> 0 | M24: אירופה | N24: ='מאזן בוחן EUROPE'!$K$391 -> 6433.08
B25: עודפים | C25: 13803 | E25: =ROUND(I25-C25,0) -> 168 | I25: =-ROUND(Consolidation!N52/1000,0)-ROUND(Consolidation!N51/1000,0)+1 -> 13971 | J25: =I25-+SUM(C25:H25) -> 0 | M25: הודו | N25: ='מאזן בוחן הודו'!$K$232 -> 18819.53
C26: =SUM(C6:C25) -> 0.328 | D26: =SUM(D6:D25) -> 3460 | E26: =SUM(E6:E25) -> -3573.2867 | F26: =SUM(F6:F25) -> -392.783 | G26: =SUM(G6:G25) -> 504.37675 | H26: =SUM(H6:H25) -> 0 | I26: =SUM(I6:I25) -> -1.365 | J26: =SUM(J6:J25) -> 0 | N26: =SUM(N21:N25) -> 849601.36
M28: רכישת רכוש קבוע שלא במזומן:
K29: Cash flows from operating activities: | M29: ישראל | N29: ='[124]ספקים פתוחים'!$O$270 -> 60912.65
B31: =Consolidation!Q77-C31 -> -1 | C31: =ROUND(-E25,0) -> -168 | K31: Net profit (Loss)
