Workbook

Sheet דוח התאמה למס
B2: Papaya Gaming LTD | C2: דוח התאמה 2021
B6: רווח לפני מס 2021 | E6: ='P&L LTD USD'!J83-'P&L LTD USD'!J81 -> -53596018
B8: תיאום הוצאות עודפות:
B9: מחקר ופיתוח - דחיית הוצאות | E9: ='R&D 20A'!G8+'R&D 20A'!G9+'R&D 20A'!H9 -> 23487602 | F9: פריסה על פני 3 שנים
B10: מחקר ופיתוח - הכרה בהוצאות ש"ק | E10: ='R&D 20A'!F7+'R&D 20A'!F8 -> 2898754.6 | F10: בגין הוצאות שמקורן ב 2018-2019
A11: 23031 | B11: הוצאות בגין תשלום מבוסס מניות | E11: =VLOOKUP(A12,'TB LTD 12.21'!D:F,3,0) -> 88061.77
A12: 20060 | B12: הוצאות בגין תשלום מבוסס מניות | E12: =VLOOKUP(A13,'TB LTD 12.21'!D:F,3,0) -> 592674.04
A13: 20048 | B13: הוצאות בגין תשלום מבוסס מניות | E13: =VLOOKUP(A14,'TB LTD 12.21'!D:F,3,0) -> -939915.53
A14: 90017 | B14: גידול בהפרשה לחופשה | E14: =VLOOKUP(A15,'TB LTD 12.21'!D:F,3,0) -> -87155.72
A15: 90018 | B15: גידול בהפרשה להבראה | E15: =VLOOKUP(A16,'TB LTD 12.21'!D:F,3,0) -> 778158.31
A16: 20024 | B16: ארוחות | E16: =VLOOKUP(A17,'TB LTD 12.21'!D:F,3,0) -> 129166.79 | F16: 100% מתואם
A17: ='[1]TB 12.2018'!C7 -> 20001 | B17: כיבודים
B18: עודפות
B19: רווחי אקוויטי | E19: =-'[2]FS ILS 12.20'!E72 -> 0
A20: 20039 | B20: תרומות | E20: =VLOOKUP(A20,'[2]TB LTD 12.20'!$D:$F,3,FALSE)-17586.4 -> #N/A
A21: 20035 | B21: קנסות | E21: =+VLOOKUP(A21,'[2]TB LTD 12.20'!$D:$F,3,FALSE) -> #N/A | F21: קנסות תנועה + מוסדות
E23: =SUM(E9:E21) -> #N/A
N24: כרטיס | O24: תאור | Q24: סה"כ הוצאה | R24: שויים | S24: הוצאה עודפת
B25: הפסד מועבר משנת 2019 | E25: -4245210 | N25: 20014 | O25: מצרכים וכיבודים | Q25: #REF! | S25: =+Q25*0.2 -> #VALUE!
N26: 20021 | O26: מתנות | P26: 90015 | Q26: #REF! | R26: #REF! | S26: =+Q26-R26 -> #VALUE!
B27: הפסד לצרכי מס - מועבר לשנת 2021 | E27: =E6+E23+E25 -> #N/A | F27: =-E27+E25 -> #N/A | N27: 20024 | O27: ארוחות | P27: 90012 | Q27: #REF! | R27: #REF! | S27: =+Q27-R27 -> #VALUE!
N28: 20036 | O28: אירוע חברה | Q28: #REF! | S28: =+Q28 -> #REF!
B29: תרומה להעברה לשנים הבאות לשם קבלת הזיכוי | E29: =+E20 -> #N/A | F29: =+E27-E29 -> #N/A | N29: 20041 | O29: מתנות לעובדים חד פעמי | Q29: #REF! | S29: =+Q29 -> #REF!
S30: =0.45*SUM(S25:S29) -> #VALUE!
C32: USD | D32: NIS | E32: שיעור המס לפי מפעל טכנולוגי מועדף (גישה שמרנית)
B33: נכס מס נדחה בגין הפסד להעברה | C33: =+D33/'[2]FS USD 12.20'!$I$1 -> #N/A | D33: =-E27*E33 -> #N/A | E33: 0.12
A34: 90017 | B34: נכס מס נדחה בגין הפרשה לחופשה | C34: #REF! | D34: =-VLOOKUP(A34,'[2]TB LTD 12.20'!$D:$F,3,FALSE)*$E$34 -> #N/A | E34: 0.12 | O34: התאמת מו"פ
A35: 90018 | B35: נכס מס נדחה בגין הפרשה להבראה | C35: #REF! | D35: =-VLOOKUP(A35,'[2]TB LTD 12.20'!$D:$F,3,FALSE)*$E$35 -> #N/A | E35: 0.12
B36: הוצאות מו״פ שנדחו | C36: =+D36/'[2]FS USD 12.20'!$I$1 -> #DIV/0! | D36: =+SUM(M9:N10)*E36 -> 0 | E36: 0.12 | N36: הוצאות מו"פ | O36: =-'[2]FS ILS 12.20'!E60 -> 0
M38: 23012 | N38: הוצאות הפרשה להבראה מופ | O38: #REF!
M39: 23011 | N39: הוצאות חופשה מופ | O39: #REF!
M40: SBC Expenses R&D | N40: הוצאות בגין תשלום מבוסס מניות | O40: =-E11 -> -88061.77
O41: =SUM(O36:O40) -> -88061.77

Sheet Exp By type
C2: 1
B4: Total revenue
B6: Ua | C6: =SUMIFS('P&L LTD USD'!F:F,'P&L LTD USD'!A:A,'Exp By type'!B6)+SUMIFS('BS & P&L INC '!H:H,'BS & P&L INC '!B:B,'Exp By type'!B6) -> 1.2202517e+08
B7: Fee | C7: =SUMIFS('P&L LTD USD'!F:F,'P&L LTD USD'!A:A,'Exp By type'!B7)+SUMIFS('BS & P&L INC '!H:H,'BS & P&L INC '!B:B,'Exp By type'!B7) -> 9974297.2
B8: Payroll | C8: =SUMIFS('P&L LTD USD'!F:F,'P&L LTD USD'!A:A,'Exp By type'!B8)+SUMIFS('BS & P&L INC '!H:H,'BS & P&L INC '!B:B,'Exp By type'!B8) -> 10705311
B9: Options | C9: =SUMIFS('P&L LTD USD'!F:F,'P&L LTD USD'!A:A,'Exp By type'!B9)+SUMIFS('BS & P&L INC '!H:H,'BS & P&L INC '!B:B,'Exp By type'!B9) -> 1799715.3
B10: Overheads | C10: =SUMIFS('P&L LTD USD'!F:F,'P&L LTD USD'!A:A,'Exp By type'!B10)+SUMIFS('BS & P&L INC '!H:H,'BS & P&L INC '!B:B,'Exp By type'!B10) -> 5791686.4
B11: Financial expenses | C11: =SUMIFS('P&L LTD USD'!F:F,'P&L LTD USD'!A:A,'Exp By type'!B11)+SUMIFS('BS & P&L INC '!H:H,'BS & P&L INC '!B:B,'Exp By type'!B11) -> 2096047.3
B12: Taxes | C12: =SUMIFS('P&L LTD USD'!F:F,'P&L LTD USD'!A:A,'Exp By type'!B12)+SUMIFS('BS & P&L INC '!H:H,'BS & P&L INC '!B:B,'Exp By type'!B12) -> 1430649.1
B13: Ua Indirect | C13: =SUMIFS('P&L LTD USD'!F:F,'P&L LTD USD'!A:A,'Exp By type'!B13)+SUMIFS('BS & P&L INC '!H:H,'BS & P&L INC '!B:B,'Exp By type'!B13) -> 1095956
B14: Depreciation | C14: =SUMIFS('P&L LTD USD'!F:F,'P&L LTD USD'!A:A,'Exp By type'!B14)+SUMIFS('BS & P&L INC '!H:H,'BS & P&L INC '!B:B,'Exp By type'!B14) -> 83930.85
C15: =SUM(C6:C14) -> 1.5500277e+08
C16: =('P&L USD CONS'!I9+'P&L USD CONS'!I13+'P&L USD CONS'!I16+'P&L USD CONS'!I19+'P&L USD CONS'!I27+'P&L USD CONS'!I35)*1000 -> 1.5500277e+08
C17: =C15-C16 -> -0.38000005

Sheet Summary 
B4: Revenues | C4: 2021 | K4: =-4903754 -> -4903754 | L4: SALES TAX
B5: Revenues from commissions | C5: =(K5+K6+K9)*-1 -> -1.6990715e+08 | E5: commissions+ withdrawals | G5: =SUM('BS & P&L INC '!H40:H44) -> 1.7281009e+08 | K5: =SUM('BS & P&L INC '!H40:H44) -> 1.7281009e+08 | L5: commissions
B6: ADJ | C6: =-K4-K7-K8 -> 6836904.5 | G6: ='P&L LTD USD'!F6+'P&L LTD USD'!F7+'BS & P&L INC '!H45 -> -2970603.9 | K6: =-'P&L LTD USD'!F8 -> -3028063.4 | L6: withdrawals
B7: Total revenues | C7: =SUM(C5:C6) -> -1.6307024e+08 | K7: =-'P&L LTD USD'!F7 -> -3485732 | L7: NET CASH
K8: =-'P&L LTD USD'!F6 -> 1552581.5 | L8: ADD
B9: UA- Direct | C9: ='Exp By type'!C6 -> 1.2202517e+08 | K9: 125124 | L9: lasr year
B10: UA -Indirect | C10: ='Exp By type'!C13 -> 1095956
B11: Total Marketing | C11: =SUM(C9:C10) -> 1.2312113e+08
B13: GP | C13: =C7+C11 -> -39949114
B14: % | C14: =C13/C7 -> 0.24498102
B16: Clearing fees | C16: ='Exp By type'!C7 -> 9974297.2
B17: Payroll | C17: ='Exp By type'!C8 -> 10705311
B18: OverHeads | C18: ='Exp By type'!C10 -> 5791686.4
B20: EBITDA (Loss) | C20: =C13+C16+C17+C18 -> -13477820
B21: Options | C21: ='Exp By type'!C9 -> 1799715.3
B22: Depreciation | C22: ='Exp By type'!C14 -> 83930.85
B23: Financial Exp, net | C23: ='Exp By type'!C11 -> 2096047.3
B25: Tax | C25: ='Exp By type'!C12 -> 1430649.1
B27: Net profit (Loss) | C27: =C20+C22+C21+C23+C25 -> -8067477.5

Sheet COA1
A1: כותרת ראשית; | B1: כותרת משנה; | C1: סעיף; | D1: חשבון | E1: תאור חשבון
A2: **1.נכסים | B2: *10.רכוש שוטף | C2: 100.מזומנים ושווי מזומנים | D2: 80020 | E2: בנק לאומי 568400 | F2: BS | G2: Cash
A3: **1.נכסים | B3: *10.רכוש שוטף | C3: 100.מזומנים ושווי מזומנים | D3: 80021 | E3: בנק לאומי 568400 דולרי $ | F3: BS | G3: Cash
A4: **1.נכסים | B4: *10.רכוש שוטף | C4: 100.מזומנים ושווי מזומנים | D4: 80022 | E4: בנק PAYPAL דולרי $ | F4: BS | G4: Cash
A5: **1.נכסים | B5: *10.רכוש שוטף | C5: 100.מזומנים ושווי מזומנים | D5: 80024 | E5: בנק לאומי 568400 אירו E | F5: BS | G5: Cash
A6: **1.נכסים | B6: *10.רכוש שוטף | C6: 100.מזומנים ושווי מזומנים | D6: 80026 | E6: בנק אמריקאי LTD SVB | F6: BS | G6: Cash
A7: **1.נכסים | B7: *10.רכוש שוטף | C7: 100.מזומנים ושווי מזומנים | D7: 80027 | E7: בנק לאומי 568400 לירה שטרלניג | F7: BS | G7: Cash
A8: **1.נכסים | B8: *10.רכוש שוטף | C8: 106.לקוחות | D8: 100000 | E8: לקוחות מזדמנים חול | F8: BS | G8: Account receivable
A9: **1.נכסים | B9: *10.רכוש שוטף | C9: 106.לקוחות | D9: 100001 | E9: FACEBOOK לקוח | F9: BS | G9: Account receivable
A10: **1.נכסים | B10: *10.רכוש שוטף | C10: 106.לקוחות | D10: 100002 | E10: Unity Technologies לקוח | F10: BS | G10: Account receivable
A11: **1.נכסים | B11: *10.רכוש שוטף | C11: 106.לקוחות | D11: 100003 | E11: IronSource Mobile LTD | F11: BS | G11: Account receivable
A12: **1.נכסים | B12: *10.רכוש שוטף | C12: 106.לקוחות | D12: 100004 | E12: ADCOLONY INC לקוח | F12: BS | G12: Account receivable
A13: **1.נכסים | B13: *10.רכוש שוטף | C13: 106.לקוחות | D13: 100005 | E13: Applovin | F13: BS | G13: Account receivable
... A193: **2.התחייבויות | B193: *20.התחייבויות שוטפות | C193: 201.ספקי חו"ל | D193: 200269 | E193: DLA PIPER LLP | F193: BS | G193: Trade payables
A194: **2.התחייבויות | B194: *20.התחייבויות שוטפות | C194: 202.הוצאות לשלם | D194: 204-0 | E194: המחאות לפרעון | F194: BS | G194: Other accounts payable
A195: **2.התחייבויות | B195: *20.התחייבויות שוטפות | C195: 202.הוצאות לשלם | D195: 79999 | E195: הוצאות לשלם | F195: BS | G195: Accrued Expenses
A196: **2.התחייבויות | B196: *20.התחייבויות שוטפות | C196: 207.כרטיסי אשראי | D196: 80005 | E196: ויזה 8214 שקלי | F196: BS | G196: Trade payables
A197: **2.התחייבויות | B197: *20.התחייבויות שוטפות | C197: 207.כרטיסי אשראי | D197: 80006 | E197: ויזה 3711 שקלי | F197: BS | G197: Trade payables
A198: **2.התחייבויות | B198: *20.התחייבויות שוטפות | C198: 207.כרטיסי אשראי | D198: 80007 | E198: ויזה 3612 שקלי | F198: BS | G198: Trade payables
A199: **2.התחייבויות | B199: *20.התחייבויות שוטפות | C199: 207.כרטיסי אשראי | D199: 80008 | E199: ויזה 3612 דולרי | F199: BS | G199: Trade payables
A200: **2.התחייבויות | B200: *20.התחייבויות שוטפות | C200: 207.כרטיסי אשראי | D200: 80010 | E200: ויזה 8214 דולרי | F200: BS | G200: Trade payables
A201: **2.התחייבויות | B201: *20.התחייבויות שוטפות | C201: 208.זכאים אחרים | D201: 51002 | E201: הלוואה SVB 800K | F201: BS | G201: Loan-Long term
A202: **2.התחייבויות | B202: *20.התחייבויות שוטפות | C202: 208.זכאים אחרים | D202: 51018 | E202: הלוואה שנייה SVB 800K | F202: BS | G202: Loan-Long term
A203: **2.התחייבויות | B203: *20.התחייבויות שוטפות | C203: 208.זכאים אחרים | D203: 51019 | E203: הלוואה שלישית $16M | F203: BS | G203: Loan-Short term
A204: **2.התחייבויות | B204: *25.התחייבויות לטווח ארוך | C204: 250.הלוואות לזמן ארוך | D204: 25001 | E204: חלויות שוטפות - הלוואה 1 SVB 800K | F204: BS | G204: Loan-Short term
A205: **2.התחייבויות | B205: *25.התחייבויות לטווח ארוך | C205: 251.צדדים קשורים | D205: 45000 | E205: אוריאל בכר | F205: BS | G205: Other accounts payable
A206: **2.התחייבויות | B206: *25.התחייבויות לטווח ארוך | C206: 251.צדדים קשורים | D206: 51000 | E206: אוריאל בכר חוז בעלים | F206: BS | G206: Shareholders' loan
... A245: **3.הון עצמי | B245: *30.הון עצמי | C245: 304.פרמיה | D245: 80001 | E245: חייבים על חשבון מניות | F245: BS | G245: Other accounts receivable
A246: **4.הכנסות | B246: *40.הכנסות | C246: 400.הכנסות ממכירות בארץ | D246: 4000 | E246: הכנסות מפרסום חייבות במעמ | F246: PL | G246: Revenues | H246: ads revenue
A247: **4.הכנסות | B247: *40.הכנסות | C247: 400.הכנסות ממכירות בארץ | D247: 4001 | E247: הכנסות פטורות ממע'מ | F247: PL | G247: Revenues | H247: ads revenue
A248: **4.הכנסות | B248: *40.הכנסות | C248: 401.הכנסות מיצוא | D248: 4002 | E248: הכנסות פטורות מעמ - פרסום | F248: PL | G248: Revenues | H248: ads revenue
A249: **4.הכנסות | B249: *40.הכנסות | C249: 401.הכנסות מיצוא | D249: 4005 | E249: הכנסות לקבל -תוצאתי | F249: PL | G249: Revenues | H249: =G249 -> Revenues
A250: **5.הוצאות מו"פ | B250: *50.הוצאות מו"פ | C250: 500.עלות מכירות | D250: 21001 | E250: COGS Salary : Support | F250: PL | G250: Cost of revenues | H250: Salary
A251: **5.הוצאות מו"פ | B251: *50.הוצאות מו"פ | C251: 500.עלות מכירות | D251: 21002 | E251: COGS Education fund : Support | F251: PL | G251: Cost of revenues | H251: Salary
A252: **5.הוצאות מו"פ | B252: *50.הוצאות מו"פ | C252: 500.עלות מכירות | D252: 21003 | E252: COGS Social security : Support | F252: PL | G252: Cost of revenues | H252: Salary
A253: **5.הוצאות מו"פ | B253: *50.הוצאות מו"פ | C253: 500.עלות מכירות | D253: 21004 | E253: COGS Gemel : Support | F253: PL | G253: Cost of revenues | H253: Salary
A254: **5.הוצאות מו"פ | B254: *50.הוצאות מו"פ | C254: 500.עלות מכירות | D254: 21005 | E254: COGS Salary : VIP | F254: PL | G254: Marketing expenses | H254: Salary
A255: **5.הוצאות מו"פ | B255: *50.הוצאות מו"פ | C255: 500.עלות מכירות | D255: 21006 | E255: COGS Education fund : VIP | F255: PL | G255: Marketing expenses | H255: Salary
A256: **5.הוצאות מו"פ | B256: *50.הוצאות מו"פ | C256: 500.עלות מכירות | D256: 21007 | E256: COGS Social security : VIP | F256: PL | G256: Marketing expenses | H256: Salary
A257: **5.הוצאות מו"פ | B257: *50.הוצאות מו"פ | C257: 500.עלות מכירות | D257: 21008 | E257: COGS Gemel : VIP | F257: PL | G257: Marketing expenses | H257: Salary
A258: **5.הוצאות מו"פ | B258: *50.הוצאות מו"פ | C258: 500.עלות מכירות | D258: 21009 | E258: COGS Vacation Exp | F258: PL | G258: Cost of revenues | H258: Salary
A259: **5.הוצאות מו"פ | B259: *50.הוצאות מו"פ | C259: 500.עלות מכירות | D259: 21010 | E259: COGS recovery | F259: PL | G259: Cost of revenues | H259: Salary
A260: **5.הוצאות מו"פ | B260: *50.הוצאות מו"פ | C260: 500.עלות מכירות | D260: 61000 | E260: עלות המכירות - החזר הוצ פרס מעל גובה ההשקע | F260: PL | G260: Revenues | H260: withdrawals
A261: **5.הוצאות מו"פ | B261: *50.הוצאות מו"פ | C261: 501.שכר עבודה | D261: 23001 | E261: R&D Salary: Analytics | F261: PL | G261: Research and development expenses, net | H261: Salary
... A293: **5.הוצאות מו"פ | B293: *50.הוצאות מו"פ | C293: 503.שונות מו"פ | D293: 20004 | E293: עיצוב/ גרפיקה | F293: PL | G293: General and administrative expenses | H293: Design Exp
A294: **5.הוצאות מו"פ | B294: *50.הוצאות מו"פ | C294: 503.שונות מו"פ | D294: 23000 | E294: פיתוח מוצר | F294: PL | G294: Research and development expenses, net | H294: Softwere subscription | I294: Upwork
A295: **5.הוצאות מו"פ | B295: *50.הוצאות מו"פ | C295: 503.שונות מו"פ | D295: 23006 | E295: שונות מו"פ | F295: PL | G295: Research and development expenses, net | H295: Softwere subscription | I295: Adobe | J295: Digital River | K295: לבדוק שאפספלייר מויין
A296: **5.הוצאות מו"פ | B296: *50.הוצאות מו"פ | C296: 503.שונות מו"פ | D296: 23009 | E296: ייעוץ מופ | F296: PL | G296: Research and development expenses, net | H296: Softwere subscription | I296: לבדוק ספקםי
A297: **5.הוצאות מו"פ | B297: *50.הוצאות מו"פ | C297: 503.שונות מו"פ | D297: 23010 | E297: תשתיות מופ | F297: PL | G297: Research and development expenses, net | H297: Softwere subscription | I297: לבדוק ספקםי
A298: **6.הוצאות שיווק ומכירה | B298: *60.הוצאות שיווק ומכירה | C298: 600.שכר עבודה שיווק ומכירה | D298: 20051 | E298: S&M Social security: Marketing | F298: PL | G298: Marketing expenses | H298: Salary
A299: **6.הוצאות שיווק ומכירה | B299: *60.הוצאות שיווק ומכירה | C299: 600.שכר עבודה שיווק ומכירה | D299: 20053 | E299: S&M Salary: Marketing | F299: PL | G299: Marketing expenses | H299: Salary
A300: **6.הוצאות שיווק ומכירה | B300: *60.הוצאות שיווק ומכירה | C300: 600.שכר עבודה שיווק ומכירה | D300: 20054 | E300: S&M Education fund: Marketing | F300: PL | G300: Marketing expenses | H300: Salary
A301: **6.הוצאות שיווק ומכירה | B301: *60.הוצאות שיווק ומכירה | C301: 600.שכר עבודה שיווק ומכירה | D301: 20055 | E301: S&M Gemel: Marketing | F301: PL | G301: Marketing expenses | H301: Salary
A302: **6.הוצאות שיווק ומכירה | B302: *60.הוצאות שיווק ומכירה | C302: 600.שכר עבודה שיווק ומכירה | D302: 20057 | E302: הוצאות חופשה שיווק | F302: PL | G302: Marketing expenses | H302: Salary
A303: **6.הוצאות שיווק ומכירה | B303: *60.הוצאות שיווק ומכירה | C303: 600.שכר עבודה שיווק ומכירה | D303: 20058 | E303: הוצאות הפרשה להבראה שיווק | F303: PL | G303: Marketing expenses | H303: Salary
A304: **6.הוצאות שיווק ומכירה | B304: *60.הוצאות שיווק ומכירה | C304: 600.שכר עבודה שיווק ומכירה | D304: 20059 | E304: שירות לקוחות | F304: PL | G304: Cost of revenues | H304: professional fees | I304: אסתר הסקיESTHER HASKY DE BROWN
A305: **6.הוצאות שיווק ומכירה | B305: *60.הוצאות שיווק ומכירה | C305: 601.פרסום ושיווק | D305: 20025 | E305: הוצאות פרסום ושיווק | F305: PL | G305: Marketing expenses | H305: User Acquisition
A306: **7.הוצאות הנהלה וכלליות | B306: *70.הוצאות הנהלה וכלליות | C306: 700.שכר עבודה הנהלה וכלליות | D306: 26000 | E306: G&A Salary: Finance | F306: PL | G306: General and administrative expenses | H306: Salary
A307: **7.הוצאות הנהלה וכלליות | B307: *70.הוצאות הנהלה וכלליות | C307: 700.שכר עבודה הנהלה וכלליות | D307: 26001 | E307: G&A Education fund: Finance | F307: PL | G307: General and administrative expenses | H307: Salary
A308: **7.הוצאות הנהלה וכלליות | B308: *70.הוצאות הנהלה וכלליות | C308: 700.שכר עבודה הנהלה וכלליות | D308: 26002 | E308: G&A Social security: Finance | F308: PL | G308: General and administrative expenses | H308: Salary
A309: **7.הוצאות הנהלה וכלליות | B309: *70.הוצאות הנהלה וכלליות | C309: 700.שכר עבודה הנהלה וכלליות | D309: 26003 | E309: G&A Gemel: Finance | F309: PL | G309: General and administrative expenses | H309: Salary
A310: **7.הוצאות הנהלה וכלליות | B310: *70.הוצאות הנהלה וכלליות | C310: 700.שכר עבודה הנהלה וכלליות | D310: 26006 | E310: הוצאות הפרשה להבראה הנהלה | F310: PL | G310: General and administrative expenses | H310: Salary
A311: **7.הוצאות הנהלה וכלליות | B311: *70.הוצאות הנהלה וכלליות | C311: 700.שכר עבודה הנהלה וכלליות | D311: 26007 | E311: הוצאות חופשה להנהלה | F311: PL | G311: General and administrative expenses | H311: Salary
A312: **7.הוצאות הנהלה וכלליות | B312: *70.הוצאות הנהלה וכלליות | C312: 700.שכר עבודה הנהלה וכלליות | D312: 26011 | E312: G&A Salary: HR | F312: PL | G312: General and administrative expenses | H312: Salary
A313: **7.הוצאות הנהלה וכלליות | B313: *70.הוצאות הנהלה וכלליות | C313: 700.שכר עבודה הנהלה וכלליות | D313: 26012 | E313: G&A Education fund: HR | F313: PL | G313: General and administrative expenses | H313: Salary
A314: **7.הוצאות הנהלה וכלליות | B314: *70.הוצאות הנהלה וכלליות | C314: 700.שכר עבודה הנהלה וכלליות | D314: 26013 | E314: G&A Social security: HR | F314: PL | G314: General and administrative expenses | H314: Salary
A315: **7.הוצאות הנהלה וכלליות | B315: *70.הוצאות הנהלה וכלליות | C315: 700.שכר עבודה הנהלה וכלליות | D315: 26014 | E315: G&A Gemel: HR | F315: PL | G315: General and administrative expenses | H315: Salary
A316: **7.הוצאות הנהלה וכלליות | B316: *70.הוצאות הנהלה וכלליות | C316: 701.צרכי משרד | D316: 20001 | E316: צרכי משרד | F316: PL | G316: General and administrative expenses | H316: Rent and related
... A342: **7.הוצאות הנהלה וכלליות | B342: *70.הוצאות הנהלה וכלליות | C342: 70A.שרותים מקצועיים | D342: 20043 | E342: שירותי השמה/גיוס | F342: PL | G342: Research and development expenses, net | H342: recruitment
A343: **7.הוצאות הנהלה וכלליות | B343: *70.הוצאות הנהלה וכלליות | C343: 70A.שרותים מקצועיים | D343: 20045 | E343: הוצאות שרותים פיננסים | F343: PL | G343: General and administrative expenses | H343: professional fees | I343: PWC
A344: **7.הוצאות הנהלה וכלליות | B344: *70.הוצאות הנהלה וכלליות | C344: 70B.אחזקת מחשב ותוכנות | D344: 20017 | E344: הוצאות תקשורת | F344: PL | G344: General and administrative expenses | H344: communication
A345: **7.הוצאות הנהלה וכלליות | B345: *70.הוצאות הנהלה וכלליות | C345: 70B.אחזקת מחשב ותוכנות | D345: 20020 | E345: רשיון לNet Suite | F345: PL | G345: General and administrative expenses | H345: Softwere subscription
A346: **7.הוצאות הנהלה וכלליות | B346: *70.הוצאות הנהלה וכלליות | C346: 70B.אחזקת מחשב ותוכנות | D346: 20029 | E346: אחזקת מחשבים | F346: PL | G346: Research and development expenses, net | H346: Softwere subscription
A347: **7.הוצאות הנהלה וכלליות | B347: *70.הוצאות הנהלה וכלליות | C347: 70B.אחזקת מחשב ותוכנות | D347: 20031 | E347: הטמעת מערכת NetSuite | F347: PL | G347: General and administrative expenses | H347: Softwere subscription
A348: **8.הוצאות מימון | B348: *80.הוצאות מימון | C348: 800.עמלות בנק | D348: 22000 | E348: עמלות בנק | F348: PL | G348: Financial expenses, net | H348: Bank fee
A349: **8.הוצאות מימון | B349: *80.הוצאות מימון | C349: 800.עמלות בנק | D349: 22003 | E349: ריבית הלוואה ראשונה SVB 800K | F349: PL | G349: Financial expenses, net | H349: Loan interest
A350: **8.הוצאות מימון | B350: *80.הוצאות מימון | C350: 800.עמלות בנק | D350: 22004 | E350: ריבית הלוואה שניה SVB 800K | F350: PL | G350: Financial expenses, net | H350: Loan interest
A351: **8.הוצאות מימון | B351: *80.הוצאות מימון | C351: 800.עמלות בנק | D351: 22005 | E351: ריבית הלוואה שלישית SVB 3M | F351: PL | G351: Financial expenses, net | H351: Loan interest
A352: **8.הוצאות מימון | B352: *80.הוצאות מימון | C352: 802.הפרשי שער | D352: 22222 | E352: הפרשי שער | F352: PL | G352: Financial expenses, net | H352: Exchange rate
A353: **8.הוצאות מימון | B353: *80.הוצאות מימון | C353: 803.ביטולי יתרות | D353: 99999 | E353: ביטולי יתרות | F353: PL | G353: Financial expenses, net | H353: Bank fee
D354: 21011 | E354: Software subscription COGS | F354: PL | G354: Cost of revenues | H354: Softwere subscription
D355: 23033 | E355: Software subscription R&D | F355: PL | G355: Research and development expenses, net | H355: Softwere subscription
D356: 20030 | E356: Software subscription S&M | F356: PL | G356: Marketing expenses | H356: Softwere subscription
D357: 20046 | E357: Software subscription G&A | F357: PL | G357: General and administrative expenses | H357: Softwere subscription
D358: 200000 | F358: BS | G358: Trade payables
D359: 200004 | F359: BS | G359: Trade payables
D360: 200008 | F360: BS | G360: Trade payables
D361: 200010 | F361: BS | G361: Trade payables
D362: 200015 | F362: BS | G362: Trade payables
D363: 20003 | F363: PL | G363: General and administrative expenses | H363: Travel Parking and transportation
D364: 200033 | F364: BS | G364: Trade payables
D365: 200034 | F365: BS | G365: Trade payables
D366: 200054 | F366: BS | G366: Trade payables
D367: 200057 | F367: BS | G367: Trade payables
D368: 200062 | F368: BS | G368: Trade payables
D369: 200064 | F369: BS | G369: Trade payables
D370: 200066 | F370: BS | G370: Trade payables
D371: 200069 | F371: BS | G371: Trade payables
D372: 200076 | F372: BS | G372: Trade payables
D373: 200078 | F373: BS | G373: Trade payables
...

Sheet FS
A1: 44561
A2: FS
A3: Papaya Gaming Ltd
A4: USD
A7: BS | F7: PL
C10: 44561 | H10: 44561
C11: Consolidated | H11: Consolidated
B14: CURRENT ASSETS | G14: Total Revenues | H14: ='P&L USD CONS'!I7 -> -163070.24
B16: Cash | C16: =(SUMIF('BS LTD USD '!B:B,$B16,'BS LTD USD '!F:F)+SUMIF('BS & P&L INC '!D:D,$B16,'BS & P&L INC '!H:H))/1000 -> 48515.492 | G16: Cost of revenues | H16: ='P&L USD CONS'!I9 -> 12204.051
A17: Deposit | B17: Restricted cash | C17: =(SUMIF('BS LTD USD '!B:B,$A17,'BS LTD USD '!F:F)+SUMIF('BS & P&L INC '!D:D,$A17,'BS & P&L INC '!H:H))/1000 -> 16.07717 | G17: Gross loss (profit) | H17: ='P&L USD CONS'!I10 -> -150866.19
B18: Account receivable | C18: =(SUMIF('BS LTD USD '!B:B,$B18,'BS LTD USD '!F:F)+SUMIF('BS & P&L INC '!D:D,$B18,'BS & P&L INC '!H:H))/1000 -> 1196.0119
B19: Shareholders' loan | C19: =(SUMIF('BS LTD USD '!B:B,$B19,'BS LTD USD '!F:F)+SUMIF('BS & P&L INC '!D:D,$B19,'BS & P&L INC '!H:H))/1000 -> 0
A20: Other accounts receivable | B20: Prepaid exepnses and other current assets | C20: =(SUMIF('BS LTD USD '!B:B,$A20,'BS LTD USD '!F:F)+SUMIF('BS & P&L INC '!D:D,$A20,'BS & P&L INC '!H:H))/1000+'BS USD CONS '!L16 -> 2484.7225 | G20: Research and development expenses, net | H20: ='P&L USD CONS'!I13 -> 11109.841
C21: =SUM(C16:C20) -> 52212.304
B23: NON-CURRENT ASSETS | G23: Marketing expenses | H23: ='P&L USD CONS'!I16 -> 124286.33
B25: Property and equipment, net | C25: =(SUMIF('BS LTD USD '!B:B,$A26,'BS LTD USD '!F:F)+SUMIF('BS & P&L INC '!D:D,$A26,'BS & P&L INC '!H:H))/1000 -> 501.8953
A26: Fixed assets, net | B26: ROU Assets | C26: ='BS USD CONS '!L23 -> 409.12167 | G26: General and administrative expenses | H26: ='P&L USD CONS'!I19 -> 3875.8447
A27: Reserve - Wordpay | B27: Long term restricted cash | C27: =+(SUMIF('BS LTD USD '!B:B,$A27,'BS LTD USD '!F:F)+SUMIF('BS & P&L INC '!D:D,$A27,'BS & P&L INC '!H:H))/1000 -> 199.999
B28: Deffered Tax | C28: ='BS USD CONS '!L24 -> 939.40895
C29: =SUM(C25:C28) -> 2050.4249
G30: Operating expenses | H30: ='P&L USD CONS'!I23 -> 139272.02
B31: Total Assets | C31: =C29+C21 -> 54262.729
G32: Operating loss (profit) | H32: ='P&L USD CONS'!I25 -> -11594.171
B34: CURRENT LIABILITIES | G34: Financial expenses, net | H34: ='P&L USD CONS'!I27 -> 2096.0473
A36: Trade payables | B36: Account payables | C36: =(SUMIF('BS LTD USD '!B:B,$A36,'BS LTD USD '!F:F)+SUMIF('BS & P&L INC '!D:D,$A36,'BS & P&L INC '!H:H))/1000 -> -13433.835 | G36: TP Expenses | H36: ='P&L USD CONS'!I29 -> 0
A37: Loan-Short Term | B37: Current maurities of short term loan | C37: =(SUMIF('BS LTD USD '!B:B,$A37,'BS LTD USD '!F:F)+SUMIF('BS & P&L INC '!D:D,$A37,'BS & P&L INC '!H:H))/1000 -> -2033.334
B38: Contract liability | C38: =(SUMIF('BS LTD USD '!B:B,$B38,'BS LTD USD '!F:F)+SUMIF('BS & P&L INC '!D:D,$B38,'BS & P&L INC '!H:H))/1000 -> -4087.657 | G38: Equity | H38: ='P&L USD CONS'!I31 -> 0
B39: Related Party-AP | C39: =(SUMIF('BS LTD USD '!B:B,$B39,'BS LTD USD '!F:F)+SUMIF('BS & P&L INC '!D:D,$B39,'BS & P&L INC '!H:H))/1000 -> 0
A40: Accrued expenses | B40: ROA Liability | C40: =(SUMIF('BS LTD USD '!B:B,$B40,'BS LTD USD '!F:F)+SUMIF('BS & P&L INC '!D:D,$B40,'BS & P&L INC '!H:H))/1000 -> -385.35969 | G40: loss before taxes | H40: ='P&L USD CONS'!I33 -> -9498.1238
A41: Other accounts payable | B41: Other accounts payable and accrued expenses | C41: =(SUMIF('BS LTD USD '!B:B,$A41,'BS LTD USD '!F:F)+SUMIF('BS & P&L INC '!D:D,$A41,'BS & P&L INC '!H:H))/1000+(SUMIF('BS LTD USD '!B:B,$A40,'BS LTD USD '!F:F)+SUMIF('BS & P&L INC '!D:D,$A40,'BS & P&L INC '!H:H))/1000+'BS USD CONS '!L38 -> -20587.203
C42: =SUM(C36:C41) -> -40527.389 | G42: Tax expenses | H42: ='P&L USD CONS'!I35 -> 1430.6491
A44: Loan-Long Term | B44: Current maurities of long term loan | C44: =(SUMIF('BS LTD USD '!B:B,$A44,'BS LTD USD '!F:F)+SUMIF('BS & P&L INC '!D:D,$A44,'BS & P&L INC '!H:H))/1000 -> -533.33272 | G44: Net loss ( profit ) | H44: ='P&L USD CONS'!I37 -> -8067.4747
B45: Shareholders | C45: =(SUMIF('BS LTD USD '!B:B,$B45,'BS LTD USD '!F:F)+SUMIF('BS & P&L INC '!D:D,$B45,'BS & P&L INC '!H:H))/1000 -> -500
B46: Convertible Loan | C46: =(SUMIF('BS LTD USD '!B:B,$B46,'BS LTD USD '!F:F)+SUMIF('BS & P&L INC '!D:D,$B46,'BS & P&L INC '!H:H))/1000 -> 0
C47: =SUM(C44:C46) -> -1033.3327
B49: Total liabilities | C49: =C47+C42 -> -41560.722
B51: SHAREHOLDERS' EQUITY
B53: Share capital - Ordinary Shares | C53: =(SUMIF('BS LTD USD '!B:B,$B53,'BS LTD USD '!F:F)+SUMIF('BS & P&L INC '!D:D,$B53,'BS & P&L INC '!H:H))/1000 -> -0.41892
B54: Share capital - Preferred Seed-1 | C54: =(SUMIF('BS LTD USD '!B:B,$B54,'BS LTD USD '!F:F)+SUMIF('BS & P&L INC '!D:D,$B54,'BS & P&L INC '!H:H))/1000 -> -0.191
A55: PL | B55: Share capital - Preferred Seed | C55: =(SUMIF('BS LTD USD '!B:B,$B55,'BS LTD USD '!F:F)+SUMIF('BS & P&L INC '!D:D,$B55,'BS & P&L INC '!H:H))/1000 -> -0.04924
B56: Share premium | C56: =(SUMIF('BS LTD USD '!B:B,$B56,'BS LTD USD '!F:F)+SUMIF('BS & P&L INC '!D:D,$B56,'BS & P&L INC '!H:H))/1000 -> -8614.9081
B57: Receivables for shares issued | C57: =(SUMIF('BS LTD USD '!B:B,$B57,'BS LTD USD '!F:F)+SUMIF('BS & P&L INC '!D:D,$B57,'BS & P&L INC '!H:H))/1000 -> 0
B58: Accumulated deficit | C58: =(SUMIF('BS LTD USD '!B:B,$B58,'BS LTD USD '!F:F)+SUMIF('BS & P&L INC '!D:D,$B58,'BS & P&L INC '!H:H))/1000+(SUMIF('BS LTD USD '!B:B,$A55,'BS LTD USD '!F:F)+SUMIF('BS & P&L INC '!D:D,$A55,'BS & P&L INC '!H:H))/1000+('BS USD CONS '!H59+'BS USD CONS '!H60)/1000 -> -4086.4396
C59: =SUM(C53:C58) -> -12702.007
B61: Total Equity | C61: =C59+C49 -> -54262.728
B64: Check | C64: =C61+C31 -> 0.00016999999

Sheet FS Notes
A1: 44561
A2: FS Notes
A3: Papaya Gaming Ltd
A4: USD
B7: Note 3 - Property and Equipment, Net
F8: Signed FS
B9: Group | D9: 44561 | F9: 44196
B10: Computers and electronic equipment | D10: ='TB LTD 12.21'!G33/1000 -> 367.919 | F10: 96
B11: Vehicles | D11: ='TB LTD 12.21'!G31/1000 -> 2.80932 | F11: 3
B12: Office furniture and equipment | D12: =('TB LTD 12.21'!G35+'TB LTD 12.21'!G40)/1000 -> 204.18 | F12: 10
B13: Leasehold improvements | D13: ='TB LTD 12.21'!G36/1000 -> 36.289 | F13: 3
D14: =SUM(D10:D13) -> 611.19732 | F14: =SUM(F10:F13) -> 112
B15: Less – accumulated depreciation | D15: =SUM('TB LTD 12.21'!G32,'TB LTD 12.21'!G34,'TB LTD 12.21'!G37,'TB LTD 12.21'!G38,'TB LTD 12.21'!G39)/1000-'AJE 2021'!H75/1000 -> -169.28042 | F15: -31
B16: Total property and equipment, net | D16: =SUM(D14:D15) -> 441.9169 | F16: =SUM(F14:F15) -> 81
B20: Note 5 - Other current Liabilities
F21: Signed FS
B22: Group | D22: 44561 | F22: 44196 | I22: Other current liabilities INC
B23: Accrued expenses | D23: =-'TB LTD 12.21'!G105/1000-(O25+O24+O26)/1000 -> 11178.135 | F23: 622 | I23: Entity | K23: Account | M23: 44196 | O23: 44561
B24: Payroll and related expenses | D24: =-SUM('TB LTD 12.21'!G19:G28)/1000 -> 787.95071 | F24: 372 | I24: INC | K24: SVB Commission | M24: -125276.67 | O24: -518442.74
B25: WHT | D25: =-'TB LTD 12.21'!G9/1000 -> 123.88293 | F25: 0 | I25: INC | K25: WorldPay Commission | M25: 0 | O25: -35916.02
B26: Income tax payable | D26: =-O27/1000 -> 101.4614 | F26: 0 | I26: INC | K26: James Kong | M26: 0 | O26: -8333.33
B27: Sales Tax | D27: ='AJE 2021'!H80/1000 -> 4903.7544 | F27: 0 | I27: INC | K27: Income tax payable | M27: 714 | O27: -101461.4
D28: =SUM(D23:D27) -> 17095.185 | F28: =SUM(F23:F27) -> 994
B31: Note 11 - Supplementary statements of operation information
F32: Signed FS
B33: a. Research and development expenses: | D33: 44561 | F33: 44196
B34: Payroll and related expenses | D34: =SUM('TB LTD 12.21'!G173,'TB LTD 12.21'!G187:G232,'TB LTD 12.21'!G249,'TB LTD 12.21'!G251,'TB LTD 12.21'!G253)/1000 -> 7099.7379 | F34: 1089
B35: Computer Maintenance | D35: =('TB LTD 12.21'!G350)/1000 -> 85.34424 | F35: 159
B36: Software subscription | D36: =SUM('TB LTD 12.21'!G238,'TB LTD 12.21'!G241,'TB LTD 12.21'!G243:G244,'TB LTD 12.21'!G247,'TB LTD 12.21'!G250)/1000 -> 928.35154 | F36: 0
B37: Professional consulting | D37: =SUM('TB LTD 12.21'!G239+'TB LTD 12.21'!G240+'TB LTD 12.21'!G254+'TB LTD 12.21'!G236)/1000 -> 325.46562 | F37: 535
B38: Share-based compensation | D38: ='TB LTD 12.21'!G245/1000+'P&L LTD USD'!E30/1000 -> 1013.82 | F38: 370
B39: Hosting and Servers | D39: ='TB LTD 12.21'!G252/1000 -> 683.8814 | F39: 0
B40: Other | D40: =SUM('TB LTD 12.21'!G233,'TB LTD 12.21'!G234,'TB LTD 12.21'!G237,'TB LTD 12.21'!G242,'TB LTD 12.21'!G246,'TB LTD 12.21'!G248)/1000 -> 973.24008 | F40: 144
D41: =SUM(D34:D40) -> 11109.841 | F41: =SUM(F34:F40) -> 2297
F43: Signed FS
B44: b. Marketing expenses: | D44: 44561 | F44: 44196
B45: Payroll and related expenses | D45: =SUM('TB LTD 12.21'!G255:G260,'TB LTD 12.21'!G262:G269,'TB LTD 12.21'!G279)/1000 -> 993.65178 | F45: 314
B46: Marketing and Advertising | D46: =SUM('TB LTD 12.21'!G270,'TB LTD 12.21'!G273,'TB LTD 12.21'!G275:G277,'TB LTD 12.21'!G329)/1000 -> 122701.85 | F46: 12695
B47: Software subscription | D47: =SUM('TB LTD 12.21'!G271:G272,'TB LTD 12.21'!G280)/1000 -> 419.27489 | F47: 0
B48: Share-based compensation | D48: ='TB LTD 12.21'!G281/1000+'P&L LTD USD'!E41/1000 -> 4.8493898 | F48: 0
B49: Other | D49: =SUM('TB LTD 12.21'!G274,,'TB LTD 12.21'!G282)/1000 -> 166.7031 | F49: 36
D50: =SUM(D45:D49) -> 124286.33 | F50: =SUM(F45:F49) -> 13045
F52: Signed FS
B53: c. General and administrative expenses: | D53: 44561 | F53: 44196
B54: Payroll and related expenses | D54: =SUM('TB LTD 12.21'!G283:G297,'TB LTD 12.21'!G337,'TB LTD 12.21'!G347)/1000 -> 1913.0526 | F54: 168
B55: Legal expenses | D55: ='TB LTD 12.21'!G340/1000 -> 413.17721 | F55: 297
B56: Professional services | D56: =SUM('TB LTD 12.21'!G336,'TB LTD 12.21'!G338:G339,'TB LTD 12.21'!G341,'TB LTD 12.21'!G344)/1000 -> 538.87834 | F56: 145
B57: Rent and maintenance | D57: =SUM('TB LTD 12.21'!G298,'TB LTD 12.21'!G302:G305)/1000 -> 365.17833 | F57: 12
B58: Depreciation | D58: =SUM('TB LTD 12.21'!G306:G310,'TB LTD 12.21'!G315)/1000 -> 83.93085 | F58: 20
B59: Software subscription | D59: =SUM('TB LTD 12.21'!G342+'TB LTD 12.21'!G349+'TB LTD 12.21'!G351)/1000 -> 84.44026 | F59: 0
B60: Share-based compensation | D60: ='TB LTD 12.21'!G332/1000 -> 152.451 | F60: 58
B61: Other | D61: =SUM('TB LTD 12.21'!G235,'TB LTD 12.21'!G278,'TB LTD 12.21'!G299:G301,'TB LTD 12.21'!G311:G314,'TB LTD 12.21'!G316:G328,'TB LTD 12.21'!G330:G331,'TB LTD 12.21'!G333:G334,'TB LTD 12.21'!G343,'TB LTD 12.21'!G345:G346,'TB LTD 12.21'!G348)/1000 -> -307.34969 | F61: 19 | G61: Including Allocation
D62: =SUM(D54:D61) -> 3243.7589 | F62: =SUM(F54:F61) -> 719

Sheet P&L USD CONS
D3: 44561 | F3: 44561 | G3: Cons | I3: 44561
D4: LTD | F4: INC | I4: Consolidated
I5: $ In thousands
B7: Total Revenues | D7: =SUMIF('P&L LTD USD'!C:C,B:B,'P&L LTD USD'!F:F) -> -1.6307024e+08 | F7: =-SUMIF('BS & P&L INC '!C:C,'P&L USD CONS'!$B:$B,'BS & P&L INC '!H:H) -> -1.9482323e+08 | G7: =-F7 -> 1.9482323e+08 | I7: =(+F7+D7+G7)/1000 -> -163070.24
B9: Cost of revenues | D9: =SUMIF('P&L LTD USD'!C:C,B:B,'P&L LTD USD'!F:F) -> 12753463 | F9: =SUMIF('BS & P&L INC '!C:C,'P&L USD CONS'!$B:$B,'BS & P&L INC '!H:H) -> 10174297 | G9: =-F9*1.054 -> -10723709 | I9: =(+F9+D9+G9)/1000 -> 12204.051 | J9: =-I9+12732 -> 527.94924
B10: Gross loss (profit) | D10: =D9+D7 -> -1.5031678e+08 | F10: =F9+F7 -> -1.8464893e+08 | G10: =G9+G7 -> 1.8409952e+08 | I10: =I9+I7 -> -150866.19
I11: =-I9/I7 -> 0.074839227
B13: Research and development expenses, net | D13: =SUMIF('P&L LTD USD'!C:C,B:B,'P&L LTD USD'!F:F) -> 11109841 | F13: =SUMIF('BS & P&L INC '!C:C,'P&L USD CONS'!$B:$B,'BS & P&L INC '!H:H) -> 0 | I13: =(+F13+D13+G13)/1000 -> 11109.841
I14: =-I13/I7 -> 0.068129174
B16: Marketing expenses | D16: =SUMIF('P&L LTD USD'!C:C,B:B,'P&L LTD USD'!F:F) -> 1.2428633e+08 | F16: =SUMIF('BS & P&L INC '!C:C,'P&L USD CONS'!$B:$B,'BS & P&L INC '!H:H) -> 16152223 | G16: =-F16 -> -16152223 | I16: =(+F16+D16+G16)/1000 -> 124286.33
I17: =-I16/I7 -> 0.76216441
B19: General and administrative expenses | D19: =SUMIF('P&L LTD USD'!C:C,B:B,'P&L LTD USD'!F:F) -> 3877943.4 | F19: =SUMIF('BS & P&L INC '!C:C,'P&L USD CONS'!$B:$B,'BS & P&L INC '!H:H) -> 38866.25 | G19: =-F19*1.054 -> -40965.028 | I19: =(+F19+D19+G19)/1000 -> 3875.8447 | J19: =-I19+3238 -> -637.84466
I21: =-I19/I7 -> 0.023767946
B23: Operating expenses | D23: =+D19+D16+D13 -> 1.3927412e+08 | E23: =+E19+E16+E13 -> 0 | F23: =+F19+F16+F13 -> 16191089 | G23: =+G19+G16+G13 -> -16193188 | I23: =+I19+I16+I13 -> 139272.02
B25: Operating loss (pprofit) | D25: =SUMIF('P&L LTD USD'!C:C,B:B,'P&L LTD USD'!F:F) -> -11042660 | F25: =F10+F23 -> -1.6845784e+08 | G25: =G10+G23 -> 1.6790633e+08 | I25: =I23+I10 -> -11594.171
B27: Financial expenses, net | D27: =SUMIF('P&L LTD USD'!C:C,B:B,'P&L LTD USD'!F:F) -> 1934278.3 | F27: =SUMIF('BS & P&L INC '!C:C,'P&L USD CONS'!$B:$B,'BS & P&L INC '!H:H) -> 161769.01 | I27: =(+F27+D27+G27)/1000 -> 2096.0473 | J27: =-I27+483 -> -1613.0473
B29: TP Expenses | D29: =SUMIF('P&L LTD USD'!C:C,B:B,'P&L LTD USD'!F:F) -> 0 | F29: =SUMIF('BS & P&L INC '!C:C,'P&L USD CONS'!$B:$B,'BS & P&L INC '!H:H) -> 1.6790633e+08 | G29: =-F29 -> -1.6790633e+08 | I29: =(+F29+D29+G29)/1000 -> 0
B31: Equity | D31: =SUMIF('P&L LTD USD'!C:C,B:B,'P&L LTD USD'!F:F) -> -258145.04 | F31: =-SUMIF('BS & P&L INC '!C:C,'P&L USD CONS'!$B:$B,'BS & P&L INC '!F:F) -> 0 | G31: =-D31 -> 258145.04 | I31: =(+F31+D31+G31)/1000 -> 0
M32: Exchange rate | N32: -30318.74 | P32: -30318.74
B33: loss before taxes | D33: =SUM(D25:D31) -> -9366527.1 | F33: =SUM(F25:F31) -> -389741.81 | G33: =SUM(G25:G31) -> 258145.04 | I33: =SUM(I25:I31) -> -9498.1238 | J33: =I33+17352 -> 7853.8762 | M33: Financial expenses | N33: 0 | O33: 1286.6572 | P33: 1286.6572
B35: Tax expenses | D35: =SUMIF('P&L LTD USD'!C:C,B:B,'P&L LTD USD'!F:F) -> 1299052.3 | F35: =SUMIF('BS & P&L INC '!C:C,'P&L USD CONS'!$B:$B,'BS & P&L INC '!H:H) -> 131596.77 | I35: =(+F35+D35+G35)/1000 -> 1430.6491 | J35: =-I35+2266 -> 835.3509 | M35: Epricing Fee -Currency difference | N35: 111676 | P35: 111676
M36: Exchange rate paypal | N36: 48647 | P36: 48647
B37: Net loss ( profit ) | D37: =+D33+D35 -> -8067474.7 | F37: =+F35+F33 -> -258145.04 | G37: =+G35+G33 -> 258145.04 | I37: =+I33+I35 -> -8067.4747 | J37: =I37+15086 -> 7018.5253
K38: =I35+I27+I19+I16+I13+I9 -> 155002.77
D39: ='P&L LTD USD'!AD83 -> 0 | G39: Old Arkava | I39: -14564.324
G41: GAP | I41: =I37-I39 -> 6496.8494
D43: =('P&L USD CONS'!I9+'P&L USD CONS'!I13+'P&L USD CONS'!I16+'P&L USD CONS'!I19+'P&L USD CONS'!I27+'P&L USD CONS'!I35)*1000 -> 1.5500277e+08 | I43: ='BS & P&L INC '!H45/1000 -> -4903.7544 | K43: Sales Tax
I44: =-'AJE 2021'!G48/1000 -> -225.333 | K44: Net cash
I45: -156 | K45: Option
I46: ='AJE 2021'!H89/1000 -> 0 | K46: Israeli Tax
G47: Check | I47: =SUM(I43:I46)+I41 -> 1211.762

Sheet BS USD CONS 
D3: 44561 | F3: =D3 -> 44561 | H3: איחוד | J3: =F3 -> 44561 | L3: =J3 -> 44561
D4: LTD | F4: INC | J4: Consolidated | L4: Consolidated
D5: USD | F5: USD | J5: $ round | L5: $ In thousands
B6: CURRENT ASSETS
B8: Cash | D8: =SUMIF('BS LTD USD '!B:B,'BS USD CONS '!$B8,'BS LTD USD '!F:F) -> 12155821 | F8: =SUMIF('BS & P&L INC '!D:D,'BS USD CONS '!$B8,'BS & P&L INC '!H:H) -> 36359671 | J8: =+F8+D8 -> 48515492 | L8: =J8/1000 -> 48515.492
B9: Account receivable | D9: =SUMIF('BS LTD USD '!B:B,'BS USD CONS '!$B9,'BS LTD USD '!F:F) -> 1196011.9 | F9: =SUMIF('BS & P&L INC '!D:D,'BS USD CONS '!$B9,'BS & P&L INC '!H:H) -> 0 | J9: =+F9+D9 -> 1196011.9 | L9: =J9/1000 -> 1196.0119
B10: Related Party | D10: =SUMIF('BS LTD USD '!B:B,'BS USD CONS '!$B10,'BS LTD USD '!F:F) -> 32471839 | F10: =SUMIF('BS & P&L INC '!D:D,'BS USD CONS '!$B10,'BS & P&L INC '!H:H) -> -32471840 | J10: =+F10+D10 -> -1.38 | L10: =J10/1000 -> -0.00138
B11: Related Party-AR | D11: =SUMIF('BS LTD USD '!B:B,'BS USD CONS '!$B11,'BS LTD USD '!F:F) -> 0 | F11: =SUMIF('BS & P&L INC '!D:D,'BS USD CONS '!$B11,'BS & P&L INC '!H:H) -> 0 | J11: =+F11+D11 -> 0 | L11: =J11/1000 -> 0
B12: Related Party-AP | D12: =SUMIF('BS LTD USD '!B:B,'BS USD CONS '!$B12,'BS LTD USD '!F:F) -> 0 | F12: =SUMIF('BS & P&L INC '!D:D,'BS USD CONS '!$B12,'BS & P&L INC '!H:H) -> 0 | J12: =+F12+D12 -> 0 | L12: =J12/1000 -> 0
B13: Temporary account | D13: =SUMIF('BS LTD USD '!B:B,'BS USD CONS '!$B13,'BS LTD USD '!F:F) -> 0 | F13: =SUMIF('BS & P&L INC '!D:D,'BS USD CONS '!$B13,'BS & P&L INC '!H:H) -> 0 | J13: =+F13+D13 -> 0 | L13: =J13/1000 -> 0
B14: Deposit | D14: =SUMIF('BS LTD USD '!B:B,'BS USD CONS '!$B14,'BS LTD USD '!F:F) -> 16077.17 | F14: =SUMIF('BS & P&L INC '!D:D,'BS USD CONS '!$B14,'BS & P&L INC '!H:H) -> 0 | J14: =+F14+D14 -> 16077.17 | L14: =J14/1000 -> 16.07717
B15: Shareholders' loan | D15: =SUMIF('BS LTD USD '!B:B,'BS USD CONS '!$B15,'BS LTD USD '!F:F) -> 0 | F15: =SUMIF('BS & P&L INC '!D:D,'BS USD CONS '!$B15,'BS & P&L INC '!H:H) -> 0 | J15: =+F15+D15 -> 0 | L15: =J15/1000 -> 0
B16: Prepaid | D16: =SUMIF('BS LTD USD '!B:B,'BS USD CONS '!$B16,'BS LTD USD '!F:F) -> 1034254.4 | F16: =SUMIF('BS & P&L INC '!D:D,'BS USD CONS '!$B16,'BS & P&L INC '!H:H) -> 0 | J16: =+F16+D16 -> 1034254.4 | L16: =J16/1000 -> 1034.2544
B17: Other accounts receivable | D17: =SUMIF('BS LTD USD '!B:B,'BS USD CONS '!$B17,'BS LTD USD '!F:F) -> 1450468.1 | F17: =SUMIF('BS & P&L INC '!D:D,'BS USD CONS '!$B17,'BS & P&L INC '!H:H) -> 0 | J17: =+F17+D17 -> 1450468.1 | L17: =J17/1000 -> 1450.4681
D18: =SUM(D8:D17) -> 48324471 | F18: =SUM(F8:F17) -> 3887831 | H18: =SUM(H8:H17) -> 0 | J18: =+F18+D18 -> 52212302 | L18: =J18/1000 -> 52212.302
B20: NON-CURRENT ASSETS
B22: Investment | D22: =SUMIF('BS LTD USD '!B:B,'BS USD CONS '!$B22,'BS LTD USD '!F:F) -> 297519.04 | F22: =SUMIF('BS & P&L INC '!D:D,'BS USD CONS '!$B22,'BS & P&L INC '!H:H) -> 0 | H22: =-D22 -> -297519.04 | J22: =+F22+D22+H22 -> 0 | L22: =J22/1000 -> 0
B23: ROA Assets | D23: =SUMIF('BS LTD USD '!B:B,'BS USD CONS '!$B23,'BS LTD USD '!F:F) -> 409121.67 | F23: =SUMIF('BS & P&L INC '!D:D,'BS USD CONS '!$B23,'BS & P&L INC '!H:H) -> 0 | J23: =+F23+D23+H23 -> 409121.67 | L23: =J23/1000 -> 409.12167
B24: Deferred tax assets | D24: =SUMIF('BS LTD USD '!B:B,'BS USD CONS '!$B24,'BS LTD USD '!F:F) -> 939408.95 | J24: =+F24+D24+H24 -> 939408.95 | L24: =J24/1000 -> 939.40895
B25: Reserve - Wordpay | D25: =SUMIF('BS LTD USD '!B:B,'BS USD CONS '!$B25,'BS LTD USD '!F:F) -> 0 | F25: =SUMIF('BS & P&L INC '!D:D,'BS USD CONS '!$B25,'BS & P&L INC '!H:H) -> 199999 | J25: =+F25+D25+H25 -> 199999 | L25: =J25/1000 -> 199.999
B26: Fixed assets, net | D26: =SUMIF('BS LTD USD '!B:B,'BS USD CONS '!$B26,'BS LTD USD '!F:F) -> 501895.3 | F26: =SUMIF('BS & P&L INC '!D:D,'BS USD CONS '!$B26,'BS & P&L INC '!H:H) -> 0 | J26: =+F26+D26 -> 501895.3 | L26: =J26/1000 -> 501.8953
D27: =SUM(D22:D26) -> 2147945 | F27: =SUM(F22:F26) -> 199999 | H27: =SUM(H22:H26) -> -297519.04 | J27: =SUM(J22:J26) -> 2050424.9 | L27: =J27/1000 -> 2050.4249
B29: Total Assets | D29: =+D27+D18 -> 50472416 | F29: =+F27+F18 -> 4087830 | H29: =+H27+H18 -> -297519.04 | J29: =J18+J27 -> 54262727 | L29: =J29/1000 -> 54262.727
B32: CURRENT LIABILITIES
B34: Trade payables | D34: =SUMIF('BS LTD USD '!B:B,'BS USD CONS '!$B34,'BS LTD USD '!F:F) -> -10307676 | F34: =SUMIF('BS & P&L INC '!D:D,'BS USD CONS '!$B34,'BS & P&L INC '!H:H) -> -3126158.6 | J34: =+F34+D34 -> -13433835 | L34: =J34/1000 -> -13433.835
B35: Accrued Expenses | D35: =SUMIF('BS LTD USD '!B:B,'BS USD CONS '!$B35,'BS LTD USD '!F:F) -> -10629163 | F35: =SUMIF('BS & P&L INC '!D:D,'BS USD CONS '!$B35,'BS & P&L INC '!H:H) -> -562692.19 | J35: =+F35+D35 -> -11191856 | L35: =J35/1000 -> -11191.856
B36: Loan-Short Term | D36: =SUMIF('BS LTD USD '!B:B,'BS USD CONS '!$B36,'BS LTD USD '!F:F) -> -2033334 | F36: =SUMIF('BS & P&L INC '!D:D,'BS USD CONS '!$B36,'BS & P&L INC '!H:H) -> 0 | J36: =+F36+D36 -> -2033334 | L36: =J36/1000 -> -2033.334
B37: Contract liability | D37: =SUMIF('BS LTD USD '!B:B,'BS USD CONS '!$B37,'BS LTD USD '!F:F) -> -4087657 | F37: =SUMIF('BS & P&L INC '!D:D,'BS USD CONS '!$B37,'BS & P&L INC '!H:H) -> 0 | J37: =+F37+D37 -> -4087657 | L37: =J37/1000 -> -4087.657
B38: Tax provision | D38: =SUMIF('BS LTD USD '!B:B,'BS USD CONS '!$B38,'BS LTD USD '!F:F) -> -1881953.5 | J38: =+F38+D38 -> -1881953.5 | L38: =J38/1000 -> -1881.9535
B39: Related Party-AP | D39: =SUMIF('BS LTD USD '!B:B,'BS USD CONS '!$B39,'BS LTD USD '!F:F) -> 0 | F39: =SUMIF('BS & P&L INC '!D:D,'BS USD CONS '!$B39,'BS & P&L INC '!H:H) -> 0 | J39: =+F39+D39 -> 0 | L39: =J39/1000 -> 0
B40: ROA Liability | D40: =SUMIF('BS LTD USD '!B:B,'BS USD CONS '!$B40,'BS LTD USD '!F:F) -> -385359.69 | F40: =SUMIF('BS & P&L INC '!D:D,'BS USD CONS '!$B40,'BS & P&L INC '!H:H) -> 0 | J40: =+F40+D40 -> -385359.69 | L40: =J40/1000 -> -385.35969
B41: Deferred tax liability | D41: =SUMIF('BS LTD USD '!B:B,'BS USD CONS '!$B41,'BS LTD USD '!F:F) -> 0 | F41: =SUMIF('BS & P&L INC '!D:D,'BS USD CONS '!$B41,'BS & P&L INC '!H:H) -> 0 | J41: =+F41+D41 -> 0 | L41: =J41/1000 -> 0
B42: Other accounts payable | D42: =SUMIF('BS LTD USD '!B:B,'BS USD CONS '!$B42,'BS LTD USD '!F:F) -> -7411932.8 | F42: =SUMIF('BS & P&L INC '!D:D,'BS USD CONS '!$B42,'BS & P&L INC '!H:H) -> -101461.4 | J42: =+F42+D42 -> -7513394.2 | L42: =J42/1000 -> -7513.3942
D43: =SUM(D34:D42) -> -36737077 | F43: =SUM(F32:F42) -> -3790312.2 | H43: =SUM(H32:H42) -> 0 | J43: =+F43+D43 -> -40527389 | L43: =J43/1000 -> -40527.389
J44: =+F44+D44 -> 0
B45: Loan-Long Term | D45: =SUMIF('BS LTD USD '!B:B,'BS USD CONS '!$B45,'BS LTD USD '!F:F) -> -533332.72 | F45: =SUMIF('BS & P&L INC '!D:D,'BS USD CONS '!$B45,'BS & P&L INC '!F:F) -> 0 | J45: =+F45+D45 -> -533332.72 | L45: =J45/1000 -> -533.33272
B46: Shareholders | D46: =SUMIF('BS LTD USD '!B:B,'BS USD CONS '!$B46,'BS LTD USD '!F:F) -> -500000 | F46: =SUMIF('BS & P&L INC '!D:D,'BS USD CONS '!$B46,'BS & P&L INC '!F:F) -> 0 | J46: =+F46+D46 -> -500000 | L46: =J46/1000 -> -500
B47: Convertible Loan | D47: =SUMIF('BS LTD USD '!B:B,'BS USD CONS '!$B47,'BS LTD USD '!F:F) -> 0 | F47: =SUMIF('BS & P&L INC '!D:D,'BS USD CONS '!$B47,'BS & P&L INC '!F:F) -> 0 | J47: =+F47+D47 -> 0 | L47: =J47/1000 -> 0
D48: =SUM(D45:D47) -> -1033332.7 | F48: =SUM(F46:F47) -> 0 | J48: =+F48+D48 -> -1033332.7 | L48: =J48/1000 -> -1033.3327
B50: Total liabilities | D50: =+D48+D43 -> -37770409 | F50: =+F48+F43 -> -3790312.2 | H50: =+H48+H43 -> 0 | J50: =+F50+D50 -> -41560722 | L50: =J50/1000 -> -41560.722
B52: SHAREHOLDERS' EQUITY
B54: Share capital - Ordinary Shares | D54: =SUMIF('BS LTD USD '!B:B,'BS USD CONS '!$B54,'BS LTD USD '!F:F) -> -418.92 | F54: =SUMIF('BS & P&L INC '!D:D,'BS USD CONS '!$B54,'BS & P&L INC '!H:H) -> 0 | J54: =+F54+D54 -> -418.92 | L54: =J54/1000 -> -0.41892
B55: Share capital - Preferred Seed-1 | D55: =SUMIF('BS LTD USD '!B:B,'BS USD CONS '!$B55,'BS LTD USD '!F:F) -> -191 | F55: =SUMIF('BS & P&L INC '!D:D,'BS USD CONS '!$B55,'BS & P&L INC '!H:H) -> 0 | J55: =+F55+D55 -> -191 | L55: =J55/1000 -> -0.191
B56: Share capital - Preferred Seed | D56: =SUMIF('BS LTD USD '!B:B,'BS USD CONS '!$B56,'BS LTD USD '!F:F) -> -49.24 | F56: =SUMIF('BS & P&L INC '!D:D,'BS USD CONS '!$B56,'BS & P&L INC '!H:H) -> 0 | J56: =+F56+D56 -> -49.24 | L56: =J56/1000 -> -0.04924
B57: Share premium | D57: =SUMIF('BS LTD USD '!B:B,'BS USD CONS '!$B57,'BS LTD USD '!F:F) -> -8614908.1 | F57: =SUMIF('BS & P&L INC '!D:D,'BS USD CONS '!$B57,'BS & P&L INC '!H:H) -> 0 | J57: =+F57+D57 -> -8614908.1 | L57: =J57/1000 -> -8614.9081
B58: Receivables for shares issued | D58: =SUMIF('BS LTD USD '!B:B,'BS USD CONS '!$B58,'BS LTD USD '!F:F) -> 0 | F58: =SUMIF('BS & P&L INC '!D:D,'BS USD CONS '!$B58,'BS & P&L INC '!H:H) -> 0 | J58: =+F58+D58 -> 0 | L58: =J58/1000 -> 0
B59: Accumulated deficit | D59: =SUMIF('BS LTD USD '!B:B,'BS USD CONS '!$B59,'BS LTD USD '!F:F) -> 3981035.1 | F59: =SUMIF('BS & P&L INC '!D:D,'BS USD CONS '!$B59,'BS & P&L INC '!H:H) -> -39372.79 | H59: =-F59 -> 39372.79 | J59: =+F59+D59+H59 -> 3981035.1 | L59: =J59/1000 -> 3981.0351
B60: PL | D60: ='P&L LTD USD'!F83 -> -8067474.7 | F60: =SUMIF('BS & P&L INC '!D:D,'BS USD CONS '!$B60,'BS & P&L INC '!H:H) -> -258145.04 | H60: =-F60 -> 258145.04 | J60: =D60+F60+H60 -> -8067474.7 | L60: =J60/1000 -> -8067.4747
D61: =SUM(D54:D60) -> -12702007 | F61: =SUM(F54:F60) -> -297517.83 | H61: =SUM(H54:H60) -> 297517.83 | J61: =SUM(J54:J60) -> -12702007 | L61: =J61/1000 -> -12702.007
J62: =+F62+D62 -> 0 | L62: =J62/1000 -> 0
D63: =D61+D50 -> -50472416 | F63: =F61+F50 -> -4087830 | H63: =H61+H50 -> 297517.83 | J63: =J61+J50 -> -54262728 | L63: =J63/1000 -> -54262.728
D64: =+D63=-D29 -> TRUE | F64: =+F63=F29 -> FALSE | H64: =+H63=H29 -> FALSE | J64: =+J63+J29 -> -1.21 | L64: =J64/1000 -> -0.00121
D65: =+D63+D29 -> 0 | F65: =+F63+F29 -> 3.3061951e-08 | H65: =+H63+H29 -> -1.2100001 | J65: =+F65+D65 -> 3.3061951e-08 | L65: =J65/1000 -> 3.3061951e-11

Sheet BS LTD USD 
D1: USD -LTD | J1: ILS -LTD
D3: 44561 | F3: 44561 | J3: 44561 | L3: 44561
E4: JE | F4: AJE | K4: JE | L4: AJE
B6: CURRENT ASSETS
B8: Cash | D8: =SUMIF('TB LTD 12.21'!I:I,B8,'TB LTD 12.21'!G:G) -> 12155821 | F8: =D8+E8 -> 12155821 | J8: =SUMIF('TB LTD 12.21'!I:I,B8,'TB LTD 12.21'!F:F) -> 37804603 | L8: =J8+K8 -> 37804603 | N8: =L8/1000 -> 37804.603
B9: Account receivable | D9: =SUMIF('TB LTD 12.21'!I:I,B9,'TB LTD 12.21'!G:G) -> 156494 | E9: ='AJE 2021'!G25 -> 1039517.9 | F9: =D9+E9 -> 1196011.9 | J9: =SUMIF('TB LTD 12.21'!I:I,B9,'TB LTD 12.21'!F:F) -> 486696.34 | K9: ='AJE 2021'!J25 -> 3232900.7 | L9: =J9+K9 -> 3719597 | M9: =K9/E9 -> 3.11 | N9: =L9/1000 -> 3719.597
B10: Related Party | D10: =SUMIF('TB LTD 12.21'!I:I,B10,'TB LTD 12.21'!G:G) -> 33417475 | E10: ='AJE 2021'!G53-'AJE 2021'!H26-'AJE 2021'!G64+'AJE 2021'!G81 -> -945636.64 | F10: =D10+E10 -> 32471839 | J10: =SUMIF('TB LTD 12.21'!I:I,B10,'TB LTD 12.21'!F:F) -> 1.0392835e+08 | K10: ='AJE 2021'!J53-'AJE 2021'!K26-'AJE 2021'!J64+'AJE 2021'!J81 -> -3514747.8 | L10: =J10+K10 -> 1.004136e+08 | M10: =K10/E10 -> 3.7168059 | N10: =L10/1000 -> 100413.6
B11: Deposit | D11: =SUMIF('TB LTD 12.21'!I:I,B11,'TB LTD 12.21'!G:G) -> 16077.17 | F11: =D11+E11 -> 16077.17 | J11: =SUMIF('TB LTD 12.21'!I:I,B11,'TB LTD 12.21'!F:F) -> 50000 | L11: =J11+K11 -> 50000 | N11: =L11/1000 -> 50
B12: Shareholders' loan | D12: =SUMIF('TB LTD 12.21'!I:I,B12,'TB LTD 12.21'!G:G) -> 0 | F12: =D12+E12 -> 0 | J12: =SUMIF('TB LTD 12.21'!I:I,B12,'TB LTD 12.21'!F:F) -> 0 | L12: =J12+K12 -> 0 | N12: =L12/1000 -> 0
B13: Prepaid | D13: =SUMIF('TB LTD 12.21'!I:I,B13,'TB LTD 12.21'!G:G) -> 1076626.7 | E13: =-'AJE 2021'!H75+'AJE 2021'!G31 -> -42372.32 | F13: =D13+E13 -> 1034254.4 | J13: =SUMIF('TB LTD 12.21'!I:I,B13,'TB LTD 12.21'!F:F) -> 3348309.1 | K13: =-'AJE 2021'!K75 -> -186398.21 | L13: =J13+K13 -> 3161910.9 | N13: =L13/1000 -> 3161.9109
B14: Other accounts receivable | D14: =SUMIF('TB LTD 12.21'!I:I,B14,'TB LTD 12.21'!G:G) -> 1438335.1 | E14: ='AJE 2021'!G100 -> 12133 | F14: =D14+E14 -> 1450468.1 | J14: =SUMIF('TB LTD 12.21'!I:I,B14,'TB LTD 12.21'!F:F) -> 4488222 | K14: ='AJE 2021'!J31+'AJE 2021'!J100 -> 97368 | L14: =J14+K14 -> 4585590 | M14: =K14/E14 -> 8.0250556 | N14: =L14/1000 -> 4585.59
D15: =SUM(D8:D14) -> 48260829 | E15: =SUM(E8:E14) -> 63641.946 | F15: =SUM(F8:F14) -> 48324471 | J15: =SUM(J8:J14) -> 1.5010618e+08 | K15: =SUM(K8:K14) -> -370877.34 | L15: =SUM(L8:L14) -> 1.497353e+08 | M15: =K15/E15 -> -5.8275612 | N15: =L15/1000 -> 149735.3
N16: =L16/1000 -> 0
B17: NON-CURRENT ASSETS | N17: =L17/1000 -> 0
N18: =L18/1000 -> 0
B19: Investment | D19: =SUMIF('TB LTD 12.21'!I:I,B19,'TB LTD 12.21'!G:G) -> 391399.71 | E19: =-'AJE 2021'!G59 -> -93880.666 | F19: =D19+E19 -> 297519.04 | J19: =SUMIF('TB LTD 12.21'!I:I,B19,'TB LTD 12.21'!F:F) -> 1231494.2 | K19: =-'AJE 2021'!J59 -> -303168.84 | L19: =J19+K19 -> 928325.41 | M19: =K19/E19 -> 3.2293 | N19: =L19/1000 -> 928.32541
B20: ROA Assets | D20: =SUMIF('TB LTD 12.21'!I:I,B20,'TB LTD 12.21'!G:G) -> 0 | E20: ='AJE 2021'!G72 -> 409121.67 | F20: =D20+E20 -> 409121.67 | K20: ='AJE 2021'!J72 -> 1306529.9 | L20: =J20+K20 -> 1306529.9 | M20: =K20/E20 -> 3.1934996 | N20: =L20/1000 -> 1306.5299
B21: Fixed assets, net | D21: =SUMIF('TB LTD 12.21'!I:I,B21,'TB LTD 12.21'!G:G) -> 501895.3 | F21: =D21+E21 -> 501895.3 | J21: =SUMIF('TB LTD 12.21'!I:I,B21,'TB LTD 12.21'!F:F) -> 1630942.9 | L21: =J21+K21 -> 1630942.9 | N21: =L21/1000 -> 1630.9429
B22: Deferred tax assets | D22: =SUMIF('TB LTD 12.21'!I:I,B22,'TB LTD 12.21'!G:G) -> -1766750.1 | E22: ='AJE 2021'!G85+'AJE 2021'!G94 -> 2706159 | F22: =D22+E22 -> 939408.95 | J22: =SUMIF('TB LTD 12.21'!I:I,B22,'TB LTD 12.21'!F:F) -> -5494592.8 | K22: ='AJE 2021'!J85+'AJE 2021'!J94 -> 8420180.7 | L22: =J22+K22 -> 2925588 | N22: =L22/1000 -> 2925.588
D23: =SUM(D17:D22) -> -873455.07 | E23: =SUM(E17:E22) -> 3021400 | F23: =SUM(F17:F22) -> 2147945 | J23: =SUM(J17:J22) -> -2632155.6 | K23: =SUM(K17:K22) -> 9423541.8 | L23: =SUM(L17:L22) -> 6791386.1 | M23: =K23/E23 -> 3.1189322 | N23: =L23/1000 -> 6791.3861
N24: =L24/1000 -> 0
B25: Total Assets | D25: =+D23+D15 -> 47387374 | E25: =+E23+E15 -> 3085042 | F25: =+F23+F15 -> 50472416 | J25: =+J23+J15 -> 1.4747402e+08 | K25: =+K23+K15 -> 9052664.5 | L25: =+L23+L15 -> 1.5652669e+08 | M25: =K25/E25 -> 2.9343732 | N25: =L25/1000 -> 156526.69
N26: =L26/1000 -> 0
N27: =L27/1000 -> 0
B28: CURRENT LIABILITIES | N28: =L28/1000 -> 0
N29: =L29/1000 -> 0
B30: Trade payables | D30: =SUMIF('TB LTD 12.21'!I:I,B30,'TB LTD 12.21'!G:G) -> -10271695 | E30: =-'AJE 2021'!H42 -> -35980.71 | F30: =D30+E30 -> -10307676 | J30: =SUMIF('TB LTD 12.21'!I:I,B30,'TB LTD 12.21'!F:F) -> -31944972 | K30: =-'AJE 2021'!K42 -> -111900 | L30: =J30+K30 -> -32056872 | M30: =K30/E30 -> 3.1099998 | N30: =L30/1000 -> -32056.872
B31: Accrued Expenses | D31: =SUMIF('TB LTD 12.21'!I:I,B31,'TB LTD 12.21'!G:G) -> -10615443 | E31: =-'AJE 2021'!H36 -> -13720.37 | F31: =D31+E31 -> -10629163 | J31: =SUMIF('TB LTD 12.21'!I:I,B31,'TB LTD 12.21'!F:F) -> -33014028 | K31: =-'AJE 2021'!K36 -> -42670.352 | L31: =J31+K31 -> -33056698 | N31: =L31/1000 -> -33056.698
B32: Loan-Short Term | D32: =SUMIF('TB LTD 12.21'!I:I,B32,'TB LTD 12.21'!G:G) -> -2033334 | F32: =D32+E32 -> -2033334 | J32: =SUMIF('TB LTD 12.21'!I:I,B32,'TB LTD 12.21'!F:F) -> -6323668.7 | L32: =J32+K32 -> -6323668.7 | N32: =L32/1000 -> -6323.6687
B33: Contract liability | D33: =SUMIF('TB LTD 12.21'!I:I,B33,'TB LTD 12.21'!G:G) -> -3862324 | E33: =-'AJE 2021'!H47 -> -225333 | F33: =D33+E33 -> -4087657 | J33: =SUMIF('TB LTD 12.21'!I:I,B33,'TB LTD 12.21'!F:F) -> -12011828 | K33: =-'AJE 2021'!K47 -> -700785.63 | L33: =J33+K33 -> -12712613 | M33: =K33/E33 -> 3.11 | N33: =L33/1000 -> -12712.613
B34: Tax provision | D34: =SUMIF('TB LTD 12.21'!I:I,B34,'TB LTD 12.21'!G:G) -> 0 | E34: =-'AJE 2021'!H86+'AJE 2021'!G89 -> -1881953.5 | F34: =D34+E34 -> -1881953.5 | J34: =SUMIF('TB LTD 12.21'!I:I,B34,'TB LTD 12.21'!F:F) -> 0 | K34: =-'AJE 2021'!K86+'AJE 2021'!J89 -> -5900052 | L34: =J34+K34 -> -5900052 | N34: =L34/1000 -> -5900.052
B35: ROA Liability | D35: =SUMIF('TB LTD 12.21'!I:I,B35,'TB LTD 12.21'!G:G) -> 0 | E35: =-'AJE 2021'!H73 -> -385359.69 | F35: =D35+E35 -> -385359.69 | K35: =-'AJE 2021'!K73 -> -1196813.8 | L35: =J35+K35 -> -1196813.8 | M35: =K35/E35 -> 3.1057058 | N35: =L35/1000 -> -1196.8138
B36: Other accounts payable | D36: =SUMIF('TB LTD 12.21'!I:I,B36,'TB LTD 12.21'!G:G) -> -911211.56 | E36: =-'AJE 2021'!H80-'AJE 2021'!H105 -> -6500721.2 | F36: =D36+E36 -> -7411932.8 | J36: =SUMIF('TB LTD 12.21'!I:I,B36,'TB LTD 12.21'!F:F) -> -2833802.6 | K36: =-'AJE 2021'!K80-'AJE 2021'!K105 -> -20217243 | L36: =J36+K36 -> -23051046 | M36: =K36/E36 -> 3.11 | N36: =L36/1000 -> -23051.046
N37: =L37/1000 -> 0
D38: =SUM(D30:D37) -> -27694008 | E38: =SUM(E30:E37) -> -9043068.5 | F38: =SUM(F30:F37) -> -36737077 | J38: =SUM(J30:J37) -> -86128299 | K38: =SUM(K30:K37) -> -28169465 | L38: =SUM(L30:L37) -> -1.1429776e+08 | N38: =L38/1000 -> -114297.76
N39: =L39/1000 -> 0
B40: Loan-Long Term | D40: =SUMIF('TB LTD 12.21'!I:I,B40,'TB LTD 12.21'!G:G) -> -533332.72 | F40: =D40+E40 -> -533332.72 | J40: =SUMIF('TB LTD 12.21'!I:I,B40,'TB LTD 12.21'!F:F) -> -1658672 | L40: =J40+K40 -> -1658672 | N40: =L40/1000 -> -1658.672
B41: Shareholders | D41: =SUMIF('TB LTD 12.21'!I:I,B41,'TB LTD 12.21'!G:G) -> -500000 | F41: =D41+E41 -> -500000 | J41: =SUMIF('TB LTD 12.21'!I:I,B41,'TB LTD 12.21'!F:F) -> -1722778.6 | L41: =J41+K41 -> -1722778.6 | N41: =L41/1000 -> -1722.7786
B42: Convertible Loan | D42: =SUMIF('TB LTD 12.21'!I:I,B42,'TB LTD 12.21'!G:G) -> 0 | J42: =SUMIF('TB LTD 12.21'!I:I,B42,'TB LTD 12.21'!F:F) -> 0 | N42: =L42/1000 -> 0
D43: =SUM(D40:D42) -> -1033332.7 | E43: =SUM(E40:E42) -> 0 | F43: =SUM(F40:F42) -> -1033332.7 | J43: =SUM(J40:J42) -> -3381450.5 | K43: =SUM(K40:K42) -> 0 | L43: =SUM(L40:L42) -> -3381450.5 | N43: =L43/1000 -> -3381.4506
N44: =L44/1000 -> 0
B45: Total libiliaties | D45: =+D43+D38 -> -28727341 | E45: =+E43+E38 -> -9043068.5 | F45: =+F43+F38 -> -37770409 | J45: =+J43+J38 -> -89509749 | K45: =+K43+K38 -> -28169465 | L45: =+L43+L38 -> -1.1767921e+08 | N45: =L45/1000 -> -117679.21
N46: =L46/1000 -> 0
B47: SHAREHOLDERS' EQUITY | N47: =L47/1000 -> 0
N48: =L48/1000 -> 0
B49: Share capital - Ordinary Shares | D49: =SUMIF('TB LTD 12.21'!I:I,B49,'TB LTD 12.21'!G:G) -> -418.92 | F49: =D49+E49 -> -418.92 | J49: =SUMIF('TB LTD 12.21'!I:I,B49,'TB LTD 12.21'!F:F) -> -1543.15 | L49: =J49+K49 -> -1543.15 | N49: =L49/1000 -> -1.54315
B50: Share capital - Preferred Seed-1 | D50: =SUMIF('TB LTD 12.21'!I:I,B50,'TB LTD 12.21'!G:G) -> -191 | F50: =D50+E50 -> -191 | J50: =SUMIF('TB LTD 12.21'!I:I,B50,'TB LTD 12.21'!F:F) -> -651 | L50: =J50+K50 -> -651 | N50: =L50/1000 -> -0.651
B51: Share capital - Preferred Seed | D51: =SUMIF('TB LTD 12.21'!I:I,B51,'TB LTD 12.21'!G:G) -> -49.24 | F51: =D51+E51 -> -49.24 | J51: =SUMIF('TB LTD 12.21'!I:I,B51,'TB LTD 12.21'!F:F) -> -169.46 | L51: =J51+K51 -> -169.46 | N51: =L51/1000 -> -0.16946
B52: Share premium | D52: =SUMIF('TB LTD 12.21'!I:I,B52,'TB LTD 12.21'!G:G) -> -7491270.8 | E52: =-'AJE 2021'!H21 -> -1123637.3 | F52: =D52+E52 -> -8614908.1 | J52: =SUMIF('TB LTD 12.21'!I:I,B52,'TB LTD 12.21'!F:F) -> -25517725 | K52: =-'AJE 2021'!K21 -> -3628561.9 | L52: =J52+K52 -> -29146287 | N52: =L52/1000 -> -29146.287
B53: Receivables for shares issued | D53: =SUMIF('TB LTD 12.21'!I:I,B53,'TB LTD 12.21'!G:G) -> 0 | F53: =D53+E53 -> 0 | J53: =SUMIF('TB LTD 12.21'!I:I,B53,'TB LTD 12.21'!F:F) -> 0 | L53: =J53+K53 -> 0 | N53: =L53/1000 -> 0
B54: Accumulated deficit | D54: =SUMIF('TB LTD 12.21'!I:I,B54,'TB LTD 12.21'!G:G) -> 3981035.1 | F54: =D54+E54 -> 3981035.1 | J54: =SUMIF('TB LTD 12.21'!I:I,B54,'TB LTD 12.21'!F:F) -> 14212769 | L54: =J54+K54 -> 14212769 | N54: =L54/1000 -> 14212.769
B55: PL | D55: ='P&L LTD USD'!D83 -> -15149139 | E55: ='P&L LTD USD'!E83 -> 7081663.8 | F55: =D55+E55 -> -8067474.7 | G55: =F55-'P&L LTD USD'!F83 -> 1.3969839e-08 | J55: ='P&L LTD USD'!J83 -> -46656954 | K55: ='P&L LTD USD'!K83 -> 22745362 | L55: =J55+K55 -> -23911592 | N55: =L55/1000 -> -23911.592
D56: =SUM(D49:D55) -> -18660033 | E56: =SUM(E49:E55) -> 5958026.5 | F56: =SUM(F49:F55) -> -12702007 | J56: =SUM(J49:J55) -> -57964274 | K56: =SUM(K49:K55) -> 19116800 | L56: =J56+K56 -> -38847474 | N56: =L56/1000 -> -38847.474
N57: =L57/1000 -> 0
D58: =D56+D45 -> -47387374 | E58: =E56+E45 -> -3085042 | F58: =F56+F45 -> -50472416 | J58: =J56+J45 -> -1.4747402e+08 | K58: =K56+K45 -> -9052664.7 | L58: =L56+L45 -> -1.5652669e+08 | N58: =L58/1000 -> -156526.69
D59: =+D58=-D25 -> TRUE | E59: =+E58=-E25 -> TRUE | F59: =+F58=-F25 -> TRUE | J59: =+J58=-J25 -> TRUE | K59: =+K58=-K25 -> FALSE | L59: =+L58=-L25 -> FALSE | N59: =L59/1000 -> 0
D60: =+D58+D25 -> 0 | E60: =+E58+E25 -> 0 | F60: =+F58+F25 -> 0 | J60: =+J58+J25 -> 0 | K60: =+K58+K25 -> -0.28288922 | L60: =+L58+L25 -> -0.28288919 | N60: =L60/1000 -> -0.00028288919

Sheet P&L LTD  USD
D1: USD -LTD | J1: ILS -LTD
D3: 44561 | F3: 44561 | J3: 44561 | L3: 44561
E4: JE | F4: AJE | J4: LTD | K4: JE | L4: AJE
B5: Revenues | C5: Revenues | D5: =SUMIFS('TB LTD 12.21'!G:G,'TB LTD 12.21'!I:I,$B5,'TB LTD 12.21'!J:J,$C5) -> -1.7342077e+08 | E5: ='AJE 2021'!G64 -> 5389318.2 | F5: =D5+E5 -> -1.6803145e+08 | J5: =SUMIFS('TB LTD 12.21'!F:F,'TB LTD 12.21'!I:I,$B5,'TB LTD 12.21'!J:J,$C5) -> -5.5200045e+08 | K5: ='AJE 2021'!J64 -> 17403725 | L5: =J5+K5 -> -5.3459672e+08
B6: Revenues | C6: ads revenue | D6: =SUMIFS('TB LTD 12.21'!G:G,'TB LTD 12.21'!I:I,$B6,'TB LTD 12.21'!J:J,$C6) -> -1552581.5 | F6: =D6+E6 -> -1552581.5 | J6: =SUMIFS('TB LTD 12.21'!F:F,'TB LTD 12.21'!I:I,$B6,'TB LTD 12.21'!J:J,$C6) -> -5007210.9 | L6: =J6+K6 -> -5007210.9
B7: Revenues | C7: Net Cash | D7: =SUMIFS('TB LTD 12.21'!G:G,'TB LTD 12.21'!I:I,$B7,'TB LTD 12.21'!J:J,$C7) -> 3260399 | E7: ='AJE 2021'!G48 -> 225333 | F7: =D7+E7 -> 3485732 | J7: =SUMIFS('TB LTD 12.21'!F:F,'TB LTD 12.21'!I:I,$B7,'TB LTD 12.21'!J:J,$C7) -> 10470022 | K7: ='AJE 2021'!J48 -> 700785.63 | L7: =J7+K7 -> 11170808
B8: Revenues | C8: withdrawals | D8: =SUMIFS('TB LTD 12.21'!G:G,'TB LTD 12.21'!I:I,$B8,'TB LTD 12.21'!J:J,$C8) -> 3028063.4 | F8: =D8+E8 -> 3028063.4 | J8: =SUMIFS('TB LTD 12.21'!F:F,'TB LTD 12.21'!I:I,$B8,'TB LTD 12.21'!J:J,$C8) -> 9740065.6 | L8: =J8+K8 -> 9740065.6
B9: Revenues | C9: Total Revenues | D9: =SUM(D5:D8) -> -1.6868489e+08 | E9: =SUM(E5:E8) -> 5614651.2 | F9: =SUM(F5:F8) -> -1.6307024e+08 | J9: =SUM(J5:J8) -> -5.3679757e+08 | K9: =SUM(K5:K8) -> 18104511 | L9: =SUM(L5:L8) -> -5.1869306e+08
B11: Cost of revenues | C11: Cost of revenues | D11: =SUM(D12:D21) -> 13306626 | E11: =SUM(E12:E21) -> -553163.28 | F11: =SUM(F12:F21) -> 12753463 | J11: =SUM(J12:J21) -> 42709721 | K11: =SUM(K12:K21) -> -1786330.2 | L11: =SUM(L12:L21) -> 40923391
A12: Overheads | B12: Cost of revenues | C12: professional fees | D12: =SUMIFS('TB LTD 12.21'!G:G,'TB LTD 12.21'!I:I,$B12,'TB LTD 12.21'!J:J,$C12) -> 107488.35 | F12: =D12+E12 -> 107488.35 | J12: =SUMIFS('TB LTD 12.21'!F:F,'TB LTD 12.21'!I:I,$B12,'TB LTD 12.21'!J:J,$C12) -> 348109.55 | L12: =J12+K12 -> 348109.55
A13: Payroll | B13: Cost of revenues | C13: Salary | D13: =SUMIFS('TB LTD 12.21'!G:G,'TB LTD 12.21'!I:I,$B13,'TB LTD 12.21'!J:J,$C13) -> 698868.45 | F13: =D13+E13 -> 698868.45 | J13: =SUMIFS('TB LTD 12.21'!F:F,'TB LTD 12.21'!I:I,$B13,'TB LTD 12.21'!J:J,$C13) -> 2241056.4 | L13: =J13+K13 -> 2241056.4
A14: Overheads | B14: Cost of revenues | C14: Softwere subscription | D14: =SUMIFS('TB LTD 12.21'!G:G,'TB LTD 12.21'!I:I,$B14,'TB LTD 12.21'!J:J,$C14) -> 35022.79 | F14: =D14+E14 -> 35022.79 | J14: =SUMIFS('TB LTD 12.21'!F:F,'TB LTD 12.21'!I:I,$B14,'TB LTD 12.21'!J:J,$C14) -> 113025.94 | L14: =J14+K14 -> 113025.94
A15: Overheads | B15: Cost of revenues | C15: Hosting and Servers | D15: =SUMIFS('TB LTD 12.21'!G:G,'TB LTD 12.21'!I:I,$B15,'TB LTD 12.21'!J:J,$C15) -> 938775.14 | F15: =D15+E15 -> 938775.14 | J15: =SUMIFS('TB LTD 12.21'!F:F,'TB LTD 12.21'!I:I,$B15,'TB LTD 12.21'!J:J,$C15) -> 3105388.1 | L15: =J15+K15 -> 3105388.1
A16: Overheads | B16: Cost of revenues | C16: Fee | D16: =SUMIFS('TB LTD 12.21'!G:G,'TB LTD 12.21'!I:I,$B16,'TB LTD 12.21'!J:J,$C16) -> 0 | F16: =D16+E16 -> 0 | J16: =SUMIFS('TB LTD 12.21'!F:F,'TB LTD 12.21'!I:I,$B16,'TB LTD 12.21'!J:J,$C16) -> 0 | L16: =J16+K16 -> 0
B17: Cost of revenues | C17: withdrawals | D17: =SUMIFS('TB LTD 12.21'!G:G,'TB LTD 12.21'!I:I,$B17,'TB LTD 12.21'!J:J,$C17) -> 0 | F17: =D17+E17 -> 0 | J17: =SUMIFS('TB LTD 12.21'!F:F,'TB LTD 12.21'!I:I,$B17,'TB LTD 12.21'!J:J,$C17) -> 0 | L17: =J17+K17 -> 0
A18: Options | B18: Cost of revenues | C18: option expenses | D18: =SUMIFS('TB LTD 12.21'!G:G,'TB LTD 12.21'!I:I,$B18,'TB LTD 12.21'!J:J,$C18) -> 21364 | E18: ='AJE 2021'!G18 -> -6811.1171 | F18: =D18+E18 -> 14552.883 | J18: =SUMIFS('TB LTD 12.21'!F:F,'TB LTD 12.21'!I:I,$B18,'TB LTD 12.21'!J:J,$C18) -> 68611.74 | K18: ='AJE 2021'!J18 -> -21995.14 | L18: =J18+K18 -> 46616.6
A19: Overheads | B19: Cost of revenues | C19: Allocation exp | D19: =SUMIFS('TB LTD 12.21'!G:G,'TB LTD 12.21'!I:I,$B19,'TB LTD 12.21'!J:J,$C19) -> 220446 | F19: =D19+E19 -> 220446 | J19: =SUMIFS('TB LTD 12.21'!F:F,'TB LTD 12.21'!I:I,$B19,'TB LTD 12.21'!J:J,$C19) -> 692152.93 | L19: =J19+K19 -> 692152.93
B20: Cost of revenues | C20: IC expenses | D20: =SUMIFS('TB LTD 12.21'!G:G,'TB LTD 12.21'!I:I,$B20,'TB LTD 12.21'!J:J,$C20) -> 11270061 | E20: =-'AJE 2021'!H54 -> -546352.16 | F20: =D20+E20 -> 10723709 | J20: =SUMIFS('TB LTD 12.21'!F:F,'TB LTD 12.21'!I:I,$B20,'TB LTD 12.21'!J:J,$C20) -> 36093860 | K20: =-'AJE 2021'!K54 -> -1764335 | L20: =J20+K20 -> 34329525
A21: Overheads | B21: Cost of revenues | C21: recruitment | D21: =SUMIFS('TB LTD 12.21'!G:G,'TB LTD 12.21'!I:I,$B21,'TB LTD 12.21'!J:J,$C21) -> 14600 | F21: =D21+E21 -> 14600 | J21: =SUMIFS('TB LTD 12.21'!F:F,'TB LTD 12.21'!I:I,$B21,'TB LTD 12.21'!J:J,$C21) -> 47516.2 | L21: =J21+K21 -> 47516.2
C22: Gross loss (profit) | D22: =D9+D11 -> -1.5537827e+08 | E22: =E9+E11 -> 5061487.9 | F22: =F9+F11 -> -1.5031678e+08 | J22: =J9+J11 -> -4.9408785e+08 | K22: =K9+K11 -> 16318181 | L22: =L9+L11 -> -4.7776967e+08
B25: Research and development expenses, net | C25: Research and development expenses, net | D25: =SUM(D26:D35) -> 10570627 | E25: =SUM(E26:E35) -> 539214 | F25: =SUM(F26:F35) -> 11109841 | J25: =SUM(J26:J35) -> 33751918 | K25: =SUM(K26:K35) -> 1741283.8 | L25: =SUM(L26:L35) -> 35493202
A26: Overheads | B26: Research and development expenses, net | C26: professional fees | D26: =SUMIFS('TB LTD 12.21'!G:G,'TB LTD 12.21'!I:I,$B26,'TB LTD 12.21'!J:J,$C26) -> 325465.62 | F26: =D26+E26 -> 325465.62 | J26: =SUMIFS('TB LTD 12.21'!F:F,'TB LTD 12.21'!I:I,$B26,'TB LTD 12.21'!J:J,$C26) -> 1179403.1 | L26: =J26+K26 -> 1179403.1
A27: Payroll | B27: Research and development expenses, net | C27: Salary | D27: =SUMIFS('TB LTD 12.21'!G:G,'TB LTD 12.21'!I:I,$B27,'TB LTD 12.21'!J:J,$C27) -> 7099737.9 | F27: =D27+E27 -> 7099737.9 | J27: =SUMIFS('TB LTD 12.21'!F:F,'TB LTD 12.21'!I:I,$B27,'TB LTD 12.21'!J:J,$C27) -> 22611084 | L27: =J27+K27 -> 22611084
A28: Overheads | B28: Research and development expenses, net | C28: Softwere subscription | D28: =SUMIFS('TB LTD 12.21'!G:G,'TB LTD 12.21'!I:I,$B28,'TB LTD 12.21'!J:J,$C28) -> 1018247.6 | F28: =D28+E28 -> 1018247.6 | J28: =SUMIFS('TB LTD 12.21'!F:F,'TB LTD 12.21'!I:I,$B28,'TB LTD 12.21'!J:J,$C28) -> 3294839.1 | L28: =J28+K28 -> 3294839.1
A29: Overheads | B29: Research and development expenses, net | C29: Hosting and Servers | D29: =SUMIFS('TB LTD 12.21'!G:G,'TB LTD 12.21'!I:I,$B29,'TB LTD 12.21'!J:J,$C29) -> 683881.4 | F29: =D29+E29 -> 683881.4 | J29: =SUMIFS('TB LTD 12.21'!F:F,'TB LTD 12.21'!I:I,$B29,'TB LTD 12.21'!J:J,$C29) -> 2126871.1 | L29: =J29+K29 -> 2126871.1
A30: Options | B30: Research and development expenses, net | C30: option expenses | D30: =SUMIFS('TB LTD 12.21'!G:G,'TB LTD 12.21'!I:I,$B30,'TB LTD 12.21'!J:J,$C30) -> 474606 | E30: ='AJE 2021'!G19 -> 539214 | F30: =D30+E30 -> 1013820 | J30: =SUMIFS('TB LTD 12.21'!F:F,'TB LTD 12.21'!I:I,$B30,'TB LTD 12.21'!J:J,$C30) -> 1523877.4 | K30: ='AJE 2021'!J19 -> 1741283.8 | L30: =J30+K30 -> 3265161.2
A31: Overheads | B31: Research and development expenses, net | C31: communication | D31: =SUMIFS('TB LTD 12.21'!G:G,'TB LTD 12.21'!I:I,$B31,'TB LTD 12.21'!J:J,$C31) -> 0 | F31: =D31+E31 -> 0 | J31: =SUMIFS('TB LTD 12.21'!F:F,'TB LTD 12.21'!I:I,$B31,'TB LTD 12.21'!J:J,$C31) -> 0 | L31: =J31+K31 -> 0
A32: Overheads | B32: Research and development expenses, net | C32: Allocation exp | D32: =SUMIFS('TB LTD 12.21'!G:G,'TB LTD 12.21'!I:I,$B32,'TB LTD 12.21'!J:J,$C32) -> 840030 | F32: =D32+E32 -> 840030 | J32: =SUMIFS('TB LTD 12.21'!F:F,'TB LTD 12.21'!I:I,$B32,'TB LTD 12.21'!J:J,$C32) -> 2604306.4 | L32: =J32+K32 -> 2604306.4
A33: Overheads | B33: Research and development expenses, net | C33: recruitment | D33: =SUMIFS('TB LTD 12.21'!G:G,'TB LTD 12.21'!I:I,$B33,'TB LTD 12.21'!J:J,$C33) -> 124269.3 | F33: =D33+E33 -> 124269.3 | J33: =SUMIFS('TB LTD 12.21'!F:F,'TB LTD 12.21'!I:I,$B33,'TB LTD 12.21'!J:J,$C33) -> 397758.91 | L33: =J33+K33 -> 397758.91
A34: Overheads | B34: Research and development expenses, net | C34: Travel Parking and transportation | D34: =SUMIFS('TB LTD 12.21'!G:G,'TB LTD 12.21'!I:I,$B34,'TB LTD 12.21'!J:J,$C34) -> 4388.97 | F34: =D34+E34 -> 4388.97 | J34: =SUMIFS('TB LTD 12.21'!F:F,'TB LTD 12.21'!I:I,$B34,'TB LTD 12.21'!J:J,$C34) -> 13778.18 | L34: =J34+K34 -> 13778.18
B35: Research and development expenses, net | C35: IC expenses | D35: =SUMIFS('TB LTD 12.21'!G:G,'TB LTD 12.21'!I:I,$B35,'TB LTD 12.21'!J:J,$C35) -> 0 | F35: =D35+E35 -> 0 | J35: =SUMIFS('TB LTD 12.21'!F:F,'TB LTD 12.21'!I:I,$B35,'TB LTD 12.21'!J:J,$C35) -> 0 | L35: =J35+K35 -> 0
C37: Marketing expenses | D37: =SUM(D38:D47) -> 1.2430914e+08 | E37: =SUM(E38:E47) -> -22807.61 | F37: =SUM(F38:F47) -> 1.2428633e+08 | J37: =SUM(J38:J47) -> 3.9774217e+08 | K37: =SUM(K38:K47) -> -73652.616 | L37: =SUM(L38:L47) -> 3.9766852e+08
A38: Payroll | B38: Marketing expenses | C38: Salary | D38: =SUMIFS('TB LTD 12.21'!G:G,'TB LTD 12.21'!I:I,$B38,'TB LTD 12.21'!J:J,$C38) -> 993651.78 | F38: =D38+E38 -> 993651.78 | J38: =SUMIFS('TB LTD 12.21'!F:F,'TB LTD 12.21'!I:I,$B38,'TB LTD 12.21'!J:J,$C38) -> 3186571.4 | L38: =J38+K38 -> 3186571.4
A39: Ua | B39: Marketing expenses | C39: User Acquisition | D39: =SUMIFS('TB LTD 12.21'!G:G,'TB LTD 12.21'!I:I,$B39,'TB LTD 12.21'!J:J,$C39) -> 1.0587177e+08 | F39: =D39+E39 -> 1.0587177e+08 | J39: =SUMIFS('TB LTD 12.21'!F:F,'TB LTD 12.21'!I:I,$B39,'TB LTD 12.21'!J:J,$C39) -> 3.3866468e+08 | L39: =J39+K39 -> 3.3866468e+08
A40: Ua Indirect | B40: Marketing expenses | C40: Softwere subscription | D40: =SUMIFS('TB LTD 12.21'!G:G,'TB LTD 12.21'!I:I,$B40,'TB LTD 12.21'!J:J,$C40) -> 419274.89 | F40: =D40+E40 -> 419274.89 | J40: =SUMIFS('TB LTD 12.21'!F:F,'TB LTD 12.21'!I:I,$B40,'TB LTD 12.21'!J:J,$C40) -> 1357908.9 | L40: =J40+K40 -> 1357908.9
A41: Options | B41: Marketing expenses | C41: option expenses | D41: =SUMIFS('TB LTD 12.21'!G:G,'TB LTD 12.21'!I:I,$B41,'TB LTD 12.21'!J:J,$C41) -> 27657 | E41: ='AJE 2021'!G20 -> -22807.61 | F41: =D41+E41 -> 4849.3898 | J41: =SUMIFS('TB LTD 12.21'!F:F,'TB LTD 12.21'!I:I,$B41,'TB LTD 12.21'!J:J,$C41) -> 88061.77 | K41: ='AJE 2021'!J20 -> -73652.616 | L41: =J41+K41 -> 14409.154
A42: Ua Indirect | B42: Marketing expenses | C42: PR | D42: =SUMIFS('TB LTD 12.21'!G:G,'TB LTD 12.21'!I:I,$B42,'TB LTD 12.21'!J:J,$C42) -> 533167.79 | F42: =D42+E42 -> 533167.79 | J42: =SUMIFS('TB LTD 12.21'!F:F,'TB LTD 12.21'!I:I,$B42,'TB LTD 12.21'!J:J,$C42) -> 1708666.7 | L42: =J42+K42 -> 1708666.7
A43: Ua Indirect | B43: Marketing expenses | C43: Gift to Users | D43: =SUMIFS('TB LTD 12.21'!G:G,'TB LTD 12.21'!I:I,$B43,'TB LTD 12.21'!J:J,$C43) -> 65345.8 | F43: =D43+E43 -> 65345.8 | J43: =SUMIFS('TB LTD 12.21'!F:F,'TB LTD 12.21'!I:I,$B43,'TB LTD 12.21'!J:J,$C43) -> 201944.48 | L43: =J43+K43 -> 201944.48
A44: Overheads | B44: Marketing expenses | C44: Allocation exp | D44: =SUMIFS('TB LTD 12.21'!G:G,'TB LTD 12.21'!I:I,$B44,'TB LTD 12.21'!J:J,$C44) -> 143693 | F44: =D44+E44 -> 143693 | J44: =SUMIFS('TB LTD 12.21'!F:F,'TB LTD 12.21'!I:I,$B44,'TB LTD 12.21'!J:J,$C44) -> 427219.73 | L44: =J44+K44 -> 427219.73
A45: Ua Indirect | B45: Marketing expenses | C45: Copywriting expenses | D45: =SUMIFS('TB LTD 12.21'!G:G,'TB LTD 12.21'!I:I,$B45,'TB LTD 12.21'!J:J,$C45) -> 79348.76 | F45: =D45+E45 -> 79348.76 | J45: =SUMIFS('TB LTD 12.21'!F:F,'TB LTD 12.21'!I:I,$B45,'TB LTD 12.21'!J:J,$C45) -> 254800 | L45: =J45+K45 -> 254800
A46: Overheads | B46: Marketing expenses | C46: recruitment | D46: =SUMIFS('TB LTD 12.21'!G:G,'TB LTD 12.21'!I:I,$B46,'TB LTD 12.21'!J:J,$C46) -> 23010.1 | F46: =D46+E46 -> 23010.1 | J46: =SUMIFS('TB LTD 12.21'!F:F,'TB LTD 12.21'!I:I,$B46,'TB LTD 12.21'!J:J,$C46) -> 74500 | L46: =J46+K46 -> 74500
B47: Marketing expenses | C47: IC expenses | D47: =SUMIFS('TB LTD 12.21'!G:G,'TB LTD 12.21'!I:I,$B47,'TB LTD 12.21'!J:J,$C47) -> 16152223 | F47: =D47+E47 -> 16152223 | J47: =SUMIFS('TB LTD 12.21'!F:F,'TB LTD 12.21'!I:I,$B47,'TB LTD 12.21'!J:J,$C47) -> 51777823 | L47: =J47+K47 -> 51777823
C49: General and administrative expenses | D49: =SUM(D50:D70) -> 3243758.9 | E49: =SUM(E50:E70) -> 634184.51 | F49: =SUM(F50:F70) -> 3877943.4 | J49: =SUM(J50:J70) -> 10612938 | K49: =SUM(K50:K70) -> 2009040.8 | L49: =SUM(L50:L70) -> 12621979
A50: Payroll | B50: General and administrative expenses | C50: Salary | D50: =SUMIFS('TB LTD 12.21'!G:G,'TB LTD 12.21'!I:I,$B50,'TB LTD 12.21'!J:J,$C50) -> 1913052.6 | F50: =D50+E50 -> 1913052.6 | J50: =SUMIFS('TB LTD 12.21'!F:F,'TB LTD 12.21'!I:I,$B50,'TB LTD 12.21'!J:J,$C50) -> 6045006.4 | L50: =J50+K50 -> 6045006.4
A51: Overheads | B51: General and administrative expenses | C51: professional fees | D51: =SUMIFS('TB LTD 12.21'!G:G,'TB LTD 12.21'!I:I,$B51,'TB LTD 12.21'!J:J,$C51) -> 538878.34 | E51: =-'AJE 2021'!H30+'AJE 2021'!G43 -> 18374.63 | F51: =D51+E51 -> 557252.97 | J51: =SUMIFS('TB LTD 12.21'!F:F,'TB LTD 12.21'!I:I,$B51,'TB LTD 12.21'!J:J,$C51) -> 1787515.2 | K51: =-'AJE 2021'!K30+'AJE 2021'!J43 -> 56300 | L51: =J51+K51 -> 1843815.2
A52: Overheads | B52: General and administrative expenses | C52: Rent and related | D52: =SUMIFS('TB LTD 12.21'!G:G,'TB LTD 12.21'!I:I,$B52,'TB LTD 12.21'!J:J,$C52) -> 365178.33 | E52: ='AJE 2021'!G74 -> 34860.776 | F52: =D52+E52 -> 400039.11 | J52: =SUMIFS('TB LTD 12.21'!F:F,'TB LTD 12.21'!I:I,$B52,'TB LTD 12.21'!J:J,$C52) -> 1176642 | K52: ='AJE 2021'!J74 -> 76681.843 | L52: =J52+K52 -> 1253323.9
A53: Overheads | B53: General and administrative expenses | C53: Meals | D53: =SUMIFS('TB LTD 12.21'!G:G,'TB LTD 12.21'!I:I,$B53,'TB LTD 12.21'!J:J,$C53) -> 242018.36 | F53: =D53+E53 -> 242018.36 | J53: =SUMIFS('TB LTD 12.21'!F:F,'TB LTD 12.21'!I:I,$B53,'TB LTD 12.21'!J:J,$C53) -> 778158.31 | L53: =J53+K53 -> 778158.31
A54: Overheads | B54: General and administrative expenses | C54: Legal | D54: =SUMIFS('TB LTD 12.21'!G:G,'TB LTD 12.21'!I:I,$B54,'TB LTD 12.21'!J:J,$C54) -> 413177.21 | F54: =D54+E54 -> 413177.21 | J54: =SUMIFS('TB LTD 12.21'!F:F,'TB LTD 12.21'!I:I,$B54,'TB LTD 12.21'!J:J,$C54) -> 1324118 | L54: =J54+K54 -> 1324118
A55: Overheads | B55: General and administrative expenses | C55: Conferences and seminars | D55: =SUMIFS('TB LTD 12.21'!G:G,'TB LTD 12.21'!I:I,$B55,'TB LTD 12.21'!J:J,$C55) -> 14103.4 | F55: =D55+E55 -> 14103.4 | J55: =SUMIFS('TB LTD 12.21'!F:F,'TB LTD 12.21'!I:I,$B55,'TB LTD 12.21'!J:J,$C55) -> 45689.34 | L55: =J55+K55 -> 45689.34
A56: depreciation | B56: General and administrative expenses | C56: depreciation Exp | D56: =SUMIFS('TB LTD 12.21'!G:G,'TB LTD 12.21'!I:I,$B56,'TB LTD 12.21'!J:J,$C56) -> 83930.85 | E56: =+'AJE 2021'!G70 -> 0 | F56: =D56+E56 -> 83930.85 | J56: =SUMIFS('TB LTD 12.21'!F:F,'TB LTD 12.21'!I:I,$B56,'TB LTD 12.21'!J:J,$C56) -> 269792.46 | K56: ='AJE 2021'!J70 -> 0 | L56: =J56+K56 -> 269792.46
A57: Overheads | B57: General and administrative expenses | C57: Design Exp | D57: =SUMIFS('TB LTD 12.21'!G:G,'TB LTD 12.21'!I:I,$B57,'TB LTD 12.21'!J:J,$C57) -> 13648.44 | F57: =D57+E57 -> 13648.44 | J57: =SUMIFS('TB LTD 12.21'!F:F,'TB LTD 12.21'!I:I,$B57,'TB LTD 12.21'!J:J,$C57) -> 44232.79 | L57: =J57+K57 -> 44232.79
A58: Overheads | B58: General and administrative expenses | C58: Gift | D58: =SUMIFS('TB LTD 12.21'!G:G,'TB LTD 12.21'!I:I,$B58,'TB LTD 12.21'!J:J,$C58) -> 92387.34 | F58: =D58+E58 -> 92387.34 | J58: =SUMIFS('TB LTD 12.21'!F:F,'TB LTD 12.21'!I:I,$B58,'TB LTD 12.21'!J:J,$C58) -> 297617.59 | L58: =J58+K58 -> 297617.59
A59: Overheads | B59: General and administrative expenses | C59: communication | D59: =SUMIFS('TB LTD 12.21'!G:G,'TB LTD 12.21'!I:I,$B59,'TB LTD 12.21'!J:J,$C59) -> 28237.86 | F59: =D59+E59 -> 28237.86 | J59: =SUMIFS('TB LTD 12.21'!F:F,'TB LTD 12.21'!I:I,$B59,'TB LTD 12.21'!J:J,$C59) -> 92315.87 | L59: =J59+K59 -> 92315.87
A60: Overheads | B60: General and administrative expenses | C60: Refreshment | D60: =SUMIFS('TB LTD 12.21'!G:G,'TB LTD 12.21'!I:I,$B60,'TB LTD 12.21'!J:J,$C60) -> 52069.57 | F60: =D60+E60 -> 52069.57 | J60: =SUMIFS('TB LTD 12.21'!F:F,'TB LTD 12.21'!I:I,$B60,'TB LTD 12.21'!J:J,$C60) -> 166380.37 | L60: =J60+K60 -> 166380.37
A61: Overheads | B61: General and administrative expenses | C61: Softwere subscription | D61: =SUMIFS('TB LTD 12.21'!G:G,'TB LTD 12.21'!I:I,$B61,'TB LTD 12.21'!J:J,$C61) -> 84440.26 | F61: =D61+E61 -> 84440.26 | J61: =SUMIFS('TB LTD 12.21'!F:F,'TB LTD 12.21'!I:I,$B61,'TB LTD 12.21'!J:J,$C61) -> 275148.99 | L61: =J61+K61 -> 275148.99
A62: Overheads | B62: General and administrative expenses | C62: Welfare | D62: =SUMIFS('TB LTD 12.21'!G:G,'TB LTD 12.21'!I:I,$B62,'TB LTD 12.21'!J:J,$C62) -> 239323.39 | F62: =D62+E62 -> 239323.39 | J62: =SUMIFS('TB LTD 12.21'!F:F,'TB LTD 12.21'!I:I,$B62,'TB LTD 12.21'!J:J,$C62) -> 755093.65 | L62: =J62+K62 -> 755093.65
A63: Overheads | B63: General and administrative expenses | C63: Travel Parking and transportation | D63: =SUMIFS('TB LTD 12.21'!G:G,'TB LTD 12.21'!I:I,$B63,'TB LTD 12.21'!J:J,$C63) -> 94539.07 | F63: =D63+E63 -> 94539.07 | J63: =SUMIFS('TB LTD 12.21'!F:F,'TB LTD 12.21'!I:I,$B63,'TB LTD 12.21'!J:J,$C63) -> 301086.98 | L63: =J63+K63 -> 301086.98
A64: Overheads | B64: General and administrative expenses | C64: insurance | D64: =SUMIFS('TB LTD 12.21'!G:G,'TB LTD 12.21'!I:I,$B64,'TB LTD 12.21'!J:J,$C64) -> 4071.9 | F64: =D64+E64 -> 4071.9 | J64: =SUMIFS('TB LTD 12.21'!F:F,'TB LTD 12.21'!I:I,$B64,'TB LTD 12.21'!J:J,$C64) -> 13030.97 | L64: =J64+K64 -> 13030.97
A65: Overheads | B65: General and administrative expenses | C65: events | D65: =SUMIFS('TB LTD 12.21'!G:G,'TB LTD 12.21'!I:I,$B65,'TB LTD 12.21'!J:J,$C65) -> 5532.59 | F65: =D65+E65 -> 5532.59 | J65: =SUMIFS('TB LTD 12.21'!F:F,'TB LTD 12.21'!I:I,$B65,'TB LTD 12.21'!J:J,$C65) -> 17902 | L65: =J65+K65 -> 17902
A66: Overheads | B66: General and administrative expenses | C66: recruitment | D66: =SUMIFS('TB LTD 12.21'!G:G,'TB LTD 12.21'!I:I,$B66,'TB LTD 12.21'!J:J,$C66) -> 0 | F66: =D66+E66 -> 0 | J66: =SUMIFS('TB LTD 12.21'!F:F,'TB LTD 12.21'!I:I,$B66,'TB LTD 12.21'!J:J,$C66) -> 0 | L66: =J66+K66 -> 0
A67: Overheads | B67: General and administrative expenses | C67: Other expenses | D67: =SUMIFS('TB LTD 12.21'!G:G,'TB LTD 12.21'!I:I,$B67,'TB LTD 12.21'!J:J,$C67) -> 28148.45 | F67: =D67+E67 -> 28148.45 | J67: =SUMIFS('TB LTD 12.21'!F:F,'TB LTD 12.21'!I:I,$B67,'TB LTD 12.21'!J:J,$C67) -> 90225.2 | L67: =J67+K67 -> 90225.2
A68: Options | B68: General and administrative expenses | C68: option expenses | D68: =SUMIFS('TB LTD 12.21'!G:G,'TB LTD 12.21'!I:I,$B68,'TB LTD 12.21'!J:J,$C68) -> 152451 | E68: ='AJE 2021'!G17 -> 614042.02 | F68: =D68+E68 -> 766493.02 | J68: =SUMIFS('TB LTD 12.21'!F:F,'TB LTD 12.21'!I:I,$B68,'TB LTD 12.21'!J:J,$C68) -> 592674.04 | K68: ='AJE 2021'!J17 -> 1982925.9 | L68: =J68+K68 -> 2575599.9
A69: Overheads | B69: General and administrative expenses | C69: Allocation exp | D69: =SUMIFS('TB LTD 12.21'!G:G,'TB LTD 12.21'!I:I,$B69,'TB LTD 12.21'!J:J,$C69) -> -1195488 | F69: =D69+E69 -> -1195488 | J69: =SUMIFS('TB LTD 12.21'!F:F,'TB LTD 12.21'!I:I,$B69,'TB LTD 12.21'!J:J,$C69) -> -3696681.2 | L69: =J69+K69 -> -3696681.2
B70: General and administrative expenses | C70: IC expenses | D70: =SUMIFS('TB LTD 12.21'!G:G,'TB LTD 12.21'!I:I,$B70,'TB LTD 12.21'!J:J,$C70) -> 74057.94 | E70: =-'AJE 2021'!H55 -> -33092.912 | F70: =D70+E70 -> 40965.028 | J70: =SUMIFS('TB LTD 12.21'!F:F,'TB LTD 12.21'!I:I,$B70,'TB LTD 12.21'!J:J,$C70) -> 236989.33 | K70: =-'AJE 2021'!K55 -> -106866.94 | L70: =J70+K70 -> 130122.39
C71: Operating expenses | D71: =D49+D37+D25 -> 1.3812353e+08 | E71: =E49+E37+E25 -> 1150590.9 | F71: =F49+F37+F25 -> 1.3927412e+08 | J71: =J49+J37+J25 -> 4.4210703e+08 | K71: =K49+K37+K25 -> 3676671.9 | L71: =L49+L37+L25 -> 4.457837e+08
C73: Operating loss (pprofit) | D73: =D71+D22 -> -17254739 | E73: =E71+E22 -> 6212078.8 | F73: =F71+F22 -> -11042660 | J73: =J71+J22 -> -51980821 | K73: =K71+K22 -> 19994853 | L73: =L71+L22 -> -31985968
C75: Financial expenses, net | D75: =SUM(D76:D80) -> 322235.48 | E75: =SUM(E76:E80) -> 1612042.8 | F75: =SUM(F76:F80) -> 1934278.3 | J75: =SUM(J76:J80) -> -520397.59 | K75: =SUM(K76:K80) -> 5009237.2 | L75: =SUM(L76:L80) -> 4488839.6
A76: Financial expenses | B76: Financial expenses, net | C76: Bank fee | D76: =SUMIFS('TB LTD 12.21'!G:G,'TB LTD 12.21'!I:I,$B76,'TB LTD 12.21'!J:J,$C76) -> 85665.14 | F76: =D76+E76 -> 85665.14 | J76: =SUMIFS('TB LTD 12.21'!F:F,'TB LTD 12.21'!I:I,$B76,'TB LTD 12.21'!J:J,$C76) -> 278103.23 | L76: =J76+K76 -> 278103.23
A77: Financial expenses | B77: Financial expenses, net | C77: Loan interest | D77: =SUMIFS('TB LTD 12.21'!G:G,'TB LTD 12.21'!I:I,$B77,'TB LTD 12.21'!J:J,$C77) -> 266889.08 | E77: ='AJE 2021'!G37+'AJE 2021'!G38+'AJE 2021'!G39 -> 13720.37 | F77: =D77+E77 -> 280609.45 | J77: =SUMIFS('TB LTD 12.21'!F:F,'TB LTD 12.21'!I:I,$B77,'TB LTD 12.21'!J:J,$C77) -> 868949.83 | K77: ='AJE 2021'!J37+'AJE 2021'!J38+'AJE 2021'!J39 -> 42670.352 | L77: =J77+K77 -> 911620.18
A78: Financial expenses | B78: Financial expenses, net | C78: Exchange rate | D78: =SUMIFS('TB LTD 12.21'!G:G,'TB LTD 12.21'!I:I,$B78,'TB LTD 12.21'!J:J,$C78) -> -30318.74 | F78: =D78+E78 -> -30318.74 | J78: =SUMIFS('TB LTD 12.21'!F:F,'TB LTD 12.21'!I:I,$B78,'TB LTD 12.21'!J:J,$C78) -> -1667450.6 | L78: =J78+K78 -> -1667450.6
A79: Financial expenses | B79: Financial expenses, net | C79: Warrant liability | D79: =SUMIFS('TB LTD 12.21'!G:G,'TB LTD 12.21'!I:I,$B79,'TB LTD 12.21'!J:J,$C79) -> 0 | E79: ='AJE 2021'!G104 -> 1596966.8 | F79: =D79+E79 -> 1596966.8 | J79: =SUMIFS('TB LTD 12.21'!F:F,'TB LTD 12.21'!I:I,$B79,'TB LTD 12.21'!J:J,$C79) -> 0 | K79: ='AJE 2021'!J104 -> 4966566.8 | L79: =J79+K79 -> 4966566.8
A80: Financial expenses | B80: Financial expenses, net | C80: Financial expenses | D80: =SUMIFS('TB LTD 12.21'!G:G,'TB LTD 12.21'!I:I,$B80,'TB LTD 12.21'!J:J,$C80) -> 0 | E80: ='AJE 2021'!G71 -> 1355.6411 | F80: =D80+E80 -> 1355.6411 | J80: =SUMIFS('TB LTD 12.21'!F:F,'TB LTD 12.21'!I:I,$B80,'TB LTD 12.21'!J:J,$C80) -> 0 | K80: =-'AJE 2021'!K71 -> 0 | L80: =J80+K80 -> 0
A81: Taxes | B81: Tax expenses | C81: Tax expenses | D81: =SUMIFS('TB LTD 12.21'!G:G,'TB LTD 12.21'!I:I,$B81,'TB LTD 12.21'!J:J,$C81) -> 2135390.8 | E81: =-'AJE 2021'!H90-'AJE 2021'!H95-'AJE 2021'!H99 -> -836338.49 | F81: =D81+E81 -> 1299052.3 | J81: =SUMIFS('TB LTD 12.21'!F:F,'TB LTD 12.21'!I:I,$B81,'TB LTD 12.21'!J:J,$C81) -> 6939064 | K81: =-'AJE 2021'!K90-'AJE 2021'!K95-'AJE 2021'!K99 -> -2561896.7 | L81: =J81+K81 -> 4377167.3
B82: Equity | C82: Equity | D82: =SUMIFS('TB LTD 12.21'!G:G,'TB LTD 12.21'!I:I,$B82,'TB LTD 12.21'!J:J,$C82) -> -352025.71 | E82: ='AJE 2021'!H60 -> 93880.666 | F82: =D82+E82 -> -258145.04 | J82: =SUMIFS('TB LTD 12.21'!F:F,'TB LTD 12.21'!I:I,$B82,'TB LTD 12.21'!J:J,$C82) -> -1094800 | K82: ='AJE 2021'!K60 -> 303168.84 | L82: =J82+K82 -> -791631.12
C83: Net loss ( profit ) | D83: =+D73+D75+D81+D82 -> -15149139 | E83: =+E73+E75+E81+E82 -> 7081663.8 | F83: =+F73+F75+F81+F82 -> -8067474.7 | J83: =+J73+J75+J81+J82 -> -46656954 | K83: =+K73+K75+K81+K82 -> 22745362 | L83: =+L73+L75+L81+L82 -> -23911592
C87: Option | D87: =D18+D30+D41+D68 -> 676078 | F87: =F18+F30+F41+F68 -> 1799715.3

Sheet BS & P&L INC 
E1: Papaya Gaming Inc
E2: Balance Sheet
F3: 44561 | G3: JE | H3: 44561
E5: Assets
E6: Current Assets
D7: Cash | E7: Paypal US | F7: 205675.8 | H7: =F7+G7 -> 205675.8
D8: Cash | E8: SVB - 80025 | F8: =36153995.34 -> 36153995 | H8: =F8+G8 -> 36153995 | I8: 7300 | J8: 19907
D9: Related Party | E9: Accounts Receivable (A/R) | F9: 29975832 | G9: ='AJE 2021'!W17+'AJE 2021'!V31-'AJE 2021'!W36-'AJE 2021'!V27 -> 945637.24 | H9: =F9+G9 -> 30921470
D10: Account receivable | E10: Other Accounts Receivable | F10: 1039517.9 | G10: =-'AJE 2021'!V16 -> -1039517.9 | H10: =F10+G10 -> 0
D11: Reserve - Wordpay | E11: Reserve - Wordpay | F11: =199999 -> 199999 | H11: =F11+G11 -> 199999
E12: Total Assets | F12: =SUM(F7:F11) -> 67575020 | H12: =SUM(H7:H11) -> 67481140
E13: Liabilities and shareholder's equity
E14: Current liabilities:
E15: Accounts payable
D16: Trade payables | E16: Accounts Payable (A/P) | F16: 0 | H16: 0
D17: Trade payables | E17: Accounts Payable (A/P) | F17: -2510837 | H17: =F17+G17 -> -2510837
E18: Total Accounts payable | F18: =F17+F15+F16 -> -2510837 | H18: =H17+H15+H16 -> -2510837
D19: Trade payables | E19: SVB - MasterCard | F19: =-615321.52 -> -615321.52 | H19: =F19+G19 -> -615321.52
D20: Accrued Expenses | E20: Accrued liabilities | F20: -562692.19 | H20: =F20+G20 -> -562692.19
D21: Related Party | E21: Due to/from Papaya LTD | F21: 1.2365046e+08 | H21: =F21+G21 -> 1.2365046e+08
D22: Other accounts payable | E22: Sales tax Provision | G22: =-'AJE 2021'!V23+'AJE 2021'!V27 -> 0 | H22: =F22+G22 -> 0
D23: Other accounts payable | E23: Income tax payable | F23: -101461.4 | H23: =F23+G23 -> -101461.4 | I23: 7300
D24: Related Party | E24: Other Accounts payable | F24: -1.8704377e+08 | H24: =F24+G24 -> -1.8704377e+08
E25: Total current liabilities | F25: =(((F18)+(F20))+(F21))+(F23)+F24+F19+F22 -> -67183622 | H25: =(((H18)+(H20))+(H21))+(H23)+H24+H19+H22 -> -67183622
E26: Shareholders' equity:
D27: PL | E27: Net Income | F27: -352025.71 | H27: =-H82 -> -258145.04
D28: Accumulated deficit | E28: Retained Earnings | F28: =-39372.79 -> -39372.79 | H28: =F28+G28 -> -39372.79
E29: Total shareholders' equity | F29: =(F27)+(F28) -> -391398.5 | H29: =(H27)+(H28) -> -297517.83
E30: Total liabilities and equity | F30: =(F25)+(F29) -> -67575020 | H30: =(H25)+(H29) -> -67481140
F31: =F30+F12 -> 0 | H31: =H30+H12 -> 0
C35: Profit and Loss
F37: Total | H37: Total
E38: Income
E39: IC Revenues | F39: =27496341.36 -> 27496341 | G39: =-'AJE 2021'!V35 -> -579444.48 | H39: =F39+G39 -> 26916897
E40: Revenue - Cyber Source | F40: 88038642 | G40: =-'AJE 2021'!V86 -> -328087 | H40: =F40+G40 -> 87710555
E41: Revenue - PayPal | F41: 53900734 | G41: =-'AJE 2021'!V87 -> -34927 | H41: =F41+G41 -> 53865807
E42: Revenue - Paypal US | F42: 219465.75 | G42: =-'AJE 2021'!V11 -> -1253.84 | H42: =F42+G42 -> 218211.91
E43: Revenue - T1 | F43: 406507.57 | H43: =F43+G43 -> 406507.57
E44: Revenue - Wordpay | F44: 30730303 | G44: =-'AJE 2021'!V12 -> -121298 | H44: =F44+G44 -> 30609005
E45: Revenue - Sales Tax | F45: 0 | G45: =-'AJE 2021'!W24 -> -4903754.4 | H45: =F45+G45 -> -4903754.4
C46: Total Revenues | D46: Total Revenues | E46: Total Income | F46: =SUM(F39:F45) -> 2.0079199e+08 | H46: =SUM(H39:H45) -> 1.9482323e+08
E47: Cost of Sales
B48: Fee | C48: Cost of revenues | D48: Fee | E48: Chargeback expenses- SVB | F48: 328087 | G48: =-'AJE 2021'!W8 -> -328087 | H48: =F48+G48 -> 0
B49: Fee | C49: Cost of revenues | D49: Fee | E49: Chargeback expenses- Worldpay | F49: 121298 | G49: =-'AJE 2021'!W9 -> -121298 | H49: =F49+G49 -> 0 | I49: =SUM(G48:G51) -> -485565.84
B50: Fee | C50: Cost of revenues | D50: Fee | E50: Chargeback Payapal US | F50: 1253.84 | G50: =-'AJE 2021'!W10 -> -1253.84 | H50: =F50+G50 -> 0 | I50: =I49*1.054 -> -511786.4
B51: Fee | C51: Cost of revenues | D51: Fee | E51: Chargeback Paypal | F51: 34927 | G51: =-'AJE 2021'!W85 -> -34927 | H51: =F51+G51 -> 0
A52: FEE | B52: Fee | C52: Cost of revenues | D52: Fee | E52: Commission - Cyber Source | F52: 674759.5 | H52: =F52+G52 -> 674759.5
A53: FEE | B53: Fee | C53: Cost of revenues | D53: Fee | E53: Fees - Wordpay | F53: 1849874.3 | H53: =F53+G53 -> 1849874.3
B54: Fee | C54: Cost of revenues | D54: Fee | E54: Fees Payapal US | F54: 12536.11 | H54: =F54+G54 -> 12536.11
E55: Total Cost of Sales | F55: =SUM(F48:F54) -> 3022735.8 | H55: =SUM(H48:H54) -> 2537169.9
E56: Gross Profit | F56: =F46-F55 -> 1.9776926e+08 | H56: =H46-H55 -> 1.9228606e+08
E57: Expenses
A58: Ua | B58: Ua | C58: Marketing expenses | D58: User Acquisition | E58: Advertising and Promotion | F58: 16153404 | H58: =F58+G58 -> 16153404
A59: Financial expenses | B59: Financial expenses | C59: Financial expenses, net | D59: Financial expenses, net | E59: Bank charges | F59: 1446.01 | H59: =F59+G59 -> 1446.01
A60: FEE | B60: Fee | C60: Cost of revenues | D60: Fee | E60: Commissions and fees | F60: 7437127.2 | H60: =F60+G60 -> 7437127.2
A61: Overheads | B61: Overheads | C61: General and administrative expenses | D61: professional fees | E61: Dues and subscriptions | F61: 7092.78 | H61: =F61+G61 -> 7092.78
B62: Financial expenses | C62: Financial expenses, net | D62: Financial expenses, net | E62: Epricing Fee -Currency difference | F62: 111676 | H62: =F62+G62 -> 111676
B63: Financial expenses | C63: Financial expenses, net | D63: Financial expenses, net | E63: Exchange rate paypal | F63: 48647 | H63: =F63+G63 -> 48647
C64: TP Expenses | D64: TP Expenses | E64: IC Expenses | F64: 1.7325995e+08 | G64: =N93 -> -5389318.2 | H64: =F64+G64 -> 1.6787063e+08
C65: TP Expenses | D65: TP Expenses | E65: IC Expenses -Israel | F65: 35700 | H65: =F65+G65 -> 35700
A66: Taxes | B66: Taxes | C66: Tax expenses | D66: Tax expenses | E66: Income tax expense | F66: 117369 | H66: =F66+G66 -> 117369
A67: Overheads | B67: Overheads | C67: General and administrative expenses | D67: professional fees | E67: Insurance - General | F67: 0 | H67: =F67+G67 -> 0
A68: Overheads | B68: Overheads | C68: General and administrative expenses | D68: professional fees | E68: irrecoverable vat | F68: 6069 | H68: =F68+G68 -> 6069
A69: Overheads | B69: Overheads | C69: General and administrative expenses | D69: professional fees | E69: James Kong consulting expenses | F69: 8333.33 | H69: =F69+G69 -> 8333.33
A70: Overheads | B70: Overheads | C70: General and administrative expenses | D70: Legal | E70: Legal and professional fees | F70: 12314.44 | H70: =F70+G70 -> 12314.44
A71: Ua | B71: Ua Indirect | C71: Marketing expenses | D71: Softwere subscription | E71: Marketing Fee | F71: -1181.27 | H71: =F71+G71 -> -1181.27
A72: Overheads | B72: Overheads | C72: General and administrative expenses | D72: Other expenses | E72: Office expenses | F72: -6000 | H72: =F72+G72 -> -6000
A73: Overheads | B73: Overheads | C73: General and administrative expenses | D73: Other expenses | E73: Other general and administrative expenses | F73: 10733.87 | H73: =F73+G73 -> 10733.87
A74: Overheads | B74: Overheads | C74: General and administrative expenses | D74: Other expenses | E74: Rent or lease payments | F74: 100 | H74: =F74+G74 -> 100
A75: Overheads | B75: Overheads | C75: Cost of revenues | D75: Softwere subscription | E75: Software Subscription | F75: 200000 | H75: =F75+G75 -> 200000
A76: Taxes | B76: Taxes | C76: Tax expenses | D76: Tax expenses | E76: State Taxes and Fees | F76: 14227.77 | H76: =F76+G76 -> 14227.77
A77: Overheads | B77: Overheads | C77: General and administrative expenses | D77: Other expenses | E77: Utilities | F77: 222.83 | H77: =F77+G77 -> 222.83
E78: Total Expenses | F78: =SUM(F58:F77) -> 1.9741723e+08 | H78: =SUM(H58:H77) -> 1.9202791e+08
E79: Other Expenses
E80: Unrealised Gain or Loss | F80: 0 | H80: 0
E81: Total Other Expenses | F81: 0 | H81: 0
E82: Net Earnings | F82: =F56-F78 -> 352025.71 | H82: =H56-H78 -> 258145.04 | I82: =H82-F82 -> -93880.666
E85: Inc Exp | F85: =SUM(F48:F54)+F60+F61+F69+F70+F72+F73+F74+F75+F77+F68 -> 10698729 | H85: =SUM(H48:H54)+H60+H61+H69+H70+H72+H73+H74+H75+H77+H68 -> 10213163 | L85: Should Be | M85: Books
E86: Inc Exp + 5.4% | F86: =F85*1.054 -> 11276461 | H86: =H85*1.054 -> 10764674 | J86: Cogs | K86: =SUM(H48:H54)+H60+H75 -> 10174297 | L86: =K86*1.054 -> 10723709 | M86: ='P&L LTD USD'!D20 -> 11270061 | N86: =L86-M86 -> -546352.16
E87: Total IC exp - Sholud Be | F87: =F58+F71+F86 -> 27428683 | H87: =H58+H71+H86 -> 26916897 | J87: S&M | K87: =F58+F71 -> 16152223 | L87: =K87 -> 16152223 | M87: ='P&L LTD USD'!D47 -> 16152223 | N87: =L87-M87 -> -0.38
E88: Total IC exp - books | F88: =F39 -> 27496341 | H88: =F39 -> 27496341 | J88: G&n | K88: =H61+H68+H69+H70+H72+H73+H74+H77 -> 38866.25 | L88: =K88*1.054 -> 40965.028 | M88: ='P&L LTD USD'!D70 -> 74057.94 | N88: =L88-M88 -> -33092.912
F89: =F87-F88 -> -67658.081 | H89: =H87-H88 -> -579444.48
N90: =SUM(N86:N89) -> -579445.46 | O90: Diff
E91: Total inc income | F91: =SUM(F40:F44) -> 1.7329565e+08 | H91: =SUM(H40:H45) -> 1.6790633e+08
E92: Total LTD income | F92: =F64+F65 -> 1.7329565e+08 | H92: =H64+H65 -> 1.6790633e+08 | L92: Should Be | M92: Books
F93: =F91-F92 -> 2.03 | H93: =H91-H92 -> 0 | J93: IC revenue | L93: =SUM(H40:H45) -> 1.6790633e+08 | M93: =F64+F65 -> 1.7329565e+08 | N93: =L93-M93 -> -5389318.2 | O93: Diff

Sheet Tech Plant Check
C1: 2018 | D1: 2019 | E1: 2020 | G1: 2021
B2: Opening Balance | D2: =+C5 -> 299492.06 | E2: =+D5 -> 1188415 | G2: =+E5 -> 2792020
B3: Expected Loss (Revenue) | E3: =2173604.92192246-570000 -> 1603604.9 | G3: =-4850953*4 -> -19403812
B4: Carryforward losses | C4: =1076644/3.5949 -> 299492.06 | D4: =3168566/3.5645 -> 888922.99
B5: Ending Balance | C5: =+SUM(C2:C4) -> 299492.06 | D5: =+SUM(D2:D4) -> 1188415 | E5: =+SUM(E2:E4) -> 2792020 | G5: =+SUM(G2:G4) -> -16611792
B10: Requirements
B12: R&D Expenses test (7%/75M NIS) | C12: 2018 | D12: 2019 | E12: 2020 | F12: 2021
B13: Revenues | C13: 0 | D13: 866635 | E13: 15116394 | F13: =-'P&L USD CONS'!I7*1000 -> 1.6307024e+08 | K13: missing
B14: R&D Expenses | C14: 201051 | D14: 692900 | E14: 2297223 | F14: ='P&L USD CONS'!I13*1000 -> 11109841 | J14: =I13*0.07 -> 0 | K14: =J14-I14 -> 0
B15: R&D Expenses\Revenues Ratio | D15: =+D14/D13 -> 0.79952921 | E15: =+E14/E13 -> 0.15196898 | F15: =+F14/F13 -> 0.068129174
B16: R&D Expenses\Revenues Ratio - 3Y AVG | E16: =+AVERAGE(C14:E14)/AVERAGE(C13:E13) -> 0.19966015 | F16: =+AVERAGE(D14:F14)/AVERAGE(D13:F13) -> 0.078747313 | K16: =J14/I13 -> #DIV/0!
B17: Missing R&D Expenses to reach the ratio | F17: =AVERAGE(D13:F13)*0.07 -> 4177909.6
B18: R&D Expenses Non GAAP | F18: =AVERAGE(D14:F14) -> 4699987.9 | J18: =+G18/0.04 -> 0 | K18: Break even point | L18: Net Income in 2022
F19: =F17-F18 -> -522078.31 | G19: =F19*3 -> -1566234.9 | H19: missing exp | K19: Above this point Its better to Increase our R&D Spend to reach the ratio
B21: Investment from VC in USD | C21: 500000 | E21: 5748600
B22: AVERAGE NIS/USD Exchange rate | C22: 3.5949 | D22: 3.5645 | E22: 3.4424 | G22: 3.2549
B23: Investment - 8M NIS investment from VC | C23: =+C21*C22 -> 1797450 | E23: =+E21*E22 -> 19788981
K24: 993 | L24: ספטמבר R&D
B25: 25% Increase in AVG revenues Yearly | C25: 0 | D25: 0 | E25: =+E13/D13-1 -> 16.44263 | K25: -181 | L25: founder Bonus
K26: =-(150+86)/3.25 -> -72.615385 | L26: Emp Bonus
B27: 25% Increase in AVG number of employees + at least 50 employees
B28: Number of employees | C28: 3 | D28: 13 | E28: 33 | G28: 67 | H28: 13 | I28: =G28+H28 -> 80 | K28: =K24+K25+K26 -> 739.38462
B29: HC Increase ratio | C29: 0 | D29: =+D28/C28-1 -> 3.3333333 | E29: =+E28/D28-1 -> 1.5384615 | G29: =+G28/E28-1 -> 1.030303 | I29: =G29+H29 -> 1.030303
I30: =G30+H30 -> 0 | L30: רועי
B31: 20% of the Company's employees expenses listed as R&D or At least 200 Employees | I31: =G31+H31 -> 0 | K31: 3461 | L31: יולי V2
B32: R&D Payroll | C32: =(330825+326191)/C22 -> 182763.36 | D32: =449059+791642/$D$22 -> 671149.62 | E32: 1527152 | G32: 5994309 | I32: =G32+H32 -> 5994309
B33: R&D HC | C33: 2 | D33: 9 | E33: 23 | G33: 40 | H33: 6 | I33: =G33+H33 -> 46 | K33: =651*5 -> 3255 | L33: הערכה
B34: Total Payroll | C34: =+(142534+73203)+C32 -> 398500.36 | D34: =958816+791642/$D$22+358000/$D$22 -> 1281341.5 | E34: 2005609 | G34: 9020947 | I34: =G34+H34 -> 9020947
B35: Total HC | C35: =+C28 -> 3 | D35: =+D28 -> 13 | E35: =+E28 -> 33 | G35: =+G28 -> 67 | H35: 13 | I35: =G35+H35 -> 80
B36: R&D Payroll expenses ratio | C36: =+C32/C34 -> 0.45862784 | D36: =+D32/D34 -> 0.5237867 | E36: =+E32/E34 -> 0.76144054 | G36: =+G32/G34 -> 0.66448778 | I36: =G36+H36 -> 0.66448778
B37: R&D HC ratio | C37: =+C33/C35 -> 0.66666667 | D37: =+D33/D35 -> 0.69230769 | E37: =+E33/E35 -> 0.6969697 | G37: =+G33/G35 -> 0.59701493 | H37: =+H33/H35 -> 0.46153846 | I37: =G37+H37 -> 1.0585534 | K37: =K31+K33 -> 6716 | L37: סה״כ RD
B39: מפעל מועדף - תנאים | C39: 0.16
B40: מפעל תעשייתי - בית תכנה נחשב מפעל תעשייתי
B41: מפעל בר תחרות - רוב ההכנסות נובעות מייצוא
C44: 3.597 | D44: 3.5643 | E44: 3.4367 | G44: 3.5882
B45: R&D Expenses test (7%/75M NIS) | C45: 2018 | D45: 2019 | E45: 2020 | G45: 2021 - ytd 9.21 | H45: Oct-Dec 2021 estimeted | I45: Total 2021
B46: Revenues | D46: =D13*D44 -> 3088947.1 | E46: =E13*3.4367 -> 51950511 | G46: =G13*3.4367 -> 0 | H46: =17500000*3*G44 -> 188380500 | I46: =G46+H46 -> 188380500
B47: R&D Expenses | C47: =C14*C44 -> 723180.45 | D47: =D14*D44 -> 2469703.5 | E47: =E14*E44 -> 7894866.3 | G47: =G14*G44 -> 0 | H47: =(993000-200000)*3*G44 -> 8536327.8 | I47: =G47+H47 -> 8536327.8
B48: R&D Expenses\Revenues Ratio | D48: =+D47/D46 -> 0.79952921 | E48: =+E47/E46 -> 0.15196898 | G48: =+G47/G46 -> #DIV/0! | H48: =+H47/H46 -> 0.045314286 | I48: =+I47/I46 -> 0.045314286
B49: R&D Expenses\Revenues Ratio - 3Y AVG | E49: =+AVERAGE(C47:E47)/AVERAGE(C46:E46) -> 0.13430062 | G49: =+AVERAGE(D47:G47)/AVERAGE(D46:G46) -> 0.18831162 | H49: =+AVERAGE(E47:H47)/AVERAGE(E46:H46) -> 0.068369013 | I49: =+AVERAGE(G47:I47)/AVERAGE(G46:I46) -> 0.045314286
B50: Missing R&D Expenses to reach the ratio | G50: =0.07*SUM(D46:G46)-SUM(D47:G47) -> -6511807.7 | H50: =0.07*SUM(E46:H46)-SUM(E47:H47) -> 391976.7
J51: =+G50/0.04 -> -1.6279519e+08 | K51: Break even point | L51: Net Income in 2022
K52: Above this point Its better to Increase our R&D Spend to reach the ratio
B53: Investment from VC in USD | C53: 500000 | E53: 5748600
B54: AVERAGE NIS/USD Exchange rate | C54: 3.5949 | D54: 3.5645 | E54: 3.4424 | G54: 3.2549
B55: Investment - 8M NIS investment from VC | C55: =+C53*C54 -> 1797450 | E55: =+E53*E54 -> 19788981
B57: 25% Increase in AVG revenues Yearly | C57: 0 | D57: 0 | E57: =+E46/D46-1 -> 15.818194 | G57: =+G46/E46-1 -> -1
B59: 25% Increase in AVG number of employees + at least 50 employees
B60: Number of employees | C60: 3 | D60: 13 | E60: 33 | G60: 67 | H60: 13 | I60: =G60+H60 -> 80
B61: HC Increase ratio | C61: 0 | D61: =+D60/C60-1 -> 3.3333333 | E61: =+E60/D60-1 -> 1.5384615 | G61: =+G60/E60-1 -> 1.030303 | I61: =G61+H61 -> 1.030303
I62: =G62+H62 -> 0
B63: 20% of the Company's employees expenses listed as R&D or At least 200 Employees | I63: =G63+H63 -> 0
B64: R&D Payroll | C64: =(330825+326191)/C54 -> 182763.36 | D64: =449059+791642/$D$22 -> 671149.62 | E64: 1527152 | G64: 5994309 | I64: =G64+H64 -> 5994309
B65: R&D HC | C65: 2 | D65: 9 | E65: 23 | G65: 40 | H65: 6 | I65: =G65+H65 -> 46
B66: Total Payroll | C66: =+(142534+73203)+C64 -> 398500.36 | D66: =958816+791642/$D$22+358000/$D$22 -> 1281341.5 | E66: 2005609 | G66: 9020947 | I66: =G66+H66 -> 9020947
B67: Total HC | C67: =+C60 -> 3 | D67: =+D60 -> 13 | E67: =+E60 -> 33 | G67: =+G60 -> 67 | H67: 13 | I67: =G67+H67 -> 80
B68: R&D Payroll expenses ratio | C68: =+C64/C66 -> 0.45862784 | D68: =+D64/D66 -> 0.5237867 | E68: =+E64/E66 -> 0.76144054 | G68: =+G64/G66 -> 0.66448778 | I68: =G68+H68 -> 0.66448778
B69: R&D HC ratio | C69: =+C65/C67 -> 0.66666667 | D69: =+D65/D67 -> 0.69230769 | E69: =+E65/E67 -> 0.6969697 | G69: =+G65/G67 -> 0.59701493 | H69: =+H65/H67 -> 0.46153846 | I69: =G69+H69 -> 1.0585534
B71: מפעל מועדף - תנאים | C71: 0.16
B72: מפעל תעשייתי - בית תכנה נחשב מפעל תעשייתי
B73: מפעל בר תחרות - רוב ההכנסות נובעות מייצוא

Sheet R&D 20A
C1: 3 | D1: =+C1+1 -> 4 | E1: =+D1+1 -> 5 | F1: =+E1+1 -> 6 | G1: =+F1+1 -> 7 | H1: =+G1+1 -> 8 | I1: =+H1+1 -> 9
A3: Research and development expenses, net | D3: פריסת הוצאות מו"פ
B4: 2017 | C4: 2018 | D4: 2019 | E4: 2020 | F4: 2021 | G4: 2022 | H4: 2023 | I4: סך הוצאה
A5: 2017 | B5: =I5/3 -> 53630.333 | C5: =B5 -> 53630.333 | D5: =C5 -> 53630.333 | I5: 160891
A6: 2018 | C6: =I6/3 -> 241060.77 | D6: =C6 -> 241060.77 | E6: =D6 -> 241060.77 | I6: 723182.3
A7: 2019 | D7: =+$I$7/3 -> 813428.31 | E7: =+$I$7/3 -> 813428.31 | F7: =+$I$7/3 -> 813428.31 | I7: 2440284.9
A8: 2020 | E8: =+$I$8/3 -> 2085326.3 | F8: =+$I$8/3 -> 2085326.3 | G8: =+$I$8/3 -> 2085326.3 | I8: 6255979
A9: 2021 | F9: =+$I$9/3 -> 10701138 | G9: =+$I$9/3 -> 10701138 | H9: =+$I$9/3 -> 10701138 | I9: =C21 -> 32103414
C16: 44531
A17: RND Expenses Adjustments | C17: ='P&L LTD USD'!J25 -> 33751918
A18: 23012 | B18: הוצאות הפרשה להבראה מופ | C18: =-VLOOKUP(A18,'TB LTD 12.21'!D:F,3,0) -> -4931.25
A19: 23011 | B19: הוצאות חופשה מופ | C19: =-VLOOKUP(A19,'TB LTD 12.21'!D:F,3,0) -> -119695.6
A20: 23031 | B20: הוצאות אופציות מחקר ופיתוח | C20: =-VLOOKUP(A20,'TB LTD 12.21'!D:F,3,0) -> -1523877.4
C21: =+SUM(C17:C20) -> 32103414

Sheet CF FS
A1: 44561
A2: Cash Flow
A3: Papaya Gaming Ltd
A4: USD
B7: Consolidated staements of cash flows 31/12/2021
B9: Operating activities | C9: USD | D9: USD in thousands
B10: Net Profit | C10: ='CF WP'!C41 -> 8067474.7 | D10: ='CF WP'!D41 -> 8067
B12: Depreciation | C12: ='CF WP'!C44 -> 80801.5 | D12: ='CF WP'!D44 -> 81
B13: Share based compensation | C13: ='CF WP'!C45 -> 1827183.8 | D13: ='CF WP'!D45 -> 1827
B14: Deffered tax liabilities | C14: ='CF WP'!C46 -> -570768.42 | D14: ='CF WP'!D46 -> -571
B15: Financial expenses (Fx) | C15: ='CF WP'!C47 -> 18328.26 | D15: ='CF WP'!D47 -> 18
B16: Changes in operating assets and liabilities:
B17: ='CF WP'!B48 -> Prepaid expenses and other current assets | C17: ='CF WP'!C48 -> -2318521.3 | D17: ='CF WP'!D48 -> -2319
B18: ='CF WP'!B49 -> Account receivable | C18: ='CF WP'!C49 -> -1095870.7 | D18: ='CF WP'!D49 -> -1096
B19: ='CF WP'!B50 -> Trade payables change | C19: ='CF WP'!C50 -> 10773849 | D19: ='CF WP'!D50 -> 10774
B20: ='CF WP'!B51 -> Other accounts payable and accrued expenses | C20: ='CF WP'!C51 -> 19521615 | D20: ='CF WP'!D51 -> 19522
B21: ='CF WP'!B52 -> Reserve - Wordpay | C21: ='CF WP'!C52 -> -199999 | D21: ='CF WP'!D52 -> -200
B22: ='CF WP'!B53 -> Deposit | C22: ='CF WP'!C53 -> -15253.2 | D22: ='CF WP'!D53 -> -15
B23: ='CF WP'!B55 -> Contract liability change | C23: ='CF WP'!C55 -> 3485732 | D23: ='CF WP'!D55 -> 3486
B24: ='CF WP'!B56 -> Receivables for shares issued | C24: ='CF WP'!C56 -> 50000 | D24: ='CF WP'!D56 -> 50
B25: ='CF WP'!B57 -> Operating lease ROU assets and liabilities, net | C25: ='CF WP'!C57 -> -23761.983 | D25: ='CF WP'!D57 -> -24
B26: ='CF WP'!B58 -> Shreholders loan | C26: ='CF WP'!C58 -> -14953 | D26: ='CF WP'!D58 -> -15
B27: ='CF WP'!B59 -> Interest received | C27: ='CF WP'!C59 -> 0 | D27: ='CF WP'!D59 -> 0
C28: ='CF WP'!C60 -> 31518383 | D28: ='CF WP'!D60 -> 31518
B30: Net cash provieded by (used in) operating activities | C30: ='CF WP'!C62 -> 39585857 | D30: ='CF WP'!D62 -> 39586
B32: Investing activities | C32: ='CF WP'!C64 -> 0 | D32: ='CF WP'!D64 -> 0
B33: Purchase of property and equipment | C33: ='CF WP'!C65 -> -499111.3 | D33: ='CF WP'!D65 -> -499
B34: Shareholders | D34: ='CF WP'!D66 -> 0
B35: Options exercised | D35: ='CF WP'!D67 -> 0
C36: ='CF WP'!C68 -> -499111.3 | D36: ='CF WP'!D68 -> -499
B38: Financing activities
B39: Proceeds from issuance of Ordinary Shares | C39: ='CF WP'!C70 -> 0 | D39: ='CF WP'!D70 -> 0
B40: Proceeds from issuance of Preffered Seed Shares, net of issiance expenses | D40: ='CF WP'!D71 -> 0
B41: Shareholders loan | D41: ='CF WP'!D72 -> 0
B42: Proceeds from issuance of Preffered Seed Shares, net of issiance expenses | D42: ='CF WP'!D73 -> 16
B43: Repayment of long term loan | C43: ='CF WP'!C74 -> 1834818.5 | D43: ='CF WP'!D74 -> 1835
C44: ='CF WP'!C75 -> 1850775.1 | D44: =SUM(D39:D43) -> 1851
B47: Cash Change | C47: ='CF WP'!C78 -> 40937521 | D47: ='CF WP'!D78 -> 40938
B48: Cash FX Change | C48: ='CF WP'!C79 -> 83437.15 | D48: ='CF WP'!D79 -> 83
B49: Cash O.B | C49: ='CF WP'!C80 -> 7494535 | D49: ='CF WP'!D80 -> 7495
B50: Cash C.B | C50: ='CF WP'!C81 -> 48515493 | D50: ='CF WP'!D81 -> 48515
B52: Check | C52: ='CF WP'!C83 -> 1.14 | D52: ='CF WP'!C83/1000 -> 0.00114
B54: ='CF WP'!B85 -> Shareholders loan | D54: ='CF WP'!C85/1000 -> 415.46835
B55: ='CF WP'!B86 -> Interest Paid | D55: ='CF WP'!C86/1000 -> 266.88908
B56: ='CF WP'!B87 -> ASC842 Adoption | D56: ='CF WP'!C87/1000 -> 610.28011
B57: ='CF WP'!B88 -> Tax Paid | D57: ='CF WP'!C88/1000 -> 57.70901

Sheet CF WP
A1: 44561
A2: Cash Flow
A3: Papaya Gaming Ltd
A4: USD
B5: Consolidated staements of cash flows
D6: $
A7: Ref | D7: 44196 | E7: Profit | F7: Operating activities | G7: Investing activities | H7: Financing activities | I7: Transfers | J7: Cash Change | K7: FX change | L7: 44561 | M7: Check
B8: Assets
B9: Cash | D9: 7494535 | J9: =L9-D9-K9 -> 40937520 | K9: =-'CF WP'!C180-C190-C193 -> 83437.15 | L9: ='BS USD CONS '!J8 -> 48515492 | M9: =SUM(D9:K9)-L9 -> 0
B10: Account receivable | D10: 110155 | F10: =L10-D10-K10 -> 1095870.7 | K10: =-C179 -> -10013.8 | L10: ='BS USD CONS '!J9 -> 1196011.9 | M10: =SUM(D10:K10)-L10 -> 0
B11: Prepaid expenses and other current assets | D11: 139176.3 | F11: =L11-D11-K11 -> 2318521.3 | K11: =-C185-C186 -> 27023.49 | L11: ='BS USD CONS '!J17+'BS USD CONS '!J16+SUM('BS USD CONS '!J10:J12) -> 2484721.1 | M11: =SUM(D11:K11)-L11 -> 0
A12: 9 | B12: ROA Assets | D12: 0 | F12: =C207 -> -201158.44 | I12: =C206 -> 610280.11 | L12: ='BS USD CONS '!J23 -> 409121.67 | M12: =SUM(D12:K12)-L12 -> 0
A13: 1 | B13: Fixed assets, net | D13: 81585 | F13: =+D97 -> -80801.5 | G13: =+D95 -> 501111.3 | L13: ='BS USD CONS '!J26 -> 501895.3 | M13: =SUM(D13:K13)-L13 -> -0.5
B14: Deferred tax assets | D14: 449291 | F14: =L14-D14-K14 -> 570768.42 | K14: =-C181 -> -80650.47 | L14: ='BS USD CONS '!J24 -> 939408.95 | M14: =SUM(D14:K14)-L14 -> 0
B15: Investment | D15: 0 | F15: =L15-D15 -> 0 | L15: ='BS USD CONS '!J22 -> 0 | M15: =SUM(D15:K15)-L15 -> 0
B16: Deposit | D16: 0 | F16: =L16-D16-K16 -> 15253.2 | K16: =-C182 -> 823.97 | L16: ='BS USD CONS '!J14 -> 16077.17 | M16: =SUM(D16:K16)-L16 -> 0
B17: Reserve - Wordpay | D17: 0 | F17: =L17-D17 -> 199999 | L17: ='BS USD CONS '!J25 -> 199999 | M17: =SUM(D17:K17)-L17 -> 0
B18: Shareholders loan | D18: 400515.77 | F18: =D129+D131 -> 14953 | I18: =D130 -> -415468.35 | L18: 0 | M18: =SUM(D18:K18)-L18 -> 0.42
B20: Liabilities and Shareholders equity | D20: =SUM(D9:D18) -> 8675258.1 | L20: =SUM(L9:L17) -> 54262727
B21: Trade payables | D21: -3058971 | F21: =L21-D21-K21-I21 -> -10775849 | I21: =-I18 -> 415468.35 | K21: =-C189 -> -14482.75 | L21: ='BS USD CONS '!J34 -> -13433835 | M21: =SUM(D21:K21)-L21 -> 0
B22: Other accounts payable and accrued expenses | D22: -994278 | F22: =L22-D22-K22-I22 -> -19521615 | K22: =-C184 -> -71310.15 | L22: ='BS USD CONS '!J42+'BS USD CONS '!J35+'BS USD CONS '!J38 -> -20587203
A23: 9 | B23: ROA Liability | D23: 0 | F23: =C216+C217 -> 224920.42 | I23: =C215 -> -610280.11 | L23: ='BS USD CONS '!J40 -> -385359.69 | M23: =SUM(D23:K23)-L23 -> 0
B24: Contract liability | D24: -601925 | F24: =L24-D24-I24 -> -3485732 | L24: ='BS USD CONS '!J37 -> -4087657 | M24: =SUM(D24:K24)-L24 -> 0
A25: 2 | B25: Loan-Short term | D25: -266667 | H25: =SUM(D106:D107)-K25 -> -1768152.1 | K25: =-C183 -> 1485.13 | L25: ='BS USD CONS '!J36 -> -2033334 | M25: =SUM(D25:K25)-L25 -> 0.03
A26: 3 | B26: Loan-Long term | D26: -466666 | H26: =SUM(D117:D119)-K26 -> -66666.39 | L26: ='BS USD CONS '!J45 -> -533332.72 | M26: =SUM(D26:K26)-L26 -> 0.33
A27: =A125 -> 4 | B27: Shareholders | D27: -545359 | F27: =L27-D27-K27-H27 -> 0.39 | K27: =-C188 -> 45358.61 | L27: ='BS USD CONS '!J46 -> -500000 | M27: =SUM(D27:K27)-L27 -> 0
A28: =A150 -> 6 | B28: Share capital - Ordinary Shares | D28: -346 | H28: =C153-K28 -> -73.88 | K28: =-C187 -> 0.56 | L28: ='BS USD CONS '!J54 -> -418.92 | M28: =SUM(D28:K28)-L28 -> -0.4
B29: Share capital - Preferred Seed-1 | D29: -191 | L29: ='BS USD CONS '!J55 -> -191 | M29: =SUM(D29:K29)-L29 -> 0
B30: Share capital - Preferred Seed | D30: -49 | L30: ='BS USD CONS '!J56 -> -49.24 | M30: =SUM(D30:K30)-L30 -> 0.24
A31: =A136 -> 5 | B31: Share premium | D31: -6771841 | F31: =C141+C140 -> -1827183.8 | H31: =C142 -> -15883.3 | L31: ='BS USD CONS '!J57 -> -8614908.1 | M31: =SUM(D31:K31)-L31 -> 0
B32: Receivables for shares issued | D32: 50000 | F32: -50000 | L32: ='BS USD CONS '!J58 -> 0 | M32: =SUM(D32:K32)-L32 -> 0
B33: Accumulated deficit | D33: =2132292+1848743 -> 3981035 | L33: ='BS USD CONS '!J59 -> 3981035.1 | M33: =SUM(D33:K33)-L33 -> -0.15
B34: PL | D34: 0 | E34: =L34-K34 -> -8067474.7 | L34: ='BS USD CONS '!J60 -> -8067474.7 | M34: =SUM(D34:K34)-L34 -> 0
D36: =SUM(D21:D35) -> -8675258 | E36: =SUM(E10:E35) -> -8067474.7 | F36: =SUM(F10:F35) -> -31502054 | G36: =SUM(G10:G35) -> 501111.3 | H36: =SUM(H10:H35) -> -1850775.7 | I36: =SUM(I10:I35) -> 0 | J36: =SUM(J9:J35) -> 40937520 | K36: =SUM(K9:K35) -> -18328.26 | L36: =SUM(L21:L35) -> -54262728 | M36: =SUM(E36:K36) -> -1.31
D37: =+D36+D20 -> 0.07 | L37: =+L36+L20 -> -1.21
B38: Consolidated staements of cash flows 31/12/2021 | F38: =F36+C60 -> 16328.65
B40: Operating activities | J40: =-K36+F18 -> 33281.26
B41: Net Profit | C41: =-E34 -> 8067474.7 | D41: =+ROUND(C41/1000,0) -> 8067
A44: התאמה בגין הוצאות שלא במזומן | B44: Depreciation | C44: =-F13 -> 80801.5 | D44: =+ROUND(C44/1000,0) -> 81
A45: התאמה בגין הוצאות שלא במזומן | B45: Share based compensation | C45: =-SUM(C140:C141) -> 1827183.8 | D45: =+ROUND(C45/1000,0) -> 1827
A46: התאמה בגין הוצאות שלא במזומן | B46: Deffered tax liabilities | C46: =-F14 -> -570768.42 | D46: =+ROUND(C46/1000,0) -> -571
B47: Financial expenses (Fx) | C47: =-K36 -> 18328.26 | D47: =+ROUND(C47/1000,0) -> 18
B48: =B11 -> Prepaid expenses and other current assets | C48: =-F11 -> -2318521.3 | D48: =+ROUND(C48/1000,0) -> -2319
B49: =B10 -> Account receivable | C49: =-F10 -> -1095870.7 | D49: =+ROUND(C49/1000,0) -> -1096
B50: Trade payables change | C50: =-F21-2000 -> 10773849 | D50: =+ROUND(C50/1000,0) -> 10774
B51: =B22 -> Other accounts payable and accrued expenses | C51: =-F22 -> 19521615 | D51: =+ROUND(C51/1000,0) -> 19522
B52: Reserve - Wordpay | C52: =-F17 -> -199999 | D52: =+ROUND(C52/1000,0) -> -200
B53: Deposit | C53: =-F16 -> -15253.2 | D53: =+ROUND(C53/1000,0) -> -15
D54: =+ROUND(C54/1000,0) -> 0
B55: Contract liability change | C55: =-F24 -> 3485732 | D55: =+ROUND(C55/1000,0) -> 3486
B56: =B32 -> Receivables for shares issued | C56: =-F32 -> 50000 | D56: =+ROUND(C56/1000,0) -> 50
B57: Operating lease ROU assets and liabilities, net | C57: =-F12-F23 -> -23761.983 | D57: =+ROUND(C57/1000,0) -> -24
B58: Shreholders loan | C58: =-F18 -> -14953 | D58: =+ROUND(C58/1000,0) -> -15
B59: Interest received
C60: =SUM(C43:C59) -> 31518383 | D60: =+ROUND(C60/1000,0) -> 31518
B62: Net cash provieded by (used in) operating activities | C62: =C60+C41 -> 39585857 | D62: =+ROUND(C62/1000,0) -> 39586
B64: Investing activities
B65: Purchase of property and equipment | C65: =-G13+2000 -> -499111.3 | D65: =+ROUND(C65/1000,0) -> -499
B66: Shareholders | C66: =-G28 -> 0 | D66: =+ROUND(C66/1000,0) -> 0
C68: =SUM(C65:C67) -> -499111.3 | D68: =+ROUND(C68/1000,0) -> -499
B69: Financing activities
B70: Proceeds from issuance of Ordinary Shares | D70: =+ROUND(C70/1000,0) -> 0
B71: Proceeds from issuance of Preffered Seed Shares, net of issiance expenses | D71: =+ROUND(C71/1000,0) -> 0
B72: Shreholders loan | C72: =-H18 -> 0 | D72: =+ROUND(C72/1000,0) -> 0
B73: =B142 -> Options exercised | C73: =-C153-C142 -> 15956.62 | D73: =+ROUND(C73/1000,0) -> 16
B74: Repayment of long term loan | C74: =-H26-H25 -> 1834818.5 | D74: =+ROUND(C74/1000,0) -> 1835
C75: =+SUM(C70:C74) -> 1850775.1 | D75: =+ROUND(C75/1000,0) -> 1851
B78: Cash Change | C78: =C68+C62+C75 -> 40937521 | D78: =+ROUND(C78/1000,0) -> 40938
B79: Cash FX Change | C79: =K9 -> 83437.15 | D79: =+ROUND(C79/1000,0) -> 83
B80: Cash O.B | C80: =D9 -> 7494535 | D80: =+ROUND(C80/1000,0) -> 7495
B81: Cash C.B | C81: =SUM(C78:C80) -> 48515493 | D81: =+ROUND(C81/1000,0) -> 48515
B83: Check | C83: =C81-L9 -> 1.14
B85: Shareholders loan | C85: =I21 -> 415468.35 | D85: =C85/1000 -> 415.46835
B86: Interest Paid | C86: ='P&L LTD USD'!D77 -> 266889.08 | D86: =C86/1000 -> 266.88908
B87: ASC842 Adoption | C87: =I12 -> 610280.11 | D87: =C87/1000 -> 610.28011
B88: Tax Paid | C88: =SUM('TB LTD 12.21'!G14:G18) -> 57709.01 | D88: =C88/1000 -> 57.70901
B90: Notes:
A92: =A13 -> 1 | B92: FA. Roll Froward
C94: O.B | D94: =+D13 -> 81585
C95: Purchases | D95: =501155.3-44 -> 501111.3
C96: Disposals | D96: 0
C97: Depreciation | D97: =-80801.5 -> -80801.5
C100: C.B | D100: =SUM(D94:D99) -> 501894.8
C101: Check | D101: =+D100-L13 -> -0.5
A103: =A25 -> 2 | B103: Short-Term Loan Roll Froward
C105: O.B | D105: =D25 -> -266667
C106: Additional loan | D106: =-3266667 -> -3266667
C107: Payments | D107: 1500000
C108: Interest (Accrual)
C111: C.B | D111: =SUM(D105:D110) -> -2033334
C112: Check | D112: =D111-L25 -> 0.03
A114: =A26 -> 3 | B114: Long-Term Loan Roll Froward
C116: O.B | D116: =D26 -> -466666
C117: Additional loan | D117: -600001.32
C118: Payments | D118: 533332.61
C119: FX | D119: 2.32
C122: C.B | D122: =SUM(D116:D121) -> -533332.39
C123: Check | D123: =D122-L26 -> 0.33
A125: 4 | B125: Shareholders Loan Roll Forward
C127: O.B | D127: =D18 -> 400515.77
...

Sheet Changes in equity
A1: 44561
A2: Changes ion equity
A3: Papaya Gaming Ltd
A4: USD | B4: USD
C5: Preferred shares | E5: Ordinary Shares
C6: Number of shares | D6: Amount | E6: Number of shares | F6: Amount | G6: Additional paid- in capital | H6: Receivables on account of shares | I6: Accumulated deficit | J6: Total
B8: Balance as of December 31, 2020 | C8: =81852*500 -> 40926000 | D8: * | E8: =130507*500 -> 65253500 | F8: * | G8: 6772 | H8: -50 | I8: -3981 | J8: =SUM(G8:I8) -> 2741
B9: Issuance of Ordinary shares upon exerise of options | E9: =(98*500+324*500)+2083+21875 -> 234958 | G9: =-'CF WP'!C142/1000 -> 15.8833 | J9: =SUM(G9:I9) -> 15.8833
B10: Stock base compensation | G10: =-('CF WP'!C140+'CF WP'!C141)/1000 -> 1827.1838 | J10: =SUM(G10:I10) -> 1827.1838
B11: Adjustment | H11: =-H8 -> 50 | J11: =SUM(G11:I11) -> 50
B12: Net Profit | I12: =-'P&L USD CONS'!I37 -> 8067.4747 | J12: =SUM(G12:I12) -> 8067.4747
B13: Balance as of December 31, 2021 | C13: =SUM(C8:C12) -> 40926000 | D13: =SUM(D8:D12) -> 0 | E13: =SUM(E8:E12) -> 65488458 | F13: =SUM(F8:F12) -> 0 | G13: =SUM(G8:G12) -> 8615.0671 | H13: =SUM(H8:H12) -> 0 | I13: =SUM(I8:I12) -> 4086.4747 | J13: =SUM(G13:I13) -> 12701.542 | K13: =SUM(J8:J12)-J13 -> 0
D14: * | F14: * | G14: =-'BS USD CONS '!L57 -> 8614.9081 | H14: =-'BS USD CONS '!M57 -> 0
G15: =G13-G14 -> 0.159 | H15: =H13-H14 -> 0
B22: ILS
C23: Preferred shares | E23: Ordinary Shares
C24: Number of shares | D24: Amount | E24: Number of shares | F24: Amount | G24: Additional paid- in capital | H24: Receivables on account of shares | I24: Accumulated deficit | J24: Total
B26: Balance as of December 31, 2020 | C26: =81852*500 -> 40926000 | D26: * | E26: =130507*500 -> 65253500 | F26: * | G26: =23106 -> 23106 | H26: -170 | I26: -14212 | J26: =SUM(F26:I26) -> 8724
B27: Issuance of Ordinary shares upon exerise of options | E27: =E9 -> 234958 | G27: =(2584.16+40202.57+8575)/1000 -> 51.36173 | J27: =SUM(G27:I27) -> 51.36173
B28: Stock base compensation | G28: =('P&L LTD USD'!L18+'P&L LTD USD'!L30+'P&L LTD USD'!L41+'P&L LTD USD'!L68+88091.6)/1000 -> 5989.8785 | J28: =SUM(G28:I28) -> 5989.8785
B29: Adjustment | H29: =-H26 -> 170 | J29: =SUM(G29:I29) -> 170
B30: Net Profit | I30: =-'BS LTD USD '!L55/1000 -> 23911.592 | J30: =SUM(G30:I30) -> 23911.592
B31: Balance as of December 31, 2021 | C31: =SUM(C26:C30) -> 40926000 | D31: =SUM(D26:D30) -> 0 | E31: =SUM(E26:E30) -> 65488458 | F31: * | G31: =SUM(G26:G30)-1 -> 29146.24 | H31: 0 | I31: =SUM(I26:I30) -> 9699.5923 | J31: =SUM(F31:I31) -> 38845.832
D32: * | F32: * | G32: =-'BS LTD USD '!L52/1000 -> 29146.287 | H32: =-'BS LTD USD '!M52/1000 -> 0 | J32: =SUM(J26:J30)-J31 -> 1
G33: =G31-G32 -> -0.04669 | H33: =H31-H32 -> 0
C34: =C26/500 -> 81852

Sheet AJE 2021
M2: End of 2021 | N2: 3.11
F3: LTD | M3: Average 2021 | N3: 3.2293 | T3: INC
M4: 44245 | N4: 3.265
M5: 8.4.2021 | N5: 3.286
S8: 1 | T8: Credit | U8: Chargeback expenses- SVB | W8: ='BS & P&L INC '!F48 -> 328087 | AA8: ביטול הכנסות מול chb
T9: Credit | U9: Chargeback expenses- Worldpay | W9: ='BS & P&L INC '!F49 -> 121298
G10: Debit USD | H10: Credit USD | J10: Debit ILS | K10: Credit ILS | T10: Credit | U10: Chargeback Payapal US | W10: ='BS & P&L INC '!F50 -> 1253.84
P11: ='AJE 2021'!J53-'AJE 2021'!K26-'AJE 2021'!J64+'AJE 2021'!J81 -> -3514747.8 | T11: Debit | U11: Revenue - Paypal US | V11: =W10 -> 1253.84
B12: 1 | C12: Debit | E12: 3335 | F12: =VLOOKUP(E12,'TB LTD 12.21'!D:E,2,0) -> מימוש אופציות/מניות | G12: 2626.34 | J12: =G12*N4 -> 8575.0001 | O12: פקודת תיקון מימוש שונטל | T12: Debit | U12: Revenue - Wordpay | V12: =W9 -> 121298
A13: מעודכן | C13: Credit | E13: 3000 | F13: =VLOOKUP(E13,'TB LTD 12.21'!D:E,2,0) -> הון מניות | H13: 0.30015314 | K13: =N4*H13 -> 0.98
C14: Credit | E14: 80000 | F14: =VLOOKUP(E14,'TB LTD 12.21'!D:E,2,0) -> פרמיה | H14: 2626.0398 | K14: =H14*N4 -> 8574.0201
S16: 2 | T16: Debit | U16: חו״ז | V16: =G25 -> 1039517.9 | AA16: העברת הכנסות לקבל מinc לltd | AB16: מעודכן
B17: 2 | C17: Debit | E17: 20048 | F17: =VLOOKUP(E17,'TB LTD 12.21'!D:E,2,0) -> הוצאות אופציות הנהלה וכלליות | G17: 614042.02 | J17: =G17*$N$3 -> 1982925.9 | O17: תיקון רישום הוצאות אופציות | T17: Credit | U17: Other Accounts Receivable | W17: =V16 -> 1039517.9 | AA17: SVB + Worldpay
C18: Debit | E18: 61003 | F18: =VLOOKUP(E18,'TB LTD 12.21'!D:E,2,0) -> הוצאות אופציות COGS | G18: -6811.1171 | J18: =G18*$N$3 -> -21995.14
C19: Debit | E19: 23031 | F19: =VLOOKUP(E19,'TB LTD 12.21'!D:E,2,0) -> הוצאות אופציות מחקר ופיתוח | G19: 539214 | J19: =G19*$N$3 -> 1741283.8
C20: Debit | E20: 20060 | F20: =VLOOKUP(E20,'TB LTD 12.21'!D:E,2,0) -> הוצאות אופציות שיווק | G20: -22807.61 | J20: =G20*$N$3 -> -73652.616
A21: מעודכן | C21: Credit | E21: 3337 | F21: =VLOOKUP(E21,'TB LTD 12.21'!D:E,2,0) -> קרן הון תשלום מבוסס מניות | H21: =SUM(G17:G20) -> 1123637.3 | K21: =SUM(J17:J20) -> 3628561.9
S23: 3 | T23: Debit | U23: ='BS & P&L INC '!E45 -> Revenue - Sales Tax | V23: ='[3]Top 10 income '!$R$21 -> 4903754.4 | AA23: עדכון sales Tax
T24: Credit | U24: Sales tax Provision | W24: =V23 -> 4903754.4 | AB24: מעודכן
B25: 3 | C25: Debit | E25: 90030 | F25: =VLOOKUP(E25,'TB LTD 12.21'!D:E,2,0) -> הכנסות לקבל - מאזני | G25: =612287.91+427230 -> 1039517.9 | J25: =G25*N2 -> 3232900.7 | O25: העברת הכנסות לקבל מinc לltd
C26: Credit | E26: 51009 | F26: =VLOOKUP(E26,'TB LTD 12.21'!D:E,2,0) -> PAPAYA GAMING INC | H26: =G25 -> 1039517.9 | K26: =J25 -> 3232900.7 | O26: SVB + Worldpay | P26: =K26/H26 -> 3.11
S27: 3 | T27: Debit | U27: Sales tax Provision | V27: ='[3]Top 10 income '!$R$21 -> 4903754.4 | AA27: העברת התחייבות לltd
T28: Credit | U28: חו״ז | W28: =V27 -> 4903754.4
A29: מעודכן
B30: 4 | C30: Debit | E30: 20090 | F30: =VLOOKUP(E30,'TB LTD 12.21'!D:E,2,0) -> ייעוץ מקצועי- הנהלה וכלליות | H30: 17606.08 | K30: 55600 | O30: קיטון הכנסה מול הקצב
C31: Credit | E31: 90031 | F31: =VLOOKUP(E31,'TB LTD 12.21'!D:E,2,0) -> הוצאות מראש | G31: =H30 -> 17606.08 | J31: =K30 -> 55600 | S31: 1 | T31: Debit | U31: חו״ז | V31: =-'BS & P&L INC '!N93 -> 5389318.2 | AA31: תיקון פקודת איחוד | AB31: מעודכן
A32: מעודכן | T32: Credit | U32: IC Expenses | W32: =V31 -> 5389318.2
B35: 5 | O35: הוצ ריבית לשלם | S35: 1 | T35: Debit | U35: IC Revenues | V35: =-'BS & P&L INC '!H89 -> 579444.48 | AA35: תיקון פקודת איחוד
A36: מעודכן | C36: Credit | E36: 79999 | F36: =VLOOKUP(E36,'TB LTD 12.21'!D:E,2,0) -> הוצאות לשלם | H36: =G37+G38+G39 -> 13720.37 | K36: =J37+J38+J39 -> 42670.352 | T36: Credit | U36: חו״ז | W36: =V35 -> 579444.48
C37: Debit | E37: 22003 | F37: =VLOOKUP(E37,'TB LTD 12.21'!D:E,2,0) -> ריבית הלוואה ראשונה SVB 800K-$ (1100493372) | G37: 2612.037 | J37: =G37*$N$2 -> 8123.4352
C38: Debit | E38: 22004 | F38: =VLOOKUP(E38,'TB LTD 12.21'!D:E,2,0) -> ריבית הלוואה שניה SVB 800K-$ (1100501685) | G38: 3358.3333 | J38: =G38*$N$2 -> 10444.417
C39: Debit | E39: 22005 | F39: =VLOOKUP(E39,'TB LTD 12.21'!D:E,2,0) -> ריבית הלוואה שלישית SVB 3M-NIS (1100514309) | G39: 7750 | J39: =G39*$N$2 -> 24102.5
B42: 6 | C42: Debit | E42: 300006 | F42: =VLOOKUP(E42,'TB LTD 12.21'!D:E,2,0) -> אוריאל בכר - ספק יעוץ | H42: 35980.71 | K42: 111900 | O42: סגירת ספק
C43: Credit | E43: 20090 | F43: =VLOOKUP(E43,'TB LTD 12.21'!D:E,2,0) -> ייעוץ מקצועי- הנהלה וכלליות | G43: =H42 -> 35980.71 | J43: =K42 -> 111900
A44: מעודכן
B47: 7 | C47: Debit | E47: 79998 | F47: =VLOOKUP(E47,'TB LTD 12.21'!D:E,2,0) -> Net cash balance -LIABILITIES | H47: =G48 -> 225333 | K47: =H47*N2 -> 700785.63 | O47: עדכון נט קאש
C48: Credit | E48: 4007 | F48: =VLOOKUP(E48,'TB LTD 12.21'!D:E,2,0) -> Income - net cash balance | G48: 225333 | J48: =K47 -> 700785.63
A49: מעודכן
B53: 8 | C53: Debit | F53: חו״ז | G53: =H54+H55 -> 579445.08 | J53: =G53*N3 -> 1871202 | O53: תיקון פקודת איחוד | P53: =J53/G53 -> 3.2293
A54: מעודכן | C54: Credit | F54: IC expenses Cogs | H54: =-'BS & P&L INC '!N86 -> 546352.16 | K54: =H54*N3 -> 1764335
C55: Credit | F55: IC expenses G&N | H55: =-'BS & P&L INC '!N88 -> 33092.912 | K55: =H55*N3 -> 106866.94
B59: 9 | C59: Debit | E59: Equity | F59: 25000 | G59: =-'BS & P&L INC '!I82 -> 93880.666 | J59: =G59*N3 -> 303168.84 | O59: תיקון משיכת אקוויטי
C60: Credit | E60: השקעה באינק | F60: 3334 | H60: =G59 -> 93880.666 | K60: =H60*N3 -> 303168.84
B63: 10 | C63: Debit | O63: תיקון פקודת איחוד
C64: Credit | E64: 51009 | F64: =VLOOKUP(E64,'TB LTD 12.21'!D:E,2,0) -> PAPAYA GAMING INC | G64: =V31 -> 5389318.2 | J64: =G64*N3 -> 17403725 | P64: =J64/G64 -> 3.2293
C65: Credit | F65: IC Revenue | H65: =G64 -> 5389318.2 | K65: =J64 -> 17403725
O69: Leases
B71: 11 | C71: Debit | F71: financial exp | G71: 1355.6411
C72: Debit | F72: ROU Assets | G72: 409121.67 | J72: 1306529.9
C73: Credit | F73: ROA Liability | H73: 385359.69 | K73: 1196813.8
C74: Debit | F74: Rent and related | G74: 34860.776 | J74: 76681.843
C75: Credit | F75: Prepiad expenses | H75: 59978.4 | K75: 186398.21
G77: =SUM(G70:G75) -> 445338.09 | H77: =SUM(H70:H75) -> 445338.09 | J77: =SUM(J70:J75) -> 1383211.7 | K77: =SUM(K70:K75) -> 1383212
B80: 12 | C80: Debit | F80: Sales tax Provision | H80: =V27 -> 4903754.4 | K80: =H80*N2 -> 15250676 | O80: העברת התחייבות slaes tax לישראל
C81: Credit | F81: חו״ז | G81: =H80 -> 4903754.4 | J81: =K80 -> 15250676 | P81: 3.2293
B85: 13 | C85: Debit | E85: 90032 | F85: נכס מס | G85: 2216041 | J85: 6939064 | O85: מיון בין סעיפי המס | T85: Credit | U85: Chargeback Paypal | W85: ='BS & P&L INC '!F51 -> 34927 | AB85: מעודכן
C86: Credit | E86: NEW 1 | F86: Tax provision | H86: =G85 -> 2216041 | K86: =J85 -> 6939064 | T86: Debit | U86: Revenue - Cyber Source | V86: =W8 -> 328087
P87: ='AJE 2021'!G53-'AJE 2021'!H26-'AJE 2021'!G64+'AJE 2021'!G81 -> -945636.64 | T87: Debit | U87: Revenue - PayPal | V87: =W85 -> 34927
B89: 14 | C89: Debit | E89: NEW 1 | F89: Tax provision | G89: =J89/N2 -> 334087.46 | H89: =K89/N2 -> 0 | J89: 1039012 | O89: עדכון הפרשה למס 2021
C90: Credit | E90: 24000 | F90: =VLOOKUP(E90,'TB LTD 12.21'!D:E,2,0) -> הוצאות מס | G90: =H89 -> 0 | H90: =G89 -> 334087.46 | J90: =K89 -> 0 | K90: =J89 -> 1039012
B94: 15 | C94: Debit | E94: 90032 | F94: נכס מס | G94: 490118.03 | H94: =G95 -> 0 | J94: =K95 -> 1481116.7 | O94: עדכון נכס מס נדחה
C95: Credit | E95: 24000 | F95: =VLOOKUP(E95,'TB LTD 12.21'!D:E,2,0) -> הוצאות מס | H95: =G94 -> 490118.03 | K95: 1481116.7
B99: 16 | C99: Debit | E99: 24000 | F99: =VLOOKUP(E99,'TB LTD 12.21'!D:E,2,0) -> הוצאות מס | H99: 12133 | K99: 41768 | O99: תיקון פקודה של מקדמות שנה קודמת
C100: Credit | E100: 50006 | F100: =VLOOKUP(E100,'TB LTD 12.21'!D:E,2,0) -> מקדמות בשל הוצאות עודפות 2020 | G100: 12133 | H100: =G99 -> 0 | J100: =K99 -> 41768
B104: 16 | C104: Debit | F104: Finance expenses - Warrant evaluation | G104: 1596966.8 | J104: =G104*$N$2 -> 4966566.8 | O104: פקודת warrant liability
C105: Credit | F105: Warrant liability | H105: =G104 -> 1596966.8 | K105: =J104 -> 4966566.8
J113: 6939064 | K113: =K90+K95+K99 -> 2561896.7 | L113: =J113-K113 -> 4377167.3
H114: =-'AJE 2021'!H90-'AJE 2021'!H95-'AJE 2021'!H99 -> -836338.49 | K114: =-'AJE 2021'!K90-'AJE 2021'!K95-'AJE 2021'!K99 -> -2561896.7
H117: =-'AJE 2021'!H86+'AJE 2021'!G89 -> -1881953.5 | K117: =-'AJE 2021'!K86+'AJE 2021'!J89 -> -5900052

Sheet Tech Plant Check ILS
C1: 2018 | D1: 2019 | E1: 2020 | G1: 2021
B2: Opening Balance | D2: =+C5 -> 299492.06 | E2: =+D5 -> 1188415 | G2: =+E5 -> 2792020
B3: Expected Loss (Revenue) | E3: =2173604.92192246-570000 -> 1603604.9 | G3: =-4850953*4 -> -19403812
B4: Carryforward losses | C4: =1076644/3.5949 -> 299492.06 | D4: =3168566/3.5645 -> 888922.99
B5: Ending Balance | C5: =+SUM(C2:C4) -> 299492.06 | D5: =+SUM(D2:D4) -> 1188415 | E5: =+SUM(E2:E4) -> 2792020 | G5: =+SUM(G2:G4) -> -16611792
B10: Requirements
B12: R&D Expenses test (7%/75M NIS) | C12: 2018 | D12: 2019 | E12: 2020 | F12: 2021
B13: Revenues | C13: 0 | D13: 3088948 | E13: 38427000 | F13: =-'P&L LTD USD'!J9 -> 5.3679757e+08 | K13: missing
B14: R&D Expenses | C14: 723182 | D14: 2469703 | E14: 7715000 | F14: ='P&L LTD USD'!J25 -> 33751918 | J14: =I13*0.07 -> 0 | K14: =J14-I14 -> 0
B15: R&D Expenses\Revenues Ratio | D15: =+D14/D13 -> 0.79952884 | E15: =+E14/E13 -> 0.20077029 | F15: =+F14/F13 -> 0.062876436
B16: R&D Expenses\Revenues Ratio - 3Y AVG | E16: =+AVERAGE(C14:E14)/AVERAGE(C13:E13) -> 0.26273963 | F16: =+AVERAGE(D14:F14)/AVERAGE(D13:F13) -> 0.075973705 | K16: =J14/I13 -> #DIV/0!
B17: 3 years revenues | F17: =AVERAGE(D13:F13)*0.07 -> 13493982
B18: 3 years rnd expenses | F18: =AVERAGE(D14:F14) -> 14645540 | J18: =+G18/0.04 -> 0 | K18: Break even point | L18: Net Income in 2022
B19: rate | F19: =F17-F18 -> -1151558.2 | K19: Above this point Its better to Increase our R&D Spend to reach the ratio
G20: =F19*3 -> -3454674.6 | H20: missing exp
B22: Investment from VC in USD | C22: 500000 | E22: 5748600
B23: AVERAGE NIS/USD Exchange rate | C23: 3.5949 | D23: 3.5645 | E23: 3.4424 | G23: 3.2549
B24: Investment - 8M NIS investment from VC | C24: =+C22*C23 -> 1797450 | E24: =+E22*E23 -> 19788981
K25: 993 | L25: ספטמבר R&D
B26: 25% Increase in AVG revenues Yearly | C26: 0 | D26: 0 | E26: =+E13/D13-1 -> 11.440158 | K26: -181 | L26: founder Bonus
K27: =-(150+86)/3.25 -> -72.615385 | L27: Emp Bonus
B28: 25% Increase in AVG number of employees + at least 50 employees
B29: Number of employees | C29: 3 | D29: 13 | E29: 33 | G29: 67 | H29: 13 | I29: =G29+H29 -> 80 | K29: =K25+K26+K27 -> 739.38462
B30: HC Increase ratio | C30: 0 | D30: =+D29/C29-1 -> 3.3333333 | E30: =+E29/D29-1 -> 1.5384615 | G30: =+G29/E29-1 -> 1.030303 | I30: =G30+H30 -> 1.030303
I31: =G31+H31 -> 0 | L31: רועי
B32: 20% of the Company's employees expenses listed as R&D or At least 200 Employees | I32: =G32+H32 -> 0 | K32: 3461 | L32: יולי V2
B33: R&D Payroll | C33: =(330825+326191)/C23 -> 182763.36 | D33: =449059+791642/$D$23 -> 671149.62 | E33: 1527152 | G33: 5994309 | I33: =G33+H33 -> 5994309
B34: R&D HC | C34: 2 | D34: 9 | E34: 23 | G34: 40 | H34: 6 | I34: =G34+H34 -> 46 | K34: =651*5 -> 3255 | L34: הערכה
B35: Total Payroll | C35: =+(142534+73203)+C33 -> 398500.36 | D35: =958816+791642/$D$23+358000/$D$23 -> 1281341.5 | E35: 2005609 | G35: 9020947 | I35: =G35+H35 -> 9020947
B36: Total HC | C36: =+C29 -> 3 | D36: =+D29 -> 13 | E36: =+E29 -> 33 | G36: =+G29 -> 67 | H36: 13 | I36: =G36+H36 -> 80
B37: R&D Payroll expenses ratio | C37: =+C33/C35 -> 0.45862784 | D37: =+D33/D35 -> 0.5237867 | E37: =+E33/E35 -> 0.76144054 | G37: =+G33/G35 -> 0.66448778 | I37: =G37+H37 -> 0.66448778
B38: R&D HC ratio | C38: =+C34/C36 -> 0.66666667 | D38: =+D34/D36 -> 0.69230769 | E38: =+E34/E36 -> 0.6969697 | G38: =+G34/G36 -> 0.59701493 | H38: =+H34/H36 -> 0.46153846 | I38: =G38+H38 -> 1.0585534 | K38: =K32+K34 -> 6716 | L38: סה״כ RD
B40: מפעל מועדף - תנאים | C40: 0.16
B41: מפעל תעשייתי - בית תכנה נחשב מפעל תעשייתי
B42: מפעל בר תחרות - רוב ההכנסות נובעות מייצוא
C45: 3.597 | D45: 3.5643 | E45: 3.4367 | G45: 3.5882
B46: R&D Expenses test (7%/75M NIS) | C46: 2018 | D46: 2019 | E46: 2020 | G46: 2021 - ytd 9.21 | H46: Oct-Dec 2021 estimeted | I46: Total 2021
B47: Revenues | D47: =D13*D45 -> 11009937 | E47: =E13*3.4367 -> 1.3206207e+08 | G47: =G13*3.4367 -> 0 | H47: =17500000*3*G45 -> 188380500 | I47: =G47+H47 -> 188380500
B48: R&D Expenses | C48: =C14*C45 -> 2601285.7 | D48: =D14*D45 -> 8802762.4 | E48: =E14*E45 -> 26514140 | G48: =G14*G45 -> 0 | H48: =(993000-200000)*3*G45 -> 8536327.8 | I48: =G48+H48 -> 8536327.8
B49: R&D Expenses\Revenues Ratio | D49: =+D48/D47 -> 0.79952884 | E49: =+E48/E47 -> 0.20077029 | G49: =+G48/G47 -> #DIV/0! | H49: =+H48/H47 -> 0.045314286 | I49: =+I48/I47 -> 0.045314286
B50: R&D Expenses\Revenues Ratio - 3Y AVG | E50: =+AVERAGE(C48:E48)/AVERAGE(C47:E47) -> 0.1766858 | G50: =+AVERAGE(D48:G48)/AVERAGE(D47:G47) -> 0.24684705 | H50: =+AVERAGE(E48:H48)/AVERAGE(E47:H47) -> 0.10938144 | I50: =+AVERAGE(G48:I48)/AVERAGE(G47:I47) -> 0.045314286
B51: Missing R&D Expenses to reach the ratio | G51: =0.07*SUM(D47:G47)-SUM(D48:G48) -> -25301862 | H51: =0.07*SUM(E47:H47)-SUM(E48:H48) -> -12619488
J52: =+G51/0.04 -> -6.3254656e+08 | K52: Break even point | L52: Net Income in 2022
K53: Above this point Its better to Increase our R&D Spend to reach the ratio
B54: Investment from VC in USD | C54: 500000 | E54: 5748600
B55: AVERAGE NIS/USD Exchange rate | C55: 3.5949 | D55: 3.5645 | E55: 3.4424 | G55: 3.2549
B56: Investment - 8M NIS investment from VC | C56: =+C54*C55 -> 1797450 | E56: =+E54*E55 -> 19788981
B58: 25% Increase in AVG revenues Yearly | C58: 0 | D58: 0 | E58: =+E47/D47-1 -> 10.994807 | G58: =+G47/E47-1 -> -1
B60: 25% Increase in AVG number of employees + at least 50 employees
B61: Number of employees | C61: 3 | D61: 13 | E61: 33 | G61: 67 | H61: 13 | I61: =G61+H61 -> 80
B62: HC Increase ratio | C62: 0 | D62: =+D61/C61-1 -> 3.3333333 | E62: =+E61/D61-1 -> 1.5384615 | G62: =+G61/E61-1 -> 1.030303 | I62: =G62+H62 -> 1.030303
I63: =G63+H63 -> 0
B64: 20% of the Company's employees expenses listed as R&D or At least 200 Employees | I64: =G64+H64 -> 0
B65: R&D Payroll | C65: =(330825+326191)/C55 -> 182763.36 | D65: =449059+791642/$D$23 -> 671149.62 | E65: 1527152 | G65: 5994309 | I65: =G65+H65 -> 5994309
B66: R&D HC | C66: 2 | D66: 9 | E66: 23 | G66: 40 | H66: 6 | I66: =G66+H66 -> 46
B67: Total Payroll | C67: =+(142534+73203)+C65 -> 398500.36 | D67: =958816+791642/$D$23+358000/$D$23 -> 1281341.5 | E67: 2005609 | G67: 9020947 | I67: =G67+H67 -> 9020947
B68: Total HC | C68: =+C61 -> 3 | D68: =+D61 -> 13 | E68: =+E61 -> 33 | G68: =+G61 -> 67 | H68: 13 | I68: =G68+H68 -> 80
B69: R&D Payroll expenses ratio | C69: =+C65/C67 -> 0.45862784 | D69: =+D65/D67 -> 0.5237867 | E69: =+E65/E67 -> 0.76144054 | G69: =+G65/G67 -> 0.66448778 | I69: =G69+H69 -> 0.66448778
B70: R&D HC ratio | C70: =+C66/C68 -> 0.66666667 | D70: =+D66/D68 -> 0.69230769 | E70: =+E66/E68 -> 0.6969697 | G70: =+G66/G68 -> 0.59701493 | H70: =+H66/H68 -> 0.46153846 | I70: =G70+H70 -> 1.0585534
B72: מפעל מועדף - תנאים | C72: 0.16
B73: מפעל תעשייתי - בית תכנה נחשב מפעל תעשייתי
B74: מפעל בר תחרות - רוב ההכנסות נובעות מייצוא

Sheet TB LTD 12.21
A1: כותרת ראשית; | B1: כותרת משנה; | C1: סעיף; | D1: חשבון | E1: תאור החשבון | F1: יתרה בשקלים | G1: יתרה בדולרים | H1: סוג דוח | I1: מחלקה | J1: תת מחלקה
A2: **1.נכסים | B2: *10.רכוש שוטף | C2: 100.מזומנים ושווי מזומנים | D2: 80020 | E2: בנק לאומי 568400 | F2: 9872366.2 | G2: 3174394.3 | H2: =VLOOKUP(D2,'COA1'!D:I,3,0) -> BS | I2: =VLOOKUP(D2,'COA1'!D:I,4,0) -> Cash | J2: =VLOOKUP(D2,'COA1'!D:I,5,0) -> 0 | K2: =F2/G2 -> 3.11 | M2: 1
A3: **1.נכסים | B3: *10.רכוש שוטף | C3: 100.מזומנים ושווי מזומנים | D3: 80021 | E3: בנק לאומי 568400 דולרי $ | F3: 10164955 | G3: 3268474.2 | H3: =VLOOKUP(D3,'COA1'!D:I,3,0) -> BS | I3: =VLOOKUP(D3,'COA1'!D:I,4,0) -> Cash | J3: =VLOOKUP(D3,'COA1'!D:I,5,0) -> 0 | K3: =F3/G3 -> 3.11
A4: **1.נכסים | B4: *10.רכוש שוטף | C4: 100.מזומנים ושווי מזומנים | D4: 80022 | E4: בנק PAYPAL דולרי $ | F4: 5101150.1 | G4: 1640241.2 | H4: =VLOOKUP(D4,'COA1'!D:I,3,0) -> BS | I4: =VLOOKUP(D4,'COA1'!D:I,4,0) -> Cash | J4: =VLOOKUP(D4,'COA1'!D:I,5,0) -> 0 | K4: =F4/G4 -> 3.11
A5: **1.נכסים | B5: *10.רכוש שוטף | C5: 100.מזומנים ושווי מזומנים | D5: 80026 | E5: בנק אמריקאי LTD SVB | F5: 12634137 | G5: 4062423.5 | H5: =VLOOKUP(D5,'COA1'!D:I,3,0) -> BS | I5: =VLOOKUP(D5,'COA1'!D:I,4,0) -> Cash | J5: =VLOOKUP(D5,'COA1'!D:I,5,0) -> 0 | K5: =F5/G5 -> 3.11
A6: **1.נכסים | B6: *10.רכוש שוטף | C6: 100.מזומנים ושווי מזומנים | D6: 80027 | E6: בנק לאומי 568400 לירה שטרלניג | F6: 3917.37 | G6: 1259.61 | H6: =VLOOKUP(D6,'COA1'!D:I,3,0) -> BS | I6: =VLOOKUP(D6,'COA1'!D:I,4,0) -> Cash | J6: =VLOOKUP(D6,'COA1'!D:I,5,0) -> 0 | K6: =F6/G6 -> 3.1099864
A7: **1.נכסים | B7: *10.רכוש שוטף | C7: 103.פקדונות | D7: 103-0 | E7: פקדון כנגד שעבוד זמן ארוך (לטובת מסגרת כ״א) | F7: 50000 | G7: 16077.17 | H7: =VLOOKUP(D7,'COA1'!D:I,3,0) -> BS | I7: =VLOOKUP(D7,'COA1'!D:I,4,0) -> deposit | J7: =VLOOKUP(D7,'COA1'!D:I,5,0) -> 0 | K7: =F7/G7 -> 3.1100001
A8: **1.נכסים | B8: *10.רכוש שוטף | C8: 106.לקוחות | D8: 100006 | E8: Papaya Gaming INC | F8: 5.7803739e+08 | G8: 1.8586411e+08 | H8: =VLOOKUP(D8,'COA1'!D:I,3,0) -> BS | I8: =VLOOKUP(D8,'COA1'!D:I,4,0) -> Related Party | J8: =VLOOKUP(D8,'COA1'!D:I,5,0) -> 0 | K8: =F8/G8 -> 3.11
A9: **1.נכסים | B9: *11.חיבים אחרים | C9: 110.חיבים אחרים | D9: 20078 | E9: הפרשה לביקורת ניכויים | F9: -385275.92 | G9: -123882.93 | H9: =VLOOKUP(D9,'COA1'!D:I,3,0) -> bs | I9: =VLOOKUP(D9,'COA1'!D:I,4,0) -> Other accounts payable | J9: =VLOOKUP(D9,'COA1'!D:I,5,0) -> 0 | K9: =F9/G9 -> 3.1100001
A10: **1.נכסים | B10: *11.חיבים אחרים | C10: 110.חיבים אחרים | D10: 90031 | E10: הוצאות מראש | F10: 3348309.1 | G10: 1076626.7 | H10: =VLOOKUP(D10,'COA1'!D:I,3,0) -> BS | I10: Prepaid | J10: =VLOOKUP(D10,'COA1'!D:I,5,0) -> 0 | K10: =F10/G10 -> 3.11
A11: **1.נכסים | B11: *11.חיבים אחרים | C11: 110.חיבים אחרים | D11: 90032 | E11: נכס מס נדחה | F11: -5494592.8 | G11: -1766750.1 | H11: =VLOOKUP(D11,'COA1'!D:I,3,0) -> BS | I11: =VLOOKUP(D11,'COA1'!D:I,4,0) -> Deferred tax assets | J11: =VLOOKUP(D11,'COA1'!D:I,5,0) -> 0 | K11: =F11/G11 -> 3.11
A12: **1.נכסים | B12: *11.חיבים אחרים | C12: 111.מוסדות | D12: 2050 | E12: מע'מ חו'ז | F12: 4193207.9 | G12: 1348298.4 | H12: =VLOOKUP(D12,'COA1'!D:I,3,0) -> BS | I12: =VLOOKUP(D12,'COA1'!D:I,4,0) -> Other accounts receivable | J12: =VLOOKUP(D12,'COA1'!D:I,5,0) -> 0 | K12: =F12/G12 -> 3.11
A13: **1.נכסים | B13: *11.חיבים אחרים | C13: 111.מוסדות | D13: 2052 | E13: מע'מ תשומות | F13: -143961.09 | G13: -46289.74 | H13: =VLOOKUP(D13,'COA1'!D:I,3,0) -> BS | I13: =VLOOKUP(D13,'COA1'!D:I,4,0) -> Other accounts receivable | J13: =VLOOKUP(D13,'COA1'!D:I,5,0) -> 0 | K13: =F13/G13 -> 3.11
A14: **1.נכסים | B14: *11.חיבים אחרים | C14: 111.מוסדות | D14: 50003 | E14: מקדמות בשל הוצאות עודפות 2017 | F14: 8467 | G14: 2722.51 | H14: =VLOOKUP(D14,'COA1'!D:I,3,0) -> BS | I14: =VLOOKUP(D14,'COA1'!D:I,4,0) -> Other accounts receivable | J14: =VLOOKUP(D14,'COA1'!D:I,5,0) -> 0 | K14: =F14/G14 -> 3.1099978
A15: **1.נכסים | B15: *11.חיבים אחרים | C15: 111.מוסדות | D15: 50004 | E15: מקדמות בשל הוצאות עודפות 2018 | F15: 33750 | G15: 10852.09 | H15: =VLOOKUP(D15,'COA1'!D:I,3,0) -> BS | I15: =VLOOKUP(D15,'COA1'!D:I,4,0) -> Other accounts receivable | J15: =VLOOKUP(D15,'COA1'!D:I,5,0) -> 0 | K15: =F15/G15 -> 3.11
A16: **1.נכסים | B16: *11.חיבים אחרים | C16: 111.מוסדות | D16: 50005 | E16: מקדמות בשל הוצאות עודפות 2019 | F16: 38723 | G16: 12451.13 | H16: =VLOOKUP(D16,'COA1'!D:I,3,0) -> BS | I16: =VLOOKUP(D16,'COA1'!D:I,4,0) -> Other accounts receivable | J16: =VLOOKUP(D16,'COA1'!D:I,5,0) -> 0 | K16: =F16/G16 -> 3.1099989
A17: **1.נכסים | B17: *11.חיבים אחרים | C17: 111.מוסדות | D17: 50006 | E17: מקדמות בשל הוצאות עודפות 2020 | F17: 3232 | G17: 1039.23 | H17: =VLOOKUP(D17,'COA1'!D:I,3,0) -> BS | I17: =VLOOKUP(D17,'COA1'!D:I,4,0) -> Other accounts receivable | J17: =VLOOKUP(D17,'COA1'!D:I,5,0) -> 0 | K17: =F17/G17 -> 3.1099949
A18: **1.נכסים | B18: *11.חיבים אחרים | C18: 111.מוסדות | D18: 50007 | E18: מקדמות בשל הוצאות עודפות 2021 | F18: 95303 | G18: 30644.05 | H18: =VLOOKUP(D18,'COA1'!D:I,3,0) -> BS | I18: =VLOOKUP(D18,'COA1'!D:I,4,0) -> Other accounts receivable | J18: =VLOOKUP(D18,'COA1'!D:I,5,0) -> 0 | K18: =F18/G18 -> 3.1100001
A19: **1.נכסים | B19: *11.חיבים אחרים | C19: 111.מוסדות | D19: 50015 | E19: ניכוי מס במקור מספקים | F19: -91277.36 | G19: -29349.63 | H19: =VLOOKUP(D19,'COA1'!D:I,3,0) -> BS | I19: =VLOOKUP(D19,'COA1'!D:I,4,0) -> Other accounts payable | J19: =VLOOKUP(D19,'COA1'!D:I,5,0) -> 0 | K19: =F19/G19 -> 3.1100004
A20: **1.נכסים | B20: *11.חיבים אחרים | C20: 111.מוסדות | D20: 90006 | E20: חוז עובדים - משכורות | F20: -72240 | G20: -23228.3 | H20: =VLOOKUP(D20,'COA1'!D:I,3,0) -> BS | I20: =VLOOKUP(D20,'COA1'!D:I,4,0) -> Other accounts payable | J20: =VLOOKUP(D20,'COA1'!D:I,5,0) -> 0 | K20: =F20/G20 -> 3.1099994
A21: **1.נכסים | B21: *11.חיבים אחרים | C21: 111.מוסדות | D21: 90007 | E21: חוז קופות גמל- שכר | F21: -522786 | G21: -168098.39 | H21: =VLOOKUP(D21,'COA1'!D:I,3,0) -> BS | I21: =VLOOKUP(D21,'COA1'!D:I,4,0) -> Other accounts payable | J21: =VLOOKUP(D21,'COA1'!D:I,5,0) -> 0 | K21: =F21/G21 -> 3.11
A22: **1.נכסים | B22: *11.חיבים אחרים | C22: 111.מוסדות | D22: 90008 | E22: ביטוח לאומי ניכויים | F22: -311925 | G22: -100297.43 | H22: =VLOOKUP(D22,'COA1'!D:I,3,0) -> BS | I22: =VLOOKUP(D22,'COA1'!D:I,4,0) -> Other accounts payable | J22: =VLOOKUP(D22,'COA1'!D:I,5,0) -> 0 | K22: =F22/G22 -> 3.1099999
... A360: **9.הוצאות מס | B360: *90.הוצאות מס | C360: 901.רווח אקוויטי | D360: 25000 | E360: רווחי אקוויטי -תוצאתי | F360: -1094800 | G360: -352025.71 | H360: =VLOOKUP(D360,'COA1'!D:I,3,0) -> PL | I360: =VLOOKUP(D360,'COA1'!D:I,4,0) -> Equity | J360: =VLOOKUP(D360,'COA1'!D:I,5,0) -> Equity | K360: =F360/G360 -> 3.11
G362: =SUBTOTAL(9,G122:G152) -> 0
G364: =F26+F25+F24+F23+F22+F21 -> -2290021.5
F366: ניכויים | G366: =G9 -> -123882.93
G367: =SUBTOTAL(9,G19:G118) -> 501895.3
G369: =SUM(G366:G367) -> 378012.37
G371: -1119799.5
G373: =-SUBTOTAL(9,G179:G332) -> 0
G375: 17606.08
G376: 12133
G377: -59978.4
D384: 3001 | E384: -2017140.3 | F384: =E384-VLOOKUP(D384,$D$122:$F$360,3,0) -> 0
D385: 3002 | E385: -9520690.6 | F385: =E385-VLOOKUP(D385,$D$122:$F$360,3,0) -> 0
D386: 3003 | E386: -305068.14 | F386: =E386-VLOOKUP(D386,$D$122:$F$360,3,0) -> 0
D387: 3004 | E387: -152555.51 | F387: =E387-VLOOKUP(D387,$D$122:$F$360,3,0) -> 0
D388: 3005 | E388: -52931.57 | F388: =E388-VLOOKUP(D388,$D$122:$F$360,3,0) -> 0
D389: 3006 | E389: -48278.01 | F389: =E389-VLOOKUP(D389,$D$122:$F$360,3,0) -> 0
D390: 3007 | E390: -152555.51 | F390: =E390-VLOOKUP(D390,$D$122:$F$360,3,0) -> 0
D391: 3008 | E391: -152533.71 | F391: =E391-VLOOKUP(D391,$D$122:$F$360,3,0) -> 0
D392: 3009 | E392: -152524.14 | F392: =E392-VLOOKUP(D392,$D$122:$F$360,3,0) -> 0
D393: 3011 | E393: -2011925.4 | F393: =E393-VLOOKUP(D393,$D$122:$F$360,3,0) -> 0
D394: 3012 | E394: -168391.4 | F394: =E394-VLOOKUP(D394,$D$122:$F$360,3,0) -> 0
D395: 3013 | E395: -2178379.8 | F395: =E395-VLOOKUP(D395,$D$122:$F$360,3,0) -> 0
... D408: 80000 | E408: -1915496.2 | F408: =E408-VLOOKUP(D408,$D$122:$F$360,3,0) -> 42786.73
D411: 3001 | E411: -2017140.3 | F411: =E411-VLOOKUP(D411,$D$384:$E$408,2,0) -> 0
D412: 3002 | E412: -9520690.6 | F412: =E412-VLOOKUP(D412,$D$384:$E$408,2,0) -> 0
D413: 3003 | E413: -305068.14 | F413: =E413-VLOOKUP(D413,$D$384:$E$408,2,0) -> 0
D414: 3004 | E414: -152555.51 | F414: =E414-VLOOKUP(D414,$D$384:$E$408,2,0) -> 0
D415: 3005 | E415: -52931.57 | F415: =E415-VLOOKUP(D415,$D$384:$E$408,2,0) -> 0
D416: 3006 | E416: -48278.01 | F416: =E416-VLOOKUP(D416,$D$384:$E$408,2,0) -> 0
D417: 3007 | E417: -152555.51 | F417: =E417-VLOOKUP(D417,$D$384:$E$408,2,0) -> 0
D418: 3008 | E418: -152533.71 | F418: =E418-VLOOKUP(D418,$D$384:$E$408,2,0) -> 0
D419: 3009 | E419: -152524.14 | F419: =E419-VLOOKUP(D419,$D$384:$E$408,2,0) -> 0
D420: 3011 | E420: -2011925.4 | F420: =E420-VLOOKUP(D420,$D$384:$E$408,2,0) -> 0
D421: 3012 | E421: -168391.4 | F421: =E421-VLOOKUP(D421,$D$384:$E$408,2,0) -> 0
D422: 3013 | E422: -2178379.8 | F422: =E422-VLOOKUP(D422,$D$384:$E$408,2,0) -> 0
... D436: 80000 | E436: -1958282.9 | F436: =E436-VLOOKUP(D436,$D$384:$E$408,2,0) -> -42786.73
