Workbook
Name Actuals: #REF!
Name Actuals: #REF!
Name Actuals: #REF!
Name Capital_Gains_Taxes: #REF!
Name Capital_Gains_Taxes: #REF!
Name Capital_Gains_Taxes: #REF!
Name codes: [1]קליטה!#REF!
Name Company_Scenarios: #REF!
Name Company_Scenarios: #REF!
Name Company_Scenarios: #REF!
Name Currency: #REF!
Name Currency: #REF!
Name Currency: #REF!
Name Days_per_Year: 365
Name Deployment_Scenarios: #REF!
Name Deployment_Scenarios: #REF!
Name Deployment_Scenarios: #REF!
Name Dividend_Tax: #REF!
Name Dividend_Tax: #REF!
Name Dividend_Tax: #REF!
Name Exchange_Rate_to_USD: #REF!
Name Exchange_Rate_to_USD: #REF!
Name Exchange_Rate_to_USD: #REF!
Name Fiscal_Year_Ending: #REF!
Name Fiscal_Year_Ending: #REF!
Name Fiscal_Year_Ending: #REF!
Name h: #REF!
Name Helpline: '[2]Debt Capex'!$AF$71:$AM$71
Name mbm: [1]קליטה!#REF!
Name mbmtuam: [1]קליטה!#REF!
Name mbnom: [1]קליטה!#REF!
Name Name: #REF!
Name Name: #REF!
Name Name: #REF!
Name NPV_Correction: #REF!
Name NPV_Correction: #REF!
Name NPV_Correction: #REF!
Name Operating_Deployment_Scenario: #REF!
Name Operating_Deployment_Scenario: #REF!
Name Operating_Deployment_Scenario: #REF!
Name Operating_Scenario: #REF!
Name Operating_Scenario: #REF!
Name Operating_Scenario: #REF!
Name pncodes: '[1]פקודות נוספות'!#REF!
Name pnmtuam: '[1]פקודות נוספות'!#REF!
Name pnnom: '[1]פקודות נוספות'!#REF!
Name Projection_Period: #REF!
Name Projection_Period: #REF!
Name Projection_Period: #REF!
Name Selected_Scenario: #REF!
Name Selected_Scenario: #REF!
Name Selected_Scenario: #REF!
Name Selected_ScenarioDV: #REF!
Name Selected_ScenarioDV: #REF!
Name Selected_ScenarioDV: #REF!
Name STV_Investment_Date: #REF!
Name STV_Investment_Date: #REF!
Name STV_Investment_Date: #REF!
Name Units: #REF!
Name Units: #REF!

Sheet HARKAVA 
C1: =+C59+C28 -> 0 | D1: =D28+D59 -> 7789953.4 | E1: =E28+E59 -> 7789953.4 | F1: =F28+F59 -> 0 | H1: =H28+H59 -> 0 | I1: =I28+I59 -> 61840 | J1: =J28+J59 -> 61840 | K1: =K28+K59 -> 0 | M1: =+M59+M28 -> 0 | N1: =+N59+N28 -> 1443366.2 | O1: =+O59+O28 -> 1443366.2 | P1: =+P59+P28 -> 0 | R1: =+R59+R28 -> 0 | S1: =+S59+S28 -> 2697288.7 | T1: =+T59+T28 -> 2697288.7 | U1: =+U59+U28 -> 0 | V1: =+V59+V28 -> 0 | X1: =+X59+X28 -> 43788.72 | Y1: =+Y59+Y28 -> 43788.72 | AD1: 0 | AF1: 0 | AG1: 61840 | AH1: 61840 | AI1: 0 | AK1: 0 | AL1: 1332358 | AM1: 1332358 | AN1: 0 | AP1: -0.0099999979 | AQ1: 2744953.8 | AR1: 2744953.8 | AS1: -0.0099999979 | AT1: -0.0099999942 | AV1: 0.72 | AW1: 0.71
F2: =B5 -> 44561 | AD2: 44561
C3: Mitiga Ltd. | H3: Mitiga USA Inc. | M3: Mitiga UK | R3: Mitiga Security Inc. | AF3: Mitiga USA Inc. | AK3: Mitiga UK | AP3: Mitiga Security Inc.
A4: code | B4: Mitiga Security Inc. | C4: Presented | D4: Addi ente. In $ | F4: Closing Balance | H4: Presented | I4: Addi ente. In $ | K4: Closing Balance | M4: Presented | N4: Addi ente. In $ | P4: Closing Balance | R4: Presented | S4: Addi ente. In $ | U4: Closing Balance | V4: Combined | X4: Consolidation entries | Y4: Consolidated | AD4: Closing Balance | AF4: Presented | AG4: Addi ente. In $ | AI4: Closing Balance | AK4: Presented | AL4: Addi ente. In $ | AN4: Closing Balance | AP4: Presented | AQ4: Addi ente. In $ | AS4: Closing Balance | AT4: Combined | AV4: Consolidation entries | AW4: Consolidated | AY4: LTD | AZ4: UK | BA4: SEC | BB4: Consolidation entries | BC4: Notes
B5: 44561 | C5: $ | D5: D | E5: C | F5: $ | P5: $ | U5: $ | V5: $ | X5: $ | Y5: $ | AD5: $ | AN5: $ | AS5: $ | AT5: $ | AV5: $ | AW5: $
A6: 1100 | B6: Cash and cash equivalents- in $ | C6: =SUMIF('TB Mitiga LTD'!A:A,'HARKAVA '!A6,'TB Mitiga LTD'!D:D) -> 919260.82 | D6: =SUMIF('Adj Entries Ltd'!$B$4:$B$954,A6,'Adj Entries Ltd'!$D$4:$D$954) -> 3000000 | E6: =SUMIF('Adj Entries Ltd'!$B$4:$B$954,A6,'Adj Entries Ltd'!$E$4:$E$954) -> 0 | F6: =(+C6+D6-E6) -> 3919260.8 | H6: =SUMIF('TB US'!A:A,'HARKAVA '!A6,'TB US'!D:D) -> 0 | I6: =SUMIF('Adj. entries US'!B:B,'HARKAVA '!A6,'Adj. entries US'!D:D) -> 0 | J6: =SUMIF('Adj. entries US'!B:B,'HARKAVA '!A6,'Adj. entries US'!E:E) -> 0 | K6: =H6+I6-J6 -> 0 | M6: =SUMIF('TB UK'!A:A,'HARKAVA '!A6,'TB UK'!E:E) -> 0 | N6: =SUMIF('Adj. Entries UK'!B:B,'HARKAVA '!A6,'Adj. Entries UK'!D:D) -> 0 | O6: =SUMIF('Adj. Entries UK'!B:B,'HARKAVA '!A6,'Adj. Entries UK'!E:E) -> 0 | P6: =M6+N6-O6 -> 0 | R6: =SUMIF('TB security'!A:A,'HARKAVA '!A6,'TB security'!D:D) -> 14375507 | S6: =SUMIF('Adj. Entries security'!B:B,'HARKAVA '!A6,'Adj. Entries security'!D:D) -> 0 | T6: =SUMIF('Adj. Entries security'!B:B,'HARKAVA '!A6,'Adj. Entries security'!E:E) -> 0 | U6: =R6+S6-T6 -> 14375507 | V6: =P6+F6+U6+K6 -> 18294768 | Y6: =V6+X6 -> 18294768 | Z6: =LEFT(A6,2) -> 11 | AD6: 3919260.8 | AF6: 0 | AG6: 0 | AH6: 0 | AI6: 0 | AK6: 0 | AL6: 0 | AM6: 0 | AN6: 0 | AP6: 14375507 | AQ6: 0 | AR6: 0 | AS6: 14375507 | AT6: 18294768 | AW6: 18294768 | AY6: =F6-AD6 -> 0 | AZ6: =P6-AN6 -> 0 | BA6: =U6-AS6 -> 0 | BB6: =X6-AV6 -> 0
A7: 1110 | B7: Cash and cash equivalents- in other currency | C7: =SUMIF('TB Mitiga LTD'!A:A,'HARKAVA '!A7,'TB Mitiga LTD'!D:D) -> 84442.69 | D7: =SUMIF('Adj Entries Ltd'!$B$4:$B$954,A7,'Adj Entries Ltd'!$D$4:$D$954) -> 0 | E7: =SUMIF('Adj Entries Ltd'!$B$4:$B$954,A7,'Adj Entries Ltd'!$E$4:$E$954) -> 0 | F7: =(+C7+D7-E7) -> 84442.69 | H7: =SUMIF('TB US'!A:A,'HARKAVA '!A7,'TB US'!D:D) -> 0 | I7: =SUMIF('Adj. entries US'!B:B,'HARKAVA '!A7,'Adj. entries US'!D:D) -> 0 | J7: =SUMIF('Adj. entries US'!B:B,'HARKAVA '!A7,'Adj. entries US'!E:E) -> 0 | K7: =H7+I7-J7 -> 0 | M7: =SUMIF('TB UK'!A:A,'HARKAVA '!A7,'TB UK'!E:E) -> 514660.89 | N7: =SUMIF('Adj. Entries UK'!B:B,'HARKAVA '!A7,'Adj. Entries UK'!D:D) -> 0 | O7: =SUMIF('Adj. Entries UK'!B:B,'HARKAVA '!A7,'Adj. Entries UK'!E:E) -> 0 | P7: =M7+N7-O7 -> 514660.89 | R7: =SUMIF('TB security'!A:A,'HARKAVA '!A7,'TB security'!D:D) -> 0 | S7: =SUMIF('Adj. Entries security'!B:B,'HARKAVA '!A7,'Adj. Entries security'!D:D) -> 0 | T7: =SUMIF('Adj. Entries security'!B:B,'HARKAVA '!A7,'Adj. Entries security'!E:E) -> 0 | U7: =R7+S7-T7 -> 0 | V7: =P7+F7+U7+K7 -> 599103.58 | Y7: =V7+X7 -> 599103.58 | Z7: =LEFT(A7,2) -> 11 | AD7: 84442.69 | AF7: 0 | AG7: 0 | AH7: 0 | AI7: 0 | AK7: 514660.89 | AL7: 0 | AM7: 0 | AN7: 514660.89 | AP7: 0 | AQ7: 0 | AR7: 0 | AS7: 0 | AT7: 599103.58 | AW7: 599103.58 | AY7: =F7-AD7 -> 0 | AZ7: =P7-AN7 -> 0 | BA7: =U7-AS7 -> 0 | BB7: =X7-AV7 -> 0
A8: 1300 | B8: Deposits | C8: =SUMIF('TB Mitiga LTD'!A:A,'HARKAVA '!A8,'TB Mitiga LTD'!D:D) -> 347835.82 | D8: =SUMIF('Adj Entries Ltd'!$B$4:$B$954,A8,'Adj Entries Ltd'!$D$4:$D$954) -> 0 | E8: =SUMIF('Adj Entries Ltd'!$B$4:$B$954,A8,'Adj Entries Ltd'!$E$4:$E$954) -> 0 | F8: =(+C8+D8-E8) -> 347835.82 | H8: =SUMIF('TB US'!A:A,'HARKAVA '!A8,'TB US'!D:D) -> 0 | I8: =SUMIF('Adj. entries US'!B:B,'HARKAVA '!A8,'Adj. entries US'!D:D) -> 0 | J8: =SUMIF('Adj. entries US'!B:B,'HARKAVA '!A8,'Adj. entries US'!E:E) -> 0 | K8: =H8+I8-J8 -> 0 | M8: =SUMIF('TB UK'!A:A,'HARKAVA '!A8,'TB UK'!E:E) -> 20272.19 | N8: =SUMIF('Adj. Entries UK'!B:B,'HARKAVA '!A8,'Adj. Entries UK'!D:D) -> 0 | O8: =SUMIF('Adj. Entries UK'!B:B,'HARKAVA '!A8,'Adj. Entries UK'!E:E) -> 0 | P8: =M8+N8-O8 -> 20272.19 | R8: =SUMIF('TB security'!A:A,'HARKAVA '!A8,'TB security'!D:D) -> 40000 | S8: =SUMIF('Adj. Entries security'!B:B,'HARKAVA '!A8,'Adj. Entries security'!D:D) -> 0 | T8: =SUMIF('Adj. Entries security'!B:B,'HARKAVA '!A8,'Adj. Entries security'!E:E) -> 0 | U8: =R8+S8-T8 -> 40000 | V8: =P8+F8+U8+K8 -> 408108.01 | Y8: =V8+X8 -> 408108.01 | Z8: =LEFT(A8,2) -> 13 | AD8: 347835.82 | AF8: 0 | AG8: 0 | AH8: 0 | AI8: 0 | AK8: 20272.19 | AL8: 0 | AM8: 0 | AN8: 20272.19 | AP8: 40000 | AQ8: 0 | AR8: 0 | AS8: 40000 | AT8: 408108.01 | AW8: 408108.01 | AY8: =F8-AD8 -> 0 | AZ8: =P8-AN8 -> 0 | BA8: =U8-AS8 -> 0 | BB8: =X8-AV8 -> 0
A9: 1400 | B9: Trade receivable, net | C9: =SUMIF('TB Mitiga LTD'!A:A,'HARKAVA '!A9,'TB Mitiga LTD'!D:D) -> 197867.53 | D9: =SUMIF('Adj Entries Ltd'!$B$4:$B$954,A9,'Adj Entries Ltd'!$D$4:$D$954) -> 0 | E9: =SUMIF('Adj Entries Ltd'!$B$4:$B$954,A9,'Adj Entries Ltd'!$E$4:$E$954) -> 0 | F9: =(+C9+D9-E9) -> 197867.53 | H9: =SUMIF('TB US'!A:A,'HARKAVA '!A9,'TB US'!D:D) -> 0 | I9: =SUMIF('Adj. entries US'!B:B,'HARKAVA '!A9,'Adj. entries US'!D:D) -> 0 | J9: =SUMIF('Adj. entries US'!B:B,'HARKAVA '!A9,'Adj. entries US'!E:E) -> 0 | K9: =H9+I9-J9 -> 0 | M9: =SUMIF('TB UK'!A:A,'HARKAVA '!A9,'TB UK'!E:E) -> 119038.28 | N9: =SUMIF('Adj. Entries UK'!B:B,'HARKAVA '!A9,'Adj. Entries UK'!D:D) -> 0 | O9: =SUMIF('Adj. Entries UK'!B:B,'HARKAVA '!A9,'Adj. Entries UK'!E:E) -> 0 | P9: =M9+N9-O9 -> 119038.28 | R9: =SUMIF('TB security'!A:A,'HARKAVA '!A9,'TB security'!D:D) -> 270540 | S9: =SUMIF('Adj. Entries security'!B:B,'HARKAVA '!A9,'Adj. Entries security'!D:D) -> 0 | T9: =SUMIF('Adj. Entries security'!B:B,'HARKAVA '!A9,'Adj. Entries security'!E:E) -> 0 | U9: =R9+S9-T9 -> 270540 | V9: =P9+F9+U9+K9 -> 587445.81 | Y9: =V9+X9 -> 587445.81 | Z9: =LEFT(A9,2) -> 14 | AD9: 197867.53 | AF9: 0 | AG9: 0 | AH9: 0 | AI9: 0 | AK9: 119038.28 | AL9: 0 | AM9: 0 | AN9: 119038.28 | AP9: 270540 | AQ9: 0 | AR9: 0 | AS9: 270540 | AT9: 587445.81 | AV9: 372917 | AW9: 960362.81 | AY9: =F9-AD9 -> 0 | AZ9: =P9-AN9 -> 0 | BA9: =U9-AS9 -> 0 | BB9: =X9-AV9 -> -372917
A10: 1450 | B10: Income receivable | C10: =SUMIF('TB Mitiga LTD'!A:A,'HARKAVA '!A10,'TB Mitiga LTD'!D:D) -> 39750 | D10: =SUMIF('Adj Entries Ltd'!$B$4:$B$954,A10,'Adj Entries Ltd'!$D$4:$D$954) -> 0 | E10: =SUMIF('Adj Entries Ltd'!$B$4:$B$954,A10,'Adj Entries Ltd'!$E$4:$E$954) -> 0 | F10: =(+C10+D10-E10) -> 39750 | H10: =SUMIF('TB US'!A:A,'HARKAVA '!A10,'TB US'!D:D) -> 0 | I10: =SUMIF('Adj. entries US'!B:B,'HARKAVA '!A10,'Adj. entries US'!D:D) -> 0 | J10: =SUMIF('Adj. entries US'!B:B,'HARKAVA '!A10,'Adj. entries US'!E:E) -> 0 | K10: =H10+I10-J10 -> 0 | M10: =SUMIF('TB UK'!A:A,'HARKAVA '!A10,'TB UK'!E:E) -> 0 | N10: =SUMIF('Adj. Entries UK'!B:B,'HARKAVA '!A10,'Adj. Entries UK'!D:D) -> 0 | O10: =SUMIF('Adj. Entries UK'!B:B,'HARKAVA '!A10,'Adj. Entries UK'!E:E) -> 0 | P10: =M10+N10-O10 -> 0 | R10: =SUMIF('TB security'!A:A,'HARKAVA '!A10,'TB security'!D:D) -> 117959 | S10: =SUMIF('Adj. Entries security'!B:B,'HARKAVA '!A10,'Adj. Entries security'!D:D) -> 0 | T10: =SUMIF('Adj. Entries security'!B:B,'HARKAVA '!A10,'Adj. Entries security'!E:E) -> 0 | U10: =R10+S10-T10 -> 117959 | V10: =P10+F10+U10+K10 -> 157709 | Y10: =V10+X10 -> 157709 | Z10: =LEFT(A10,2) -> 14 | AD10: 110000 | AF10: 0 | AG10: 0 | AH10: 0 | AI10: 0 | AK10: 0 | AL10: 0 | AM10: 0 | AN10: 0 | AP10: 47709 | AQ10: 0 | AR10: 0 | AS10: 47709 | AT10: 157709 | AW10: 157709 | AY10: =F10-AD10 -> -70250 | AZ10: =P10-AN10 -> 0 | BA10: =U10-AS10 -> 70250 | BB10: =X10-AV10 -> 0 | BC10: Moved Income receivable that was initially recorded in IL to Security (Safebreach). This is a was through I/C, so no impact.
A11: 1500 | B11: Related parties | C11: =SUMIF('TB Mitiga LTD'!A:A,'HARKAVA '!A11,'TB Mitiga LTD'!D:D) -> 958184.27 | D11: =SUMIF('Adj Entries Ltd'!$B$4:$B$954,A11,'Adj Entries Ltd'!$D$4:$D$954) -> 0 | E11: =SUMIF('Adj Entries Ltd'!$B$4:$B$954,A11,'Adj Entries Ltd'!$E$4:$E$954) -> 0 | F11: =(+C11+D11-E11) -> 958184.27 | H11: =SUMIF('TB US'!A:A,'HARKAVA '!A11,'TB US'!D:D) -> 67042.28 | I11: =SUMIF('Adj. entries US'!B:B,'HARKAVA '!A11,'Adj. entries US'!D:D) -> 0 | J11: =SUMIF('Adj. entries US'!B:B,'HARKAVA '!A11,'Adj. entries US'!E:E) -> 0 | K11: =H11+I11-J11 -> 67042.28 | M11: =SUMIF('TB UK'!A:A,'HARKAVA '!A11,'TB UK'!E:E) -> 0 | N11: =SUMIF('Adj. Entries UK'!B:B,'HARKAVA '!A11,'Adj. Entries UK'!D:D) -> 0 | O11: =SUMIF('Adj. Entries UK'!B:B,'HARKAVA '!A11,'Adj. Entries UK'!E:E) -> 0 | P11: =M11+N11-O11 -> 0 | R11: =SUMIF('TB security'!A:A,'HARKAVA '!A11,'TB security'!D:D) -> 16350 | S11: =SUMIF('Adj. Entries security'!B:B,'HARKAVA '!A11,'Adj. Entries security'!D:D) -> 0 | T11: =SUMIF('Adj. Entries security'!B:B,'HARKAVA '!A11,'Adj. Entries security'!E:E) -> 0 | U11: =R11+S11-T11 -> 16350 | V11: =P11+F11+U11+K11 -> 1041576.5 | X11: =-V11+16350+4721 -> -1020505.5 | Y11: =V11+X11 -> 21071 | Z11: 16 | AD11: 958184.27 | AF11: 67042.28 | AG11: 0 | AH11: 0 | AI11: 67042.28 | AK11: 0 | AL11: 0 | AM11: 0 | AN11: 0 | AP11: 16350 | AQ11: 0 | AR11: 0 | AS11: 16350 | AT11: 1041576.5 | AV11: -1020505.5 | AW11: 21071 | AY11: =F11-AD11 -> 0 | AZ11: =P11-AN11 -> 0 | BA11: =U11-AS11 -> 0 | BB11: =X11-AV11 -> 0
A12: 1600 | B12: Prepaid expenses | C12: =SUMIF('TB Mitiga LTD'!A:A,'HARKAVA '!A12,'TB Mitiga LTD'!D:D) -> 189723.68 | D12: =SUMIF('Adj Entries Ltd'!$B$4:$B$954,A12,'Adj Entries Ltd'!$D$4:$D$954) -> 11383.25 | E12: =SUMIF('Adj Entries Ltd'!$B$4:$B$954,A12,'Adj Entries Ltd'!$E$4:$E$954) -> 0 | F12: =(+C12+D12-E12) -> 201106.93 | H12: =SUMIF('TB US'!A:A,'HARKAVA '!A12,'TB US'!D:D) -> 0 | I12: =SUMIF('Adj. entries US'!B:B,'HARKAVA '!A12,'Adj. entries US'!D:D) -> 0 | J12: =SUMIF('Adj. entries US'!B:B,'HARKAVA '!A12,'Adj. entries US'!E:E) -> 0 | K12: =H12+I12-J12 -> 0 | M12: =SUMIF('TB UK'!A:A,'HARKAVA '!A12,'TB UK'!E:E) -> 6166.63 | N12: =SUMIF('Adj. Entries UK'!B:B,'HARKAVA '!A12,'Adj. Entries UK'!D:D) -> 0 | O12: =SUMIF('Adj. Entries UK'!B:B,'HARKAVA '!A12,'Adj. Entries UK'!E:E) -> 0 | P12: =M12+N12-O12 -> 6166.63 | R12: =SUMIF('TB security'!A:A,'HARKAVA '!A12,'TB security'!D:D) -> 49885.48 | S12: =SUMIF('Adj. Entries security'!B:B,'HARKAVA '!A12,'Adj. Entries security'!D:D) -> 0 | T12: =SUMIF('Adj. Entries security'!B:B,'HARKAVA '!A12,'Adj. Entries security'!E:E) -> 0 | U12: =R12+S12-T12 -> 49885.48 | V12: =P12+F12+U12+K12 -> 257159.04 | Y12: =V12+X12 -> 257159.04 | Z12: =LEFT(A12,2) -> 16 | AD12: 189723.68 | AF12: 0 | AG12: 0 | AH12: 0 | AI12: 0 | AK12: 6166.63 | AL12: 0 | AM12: 0 | AN12: 6166.63 | AP12: 49885.48 | AQ12: 0 | AR12: 0 | AS12: 49885.48 | AT12: 245775.79 | AW12: 245775.79 | AY12: =F12-AD12 -> 11383.25 | AZ12: =P12-AN12 -> 0 | BA12: =U12-AS12 -> 0 | BB12: =X12-AV12 -> 0
A13: 1610 | B13: Government of Israel-tax | C13: =SUMIF('TB Mitiga LTD'!A:A,'HARKAVA '!A13,'TB Mitiga LTD'!D:D) -> 14985.11 | D13: =SUMIF('Adj Entries Ltd'!$B$4:$B$954,A13,'Adj Entries Ltd'!$D$4:$D$954) -> 0 | E13: =SUMIF('Adj Entries Ltd'!$B$4:$B$954,A13,'Adj Entries Ltd'!$E$4:$E$954) -> 0 | F13: =(+C13+D13-E13) -> 14985.11 | H13: =SUMIF('TB US'!A:A,'HARKAVA '!A13,'TB US'!D:D) -> 0 | I13: =SUMIF('Adj. entries US'!B:B,'HARKAVA '!A13,'Adj. entries US'!D:D) -> 0 | J13: =SUMIF('Adj. entries US'!B:B,'HARKAVA '!A13,'Adj. entries US'!E:E) -> 0 | K13: =H13+I13-J13 -> 0 | M13: =SUMIF('TB UK'!A:A,'HARKAVA '!A13,'TB UK'!E:E) -> 5611.91 | N13: =SUMIF('Adj. Entries UK'!B:B,'HARKAVA '!A13,'Adj. Entries UK'!D:D) -> 0 | O13: =SUMIF('Adj. Entries UK'!B:B,'HARKAVA '!A13,'Adj. Entries UK'!E:E) -> 0 | P13: =M13+N13-O13 -> 5611.91 | R13: =SUMIF('TB security'!A:A,'HARKAVA '!A13,'TB security'!D:D) -> 0 | S13: =SUMIF('Adj. Entries security'!B:B,'HARKAVA '!A13,'Adj. Entries security'!D:D) -> 0 | T13: =SUMIF('Adj. Entries security'!B:B,'HARKAVA '!A13,'Adj. Entries security'!E:E) -> 0 | U13: =R13+S13-T13 -> 0 | V13: =P13+F13+U13+K13 -> 20597.02 | Y13: =V13+X13 -> 20597.02 | Z13: =LEFT(A13,2) -> 16 | AD13: 14985.11 | AF13: 0 | AG13: 0 | AH13: 0 | AI13: 0 | AK13: 5611.91 | AL13: 0 | AM13: 0 | AN13: 5611.91 | AP13: 0 | AQ13: 0 | AR13: 0 | AS13: 0 | AT13: 20597.02 | AW13: 20597.02 | AY13: =F13-AD13 -> 0 | AZ13: =P13-AN13 -> 0 | BA13: =U13-AS13 -> 0 | BB13: =X13-AV13 -> 0
A14: 1620 | B14: AR-government of Israel-VAT (net) | C14: =SUMIF('TB Mitiga LTD'!A:A,'HARKAVA '!A14,'TB Mitiga LTD'!D:D) -> 237762.45 | D14: =SUMIF('Adj Entries Ltd'!$B$4:$B$954,A14,'Adj Entries Ltd'!$D$4:$D$954) -> 0 | E14: =SUMIF('Adj Entries Ltd'!$B$4:$B$954,A14,'Adj Entries Ltd'!$E$4:$E$954) -> 0 | F14: =(+C14+D14-E14) -> 237762.45 | H14: =SUMIF('TB US'!A:A,'HARKAVA '!A14,'TB US'!D:D) -> 0 | I14: =SUMIF('Adj. entries US'!B:B,'HARKAVA '!A14,'Adj. entries US'!D:D) -> 0 | J14: =SUMIF('Adj. entries US'!B:B,'HARKAVA '!A14,'Adj. entries US'!E:E) -> 0 | K14: =H14+I14-J14 -> 0 | M14: =SUMIF('TB UK'!A:A,'HARKAVA '!A14,'TB UK'!E:E) -> 0 | N14: =SUMIF('Adj. Entries UK'!B:B,'HARKAVA '!A14,'Adj. Entries UK'!D:D) -> 0 | O14: =SUMIF('Adj. Entries UK'!B:B,'HARKAVA '!A14,'Adj. Entries UK'!E:E) -> 0 | P14: =M14+N14-O14 -> 0 | R14: =SUMIF('TB security'!A:A,'HARKAVA '!A14,'TB security'!D:D) -> 0 | S14: =SUMIF('Adj. Entries security'!B:B,'HARKAVA '!A14,'Adj. Entries security'!D:D) -> 0 | T14: =SUMIF('Adj. Entries security'!B:B,'HARKAVA '!A14,'Adj. Entries security'!E:E) -> 0 | U14: =R14+S14-T14 -> 0 | V14: =P14+F14+U14+K14 -> 237762.45 | Y14: =V14+X14 -> 237762.45 | Z14: =LEFT(A14,2) -> 16 | AD14: 237762.45 | AF14: 0 | AG14: 0 | AH14: 0 | AI14: 0 | AK14: 0 | AL14: 0 | AM14: 0 | AN14: 0 | AP14: 0 | AQ14: 0 | AR14: 0 | AS14: 0 | AT14: 237762.45 | AW14: 237762.45 | AY14: =F14-AD14 -> 0 | AZ14: =P14-AN14 -> 0 | BA14: =U14-AS14 -> 0 | BB14: =X14-AV14 -> 0
A15: 1630 | B15: DEFERRED_TAXES_CUR | C15: =SUMIF('TB Mitiga LTD'!A:A,'HARKAVA '!A15,'TB Mitiga LTD'!D:D) -> 0 | D15: =SUMIF('Adj Entries Ltd'!$B$4:$B$954,A15,'Adj Entries Ltd'!$D$4:$D$954) -> 0 | E15: =SUMIF('Adj Entries Ltd'!$B$4:$B$954,A15,'Adj Entries Ltd'!$E$4:$E$954) -> 0 | F15: =(+C15+D15-E15) -> 0 | H15: =SUMIF('TB US'!A:A,'HARKAVA '!A15,'TB US'!D:D) -> 0 | I15: =SUMIF('Adj. entries US'!B:B,'HARKAVA '!A15,'Adj. entries US'!D:D) -> 0 | J15: =SUMIF('Adj. entries US'!B:B,'HARKAVA '!A15,'Adj. entries US'!E:E) -> 0 | K15: =H15+I15-J15 -> 0 | M15: =SUMIF('TB UK'!A:A,'HARKAVA '!A15,'TB UK'!E:E) -> 0 | N15: =SUMIF('Adj. Entries UK'!B:B,'HARKAVA '!A15,'Adj. Entries UK'!D:D) -> 0 | O15: =SUMIF('Adj. Entries UK'!B:B,'HARKAVA '!A15,'Adj. Entries UK'!E:E) -> 0 | P15: =M15+N15-O15 -> 0 | R15: =SUMIF('TB security'!A:A,'HARKAVA '!A15,'TB security'!D:D) -> 0 | S15: =SUMIF('Adj. Entries security'!B:B,'HARKAVA '!A15,'Adj. Entries security'!D:D) -> 0 | T15: =SUMIF('Adj. Entries security'!B:B,'HARKAVA '!A15,'Adj. Entries security'!E:E) -> 0 | U15: =R15+S15-T15 -> 0 | V15: =P15+F15+U15+K15 -> 0 | Y15: =V15+X15 -> 0 | Z15: =LEFT(A15,2) -> 16 | AD15: 0 | AF15: 0 | AG15: 0 | AH15: 0 | AI15: 0 | AK15: 0 | AL15: 0 | AM15: 0 | AN15: 0 | AP15: 0 | AQ15: 0 | AR15: 0 | AS15: 0 | AT15: 0 | AW15: 0 | AY15: =F15-AD15 -> 0 | AZ15: =P15-AN15 -> 0 | BA15: =U15-AS15 -> 0 | BB15: =X15-AV15 -> 0
A16: 1640 | B16: AR-short term leasing deposits | C16: =SUMIF('TB Mitiga LTD'!A:A,'HARKAVA '!A16,'TB Mitiga LTD'!D:D) -> 294311 | D16: =SUMIF('Adj Entries Ltd'!$B$4:$B$954,A16,'Adj Entries Ltd'!$D$4:$D$954) -> 0 | E16: =SUMIF('Adj Entries Ltd'!$B$4:$B$954,A16,'Adj Entries Ltd'!$E$4:$E$954) -> 0 | F16: =(+C16+D16-E16) -> 294311 | H16: =SUMIF('TB US'!A:A,'HARKAVA '!A16,'TB US'!D:D) -> 0 | I16: =SUMIF('Adj. entries US'!B:B,'HARKAVA '!A16,'Adj. entries US'!D:D) -> 0 | J16: =SUMIF('Adj. entries US'!B:B,'HARKAVA '!A16,'Adj. entries US'!E:E) -> 0 | K16: =H16+I16-J16 -> 0 | M16: =SUMIF('TB UK'!A:A,'HARKAVA '!A16,'TB UK'!E:E) -> 0 | N16: =SUMIF('Adj. Entries UK'!B:B,'HARKAVA '!A16,'Adj. Entries UK'!D:D) -> 0 | O16: =SUMIF('Adj. Entries UK'!B:B,'HARKAVA '!A16,'Adj. Entries UK'!E:E) -> 0 | P16: =M16+N16-O16 -> 0 | R16: =SUMIF('TB security'!A:A,'HARKAVA '!A16,'TB security'!D:D) -> 0 | S16: =SUMIF('Adj. Entries security'!B:B,'HARKAVA '!A16,'Adj. Entries security'!D:D) -> 0 | T16: =SUMIF('Adj. Entries security'!B:B,'HARKAVA '!A16,'Adj. Entries security'!E:E) -> 0 | U16: =R16+S16-T16 -> 0 | V16: =P16+F16+U16+K16 -> 294311 | Y16: =V16+X16 -> 294311 | Z16: =LEFT(A16,2) -> 16 | AD16: 294311 | AF16: 0 | AG16: 0 | AH16: 0 | AI16: 0 | AK16: 0 | AL16: 0 | AM16: 0 | AN16: 0 | AP16: 0 | AQ16: 0 | AR16: 0 | AS16: 0 | AT16: 294311 | AW16: 294311 | AY16: =F16-AD16 -> 0 | AZ16: =P16-AN16 -> 0 | BA16: =U16-AS16 -> 0 | BB16: =X16-AV16 -> 0
A17: 1650 | B17: AR others | C17: =SUMIF('TB Mitiga LTD'!A:A,'HARKAVA '!A17,'TB Mitiga LTD'!D:D) -> 929980.71 | D17: =SUMIF('Adj Entries Ltd'!$B$4:$B$954,A17,'Adj Entries Ltd'!$D$4:$D$954) -> 0 | E17: =SUMIF('Adj Entries Ltd'!$B$4:$B$954,A17,'Adj Entries Ltd'!$E$4:$E$954) -> 0 | F17: =(+C17+D17-E17) -> 929980.71 | H17: =SUMIF('TB US'!A:A,'HARKAVA '!A17,'TB US'!D:D) -> 0 | I17: =SUMIF('Adj. entries US'!B:B,'HARKAVA '!A17,'Adj. entries US'!D:D) -> 0 | J17: =SUMIF('Adj. entries US'!B:B,'HARKAVA '!A17,'Adj. entries US'!E:E) -> 0 | K17: =H17+I17-J17 -> 0 | M17: =SUMIF('TB UK'!A:A,'HARKAVA '!A17,'TB UK'!E:E) -> 0 | N17: =SUMIF('Adj. Entries UK'!B:B,'HARKAVA '!A17,'Adj. Entries UK'!D:D) -> 0 | O17: =SUMIF('Adj. Entries UK'!B:B,'HARKAVA '!A17,'Adj. Entries UK'!E:E) -> 0 | P17: =M17+N17-O17 -> 0 | R17: =SUMIF('TB security'!A:A,'HARKAVA '!A17,'TB security'!D:D) -> 0 | S17: =SUMIF('Adj. Entries security'!B:B,'HARKAVA '!A17,'Adj. Entries security'!D:D) -> 0 | T17: =SUMIF('Adj. Entries security'!B:B,'HARKAVA '!A17,'Adj. Entries security'!E:E) -> 0 | U17: =R17+S17-T17 -> 0 | V17: =P17+F17+U17+K17 -> 929980.71 | Y17: =V17+X17 -> 929980.71 | Z17: 16 | AD17: 929980.71 | AF17: 0 | AG17: 0 | AH17: 0 | AI17: 0 | AK17: 0 | AL17: 0 | AM17: 0 | AN17: 0 | AP17: 0 | AQ17: 0 | AR17: 0 | AS17: 0 | AT17: 929980.71 | AW17: 929980.71 | AY17: =F17-AD17 -> 0 | AZ17: =P17-AN17 -> 0 | BA17: =U17-AS17 -> 0 | BB17: =X17-AV17 -> 0
A18: 1660 | B18: Leasehold assets - short term | C18: =SUMIF('TB Mitiga LTD'!A:A,'HARKAVA '!A18,'TB Mitiga LTD'!D:D) -> 0 | D18: =SUMIF('Adj Entries Ltd'!$B$4:$B$954,A18,'Adj Entries Ltd'!$D$4:$D$954) -> 0 | E18: =SUMIF('Adj Entries Ltd'!$B$4:$B$954,A18,'Adj Entries Ltd'!$E$4:$E$954) -> 0 | F18: =(+C18+D18-E18) -> 0 | H18: =SUMIF('TB US'!A:A,'HARKAVA '!A18,'TB US'!D:D) -> 0 | I18: =SUMIF('Adj. entries US'!B:B,'HARKAVA '!A18,'Adj. entries US'!D:D) -> 0 | J18: =SUMIF('Adj. entries US'!B:B,'HARKAVA '!A18,'Adj. entries US'!E:E) -> 0 | K18: =H18+I18-J18 -> 0 | M18: =SUMIF('TB UK'!A:A,'HARKAVA '!A18,'TB UK'!E:E) -> 0 | N18: =SUMIF('Adj. Entries UK'!B:B,'HARKAVA '!A18,'Adj. Entries UK'!D:D) -> 0 | O18: =SUMIF('Adj. Entries UK'!B:B,'HARKAVA '!A18,'Adj. Entries UK'!E:E) -> 0 | P18: =M18+N18-O18 -> 0 | R18: =SUMIF('TB security'!A:A,'HARKAVA '!A18,'TB security'!D:D) -> 0 | S18: =SUMIF('Adj. Entries security'!B:B,'HARKAVA '!A18,'Adj. Entries security'!D:D) -> 0 | T18: =SUMIF('Adj. Entries security'!B:B,'HARKAVA '!A18,'Adj. Entries security'!E:E) -> 0 | U18: =R18+S18-T18 -> 0 | V18: =P18+F18+U18+K18 -> 0 | Y18: =V18+X18 -> 0 | Z18: 19 | AD18: 0 | AF18: 0 | AG18: 0 | AH18: 0 | AI18: 0 | AK18: 0 | AL18: 0 | AM18: 0 | AN18: 0 | AP18: 0 | AQ18: 0 | AR18: 0 | AS18: 0 | AT18: 0 | AW18: 0 | AY18: =F18-AD18 -> 0 | AZ18: =P18-AN18 -> 0 | BA18: =U18-AS18 -> 0 | BB18: =X18-AV18 -> 0
A19: 1700 | B19: Deferred taxes | C19: =SUMIF('TB Mitiga LTD'!A:A,'HARKAVA '!A19,'TB Mitiga LTD'!D:D) -> 0 | D19: =SUMIF('Adj Entries Ltd'!$B$4:$B$954,A19,'Adj Entries Ltd'!$D$4:$D$954) -> 0 | E19: =SUMIF('Adj Entries Ltd'!$B$4:$B$954,A19,'Adj Entries Ltd'!$E$4:$E$954) -> 0 | F19: =(+C19+D19-E19) -> 0 | H19: =SUMIF('TB US'!A:A,'HARKAVA '!A19,'TB US'!D:D) -> 0 | I19: =SUMIF('Adj. entries US'!B:B,'HARKAVA '!A19,'Adj. entries US'!D:D) -> 0 | J19: =SUMIF('Adj. entries US'!B:B,'HARKAVA '!A19,'Adj. entries US'!E:E) -> 0 | K19: =H19+I19-J19 -> 0 | M19: =SUMIF('TB UK'!A:A,'HARKAVA '!A19,'TB UK'!E:E) -> 0 | N19: =SUMIF('Adj. Entries UK'!B:B,'HARKAVA '!A19,'Adj. Entries UK'!D:D) -> 0 | O19: =SUMIF('Adj. Entries UK'!B:B,'HARKAVA '!A19,'Adj. Entries UK'!E:E) -> 0 | P19: =M19+N19-O19 -> 0 | R19: =SUMIF('TB security'!A:A,'HARKAVA '!A19,'TB security'!D:D) -> 0 | S19: =SUMIF('Adj. Entries security'!B:B,'HARKAVA '!A19,'Adj. Entries security'!D:D) -> 0 | T19: =SUMIF('Adj. Entries security'!B:B,'HARKAVA '!A19,'Adj. Entries security'!E:E) -> 0 | U19: =R19+S19-T19 -> 0 | V19: =P19+F19+U19+K19 -> 0 | Y19: =V19+X19 -> 0 | Z19: =LEFT(A19,2) -> 17 | AD19: 0 | AF19: 0 | AG19: 0 | AH19: 0 | AI19: 0 | AK19: 0 | AL19: 0 | AM19: 0 | AN19: 0 | AP19: 0 | AQ19: 0 | AR19: 0 | AS19: 0 | AT19: 0 | AW19: 0 | AY19: =F19-AD19 -> 0 | AZ19: =P19-AN19 -> 0 | BA19: =U19-AS19 -> 0 | BB19: =X19-AV19 -> 0
A20: 2100 | B20: Intercompany Capital notes | C20: =SUMIF('TB Mitiga LTD'!A:A,'HARKAVA '!A20,'TB Mitiga LTD'!D:D) -> 0 | D20: =SUMIF('Adj Entries Ltd'!$B$4:$B$954,A20,'Adj Entries Ltd'!$D$4:$D$954) -> 0 | E20: =SUMIF('Adj Entries Ltd'!$B$4:$B$954,A20,'Adj Entries Ltd'!$E$4:$E$954) -> 0 | F20: =(+C20+D20-E20) -> 0 | H20: =SUMIF('TB US'!A:A,'HARKAVA '!A20,'TB US'!D:D) -> 0 | I20: =SUMIF('Adj. entries US'!B:B,'HARKAVA '!A20,'Adj. entries US'!D:D) -> 0 | J20: =SUMIF('Adj. entries US'!B:B,'HARKAVA '!A20,'Adj. entries US'!E:E) -> 0 | K20: =H20+I20-J20 -> 0 | M20: =SUMIF('TB UK'!A:A,'HARKAVA '!A20,'TB UK'!E:E) -> 0 | N20: =SUMIF('Adj. Entries UK'!B:B,'HARKAVA '!A20,'Adj. Entries UK'!D:D) -> 0 | O20: =SUMIF('Adj. Entries UK'!B:B,'HARKAVA '!A20,'Adj. Entries UK'!E:E) -> 0 | P20: =M20+N20-O20 -> 0 | R20: =SUMIF('TB security'!A:A,'HARKAVA '!A20,'TB security'!D:D) -> 0 | S20: =SUMIF('Adj. Entries security'!B:B,'HARKAVA '!A20,'Adj. Entries security'!D:D) -> 0 | T20: =SUMIF('Adj. Entries security'!B:B,'HARKAVA '!A20,'Adj. Entries security'!E:E) -> 0 | U20: =R20+S20-T20 -> 0 | V20: =P20+F20+U20+K20 -> 0 | Y20: =V20+X20 -> 0 | Z20: =LEFT(A20,2) -> 21 | AD20: 0 | AF20: 0 | AG20: 0 | AH20: 0 | AI20: 0 | AK20: 0 | AL20: 0 | AM20: 0 | AN20: 0 | AP20: 0 | AQ20: 0 | AR20: 0 | AS20: 0 | AT20: 0 | AW20: 0 | AY20: =F20-AD20 -> 0 | AZ20: =P20-AN20 -> 0 | BA20: =U20-AS20 -> 0 | BB20: =X20-AV20 -> 0
A21: 2200 | B21: AR-long term leasing deposits | C21: =SUMIF('TB Mitiga LTD'!A:A,'HARKAVA '!A21,'TB Mitiga LTD'!D:D) -> 0 | D21: =SUMIF('Adj Entries Ltd'!$B$4:$B$954,A21,'Adj Entries Ltd'!$D$4:$D$954) -> 0 | E21: =SUMIF('Adj Entries Ltd'!$B$4:$B$954,A21,'Adj Entries Ltd'!$E$4:$E$954) -> 0 | F21: =(+C21+D21-E21) -> 0 | H21: =SUMIF('TB US'!A:A,'HARKAVA '!A21,'TB US'!D:D) -> 0 | I21: =SUMIF('Adj. entries US'!B:B,'HARKAVA '!A21,'Adj. entries US'!D:D) -> 0 | J21: =SUMIF('Adj. entries US'!B:B,'HARKAVA '!A21,'Adj. entries US'!E:E) -> 0 | K21: =H21+I21-J21 -> 0 | M21: =SUMIF('TB UK'!A:A,'HARKAVA '!A21,'TB UK'!E:E) -> 0 | N21: =SUMIF('Adj. Entries UK'!B:B,'HARKAVA '!A21,'Adj. Entries UK'!D:D) -> 0 | O21: =SUMIF('Adj. Entries UK'!B:B,'HARKAVA '!A21,'Adj. Entries UK'!E:E) -> 0 | P21: =M21+N21-O21 -> 0 | R21: =SUMIF('TB security'!A:A,'HARKAVA '!A21,'TB security'!D:D) -> 0 | S21: =SUMIF('Adj. Entries security'!B:B,'HARKAVA '!A21,'Adj. Entries security'!D:D) -> 0 | T21: =SUMIF('Adj. Entries security'!B:B,'HARKAVA '!A21,'Adj. Entries security'!E:E) -> 0 | U21: =R21+S21-T21 -> 0 | V21: =P21+F21+U21+K21 -> 0 | Y21: =V21+X21 -> 0 | Z21: =LEFT(A21,2) -> 22 | AD21: 0 | AF21: 0 | AG21: 0 | AH21: 0 | AI21: 0 | AK21: 0 | AL21: 0 | AM21: 0 | AN21: 0 | AP21: 0 | AQ21: 0 | AR21: 0 | AS21: 0 | AT21: 0 | AW21: 0 | AY21: =F21-AD21 -> 0 | AZ21: =P21-AN21 -> 0 | BA21: =U21-AS21 -> 0 | BB21: =X21-AV21 -> 0
A22: 2300 | B22: Deferred taxes- Long term | C22: =SUMIF('TB Mitiga LTD'!A:A,'HARKAVA '!A22,'TB Mitiga LTD'!D:D) -> 0 | D22: =SUMIF('Adj Entries Ltd'!$B$4:$B$954,A22,'Adj Entries Ltd'!$D$4:$D$954) -> 0 | E22: =SUMIF('Adj Entries Ltd'!$B$4:$B$954,A22,'Adj Entries Ltd'!$E$4:$E$954) -> 0 | F22: =(+C22+D22-E22) -> 0 | H22: =SUMIF('TB US'!A:A,'HARKAVA '!A22,'TB US'!D:D) -> 0 | I22: =SUMIF('Adj. entries US'!B:B,'HARKAVA '!A22,'Adj. entries US'!D:D) -> 0 | J22: =SUMIF('Adj. entries US'!B:B,'HARKAVA '!A22,'Adj. entries US'!E:E) -> 0 | K22: =H22+I22-J22 -> 0 | M22: =SUMIF('TB UK'!A:A,'HARKAVA '!A22,'TB UK'!E:E) -> 0 | N22: =SUMIF('Adj. Entries UK'!B:B,'HARKAVA '!A22,'Adj. Entries UK'!D:D) -> 0 | O22: =SUMIF('Adj. Entries UK'!B:B,'HARKAVA '!A22,'Adj. Entries UK'!E:E) -> 0 | P22: =M22+N22-O22 -> 0 | R22: =SUMIF('TB security'!A:A,'HARKAVA '!A22,'TB security'!D:D) -> 0 | S22: =SUMIF('Adj. Entries security'!B:B,'HARKAVA '!A22,'Adj. Entries security'!D:D) -> 0 | T22: =SUMIF('Adj. Entries security'!B:B,'HARKAVA '!A22,'Adj. Entries security'!E:E) -> 0 | U22: =R22+S22-T22 -> 0 | V22: =P22+F22+U22+K22 -> 0 | Y22: =V22+X22 -> 0 | Z22: =LEFT(A22,2) -> 23 | AD22: 0 | AF22: 0 | AG22: 0 | AH22: 0 | AI22: 0 | AK22: 0 | AL22: 0 | AM22: 0 | AN22: 0 | AP22: 0 | AQ22: 0 | AR22: 0 | AS22: 0 | AT22: 0 | AW22: 0 | AY22: =F22-AD22 -> 0 | AZ22: =P22-AN22 -> 0 | BA22: =U22-AS22 -> 0 | BB22: =X22-AV22 -> 0
A23: 2350 | B23: Leasehold assets | C23: =SUMIF('TB Mitiga LTD'!A:A,'HARKAVA '!A23,'TB Mitiga LTD'!D:D) -> 0 | D23: =SUMIF('Adj Entries Ltd'!$B$4:$B$954,A23,'Adj Entries Ltd'!$D$4:$D$954) -> 0 | E23: =SUMIF('Adj Entries Ltd'!$B$4:$B$954,A23,'Adj Entries Ltd'!$E$4:$E$954) -> 0 | F23: =(+C23+D23-E23) -> 0 | H23: =SUMIF('TB US'!A:A,'HARKAVA '!A23,'TB US'!D:D) -> 0 | I23: =SUMIF('Adj. entries US'!B:B,'HARKAVA '!A23,'Adj. entries US'!D:D) -> 0 | J23: =SUMIF('Adj. entries US'!B:B,'HARKAVA '!A23,'Adj. entries US'!E:E) -> 0 | K23: =H23+I23-J23 -> 0 | M23: =SUMIF('TB UK'!A:A,'HARKAVA '!A23,'TB UK'!E:E) -> 0 | N23: =SUMIF('Adj. Entries UK'!B:B,'HARKAVA '!A23,'Adj. Entries UK'!D:D) -> 0 | O23: =SUMIF('Adj. Entries UK'!B:B,'HARKAVA '!A23,'Adj. Entries UK'!E:E) -> 0 | P23: =M23+N23-O23 -> 0 | R23: =SUMIF('TB security'!A:A,'HARKAVA '!A23,'TB security'!D:D) -> 0 | S23: =SUMIF('Adj. Entries security'!B:B,'HARKAVA '!A23,'Adj. Entries security'!D:D) -> 0 | T23: =SUMIF('Adj. Entries security'!B:B,'HARKAVA '!A23,'Adj. Entries security'!E:E) -> 0 | U23: =R23+S23-T23 -> 0 | V23: =P23+F23+U23+K23 -> 0 | Y23: =V23+X23 -> 0 | Z23: 25 | AD23: 0 | AF23: 0 | AG23: 0 | AH23: 0 | AI23: 0 | AK23: 0 | AL23: 0 | AM23: 0 | AN23: 0 | AP23: 0 | AQ23: 0 | AR23: 0 | AS23: 0 | AT23: 0 | AW23: 0 | AY23: =F23-AD23 -> 0 | AZ23: =P23-AN23 -> 0 | BA23: =U23-AS23 -> 0 | BB23: =X23-AV23 -> 0
A24: 2400 | B24: Investment in subsidiary | C24: =SUMIF('TB Mitiga LTD'!A:A,'HARKAVA '!A24,'TB Mitiga LTD'!D:D) -> 129.64 | D24: =SUMIF('Adj Entries Ltd'!$B$4:$B$954,A24,'Adj Entries Ltd'!$D$4:$D$954) -> 0 | E24: =SUMIF('Adj Entries Ltd'!$B$4:$B$954,A24,'Adj Entries Ltd'!$E$4:$E$954) -> 0 | F24: =(+C24+D24-E24) -> 129.64 | H24: =SUMIF('TB US'!A:A,'HARKAVA '!A24,'TB US'!D:D) -> 0 | I24: =SUMIF('Adj. entries US'!B:B,'HARKAVA '!A24,'Adj. entries US'!D:D) -> 0 | J24: =SUMIF('Adj. entries US'!B:B,'HARKAVA '!A24,'Adj. entries US'!E:E) -> 0 | K24: =H24+I24-J24 -> 0 | M24: =SUMIF('TB UK'!A:A,'HARKAVA '!A24,'TB UK'!E:E) -> 0 | N24: =SUMIF('Adj. Entries UK'!B:B,'HARKAVA '!A24,'Adj. Entries UK'!D:D) -> 0 | O24: =SUMIF('Adj. Entries UK'!B:B,'HARKAVA '!A24,'Adj. Entries UK'!E:E) -> 0 | P24: =M24+N24-O24 -> 0 | R24: =SUMIF('TB security'!A:A,'HARKAVA '!A24,'TB security'!D:D) -> 320 | S24: =SUMIF('Adj. Entries security'!B:B,'HARKAVA '!A24,'Adj. Entries security'!D:D) -> 0 | T24: =SUMIF('Adj. Entries security'!B:B,'HARKAVA '!A24,'Adj. Entries security'!E:E) -> 0 | U24: =R24+S24-T24 -> 320 | V24: =P24+F24+U24+K24 -> 449.64 | X24: =-V24 -> -449.64 | Y24: =V24+X24 -> 0 | Z24: =LEFT(A24,2) -> 24 | AD24: 129.64 | AF24: 0 | AG24: 0 | AH24: 0 | AI24: 0 | AK24: 0 | AL24: 0 | AM24: 0 | AN24: 0 | AP24: 320 | AQ24: 0 | AR24: 0 | AS24: 320 | AT24: 449.64 | AV24: -449.64 | AW24: 0 | AY24: =F24-AD24 -> 0 | AZ24: =P24-AN24 -> 0 | BA24: =U24-AS24 -> 0 | BB24: =X24-AV24 -> 0
A25: 3100 | B25: Fixed assets-cost | C25: =SUMIF('TB Mitiga LTD'!A:A,'HARKAVA '!A25,'TB Mitiga LTD'!D:D) -> 1431538.9 | D25: =SUMIF('Adj Entries Ltd'!$B$4:$B$954,A25,'Adj Entries Ltd'!$D$4:$D$954) -> 0 | E25: =SUMIF('Adj Entries Ltd'!$B$4:$B$954,A25,'Adj Entries Ltd'!$E$4:$E$954) -> 11383.25 | F25: =(+C25+D25-E25) -> 1420155.7 | H25: =SUMIF('TB US'!A:A,'HARKAVA '!A25,'TB US'!D:D) -> 0 | I25: =SUMIF('Adj. entries US'!B:B,'HARKAVA '!A25,'Adj. entries US'!D:D) -> 0 | J25: =SUMIF('Adj. entries US'!B:B,'HARKAVA '!A25,'Adj. entries US'!E:E) -> 0 | K25: =H25+I25-J25 -> 0 | M25: =SUMIF('TB UK'!A:A,'HARKAVA '!A25,'TB UK'!E:E) -> 26887.96 | N25: =SUMIF('Adj. Entries UK'!B:B,'HARKAVA '!A25,'Adj. Entries UK'!D:D) -> 0 | O25: =SUMIF('Adj. Entries UK'!B:B,'HARKAVA '!A25,'Adj. Entries UK'!E:E) -> 0 | P25: =M25+N25-O25 -> 26887.96 | R25: =SUMIF('TB security'!A:A,'HARKAVA '!A25,'TB security'!D:D) -> 50601.48 | S25: =SUMIF('Adj. Entries security'!B:B,'HARKAVA '!A25,'Adj. Entries security'!D:D) -> 0 | T25: =SUMIF('Adj. Entries security'!B:B,'HARKAVA '!A25,'Adj. Entries security'!E:E) -> 0 | U25: =R25+S25-T25 -> 50601.48 | V25: =P25+F25+U25+K25 -> 1497645.1 | Y25: =V25+X25 -> 1497645.1 | Z25: =LEFT(A25,2) -> 31 | AD25: 1431538.9 | AF25: 0 | AG25: 0 | AH25: 0 | AI25: 0 | AK25: 26887.96 | AL25: 0 | AM25: 0 | AN25: 26887.96 | AP25: 50601.48 | AQ25: 0 | AR25: 0 | AS25: 50601.48 | AT25: 1509028.4 | AW25: 1509028.4 | AY25: =F25-AD25 -> -11383.25 | AZ25: =P25-AN25 -> 0 | BA25: =U25-AS25 -> 0 | BB25: =X25-AV25 -> 0
A26: 3110 | B26: Fixed assets-accumulated dep. | C26: =SUMIF('TB Mitiga LTD'!A:A,'HARKAVA '!A26,'TB Mitiga LTD'!D:D) -> -93369 | D26: =SUMIF('Adj Entries Ltd'!$B$4:$B$954,A26,'Adj Entries Ltd'!$D$4:$D$954) -> 0 | E26: =SUMIF('Adj Entries Ltd'!$B$4:$B$954,A26,'Adj Entries Ltd'!$E$4:$E$954) -> 0 | F26: =(+C26+D26-E26) -> -93369 | H26: =SUMIF('TB US'!A:A,'HARKAVA '!A26,'TB US'!D:D) -> 0 | I26: =SUMIF('Adj. entries US'!B:B,'HARKAVA '!A26,'Adj. entries US'!D:D) -> 0 | J26: =SUMIF('Adj. entries US'!B:B,'HARKAVA '!A26,'Adj. entries US'!E:E) -> 0 | K26: =H26+I26-J26 -> 0 | M26: =SUMIF('TB UK'!A:A,'HARKAVA '!A26,'TB UK'!E:E) -> -9443 | N26: =SUMIF('Adj. Entries UK'!B:B,'HARKAVA '!A26,'Adj. Entries UK'!D:D) -> 0 | O26: =SUMIF('Adj. Entries UK'!B:B,'HARKAVA '!A26,'Adj. Entries UK'!E:E) -> 0 | P26: =M26+N26-O26 -> -9443 | R26: =SUMIF('TB security'!A:A,'HARKAVA '!A26,'TB security'!D:D) -> -3702 | S26: =SUMIF('Adj. Entries security'!B:B,'HARKAVA '!A26,'Adj. Entries security'!D:D) -> 0 | T26: =SUMIF('Adj. Entries security'!B:B,'HARKAVA '!A26,'Adj. Entries security'!E:E) -> 0 | U26: =R26+S26-T26 -> -3702 | V26: =P26+F26+U26+K26 -> -106514 | Y26: =V26+X26 -> -106514 | Z26: =LEFT(A26,2) -> 31 | AD26: -93369 | AF26: 0 | AG26: 0 | AH26: 0 | AI26: 0 | AK26: -9443 | AL26: 0 | AM26: 0 | AN26: -9443 | AP26: -3702 | AQ26: 0 | AR26: 0 | AS26: -3702 | AT26: -106514 | AW26: -106514 | AY26: =F26-AD26 -> 0 | AZ26: =P26-AN26 -> 0 | BA26: =U26-AS26 -> 0 | BB26: =X26-AV26 -> 0
A27: 3200 | B27: In Process R&DS | C27: =SUMIF('TB Mitiga LTD'!A:A,'HARKAVA '!A27,'TB Mitiga LTD'!D:D) -> 0 | D27: =SUMIF('Adj Entries Ltd'!$B$4:$B$954,A27,'Adj Entries Ltd'!$D$4:$D$954) -> 0 | E27: =SUMIF('Adj Entries Ltd'!$B$4:$B$954,A27,'Adj Entries Ltd'!$E$4:$E$954) -> 0 | F27: =(+C27+D27-E27) -> 0 | H27: =SUMIF('TB US'!A:A,'HARKAVA '!A27,'TB US'!D:D) -> 0 | I27: =SUMIF('Adj. entries US'!B:B,'HARKAVA '!A27,'Adj. entries US'!D:D) -> 0 | J27: =SUMIF('Adj. entries US'!B:B,'HARKAVA '!A27,'Adj. entries US'!E:E) -> 0 | K27: =H27+I27-J27 -> 0 | M27: =SUMIF('TB UK'!A:A,'HARKAVA '!A27,'TB UK'!E:E) -> 0 | N27: =SUMIF('Adj. Entries UK'!B:B,'HARKAVA '!A27,'Adj. Entries UK'!D:D) -> 0 | O27: =SUMIF('Adj. Entries UK'!B:B,'HARKAVA '!A27,'Adj. Entries UK'!E:E) -> 0 | P27: =M27+N27-O27 -> 0 | R27: =SUMIF('TB security'!A:A,'HARKAVA '!A27,'TB security'!D:D) -> 0 | S27: =SUMIF('Adj. Entries security'!B:B,'HARKAVA '!A27,'Adj. Entries security'!D:D) -> 0 | T27: =SUMIF('Adj. Entries security'!B:B,'HARKAVA '!A27,'Adj. Entries security'!E:E) -> 0 | U27: =R27+S27-T27 -> 0 | V27: =P27+F27+U27+K27 -> 0 | Y27: =V27+X27 -> 0 | Z27: =LEFT(A27,2) -> 32 | AD27: 0 | AF27: 0 | AG27: 0 | AH27: 0 | AI27: 0 | AK27: 0 | AL27: 0 | AM27: 0 | AN27: 0 | AP27: 0 | AQ27: 0 | AR27: 0 | AS27: 0 | AT27: 0 | AW27: 0 | AY27: =F27-AD27 -> 0 | AZ27: =P27-AN27 -> 0 | BA27: =U27-AS27 -> 0 | BB27: =X27-AV27 -> 0
C28: =SUM(C6:C27) -> 5552403.7 | D28: =SUM(D6:D27) -> 3011383.2 | E28: =SUM(E6:E27) -> 11383.25 | F28: =SUM(F6:F27) -> 8552403.7 | H28: =SUM(H6:H27) -> 67042.28 | I28: =SUM(I6:I27) -> 0 | J28: =SUM(J6:J27) -> 0 | K28: =SUM(K6:K27) -> 67042.28 | M28: =SUM(M6:M27) -> 683194.86 | N28: =SUM(N6:N27) -> 0 | O28: =SUM(O6:O27) -> 0 | P28: =SUM(P6:P27) -> 683194.86 | R28: =SUM(R6:R27) -> 14917461 | S28: =SUM(S6:S27) -> 0 | T28: =SUM(T6:T27) -> 0 | U28: =SUM(U6:U27) -> 14917461 | V28: =SUM(V6:V27) -> 24220102 | X28: =SUM(X6:X27) -> -1020955.2 | Y28: =SUM(Y6:Y27) -> 23199147 | Z28: =LEFT(A28,2) | AD28: 8622653.7 | AF28: 67042.28 | AG28: 0 | AH28: 0 | AI28: 67042.28 | AK28: 683194.86 | AL28: 0 | AM28: 0 | AN28: 683194.86 | AP28: 14847211 | AQ28: 0 | AR28: 0 | AS28: 14847211 | AT28: 24220102 | AV28: -648038.19 | AW28: 23572064 | AY28: =F28-AD28 -> -70250 | AZ28: =P28-AN28 -> 0 | BA28: =U28-AS28 -> 70250 | BB28: =X28-AV28 -> -372917
AY29: =F29-AD29 -> 0 | AZ29: =P29-AN29 -> 0 | BA29: =U29-AS29 -> 0 | BB29: =X29-AV29 -> 0
AY30: =F30-AD30 -> 0 | AZ30: =P30-AN30 -> 0 | BA30: =U30-AS30 -> 0 | BB30: =X30-AV30 -> 0
Z31: =LEFT(A31,2) | AY31: =F31-AD31 -> 0 | AZ31: =P31-AN31 -> 0 | BA31: =U31-AS31 -> 0 | BB31: =X31-AV31 -> 0
A32: 3300 | B32: Short term bank credit | C32: =SUMIF('TB Mitiga LTD'!A:A,'HARKAVA '!A32,'TB Mitiga LTD'!D:D) -> 0 | D32: =SUMIF('Adj Entries Ltd'!$B$4:$B$954,A32,'Adj Entries Ltd'!$D$4:$D$954) -> 0 | E32: =SUMIF('Adj Entries Ltd'!$B$4:$B$954,A32,'Adj Entries Ltd'!$E$4:$E$954) -> 0 | F32: =(+C32+D32-E32) -> 0 | H32: =SUMIF('TB US'!A:A,'HARKAVA '!A32,'TB US'!D:D) -> 0 | I32: =SUMIF('Adj. entries US'!B:B,'HARKAVA '!A32,'Adj. entries US'!D:D) -> 0 | J32: =SUMIF('Adj. entries US'!B:B,'HARKAVA '!A32,'Adj. entries US'!E:E) -> 0 | K32: =H32+I32-J32 -> 0 | M32: =SUMIF('TB UK'!A:A,'HARKAVA '!A32,'TB UK'!E:E) -> 0 | N32: =SUMIF('Adj. Entries UK'!B:B,'HARKAVA '!A32,'Adj. Entries UK'!D:D) -> 0 | O32: =SUMIF('Adj. Entries UK'!B:B,'HARKAVA '!A32,'Adj. Entries UK'!E:E) -> 0 | P32: =M32+N32-O32 -> 0 | R32: =SUMIF('TB security'!A:A,'HARKAVA '!A32,'TB security'!D:D) -> 0 | S32: =SUMIF('Adj. Entries security'!B:B,'HARKAVA '!A32,'Adj. Entries security'!D:D) -> 0 | T32: =SUMIF('Adj. Entries security'!B:B,'HARKAVA '!A32,'Adj. Entries security'!E:E) -> 0 | U32: =R32+S32-T32 -> 0 | V32: =P32+F32+U32+K32 -> 0 | Y32: =V32+X32 -> 0 | Z32: 33 | AD32: 0 | AF32: 0 | AG32: 0 | AH32: 0 | AI32: 0 | AK32: 0 | AL32: 0 | AM32: 0 | AN32: 0 | AP32: 0 | AQ32: 0 | AR32: 0 | AS32: 0 | AT32: 0 | AW32: 0 | AY32: =F32-AD32 -> 0 | AZ32: =P32-AN32 -> 0 | BA32: =U32-AS32 -> 0 | BB32: =X32-AV32 -> 0
A33: 3400 | B33: Trade payables | C33: =SUMIF('TB Mitiga LTD'!A:A,'HARKAVA '!A33,'TB Mitiga LTD'!D:D) -> -552171.51 | D33: =SUMIF('Adj Entries Ltd'!$B$4:$B$954,A33,'Adj Entries Ltd'!$D$4:$D$954) -> 0 | E33: =SUMIF('Adj Entries Ltd'!$B$4:$B$954,A33,'Adj Entries Ltd'!$E$4:$E$954) -> 2081.9936 | F33: =(+C33+D33-E33) -> -554253.5 | H33: =SUMIF('TB US'!A:A,'HARKAVA '!A33,'TB US'!D:D) -> 0 | I33: =SUMIF('Adj. entries US'!B:B,'HARKAVA '!A33,'Adj. entries US'!D:D) -> 0 | J33: =SUMIF('Adj. entries US'!B:B,'HARKAVA '!A33,'Adj. entries US'!E:E) -> 0 | K33: =H33+I33-J33 -> 0 | M33: =SUMIF('TB UK'!A:A,'HARKAVA '!A33,'TB UK'!E:E) -> -2567.03 | N33: =SUMIF('Adj. Entries UK'!B:B,'HARKAVA '!A33,'Adj. Entries UK'!D:D) -> 0 | O33: =SUMIF('Adj. Entries UK'!B:B,'HARKAVA '!A33,'Adj. Entries UK'!E:E) -> 0 | P33: =M33+N33-O33 -> -2567.03 | R33: =SUMIF('TB security'!A:A,'HARKAVA '!A33,'TB security'!D:D) -> -115788.09 | S33: =SUMIF('Adj. Entries security'!B:B,'HARKAVA '!A33,'Adj. Entries security'!D:D) -> 0 | T33: =SUMIF('Adj. Entries security'!B:B,'HARKAVA '!A33,'Adj. Entries security'!E:E) -> 0 | U33: =R33+S33-T33 -> -115788.09 | V33: =P33+F33+U33+K33 -> -672608.62 | Y33: =V33+X33 -> -672608.62 | Z33: =LEFT(A33,2) -> 34 | AD33: -554253.5 | AF33: 0 | AG33: 0 | AH33: 0 | AI33: 0 | AK33: -2567.03 | AL33: 0 | AM33: 0 | AN33: -2567.03 | AP33: -115788.09 | AQ33: 0 | AR33: 0 | AS33: -115788.09 | AT33: -672608.62 | AW33: -672608.62 | AY33: =F33-AD33 -> 0 | AZ33: =P33-AN33 -> 0 | BA33: =U33-AS33 -> 0 | BB33: =X33-AV33 -> 0
A34: 3500 | B34: consolidated company | C34: =SUMIF('TB Mitiga LTD'!A:A,'HARKAVA '!A34,'TB Mitiga LTD'!D:D) -> -5950440.4 | D34: =SUMIF('Adj Entries Ltd'!$B$4:$B$954,A34,'Adj Entries Ltd'!$D$4:$D$954) -> 61840 | E34: =SUMIF('Adj Entries Ltd'!$B$4:$B$954,A34,'Adj Entries Ltd'!$E$4:$E$954) -> 5771962 | F34: =(+C34+D34-E34) -> -11660562 | H34: =SUMIF('TB US'!A:A,'HARKAVA '!A34,'TB US'!D:D) -> -2502.03 | I34: =SUMIF('Adj. entries US'!B:B,'HARKAVA '!A34,'Adj. entries US'!D:D) -> 0 | J34: =SUMIF('Adj. entries US'!B:B,'HARKAVA '!A34,'Adj. entries US'!E:E) -> 61840 | K34: =H34+I34-J34 -> -64342.03 | M34: =SUMIF('TB UK'!A:A,'HARKAVA '!A34,'TB UK'!E:E) -> -1602566.1 | N34: =SUMIF('Adj. Entries UK'!B:B,'HARKAVA '!A34,'Adj. Entries UK'!D:D) -> 1265642.5 | O34: =SUMIF('Adj. Entries UK'!B:B,'HARKAVA '!A34,'Adj. Entries UK'!E:E) -> 0 | P34: =M34+N34-O34 -> -336923.62 | R34: =SUMIF('TB security'!A:A,'HARKAVA '!A34,'TB security'!D:D) -> 9535002.3 | S34: =SUMIF('Adj. Entries security'!B:B,'HARKAVA '!A34,'Adj. Entries security'!D:D) -> 1877446 | T34: =SUMIF('Adj. Entries security'!B:B,'HARKAVA '!A34,'Adj. Entries security'!E:E) -> 414915 | U34: =R34+S34-T34 -> 10997533 | V34: =P34+F34+U34+K34 -> -1064294.7 | X34: =-V34 -> 1064294.7 | Y34: =V34+X34 -> 0 | Z34: 36 | AD34: -11546524 | AF34: -2502.03 | AG34: 0 | AH34: 61840 | AI34: -64342.03 | AK34: -1602566.1 | AL34: 1149913 | AM34: 0 | AN34: -452653.15 | AP34: 9535002.3 | AQ34: 1922926 | AR34: 414915 | AS34: 11043013 | AT34: -1020506.3 | AV34: 1020506.3 | AW34: 0 | AY34: =F34-AD34 -> -114038 | AZ34: =P34-AN34 -> 115729.52 | BA34: =U34-AS34 -> -45480 | BB34: =X34-AV34 -> 43788.475 | BC34: See TP wp
A35: 3600 | B35: AP-employees and emp. Instit. | C35: =SUMIF('TB Mitiga LTD'!A:A,'HARKAVA '!A35,'TB Mitiga LTD'!D:D) -> -1008607.2 | D35: =SUMIF('Adj Entries Ltd'!$B$4:$B$954,A35,'Adj Entries Ltd'!$D$4:$D$954) -> 0 | E35: =SUMIF('Adj Entries Ltd'!$B$4:$B$954,A35,'Adj Entries Ltd'!$E$4:$E$954) -> 0 | F35: =(+C35+D35-E35) -> -1008607.2 | H35: =SUMIF('TB US'!A:A,'HARKAVA '!A35,'TB US'!D:D) -> 0 | I35: =SUMIF('Adj. entries US'!B:B,'HARKAVA '!A35,'Adj. entries US'!D:D) -> 0 | J35: =SUMIF('Adj. entries US'!B:B,'HARKAVA '!A35,'Adj. entries US'!E:E) -> 0 | K35: =H35+I35-J35 -> 0 | M35: =SUMIF('TB UK'!A:A,'HARKAVA '!A35,'TB UK'!E:E) -> -233604.76 | N35: =SUMIF('Adj. Entries UK'!B:B,'HARKAVA '!A35,'Adj. Entries UK'!D:D) -> 0 | O35: =SUMIF('Adj. Entries UK'!B:B,'HARKAVA '!A35,'Adj. Entries UK'!E:E) -> 0 | P35: =M35+N35-O35 -> -233604.76 | R35: =SUMIF('TB security'!A:A,'HARKAVA '!A35,'TB security'!D:D) -> -287579 | S35: =SUMIF('Adj. Entries security'!B:B,'HARKAVA '!A35,'Adj. Entries security'!D:D) -> 0 | T35: =SUMIF('Adj. Entries security'!B:B,'HARKAVA '!A35,'Adj. Entries security'!E:E) -> 0 | U35: =R35+S35-T35 -> -287579 | V35: =P35+F35+U35+K35 -> -1529790.9 | Y35: =V35+X35 -> -1529790.9 | Z35: =LEFT(A35,2) -> 36 | AD35: -1008607.2 | AF35: 0 | AG35: 0 | AH35: 0 | AI35: 0 | AK35: -233604.76 | AL35: 0 | AM35: 0 | AN35: -233604.76 | AP35: -287579 | AQ35: 0 | AR35: 0 | AS35: -287579 | AT35: -1529790.9 | AW35: -1529790.9 | AY35: =F35-AD35 -> 0 | AZ35: =P35-AN35 -> 0 | BA35: =U35-AS35 -> 0 | BB35: =X35-AV35 -> 0
A36: 3650 | B36: AP- VAT | C36: =SUMIF('TB Mitiga LTD'!A:A,'HARKAVA '!A36,'TB Mitiga LTD'!D:D) -> 0 | D36: =SUMIF('Adj Entries Ltd'!$B$4:$B$954,A36,'Adj Entries Ltd'!$D$4:$D$954) -> 0 | E36: =SUMIF('Adj Entries Ltd'!$B$4:$B$954,A36,'Adj Entries Ltd'!$E$4:$E$954) -> 0 | F36: =(+C36+D36-E36) -> 0 | H36: =SUMIF('TB US'!A:A,'HARKAVA '!A36,'TB US'!D:D) -> 0 | I36: =SUMIF('Adj. entries US'!B:B,'HARKAVA '!A36,'Adj. entries US'!D:D) -> 0 | J36: =SUMIF('Adj. entries US'!B:B,'HARKAVA '!A36,'Adj. entries US'!E:E) -> 0 | K36: =H36+I36-J36 -> 0 | M36: =SUMIF('TB UK'!A:A,'HARKAVA '!A36,'TB UK'!E:E) -> -7196.95 | N36: =SUMIF('Adj. Entries UK'!B:B,'HARKAVA '!A36,'Adj. Entries UK'!D:D) -> 0 | O36: =SUMIF('Adj. Entries UK'!B:B,'HARKAVA '!A36,'Adj. Entries UK'!E:E) -> 0 | P36: =M36+N36-O36 -> -7196.95 | R36: =SUMIF('TB security'!A:A,'HARKAVA '!A36,'TB security'!D:D) -> 0 | S36: =SUMIF('Adj. Entries security'!B:B,'HARKAVA '!A36,'Adj. Entries security'!D:D) -> 0 | T36: =SUMIF('Adj. Entries security'!B:B,'HARKAVA '!A36,'Adj. Entries security'!E:E) -> 0 | U36: =R36+S36-T36 -> 0 | V36: =P36+F36+U36+K36 -> -7196.95 | Y36: =V36+X36 -> -7196.95 | Z36: 36 | AD36: 0 | AF36: 0 | AG36: 0 | AH36: 0 | AI36: 0 | AK36: -7196.95 | AL36: 0 | AM36: 0 | AN36: -7196.95 | AP36: 0 | AQ36: 0 | AR36: 0 | AS36: 0 | AT36: -7196.95 | AW36: -7196.95 | AY36: =F36-AD36 -> 0 | AZ36: =P36-AN36 -> 0 | BA36: =U36-AS36 -> 0 | BB36: =X36-AV36 -> 0
A37: 3800 | B37: Deferred income | C37: =SUMIF('TB Mitiga LTD'!A:A,'HARKAVA '!A37,'TB Mitiga LTD'!D:D) -> -53416 | D37: =SUMIF('Adj Entries Ltd'!$B$4:$B$954,A37,'Adj Entries Ltd'!$D$4:$D$954) -> 0 | E37: =SUMIF('Adj Entries Ltd'!$B$4:$B$954,A37,'Adj Entries Ltd'!$E$4:$E$954) -> 0 | F37: =(+C37+D37-E37) -> -53416 | H37: =SUMIF('TB US'!A:A,'HARKAVA '!A37,'TB US'!D:D) -> 0 | I37: =SUMIF('Adj. entries US'!B:B,'HARKAVA '!A37,'Adj. entries US'!D:D) -> 0 | J37: =SUMIF('Adj. entries US'!B:B,'HARKAVA '!A37,'Adj. entries US'!E:E) -> 0 | K37: =H37+I37-J37 -> 0 | M37: =SUMIF('TB UK'!A:A,'HARKAVA '!A37,'TB UK'!E:E) -> -123540 | N37: =SUMIF('Adj. Entries UK'!B:B,'HARKAVA '!A37,'Adj. Entries UK'!D:D) -> 0 | O37: =SUMIF('Adj. Entries UK'!B:B,'HARKAVA '!A37,'Adj. Entries UK'!E:E) -> 0 | P37: =M37+N37-O37 -> -123540 | R37: =SUMIF('TB security'!A:A,'HARKAVA '!A37,'TB security'!D:D) -> -376253 | S37: =SUMIF('Adj. Entries security'!B:B,'HARKAVA '!A37,'Adj. Entries security'!D:D) -> 0 | T37: =SUMIF('Adj. Entries security'!B:B,'HARKAVA '!A37,'Adj. Entries security'!E:E) -> 0 | U37: =R37+S37-T37 -> -376253 | V37: =P37+F37+U37+K37 -> -553209 | Y37: =V37+X37 -> -553209 | Z37: 38 | AD37: -53416 | AF37: 0 | AG37: 0 | AH37: 0 | AI37: 0 | AK37: 0 | AL37: 0 | AM37: 0 | AN37: 0 | AP37: -376253 | AQ37: 0 | AR37: 0 | AS37: -376253 | AT37: -429669 | AV37: -372917 | AW37: -802586 | AY37: =F37-AD37 -> 0 | AZ37: =P37-AN37 -> -123540 | BA37: =U37-AS37 -> 0 | BB37: =X37-AV37 -> 372917 | BC37: Pushed any GUS revenue that was recorded initially from April 2021 to March 2022
A38: 3900 | B38: Related parties | C38: =SUMIF('TB Mitiga LTD'!A:A,'HARKAVA '!A38,'TB Mitiga LTD'!D:D) -> 23616.2 | D38: =SUMIF('Adj Entries Ltd'!$B$4:$B$954,A38,'Adj Entries Ltd'!$D$4:$D$954) -> 0 | E38: =SUMIF('Adj Entries Ltd'!$B$4:$B$954,A38,'Adj Entries Ltd'!$E$4:$E$954) -> 25401.929 | F38: =(+C38+D38-E38) -> -1785.7293 | H38: =SUMIF('TB US'!A:A,'HARKAVA '!A38,'TB US'!D:D) -> 0 | I38: =SUMIF('Adj. entries US'!B:B,'HARKAVA '!A38,'Adj. entries US'!D:D) -> 0 | J38: =SUMIF('Adj. entries US'!B:B,'HARKAVA '!A38,'Adj. entries US'!E:E) -> 0 | K38: =H38+I38-J38 -> 0 | M38: =SUMIF('TB UK'!A:A,'HARKAVA '!A38,'TB UK'!E:E) -> -12422.61 | N38: =SUMIF('Adj. Entries UK'!B:B,'HARKAVA '!A38,'Adj. Entries UK'!D:D) -> 0 | O38: =SUMIF('Adj. Entries UK'!B:B,'HARKAVA '!A38,'Adj. Entries UK'!E:E) -> 0 | P38: =M38+N38-O38 -> -12422.61 | R38: =SUMIF('TB security'!A:A,'HARKAVA '!A38,'TB security'!D:D) -> 0 | S38: =SUMIF('Adj. Entries security'!B:B,'HARKAVA '!A38,'Adj. Entries security'!D:D) -> 0 | T38: =SUMIF('Adj. Entries security'!B:B,'HARKAVA '!A38,'Adj. Entries security'!E:E) -> 0 | U38: =R38+S38-T38 -> 0 | V38: =P38+F38+U38+K38 -> -14208.339 | Y38: =V38+X38 -> -14208.339 | Z38: 36 | AD38: -1785.7293 | AF38: 0 | AG38: 0 | AH38: 0 | AI38: 0 | AK38: -12422.61 | AL38: 0 | AM38: 0 | AN38: -12422.61 | AP38: 0 | AQ38: 0 | AR38: 0 | AS38: 0 | AT38: -14208.339 | AW38: -14208.339 | AY38: =F38-AD38 -> 0 | AZ38: =P38-AN38 -> 0 | BA38: =U38-AS38 -> 0 | BB38: =X38-AV38 -> 0
A39: 3910 | B39: Accrued expenses | C39: =SUMIF('TB Mitiga LTD'!A:A,'HARKAVA '!A39,'TB Mitiga LTD'!D:D) -> -148353.23 | D39: =SUMIF('Adj Entries Ltd'!$B$4:$B$954,A39,'Adj Entries Ltd'!$D$4:$D$954) -> 27483.923 | E39: =SUMIF('Adj Entries Ltd'!$B$4:$B$954,A39,'Adj Entries Ltd'!$E$4:$E$954) -> 0 | F39: =(+C39+D39-E39) -> -120869.31 | H39: =SUMIF('TB US'!A:A,'HARKAVA '!A39,'TB US'!D:D) -> 0 | I39: =SUMIF('Adj. entries US'!B:B,'HARKAVA '!A39,'Adj. entries US'!D:D) -> 0 | J39: =SUMIF('Adj. entries US'!B:B,'HARKAVA '!A39,'Adj. entries US'!E:E) -> 0 | K39: =H39+I39-J39 -> 0 | M39: =SUMIF('TB UK'!A:A,'HARKAVA '!A39,'TB UK'!E:E) -> -1935.99 | N39: =SUMIF('Adj. Entries UK'!B:B,'HARKAVA '!A39,'Adj. Entries UK'!D:D) -> 0 | O39: =SUMIF('Adj. Entries UK'!B:B,'HARKAVA '!A39,'Adj. Entries UK'!E:E) -> 0 | P39: =M39+N39-O39 -> -1935.99 | R39: =SUMIF('TB security'!A:A,'HARKAVA '!A39,'TB security'!D:D) -> -77992.19 | S39: =SUMIF('Adj. Entries security'!B:B,'HARKAVA '!A39,'Adj. Entries security'!D:D) -> 0 | T39: =SUMIF('Adj. Entries security'!B:B,'HARKAVA '!A39,'Adj. Entries security'!E:E) -> 0 | U39: =R39+S39-T39 -> -77992.19 | V39: =P39+F39+U39+K39 -> -200797.49 | Y39: =V39+X39 -> -200797.49 | Z39: 36 | AD39: -120869.31 | AF39: 0 | AG39: 0 | AH39: 0 | AI39: 0 | AK39: -1935.99 | AL39: 0 | AM39: 0 | AN39: -1935.99 | AP39: -52792.19 | AQ39: 0 | AR39: 0 | AS39: -52792.19 | AT39: -175597.49 | AW39: -175597.49 | AY39: =F39-AD39 -> 0 | AZ39: =P39-AN39 -> 0 | BA39: =U39-AS39 -> -25200 | BB39: =X39-AV39 -> 0 | BC39: Accrual recorded for 2021 Delaware franchise tax that was paid in March 2022
A40: 3915 | B40: Leasehold liablities - short term | C40: =SUMIF('TB Mitiga LTD'!A:A,'HARKAVA '!A40,'TB Mitiga LTD'!D:D) -> 0 | D40: =SUMIF('Adj Entries Ltd'!$B$4:$B$954,A40,'Adj Entries Ltd'!$D$4:$D$954) -> 0 | E40: =SUMIF('Adj Entries Ltd'!$B$4:$B$954,A40,'Adj Entries Ltd'!$E$4:$E$954) -> 0 | F40: =(+C40+D40-E40) -> 0 | H40: =SUMIF('TB US'!A:A,'HARKAVA '!A40,'TB US'!D:D) -> 0 | I40: =SUMIF('Adj. entries US'!B:B,'HARKAVA '!A40,'Adj. entries US'!D:D) -> 0 | J40: =SUMIF('Adj. entries US'!B:B,'HARKAVA '!A40,'Adj. entries US'!E:E) -> 0 | K40: =H40+I40-J40 -> 0 | M40: =SUMIF('TB UK'!A:A,'HARKAVA '!A40,'TB UK'!E:E) -> 0 | N40: =SUMIF('Adj. Entries UK'!B:B,'HARKAVA '!A40,'Adj. Entries UK'!D:D) -> 0 | O40: =SUMIF('Adj. Entries UK'!B:B,'HARKAVA '!A40,'Adj. Entries UK'!E:E) -> 0 | P40: =M40+N40-O40 -> 0 | R40: =SUMIF('TB security'!A:A,'HARKAVA '!A40,'TB security'!D:D) -> 0 | S40: =SUMIF('Adj. Entries security'!B:B,'HARKAVA '!A40,'Adj. Entries security'!D:D) -> 0 | T40: =SUMIF('Adj. Entries security'!B:B,'HARKAVA '!A40,'Adj. Entries security'!E:E) -> 0 | U40: =R40+S40-T40 -> 0 | V40: =P40+F40+U40+K40 -> 0 | Y40: =V40+X40 -> 0 | Z40: 40 | AD40: 0 | AF40: 0 | AG40: 0 | AH40: 0 | AI40: 0 | AK40: 0 | AL40: 0 | AM40: 0 | AN40: 0 | AP40: 0 | AQ40: 0 | AR40: 0 | AS40: 0 | AT40: 0 | AW40: 0 | AY40: =F40-AD40 -> 0 | AZ40: =P40-AN40 -> 0 | BA40: =U40-AS40 -> 0 | BB40: =X40-AV40 -> 0
A41: 3920 | B41: Other liabilities | C41: =SUMIF('TB Mitiga LTD'!A:A,'HARKAVA '!A41,'TB Mitiga LTD'!D:D) -> 0 | D41: =SUMIF('Adj Entries Ltd'!$B$4:$B$954,A41,'Adj Entries Ltd'!$D$4:$D$954) -> 0 | E41: =SUMIF('Adj Entries Ltd'!$B$4:$B$954,A41,'Adj Entries Ltd'!$E$4:$E$954) -> 0 | F41: =(+C41+D41-E41) -> 0 | H41: =SUMIF('TB US'!A:A,'HARKAVA '!A41,'TB US'!D:D) -> 0 | I41: =SUMIF('Adj. entries US'!B:B,'HARKAVA '!A41,'Adj. entries US'!D:D) -> 0 | J41: =SUMIF('Adj. entries US'!B:B,'HARKAVA '!A41,'Adj. entries US'!E:E) -> 0 | K41: =H41+I41-J41 -> 0 | M41: =SUMIF('TB UK'!A:A,'HARKAVA '!A41,'TB UK'!E:E) -> 0 | N41: =SUMIF('Adj. Entries UK'!B:B,'HARKAVA '!A41,'Adj. Entries UK'!D:D) -> 0 | O41: =SUMIF('Adj. Entries UK'!B:B,'HARKAVA '!A41,'Adj. Entries UK'!E:E) -> 0 | P41: =M41+N41-O41 -> 0 | R41: =SUMIF('TB security'!A:A,'HARKAVA '!A41,'TB security'!D:D) -> 0 | S41: =SUMIF('Adj. Entries security'!B:B,'HARKAVA '!A41,'Adj. Entries security'!D:D) -> 0 | T41: =SUMIF('Adj. Entries security'!B:B,'HARKAVA '!A41,'Adj. Entries security'!E:E) -> 0 | U41: =R41+S41-T41 -> 0 | V41: =P41+F41+U41+K41 -> 0 | Y41: =V41+X41 -> 0 | Z41: 37 | AD41: 0 | AF41: 0 | AG41: 0 | AH41: 0 | AI41: 0 | AK41: 0 | AL41: 0 | AM41: 0 | AN41: 0 | AP41: 0 | AQ41: 0 | AR41: 0 | AS41: 0 | AT41: 0 | AW41: 0 | AY41: =F41-AD41 -> 0 | AZ41: =P41-AN41 -> 0 | BA41: =U41-AS41 -> 0 | BB41: =X41-AV41 -> 0
A42: 3930 | B42: Short - term compensation | C42: =SUMIF('TB Mitiga LTD'!A:A,'HARKAVA '!A42,'TB Mitiga LTD'!D:D) -> 0 | D42: =SUMIF('Adj Entries Ltd'!$B$4:$B$954,A42,'Adj Entries Ltd'!$D$4:$D$954) -> 0 | E42: =SUMIF('Adj Entries Ltd'!$B$4:$B$954,A42,'Adj Entries Ltd'!$E$4:$E$954) -> 0 | F42: =(+C42+D42-E42) -> 0 | H42: =SUMIF('TB US'!A:A,'HARKAVA '!A42,'TB US'!D:D) -> 0 | I42: =SUMIF('Adj. entries US'!B:B,'HARKAVA '!A42,'Adj. entries US'!D:D) -> 0 | J42: =SUMIF('Adj. entries US'!B:B,'HARKAVA '!A42,'Adj. entries US'!E:E) -> 0 | K42: =H42+I42-J42 -> 0 | M42: =SUMIF('TB UK'!A:A,'HARKAVA '!A42,'TB UK'!E:E) -> 0 | N42: =SUMIF('Adj. Entries UK'!B:B,'HARKAVA '!A42,'Adj. Entries UK'!D:D) -> 0 | O42: =SUMIF('Adj. Entries UK'!B:B,'HARKAVA '!A42,'Adj. Entries UK'!E:E) -> 0 | P42: =M42+N42-O42 -> 0 | R42: =SUMIF('TB security'!A:A,'HARKAVA '!A42,'TB security'!D:D) -> 0 | S42: =SUMIF('Adj. Entries security'!B:B,'HARKAVA '!A42,'Adj. Entries security'!D:D) -> 0 | T42: =SUMIF('Adj. Entries security'!B:B,'HARKAVA '!A42,'Adj. Entries security'!E:E) -> 0 | U42: =R42+S42-T42 -> 0 | V42: =P42+F42+U42+K42 -> 0 | Y42: =V42+X42 -> 0 | Z42: 38 | AD42: 0 | AF42: 0 | AG42: 0 | AH42: 0 | AI42: 0 | AK42: 0 | AL42: 0 | AM42: 0 | AN42: 0 | AP42: 0 | AQ42: 0 | AR42: 0 | AS42: 0 | AT42: 0 | AW42: 0 | AY42: =F42-AD42 -> 0 | AZ42: =P42-AN42 -> 0 | BA42: =U42-AS42 -> 0 | BB42: =X42-AV42 -> 0
A43: 3950 | B43: Derivatives | C43: =SUMIF('TB Mitiga LTD'!A:A,'HARKAVA '!A43,'TB Mitiga LTD'!D:D) -> 0 | D43: =SUMIF('Adj Entries Ltd'!$B$4:$B$954,A43,'Adj Entries Ltd'!$D$4:$D$954) -> 0 | E43: =SUMIF('Adj Entries Ltd'!$B$4:$B$954,A43,'Adj Entries Ltd'!$E$4:$E$954) -> 0 | F43: =(+C43+D43-E43) -> 0 | H43: =SUMIF('TB US'!A:A,'HARKAVA '!A43,'TB US'!D:D) -> 0 | I43: =SUMIF('Adj. entries US'!B:B,'HARKAVA '!A43,'Adj. entries US'!D:D) -> 0 | J43: =SUMIF('Adj. entries US'!B:B,'HARKAVA '!A43,'Adj. entries US'!E:E) -> 0 | K43: =H43+I43-J43 -> 0 | M43: =SUMIF('TB UK'!A:A,'HARKAVA '!A43,'TB UK'!E:E) -> 0 | N43: =SUMIF('Adj. Entries UK'!B:B,'HARKAVA '!A43,'Adj. Entries UK'!D:D) -> 0 | O43: =SUMIF('Adj. Entries UK'!B:B,'HARKAVA '!A43,'Adj. Entries UK'!E:E) -> 0 | P43: =M43+N43-O43 -> 0 | R43: =SUMIF('TB security'!A:A,'HARKAVA '!A43,'TB security'!D:D) -> 0 | S43: =SUMIF('Adj. Entries security'!B:B,'HARKAVA '!A43,'Adj. Entries security'!D:D) -> 0 | T43: =SUMIF('Adj. Entries security'!B:B,'HARKAVA '!A43,'Adj. Entries security'!E:E) -> 0 | U43: =R43+S43-T43 -> 0 | V43: =P43+F43+U43+K43 -> 0 | Y43: =V43+X43 -> 0 | Z43: 39 | AD43: 0 | AF43: 0 | AG43: 0 | AH43: 0 | AI43: 0 | AK43: 0 | AL43: 0 | AM43: 0 | AN43: 0 | AP43: 0 | AQ43: 0 | AR43: 0 | AS43: 0 | AT43: 0 | AW43: 0 | AY43: =F43-AD43 -> 0 | AZ43: =P43-AN43 -> 0 | BA43: =U43-AS43 -> 0 | BB43: =X43-AV43 -> 0
A44: 4200 | B44: Long term liabilities | C44: =SUMIF('TB Mitiga LTD'!A:A,'HARKAVA '!A44,'TB Mitiga LTD'!D:D) -> 0 | D44: =SUMIF('Adj Entries Ltd'!$B$4:$B$954,A44,'Adj Entries Ltd'!$D$4:$D$954) -> 0 | E44: =SUMIF('Adj Entries Ltd'!$B$4:$B$954,A44,'Adj Entries Ltd'!$E$4:$E$954) -> 0 | F44: =(+C44+D44-E44) -> 0 | H44: =SUMIF('TB US'!A:A,'HARKAVA '!A44,'TB US'!D:D) -> 0 | I44: =SUMIF('Adj. entries US'!B:B,'HARKAVA '!A44,'Adj. entries US'!D:D) -> 0 | J44: =SUMIF('Adj. entries US'!B:B,'HARKAVA '!A44,'Adj. entries US'!E:E) -> 0 | K44: =H44+I44-J44 -> 0 | M44: =SUMIF('TB UK'!A:A,'HARKAVA '!A44,'TB UK'!E:E) -> 0 | N44: =SUMIF('Adj. Entries UK'!B:B,'HARKAVA '!A44,'Adj. Entries UK'!D:D) -> 0 | O44: =SUMIF('Adj. Entries UK'!B:B,'HARKAVA '!A44,'Adj. Entries UK'!E:E) -> 0 | P44: =M44+N44-O44 -> 0 | R44: =SUMIF('TB security'!A:A,'HARKAVA '!A44,'TB security'!D:D) -> 0 | S44: =SUMIF('Adj. Entries security'!B:B,'HARKAVA '!A44,'Adj. Entries security'!D:D) -> 0 | T44: =SUMIF('Adj. Entries security'!B:B,'HARKAVA '!A44,'Adj. Entries security'!E:E) -> 0 | U44: =R44+S44-T44 -> 0 | V44: =P44+F44+U44+K44 -> 0 | Y44: =V44+X44 -> 0 | Z44: =LEFT(A44,2) -> 42 | AD44: 0 | AF44: 0 | AG44: 0 | AH44: 0 | AI44: 0 | AK44: 0 | AL44: 0 | AM44: 0 | AN44: 0 | AP44: 0 | AQ44: 0 | AR44: 0 | AS44: 0 | AT44: 0 | AW44: 0 | AY44: =F44-AD44 -> 0 | AZ44: =P44-AN44 -> 0 | BA44: =U44-AS44 -> 0 | BB44: =X44-AV44 -> 0
A45: 4300 | B45: Investment in sub | C45: =SUMIF('TB Mitiga LTD'!A:A,'HARKAVA '!A45,'TB Mitiga LTD'!D:D) -> 0 | D45: =SUMIF('Adj Entries Ltd'!$B$4:$B$954,A45,'Adj Entries Ltd'!$D$4:$D$954) -> 0 | E45: =SUMIF('Adj Entries Ltd'!$B$4:$B$954,A45,'Adj Entries Ltd'!$E$4:$E$954) -> 0 | F45: =(+C45+D45-E45) -> 0 | H45: =SUMIF('TB US'!A:A,'HARKAVA '!A45,'TB US'!D:D) -> 0 | I45: =SUMIF('Adj. entries US'!B:B,'HARKAVA '!A45,'Adj. entries US'!D:D) -> 0 | J45: =SUMIF('Adj. entries US'!B:B,'HARKAVA '!A45,'Adj. entries US'!E:E) -> 0 | K45: =H45+I45-J45 -> 0 | M45: =SUMIF('TB UK'!A:A,'HARKAVA '!A45,'TB UK'!E:E) -> 0 | N45: =SUMIF('Adj. Entries UK'!B:B,'HARKAVA '!A45,'Adj. Entries UK'!D:D) -> 0 | O45: =SUMIF('Adj. Entries UK'!B:B,'HARKAVA '!A45,'Adj. Entries UK'!E:E) -> 0 | P45: =M45+N45-O45 -> 0 | R45: =SUMIF('TB security'!A:A,'HARKAVA '!A45,'TB security'!D:D) -> 0 | S45: =SUMIF('Adj. Entries security'!B:B,'HARKAVA '!A45,'Adj. Entries security'!D:D) -> 0 | T45: =SUMIF('Adj. Entries security'!B:B,'HARKAVA '!A45,'Adj. Entries security'!E:E) -> 0 | U45: =R45+S45-T45 -> 0 | V45: =P45+F45+U45+K45 -> 0 | Y45: =V45+X45 -> 0 | Z45: =LEFT(A45,2) -> 43 | AD45: 0 | AF45: 0 | AG45: 0 | AH45: 0 | AI45: 0 | AK45: 0 | AL45: 0 | AM45: 0 | AN45: 0 | AP45: 0 | AQ45: 0 | AR45: 0 | AS45: 0 | AT45: 0 | AW45: 0 | AY45: =F45-AD45 -> 0 | AZ45: =P45-AN45 -> 0 | BA45: =U45-AS45 -> 0 | BB45: =X45-AV45 -> 0
A46: 4400 | B46: Loans from related parties | C46: =SUMIF('TB Mitiga LTD'!A:A,'HARKAVA '!A46,'TB Mitiga LTD'!D:D) -> 0 | D46: =SUMIF('Adj Entries Ltd'!$B$4:$B$954,A46,'Adj Entries Ltd'!$D$4:$D$954) -> 0 | E46: =SUMIF('Adj Entries Ltd'!$B$4:$B$954,A46,'Adj Entries Ltd'!$E$4:$E$954) -> 0 | F46: =(+C46+D46-E46) -> 0 | H46: =SUMIF('TB US'!A:A,'HARKAVA '!A46,'TB US'!D:D) -> 0 | I46: =SUMIF('Adj. entries US'!B:B,'HARKAVA '!A46,'Adj. entries US'!D:D) -> 0 | J46: =SUMIF('Adj. entries US'!B:B,'HARKAVA '!A46,'Adj. entries US'!E:E) -> 0 | K46: =H46+I46-J46 -> 0 | M46: =SUMIF('TB UK'!A:A,'HARKAVA '!A46,'TB UK'!E:E) -> 0 | N46: =SUMIF('Adj. Entries UK'!B:B,'HARKAVA '!A46,'Adj. Entries UK'!D:D) -> 0 | O46: =SUMIF('Adj. Entries UK'!B:B,'HARKAVA '!A46,'Adj. Entries UK'!E:E) -> 0 | P46: =M46+N46-O46 -> 0 | R46: =SUMIF('TB security'!A:A,'HARKAVA '!A46,'TB security'!D:D) -> 0 | S46: =SUMIF('Adj. Entries security'!B:B,'HARKAVA '!A46,'Adj. Entries security'!D:D) -> 0 | T46: =SUMIF('Adj. Entries security'!B:B,'HARKAVA '!A46,'Adj. Entries security'!E:E) -> 0 | U46: =R46+S46-T46 -> 0 | V46: =P46+F46+U46+K46 -> 0 | Y46: =V46+X46 -> 0 | Z46: =LEFT(A46,2) -> 44 | AD46: 0 | AF46: 0 | AG46: 0 | AH46: 0 | AI46: 0 | AK46: 0 | AL46: 0 | AM46: 0 | AN46: 0 | AP46: 0 | AQ46: 0 | AR46: 0 | AS46: 0 | AT46: 0 | AW46: 0 | AY46: =F46-AD46 -> 0 | AZ46: =P46-AN46 -> 0 | BA46: =U46-AS46 -> 0 | BB46: =X46-AV46 -> 0
A47: 4450 | B47: Loans from others | C47: =SUMIF('TB Mitiga LTD'!A:A,'HARKAVA '!A47,'TB Mitiga LTD'!D:D) -> 0 | D47: =SUMIF('Adj Entries Ltd'!$B$4:$B$954,A47,'Adj Entries Ltd'!$D$4:$D$954) -> 0 | E47: =SUMIF('Adj Entries Ltd'!$B$4:$B$954,A47,'Adj Entries Ltd'!$E$4:$E$954) -> 0 | F47: =(+C47+D47-E47) -> 0 | H47: =SUMIF('TB US'!A:A,'HARKAVA '!A47,'TB US'!D:D) -> 0 | I47: =SUMIF('Adj. entries US'!B:B,'HARKAVA '!A47,'Adj. entries US'!D:D) -> 0 | J47: =SUMIF('Adj. entries US'!B:B,'HARKAVA '!A47,'Adj. entries US'!E:E) -> 0 | K47: =H47+I47-J47 -> 0 | M47: =SUMIF('TB UK'!A:A,'HARKAVA '!A47,'TB UK'!E:E) -> 0 | N47: =SUMIF('Adj. Entries UK'!B:B,'HARKAVA '!A47,'Adj. Entries UK'!D:D) -> 0 | O47: =SUMIF('Adj. Entries UK'!B:B,'HARKAVA '!A47,'Adj. Entries UK'!E:E) -> 0 | P47: =M47+N47-O47 -> 0 | R47: =SUMIF('TB security'!A:A,'HARKAVA '!A47,'TB security'!D:D) -> 0 | S47: =SUMIF('Adj. Entries security'!B:B,'HARKAVA '!A47,'Adj. Entries security'!D:D) -> 0 | T47: =SUMIF('Adj. Entries security'!B:B,'HARKAVA '!A47,'Adj. Entries security'!E:E) -> 0 | U47: =R47+S47-T47 -> 0 | V47: =P47+F47+U47+K47 -> 0 | Y47: =V47+X47 -> 0 | Z47: =LEFT(A47,2) -> 44 | AD47: 0 | AF47: 0 | AG47: 0 | AH47: 0 | AI47: 0 | AK47: 0 | AL47: 0 | AM47: 0 | AN47: 0 | AP47: 0 | AQ47: 0 | AR47: 0 | AS47: 0 | AT47: 0 | AW47: 0 | AY47: =F47-AD47 -> 0 | AZ47: =P47-AN47 -> 0 | BA47: =U47-AS47 -> 0 | BB47: =X47-AV47 -> 0
A48: 4500 | B48: Liability for employee severance benefits, net | C48: =SUMIF('TB Mitiga LTD'!A:A,'HARKAVA '!A48,'TB Mitiga LTD'!D:D) -> 0 | D48: =SUMIF('Adj Entries Ltd'!$B$4:$B$954,A48,'Adj Entries Ltd'!$D$4:$D$954) -> 0 | E48: =SUMIF('Adj Entries Ltd'!$B$4:$B$954,A48,'Adj Entries Ltd'!$E$4:$E$954) -> 0 | F48: =(+C48+D48-E48) -> 0 | H48: =SUMIF('TB US'!A:A,'HARKAVA '!A48,'TB US'!D:D) -> 0 | I48: =SUMIF('Adj. entries US'!B:B,'HARKAVA '!A48,'Adj. entries US'!D:D) -> 0 | J48: =SUMIF('Adj. entries US'!B:B,'HARKAVA '!A48,'Adj. entries US'!E:E) -> 0 | K48: =H48+I48-J48 -> 0 | M48: =SUMIF('TB UK'!A:A,'HARKAVA '!A48,'TB UK'!E:E) -> 0 | N48: =SUMIF('Adj. Entries UK'!B:B,'HARKAVA '!A48,'Adj. Entries UK'!D:D) -> 0 | O48: =SUMIF('Adj. Entries UK'!B:B,'HARKAVA '!A48,'Adj. Entries UK'!E:E) -> 0 | P48: =M48+N48-O48 -> 0 | R48: =SUMIF('TB security'!A:A,'HARKAVA '!A48,'TB security'!D:D) -> 0 | S48: =SUMIF('Adj. Entries security'!B:B,'HARKAVA '!A48,'Adj. Entries security'!D:D) -> 0 | T48: =SUMIF('Adj. Entries security'!B:B,'HARKAVA '!A48,'Adj. Entries security'!E:E) -> 0 | U48: =R48+S48-T48 -> 0 | V48: =P48+F48+U48+K48 -> 0 | Y48: =V48+X48 -> 0 | Z48: =LEFT(A48,2) -> 45 | AD48: 0 | AF48: 0 | AG48: 0 | AH48: 0 | AI48: 0 | AK48: 0 | AL48: 0 | AM48: 0 | AN48: 0 | AP48: 0 | AQ48: 0 | AR48: 0 | AS48: 0 | AT48: 0 | AW48: 0 | AY48: =F48-AD48 -> 0 | AZ48: =P48-AN48 -> 0 | BA48: =U48-AS48 -> 0 | BB48: =X48-AV48 -> 0
A49: 4600 | B49: Leasehold liablities | C49: =SUMIF('TB Mitiga LTD'!A:A,'HARKAVA '!A49,'TB Mitiga LTD'!D:D) -> -794855.31 | D49: =SUMIF('Adj Entries Ltd'!$B$4:$B$954,A49,'Adj Entries Ltd'!$D$4:$D$954) -> 0 | E49: =SUMIF('Adj Entries Ltd'!$B$4:$B$954,A49,'Adj Entries Ltd'!$E$4:$E$954) -> 0 | F49: =(+C49+D49-E49) -> -794855.31 | H49: =SUMIF('TB US'!A:A,'HARKAVA '!A49,'TB US'!D:D) -> 0 | I49: =SUMIF('Adj. entries US'!B:B,'HARKAVA '!A49,'Adj. entries US'!D:D) -> 0 | J49: =SUMIF('Adj. entries US'!B:B,'HARKAVA '!A49,'Adj. entries US'!E:E) -> 0 | K49: =H49+I49-J49 -> 0 | M49: =SUMIF('TB UK'!A:A,'HARKAVA '!A49,'TB UK'!E:E) -> 0 | N49: =SUMIF('Adj. Entries UK'!B:B,'HARKAVA '!A49,'Adj. Entries UK'!D:D) -> 0 | O49: =SUMIF('Adj. Entries UK'!B:B,'HARKAVA '!A49,'Adj. Entries UK'!E:E) -> 0 | P49: =M49+N49-O49 -> 0 | R49: =SUMIF('TB security'!A:A,'HARKAVA '!A49,'TB security'!D:D) -> 0 | S49: =SUMIF('Adj. Entries security'!B:B,'HARKAVA '!A49,'Adj. Entries security'!D:D) -> 0 | T49: =SUMIF('Adj. Entries security'!B:B,'HARKAVA '!A49,'Adj. Entries security'!E:E) -> 0 | U49: =R49+S49-T49 -> 0 | V49: =P49+F49+U49+K49 -> -794855.31 | Y49: =V49+X49 -> -794855.31 | Z49: =LEFT(A49,2) -> 46 | AD49: -794855.31 | AF49: 0 | AG49: 0 | AH49: 0 | AI49: 0 | AK49: 0 | AL49: 0 | AM49: 0 | AN49: 0 | AP49: 0 | AQ49: 0 | AR49: 0 | AS49: 0 | AT49: -794855.31 | AW49: -794855.31 | AY49: =F49-AD49 -> 0 | AZ49: =P49-AN49 -> 0 | BA49: =U49-AS49 -> 0 | BB49: =X49-AV49 -> 0
A50: 4900 | B50: Premium on shares | C50: =SUMIF('TB Mitiga LTD'!A:A,'HARKAVA '!A50,'TB Mitiga LTD'!D:D) -> -7414943.1 | D50: =SUMIF('Adj Entries Ltd'!$B$4:$B$954,A50,'Adj Entries Ltd'!$D$4:$D$954) -> 0 | E50: =SUMIF('Adj Entries Ltd'!$B$4:$B$954,A50,'Adj Entries Ltd'!$E$4:$E$954) -> 34894.91 | F50: =(+C50+D50-E50) -> -7449838 | H50: =SUMIF('TB US'!A:A,'HARKAVA '!A50,'TB US'!D:D) -> 0 | I50: =SUMIF('Adj. entries US'!B:B,'HARKAVA '!A50,'Adj. entries US'!D:D) -> 0 | J50: =SUMIF('Adj. entries US'!B:B,'HARKAVA '!A50,'Adj. entries US'!E:E) -> 0 | K50: =H50+I50-J50 -> 0 | M50: =SUMIF('TB UK'!A:A,'HARKAVA '!A50,'TB UK'!E:E) -> -129.64 | N50: =SUMIF('Adj. Entries UK'!B:B,'HARKAVA '!A50,'Adj. Entries UK'!D:D) -> 0 | O50: =SUMIF('Adj. Entries UK'!B:B,'HARKAVA '!A50,'Adj. Entries UK'!E:E) -> 0 | P50: =M50+N50-O50 -> -129.64 | R50: =SUMIF('TB security'!A:A,'HARKAVA '!A50,'TB security'!D:D) -> -25015508 | S50: =SUMIF('Adj. Entries security'!B:B,'HARKAVA '!A50,'Adj. Entries security'!D:D) -> 0 | T50: =SUMIF('Adj. Entries security'!B:B,'HARKAVA '!A50,'Adj. Entries security'!E:E) -> 0 | U50: =R50+S50-T50 -> -25015508 | V50: =P50+F50+U50+K50 -> -32465475 | X50: =-X24 -> 449.64 | Y50: =V50+X50 -> -32465026 | Z50: 49 | AD50: -7414943.1 | AF50: 0 | AG50: 0 | AH50: 0 | AI50: 0 | AK50: -129.64 | AL50: 0 | AM50: 0 | AN50: -129.64 | AP50: -25015508 | AQ50: 0 | AR50: 0 | AS50: -25015508 | AT50: -32430580 | AV50: 449.64 | AW50: -32430131 | AY50: =F50-AD50 -> -34894.91 | AZ50: =P50-AN50 -> 0 | BA50: =U50-AS50 -> 0 | BB50: =X50-AV50 -> 0
A51: 5100 | B51: Share based payments | C51: =SUMIF('TB Mitiga LTD'!A:A,'HARKAVA '!A51,'TB Mitiga LTD'!D:D) -> -56651 | D51: =SUMIF('Adj Entries Ltd'!$B$4:$B$954,A51,'Adj Entries Ltd'!$D$4:$D$954) -> 0 | E51: =SUMIF('Adj Entries Ltd'!$B$4:$B$954,A51,'Adj Entries Ltd'!$E$4:$E$954) -> 27746.948 | F51: =(+C51+D51-E51) -> -84397.948 | H51: =SUMIF('TB US'!A:A,'HARKAVA '!A51,'TB US'!D:D) -> 0 | I51: =SUMIF('Adj. entries US'!B:B,'HARKAVA '!A51,'Adj. entries US'!D:D) -> 0 | J51: =SUMIF('Adj. entries US'!B:B,'HARKAVA '!A51,'Adj. entries US'!E:E) -> 0 | K51: =H51+I51-J51 -> 0 | M51: =SUMIF('TB UK'!A:A,'HARKAVA '!A51,'TB UK'!E:E) -> 0 | N51: =SUMIF('Adj. Entries UK'!B:B,'HARKAVA '!A51,'Adj. Entries UK'!D:D) -> 0 | O51: =SUMIF('Adj. Entries UK'!B:B,'HARKAVA '!A51,'Adj. Entries UK'!E:E) -> 8351.7454 | P51: =M51+N51-O51 -> -8351.7454 | R51: =SUMIF('TB security'!A:A,'HARKAVA '!A51,'TB security'!D:D) -> -5338 | S51: =SUMIF('Adj. Entries security'!B:B,'HARKAVA '!A51,'Adj. Entries security'!D:D) -> 0 | T51: =SUMIF('Adj. Entries security'!B:B,'HARKAVA '!A51,'Adj. Entries security'!E:E) -> 6332.9131 | U51: =R51+S51-T51 -> -11670.913 | V51: =P51+F51+U51+K51 -> -104420.61 | Y51: =V51+X51 -> -104420.61 | Z51: 49.5 | AD51: -95274 | AF51: 0 | AG51: 0 | AH51: 0 | AI51: 0 | AK51: 0 | AL51: 0 | AM51: 13073 | AN51: -13073 | AP51: -5338 | AQ51: 0 | AR51: 8518 | AS51: -13856 | AT51: -122203 | AW51: -122203 | AY51: =F51-AD51 -> 10876.052 | AZ51: =P51-AN51 -> 4721.2546 | BA51: =U51-AS51 -> 2185.0869 | BB51: =X51-AV51 -> 0 | BC51: Adjustments made for the SBC expense for employee that left during 2021
A52: 5101 | B52: Receipts on account of warrants | C52: =SUMIF('TB Mitiga LTD'!A:A,'HARKAVA '!A52,'TB Mitiga LTD'!D:D) -> 0 | D52: =SUMIF('Adj Entries Ltd'!$B$4:$B$954,A52,'Adj Entries Ltd'!$D$4:$D$954) -> 0 | E52: =SUMIF('Adj Entries Ltd'!$B$4:$B$954,A52,'Adj Entries Ltd'!$E$4:$E$954) -> 0 | F52: =(+C52+D52-E52) -> 0 | H52: =SUMIF('TB US'!A:A,'HARKAVA '!A52,'TB US'!D:D) -> 0 | I52: =SUMIF('Adj. entries US'!B:B,'HARKAVA '!A52,'Adj. entries US'!D:D) -> 0 | J52: =SUMIF('Adj. entries US'!B:B,'HARKAVA '!A52,'Adj. entries US'!E:E) -> 0 | K52: =H52+I52-J52 -> 0 | M52: =SUMIF('TB UK'!A:A,'HARKAVA '!A52,'TB UK'!E:E) -> 0 | N52: =SUMIF('Adj. Entries UK'!B:B,'HARKAVA '!A52,'Adj. Entries UK'!D:D) -> 0 | O52: =SUMIF('Adj. Entries UK'!B:B,'HARKAVA '!A52,'Adj. Entries UK'!E:E) -> 0 | P52: =M52+N52-O52 -> 0 | R52: =SUMIF('TB security'!A:A,'HARKAVA '!A52,'TB security'!D:D) -> 0 | S52: =SUMIF('Adj. Entries security'!B:B,'HARKAVA '!A52,'Adj. Entries security'!D:D) -> 0 | T52: =SUMIF('Adj. Entries security'!B:B,'HARKAVA '!A52,'Adj. Entries security'!E:E) -> 0 | U52: =R52+S52-T52 -> 0 | V52: =P52+F52+U52+K52 -> 0 | Y52: =V52+X52 -> 0 | Z52: 50 | AD52: 0 | AF52: 0 | AG52: 0 | AH52: 0 | AI52: 0 | AK52: 0 | AL52: 0 | AM52: 0 | AN52: 0 | AP52: 0 | AQ52: 0 | AR52: 0 | AS52: 0 | AT52: 0 | AW52: 0 | AY52: =F52-AD52 -> 0 | AZ52: =P52-AN52 -> 0 | BA52: =U52-AS52 -> 0 | BB52: =X52-AV52 -> 0
A53: 5103 | B53: Capital reserves | C53: =SUMIF('TB Mitiga LTD'!A:A,'HARKAVA '!A53,'TB Mitiga LTD'!D:D) -> 0 | D53: =SUMIF('Adj Entries Ltd'!$B$4:$B$954,A53,'Adj Entries Ltd'!$D$4:$D$954) -> 0 | E53: =SUMIF('Adj Entries Ltd'!$B$4:$B$954,A53,'Adj Entries Ltd'!$E$4:$E$954) -> 0 | F53: =(+C53+D53-E53) -> 0 | H53: =SUMIF('TB US'!A:A,'HARKAVA '!A53,'TB US'!D:D) -> 0 | I53: =SUMIF('Adj. entries US'!B:B,'HARKAVA '!A53,'Adj. entries US'!D:D) -> 0 | J53: =SUMIF('Adj. entries US'!B:B,'HARKAVA '!A53,'Adj. entries US'!E:E) -> 0 | K53: =H53+I53-J53 -> 0 | M53: =SUMIF('TB UK'!A:A,'HARKAVA '!A53,'TB UK'!E:E) -> 0 | N53: =SUMIF('Adj. Entries UK'!B:B,'HARKAVA '!A53,'Adj. Entries UK'!D:D) -> 0 | O53: =SUMIF('Adj. Entries UK'!B:B,'HARKAVA '!A53,'Adj. Entries UK'!E:E) -> 0 | P53: =M53+N53-O53 -> 0 | R53: =SUMIF('TB security'!A:A,'HARKAVA '!A53,'TB security'!D:D) -> 0 | S53: =SUMIF('Adj. Entries security'!B:B,'HARKAVA '!A53,'Adj. Entries security'!D:D) -> 0 | T53: =SUMIF('Adj. Entries security'!B:B,'HARKAVA '!A53,'Adj. Entries security'!E:E) -> 0 | U53: =R53+S53-T53 -> 0 | V53: =P53+F53+U53+K53 -> 0 | Y53: =V53+X53 -> 0 | Z53: 50.5 | AD53: 0 | AF53: 0 | AG53: 0 | AH53: 0 | AI53: 0 | AK53: 0 | AL53: 0 | AM53: 0 | AN53: 0 | AP53: 0 | AQ53: 0 | AR53: 0 | AS53: 0 | AT53: 0 | AW53: 0 | AY53: =F53-AD53 -> 0 | AZ53: =P53-AN53 -> 0 | BA53: =U53-AS53 -> 0 | BB53: =X53-AV53 -> 0
A54: 5105 | B54: NCI | C54: =SUMIF('TB Mitiga LTD'!A:A,'HARKAVA '!A54,'TB Mitiga LTD'!D:D) -> 0 | D54: =SUMIF('Adj Entries Ltd'!$B$4:$B$954,A54,'Adj Entries Ltd'!$D$4:$D$954) -> 0 | E54: =SUMIF('Adj Entries Ltd'!$B$4:$B$954,A54,'Adj Entries Ltd'!$E$4:$E$954) -> 0 | F54: =(+C54+D54-E54) -> 0 | H54: =SUMIF('TB US'!A:A,'HARKAVA '!A54,'TB US'!D:D) -> 0 | I54: =SUMIF('Adj. entries US'!B:B,'HARKAVA '!A54,'Adj. entries US'!D:D) -> 0 | J54: =SUMIF('Adj. entries US'!B:B,'HARKAVA '!A54,'Adj. entries US'!E:E) -> 0 | K54: =H54+I54-J54 -> 0 | M54: =SUMIF('TB UK'!A:A,'HARKAVA '!A54,'TB UK'!E:E) -> 0 | N54: =SUMIF('Adj. Entries UK'!B:B,'HARKAVA '!A54,'Adj. Entries UK'!D:D) -> 0 | O54: =SUMIF('Adj. Entries UK'!B:B,'HARKAVA '!A54,'Adj. Entries UK'!E:E) -> 0 | P54: =M54+N54-O54 -> 0 | R54: =SUMIF('TB security'!A:A,'HARKAVA '!A54,'TB security'!D:D) -> 0 | S54: =SUMIF('Adj. Entries security'!B:B,'HARKAVA '!A54,'Adj. Entries security'!D:D) -> 0 | T54: =SUMIF('Adj. Entries security'!B:B,'HARKAVA '!A54,'Adj. Entries security'!E:E) -> 0 | U54: =R54+S54-T54 -> 0 | V54: =P54+F54+U54+K54 -> 0 | Y54: =V54+X54 -> 0 | Z54: 50.6 | AD54: 0 | AF54: 0 | AG54: 0 | AH54: 0 | AI54: 0 | AK54: 0 | AL54: 0 | AM54: 0 | AN54: 0 | AP54: 0 | AQ54: 0 | AR54: 0 | AS54: 0 | AT54: 0 | AW54: 0 | AY54: =F54-AD54 -> 0 | AZ54: =P54-AN54 -> 0 | BA54: =U54-AS54 -> 0 | BB54: =X54-AV54 -> 0
A55: 5106 | B55: transactions with related parties | C55: =SUMIF('TB Mitiga LTD'!A:A,'HARKAVA '!A55,'TB Mitiga LTD'!D:D) -> 0 | D55: =SUMIF('Adj Entries Ltd'!$B$4:$B$954,A55,'Adj Entries Ltd'!$D$4:$D$954) -> 0 | E55: =SUMIF('Adj Entries Ltd'!$B$4:$B$954,A55,'Adj Entries Ltd'!$E$4:$E$954) -> 0 | F55: =(+C55+D55-E55) -> 0 | H55: =SUMIF('TB US'!A:A,'HARKAVA '!A55,'TB US'!D:D) -> 0 | I55: =SUMIF('Adj. entries US'!B:B,'HARKAVA '!A55,'Adj. entries US'!D:D) -> 0 | J55: =SUMIF('Adj. entries US'!B:B,'HARKAVA '!A55,'Adj. entries US'!E:E) -> 0 | K55: =H55+I55-J55 -> 0 | M55: =SUMIF('TB UK'!A:A,'HARKAVA '!A55,'TB UK'!E:E) -> 0 | N55: =SUMIF('Adj. Entries UK'!B:B,'HARKAVA '!A55,'Adj. Entries UK'!D:D) -> 0 | O55: =SUMIF('Adj. Entries UK'!B:B,'HARKAVA '!A55,'Adj. Entries UK'!E:E) -> 0 | P55: =M55+N55-O55 -> 0 | R55: =SUMIF('TB security'!A:A,'HARKAVA '!A55,'TB security'!D:D) -> 0 | S55: =SUMIF('Adj. Entries security'!B:B,'HARKAVA '!A55,'Adj. Entries security'!D:D) -> 0 | T55: =SUMIF('Adj. Entries security'!B:B,'HARKAVA '!A55,'Adj. Entries security'!E:E) -> 0 | U55: =R55+S55-T55 -> 0 | V55: =P55+F55+U55+K55 -> 0 | Y55: =V55+X55 -> 0 | Z55: 50.7 | AD55: 0 | AF55: 0 | AG55: 0 | AH55: 0 | AI55: 0 | AK55: 0 | AL55: 0 | AM55: 0 | AN55: 0 | AP55: 0 | AQ55: 0 | AR55: 0 | AS55: 0 | AT55: 0 | AW55: 0 | AY55: =F55-AD55 -> 0 | AZ55: =P55-AN55 -> 0 | BA55: =U55-AS55 -> 0 | BB55: =X55-AV55 -> 0
A56: 5107 | B56: OCI | C56: =SUMIF('TB Mitiga LTD'!A:A,'HARKAVA '!A56,'TB Mitiga LTD'!D:D) -> 0 | D56: =SUMIF('Adj Entries Ltd'!$B$4:$B$954,A56,'Adj Entries Ltd'!$D$4:$D$954) -> 0 | E56: =SUMIF('Adj Entries Ltd'!$B$4:$B$954,A56,'Adj Entries Ltd'!$E$4:$E$954) -> 0 | F56: =(+C56+D56-E56) -> 0 | H56: =SUMIF('TB US'!A:A,'HARKAVA '!A56,'TB US'!D:D) -> 0 | I56: =SUMIF('Adj. entries US'!B:B,'HARKAVA '!A56,'Adj. entries US'!D:D) -> 0 | J56: =SUMIF('Adj. entries US'!B:B,'HARKAVA '!A56,'Adj. entries US'!E:E) -> 0 | K56: =H56+I56-J56 -> 0 | M56: =SUMIF('TB UK'!A:A,'HARKAVA '!A56,'TB UK'!E:E) -> 0 | N56: =SUMIF('Adj. Entries UK'!B:B,'HARKAVA '!A56,'Adj. Entries UK'!D:D) -> 0 | O56: =SUMIF('Adj. Entries UK'!B:B,'HARKAVA '!A56,'Adj. Entries UK'!E:E) -> 0 | P56: =M56+N56-O56 -> 0 | R56: =SUMIF('TB security'!A:A,'HARKAVA '!A56,'TB security'!D:D) -> 0 | S56: =SUMIF('Adj. Entries security'!B:B,'HARKAVA '!A56,'Adj. Entries security'!D:D) -> 0 | T56: =SUMIF('Adj. Entries security'!B:B,'HARKAVA '!A56,'Adj. Entries security'!E:E) -> 0 | U56: =R56+S56-T56 -> 0 | V56: =P56+F56+U56+K56 -> 0 | Y56: =V56+X56 -> 0 | Z56: 51 | AD56: 0 | AF56: 0 | AG56: 0 | AH56: 0 | AI56: 0 | AK56: 0 | AL56: 0 | AM56: 0 | AN56: 0 | AP56: 0 | AQ56: 0 | AR56: 0 | AS56: 0 | AT56: 0 | AW56: 0 | AY56: =F56-AD56 -> 0 | AZ56: =P56-AN56 -> 0 | BA56: =U56-AS56 -> 0 | BB56: =X56-AV56 -> 0
A57: 5110 | B57: Retained earning prior years | C57: =SUMIF('TB Mitiga LTD'!A:A,'HARKAVA '!A57,'TB Mitiga LTD'!D:D) -> 3480454.6 | D57: =SUMIF('Adj Entries Ltd'!$B$4:$B$954,A57,'Adj Entries Ltd'!$D$4:$D$954) -> 0 | E57: =SUMIF('Adj Entries Ltd'!$B$4:$B$954,A57,'Adj Entries Ltd'!$E$4:$E$954) -> 0 | F57: =(+C57+D57-E57) -> 3480454.6 | H57: =SUMIF('TB US'!A:A,'HARKAVA '!A57,'TB US'!D:D) -> -1079.85 | I57: =SUMIF('Adj. entries US'!B:B,'HARKAVA '!A57,'Adj. entries US'!D:D) -> 0 | J57: =SUMIF('Adj. entries US'!B:B,'HARKAVA '!A57,'Adj. entries US'!E:E) -> 0 | K57: =H57+I57-J57 -> -1079.85 | M57: =SUMIF('TB UK'!A:A,'HARKAVA '!A57,'TB UK'!E:E) -> 73812.55 | N57: =SUMIF('Adj. Entries UK'!B:B,'HARKAVA '!A57,'Adj. Entries UK'!D:D) -> 0 | O57: =SUMIF('Adj. Entries UK'!B:B,'HARKAVA '!A57,'Adj. Entries UK'!E:E) -> 0 | P57: =M57+N57-O57 -> 73812.55 | R57: =SUMIF('TB security'!A:A,'HARKAVA '!A57,'TB security'!D:D) -> -9871.28 | S57: =SUMIF('Adj. Entries security'!B:B,'HARKAVA '!A57,'Adj. Entries security'!D:D) -> 0 | T57: =SUMIF('Adj. Entries security'!B:B,'HARKAVA '!A57,'Adj. Entries security'!E:E) -> 0 | U57: =R57+S57-T57 -> -9871.28 | V57: =P57+F57+U57+K57 -> 3543316 | Y57: =V57+X57 -> 3543316 | Z57: 51 | AD57: 3480454.6 | AF57: -1079.85 | AG57: 0 | AH57: 0 | AI57: -1079.85 | AK57: 73812.55 | AL57: 0 | AM57: 0 | AN57: 73812.55 | AP57: -9871.28 | AQ57: 0 | AR57: 0 | AS57: -9871.28 | AT57: 3543316 | AW57: 3543316 | AY57: =F57-AD57 -> 0 | AZ57: =P57-AN57 -> 0 | BA57: =U57-AS57 -> 0 | BB57: =X57-AV57 -> 0
A58: 5120 | B58: Loss (profit) for the period | C58: =C114 -> 6922963.3 | D58: =D114 -> 4689246.3 | E58: =E114 -> 1916482.4 | F58: =F114 -> 9695727.1 | H58: =H114 -> -63460.4 | I58: =I114 -> 61840 | J58: =J114 -> 0 | K58: =K114 -> -1620.4 | M58: =M114 -> 1226955.7 | N58: =N114 -> 177723.7 | O58: =O114 -> 1435014.5 | P58: =P114 -> -30335.06 | R58: =R114 -> 1435865.5 | S58: =S114 -> 819842.73 | T58: =T114 -> 2276040.8 | U58: =U114 -> -20332.557 | V58: =V114 -> 9643439.1 | X58: =X114 -> -0.475 | Y58: =Y114 -> 9643438.7 | Z58: 51 | AD58: 9487420.3 | AF58: -63460.4 | AG58: 61840 | AH58: 0 | AI58: -1620.4 | AK58: 1103415.7 | AL58: 182444.95 | AM58: 1319285 | AN58: -33424.28 | AP58: 1480915.5 | AQ58: 822027.82 | AR58: 2321520.8 | AS58: -18577.48 | AT58: 9433798.1 | AV58: 0 | AW58: 9433798.1 | AY58: =F58-AD58 -> 208306.86 | AZ58: =P58-AN58 -> 3089.2204 | BA58: =U58-AS58 -> -1755.0769 | BB58: =X58-AV58 -> -0.475
C59: =SUM(C32:C58) -> -5552403.7 | D59: =SUM(D32:D58) -> 4778570.2 | E59: =SUM(E32:E58) -> 7778570.2 | F59: =SUM(F32:F58) -> -8552403.7 | H59: =SUM(H32:H58) -> -67042.28 | I59: =SUM(I32:I58) -> 61840 | J59: =SUM(J32:J58) -> 61840 | K59: =SUM(K32:K58) -> -67042.28 | M59: =SUM(M32:M58) -> -683194.86 | N59: =SUM(N32:N58) -> 1443366.2 | O59: =SUM(O32:O58) -> 1443366.2 | P59: =SUM(P32:P58) -> -683194.86 | R59: =SUM(R32:R58) -> -14917461 | S59: =SUM(S32:S58) -> 2697288.7 | T59: =SUM(T32:T58) -> 2697288.7 | U59: =SUM(U32:U58) -> -14917461 | V59: =SUM(V32:V58) -> -24220102 | X59: =SUM(X32:X58) -> 1064743.9 | Y59: =SUM(Y32:Y58) -> -23155358 | Z59: =LEFT(A59,2) | AD59: -8622653.7 | AF59: -67042.28 | AG59: 61840 | AH59: 61840 | AI59: -67042.28 | AK59: -683194.86 | AL59: 1332358 | AM59: 1332358 | AN59: -683194.86 | AP59: -14847211 | AQ59: 2744953.8 | AR59: 2744953.8 | AS59: -14847211 | AT59: -24220102 | AV59: 648038.91 | AW59: -23572063 | AY59: =F59-AD59 -> 70250 | AZ59: =P59-AN59 -> 0 | BA59: =U59-AS59 -> -70249.99 | BB59: =X59-AV59 -> 416705
Z60: =LEFT(A60,2) | BB60: =X60-AV60 -> 0
Z61: =LEFT(A61,2) | BB61: =X61-AV61 -> 0
Z62: =LEFT(A62,2) | BB62: =X62-AV62 -> 0
A63: 5200 | B63: Sales | C63: =SUMIF('TB Mitiga LTD'!A:A,'HARKAVA '!A63,'TB Mitiga LTD'!D:D) -> -687421.09 | D63: =SUMIF('Adj Entries Ltd'!$B$4:$B$954,A63,'Adj Entries Ltd'!$D$4:$D$954) -> 0 | E63: =SUMIF('Adj Entries Ltd'!$B$4:$B$954,A63,'Adj Entries Ltd'!$E$4:$E$954) -> 0 | F63: =(+C63+D63-E63) -> -687421.09 | H63: =SUMIF('TB US'!A:A,'HARKAVA '!A63,'TB US'!D:D) -> -64800 | I63: =SUMIF('Adj. entries US'!B:B,'HARKAVA '!A63,'Adj. entries US'!D:D) -> 0 | J63: =SUMIF('Adj. entries US'!B:B,'HARKAVA '!A63,'Adj. entries US'!E:E) -> 0 | K63: =H63+I63-J63 -> -64800 | M63: =SUMIF('TB UK'!A:A,'HARKAVA '!A63,'TB UK'!E:E) -> -55512.8 | N63: =SUMIF('Adj. Entries UK'!B:B,'HARKAVA '!A63,'Adj. Entries UK'!D:D) -> 0 | O63: =SUMIF('Adj. Entries UK'!B:B,'HARKAVA '!A63,'Adj. Entries UK'!E:E) -> 0 | P63: =M63+N63-O63 -> -55512.8 | R63: =SUMIF('TB security'!A:A,'HARKAVA '!A63,'TB security'!D:D) -> -813339 | S63: =SUMIF('Adj. Entries security'!B:B,'HARKAVA '!A63,'Adj. Entries security'!D:E) -> 0 | T63: =SUMIF('Adj. Entries security'!B:B,'HARKAVA '!A63,'Adj. Entries security'!E:E) -> 0 | U63: =R63+S63-T63 -> -813339 | V63: =P63+F63+U63+K63 -> -1621072.9 | Y63: =V63+X63 -> -1621072.9 | Z63: =A63 -> 5200 | AD63: -757671.09 | AF63: -64800 | AG63: 0 | AH63: 0 | AI63: -64800 | AK63: -179052.8 | AL63: 0 | AM63: 0 | AN63: -179052.8 | AP63: -743089 | AQ63: 0 | AR63: 0 | AS63: -743089 | AT63: -1744612.9 | AW63: -1744612.9 | AY63: =F63-AD63 -> 70250 | AZ63: =P63-AN63 -> 123540 | BA63: =U63-AS63 -> -70250 | BB63: =X63-AV63 -> 0 | BC63: US+IL: Moved Income receivable/sales that was initially recorded in IL to Security (Safebreach). This is a was through I/C, so no impact in consolidation. UK: Pushed any GUS revenue that was recorded initially from April 2021 to March 2022
A64: 5201 | B64: Intercompany revenues | C64: =SUMIF('TB Mitiga LTD'!A:A,'HARKAVA '!A64,'TB Mitiga LTD'!D:D) -> 0 | D64: =SUMIF('Adj Entries Ltd'!$B$4:$B$954,A64,'Adj Entries Ltd'!$D$4:$D$954) -> 0 | E64: =SUMIF('Adj Entries Ltd'!$B$4:$B$954,A64,'Adj Entries Ltd'!$E$4:$E$954) -> 61840 | F64: =(+C64+D64-E64) -> -61840 | H64: =SUMIF('TB US'!A:A,'HARKAVA '!A64,'TB US'!D:D) -> 0 | I64: =SUMIF('Adj. entries US'!B:B,'HARKAVA '!A64,'Adj. entries US'!D:D) -> 0 | J64: =SUMIF('Adj. entries US'!B:B,'HARKAVA '!A64,'Adj. entries US'!E:E) -> 0 | K64: =H64+I64-J64 -> 0 | M64: =SUMIF('TB UK'!A:A,'HARKAVA '!A64,'TB UK'!E:E) -> 0 | N64: =SUMIF('Adj. Entries UK'!B:B,'HARKAVA '!A64,'Adj. Entries UK'!D:D) -> 0 | O64: =SUMIF('Adj. Entries UK'!B:B,'HARKAVA '!A64,'Adj. Entries UK'!E:E) -> 1265642.5 | P64: =M64+N64-O64 -> -1265642.5 | R64: =SUMIF('TB security'!A:A,'HARKAVA '!A64,'TB security'!D:D) -> 0 | S64: =SUMIF('Adj. Entries security'!B:B,'HARKAVA '!A64,'Adj. Entries security'!D:E) -> 0 | T64: =SUMIF('Adj. Entries security'!B:B,'HARKAVA '!A64,'Adj. Entries security'!E:E) -> 1877446 | U64: =R64+S64-T64 -> -1877446 | V64: =P64+F64+U64+K64 -> -3204928.5 | X64: =-V64 -> 3204928.5 | Y64: =V64+X64 -> 0 | AD64: -61840 | AF64: 0 | AG64: 0 | AH64: 0 | AI64: 0 | AK64: 0 | AL64: 0 | AM64: 1149913 | AN64: -1149913 | AP64: 0 | AQ64: 0 | AR64: 1922926 | AS64: -1922926 | AT64: -3134679 | AV64: 3134679 | AW64: 0 | AY64: =F64-AD64 -> 0 | AZ64: =P64-AN64 -> -115729.52 | BA64: =U64-AS64 -> 45480 | BB64: =X64-AV64 -> 70249.525 | BC64: See TP wp
A65: 5300 | B65: Cost of goods sold:salaries and relatedexpenses | C65: =SUMIF('TB Mitiga LTD'!A:A,'HARKAVA '!A65,'TB Mitiga LTD'!D:D) -> 1671592.2 | D65: =SUMIF('Adj Entries Ltd'!$B$4:$B$954,A65,'Adj Entries Ltd'!$D$4:$D$954) -> 0 | E65: =SUMIF('Adj Entries Ltd'!$B$4:$B$954,A65,'Adj Entries Ltd'!$E$4:$E$954) -> 1118928 | F65: =(+C65+D65-E65) -> 552664.29 | H65: =SUMIF('TB US'!A:A,'HARKAVA '!A65,'TB US'!D:D) -> 0 | I65: =SUMIF('Adj. entries US'!B:B,'HARKAVA '!A65,'Adj. entries US'!D:D) -> 0 | J65: =SUMIF('Adj. entries US'!B:B,'HARKAVA '!A65,'Adj. entries US'!E:E) -> 0 | K65: =H65+I65-J65 -> 0 | M65: =SUMIF('TB UK'!A:A,'HARKAVA '!A65,'TB UK'!E:E) -> 194256.38 | N65: =SUMIF('Adj. Entries UK'!B:B,'HARKAVA '!A65,'Adj. Entries UK'!D:D) -> 106492 | O65: =SUMIF('Adj. Entries UK'!B:B,'HARKAVA '!A65,'Adj. Entries UK'!E:E) -> 55908.28 | P65: =M65+N65-O65 -> 244840.1 | R65: =SUMIF('TB security'!A:A,'HARKAVA '!A65,'TB security'!D:D) -> 649580.67 | S65: =SUMIF('Adj. Entries security'!B:B,'HARKAVA '!A65,'Adj. Entries security'!D:E) -> 0 | T65: =SUMIF('Adj. Entries security'!B:B,'HARKAVA '!A65,'Adj. Entries security'!E:E) -> 310897.93 | U65: =R65+S65-T65 -> 338682.74 | V65: =P65+F65+U65+K65 -> 1136187.1 | Y65: =V65+X65 -> 1136187.1 | Z65: =A65 -> 5300 | AD65: 552664.29 | AF65: 0 | AG65: 0 | AH65: 0 | AI65: 0 | AK65: 194256.38 | AL65: 106492 | AM65: 55908.28 | AN65: 244840.1 | AP65: 649580.67 | AQ65: 0 | AR65: 310897.93 | AS65: 338682.74 | AT65: 1136187.1 | AW65: 1136187.1 | AY65: =F65-AD65 -> 0 | AZ65: =P65-AN65 -> 0 | BA65: =U65-AS65 -> 0 | BB65: =X65-AV65 -> 0
A66: 5310 | B66: Cost of goods sold:management fee | C66: =SUMIF('TB Mitiga LTD'!A:A,'HARKAVA '!A66,'TB Mitiga LTD'!D:D) -> 189300.92 | D66: =SUMIF('Adj Entries Ltd'!$B$4:$B$954,A66,'Adj Entries Ltd'!$D$4:$D$954) -> 0 | E66: =SUMIF('Adj Entries Ltd'!$B$4:$B$954,A66,'Adj Entries Ltd'!$E$4:$E$954) -> 108192.24 | F66: =(+C66+D66-E66) -> 81108.685 | H66: =SUMIF('TB US'!A:A,'HARKAVA '!A66,'TB US'!D:D) -> 0 | I66: =SUMIF('Adj. entries US'!B:B,'HARKAVA '!A66,'Adj. entries US'!D:D) -> 0 | J66: =SUMIF('Adj. entries US'!B:B,'HARKAVA '!A66,'Adj. entries US'!E:E) -> 0 | M66: =SUMIF('TB UK'!A:A,'HARKAVA '!A66,'TB UK'!E:E) -> 0 | O66: =SUMIF('Adj. Entries UK'!B:B,'HARKAVA '!A66,'Adj. Entries UK'!E:E) -> 0 | P66: =M66+N66-O66 -> 0 | R66: =SUMIF('TB security'!A:A,'HARKAVA '!A66,'TB security'!D:D) -> 0 | S66: =SUMIF('Adj. Entries security'!B:B,'HARKAVA '!A66,'Adj. Entries security'!D:E) -> 0 | T66: =SUMIF('Adj. Entries security'!B:B,'HARKAVA '!A66,'Adj. Entries security'!E:E) -> 0 | U66: =R66+S66-T66 -> 0 | V66: =P66+F66+U66+K66 -> 81108.685 | Y66: =V66+X66 -> 81108.685 | Z66: 5300 | AD66: 81108.685 | AF66: 0 | AG66: 0 | AH66: 0 | AK66: 0 | AM66: 0 | AN66: 0 | AP66: 0 | AQ66: 0 | AR66: 0 | AS66: 0 | AT66: 81108.685 | AW66: 81108.685 | AY66: =F66-AD66 -> 0 | AZ66: =P66-AN66 -> 0 | BA66: =U66-AS66 -> 0 | BB66: =X66-AV66 -> 0
A67: 5311 | B67: Cost of goods sold: non budgeted items (esop, vacation provision) | C67: =SUMIF('TB Mitiga LTD'!A:A,'HARKAVA '!A67,'TB Mitiga LTD'!D:D) -> 14526.32 | D67: =SUMIF('Adj Entries Ltd'!$B$4:$B$954,A67,'Adj Entries Ltd'!$D$4:$D$954) -> 6909.1703 | E67: =SUMIF('Adj Entries Ltd'!$B$4:$B$954,A67,'Adj Entries Ltd'!$E$4:$E$954) -> 6583.805 | F67: =(+C67+D67-E67) -> 14851.685 | M67: =SUMIF('TB UK'!A:A,'HARKAVA '!A67,'TB UK'!E:E) -> 4620.73 | O67: =SUMIF('Adj. Entries UK'!B:B,'HARKAVA '!A67,'Adj. Entries UK'!E:E) -> 2310.365 | P67: =M67+N67-O67 -> 2310.365 | R67: =SUMIF('TB security'!A:A,'HARKAVA '!A67,'TB security'!D:D) -> 0 | T67: =SUMIF('Adj. Entries security'!B:B,'HARKAVA '!A67,'Adj. Entries security'!E:E) -> -5202 | U67: =R67+S67-T67 -> 5202 | V67: =P67+F67+U67+K67 -> 22364.05 | Y67: =V67+X67 -> 22364.05 | Z67: 5311 | AD67: 24236.515 | AK67: 4620.73 | AM67: 2310.365 | AN67: 2310.365 | AP67: 0 | AR67: -5202 | AS67: 5202 | AT67: 31748.88 | AW67: 31748.88 | AY67: =F67-AD67 -> -9384.8297 | AZ67: =P67-AN67 -> 0 | BA67: =U67-AS67 -> 0 | BB67: =X67-AV67 -> 0 | BC67: Adjustments made for the SBC expense for employee that left during 2021
A68: 5320 | B68: Cost of goods sold:subcontractors | C68: =SUMIF('TB Mitiga LTD'!A:A,'HARKAVA '!A68,'TB Mitiga LTD'!D:D) -> 99857.2 | D68: =SUMIF('Adj Entries Ltd'!$B$4:$B$954,A68,'Adj Entries Ltd'!$D$4:$D$954) -> 0 | E68: =SUMIF('Adj Entries Ltd'!$B$4:$B$954,A68,'Adj Entries Ltd'!$E$4:$E$954) -> 13576.715 | F68: =(+C68+D68-E68) -> 86280.485 | H68: =SUMIF('TB US'!A:A,'HARKAVA '!A68,'TB US'!D:D) -> 0 | I68: =SUMIF('Adj. entries US'!B:B,'HARKAVA '!A68,'Adj. entries US'!D:D) -> 0 | J68: =SUMIF('Adj. entries US'!B:B,'HARKAVA '!A68,'Adj. entries US'!E:E) -> 0 | K68: =H68+I68-J68 -> 0 | M68: =SUMIF('TB UK'!A:A,'HARKAVA '!A68,'TB UK'!E:E) -> 0 | N68: =SUMIF('Adj. Entries UK'!B:B,'HARKAVA '!A68,'Adj. Entries UK'!D:D) -> 0 | O68: =SUMIF('Adj. Entries UK'!B:B,'HARKAVA '!A68,'Adj. Entries UK'!E:E) -> 0 | P68: =M68+N68-O68 -> 0 | R68: =SUMIF('TB security'!A:A,'HARKAVA '!A68,'TB security'!D:D) -> 31670 | S68: =SUMIF('Adj. Entries security'!B:B,'HARKAVA '!A68,'Adj. Entries security'!D:E) -> 0 | T68: =SUMIF('Adj. Entries security'!B:B,'HARKAVA '!A68,'Adj. Entries security'!E:E) -> 2200 | U68: =R68+S68-T68 -> 29470 | V68: =P68+F68+U68+K68 -> 115750.49 | Y68: =V68+X68 -> 115750.49 | Z68: =A68 -> 5320 | AD68: 86280.485 | AF68: 0 | AG68: 0 | AH68: 0 | AI68: 0 | AK68: 0 | AL68: 0 | AM68: 0 | AN68: 0 | AP68: 31670 | AQ68: 0 | AR68: 2200 | AS68: 29470 | AT68: 115750.49 | AW68: 115750.49 | AY68: =F68-AD68 -> 0 | AZ68: =P68-AN68 -> 0 | BA68: =U68-AS68 -> 0 | BB68: =X68-AV68 -> 0
A69: 5330 | B69: Cost of goods sold:Other | C69: =SUMIF('TB Mitiga LTD'!A:A,'HARKAVA '!A69,'TB Mitiga LTD'!D:D) -> 58962.71 | D69: =SUMIF('Adj Entries Ltd'!$B$4:$B$954,A69,'Adj Entries Ltd'!$D$4:$D$954) -> 203147.41 | E69: =SUMIF('Adj Entries Ltd'!$B$4:$B$954,A69,'Adj Entries Ltd'!$E$4:$E$954) -> 40936.295 | F69: =(+C69+D69-E69) -> 221173.82 | H69: =SUMIF('TB US'!A:A,'HARKAVA '!A69,'TB US'!D:D) -> 0 | I69: =SUMIF('Adj. entries US'!B:B,'HARKAVA '!A69,'Adj. entries US'!D:D) -> 0 | J69: =SUMIF('Adj. entries US'!B:B,'HARKAVA '!A69,'Adj. entries US'!E:E) -> 0 | K69: =H69+I69-J69 -> 0 | M69: =SUMIF('TB UK'!A:A,'HARKAVA '!A69,'TB UK'!E:E) -> 15634.26 | N69: =SUMIF('Adj. Entries UK'!B:B,'HARKAVA '!A69,'Adj. Entries UK'!D:D) -> 0 | O69: =SUMIF('Adj. Entries UK'!B:B,'HARKAVA '!A69,'Adj. Entries UK'!E:E) -> 4661.31 | P69: =M69+N69-O69 -> 10972.95 | R69: =SUMIF('TB security'!A:A,'HARKAVA '!A69,'TB security'!D:D) -> 12544.62 | S69: =SUMIF('Adj. Entries security'!B:B,'HARKAVA '!A69,'Adj. Entries security'!D:E) -> 35790.548 | T69: =SUMIF('Adj. Entries security'!B:B,'HARKAVA '!A69,'Adj. Entries security'!E:E) -> 24054.419 | U69: =R69+S69-T69 -> 24280.749 | V69: =P69+F69+U69+K69 -> 256427.52 | Y69: =V69+X69 -> 256427.52 | Z69: =A69 -> 5330 | AD69: 221173.82 | AF69: 0 | AG69: 0 | AH69: 0 | AI69: 0 | AK69: 15634.26 | AL69: 0 | AM69: 4661.31 | AN69: 10972.95 | AP69: 12544.62 | AQ69: 35790.548 | AR69: 24054.419 | AS69: 24280.749 | AT69: 256427.52 | AW69: 256427.52 | AY69: =F69-AD69 -> 0 | AZ69: =P69-AN69 -> 0 | BA69: =U69-AS69 -> 0 | BB69: =X69-AV69 -> 0
A70: 5400 | B70: R&D expenses: Salaries and related expenses | C70: =SUMIF('TB Mitiga LTD'!A:A,'HARKAVA '!A70,'TB Mitiga LTD'!D:D) -> 2482625 | D70: =SUMIF('Adj Entries Ltd'!$B$4:$B$954,A70,'Adj Entries Ltd'!$D$4:$D$954) -> 1118928 | E70: =SUMIF('Adj Entries Ltd'!$B$4:$B$954,A70,'Adj Entries Ltd'!$E$4:$E$954) -> 20000 | F70: =(+C70+D70-E70) -> 3581553 | H70: =SUMIF('TB US'!A:A,'HARKAVA '!A70,'TB US'!D:D) -> 0 | I70: =SUMIF('Adj. entries US'!B:B,'HARKAVA '!A70,'Adj. entries US'!D:D) -> 0 | J70: =SUMIF('Adj. entries US'!B:B,'HARKAVA '!A70,'Adj. entries US'!E:E) -> 0 | K70: =H70+I70-J70 -> 0 | M70: =SUMIF('TB UK'!A:A,'HARKAVA '!A70,'TB UK'!E:E) -> 0 | N70: =SUMIF('Adj. Entries UK'!B:B,'HARKAVA '!A70,'Adj. Entries UK'!D:D) -> 55908.28 | O70: =SUMIF('Adj. Entries UK'!B:B,'HARKAVA '!A70,'Adj. Entries UK'!E:E) -> 0 | P70: =M70+N70-O70 -> 55908.28 | R70: =SUMIF('TB security'!A:A,'HARKAVA '!A70,'TB security'!D:D) -> 0 | S70: =SUMIF('Adj. Entries security'!B:B,'HARKAVA '!A70,'Adj. Entries security'!D:E) -> 142244.93 | T70: =SUMIF('Adj. Entries security'!B:B,'HARKAVA '!A70,'Adj. Entries security'!E:E) -> 0 | U70: =R70+S70-T70 -> 142244.93 | V70: =P70+F70+U70+K70 -> 3779706.2 | Y70: =V70+X70 -> 3779706.2 | Z70: =A70 -> 5400 | AD70: 3581553 | AF70: 0 | AG70: 0 | AH70: 0 | AI70: 0 | AK70: 0 | AL70: 55908.28 | AM70: 0 | AN70: 55908.28 | AP70: 0 | AQ70: 142244.93 | AR70: 0 | AS70: 142244.93 | AT70: 3779706.2 | AW70: 3779706.2 | AY70: =F70-AD70 -> 0 | AZ70: =P70-AN70 -> 0 | BA70: =U70-AS70 -> 0 | BB70: =X70-AV70 -> 0
A71: 5405 | B71: R&D expenses: management fee | C71: =SUMIF('TB Mitiga LTD'!A:A,'HARKAVA '!A71,'TB Mitiga LTD'!D:D) -> 272586.36 | D71: =SUMIF('Adj Entries Ltd'!$B$4:$B$954,A71,'Adj Entries Ltd'!$D$4:$D$954) -> 13541.735 | E71: =SUMIF('Adj Entries Ltd'!$B$4:$B$954,A71,'Adj Entries Ltd'!$E$4:$E$954) -> 54771 | F71: =(+C71+D71-E71) -> 231357.09 | I71: =SUMIF('Adj. entries US'!B:B,'HARKAVA '!A71,'Adj. entries US'!D:D) -> 0 | J71: =SUMIF('Adj. entries US'!B:B,'HARKAVA '!A71,'Adj. entries US'!E:E) -> 0 | M71: =SUMIF('TB UK'!A:A,'HARKAVA '!A71,'TB UK'!E:E) -> 0 | N71: =SUMIF('Adj. Entries UK'!B:B,'HARKAVA '!A71,'Adj. Entries UK'!D:D) -> 0 | O71: =SUMIF('Adj. Entries UK'!B:B,'HARKAVA '!A71,'Adj. Entries UK'!E:E) -> 0 | P71: =M71+N71-O71 -> 0 | R71: =SUMIF('TB security'!A:A,'HARKAVA '!A71,'TB security'!D:D) -> 0 | S71: =SUMIF('Adj. Entries security'!B:B,'HARKAVA '!A71,'Adj. Entries security'!D:E) -> 0 | T71: =SUMIF('Adj. Entries security'!B:B,'HARKAVA '!A71,'Adj. Entries security'!E:E) -> 0 | U71: =R71+S71-T71 -> 0 | V71: =P71+F71+U71+K71 -> 231357.09 | Y71: =V71+X71 -> 231357.09 | Z71: 5400 | AD71: 231357.09 | AG71: 0 | AH71: 0 | AK71: 0 | AL71: 0 | AM71: 0 | AN71: 0 | AP71: 0 | AQ71: 0 | AR71: 0 | AS71: 0 | AT71: 231357.09 | AW71: 231357.09 | AY71: =F71-AD71 -> 0 | AZ71: =P71-AN71 -> 0 | BA71: =U71-AS71 -> 0 | BB71: =X71-AV71 -> 0
A72: 5410 | B72: R&D Expenses: outsource | C72: =SUMIF('TB Mitiga LTD'!A:A,'HARKAVA '!A72,'TB Mitiga LTD'!D:D) -> 932650.61 | D72: =SUMIF('Adj Entries Ltd'!$B$4:$B$954,A72,'Adj Entries Ltd'!$D$4:$D$954) -> 13576.715 | E72: =SUMIF('Adj Entries Ltd'!$B$4:$B$954,A72,'Adj Entries Ltd'!$E$4:$E$954) -> 0 | F72: =(+C72+D72-E72) -> 946227.32 | H72: =SUMIF('TB US'!A:A,'HARKAVA '!A72,'TB US'!D:D) -> 0 | I72: =SUMIF('Adj. entries US'!B:B,'HARKAVA '!A72,'Adj. entries US'!D:D) -> 0 | J72: =SUMIF('Adj. entries US'!B:B,'HARKAVA '!A72,'Adj. entries US'!E:E) -> 0 | K72: =H72+I72-J72 -> 0 | M72: =SUMIF('TB UK'!A:A,'HARKAVA '!A72,'TB UK'!E:E) -> 635.11 | N72: =SUMIF('Adj. Entries UK'!B:B,'HARKAVA '!A72,'Adj. Entries UK'!D:D) -> 0 | O72: =SUMIF('Adj. Entries UK'!B:B,'HARKAVA '!A72,'Adj. Entries UK'!E:E) -> 0 | P72: =M72+N72-O72 -> 635.11 | R72: =SUMIF('TB security'!A:A,'HARKAVA '!A72,'TB security'!D:D) -> 2337.39 | S72: =SUMIF('Adj. Entries security'!B:B,'HARKAVA '!A72,'Adj. Entries security'!D:E) -> 2200 | T72: =SUMIF('Adj. Entries security'!B:B,'HARKAVA '!A72,'Adj. Entries security'!E:E) -> 0 | U72: =R72+S72-T72 -> 4537.39 | V72: =P72+F72+U72+K72 -> 951399.82 | Y72: =V72+X72 -> 951399.82 | Z72: =A72 -> 5410 | AD72: 946227.32 | AF72: 0 | AG72: 0 | AH72: 0 | AI72: 0 | AK72: 635.11 | AL72: 0 | AM72: 0 | AN72: 635.11 | AP72: 2337.39 | AQ72: 2200 | AR72: 0 | AS72: 4537.39 | AT72: 951399.82 | AW72: 951399.82 | AY72: =F72-AD72 -> 0 | AZ72: =P72-AN72 -> 0 | BA72: =U72-AS72 -> 0 | BB72: =X72-AV72 -> 0
A73: 5411 | B73: R&D expenses: non budgeted items (esop, vacation provision) | C73: =SUMIF('TB Mitiga LTD'!A:A,'HARKAVA '!A73,'TB Mitiga LTD'!D:D) -> 103077.98 | D73: =SUMIF('Adj Entries Ltd'!$B$4:$B$954,A73,'Adj Entries Ltd'!$D$4:$D$954) -> 23594.582 | E73: =SUMIF('Adj Entries Ltd'!$B$4:$B$954,A73,'Adj Entries Ltd'!$E$4:$E$954) -> 0 | F73: =(+C73+D73-E73) -> 126672.56 | K73: =H73+I73-J73 -> 0 | M73: =SUMIF('TB UK'!A:A,'HARKAVA '!A73,'TB UK'!E:E) -> 0 | N73: =SUMIF('Adj. Entries UK'!B:B,'HARKAVA '!A73,'Adj. Entries UK'!D:D) -> 2310.365 | O73: =SUMIF('Adj. Entries UK'!B:B,'HARKAVA '!A73,'Adj. Entries UK'!E:E) -> 0 | P73: =M73+N73-O73 -> 2310.365 | R73: =SUMIF('TB security'!A:A,'HARKAVA '!A73,'TB security'!D:D) -> 0 | S73: =SUMIF('Adj. Entries security'!B:B,'HARKAVA '!A73,'Adj. Entries security'!D:E) -> -5202 | T73: =SUMIF('Adj. Entries security'!B:B,'HARKAVA '!A73,'Adj. Entries security'!E:E) -> 0 | U73: =R73+S73-T73 -> -5202 | V73: =P73+F73+U73+K73 -> 123780.93 | Y73: =V73+X73 -> 123780.93 | Z73: 5411 | AD73: 128163.79 | AI73: 0 | AK73: 0 | AL73: 2310.365 | AM73: 0 | AN73: 2310.365 | AP73: 0 | AQ73: -5202 | AR73: 0 | AS73: -5202 | AT73: 125272.15 | AW73: 125272.15 | AY73: =F73-AD73 -> -1491.2227 | AZ73: =P73-AN73 -> 0 | BA73: =U73-AS73 -> 0 | BB73: =X73-AV73 -> 0 | BC73: Adjustments made for the SBC expense for employee that left during 2021
A74: 5416 | B74: R&D Expenses: Other | C74: =SUMIF('TB Mitiga LTD'!A:A,'HARKAVA '!A74,'TB Mitiga LTD'!D:D) -> 48058.27 | D74: =SUMIF('Adj Entries Ltd'!$B$4:$B$954,A74,'Adj Entries Ltd'!$D$4:$D$954) -> 329443.27 | E74: =SUMIF('Adj Entries Ltd'!$B$4:$B$954,A74,'Adj Entries Ltd'!$E$4:$E$954) -> 0 | F74: =(+C74+D74-E74) -> 377501.54 | H74: =SUMIF('TB US'!A:A,'HARKAVA '!A74,'TB US'!D:D) -> 0 | I74: =SUMIF('Adj. entries US'!B:B,'HARKAVA '!A74,'Adj. entries US'!D:D) -> 0 | J74: =SUMIF('Adj. entries US'!B:B,'HARKAVA '!A74,'Adj. entries US'!E:E) -> 0 | K74: =H74+I74-J74 -> 0 | M74: =SUMIF('TB UK'!A:A,'HARKAVA '!A74,'TB UK'!E:E) -> 0 | N74: =SUMIF('Adj. Entries UK'!B:B,'HARKAVA '!A74,'Adj. Entries UK'!D:D) -> 4661.31 | O74: =SUMIF('Adj. Entries UK'!B:B,'HARKAVA '!A74,'Adj. Entries UK'!E:E) -> 0 | P74: =M74+N74-O74 -> 4661.31 | R74: =SUMIF('TB security'!A:A,'HARKAVA '!A74,'TB security'!D:D) -> 0 | S74: =SUMIF('Adj. Entries security'!B:B,'HARKAVA '!A74,'Adj. Entries security'!D:E) -> 24054.419 | T74: =SUMIF('Adj. Entries security'!B:B,'HARKAVA '!A74,'Adj. Entries security'!E:E) -> 0 | U74: =R74+S74-T74 -> 24054.419 | V74: =P74+F74+U74+K74 -> 406217.27 | Y74: =V74+X74 -> 406217.27 | Z74: =A74 -> 5416 | AD74: 377501.54 | AF74: 0 | AG74: 0 | AH74: 0 | AI74: 0 | AK74: 0 | AL74: 4661.31 | AM74: 0 | AN74: 4661.31 | AP74: 0 | AQ74: 24054.419 | AR74: 0 | AS74: 24054.419 | AT74: 406217.27 | AW74: 406217.27 | AY74: =F74-AD74 -> 0 | AZ74: =P74-AN74 -> 0 | BA74: =U74-AS74 -> 0 | BB74: =X74-AV74 -> 0
A75: 5417 | B75: R&D Expenses: Patents | C75: =SUMIF('TB Mitiga LTD'!A:A,'HARKAVA '!A75,'TB Mitiga LTD'!D:D) -> 0 | D75: =SUMIF('Adj Entries Ltd'!$B$4:$B$954,A75,'Adj Entries Ltd'!$D$4:$D$954) -> 0 | E75: =SUMIF('Adj Entries Ltd'!$B$4:$B$954,A75,'Adj Entries Ltd'!$E$4:$E$954) -> 0 | F75: =(+C75+D75-E75) -> 0 | H75: =SUMIF('TB US'!A:A,'HARKAVA '!A75,'TB US'!D:D) -> 0 | I75: =SUMIF('Adj. entries US'!B:B,'HARKAVA '!A75,'Adj. entries US'!D:D) -> 0 | J75: =SUMIF('Adj. entries US'!B:B,'HARKAVA '!A75,'Adj. entries US'!E:E) -> 0 | K75: =H75+I75-J75 -> 0 | M75: =SUMIF('TB UK'!A:A,'HARKAVA '!A75,'TB UK'!E:E) -> 0 | N75: =SUMIF('Adj. Entries UK'!B:B,'HARKAVA '!A75,'Adj. Entries UK'!D:D) -> 0 | O75: =SUMIF('Adj. Entries UK'!B:B,'HARKAVA '!A75,'Adj. Entries UK'!E:E) -> 0 | P75: =M75+N75-O75 -> 0 | R75: =SUMIF('TB security'!A:A,'HARKAVA '!A75,'TB security'!D:D) -> 0 | S75: =SUMIF('Adj. Entries security'!B:B,'HARKAVA '!A75,'Adj. Entries security'!D:E) -> 0 | T75: =SUMIF('Adj. Entries security'!B:B,'HARKAVA '!A75,'Adj. Entries security'!E:E) -> 0 | U75: =R75+S75-T75 -> 0 | V75: =P75+F75+U75+K75 -> 0 | Y75: =V75+X75 -> 0 | Z75: =A75 -> 5417 | AD75: 0 | AF75: 0 | AG75: 0 | AH75: 0 | AI75: 0 | AK75: 0 | AL75: 0 | AM75: 0 | AN75: 0 | AP75: 0 | AQ75: 0 | AR75: 0 | AS75: 0 | AT75: 0 | AW75: 0 | AY75: =F75-AD75 -> 0 | AZ75: =P75-AN75 -> 0 | BA75: =U75-AS75 -> 0 | BB75: =X75-AV75 -> 0
A76: 5420 | B76: R&D expenses: Travels | C76: =SUMIF('TB Mitiga LTD'!A:A,'HARKAVA '!A76,'TB Mitiga LTD'!D:D) -> 23799.72 | D76: =SUMIF('Adj Entries Ltd'!$B$4:$B$954,A76,'Adj Entries Ltd'!$D$4:$D$954) -> 0 | E76: =SUMIF('Adj Entries Ltd'!$B$4:$B$954,A76,'Adj Entries Ltd'!$E$4:$E$954) -> 0 | F76: =(+C76+D76-E76) -> 23799.72 | H76: =SUMIF('TB US'!A:A,'HARKAVA '!A76,'TB US'!D:D) -> 0 | I76: =SUMIF('Adj. entries US'!B:B,'HARKAVA '!A76,'Adj. entries US'!D:D) -> 0 | J76: =SUMIF('Adj. entries US'!B:B,'HARKAVA '!A76,'Adj. entries US'!E:E) -> 0 | K76: =H76+I76-J76 -> 0 | M76: =SUMIF('TB UK'!A:A,'HARKAVA '!A76,'TB UK'!E:E) -> 0 | N76: =SUMIF('Adj. Entries UK'!B:B,'HARKAVA '!A76,'Adj. Entries UK'!D:D) -> 0 | O76: =SUMIF('Adj. Entries UK'!B:B,'HARKAVA '!A76,'Adj. Entries UK'!E:E) -> 0 | P76: =M76+N76-O76 -> 0 | R76: =SUMIF('TB security'!A:A,'HARKAVA '!A76,'TB security'!D:D) -> 0 | S76: =SUMIF('Adj. Entries security'!B:B,'HARKAVA '!A76,'Adj. Entries security'!D:E) -> 0 | T76: =SUMIF('Adj. Entries security'!B:B,'HARKAVA '!A76,'Adj. Entries security'!E:E) -> 0 | U76: =R76+S76-T76 -> 0 | V76: =P76+F76+U76+K76 -> 23799.72 | Y76: =V76+X76 -> 23799.72 | Z76: 5416 | AD76: 23799.72 | AF76: 0 | AG76: 0 | AH76: 0 | AI76: 0 | AK76: 0 | AL76: 0 | AM76: 0 | AN76: 0 | AP76: 0 | AQ76: 0 | AR76: 0 | AS76: 0 | AT76: 23799.72 | AW76: 23799.72 | AY76: =F76-AD76 -> 0 | AZ76: =P76-AN76 -> 0 | BA76: =U76-AS76 -> 0 | BB76: =X76-AV76 -> 0
A77: 5430 | B77: R&D expenses: Depreciation and amortization | C77: =SUMIF('TB Mitiga LTD'!A:A,'HARKAVA '!A77,'TB Mitiga LTD'!D:D) -> 30845.74 | D77: =SUMIF('Adj Entries Ltd'!$B$4:$B$954,A77,'Adj Entries Ltd'!$D$4:$D$954) -> 0 | E77: =SUMIF('Adj Entries Ltd'!$B$4:$B$954,A77,'Adj Entries Ltd'!$E$4:$E$954) -> 0 | F77: =(+C77+D77-E77) -> 30845.74 | H77: =SUMIF('TB US'!A:A,'HARKAVA '!A77,'TB US'!D:D) -> 0 | I77: =SUMIF('Adj. entries US'!B:B,'HARKAVA '!A77,'Adj. entries US'!D:D) -> 0 | J77: =SUMIF('Adj. entries US'!B:B,'HARKAVA '!A77,'Adj. entries US'!E:E) -> 0 | K77: =H77+I77-J77 -> 0 | M77: =SUMIF('TB UK'!A:A,'HARKAVA '!A77,'TB UK'!E:E) -> 0 | N77: =SUMIF('Adj. Entries UK'!B:B,'HARKAVA '!A77,'Adj. Entries UK'!D:D) -> 0 | O77: =SUMIF('Adj. Entries UK'!B:B,'HARKAVA '!A77,'Adj. Entries UK'!E:E) -> 0 | P77: =M77+N77-O77 -> 0 | R77: =SUMIF('TB security'!A:A,'HARKAVA '!A77,'TB security'!D:D) -> 0 | S77: =SUMIF('Adj. Entries security'!B:B,'HARKAVA '!A77,'Adj. Entries security'!D:E) -> 0 | T77: =SUMIF('Adj. Entries security'!B:B,'HARKAVA '!A77,'Adj. Entries security'!E:E) -> 0 | U77: =R77+S77-T77 -> 0 | V77: =P77+F77+U77+K77 -> 30845.74 | Y77: =V77+X77 -> 30845.74 | Z77: 5416 | AD77: 30845.74 | AF77: 0 | AG77: 0 | AH77: 0 | AI77: 0 | AK77: 0 | AL77: 0 | AM77: 0 | AN77: 0 | AP77: 0 | AQ77: 0 | AR77: 0 | AS77: 0 | AT77: 30845.74 | AW77: 30845.74 | AY77: =F77-AD77 -> 0 | AZ77: =P77-AN77 -> 0 | BA77: =U77-AS77 -> 0 | BB77: =X77-AV77 -> 0
A78: 5440 | B78: R&D expenses: overhead | C78: =SUMIF('TB Mitiga LTD'!A:A,'HARKAVA '!A78,'TB Mitiga LTD'!D:D) -> 0 | D78: =SUMIF('Adj Entries Ltd'!$B$4:$B$954,A78,'Adj Entries Ltd'!$D$4:$D$954) -> 0 | E78: =SUMIF('Adj Entries Ltd'!$B$4:$B$954,A78,'Adj Entries Ltd'!$E$4:$E$954) -> 0 | F78: =(+C78+D78-E78) -> 0 | H78: =SUMIF('TB US'!A:A,'HARKAVA '!A78,'TB US'!D:D) -> 0 | I78: =SUMIF('Adj. entries US'!B:B,'HARKAVA '!A78,'Adj. entries US'!D:D) -> 0 | J78: =SUMIF('Adj. entries US'!B:B,'HARKAVA '!A78,'Adj. entries US'!E:E) -> 0 | K78: =H78+I78-J78 -> 0 | M78: =SUMIF('TB UK'!A:A,'HARKAVA '!A78,'TB UK'!E:E) -> 0 | N78: =SUMIF('Adj. Entries UK'!B:B,'HARKAVA '!A78,'Adj. Entries UK'!D:D) -> 0 | O78: =SUMIF('Adj. Entries UK'!B:B,'HARKAVA '!A78,'Adj. Entries UK'!E:E) -> 0 | P78: =M78+N78-O78 -> 0 | R78: =SUMIF('TB security'!A:A,'HARKAVA '!A78,'TB security'!D:D) -> 0 | S78: =SUMIF('Adj. Entries security'!B:B,'HARKAVA '!A78,'Adj. Entries security'!D:E) -> 0 | T78: =SUMIF('Adj. Entries security'!B:B,'HARKAVA '!A78,'Adj. Entries security'!E:E) -> 0 | U78: =R78+S78-T78 -> 0 | V78: =P78+F78+U78+K78 -> 0 | Y78: =V78+X78 -> 0 | Z78: =A78 -> 5440 | AD78: 0 | AF78: 0 | AG78: 0 | AH78: 0 | AI78: 0 | AK78: 0 | AL78: 0 | AM78: 0 | AN78: 0 | AP78: 0 | AQ78: 0 | AR78: 0 | AS78: 0 | AT78: 0 | AW78: 0 | AY78: =F78-AD78 -> 0 | AZ78: =P78-AN78 -> 0 | BA78: =U78-AS78 -> 0 | BB78: =X78-AV78 -> 0
A79: 5500 | B79: S&M Salaries and related expenses | C79: =SUMIF('TB Mitiga LTD'!A:A,'HARKAVA '!A79,'TB Mitiga LTD'!D:D) -> 30995.54 | D79: =SUMIF('Adj Entries Ltd'!$B$4:$B$954,A79,'Adj Entries Ltd'!$D$4:$D$954) -> 0 | E79: =SUMIF('Adj Entries Ltd'!$B$4:$B$954,A79,'Adj Entries Ltd'!$E$4:$E$954) -> 0 | F79: =(+C79+D79-E79) -> 30995.54 | H79: =SUMIF('TB US'!A:A,'HARKAVA '!A79,'TB US'!D:D) -> 0 | I79: =SUMIF('Adj. entries US'!B:B,'HARKAVA '!A79,'Adj. entries US'!D:D) -> 0 | J79: =SUMIF('Adj. entries US'!B:B,'HARKAVA '!A79,'Adj. entries US'!E:E) -> 0 | K79: =H79+I79-J79 -> 0 | M79: =SUMIF('TB UK'!A:A,'HARKAVA '!A79,'TB UK'!E:E) -> 524284.74 | N79: =SUMIF('Adj. Entries UK'!B:B,'HARKAVA '!A79,'Adj. Entries UK'!D:D) -> 0 | O79: =SUMIF('Adj. Entries UK'!B:B,'HARKAVA '!A79,'Adj. Entries UK'!E:E) -> 106492 | P79: =M79+N79-O79 -> 417792.74 | R79: =SUMIF('TB security'!A:A,'HARKAVA '!A79,'TB security'!D:D) -> 758669.27 | S79: =SUMIF('Adj. Entries security'!B:B,'HARKAVA '!A79,'Adj. Entries security'!D:E) -> 0 | T79: =SUMIF('Adj. Entries security'!B:B,'HARKAVA '!A79,'Adj. Entries security'!E:E) -> 0 | U79: =R79+S79-T79 -> 758669.27 | V79: =P79+F79+U79+K79 -> 1207457.5 | Y79: =V79+X79 -> 1207457.5 | Z79: =A79 -> 5500 | AD79: 30995.54 | AF79: 0 | AG79: 0 | AH79: 0 | AI79: 0 | AK79: 524284.74 | AL79: 0 | AM79: 106492 | AN79: 417792.74 | AP79: 758669.27 | AQ79: 0 | AR79: 0 | AS79: 758669.27 | AT79: 1207457.5 | AW79: 1207457.5 | AY79: =F79-AD79 -> 0 | AZ79: =P79-AN79 -> 0 | BA79: =U79-AS79 -> 0 | BB79: =X79-AV79 -> 0
A80: 5505 | B80: S&M expenses: non budgeted items (esop, vacation provision) | C80: =SUMIF('TB Mitiga LTD'!A:A,'HARKAVA '!A80,'TB Mitiga LTD'!D:D) -> 1147.91 | D80: =SUMIF('Adj Entries Ltd'!$B$4:$B$954,A80,'Adj Entries Ltd'!$D$4:$D$954) -> 0 | E80: =SUMIF('Adj Entries Ltd'!$B$4:$B$954,A80,'Adj Entries Ltd'!$E$4:$E$954) -> 0 | F80: =(+C80+D80-E80) -> 1147.91 | K80: =H80+I80-J80 -> 0 | M80: =SUMIF('TB UK'!A:A,'HARKAVA '!A80,'TB UK'!E:E) -> 5386.85 | N80: =SUMIF('Adj. Entries UK'!B:B,'HARKAVA '!A80,'Adj. Entries UK'!D:D) -> 8351.7454 | O80: =SUMIF('Adj. Entries UK'!B:B,'HARKAVA '!A80,'Adj. Entries UK'!E:E) -> 0 | P80: =M80+N80-O80 -> 13738.595 | R80: =SUMIF('TB security'!A:A,'HARKAVA '!A80,'TB security'!D:D) -> 0 | S80: =SUMIF('Adj. Entries security'!B:B,'HARKAVA '!A80,'Adj. Entries security'!D:E) -> -701.08694 | T80: =SUMIF('Adj. Entries security'!B:B,'HARKAVA '!A80,'Adj. Entries security'!E:E) -> 0 | U80: =R80+S80-T80 -> -701.08694 | V80: =P80+F80+U80+K80 -> 14185.418 | Y80: =V80+X80 -> 14185.418 | Z80: 5505 | AD80: 1147.91 | AI80: 0 | AK80: 5386.85 | AL80: 13073 | AM80: 0 | AN80: 18459.85 | AP80: 0 | AQ80: 1484 | AR80: 0 | AS80: 1484 | AT80: 21091.76 | AW80: 21091.76 | AY80: =F80-AD80 -> 0 | AZ80: =P80-AN80 -> -4721.2546 | BA80: =U80-AS80 -> -2185.0869 | BB80: =X80-AV80 -> 0 | BC80: Adjustments made for the SBC expense for employee that left during 2021
A81: 5508 | B81: S&M Comissions | C81: =SUMIF('TB Mitiga LTD'!A:A,'HARKAVA '!A81,'TB Mitiga LTD'!D:D) -> 0 | D81: =SUMIF('Adj Entries Ltd'!$B$4:$B$954,A81,'Adj Entries Ltd'!$D$4:$D$954) -> 0 | E81: =SUMIF('Adj Entries Ltd'!$B$4:$B$954,A81,'Adj Entries Ltd'!$E$4:$E$954) -> 0 | F81: =(+C81+D81-E81) -> 0 | H81: =SUMIF('TB US'!A:A,'HARKAVA '!A81,'TB US'!D:D) -> 0 | I81: =SUMIF('Adj. entries US'!B:B,'HARKAVA '!A81,'Adj. entries US'!D:D) -> 0 | J81: =SUMIF('Adj. entries US'!B:B,'HARKAVA '!A81,'Adj. entries US'!E:E) -> 0 | K81: =H81+I81-J81 -> 0 | M81: =SUMIF('TB UK'!A:A,'HARKAVA '!A81,'TB UK'!E:E) -> 0 | N81: =SUMIF('Adj. Entries UK'!B:B,'HARKAVA '!A81,'Adj. Entries UK'!D:D) -> 0 | O81: =SUMIF('Adj. Entries UK'!B:B,'HARKAVA '!A81,'Adj. Entries UK'!E:E) -> 0 | P81: =M81+N81-O81 -> 0 | R81: =SUMIF('TB security'!A:A,'HARKAVA '!A81,'TB security'!D:D) -> 0 | S81: =SUMIF('Adj. Entries security'!B:B,'HARKAVA '!A81,'Adj. Entries security'!D:E) -> 0 | T81: =SUMIF('Adj. Entries security'!B:B,'HARKAVA '!A81,'Adj. Entries security'!E:E) -> 0 | U81: =R81+S81-T81 -> 0 | V81: =P81+F81+U81+K81 -> 0 | Y81: =V81+X81 -> 0 | Z81: =A81 -> 5508 | AD81: 0 | AF81: 0 | AG81: 0 | AH81: 0 | AI81: 0 | AK81: 0 | AL81: 0 | AM81: 0 | AN81: 0 | AP81: 0 | AQ81: 0 | AR81: 0 | AS81: 0 | AT81: 0 | AW81: 0 | AY81: =F81-AD81 -> 0 | AZ81: =P81-AN81 -> 0 | BA81: =U81-AS81 -> 0 | BB81: =X81-AV81 -> 0
A82: 5510 | B82: S&M Consulting | C82: =SUMIF('TB Mitiga LTD'!A:A,'HARKAVA '!A82,'TB Mitiga LTD'!D:D) -> 36378.96 | D82: =SUMIF('Adj Entries Ltd'!$B$4:$B$954,A82,'Adj Entries Ltd'!$D$4:$D$954) -> 0 | E82: =SUMIF('Adj Entries Ltd'!$B$4:$B$954,A82,'Adj Entries Ltd'!$E$4:$E$954) -> 0 | F82: =(+C82+D82-E82) -> 36378.96 | H82: =SUMIF('TB US'!A:A,'HARKAVA '!A82,'TB US'!D:D) -> 0 | I82: =SUMIF('Adj. entries US'!B:B,'HARKAVA '!A82,'Adj. entries US'!D:D) -> 0 | J82: =SUMIF('Adj. entries US'!B:B,'HARKAVA '!A82,'Adj. entries US'!E:E) -> 0 | K82: =H82+I82-J82 -> 0 | M82: =SUMIF('TB UK'!A:A,'HARKAVA '!A82,'TB UK'!E:E) -> 16893.86 | N82: =SUMIF('Adj. Entries UK'!B:B,'HARKAVA '!A82,'Adj. Entries UK'!D:D) -> 0 | O82: =SUMIF('Adj. Entries UK'!B:B,'HARKAVA '!A82,'Adj. Entries UK'!E:E) -> 0 | P82: =M82+N82-O82 -> 16893.86 | R82: =SUMIF('TB security'!A:A,'HARKAVA '!A82,'TB security'!D:D) -> 235045.25 | S82: =SUMIF('Adj. Entries security'!B:B,'HARKAVA '!A82,'Adj. Entries security'!D:E) -> 0 | T82: =SUMIF('Adj. Entries security'!B:B,'HARKAVA '!A82,'Adj. Entries security'!E:E) -> 0 | U82: =R82+S82-T82 -> 235045.25 | V82: =P82+F82+U82+K82 -> 288318.07 | Y82: =V82+X82 -> 288318.07 | Z82: =A82 -> 5510 | AD82: 36378.96 | AF82: 0 | AG82: 0 | AH82: 0 | AI82: 0 | AK82: 16893.86 | AL82: 0 | AM82: 0 | AN82: 16893.86 | AP82: 235045.25 | AQ82: 0 | AR82: 0 | AS82: 235045.25 | AT82: 288318.07 | AW82: 288318.07 | AY82: =F82-AD82 -> 0 | AZ82: =P82-AN82 -> 0 | BA82: =U82-AS82 -> 0 | BB82: =X82-AV82 -> 0
A83: 5520 | B83: S&M Commercials and advertising | C83: =SUMIF('TB Mitiga LTD'!A:A,'HARKAVA '!A83,'TB Mitiga LTD'!D:D) -> 0 | D83: =SUMIF('Adj Entries Ltd'!$B$4:$B$954,A83,'Adj Entries Ltd'!$D$4:$D$954) -> 0 | E83: =SUMIF('Adj Entries Ltd'!$B$4:$B$954,A83,'Adj Entries Ltd'!$E$4:$E$954) -> 0 | F83: =(+C83+D83-E83) -> 0 | H83: =SUMIF('TB US'!A:A,'HARKAVA '!A83,'TB US'!D:D) -> 0 | I83: =SUMIF('Adj. entries US'!B:B,'HARKAVA '!A83,'Adj. entries US'!D:D) -> 0 | J83: =SUMIF('Adj. entries US'!B:B,'HARKAVA '!A83,'Adj. entries US'!E:E) -> 0 | K83: =H83+I83-J83 -> 0 | M83: =SUMIF('TB UK'!A:A,'HARKAVA '!A83,'TB UK'!E:E) -> 0 | N83: =SUMIF('Adj. Entries UK'!B:B,'HARKAVA '!A83,'Adj. Entries UK'!D:D) -> 0 | O83: =SUMIF('Adj. Entries UK'!B:B,'HARKAVA '!A83,'Adj. Entries UK'!E:E) -> 0 | P83: =M83+N83-O83 -> 0 | R83: =SUMIF('TB security'!A:A,'HARKAVA '!A83,'TB security'!D:D) -> 0 | S83: =SUMIF('Adj. Entries security'!B:B,'HARKAVA '!A83,'Adj. Entries security'!D:E) -> 0 | T83: =SUMIF('Adj. Entries security'!B:B,'HARKAVA '!A83,'Adj. Entries security'!E:E) -> 0 | U83: =R83+S83-T83 -> 0 | V83: =P83+F83+U83+K83 -> 0 | Y83: =V83+X83 -> 0 | Z83: 5510 | AD83: 0 | AF83: 0 | AG83: 0 | AH83: 0 | AI83: 0 | AK83: 0 | AL83: 0 | AM83: 0 | AN83: 0 | AP83: 0 | AQ83: 0 | AR83: 0 | AS83: 0 | AT83: 0 | AW83: 0 | AY83: =F83-AD83 -> 0 | AZ83: =P83-AN83 -> 0 | BA83: =U83-AS83 -> 0 | BB83: =X83-AV83 -> 0
A84: 5540 | B84: S&M Travel expenses | C84: =SUMIF('TB Mitiga LTD'!A:A,'HARKAVA '!A84,'TB Mitiga LTD'!D:D) -> 192.85 | D84: =SUMIF('Adj Entries Ltd'!$B$4:$B$954,A84,'Adj Entries Ltd'!$D$4:$D$954) -> 0 | E84: =SUMIF('Adj Entries Ltd'!$B$4:$B$954,A84,'Adj Entries Ltd'!$E$4:$E$954) -> 0 | F84: =(+C84+D84-E84) -> 192.85 | H84: =SUMIF('TB US'!A:A,'HARKAVA '!A84,'TB US'!D:D) -> 0 | I84: =SUMIF('Adj. entries US'!B:B,'HARKAVA '!A84,'Adj. entries US'!D:D) -> 0 | J84: =SUMIF('Adj. entries US'!B:B,'HARKAVA '!A84,'Adj. entries US'!E:E) -> 0 | K84: =H84+I84-J84 -> 0 | M84: =SUMIF('TB UK'!A:A,'HARKAVA '!A84,'TB UK'!E:E) -> 3019.17 | N84: =SUMIF('Adj. Entries UK'!B:B,'HARKAVA '!A84,'Adj. Entries UK'!D:D) -> 0 | O84: =SUMIF('Adj. Entries UK'!B:B,'HARKAVA '!A84,'Adj. Entries UK'!E:E) -> 0 | P84: =M84+N84-O84 -> 3019.17 | R84: =SUMIF('TB security'!A:A,'HARKAVA '!A84,'TB security'!D:D) -> 2071.87 | S84: =SUMIF('Adj. Entries security'!B:B,'HARKAVA '!A84,'Adj. Entries security'!D:E) -> 10539.841 | T84: =SUMIF('Adj. Entries security'!B:B,'HARKAVA '!A84,'Adj. Entries security'!E:E) -> 0 | U84: =R84+S84-T84 -> 12611.711 | V84: =P84+F84+U84+K84 -> 15823.731 | Y84: =V84+X84 -> 15823.731 | Z84: =A84 -> 5540 | AD84: 192.85 | AF84: 0 | AG84: 0 | AH84: 0 | AI84: 0 | AK84: 3019.17 | AL84: 0 | AM84: 0 | AN84: 3019.17 | AP84: 2071.87 | AQ84: 10539.841 | AR84: 0 | AS84: 12611.711 | AT84: 15823.731 | AW84: 15823.731 | AY84: =F84-AD84 -> 0 | AZ84: =P84-AN84 -> 0 | BA84: =U84-AS84 -> 0 | BB84: =X84-AV84 -> 0
A85: 5550 | B85: S&M Other | C85: =SUMIF('TB Mitiga LTD'!A:A,'HARKAVA '!A85,'TB Mitiga LTD'!D:D) -> 1457.04 | D85: =SUMIF('Adj Entries Ltd'!$B$4:$B$954,A85,'Adj Entries Ltd'!$D$4:$D$954) -> 0 | E85: =SUMIF('Adj Entries Ltd'!$B$4:$B$954,A85,'Adj Entries Ltd'!$E$4:$E$954) -> 0 | F85: =(+C85+D85-E85) -> 1457.04 | H85: =SUMIF('TB US'!A:A,'HARKAVA '!A85,'TB US'!D:D) -> 0 | I85: =SUMIF('Adj. entries US'!B:B,'HARKAVA '!A85,'Adj. entries US'!D:D) -> 0 | J85: =SUMIF('Adj. entries US'!B:B,'HARKAVA '!A85,'Adj. entries US'!E:E) -> 0 | K85: =H85+I85-J85 -> 0 | M85: =SUMIF('TB UK'!A:A,'HARKAVA '!A85,'TB UK'!E:E) -> 2722 | N85: =SUMIF('Adj. Entries UK'!B:B,'HARKAVA '!A85,'Adj. Entries UK'!D:D) -> 0 | O85: =SUMIF('Adj. Entries UK'!B:B,'HARKAVA '!A85,'Adj. Entries UK'!E:E) -> 0 | P85: =M85+N85-O85 -> 2722 | R85: =SUMIF('TB security'!A:A,'HARKAVA '!A85,'TB security'!D:D) -> 746 | S85: =SUMIF('Adj. Entries security'!B:B,'HARKAVA '!A85,'Adj. Entries security'!D:E) -> 20314.079 | T85: =SUMIF('Adj. Entries security'!B:B,'HARKAVA '!A85,'Adj. Entries security'!E:E) -> 0 | U85: =R85+S85-T85 -> 21060.079 | V85: =P85+F85+U85+K85 -> 25239.119 | Y85: =V85+X85 -> 25239.119 | Z85: 5550 | AD85: 1457.04 | AF85: 0 | AG85: 0 | AH85: 0 | AI85: 0 | AK85: 2722 | AL85: 0 | AM85: 0 | AN85: 2722 | AP85: 746 | AQ85: 20314.079 | AR85: 0 | AS85: 21060.079 | AT85: 25239.119 | AW85: 25239.119 | AY85: =F85-AD85 -> 0 | AZ85: =P85-AN85 -> 0 | BA85: =U85-AS85 -> 0 | BB85: =X85-AV85 -> 0
A86: 5551 | B86: Intercompany expenses | C86: =SUMIF('TB Mitiga LTD'!A:A,'HARKAVA '!A86,'TB Mitiga LTD'!D:D) -> 0 | D86: =SUMIF('Adj Entries Ltd'!$B$4:$B$954,A86,'Adj Entries Ltd'!$D$4:$D$954) -> 2728174 | E86: =SUMIF('Adj Entries Ltd'!$B$4:$B$954,A86,'Adj Entries Ltd'!$E$4:$E$954) -> 0 | F86: =(+C86+D86-E86) -> 2728174 | H86: =SUMIF('TB US'!A:A,'HARKAVA '!A86,'TB US'!D:D) -> 0 | I86: =SUMIF('Adj. entries US'!B:B,'HARKAVA '!A86,'Adj. entries US'!D:D) -> 61840 | J86: =SUMIF('Adj. entries US'!B:B,'HARKAVA '!A86,'Adj. entries US'!E:E) -> 0 | K86: =H86+I86-J86 -> 61840 | M86: =SUMIF('TB UK'!A:A,'HARKAVA '!A86,'TB UK'!E:E) -> 0 | N86: =SUMIF('Adj. Entries UK'!B:B,'HARKAVA '!A86,'Adj. Entries UK'!D:D) -> 0 | O86: =SUMIF('Adj. Entries UK'!B:B,'HARKAVA '!A86,'Adj. Entries UK'!E:E) -> 0 | P86: =M86+N86-O86 -> 0 | R86: =SUMIF('TB security'!A:A,'HARKAVA '!A86,'TB security'!D:D) -> 0 | S86: =SUMIF('Adj. Entries security'!B:B,'HARKAVA '!A86,'Adj. Entries security'!D:E) -> 414915 | T86: =SUMIF('Adj. Entries security'!B:B,'HARKAVA '!A86,'Adj. Entries security'!E:E) -> 0 | U86: =R86+S86-T86 -> 414915 | V86: =P86+F86+U86+K86 -> 3204929 | X86: =-V86 -> -3204929 | Y86: =V86+X86 -> 0 | AD86: 2657924 | AF86: 0 | AG86: 61840 | AH86: 0 | AI86: 61840 | AK86: 0 | AL86: 0 | AM86: 0 | AN86: 0 | AP86: 0 | AQ86: 414915 | AR86: 0 | AS86: 414915 | AT86: 3134679 | AV86: -3134679 | AW86: 0 | AY86: =F86-AD86 -> 70250 | AZ86: =P86-AN86 -> 0 | BA86: =U86-AS86 -> 0 | BB86: =X86-AV86 -> -70250 | BC86: See TP wp
A87: 5600 | B87: G&A Salaries and related expenses | C87: =SUMIF('TB Mitiga LTD'!A:A,'HARKAVA '!A87,'TB Mitiga LTD'!D:D) -> 359435.73 | D87: =SUMIF('Adj Entries Ltd'!$B$4:$B$954,A87,'Adj Entries Ltd'!$D$4:$D$954) -> 169421.5 | E87: =SUMIF('Adj Entries Ltd'!$B$4:$B$954,A87,'Adj Entries Ltd'!$E$4:$E$954) -> 0 | F87: =(+C87+D87-E87) -> 528857.23 | H87: =SUMIF('TB US'!A:A,'HARKAVA '!A87,'TB US'!D:D) -> 0 | I87: =SUMIF('Adj. entries US'!B:B,'HARKAVA '!A87,'Adj. entries US'!D:D) -> 0 | J87: =SUMIF('Adj. entries US'!B:B,'HARKAVA '!A87,'Adj. entries US'!E:E) -> 0 | K87: =H87+I87-J87 -> 0 | M87: =SUMIF('TB UK'!A:A,'HARKAVA '!A87,'TB UK'!E:E) -> 385966.53 | N87: =SUMIF('Adj. Entries UK'!B:B,'HARKAVA '!A87,'Adj. Entries UK'!D:D) -> 0 | O87: =SUMIF('Adj. Entries UK'!B:B,'HARKAVA '!A87,'Adj. Entries UK'!E:E) -> 0 | P87: =M87+N87-O87 -> 385966.53 | R87: =SUMIF('TB security'!A:A,'HARKAVA '!A87,'TB security'!D:D) -> 245189.32 | S87: =SUMIF('Adj. Entries security'!B:B,'HARKAVA '!A87,'Adj. Entries security'!D:E) -> 168653 | T87: =SUMIF('Adj. Entries security'!B:B,'HARKAVA '!A87,'Adj. Entries security'!E:E) -> 0 | U87: =R87+S87-T87 -> 413842.32 | V87: =P87+F87+U87+K87 -> 1328666.1 | Y87: =V87+X87 -> 1328666.1 | Z87: =A87 -> 5600 | AD87: 528857.23 | AF87: 0 | AG87: 0 | AH87: 0 | AI87: 0 | AK87: 385966.53 | AL87: 0 | AM87: 0 | AN87: 385966.53 | AP87: 245189.32 | AQ87: 168653 | AR87: 0 | AS87: 413842.32 | AT87: 1328666.1 | AW87: 1328666.1 | AY87: =F87-AD87 -> 0 | AZ87: =P87-AN87 -> 0 | BA87: =U87-AS87 -> 0 | BB87: =X87-AV87 -> 0
A88: 5601 | B88: G&A Bounses | C88: =SUMIF('TB Mitiga LTD'!A:A,'HARKAVA '!A88,'TB Mitiga LTD'!D:D) -> 0 | D88: =SUMIF('Adj Entries Ltd'!$B$4:$B$954,A88,'Adj Entries Ltd'!$D$4:$D$954) -> 0 | E88: =SUMIF('Adj Entries Ltd'!$B$4:$B$954,A88,'Adj Entries Ltd'!$E$4:$E$954) -> 0 | F88: =(+C88+D88-E88) -> 0 | H88: =SUMIF('TB US'!A:A,'HARKAVA '!A88,'TB US'!D:D) -> 0 | I88: =SUMIF('Adj. entries US'!B:B,'HARKAVA '!A88,'Adj. entries US'!D:D) -> 0 | J88: =SUMIF('Adj. entries US'!B:B,'HARKAVA '!A88,'Adj. entries US'!E:E) -> 0 | K88: =H88+I88-J88 -> 0 | M88: =SUMIF('TB UK'!A:A,'HARKAVA '!A88,'TB UK'!E:E) -> 0 | N88: =SUMIF('Adj. Entries UK'!B:B,'HARKAVA '!A88,'Adj. Entries UK'!D:D) -> 0 | O88: =SUMIF('Adj. Entries UK'!B:B,'HARKAVA '!A88,'Adj. Entries UK'!E:E) -> 0 | P88: =M88+N88-O88 -> 0 | R88: =SUMIF('TB security'!A:A,'HARKAVA '!A88,'TB security'!D:D) -> 0 | S88: =SUMIF('Adj. Entries security'!B:B,'HARKAVA '!A88,'Adj. Entries security'!D:E) -> 0 | T88: =SUMIF('Adj. Entries security'!B:B,'HARKAVA '!A88,'Adj. Entries security'!E:E) -> 0 | U88: =R88+S88-T88 -> 0 | V88: =P88+F88+U88+K88 -> 0 | Y88: =V88+X88 -> 0 | Z88: =A88 -> 5601 | AD88: 0 | AF88: 0 | AG88: 0 | AH88: 0 | AI88: 0 | AK88: 0 | AL88: 0 | AM88: 0 | AN88: 0 | AP88: 0 | AQ88: 0 | AR88: 0 | AS88: 0 | AT88: 0 | AW88: 0 | AY88: =F88-AD88 -> 0 | AZ88: =P88-AN88 -> 0 | BA88: =U88-AS88 -> 0 | BB88: =X88-AV88 -> 0
A89: 5603 | B89: G&A non budgeted items | C89: =SUMIF('TB Mitiga LTD'!A:A,'HARKAVA '!A89,'TB Mitiga LTD'!D:D) -> -12639.69 | D89: =SUMIF('Adj Entries Ltd'!$B$4:$B$954,A89,'Adj Entries Ltd'!$D$4:$D$954) -> 3827 | E89: =SUMIF('Adj Entries Ltd'!$B$4:$B$954,A89,'Adj Entries Ltd'!$E$4:$E$954) -> 0 | F89: =(+C89+D89-E89) -> -8812.69 | H89: =SUMIF('TB US'!A:A,'HARKAVA '!A89,'TB US'!D:D) -> 0 | I89: =SUMIF('Adj. entries US'!B:B,'HARKAVA '!A89,'Adj. entries US'!D:D) -> 0 | J89: =SUMIF('Adj. entries US'!B:B,'HARKAVA '!A89,'Adj. entries US'!E:E) -> 0 | K89: =H89+I89-J89 -> 0 | M89: =SUMIF('TB UK'!A:A,'HARKAVA '!A89,'TB UK'!E:E) -> 780.68 | N89: =SUMIF('Adj. Entries UK'!B:B,'HARKAVA '!A89,'Adj. Entries UK'!D:D) -> 0 | O89: =SUMIF('Adj. Entries UK'!B:B,'HARKAVA '!A89,'Adj. Entries UK'!E:E) -> 0 | P89: =M89+N89-O89 -> 780.68 | R89: =SUMIF('TB security'!A:A,'HARKAVA '!A89,'TB security'!D:D) -> 0 | S89: =SUMIF('Adj. Entries security'!B:B,'HARKAVA '!A89,'Adj. Entries security'!D:E) -> 7034 | T89: =SUMIF('Adj. Entries security'!B:B,'HARKAVA '!A89,'Adj. Entries security'!E:E) -> 0 | U89: =R89+S89-T89 -> 7034 | V89: =P89+F89+U89+K89 -> -998.01 | Y89: =V89+X89 -> -998.01 | Z89: 5603 | AD89: -8812.69 | AF89: 0 | AG89: 0 | AH89: 0 | AI89: 0 | AK89: 780.68 | AL89: 0 | AM89: 0 | AN89: 780.68 | AP89: 0 | AQ89: 7034 | AR89: 0 | AS89: 7034 | AT89: -998.01 | AW89: -998.01 | AY89: =F89-AD89 -> 0 | AZ89: =P89-AN89 -> 0 | BA89: =U89-AS89 -> 0 | BB89: =X89-AV89 -> 0
A90: 5605 | B90: G&A Management fees | C90: =SUMIF('TB Mitiga LTD'!A:A,'HARKAVA '!A90,'TB Mitiga LTD'!D:D) -> 0 | D90: =SUMIF('Adj Entries Ltd'!$B$4:$B$954,A90,'Adj Entries Ltd'!$D$4:$D$954) -> 0 | E90: =SUMIF('Adj Entries Ltd'!$B$4:$B$954,A90,'Adj Entries Ltd'!$E$4:$E$954) -> 0 | F90: =(+C90+D90-E90) -> 0 | H90: =SUMIF('TB US'!A:A,'HARKAVA '!A90,'TB US'!D:D) -> 0 | I90: =SUMIF('Adj. entries US'!B:B,'HARKAVA '!A90,'Adj. entries US'!D:D) -> 0 | J90: =SUMIF('Adj. entries US'!B:B,'HARKAVA '!A90,'Adj. entries US'!E:E) -> 0 | K90: =H90+I90-J90 -> 0 | M90: =SUMIF('TB UK'!A:A,'HARKAVA '!A90,'TB UK'!E:E) -> 0 | N90: =SUMIF('Adj. Entries UK'!B:B,'HARKAVA '!A90,'Adj. Entries UK'!D:D) -> 0 | O90: =SUMIF('Adj. Entries UK'!B:B,'HARKAVA '!A90,'Adj. Entries UK'!E:E) -> 0 | P90: =M90+N90-O90 -> 0 | R90: =SUMIF('TB security'!A:A,'HARKAVA '!A90,'TB security'!D:D) -> 0 | S90: =SUMIF('Adj. Entries security'!B:B,'HARKAVA '!A90,'Adj. Entries security'!D:E) -> 0 | T90: =SUMIF('Adj. Entries security'!B:B,'HARKAVA '!A90,'Adj. Entries security'!E:E) -> 0 | U90: =R90+S90-T90 -> 0 | V90: =P90+F90+U90+K90 -> 0 | Y90: =V90+X90 -> 0 | Z90: 5610 | AD90: 0 | AF90: 0 | AG90: 0 | AH90: 0 | AI90: 0 | AK90: 0 | AL90: 0 | AM90: 0 | AN90: 0 | AP90: 0 | AQ90: 0 | AR90: 0 | AS90: 0 | AT90: 0 | AW90: 0 | AY90: =F90-AD90 -> 0 | AZ90: =P90-AN90 -> 0 | BA90: =U90-AS90 -> 0 | BB90: =X90-AV90 -> 0
A91: 5610 | B91: G&A Professional fees | C91: =SUMIF('TB Mitiga LTD'!A:A,'HARKAVA '!A91,'TB Mitiga LTD'!D:D) -> 626428.46 | D91: =SUMIF('Adj Entries Ltd'!$B$4:$B$954,A91,'Adj Entries Ltd'!$D$4:$D$954) -> 34894.91 | E91: =SUMIF('Adj Entries Ltd'!$B$4:$B$954,A91,'Adj Entries Ltd'!$E$4:$E$954) -> 0 | F91: =(+C91+D91-E91) -> 661323.37 | H91: =SUMIF('TB US'!A:A,'HARKAVA '!A91,'TB US'!D:D) -> 0 | I91: =SUMIF('Adj. entries US'!B:B,'HARKAVA '!A91,'Adj. entries US'!D:D) -> 0 | J91: =SUMIF('Adj. entries US'!B:B,'HARKAVA '!A91,'Adj. entries US'!E:E) -> 0 | K91: =H91+I91-J91 -> 0 | M91: =SUMIF('TB UK'!A:A,'HARKAVA '!A91,'TB UK'!E:E) -> 69596.86 | N91: =SUMIF('Adj. Entries UK'!B:B,'HARKAVA '!A91,'Adj. Entries UK'!D:D) -> 0 | O91: =SUMIF('Adj. Entries UK'!B:B,'HARKAVA '!A91,'Adj. Entries UK'!E:E) -> 0 | P91: =M91+N91-O91 -> 69596.86 | R91: =SUMIF('TB security'!A:A,'HARKAVA '!A91,'TB security'!D:D) -> 175234.12 | S91: =SUMIF('Adj. Entries security'!B:B,'HARKAVA '!A91,'Adj. Entries security'!D:E) -> 0 | T91: =SUMIF('Adj. Entries security'!B:B,'HARKAVA '!A91,'Adj. Entries security'!E:E) -> 0 | U91: =R91+S91-T91 -> 175234.12 | V91: =P91+F91+U91+K91 -> 906154.35 | Y91: =V91+X91 -> 906154.35 | Z91: 5610 | AD91: 626428.46 | AF91: 0 | AG91: 0 | AH91: 0 | AI91: 0 | AK91: 69596.86 | AL91: 0 | AM91: 0 | AN91: 69596.86 | AP91: 175234.12 | AQ91: 0 | AR91: 0 | AS91: 175234.12 | AT91: 871259.44 | AW91: 871259.44 | AY91: =F91-AD91 -> 34894.91 | AZ91: =P91-AN91 -> 0 | BA91: =U91-AS91 -> 0 | BB91: =X91-AV91 -> 0
A92: 5615 | B92: G&A Legal fees for claims | C92: =SUMIF('TB Mitiga LTD'!A:A,'HARKAVA '!A92,'TB Mitiga LTD'!D:D) -> 0 | D92: =SUMIF('Adj Entries Ltd'!$B$4:$B$954,A92,'Adj Entries Ltd'!$D$4:$D$954) -> 0 | E92: =SUMIF('Adj Entries Ltd'!$B$4:$B$954,A92,'Adj Entries Ltd'!$E$4:$E$954) -> 0 | F92: =(+C92+D92-E92) -> 0 | H92: =SUMIF('TB US'!A:A,'HARKAVA '!A92,'TB US'!D:D) -> 0 | I92: =SUMIF('Adj. entries US'!B:B,'HARKAVA '!A92,'Adj. entries US'!D:D) -> 0 | J92: =SUMIF('Adj. entries US'!B:B,'HARKAVA '!A92,'Adj. entries US'!E:E) -> 0 | K92: =H92+I92-J92 -> 0 | M92: =SUMIF('TB UK'!A:A,'HARKAVA '!A92,'TB UK'!E:E) -> 0 | N92: =SUMIF('Adj. Entries UK'!B:B,'HARKAVA '!A92,'Adj. Entries UK'!D:D) -> 0 | O92: =SUMIF('Adj. Entries UK'!B:B,'HARKAVA '!A92,'Adj. Entries UK'!E:E) -> 0 | P92: =M92+N92-O92 -> 0 | R92: =SUMIF('TB security'!A:A,'HARKAVA '!A92,'TB security'!D:D) -> 0 | S92: =SUMIF('Adj. Entries security'!B:B,'HARKAVA '!A92,'Adj. Entries security'!D:E) -> 0 | T92: =SUMIF('Adj. Entries security'!B:B,'HARKAVA '!A92,'Adj. Entries security'!E:E) -> 0 | U92: =R92+S92-T92 -> 0 | V92: =P92+F92+U92+K92 -> 0 | Y92: =V92+X92 -> 0 | Z92: =A92 -> 5615 | AD92: 0 | AF92: 0 | AG92: 0 | AH92: 0 | AI92: 0 | AK92: 0 | AL92: 0 | AM92: 0 | AN92: 0 | AP92: 0 | AQ92: 0 | AR92: 0 | AS92: 0 | AT92: 0 | AW92: 0 | AY92: =F92-AD92 -> 0 | AZ92: =P92-AN92 -> 0 | BA92: =U92-AS92 -> 0 | BB92: =X92-AV92 -> 0
A93: 5620 | B93: G&A Rent, insurance, communication and office maintenance | C93: =SUMIF('TB Mitiga LTD'!A:A,'HARKAVA '!A93,'TB Mitiga LTD'!D:D) -> 341270.8 | D93: =SUMIF('Adj Entries Ltd'!$B$4:$B$954,A93,'Adj Entries Ltd'!$D$4:$D$954) -> 0 | E93: =SUMIF('Adj Entries Ltd'!$B$4:$B$954,A93,'Adj Entries Ltd'!$E$4:$E$954) -> 291746.63 | F93: =(+C93+D93-E93) -> 49524.168 | H93: =SUMIF('TB US'!A:A,'HARKAVA '!A93,'TB US'!D:D) -> 0 | I93: =SUMIF('Adj. entries US'!B:B,'HARKAVA '!A93,'Adj. entries US'!D:D) -> 0 | J93: =SUMIF('Adj. entries US'!B:B,'HARKAVA '!A93,'Adj. entries US'!E:E) -> 0 | K93: =H93+I93-J93 -> 0 | M93: =SUMIF('TB UK'!A:A,'HARKAVA '!A93,'TB UK'!E:E) -> 10178.79 | N93: =SUMIF('Adj. Entries UK'!B:B,'HARKAVA '!A93,'Adj. Entries UK'!D:D) -> 0 | O93: =SUMIF('Adj. Entries UK'!B:B,'HARKAVA '!A93,'Adj. Entries UK'!E:E) -> 0 | P93: =M93+N93-O93 -> 10178.79 | R93: =SUMIF('TB security'!A:A,'HARKAVA '!A93,'TB security'!D:D) -> 6950.2 | S93: =SUMIF('Adj. Entries security'!B:B,'HARKAVA '!A93,'Adj. Entries security'!D:E) -> 0 | T93: =SUMIF('Adj. Entries security'!B:B,'HARKAVA '!A93,'Adj. Entries security'!E:E) -> 5957.3143 | U93: =R93+S93-T93 -> 992.88571 | V93: =P93+F93+U93+K93 -> 60695.844 | Y93: =V93+X93 -> 60695.844 | Z93: =A93 -> 5620 | AD93: 49524.168 | AF93: 0 | AG93: 0 | AH93: 0 | AI93: 0 | AK93: 10178.79 | AL93: 0 | AM93: 0 | AN93: 10178.79 | AP93: 6950.2 | AQ93: 0 | AR93: 5957.3143 | AS93: 992.88571 | AT93: 60695.844 | AW93: 60695.844 | AY93: =F93-AD93 -> 0 | AZ93: =P93-AN93 -> 0 | BA93: =U93-AS93 -> 0 | BB93: =X93-AV93 -> 0
A94: 5630 | B94: G&A car expenses | C94: =SUMIF('TB Mitiga LTD'!A:A,'HARKAVA '!A94,'TB Mitiga LTD'!D:D) -> 0 | D94: =SUMIF('Adj Entries Ltd'!$B$4:$B$954,A94,'Adj Entries Ltd'!$D$4:$D$954) -> 0 | E94: =SUMIF('Adj Entries Ltd'!$B$4:$B$954,A94,'Adj Entries Ltd'!$E$4:$E$954) -> 0 | F94: =(+C94+D94-E94) -> 0 | H94: =SUMIF('TB US'!A:A,'HARKAVA '!A94,'TB US'!D:D) -> 0 | I94: =SUMIF('Adj. entries US'!B:B,'HARKAVA '!A94,'Adj. entries US'!D:D) -> 0 | J94: =SUMIF('Adj. entries US'!B:B,'HARKAVA '!A94,'Adj. entries US'!E:E) -> 0 | K94: =H94+I94-J94 -> 0 | M94: =SUMIF('TB UK'!A:A,'HARKAVA '!A94,'TB UK'!E:E) -> 0 | N94: =SUMIF('Adj. Entries UK'!B:B,'HARKAVA '!A94,'Adj. Entries UK'!D:D) -> 0 | O94: =SUMIF('Adj. Entries UK'!B:B,'HARKAVA '!A94,'Adj. Entries UK'!E:E) -> 0 | P94: =M94+N94-O94 -> 0 | R94: =SUMIF('TB security'!A:A,'HARKAVA '!A94,'TB security'!D:D) -> 0 | S94: =SUMIF('Adj. Entries security'!B:B,'HARKAVA '!A94,'Adj. Entries security'!D:E) -> 0 | T94: =SUMIF('Adj. Entries security'!B:B,'HARKAVA '!A94,'Adj. Entries security'!E:E) -> 0 | U94: =R94+S94-T94 -> 0 | V94: =P94+F94+U94+K94 -> 0 | Y94: =V94+X94 -> 0 | Z94: =A94 -> 5630 | AD94: 0 | AF94: 0 | AG94: 0 | AH94: 0 | AI94: 0 | AK94: 0 | AL94: 0 | AM94: 0 | AN94: 0 | AP94: 0 | AQ94: 0 | AR94: 0 | AS94: 0 | AT94: 0 | AW94: 0 | AY94: =F94-AD94 -> 0 | AZ94: =P94-AN94 -> 0 | BA94: =U94-AS94 -> 0 | BB94: =X94-AV94 -> 0
A95: 5635 | B95: Insurance (Directors and office) | C95: =SUMIF('TB Mitiga LTD'!A:A,'HARKAVA '!A95,'TB Mitiga LTD'!D:D) -> 0 | D95: =SUMIF('Adj Entries Ltd'!$B$4:$B$954,A95,'Adj Entries Ltd'!$D$4:$D$954) -> 0 | E95: =SUMIF('Adj Entries Ltd'!$B$4:$B$954,A95,'Adj Entries Ltd'!$E$4:$E$954) -> 0 | F95: =(+C95+D95-E95) -> 0 | H95: =SUMIF('TB US'!A:A,'HARKAVA '!A95,'TB US'!D:D) -> 0 | I95: =SUMIF('Adj. entries US'!B:B,'HARKAVA '!A95,'Adj. entries US'!D:D) -> 0 | J95: =SUMIF('Adj. entries US'!B:B,'HARKAVA '!A95,'Adj. entries US'!E:E) -> 0 | K95: =H95+I95-J95 -> 0 | M95: =SUMIF('TB UK'!A:A,'HARKAVA '!A95,'TB UK'!E:E) -> 0 | N95: =SUMIF('Adj. Entries UK'!B:B,'HARKAVA '!A95,'Adj. Entries UK'!D:D) -> 0 | O95: =SUMIF('Adj. Entries UK'!B:B,'HARKAVA '!A95,'Adj. Entries UK'!E:E) -> 0 | P95: =M95+N95-O95 -> 0 | R95: =SUMIF('TB security'!A:A,'HARKAVA '!A95,'TB security'!D:D) -> 0 | S95: =SUMIF('Adj. Entries security'!B:B,'HARKAVA '!A95,'Adj. Entries security'!D:E) -> 0 | T95: =SUMIF('Adj. Entries security'!B:B,'HARKAVA '!A95,'Adj. Entries security'!E:E) -> 0 | U95: =R95+S95-T95 -> 0 | V95: =P95+F95+U95+K95 -> 0 | Y95: =V95+X95 -> 0 | Z95: =A95 -> 5635 | AD95: 0 | AF95: 0 | AG95: 0 | AH95: 0 | AI95: 0 | AK95: 0 | AL95: 0 | AM95: 0 | AN95: 0 | AP95: 0 | AQ95: 0 | AR95: 0 | AS95: 0 | AT95: 0 | AW95: 0 | AY95: =F95-AD95 -> 0 | AZ95: =P95-AN95 -> 0 | BA95: =U95-AS95 -> 0 | BB95: =X95-AV95 -> 0
A96: 5640 | B96: Directors' fees | C96: =SUMIF('TB Mitiga LTD'!A:A,'HARKAVA '!A96,'TB Mitiga LTD'!D:D) -> 0 | D96: =SUMIF('Adj Entries Ltd'!$B$4:$B$954,A96,'Adj Entries Ltd'!$D$4:$D$954) -> 0 | E96: =SUMIF('Adj Entries Ltd'!$B$4:$B$954,A96,'Adj Entries Ltd'!$E$4:$E$954) -> 0 | F96: =(+C96+D96-E96) -> 0 | H96: =SUMIF('TB US'!A:A,'HARKAVA '!A96,'TB US'!D:D) -> 0 | I96: =SUMIF('Adj. entries US'!B:B,'HARKAVA '!A96,'Adj. entries US'!D:D) -> 0 | J96: =SUMIF('Adj. entries US'!B:B,'HARKAVA '!A96,'Adj. entries US'!E:E) -> 0 | K96: =H96+I96-J96 -> 0 | M96: =SUMIF('TB UK'!A:A,'HARKAVA '!A96,'TB UK'!E:E) -> 0 | N96: =SUMIF('Adj. Entries UK'!B:B,'HARKAVA '!A96,'Adj. Entries UK'!D:D) -> 0 | O96: =SUMIF('Adj. Entries UK'!B:B,'HARKAVA '!A96,'Adj. Entries UK'!E:E) -> 0 | P96: =M96+N96-O96 -> 0 | R96: =SUMIF('TB security'!A:A,'HARKAVA '!A96,'TB security'!D:D) -> 0 | S96: =SUMIF('Adj. Entries security'!B:B,'HARKAVA '!A96,'Adj. Entries security'!D:E) -> 0 | T96: =SUMIF('Adj. Entries security'!B:B,'HARKAVA '!A96,'Adj. Entries security'!E:E) -> 0 | U96: =R96+S96-T96 -> 0 | V96: =P96+F96+U96+K96 -> 0 | Y96: =V96+X96 -> 0 | Z96: =A96 -> 5640 | AD96: 0 | AF96: 0 | AG96: 0 | AH96: 0 | AI96: 0 | AK96: 0 | AL96: 0 | AM96: 0 | AN96: 0 | AP96: 0 | AQ96: 0 | AR96: 0 | AS96: 0 | AT96: 0 | AW96: 0 | AY96: =F96-AD96 -> 0 | AZ96: =P96-AN96 -> 0 | BA96: =U96-AS96 -> 0 | BB96: =X96-AV96 -> 0
A97: 5645 | B97: Directors' ESOP | C97: =SUMIF('TB Mitiga LTD'!A:A,'HARKAVA '!A97,'TB Mitiga LTD'!D:D) -> 0 | D97: =SUMIF('Adj Entries Ltd'!$B$4:$B$954,A97,'Adj Entries Ltd'!$D$4:$D$954) -> 0 | E97: =SUMIF('Adj Entries Ltd'!$B$4:$B$954,A97,'Adj Entries Ltd'!$E$4:$E$954) -> 0 | F97: =(+C97+D97-E97) -> 0 | H97: =SUMIF('TB US'!A:A,'HARKAVA '!A97,'TB US'!D:D) -> 0 | I97: =SUMIF('Adj. entries US'!B:B,'HARKAVA '!A97,'Adj. entries US'!D:D) -> 0 | J97: =SUMIF('Adj. entries US'!B:B,'HARKAVA '!A97,'Adj. entries US'!E:E) -> 0 | K97: =H97+I97-J97 -> 0 | M97: =SUMIF('TB UK'!A:A,'HARKAVA '!A97,'TB UK'!E:E) -> 0 | N97: =SUMIF('Adj. Entries UK'!B:B,'HARKAVA '!A97,'Adj. Entries UK'!D:D) -> 0 | O97: =SUMIF('Adj. Entries UK'!B:B,'HARKAVA '!A97,'Adj. Entries UK'!E:E) -> 0 | P97: =M97+N97-O97 -> 0 | R97: =SUMIF('TB security'!A:A,'HARKAVA '!A97,'TB security'!D:D) -> 0 | S97: =SUMIF('Adj. Entries security'!B:B,'HARKAVA '!A97,'Adj. Entries security'!D:E) -> 0 | T97: =SUMIF('Adj. Entries security'!B:B,'HARKAVA '!A97,'Adj. Entries security'!E:E) -> 0 | U97: =R97+S97-T97 -> 0 | V97: =P97+F97+U97+K97 -> 0 | Y97: =V97+X97 -> 0 | Z97: =A97 -> 5645 | AD97: 0 | AF97: 0 | AG97: 0 | AH97: 0 | AI97: 0 | AK97: 0 | AL97: 0 | AM97: 0 | AN97: 0 | AP97: 0 | AQ97: 0 | AR97: 0 | AS97: 0 | AT97: 0 | AW97: 0 | AY97: =F97-AD97 -> 0 | AZ97: =P97-AN97 -> 0 | BA97: =U97-AS97 -> 0 | BB97: =X97-AV97 -> 0
A98: 5680 | B98: G&A travel | C98: =SUMIF('TB Mitiga LTD'!A:A,'HARKAVA '!A98,'TB Mitiga LTD'!D:D) -> 12400.91 | D98: =SUMIF('Adj Entries Ltd'!$B$4:$B$954,A98,'Adj Entries Ltd'!$D$4:$D$954) -> 0 | E98: =SUMIF('Adj Entries Ltd'!$B$4:$B$954,A98,'Adj Entries Ltd'!$E$4:$E$954) -> 0 | F98: =(+C98+D98-E98) -> 12400.91 | H98: =SUMIF('TB US'!A:A,'HARKAVA '!A98,'TB US'!D:D) -> 0 | I98: =SUMIF('Adj. entries US'!B:B,'HARKAVA '!A98,'Adj. entries US'!D:D) -> 0 | J98: =SUMIF('Adj. entries US'!B:B,'HARKAVA '!A98,'Adj. entries US'!E:E) -> 0 | K98: =H98+I98-J98 -> 0 | M98: =SUMIF('TB UK'!A:A,'HARKAVA '!A98,'TB UK'!E:E) -> 17359.04 | N98: =SUMIF('Adj. Entries UK'!B:B,'HARKAVA '!A98,'Adj. Entries UK'!D:D) -> 0 | O98: =SUMIF('Adj. Entries UK'!B:B,'HARKAVA '!A98,'Adj. Entries UK'!E:E) -> 0 | P98: =M98+N98-O98 -> 17359.04 | R98: =SUMIF('TB security'!A:A,'HARKAVA '!A98,'TB security'!D:D) -> 33870.35 | S98: =SUMIF('Adj. Entries security'!B:B,'HARKAVA '!A98,'Adj. Entries security'!D:E) -> 0 | T98: =SUMIF('Adj. Entries security'!B:B,'HARKAVA '!A98,'Adj. Entries security'!E:E) -> 22766.057 | U98: =R98+S98-T98 -> 11104.293 | V98: =P98+F98+U98+K98 -> 40864.243 | Y98: =V98+X98 -> 40864.243 | Z98: 5680 | AD98: 12400.91 | AF98: 0 | AG98: 0 | AH98: 0 | AI98: 0 | AK98: 17359.04 | AL98: 0 | AM98: 0 | AN98: 17359.04 | AP98: 33870.35 | AQ98: 0 | AR98: 22766.057 | AS98: 11104.293 | AT98: 40864.243 | AW98: 40864.243 | AY98: =F98-AD98 -> 0 | AZ98: =P98-AN98 -> 0 | BA98: =U98-AS98 -> 0 | BB98: =X98-AV98 -> 0
A99: 5670 | B99: G&A Depreciation and amortization | C99: =SUMIF('TB Mitiga LTD'!A:A,'HARKAVA '!A99,'TB Mitiga LTD'!D:D) -> 9230.93 | D99: =SUMIF('Adj Entries Ltd'!$B$4:$B$954,A99,'Adj Entries Ltd'!$D$4:$D$954) -> 0 | E99: =SUMIF('Adj Entries Ltd'!$B$4:$B$954,A99,'Adj Entries Ltd'!$E$4:$E$954) -> 0 | F99: =(+C99+D99-E99) -> 9230.93 | H99: =SUMIF('TB US'!A:A,'HARKAVA '!A99,'TB US'!D:D) -> 0 | I99: =SUMIF('Adj. entries US'!B:B,'HARKAVA '!A99,'Adj. entries US'!D:D) -> 0 | J99: =SUMIF('Adj. entries US'!B:B,'HARKAVA '!A99,'Adj. entries US'!E:E) -> 0 | K99: =H99+I99-J99 -> 0 | M99: =SUMIF('TB UK'!A:A,'HARKAVA '!A99,'TB UK'!E:E) -> 2061 | N99: =SUMIF('Adj. Entries UK'!B:B,'HARKAVA '!A99,'Adj. Entries UK'!D:D) -> 0 | O99: =SUMIF('Adj. Entries UK'!B:B,'HARKAVA '!A99,'Adj. Entries UK'!E:E) -> 0 | P99: =M99+N99-O99 -> 2061 | R99: =SUMIF('TB security'!A:A,'HARKAVA '!A99,'TB security'!D:D) -> 633 | S99: =SUMIF('Adj. Entries security'!B:B,'HARKAVA '!A99,'Adj. Entries security'!D:E) -> 0 | T99: =SUMIF('Adj. Entries security'!B:B,'HARKAVA '!A99,'Adj. Entries security'!E:E) -> 0 | U99: =R99+S99-T99 -> 633 | V99: =P99+F99+U99+K99 -> 11924.93 | Y99: =V99+X99 -> 11924.93 | Z99: 5620 | AD99: 9230.93 | AF99: 0 | AG99: 0 | AH99: 0 | AI99: 0 | AK99: 2061 | AL99: 0 | AM99: 0 | AN99: 2061 | AP99: 633 | AQ99: 0 | AR99: 0 | AS99: 633 | AT99: 11924.93 | AW99: 11924.93 | AY99: =F99-AD99 -> 0 | AZ99: =P99-AN99 -> 0 | BA99: =U99-AS99 -> 0 | BB99: =X99-AV99 -> 0
A100: 5660 | B100: G&A Other | C100: =SUMIF('TB Mitiga LTD'!A:A,'HARKAVA '!A100,'TB Mitiga LTD'!D:D) -> 275738.14 | D100: =SUMIF('Adj Entries Ltd'!$B$4:$B$954,A100,'Adj Entries Ltd'!$D$4:$D$954) -> 0 | E100: =SUMIF('Adj Entries Ltd'!$B$4:$B$954,A100,'Adj Entries Ltd'!$E$4:$E$954) -> 199907.75 | F100: =(+C100+D100-E100) -> 75830.387 | H100: =SUMIF('TB US'!A:A,'HARKAVA '!A100,'TB US'!D:D) -> 1279.6 | I100: =SUMIF('Adj. entries US'!B:B,'HARKAVA '!A100,'Adj. entries US'!D:D) -> 0 | J100: =SUMIF('Adj. entries US'!B:B,'HARKAVA '!A100,'Adj. entries US'!E:E) -> 0 | K100: =H100+I100-J100 -> 1279.6 | M100: =SUMIF('TB UK'!A:A,'HARKAVA '!A100,'TB UK'!E:E) -> 27052.29 | N100: =SUMIF('Adj. Entries UK'!B:B,'HARKAVA '!A100,'Adj. Entries UK'!D:D) -> 0 | O100: =SUMIF('Adj. Entries UK'!B:B,'HARKAVA '!A100,'Adj. Entries UK'!E:E) -> 0 | P100: =M100+N100-O100 -> 27052.29 | R100: =SUMIF('TB security'!A:A,'HARKAVA '!A100,'TB security'!D:D) -> 91041.55 | S100: =SUMIF('Adj. Entries security'!B:B,'HARKAVA '!A100,'Adj. Entries security'!D:E) -> 0 | T100: =SUMIF('Adj. Entries security'!B:B,'HARKAVA '!A100,'Adj. Entries security'!E:E) -> 37921.097 | U100: =R100+S100-T100 -> 53120.453 | V100: =P100+F100+U100+K100 -> 157282.73 | Y100: =V100+X100 -> 157282.73 | Z100: =A100 -> 5660 | AD100: 75830.387 | AF100: 1279.6 | AG100: 0 | AH100: 0 | AI100: 1279.6 | AK100: 27052.29 | AL100: 0 | AM100: 0 | AN100: 27052.29 | AP100: 64391.55 | AQ100: 0 | AR100: 37921.097 | AS100: 26470.453 | AT100: 130632.73 | AW100: 130632.73 | AY100: =F100-AD100 -> 0 | AZ100: =P100-AN100 -> 0 | BA100: =U100-AS100 -> 26650 | BB100: =X100-AV100 -> 0 | BC100: Expenses recorded for 2021 Delaware registration fees that was paid in March 2022
...

Sheet intercompany
B1: Security | C1: Ltd. | D1: UK | E1: USA
A2: Security | C2: 200000 | E2: 600 | F2: =SUM(B2:E2) -> 200600
A3: Ltd. | B3: -200000 | D3: =-113464-506459 -> -619923 | E3: -5000 | F3: =SUM(B3:E3) -> -824923
A4: UK | C4: =113464+506459 -> 619923 | E4: -2502.03 | F4: =SUM(B4:E4) -> 617420.97
A5: USA | B5: -600 | C5: 5000 | D5: 2502 | F5: =SUM(B5:E5) -> 6902
B6: =SUM(B2:B5) -> -200600 | C6: =SUM(C2:C5) -> 824923 | D6: =SUM(D2:D5) -> -617421 | E6: =SUM(E2:E5) -> -6902.03 | F6: =SUM(F2:F5) -> -0.03
A13: TP
B15: Security | C15: Ltd. | D15: USA | E15: UK | H15: =1050905 -> 1050905
A16: Security | C16: -323155 | E16: 346161 | F16: 23006 | H16: 669316
A17: Ltd. | B17: 323155 | D17: -36948 | E17: -344641 | F17: -58434 | H17: =H15-H16 -> 381589
A18: USA | C18: 36948 | F18: 36948
A19: UK | B19: -346161 | C19: 344641 | F19: -1520
B20: -23006 | C20: 58434 | D20: -36948 | E20: 1520 | F20: 0

Sheet budget
I2: 2021
I3: Q1 | M3: Q2
I4: Jan | J4: Feb | K4: Mar | L4: Q1 | M4: Apr | N4: May | O4: Jun | P4: Q2 | Q4: Jul | R4: Aug | S4: Sep | T4: Q3 | U4: code | V4: Oct | W4: Nov | X4: Dec | Y4: Q4 total
B5: Role/Function | C5: Name/Vendor | D5: Salary | E5: Cost | F5: Bonus | G5: Comment
B7: Head count | I7: =I182+I135+I26 -> 18.8 | J7: =J182+J135+J26 -> 20.8 | K7: =K182+K135+K26 -> 21.8 | M7: =M182+M135+M26 -> 25.8 | N7: =N182+N135+N26 -> 26.8 | O7: =O182+O135+O26 -> 29.8 | R7: 45.8 | S7: 46.8 | V7: 53.8 | W7: 53.8 | X7: 53.8
B9: Founders, Management & General
B10: Founders
A11: * | B11: CEO | C11: Tal Mozes | D11: 185000 | E11: =D11*[4]Assumptions!B15*[4]Assumptions!B13/12 -> 26979.167 | F11: 100K | I11: 23664.773 | J11: 23664.773 | K11: 23664.773 | L11: =SUM(I11:K11) -> 70994.318 | M11: 23664.773 | N11: 23664.773 | O11: 23664.773 | P11: =SUM(M11:O11) -> 70994.318 | Q11: 26979.167 | R11: 26979.167 | S11: 26979.167 | T11: =SUM(Q11:S11) -> 80937.5 | U11: 5600 | V11: 26979.167 | W11: 26979.167 | X11: 126979.17 | Y11: =+SUM(V11:X11) -> 180937.5
A12: * | B12: Chief Delivery Officer | C12: Ariel Parnes | D12: 280000 | E12: =D12*[4]Assumptions!B14/12 -> 28000 | F12: 100K | G12: 50% G&A (50% Delivery) | I12: =19727.2727272727*0.5 -> 9863.6364 | J12: =I12 -> 9863.6364 | K12: =J12 -> 9863.6364 | L12: =SUM(I12:K12) -> 29590.909 | M12: =K12 -> 9863.6364 | N12: =M12 -> 9863.6364 | O12: =N12 -> 9863.6364 | P12: =SUM(M12:O12) -> 29590.909 | Q12: 14000 | R12: 14000 | S12: 14000 | T12: =SUM(Q12:S12) -> 42000 | U12: 5600 | V12: 14000 | W12: 14000 | X12: 64000 | Y12: =+SUM(V12:X12) -> 92000
A13: * | B13: CTO | C13: Ofer Maor | D13: 55000 | E13: =D13*[4]Assumptions!B11/[4]Assumptions!B12 -> 21666.667 | F13: 100K | G13: 20% G&A (80% R&D) | I13: =I12*2*0.2 -> 3945.4545 | J13: =I13 -> 3945.4545 | K13: =J13 -> 3945.4545 | L13: =SUM(I13:K13) -> 11836.364 | M13: =K13 -> 3945.4545 | N13: =M13 -> 3945.4545 | O13: =N13 -> 3945.4545 | P13: =SUM(M13:O13) -> 11836.364 | Q13: 4333.3333 | R13: 4333.3333 | S13: 4333.3333 | T13: =SUM(Q13:S13) -> 13000 | U13: 5600 | V13: 4333.3333 | W13: 4333.3333 | X13: 24333.333 | Y13: =+SUM(V13:X13) -> 33000
A14: * | B14: CFO | D14: 225000 | E14: =D14*[4]Assumptions!B14/12 -> 22500 | F14: 0.15 | I14: 0 | J14: =I14 -> 0 | K14: =J14 -> 0 | L14: =SUM(I14:K14) -> 0 | M14: =K14 -> 0 | N14: =M14 -> 0 | O14: =275*19 -> 5225 | P14: =SUM(M14:O14) -> 5225 | Q14: 27500 | R14: 27500 | S14: 27500 | T14: =SUM(Q14:S14) -> 82500 | U14: 5610 | V14: 27500 | W14: 27500 | X14: 27500 | Y14: =+SUM(V14:X14) -> 82500
B15: VP HR | C15: TBD | D15: 50000 | E15: =D15*[4]Assumptions!B11/[4]Assumptions!B12 -> 19696.97 | F15: 0.1 | I15: =15000*[4]Assumptions!$B$11/[4]Assumptions!$B$12 -> 5909.0909 | J15: =21000*[4]Assumptions!$B$11/[4]Assumptions!$B$12 -> 8272.7273 | K15: =J15 -> 8272.7273 | L15: =SUM(I15:K15) -> 22454.545 | M15: =K15 -> 8272.7273 | N15: =M15 -> 8272.7273 | O15: =N15 -> 8272.7273 | P15: =SUM(M15:O15) -> 24818.182 | Q15: 19696.97 | R15: 19696.97 | S15: 19696.97 | T15: =SUM(Q15:S15) -> 59090.909 | U15: 5600 | V15: 19696.97 | W15: 19696.97 | X15: 36242.424 | Y15: =+SUM(V15:X15) -> 75636.364
B16: Director Operations | C16: TBD | D16: 175000 | E16: =D16*[4]Assumptions!B14/12 -> 17500 | F16: 0.1 | L16: =SUM(I16:K16) -> 0 | P16: =SUM(M16:O16) -> 0
L17: =SUM(I17:K17) -> 0 | P17: =SUM(M17:O17) -> 0
B18: Other G&A Staff | L18: =SUM(I18:K18) -> 0 | P18: =SUM(M18:O18) -> 0
A19: * | B19: Operation/Finance Staff | C19: Noa | E19: 7500 | F19: 0.15 | I19: 6204.5455 | J19: 6204.5455 | K19: 6204.5455 | L19: =SUM(I19:K19) -> 18613.636 | M19: 6204.5455 | N19: =M19 -> 6204.5455 | O19: =N19 -> 6204.5455 | P19: =SUM(M19:O19) -> 18613.636 | Q19: 7500 | R19: 7500 | S19: 7500 | T19: =SUM(Q19:S19) -> 22500 | U19: 5600 | V19: 7500 | W19: 7500 | X19: 19834.091 | Y19: =+SUM(V19:X19) -> 34834.091
Q20: 1 | R20: 1 | V20: 1 | W20: 1 | X20: 1
A21: * | B21: Admins | C21: Eden | E21: 6000 | I21: 0 | J21: =I21 -> 0 | K21: =J21 -> 0 | L21: =SUM(I21:K21) -> 0 | M21: =K21 -> 0 | N21: 1970 | O21: 1970 | P21: =SUM(M21:O21) -> 3940 | Q21: 6000 | R21: 6000 | S21: 6000 | T21: =SUM(Q21:S21) -> 18000 | U21: 5600 | V21: 6000 | W21: 6000 | X21: 6000 | Y21: =+SUM(V21:X21) -> 18000
L22: =SUM(I22:K22) -> 0 | Q22: 1 | R22: 1 | V22: 1 | W22: 1 | X22: 1
B23: Recruiters/HR Staff | C23: Shiran | E23: 10000 | L23: =SUM(I23:K23) -> 0 | O23: 7879 | P23: =SUM(M23:O23) -> 7879 | Q23: 20000 | R23: 20000 | S23: 20000 | T23: =SUM(Q23:S23) -> 60000 | U23: 5600 | V23: 20000 | W23: 20000 | X23: 20000 | Y23: =+SUM(V23:X23) -> 60000
Q24: 2 | R24: 2 | V24: 2 | W24: 2 | X24: 2
P25: =SUM(M25:O25) -> 0
B26: ------------------------------------- | C26: ------------------------- | D26: -------------- | G26: Employee Count | I26: =COUNTIF(I11:I19,">0")+I22+I24 -> 5 | J26: =COUNTIF(J11:J19,">0")+J22+J24 -> 5 | K26: =COUNTIF(K11:K19,">0")+K22+K24 -> 5 | M26: =COUNTIF(M11:M19,">0")+M22+M24 -> 5 | N26: =COUNTIF(N11:N19,">0")+N22+N24 -> 5 | O26: =COUNTIF(O11:O19,">0")+O22+O24 -> 6 | Q26: 9 | R26: 9 | V26: 9 | W26: 9 | X26: 9
G27: Subtotal FMG Salaries | I27: =SUBTOTAL(9,I11:I19)+I21+I23 -> 49587.5 | J27: =SUBTOTAL(9,J11:J19)+J21+J23 -> 51951.136 | K27: =SUBTOTAL(9,K11:K19)+K21+K23 -> 51951.136 | L27: =SUBTOTAL(9,L11:L19)+L21+L23 -> 153489.77 | M27: =SUBTOTAL(9,M11:M19)+M21+M23 -> 51951.136 | N27: =SUBTOTAL(9,N11:N19)+N21+N23 -> 53921.136 | O27: =SUBTOTAL(9,O11:O19)+O21+O23 -> 67025.136 | P27: =SUBTOTAL(9,P11:P19)+P21+P23 -> 172897.41 | ... T27: =SUBTOTAL(9,T11:T19)+T21+T23 -> 378028.41 | V27: 126009.47 | W27: 126009.47 | X27: 324889.02 | Y27: =SUBTOTAL(9,Y11:Y19)+Y21+Y23 -> 576907.95
B28: Expenses | L28: =SUM(I28:K28) -> 0
B29: IT (Laptop, Phone, etc.) | C29: Dell/Apple | E29: 150 | G29: Monthly per Employee | I29: =$E$29*I26 -> 750 | J29: =$E$29*J26 -> 750 | K29: =$E$29*K26 -> 750 | L29: =SUM(I29:K29) -> 2250 | M29: =$E$29*M26 -> 750 | N29: 825 | O29: 1125 | P29: =SUM(M29:O29) -> 2700 | Q29: 1350 | R29: 1350 | S29: 1350 | T29: =SUM(Q29:S29) -> 4050 | U29: 5660 | V29: 1350 | W29: 1350 | X29: 1350 | Y29: =SUM(V29:X29) -> 4050
B30: Welfare (10Bis, Misc.) | E30: 500 | G30: Monthly per Employee | I30: =$E$30*I26 -> 2500 | J30: =$E$30*J26 -> 2500 | K30: =$E$30*K26 -> 2500 | L30: =SUM(I30:K30) -> 7500 | M30: =$E$30*M26 -> 2500 | N30: 2750 | O30: 3750 | P30: =SUM(M30:O30) -> 9000 | Q30: 4500 | R30: 4500 | S30: 4500 | T30: =SUM(Q30:S30) -> 13500 | U30: 5660 | V30: 4500 | W30: 4500 | X30: 4500 | Y30: =SUM(V30:X30) -> 13500
B31: Licensing, Phone Plans, etc. | C31: 150$/Month/Employee | E31: 150 | G31: Monthly per Employee | I31: =I26*$E31 -> 750 | J31: =J26*$E31 -> 750 | K31: =K26*$E31 -> 750 | L31: =SUM(I31:K31) -> 2250 | M31: =M26*$E31 -> 750 | N31: 825 | O31: 1125 | P31: =SUM(M31:O31) -> 2700 | Q31: 1350 | R31: 1350 | S31: 1350 | T31: =SUM(Q31:S31) -> 4050 | U31: 5660 | V31: 1350 | W31: 1350 | X31: 1350 | Y31: =SUM(V31:X31) -> 4050
B32: ------------------------------------- | C32: ------------------------- | D32: -------------- | L32: =SUM(I32:K32) -> 0 | P32: =SUM(M32:O32) -> 0
B33: Offices, Israel | C33: BE ALL | G33: Inc. all (Parking, cleaning, etc). | I33: 16000 | J33: 16000 | K33: 16000 | L33: =SUM(I33:K33) -> 48000 | M33: 17500 | N33: 17500 | O33: 17500 | P33: =SUM(M33:O33) -> 52500 | Q33: 20000 | R33: 20000 | S33: 20000 | T33: =SUM(Q33:S33) -> 60000 | U33: 5620 | V33: 25000 | W33: 25000 | X33: 25000 | Y33: =SUM(V33:X33) -> 75000
B34: Relocation expenses - Ariel | K34: =70000/7 -> 10000 | L34: =SUM(I34:K34) -> 10000 | M34: =70000/7 -> 10000 | N34: =70000/7 -> 10000 | O34: =70000/7 -> 10000 | P34: =SUM(M34:O34) -> 30000 | Q34: 10000 | R34: 10000 | S34: 10000 | T34: =SUM(Q34:S34) -> 30000 | U34: 5660 | V34: 10000 | W34: 10000 | X34: 10000 | Y34: =SUM(V34:X34) -> 30000
B35: Relocation professional advise | L35: =SUM(I35:K35) -> 0 | P35: =SUM(M35:O35) -> 0
B36: Ofice Expenses, Israel | I36: 0 | J36: 0 | K36: 0 | L36: =SUM(I36:K36) -> 0 | M36: 0 | N36: 0 | O36: 0 | P36: =SUM(M36:O36) -> 0 | Q36: 0 | R36: 0 | S36: 0 | T36: =SUM(Q36:S36) -> 0 | Y36: =SUM(V36:X36) -> 0
B37: Offices, UK | G37: Inc. all (Parking, cleaning, etc). | I37: 2500 | J37: 2500 | K37: 2500 | L37: =SUM(I37:K37) -> 7500 | M37: 2500 | N37: 2500 | O37: 2500 | P37: =SUM(M37:O37) -> 7500 | Q37: 2500 | R37: 2500 | S37: 2500 | T37: =SUM(Q37:S37) -> 7500 | U37: 5620 | V37: 2500 | W37: 2500 | X37: 2500 | Y37: =SUM(V37:X37) -> 7500
B38: Offices, US | G38: Inc. all (Parking, cleaning, etc). | I38: 3000 | J38: 3000 | K38: 3000 | L38: =SUM(I38:K38) -> 9000 | M38: 3000 | N38: 3000 | O38: 3000 | P38: =SUM(M38:O38) -> 9000 | Q38: 10000 | R38: 10000 | S38: 10000 | T38: =SUM(Q38:S38) -> 30000 | U38: 5620 | V38: 10000 | W38: 10000 | X38: 10000 | Y38: =SUM(V38:X38) -> 30000
B39: Travel (Non Sales/Billable) | I39: 0 | J39: 0 | K39: 0 | L39: =SUM(I39:K39) -> 0 | M39: =10000/3 -> 3333.3333 | N39: =10000/3 -> 3333.3333 | O39: =10000/3 -> 3333.3333 | P39: =SUM(M39:O39) -> 10000 | Q39: 5000 | R39: 5000 | S39: 5000 | T39: =SUM(Q39:S39) -> 15000 | U39: 5680 | V39: 8333.3333 | W39: 8333.3333 | X39: 8333.3333 | Y39: =SUM(V39:X39) -> 25000
B40: IT retainer | L40: =SUM(I40:K40) -> 0 | P40: =SUM(M40:O40) -> 0 | S40: 0
B41: IT Consulting | C41: netsuite | L41: =SUM(I41:K41) -> 0 | P41: =SUM(M41:O41) -> 0 | R41: 3333.3333 | S41: 3333.3333 | T41: =SUM(Q41:S41) -> 6666.6667 | U41: 5610 | V41: 3333.3333 | W41: 3333.3333 | X41: 3333.3333 | Y41: =SUM(V41:X41) -> 10000
B42: Legal Retainer - Israel | C42: Banai Azriel Stern | G42: Monthly Fee | I42: 20000 | J42: =I42 -> 20000 | K42: =J42 -> 20000 | L42: =SUM(I42:K42) -> 60000 | M42: =K42 -> 20000 | N42: =M42 -> 20000 | O42: =N42 -> 20000 | P42: =SUM(M42:O42) -> 60000 | Q42: 25000 | R42: 25000 | S42: 25000 | T42: =SUM(Q42:S42) -> 75000 | U42: 5610 | V42: 25000 | W42: 25000 | X42: 25000 | Y42: =SUM(V42:X42) -> 75000
B43: Legal Round / Special Fees | C43: Banai Azriel Stern | I43: 0 | J43: 0 | K43: 0 | L43: =SUM(I43:K43) -> 0 | M43: 0 | N43: 60000 | P43: =SUM(M43:O43) -> 60000 | Q43: 0 | R43: 0 | S43: 0 | U43: 5610 | V43: 0 | W43: 0 | X43: 0
B44: Legal Retainers/Fees - UK | L44: =SUM(I44:K44) -> 0 | P44: =SUM(M44:O44) -> 0
B45: Legal Retainers/Fees - US | L45: =SUM(I45:K45) -> 0 | P45: =SUM(M45:O45) -> 0
B46: Finance Retainer - Israel | C46: Rand Finance | D46: 50000 | E46: =D46/[4]Assumptions!$B$12 -> 15151.515 | G46: Grows over time | I46: =$E$46 -> 15151.515 | J46: =$E$46 -> 15151.515 | K46: =$E$46 -> 15151.515 | L46: =SUM(I46:K46) -> 45454.545 | M46: =$E$46 -> 15151.515 | N46: =$E$46 -> 15151.515 | O46: =$E$46 -> 15151.515 | P46: =SUM(M46:O46) -> 45454.545 | Q46: 20000 | R46: 20000 | S46: 20000 | T46: =SUM(Q46:S46) -> 60000 | U46: 5610 | V46: 20000 | W46: 20000 | X46: 20000 | Y46: =SUM(V46:X46) -> 60000
B47: Finance Retainer - UK | C47: FKGB | E47: 500 | G47: TBD | I47: =E47 -> 500 | J47: =I47 -> 500 | K47: =J47 -> 500 | L47: =SUM(I47:K47) -> 1500 | M47: =K47 -> 500 | N47: =M47 -> 500 | O47: =N47 -> 500 | P47: =SUM(M47:O47) -> 1500 | Q47: 500 | R47: 500 | S47: 500 | T47: =SUM(Q47:S47) -> 1500 | U47: 5610 | V47: 500 | W47: 500 | X47: 500 | Y47: =SUM(V47:X47) -> 1500
B48: Finance Retainer - US | C48: Vensure | I48: =72.5*2*2 -> 290 | J48: =72.5*2*2 -> 290 | K48: =72.5*2*2 -> 290 | L48: =SUM(I48:K48) -> 870 | M48: =72.5*2*2 -> 290 | N48: =72.5*2*2 -> 290 | O48: =72.5*2*2 -> 290 | P48: =SUM(M48:O48) -> 870 | Q48: 580 | R48: 870 | S48: 870 | T48: =SUM(Q48:S48) -> 2320 | U48: 5610 | V48: 1160 | W48: 1160 | X48: 1160 | Y48: =SUM(V48:X48) -> 3480
B49: Finance - Audit | C49: EY | E49: =8000+8000 -> 16000 | G49: Annual, plus specials | I49: 0 | J49: 0 | K49: 0 | L49: =SUM(I49:K49) -> 0 | M49: 0 | O49: 4000 | P49: =SUM(M49:O49) -> 4000 | Q49: 0 | R49: 8000 | S49: 0 | T49: =SUM(Q49:S49) -> 8000 | U49: 5610 | V49: 4000 | W49: 0 | X49: 0 | Y49: =SUM(V49:X49) -> 4000
B50: Insurance - Directors + Cyber | C50: Howden | E50: =10963 -> 10963 | G50: Annual | I50: =$E$50/12 -> 913.58333 | J50: =$E$50/12 -> 913.58333 | K50: =$E$50/12 -> 913.58333 | L50: =SUM(I50:K50) -> 2740.75 | M50: =$E$50/12 -> 913.58333 | N50: =$E$50/12 -> 913.58333 | O50: =$E$50/12 -> 913.58333 | P50: =SUM(M50:O50) -> 2740.75 | Q50: 913.58333 | R50: 913.58333 | S50: 913.58333 | T50: =SUM(Q50:S50) -> 2740.75 | U50: 5660 | V50: 913.58333 | W50: 913.58333 | X50: 913.58333 | Y50: =SUM(V50:X50) -> 2740.75
B51: Insurance -other (GL, BOP) | C51: TBD | E51: =1071*[4]Assumptions!B13+749+728 -> 2976.4 | G51: Annual | I51: =$E$51/12 -> 248.03333 | J51: =I51 -> 248.03333 | K51: =J51 -> 248.03333 | L51: =SUM(I51:K51) -> 744.1 | M51: =K51 -> 248.03333 | N51: =M51 -> 248.03333 | O51: =N51 -> 248.03333 | P51: =SUM(M51:O51) -> 744.1 | Q51: 248.03333 | R51: 248.03333 | S51: 248.03333 | T51: =SUM(Q51:S51) -> 744.1 | U51: 5660 | V51: 248.03333 | W51: 248.03333 | X51: 248.03333 | Y51: =SUM(V51:X51) -> 744.1
B52: Insurance - Company | C52: Sela | E52: 1552 | G52: Annual | I52: =$E$52/12 -> 129.33333 | J52: =$E$52/12 -> 129.33333 | K52: =$E$52/12 -> 129.33333 | L52: =SUM(I52:K52) -> 388 | M52: =$E$52/12 -> 129.33333 | N52: =$E$52/12 -> 129.33333 | O52: =$E$52/12 -> 129.33333 | P52: =SUM(M52:O52) -> 388 | Q52: 129.33333 | R52: 129.33333 | S52: 129.33333 | T52: =SUM(Q52:S52) -> 388 | U52: 5660 | V52: 129.33333 | W52: 129.33333 | X52: 129.33333 | Y52: =SUM(V52:X52) -> 388
B53: Professional Insurance | C53: Howden | E53: 13033 | G53: Annual | I53: =$E$53/12 -> 1086.0833 | J53: =$E$53/12 -> 1086.0833 | K53: =$E$53/12 -> 1086.0833 | L53: =SUM(I53:K53) -> 3258.25 | M53: =$E$53/12 -> 1086.0833 | N53: =$E$53/12 -> 1086.0833 | O53: =$E$53/12 -> 1086.0833 | P53: =SUM(M53:O53) -> 3258.25 | Q53: 1086.0833 | R53: 1086.0833 | S53: 1086.0833 | T53: =SUM(Q53:S53) -> 3258.25 | U53: 5660 | V53: 1086.0833 | W53: 1086.0833 | X53: 1086.0833 | Y53: =SUM(V53:X53) -> 3258.25
B54: Talent Acquisition Costs | C54: Placement/Bonus/etc | E54: 10000 | G54: Estimate Avg per Employee | I54: 0 | J54: 0 | K54: 0 | L54: =SUM(I54:K54) -> 0 | M54: =$E$54*(M7-K7) -> 40000 | N54: 15000 | O54: 40000 | P54: =SUM(M54:O54) -> 95000 | Q54: 135000 | R54: 10000 | S54: 10000 | T54: =SUM(Q54:S54) -> 155000 | U54: 5610 | V54: 70000 | W54: 0 | X54: 0 | Y54: =SUM(V54:X54) -> 70000
B55: Misc | E55: 5000 | G55: Grows over time | I55: 5000 | J55: 5000 | K55: 5000 | L55: =SUM(I55:K55) -> 15000 | M55: 5000 | N55: 5000 | O55: 5000 | P55: =SUM(M55:O55) -> 15000 | Q55: 6666.6667 | R55: 6666.6667 | S55: 6666.6667 | T55: =SUM(Q55:S55) -> 20000 | U55: 5660 | V55: 6666.6667 | W55: 6666.6667 | X55: 6666.6667 | Y55: =SUM(V55:X55) -> 20000
B56: ------------------------------------- | C56: ------------------------- | D56: -------------- | L56: =SUM(I56:K56) -> 0
G57: Subtotal FMG Expenses | I57: =SUBTOTAL(9,I29:I55) -> 68818.548 | J57: =SUBTOTAL(9,J29:J55) -> 68818.548 | K57: =SUBTOTAL(9,K29:K55) -> 78818.548 | L57: =SUM(I57:K57) -> 216455.65 | M57: =SUBTOTAL(9,M29:M55) -> 123651.88 | N57: =SUBTOTAL(9,N29:N55) -> 159051.88 | O57: =SUBTOTAL(9,O29:O55) -> 129651.88 | P57: =SUBTOTAL(9,P29:P55) -> 412355.65 | Q57: =SUBTOTAL(9,Q29:Q55) -> 244823.7 | R57: =SUBTOTAL(9,R29:R55) -> 131447.03 | S57: =SUBTOTAL(9,S29:S55) -> 123447.03 | T57: =SUBTOTAL(9,T29:T55) -> 499717.77 | V57: 196070.37 | W57: 122070.37 | X57: 122070.37 | Y57: =SUBTOTAL(9,Y29:Y55) -> 440211.1
I58: =I57+I27 -> 118406.05 | J58: =J57+J27 -> 120769.68 | K58: =K57+K27 -> 130769.68 | L58: =L57+L27 -> 369945.42 | M58: =M57+M27 -> 175603.02 | N58: =N57+N27 -> 212973.02 | O58: =O57+O27 -> 196677.02 | P58: =P57+P27 -> 585253.05 | ... T58: =T57+T27 -> 877746.18 | V58: 322079.84 | W58: 248079.84 | X58: 446959.38 | Y58: =Y57+Y27 -> 1017119.1
B59: Sales & Marketing | L59: =SUM(I59:K59) -> 0
B60: Marketing Leadership | L60: =SUM(I60:K60) -> 0
B61: CMO | C61: Bob Canaway | D61: 300000 | E61: =D61*[4]Assumptions!$B$14/12 -> 30000 | F61: 0.3 | L61: =SUM(I61:K61) -> 0 | N61: =E61*0.5/4 -> 3750 | O61: =E61/2 -> 15000 | P61: =SUM(M61:O61) -> 18750 | Q61: 30000 | R61: 30000 | S61: 30000 | T61: =SUM(Q61:S61) -> 90000 | U61: 5500 | V61: 30000 | W61: 30000 | X61: 89625 | Y61: =SUM(V61:X61) -> 149625
B62: Director of Marketing | D62: 160000 | E62: =D62*[4]Assumptions!$B$14/12 -> 16000 | F62: 0.1 | I62: =$E$62 -> 16000 | J62: =$E$62 -> 16000 | K62: =$E$62 -> 16000 | L62: =SUM(I62:K62) -> 48000 | M62: =$E$62 -> 16000 | N62: =M62*7/31 -> 3612.9032 | P62: =SUM(M62:O62) -> 19612.903 | Q62: 16000 | R62: 16000 | S62: 16000 | T62: =SUM(Q62:S62) -> 48000 | U62: 5500 | V62: 16000 | W62: 16000 | X62: 25600 | Y62: =SUM(V62:X62) -> 57600
A63: * | B63: Demand Gen / Marketing | C63: TBD | D63: 200000 | E63: =D63*[4]Assumptions!$B$14/12 -> 20000 | F63: 0.1 | I63: 0 | J63: =I63 -> 0 | K63: =J63 -> 0 | L63: =SUM(I63:K63) -> 0 | M63: =K63 -> 0 | N63: =M63 -> 0 | O63: =N63 -> 0 | P63: =SUM(M63:O63) -> 0 | Q63: 0 | R63: 0 | S63: 0 | T63: =SUM(Q63:S63) -> 0 | U63: 5500 | V63: 0 | W63: 0 | X63: 0 | Y63: =SUM(V63:X63) -> 0
L64: =SUM(I64:K64) -> 0 | P64: =SUM(M64:O64) -> 0
B65: Marketing Staff | L65: =SUM(I65:K65) -> 0 | P65: =SUM(M65:O65) -> 0
B66: Marketing Staff | C66: Average monthly cost | E66: 10000 | L66: =SUM(I66:K66) -> 0 | P66: =SUM(M66:O66) -> 0 | Q66: 10000 | R66: 10000 | S66: 10000 | T66: =SUM(Q66:S66) -> 30000 | U66: 5500 | V66: 10000 | W66: 10000 | X66: 10000 | Y66: =SUM(V66:X66) -> 30000
L67: =SUM(I67:K67) -> 0 | P67: =SUM(M67:O67) -> 0 | Q67: 1 | R67: 1 | V67: 1 | W67: 1 | X67: 1
B68: Headcount marketing | I68: =COUNTIF(I61:I63,">0")+I67 -> 1 | J68: =COUNTIF(J61:J63,">0")+J67 -> 1 | K68: =COUNTIF(K61:K63,">0")+K67 -> 1 | L68: =SUM(I68:K68) -> 3 | M68: =COUNTIF(M61:M63,">0")+M67 -> 1 | N68: =COUNTIF(N61:N63,">0")+N67 -> 2 | O68: =COUNTIF(O61:O63,">0")+O67 -> 1 | P68: =SUM(M68:O68) -> 4 | Q68: 3 | R68: 3 | V68: 3 | W68: 3 | X68: 3
B69: Total marketing salary expensese | I69: =SUM(I61:I63)+I66 -> 16000 | J69: =SUM(J61:J63)+J66 -> 16000 | K69: =SUM(K61:K63)+K66 -> 16000 | L69: =SUM(I69:K69) -> 48000 | M69: =SUM(M61:M63)+M66 -> 16000 | N69: =SUM(N61:N63)+N66 -> 7362.9032 | O69: =SUM(O61:O63)+O66 -> 15000 | P69: =SUM(P61:P63)+P66 -> 38362.903 | Q69: =SUM(Q61:Q63)+Q66 -> 56000 | R69: =SUM(R61:R63)+R66 -> 56000 | S69: =SUM(S61:S63)+S66 -> 56000 | T69: =SUM(T61:T63)+T66 -> 168000 | V69: 56000 | W69: 56000 | X69: 125225 | Y69: =SUM(Y61:Y63)+Y66 -> 237225
L70: =SUM(I70:K70) -> 0
B71: Expenses | L71: =SUM(I71:K71) -> 0
B72: IT (Laptop, Phone, etc.) | C72: Dell/Apple | E72: 150 | G72: Monthly per Employee | I72: =$E$72*I68 -> 150 | J72: =$E$72*J68 -> 150 | K72: =$E$72*K68 -> 150 | L72: =SUM(I72:K72) -> 450 | M72: =$E$72*M68 -> 150 | N72: =$E$72*N68 -> 300 | O72: =$E$72*O68 -> 150 | P72: =SUM(M72:O72) -> 600 | Q72: 450 | R72: 450 | S72: 450 | T72: =SUM(Q72:S72) -> 1350 | U72: 5550 | V72: 450 | W72: 450 | X72: 450 | Y72: =SUM(V72:X72) -> 1350
B73: Welfare (10Bis, Misc.) | E73: 500 | G73: Monthly per Employee | I73: =$E$73*I68 -> 500 | J73: =$E$73*J68 -> 500 | K73: =$E$73*K68 -> 500 | L73: =SUM(I73:K73) -> 1500 | M73: =$E$73*M68 -> 500 | N73: =$E$73*N68 -> 1000 | O73: =$E$73*O68 -> 500 | P73: =SUM(M73:O73) -> 2000 | Q73: 1500 | R73: 1500 | S73: 1500 | T73: =SUM(Q73:S73) -> 4500 | U73: 5550 | V73: 1500 | W73: 1500 | X73: 1500 | Y73: =SUM(V73:X73) -> 4500
B74: Licensing, Phone Plans, etc. | C74: 150$/Month/Employee | E74: 150 | G74: Monthly per Employee | I74: =$E$74*I68 -> 150 | J74: =$E$74*J68 -> 150 | K74: =$E$74*K68 -> 150 | L74: =SUM(I74:K74) -> 450 | M74: =$E$74*M68 -> 150 | N74: =$E$74*N68 -> 300 | O74: =$E$74*O68 -> 150 | P74: =SUM(M74:O74) -> 600 | Q74: 450 | R74: 450 | S74: 450 | T74: =SUM(Q74:S74) -> 1350 | U74: 5550 | V74: 450 | W74: 450 | X74: 450 | Y74: =SUM(V74:X74) -> 1350
B75: Marketing Operations | I75: 20000 | J75: 20000 | K75: 20000 | L75: =SUM(I75:K75) -> 60000 | M75: 33333 | N75: 33333 | O75: 33334 | P75: =SUM(M75:O75) -> 100000 | Q75: 50000 | R75: 50000 | S75: 50000 | T75: =SUM(Q75:S75) -> 150000 | U75: 5510 | V75: 50000 | W75: 50000 | X75: 50000 | Y75: =SUM(V75:X75) -> 150000
B76: Total marketing expensese | I76: =SUM(I72:I75) -> 20800 | J76: =SUM(J72:J75) -> 20800 | K76: =SUM(K72:K75) -> 20800 | L76: =SUM(I76:K76) -> 62400 | M76: =SUM(M72:M75) -> 34133 | N76: =SUM(N72:N75) -> 34933 | O76: =SUM(O72:O75) -> 34134 | P76: =SUM(P72:P75) -> 103200 | Q76: =SUM(Q72:Q75) -> 52400 | R76: =SUM(R72:R75) -> 52400 | S76: =SUM(S72:S75) -> 52400 | T76: =SUM(T72:T75) -> 157200 | V76: 52400 | W76: 52400 | X76: 52400 | Y76: =SUM(Y72:Y75) -> 157200
I77: =I69+I76 -> 36800 | J77: =J69+J76 -> 36800 | K77: =K69+K76 -> 36800 | L77: =SUM(I77:K77) -> 110400 | M77: =M69+M76 -> 50133 | N77: =N69+N76 -> 42295.903 | O77: =O69+O76 -> 49134 | P77: =P69+P76 -> 141562.9 | Q77: =Q69+Q76 -> 108400 | R77: =R69+R76 -> 108400 | S77: =S69+S76 -> 108400 | T77: =T69+T76 -> 325200 | V77: 108400 | W77: 108400 | X77: 177625 | Y77: =Y69+Y76 -> 394425
B78: Sales | L78: =SUM(I78:K78) -> 0
B79: Sales Leadership | F79: OTB | L79: =SUM(I79:K79) -> 0
B80: CRO | C80: TBD | D80: 250000 | E80: =D80*[4]Assumptions!B14/12 -> 25000 | F80: 1 | L80: =SUM(I80:K80) -> 0
A81: * | B81: VP Sales | C81: TBD (William) | D81: 180000 | E81: =D81*[4]Assumptions!$B$14/12 -> 18000 | F81: 1 | G81: Annual, USD | I81: =15000+1824 -> 16824 | J81: =I81 -> 16824 | K81: =J81 -> 16824 | L81: =SUM(I81:K81) -> 50472 | M81: =K81 -> 16824 | N81: =M81+45000 -> 61824 | P81: =SUM(M81:O81) -> 78648 | Q81: 18000 | R81: 18000 | S81: 72000 | T81: =SUM(Q81:S81) -> 108000 | U81: 5500 | V81: 18000 | W81: 18000 | X81: 72000 | Y81: =SUM(V81:X81) -> 108000
A82: * | B82: Head of Sales EMEA | C82: Colin | D82: 125000 | E82: =D82*[4]Assumptions!$B$15*[4]Assumptions!B13/12 -> 18229.167 | F82: 1 | G82: Annual, GBP | I82: =$E$82 -> 18229.167 | J82: =$E$82 -> 18229.167 | K82: =$E$82+SUM(I82:J82)+$E$82 -> 72916.667 | L82: =SUM(I82:K82) -> 109375 | M82: =$E$82 -> 18229.167 | N82: =$E$82 -> 18229.167 | O82: =$E$82+SUM(M82:N82)+$E$82 -> 72916.667 | P82: =SUM(M82:O82) -> 109375 | Q82: 18229.167 | R82: 18229.167 | S82: 72916.667 | T82: =SUM(Q82:S82) -> 109375 | U82: 5500 | V82: 18229.167 | W82: 18229.167 | X82: 72916.667 | Y82: =SUM(V82:X82) -> 109375
L83: =SUM(I83:K83) -> 0 | P83: =SUM(M83:O83) -> 0
B84: Sales Staff | L84: =SUM(I84:K84) -> 0 | P84: =SUM(M84:O84) -> 0
B85: Sales Director | C85: Average Cost | D85: 175000 | E85: =D85*[4]Assumptions!$B$14/12 -> 17500 | F85: 1 | G85: בונוס אחת לרבעון | I85: =E85*I86 -> 0 | L85: =SUM(I85:K85) -> 0 | M85: =$E$85*M86 -> 0 | N85: =$E$85*N86 -> 0 | O85: =$E$85*O86+SUM(M85:N85)+$E$85 -> 35000 | P85: =SUM(M85:O85) -> 35000 | Q85: 35000 | R85: 35000 | S85: 140000 | T85: =SUM(Q85:S85) -> 210000 | U85: 5500 | V85: 35000 | W85: 35000 | X85: 140000 | Y85: =SUM(V85:X85) -> 210000
L86: =SUM(I86:K86) -> 0 | O86: 1 | Q86: 2 | R86: 2 | V86: 2 | W86: 2 | X86: 2
B87: Sales Manager | C87: Average Cost | D87: 125000 | E87: =D87*[4]Assumptions!$B$14/12 -> 12500 | F87: 1 | L87: =SUM(I87:K87) -> 0 | Q87: 12500 | R87: 12500 | S87: 50000 | T87: =SUM(Q87:S87) -> 75000 | U87: 5500 | V87: 25000 | W87: 25000 | X87: 100000 | Y87: =SUM(V87:X87) -> 150000
L88: =SUM(I88:K88) -> 0 | Q88: 1 | R88: 1 | V88: 2 | W88: 2 | X88: 2
B89: Inside Sales | C89: Average Cost | D89: 60000 | E89: =D89*[4]Assumptions!$B$14/12 -> 6000 | F89: 1 | L89: =SUM(I89:K89) -> 0 | U89: 5500 | V89: 6000 | W89: 6000 | X89: 24000 | Y89: =SUM(V89:X89) -> 36000
L90: =SUM(I90:K90) -> 0 | V90: 1 | W90: 1 | X90: 1
B91: Sales salaries | L91: =SUM(I91:K91) -> 0
B92: Sales headcount | I92: =COUNTIF(I80:I82,">0")+I86+I90+I88 -> 2 | J92: =COUNTIF(J80:J82,">0")+J86+J90+J88 -> 2 | K92: =COUNTIF(K80:K82,">0")+K86+K90+K88 -> 2 | L92: =SUM(I92:K92) -> 6 | M92: =COUNTIF(M80:M82,">0")+M86+M90+M88 -> 2 | N92: =COUNTIF(N80:N82,">0")+N86+N90+N88 -> 2 | O92: =COUNTIF(O80:O82,">0")+O86+O90+O88 -> 2 | Q92: 5 | R92: 5 | V92: 7 | W92: 7 | X92: 7
B93: Total sales salary expenses | I93: =SUM(I80:I82)+I85+I89+I87 -> 35053.167 | J93: =SUM(J80:J82)+J85+J89+J87 -> 35053.167 | K93: =SUM(K80:K82)+K85+K89+K87 -> 89740.667 | L93: =SUM(I93:K93) -> 159847 | M93: =SUM(M80:M82)+M85+M89+M87 -> 35053.167 | N93: =SUM(N80:N82)+N85+N89+N87 -> 80053.167 | O93: =SUM(O80:O82)+O85+O89+O87 -> 107916.67 | P93: =SUM(P80:P82)+P85+P89+P87 -> 223023 | Q93: =SUM(Q80:Q82)+Q85+Q89+Q87 -> 83729.167 | R93: =SUM(R80:R82)+R85+R89+R87 -> 83729.167 | S93: =SUM(S80:S82)+S85+S89+S87 -> 334916.67 | T93: =SUM(T80:T82)+T85+T89+T87 -> 502375 | V93: 102229.17 | W93: 102229.17 | X93: 408916.67 | Y93: =SUM(Y80:Y82)+Y85+Y89+Y87 -> 613375
L94: =SUM(I94:K94) -> 0
L95: =SUM(I95:K95) -> 0
B96: Sales Expenses | L96: =SUM(I96:K96) -> 0
B97: IT (Laptop, Phone, etc.) | C97: Dell/Apple | E97: 150 | G97: Monthly per Employee | I97: =$E$97*I92 -> 300 | J97: =$E$97*J92 -> 300 | K97: =$E$97*K92 -> 300 | L97: =SUM(I97:K97) -> 900 | M97: =$E$97*M92 -> 300 | N97: =$E$97*N92 -> 300 | O97: =$E$97*O92 -> 300 | P97: =SUM(M97:O97) -> 900 | Q97: 750 | R97: 750 | S97: 750 | T97: =SUM(Q97:S97) -> 2250 | U97: 5550 | V97: 1050 | W97: 1050 | X97: 1050 | Y97: =SUM(V97:X97) -> 3150
B98: Welfare (10Bis, Misc.) | E98: 500 | G98: Monthly per Employee | I98: =$E$98*I92 -> 1000 | J98: =$E$98*J92 -> 1000 | K98: =$E$98*K92 -> 1000 | L98: =SUM(I98:K98) -> 3000 | M98: =$E$98*M92 -> 1000 | N98: =$E$98*N92 -> 1000 | O98: =$E$98*O92 -> 1000 | P98: =SUM(M98:O98) -> 3000 | Q98: 2500 | R98: 2500 | S98: 2500 | T98: =SUM(Q98:S98) -> 7500 | U98: 5550 | V98: 3500 | W98: 3500 | X98: 3500 | Y98: =SUM(V98:X98) -> 10500
B99: Licensing, Phone Plans, etc. | C99: 150$/Month/Employee | E99: 150 | G99: Monthly per Employee | I99: =$E$99*I92 -> 300 | J99: =$E$99*J92 -> 300 | K99: =$E$99*K92 -> 300 | L99: =SUM(I99:K99) -> 900 | M99: =$E$99*M92 -> 300 | N99: =$E$99*N92 -> 300 | O99: =$E$99*O92 -> 300 | P99: =SUM(M99:O99) -> 900 | Q99: 750 | R99: 750 | S99: 750 | T99: =SUM(Q99:S99) -> 2250 | U99: 5550 | V99: 1050 | W99: 1050 | X99: 1050 | Y99: =SUM(V99:X99) -> 3150
B100: Sales Travel | L100: =SUM(I100:K100) -> 0 | P100: =SUM(M100:O100) -> 0 | Q100: 5000 | R100: 5000 | S100: 5000 | T100: =SUM(Q100:S100) -> 15000 | U100: 5540 | V100: 5000 | W100: 5000 | X100: 5000 | Y100: =SUM(V100:X100) -> 15000
B101: Sales operations | L101: =SUM(I101:K101) -> 0 | P101: =SUM(M101:O101) -> 0 | Q101: 3000 | R101: 3000 | S101: 5000 | T101: =SUM(Q101:S101) -> 11000 | U101: 5510 | V101: 6666.6667 | W101: 6666.6667 | X101: 6666.6667 | Y101: =SUM(V101:X101) -> 20000
B102: Total sales expenses | C102: ------------------------- | D102: -------------- | I102: =SUM(I97:I101) -> 1600 | J102: =SUM(J97:J101) -> 1600 | K102: =SUM(K97:K101) -> 1600 | L102: =SUM(I102:K102) -> 4800 | M102: =SUM(M97:M101) -> 1600 | N102: =SUM(N97:N101) -> 1600 | O102: =SUM(O97:O101) -> 1600 | P102: =SUM(P97:P101) -> 4800 | Q102: =SUM(Q97:Q101) -> 12000 | R102: =SUM(R97:R101) -> 12000 | S102: =SUM(S97:S101) -> 14000 | T102: =SUM(T97:T101) -> 38000 | V102: 17266.667 | W102: 17266.667 | X102: 17266.667 | Y102: =SUM(Y97:Y101) -> 51800
I103: =I93+I102 -> 36653.167 | J103: =J93+J102 -> 36653.167 | K103: =K93+K102 -> 91340.667 | L103: =SUM(I103:K103) -> 164647 | M103: =M93+M102 -> 36653.167 | N103: =N93+N102 -> 81653.167 | O103: =O93+O102 -> 109516.67 | P103: =P93+P102 -> 227823 | Q103: =Q93+Q102 -> 95729.167 | R103: =R93+R102 -> 95729.167 | S103: =S93+S102 -> 348916.67 | T103: =T93+T102 -> 540375 | V103: 119495.83 | W103: 119495.83 | X103: 426183.33 | Y103: =+SUM(V103:X103) -> 665175
...

Sheet BS
B1: Mitiga Security Inc | AH1: For Oct Meeting
B2: Consolidated Balance sheet as of | D2: 44166 | F2: 44286 | H2: 44377 | J2: 44408 | L2: 44439 | N2: 44469 | P2: 44500 | R2: 44530 | T2: 44561 | AH2: Forecasted 12/21/2021
D3: $ | F3: $ | H3: $ | J3: $ | L3: $ | N3: $ | P3: $ | R3: $ | T3: $ | AD3: Dec deals going into A/R or unbilled A/R | AH3: $
B4: Current assets: | AD4: Questrade | AE4: 200000 | AF4: =+AE4/12 -> 16666.667 | AZ4: JFrog | BA4: 23407.52 | BB4: Billing during Dec
A5: 11 | B5: Cash and cash equivalents | D5: 3512559 | F5: 2348479 | H5: 20776272 | J5: 25201966 | L5: 24132936 | N5: 23109419 | P5: 21687740 | R5: 20219043 | T5: =ROUND(SUMIF('HARKAVA '!$Z:$Z,BS!A5,'HARKAVA '!Y:Y),0) -> 18893872 | V5: =T5-R5 -> -1325171 | Y5: =T5-P5 -> -2793868 | Z5: =T5-H5 -> -1882400.4 | AD5: Blackstone | AE5: 200000 | AF5: =+AE5 -> 200000 | AH5: 20316014 | AZ5: Fiverr International Ltd | BA5: 36515.74 | BB5: Billing during Dec
A6: 13 | B6: Deposits | D6: 54215 | F6: 52993.52 | H6: 53742.45 | J6: 54024 | L6: 377999.81 | N6: 375176 | P6: 383233 | R6: 402110 | T6: =ROUND(SUMIF('HARKAVA '!$Z:$Z,BS!A6,'HARKAVA '!Y:Y),0) -> 408108 | V6: =T6-R6 -> 5998 | Y6: =T6-P6 -> 24875 | Z6: =T6-H6 -> 354365.55 | AD6: Renorun | AE6: 120000 | AF6: =+AE6/12 -> 10000 | AH6: 375176 | AZ6: Elementor Ltd | BA6: 26918.65 | BB6: Billing during Dec
A7: 14 | B7: Trade receivable | D7: 969856 | F7: 693731.96 | H7: 663746.07 | J7: 836533 | L7: 906544.34 | N7: 831623 | P7: 756843 | R7: 483353 | T7: =ROUND(SUMIF('HARKAVA '!$Z:$Z,BS!A7,'HARKAVA '!Y:Y),0) -> 745155 | V7: =T7-R7 -> 261802 | Y7: =T7-P7 -> -11688 | Z7: =T7-H7 -> 81408.93 | AA7: Rubicon- paid USD350 during NOV | AD7: Accuweather | AE7: 225000 | AF7: =+AE7/4 -> 56250 | AH7: 1075000 | AZ7: LivePerson Inc | BA7: 44450 | BB7: Billing during Dec
A8: 16 | B8: Other receivables | D8: 169203 | F8: 241731.47 | H8: 330311.48 | J8: 282949 | L8: 680044.85 | N8: 747250 | P8: 877851 | R8: 1680347 | T8: =ROUND(SUMIF('HARKAVA '!$Z:$Z,BS!A8,'HARKAVA '!Y:Y),0)-1 -> 1760880 | V8: =T8-R8 -> 80533 | Y8: =T8-P8 -> 883029 | Z8: =T8-H8 -> 1430568.5 | AA8: 2.8M NIS (USD914K) from the landlord | AD8: Imperva | AE8: 360000 | AF8: =+AE8/4 -> 90000 | AH8: 1000000 | AZ8: Open Education LLC | BA8: 39100 | BB8: Billing during Dec
B9: Total current assets | D9: =SUM(D5:D8) -> 4705833 | F9: =SUM(F5:F8) -> 3336935.9 | H9: =SUM(H5:H8) -> 21824072 | J9: =SUM(J5:J8) -> 26375472 | L9: 26097524 | N9: 25063468 | P9: =+SUM(P5:P8) -> 23705667 | R9: 22784853 | T9: =SUM(T5:T8) -> 21808015 | Y9: =SUM(Y6:Y8) -> 896216 | AD9: Imperva | AE9: 120000 | AF9: =+AE9 -> 120000 | AH9: 22766190 | AU9: Prepaid expenses | AV9: -57 | AW9: Recognition of expenses | AZ9: Blackstone | BA9: 139500 | BB9: Billing during Dec
AD10: SafeBreach | AE10: 139500 | AF10: =+AE10 -> 139500 | AU10: Vat | AV10: 100 | AW10: Exchange rate+ Vat 11-12.21 | AZ10: Imperva Inc | BA10: 120000 | BB10: Billing during Dec
AD11: Others | AE11: =+SUM(AE4:AE10) -> 1364500 | AF11: =+SUM(AF4:AF10) -> 632416.67 | AU11: AR others | AV11: =AX19/1000 -> 15.2938 | AW11: Exchange rate | AZ11: Lemonade, Inc | BA11: -120000 | BB11: Collecting during Dec
A12: 31 | B12: Fixed assets | D12: 112251.68 | F12: 138031 | H12: 175053.38 | J12: 192701 | L12: 191982.97 | N12: 193056 | P12: 709629 | R12: 1184212 | T12: =ROUND(SUMIF('HARKAVA '!$Z:$Z,BS!$A$12,'HARKAVA '!Y:Y),0) -> 1391131 | V12: =T12-R12 -> 206919 | Y12: =T12-P12 -> 681502 | Z12: =T12-H12 -> 1216077.6 | AA12: Leasehold improvement | AH12: 211056 | AV12: =SUM(AV9:AV11) -> 58.2938 | AZ12: Interactive Pro | BA12: =119038.28-101414 -> 17624.28
AD13: Nov balance | AF13: =+T7 -> 745155 | AZ13: Dif income recievable | BA13: =157709-223552 -> -65843
W14: Furniture | AD14: Payments from Oct | AF14: -200000 | AU14: 25 | AW14: 12.2021 | AX14: 3.11 | BA14: =SUM(BA4:BA13) -> 261673.19
B15: Total assets | D15: =D9+D12 -> 4818084.7 | F15: =F9+F12 -> 3474966.9 | H15: =H9+H12 -> 21999126 | J15: =J9+J12 -> 26568173 | L15: 26289506 | N15: 25256524 | P15: =+SUM(P9+P12) -> 24415296 | R15: 23969065 | T15: =T9+T12 -> 23199146 | W15: Computers& Phones | AD15: Dec Balance | AF15: =+AF11+AF13+AF14 -> 1177571.7 | AH15: 22977246 | AU15: 153 | AW15: 11.2021 | AX15: 3.162
W16: Leasehold improvement | AU16: 40 | AX16: ='TB Mitiga LTD'!E12 -> 2892240
B17: Current liabilities: | AU17: =SUM(AU14:AU16) -> 218 | AX17: =AX16/AX14 -> 929980.71
A18: 34 | B18: Trade payables | D18: 110116.14 | F18: 212308.2 | H18: =195794.2+1 -> 195795.2 | J18: 151604 | L18: 314764.55 | N18: 150220 | P18: 312207 | R18: 241126 | T18: =-ROUND(SUMIF('HARKAVA '!$Z:$Z,BS!A18,'HARKAVA '!Y:Y),0) -> 672609 | V18: =T18-R18 -> 431483 | Y18: =T18-P18 -> 360402 | Z18: =T18-H18 -> 476813.8 | AD18: Deferred Revenue Calculation | AH18: 200000 | AX18: =AX16/AX15 -> 914686.91
A19: 38 | B19: Deferred revenue | D19: 69750 | F19: 61445 | H19: 40865 | J19: 349711 | L19: 453473 | N19: 396938 | P19: 352455 | R19: 386902 | T19: =-ROUND(SUMIF('HARKAVA '!$Z:$Z,BS!A19,'HARKAVA '!Y:Y),0) -> 553209 | V19: =T19-R19 -> 166307 | Y19: =T19-P19 -> 200754 | Z19: =T19-H19 -> 512344 | AD19: Nov balance | AF19: =+T19 -> 553209 | AH19: 1071938 | AX19: =AX17-AX18 -> 15293.8
A20: 36 | B20: Other payables | D20: =739458.23-D19 -> 669708.23 | F20: =515709.95-F19 -> 454264.95 | H20: 791187.11 | J20: 705406 | L20: 878894.6 | N20: 902309 | P20: 1047125 | R20: 1017767 | T20: =-ROUND(SUMIF('HARKAVA '!$Z:$Z,BS!A20,'HARKAVA '!Y:Y),0) -> 1751994 | V20: =T20-R20 -> 734227 | W20: Bonus+Commission 2021 | Y20: =T20-P20 -> 704869 | Z20: =T20-H20 -> 960806.89 | AD20: Additions from Dec Deals invoiced | AF20: =+AF11 -> 632416.67 | AH20: 1550000
B21: Total current liabilities | D21: =SUM(D18:D20) -> 849574.37 | F21: =SUM(F18:F20) -> 728018.15 | H21: =SUM(H18:H20) -> 1027847.3 | J21: =SUM(J18:J20) -> 1206721 | L21: 1647132.2 | N21: 1449467 | P21: =+SUM(P18:P20) -> 1711787 | R21: 1645795 | T21: =SUM(T18:T20) -> 2977812 | Y21: =SUM(Y18:Y20) -> 1266025 | AD21: Recognized in Dec | AF21: =-PL!#REF! -> #REF! | AH21: 2821938 | AV21: =180+33+34 -> 247 | AW21: Fixed assets providers
AD22: Dec Balance | AF22: =+SUM(AF19:AF21) -> #REF! | AV22: 75 | AW22: Doit
A23: 46 | B23: Leasehold liabilities | R23: 781784 | T23: =-ROUND(SUMIF('HARKAVA '!$Z:$Z,BS!A23,'HARKAVA '!Y:Y),0) -> 794855 | V23: =T23-R23 -> 13071 | W23: Exchange rate | AV23: 28 | AW23: Auth0
AV24: =SUM(AV21:AV23) -> 350
B25: Shareholders' equity | AD25: Other Payables
A26: 49 | B26: Share capital and premium on shares | D26: 7449838 | F26: 7449838 | H26: 27414943 | J26: 32414943 | L26: 32417373 | N26: 32427768 | P26: 32427768 | R26: 32427772 | T26: =-ROUND(SUMIF('HARKAVA '!$Z:$Z,BS!A26,'HARKAVA '!Y:Y),0) -> 32465026 | V26: =T26-R26 -> 37254 | Y26: =T26-P26 -> 37258 | Z26: =T26-H26 -> 5050082.9 | AD26: November amount | AF26: =+T20 -> 1751994 | AH26: 32427768 | AU26: 2472000 | AV26: =AU26/AX14 -> 794855.31
A27: 49.5 | B27: Capital reserve for share-based payments | D27: 61989 | F27: 89881 | H27: 102779 | J27: 109577 | L27: 110802 | N27: 113852 | P27: 117071 | R27: 119551 | T27: =-ROUND(SUMIF('HARKAVA '!$Z:$Z,BS!A27,'HARKAVA '!Y:Y),0) -> 104421 | V27: =T27-R27 -> -15130 | Y27: =T27-P27 -> -12650 | Z27: =T27-H27 -> 1642 | AD27: Dec Commissions | AF27: 200000 | AH27: 128853 | AV27: =AU26/AX15 -> 781783.68
A28: 51 | B28: Accumulated deficit | D28: -3543316.3 | F28: -4792770.1 | H28: -6546443.7 | J28: -7163068 | L28: -7885800 | N28: -8734563 | P28: -9841330 | R28: -11005837 | T28: =-ROUND(SUMIF('HARKAVA '!$Z:$Z,BS!A28,'HARKAVA '!Y:Y),0) -> -13186755 | V28: =T28-R28 -> -2180918 | Y28: =T28-P28 -> -3345425 | Z28: =T28-H28 -> -6640311.3 | AA28: =#REF!-T28 -> #REF! | AB28: =+#REF!-D28 -> #REF! | AD28: Bonuses payable | AF28: =+PL!BB53 -> 502650 | AH28: -12401313 | AV28: =AV26-AV27 -> 13071.624
B29: Total shareholders' deficit | D29: =SUM(D26:D28) -> 3968510.7 | F29: =SUM(F26:F28) -> 2746948.9 | H29: =SUM(H26:H28) -> 20971278 | J29: =SUM(J26:J28) -> 25361452 | L29: 24642375 | N29: 23807057 | P29: 22703509 | R29: 21541486 | T29: =SUM(T26:T28) -> 19382692 | Y29: =SUM(Y26:Y28) -> -3320817 | AD29: total | AF29: =+SUM(AF26:AF28) -> 2454644 | AH29: 20155308
B30: Total liabilities and shareholders' equity | D30: =D21+D29 -> 4818085.1 | F30: =F21+F29 -> 3474967.1 | H30: =H21+H29 -> 21999126 | J30: =J21+J29 -> 26568173 | L30: 26289506 | N30: 25256524 | P30: 24415296 | R30: 23969065 | T30: =T21+T29+T23 -> 23155359 | AH30: 22977246
D32: =+D15-D30 -> -0.41 | F32: =+F15-F30 -> -0.16 | H32: =+H15-H30 -> 0 | I32: =+I15-I30 -> 0 | L32: 0.14666667 | N32: 0 | P32: 0 | R32: 0 | T32: =+T15-T30 -> 43787 | AB32: =+AB28-PL!AQ45 -> #REF!
F37: =+F28-D28 -> -1249453.8 | H37: =+H28-F28 -> -1753673.5 | N37: -2188119.3 | P37: =+P28-N28 -> -1106767 | R37: -1164507 | T37: =+T28-R28 -> -2180918
F38: =+PL!F45 -> -1227985.6 | H38: =+PL!I45 -> -1775141.5 | L38: 1.1466667 | N38: -2188119.2 | P38: =PL!AB45 -> -1106767 | R38: -1164507.3 | T38: =+PL!AJ45 -> -2137130.1
F39: =-F37+F38 -> 21468.23 | H39: =-H37+H38 -> -21467.902 | N39: 0.132 | P39: =-P37+P38 -> 0.012222222 | R39: -0.29224796 | T39: =-T37+T38 -> 43787.854
L40: 2.1466667 | N40: 2585057.2 | P40: 352455 | R40: 1551409.3 | T40: =T19-T38 -> 2690339.1

Sheet PL
B1: Mitiga Security Inc. | BA1: Workpapers for Q4 estimate for BoD on Jan 2022 | BI1: Workpapers for Q4 estimate for BoD on Oct 2021
B2: Consolidated Statement of operations | D2: 2020 | F2: Q1 2021. Actual | I2: Q2 2021 Actual | L2: 44378 | P2: 44409 | T2: 44440 | Y2: Q3 2021 Actual | AB2: 44500 | AF2: 44530 | AJ2: 44561 | AN2: Q4 2021 Actual | AQ2: 2021 | AT2: Growth | AU2: Prior Q4 Estimate | BI2: Growth Factor | BW2: 2020 | BY2: Q1 2021 | CB2: Q2 2021 | CE2: Q3 2021 | CH2: Year to date as of Dec
D3: Actual | F3: Actual | G3: Budget | I3: Actual | J3: Budget | L3: Actual | N3: Budget | P3: Actual | R3: Budget | T3: Actual | V3: Budget | Y3: Actual | Z3: Budget | AB3: Actual | AD3: Budget | AF3: Actual | AH3: Budget | AJ3: Actual | AL3: Budget | AN3: Actual | AO3: Budget | AQ3: =+AN3 -> Actual | AR3: Budget | AS3: Variance | AT3: 12/21-11/21 | AU3: Forecast | BI3: Q4/Q3 | BK3: Assumptions | BW3: Actual | BY3: Actual | BZ3: Budget | CB3: Actual | CC3: Budget | CE3: Actual | CF3: Budget | CH3: Actual | CI3: Budget
D4: $ | F4: $ | G4: $ | I4: $ | J4: $ | L4: $ | N4: $ | P4: $ | R4: $ | T4: $ | V4: $ | Y4: $ | Z4: $ | AB4: $ | AD4: $ | AF4: $ | AH4: $ | AJ4: $ | AL4: $ | AN4: $ | AO4: $ | AQ4: $ | AR4: $ | AS4: $ | AU4: $ | AX4: Franko Bar-increase salary retro from SEP+Bonus- Nov | AY4: -6632 | BA4: Regular ARR revenue $80,000 plus SearchBreach hours of $139,500 | BK4: Revenue | BL4: ARR | BM4: 244000 | BW4: $ | BY4: $ | BZ4: $ | CB4: $ | CC4: $ | CE4: $ | CF4: $ | CH4: $ | CI4: $
A5: 5200 | B5: Revenues | D5: 1520347 | F5: 366288.87 | G5: 435000 | I5: 413530.32 | J5: 725000 | L5: 100457.04 | N5: 383333 | P5: 94439.83 | R5: 383333 | T5: 176457 | V5: 383333 | Y5: =L5+P5+T5 -> 371353.87 | Z5: =N5+R5+V5 -> 1149999 | AB5: 110451.38 | AD5: 508333.33 | AF5: 149267.86 | AH5: 508333.33 | AJ5: =CH5-I5-F5-L5-P5-T5-AB5-AF5 -> 210180.59 | AL5: =1525000/3 -> 508333.33 | AN5: =+AB5+AF5+AJ5 -> 469899.83 | AO5: =508333*3+1 -> 1525000 | AQ5: =+F5+I5+Y5+AN5 -> 1621072.9 | AR5: =+G5+J5+Z5+AO5+1 -> 3835000 | AS5: =+AQ5-AR5 -> -2213927.1 | AU5: 400000 | AX5: Ori abulnil full month | AY5: 8409 | BJ5: =AJ5+Y5+I5+F5 -> 1361353.7 | BL5: Non-ARR | BM5: =18400+9625 -> 28025 | BN5: Elementor & Blackstone | BW5: =+D5 -> 1520347 | BY5: =+F5 -> 366288.87 | BZ5: =+G5 -> 435000 | CB5: =+I5 -> 413530.32 | CC5: =+J5 -> 725000 | CE5: =+Y5 -> 371353.87 | CF5: =+Z5 -> 1149999 | CH5: =-SUMIF('HARKAVA '!$Z:$Z,PL!A5,'HARKAVA '!Y:Y) -> 1621072.9 | CI5: =G5+J5+Z5+AD5+AL5 -> 3326665.7
AX6: Ross- full month | AY6: 8000 | BJ6: 1410891.1 | BL6: Jeffreries | BM6: 47000 | BN6: & others
B7: Cost of goods sold | AX7: Ariel- bonus 65.5K (50%) | AY7: -65500 | BJ7: =BJ6-BJ5 -> 49537.428 | BL7: K-Health | BM7: =36000+45000 -> 81000 | BN7: Red team $36k plus 27 tokens ~$45k
A8: 5300 | B8: Salaries and related expenses | D8: 911168.12 | F8: 263015.29 | G8: =SUMIF(budget!U:U,PL!A8,budget!L:L) -> 277413.64 | I8: =259423 -> 259423 | J8: =SUMIF(budget!U:U,PL!A8,budget!P:P) -> 595733.33 | L8: 123092.48 | N8: 263618.18 | P8: 107026.4 | R8: 279375.76 | T8: 49995.73 | V8: =SUMIF(budget!U:U,PL!A8,budget!S:S) -> 279375.76 | Y8: =L8+P8+T8 -> 280114.61 | Z8: =N8+R8+V8 -> 822369.7 | AB8: 74016.46 | AD8: 324375.76 | AF8: 122229.31 | AH8: 324375.76 | AJ8: =CH8-I8-F8-L8-P8-T8-AB8-AF8 -> 218497.14 | AL8: =SUMIF(budget!U:U,PL!A8,budget!X:X) -> 553112.27 | AN8: =+AB8+AF8+AJ8 -> 414742.91 | AO8: =SUMIF(budget!U:U,PL!A8,budget!Y:Y) -> 1201863.8 | AQ8: =+F8+I8+Y8+AN8 -> 1217295.8 | AR8: =+G8+J8+Z8+AO8 -> 2897380.5 | AS8: =+AR8-AQ8 -> 1680084.6 | AT8: =+AJ8/AF8 -> 1.7876002 | AU8: 344000 | AV8: =AJ8-AF8 -> 96267.83 | AX8: John z- new employees | AY8: 12000 | BA8: =+AJ8 -> 218497.14 | BB8: will take Ariel's bonus as the growth for new hires | BI8: 1.05 | BM8: =+SUM(BM4:BM7) -> 400025 | BW8: =+D8 -> 911168.12 | BY8: =+F8 -> 263015.29 | BZ8: =+G8 -> 277413.64 | CB8: =+I8 -> 259423 | CC8: =+J8 -> 595733.33 | CE8: =+Y8 -> 280114.61 | CF8: =+Z8 -> 822369.7 | CH8: =SUMIF('HARKAVA '!$Z:$Z,PL!A8,'HARKAVA '!Y:Y) -> 1217295.8 | CI8: =G8+J8+Z8+AD8+AL8 -> 2573004.7 | CJ8: Analytics
A9: 5311 | B9: Non budgeted items (Esop, vacation provision) | D9: 45511 | F9: 7976.08 | G9: =SUMIF(budget!U:U,PL!A9,budget!L:L) -> 0 | I9: 31725.23 | J9: 0 | L9: 1785 | N9: 0 | P9: 665 | R9: 0 | T9: -14961.6 | V9: =SUMIF(budget!U:U,PL!A9,budget!S:S) -> 0 | Y9: =L9+P9+T9 -> -12511.6 | Z9: =N9+R9+V9 -> 0 | AB9: 7989.32 | AD9: 0 | AF9: -9636 | AH9: 0 | AJ9: =CH9-I9-F9-L9-P9-T9-AB9-AF9 -> -3178.9797 | AL9: =SUMIF(budget!U:U,PL!A9,budget!X:X) -> 0 | AN9: =+AB9+AF9+AJ9 -> -4825.6597 | AO9: =SUMIF(budget!U:U,PL!A9,budget!Y:Y) -> 0 | AQ9: =+F9+I9+Y9+AN9 -> 22364.05 | AR9: =+G9+J9+Z9+AO9 -> 0 | AS9: =+AR9-AQ9 -> -22364.05 | AT9: =+AJ9/AF9 -> 0.32990657 | AU9: 7000 | AV9: =AJ9-AF9 -> 6457.0203 | AX9: Ariel Bonus 2021 | AY9: =54167*0.5+45833*0.5 -> 50000 | BA9: =56000/2 -> 28000 | BB9: 50% Ariel's bonus paid in IL in June expenses now | BI9: =+AT9 -> 0.32990657 | BK9: Increases in Q4 Delivery | BW9: =+D9 -> 45511 | BY9: =+F9 -> 7976.08 | BZ9: =+G9 -> 0 | CB9: =+I9 -> 31725.23 | CC9: =+J9 -> 0 | CE9: =+Y9 -> -12511.6 | CF9: =+Z9 -> 0 | CH9: =SUMIF('HARKAVA '!$Z:$Z,PL!A9,'HARKAVA '!Y:Y) -> 22364.05 | CI9: =G9+J9+Z9+AD9+AL9 -> 0
A10: 5320 | B10: Materials and outsourced work | D10: 194234.05 | F10: 33082.22 | G10: =SUMIF(budget!U:U,PL!A10,budget!L:L) -> 10000 | I10: 55133.82 | J10: =SUMIF(budget!U:U,PL!A10,budget!P:P) -> 10000 | L10: 2622.24 | N10: 5000 | P10: 2933.9 | R10: 5000 | T10: 6201.59 | V10: =SUMIF(budget!U:U,PL!A10,budget!S:S) -> 5000 | Y10: =L10+P10+T10 -> 11757.73 | Z10: =N10+R10+V10 -> 15000 | AB10: 2323.7 | AD10: 5000 | AF10: 1589.14 | AH10: 5000 | AJ10: =CH10-I10-F10-L10-P10-T10-AB10-AF10 -> 11863.875 | AL10: =SUMIF(budget!U:U,PL!A10,budget!X:X) -> 5000 | AN10: =+AB10+AF10+AJ10 -> 15776.715 | AO10: =SUMIF(budget!U:U,PL!A10,budget!Y:Y) -> 15000 | AQ10: =+F10+I10+Y10+AN10 -> 115750.49 | AR10: =+G10+J10+Z10+AO10 -> 50000 | AS10: =+AR10-AQ10 -> -65750.485 | AT10: =+AJ10/AF10 -> 7.4655946 | AU10: 4000 | AV10: =AJ10-AF10 -> 10274.735 | AX10: Bonus 2021 | AY10: =12000+32000+42000 -> 86000 | BA10: =+BB48*0.5 -> 47150 | BB10: Bonus 50% of cell AZ 48 | BI10: =+AT10 -> 7.4655946 | BK10: Director IR IL (Ori), Delivery Manager US (Ross), Director IR US, 3 IR EE | BW10: =+D10 -> 194234.05 | BY10: =+F10 -> 33082.22 | BZ10: =+G10 -> 10000 | CB10: =+I10 -> 55133.82 | CC10: =+J10 -> 10000 | CE10: =+Y10 -> 11757.73 | CF10: =+Z10 -> 15000 | CH10: =SUMIF('HARKAVA '!$Z:$Z,PL!A10,'HARKAVA '!Y:Y) -> 115750.49 | CI10: =G10+J10+Z10+AD10+AL10 -> 45000
A11: 5330 | B11: Other | D11: 50334.45 | F11: 50190.24 | G11: =SUMIF(budget!U:U,PL!A11,budget!L:L) -> 28400 | I11: 51165.919 | J11: =SUMIF(budget!U:U,PL!A11,budget!P:P) -> 38000 | L11: 21384.06 | N11: 20267 | P11: 21819.16 | R11: 21067 | T11: 42216.121 | V11: =SUMIF(budget!U:U,PL!A11,budget!S:S) -> 21066 | Y11: =L11+P11+T11 -> 85419.341 | Z11: =N11+R11+V11 -> 62400 | AB11: 32891.783 | AD11: 25133 | AF11: 38043.964 | AH11: 25133 | AJ11: =CH11-I11-F11-L11-P11-T11-AB11-AF11 -> -1283.7232 | AL11: =SUMIF(budget!U:U,PL!A11,budget!X:X) -> 25134 | AN11: =+AB11+AF11+AJ11 -> 69652.023 | AO11: =SUMIF(budget!U:U,PL!A11,budget!Y:Y) -> 75400 | AQ11: =+F11+I11+Y11+AN11 -> 256427.52 | AR11: =+G11+J11+Z11+AO11 -> 204200 | AS11: =+AR11-AQ11 -> -52227.523 | AT11: =+AJ11/AF11 -> -0.033743151 | AU11: 43000 | AV11: =AJ11-AF11 -> -39327.687 | AW11: Overhead- increase in License+ IT expenses+Travel | AX11: Reclass to R&D | AY11: -68329 | BA11: =+BA8+BA10+BA9 -> 293647.14 | BI11: 0.5 | BK11: 6 EE at avg of $200k = $1.2M /128.1.5 months = $150,000 | BW11: =+D11 -> 50334.45 | BY11: =+F11 -> 50190.24 | BZ11: =+G11 -> 28400 | CB11: =+I11 -> 51165.919 | CC11: =+J11 -> 38000 | CE11: =+Y11 -> 85419.341 | CF11: =+Z11 -> 62400 | CH11: =SUMIF('HARKAVA '!$Z:$Z,PL!A11,'HARKAVA '!Y:Y) -> 256427.52 | CI11: =G11+J11+Z11+AD11+AL11 -> 179067 | CJ11: Visa rob (6K)+ Depreciation (12K)
D12: =SUM(D8:D11) -> 1201247.6 | F12: =SUM(F8:F11) -> 354263.83 | G12: =SUM(G8:G11) -> 315813.64 | I12: =SUM(I8:I11) -> 397447.97 | J12: =SUM(J8:J11) -> 643733.33 | L12: =SUM(L8:L11) -> 148883.78 | N12: =SUM(N8:N11) -> 288885.18 | P12: =SUM(P8:P11) -> 132444.46 | R12: 305442.76 | T12: =SUM(T8:T11) -> 83451.841 | V12: =SUM(V8:V11) -> 305441.76 | Y12: =SUM(Y8:Y11) -> 364780.08 | Z12: =SUM(Z8:Z11) -> 899769.7 | AB12: 117221.26 | AD12: 354508.76 | AF12: 152226.41 | AH12: 354508.76 | AJ12: =SUM(AJ8:AJ11) -> 225898.31 | AL12: =SUM(AL8:AL11) -> 583246.27 | AN12: =+SUM(AN8:AN11) -> 495345.99 | AO12: =+SUM(AO8:AO11) -> 1292263.8 | AQ12: =+SUM(AQ8:AQ11) -> 1611837.9 | AR12: =+SUM(AR8:AR11) -> 3151580.5 | AS12: =+SUM(AS8:AS11) -> 1539742.6 | AT12: =+AJ12/AF12 -> 1.4839627 | AU12: 398000 | AV12: =AJ12-AF12 -> 73671.899 | AY12: =SUM(AY4:AY11) -> 23948 | BI12: =+AT12 -> 1.4839627 | BK12: However, only 50% in Delivery ($75K) and 50% in R&D ($75k) | BW12: =+D12 -> 1201247.6 | BY12: =+F12 -> 354263.83 | BZ12: =+G12 -> 315813.64 | CB12: =+I12 -> 397447.97 | CC12: =+J12 -> 643733.33 | CE12: =+Y12 -> 364780.08 | CF12: =+Z12 -> 899769.7 | CH12: =SUM(CH8:CH11) -> 1611837.9 | CI12: =SUM(CI8:CI11) -> 2797071.7
BK13: Plus Expected 2021 bonuses at 50% = $50,000
B14: Gross profit (loss) | D14: =D5-D12 -> 319099.37 | F14: =F5-F12 -> 12025.04 | G14: =G5-G12 -> 119186.36 | I14: =I5-I12 -> 16082.351 | J14: =J5-J12 -> 81266.667 | L14: =L5-L12 -> -48426.74 | N14: =N5-N12 -> 94447.818 | P14: =P5-P12 -> -38004.63 | R14: 77890.242 | T14: =T5-T12 -> 93005.159 | V14: =V5-V12 -> 77891.242 | Y14: =Y5-Y12 -> 6573.7886 | Z14: =Z5-Z12 -> 250229.3 | AB14: -6769.8831 | AD14: 153824.58 | AF14: -2958.5536 | AH14: 153824.58 | AJ14: =AJ5-AJ12 -> -15717.722 | AL14: =AL5-AL12 -> -74912.939 | AN14: =AN5-AN12 -> -25446.159 | AO14: =AO5-AO12 -> 232736.21 | AQ14: =+F14+I14+Y14+AN14 -> 9235.0212 | AR14: =AR5-AR12 -> 683419.55 | AS14: =+AQ14-AR14 -> -674184.52 | AU14: 2000 | BW14: =+D14 -> 319099.37 | BY14: =+F14 -> 12025.04 | BZ14: =+G14 -> 119186.36 | CB14: =+I14 -> 16082.351 | CC14: =+J14 -> 81266.667 | CE14: =+Y14 -> 6573.7886 | CF14: =+Z14 -> 250229.3 | CH14: =CH5-CH12 -> 9235.0212 | CI14: =CI5-CI12 -> 529593.97
F15: =F14/F5 -> 0.03282939 | I15: =I14/I5 -> 0.03889038 | Y15: =Y14/Y5 -> 0.017702222 | AN15: =AN14/AN5 -> -0.054152305 | AQ15: =AQ14/AQ5 -> 0.0056968575
B16: S&M Expenses:
A17: 5500 | B17: Salaries and related expenses | D17: 463751.83 | F17: 165477.99 | G17: =SUMIF(budget!U:U,PL!A17,budget!L:L) -> 207847 | I17: 163810.85 | J17: =SUMIF(budget!U:U,PL!A17,budget!P:P) -> 261385.9 | L17: 68209.07 | N17: 139729.17 | P17: 67984.37 | R17: 139729.17 | T17: 90951.49 | V17: =SUMIF(budget!U:U,PL!A17,budget!S:S) -> 390916.67 | Y17: =L17+P17+T17 -> 227144.93 | Z17: =N17+R17+V17 -> 670375 | AB17: 223000.02 | AD17: 158229.17 | AF17: 81746.31 | AH17: 158229.17 | AJ17: =CH17-I17-F17-L17-P17-T17-AB17-AF17 -> 346277.45 | AL17: =SUMIF(budget!U:U,PL!A17,budget!X:X) -> 534141.67 | AN17: =+AB17+AF17+AJ17 -> 651023.78 | AO17: =SUMIF(budget!U:U,PL!A17,budget!Y:Y) -> 850600 | AQ17: =+F17+I17+Y17+AN17 -> 1207457.5 | AR17: =+G17+J17+Z17+AO17 -> 1990207.9 | AT17: =+AJ17/AF17 -> 4.236001 | AU17: 609750 | AV17: =AJ17-AF17 -> 264531.14 | AX17: Bonus 2021 | AY17: =17000+230000 -> 247000 | BA17: 80000 | BB17: without Colin's average would be $77,000 but we need to add | BI17: 1.7 | BJ17: Colin- retirement (128K)+ Sara (full month work- 10K) | BK17: New EE: BDR, 2 sales reps, 1 SE, | BW17: =+D17 -> 463751.83 | BY17: =+F17 -> 165477.99 | BZ17: =+G17 -> 207847 | CB17: =+I17 -> 163810.85 | CC17: =+J17 -> 261385.9 | CE17: =+Y17 -> 227144.93 | CF17: =+Z17 -> 670375 | CH17: =SUMIF('HARKAVA '!$Z:$Z,PL!A17,'HARKAVA '!Y:Y) -> 1207457.5 | CI17: =G17+J17+Z17+AD17+AL17 -> 1831978.7
A18: 5505 | B18: Non budgeted items (Esop, vacation provision) | D18: 5653.56 | F18: 11792 | G18: 0 | I18: 20003.4 | J18: 0 | L18: 1892 | N18: 0 | P18: -453 | R18: 0 | T18: 21648.13 | V18: =SUMIF(budget!U:U,PL!A18,budget!S:S) -> 0 | Y18: =L18+P18+T18 -> 23087.13 | Z18: =N18+R18+V18 -> 0 | AB18: -6455.32 | AD18: 0 | AF18: -8042 | AH18: 0 | AJ18: =CH18-I18-F18-L18-P18-T18-AB18-AF18 -> -26199.792 | AL18: =SUMIF(budget!U:U,PL!A18,budget!X:X) -> 0 | AN18: =+AB18+AF18+AJ18 -> -40697.112 | AO18: =SUMIF(budget!U:U,PL!A18,budget!Y:Y) -> 0 | AQ18: =+F18+I18+Y18+AN18 -> 14185.418 | AR18: =+G18+J18+Z18+AO18 -> 0 | AT18: =+AJ18/AF18 -> 3.2578701 | AU18: -7000 | AV18: =AJ18-AF18 -> -18157.792 | AX18: Sara- monthly commission (2 months) | AY18: =13000 -> 13000 | BA18: =+BB49+BB50 -> 68150 | BB18: bonus | BI18: =+AT18 -> 3.2578701 | BK18: 4 HC @$175,000 = $700,000 /12 * 1.5 = ~$100,000 | BW18: =+D18 -> 5653.56 | BY18: =+F18 -> 11792 | BZ18: =+G18 -> 0 | CB18: =+I18 -> 20003.4 | CC18: =+J18 -> 0 | CE18: =+Y18 -> 23087.13 | CF18: =+Z18 -> 0 | CH18: =SUMIF('HARKAVA '!$Z:$Z,PL!A18,'HARKAVA '!Y:Y) -> 14185.418 | CI18: =G18+J18+Z18+AD18+AL18 -> 0
A19: 5510 | B19: Consulting and outsourced work | D19: 93419.56 | F19: 43953.47 | G19: =SUMIF(budget!U:U,PL!A19,budget!L:L) -> 60000 | I19: 42632.53 | J19: =SUMIF(budget!U:U,PL!A19,budget!P:P) -> 100000 | L19: =10886.76+17000 -> 27886.76 | N19: 53000 | P19: 3753.02 | R19: 53000 | T19: 51784.83 | V19: =SUMIF(budget!U:U,PL!A19,budget!S:S) -> 55000 | Y19: =L19+P19+T19 -> 83424.61 | Z19: =N19+R19+V19 -> 161000 | AB19: 22084.74 | AD19: 56666.667 | AF19: 30959.39 | AH19: 56666.667 | AJ19: =CH19-I19-F19-L19-P19-T19-AB19-AF19 -> 65263.33 | AL19: =SUMIF(budget!U:U,PL!A19,budget!X:X) -> 56666.667 | AN19: =+AB19+AF19+AJ19 -> 118307.46 | AO19: =SUMIF(budget!U:U,PL!A19,budget!Y:Y) -> 170000 | AQ19: =+F19+I19+Y19+AN19 -> 288318.07 | AR19: =+G19+J19+Z19+AO19 -> 491000 | AT19: =+AJ19/AF19 -> 2.1080302 | AU19: 100000 | AV19: =AJ19-AF19 -> 34303.94 | AW19: Magdalene 20K | AX19: Frida Ethan- full month | AY19: 4124 | BA19: 186400 | BB19: Sarah's commission for Dec deals | BI19: 1.2 | BJ19: Less marketing expenses | BK19: Non-HC: PR ($15kx3), Gartner, Forrester @ 12 month contract $100,000/12 *2 = $17k | BW19: =+D19 -> 93419.56 | BY19: =+F19 -> 43953.47 | BZ19: =+G19 -> 60000 | CB19: =+I19 -> 42632.53 | CC19: =+J19 -> 100000 | CE19: =+Y19 -> 83424.61 | CF19: =+Z19 -> 161000 | CH19: =SUMIF('HARKAVA '!$Z:$Z,PL!A19,'HARKAVA '!Y:Y) -> 288318.07 | CI19: =G19+J19+Z19+AD19+AL19 -> 434333.33 | CJ19: Marketing Expenses- RSA conference+ cybertech NYC (40usd)
A20: 5540 | B20: Travel | N20: 5000 | P20: 0 | R20: 5000 | T20: 436.84 | V20: =SUMIF(budget!U:U,PL!A20,budget!S:S) -> 5000 | Y20: =L20+P20+T20 -> 436.84 | Z20: =N20+R20+V20 -> 15000 | AB20: -260.25 | AD20: 5000 | AF20: 3923.6 | AH20: 5000 | AJ20: =CH20-I20-F20-L20-P20-T20-AB20-AF20 -> 11723.541 | AL20: =SUMIF(budget!U:U,PL!A20,budget!X:X) -> 5000 | AN20: =+AB20+AF20+AJ20 -> 15386.891 | AO20: =SUMIF(budget!U:U,PL!A20,budget!Y:Y) -> 15000 | AQ20: =+F20+I20+Y20+AN20 -> 15823.731 | AR20: =+G20+J20+Z20+AO20 -> 30000 | AU20: - | AV20: =AJ20-AF20 -> 7799.9413 | AW20: Overhead- Travel | AY20: =SUM(AY17:AY19) -> 264124 | BA20: =+SUM(BA17:BA19) -> 334550 | BI20: =+AT20 -> 0 | BK20: Plus Expected 2021 bonuses = $125,000 | BW20: =+D20 -> 0 | BY20: =+F20 -> 0 | BZ20: =+G20 -> 0 | CB20: =+I20 -> 0 | CC20: =+J20 -> 0 | CE20: =+Y20 -> 436.84 | CF20: =+Z20 -> 15000 | CH20: =SUMIF('HARKAVA '!$Z:$Z,PL!A20,'HARKAVA '!Y:Y) -> 15823.731 | CI20: =G20+J20+Z20+AD20+AL20 -> 25000
A21: 5550 | B21: Other | D21: 4552.13 | F21: 1662.86 | G21: =SUMIF(budget!U:U,PL!A21,budget!L:L) -> 7200 | I21: -1368.55 | J21: =SUMIF(budget!U:U,PL!A21,budget!P:P) -> 8000 | L21: 0 | N21: 6400 | P21: 1398.68 | R21: 6400 | T21: -896.19 | V21: =SUMIF(budget!U:U,PL!A21,budget!S:S) -> 6400 | Y21: =L21+P21+T21 -> 502.49 | Z21: =N21+R21+V21 -> 19200 | AB21: 1856 | AD21: 8000 | AF21: 282.8 | AH21: 8000 | AJ21: =CH21-I21-F21-L21-P21-T21-AB21-AF21 -> 22303.519 | AL21: =SUMIF(budget!U:U,PL!A21,budget!X:X) -> 8000 | AN21: =+AB21+AF21+AJ21 -> 24442.319 | AO21: =SUMIF(budget!U:U,PL!A21,budget!Y:Y) -> 24000 | AQ21: =+F21+I21+Y21+AN21 -> 25239.119 | AR21: =+G21+J21+Z21+AO21 -> 58400 | AT21: =+AJ21/AF21 -> 78.866759 | AU21: -1000 | AV21: =AJ21-AF21 -> 22020.719 | AW21: Overhead- increase in License+ IT expenses | BI21: =+AT21 -> 78.866759 | BK21: Plus $80k Colin & $6,250x3 Sarah | BW21: =+D21 -> 4552.13 | BY21: =+F21 -> 1662.86 | BZ21: =+G21 -> 7200 | CB21: =+I21 -> -1368.55 | CC21: =+J21 -> 8000 | CE21: =+Y21 -> 502.49 | CF21: =+Z21 -> 19200 | CH21: =SUMIF('HARKAVA '!$Z:$Z,PL!A21,'HARKAVA '!Y:Y) -> 25239.119 | CI21: =G21+J21+Z21+AD21+AL21 -> 50400
B22: Total sales and marketing expenses | D22: =SUM(D17:D21) -> 567377.08 | F22: =SUM(F17:F21) -> 222886.32 | G22: =SUM(G17:G21) -> 275047 | I22: =SUM(I17:I21) -> 225078.23 | J22: =SUM(J17:J21) -> 369385.9 | L22: =SUM(L17:L21) -> 97987.83 | N22: =SUM(N17:N21) -> 204129.17 | P22: =SUM(P17:P21) -> 72683.07 | R22: 204129.17 | T22: =SUM(T17:T21) -> 163925.1 | V22: =SUM(V17:V21) -> 457316.67 | Y22: =SUM(Y17:Y21) -> 334596 | Z22: =SUM(Z17:Z21) -> 865575 | AB22: 240225.19 | AD22: 227895.83 | AF22: 108870.1 | AH22: 227895.83 | AJ22: =SUM(AJ17:AJ21) -> 419368.05 | AL22: =SUM(AL17:AL21) -> 603808.33 | AN22: =+SUM(AN17:AN21) -> 768463.34 | AO22: =+SUM(AO17:AO21) -> 1059600 | AQ22: =+SUM(AQ17:AQ21) -> 1551023.9 | AR22: =+SUM(AR17:AR21) -> 2569607.9 | AS22: =+AR22-AQ22 -> 1018584 | AU22: 701750 | AV22: =AJ22-AF22 -> 310497.95 | BW22: =+D22 -> 567377.08 | BY22: =+F22 -> 222886.32 | BZ22: =+G22 -> 275047 | CB22: =+I22 -> 225078.23 | CC22: =+J22 -> 369385.9 | CE22: =+Y22 -> 334596 | CF22: =+Z22 -> 865575 | CH22: =SUM(CH17:CH21) -> 1551023.9 | CI22: =SUM(CI17:CI21) -> 2341712.1
B24: R&D Expenses:
A25: 5400 | B25: Salaries and related expenses | D25: 1134381.5 | F25: 540574.01 | G25: =SUMIF(budget!U:U,PL!A25,budget!L:L) -> 499348.56 | I25: =857142 -> 857142 | J25: =SUMIF(budget!U:U,PL!A25,budget!P:P) -> 649017.05 | L25: 280219.78 | N25: 358689.39 | P25: 290018.96 | R25: 358689.39 | T25: 416439.58 | V25: =SUMIF(budget!U:U,PL!A25,budget!S:S) -> 397390.98 | Y25: =L25+P25+T25 -> 986678.32 | Z25: =N25+R25+V25 -> 1114769.8 | AB25: 431215.01 | AD25: 442507.58 | AF25: 516477.77 | AH25: 442507.58 | AJ25: =CH25-I25-F25-L25-P25-T25-AB25-AF25 -> 678976.19 | AL25: =SUMIF(budget!U:U,PL!A25,budget!X:X) -> 549390.98 | AN25: =+AB25+AF25+AJ25 -> 1626669 | AO25: =SUMIF(budget!U:U,PL!A25,budget!Y:Y) -> 1434406.1 | AQ25: =+F25+I25+Y25+AN25 -> 4011063.3 | AR25: =+G25+J25+Z25+AO25 -> 3697541.5 | AT25: =+AJ25/AF25 -> 1.3146281 | AU25: 1596000 | AV25: =AJ25-AF25 -> 162498.42 | AX25: Bonus 2021 | AY25: =178000-20000 -> 158000 | BA25: =+AJ25 -> 678976.19 | BB25: will use the $50,000 as the increase in employees in R&D for Dec | BI25: 1.4 | BK25: 10 Developers @$120,000x 10 = $1,200,000 /12 x 3 = $300,000 | BW25: =+D25 -> 1134381.5 | BY25: =+F25 -> 540574.01 | BZ25: =+G25 -> 499348.56 | CB25: =+I25 -> 857142 | CC25: =+J25 -> 649017.05 | CE25: =+Y25 -> 986678.32 | CF25: =+Z25 -> 1114769.8 | CH25: =SUMIF('HARKAVA '!$Z:$Z,PL!A25,'HARKAVA '!Y:Y) -> 4011063.3 | CI25: =G25+J25+Z25+AD25+AL25 -> 3255033.9
A26: 5411 | B26: Non budgeted items (Esop, vacation provision) | D26: 81016 | F26: 7331.56 | G26: =SUMIF(budget!U:U,PL!A26,budget!L:L) -> 0 | I26: 40307.19 | J26: 0 | L26: 1922 | N26: 0 | P26: 933 | R26: 0 | T26: 17961.18 | V26: =SUMIF(budget!U:U,PL!A26,budget!S:S) -> 0 | Y26: =L26+P26+T26 -> 20816.18 | Z26: =N26+R26+V26 -> 0 | AB26: 1112 | AD26: 0 | AF26: 998 | AH26: 0 | AJ26: =CH26-I26-F26-L26-P26-T26-AB26-AF26 -> 53215.997 | AL26: =SUMIF(budget!U:U,PL!A26,budget!X:X) -> 0 | AN26: =+AB26+AF26+AJ26 -> 55325.997 | AO26: =SUMIF(budget!U:U,PL!A26,budget!Y:Y) -> 0 | AQ26: =+F26+I26+Y26+AN26 -> 123780.93 | AR26: =+G26+J26+Z26+AO26 -> 0 | AT26: =+AJ26/AF26 -> 53.322643 | AU26: 1000 | AV26: =AJ26-AF26 -> 52217.997 | AX26: Vardi Daniel- new employee | AY26: 10523 | BA26: =+BB51 -> 176400 | BB26: Bonus | BI26: =+AT26 -> 53.322643 | BK26: Plus $75k from Delivery | BW26: =+D26 -> 81016 | BY26: =+F26 -> 7331.56 | BZ26: =+G26 -> 0 | CB26: =+I26 -> 40307.19 | CC26: =+J26 -> 0 | CE26: =+Y26 -> 20816.18 | CF26: =+Z26 -> 0 | CH26: =SUMIF('HARKAVA '!$Z:$Z,PL!A26,'HARKAVA '!Y:Y) -> 123780.93 | CI26: =G26+J26+Z26+AD26+AL26 -> 0
A27: 5410 | B27: Outsourced work | D27: 69106.37 | F27: 120676.98 | G27: =SUMIF(budget!U:U,PL!A27,budget!L:L) -> 34999.667 | I27: 228889.35 | J27: =SUMIF(budget!U:U,PL!A27,budget!P:P) -> 38332.667 | L27: 25409.45 | N27: 20000 | P27: 72356.79 | R27: 20000 | T27: 91427.39 | V27: =SUMIF(budget!U:U,PL!A27,budget!S:S) -> 20000 | Y27: =L27+P27+T27 -> 189193.63 | Z27: =N27+R27+V27 -> 60000 | AB27: 138662.99 | AD27: 20000 | AF27: 115169.38 | AH27: 20000 | AJ27: =CH27-I27-F27-L27-P27-T27-AB27-AF27 -> 158807.49 | AL27: =SUMIF(budget!U:U,PL!A27,budget!X:X) -> 20000 | AN27: =+AB27+AF27+AJ27 -> 412639.86 | AO27: =SUMIF(budget!U:U,PL!A27,budget!Y:Y) -> 60000 | AQ27: =+F27+I27+Y27+AN27 -> 951399.82 | AR27: =+G27+J27+Z27+AO27 -> 193332.33 | AT27: =+AJ27/AF27 -> 1.3789038 | AU27: 284000 | AV27: =AJ27-AF27 -> 43638.115 | AW27: Doit 16K+ Snyk 9K | AX27: Furman Vitaly- new employee | AY27: 14325 | BA27: =+BA10 -> 47150 | BB27: 50% Bonus from Delivery | BI27: 1.5 | BJ27: Product security (21K)+ Architecture professional services (ilana moskovitz- 15K) | BK27: Plus 2021 expected bonuses = $215,000 (includes $50,000 from Delivery) | BW27: =+D27 -> 69106.37 | BY27: =+F27 -> 120676.98 | BZ27: =+G27 -> 34999.667 | CB27: =+I27 -> 228889.35 | CC27: =+J27 -> 38332.667 | CE27: =+Y27 -> 189193.63 | CF27: =+Z27 -> 60000 | CH27: =SUMIF('HARKAVA '!$Z:$Z,PL!A27,'HARKAVA '!Y:Y) -> 951399.82 | CI27: =G27+J27+Z27+AD27+AL27 -> 173332.33 | CJ27: doit (50K), graphics design (-13K), architectures professional (-12K)
A28: 5417 | B28: Patents | N28: 3333 | P28: 0 | R28: 3333 | T28: 0 | V28: =SUMIF(budget!U:U,PL!A28,budget!S:S) -> 3334 | Y28: =L28+P28+T28 -> 0 | Z28: =N28+R28+V28 -> 10000 | AB28: 0 | AD28: 3333 | AF28: 0 | AH28: 3333 | AJ28: =CH28-I28-F28-L28-P28-T28-AB28-AF28 -> 0 | AL28: =SUMIF(budget!U:U,PL!A28,budget!X:X) -> 3334 | AN28: =+AB28+AF28+AJ28 -> 0 | AO28: =SUMIF(budget!U:U,PL!A28,budget!Y:Y) -> 10000 | AQ28: =+F28+I28+Y28+AN28 -> 0 | AR28: =+G28+J28+Z28+AO28 -> 20000 | AU28: - | AV28: =AJ28-AF28 -> 0 | AX28: Retro Pension during Nov | AY28: -14000 | BA28: =+SUM(BA25:BA27) -> 902526.19 | BI28: =+AT28 -> 0 | BW28: =+D28 -> 0 | BY28: =+F28 -> 0 | BZ28: =+G28 -> 0 | CB28: =+I28 -> 0 | CC28: =+J28 -> 0 | CE28: =+Y28 -> 0 | CF28: =+Z28 -> 10000 | CH28: =SUMIF('HARKAVA '!$Z:$Z,PL!A28,'HARKAVA '!Y:Y) -> 0 | CI28: =G28+J28+Z28+AD28+AL28 -> 16667
A29: 5416 | B29: Other | D29: =8805.03+132809 -> 141614.03 | F29: =7616+41035 -> 48651 | G29: =SUMIF(budget!U:U,PL!A29,budget!L:L) -> 43720 | I29: 38763.989 | J29: =SUMIF(budget!U:U,PL!A29,budget!P:P) -> 50120 | L29: 26561.31 | N29: 25040 | P29: 22946.34 | R29: 25040 | T29: 30053.751 | V29: =SUMIF(budget!U:U,PL!A29,budget!S:S) -> 25840 | Y29: =L29+P29+T29 -> 79561.401 | Z29: =N29+R29+V29 -> 75920 | AB29: 47549.919 | AD29: 29040 | AF29: 57605.686 | AH29: 29040 | AJ29: =CH29-I29-F29-L29-P29-T29-AB29-AF29 -> 188730.73 | AL29: =SUMIF(budget!U:U,PL!A29,budget!X:X) -> 29040 | AN29: =+AB29+AF29+AJ29 -> 293886.34 | AO29: =SUMIF(budget!U:U,PL!A29,budget!Y:Y) -> 87120 | AQ29: =+F29+I29+Y29+AN29 -> 460862.73 | AR29: =+G29+J29+Z29+AO29 -> 256880 | AT29: =+AJ29/AF29 -> 3.2762518 | AU29: 126000 | AV29: =AJ29-AF29 -> 131125.05 | AW29: Overhead- increase in License+ IT expenses+Travel | AX29: Reclass from COGS | AY29: =-AY11 -> 68329 | BI29: =+AT29 -> 3.2762518 | BW29: =+D29 -> 141614.03 | BY29: =+F29 -> 48651 | BZ29: =+G29 -> 43720 | CB29: =+I29 -> 38763.989 | CC29: =+J29 -> 50120 | CE29: =+Y29 -> 79561.401 | CF29: =+Z29 -> 75920 | CH29: =SUMIF('HARKAVA '!$Z:$Z,PL!A29,'HARKAVA '!Y:Y) -> 460862.73 | CI29: =G29+J29+Z29+AD29+AL29 -> 227840 | CJ29: (depreciation 3K)+ overhead (more employees)
A30: 54 | B30: Total research and development expenses | D30: =SUM(D25:D29)-1 -> 1426116.9 | F30: =SUM(F25:F29) -> 717233.55 | G30: =SUM(G25:G29) -> 578068.23 | I30: =SUM(I25:I29) -> 1165102.5 | J30: =SUM(J25:J29) -> 737469.71 | L30: =SUM(L25:L29) -> 334112.54 | N30: =SUM(N25:N29) -> 407062.39 | P30: =SUM(P25:P29) -> 386255.09 | R30: 407062.39 | T30: =SUM(T25:T29) -> 555881.9 | V30: =SUM(V25:V29) -> 446564.98 | Y30: =SUM(Y25:Y29) -> 1276249.5 | Z30: =SUM(Z25:Z29) -> 1260689.8 | AB30: 618539.92 | AD30: 494880.58 | AF30: 690250.84 | AH30: 494880.58 | AJ30: =SUM(AJ25:AJ29) -> 1079730.4 | AL30: =SUM(AL25:AL29) -> 601764.98 | AN30: =+SUM(AN25:AN29) -> 2388521.2 | AO30: =+SUM(AO25:AO29) -> 1591526.1 | AQ30: =+SUM(AQ25:AQ29) -> 5547106.8 | AR30: =+SUM(AR25:AR29) -> 4167753.8 | AS30: =+AR30-AQ30 -> -1379352.9 | AT30: =+AJ30/AF30 -> 1.564258 | AU30: 2007000 | AV30: =AJ30-AF30 -> 389479.58 | AY30: =SUM(AY25:AY29) -> 237177 | BI30: =+AT30 -> 1.564258 | BW30: =+D30 -> 1426116.9 | BY30: =+F30 -> 717233.55 | BZ30: =+G30 -> 578068.23 | CB30: =+I30 -> 1165102.5 | CC30: =+J30 -> 737469.71 | CE30: =+Y30 -> 1276249.5 | CF30: =+Z30 -> 1260689.8 | CH30: =SUM(CH25:CH29)-1 -> 5547105.8 | CI30: =SUM(CI25:CI29) -> 3672873.3
B32: G&A Expenses:
A33: 5600 | B33: Salaries and related | D33: 483516.96 | F33: 144947.84 | G33: =SUMIF(budget!U:U,PL!A33,budget!L:L) -> 153489.77 | I33: 186627.57 | J33: =SUMIF(budget!U:U,PL!A33,budget!P:P) -> 167672.41 | L33: 56249.628 | N33: 98509.47 | P33: 72334.77 | R33: 98509.47 | T33: 72571.87 | V33: =SUMIF(budget!U:U,PL!A33,budget!S:S) -> 98509.47 | Y33: =L33+P33+T33 -> 201156.27 | Z33: =N33+R33+V33 -> 295528.41 | AB33: 191312.76 | AD33: 98509.47 | AF33: 228756.45 | AH33: 98509.47 | AJ33: =CH33-I33-F33-L33-P33-T33-AB33-AF33 -> 375865.19 | AL33: =SUMIF(budget!U:U,PL!A33,budget!X:X) -> 297389.02 | AN33: =+AB33+AF33+AJ33 -> 795934.4 | AO33: =SUMIF(budget!U:U,PL!A33,budget!Y:Y) -> 494407.95 | AQ33: =+F33+I33+Y33+AN33 -> 1328666.1 | AR33: =+G33+J33+Z33+AO33 -> 1111098.5 | AT33: =+AJ33/AF33 -> 1.6430802 | AU33: 472000 | AV33: =AJ33-AF33 -> 147108.74 | AX33: Bonus 2021 | AY33: =100000+27000 -> 127000 | BA33: =+AJ33+BE33-65000 -> 340865.19 | BB33: Nov Actual plus a few hires @ | BE33: 30000 | BI33: 1.3 | BK33: Plus 2021 Expected Bonuses = $210,000 | BW33: =+D33 -> 483516.96 | BY33: =+F33 -> 144947.84 | BZ33: =+G33 -> 153489.77 | CB33: =+I33 -> 186627.57 | CC33: =+J33 -> 167672.41 | CE33: =+Y33 -> 201156.27 | CF33: =+Z33 -> 295528.41 | CH33: =SUMIF('HARKAVA '!$Z:$Z,PL!A33,'HARKAVA '!Y:Y) -> 1328666.1 | CI33: =G33+J33+Z33+AD33+AL33 -> 1012589.1 | CK33: What happened in September?
A34: 5603 | B34: Non budgeted items (Esop, vacation provision) | D34: -7391.12 | F34: -699.93 | G34: 0 | I34: 9687.84 | J34: 0 | L34: -4482.62 | N34: 0 | P34: -950.43 | R34: 0 | T34: 11817.36 | V34: =SUMIF(budget!U:U,PL!A34,budget!S:S) -> 0 | Y34: =L34+P34+T34 -> 6384.31 | Z34: =N34+R34+V34 -> 0 | AB34: 573 | AD34: 0 | AF34: -5035.52 | AH34: 0 | AJ34: =CH34-I34-F34-L34-P34-T34-AB34-AF34 -> -11907.71 | AL34: =SUMIF(budget!U:U,PL!A34,budget!X:X) -> 0 | AN34: =+AB34+AF34+AJ34 -> -16370.23 | AO34: =SUMIF(budget!U:U,PL!A34,budget!Y:Y) -> 0 | AQ34: =+F34+I34+Y34+AN34 -> -998.01 | AR34: =+G34+J34+Z34+AO34 -> 0 | AT34: =+AJ34/AF34 -> 2.3647429 | AU34: - | AV34: =AJ34-AF34 -> -6872.19 | AX34: Ariel Bonus | AY34: =AY7+AY9 -> -15500 | BA34: =56000/2 -> 28000 | BB34: 50% Ariel's bonus paid in IL in June expenses now | BI34: =+AT34 -> 2.3647429 | BW34: =+D34 -> -7391.12 | BY34: =+F34 -> -699.93 | BZ34: =+G34 -> 0 | CB34: =+I34 -> 9687.84 | CC34: =+J34 -> 0 | CE34: =+Y34 -> 6384.31 | CF34: =+Z34 -> 0 | CH34: =SUMIF('HARKAVA '!$Z:$Z,PL!A34,'HARKAVA '!Y:Y) -> -998.01 | CI34: =G34+J34+Z34+AD34+AL34 -> 0 | CK34: Reserve refunds - divide between departments
A35: 5610 | B35: Professional fees | D35: 308741.54 | F35: 110882.83 | G35: =SUMIF(budget!U:U,PL!A35,budget!L:L) -> 107824.55 | I35: 152411.56 | J35: =SUMIF(budget!U:U,PL!A35,budget!P:P) -> 272049.55 | L35: 62846.33 | N35: 208580 | P35: 128164.18 | R35: 95203.333 | T35: 87596.44 | V35: =SUMIF(budget!U:U,PL!A35,budget!S:S) -> 87203.333 | Y35: =L35+P35+T35 -> 278606.95 | Z35: =N35+R35+V35 -> 390986.67 | AB35: 60043.94 | AD35: 151493.33 | AF35: 91057.42 | AH35: 77493.333 | AJ35: =CH35-I35-F35-L35-P35-T35-AB35-AF35 -> 213151.65 | AL35: =SUMIF(budget!U:U,PL!A35,budget!X:X) -> 77493.333 | AN35: =+AB35+AF35+AJ35 -> 364253.01 | AO35: =SUMIF(budget!U:U,PL!A35,budget!Y:Y) -> 306480 | AQ35: =+F35+I35+Y35+AN35 -> 906154.35 | AR35: =+G35+J35+Z35+AO35 -> 1077340.8 | AT35: =+AJ35/AF35 -> 2.3408488 | AU35: 334000 | AV35: =AJ35-AF35 -> 122094.23 | AX35: Ofer bonus2021 | AY35: =100000*0.2 -> 20000 | BA35: =+BB52 -> 163800 | BB35: Bonus | BI35: 1.2 | BJ35: Jorge- Reclassification to salaries (-95K)+ recruitments (56K) | BW35: =+D35 -> 308741.54 | BY35: =+F35 -> 110882.83 | BZ35: =+G35 -> 107824.55 | CB35: =+I35 -> 152411.56 | CC35: =+J35 -> 272049.55 | CE35: =+Y35 -> 278606.95 | CF35: =+Z35 -> 390986.67 | CH35: =SUMIF('HARKAVA '!$Z:$Z,PL!A35,'HARKAVA '!Y:Y) -> 906154.35 | CI35: =G35+J35+Z35+AD35+AL35 -> 999847.42 | CJ35: Malka (decrease 28,600)+ recruitment (decrease 30K)
A36: 5620 | B36: Rent and office | D36: 51729.66 | F36: 10479 | G36: =SUMIF(budget!U:U,PL!A36,budget!L:L) -> 64500 | I36: 14221.063 | J36: =SUMIF(budget!U:U,PL!A36,budget!P:P) -> 69000 | L36: 4800.9 | N36: 32500 | P36: 8552.4967 | R36: 32500 | T36: 9681.4298 | V36: =SUMIF(budget!U:U,PL!A36,budget!S:S) -> 32500 | Y36: =L36+P36+T36 -> 23034.827 | Z36: =N36+R36+V36 -> 97500 | AB36: 5398.2654 | AD36: 37500 | AF36: 14059.333 | AH36: 37500 | AJ36: =CH36-I36-F36-L36-P36-T36-AB36-AF36 -> 5428.2855 | AL36: =SUMIF(budget!U:U,PL!A36,budget!X:X) -> 37500 | AN36: =+AB36+AF36+AJ36 -> 24885.884 | AO36: =SUMIF(budget!U:U,PL!A36,budget!Y:Y) -> 112500 | AQ36: =+F36+I36+Y36+AN36 -> 72620.774 | AR36: =+G36+J36+Z36+AO36 -> 343500 | AT36: =+AJ36/AF36 -> 0.38609837 | AU36: - | AV36: =AJ36-AF36 -> -8631.0475 | AX36: Orit- new employee | AY36: 11000 | BA36: =+SUM(BA33:BA35) -> 532665.19 | BI36: =+AT36 -> 0.38609837 | BW36: =+D36 -> 51729.66 | BY36: =+F36 -> 10479 | BZ36: =+G36 -> 64500 | CB36: =+I36 -> 14221.063 | CC36: =+J36 -> 69000 | CE36: =+Y36 -> 23034.827 | CF36: =+Z36 -> 97500 | CH36: =SUMIF('HARKAVA '!$Z:$Z,PL!A36,'HARKAVA '!Y:Y) -> 72620.774 | CI36: =G36+J36+Z36+AD36+AL36 -> 306000
A37: 5680 | B37: Travel | D37: 16569.96 | F37: 6213 | G37: =SUMIF(budget!U:U,PL!A37,budget!L:L) -> 0 | I37: 10302.6 | J37: =SUMIF(budget!U:U,PL!A37,budget!P:P) -> 10000 | L37: 314.94 | N37: 5000 | P37: 567.67 | R37: 5000 | T37: 3100.33 | V37: =SUMIF(budget!U:U,PL!A37,budget!S:S) -> 5000 | Y37: =L37+P37+T37 -> 3982.94 | Z37: =N37+R37+V37 -> 15000 | AB37: 8174.6 | AD37: 8333.3333 | AF37: 7395.4 | AH37: 8333.3333 | AJ37: =CH37-I37-F37-L37-P37-T37-AB37-AF37 -> 4795.7029 | AL37: =SUMIF(budget!U:U,PL!A37,budget!X:X) -> 8333.3333 | AN37: =+AB37+AF37+AJ37 -> 20365.703 | AO37: =SUMIF(budget!U:U,PL!A37,budget!Y:Y) -> 25000 | AQ37: =+F37+I37+Y37+AN37 -> 40864.243 | AR37: =+G37+J37+Z37+AO37 -> 50000 | AT37: =+AJ37/AF37 -> 0.64847106 | AU37: 11000 | AV37: =AJ37-AF37 -> -2599.6971 | AX37: Shir Gazit- new employee | AY37: 5973 | BI37: =+AT37 -> 0.64847106 | BW37: =+D37 -> 16569.96 | BY37: =+F37 -> 6213 | BZ37: =+G37 -> 0 | CB37: =+I37 -> 10302.6 | CC37: =+J37 -> 10000 | CE37: =+Y37 -> 3982.94 | CF37: =+Z37 -> 15000 | CH37: =SUMIF('HARKAVA '!$Z:$Z,PL!A37,'HARKAVA '!Y:Y) -> 40864.243 | CI37: =G37+J37+Z37+AD37+AL37 -> 41666.667
