Workbook

Sheet BS USD
C1: Wematch.live
C2: USD
E5: WUS- INC | F5: EQD | G5: WIR | H5: WSF- LTD [IL] | I5: WSF LTD | J5: R&D | K5: WTSE | L5: Elimination | N5: JE'S | O5: Total
E6: 31.12.2022 | F6: 31.12.2022 | G6: 31.12.2022 | H6: 31.12.2022 | I6: 31.12.2022 | J6: 31.12.2022 | K6: 31.12.2022 | O6: 31.12.2022 | Q6: in 000' | S6: NOTE
B7: INDEX
C8: Assets | Q8: =+O8/1000 -> 0
C10: Current Assets: | Q10: =+O10/1000 -> 0
B11: 10 | C11: Cash and cash equivalent | E11: =+SUMIF('Full BS-USD'!$K:$K,B11,'Full BS-USD'!$C:$C) -> 222640.47 | F11: =+SUMIF('Full BS-USD'!$K:$K,B11,'Full BS-USD'!$D:$D) -> 20671.85 | G11: =+SUMIF('Full BS-USD'!$K:$K,B11,'Full BS-USD'!$E:$E) -> 21.81 | H11: =+SUMIF('Full BS-USD'!$K:$K,B11,'Full BS-USD'!$F:$F) -> 476.55 | I11: =+SUMIF('Full BS-USD'!$K:$K,B11,'Full BS-USD'!$G:$G) -> 671296.2 | J11: =+SUMIF('Full BS-USD'!$K:$K,B11,'Full BS-USD'!$H:$H) -> 6448566.6 | K11: =+SUMIF('Full BS-USD'!$K:$K,B11,'Full BS-USD'!$I:$I) -> 294848.47 | L11: =+SUMIF('Full BS-USD'!$K:$K,B11,'Full BS-USD'!$B:$B) -> 0 | O11: =+SUMIF('Full BS-USD'!$K:$K,B11,'Full BS-USD'!$J:$J) -> 7658522 | P11: =+O11-SUM(E11:L11) -> 0 | Q11: =+ROUND((O11/1000),0)+1 -> 7660
B12: 11 | C12: Short term restricted deposits | E12: =+SUMIF('Full BS-USD'!$K:$K,B12,'Full BS-USD'!$C:$C) -> 0 | F12: =+SUMIF('Full BS-USD'!$K:$K,B12,'Full BS-USD'!$D:$D) -> 0 | G12: =+SUMIF('Full BS-USD'!$K:$K,B12,'Full BS-USD'!$E:$E) -> 0 | H12: =+SUMIF('Full BS-USD'!$K:$K,B12,'Full BS-USD'!$F:$F) -> 0 | I12: =+SUMIF('Full BS-USD'!$K:$K,B12,'Full BS-USD'!$G:$G) -> 0 | J12: =+SUMIF('Full BS-USD'!$K:$K,B12,'Full BS-USD'!$H:$H) -> 11163411 | K12: =+SUMIF('Full BS-USD'!$K:$K,B12,'Full BS-USD'!$I:$I) -> 0 | L12: =+SUMIF('Full BS-USD'!$K:$K,B12,'Full BS-USD'!$B:$B) -> 0 | O12: =+SUMIF('Full BS-USD'!$K:$K,B12,'Full BS-USD'!$J:$J) -> 11163411 | P12: =+O12-SUM(E12:L12) -> 0 | Q12: =+ROUND((O12/1000),0) -> 11163
B13: 12 | C13: Trade recievables | E13: =+SUMIF('Full BS-USD'!$K:$K,B13,'Full BS-USD'!$C:$C) -> 0 | F13: =+SUMIF('Full BS-USD'!$K:$K,B13,'Full BS-USD'!$D:$D) -> 0 | G13: =+SUMIF('Full BS-USD'!$K:$K,B13,'Full BS-USD'!$E:$E) -> 0 | H13: =+SUMIF('Full BS-USD'!$K:$K,B13,'Full BS-USD'!$F:$F) -> 0 | I13: =+SUMIF('Full BS-USD'!$K:$K,B13,'Full BS-USD'!$G:$G) -> 0 | J13: =+SUMIF('Full BS-USD'!$K:$K,B13,'Full BS-USD'!$H:$H) -> 2037911.9 | K13: =+SUMIF('Full BS-USD'!$K:$K,B13,'Full BS-USD'!$I:$I) -> 28375.56 | L13: =+SUMIF('Full BS-USD'!$K:$K,B13,'Full BS-USD'!$B:$B) -> -28375.56 | O13: =+SUMIF('Full BS-USD'!$K:$K,B13,'Full BS-USD'!$J:$J) -> 2037911.9 | P13: =+O13-SUM(E13:L13) -> 0 | Q13: =+ROUND((O13/1000),0)-1 -> 2037 | S13: =+NOTES!B5 -> 3
B14: 13 | C14: other recievables and prepaid expenses | E14: =+SUMIF('Full BS-USD'!$K:$K,B14,'Full BS-USD'!$C:$C) -> 754723.55 | F14: =+SUMIF('Full BS-USD'!$K:$K,B14,'Full BS-USD'!$D:$D) -> 4129.04 | G14: =+SUMIF('Full BS-USD'!$K:$K,B14,'Full BS-USD'!$E:$E) -> 491.94 | H14: =+SUMIF('Full BS-USD'!$K:$K,B14,'Full BS-USD'!$F:$F) -> 48261.82 | I14: =+SUMIF('Full BS-USD'!$K:$K,B14,'Full BS-USD'!$G:$G)+1012 -> 2440457 | J14: =+SUMIF('Full BS-USD'!$K:$K,B14,'Full BS-USD'!$H:$H)+1644 -> 4744524.1 | K14: =+SUMIF('Full BS-USD'!$K:$K,B14,'Full BS-USD'!$I:$I) -> 939180.31 | L14: =+SUMIF('Full BS-USD'!$K:$K,B14,'Full BS-USD'!$B:$B) -> -8155804.9 | O14: =+SUMIF('Full BS-USD'!$K:$K,B14,'Full BS-USD'!$J:$J)+2656 -> 775962.88 | P14: =+O14-SUM(E14:L14) -> 0 | Q14: =+ROUND((O14/1000),0) -> 776 | S14: =+NOTES!B10 -> 4
P15: =+O15-SUM(E15:L15) -> 0 | Q15: =+O15/1000 -> 0
C16: Total cerrent assets | E16: =+SUM(E11:E14) -> 977364.02 | F16: =+SUM(F11:F14) -> 24800.89 | G16: =+SUM(G11:G14) -> 513.75 | H16: =+SUM(H11:H14) -> 48738.37 | I16: =+SUM(I11:I14) -> 3111753.2 | J16: =+SUM(J11:J14) -> 24394413 | K16: =+SUM(K11:K14) -> 1262404.3 | L16: =+SUM(L11:L14) -> -8184180.5 | O16: =+SUM(O11:O14) -> 21635807 | P16: =+O16-SUM(E16:L16) -> 0 | Q16: =+SUM(Q11:Q14) -> 21636
P17: =+O17-SUM(E17:L17) -> 0 | Q17: =+O17/1000 -> 0
P18: =+O18-SUM(E18:L18) -> 0
C19: Long-Term assets: | P19: =+O19-SUM(E19:L19) -> 0
B20: 14 | C20: loans to employees | E20: =+SUMIF('Full BS-USD'!$K:$K,B20,'Full BS-USD'!$C:$C) -> -2371.05 | F20: =+SUMIF('Full BS-USD'!$K:$K,B20,'Full BS-USD'!$D:$D) -> 37427.66 | G20: =+SUMIF('Full BS-USD'!$K:$K,B20,'Full BS-USD'!$E:$E) -> 0 | H20: =+SUMIF('Full BS-USD'!$K:$K,B20,'Full BS-USD'!$F:$F) -> 0 | I20: =+SUMIF('Full BS-USD'!$K:$K,B20,'Full BS-USD'!$G:$G) -> -3045.65 | J20: =+SUMIF('Full BS-USD'!$K:$K,B20,'Full BS-USD'!$H:$H) -> 262306.48 | K20: =+SUMIF('Full BS-USD'!$K:$K,B20,'Full BS-USD'!$I:$I) -> -32.19 | L20: =+SUMIF('Full BS-USD'!$K:$K,B20,'Full BS-USD'!$B:$B) -> -261263.83 | O20: =+SUMIF('Full BS-USD'!$K:$K,B20,'Full BS-USD'!$J:$J) -> 33021.42 | P20: =+O20-SUM(E20:L20) -> 0 | Q20: =+ROUND((O20/1000),0) -> 33
B21: 15 | C21: property and equipment | E21: =+SUMIF('Full BS-USD'!$K:$K,B21,'Full BS-USD'!$C:$C) -> 1036.51 | F21: =+SUMIF('Full BS-USD'!$K:$K,B21,'Full BS-USD'!$D:$D) -> 0 | G21: =+SUMIF('Full BS-USD'!$K:$K,B21,'Full BS-USD'!$E:$E) -> 0 | H21: =+SUMIF('Full BS-USD'!$K:$K,B21,'Full BS-USD'!$F:$F) -> 0 | I21: =+SUMIF('Full BS-USD'!$K:$K,B21,'Full BS-USD'!$G:$G) -> 57330.94 | J21: =+SUMIF('Full BS-USD'!$K:$K,B21,'Full BS-USD'!$H:$H) -> 56102.66 | K21: =+SUMIF('Full BS-USD'!$K:$K,B21,'Full BS-USD'!$I:$I) -> 8608.31 | L21: =+SUMIF('Full BS-USD'!$K:$K,B21,'Full BS-USD'!$B:$B) -> 0 | O21: =+SUMIF('Full BS-USD'!$K:$K,B21,'Full BS-USD'!$J:$J) -> 123078.42 | P21: =+O21-SUM(E21:L21) -> 0 | Q21: =+ROUND((O21/1000),0) -> 123 | S21: 5
P22: =+O22-SUM(E22:L22) -> 0
P23: =+O23-SUM(E23:L23) -> 0
C24: Total Long-term assets | E24: =+E20+E21 -> -1334.54 | F24: =+F20+F21 -> 37427.66 | G24: =+G20+G21 -> 0 | H24: =+H20+H21 -> 0 | I24: =+I20+I21 -> 54285.29 | J24: =+J20+J21 -> 318409.14 | K24: =+K20+K21 -> 8576.12 | L24: =+L20+L21 -> -261263.83 | O24: =+O20+O21 -> 156099.84 | P24: =+O24-SUM(E24:L24) -> 0 | Q24: =+ROUND(O24/1000,0) -> 156
P25: =+O25-SUM(E25:L25) -> 0
P26: =+O26-SUM(E26:L26) -> 0
C27: Total assets | E27: =+E24+E16 -> 976029.48 | F27: =+F24+F16 -> 62228.55 | G27: =+G24+G16 -> 513.75 | H27: =+H24+H16 -> 48738.37 | I27: =+I24+I16 -> 3166038.5 | J27: =+J24+J16 -> 24712823 | K27: =+K24+K16 -> 1270980.5 | L27: =+L24+L16 -> -8445444.3 | O27: =+O24+O16 -> 21791907 | P27: =+O27-SUM(E27:L27) -> 0 | Q27: =+Q24+Q16 -> 21792
Q29: =+O29/1000 -> 0
C30: Liabilities and shareholders' equity
C32: Current Liabilities:
B34: 16 | C34: Trade payables | E34: =+SUMIF('Full BS-USD'!$K:$K,B34,'Full BS-USD'!$C:$C) -> 37909.68 | F34: =+SUMIF('Full BS-USD'!$K:$K,B34,'Full BS-USD'!$D:$D) -> 0 | G34: =+SUMIF('Full BS-USD'!$K:$K,B34,'Full BS-USD'!$E:$E) -> 0 | H34: =+SUMIF('Full BS-USD'!$K:$K,B34,'Full BS-USD'!$F:$F) -> 0 | I34: =+SUMIF('Full BS-USD'!$K:$K,B34,'Full BS-USD'!$G:$G) -> 34022.45 | J34: =+SUMIF('Full BS-USD'!$K:$K,B34,'Full BS-USD'!$H:$H) -> 146906.29 | K34: =+SUMIF('Full BS-USD'!$K:$K,B34,'Full BS-USD'!$I:$I) -> 11256.91 | L34: =+SUMIF('Full BS-USD'!$K:$K,B34,'Full BS-USD'!$B:$B) -> -28375.56 | O34: =+SUMIF('Full BS-USD'!$K:$K,B34,'Full BS-USD'!$J:$J) -> 201719.77 | P34: =+O34-SUM(E34:L34) -> 0 | Q34: =+ROUND((O34/1000),0) -> 202
B35: 17 | C35: Accrued expenses and other liabilities | E35: =+SUMIF('Full BS-USD'!$K:$K,B35,'Full BS-USD'!$C:$C) -> 878638.47 | F35: =+SUMIF('Full BS-USD'!$K:$K,B35,'Full BS-USD'!$D:$D) -> 330.61 | G35: =+SUMIF('Full BS-USD'!$K:$K,B35,'Full BS-USD'!$E:$E) -> 330.61 | H35: =+SUMIF('Full BS-USD'!$K:$K,B35,'Full BS-USD'!$F:$F) -> 8607.33 | I35: =+SUMIF('Full BS-USD'!$K:$K,B35,'Full BS-USD'!$G:$G) -> 2789090.5 | J35: =+SUMIF('Full BS-USD'!$K:$K,B35,'Full BS-USD'!$H:$H) -> 4277167 | K35: =+SUMIF('Full BS-USD'!$K:$K,B35,'Full BS-USD'!$I:$I) -> 993737.4 | L35: =+SUMIF('Full BS-USD'!$K:$K,B35,'Full BS-USD'!$B:$B) -> -8155804.9 | O35: =+SUMIF('Full BS-USD'!$K:$K,B35,'Full BS-USD'!$J:$J) -> 792096.95 | P35: =+O35-SUM(E35:L35) -> 1.0477379e-09 | Q35: =+ROUND((O35/1000),0) -> 792 | S35: =+NOTES!B27 -> 6
C37: Total current liabilities | E37: =+E35+E34 -> 916548.15 | F37: =+F35+F34 -> 330.61 | G37: =+G35+G34 -> 330.61 | H37: =+H35+H34 -> 8607.33 | I37: =+I35+I34 -> 2823112.9 | J37: =+J35+J34 -> 4424073.2 | K37: =+K35+K34 -> 1004994.3 | L37: =+L35+L34 -> -8184180.5 | O37: =+O35+O34 -> 993816.72 | P37: =+O37-SUM(E37:L37) -> 0 | Q37: =+Q35+Q34 -> 994
C40: Non current Liabilities:
B42: 18 | C42: Long-Term liabilities: | E42: =+SUMIF('Full BS-USD'!$K:$K,B42,'Full BS-USD'!$C:$C) -> 0 | F42: =+SUMIF('Full BS-USD'!$K:$K,B42,'Full BS-USD'!$D:$D) -> 0 | G42: =+SUMIF('Full BS-USD'!$K:$K,B42,'Full BS-USD'!$E:$E) -> 261263.83 | H42: =+SUMIF('Full BS-USD'!$K:$K,B42,'Full BS-USD'!$F:$F) -> 0 | I42: =+SUMIF('Full BS-USD'!$K:$K,B42,'Full BS-USD'!$G:$G) -> 0 | J42: =+SUMIF('Full BS-USD'!$K:$K,B42,'Full BS-USD'!$H:$H) -> 414497.66 | K42: =+SUMIF('Full BS-USD'!$K:$K,B42,'Full BS-USD'!$I:$I) -> 49.23 | L42: =+SUMIF('Full BS-USD'!$K:$K,B42,'Full BS-USD'!$B:$B) -> -261263.83 | O42: =+SUMIF('Full BS-USD'!$K:$K,B42,'Full BS-USD'!$J:$J) -> 414546.89 | P42: =+O42-SUM(E42:L42) -> 0 | Q42: =+ROUND(O42/1000,0)-1 -> 414
C44: Shareholders equity
B46: 19 | C46: additrional paid in capital | E46: =+SUMIF('Full BS-USD'!$K:$K,B46,'Full BS-USD'!$C:$C) -> 0 | F46: =+SUMIF('Full BS-USD'!$K:$K,B46,'Full BS-USD'!$D:$D) -> 600244.31 | G46: =+SUMIF('Full BS-USD'!$K:$K,B46,'Full BS-USD'!$E:$E) -> 27.32 | H46: =+SUMIF('Full BS-USD'!$K:$K,B46,'Full BS-USD'!$F:$F) -> 1000280.6 | I46: =+SUMIF('Full BS-USD'!$K:$K,B46,'Full BS-USD'!$G:$G) -> 0 | J46: =+SUMIF('Full BS-USD'!$K:$K,B46,'Full BS-USD'!$H:$H) -> 40523528 | K46: =+SUMIF('Full BS-USD'!$K:$K,B46,'Full BS-USD'!$I:$I) -> 1227 | L46: =+SUMIF('Full BS-USD'!$K:$K,B46,'Full BS-USD'!$B:$B) -> 0 | O46: =+SUMIF('Full BS-USD'!$K:$K,B46,'Full BS-USD'!$J:$J) -> 42125308 | P46: =+O46-SUM(E46:L46) -> 0 | Q46: =+ROUND((O46/1000),0)+1 -> 42126
B47: 20 | C47: Recievable on share account | E47: =+SUMIF('Full BS-USD'!$K:$K,B47,'Full BS-USD'!$C:$C) -> 0 | F47: =+SUMIF('Full BS-USD'!$K:$K,B47,'Full BS-USD'!$D:$D) -> 0 | G47: =+SUMIF('Full BS-USD'!$K:$K,B47,'Full BS-USD'!$E:$E) -> 0 | H47: =+SUMIF('Full BS-USD'!$K:$K,B47,'Full BS-USD'!$F:$F) -> 0 | I47: =+SUMIF('Full BS-USD'!$K:$K,B47,'Full BS-USD'!$G:$G) -> 0 | J47: =+SUMIF('Full BS-USD'!$K:$K,B47,'Full BS-USD'!$H:$H) -> 0 | K47: =+SUMIF('Full BS-USD'!$K:$K,B47,'Full BS-USD'!$I:$I) -> 0 | L47: =+SUMIF('Full BS-USD'!$K:$K,B47,'Full BS-USD'!$B:$B) -> 0 | O47: =+SUMIF('Full BS-USD'!$K:$K,B47,'Full BS-USD'!$J:$J) -> 0 | P47: =+O47-SUM(E47:L47) -> 0 | Q47: =+ROUND((O47/1000),0) -> 0
B48: 21 | C48: Accumulated deficit | E48: =+SUMIF('Full BS-USD'!$K:$K,B48,'Full BS-USD'!$C:$C) -> 59481.33 | F48: =+SUMIF('Full BS-USD'!$K:$K,B48,'Full BS-USD'!$D:$D) -> -538346.37 | G48: =+SUMIF('Full BS-USD'!$K:$K,B48,'Full BS-USD'!$E:$E) -> -261108.01 | H48: =+SUMIF('Full BS-USD'!$K:$K,B48,'Full BS-USD'!$F:$F) -> -960149.58 | I48: =+SUMIF('Full BS-USD'!$K:$K,B48,'Full BS-USD'!$G:$G) -> 342925.47 | J48: =+SUMIF('Full BS-USD'!$K:$K,B48,'Full BS-USD'!$H:$H) -> -20649266 | K48: =+SUMIF('Full BS-USD'!$K:$K,B48,'Full BS-USD'!$I:$I) -> 264709.92 | L48: =+SUMIF('Full BS-USD'!$K:$K,B48,'Full BS-USD'!$B:$B) -> 0 | O48: =+SUMIF('Full BS-USD'!$K:$K,B48,'Full BS-USD'!$J:$J) -> -21741753 | P48: =+O48-SUM(E48:L48) -> 0 | Q48: =+ROUND((O48/1000),0) -> -21742
C50: Total shareholders equity | E50: =+SUM(E46:E48) -> 59481.33 | F50: =+SUM(F46:F48) -> 61897.94 | G50: =+SUM(G46:G48) -> -261080.69 | H50: =+SUM(H46:H48) -> 40131.04 | I50: =+SUM(I46:I48) -> 342925.47 | J50: =+SUM(J46:J48) -> 19874263 | K50: =+SUM(K46:K48) -> 265936.92 | L50: =+SUM(L46:L48) -> 0 | O50: =+SUM(O46:O48) -> 20383555 | Q50: =+SUM(Q46:Q48) -> 20384
C52: Total liabilities and shareholders' equity | E52: =+E50+E42+E37 -> 976029.48 | F52: =+F50+F42+F37 -> 62228.55 | G52: =+G50+G42+G37 -> 513.75 | H52: =+H50+H42+H37 -> 48738.37 | I52: =+I50+I42+I37 -> 3166038.4 | J52: =+J50+J42+J37 -> 24712834 | K52: =+K50+K42+K37 -> 1270980.5 | L52: =+L50+L42+L37 -> -8445444.3 | O52: =+O50+O42+O37 -> 21791918 | Q52: =+Q50+Q42+Q37 -> 21792
C54: check | E54: =+E52-E27 -> 0 | F54: =+F52-F27 -> 5.8207661e-11 | G54: =+G52-G27 -> -4.422418e-11 | H54: =+H52-H27 -> -8.0035534e-11 | I54: =+I52-I27 -> -0.079999999 | J54: =+J52-J27 -> 11.16 | K54: =+K52-K27 -> 0 | L54: =+L52-L27 -> 0 | O54: =+O52-O27 -> 11.08 | Q54: =+Q52-Q27 -> 0

Sheet P&L
C1: Wematch.live
C2: USD
B5: INDEX | E5: WUS- INC | F5: EQD | G5: WIR | H5: WSF- LTD [IL] | I5: WSF LTD | J5: R&D | K5: WTSE | M5: Total
E6: 2022 | F6: 2022 | G6: 2022 | H6: 2022 | I6: 2022 | J6: 2022 | K6: 2022 | M6: 2022 | O6: in 000' | Q6: NOTE
B8: 1 | C8: Revenues | E8: =+SUMIF('Full P&L-USD'!$J:$J,B8,'Full P&L-USD'!$B:$B) -> 0 | F8: =+SUMIF('Full P&L-USD'!$J:$J,B8,'Full P&L-USD'!$C:$C) -> 0 | G8: =+SUMIF('Full P&L-USD'!$J:$J,B8,'Full P&L-USD'!$D:$D) -> 0 | H8: =+SUMIF('Full P&L-USD'!$J:$J,B8,'Full P&L-USD'!$E:$E) -> 0 | I8: =+SUMIF('Full P&L-USD'!$J:$J,B8,'Full P&L-USD'!$F:$F) -> 0 | J8: =+SUMIF('Full P&L-USD'!$J:$J,B8,'Full P&L-USD'!$G:$G) -> 6849954.6 | K8: =+SUMIF('Full P&L-USD'!$J:$J,B8,'Full P&L-USD'!$H:$H) -> 0 | M8: =+SUMIF('Full P&L-USD'!$J:$J,B8,'Full P&L-USD'!$I:$I) -> 6849954.6 | N8: =+M8-SUM(E8:K8) -> 0 | O8: =+ROUND(M8/1000,0) -> 6850 | Q8: =+NOTES!B50 -> 9
N9: =+M9-SUM(E9:K9) -> 0
B10: 2 | C10: Cost of Revenues | E10: =+SUMIF('Full P&L-USD'!$J:$J,B10,'Full P&L-USD'!$B:$B) -> 0 | F10: =+SUMIF('Full P&L-USD'!$J:$J,B10,'Full P&L-USD'!$C:$C) -> 0 | G10: =+SUMIF('Full P&L-USD'!$J:$J,B10,'Full P&L-USD'!$D:$D) -> 0 | H10: =+SUMIF('Full P&L-USD'!$J:$J,B10,'Full P&L-USD'!$E:$E) -> 0 | I10: =+SUMIF('Full P&L-USD'!$J:$J,B10,'Full P&L-USD'!$F:$F) -> -69088.03 | J10: =+SUMIF('Full P&L-USD'!$J:$J,B10,'Full P&L-USD'!$G:$G) -> -1758857 | K10: =+SUMIF('Full P&L-USD'!$J:$J,B10,'Full P&L-USD'!$H:$H) -> -313932.24 | M10: =+SUMIF('Full P&L-USD'!$J:$J,B10,'Full P&L-USD'!$I:$I) -> -2141877.3 | N10: =+M10-SUM(E10:K10) -> 0 | O10: =+ROUND(M10/1000,0) -> -2142 | Q10: =+NOTES!B59 -> 10
N11: =+M11-SUM(E11:K11) -> 0
B12: 3 | C12: Gross profit | E12: =+E8+E10 -> 0 | F12: =+F8+F10 -> 0 | G12: =+G8+G10 -> 0 | H12: =+H8+H10 -> 0 | I12: =+I8+I10 -> -69088.03 | J12: =+J8+J10 -> 5091097.6 | K12: =+K8+K10 -> -313932.24 | M12: =+M8+M10 -> 4708077.3 | N12: =+M12-SUM(E12:K12) -> 0 | O12: =+O8+O10 -> 4708
N13: =+M13-SUM(E13:K13) -> 0
C14: Operating expenses: | N14: =+M14-SUM(E14:K14) -> 0
A15: Total - R&D | B15: 4.1 | C15: R&D | E15: =+SUMIF('Full P&L-USD'!$J:$J,B15,'Full P&L-USD'!$B:$B) -> 96722.92 | F15: =+SUMIF('Full P&L-USD'!$J:$J,B15,'Full P&L-USD'!$C:$C) -> 0 | G15: =+SUMIF('Full P&L-USD'!$J:$J,B15,'Full P&L-USD'!$D:$D) -> 0 | H15: =+SUMIF('Full P&L-USD'!$J:$J,B15,'Full P&L-USD'!$E:$E) -> 0 | I15: =+SUMIF('Full P&L-USD'!$J:$J,B15,'Full P&L-USD'!$F:$F) -> 915306.08 | J15: =+SUMIF('Full P&L-USD'!$J:$J,B15,'Full P&L-USD'!$G:$G) -> 2942658.1 | K15: =+SUMIF('Full P&L-USD'!$J:$J,B15,'Full P&L-USD'!$H:$H) -> 482346.81 | M15: =+VLOOKUP(A15,'Full P&L-USD'!$A:$I,9,0)+'Full P&L-USD'!I126 -> 4437033.9 | N15: =+M15-SUM(E15:K15) -> 0 | O15: =+ROUND(M15/1000,0) -> 4437
A16: Total - S&M | B16: 4.2 | C16: S&M | E16: =+SUMIF('Full P&L-USD'!$J:$J,B16,'Full P&L-USD'!$B:$B) -> 424507.61 | F16: =+SUMIF('Full P&L-USD'!$J:$J,B16,'Full P&L-USD'!$C:$C) -> 0 | G16: =+SUMIF('Full P&L-USD'!$J:$J,B16,'Full P&L-USD'!$D:$D) -> 0 | H16: =+SUMIF('Full P&L-USD'!$J:$J,B16,'Full P&L-USD'!$E:$E) -> 0 | I16: =+SUMIF('Full P&L-USD'!$J:$J,B16,'Full P&L-USD'!$F:$F) -> 2211092 | J16: =+SUMIF('Full P&L-USD'!$J:$J,B16,'Full P&L-USD'!$G:$G) -> 2086267.7 | K16: =+SUMIF('Full P&L-USD'!$J:$J,B16,'Full P&L-USD'!$H:$H) -> 113052.5 | M16: =+VLOOKUP(A16,'Full P&L-USD'!$A:$I,9,0) -> 4834919.8 | N16: =+M16-SUM(E16:K16) -> 0 | O16: =+ROUND(M16/1000,0) -> 4835
A17: Total - G&A | B17: 4.3 | C17: G&A | E17: =+SUMIF('Full P&L-USD'!$J:$J,B17,'Full P&L-USD'!$B:$B) -> 334345.02 | F17: =+SUMIF('Full P&L-USD'!$J:$J,B17,'Full P&L-USD'!$C:$C) -> 353.51 | G17: =+SUMIF('Full P&L-USD'!$J:$J,B17,'Full P&L-USD'!$D:$D) -> 353.51 | H17: =+SUMIF('Full P&L-USD'!$J:$J,B17,'Full P&L-USD'!$E:$E) -> 353.51 | I17: =+SUMIF('Full P&L-USD'!$J:$J,B17,'Full P&L-USD'!$F:$F) -> 722121.38 | J17: =+SUMIF('Full P&L-USD'!$J:$J,B17,'Full P&L-USD'!$G:$G) -> 1893021.2 | K17: =+SUMIF('Full P&L-USD'!$J:$J,B17,'Full P&L-USD'!$H:$H) -> 67638.42 | M17: =+VLOOKUP(A17,'Full P&L-USD'!$A:$I,9,0) -> 3018181.2 | N17: =+M17-SUM(E17:K17)+'Full P&L-USD'!I798 -> -5.587939e-10 | O17: =+ROUND(M17/1000,0) -> 3018
N18: =+M18-SUM(E18:K18) -> 0
A19: Total Operation Expense | B19: 4 | C19: Total Operatiing Expense | E19: =+SUM(E15:E17) -> 855575.55 | F19: =+SUM(F15:F17) -> 353.51 | G19: =+SUM(G15:G17) -> 353.51 | H19: =+SUM(H15:H17) -> 353.51 | I19: =+SUM(I15:I17) -> 3848519.5 | J19: =+SUM(J15:J17) -> 6921947 | K19: =+SUM(K15:K17) -> 663037.73 | M19: =+VLOOKUP(A19,'Full P&L-USD'!$A:$I,9,0) -> 12290140 | N19: =+M19-SUM(E19:K19) -> 0 | O19: =+SUM(O15:O17) -> 12290
N20: =+M20-SUM(E20:K20) -> 0
C21: Operating Loss | E21: =+E12-E19 -> -855575.55 | F21: =+F12-F19 -> -353.51 | G21: =+G12-G19 -> -353.51 | H21: =+H12-H19 -> -353.51 | I21: =+I12-I19 -> -3917607.5 | J21: =+J12-J19 -> -1830849.4 | K21: =+K12-K19 -> -976969.97 | M21: =+M12-M19 -> -7582063 | O21: =+O12-O19 -> -7582
B23: 5 | C23: Earning/(Loss) Before Interest & Tax | E23: =+E12-E19 -> -855575.55 | F23: =+F12-F19 -> -353.51 | G23: =+G12-G19 -> -353.51 | H23: =+H12-H19 -> -353.51 | I23: =+I12-I19 -> -3917607.5 | J23: =+J12-J19 -> -1830849.4 | K23: =+K12-K19 -> -976969.97 | M23: =+M12-M19 -> -7582063 | N23: =+M23-SUM(E23:K23) -> 0 | O23: =+O12-O19 -> -7582
N24: =+M24-SUM(E24:K24) -> 0
B25: 6 | C25: Financial expenses, net | E25: =+SUMIF('Full P&L-USD'!$J:$J,B25,'Full P&L-USD'!$B:$B) -> 186.03 | F25: =+SUMIF('Full P&L-USD'!$J:$J,B25,'Full P&L-USD'!$C:$C) -> -51.51 | G25: =+SUMIF('Full P&L-USD'!$J:$J,B25,'Full P&L-USD'!$D:$D) -> -111.66 | H25: =+SUMIF('Full P&L-USD'!$J:$J,B25,'Full P&L-USD'!$E:$E) -> 221.48 | I25: =+SUMIF('Full P&L-USD'!$J:$J,B25,'Full P&L-USD'!$F:$F) -> -99081.95 | J25: =+SUMIF('Full P&L-USD'!$J:$J,B25,'Full P&L-USD'!$G:$G) -> 323867.05 | K25: =+SUMIF('Full P&L-USD'!$J:$J,B25,'Full P&L-USD'!$H:$H) -> -21418.02 | M25: =+SUMIF('Full P&L-USD'!$J:$J,B25,'Full P&L-USD'!$I:$I) -> 203611.42 | N25: =+M25-SUM(E25:K25) -> 0 | O25: =+ROUND(M25/1000,0) -> 204 | Q25: =+NOTES!B67 -> 11
N26: =+M26-SUM(E26:K26) -> 0
B27: 7 | C27: Loss Before Taxes On Income | E27: =+E25+E23 -> -855389.52 | F27: =+F25+F23 -> -405.02 | G27: =+G25+G23 -> -465.17 | H27: =+H25+H23 -> -132.03 | I27: =+I25+I23 -> -4016689.4 | J27: =+J25+J23 -> -1506982.4 | K27: =+K25+K23 -> -998387.99 | M27: =+M25+M23 -> -7378451.5 | N27: =+M27-SUM(E27:K27) -> 0 | O27: =+O25+O23 -> -7378
N28: =+M28-SUM(E28:K28) -> 0
B29: 8 | C29: Tax on Income | E29: =+SUMIF('Full P&L-USD'!$J:$J,B29,'Full P&L-USD'!$B:$B) -> -15762.04 | F29: =+SUMIF('Full P&L-USD'!$J:$J,B29,'Full P&L-USD'!$C:$C) -> 0 | G29: =+SUMIF('Full P&L-USD'!$J:$J,B29,'Full P&L-USD'!$D:$D) -> 0 | H29: =+SUMIF('Full P&L-USD'!$J:$J,B29,'Full P&L-USD'!$E:$E) -> 0 | I29: =+SUMIF('Full P&L-USD'!$J:$J,B29,'Full P&L-USD'!$F:$F) -> -63044.47 | J29: =+SUMIF('Full P&L-USD'!$J:$J,B29,'Full P&L-USD'!$G:$G) -> 0 | K29: =+SUMIF('Full P&L-USD'!$J:$J,B29,'Full P&L-USD'!$H:$H) -> 65201.39 | M29: =+SUMIF('Full P&L-USD'!$J:$J,B29,'Full P&L-USD'!$I:$I) -> -13605.12 | N29: =+M29-SUM(E29:K29) -> 0 | O29: =+ROUND(M29/1000,0) -> -14
N30: =+M30-SUM(E30:K30) -> 0
C31: Net Loss | E31: =+E27+E29 -> -871151.56 | F31: =+F27+F29 -> -405.02 | G31: =+G27+G29 -> -465.17 | H31: =+H27+H29 -> -132.03 | I31: =+I27+I29 -> -4079733.9 | J31: =+J27+J29 -> -1506982.4 | K31: =+K27+K29 -> -933186.6 | M31: =+M27+M29 -> -7392056.7 | N31: =+M31-SUM(E31:K31) -> 0 | O31: =+O27+O29 -> -7392

Sheet CF
A4: Cash flows from operating activities:
C5: As of December 31, 2022
C7: US thousand
A9: Net loss | C9: =-E96 -> -7392
A11: Adjustments to reconcile net loss to net cash provided by operating activities:
A14: Depreciation and amortization and impermanent | C14: =-E83 -> 29.55433
A15: Share-based compensation expense | C15: =-E93 -> 258.137
A16: Change in employee long term loans | C16: =-E82 -> 4.428
A17: Change in long time employee benefit | C17: =-E89 -> 20.77
A19: Change in SAFE fair value | C19: =-E88 -> 0
A21: Changes in operating assets and liabilities:
A22: Accounts receivable | C22: =-E80 -> -1020.612
A23: Prepaid expenses and other assets | C23: =-E81 -> -523.098
A24: Accounts payable | C24: =-E84 -> 70
A25: Accrued expenses and other liabilities | C25: =-E85 -> 27.617
A26: Change in Deferred revenue | C26: =-E86 -> 0.001
A28: Net cash provided by operating activities | C28: =SUM(C9:C27) -> -8525.2027
A30: Cash flows from investing activities:
A32: Change in short term restricted deposit | C32: =-F79-284 -> -11415.935
A33: Purchases of property and equipment | C33: =-F83 -> -92.416
A35: Net cash used in investing activities | C35: =-F97 -> -11224.351
A37: Cash flows from financing activities:
A39: Proceeds from issuance of Sample agreement for future equity ("SAFE") | C39: 0
A40: Proceeds from opsions excersize | C40: =-G91 -> 7
A41: Issuance of Preferred B shares, net of issuance cost
A42: Proceeds from issuance of convertible preferred shares, net of issuance costs
A44: Net cash provided by financing activities | C44: =+C42+C41+C39+C40 -> 7
A46: Net increase (decrease) in cash, cash equivalents, and restricted cash | C46: =+C44+C28+C35 -> -19742.554
A47: Cash, cash equivalents, and restricted cash—beginning of period | C47: =+D78 -> 27403
A49: Cash, cash equivalents, and restricted cash—end of period | C49: =+C46+C47 -> 7660.4463 | D49: =+J78 -> 7660 | E49: =+C49-D49 -> 0.44633
E55: אם הפקדונות משמשים לפעילות השוטפת או נזילים תוך פחות מ-3 חודשים הם מסווגים כמזומן ושווי מזומן
E56: .
F71: Working peper for cash flow
D75: Closing balance as | E75: Cash flow from | F75: Cash flow from | G75: Cash flow from | J75: Closing balance as
D76: 44561 | E76: Opeartion | F76: Investing | G76: Financing | H76: Non-cash activites | I76: Change in cash | J76: 44926 | L76: Check
B78: 10 | C78: Cash and cash equivalents | D78: =27403 -> 27403 | I78: =J78-D78-E78 -> -19743 | J78: =+'BS USD'!Q11 -> 7660 | K78: =+J78-'BS USD'!$Q11 -> 0 | L78: =SUM(D78:I78)-J78 -> 0
B79: 11 | C79: Restricted Bank Deposit | D79: 31.065 | F79: =J79-D79 -> 11131.935 | J79: =+'BS USD'!Q12 -> 11163 | K79: =+J79-'BS USD'!$Q12 -> 0 | L79: =SUM(D79:I79)-J79 -> 0
B80: 12 | C80: Account Receivable | D80: 1016.388 | E80: =J80-D80 -> 1020.612 | J80: =+'BS USD'!Q13 -> 2037 | K80: =+J80-'BS USD'!$Q13 -> 0 | L80: =SUM(D80:I80)-J80 -> 0
B81: 13 | C81: Prepaid expenses and other current assets | D81: 252.902 | E81: =J81-D81 -> 523.098 | J81: =+'BS USD'!Q14 -> 776 | K81: =+J81-'BS USD'!$Q14 -> 0 | L81: =SUM(D81:I81)-J81 -> 0
B82: 14 | C82: Other long term accounts receivables | D82: 37.428 | E82: =J82-D82 -> -4.428 | J82: =+'BS USD'!Q20 -> 33 | K82: =+J82-'BS USD'!$Q20 -> 0 | L82: =SUM(D82:I82)-J82 -> 0
B83: 15 | C83: Property & Equipment, Net | D83: 60.216 | E83: =-(26238+1110.97+2205.36)/1000 -> -29.55433 | F83: =(68134+17016+7266)/1000 -> 92.416 | J83: =+'BS USD'!Q21 -> 123 | K83: =+J83-'BS USD'!$Q21 -> 0 | L83: =SUM(D83:I83)-J83 -> 0.07767
A84: Total Credit Card- add manualy | B84: 16 | C84: Account Payable | D84: -132 | E84: =J84-D84 -> -70 | J84: =-'BS USD'!Q34 -> -202 | K84: =+J84+'BS USD'!$Q34 -> 0 | L84: =SUM(D84:I84)-J84 -> 0
B85: 17 | C85: Accrued expenses and other current liabilities | D85: -764.383 | E85: =J85-D85 -> -27.617 | J85: =-'BS USD'!Q35 -> -792 | K85: =+J85+'BS USD'!$Q35 -> 0 | L85: =SUM(D85:I85)-J85 -> 0
B86: 17.4 | C86: Deferred Revenues | D86: 0.001 | E86: =J86-D86 -> -0.001 | L86: =SUM(D86:I86)-J86 -> 0
C87: Warrants | D87: 0 | E87: =J87-D87 -> 0 | J87: =+ROUND(SUMIF('BS USD'!$B$7:$B$54,B87,'BS USD'!$Q$7:$Q$54),0) -> 0 | L87: =SUM(D87:I87)-J87 -> 0
C88: Safe agreement | D88: 0 | E88: =J88-D88 -> 0 | J88: =+ROUND(SUMIF('BS USD'!$B$7:$B$54,B88,'BS USD'!$Q$7:$Q$54),0) -> 0 | L88: =SUM(D88:I88)-J88 -> 0
B89: 18 | C89: Provision for post employment benefits | D89: -393.23 | E89: =J89-D89 -> -20.77 | J89: =-'BS USD'!Q42 -> -414 | K89: =+J89+'BS USD'!Q42 -> 0 | L89: =SUM(D89:I89)-J89 -> 0
C90: Ordinary shares | D90: 0 | J90: =+ROUND(SUMIF('BS USD'!$B$7:$B$54,B90,'BS USD'!$Q$7:$Q$54),0) -> 0 | K90: Capital and Reserves | L90: =SUM(D90:I90)-J90 -> 0
C91: Option exercise by employees | D91: 0 | G91: -7 | J91: =+G91-D91 -> -7 | L91: =SUM(D91:I91)-J91 -> 0
B92: 19.1 | C92: Preferred shares | D92: -31125 | G92: =+J92-D92 -> 0.294 | J92: =-ROUND(SUMIF('Full BS-USD'!K:K,B92,'Full BS-USD'!J:J),0)/1000 -> -31124.706 | L92: =SUM(D92:I92)-J92 -> 0
B93: 19.2 | C93: Additional paid in capital-Share based compensation | D93: -1397 | E93: =J93-D93-1 -> -258.137 | J93: =-ROUND(SUMIF('Full BS-USD'!K:K,B93,'Full BS-USD'!J:J),0)/1000 -> -1654.137 | L93: =SUM(D93:I93)-J93 -> -1 | M93: 31005
B94: 19.3 | C94: Additional paid in capital | D94: -9339 | J94: =-ROUND(SUMIF('Full BS-USD'!K:K,B94,'Full BS-USD'!J:J),0)/1000+7 -> -9339.464
C95: Retained Earnings | D95: =11079+3271 -> 14350 | J95: =-ROUND(SUMIF('Full BS-USD'!A:A,C95,'Full BS-USD'!J:J),0)/1000 -> 14349.72
C96: Current year Profit (loss) | E96: =+J96 -> 7392 | J96: =-'P&L'!O31 -> 7392 | L96: =SUM(D96:I96)-J96 -> 0
E97: =SUM(E78:E96) -> 8525.2027 | F97: =SUM(F77:F96) -> 11224.351 | G97: =SUM(G77:G96) -> -6.706 | I97: =SUM(I78:I96) -> -19743 | J97: =SUM(J78:J96) -> 0.413 | L97: =SUM(D97:I97)-J97 -> -0.56533
C98: Check | D98: =SUM(D78:D97) -> 0.387 | L98: =SUM(D98:I98)-J98 -> 0.387
E99: =+E97+C28 -> 0
J101: =9339+J94 -> -0.464

Sheet Change in Equity
D3: Ordinary shares | H3: Preferred Shares | L3: Additional | N3: Receivable on | P3: Accumulated | R3: Total shareholders' equity
L4: paid-in
D5: Number | F5: Amount | H5: Number | J5: Amount | L5: capital | N5: Shares account | P5: deficit | R5: (deficit)
B7: Balance as of January 1, 2021 | D7: 1401739 | F7: 4 | H7: 198028 | J7: (*) | L7: 12952 | N7: -50 | P7: -10806 | R7: =+P7+F7+L7+N7 -> 2100
B9: Net loss and other comprehensive loss | D9: 0 | F9: 0 | H9: 0 | J9: 0 | L9: 0 | N9: 0 | P9: -3272 | R9: =+P9+F9+L9+J9 -> -3272
B10: Receivable of shares | N10: 50 | R10: =+P10+F10+L10+J10+N10 -> 50
B11: Share based compensation | D11: 0 | F11: 0 | H11: 0 | J11: 0 | L11: 565 | N11: 0 | P11: 0 | R11: =+P11+F11+L11+J11 -> 565
B12: Warrant exercise | H12: 315996 | J12: 1 | L12: 3124 | R12: =+P12+F12+L12+J12 -> 3125
B13: SAFE exercise | D13: 0 | F13: 0 | H13: 105500 | J13: 1 | L13: =[1]CF!D35+[1]CF!D15-1 -> -1 | N13: - | P13: 0 | R13: =+P13+F13+L13+J13 -> 0
B14: Issuance of preferred B Shares, net of issuance cost | D14: 0 | F14: 0 | H14: =570204+293045 -> 863249 | J14: 3 | L14: 24940 | P14: 0 | R14: =+P14+J14+L14+N14 -> 24943
B16: Balance as of December 31, 2021 | D16: =SUM(D7:D15) -> 1401739 | F16: =SUM(F7:F15) -> 4 | H16: =SUM(H7:H15) -> 1482773 | J16: =SUM(J7:J15) -> 5 | L16: =SUM(L7:L15) -> 41580 | N16: =SUM(N7:N15) -> 0 | P16: =SUM(P7:P15) -> -14078 | R16: =+P16+F16+L16+N16+J16 -> 27511
B18: Net loss and other comprehensive loss | D18: 0 | F18: 0 | H18: 0 | J18: 0 | L18: 0 | N18: 0 | P18: =+'P&L'!O31 -> -7392 | R18: =SUM(J18:P18,F18) -> -7392
B19: recievable on account of shares | D19: 800 | R19: =SUM(J19:P19,F19) -> 0
B20: Share based compensation | D20: =584+1216 -> 1800 | L20: =-CF!E93+7 -> 265.137 | R20: =SUM(J20:P20,F20) -> 265.137
B21: SAFE exercise | R21: =SUM(J21:P21,F21) -> 0
B22: Warrant exercise | H22: 127247 | J22: (*) | R22: =SUM(J22:P22,F22) -> 0
B23: Issuance of preferred A Shares, net of issuance cost
B24: Issuance of ordinary stocks, net of issuance cost | F24: 0 | P24: 0 | R24: =SUM(J24:P24,F24) -> 0
B26: Balance as of December 31, 2022 | D26: =SUM(D16:D24) -> 1404339 | F26: =SUM(F16:F24) -> 4 | H26: =SUM(H16:H24) -> 1610020 | J26: =SUM(J16:J24) -> 5 | L26: =SUM(L16:L24) -> 41845.137 | N26: =SUM(N16:N24) -> 0 | P26: =SUM(P16:P24) -> -21470 | R26: =+R16+R18+R20 -> 20384.137
D28: =+D16+D19+D20-D26 -> 0 | H28: =+H16+H22-H26 -> 0 | L28: =+L16+L20-L26 -> 0 | P28: =+P16+P18-P26 -> 0 | Q28: =+Q16+Q18-Q26 -> 0
R29: =+'BS USD'!Q50-R26 -> -0.137

Sheet JE'S
B5: 1 | D5: AR-DR Offset | G5: JEIL-01719
C9: D | D9: 12002 AR OFFSET | E9: 47763.9
C10: C | D10: 26002 DR OFFSET | E10: 47763.9
B14: 2 | D14: NS Open balance correction | G14: JE10500 | H14: =+'AP correction OB'!H2 -> A
F16: USD | G16: ILS
C17: D | D17: WEQD - 10010 Bank BIA | F17: 14237.25 | G17: =+F17/0.32154341 -> 44277.847 | I17: Max corrected the open balance
C18: C | D18: Retained Earnings | F18: =+F17 -> 14237.25 | G18: =+F18/0.32154341 -> 44277.847
D21: JE10500 | E21: reversal--> | G21: JEIL-03302
F22: USD | G22: ILS
C23: D | D23: Retained Earnings | F23: =+F24+F25 -> 2750.4 | G23: =+F23/0.32154341 -> 8553.744
C24: C | D24: AP Z Hotel | F24: 652.27 | G24: =+F24/0.32154341 -> 2028.5597
C25: C | D25: AP Vissensa Ltd | F25: 2098.13 | G25: =+F25/0.32154341 -> 6525.1843
F28: USD | G28: ILS | H28: JEIL-03349
C29: D | D29: I digital | G29: 2855 | I29: Open balance correction | L29: FX rate | M29: 0.26342132
C30: C | D30: 67301 | G30: =+G29 -> 2855
B35: 3 | D35: Rent pad upfront- wework | G35: JEIL-03339
G36: ILS
C37: D | D37: 67101 Rent | G37: 53520
C38: C | D38: 20001 AP | G38: =+G37 -> 53520

Sheet NOTES
D3: Balance Sheet Notes
B5: 3 | D5: Trade recievables | E5: =+SUMIF('Full BS-USD'!$K$9:$K$201,F5,'Full BS-USD'!$J$9:$J$201)/1000-1 -> 1582.7382 | F5: 12.1
D6: Unbilled revenue | E6: =SUMIF('Full BS-USD'!$K$9:$K$201,F6,'Full BS-USD'!$J$9:$J$201)/1000-E5-2 -> 453.17373 | F6: 12
E7: =SUM(E5:E6) -> 2035.9119
E8: =+E7-'BS USD'!Q13 -> -1.08809
B10: 4 | D10: Prepaid expenses | E10: =+SUMIF('Full BS-USD'!$K$9:$K$201,F10,'Full BS-USD'!$J$9:$J$201)/1000 -> 404.47206 | F10: 13.1
D11: Government institutions | E11: =+SUMIF('Full BS-USD'!$K$9:$K$201,F11,'Full BS-USD'!$J$9:$J$201)/1000 -> 197.99699 | F11: 13.2
D12: Other current assts | E12: =SUMIF('Full BS-USD'!$K$9:$K$201,F12,'Full BS-USD'!$J$9:$J$201)/1000-E11-E10-'Full BS-USD'!J143/1000 -> 173.50492 | F12: 13
E13: =SUM(E10:E12) -> 775.97397
E14: =+E13-'BS USD'!Q14 -> -0.02603
B15: 5 | D15: Cost:
D16: Computers & Software | E16: =+SUMIF('Full BS-USD'!$K$9:$K$201,F16,'Full BS-USD'!$J$9:$J$201)/1000 -> 197.37263 | F16: 15.1
D17: Office furniture | E17: =+SUMIF('Full BS-USD'!$K$9:$K$201,F17,'Full BS-USD'!$J$9:$J$201)/1000 -> 18.92198 | F17: 15.2
D18: Leasehold improvements | E18: =SUMIF('Full BS-USD'!$K$9:$K$201,F18,'Full BS-USD'!$J$9:$J$201)/1000 -> 2.65233 | F18: 15.3
E19: =SUM(E16:E18) -> 218.94694
D21: Accumulated depritiation | E21: =SUMIF('Full BS-USD'!$K$9:$K$201,F21,'Full BS-USD'!$J$9:$J$201)/1000 -> -95.86852 | F21: 15.4
D23: Preperty and equipment, net | E23: =+E19+E21 -> 123.07842
E24: =+E23-'BS USD'!Q21 -> 0.07842
B27: 6 | D27: Accrued employee compensation and benefits | E27: =+SUMIF('Full BS-USD'!$K$9:$K$201,F27,'Full BS-USD'!$J$9:$J$201)/1000 -> 542.77519 | F27: 17.1
D28: Accrued expenses | E28: =+SUMIF('Full BS-USD'!$K$9:$K$201,F28,'Full BS-USD'!$J$9:$J$201)/1000 -> 136.42016 | F28: 17.2
D29: Income and indirect tax payable | E29: =+SUMIF('Full BS-USD'!$K$9:$K$201,F29,'Full BS-USD'!$J$9:$J$201)/1000-E28-E27 -> 112.9016 | F29: 17 | G29: includes DR
E30: =SUM(E27:E29) -> 792.09695
E31: =+E30-'BS USD'!Q35 -> 0.09695
B33: 8 | D33: Share capital: | O33: Shareholders' equity
O35: 2022
E36: Authorized | F36: issued and outstanding | J36: Authorized | K36: issued and outstanding | O36: number of options | P36: weightes average excersise price
E37: December 31,2022 | J37: December 31,2021 | N37: Balance as of December 31,2021
D38: ordinary shares | E38: 3074000 | F38: 1223458 | J38: 3074000 | K38: 1220858 | N38: Granted
D39: ordinary A Shares | E39: 205000 | F39: 180881 | J39: 205000 | K39: 180881 | N39: Balance as of December 31,2022
D40: Preferred A shares (*) | E40: 651000 | F40: 641271 | J40: 651000 | K40: 514024 | N40: Excercisable as of December 31,2021
D41: preferred B shares (*) | E41: 1070000 | F41: 967678 | G41: =+K41 -> 968749 | H41: =+F41-G41 -> -1071 | J41: 1070000 | K41: 968749
E42: =SUM(E38:E41) -> 5000000 | F42: =SUM(F38:F41) -> 3013288 | J42: =SUM(J38:J41) -> 5000000 | K42: =SUM(K38:K41) -> 2884512
K45: The information is taken from Carta- "Summery Cap Table" report
D48: P&L Notes
B50: 9
D51: Subscription fees | E51: 5884 | F51: From rev File
D52: Variable Fees | E52: =965+97 -> 1062 | F52: From rev File
E53: =SUM(E51:E52) -> 6946
E54: =+'P&L'!O8 -> 6850 | F54: NS
E55: =+E53-E54 -> 96 | F55: DIFF
B59: 10 | D59: Revenues shared with third parties | E59: =-SUMIF('Full P&L-USD'!$J$8:$J$808,F59,'Full P&L-USD'!$I$8:$I$808)/1000+1 -> 903.61397 | F59: 2.1
D60: Other cost of sales | E60: =-SUMIF('Full P&L-USD'!$J$8:$J$808,F60,'Full P&L-USD'!$I$8:$I$808)/1000+1 -> 1238.8133 | F60: 2.2
E61: =SUM(E59:E60) -> 2142.4273
E62: =+E61+'P&L'!O10 -> 0.42726
B67: 11 | D67: Bank fees | E67: =+SUMIF('Full P&L-USD'!$J$8:$J$826,F67,'Full P&L-USD'!$I$8:$I$826)/1000 -> 65.4715 | F67: 6.1
D68: Revaluation expenses | E68: =+SUMIF('Full P&L-USD'!$J$8:$J$826,F68,'Full P&L-USD'!$I$8:$I$826)/1000 -> 48.15405 | F68: 6.2
D69: Exchange difference | E69: =+SUMIF('Full P&L-USD'!$J$8:$J$826,F69,'Full P&L-USD'!$I$8:$I$826)/1000 -> 0 | F69: 6.3
D70: Interest income | E70: =-SUMIF('Full P&L-USD'!$J$8:$J$808,F70,'Full P&L-USD'!$I$8:$I$808)/1000 -> -317.23697 | F70: 6.4
E71: =SUM(E67:E70) -> -203.61142
E72: =+E71+'P&L'!O25 -> 0.38858

Sheet Options -Outstanding Awards
B5: Number of Awards | C5: Weighted Average Exercise Price | D5: Weighted Average Share Price on Date of Exercise | E5: Weighted Average Remaining Contractual Life | F5: Aggregate Intrinsic Value
A6: Outstanding, beginning of period | B6: 146702 | C6: 8.431322 | F6: 3604274.2
A7: Granted | B7: 23750 | C7: 21.18
A8: Exercised/Released | B8: -2600 | C8: 4.3474829 | D8: 4.3474829
A9: Cancelled/Forfeited | B9: -5752 | C9: 13.90386
A10: Expired | B10: -765 | C10: 12.5
A11: Outstanding, End of period | B11: 161335 | C11: 10.159456 | E11: 7.7855858 | F11: 3684979.2
A12: Exercisable, End of period | B12: 89352 | C12: 4.9935285 | E12: 6.9678835 | F12: 2502434.2
B18: 2022
B19: Number of options | C19: Weightes average exercise price | E19: *
A20: Balance as of December 31,2021 | B20: 105702 | C20: 5.47 | E20: =+B20/B22 -> 0.81653431 | F20: =+C20*E20 -> 4.4664427 | L20: From Carta
A21: Granted | B21: =+B7 -> 23750 | C21: =+C7 -> 21.18 | E21: =+B21/B22 -> 0.18346569 | F21: =+E21*C21 -> 3.8858032 | L21: Wematch.live R&D LTD Options Exercised & RSUs Settled
A22: Balance as of December 31,2022 | B22: =+B21+B20 -> 129452 | C22: 8.35 | D22: * | F22: =+F21+F20 -> 8.3522459 | L22: As of 12/31/2022 • Generated by Hila Eliasi (hila.eliasi@wematch.live) at 08/10/2023 06:10:37
A23: Excercisable as of December 31,2022 | B23: =+B12 -> 89352 | C23: =+C12 -> 4.9935285
L24: ID | M24: Optionholder | N24: Employee ID | O24: Shares Exercised | P24: Grant Date | Q24: Exercise Request Date | R24: Off System Transaction | S24: Exercise Price | T24: Total Exercise Price
L25: ES-1008 | M25: Rudy Perez | O25: 1216 | P25: 43586 | Q25: 44650 | S25: 0.002783 | T25: =O25*S25 -> 3.384128
L26: ES-1019 | M26: Eitan Katz | O26: 800 | P26: 43952 | Q26: 44921 | S26: 5 | T26: =O26*S26 -> 4000
L27: ES-1054 | M27: Rudy Perez | O27: 584 | P27: 44317 | Q27: 44650 | S27: 12.5 | T27: =O27*S27 -> 7300
A28: Grant date | B28: number of options granted during 2022 | C28: number of options excercised during 2022 | D28: Options outstanding as of December 31, 2022 | E28: Exercise price | F28: Options excercisable as of December 31,2022 | G28: Excercisable through
A29: 43647 | B29: 14900 | C29: =+O25 -> 1216 | D29: =+C29+B29 -> 16116 | E29: 0.001 | F29: 7450 | G29: =+A29+365*10+3 -> 47300
A30: 43952 | B30: 9500 | C30: =+O26 -> 800 | E30: 5 | G30: =+A30+365*10+2 -> 47604
A31: 44317 | B31: 300 | C31: =+O27 -> 584 | D31: =+C31+B31 -> 884 | E31: 12.5 | F31: 100 | G31: =+A31+365*10+2 -> 47969
A32: 01/05/2022 | B32: 11800 | C32: - | E32: =+C7 -> 21.18 | F32: =+F33 -> 89352 | G32: =+A32+365*10+3 -> 48335
A33: 22/09/2022 | B33: 11950 | C33: - | D33: =+B11 -> 161335 | E33: =+E32 -> 21.18 | F33: =+B12 -> 89352 | G33: =+A33+365*10+3 -> 48479
E39: December 31,
E40: 2022 | F40: 2021
D41: CogS | E41: 0 | F41: 5 | J41: CogS | L41: -1450
D42: R&D | E42: 80 | F42: 134 | J42: R&D | K42: Product | L42: 60098
D43: S&M | E43: 51 | F43: 125 | K43: Technology | L43: 19839
D44: G&A | E44: 131 | F44: 301 | J44: S&M | K44: Sales | L44: 63820
E45: =SUM(E41:E44) -> 262 | F45: =SUM(F41:F44) -> 565 | K45: Marketing | L45: -13087
J46: G&A | L46: =97986+19940+1135+12277 -> 131338
L47: =SUM(L41:L46) -> 260558
B53: 01/08/2023 from Carta | C53: 66288
B54: Niv Sabag | C54: -800
B55: Shane Martin | C55: -2000
B56: Christine Lowe | C56: -1000
B57: Jason Hunter | C57: -750
B58: Jason Hunter | C58: -1500
B59: Shane Martin | C59: -2000
B60: Michael Sabbah | C60: -1100
B61: 2023 grants | C61: 5000
B62: Michael Sabbah | C62: -11000
B63: Rudy Perez | C63: 1216
B64: Eitan Katz | C64: 800
C65: =SUM(C53:C64) -> 53154
C69: 53144
B70: Diff | C70: =+C65-C69 -> 10

Sheet Options JE's
A5: Expense to Amortize for the Period | B5: Debit | C5: Credit
A6: Compensation Expense | B6: 440195.56
A7: Additional Paid-in-Capital | C7: 440195.56
A8: Expense (Fair Value) of Awards Exercised / Released in Period | B8: Debit | C8: Credit
A9: Additional Paid-in-Capital | B9: 40288.686
A10: Cash | B10: 11312.16
A11: Common Stock | C11: 51600.846
A12: Expiration | B12: Debit | C12: Credit
A13: Additional Paid-in-Capital | B13: 4466.7839
A14: Premium | C14: 4466.7839

Sheet Full BS-USD
A1: Wematch.live R&D LTD
A2: Wematch.live R&D LTD (Consolidated)
A3: Balance Sheet
A4: End of FY 2022
A7: Financial Row | B7: Elimination | C7: WEMATCH.SUPPORT US INC. | D7: Wematch EQD LTD | E7: Wematch Interest rate LTD | F7: Wematch Securities. Financing LTD [IL] | G7: Wematch.SecuritiesFinancing LTD | H7: Wematch.live R&D LTD | I7: Wematch.live Tech Support Europe | J7: Total | K7: INDEX
B8: Amount | C8: Amount | D8: Amount | E8: Amount | F8: Amount | G8: Amount | H8: Amount | I8: Amount | J8: Amount
A9: Current Assets
A10: Bank
A11: 10000 - Cash and Cash Equivalent (WRD-IL)
A12: 10001 - Bank Fibi 327492 NIS | B12: 0 | C12: 0 | D12: 0 | E12: 0 | F12: 0 | G12: 0 | H12: 98942.75 | I12: 0 | J12: =SUM(B12:I12) -> 98942.75
A13: 10002 - Bank Hapoalim 120737 NIS | B13: 0 | C13: 0 | D13: 0 | E13: 0 | F13: 0 | G13: 0 | H13: 184405.88 | I13: 0 | J13: =SUM(B13:I13) -> 184405.88
A14: 10003 - Bank Hapoalim 120737 USD | B14: 0 | C14: 0 | D14: 0 | E14: 0 | F14: 0 | G14: 0 | H14: 6136719.3 | I14: 0 | J14: =SUM(B14:I14) -> 6136719.3
A15: 10004 - Bank Hapoalim 120737 GBP | B15: 0 | C15: 0 | D15: 0 | E15: 0 | F15: 0 | G15: 0 | H15: 11685.56 | I15: 0 | J15: =SUM(B15:I15) -> 11685.56
A16: 10005 - Bank Hapoalim 120737 EUR | B16: 0 | C16: 0 | D16: 0 | E16: 0 | F16: 0 | G16: 0 | H16: 16813.13 | I16: 0 | J16: =SUM(B16:I16) -> 16813.13
A17: Total - 10000 - Cash and Cash Equivalent (WRD-IL) | B17: =SUM(B12:B16) -> 0 | C17: =SUM(C12:C16) -> 0 | D17: =SUM(D12:D16) -> 0 | E17: =SUM(E12:E16) -> 0 | F17: =SUM(F12:F16) -> 0 | G17: =SUM(G12:G16) -> 0 | H17: =SUM(H12:H16) -> 6448566.6 | I17: =SUM(I12:I16) -> 0 | J17: =SUM(J12:J16) -> 6448566.6 | K17: 10
A18: 101 - Dummy USD [UK] | B18: 0 | C18: 0 | D18: 0 | E18: 0 | F18: 0 | G18: -0.01 | H18: 0 | I18: 0 | J18: =SUM(B18:I18) -> -0.01
A19: 10100 - Cash and Cash Equivalent (WIR-IL)
A20: 10101 - Bank Hapoalim 120720 NIS | B20: 0 | C20: 0 | D20: 0 | E20: 21.81 | F20: 0 | G20: 0 | H20: 0 | I20: 0 | J20: =SUM(B20:I20) -> 21.81
A21: Total - 10100 - Cash and Cash Equivalent (WIR-IL) | B21: =SUM(B20) -> 0 | C21: =SUM(C20) -> 0 | D21: =SUM(D20) -> 0 | E21: =SUM(E20) -> 21.81 | F21: =SUM(F20) -> 0 | G21: =SUM(G20) -> 0 | H21: =SUM(H20) -> 0 | I21: =SUM(I20) -> 0 | J21: =SUM(J20) -> 21.81 | K21: 10
A22: 10200 - Cash and Cash Equivalent (WSF-IL)
A23: 10201 - Bank Hapoalim 120729 NIS | B23: 0 | C23: 0 | D23: 0 | E23: 0 | F23: 124.45 | G23: 0 | H23: 0 | I23: 0 | J23: =SUM(B23:I23) -> 124.45
A24: 10202 - Bank Hapoalim 120729 USD | B24: 0 | C24: 0 | D24: 0 | E24: 0 | F24: 24.67 | G24: 0 | H24: 0 | I24: 0 | J24: =SUM(B24:I24) -> 24.67
A25: 10203 - Bank Hapoalim 120729 EUR | B25: 0 | C25: 0 | D25: 0 | E25: 0 | F25: 327.43 | G25: 0 | H25: 0 | I25: 0 | J25: =SUM(B25:I25) -> 327.43
A26: Total - 10200 - Cash and Cash Equivalent (WSF-IL) | B26: =SUM(B23:B25) -> 0 | C26: =SUM(C23:C25) -> 0 | D26: =SUM(D23:D25) -> 0 | E26: =SUM(E23:E25) -> 0 | F26: =SUM(F23:F25) -> 476.55 | G26: =SUM(G23:G25) -> 0 | H26: =SUM(H23:H25) -> 0 | I26: =SUM(I23:I25) -> 0 | J26: =SUM(J23:J25) -> 476.55 | K26: 10
A27: 10300 - Cash and Cash Equivalent (WEQD-IL)
A28: 10301 - Bank Hapoalim 120702 NIS | B28: 0 | C28: 0 | D28: -3.42 | E28: 0 | F28: 0 | G28: 0 | H28: 0 | I28: 0 | J28: =SUM(B28:I28) -> -3.42
A29: 10302 - Bank Hapoalim 120702 USD | B29: 0 | C29: 0 | D29: 6438.02 | E29: 0 | F29: 0 | G29: 0 | H29: 0 | I29: 0 | J29: =SUM(B29:I29) -> 6438.02
A30: 10303 - Bank BIA | B30: 0 | C30: 0 | D30: 14237.25 | E30: 0 | F30: 0 | G30: 0 | H30: 0 | I30: 0 | J30: =SUM(B30:I30) -> 14237.25
A31: Total - 10300 - Cash and Cash Equivalent (WEQD-IL) | B31: =SUM(B28:B30) -> 0 | C31: =SUM(C28:C30) -> 0 | D31: =SUM(D28:D30) -> 20671.85 | E31: =SUM(E28:E30) -> 0 | F31: =SUM(F28:F30) -> 0 | G31: =SUM(G28:G30) -> 0 | H31: =SUM(H28:H30) -> 0 | I31: =SUM(I28:I30) -> 0 | J31: =SUM(J28:J30) -> 20671.85 | K31: 10
A32: 10400 - Cash and Cash Equivalent (WSF-UK)
A33: 10401 - Bank Netwest 27557405 GBP | B33: 0 | C33: 0 | D33: 0 | E33: 0 | F33: 0 | G33: 671296.2 | H33: 0 | I33: 0 | J33: =SUM(B33:I33) -> 671296.2
A34: Total - 10400 - Cash and Cash Equivalent (WSF-UK) | B34: =SUM(B33) -> 0 | C34: =SUM(C33) -> 0 | D34: =SUM(D33) -> 0 | E34: =SUM(E33) -> 0 | F34: =SUM(F33) -> 0 | G34: =SUM(G33) -> 671296.2 | H34: =SUM(H33) -> 0 | I34: =SUM(I33) -> 0 | J34: =SUM(J33) -> 671296.2 | K34: 10
A35: 10500 - Cash and Cash Equivalent (WTSE-FR)
A36: 10501 - Bank SG 20020671 EUR | B36: 0 | C36: 0 | D36: 0 | E36: 0 | F36: 0 | G36: 0 | H36: 0 | I36: 294848.47 | J36: =SUM(B36:I36) -> 294848.47
A37: Total - 10500 - Cash and Cash Equivalent (WTSE-FR) | B37: =SUM(B36) -> 0 | C37: =SUM(C36) -> 0 | D37: =SUM(D36) -> 0 | E37: =SUM(E36) -> 0 | F37: =SUM(F36) -> 0 | G37: =SUM(G36) -> 0 | H37: =SUM(H36) -> 0 | I37: =SUM(I36) -> 294848.47 | J37: =SUM(J36) -> 294848.47 | K37: 10
A38: 10600 - Cash and Cash Equivalent (WUS-US)
A39: 10601 - Bank Hapoalim 542 Saving USD | B39: 0 | C39: 180344.74 | D39: 0 | E39: 0 | F39: 0 | G39: 0 | H39: 0 | I39: 0 | J39: =SUM(B39:I39) -> 180344.74
A40: 10602 - Bank Hapoalim 0700 Checking USD | B40: 0 | C40: 42295.73 | D40: 0 | E40: 0 | F40: 0 | G40: 0 | H40: 0 | I40: 0 | J40: =SUM(B40:I40) -> 42295.73
A41: Total - 10600 - Cash and Cash Equivalent (WUS-US) | B41: =SUM(B39:B40) -> 0 | C41: =SUM(C39:C40) -> 222640.47 | D41: =SUM(D39:D40) -> 0 | E41: =SUM(E39:E40) -> 0 | F41: =SUM(F39:F40) -> 0 | G41: =SUM(G39:G40) -> 0 | H41: =SUM(H39:H40) -> 0 | I41: =SUM(I39:I40) -> 0 | J41: =SUM(J39:J40) -> 222640.47 | K41: 10
A42: 11000 - Short-term Restricted cash
A43: 11001 - Bank Hapoalim Deposit NIS | B43: 0 | C43: 0 | D43: 0 | E43: 0 | F43: 0 | G43: 0 | H43: 17108.38 | I43: 0 | J43: =SUM(B43:I43) -> 17108.38
A44: 11002 - Bank FIBI Deposit NIS | B44: 0 | C44: 0 | D44: 0 | E44: 0 | F44: 0 | G44: 0 | H44: 2860.69 | I44: 0 | J44: =SUM(B44:I44) -> 2860.69
A45: 11003 - Bank FIBI Deposit EUR | B45: 0 | C45: 0 | D45: 0 | E45: 0 | F45: 0 | G45: 0 | H45: 8090.49 | I45: 0 | J45: =SUM(B45:I45) -> 8090.49
A46: Total - 11000 - Short-term Restricted cash | B46: =SUM(B43:B45) -> 0 | C46: =SUM(C43:C45) -> 0 | D46: =SUM(D43:D45) -> 0 | E46: =SUM(E43:E45) -> 0 | F46: =SUM(F43:F45) -> 0 | G46: =SUM(G43:G45) -> 0 | H46: =SUM(H43:H45) -> 28059.56 | I46: =SUM(I43:I45) -> 0 | J46: =SUM(J43:J45) -> 28059.56 | K46: 11
A47: 11100 - Short term Bank Deposit
A48: 11101 - Short term Bank Deposit [BANK HAPOALIM] | B48: 0 | C48: 0 | D48: 0 | E48: 0 | F48: 0 | G48: 0 | H48: 11135351 | I48: 0 | J48: =SUM(B48:I48) -> 11135351 | K48: 11
A49: Total - 11100 - Short term Bank Deposit | B49: =SUM(B48) -> 0 | C49: =SUM(C48) -> 0 | D49: =SUM(D48) -> 0 | E49: =SUM(E48) -> 0 | F49: =SUM(F48) -> 0 | G49: =SUM(G48) -> 0 | H49: =SUM(H48) -> 11135351 | I49: =SUM(I48) -> 0 | J49: =SUM(J48) -> 11135351
A50: Total Bank | B50: =SUM(B17:B18,B21,B26,B31,B34,B37,B41,B46,B49) -> 0 | C50: =SUM(C17:C18,C21,C26,C31,C34,C37,C41,C46,C49) -> 222640.47 | D50: =SUM(D17:D18,D21,D26,D31,D34,D37,D41,D46,D49) -> 20671.85 | E50: =SUM(E17:E18,E21,E26,E31,E34,E37,E41,E46,E49) -> 21.81 | F50: =SUM(F17:F18,F21,F26,F31,F34,F37,F41,F46,F49) -> 476.55 | G50: =SUM(G17:G18,G21,G26,G31,G34,G37,G41,G46,G49) -> 671296.19 | H50: =SUM(H17:H18,H21,H26,H31,H34,H37,H41,H46,H49) -> 17611977 | I50: =SUM(I17:I18,I21,I26,I31,I34,I37,I41,I46,I49) -> 294848.47 | J50: =SUM(J17:J18,J21,J26,J31,J34,J37,J41,J46,J49) -> 18821933
A51: Accounts Receivable
A52: 12000 - Accounts Receivable
A53: 12001 - Accounts Receivable | B53: 0 | C53: 0 | D53: 0 | E53: 0 | F53: 0 | G53: 0 | H53: 1631201.2 | I53: 0 | J53: =SUM(B53:I53) -> 1631201.2
A54: 12002 - Accounts Receivable - Customers offset | B54: 0 | C54: 0 | D54: 0 | E54: 0 | F54: 0 | G54: 0 | H54: -47463 | I54: 0 | J54: =SUM(B54:I54) -> -47463
A55: Total - 12000 - Accounts Receivable | B55: =SUM(B53:B54) -> 0 | C55: =SUM(C53:C54) -> 0 | D55: =SUM(D53:D54) -> 0 | E55: =SUM(E53:E54) -> 0 | F55: =SUM(F53:F54) -> 0 | G55: =SUM(G53:G54) -> 0 | H55: =SUM(H53:H54) -> 1583738.2 | I55: =SUM(I53:I54) -> 0 | J55: =SUM(J53:J54) -> 1583738.2 | K55: 12.1
A56: 12500 - Intercompany (Receviable)
A57: 12502 - WeMatch.Live Tech Support Europe | B57: -28375.56 | C57: 0 | D57: 0 | E57: 0 | F57: 0 | G57: 0 | H57: 0 | I57: 28375.56 | J57: =SUM(B57:I57) -> 0
A58: Total - 12500 - Intercompany (Receviable) | B58: =SUM(B57) -> -28375.56 | C58: =SUM(C57) -> 0 | D58: =SUM(D57) -> 0 | E58: =SUM(E57) -> 0 | F58: =SUM(F57) -> 0 | G58: =SUM(G57) -> 0 | H58: =SUM(H57) -> 0 | I58: =SUM(I57) -> 28375.56 | J58: =SUM(J57) -> 0 | K58: 12.1
A59: Total Accounts Receivable | B59: =SUM(B55,B58) -> -28375.56 | C59: =SUM(C55,C58) -> 0 | D59: =SUM(D55,D58) -> 0 | E59: =SUM(E55,E58) -> 0 | F59: =SUM(F55,F58) -> 0 | G59: =SUM(G55,G58) -> 0 | H59: =SUM(H55,H58) -> 1583738.2 | I59: =SUM(I55,I58) -> 28375.56 | J59: =SUM(J55,J58) -> 1583738.2 | K59: 12
A60: Unbilled Receivable
A61: 12003 - Accrued income | B61: 0 | C61: 0 | D61: 0 | E61: 0 | F61: 0 | G61: 0 | H61: 126335.77 | I61: 0 | J61: =SUM(B61:I61) -> 126335.77
A62: Total Unbilled Receivable | B62: =SUM(B61) -> 0 | C62: =SUM(C61) -> 0 | D62: =SUM(D61) -> 0 | E62: =SUM(E61) -> 0 | F62: =SUM(F61) -> 0 | G62: =SUM(G61) -> 0 | H62: =SUM(H61) -> 126335.77 | I62: =SUM(I61) -> 0 | J62: =SUM(J61) -> 126335.77 | K62: 12
A63: Other Current Asset
A64: 12004 - Unbilled Revenue | B64: 0 | C64: 0 | D64: 0 | E64: 0 | F64: 0 | G64: 0 | H64: 327837.96 | I64: 0 | J64: =SUM(B64:I64) -> 327837.96 | K64: 12
A65: 12600 - Intercompany (O.C Assets)
A66: 12601 - WeMatch.Securitiesfinancing Ltd. [P] | B66: -5003503.8 | C66: 0 | D66: 0 | E66: 0 | F66: 0 | G66: 2284953.2 | H66: 2718550.6 | I66: 0 | J66: =SUM(B66:I66) -> 4.6566129e-10
A67: 12602 - WeMatch.Live Tech Support Europe [P] | B67: -1664719.2 | C67: 0 | D67: 0 | E67: 0 | F67: 0 | G67: 0 | H67: 865505.1 | I67: 799214.12 | J67: =SUM(B67:I67) -> 0
A68: 12603 - WeMatch Securities Financing Ltd. [P] | B68: -49169.73 | C68: 0 | D68: 0 | E68: 0 | F68: 48177.9 | G68: 0 | H68: 991.83 | I68: 0 | J68: =SUM(B68:I68) -> -1.7053026e-12
A69: 12605 - WeMatch EQD Ltd. [P] | B69: -4459 | C69: 0 | D69: 4459 | E69: 0 | F69: 0 | G69: 0 | H69: 0 | I69: 0 | J69: =SUM(B69:I69) -> 0
A70: 12606 - Wematch.Support US INC [P] | B70: -1433953.1 | C70: 574641.37 | D70: 0 | E70: 0 | F70: 0 | G70: 15878.25 | H70: 843433.48 | I70: 0 | J70: =SUM(B70:I70) -> -1.1641532e-10
A71: Total - 12600 - Intercompany (O.C Assets) | B71: =SUM(B66:B70) -> -8155804.9 | C71: =SUM(C66:C70) -> 574641.37 | D71: =SUM(D66:D70) -> 4459 | E71: =SUM(E66:E70) -> 0 | F71: =SUM(F66:F70) -> 48177.9 | G71: =SUM(G66:G70) -> 2300831.5 | H71: =SUM(H66:H70) -> 4428481 | I71: =SUM(I66:I70) -> 799214.12 | J71: =SUM(J66:J70) -> 3.4754066e-10 | K71: 13
A72: 13000 - Prepaid Exp.
A73: 13001 - Prepaid Expenses | B73: 0 | C73: 143307.18 | D73: 0 | E73: 0 | F73: 0 | G73: 15354.25 | H73: 130211.74 | I73: 4547.06 | J73: =SUM(B73:I73) -> 293420.23 | K73: 13.1
A74: 13002 - Prepaid rent | B74: 0 | C74: 0 | D74: 0 | E74: 0 | F74: 0 | G74: 11711.35 | H74: 0 | I74: 0 | J74: =SUM(B74:I74) -> 11711.35 | K74: 13.1
A75: 13003 - Deferred Customer acquisition cost | B75: 0 | C75: 0 | D75: 0 | E75: 0 | F75: 0 | G75: 0 | H75: 99340.48 | I75: 0 | J75: =SUM(B75:I75) -> 99340.48 | K75: 13.1
A76: Total - 13000 - Prepaid Exp. | B76: =SUM(B73:B75) -> 0 | C76: =SUM(C73:C75) -> 143307.18 | D76: =SUM(D73:D75) -> 0 | E76: =SUM(E73:E75) -> 0 | F76: =SUM(F73:F75) -> 0 | G76: =SUM(G73:G75) -> 27065.6 | H76: =SUM(H73:H75) -> 229552.22 | I76: =SUM(I73:I75) -> 4547.06 | J76: =SUM(J73:J75) -> 404472.06 | K76: 13
A77: 13009 - Government Institutions
A78: 13100 - VAT Assets
A79: 13101 - VAT on FA Purchases IL | B79: 0 | C79: 0 | D79: 0 | E79: 0 | F79: 0 | G79: 0 | H79: 49.25 | I79: 0 | J79: =SUM(B79:I79) -> 49.25
A80: 13102 - VAT on Purchases IL | B80: 0 | C80: 0 | D80: 0 | E80: 0 | F80: 0 | G80: 0 | H80: 625.84 | I80: 0 | J80: =SUM(B80:I80) -> 625.84
A81: 13103 - VAT Proforma IL | B81: 0 | C81: 0 | D81: 0 | E81: 0 | F81: 0 | G81: 0 | H81: 3165.33 | I81: 0 | J81: =SUM(B81:I81) -> 3165.33
A82: 13107 - VAT D/C | B82: 0 | C82: 0 | D82: 0 | E82: 0 | F82: 0 | G82: 0 | H82: 31238.41 | I82: 0 | J82: =SUM(B82:I82) -> 31238.41
A83: 13122 - VAT on FA Purchases FR | B83: 0 | C83: 0 | D83: 0 | E83: 0 | F83: 0 | G83: 0 | H83: 0 | I83: 5870.77 | J83: =SUM(B83:I83) -> 5870.77
A84: 13123 - VAT on Purchases FR | B84: 0 | C84: 0 | D84: 0 | E84: 0 | F84: 0 | G84: 0 | H84: 0 | I84: 38437.97 | J84: =SUM(B84:I84) -> 38437.97
A85: 13124 - VAT deductible on goods and services | B85: 0 | C85: 0 | D85: 0 | E85: 0 | F85: 0 | G85: 0 | H85: 0 | I85: 848.64 | J85: =SUM(B85:I85) -> 848.64
A86: 13202 - VAT on Purchases UK | B86: 0 | C86: 0 | D86: 0 | E86: 0 | F86: 0 | G86: 39429.68 | H86: 0 | I86: 0 | J86: =SUM(B86:I86) -> 39429.68
A87: Total - 13100 - VAT Assets | B87: =SUM(B79:B86) -> 0 | C87: =SUM(C79:C86) -> 0 | D87: =SUM(D79:D86) -> 0 | E87: =SUM(E79:E86) -> 0 | F87: =SUM(F79:F86) -> 0 | G87: =SUM(G79:G86) -> 39429.68 | H87: =SUM(H79:H86) -> 35078.83 | I87: =SUM(I79:I86) -> 45157.38 | J87: =SUM(J79:J86) -> 119665.89 | K87: 13.2
A88: 13300 - TAX Assets
A89: 13301 - Advances for Odfot | B89: 0 | C89: 0 | D89: 0 | E89: 0 | F89: 0 | G89: 0 | H89: 17204.02 | I89: 0 | J89: =SUM(B89:I89) -> 17204.02
A90: 13302 - Reversal for Exceed expenses | B90: 0 | C90: 0 | D90: 0 | E90: 0 | F90: 0 | G90: 0 | H90: -17204.02 | I90: 0 | J90: =SUM(B90:I90) -> -17204.02
A91: 13303 - Tax Benefits | B91: 0 | C91: 0 | D91: -447.84 | E91: 0 | F91: 0 | G91: 0 | H91: 0 | I91: 75511.06 | J91: =SUM(B91:I91) -> 75063.22
A92: 13304 - Other current tax asset | B92: 0 | C92: 0 | D92: 0 | E92: 0 | F92: 0 | G92: 3267.88 | H92: 0 | I92: 0 | J92: =SUM(B92:I92) -> 3267.88
A93: Total - 13300 - TAX Assets | B93: =SUM(B89:B92) -> 0 | C93: =SUM(C89:C92) -> 0 | D93: =SUM(D89:D92) -> -447.84 | E93: =SUM(E89:E92) -> 0 | F93: =SUM(F89:F92) -> 0 | G93: =SUM(G89:G92) -> 3267.88 | H93: =SUM(H89:H92) -> 0 | I93: =SUM(I89:I92) -> 75511.06 | J93: =SUM(J89:J92) -> 78331.1 | K93: 13.2
A94: Total - 13009 - Government Institutions | B94: =SUM(B87,B93) -> 0 | C94: =SUM(C87,C93) -> 0 | D94: =SUM(D87,D93) -> -447.84 | E94: =SUM(E87,E93) -> 0 | F94: =SUM(F87,F93) -> 0 | G94: =SUM(G87,G93) -> 42697.56 | H94: =SUM(H87,H93) -> 35078.83 | I94: =SUM(I87,I93) -> 120668.44 | J94: =SUM(J87,J93) -> 197996.99 | K94: 13
A95: 16000 - Other Current Asset
A96: 16001 - Rent deposit | B96: 0 | C96: 36775 | D96: 0 | E96: 0 | F96: 0 | G96: 68850.34 | H96: 37820.53 | I96: 14750.69 | J96: =SUM(B96:I96) -> 158196.56 | K96: 13.3
A97: 16002 - Other Deposits | B97: 0 | C97: 0 | D97: 0 | E97: 0 | F97: 0 | G97: 0 | H97: 11921 | I97: 0 | J97: =SUM(B97:I97) -> 11921 | K97: 13.3
A98: Total - 16000 - Other Current Asset | B98: =SUM(B96:B97) -> 0 | C98: =SUM(C96:C97) -> 36775 | D98: =SUM(D96:D97) -> 0 | E98: =SUM(E96:E97) -> 0 | F98: =SUM(F96:F97) -> 0 | G98: =SUM(G96:G97) -> 68850.34 | H98: =SUM(H96:H97) -> 49741.53 | I98: =SUM(I96:I97) -> 14750.69 | J98: =SUM(J96:J97) -> 170117.56 | K98: 13
A99: 16100 - other current asset | B99: 0 | C99: 0 | D99: 117.88 | E99: 491.94 | F99: 83.92 | G99: 0 | H99: 26.53 | I99: 0 | J99: =SUM(B99:I99) -> 720.27 | K99: 13 | L99: 13.3
A100: 17000 - Other long term assets
A101: 17001 - Interco Loans | B101: -261263.83 | C101: 0 | D101: 0 | E101: 0 | F101: 0 | G101: 0 | H101: 261263.83 | I101: 0 | J101: =SUM(B101:I101) -> 0
A102: 17002 - Employee Loans | B102: 0 | C102: 0 | D102: 37427.66 | E102: 0 | F102: 0 | G102: 0 | H102: 0 | I102: 0 | J102: =SUM(B102:I102) -> 37427.66
...

Sheet Full P&L-USD
A1: Wematch.live R&D LTD
A2: Wematch.live R&D LTD (Consolidated)
A3: WM INCOME STATEMENT
A4: From Jan 2022 to Dec 2022
A7: Financial Row | B7: WEMATCH.SUPPORT US INC. | C7: Wematch EQD LTD | D7: Wematch Interest rate LTD | E7: Wematch Securities. Financing LTD [IL] | F7: Wematch.SecuritiesFinancing LTD | G7: Wematch.live R&D LTD | H7: Wematch.live Tech Support Europe | I7: Total | J7: INDEX | L7: note
B8: Amount | C8: Amount | D8: Amount | E8: Amount | F8: Amount | G8: Amount | H8: Amount | I8: Amount
A9: Gross Income
A10: TRS | B10: 0 | C10: 0 | D10: 0 | E10: 0 | F10: 0 | G10: 5714412.2 | H10: 0 | I10: =SUM(B10:H10) -> 5714412.2
A11: SBL | B11: 0 | C11: 0 | D11: 0 | E11: 0 | F11: 0 | G11: 381782.67 | H11: 0 | I11: =SUM(B11:H11) -> 381782.67
A12: Interest rate | B12: 0 | C12: 0 | D12: 0 | E12: 0 | F12: 0 | G12: 464323.65 | H12: 0 | I12: =SUM(B12:H12) -> 464323.65
A13: Equity Derivative | B13: 0 | C13: 0 | D13: 0 | E13: 0 | F13: 0 | G13: 289436.07 | H13: 0 | I13: =SUM(B13:H13) -> 289436.07
A14: Total Gross Income | B14: =SUM(B10:B13) -> 0 | C14: =SUM(C10:C13) -> 0 | D14: =SUM(D10:D13) -> 0 | E14: =SUM(E10:E13) -> 0 | F14: =SUM(F10:F13) -> 0 | G14: =SUM(G10:G13) -> 6849954.6 | H14: =SUM(H10:H13) -> 0 | I14: =SUM(I10:I13) -> 6849954.6 | J14: 1 | L14: 9
A15: Revenue Shared With Regulated Broker Dealer
A16: 45000 - Revenues shared to third parties
A17: 45002 - Commission Shared with third party | B17: 0 | C17: 0 | D17: 0 | E17: 0 | F17: 0 | G17: -672410.8 | H17: 0 | I17: =SUM(B17:H17) -> -672410.8 | J17: 2.1
A18: 45001 - IS IN | B18: 0 | C18: 0 | D18: 0 | E18: 0 | F18: 0 | G18: -64227.52 | H18: 0 | I18: =SUM(B18:H18) -> -64227.52 | J18: 2.1
A19: 45003 - Non Reclaimable VAT | B19: 0 | C19: 0 | D19: 0 | E19: 0 | F19: 0 | G19: -165975.65 | H19: 0 | I19: =SUM(B19:H19) -> -165975.65 | J19: 2.1
A20: Total - 45000 - Revenues shared to third parties | B20: =SUM(B17:B19) -> 0 | C20: =SUM(C17:C19) -> 0 | D20: =SUM(D17:D19) -> 0 | E20: =SUM(E17:E19) -> 0 | F20: =SUM(F17:F19) -> 0 | G20: =SUM(G17:G19) -> -902613.97 | H20: =SUM(H17:H19) -> 0 | I20: =SUM(I17:I19) -> -902613.97 | J20: 2
A21: Total Revenue Shared With Regulated Broker Dealer | B21: =SUM(B20) -> 0 | C21: =SUM(C20) -> 0 | D21: =SUM(D20) -> 0 | E21: =SUM(E20) -> 0 | F21: =SUM(F20) -> 0 | G21: =SUM(G20) -> -902613.97 | H21: =SUM(H20) -> 0 | I21: =SUM(I20) -> -902613.97
A22: Net Income | B22: =+B14+B21 -> 0 | C22: =+C14+C21 -> 0 | D22: =+D14+D21 -> 0 | E22: =+E14+E21 -> 0 | F22: =+F14+F21 -> 0 | G22: =+G14+G21 -> 5947340.6 | H22: =+H14+H21 -> 0 | I22: =+I14+I21 -> 5947340.6
A23: Cost Of Sales
A24: 50000 - COGS expenses
A25: 50100 - Payroll and Related expenses [COGS]
A26: 50101 - COGS Gross Salaries | B26: 0 | C26: 0 | D26: 0 | E26: 0 | F26: 0 | G26: -416682.64 | H26: -188919.56 | I26: =SUM(B26:H26) -> -605602.2
A27: 50105 - COGS Employer taxes | B27: 0 | C27: 0 | D27: 0 | E27: 0 | F27: 0 | G27: 0 | H27: -2565.5 | I27: =SUM(B27:H27) -> -2565.5
A28: 50107 - COGS Benefits | B28: 0 | C28: 0 | D28: 0 | E28: 0 | F28: 0 | G28: 0 | H28: -1971.42 | I28: =SUM(B28:H28) -> -1971.42
A29: 50108 - COGS Employee stock-based compensation | B29: 0 | C29: 0 | D29: 0 | E29: 0 | F29: 6549.24 | G29: 0 | H29: -36.17 | I29: =SUM(B29:H29) -> 6513.07
A30: Total - 50100 - Payroll and Related expenses [COGS] | B30: =SUM(B26:B29) -> 0 | C30: =SUM(C26:C29) -> 0 | D30: =SUM(D26:D29) -> 0 | E30: =SUM(E26:E29) -> 0 | F30: =SUM(F26:F29) -> 6549.24 | G30: =SUM(G26:G29) -> -416682.64 | H30: =SUM(H26:H29) -> -193492.65 | I30: =SUM(I26:I29) -> -603626.05
A31: 51000 - Pyroll Taxes [COGS]
A32: 51001 - Social Security | B32: 0 | C32: 0 | D32: 0 | E32: 0 | F32: 0 | G32: 0 | H32: -50011.9 | I32: =SUM(B32:H32) -> -50011.9
A33: 51002 - Participation in vocational training | B33: 0 | C33: 0 | D33: 0 | E33: 0 | F33: 0 | G33: 0 | H33: -2302.4 | I33: =SUM(B33:H33) -> -2302.4
A34: 51003 - Medical Insurance | B34: 0 | C34: 0 | D34: 0 | E34: 0 | F34: 0 | G34: 0 | H34: -1264.1 | I34: =SUM(B34:H34) -> -1264.1
A35: Total - 51000 - Pyroll Taxes [COGS] | B35: =SUM(B32:B34) -> 0 | C35: =SUM(C32:C34) -> 0 | D35: =SUM(D32:D34) -> 0 | E35: =SUM(E32:E34) -> 0 | F35: =SUM(F32:F34) -> 0 | G35: =SUM(G32:G34) -> 0 | H35: =SUM(H32:H34) -> -53578.4 | I35: =SUM(I32:I34) -> -53578.4
A36: 51100 - Other Payroll related cost [COGS]
A37: 51101 - Pension Contribution [COGS] | B37: 0 | C37: 0 | D37: 0 | E37: 0 | F37: 0 | G37: 0 | H37: -20104.84 | I37: =SUM(B37:H37) -> -20104.84
A38: Total - 51100 - Other Payroll related cost [COGS] | B38: =SUM(B37) -> 0 | C38: =SUM(C37) -> 0 | D38: =SUM(D37) -> 0 | E38: =SUM(E37) -> 0 | F38: =SUM(F37) -> 0 | G38: =SUM(G37) -> 0 | H38: =SUM(H37) -> -20104.84 | I38: =SUM(I37) -> -20104.84
A39: 50400 - COGS Hosting
A40: 50402 - AWS | B40: 0 | C40: 0 | D40: 0 | E40: 0 | F40: 0 | G40: -214611.22 | H40: 0 | I40: =SUM(B40:H40) -> -214611.22
A41: 50401 - COGS Hosting exp. | B41: 0 | C41: 0 | D41: 0 | E41: 0 | F41: 0 | G41: -61140.65 | H41: 0 | I41: =SUM(B41:H41) -> -61140.65
A42: Total - 50400 - COGS Hosting | B42: =SUM(B40:B41) -> 0 | C42: =SUM(C40:C41) -> 0 | D42: =SUM(D40:D41) -> 0 | E42: =SUM(E40:E41) -> 0 | F42: =SUM(F40:F41) -> 0 | G42: =SUM(G40:G41) -> -275751.87 | H42: =SUM(H40:H41) -> 0 | I42: =SUM(I40:I41) -> -275751.87
A43: 50300 - COGS Tools/ Systems
A44: 50301 - COGS Tools | B44: 0 | C44: 0 | D44: 0 | E44: 0 | F44: 0 | G44: -158687.56 | H44: 0 | I44: =SUM(B44:H44) -> -158687.56
A45: Total - 50300 - COGS Tools/ Systems | B45: =SUM(B44) -> 0 | C45: =SUM(C44) -> 0 | D45: =SUM(D44) -> 0 | E45: =SUM(E44) -> 0 | F45: =SUM(F44) -> 0 | G45: =SUM(G44) -> -158687.56 | H45: =SUM(H44) -> 0 | I45: =SUM(I44) -> -158687.56
A46: 51110 - Recruiting Fees | B46: 0 | C46: 0 | D46: 0 | E46: 0 | F46: 0 | G46: -3670.95 | H46: -14373.13 | I46: =SUM(B46:H46) -> -18044.08
A47: Total - 50000 - COGS expenses | B47: =SUM(B30,B35,B38,B42,B45:B46) -> 0 | C47: =SUM(C30,C35,C38,C42,C45:C46) -> 0 | D47: =SUM(D30,D35,D38,D42,D45:D46) -> 0 | E47: =SUM(E30,E35,E38,E42,E45:E46) -> 0 | F47: =SUM(F30,F35,F38,F42,F45:F46) -> 6549.24 | G47: =SUM(G30,G35,G38,G42,G45:G46) -> -854793.02 | H47: =SUM(H30,H35,H38,H42,H45:H46) -> -281549.02 | I47: =SUM(I30,I35,I38,I42,I45:I46) -> -1129792.8 | J47: 2.2
A48: 61200 - Benefits - Financial
A49: 61203 - Benefits | B49: 0 | C49: 0 | D49: 0 | E49: 0 | F49: -4636.16 | G49: 0 | H49: 0 | I49: =SUM(B49:H49) -> -4636.16
A50: 61118 - Medical Insurance | B50: 0 | C50: 0 | D50: 0 | E50: 0 | F50: -2140.22 | G50: 0 | H50: 0 | I50: =SUM(B50:H50) -> -2140.22
A51: Total - 61200 - Benefits - Financial | B51: =SUM(B49:B50) -> 0 | C51: =SUM(C49:C50) -> 0 | D51: =SUM(D49:D50) -> 0 | E51: =SUM(E49:E50) -> 0 | F51: =SUM(F49:F50) -> -6776.38 | G51: =SUM(G49:G50) -> 0 | H51: =SUM(H49:H50) -> 0 | I51: =SUM(I49:I50) -> -6776.38 | J51: 2.2
A52: 69000 - Depreciation & Amortization
A53: 69001 - Depr. - Computers & Software Licenses | B53: 0 | C53: 0 | D53: 0 | E53: 0 | F53: -890.16 | G53: 0 | H53: -196.98 | I53: =SUM(B53:H53) -> -1087.14
A54: 69003 - Depr. - Electric & Office Equipment | B54: 0 | C54: 0 | D54: 0 | E54: 0 | F54: -101.09 | G54: 0 | H54: -90.92 | I54: =SUM(B54:H54) -> -192.01
A55: 69002 - Depr. - Furniture and Fixtures | B55: 0 | C55: 0 | D55: 0 | E55: 0 | F55: -175.57 | G55: 0 | H55: 0 | I55: =SUM(B55:H55) -> -175.57
A56: Total - 69000 - Depreciation & Amortization | B56: =SUM(B53:B55) -> 0 | C56: =SUM(C53:C55) -> 0 | D56: =SUM(D53:D55) -> 0 | E56: =SUM(E53:E55) -> 0 | F56: =SUM(F53:F55) -> -1166.82 | G56: =SUM(G53:G55) -> 0 | H56: =SUM(H53:H55) -> -287.9 | I56: =SUM(I53:I55) -> -1454.72 | J56: 2.2
A57: 67000 - IT, Rent, & Office Expenses
A58: 67500 - Insurance
A59: 67504 - Life / Risk insurance | B59: 0 | C59: 0 | D59: 0 | E59: 0 | F59: -1366.07 | G59: 0 | H59: 0 | I59: =SUM(B59:H59) -> -1366.07
A60: Total - 67500 - Insurance | B60: =SUM(B59) -> 0 | C60: =SUM(C59) -> 0 | D60: =SUM(D59) -> 0 | E60: =SUM(E59) -> 0 | F60: =SUM(F59) -> -1366.07 | G60: =SUM(G59) -> 0 | H60: =SUM(H59) -> 0 | I60: =SUM(I59) -> -1366.07 | J60: 2.2
A61: 67400 - Other Office Expenses
A62: 67402 - Office Food | B62: 0 | C62: 0 | D62: 0 | E62: 0 | F62: -2347.64 | G62: 0 | H62: -1753.98 | I62: =SUM(B62:H62) -> -4101.62
A63: 67401 - Office Supplies | B63: 0 | C63: 0 | D63: 0 | E63: 0 | F63: -2336.8 | G63: 0 | H63: -364.94 | I63: =SUM(B63:H63) -> -2701.74
A64: Total - 67400 - Other Office Expenses | B64: =SUM(B62:B63) -> 0 | C64: =SUM(C62:C63) -> 0 | D64: =SUM(D62:D63) -> 0 | E64: =SUM(E62:E63) -> 0 | F64: =SUM(F62:F63) -> -4684.44 | G64: =SUM(G62:G63) -> 0 | H64: =SUM(H62:H63) -> -2118.92 | I64: =SUM(I62:I63) -> -6803.36 | J64: 2.2
A65: 67100 - Rent Expenses
A66: 67101 - Office rent | B66: 0 | C66: 0 | D66: 0 | E66: 0 | F66: -58590.89 | G66: 0 | H66: -23307.54 | I66: =SUM(B66:H66) -> -81898.43
A67: Total - 67100 - Rent Expenses | B67: =SUM(B66) -> 0 | C67: =SUM(C66) -> 0 | D67: =SUM(D66) -> 0 | E67: =SUM(E66) -> 0 | F67: =SUM(F66) -> -58590.89 | G67: =SUM(G66) -> 0 | H67: =SUM(H66) -> -23307.54 | I67: =SUM(I66) -> -81898.43 | J67: 2.2
A68: 67300 - Software & Equipment
A69: 62105 - Communication | B69: 0 | C69: 0 | D69: 0 | E69: 0 | F69: -356.44 | G69: 0 | H69: -12.28 | I69: =SUM(B69:H69) -> -368.72
A70: 67301 - IT Equipment (non-capitalizable) | B70: 0 | C70: 0 | D70: 0 | E70: 0 | F70: -960.32 | G70: 0 | H70: -503.58 | I70: =SUM(B70:H70) -> -1463.9
A71: 67303 - IT services | B71: 0 | C71: 0 | D71: 0 | E71: 0 | F71: -82.7 | G71: 0 | H71: -1096.56 | I71: =SUM(B71:H71) -> -1179.26
A72: Total - 67300 - Software & Equipment | B72: =SUM(B69:B71) -> 0 | C72: =SUM(C69:C71) -> 0 | D72: =SUM(D69:D71) -> 0 | E72: =SUM(E69:E71) -> 0 | F72: =SUM(F69:F71) -> -1399.46 | G72: =SUM(G69:G71) -> 0 | H72: =SUM(H69:H71) -> -1612.42 | I72: =SUM(I69:I71) -> -3011.88 | J72: 2.2
A73: Total - 67000 - IT, Rent, & Office Expenses | B73: =SUM(B60,B64,B67,B72) -> 0 | C73: =SUM(C60,C64,C67,C72) -> 0 | D73: =SUM(D60,D64,D67,D72) -> 0 | E73: =SUM(E60,E64,E67,E72) -> 0 | F73: =SUM(F60,F64,F67,F72) -> -66040.86 | G73: =SUM(G60,G64,G67,G72) -> 0 | H73: =SUM(H60,H64,H67,H72) -> -27038.88 | I73: =SUM(I60,I64,I67,I72) -> -93079.74
A74: 61400 - Payroll Services
A75: 61401 - Payroll processing fees | B75: 0 | C75: 0 | D75: 0 | E75: 0 | F75: -590.85 | G75: 0 | H75: 0 | I75: =SUM(B75:H75) -> -590.85
A76: Total - 61400 - Payroll Services | B76: =SUM(B75) -> 0 | C76: =SUM(C75) -> 0 | D76: =SUM(D75) -> 0 | E76: =SUM(E75) -> 0 | F76: =SUM(F75) -> -590.85 | G76: =SUM(G75) -> 0 | H76: =SUM(H75) -> 0 | I76: =SUM(I75) -> -590.85 | J76: 2.2
A77: 61100 - Payroll Taxes
A78: 61101 - Employer taxes | B78: 0 | C78: 0 | D78: 0 | E78: 0 | F78: 0 | G78: 0 | H78: -2437.14 | I78: =SUM(B78:H78) -> -2437.14
A79: Total - 61100 - Payroll Taxes | B79: =SUM(B78) -> 0 | C79: =SUM(C78) -> 0 | D79: =SUM(D78) -> 0 | E79: =SUM(E78) -> 0 | F79: =SUM(F78) -> 0 | G79: =SUM(G78) -> 0 | H79: =SUM(H78) -> -2437.14 | I79: =SUM(I78) -> -2437.14 | J79: 2.2
A80: 61000 - Salaries & Wages
A81: 61700 - Team Events & Welfare
A82: 61701 - Employee gifts | B82: 0 | C82: 0 | D82: 0 | E82: 0 | F82: -53.42 | G82: 0 | H82: 0 | I82: =SUM(B82:H82) -> -53.42
A83: 61703 - Employee meals | B83: 0 | C83: 0 | D83: 0 | E83: 0 | F83: 0 | G83: 0 | H83: -1933 | I83: =SUM(B83:H83) -> -1933
A84: 61705 - Team events | B84: 0 | C84: 0 | D84: 0 | E84: 0 | F84: -1008.94 | G84: 0 | H84: -686.3 | I84: =SUM(B84:H84) -> -1695.24
A85: Total - 61700 - Team Events & Welfare | B85: =SUM(B82:B84) -> 0 | C85: =SUM(C82:C84) -> 0 | D85: =SUM(D82:D84) -> 0 | E85: =SUM(E82:E84) -> 0 | F85: =SUM(F82:F84) -> -1062.36 | G85: =SUM(G82:G84) -> 0 | H85: =SUM(H82:H84) -> -2619.3 | I85: =SUM(I82:I84) -> -3681.66 | J85: 2.2
A86: Total - 61000 - Salaries & Wages | B86: =SUM(B85) -> 0 | C86: =SUM(C85) -> 0 | D86: =SUM(D85) -> 0 | E86: =SUM(E85) -> 0 | F86: =SUM(F85) -> -1062.36 | G86: =SUM(G85) -> 0 | H86: =SUM(H85) -> -2619.3 | I86: =SUM(I85) -> -3681.66
A87: 61300 - Stock-Based Compensation
A88: 61301 - Employee stock-based compensation | B88: 0 | C88: 0 | D88: 0 | E88: 0 | F88: 0 | G88: -1450 | H88: 0 | I88: =SUM(B88:H88) -> -1450
A89: Total - 61300 - Stock-Based Compensation | B89: =SUM(B88) -> 0 | C89: =SUM(C88) -> 0 | D89: =SUM(D88) -> 0 | E89: =SUM(E88) -> 0 | F89: =SUM(F88) -> 0 | G89: =SUM(G88) -> -1450 | H89: =SUM(H88) -> 0 | I89: =SUM(I88) -> -1450
A90: Total - Cost Of Sales | B90: =SUM(B47,B51,B56,B73,B76,B79,B86,B89) -> 0 | C90: =SUM(C47,C51,C56,C73,C76,C79,C86,C89) -> 0 | D90: =SUM(D47,D51,D56,D73,D76,D79,D86,D89) -> 0 | E90: =SUM(E47,E51,E56,E73,E76,E79,E86,E89) -> 0 | F90: =SUM(F47,F51,F56,F73,F76,F79,F86,F89) -> -69088.03 | G90: =SUM(G47,G51,G56,G73,G76,G79,G86,G89) -> -856243.02 | H90: =SUM(H47,H51,H56,H73,H76,H79,H86,H89) -> -313932.24 | I90: =SUM(I47,I51,I56,I73,I76,I79,I86,I89) -> -1239263.3 | J90: 2
A91: Gross Profit | B91: =B22+B90 -> 0 | C91: =C22+C90 -> 0 | D91: =D22+D90 -> 0 | E91: =E22+E90 -> 0 | F91: =F22+F90 -> -69088.03 | G91: =G22+G90 -> 5091097.6 | H91: =H22+H90 -> -313932.24 | I91: =I22+I90 -> 4708077.3 | J91: 3
A92: Gross Profit as % of Gross Income | B92: =B91/B14*100 -> #DIV/0! | C92: =C91/C14*100 -> #DIV/0! | D92: =D91/D14*100 -> #DIV/0! | E92: =E91/E14*100 -> #DIV/0! | F92: =F91/F14*100 -> #DIV/0! | G92: =G91/G14*100 -> 74.323085 | H92: =H91/H14*100 -> #DIV/0! | I92: =I91/I14*100 -> 68.731512
A93: Operation Expense
A94: - No Department -
A95: 299997 - Conversion payable account | B95: 0 | C95: 0 | D95: 0 | E95: 0 | F95: 0 | G95: -1721.06 | H95: 0 | I95: =SUM(B95:H95) -> -1721.06
A96: 61000 - Salaries & Wages
A97: 61001 - Gross Salaries | B97: 0 | C97: 0 | D97: 0 | E97: 0 | F97: -2865.52 | G97: 0 | H97: 0 | I97: =SUM(B97:H97) -> -2865.52
A98: 61700 - Team Events & Welfare
A99: 61705 - Team events | B99: 0 | C99: 0 | D99: 0 | E99: 0 | F99: 0 | G99: -304.03 | H99: 0 | I99: =SUM(B99:H99) -> -304.03
A100: Total - 61700 - Team Events & Welfare | B100: =SUM(B99) -> 0 | C100: =SUM(C99) -> 0 | D100: =SUM(D99) -> 0 | E100: =SUM(E99) -> 0 | F100: =SUM(F99) -> 0 | G100: =SUM(G99) -> -304.03 | H100: =SUM(H99) -> 0 | I100: =SUM(I99) -> -304.03
A101: Total - 61000 - Salaries & Wages | B101: =SUM(B97,B100) -> 0 | C101: =SUM(C97,C100) -> 0 | D101: =SUM(D97,D100) -> 0 | E101: =SUM(E97,E100) -> 0 | F101: =SUM(F97,F100) -> -2865.52 | G101: =SUM(G97,G100) -> -304.03 | H101: =SUM(H97,H100) -> 0 | I101: =SUM(I97,I100) -> -3169.55
A102: 61100 - Payroll Taxes
...

Sheet AP correction OB
A1: Wematch.live R&D LTD
A2: Wematch.live R&D LTD | H2: A
A3: Balance Sheet Detail
A4: From Jan 2021 to Dec 2021
A7: Financial Row | B7: Type | C7: Date | D7: Document Number | E7: Name | F7: Amount
A8: Current Liabilities | F8: 0 | J8: תפעול פנסיוני | K8: 425.37
A9: Accounts Payable | F9: 0 | J9: איי דיגיטל סטור בע"מ | K9: -225.34
A10: 20000 - AP | F10: 0 | J10: אל על | K10: 2889.67
A11: 20001 - Accounts Payable | F11: 0 | J11: NOBU HOTEL | K11: 550.75
B12: Bill | C12: 44389 | D12: 467 | E12: Vissensa Ltd | F12: 1068.79 | G12: =-K12 -> 3295.07 | H12: =+F12-G12 -> -2226.28 | J12: VISSENSA | K12: -3295.07
B13: Bill | C13: 44486 | D13: 87KL2Y | E13: Z Hotel | F13: 652.27 | G13: =-K13 -> 997.27 | H13: =+F13-G13 -> -345 | J13: GLOUCESTER PLACE HOTEL | K13: -997.27
B14: Bill | C14: 44515 | D14: 1429268 | E14: Intralinks, Inc. | F14: 929.99 | G14: =-K14 -> 1871.48 | H14: =+F14-G14 -> -941.49 | J14: INTRALINKS | K14: -1871.48
B15: Bill | C15: 44530 | D15: IN214008196 | E15: DoiT International LTD | F15: 11709.22 | G15: =-K20-F26 -> 11708.29 | H15: =+F15-G15 -> 0.93 | J15: ENGAGE - ADRIAN | K15: -716.95
B16: Bill | C16: 44531 | D16: 1912 | E16: OpenFin Inc | F16: 5000 | G16: =-K19 -> 5000 | H16: =+F16-G16 -> 0 | J16: תן ביס | K16: -4411.58
B17: Bill | C17: 44545 | D17: 1456847 | E17: Intralinks, Inc. | F17: 931.26 | H17: =+F17-G17 -> 931.26 | J17: MONGODBCLOUD | K17: -4467.73
B18: Bill | C18: 44551 | D18: 21-124 | E18: Engage-Adrian S.L. | F18: 724.71 | G18: =-K15 -> 716.95 | H18: =+F18-G18 -> 7.76 | J18: BLOOMBERG | K18: -17115.93
B19: Bill | C19: 44551 | D19: IN21010009624 | E19: monday.com Ltd | F19: 982 | G19: =-K24 -> 977.43 | H19: =+F19-G19 -> 4.57 | J19: OPENFIN INC | K19: -5000
B20: Bill | C20: 44552 | D20: BD0002081 | E20: eFinancialCareers Limited | F20: 4058.7 | G20: =-K27 -> 4039.87 | H20: =+F20-G20 -> 18.83 | J20: DOIT INTERNATIONAL LTD | K20: -18923.35
B21: Bill | C21: 44557 | D21: 5606566270 | E21: BLOOMBERG FINANCE L.P | F21: 140 | H21: =+F21-G21 -> 140 | J21: JAMES BOYCE | K21: -25220.29
B22: Bill | C22: 44557 | D22: 5606566274 | E22: BLOOMBERG FINANCE L.P | F22: 17070 | G22: =-K18 -> 17115.93 | H22: =+F22-G22 -> -45.93 | J22: הפרשה לספקים בחובה(אל על) | K22: -3605.76
B23: Bill | C23: 44559 | D23: IIR025280 | E23: MongoDB Limited | F23: 3200 | G23: =-K17-F25 -> 3175.44 | H23: =+F23-G23 -> 24.56 | J23: דאטהצ'ק בע"מ | K23: 112.22
B24: Bill | C24: 44561 | D24: UNK 1 | E24: iDigital Store LTD | F24: 72.35 | G24: =-K9 -> 225.34 | H24: =+F24-G24 -> -152.99 | J24: MONDAY | K24: -977.43
B25: Bill | C25: 44561 | D25: IIR025446 | E25: MongoDB Limited | F25: 1292.29 | H25: =+F25-G25 -> 1292.29 | J25: מוזגו מנשה | K25: -26898.71
B26: Bill | C26: 44561 | D26: IN214008800 | E26: DoiT International LTD | F26: 7215.06 | J26: EXPENSIFY | K26: -20
B27: Bill | C27: 44561 | D27: 1 | E27: Menashe Mozago | F27: 26898.72 | G27: =-K25 -> 26898.71 | H27: =+F27-G27 -> 0.01 | J27: EFINANCIAL CAREERS | K27: -4039.87
B28: Bill | C28: 44561 | D28: 3 | E28: James Boyce | F28: 25220.29 | G28: =-K21 -> 25220.29 | H28: =+F28-G28 -> 0
B29: Bill | C29: 44561 | D29: 86344375 | E29: Expensify, Inc. | F29: 20 | G29: =-K26 -> 20 | H29: =+F29-G29 -> 0
B30: Bill | C30: 44561 | D30: 202146051 | E30: 10Bis LTD | F30: 4411.58 | G30: =-K16 -> 4411.58 | H30: =+F30-G30 -> 0
A31: Total - 20001 - Accounts Payable | F31: =SUM(F11:F30) -> 111597.23
A32: Total - 20000 - AP | F32: =SUM(F10,F31) -> 111597.23
A33: Total Accounts Payable | F33: =SUM(F9,F32) -> 111597.23
A34: Total Liabilities | F34: =F33+0+0 -> 111597.23
A35: Current Assets Less Current Liabilities | F35: =0-F34 -> -111597.23
A36: Total Assets Less Current Liabilities | F36: =F35+0+0 -> -111597.23
A37: Total Assets Less Total Liabilities | F37: =F36-0 -> -111597.23
A46: Wematch.live R&D LTD
A47: Wematch.live R&D LTD
A48: Israeli A/P Register
A49: 31 December 2021 - 31 August 2023
A52: Vendor Name | B52: Type | C52: Date | D52: No. | E52: Memo | F52: Date Due | G52: Billed | H52: Paid | I52: Balance | J52: Amount (Foreign Currency) | K52: Currency: Currency Symbol | L52: Exchange Rate
A53: AP | I53: 0
A54: Accounts Payable | I54: 0
A55: iDigital Store LTD | I55: 0
B56: Bill | C56: 44561 | D56: UNK 1 | E56: Open Balance AP 31/12/2021 | F56: Paid | G56: 72.35 | I56: =I55+H56-G56 -> -72.35 | J56: 225 | K56: ILS | L56: 0.32154344 | M56: O.B | N56: diff | O56: =+J65+J61+J57+J56 -> 2855
B57: Bill | C57: 44573 | D57: SI22RA0000784 | E57: iDigital - MBP X2 (Dima Solodukha + Joseph Seroussi) | F57: 44573 | G57: 6977.5 | I57: =I56+H57-G57 -> -7049.85 | J57: 21714 | K57: ILS | L57: 0.32133676
B58: Bill Credit | C58: 44573 | D58: SI22RA0000784 | E58: iDigital - MBP X2 (Dima Solodukha + Joseph Seroussi) | H58: 917.42 | I58: =I57+H58-G58 -> -6132.43 | J58: -2855 | K58: ILS | L58: 0.32133676
B59: Currency Revaluation | C59: 44573 | D59: REVIL-730 | G59: 0.01 | I59: =I58+H59-G59 -> -6132.44 | K59: USD | L59: 1.0
B60: Journal | C60: 44573 | D60: JEIL-03297 | E60: correcting Bill credit SI22RA0000784 | F60: Paid | G60: 917.42 | I60: =I59+H60-G60 -> -7049.86 | J60: 2855 | K60: ILS | L60: 0.32133676
B61: Bill | C61: 44581 | D61: SI22RA0001361 | E61: iDigital - MBP (Barak Saidoff) + It equipment | F61: Paid | G61: 3294.19 | I61: =I60+H61-G61 -> -10344.05 | J61: 10324 | K61: ILS | L61: 0.31908105
B62: Currency Revaluation | C62: 44592 | D62: REVIL-1042 | H62: 222.25 | I62: =I61+H62-G62 -> -10121.8 | K62: USD | L62: 1.0
B63: Currency Revaluation | C63: 44593 | D63: REVIL-1043 | F63: Paid | G63: 222.25 | I63: =I62+H63-G63 -> -10344.05 | K63: USD | L63: 1.0
B64: Bill | C64: 44599 | D64: SI22RA0002143 | E64: iDigital - Mac Mini + Magic Keyboared | F64: Paid | G64: 1375.59 | I64: =I63+H64-G64 -> -11719.64 | J64: 4395 | K64: ILS | L64: 0.31298905
B65: Bill Payment | C65: 44599 | H65: 9204.38 | I65: =I64+H65-G65 -> -2515.26 | J65: -29408 | K65: ILS | L65: 0.31298905
B66: Currency Revaluation | C66: 44599 | D66: REVIL-725 | H66: 1.92 | I66: =I65+H66-G66 -> -2513.34 | K66: USD | L66: 1.0
B67: Currency Revaluation | C67: 44599 | D67: REVIL-726 | H67: 220.32 | I67: =I66+H67-G67 -> -2293.02 | K67: USD | L67: 1.0
B68: Bill | C68: 44613 | D68: SI22RA0003149 | E68: iDigital -Type C adapter, Magic Trackpad, Magic Keyboard, USB charger | F68: Paid | G68: 1193.14 | I68: =I67+H68-G68 -> -3486.16 | J68: 3830 | K68: ILS | L68: 0.31152648
B69: Currency Revaluation | C69: 44613 | D69: REVIL-720 | G69: 0.01 | I69: =I68+H69-G69 -> -3486.17 | K69: USD | L69: 1.0
B70: Currency Revaluation | C70: 44620 | D70: REVIL-1058 | H70: 28.6 | I70: =I69+H70-G70 -> -3457.57 | K70: USD | L70: 1.0
B71: Currency Revaluation | C71: 44621 | D71: REVIL-1059 | F71: Paid | G71: 28.6 | I71: =I70+H71-G71 -> -3486.17 | K71: USD | L71: 1.0
B72: Bill | C72: 44629 | D72: SI22RA0004210 | E72: iDigital - IPAD PRO 256GB X2, Glass Screen, Ipad Pro X2 | F72: Paid | G72: 3091.96 | I72: =I71+H72-G72 -> -6578.13 | J72: 10154 | K72: ILS | L72: 0.3045067
B73: Bill | C73: 44630 | D73: SI22RA0004249 | E73: iDigital - MBP Pro (Micael Jorje) | F73: Paid | G73: 2381.23 | I73: =I72+H73-G73 -> -8959.36 | J73: 7789 | K73: ILS | L73: 0.30571691
B74: Bill Payment | C74: 44635 | H74: 7961.06 | I74: =I73+H74-G74 -> -998.3 | J74: -26168 | K74: ILS | L74: 0.30422878
B75: Currency Revaluation | C75: 44635 | D75: REVIL-716 | H75: 66.45 | I75: =I74+H75-G75 -> -931.85 | K75: USD | L75: 1.0
B76: Currency Revaluation | C76: 44635 | D76: REVIL-717 | H76: 14.41 | I76: =I75+H76-G76 -> -917.44 | K76: USD | L76: 1.0
B77: Currency Revaluation | C77: 44635 | D77: REVIL-718 | H77: 0.01 | I77: =I76+H77-G77 -> -917.43 | K77: USD | L77: 1.0
B78: Currency Revaluation | C78: 44651 | D78: REVIL-1060 | H78: 0.01 | I78: =I77+H78-G78 -> -917.42 | K78: USD | L78: 1.0
B79: Currency Revaluation | C79: 44652 | D79: REVIL-1061 | F79: Paid | G79: 0.01 | I79: =I78+H79-G79 -> -917.43 | K79: USD | L79: 1.0
B80: Currency Revaluation | C80: 44681 | D80: REVIL-1075 | H80: 0.01 | I80: =I79+H80-G80 -> -917.42 | K80: USD | L80: 1.0
B81: Currency Revaluation | C81: 44682 | D81: REVIL-1076 | F81: Paid | G81: 0.01 | I81: =I80+H81-G81 -> -917.43 | K81: USD | L81: 1.0
B82: Bill | C82: 44696 | D82: SI22RA0006798 | E82: iDigital - MBP 14.2 [Marina Anisimova] Type C adapter X5, Magic Mouse | F82: Paid | G82: 3027.55 | I82: =I81+H82-G82 -> -3944.98 | J82: 10330 | K82: ILS | L82: 0.293083
B83: Currency Revaluation | C83: 44696 | D83: REVIL-714 | H83: 0.01 | I83: =I82+H83-G83 -> -3944.97 | K83: USD | L83: 1.0
B84: Bill | C84: 44703 | D84: SI22RA0007078 | E84: iDigital - HyperJuice charger, USB C charge cable, Magic Keyboared | F84: Paid | G84: 280.15 | I84: =I83+H84-G84 -> -4225.12 | J84: 941 | K84: ILS | L84: 0.297708
B85: Currency Revaluation | C85: 44703 | D85: REVIL-715 | H85: 0.01 | I85: =I84+H85-G85 -> -4225.11 | K85: USD | L85: 1.0
B86: Currency Revaluation | C86: 44712 | D86: REVIL-1090 | F86: Paid | G86: 68.89 | I86: =I85+H86-G86 -> -4294 | K86: USD | L86: 1.0
B87: Currency Revaluation | C87: 44713 | D87: REVIL-1091 | H87: 68.89 | I87: =I86+H87-G87 -> -4225.11 | K87: USD | L87: 1.0
B88: Bill Payment | C88: 44728 | H88: 3254.69 | I88: =I87+H88-G88 -> -970.42 | J88: -11271 | K88: ILS | L88: 0.288767
B89: Currency Revaluation | C89: 44728 | D89: REVIL-713 | H89: 52.99 | I89: =I88+H89-G89 -> -917.43 | K89: USD | L89: 1.0
B90: Bill | C90: 44738 | D90: SI22RA0008402 | E90: iDigital - MBP 16.2 SG/16C GPU/16GB/512G-ISR [Andrew Vorobyov] | F90: Paid | G90: 2797.51 | I90: =I89+H90-G90 -> -3714.94 | J90: 9629 | K90: ILS | L90: 0.290529
B91: Currency Revaluation | C91: 44738 | D91: REVIL-712 | H91: 0.01 | I91: =I90+H91-G91 -> -3714.93 | K91: USD | L91: 1.0
B92: Bill Payment | C92: 44741 | H92: 2791.01 | I92: =I91+H92-G92 -> -923.92 | J92: -9629 | K92: ILS | L92: 0.289855
B93: Currency Revaluation | C93: 44741 | D93: REVIL-711 | H93: 6.49 | I93: =I92+H93-G93 -> -917.43 | K93: USD | L93: 1.0
B94: Currency Revaluation | C94: 44742 | D94: REVIL-1104 | H94: 0.01 | I94: =I93+H94-G94 -> -917.42 | K94: USD | L94: 1.0
B95: Currency Revaluation | C95: 44743 | D95: REVIL-1105 | F95: Paid | G95: 0.01 | I95: =I94+H95-G95 -> -917.43 | K95: USD | L95: 1.0
B96: Currency Revaluation | C96: 44773 | D96: REVIL-1131 | H96: 0.01 | I96: =I95+H96-G96 -> -917.42 | K96: USD | L96: 1.0
B97: Currency Revaluation | C97: 44774 | D97: REVIL-1132 | F97: Paid | G97: 0.01 | I97: =I96+H97-G97 -> -917.43 | K97: USD | L97: 1.0
B98: Bill | C98: 44782 | D98: SI22RA0009993 | E98: iDigital - MBP 16.2 SG/16C GPU/16GB/512G-ISR [Jenny Ronen], Magic Mouse & Keyboard | F98: Paid | G98: 3199.27 | I98: =I97+H98-G98 -> -4116.7 | J98: 10580 | K98: ILS | L98: 0.302389
B99: Bill | C99: 44801 | D99: SI22RA0010755 | E99: iDigital - MBP 14.2 SL/8C CPU/14GB/512G-ISR , Magic Mouse & Keyboard | F99: Paid | G99: 2511.21 | I99: =I98+H99-G99 -> -6627.91 | J99: 8184 | K99: ILS | L99: 0.306843
B100: Currency Revaluation | C100: 44804 | D100: REVIL-1146 | H100: 94.2 | I100: =I99+H100-G100 -> -6533.71 | K100: USD | L100: 1.0
B101: Bill Payment | C101: 44805 | H101: 5577.88 | I101: =I100+H101-G101 -> -955.83 | J101: -18764 | K101: ILS | L101: 0.297265
B102: Currency Revaluation | C102: 44805 | D102: REVIL-708 | H102: 132.6 | I102: =I101+H102-G102 -> -823.23 | K102: USD | L102: 1.0
B103: Currency Revaluation | C103: 44805 | D103: REVIL-1147 | F103: Paid | G103: 94.2 | I103: =I102+H103-G103 -> -917.43 | K103: USD | L103: 1.0
B104: Currency Revaluation | C104: 44834 | D104: REVIL-1148 | H104: 0.01 | I104: =I103+H104-G104 -> -917.42 | K104: USD | L104: 1.0
B105: Currency Revaluation | C105: 44835 | D105: REVIL-1149 | F105: Paid | G105: 0.01 | I105: =I104+H105-G105 -> -917.43 | K105: USD | L105: 1.0
B106: Currency Revaluation | C106: 44865 | D106: REVIL-1188 | H106: 0.01 | I106: =I105+H106-G106 -> -917.42 | K106: USD | L106: 1.0
B107: Currency Revaluation | C107: 44866 | D107: REVIL-1189 | F107: Paid | G107: 0.01 | I107: =I106+H107-G107 -> -917.43 | K107: USD | L107: 1.0
B108: Currency Revaluation | C108: 44895 | D108: REVIL-1190 | H108: 0.01 | I108: =I107+H108-G108 -> -917.42 | K108: USD | L108: 1.0
B109: Currency Revaluation | C109: 44896 | D109: REVIL-1191 | F109: Paid | G109: 0.01 | I109: =I108+H109-G109 -> -917.43 | K109: USD | L109: 1.0
B110: Currency Revaluation | C110: 44901 | D110: REVIL-728 | H110: 0.01 | I110: =I109+H110-G110 -> -917.42 | K110: USD | L110: 1.0
B111: Currency Revaluation | C111: 44926 | D111: REVIL-2154 | H111: 105.12 | I111: =I110+H111-G111 -> -812.3 | K111: USD | L111: 1.0
B112: Currency Revaluation | C112: 44927 | D112: REVIL-2155 | F112: Paid | G112: 105.12 | I112: =I111+H112-G112 -> -917.42 | K112: USD | L112: 1.0
...

Sheet OLD--->

Sheet CF.
A4: Cash flows from operating activities:
C5: As of December 31, 2022
C7: US thousand
A9: Net loss | C9: =-E95 -> -7371
A11: Adjustments to reconcile net loss to net cash provided by operating activities:
A14: Depreciation and amortization and impermanent | C14: =-E82 -> 28.55433
A15: Share-based compensation expense | C15: =-E92 -> 257.137
A16: Change in employee long term loans | C16: =-E81 -> 4
A17: Change in long time employee benefit | C17: =-E88 -> -2
A19: Change in SAFE fair value | C19: =-E87 -> 0
A21: Changes in operating assets and liabilities:
A22: Accounts receivable | C22: =-E79 -> -1020
A23: Prepaid expenses and other assets | C23: =-E80 -> -517
A24: Accounts payable | C24: =-E83 -> 69
A25: Accrued expenses and other liabilities | C25: =-E84 -> 47
A26: Change in Deferred revenue | C26: =-E85 -> 0
A28: Net cash provided by operating activities | C28: =SUM(C9:C27) -> -8504.3087
A30: Cash flows from investing activities:
A32: Change in short term restricted deposit | C32: =-F78-284 -> -11416
A33: Purchases of property and equipment | C33: =-F82 -> -92.63258
A35: Net cash used in investing activities | C35: =-F96 -> -11508.633
A37: Cash flows from financing activities:
A39: Proceeds from issuance of Sample agreement for future equity ("SAFE")
A40: Issuance of Preferred B shares, net of issuance cost | C40: =-G91-G89 -> 3185.706
A41: Proceeds from issuance of convertible preferred shares, net of issuance costs
A43: Net cash provided by financing activities | C43: =+C41+C40+C39 -> 3185.706
A45: Net increase (decrease) in cash, cash equivalents, and restricted cash | C45: =+C43+C28+C35 -> -16827.235
A46: Cash, cash equivalents, and restricted cash—beginning of period | C46: =+D77+E77 -> 27388
A48: Cash, cash equivalents, and restricted cash—end of period | C48: =+C45+C46 -> 10560.765 | D48: =+J77 -> 7660 | E48: =+C48-D48 -> 2900.7647
D53: לבדוק האם לשים יתרה עם פקדונות או בלי? | E53: EY
F70: Working peper for cash flow
D74: Closing balance as | E74: Cash flow from | F74: Cash flow from | G74: Cash flow from | J74: Closing balance as
D75: 44561 | E75: Opeartion | F75: Investing | G75: Financing | H75: Non-cash activites | I75: Change in cash | J75: 44926 | L75: Check
B77: 10 | C77: Cash and cash equivalents | D77: 27403 | E77: =-27403+27388 -> -15 | I77: =J77-D77-E77 -> -19728 | J77: =+ROUND(SUMIF('BS USD'!$B$7:$B$54,B77,'BS USD'!$Q$7:$Q$54),0) -> 7660 | L77: =SUM(D77:I77)-J77 -> 0
B78: 11 | C78: Restricted Bank Deposit | D78: 31 | F78: =J78-D78 -> 11132 | J78: =+ROUND(SUMIF('BS USD'!$B$7:$B$54,B78,'BS USD'!$Q$7:$Q$54),0) -> 11163 | L78: =SUM(D78:I78)-J78 -> 0
B79: 12 | C79: Account Receivable | D79: 1017 | E79: =J79-D79 -> 1020 | J79: =+ROUND(SUMIF('BS USD'!$B$7:$B$54,B79,'BS USD'!$Q$7:$Q$54),0) -> 2037 | L79: =SUM(D79:I79)-J79 -> 0
B80: 13 | C80: Prepaid expenses and other current assets | D80: 259 | E80: =J80-D80 -> 517 | J80: =+ROUND(SUMIF('BS USD'!$B$7:$B$54,B80,'BS USD'!$Q$7:$Q$54),0) -> 776 | L80: =SUM(D80:I80)-J80 -> 0
B81: 14 | C81: Other long term accounts receivables | D81: 37 | E81: =J81-D81 -> -4 | J81: =+ROUND(SUMIF('BS USD'!$B$7:$B$54,B81,'BS USD'!$Q$7:$Q$54),0) -> 33 | L81: =SUM(D81:I81)-J81 -> 0
B82: 15 | C82: Property & Equipment, Net | D82: 58 | E82: =-(26238+1110.97+2205.36)/1000+1 -> -28.55433 | F82: =+(67350.26+17015.98+7266.34)/1000+1 -> 92.63258 | J82: =+ROUND(SUMIF('BS USD'!$B$7:$B$54,B82,'BS USD'!$Q$7:$Q$54),0) -> 123 | L82: =SUM(D82:I82)-J82 -> -0.92175
B83: 16 | C83: Account Payable | D83: -133 | E83: =J83-D83 -> -69 | J83: =-ROUND(SUMIF('BS USD'!$B$7:$B$54,B83,'BS USD'!$Q$7:$Q$54),0) -> -202 | L83: =SUM(D83:I83)-J83 -> 0
B84: 17 | C84: Accrued expenses and other current liabilities | D84: -745 | E84: =J84-D84 -> -47 | J84: =-ROUND(SUMIF('BS USD'!$B$7:$B$54,B84,'BS USD'!$Q$7:$Q$54),0) -> -792 | L84: =SUM(D84:I84)-J84 -> 0
B85: 17.4 | C85: Deferred Revenues | D85: 0 | E85: =J85-D85 -> 0 | L85: =SUM(D85:I85)-J85 -> 0
C86: Warrants | D86: 0 | E86: =J86-D86 -> 0 | J86: =+ROUND(SUMIF('BS USD'!$B$7:$B$54,B86,'BS USD'!$Q$7:$Q$54),0) -> 0 | L86: =SUM(D86:I86)-J86 -> 0
C87: Safe agreement | D87: 0 | E87: =J87-D87 -> 0 | J87: =+ROUND(SUMIF('BS USD'!$B$7:$B$54,B87,'BS USD'!$Q$7:$Q$54),0) -> 0 | L87: =SUM(D87:I87)-J87 -> 0
B88: 18 | C88: Provision for post employment benefits | D88: -416 | E88: =J88-D88 -> 2 | J88: =-ROUND(SUMIF('BS USD'!$B$7:$B$54,B88,'BS USD'!$Q$7:$Q$54),0) -> -414 | L88: =SUM(D88:I88)-J88 -> 0
C89: Ordinary shares | D89: -9 | G89: 9 | J89: =+ROUND(SUMIF('BS USD'!$B$7:$B$54,B89,'BS USD'!$Q$7:$Q$54),0) -> 0 | L89: =SUM(D89:I89)-J89 -> 0
C90: Option exercise by employees | D90: 0 | E90: =J90-D90 -> -7 | G90: -7 | J90: =+G90+D90 -> -7 | L90: =SUM(D90:I90)-J90 -> -7
B91: 19.1 | C91: Preferred shares | D91: -27930 | G91: =+J91-D91 -> -3194.706 | J91: =-ROUND(SUMIF('Full BS-USD'!K:K,B91,'Full BS-USD'!J:J),0)/1000 -> -31124.706 | L91: =SUM(D91:I91)-J91 -> 0
B92: 19.2 | C92: Additional paid in capital-Share based compensation | D92: -1397 | E92: =J92-D92 -> -257.137 | J92: =-ROUND(SUMIF('Full BS-USD'!K:K,B92,'Full BS-USD'!J:J),0)/1000 -> -1654.137 | L92: =SUM(D92:I92)-J92 -> 0 | M92: 31005
B93: 19.3 | C93: Additional paid in capital | D93: -12253 | J93: =-ROUND(SUMIF('Full BS-USD'!K:K,B93,'Full BS-USD'!J:J),0)/1000+7 -> -9339.464
C94: Retained Earnings | D94: =10806+3272 -> 14078 | F94: =11090-10806 -> 284 | J94: =-ROUND(SUMIF('Full BS-USD'!A:A,C94,'Full BS-USD'!J:J),0)/1000 -> 14349.72 | L94: =SUM(D94:I94)-J94 -> 12.28
C95: Current year Profit (loss) | E95: 7371 | J95: =-'P&L'!O31 -> 7392 | L95: =SUM(D95:I95)-J95 -> -21
E96: =SUM(E77:E95) -> 8482.3087 | F96: =SUM(F76:F95) -> 11508.633 | I96: =SUM(I77:I95) -> -19728 | J96: =SUM(J77:J95) -> 0.413 | L96: =SUM(D96:I96)-J96 -> 262.52825
C97: Check | D97: =SUM(D77:D96) -> 0 | L97: =SUM(D97:I97)-J97 -> 0
E98: =+E96+C28 -> -22
E99: =+E98/2 -> -11
D102: =+D77-27388 -> 15

Sheet CF NS
A1: Wematch.live R&D LTD
A2: Wematch.live R&D LTD (Consolidated)
A3: Cash Flow Statement
A4: From Jan 2022 to Dec 2022
A7: Financial Row | B7: Amount
A8: Operating Activities
A9: Net Income | B9: -7370915.9
A10: Adjustments to Profit/(Loss)
A11: Accounts Receivable | B11: -786713.56
A12: Unbilled Receivable | B12: -126335.77
A13: Other Current Asset | B13: -660237.04
A14: Accounts Payable | B14: 72052.69
A15: Sales Tax Payable | B15: 10196.89
A16: Other Current Liabilities | B16: 47875.8
A17: Total Adjustments to Profit/(Loss) | B17: -1443161
A18: Total Operating Activities | B18: -8814076.9
A19: Investing Activities
A20: Fixed Asset | B20: -62078.09
A21: Total Investing Activities | B21: -62078.09
A22: Financing Activities
A23: Other Equity | B23: 264248.86
A24: Total Financing Activities | B24: 264248.86
A25: Net Change in Cash for Period | B25: -8611906.1
A26: Cash at Beginning of Period | B26: 27419436
A27: Cash at End of Period | B27: 18807530

Sheet Change in Equity (2)
D3: Ordinary shares | H3: Preferred Shares | L3: Additional | N3: Receivable on | P3: Accumulated | R3: Total shareholders' equity
L4: paid-in
D5: Number | F5: Amount | H5: Number | J5: Amount | L5: capital | N5: Shares account | P5: deficit | R5: (deficit)
B7: Balance as of January 1, 2021 | D7: 1401739 | F7: 4 | H7: 198028 | J7: (*) | L7: 12952 | N7: -50 | P7: -10806 | R7: =+P7+F7+L7+N7 -> 2100
B9: Net loss and other comprehensive loss | D9: 0 | F9: 0 | H9: 0 | J9: 0 | L9: 0 | N9: 0 | P9: -3272 | R9: =+P9+F9+L9+J9 -> -3272
B10: Receivable of shares | N10: 50 | R10: =+P10+F10+L10+J10+N10 -> 50
B11: Share based compensation | D11: 0 | F11: 0 | H11: 0 | J11: 0 | L11: 565 | N11: 0 | P11: 0 | R11: =+P11+F11+L11+J11 -> 565 | T11: =+SUM('[2]Summary Cap Table'!$C$12:$C$22)-H16 -> -1071
B12: Warrant exercise | H12: 315996 | J12: 1 | L12: 3124 | R12: =+P12+F12+L12+J12 -> 3125
B13: SAFE exercise | D13: 0 | F13: 0 | H13: 105500 | J13: 1 | L13: =[1]CF!D35+[1]CF!D15-1 -> -1 | N13: - | P13: 0 | R13: =+P13+F13+L13+J13 -> 0
B14: Issuance of preferred B Shares, net of issuance cost | D14: 0 | F14: 0 | H14: =570204+293045 -> 863249 | J14: 3 | L14: 24940 | P14: 0 | R14: =+P14+J14+L14+N14 -> 24943
B16: Balance as of December 31, 2021 | D16: =SUM(D7:D15) -> 1401739 | F16: =SUM(F7:F15) -> 4 | H16: =SUM(H7:H15) -> 1482773 | J16: =SUM(J7:J15) -> 5 | L16: =SUM(L7:L15) -> 41580 | N16: =SUM(N7:N15) -> 0 | P16: =SUM(P7:P15) -> -14078 | R16: =+P16+F16+L16+N16+J16 -> 27511
B18: Net loss and other comprehensive loss | D18: 0 | F18: 0 | H18: 0 | J18: 0 | L18: 0 | N18: 0 | P18: =+'P&L'!O31 -> -7392 | R18: =SUM(J18:P18,F18) -> -7392
B19: recievable on account of shares | D19: 800 | R19: =SUM(J19:P19,F19) -> 0
B20: Share based compensation | D20: =584+1216 -> 1800 | L20: =-CF!E93+7 -> 265.137 | R20: =SUM(J20:P20,F20) -> 265.137
B21: SAFE exercise | R21: =SUM(J21:P21,F21) -> 0
B22: Warrant exercise | H22: 127247 | J22: (*) | R22: =SUM(J22:P22,F22) -> 0
B23: Issuance of preferred A Shares, net of issuance cost
B24: Issuance of ordinary stocks, net of issuance cost | F24: 0 | P24: 0 | R24: =SUM(J24:P24,F24) -> 0
B26: Balance as of December 31, 2022 | D26: =SUM(D16:D24) -> 1404339 | F26: =SUM(F16:F24) -> 4 | H26: =SUM(H16:H24) -> 1610020 | J26: =SUM(J16:J24) -> 5 | L26: =SUM(L16:L24) -> 41845.137 | N26: =SUM(N16:N24) -> 0 | P26: =SUM(P16:P24) -> -21470 | R26: =SUM(R16:R24) -> 20384.137
J27: =F26+J26-[1]BS!O134 -> 0
D28: =+D16+D19+D20-D26 -> 0 | H28: =+H16+H22-H26 -> 0 | L28: =+L16+L20-L26 -> 0 | P28: =+P16+P18-P26 -> 0 | Q28: =+Q16+Q18-Q26 -> 0
L32: 42125 | P32: 21732
L33: =+L26-L32 -> -279.863 | P33: =+P26+P32 -> 262

Sheet Full BS-USD (2)
A1: Wematch.live R&D LTD
A2: Wematch.live R&D LTD (Consolidated)
A3: Balance Sheet
A4: End of FY 2022
A7: Financial Row | B7: Elimination | C7: WEMATCH.SUPPORT US INC. | D7: Wematch EQD LTD | E7: Wematch Interest rate LTD | F7: Wematch Securities. Financing LTD [IL] | G7: Wematch.Securities Financing LTD | H7: Wematch.live R&D LTD | I7: Wematch.live Tech Support Europe | J7: Total | K7: INDEX
B8: Amount | C8: Amount | D8: Amount | E8: Amount | F8: Amount | G8: Amount | H8: Amount | I8: Amount | J8: Amount
A9: Current Assets
A10: Bank
A11: 10000 - Cash and Cash Equivalent (WRD-IL)
A12: 10001 - Bank Fibi 327492 NIS | B12: 0 | C12: 0 | D12: 0 | E12: 0 | F12: 0 | G12: 0 | H12: 98925.39 | I12: 0 | J12: =+IFERROR(VLOOKUP(A12,[3]BalanceSheet!A$8:B$154,2,0),0) -> 26151.22
A13: 10002 - Bank Hapoalim 120737 NIS | B13: 0 | C13: 0 | D13: 0 | E13: 0 | F13: 0 | G13: 0 | H13: 184319.33 | I13: 0 | J13: =+IFERROR(VLOOKUP(A13,[3]BalanceSheet!A$8:B$154,2,0),0) -> 344.4
A14: 10003 - Bank Hapoalim 120737 USD | B14: 0 | C14: 0 | D14: 0 | E14: 0 | F14: 0 | G14: 0 | H14: 6136719.3 | I14: 0 | J14: =+IFERROR(VLOOKUP(A14,[3]BalanceSheet!A$8:B$154,2,0),0) -> 26906064
A15: 10004 - Bank Hapoalim 120737 GBP | B15: 0 | C15: 0 | D15: 0 | E15: 0 | F15: 0 | G15: 0 | H15: 11685.56 | I15: 0 | J15: =+IFERROR(VLOOKUP(A15,[3]BalanceSheet!A$8:B$154,2,0),0) -> 5309.75
A16: 10005 - Bank Hapoalim 120737 EUR | B16: 0 | C16: 0 | D16: 0 | E16: 0 | F16: 0 | G16: 0 | H16: 16813.13 | I16: 0 | J16: =+IFERROR(VLOOKUP(A16,[3]BalanceSheet!A$8:B$154,2,0),0) -> 367423.66
A17: Total - 10000 - Cash and Cash Equivalent (WRD-IL) | B17: =SUM(B12:B16) -> 0 | C17: =SUM(C12:C16) -> 0 | D17: =SUM(D12:D16) -> 0 | E17: =SUM(E12:E16) -> 0 | F17: =SUM(F12:F16) -> 0 | G17: =SUM(G12:G16) -> 0 | H17: =SUM(H12:H16) -> 6448462.7 | I17: =SUM(I12:I16) -> 0 | J17: =+IFERROR(VLOOKUP(A17,[3]BalanceSheet!A$8:B$154,2,0),0) -> 27305293 | K17: 10
A18: 101 - Dummy USD [UK] | B18: 0 | C18: 0 | D18: 0 | E18: 0 | F18: 0 | G18: -0.01 | H18: 0 | I18: 0 | J18: =+IFERROR(VLOOKUP(A18,[3]BalanceSheet!A$8:B$154,2,0),0) -> 0
A19: 10100 - Cash and Cash Equivalent (WIR-IL) | J19: =+IFERROR(VLOOKUP(A19,[3]BalanceSheet!A$8:B$154,2,0),0) -> 0
A20: 10101 - Bank Hapoalim 120720 NIS | B20: 0 | C20: 0 | D20: 0 | E20: 21.81 | F20: 0 | G20: 0 | H20: 0 | I20: 0 | J20: =+IFERROR(VLOOKUP(A20,[3]BalanceSheet!A$8:B$154,2,0),0) -> 156.37
A21: Total - 10100 - Cash and Cash Equivalent (WIR-IL) | B21: =SUM(B20) -> 0 | C21: =SUM(C20) -> 0 | D21: =SUM(D20) -> 0 | E21: =SUM(E20) -> 21.81 | F21: =SUM(F20) -> 0 | G21: =SUM(G20) -> 0 | H21: =SUM(H20) -> 0 | I21: =SUM(I20) -> 0 | J21: =+IFERROR(VLOOKUP(A21,[3]BalanceSheet!A$8:B$154,2,0),0) -> 156.37 | K21: 10
A22: 10200 - Cash and Cash Equivalent (WSF-IL) | J22: =+IFERROR(VLOOKUP(A22,[3]BalanceSheet!A$8:B$154,2,0),0) -> 0
A23: 10201 - Bank Hapoalim 120729 NIS | B23: 0 | C23: 0 | D23: 0 | E23: 0 | F23: 124.45 | G23: 0 | H23: 0 | I23: 0 | J23: =+IFERROR(VLOOKUP(A23,[3]BalanceSheet!A$8:B$154,2,0),0) -> 422.32
A24: 10202 - Bank Hapoalim 120729 USD | B24: 0 | C24: 0 | D24: 0 | E24: 0 | F24: 24.67 | G24: 0 | H24: 0 | I24: 0 | J24: =+IFERROR(VLOOKUP(A24,[3]BalanceSheet!A$8:B$154,2,0),0) -> 24.67
A25: 10203 - Bank Hapoalim 120729 EUR | B25: 0 | C25: 0 | D25: 0 | E25: 0 | F25: 327.43 | G25: 0 | H25: 0 | I25: 0 | J25: =+IFERROR(VLOOKUP(A25,[3]BalanceSheet!A$8:B$154,2,0),0) -> 346.29
A26: Total - 10200 - Cash and Cash Equivalent (WSF-IL) | B26: =SUM(B23:B25) -> 0 | C26: =SUM(C23:C25) -> 0 | D26: =SUM(D23:D25) -> 0 | E26: =SUM(E23:E25) -> 0 | F26: =SUM(F23:F25) -> 476.55 | G26: =SUM(G23:G25) -> 0 | H26: =SUM(H23:H25) -> 0 | I26: =SUM(I23:I25) -> 0 | J26: =+IFERROR(VLOOKUP(A26,[3]BalanceSheet!A$8:B$154,2,0),0) -> 793.28 | K26: 10
A27: 10300 - Cash and Cash Equivalent (WEQD-IL) | J27: =+IFERROR(VLOOKUP(A27,[3]BalanceSheet!A$8:B$154,2,0),0) -> 0
A28: 10301 - Bank Hapoalim 120702 NIS | B28: 0 | C28: 0 | D28: -3.42 | E28: 0 | F28: 0 | G28: 0 | H28: 0 | I28: 0 | J28: =+IFERROR(VLOOKUP(A28,[3]BalanceSheet!A$8:B$154,2,0),0) -> 3.88
A29: 10302 - Bank Hapoalim 120702 USD | B29: 0 | C29: 0 | D29: 6438.02 | E29: 0 | F29: 0 | G29: 0 | H29: 0 | I29: 0 | J29: =+IFERROR(VLOOKUP(A29,[3]BalanceSheet!A$8:B$154,2,0),0) -> 6563.41
A30: Total - 10300 - Cash and Cash Equivalent (WEQD-IL) | B30: =SUM(B28:B29) -> 0 | C30: =SUM(C28:C29) -> 0 | D30: =SUM(D28:D29) -> 6434.6 | E30: =SUM(E28:E29) -> 0 | F30: =SUM(F28:F29) -> 0 | G30: =SUM(G28:G29) -> 0 | H30: =SUM(H28:H29) -> 0 | I30: =SUM(I28:I29) -> 0 | J30: =+IFERROR(VLOOKUP(A30,[3]BalanceSheet!A$8:B$154,2,0),0) -> 6567.29 | K30: 10
A31: 10400 - Cash and Cash Equivalent (WSF-UK) | J31: =+IFERROR(VLOOKUP(A31,[3]BalanceSheet!A$8:B$154,2,0),0) -> 0
A32: 10401 - Bank Netwest 27557405 GBP | B32: 0 | C32: 0 | D32: 0 | E32: 0 | F32: 0 | G32: 671354.25 | H32: 0 | I32: 0 | J32: =+IFERROR(VLOOKUP(A32,[3]BalanceSheet!A$8:B$154,2,0),0) -> 25648.28
A33: Total - 10400 - Cash and Cash Equivalent (WSF-UK) | B33: =SUM(B32) -> 0 | C33: =SUM(C32) -> 0 | D33: =SUM(D32) -> 0 | E33: =SUM(E32) -> 0 | F33: =SUM(F32) -> 0 | G33: =SUM(G32) -> 671354.25 | H33: =SUM(H32) -> 0 | I33: =SUM(I32) -> 0 | J33: =+IFERROR(VLOOKUP(A33,[3]BalanceSheet!A$8:B$154,2,0),0) -> 25648.28 | K33: 10
A34: 10500 - Cash and Cash Equivalent (WTSE-FR) | J34: =+IFERROR(VLOOKUP(A34,[3]BalanceSheet!A$8:B$154,2,0),0) -> 0
A35: 10501 - Bank SG 20020671 EUR | B35: 0 | C35: 0 | D35: 0 | E35: 0 | F35: 0 | G35: 0 | H35: 0 | I35: 294780.88 | J35: =+IFERROR(VLOOKUP(A35,[3]BalanceSheet!A$8:B$154,2,0),0) -> 49912.93
A36: Total - 10500 - Cash and Cash Equivalent (WTSE-FR) | B36: =SUM(B35) -> 0 | C36: =SUM(C35) -> 0 | D36: =SUM(D35) -> 0 | E36: =SUM(E35) -> 0 | F36: =SUM(F35) -> 0 | G36: =SUM(G35) -> 0 | H36: =SUM(H35) -> 0 | I36: =SUM(I35) -> 294780.88 | J36: =+IFERROR(VLOOKUP(A36,[3]BalanceSheet!A$8:B$154,2,0),0) -> 49912.93 | K36: 10
A37: 10600 - Cash and Cash Equivalent (WUS-US) | J37: =+IFERROR(VLOOKUP(A37,[3]BalanceSheet!A$8:B$154,2,0),0) -> 0
A38: 10601 - Bank Hapoalim 542 Saving USD | B38: 0 | C38: 180344.74 | D38: 0 | E38: 0 | F38: 0 | G38: 0 | H38: 0 | I38: 0 | J38: =+IFERROR(VLOOKUP(A38,[3]BalanceSheet!A$8:B$154,2,0),0) -> 0
A39: 10602 - Bank Hapoalim 0700 Checking USD | B39: 0 | C39: 42295.73 | D39: 0 | E39: 0 | F39: 0 | G39: 0 | H39: 0 | I39: 0 | J39: =+IFERROR(VLOOKUP(A39,[3]BalanceSheet!A$8:B$154,2,0),0) -> 0
A40: Total - 10600 - Cash and Cash Equivalent (WUS-US) | B40: =SUM(B38:B39) -> 0 | C40: =SUM(C38:C39) -> 222640.47 | D40: =SUM(D38:D39) -> 0 | E40: =SUM(E38:E39) -> 0 | F40: =SUM(F38:F39) -> 0 | G40: =SUM(G38:G39) -> 0 | H40: =SUM(H38:H39) -> 0 | I40: =SUM(I38:I39) -> 0 | J40: =+IFERROR(VLOOKUP(A40,[3]BalanceSheet!A$8:B$154,2,0),0) -> 0 | K40: 10
A41: 11000 - Short-term Restricted cash | J41: =+IFERROR(VLOOKUP(A41,[3]BalanceSheet!A$8:B$154,2,0),0) -> 0
A42: 11001 - Bank Hapoalim Deposit NIS | B42: 0 | C42: 0 | D42: 0 | E42: 0 | F42: 0 | G42: 0 | H42: 17071.92 | I42: 0 | J42: =+IFERROR(VLOOKUP(A42,[3]BalanceSheet!A$8:B$154,2,0),0) -> 19293.46
A43: 11002 - Bank FIBI Deposit NIS | B43: 0 | C43: 0 | D43: 0 | E43: 0 | F43: 0 | G43: 0 | H43: 2845.19 | I43: 0 | J43: =+IFERROR(VLOOKUP(A43,[3]BalanceSheet!A$8:B$154,2,0),0) -> 3215.43
A44: 11003 - Bank FIBI Deposit EUR | B44: 0 | C44: 0 | D44: 0 | E44: 0 | F44: 0 | G44: 0 | H44: 8090.49 | I44: 0 | J44: =+IFERROR(VLOOKUP(A44,[3]BalanceSheet!A$8:B$154,2,0),0) -> 8556.41
A45: Total - 11000 - Short-term Restricted cash | B45: =SUM(B42:B44) -> 0 | C45: =SUM(C42:C44) -> 0 | D45: =SUM(D42:D44) -> 0 | E45: =SUM(E42:E44) -> 0 | F45: =SUM(F42:F44) -> 0 | G45: =SUM(G42:G44) -> 0 | H45: =SUM(H42:H44) -> 28007.6 | I45: =SUM(I42:I44) -> 0 | J45: =+IFERROR(VLOOKUP(A45,[3]BalanceSheet!A$8:B$154,2,0),0) -> 31065.3 | K45: 11
A46: 11100 - Short term Bank Deposit | J46: =+IFERROR(VLOOKUP(A46,[3]BalanceSheet!A$8:B$154,2,0),0) -> 0
A47: 11101 - Short term Bank Deposit [BANK HAPOALIM] | B47: 0 | C47: 0 | D47: 0 | E47: 0 | F47: 0 | G47: 0 | H47: 11135351 | I47: 0 | J47: =+IFERROR(VLOOKUP(A47,[3]BalanceSheet!A$8:B$154,2,0),0) -> 0 | K47: 11
A48: Total - 11100 - Short term Bank Deposit | B48: =SUM(B47) -> 0 | C48: =SUM(C47) -> 0 | D48: =SUM(D47) -> 0 | E48: =SUM(E47) -> 0 | F48: =SUM(F47) -> 0 | G48: =SUM(G47) -> 0 | H48: =SUM(H47) -> 11135351 | I48: =SUM(I47) -> 0 | J48: =+IFERROR(VLOOKUP(A48,[3]BalanceSheet!A$8:B$154,2,0),0) -> 0
A49: Total Bank | B49: =SUM(B17:B18,B21,B26,B30,B33,B36,B40,B45,B48) -> 0 | C49: =SUM(C17:C18,C21,C26,C30,C33,C36,C40,C45,C48) -> 222640.47 | D49: =SUM(D17:D18,D21,D26,D30,D33,D36,D40,D45,D48) -> 6434.6 | E49: =SUM(E17:E18,E21,E26,E30,E33,E36,E40,E45,E48) -> 21.81 | F49: =SUM(F17:F18,F21,F26,F30,F33,F36,F40,F45,F48) -> 476.55 | G49: =SUM(G17:G18,G21,G26,G30,G33,G36,G40,G45,G48) -> 671354.24 | H49: =SUM(H17:H18,H21,H26,H30,H33,H36,H40,H45,H48) -> 17611821 | I49: =SUM(I17:I18,I21,I26,I30,I33,I36,I40,I45,I48) -> 294780.88 | J49: =+IFERROR(VLOOKUP(A49,[3]BalanceSheet!A$8:B$154,2,0),0) -> 27419436
A50: Accounts Receivable | J50: =+IFERROR(VLOOKUP(A50,[3]BalanceSheet!A$8:B$154,2,0),0) -> 0
A51: 12000 - Accounts Receivable | J51: =+IFERROR(VLOOKUP(A51,[3]BalanceSheet!A$8:B$154,2,0),0) -> 0
A52: 12001 - Accounts Receivable | B52: 0 | C52: 0 | D52: 0 | E52: 0 | F52: 0 | G52: 0 | H52: 1631201.2 | I52: 0 | J52: =+IFERROR(VLOOKUP(A52,[3]BalanceSheet!A$8:B$154,2,0),0) -> 867787
A53: 12002 - Accounts Receivable - Customers offset | B53: 0 | C53: 0 | D53: 0 | E53: 0 | F53: 0 | G53: 0 | H53: -20670 | I53: 0 | J53: =+IFERROR(VLOOKUP(A53,[3]BalanceSheet!A$8:B$154,2,0),0) -> -43969.38
A54: Total - 12000 - Accounts Receivable | B54: =SUM(B52:B53) -> 0 | C54: =SUM(C52:C53) -> 0 | D54: =SUM(D52:D53) -> 0 | E54: =SUM(E52:E53) -> 0 | F54: =SUM(F52:F53) -> 0 | G54: =SUM(G52:G53) -> 0 | H54: =SUM(H52:H53) -> 1610531.2 | I54: =SUM(I52:I53) -> 0 | J54: =+IFERROR(VLOOKUP(A54,[3]BalanceSheet!A$8:B$154,2,0),0) -> 823817.62 | K54: 12.1
A55: 12500 - Intercompany (Receviable) | J55: =+IFERROR(VLOOKUP(A55,[3]BalanceSheet!A$8:B$154,2,0),0) -> 0
A56: 12502 - WeMatch.Live Tech Support Europe | B56: -28375.56 | C56: 0 | D56: 0 | E56: 0 | F56: 0 | G56: 0 | H56: 0 | I56: 28375.56 | J56: =+IFERROR(VLOOKUP(A56,[3]BalanceSheet!A$8:B$154,2,0),0) -> 0
A57: Total - 12500 - Intercompany (Receviable) | B57: =SUM(B56) -> -28375.56 | C57: =SUM(C56) -> 0 | D57: =SUM(D56) -> 0 | E57: =SUM(E56) -> 0 | F57: =SUM(F56) -> 0 | G57: =SUM(G56) -> 0 | H57: =SUM(H56) -> 0 | I57: =SUM(I56) -> 28375.56 | J57: =+IFERROR(VLOOKUP(A57,[3]BalanceSheet!A$8:B$154,2,0),0) -> 0 | K57: 12.1
A58: Total Accounts Receivable | B58: =SUM(B54,B57) -> -28375.56 | C58: =SUM(C54,C57) -> 0 | D58: =SUM(D54,D57) -> 0 | E58: =SUM(E54,E57) -> 0 | F58: =SUM(F54,F57) -> 0 | G58: =SUM(G54,G57) -> 0 | H58: =SUM(H54,H57) -> 1610531.2 | I58: =SUM(I54,I57) -> 28375.56 | J58: =+IFERROR(VLOOKUP(A58,[3]BalanceSheet!A$8:B$154,2,0),0) -> 823817.62 | K58: 12
A59: Unbilled Receivable | J59: =+IFERROR(VLOOKUP(A59,[3]BalanceSheet!A$8:B$154,2,0),0) -> 0
A60: Unbilled Receivable | B60: 0 | C60: 0 | D60: 0 | E60: 0 | F60: 0 | G60: 0 | H60: 126335.77 | I60: 0 | J60: =+IFERROR(VLOOKUP(A60,[3]BalanceSheet!A$8:B$154,2,0),0) -> 0
A61: Total Unbilled Receivable | B61: =SUM(B60) -> 0 | C61: =SUM(C60) -> 0 | D61: =SUM(D60) -> 0 | E61: =SUM(E60) -> 0 | F61: =SUM(F60) -> 0 | G61: =SUM(G60) -> 0 | H61: =SUM(H60) -> 126335.77 | I61: =SUM(I60) -> 0 | J61: =+IFERROR(VLOOKUP(A61,[3]BalanceSheet!A$8:B$154,2,0),0) -> 0 | K61: 12
A62: Other Current Asset | J62: =+IFERROR(VLOOKUP(A62,[3]BalanceSheet!A$8:B$154,2,0),0) -> 0
A63: 12004 - Unbilled Revenue | B63: 0 | C63: 0 | D63: 0 | E63: 0 | F63: 0 | G63: 0 | H63: 327837.96 | I63: 0 | J63: =+IFERROR(VLOOKUP(A63,[3]BalanceSheet!A$8:B$154,2,0),0) -> 192570.33 | K63: 12
A64: 12600 - Intercompany (O.C Assets) | J64: =+IFERROR(VLOOKUP(A64,[3]BalanceSheet!A$8:B$154,2,0),0) -> 0
A65: 12601 - WeMatch.Securitiesfinancing Ltd. [P] | B65: -4619805.9 | C65: 0 | D65: 0 | E65: 0 | F65: 0 | G65: 2284953.2 | H65: 2334852.7 | I65: 0 | J65: =+IFERROR(VLOOKUP(A65,[3]BalanceSheet!A$8:B$154,2,0),0) -> 0
A66: 12602 - WeMatch.Live Tech Support Europe [P] | B66: -1664719.2 | C66: 0 | D66: 0 | E66: 0 | F66: 0 | G66: 0 | H66: 865505.1 | I66: 799214.12 | J66: =+IFERROR(VLOOKUP(A66,[3]BalanceSheet!A$8:B$154,2,0),0) -> 0
A67: 12603 - WeMatch Securities Financing Ltd. [P] | B67: -49169.73 | C67: 0 | D67: 0 | E67: 0 | F67: 48177.9 | G67: 0 | H67: 991.83 | I67: 0 | J67: =+IFERROR(VLOOKUP(A67,[3]BalanceSheet!A$8:B$154,2,0),0) -> 0
A68: 12605 - WeMatch EQD Ltd. [P] | B68: -4459 | C68: 0 | D68: 4459 | E68: 0 | F68: 0 | G68: 0 | H68: 0 | I68: 0 | J68: =+IFERROR(VLOOKUP(A68,[3]BalanceSheet!A$8:B$154,2,0),0) -> 0
A69: 12606 - Wematch.Support US INC [P] | B69: -1396757.1 | C69: 537445.42 | D69: 0 | E69: 0 | F69: 0 | G69: 15878.25 | H69: 843433.48 | I69: 0 | J69: =+IFERROR(VLOOKUP(A69,[3]BalanceSheet!A$8:B$154,2,0),0) -> 0
A70: Total - 12600 - Intercompany (O.C Assets) | B70: -7734911 | C70: 537445.42 | D70: 4459 | E70: 0 | F70: 48177.9 | G70: 2300831.5 | H70: 4044783.1 | I70: 799214.12 | J70: =+IFERROR(VLOOKUP(A70,[3]BalanceSheet!A$8:B$154,2,0),0) -> 0 | K70: 13
A71: 13000 - Prepaid Exp. | J71: =+IFERROR(VLOOKUP(A71,[3]BalanceSheet!A$8:B$154,2,0),0) -> 0
A72: 13001 - Prepaid Expenses | B72: 0 | C72: 143307.18 | D72: 0 | E72: 0 | F72: 0 | G72: 15354.25 | H72: 129071.74 | I72: 4547.06 | J72: =+IFERROR(VLOOKUP(A72,[3]BalanceSheet!A$8:B$154,2,0),0) -> 37005.61 | K72: 13.1
A73: 13002 - Prepaid rent | B73: 0 | C73: 0 | D73: 0 | E73: 0 | F73: 0 | G73: 11711.35 | H73: 0 | I73: 0 | J73: =+IFERROR(VLOOKUP(A73,[3]BalanceSheet!A$8:B$154,2,0),0) -> 0 | K73: 13.1
A74: 13003 - Deferred Customer acquisition cost | B74: 0 | C74: 0 | D74: 0 | E74: 0 | F74: 0 | G74: 0 | H74: 99340.48 | I74: 0 | J74: =+IFERROR(VLOOKUP(A74,[3]BalanceSheet!A$8:B$154,2,0),0) -> 0 | K74: 13.1
A75: Total - 13000 - Prepaid Exp. | B75: 0 | C75: 143307.18 | D75: 0 | E75: 0 | F75: 0 | G75: 27065.6 | H75: 228412.22 | I75: 4547.06 | J75: =+IFERROR(VLOOKUP(A75,[3]BalanceSheet!A$8:B$154,2,0),0) -> 37005.61 | K75: 13
A76: 13009 - Government Institutions | J76: =+IFERROR(VLOOKUP(A76,[3]BalanceSheet!A$8:B$154,2,0),0) -> 0
A77: 13100 - VAT Assets | J77: =+IFERROR(VLOOKUP(A77,[3]BalanceSheet!A$8:B$154,2,0),0) -> 0
A78: 13101 - VAT on FA Purchases IL | B78: 0 | C78: 0 | D78: 0 | E78: 0 | F78: 0 | G78: 0 | H78: -84.05 | I78: 0 | J78: =+IFERROR(VLOOKUP(A78,[3]BalanceSheet!A$8:B$154,2,0),0) -> 0
A79: 13102 - VAT on Purchases IL | B79: 0 | C79: 0 | D79: 0 | E79: 0 | F79: 0 | G79: 0 | H79: 655.96 | I79: 0 | J79: =+IFERROR(VLOOKUP(A79,[3]BalanceSheet!A$8:B$154,2,0),0) -> 32.8
A80: 13103 - VAT Proforma IL | B80: 0 | C80: 0 | D80: 0 | E80: 0 | F80: 0 | G80: 0 | H80: 3165.33 | I80: 0 | J80: =+IFERROR(VLOOKUP(A80,[3]BalanceSheet!A$8:B$154,2,0),0) -> 80072.82
A81: 13107 - VAT D/C | B81: 0 | C81: 0 | D81: 0 | E81: 0 | F81: 0 | G81: 0 | H81: 31238.41 | I81: 0 | J81: =+IFERROR(VLOOKUP(A81,[3]BalanceSheet!A$8:B$154,2,0),0) -> 0
A82: 13122 - VAT on FA Purchases FR | B82: 0 | C82: 0 | D82: 0 | E82: 0 | F82: 0 | G82: 0 | H82: 0 | I82: 5870.77 | J82: =+IFERROR(VLOOKUP(A82,[3]BalanceSheet!A$8:B$154,2,0),0) -> 5870.77
A83: 13123 - VAT on Purchases FR | B83: 0 | C83: 0 | D83: 0 | E83: 0 | F83: 0 | G83: 0 | H83: 0 | I83: 38437.97 | J83: =+IFERROR(VLOOKUP(A83,[3]BalanceSheet!A$8:B$154,2,0),0) -> 11696.16
A84: 13124 - VAT deductible on goods and services | B84: 0 | C84: 0 | D84: 0 | E84: 0 | F84: 0 | G84: 0 | H84: 0 | I84: 848.64 | J84: =+IFERROR(VLOOKUP(A84,[3]BalanceSheet!A$8:B$154,2,0),0) -> 899.79
A85: 13202 - VAT on Purchases UK | B85: 0 | C85: 0 | D85: 0 | E85: 0 | F85: 0 | G85: 39429.68 | H85: 0 | I85: 0 | J85: =+IFERROR(VLOOKUP(A85,[3]BalanceSheet!A$8:B$154,2,0),0) -> 0
A86: Total - 13100 - VAT Assets | B86: 0 | C86: 0 | D86: 0 | E86: 0 | F86: 0 | G86: 39429.68 | H86: 34975.65 | I86: 45157.38 | J86: =+IFERROR(VLOOKUP(A86,[3]BalanceSheet!A$8:B$154,2,0),0) -> 98572.34 | K86: 13.2
A87: 13300 - TAX Assets | J87: =+IFERROR(VLOOKUP(A87,[3]BalanceSheet!A$8:B$154,2,0),0) -> 0
A88: 13301 - Advances for Odfot | B88: 0 | C88: 0 | D88: 0 | E88: 0 | F88: 0 | G88: 0 | H88: 17204.02 | I88: 0 | J88: =+IFERROR(VLOOKUP(A88,[3]BalanceSheet!A$8:B$154,2,0),0) -> 17204.02
A89: 13302 - Reversal for Exceed expenses | B89: 0 | C89: 0 | D89: 0 | E89: 0 | F89: 0 | G89: 0 | H89: -17204.02 | I89: 0 | J89: =+IFERROR(VLOOKUP(A89,[3]BalanceSheet!A$8:B$154,2,0),0) -> -17204.02
A90: 13303 - Tax Benefits | B90: 0 | C90: 0 | D90: -447.84 | E90: 0 | F90: 0 | G90: 0 | H90: 0 | I90: 75511.06 | J90: =+IFERROR(VLOOKUP(A90,[3]BalanceSheet!A$8:B$154,2,0),0) -> 76473.19
A91: 13304 - Other current tax asset | B91: 0 | C91: 0 | D91: 0 | E91: 0 | F91: 0 | G91: 3267.88 | H91: 0 | I91: 0 | J91: =+IFERROR(VLOOKUP(A91,[3]BalanceSheet!A$8:B$154,2,0),0) -> 3267.88
A92: Total - 13300 - TAX Assets | B92: 0 | C92: 0 | D92: -447.84 | E92: 0 | F92: 0 | G92: 3267.88 | H92: 0 | I92: 75511.06 | J92: =+IFERROR(VLOOKUP(A92,[3]BalanceSheet!A$8:B$154,2,0),0) -> 79741.07 | K92: 13.2
A93: Total - 13009 - Government Institutions | B93: 0 | C93: 0 | D93: -447.84 | E93: 0 | F93: 0 | G93: 42697.56 | H93: 34975.65 | I93: 120668.44 | J93: =+IFERROR(VLOOKUP(A93,[3]BalanceSheet!A$8:B$154,2,0),0) -> 178313.41 | K93: 13
A94: 16000 - Other Current Asset | J94: =+IFERROR(VLOOKUP(A94,[3]BalanceSheet!A$8:B$154,2,0),0) -> 0
A95: 16001 - Rent deposit | B95: 0 | C95: 36775 | D95: 0 | E95: 0 | F95: 0 | G95: 68850.34 | H95: 37820.53 | I95: 14750.69 | J95: =+IFERROR(VLOOKUP(A95,[3]BalanceSheet!A$8:B$154,2,0),0) -> 36888.95 | K95: 13.3
A96: 16002 - Other Deposits | B96: 0 | C96: 0 | D96: 0 | E96: 0 | F96: 0 | G96: 0 | H96: 11921 | I96: 0 | J96: =+IFERROR(VLOOKUP(A96,[3]BalanceSheet!A$8:B$154,2,0),0) -> 0 | K96: 13.3
A97: Total - 16000 - Other Current Asset | B97: 0 | C97: 36775 | D97: 0 | E97: 0 | F97: 0 | G97: 68850.34 | H97: 49741.53 | I97: 14750.69 | J97: =+IFERROR(VLOOKUP(A97,[3]BalanceSheet!A$8:B$154,2,0),0) -> 36888.95 | K97: 13
A98: 16100 - other current asset | B98: 0 | C98: 0 | D98: 117.88 | E98: 491.94 | F98: 83.92 | G98: 0 | H98: 26.53 | I98: 0 | J98: =+IFERROR(VLOOKUP(A98,[3]BalanceSheet!A$8:B$154,2,0),0) -> 693.74 | K98: 13 | L98: 13.3
A99: 17000 - Other long term assets | J99: =+IFERROR(VLOOKUP(A99,[3]BalanceSheet!A$8:B$154,2,0),0) -> 0
A100: 17001 - Interco Loans | B100: -261263.83 | C100: 0 | D100: 0 | E100: 0 | F100: 0 | G100: 0 | H100: 261263.83 | I100: 0 | J100: =+IFERROR(VLOOKUP(A100,[3]BalanceSheet!A$8:B$154,2,0),0) -> 0
A101: 17002 - Employee Loans | B101: 0 | C101: 0 | D101: 37427.66 | E101: 0 | F101: 0 | G101: 0 | H101: 0 | I101: 0 | J101: =+IFERROR(VLOOKUP(A101,[3]BalanceSheet!A$8:B$154,2,0),0) -> 37427.66
A102: Total - 17000 - Other long term assets | B102: -261263.83 | C102: 0 | D102: 37427.66 | E102: 0 | F102: 0 | G102: 0 | H102: 261263.83 | I102: 0 | J102: =+IFERROR(VLOOKUP(A102,[3]BalanceSheet!A$8:B$154,2,0),0) -> 37427.66 | K102: 14
...
