Workbook
Name \A: '[1]טורים 98'!$HJ$133
Name \A: '[2]טורים 98'!$HJ$133
Name \B: #REF!
Name \B: #REF!
Name \B: #REF!
Name \C: '[1]טורים 98'!$HJ$154
Name \C: '[2]טורים 98'!$HJ$154
Name \D: '[2]טורים 98'!#REF!
Name \D: '[1]טורים 98'!#REF!
Name \D: '[2]טורים 98'!#REF!
Name \E: '[1]טורים 98'!$HJ$155
Name \E: '[2]טורים 98'!$HJ$155
Name \F: '[1]טורים 98'!$GS$2
Name \F: '[2]טורים 98'!$GS$2
Name \H: '[1]טורים 98'!$B$336
Name \H: '[2]טורים 98'!$B$336
Name \J: '[1]טורים 98'!$HJ$164
Name \J: '[2]טורים 98'!$HJ$164
Name \K: '[1]טורים 98'!$HJ$166
Name \K: '[2]טורים 98'!$HJ$166
Name \L: '[1]טורים 98'!$HJ$124
Name \L: '[2]טורים 98'!$HJ$124
Name \M: '[1]טורים 98'!$HJ$121
Name \M: '[2]טורים 98'!$HJ$121
Name \O: '[1]טורים 98'!$HJ$144
Name \O: '[2]טורים 98'!$HJ$144
Name \P: '[1]טורים 98'!$GT$13
Name \P: '[2]טורים 98'!$GT$13
Name \Q: '[1]טורים 98'!$HJ$127
Name \Q: '[2]טורים 98'!$HJ$127
Name \R: '[1]טורים 98'!$HJ$118
Name \R: '[2]טורים 98'!$HJ$118
Name \S: '[1]טורים 98'!$HJ$151
Name \S: '[2]טורים 98'!$HJ$151
Name \U: '[1]טורים 98'!$HJ$116
Name \U: '[2]טורים 98'!$HJ$116
Name \W: '[1]טורים 98'!$HJ$113
Name \W: '[2]טורים 98'!$HJ$113
Name \X: '[1]טורים 98'!$HJ$146
Name \X: '[2]טורים 98'!$HJ$146
Name \Y: '[1]טורים 98'!$GT$6
Name \Y: '[2]טורים 98'!$GT$6
Name \Z: '[1]טורים 98'!$HJ$129
Name \Z: '[2]טורים 98'!$HJ$129
Name _______DAT1: #REF!
Name _______DAT1: #REF!
Name _______DAT1: #REF!
Name _______DAT10: #REF!
Name _______DAT10: #REF!
Name _______DAT10: #REF!
Name _______DAT11: #REF!
Name _______DAT11: #REF!
Name _______DAT11: #REF!
Name _______DAT12: #REF!
Name _______DAT12: #REF!
Name _______DAT12: #REF!
Name _______DAT13: #REF!
Name _______DAT13: #REF!
Name _______DAT13: #REF!
Name _______DAT14: #REF!

Sheet 2021
C2: 2021
C3: Treeverse Ltd | D3: Treeverse Inc | E3: Cons | G3: Treeverse Ltd
C4: USD | G4: NIS
A5: 10 | B5: Cash | C5: =SUMIF('TB LTD 2021'!A:A,'2021'!A5,'TB LTD 2021'!I:I) -> 954502.98 | D5: =SUMIF('TB INC'!A:A,'2021'!A5,'TB INC'!F:F) -> 17264660 | E5: =C5+D5 -> 18219163 | G5: =SUMIF('TB LTD 2021'!A:A,'2021'!A5,'TB LTD 2021'!F:F) -> 2968504.3 | I5: =G5/C5 -> 3.11
A6: 11 | B6: Restricted Cash | C6: =SUMIF('TB LTD 2021'!A:A,'2021'!A6,'TB LTD 2021'!I:I) -> 32165.01 | D6: =SUMIF('TB INC'!A:A,'2021'!A6,'TB INC'!F:F) -> 0 | E6: =C6+D6 -> 32165.01 | G6: =SUMIF('TB LTD 2021'!A:A,'2021'!A6,'TB LTD 2021'!D:D) -> 100033.18 | I6: =G6/C6 -> 3.11
A7: 12 | B7: Accounts Receivable | C7: =SUMIF('TB LTD 2021'!A:A,'2021'!A7,'TB LTD 2021'!I:I) -> 0 | D7: =SUMIF('TB INC'!A:A,'2021'!A7,'TB INC'!F:F) -> 0 | E7: =C7+D7 -> 0 | G7: =SUMIF('TB LTD 2021'!A:A,'2021'!A7,'TB LTD 2021'!D:D) -> 0
A8: 13 | B8: prepaid expenses | C8: =SUMIF('TB LTD 2021'!A:A,'2021'!A8,'TB LTD 2021'!I:I) -> 7516.82 | D8: =SUMIF('TB INC'!A:A,'2021'!A8,'TB INC'!F:F) -> 9166.67 | E8: =C8+D8 -> 16683.49 | G8: =SUMIF('TB LTD 2021'!A:A,'2021'!A8,'TB LTD 2021'!F:F) -> 24476.7 | I8: =G8/C8 -> 3.2562573
A9: 14 | B9: Other current assets | C9: =SUMIF('TB LTD 2021'!A:A,'2021'!A9,'TB LTD 2021'!I:I) -> 42827.32 | D9: =SUMIF('TB INC'!A:A,'2021'!A9,'TB INC'!F:F) -> 1000 | E9: =C9+D9 -> 43827.32 | G9: =SUMIF('TB LTD 2021'!A:A,'2021'!A9,'TB LTD 2021'!F:F) -> 133234.8 | I9: =G9/C9 -> 3.1109768
A10: 27 | B10: Fixed assets - Cost | C10: =SUMIF('TB LTD 2021'!A:A,'2021'!A10,'TB LTD 2021'!I:I) -> 212051.74 | D10: =SUMIF('TB INC'!A:A,'2021'!A10,'TB INC'!F:F) -> 2151.26 | E10: =C10+D10 -> 214203 | G10: =SUMIF('TB LTD 2021'!A:A,'2021'!A10,'TB LTD 2021'!F:F) -> 684157.79 | I10: =G10/C10 -> 3.226372
A11: 28 | B11: Fixed assets - Accumulated Depreciation | C11: =SUMIF('TB LTD 2021'!A:A,'2021'!A11,'TB LTD 2021'!I:I) -> -22802.5 | D11: =SUMIF('TB INC'!A:A,'2021'!A11,'TB INC'!F:F) -> -537.84 | E11: =C11+D11 -> -23340.34 | G11: =SUMIF('TB LTD 2021'!A:A,'2021'!A11,'TB LTD 2021'!F:F) -> -78512.75 | I11: =G11/C11 -> 3.4431641
A12: 29 | B12: Long term deposits | C12: =SUMIF('TB LTD 2021'!A:A,'2021'!A12,'TB LTD 2021'!I:I) -> 0 | D12: =SUMIF('TB INC'!A:A,'2021'!A12,'TB INC'!F:F) -> 0 | E12: =C12+D12 -> 0 | G12: =SUMIF('TB LTD 2021'!A:A,'2021'!A12,'TB LTD 2021'!D:D) -> 0
C13: =SUM(C5:C12) -> 1226261.4 | D13: =SUM(D5:D12) -> 17276440 | E13: =C13+D13 -> 18502701 | G13: =SUM(G5:G12) -> 3831894 | I13: =G13/C13 -> 3.1248591
A15: 31 | B15: Trade payables | C15: =SUMIF('TB LTD 2021'!A:A,'2021'!A15,'TB LTD 2021'!I:I) -> -51470.63 | D15: =SUMIF('TB INC'!A:A,'2021'!A15,'TB INC'!F:F) -> -3196.59 | E15: =C15+D15 -> -54667.22 | G15: =SUMIF('TB LTD 2021'!A:A,'2021'!A15,'TB LTD 2021'!F:F) -> 21521.96 | I15: =G15/C15 -> -0.4181406
A16: 32 | B16: Accrued expenses | C16: =SUMIF('TB LTD 2021'!A:A,'2021'!A16,'TB LTD 2021'!I:I) -> -19628.74 | D16: =SUMIF('TB INC'!A:A,'2021'!A16,'TB INC'!F:F) -> -10458.64 | E16: =C16+D16 -> -30087.38 | G16: =SUMIF('TB LTD 2021'!A:A,'2021'!A16,'TB LTD 2021'!F:F) -> -247344.38 | I16: =G16/C16 -> 12.601134
A17: 33 | B17: Employees and payroll accruals | C17: =SUMIF('TB LTD 2021'!A:A,'2021'!A17,'TB LTD 2021'!I:I) -> -142655.32 | D17: =SUMIF('TB INC'!A:A,'2021'!A17,'TB INC'!F:F) -> 0 | E17: =C17+D17 -> -142655.32 | G17: =SUMIF('TB LTD 2021'!A:A,'2021'!A17,'TB LTD 2021'!F:F) -> -443776.38 | I17: =G17/C17 -> 3.1108295
A18: 34 | B18: Employee institution | C18: =SUMIF('TB LTD 2021'!A:A,'2021'!A18,'TB LTD 2021'!I:I) -> -99386.71 | D18: =SUMIF('TB INC'!A:A,'2021'!A18,'TB INC'!F:F) -> 0 | E18: =C18+D18 -> -99386.71 | G18: =SUMIF('TB LTD 2021'!A:A,'2021'!A18,'TB LTD 2021'!F:F) -> -309092.68 | I18: =G18/C18 -> 3.1100001
A19: 35 | B19: Other current liabilities | C19: =SUMIF('TB LTD 2021'!A:A,'2021'!A19,'TB LTD 2021'!I:I) -> 0 | D19: =SUMIF('TB INC'!A:A,'2021'!A19,'TB INC'!F:F) -> 0 | E19: =C19+D19 -> 0 | G19: =SUMIF('TB LTD 2021'!A:A,'2021'!A19,'TB LTD 2021'!F:F) -> 0
A20: 36 | B20: Intercompany | C20: =SUMIF('TB LTD 2021'!A:A,'2021'!A20,'TB LTD 2021'!I:I) -> -4886951.9 | D20: =SUMIF('TB INC'!A:A,'2021'!A20,'TB INC'!F:F) -> 4886951.6 | E20: =C20+D20 -> -0.31 | G20: =SUMIF('TB LTD 2021'!A:A,'2021'!A20,'TB LTD 2021'!F:F) -> -16198518 | I20: =G20/C20 -> 3.3146464
A21: 37 | B21: Long term provisions | C21: =SUMIF('TB LTD 2021'!A:A,'2021'!A21,'TB LTD 2021'!I:I) -> 0 | D21: =SUMIF('TB INC'!A:A,'2021'!A21,'TB INC'!F:F) -> 0 | E21: =C21+D21 -> 0 | G21: =SUMIF('TB LTD 2021'!A:A,'2021'!A21,'TB LTD 2021'!F:F) -> 0
A22: 40 | B22: Ordinary shares | C22: =SUMIF('TB LTD 2021'!A:A,'2021'!A22,'TB LTD 2021'!I:I) -> 0 | D22: =SUMIF('TB INC'!A:A,'2021'!A22,'TB INC'!F:F) -> -20105 | E22: =C22+D22 -> -20105
A23: 42 | B23: Seed Round shares | C23: =SUMIF('TB LTD 2021'!A:A,'2021'!A23,'TB LTD 2021'!I:I) -> 0 | D23: =SUMIF('TB INC'!A:A,'2021'!A23,'TB INC'!F:F) -> -16000 | E23: =C23+D23 -> -16000
A24: 43 | B24: Preferred A shares | C24: =SUMIF('TB LTD 2021'!A:A,'2021'!A22,'TB LTD 2021'!I:I) -> 0 | D24: =SUMIF('TB INC'!A:A,'2021'!A24,'TB INC'!F:F) -> -10363.64 | E24: =C24+D24 -> -10363.64 | G24: =SUMIF('TB LTD 2021'!A:A,'2021'!A22,'TB LTD 2021'!F:F) -> 0
A25: 41 | B25: Additional paid in capital | C25: =SUMIF('TB LTD 2021'!A:A,'2021'!A25,'TB LTD 2021'!I:I) -> 0 | D25: =SUMIF('TB INC'!A:A,'2021'!A25,'TB INC'!F:F) -> -22214001 | E25: =C25+D25 -> -22214001 | G25: =SUMIF('TB LTD 2021'!A:A,'2021'!A25,'TB LTD 2021'!F:F) -> 0
A26: 44 | B26: Issuance costs | C26: =SUMIF('TB LTD 2021'!A:A,'2021'!A26,'TB LTD 2021'!I:I) -> 0 | D26: =SUMIF('TB INC'!A:A,'2021'!A26,'TB INC'!F:F) -> 208091.78 | E26: =C26+D26 -> 208091.78 | G26: =SUMIF('TB LTD 2021'!A:A,'2021'!A26,'TB LTD 2021'!F:F) -> 0 | I26: =G26/C26 -> #DIV/0!
A27: 46 | B27: Option fund | C27: =SUMIF('TB LTD 2021'!A:A,'2021'!A27,'TB LTD 2021'!I:I) -> 0 | D27: =SUMIF('TB INC'!A:A,'2021'!A27,'TB INC'!F:F) -> -73733.428 | E27: =C27+D27 -> -73733.428 | G27: =SUMIF('TB LTD 2021'!A:A,'2021'!A27,'TB LTD 2021'!F:F) -> 0
A28: 47 | B28: Repurchaseable shares fund | C28: =SUMIF('TB LTD 2021'!A:A,'2021'!A28,'TB LTD 2021'!I:I) -> 0 | D28: =SUMIF('TB INC'!A:A,'2021'!A28,'TB INC'!F:F) -> 0 | E28: =C28+D28 -> 0 | G28: =SUMIF('TB LTD 2021'!A:A,'2021'!A28,'TB LTD 2021'!F:F) -> 0
A29: 48 | B29: Accumulated deficit | C29: =SUMIF('TB LTD 2021'!A:A,'2021'!A29,'TB LTD 2021'!I:I) -> 1249522.6 | D29: =SUMIF('TB INC'!A:A,'2021'!A29,'TB INC'!F:F) -> -1413.16 | E29: =C29+D29 -> 1248109.5 | G29: =SUMIF('TB LTD 2021'!A:A,'2021'!A29,'TB LTD 2021'!F:F) -> 4501657.5 | I29: =G29/C29 -> 3.6027019
B30: Profit (loss) - for the period | C30: =C43 -> 2724309.3 | D30: =D43 -> -22211.53 | E30: =C30+D30 -> 2702097.7 | G30: =G43 -> 8843657.6 | I30: =G30/C30 -> 3.2462018
C31: =SUM(C15:C30) -> -1226261.4 | D31: =SUM(D15:D30) -> -17276440 | E31: =C31+D31 -> -18502701 | G31: =SUM(G15:G30) -> -3831894 | I31: =G31/C31 -> 3.1248591
C32: =IF(ROUND(C31+C13,0)=0,"OK","CHECK") -> OK | D32: =IF(ROUND(D31+D13,0)=0,"OK","CHECK") -> OK | E32: =IF(ROUND(E31+E13,0)=0,"OK","CHECK") -> OK | G32: =IF(ROUND(G31+G13,0)=0,"OK","CHECK") -> OK
C34: =C13+C31 -> 0 | D34: =D13+D31 -> 0
A35: 51 | B35: Net Revenues | C35: =SUMIF('TB LTD 2021'!A:A,'2021'!A35,'TB LTD 2021'!I:I) -> 404004.92 | D35: =SUMIF('TB INC'!A:A,'2021'!A35,'TB INC'!F:F) -> -404004.92 | E35: =C35+D35 -> 0 | G35: =SUMIF('TB LTD 2021'!A:A,'2021'!A35,'TB LTD 2021'!F:F) -> 1279228.3 | I35: =G35/C35 -> 3.1663682
A36: 52 | B36: Cost of Goods | C36: =SUMIF('TB LTD 2021'!A:A,'2021'!A36,'TB LTD 2021'!I:I) -> 0 | D36: =SUMIF('TB INC'!A:A,'2021'!A36,'TB INC'!F:F) -> 0 | E36: =C36+D36 -> 0 | G36: =SUMIF('TB LTD 2021'!A:A,'2021'!A36,'TB LTD 2021'!F:F) -> 0
A37: 53 | B37: R&D expenses | C37: =SUMIF('TB LTD 2021'!A:A,'2021'!A37,'TB LTD 2021'!I:I) -> 1649671 | D37: =SUMIF('TB INC'!A:A,'2021'!A37,'TB INC'!F:F) -> 0 | E37: =C37+D37 -> 1649671 | G37: =SUMIF('TB LTD 2021'!A:A,'2021'!A37,'TB LTD 2021'!F:F) -> 5316284.8 | I37: =G37/C37 -> 3.2226334
A38: 54 | B38: Marketing expenses | C38: =SUMIF('TB LTD 2021'!A:A,'2021'!A38,'TB LTD 2021'!I:I) -> 236159.02 | D38: =SUMIF('TB INC'!A:A,'2021'!A38,'TB INC'!F:F) -> 210191.14 | E38: =C38+D38 -> 446350.16 | G38: =SUMIF('TB LTD 2021'!A:A,'2021'!A38,'TB LTD 2021'!F:F) -> 761002.14 | I38: =G38/C38 -> 3.222414
A39: 55 | B39: G&A expenses | C39: =SUMIF('TB LTD 2021'!A:A,'2021'!A39,'TB LTD 2021'!I:I) -> 459595.77 | D39: =SUMIF('TB INC'!A:A,'2021'!A39,'TB INC'!F:F) -> 157086.06 | E39: =C39+D39 -> 616681.83 | G39: =SUMIF('TB LTD 2021'!A:A,'2021'!A39,'TB LTD 2021'!F:F) -> 1479453.9 | I39: =G39/C39 -> 3.2190329
A40: 59 | B40: Sales expenses | C40: =SUMIF('TB LTD 2021'!A:A,'2021'!A40,'TB LTD 2021'!I:I) -> 0 | D40: =SUMIF('TB INC'!A:A,'2021'!A40,'TB INC'!F:F) -> 0 | E40: =C40+D40 -> 0 | G40: =SUMIF('TB LTD 2021'!A:A,'2021'!A40,'TB LTD 2021'!F:F) -> 0
A41: 56 | B41: Financial expenses | C41: =SUMIF('TB LTD 2021'!A:A,'2021'!A41,'TB LTD 2021'!I:I) -> -25121.44 | D41: =SUMIF('TB INC'!A:A,'2021'!A41,'TB INC'!F:F) -> 3437.09 | E41: =C41+D41 -> -21684.35 | G41: =SUMIF('TB LTD 2021'!A:A,'2021'!A41,'TB LTD 2021'!F:F) -> 7688.39 | I41: =G41/C41 -> -0.30604894
A42: 58 | B42: Income Tax | C42: =SUMIF('TB LTD 2021'!A:A,'2021'!A42,'TB LTD 2021'!I:I) -> 0 | D42: =SUMIF('TB INC'!A:A,'2021'!A42,'TB INC'!F:F) -> 11079.1 | E42: =C42+D42 -> 11079.1 | G42: =SUMIF('TB LTD 2021'!A:A,'2021'!A42,'TB LTD 2021'!F:F) -> 0
B43: Loss for the period | C43: =SUM(C35:C42) -> 2724309.3 | D43: =SUM(D35:D42) -> -22211.53 | E43: =C43+D43 -> 2702097.7 | G43: =SUM(G35:G42) -> 8843657.6 | I43: =G43/C43 -> 3.2462018

Sheet TB LTD 2021
B1: , | D1: =SUM(D3:D312) -> -8.4980911e-10 | E1: =SUM(E3:E312) -> 0 | F1: =SUM(F3:F312) -> -2.910383e-09 | G1: =SUM(G3:G312) -> -2.467857e-10 | H1: =SUM(H3:H312) -> 1.4551915e-11 | I1: =SUM(I3:I333) -> 1.4551915e-11 | N1: =SUM(N3:N330) -> 0 | O1: =SUM(O3:O330) -> -430.89 | P1: =SUM(P3:P316) -> #REF! | S1: =SUM(S3:S330) -> 2804779.3 | T1: =SUM(T3:T316) -> 4024341.6
B2: Account No. | C2: Account Description | D2: Balance (ILS) | E2: AJE ILS | F2: Balance ILS | G2: Balance (USD) | H2: AJE USD | I2: Balance USD | M2: חשבון | N2: תאור החשבון | O2: יתרה בשקלים | Q2: חשבון | S2: יתרה בדולר | T2: הפרש
A3: 10 | B3: 10000 | C3: בנק לאומי ש"ח | D3: 1444853.5 | E3: =SUMIF('AJE LTD'!A:A,'TB LTD 2021'!B3,'AJE LTD'!C:C) -> 0 | F3: =SUM(D3:E3) -> 1444853.5 | G3: 464583.12 | H3: =SUMIF('AJE LTD'!A:A,'TB LTD 2021'!B3,'AJE LTD'!D:D) -> 0 | I3: =SUM(G3:H3) -> 464583.12 | J3: V | M3: 10000 | N3: בנק לאומי ש"ח | O3: 342537.58 | P3: =O3-D3 -> -1102315.9 | Q3: 10000 | R3: 106543.57 | S3: =SUMIF(B:B,Q3,G:G) -> 464583.12 | T3: =S3-R3 -> 358039.55
A4: 10 | B4: 10001 | C4: בנק לאומי $ | D4: 1523650.8 | E4: =SUMIF('AJE LTD'!A:A,'TB LTD 2021'!B4,'AJE LTD'!C:C) -> 0 | F4: =SUM(D4:E4) -> 1523650.8 | G4: 489919.86 | H4: =SUMIF('AJE LTD'!A:A,'TB LTD 2021'!B4,'AJE LTD'!D:D) -> 0 | I4: =SUM(G4:H4) -> 489919.86 | J4: V | M4: 10001 | N4: בP4:V5נק לאומי $ | O4: 1104775 | P4: =O4-D4 -> -418875.74 | Q4: 10001 | R4: 343631.42 | S4: =SUMIF(B:B,Q4,G:G) -> 489919.86 | T4: =S4-R4 -> 146288.44
A5: 31 | B5: 10200 | C5: כ.א.1912 ש"ח | D5: -99828.87 | E5: =SUMIF('AJE LTD'!A:A,'TB LTD 2021'!B5,'AJE LTD'!C:C) -> 0 | F5: =SUM(D5:E5) -> -99828.87 | G5: -32099.32 | H5: =SUMIF('AJE LTD'!A:A,'TB LTD 2021'!B5,'AJE LTD'!D:D) -> 0 | I5: =SUM(G5:H5) -> -32099.32 | J5: V | P5: =O5-D5 -> 99828.87 | Q5: 10200 | R5: -1328.27 | S5: =SUMIF(B:B,Q5,G:G) -> -32099.32 | T5: =S5-R5 -> -30771.05
A6: 11 | B6: 10300 | C6: פקדון ש"ח בנק לאומי | D6: 100033.18 | E6: =SUMIF('AJE LTD'!A:A,'TB LTD 2021'!B6,'AJE LTD'!C:C) -> 0 | F6: =SUM(D6:E6) -> 100033.18 | G6: 32165.01 | H6: =SUMIF('AJE LTD'!A:A,'TB LTD 2021'!B6,'AJE LTD'!D:D) -> 0 | I6: =SUM(G6:H6) -> 32165.01 | J6: V | M6: 10003 | N6: בנק $ TIPALTI | O6: 1385.15 | P6: =O6-D6 -> -98648.03 | Q6: 10201 | R6: -10528.07 | S6: =SUMIF(B:B,Q6,G:G) -> 0 | T6: =S6-R6 -> 10528.07
A7: 14 | B7: 10501 | C7: פקדון SOK WORKS | D7: 16380 | E7: =SUMIF('AJE LTD'!A:A,'TB LTD 2021'!B7,'AJE LTD'!C:C) -> 0 | F7: =SUM(D7:E7) -> 16380 | G7: 5266.88 | H7: =SUMIF('AJE LTD'!A:A,'TB LTD 2021'!B7,'AJE LTD'!D:D) -> 0 | I7: =SUM(G7:H7) -> 5266.88 | J7: V | M7: 10004 | N7: בנק SVB | O7: 28904.1 | P7: =O7-D7 -> 12524.1 | Q7: 10300 | R7: 0 | S7: =SUMIF(B:B,Q7,G:G) -> 32165.01 | T7: =S7-R7 -> 32165.01
A8: 13 | B8: 10800 | C8: הוצאות מראש | D8: 24476.7 | E8: =SUMIF('AJE LTD'!A:A,'TB LTD 2021'!B8,'AJE LTD'!C:C) -> 0 | F8: =SUM(D8:E8) -> 24476.7 | G8: 7516.82 | H8: =SUMIF('AJE LTD'!A:A,'TB LTD 2021'!B8,'AJE LTD'!D:D) -> 0 | I8: =SUM(G8:H8) -> 7516.82 | J8: V | M8: 10005 | N8: בנק Payoneer | O8: 19008.94 | P8: =O8-D8 -> -5467.76 | Q8: 10310 | R8: 1000000 | S8: =SUMIF(B:B,Q8,G:G) -> 0 | T8: =S8-R8 -> -1000000
A9: 27 | B9: 15000 | C9: מחשבים ותוכנות | D9: 171352.56 | E9: =SUMIF('AJE LTD'!A:A,'TB LTD 2021'!B9,'AJE LTD'!C:C) -> 0 | F9: =SUM(D9:E9) -> 171352.56 | G9: 50769.77 | H9: =SUMIF('AJE LTD'!A:A,'TB LTD 2021'!B9,'AJE LTD'!D:D) -> 0 | I9: =SUM(G9:H9) -> 50769.77 | J9: V | M9: 10006 | N9: בנק $ TIPALTI 2 | O9: 167231.63 | P9: =O9-D9 -> -4120.93 | Q9: 10501 | R9: 3965.79 | S9: =SUMIF(B:B,Q9,G:G) -> 5266.88 | T9: =S9-R9 -> 1301.09
A10: 27 | B10: 15001 | C10: ריהוט וציוד | D10: 86683.76 | E10: =SUMIF('AJE LTD'!A:A,'TB LTD 2021'!B10,'AJE LTD'!C:C) -> 0 | F10: =SUM(D10:E10) -> 86683.76 | G10: 26706.97 | H10: =SUMIF('AJE LTD'!A:A,'TB LTD 2021'!B10,'AJE LTD'!D:D) -> 0 | I10: =SUM(G10:H10) -> 26706.97 | J10: V | M10: 10200 | N10: כרטיס אשראי 9110 ש"ח | O10: -4270.38 | P10: =O10-D10 -> -90954.14 | Q10: 10800 | R10: 3962.57 | S10: =SUMIF(B:B,Q10,G:G) -> 7516.82 | T10: =S10-R10 -> 3554.25
A11: 27 | B11: 15002 | C11: ציוד אלקטרוני | D11: 26085.53 | E11: =SUMIF('AJE LTD'!A:A,'TB LTD 2021'!B11,'AJE LTD'!C:C) -> 0 | F11: =SUM(D11:E11) -> 26085.53 | G11: 8029.34 | H11: =SUMIF('AJE LTD'!A:A,'TB LTD 2021'!B11,'AJE LTD'!D:D) -> 0 | I11: =SUM(G11:H11) -> 8029.34 | J11: V | M11: 10201 | N11: כרטיס אשראי $ 9110 | O11: -33847.75 | P11: =O11-D11 -> -59933.28 | Q11: 100001 | R11: 36065.42 | S11: =SUMIF(B:B,Q11,G:G) -> 0 | T11: =S11-R11 -> -36065.42
A12: 27 | B12: 15003 | C12: שיפורים במושכר | D12: 400035.94 | E12: =SUMIF('AJE LTD'!A:A,'TB LTD 2021'!B12,'AJE LTD'!C:C) -> 0 | F12: =SUM(D12:E12) -> 400035.94 | G12: 126545.66 | H12: =SUMIF('AJE LTD'!A:A,'TB LTD 2021'!B12,'AJE LTD'!D:D) -> 0 | I12: =SUM(G12:H12) -> 126545.66 | J12: V | M12: 10310 | N12: פקדון $ בנק לאומי | O12: 3215000 | P12: =O12-D12 -> 2814964.1 | Q12: 100002 | R12: 0 | S12: =SUMIF(B:B,Q12,G:G) -> 0 | T12: =S12-R12 -> 0
A13: 28 | B13: 15100 | C13: פחת נצבר מחשבים | D13: -65299.06 | E13: =SUMIF('AJE LTD'!A:A,'TB LTD 2021'!B13,'AJE LTD'!C:C) -> 0 | F13: =SUM(D13:E13) -> -65299.06 | G13: -18811.95 | H13: =SUMIF('AJE LTD'!A:A,'TB LTD 2021'!B13,'AJE LTD'!D:D) -> 0 | I13: =SUM(G13:H13) -> -18811.95 | J13: V | M13: 10500 | N13: פקדון 10 ביס | O13: 1800 | P13: =O13-D13 -> 67099.06 | Q13: 10900 | R13: 3746.91 | S13: =SUMIF(B:B,Q13,G:G) -> 0 | T13: =S13-R13 -> -3746.91
A14: 28 | B14: 15101 | C14: פחת נצבר ריהוט וציוד | D14: -2865.47 | E14: =SUMIF('AJE LTD'!A:A,'TB LTD 2021'!B14,'AJE LTD'!C:C) -> 0 | F14: =SUM(D14:E14) -> -2865.47 | G14: -828.83 | H14: =SUMIF('AJE LTD'!A:A,'TB LTD 2021'!B14,'AJE LTD'!D:D) -> 0 | I14: =SUM(G14:H14) -> -828.83 | J14: V | M14: 10501 | N14: פקדון שכר דירה | O14: 12750 | P14: =O14-D14 -> 15615.47 | Q14: 15000 | R14: 15902.06 | S14: =SUMIF(B:B,Q14,G:G) -> 50769.77 | T14: =S14-R14 -> 34867.71
A15: 28 | B15: 15102 | C15: פחת נצבר ציוד אלקטרוני | D15: -2890.77 | E15: =SUMIF('AJE LTD'!A:A,'TB LTD 2021'!B15,'AJE LTD'!C:C) -> 0 | F15: =SUM(D15:E15) -> -2890.77 | G15: -865.29 | H15: =SUMIF('AJE LTD'!A:A,'TB LTD 2021'!B15,'AJE LTD'!D:D) -> 0 | I15: =SUM(G15:H15) -> -865.29 | J15: V | M15: 100001 | N15: ורביט סופטוור בע"מ | O15: 115950.33 | P15: =O15-D15 -> 118841.1 | Q15: 15100 | R15: -7144.22 | S15: =SUMIF(B:B,Q15,G:G) -> -18811.95 | T15: =S15-R15 -> -11667.73
A16: 28 | B16: 15103 | C16: פחת נצבר שפורים במושכר | D16: -7457.45 | E16: =SUMIF('AJE LTD'!A:A,'TB LTD 2021'!B16,'AJE LTD'!C:C) -> 0 | F16: =SUM(D16:E16) -> -7457.45 | G16: -2296.43 | H16: =SUMIF('AJE LTD'!A:A,'TB LTD 2021'!B16,'AJE LTD'!D:D) -> 0 | I16: =SUM(G16:H16) -> -2296.43 | J16: V | M16: 100005 | N16: Cardlytics, Inc. | O16: 5386.73 | P16: =O16-D16 -> 12844.18 | Q16: 200004 | R16: 0 | S16: =SUMIF(B:B,Q16,G:G) -> 0 | T16: =S16-R16 -> 0
A17: 31 | B17: 200003 | C17: נשיץ ברנדס אמיר ושות', עורכי דין | D17: 0 | E17: =SUMIF('AJE LTD'!A:A,'TB LTD 2021'!B17,'AJE LTD'!C:C) -> 0 | F17: =SUM(D17:E17) -> 0 | G17: 91.2 | H17: =SUMIF('AJE LTD'!A:A,'TB LTD 2021'!B17,'AJE LTD'!D:D) -> -91.2 | I17: =SUM(G17:H17) -> 0 | M17: 100007 | N17: SimilarWeb | O17: 163489.98 | P17: =O17-D17 -> 163489.98 | Q17: 200005 | R17: 3483.36 | S17: =SUMIF(B:B,Q17,G:G) -> 0 | T17: =S17-R17 -> -3483.36
A18: 31 | B18: 200007 | C18: שטראוס מים בע"מ - תמי 4 | D18: -34 | E18: =SUMIF('AJE LTD'!A:A,'TB LTD 2021'!B18,'AJE LTD'!C:C) -> 0 | F18: =SUM(D18:E18) -> -34 | G18: -10.93 | H18: =SUMIF('AJE LTD'!A:A,'TB LTD 2021'!B18,'AJE LTD'!D:D) -> 0 | I18: =SUM(G18:H18) -> -10.93 | J18: V | M18: 100008 | N18: Panaya | O18: -662.29 | P18: =O18-D18 -> -628.29 | Q18: 200006 | R18: 13247.9 | S18: =SUMIF(B:B,Q18,G:G) -> 0 | T18: =S18-R18 -> -13247.9
A19: 31 | B19: 200015 | C19: אספירקום מערכות בע"מ | D19: -456.1 | E19: =SUMIF('AJE LTD'!A:A,'TB LTD 2021'!B19,'AJE LTD'!C:C) -> 0 | F19: =SUM(D19:E19) -> -456.1 | G19: -146.66 | H19: =SUMIF('AJE LTD'!A:A,'TB LTD 2021'!B19,'AJE LTD'!D:D) -> 0 | I19: =SUM(G19:H19) -> -146.66 | J19: V | M19: 100009 | N19: Buildots Ltd | O19: 182532.56 | P19: =O19-D19 -> 182988.66 | Q19: 200022 | R19: 0 | S19: =SUMIF(B:B,Q19,G:G) -> 0 | T19: =S19-R19 -> 0
A20: 31 | B20: 200017 | C20: חניון מרכז עזריאלי בע"מ | D20: 3404 | E20: =SUMIF('AJE LTD'!A:A,'TB LTD 2021'!B20,'AJE LTD'!C:C) -> 0 | F20: =SUM(D20:E20) -> 3404 | G20: 1094.53 | H20: =SUMIF('AJE LTD'!A:A,'TB LTD 2021'!B20,'AJE LTD'!D:D) -> 0 | I20: =SUM(G20:H20) -> 1094.53 | M20: 100011 | N20: Upkeep Maintenance Management | O20: 26214.76 | P20: =O20-D20 -> 22810.76 | Q20: 200024 | R20: 13974.49 | S20: =SUMIF(B:B,Q20,G:G) -> 0 | T20: =S20-R20 -> -13974.49
A21: 31 | B21: 200023 | C21: חברת פרטנר תקשורת בע"מ | D21: 299.84 | E21: =SUMIF('AJE LTD'!A:A,'TB LTD 2021'!B21,'AJE LTD'!C:C) -> 0 | F21: =SUM(D21:E21) -> 299.84 | G21: 96.41 | H21: =SUMIF('AJE LTD'!A:A,'TB LTD 2021'!B21,'AJE LTD'!D:D) -> 0 | I21: =SUM(G21:H21) -> 96.41 | M21: 100012 | N21: Hurra Communications GmbH | O21: 17611.9 | P21: =O21-D21 -> 17312.06 | Q21: 200052 | R21: 0 | S21: =SUMIF(B:B,Q21,G:G) -> 0 | T21: =S21-R21 -> 0
A22: 31 | B22: 200026 | C22: ג.ש.ניצוץ בע"מ | D22: -6690 | E22: =SUMIF('AJE LTD'!A:A,'TB LTD 2021'!B22,'AJE LTD'!C:C) -> 0 | F22: =SUM(D22:E22) -> -6690 | G22: -2151.13 | H22: =SUMIF('AJE LTD'!A:A,'TB LTD 2021'!B22,'AJE LTD'!D:D) -> 0 | I22: =SUM(G22:H22) -> -2151.13 | J22: V | M22: 100013 | N22: Mixtiles Ltd | O22: 34332.6 | P22: =O22-D22 -> 41022.6 | Q22: 200053 | R22: 0 | S22: =SUMIF(B:B,Q22,G:G) -> 0 | T22: =S22-R22 -> 0
A23: 31 | B23: 200027 | C23: מגדל חברה לבטוח בע"מ | D23: 2145 | E23: =SUMIF('AJE LTD'!A:A,'TB LTD 2021'!B23,'AJE LTD'!C:C) -> 0 | F23: =SUM(D23:E23) -> 2145 | G23: 689.71 | H23: =SUMIF('AJE LTD'!A:A,'TB LTD 2021'!B23,'AJE LTD'!D:D) -> 0 | I23: =SUM(G23:H23) -> 689.71 | M23: 10800 | N23: הוצאות מראש | O23: 13567.85 | P23: =O23-D23 -> 11422.85 | Q23: 200070 | R23: 0 | S23: =SUMIF(B:B,Q23,G:G) -> 0 | T23: =S23-R23 -> 0
A24: 31 | B24: 20003 | C24: עיריית תל אביב | D24: 7344.29 | E24: =SUMIF('AJE LTD'!A:A,'TB LTD 2021'!B24,'AJE LTD'!C:C) -> 0 | F24: =SUM(D24:E24) -> 7344.29 | G24: 2361.51 | H24: =SUMIF('AJE LTD'!A:A,'TB LTD 2021'!B24,'AJE LTD'!D:D) -> 0 | I24: =SUM(G24:H24) -> 2361.51 | M24: 10900 | N24: הכנסות לקבל | O24: 12642.05 | P24: =O24-D24 -> 5297.76 | Q24: 200073 | R24: -0.07 | S24: =SUMIF(B:B,Q24,G:G) -> 0 | T24: =S24-R24 -> 0.07
A25: 31 | B25: 200037 | C25: ליבנה צפוני בע"מ IKEA | D25: 450 | E25: =SUMIF('AJE LTD'!A:A,'TB LTD 2021'!B25,'AJE LTD'!C:C) -> 0 | F25: =SUM(D25:E25) -> 450 | G25: 144.69 | H25: =SUMIF('AJE LTD'!A:A,'TB LTD 2021'!B25,'AJE LTD'!D:D) -> 0 | I25: =SUM(G25:H25) -> 144.69 | M25: 15000 | N25: מחשבים ותוכנות | O25: 56067.51 | P25: =O25-D25 -> 55617.51 | Q25: 200074 | R25: 0 | S25: =SUMIF(B:B,Q25,G:G) -> 556.74 | T25: =S25-R25 -> 556.74
A26: 31 | B26: 200046 | C26: אמזון ווב סרביסס ישראל AMAZON | D26: 49886.91 | E26: =SUMIF('AJE LTD'!A:A,'TB LTD 2021'!B26,'AJE LTD'!C:C) -> 0 | F26: =SUM(D26:E26) -> 49886.91 | G26: 16040.81 | H26: =SUMIF('AJE LTD'!A:A,'TB LTD 2021'!B26,'AJE LTD'!D:D) -> 0 | I26: =SUM(G26:H26) -> 16040.81 | M26: 15002 | N26: ציוד אלקטרוני | O26: 1247.86 | P26: =O26-D26 -> -48639.05 | Q26: 200075 | R26: 0 | S26: =SUMIF(B:B,Q26,G:G) -> 0 | T26: =S26-R26 -> 0
A27: 31 | B27: 200050 | C27: בזק החברה הישראלית לתקשורת בע"מ | D27: 2653.56 | E27: =SUMIF('AJE LTD'!A:A,'TB LTD 2021'!B27,'AJE LTD'!C:C) -> 0 | F27: =SUM(D27:E27) -> 2653.56 | G27: 853.23 | H27: =SUMIF('AJE LTD'!A:A,'TB LTD 2021'!B27,'AJE LTD'!D:D) -> 0 | I27: =SUM(G27:H27) -> 853.23 | M27: 15100 | N27: פחת נצבר מחשבים | O27: -24759.89 | P27: =O27-D27 -> -27413.45 | Q27: 200009 | R27: 0 | S27: =SUMIF(B:B,Q27,G:G) -> 0 | T27: =S27-R27 -> 0
A28: 31 | B28: 200059 | C28: ג'יטי גט טקסי סרוויסס בע"מ | D28: 1510 | E28: =SUMIF('AJE LTD'!A:A,'TB LTD 2021'!B28,'AJE LTD'!C:C) -> 0 | F28: =SUM(D28:E28) -> 1510 | G28: 485.53 | H28: =SUMIF('AJE LTD'!A:A,'TB LTD 2021'!B28,'AJE LTD'!D:D) -> 0 | I28: =SUM(G28:H28) -> 485.53 | M28: 15102 | N28: פחת נצבר ציוד אלקטרוני | O28: -277.47 | P28: =O28-D28 -> -1787.47 | Q28: 200045 | R28: 0 | S28: =SUMIF(B:B,Q28,G:G) -> 0 | T28: =S28-R28 -> 0
A29: 31 | B29: 200060 | C29: הפניקס חברה לביטוח בע"מ | D29: 2844.38 | E29: =SUMIF('AJE LTD'!A:A,'TB LTD 2021'!B29,'AJE LTD'!C:C) -> 0 | F29: =SUM(D29:E29) -> 2844.38 | G29: 914.59 | H29: =SUMIF('AJE LTD'!A:A,'TB LTD 2021'!B29,'AJE LTD'!D:D) -> 0 | I29: =SUM(G29:H29) -> 914.59 | M29: 20000 | N29: 10 ביס | O29: -3669 | P29: =O29-D29 -> -6513.38 | Q29: 200054 | R29: 430.44 | S29: =SUMIF(B:B,Q29,G:G) -> 0 | T29: =S29-R29 -> -430.44
A30: 31 | B30: 200069 | C30: מי אביבים 2010 בע"מ | D30: 881.21 | E30: =SUMIF('AJE LTD'!A:A,'TB LTD 2021'!B30,'AJE LTD'!C:C) -> 0 | F30: =SUM(D30:E30) -> 881.21 | G30: 283.35 | H30: =SUMIF('AJE LTD'!A:A,'TB LTD 2021'!B30,'AJE LTD'!D:D) -> 0 | I30: =SUM(G30:H30) -> 283.35 | P30: =O30-D30 -> -881.21 | Q30: 200058 | R30: 1089.9 | S30: =SUMIF(B:B,Q30,G:G) -> 0 | T30: =S30-R30 -> -1089.9
A31: 31 | B31: 200076 | C31: מיתר עורכי דין | D31: -119901.6 | E31: =SUMIF('AJE LTD'!A:A,'TB LTD 2021'!B31,'AJE LTD'!C:C) -> 0 | F31: =SUM(D31:E31) -> -119901.6 | G31: -37294.43 | H31: =SUMIF('AJE LTD'!A:A,'TB LTD 2021'!B31,'AJE LTD'!D:D) -> 0 | I31: =SUM(G31:H31) -> -37294.43 | J31: V | M31: 200005 | N31: אספירקום מערכות בע"מ | O31: 11199 | P31: =O31-D31 -> 131100.6 | Q31: 200015 | R31: 0 | S31: =SUMIF(B:B,Q31,G:G) -> -146.66 | T31: =S31-R31 -> -146.66
A32: 31 | B32: 200086 | C32: אברם גילברט | D32: -16523.52 | E32: =SUMIF('AJE LTD'!A:A,'TB LTD 2021'!B32,'AJE LTD'!C:C) -> 16523.52 | F32: =SUM(D32:E32) -> 0 | G32: -5313.03 | H32: =SUMIF('AJE LTD'!A:A,'TB LTD 2021'!B32,'AJE LTD'!D:D) -> 5313.03 | I32: =SUM(G32:H32) -> 0 | M32: 200006 | N32: בי אול סנטרס בע"מ | O32: 42592 | P32: =O32-D32 -> 59115.52 | Q32: 200007 | R32: 610.33 | S32: =SUMIF(B:B,Q32,G:G) -> -10.93 | T32: =S32-R32 -> -621.26
A33: 31 | B33: 200092 | C33: אר.טו.אם קורפוראשיין בע"מ | D33: -536 | E33: =SUMIF('AJE LTD'!A:A,'TB LTD 2021'!B33,'AJE LTD'!C:C) -> 0 | F33: =SUM(D33:E33) -> -536 | G33: -172.35 | H33: =SUMIF('AJE LTD'!A:A,'TB LTD 2021'!B33,'AJE LTD'!D:D) -> 0 | I33: =SUM(G33:H33) -> -172.35 | J33: V | P33: =O33-D33 -> 536 | Q33: 200050 | R33: 0 | S33: =SUMIF(B:B,Q33,G:G) -> 853.23 | T33: =S33-R33 -> 853.23
A34: 31 | B34: 200096 | C34: אלטשולר שחם - להשלים פרטים | D34: 1920 | E34: =SUMIF('AJE LTD'!A:A,'TB LTD 2021'!B34,'AJE LTD'!C:C) -> 0 | F34: =SUM(D34:E34) -> 1920 | G34: 617.36 | H34: =SUMIF('AJE LTD'!A:A,'TB LTD 2021'!B34,'AJE LTD'!D:D) -> 0 | I34: =SUM(G34:H34) -> 617.36 | P34: =O34-D34 -> -1920 | Q34: 20200 | R34: -97048.895 | S34: =SUMIF(B:B,Q34,G:G) -> -79278.74 | T34: =S34-R34 -> 17770.155
A35: 31 | B35: 200099 | C35: קיי.אס.פי. מחשבים (ראשון לציון) בע"מ | D35: 2315 | E35: =SUMIF('AJE LTD'!A:A,'TB LTD 2021'!B35,'AJE LTD'!C:C) -> 0 | F35: =SUM(D35:E35) -> 2315 | G35: 744.37 | H35: =SUMIF('AJE LTD'!A:A,'TB LTD 2021'!B35,'AJE LTD'!D:D) -> 0 | I35: =SUM(G35:H35) -> 744.37 | P35: =O35-D35 -> -2315
A36: 31 | B36: 200105 | C36: ול"ך דן ייעוץ | D36: -11436.76 | E36: =SUMIF('AJE LTD'!A:A,'TB LTD 2021'!B36,'AJE LTD'!C:C) -> 0 | F36: =SUM(D36:E36) -> -11436.76 | G36: -3677.41 | H36: =SUMIF('AJE LTD'!A:A,'TB LTD 2021'!B36,'AJE LTD'!D:D) -> 0 | I36: =SUM(G36:H36) -> -3677.41 | J36: V | M36: 200024 | N36: אלינור וייס | O36: 44928 | P36: =O36-D36 -> 56364.76 | Q36: 20402 | R36: 0 | S36: =SUMIF(B:B,Q36,G:G) -> 16549.1 | T36: =S36-R36 -> 16549.1
A37: 31 | B37: 200113 | C37: דור אלון ניהול מתחמים AM PM | D37: 853.02 | E37: =SUMIF('AJE LTD'!A:A,'TB LTD 2021'!B37,'AJE LTD'!C:C) -> 0 | F37: =SUM(D37:E37) -> 853.02 | G37: 274.28 | H37: =SUMIF('AJE LTD'!A:A,'TB LTD 2021'!B37,'AJE LTD'!D:D) -> 0 | I37: =SUM(G37:H37) -> 274.28 | P37: =O37-D37 -> -853.02 | Q37: 20403 | R37: 0 | S37: =SUMIF(B:B,Q37,G:G) -> 21589.06 | T37: =S37-R37 -> 21589.06
A38: 31 | B38: 200139 | C38: ארביב פרוייקטים משה וירין בע"מ | D38: -0.01 | E38: =SUMIF('AJE LTD'!A:A,'TB LTD 2021'!B38,'AJE LTD'!C:C) -> 0 | F38: =SUM(D38:E38) -> -0.01 | G38: 0 | H38: =SUMIF('AJE LTD'!A:A,'TB LTD 2021'!B38,'AJE LTD'!D:D) -> 0 | I38: =SUM(G38:H38) -> 0 | M38: 200046 | N38: אקס. אנג'וי אירועים והפקות בע"מ - הסטודיו לבישול | O38: -260 | P38: =O38-D38 -> -259.99 | Q38: 20502 | R38: 1912.29 | S38: =SUMIF(B:B,Q38,G:G) -> 0 | T38: =S38-R38 -> -1912.29
A39: 31 | B39: 200141 | C39: מולט | D39: -46.29 | E39: =SUMIF('AJE LTD'!A:A,'TB LTD 2021'!B39,'AJE LTD'!C:C) -> 0 | F39: =SUM(D39:E39) -> -46.29 | G39: -14.88 | H39: =SUMIF('AJE LTD'!A:A,'TB LTD 2021'!B39,'AJE LTD'!D:D) -> 0 | I39: =SUM(G39:H39) -> -14.88 | J39: V | M39: 200067 | N39: פריוריטי סופטוור בע"מ | O39: 6248 | P39: =O39-D39 -> 6294.29 | Q39: 20604 | R39: 663.87 | S39: =SUMIF(B:B,Q39,G:G) -> 2.03 | T39: =S39-R39 -> -661.84
A40: 31 | B40: 200144 | C40: ניסקו חשמל שקע ותקע תאורה בע"מ | D40: -220 | E40: =SUMIF('AJE LTD'!A:A,'TB LTD 2021'!B40,'AJE LTD'!C:C) -> 0 | F40: =SUM(D40:E40) -> -220 | G40: -70.74 | H40: =SUMIF('AJE LTD'!A:A,'TB LTD 2021'!B40,'AJE LTD'!D:D) -> 0 | I40: =SUM(G40:H40) -> -70.74 | J40: V | M40: 200084 | N40: יוניק סיסטמס פתרונות בע"מ | O40: 702 | P40: =O40-D40 -> 922 | Q40: 20500 | R40: -13276.52 | S40: =SUMIF(B:B,Q40,G:G) -> -54413.5 | T40: =S40-R40 -> -41136.98
A41: 31 | B41: 200156 | C41: גנח שמעון-שיא הובלות | D41: -1400 | E41: =SUMIF('AJE LTD'!A:A,'TB LTD 2021'!B41,'AJE LTD'!C:C) -> 0 | F41: =SUM(D41:E41) -> -1400 | G41: -450.16 | H41: =SUMIF('AJE LTD'!A:A,'TB LTD 2021'!B41,'AJE LTD'!D:D) -> 0 | I41: =SUM(G41:H41) -> -450.16 | J41: V | M41: 200114 | N41: יקבי גוש עציון | O41: 2090 | P41: =O41-D41 -> 3490 | Q41: 20501 | R41: -15162.67 | S41: =SUMIF(B:B,Q41,G:G) -> -44975.24 | T41: =S41-R41 -> -29812.57
A42: 31 | B42: 200158 | C42: פוקס ויזל בע"מ | D42: 299.52 | E42: =SUMIF('AJE LTD'!A:A,'TB LTD 2021'!B42,'AJE LTD'!C:C) -> 0 | F42: =SUM(D42:E42) -> 299.52 | G42: 96.31 | H42: =SUMIF('AJE LTD'!A:A,'TB LTD 2021'!B42,'AJE LTD'!D:D) -> 0 | I42: =SUM(G42:H42) -> 96.31 | M42: 200007 | N42: GOOGLE | O42: 1962.21 | P42: =O42-D42 -> 1662.69 | Q42: 20799 | R42: -19907.31 | S42: =SUMIF(B:B,Q42,G:G) -> -46746.3 | T42: =S42-R42 -> -26838.99
A43: 31 | B43: 200008 | C43: GOOGLE | D43: 4816.58 | E43: =SUMIF('AJE LTD'!A:A,'TB LTD 2021'!B43,'AJE LTD'!C:C) -> 0 | F43: =SUM(D43:E43) -> 4816.58 | G43: 1548.74 | H43: =SUMIF('AJE LTD'!A:A,'TB LTD 2021'!B43,'AJE LTD'!D:D) -> 0 | I43: =SUM(G43:H43) -> 1548.74 | P43: =O43-D43 -> -4816.58 | Q43: 20900 | R43: -47419.91 | S43: =SUMIF(B:B,Q43,G:G) -> -95108.04 | T43: =S43-R43 -> -47688.13
A44: 31 | B44: 200032 | C44: UNITED | D44: 27445.59 | E44: =SUMIF('AJE LTD'!A:A,'TB LTD 2021'!B44,'AJE LTD'!C:C) -> 0 | F44: =SUM(D44:E44) -> 27445.59 | G44: 8824.95 | H44: =SUMIF('AJE LTD'!A:A,'TB LTD 2021'!B44,'AJE LTD'!D:D) -> 0 | I44: =SUM(G44:H44) -> 8824.95 | P44: =O44-D44 -> -27445.59 | Q44: 20901 | R44: -705.82 | S44: =SUMIF(B:B,Q44,G:G) -> 632.44 | T44: =S44-R44 -> 1338.26
A45: 31 | B45: 200035 | C45: SLACK | D45: 686.59 | E45: =SUMIF('AJE LTD'!A:A,'TB LTD 2021'!B45,'AJE LTD'!C:C) -> 0 | F45: =SUM(D45:E45) -> 686.59 | G45: 220.77 | H45: =SUMIF('AJE LTD'!A:A,'TB LTD 2021'!B45,'AJE LTD'!D:D) -> 0 | I45: =SUM(G45:H45) -> 220.77 | P45: =O45-D45 -> -686.59 | Q45: 20903 | R45: 138.72 | S45: =SUMIF(B:B,Q45,G:G) -> 49.52 | T45: =S45-R45 -> -89.2
A46: 31 | B46: 200074 | C46: HubSpot | D46: 1731.46 | E46: =SUMIF('AJE LTD'!A:A,'TB LTD 2021'!B46,'AJE LTD'!C:C) -> 0 | F46: =SUM(D46:E46) -> 1731.46 | G46: 556.74 | H46: =SUMIF('AJE LTD'!A:A,'TB LTD 2021'!B46,'AJE LTD'!D:D) -> 0 | I46: =SUM(G46:H46) -> 556.74 | P46: =O46-D46 -> -1731.46 | Q46: 20998 | R46: -33820.38 | S46: =SUMIF(B:B,Q46,G:G) -> 0.01 | T46: =S46-R46 -> 33820.39
A47: 31 | B47: 200094 | C47: Microsoft | D47: 3736.42 | E47: =SUMIF('AJE LTD'!A:A,'TB LTD 2021'!B47,'AJE LTD'!C:C) -> 0 | F47: =SUM(D47:E47) -> 3736.42 | G47: 1201.42 | H47: =SUMIF('AJE LTD'!A:A,'TB LTD 2021'!B47,'AJE LTD'!D:D) -> 0 | I47: =SUM(G47:H47) -> 1201.42 | P47: =O47-D47 -> -3736.42 | Q47: 20999 | R47: -1529.75 | S47: =SUMIF(B:B,Q47,G:G) -> -2076.58 | T47: =S47-R47 -> -546.83
A48: 31 | B48: 200098 | C48: DATABRICKS INC | D48: 5845.68 | E48: =SUMIF('AJE LTD'!A:A,'TB LTD 2021'!B48,'AJE LTD'!C:C) -> 0 | F48: =SUM(D48:E48) -> 5845.68 | G48: 1879.64 | H48: =SUMIF('AJE LTD'!A:A,'TB LTD 2021'!B48,'AJE LTD'!D:D) -> 0 | I48: =SUM(G48:H48) -> 1879.64 | M48: 200054 | N48: LinkedIn | O48: 1383.86 | P48: =O48-#REF! -> #REF! | Q48: 30011 | R48: -3208390 | S48: =SUMIF(B:B,Q48,G:G) -> 0 | T48: =S48-R48 -> 3208390
A49: 31 | B49: 200112 | C49: LinkedIn | D49: 342.04 | E49: =SUMIF('AJE LTD'!A:A,'TB LTD 2021'!B49,'AJE LTD'!C:C) -> 0 | F49: =SUM(D49:E49) -> 342.04 | G49: 109.98 | H49: =SUMIF('AJE LTD'!A:A,'TB LTD 2021'!B49,'AJE LTD'!D:D) -> 0 | I49: =SUM(G49:H49) -> 109.98 | M49: 200058 | N49: Freelancer International | O49: 3504.03 | P49: =O49-D48 -> -2341.65 | Q49: 30012 | R49: -41610 | S49: =SUMIF(B:B,Q49,G:G) -> 0 | T49: =S49-R49 -> 41610
A50: 31 | B50: 200127 | C50: JumpCloud Inc | D50: -634.44 | E50: =SUMIF('AJE LTD'!A:A,'TB LTD 2021'!B50,'AJE LTD'!C:C) -> 0 | F50: =SUM(D50:E50) -> -634.44 | G50: -204 | H50: =SUMIF('AJE LTD'!A:A,'TB LTD 2021'!B50,'AJE LTD'!D:D) -> 0 | I50: =SUM(G50:H50) -> -204 | J50: V | M50: 200073 | N50: אביאל יעוץ והשקעות בע"מ | O50: -0.23 | P50: =O50-D49 -> -342.27 | Q50: 30013 | R50: -50000 | S50: =SUMIF(B:B,Q50,G:G) -> 0 | T50: =S50-R50 -> 50000
A51: 31 | B51: 200131 | C51: INTERCONTINENTAL SAN | D51: 3092.54 | E51: =SUMIF('AJE LTD'!A:A,'TB LTD 2021'!B51,'AJE LTD'!C:C) -> 0 | F51: =SUM(D51:E51) -> 3092.54 | G51: 994.39 | H51: =SUMIF('AJE LTD'!A:A,'TB LTD 2021'!B51,'AJE LTD'!D:D) -> 0 | I51: =SUM(G51:H51) -> 994.39 | M51: 200087 | N51: Name.com, Inc | O51: 131.78 | P51: =O51-D50 -> 766.22 | Q51: 30014 | R51: -50000 | S51: =SUMIF(B:B,Q51,G:G) -> 0 | T51: =S51-R51 -> 50000
A52: 31 | B52: 200142 | C52: 10110732 Manitoba Ltd | D52: 146532.78 | E52: =SUMIF('AJE LTD'!A:A,'TB LTD 2021'!B52,'AJE LTD'!C:C) -> 0 | F52: =SUM(D52:E52) -> 146532.78 | G52: 47116.65 | H52: =SUMIF('AJE LTD'!A:A,'TB LTD 2021'!B52,'AJE LTD'!D:D) -> 0 | I52: =SUM(G52:H52) -> 47116.65 | M52: 200092 | N52: AG-GRID | O52: 7233.75 | P52: =O52-D51 -> 4141.21 | Q52: 30015 | R52: -57219 | S52: =SUMIF(B:B,Q52,G:G) -> 0 | T52: =S52-R52 -> 57219
A53: 31 | B53: 200146 | C53: LUKS CORMANEY LLP | D53: -2799 | E53: =SUMIF('AJE LTD'!A:A,'TB LTD 2021'!B53,'AJE LTD'!C:C) -> 0 | F53: =SUM(D53:E53) -> -2799 | G53: -900 | H53: =SUMIF('AJE LTD'!A:A,'TB LTD 2021'!B53,'AJE LTD'!D:D) -> 0 | I53: =SUM(G53:H53) -> -900 | J53: V | M53: 200118 | N53: Vladimir Marinovic Martini | O53: -562.63 | P53: =O53-D52 -> -147095.41 | Q53: 30016 | R53: -75000 | S53: =SUMIF(B:B,Q53,G:G) -> 0 | T53: =S53-R53 -> 75000
A54: 31 | B54: 200149 | C54: Airbnb inc | D54: 366.23 | E54: =SUMIF('AJE LTD'!A:A,'TB LTD 2021'!B54,'AJE LTD'!C:C) -> 0 | F54: =SUM(D54:E54) -> 366.23 | G54: 117.76 | H54: =SUMIF('AJE LTD'!A:A,'TB LTD 2021'!B54,'AJE LTD'!D:D) -> 0 | I54: =SUM(G54:H54) -> 117.76 | M54: 200122 | N54: Rise LLC (Yi Ding) | O54: 12953.27 | P54: =O54-D53 -> 15752.27 | Q54: 30017 | R54: -92781 | S54: =SUMIF(B:B,Q54,G:G) -> 0 | T54: =S54-R54 -> 92781
A55: 31 | B55: 200153 | C55: Brand24 Global Inc | D55: 162.78 | E55: =SUMIF('AJE LTD'!A:A,'TB LTD 2021'!B55,'AJE LTD'!C:C) -> 0 | F55: =SUM(D55:E55) -> 162.78 | G55: 52.34 | H55: =SUMIF('AJE LTD'!A:A,'TB LTD 2021'!B55,'AJE LTD'!D:D) -> 0 | I55: =SUM(G55:H55) -> 52.34 | M55: 200123 | N55: Self (Suzanna Colberg) | O55: 4983.25 | P55: =O55-D54 -> 4617.02 | Q55: 30018 | R55: -100000 | S55: =SUMIF(B:B,Q55,G:G) -> 0 | T55: =S55-R55 -> 100000
A56: 36 | B56: 200161 | C56: , Inc | D56: -1244872.7 | E56: =SUMIF('AJE LTD'!A:A,'TB LTD 2021'!B56,'AJE LTD'!C:C) -> -61011.842 | F56: =SUM(D56:E56) -> -1305884.5 | G56: -392958.09 | H56: =SUMIF('AJE LTD'!A:A,'TB LTD 2021'!B56,'AJE LTD'!D:D) -> -21163.528 | I56: =SUM(G56:H56) -> -414121.62 | M56: 200126 | N56: ECOMPANYSTORE COM | O56: 64.3 | P56: =O56-D55 -> -98.48 | Q56: 30019 | R56: -200000 | S56: =SUMIF(B:B,Q56,G:G) -> 0 | T56: =S56-R56 -> 200000
A57: 31 | B57: 21001 | C57: Amazon | D57: -6060.39 | E57: =SUMIF('AJE LTD'!A:A,'TB LTD 2021'!B57,'AJE LTD'!C:C) -> 0 | F57: =SUM(D57:E57) -> -6060.39 | G57: -1948.68 | H57: =SUMIF('AJE LTD'!A:A,'TB LTD 2021'!B57,'AJE LTD'!D:D) -> 0 | I57: =SUM(G57:H57) -> -1948.68 | J57: V | M57: 21001 | N57: Amazon | O57: 321.5 | P57: =O57-D56 -> 1245194.2 | Q57: 30020 | R57: -80000 | S57: =SUMIF(B:B,Q57,G:G) -> 0 | T57: =S57-R57 -> 80000
A58: 32 | B58: 20200 | C58: הוצאות לשלם | D58: -247344.38 | E58: =SUMIF('AJE LTD'!A:A,'TB LTD 2021'!B58,'AJE LTD'!C:C) -> 0 | F58: =SUM(D58:E58) -> -247344.38 | G58: -79278.74 | H58: =SUMIF('AJE LTD'!A:A,'TB LTD 2021'!B58,'AJE LTD'!D:D) -> 59650 | I58: =SUM(G58:H58) -> -19628.74 | J58: V | M58: 20200 | N58: הוצאות לשלם | O58: -314795.09 | P58: =O58-D57 -> -308734.7 | Q58: 30021 | R58: -520000 | S58: =SUMIF(B:B,Q58,G:G) -> 0 | T58: =S58-R58 -> 520000
A59: 14 | B59: 20401 | C59: מע'מ עסקאות | D59: -1796.12 | E59: =SUMIF('AJE LTD'!A:A,'TB LTD 2021'!B59,'AJE LTD'!C:C) -> 0 | F59: =SUM(D59:E59) -> -1796.12 | G59: -577.53 | H59: =SUMIF('AJE LTD'!A:A,'TB LTD 2021'!B59,'AJE LTD'!D:D) -> 0 | I59: =SUM(G59:H59) -> -577.53 | M59: 20400 | N59: מע'מ חו'ז | O59: 78206.04 | P59: =O59-D58 -> 325550.42 | Q59: 30022 | R59: -24999.97 | S59: =SUMIF(B:B,Q59,G:G) -> 0 | T59: =S59-R59 -> 24999.97
A60: 14 | B60: 20402 | C60: מע'מ תשומות | D60: 51508.93 | E60: =SUMIF('AJE LTD'!A:A,'TB LTD 2021'!B60,'AJE LTD'!C:C) -> 0 | F60: =SUM(D60:E60) -> 51508.93 | G60: 16549.1 | H60: =SUMIF('AJE LTD'!A:A,'TB LTD 2021'!B60,'AJE LTD'!D:D) -> 0 | I60: =SUM(G60:H60) -> 16549.1 | M60: 20402 | N60: מע'מ תשומות | O60: 0 | P60: =O60-D59 -> 1796.12 | Q60: 10003 | R60: 430.84 | S60: =SUMIF(B:B,Q60,G:G) -> 0 | T60: =S60-R60 -> -430.84
A61: 14 | B61: 20403 | C61: מע'מ תשומות לנכסים | D61: 67141.99 | E61: =SUMIF('AJE LTD'!A:A,'TB LTD 2021'!B61,'AJE LTD'!C:C) -> 0 | F61: =SUM(D61:E61) -> 67141.99 | G61: 21589.06 | H61: =SUMIF('AJE LTD'!A:A,'TB LTD 2021'!B61,'AJE LTD'!D:D) -> 0 | I61: =SUM(G61:H61) -> 21589.06 | M61: 20405 | N61: מע"מ במקור (אינו משתתף בדוח מע"מ) | O61: -101436.32 | P61: =O61-D60 -> -152945.25 | Q61: 10004 | R61: 8990.39 | S61: =SUMIF(B:B,Q61,G:G) -> 0 | T61: =S61-R61 -> -8990.39
A62: 14 | B62: 20405 | C62: מע"מ במקור (אינו משתתף בדוח מע"מ) | D62: -45134.02 | E62: =SUMIF('AJE LTD'!A:A,'TB LTD 2021'!B62,'AJE LTD'!C:C) -> 0 | F62: =SUM(D62:E62) -> -45134.02 | G62: -14512.55 | H62: =SUMIF('AJE LTD'!A:A,'TB LTD 2021'!B62,'AJE LTD'!D:D) -> 0 | I62: =SUM(G62:H62) -> -14512.55 | M62: 20406 | N62: קיזוז מע"מ חשבונית עצמית (אינו משתתף בדוח מע"מ) | O62: 101436.32 | P62: =O62-D61 -> 34294.33 | Q62: 15002 | R62: 350.68 | S62: =SUMIF(B:B,Q62,G:G) -> 8029.34 | T62: =S62-R62 -> 7678.66
A63: 14 | B63: 20406 | C63: קיזוז מע"מ חשבונית עצמית (אינו משתתף בדוח מע"מ) | D63: 45134.02 | E63: =SUMIF('AJE LTD'!A:A,'TB LTD 2021'!B63,'AJE LTD'!C:C) -> 0 | F63: =SUM(D63:E63) -> 45134.02 | G63: 14512.55 | H63: =SUMIF('AJE LTD'!A:A,'TB LTD 2021'!B63,'AJE LTD'!D:D) -> 0 | I63: =SUM(G63:H63) -> 14512.55 | M63: 20500 | N63: ביטוח לאומי ניכויים | O63: -42684 | P63: =O63-D62 -> 2450.02 | Q63: 15102 | R63: -79.88 | S63: =SUMIF(B:B,Q63,G:G) -> -865.29 | T63: =S63-R63 -> -785.41
A64: 34 | B64: 20500 | C64: ביטוח לאומי ניכויים | D64: -169226 | E64: =SUMIF('AJE LTD'!A:A,'TB LTD 2021'!B64,'AJE LTD'!C:C) -> 0 | F64: =SUM(D64:E64) -> -169226 | G64: -54413.5 | H64: =SUMIF('AJE LTD'!A:A,'TB LTD 2021'!B64,'AJE LTD'!D:D) -> 0 | I64: =SUM(G64:H64) -> -54413.5 | J64: V | M64: 20501 | N64: מס הכנסה ניכויים | O64: -48748 | P64: =O64-D63 -> -93882.02 | Q64: 20000 | R64: -1141.21 | S64: =SUMIF(B:B,Q64,G:G) -> 0 | T64: =S64-R64 -> 1141.21
A65: 34 | B65: 20501 | C65: מס הכנסה ניכויים | D65: -139873 | E65: =SUMIF('AJE LTD'!A:A,'TB LTD 2021'!B65,'AJE LTD'!C:C) -> 0 | F65: =SUM(D65:E65) -> -139873 | G65: -44975.24 | H65: =SUMIF('AJE LTD'!A:A,'TB LTD 2021'!B65,'AJE LTD'!D:D) -> 0 | I65: =SUM(G65:H65) -> -44975.24 | J65: V | M65: 20502 | N65: עודפות 2019 | O65: 6148 | P65: =O65-D64 -> 175374 | Q65: 200002 | R65: 0 | S65: =SUMIF(B:B,Q65,G:G) -> 0 | T65: =S65-R65 -> 0
A66: 34 | B66: 20604 | C66: ניכוי מס במקור - ריבית | D66: 6.32 | E66: =SUMIF('AJE LTD'!A:A,'TB LTD 2021'!B66,'AJE LTD'!C:C) -> 0 | F66: =SUM(D66:E66) -> 6.32 | G66: 2.03 | H66: =SUMIF('AJE LTD'!A:A,'TB LTD 2021'!B66,'AJE LTD'!D:D) -> 0 | I66: =SUM(G66:H66) -> 2.03 | M66: 20602 | N66: ניכוי מס במקור - ספקים | O66: -4340.64 | P66: =O66-D65 -> 135532.36 | Q66: 200011 | R66: 0 | S66: =SUMIF(B:B,Q66,G:G) -> 0 | T66: =S66-R66 -> 0
A67: 14 | B67: 20605 | C67: מקדמות בגין עודפות 2020 | D67: 2080 | E67: =SUMIF('AJE LTD'!A:A,'TB LTD 2021'!B67,'AJE LTD'!C:C) -> -2080 | F67: =SUM(D67:E67) -> 0 | G67: 668.81 | H67: =SUMIF('AJE LTD'!A:A,'TB LTD 2021'!B67,'AJE LTD'!D:D) -> -669 | I67: =SUM(G67:H67) -> -0.19 | J67: V | M67: 20604 | N67: ניכוי מס במקור - רבית פקדון | O67: 2134.34 | P67: =O67-D66 -> 2128.02 | Q67: 200019 | R67: 30.14 | S67: =SUMIF(B:B,Q67,G:G) -> 0 | T67: =S67-R67 -> -30.14
A68: 33 | B68: 20799 | C68: חו"ז גמל | D68: -145381 | E68: =SUMIF('AJE LTD'!A:A,'TB LTD 2021'!B68,'AJE LTD'!C:C) -> 0 | F68: =SUM(D68:E68) -> -145381 | G68: -46746.3 | H68: =SUMIF('AJE LTD'!A:A,'TB LTD 2021'!B68,'AJE LTD'!D:D) -> 0 | I68: =SUM(G68:H68) -> -46746.3 | J68: V | M68: 20799 | N68: אמנון גור - חו"ז גמל | O68: -64002 | P68: =O68-D67 -> -66082 | Q68: 200025 | R68: 0 | S68: =SUMIF(B:B,Q68,G:G) -> 0 | T68: =S68-R68 -> 0
A69: 33 | B69: 20900 | C69: חו"ז עובדים | D69: -295786 | E69: =SUMIF('AJE LTD'!A:A,'TB LTD 2021'!B69,'AJE LTD'!C:C) -> 0 | F69: =SUM(D69:E69) -> -295786 | G69: -95108.04 | H69: =SUMIF('AJE LTD'!A:A,'TB LTD 2021'!B69,'AJE LTD'!D:D) -> 0 | I69: =SUM(G69:H69) -> -95108.04 | J69: V | P69: =O69-D68 -> 145381 | Q69: 200028 | R69: 0 | S69: =SUMIF(B:B,Q69,G:G) -> 0 | T69: =S69-R69 -> 0
A70: 33 | B70: 20901 | C70: כץ עוז | D70: 1848.26 | E70: =SUMIF('AJE LTD'!A:A,'TB LTD 2021'!B70,'AJE LTD'!C:C) -> 0 | F70: =SUM(D70:E70) -> 1848.26 | G70: 632.44 | H70: =SUMIF('AJE LTD'!A:A,'TB LTD 2021'!B70,'AJE LTD'!D:D) -> 0 | I70: =SUM(G70:H70) -> 632.44 | P70: =O70-D69 -> 295786 | Q70: 200031 | R70: 0 | S70: =SUMIF(B:B,Q70,G:G) -> 0 | T70: =S70-R70 -> 0
A71: 33 | B71: 20902 | C71: אור עינת | D71: 1179 | E71: =SUMIF('AJE LTD'!A:A,'TB LTD 2021'!B71,'AJE LTD'!C:C) -> 0 | F71: =SUM(D71:E71) -> 1179 | G71: 379.1 | H71: =SUMIF('AJE LTD'!A:A,'TB LTD 2021'!B71,'AJE LTD'!D:D) -> 0 | I71: =SUM(G71:H71) -> 379.1 | M71: 20900 | N71: חו"ז עובדים | O71: -152455 | P71: =O71-D70 -> -154303.26 | Q71: 200034 | R71: 0 | S71: =SUMIF(B:B,Q71,G:G) -> 0 | T71: =S71-R71 -> 0
A72: 33 | B72: 20903 | C72: יעקובוביץ יצחק | D72: 154 | E72: =SUMIF('AJE LTD'!A:A,'TB LTD 2021'!B72,'AJE LTD'!C:C) -> 0 | F72: =SUM(D72:E72) -> 154 | G72: 49.52 | H72: =SUMIF('AJE LTD'!A:A,'TB LTD 2021'!B72,'AJE LTD'!D:D) -> 0 | I72: =SUM(G72:H72) -> 49.52 | M72: 20901 | N72: שחר ארז | O72: -2269.22 | P72: =O72-D71 -> -3448.22 | Q72: 200008 | R72: 0 | S72: =SUMIF(B:B,Q72,G:G) -> 1548.74 | T72: =S72-R72 -> 1548.74
A73: 33 | B73: 20905 | C73: עמר ברק | D73: 222 | E73: =SUMIF('AJE LTD'!A:A,'TB LTD 2021'!B73,'AJE LTD'!C:C) -> 0 | F73: =SUM(D73:E73) -> 222 | G73: 71.38 | H73: =SUMIF('AJE LTD'!A:A,'TB LTD 2021'!B73,'AJE LTD'!D:D) -> 0 | I73: =SUM(G73:H73) -> 71.38 | M73: 20903 | N73: נפתלי ריין | O73: 446 | P73: =O73-D72 -> 292 | Q73: 200017 | R73: 0 | S73: =SUMIF(B:B,Q73,G:G) -> 1094.53 | T73: =S73-R73 -> 1094.53
A74: 33 | B74: 20906 | C74: ריבקינד יעל | D74: -217.8 | E74: =SUMIF('AJE LTD'!A:A,'TB LTD 2021'!B74,'AJE LTD'!C:C) -> 0 | F74: =SUM(D74:E74) -> -217.8 | G74: -70.03 | H74: =SUMIF('AJE LTD'!A:A,'TB LTD 2021'!B74,'AJE LTD'!D:D) -> 0 | I74: =SUM(G74:H74) -> -70.03 | J74: V | M74: 20904 | N74: שי אשכנזי | O74: 7206.66 | P74: =O74-D73 -> 6984.66 | Q74: 200032 | R74: 0 | S74: =SUMIF(B:B,Q74,G:G) -> 8824.95 | T74: =S74-R74 -> 8824.95
A75: 33 | B75: 20908 | C75: שקד אריאל | D75: 105 | E75: =SUMIF('AJE LTD'!A:A,'TB LTD 2021'!B75,'AJE LTD'!C:C) -> 0 | F75: =SUM(D75:E75) -> 105 | G75: 33.76 | H75: =SUMIF('AJE LTD'!A:A,'TB LTD 2021'!B75,'AJE LTD'!D:D) -> 0 | I75: =SUM(G75:H75) -> 33.76 | P75: =O75-D74 -> 217.8 | Q75: 200033 | R75: 0 | S75: =SUMIF(B:B,Q75,G:G) -> 0 | T75: =S75-R75 -> 0
A76: 33 | B76: 20909 | C76: אדמי איתי | D76: 468 | E76: =SUMIF('AJE LTD'!A:A,'TB LTD 2021'!B76,'AJE LTD'!C:C) -> 0 | F76: =SUM(D76:E76) -> 468 | G76: 150.48 | H76: =SUMIF('AJE LTD'!A:A,'TB LTD 2021'!B76,'AJE LTD'!D:D) -> 0 | I76: =SUM(G76:H76) -> 150.48 | M76: 20998 | N76: עתודה לחופשה | O76: -108732.5 | P76: =O76-D75 -> -108837.5 | Q76: 21001 | R76: 100 | S76: =SUMIF(B:B,Q76,G:G) -> -1948.68 | T76: =S76-R76 -> -2048.68
A77: 33 | B77: 20919 | C77: מנו שיר | D77: 90 | E77: =SUMIF('AJE LTD'!A:A,'TB LTD 2021'!B77,'AJE LTD'!C:C) -> 0 | F77: =SUM(D77:E77) -> 90 | G77: 28.94 | H77: =SUMIF('AJE LTD'!A:A,'TB LTD 2021'!B77,'AJE LTD'!D:D) -> 0 | I77: =SUM(G77:H77) -> 28.94 | M77: 20999 | N77: עתודה להבראה | O77: -4918.16 | P77: =O77-D76 -> -5386.16 | Q77: 20400 | R77: 24325.36 | S77: =SUMIF(B:B,Q77,G:G) -> 0 | T77: =S77-R77 -> -24325.36
A78: 33 | B78: 20998 | C78: עתודה לחופשה | D78: 0 | E78: =SUMIF('AJE LTD'!A:A,'TB LTD 2021'!B78,'AJE LTD'!C:C) -> 0 | F78: =SUM(D78:E78) -> 0 | G78: 0.01 | H78: =SUMIF('AJE LTD'!A:A,'TB LTD 2021'!B78,'AJE LTD'!D:D) -> 0 | I78: =SUM(G78:H78) -> 0.01 | M78: 25200 | N78: חו"ז בינחברתי סטוק טאלנט | O78: 947270.56 | P78: =O78-D77 -> 947180.56 | Q78: 20405 | R78: -31550.95 | S78: =SUMIF(B:B,Q78,G:G) -> -14512.55 | T78: =S78-R78 -> 17038.4
A79: 33 | B79: 20999 | C79: עתודה להבראה | D79: -6457.84 | E79: =SUMIF('AJE LTD'!A:A,'TB LTD 2021'!B79,'AJE LTD'!C:C) -> 0 | F79: =SUM(D79:E79) -> -6457.84 | G79: -2076.58 | H79: =SUMIF('AJE LTD'!A:A,'TB LTD 2021'!B79,'AJE LTD'!D:D) -> 0 | I79: =SUM(G79:H79) -> -2076.58 | J79: V | M79: 30010 | N79: הוצאות הנפקה | O79: 111209.62 | P79: =O79-D78 -> 111209.62 | Q79: 20406 | R79: 31550.95 | S79: =SUMIF(B:B,Q79,G:G) -> 14512.55 | T79: =S79-R79 -> -17038.4
A80: 36 | B80: 20800 | C80: INC | D80: -13912398 | E80: =SUMIF('AJE LTD'!A:A,'TB LTD 2021'!B80,'AJE LTD'!C:C) -> -980234.95 | F80: =SUM(D80:E80) -> -14892633 | G80: -4472830.2 | H80: =SUMIF('AJE LTD'!A:A,'TB LTD 2021'!B80,'AJE LTD'!D:D) -> 0 | I80: =SUM(G80:H80) -> -4472830.2 | M80: 30011 | N80: TLV Partners II, L.P. | O80: -11662498 | P80: =O80-D79 -> -11656040 | Q80: 30010 | R80: 30916.21 | S80: =SUMIF(B:B,Q80,G:G) -> 35463.35 | T80: =S80-R80 -> 4547.14
A81: 44 | B81: 30010 | C81: הוצאות הנפקה | D81: 119901.6 | E81: =SUMIF('AJE LTD'!A:A,'TB LTD 2021'!B81,'AJE LTD'!C:C) -> -119901.6 | F81: =SUM(D81:E81) -> 0 | G81: 35463.35 | H81: =SUMIF('AJE LTD'!A:A,'TB LTD 2021'!B81,'AJE LTD'!D:D) -> -35463.35 | I81: =SUM(G81:H81) -> 0 | M81: 30012 | N81: TLV Partners Strategic Fund II, L.P. | O81: -151252.35 | P81: =O81-D80 -> 13761146 | Q81: 20602 | R81: -1350.12 | S81: =SUMIF(B:B,Q81,G:G) -> 0 | T81: =S81-R81 -> 1350.12
A82: 48 | B82: 39001 | C82: יתרת רווח שנים קודמות | D82: 4010091.2 | E82: =SUMIF('AJE LTD'!A:A,'TB LTD 2021'!B82,'AJE LTD'!C:C) -> 491566.32 | F82: =SUM(D82:E82) -> 4501657.5 | G82: 1249522.6 | H82: =SUMIF('AJE LTD'!A:A,'TB LTD 2021'!B82,'AJE LTD'!D:D) -> 0 | I82: =SUM(G82:H82) -> 1249522.6 | M82: 30013 | N82: ASSAF AND LIRON-COMCAST VENTURES LP | O82: -178900 | P82: =O82-D81 -> -298801.6 | Q82: 20904 | R82: 2241.57 | S82: =SUMIF(B:B,Q82,G:G) -> 0 | T82: =S82-R82 -> -2241.57
A83: 51 | B83: 40005 | C83: הכנסות מחשבונית עצמית (משתתף בדוח מע"מ) | D83: -164697.77 | E83: =SUMIF('AJE LTD'!A:A,'TB LTD 2021'!B83,'AJE LTD'!C:C) -> 0 | F83: =SUM(D83:E83) -> -164697.77 | G83: -51514.98 | H83: =SUMIF('AJE LTD'!A:A,'TB LTD 2021'!B83,'AJE LTD'!D:D) -> 0 | I83: =SUM(G83:H83) -> -51514.98 | M83: 30014 | N83: ANURAG PAL | O83: -178900 | P83: =O83-D82 -> -4188991.2 | Q83: 20905 | R83: 0 | S83: =SUMIF(B:B,Q83,G:G) -> 71.38 | T83: =S83-R83 -> 71.38
A84: 51 | B84: 40006 | C84: הכנסות מחשבונית עצמית (אינו משתתף בדוח מע"מ) | D84: 164697.77 | E84: =SUMIF('AJE LTD'!A:A,'TB LTD 2021'!B84,'AJE LTD'!C:C) -> 0 | F84: =SUM(D84:E84) -> 164697.77 | G84: 51514.98 | H84: =SUMIF('AJE LTD'!A:A,'TB LTD 2021'!B84,'AJE LTD'!D:D) -> 0 | I84: =SUM(G84:H84) -> 51514.98 | M84: 30015 | N84: PIPELINE CAPITAL PARTNERS | O84: -204729.58 | P84: =O84-D83 -> -40031.81 | Q84: 40007 | R84: -3746.91 | S84: =SUMIF(B:B,Q84,G:G) -> 0 | T84: =S84-R84 -> 3746.91
A85: 53 | B85: 50101 | C85: מתנות עובדים מו"פ | D85: 1378 | E85: =SUMIF('AJE LTD'!A:A,'TB LTD 2021'!B85,'AJE LTD'!C:C) -> 0 | F85: =SUM(D85:E85) -> 1378 | G85: 429.28 | H85: =SUMIF('AJE LTD'!A:A,'TB LTD 2021'!B85,'AJE LTD'!D:D) -> 0 | I85: =SUM(G85:H85) -> 429.28 | M85: 30016 | N85: BOGOMIL G BALKANSKY | O85: -268350 | P85: =O85-D84 -> -433047.77 | Q85: 50100 | R85: 9535.09 | S85: =SUMIF(B:B,Q85,G:G) -> 0 | T85: =S85-R85 -> -9535.09
A86: 53 | B86: 50102 | C86: גיוס והשמה מו"פ - אדד ווליו | D86: 85740.17 | E86: =SUMIF('AJE LTD'!A:A,'TB LTD 2021'!B86,'AJE LTD'!C:C) -> 0 | F86: =SUM(D86:E86) -> 85740.17 | G86: 26780.28 | H86: =SUMIF('AJE LTD'!A:A,'TB LTD 2021'!B86,'AJE LTD'!D:D) -> 0 | I86: =SUM(G86:H86) -> 26780.28 | M86: 30017 | N86: PIPELINE CAPITAL PARTNERS I LP | O86: -331970.42 | P86: =O86-D85 -> -333348.42 | Q86: 50103 | R86: 1923.45 | S86: =SUMIF(B:B,Q86,G:G) -> 0 | T86: =S86-R86 -> -1923.45
A87: 53 | B87: 50107 | C87: אחזקת שרתים AMAZON | D87: 14414.96 | E87: =SUMIF('AJE LTD'!A:A,'TB LTD 2021'!B87,'AJE LTD'!C:C) -> 0 | F87: =SUM(D87:E87) -> 14414.96 | G87: 4578.32 | H87: =SUMIF('AJE LTD'!A:A,'TB LTD 2021'!B87,'AJE LTD'!D:D) -> 0 | I87: =SUM(G87:H87) -> 4578.32 | M87: 30018 | N87: QUAKER HEALTH, LLC (CLASS C) | O87: -357800 | P87: =O87-D86 -> -443540.17 | Q87: 50107 | R87: 272.91 | S87: =SUMIF(B:B,Q87,G:G) -> 4578.32 | T87: =S87-R87 -> 4305.41
A88: 53 | B88: 50109 | C88: אחזקת תוכנה ורשיונות מו"פ | D88: 64840.03 | E88: =SUMIF('AJE LTD'!A:A,'TB LTD 2021'!B88,'AJE LTD'!C:C) -> 0 | F88: =SUM(D88:E88) -> 64840.03 | G88: 19083.3 | H88: =SUMIF('AJE LTD'!A:A,'TB LTD 2021'!B88,'AJE LTD'!D:D) -> 0 | I88: =SUM(G88:H88) -> 19083.3 | M88: 30019 | N88: ARC GROWTH LLC | O88: -715600 | P88: =O88-D87 -> -730014.96 | Q88: 50109 | R88: 2148.05 | S88: =SUMIF(B:B,Q88,G:G) -> 19083.3 | T88: =S88-R88 -> 16935.25
A89: 53 | B89: 50110 | C89: הוצאות OPSGENIE | D89: 7710.2 | E89: =SUMIF('AJE LTD'!A:A,'TB LTD 2021'!B89,'AJE LTD'!C:C) -> 0 | F89: =SUM(D89:E89) -> 7710.2 | G89: 2397.38 | H89: =SUMIF('AJE LTD'!A:A,'TB LTD 2021'!B89,'AJE LTD'!D:D) -> 0 | I89: =SUM(G89:H89) -> 2397.38 | M89: 30020 | N89: CHALAMISH BOAZ | O89: -286640 | P89: =O89-D88 -> -351480.03 | Q89: 51000 | R89: 670329.38 | S89: =SUMIF(B:B,Q89,G:G) -> 1153882.8 | T89: =S89-R89 -> 483553.37
A90: 53 | B90: 50112 | C90: הוצ רידאש אי.או | D90: 673.25 | E90: =SUMIF('AJE LTD'!A:A,'TB LTD 2021'!B90,'AJE LTD'!C:C) -> 0 | F90: =SUM(D90:E90) -> 673.25 | G90: 205.23 | H90: =SUMIF('AJE LTD'!A:A,'TB LTD 2021'!B90,'AJE LTD'!D:D) -> 0 | I90: =SUM(G90:H90) -> 205.23 | M90: 30021 | N90: סר כהן רונלד וכהן שרון הראל | O90: -1866280 | P90: =O90-D89 -> -1873990.2 | Q90: 51001 | R90: 46034.81 | S90: =SUMIF(B:B,Q90,G:G) -> 143115.98 | T90: =S90-R90 -> 97081.17
A91: 53 | B91: 50113 | C91: הוצ מיסטורי-נגר אייל | D91: 11882.51 | E91: =SUMIF('AJE LTD'!A:A,'TB LTD 2021'!B91,'AJE LTD'!C:C) -> 0 | F91: =SUM(D91:E91) -> 11882.51 | G91: 3656.14 | H91: =SUMIF('AJE LTD'!A:A,'TB LTD 2021'!B91,'AJE LTD'!D:D) -> 0 | I91: =SUM(G91:H91) -> 3656.14 | M91: 30022 | N91: שר ערן | O91: -89451.27 | P91: =O91-D90 -> -90124.52 | Q91: 51002 | R91: 39899.48 | S91: =SUMIF(B:B,Q91,G:G) -> 0 | T91: =S91-R91 -> -39899.48
... A99: 53 | B99: 51004 | C99: הוצאות גמל א.כ.ע מו"פ | D99: 19225 | E99: =SUMIF('AJE LTD'!A:A,'TB LTD 2021'!B99,'AJE LTD'!C:C) -> 0 | F99: =SUM(D99:E99) -> 19225 | G99: 5961.62 | H99: =SUMIF('AJE LTD'!A:A,'TB LTD 2021'!B99,'AJE LTD'!D:D) -> 0 | I99: =SUM(G99:H99) -> 5961.62 | M99: 40101 | N99: הכנסות תחזוקה - חו"ל | O99: -364.14 | P99: =O99-D98 -> -289849.14 | Q99: 51107 | R99: 1677.33 | S99: =SUMIF(B:B,Q99,G:G) -> 5825.3 | T99: =S99-R99 -> 4147.97
A100: 53 | B100: 51005 | C100: הוצאות קה"ל מו"פ | D100: 106920 | E100: =SUMIF('AJE LTD'!A:A,'TB LTD 2021'!B100,'AJE LTD'!C:C) -> 0 | F100: =SUM(D100:E100) -> 106920 | G100: 33199.33 | H100: =SUMIF('AJE LTD'!A:A,'TB LTD 2021'!B100,'AJE LTD'!D:D) -> 0 | I100: =SUM(G100:H100) -> 33199.33 | P100: =O100-D99 -> -19225 | Q100: 51108 | R100: 263.14 | S100: =SUMIF(B:B,Q100,G:G) -> 11134.37 | T100: =S100-R100 -> 10871.23
A101: 53 | B101: 51097 | C101: הוצאות הפרשה להבראה מו"פ | D101: -4588.15 | E101: =SUMIF('AJE LTD'!A:A,'TB LTD 2021'!B101,'AJE LTD'!C:C) -> 0 | F101: =SUM(D101:E101) -> -4588.15 | G101: -1475.66 | H101: =SUMIF('AJE LTD'!A:A,'TB LTD 2021'!B101,'AJE LTD'!D:D) -> 0 | I101: =SUM(G101:H101) -> -1475.66 | M101: 50100 | N101: ארוחות מו"פ | O101: 32295 | P101: =O101-D100 -> -74625 | Q101: 51199 | R101: -11542.21 | S101: =SUMIF(B:B,Q101,G:G) -> -32522.27 | T101: =S101-R101 -> -20980.06
A102: 53 | B102: 51098 | C102: תגמולי מילואים מו"פ | D102: -5955 | E102: =SUMIF('AJE LTD'!A:A,'TB LTD 2021'!B102,'AJE LTD'!C:C) -> 0 | F102: =SUM(D102:E102) -> -5955 | G102: -1848.8 | H102: =SUMIF('AJE LTD'!A:A,'TB LTD 2021'!B102,'AJE LTD'!D:D) -> 0 | I102: =SUM(G102:H102) -> -1848.8 | M102: 50101 | N102: מתנות עובדים מו"פ | O102: 5052.12 | P102: =O102-D101 -> 9640.27 | Q102: 50019 | R102: 0 | S102: =SUMIF(B:B,Q102,G:G) -> 0 | T102: =S102-R102 -> 0
A103: 53 | B103: 51101 | C103: שווי פלאפון מו"פ | D103: 240 | E103: =SUMIF('AJE LTD'!A:A,'TB LTD 2021'!B103,'AJE LTD'!C:C) -> 0 | F103: =SUM(D103:E103) -> 240 | G103: 74.33 | H103: =SUMIF('AJE LTD'!A:A,'TB LTD 2021'!B103,'AJE LTD'!D:D) -> 0 | I103: =SUM(G103:H103) -> 74.33 | M103: 50102 | N103: גיוס והשמה מו"פ | O103: 27600 | P103: =O103-D102 -> 33555 | Q103: 50101 | R103: 1507.52 | S103: =SUMIF(B:B,Q103,G:G) -> 429.28 | T103: =S103-R103 -> -1078.24
A104: 53 | B104: 51104 | C104: שווי קצבה מו"פ | D104: 35898 | E104: =SUMIF('AJE LTD'!A:A,'TB LTD 2021'!B104,'AJE LTD'!C:C) -> 0 | F104: =SUM(D104:E104) -> 35898 | G104: 11180.3 | H104: =SUMIF('AJE LTD'!A:A,'TB LTD 2021'!B104,'AJE LTD'!D:D) -> 0 | I104: =SUM(G104:H104) -> 11180.3 | M104: 50103 | N104: הוצאות פיתוח | O104: 6705.72 | P104: =O104-D103 -> 6465.72 | Q104: 50113 | R104: 47282.1 | S104: =SUMIF(B:B,Q104,G:G) -> 3656.14 | T104: =S104-R104 -> -43625.96
A105: 53 | B105: 51106 | C105: שווי מתנות מו"פ | D105: 14080 | E105: =SUMIF('AJE LTD'!A:A,'TB LTD 2021'!B105,'AJE LTD'!C:C) -> 0 | F105: =SUM(D105:E105) -> 14080 | G105: 4307.99 | H105: =SUMIF('AJE LTD'!A:A,'TB LTD 2021'!B105,'AJE LTD'!D:D) -> 0 | I105: =SUM(G105:H105) -> 4307.99 | M105: 50107 | N105: אחזקת שרתים AMAZON | O105: 917.25 | P105: =O105-D104 -> -34980.75 | Q105: 50115 | R105: 38044.05 | S105: =SUMIF(B:B,Q105,G:G) -> 4000 | T105: =S105-R105 -> -34044.05
A106: 53 | B106: 51107 | C106: שווי א.כ.ע מו"פ | D106: 18777 | E106: =SUMIF('AJE LTD'!A:A,'TB LTD 2021'!B106,'AJE LTD'!C:C) -> 0 | F106: =SUM(D106:E106) -> 18777 | G106: 5825.3 | H106: =SUMIF('AJE LTD'!A:A,'TB LTD 2021'!B106,'AJE LTD'!D:D) -> 0 | I106: =SUM(G106:H106) -> 5825.3 | M106: 50109 | N106: רשיונות תוכנה | O106: 7476.16 | P106: =O106-D105 -> -6603.84 | Q106: 50116 | R106: 10139.99 | S106: =SUMIF(B:B,Q106,G:G) -> 47117 | T106: =S106-R106 -> 36977.01
A107: 53 | B107: 51108 | C107: שווי פיצויים מו"פ | D107: 35695 | E107: =SUMIF('AJE LTD'!A:A,'TB LTD 2021'!B107,'AJE LTD'!C:C) -> 0 | F107: =SUM(D107:E107) -> 35695 | G107: 11134.37 | H107: =SUMIF('AJE LTD'!A:A,'TB LTD 2021'!B107,'AJE LTD'!D:D) -> 0 | I107: =SUM(G107:H107) -> 11134.37 | M107: 50110 | N107: קבלני משנה מו"פ | O107: -57550 | P107: =O107-D106 -> -76327 | Q107: 50118 | R107: 133892.6 | S107: =SUMIF(B:B,Q107,G:G) -> 0 | T107: =S107-R107 -> -133892.6
...

Sheet AJE LTD
I1: 3.11 | J1: 3.2293
A2: GL# | B2: GL Description | C2: ILS | D2: USD | E2: Details | I2: 31.12.2021 | J2: ממוצע 2021
A3: 20605 | B3: מקדמות בגין עודפות 2020 | C3: -2080 | D3: -669 | E3: הפחתת נכס מקדמות עודפות-אין צפי לקיזוז בעתיד הנראה לעין
A4: NEW1 | B4: הפחתת נכס מקדמות עודפות | C4: =-C3 -> 2080 | D4: =-D3 -> 669
A6: NEW2 | B6: Options expenses R&D | C6: =D6*$J$1 -> 119462.71 | D6: 36993.376 | E6: Options exp
A7: NEW3 | B7: Options expenses Marketing | C7: =D7*$J$1 -> 4208.8113 | D7: 1303.32
A8: NEW4 | B8: Options expenses G&A | C8: =D8*$J$1 -> 6362.7702 | D8: 1970.3249
A9: 200161 | B9: INC | C9: =SUM(C6:C8)*-1 -> -130034.29 | D9: =SUM(D6:D8)*-1 -> -40267.021
A11: NEW5 | B11: R&D Allocation | C11: ='Allocation - G&A'!I3 -> 256287.19 | D11: ='Allocation - G&A'!J3 -> 78920.731 | E11: Expenses allocation
A12: NEW6 | B12: Marketing Allocation | C12: ='Allocation - G&A'!I5 -> 102514.88 | D12: ='Allocation - G&A'!J5 -> 31568.292
A13: NEW7 | B13: G&A Allocation | C13: =SUM(C11:C12)*-1 -> -358802.07 | D13: =SUM(D11:D12)*-1 -> -110489.02
A15: 90002 | B15: הפרשי שער | C15: 0 | D15: 91.2 | E15: שערוך יתרת ספק ל-31.12.21
A16: 200003 | B16: נשיץ ברנדס אמיר ושות', עורכי דין | C16: 0 | D16: =-D15 -> -91.2
A18: 200086 | B18: אברם גילברט | C18: =-C19 -> 16523.52 | D18: =-D19 -> 5313.03 | E18: רישום הענקת האופציות של אברום מול קרן הון בגין אופציות בחברת האם
A19: 200161 | B19: Treeverse, Inc | C19: -16523.52 | D19: -5313.03
A21: 30010 | B21: הוצאות הנפקה | C21: =-C22 -> -119901.6 | D21: =-D22 -> -35463.35 | E21: מיון הוצאות הנפקה ל-INTERCIMPANY
A22: 200161 | B22: INC | C22: 119901.6 | D22: 35463.35
A24: 200161 | B24: INC | C24: =D24*I1 -> -34355.631 | D24: ='AJE INC'!C25 -> -11046.827 | E24: עדכון של TP
A25: 65006 | B25: INC | C25: =D25*I1 -> 34355.631 | D25: ='AJE INC'!C26 -> 11046.827
A27: 20800 | B27: INC | C27: =-C28 -> -491566.32 | E27: ביטול הפרשי שער שנעשו על רכיב הוני בשנים קודמות- בספרים יש להעביר את זה מול כרטיס הפרשי שער לשנת 2020 ולא לעשות שיערוכים לכרטיס 20800
A28: 39001 | B28: יתרת רווח שנים קודמות | C28: 491566.32
A30: 20800 | B30: INC | C30: =-C31 -> -488668.63 | E30: ביטול הפרשי שער שנעשו על רכיב הוני
A31: 90002 | B31: הפרשי שער | C31: 488668.63
A33: 20200 | B33: הוצאות לשלם | D33: 59650 | E33: מיון הוצאות לשלם בגין ספקים
A34: NEW8 | B34: הוצאות לשלם בגין ספקים | D34: =-D33 -> -59650

Sheet TB INC
D1: =SUM(D3:D198) -> 2.4078872e-09 | E1: =SUM(E3:E198) -> 1.4551915e-11 | F1: =SUM(F3:F198) -> 3.0995579e-09
B2: Account No. | C2: Account Description | D2: Balance (USD) | E2: AJE USD | F2: Balance USD
A3: 10 | B3: =LEFT(C3,4) -> 1010 | C3: 1010 Chase Checking:2986 Checking Leumi Activity - Deposit Accounts | D3: 13512450 | E3: =SUMIF('AJE INC'!A:A,'TB INC'!B3,'AJE INC'!C:C) -> 0 | F3: =D3+E3 -> 13512450
A4: 10 | B4: =LEFT(C4,4) -> 1020 | C4: 1020 Chase Checking: INC - BUSINESS MONEY MARKET | D4: 3554650 | E4: =SUMIF('AJE INC'!A:A,'TB INC'!B4,'AJE INC'!C:C) -> 0 | F4: =D4+E4 -> 3554650
A5: 10 | B5: =LEFT(C5,4) -> 1030 | C5: 1030 Chase Checking:Time Deposit | D5: 20000 | E5: =SUMIF('AJE INC'!A:A,'TB INC'!B5,'AJE INC'!C:C) -> 0 | F5: =D5+E5 -> 20000
A6: 10 | B6: =LEFT(C6,4) -> 1015 | C6: 1015 Euro Account | D6: 56618.33 | E6: =SUMIF('AJE INC'!A:A,'TB INC'!B6,'AJE INC'!C:C) -> 0 | F6: =D6+E6 -> 56618.33
A7: 10 | B7: =LEFT(C7,4) -> 1025 | C7: 1025 CAD Account | D7: 120941.99 | E7: =SUMIF('AJE INC'!A:A,'TB INC'!B7,'AJE INC'!C:C) -> 0 | F7: =D7+E7 -> 120941.99
A8: 12 | B8: =LEFT(C8,4) -> 1100 | C8: 1100 Accounts Receivable | D8: 0 | E8: =SUMIF('AJE INC'!A:A,'TB INC'!B8,'AJE INC'!C:C) -> 0 | F8: =D8+E8 -> 0
A9: 13 | B9: =LEFT(C9,4) -> 1300 | C9: 1300 Prepaid Expenses | D9: 9166.67 | E9: =SUMIF('AJE INC'!A:A,'TB INC'!B9,'AJE INC'!C:C) -> 0 | F9: =D9+E9 -> 9166.67
A10: 14 | B10: =LEFT(C10,4) -> 1400 | C10: 1400 Security Deposits | D10: 1000 | E10: =SUMIF('AJE INC'!A:A,'TB INC'!B10,'AJE INC'!C:C) -> 0 | F10: =D10+E10 -> 1000
A11: 36 | B11: =LEFT(C11,4) -> 1410 | C11: 1410 Inter Company account | D11: 4865788 | E11: =SUMIF('AJE INC'!A:A,'TB INC'!B11,'AJE INC'!C:C) -> 21163.528 | F11: =D11+E11 -> 4886951.6
A12: 27 | B12: =LEFT(C12,4) -> 1601 | C12: 1601 Fixed Assets:Fixed Asset Computers | D12: 2151.26 | E12: =SUMIF('AJE INC'!A:A,'TB INC'!B12,'AJE INC'!C:C) -> 0 | F12: =D12+E12 -> 2151.26
A13: 28 | B13: =LEFT(C13,4) -> 1611 | C13: 1611 Fixed Assets:Fixed Assets- Accumulated Depreciation:Accumulated Depreciation- Computers | D13: -537.84 | E13: =SUMIF('AJE INC'!A:A,'TB INC'!B13,'AJE INC'!C:C) -> 0 | F13: =D13+E13 -> -537.84
A14: 31 | B14: =LEFT(C14,4) -> 2000 | C14: 2000 Accounts Payable | D14: -2715.64 | E14: =SUMIF('AJE INC'!A:A,'TB INC'!B14,'AJE INC'!C:C) -> 0 | F14: =D14+E14 -> -2715.64
... A49: 55 | B49: =LEFT(C49,4) -> 6720 | C49: 6720 IT & Related Expenses:Software Subscription | D49: 371 | E49: =SUMIF('AJE INC'!A:A,'TB INC'!B49,'AJE INC'!C:C) -> 0 | F49: =D49+E49 -> 371
A50: 55 | C50: 6730 IT & Related Expenses:Software Expenses <$1k | D50: 699.98 | E50: =SUMIF('AJE INC'!A:A,'TB INC'!B50,'AJE INC'!C:C) -> 0 | F50: =D50+E50 -> 699.98
A51: 58 | C51: 8010 Taxes:Federal | D51: 2500 | E51: =SUMIF('AJE INC'!A:A,'TB INC'!B51,'AJE INC'!C:C) -> 0 | F51: =D51+E51 -> 2500
A52: 58 | C52: 8020 Taxes:State | D52: 7956.46 | E52: =SUMIF('AJE INC'!A:A,'TB INC'!B52,'AJE INC'!C:C) -> 0 | F52: =D52+E52 -> 7956.46
A53: 56 | C53: Bank Charges & Fees | D53: 2216.3 | E53: =SUMIF('AJE INC'!A:A,'TB INC'!B53,'AJE INC'!C:C) -> 0 | F53: =D53+E53 -> 2216.3
A54: 56 | C54: Interest Paid | D54: 105.85 | E54: =SUMIF('AJE INC'!A:A,'TB INC'!B54,'AJE INC'!C:C) -> 0 | F54: =D54+E54 -> 105.85
A55: 58 | C55: Taxes & Licenses | D55: 622.64 | E55: =SUMIF('AJE INC'!A:A,'TB INC'!B55,'AJE INC'!C:C) -> 0 | F55: =D55+E55 -> 622.64
A56: 56 | B56: =LEFT(C56,4) -> 7010 | C56: 7010 Other Income:Interest Received | D56: -1897.85 | F56: =D56+E56 -> -1897.85
A57: 56 | C57: Exchange Gain or Loss | D57: 3012.79 | F57: =D57+E57 -> 3012.79
A58: 56 | C58: Other Miscellaneous Expense | D58: 0 | E58: =SUMIF('AJE INC'!A:A,'TB INC'!B58,'AJE INC'!C:C) -> 0 | F58: =D58+E58 -> 0
A59: 54 | B59: NEW2 | C59: Sales Options expenses | E59: =SUMIF('AJE INC'!A:A,'TB INC'!B59,'AJE INC'!C:C) -> 707.59677 | F59: =D59+E59 -> 707.59677
A60: 55 | B60: NEW3 | C60: Donation Exp "Tmura" | E60: =SUMIF('AJE INC'!A:A,'TB INC'!B60,'AJE INC'!C:C) -> 9655.0902 | F60: =D60+E60 -> 9655.0902
A61: 40 | B61: NEW4 | C61: Ordinary shares | E61: =SUMIF('AJE INC'!A:A,'TB INC'!B61,'AJE INC'!C:C) -> -20105 | F61: =D61+E61 -> -20105
A62: 42 | B62: NEW5 | C62: Seed Round shares | E62: =SUMIF('AJE INC'!A:A,'TB INC'!B62,'AJE INC'!C:C) -> -16000 | F62: =D62+E62 -> -16000
A63: 43 | B63: NEW6 | C63: Preferred A shares | E63: =SUMIF('AJE INC'!A:A,'TB INC'!B63,'AJE INC'!C:C) -> -10363.64 | F63: =D63+E63 -> -10363.64
E64: =SUMIF('AJE INC'!A:A,'TB INC'!B64,'AJE INC'!C:C) -> 0 | F64: =D64+E64 -> 0
E65: =SUMIF('AJE INC'!A:A,'TB INC'!B65,'AJE INC'!C:C) -> 0 | F65: =D65+E65 -> 0
E66: =SUMIF('AJE INC'!A:A,'TB INC'!B66,'AJE INC'!C:C) -> 0 | F66: =D66+E66 -> 0
E67: =SUMIF('AJE INC'!A:A,'TB INC'!B67,'AJE INC'!C:C) -> 0 | F67: =D67+E67 -> 0
E68: =SUMIF('AJE INC'!A:A,'TB INC'!B68,'AJE INC'!C:C) -> 0 | F68: =D68+E68 -> 0
E69: =SUMIF('AJE INC'!A:A,'TB INC'!B69,'AJE INC'!C:C) -> 0 | F69: =D69+E69 -> 0
E70: =SUMIF('AJE INC'!A:A,'TB INC'!B70,'AJE INC'!C:C) -> 0 | F70: =D70+E70 -> 0
E71: =SUMIF('AJE INC'!A:A,'TB INC'!B71,'AJE INC'!C:C) -> 0 | F71: =D71+E71 -> 0
E72: =SUMIF('AJE INC'!A:A,'TB INC'!B72,'AJE INC'!C:C) -> 0 | F72: =D72+E72 -> 0
E73: =SUMIF('AJE INC'!A:A,'TB INC'!B73,'AJE INC'!C:C) -> 0 | F73: =D73+E73 -> 0
E74: =SUMIF('AJE INC'!A:A,'TB INC'!B74,'AJE INC'!C:C) -> 0 | F74: =D74+E74 -> 0
E75: =SUMIF('AJE INC'!A:A,'TB INC'!B75,'AJE INC'!C:C) -> 0 | F75: =D75+E75 -> 0
... E79: =SUMIF('AJE INC'!A:A,'TB INC'!B79,'AJE INC'!C:C) -> 0 | F79: =D79+E79 -> 0

Sheet AJE INC
A2: GL# | B2: GL Description | C2: USD | D2: Details
A6: 1410 | B6: 1410 Inter Company account | C6: ='AJE LTD'!D9*-1 -> 40267.021 | D6: Options 2021
A7: 3210 | B7: Options fund | C7: =-C6 -> -40267.021
A9: NEW2 | B9: Sales Options expenses | C9: 707.59677 | D9: Options 2021
A10: =A7 -> 3210 | B10: Options fund | C10: =-C9 -> -707.59677
A13: =LEFT(B13,4) -> 3200 | B13: 3200 Retained Earnings | C13: =-C14 -> -6891.32 | D13: reclassification exp from retained earning to travel
A14: 6310 | B14: 6310 Travel & Entertainment:Airfare | C14: 6891.32
A16: 1410 | B16: 1410 Inter Company account | C16: 5313.03 | D16: options grants of Avrom Gilbert
A17: 3210 | B17: 3210 Options Fund | C17: -5313.03 | D17: consultant of LTD
A19: 1410 | B19: 1410 Inter Company account | C19: ='AJE LTD'!D21 -> -35463.35 | D19: Issuance cost that paid by Ltd
A20: 3130 | B20: 3130 Issuance Cost | C20: =-C19 -> 35463.35
A22: NEW3 | B22: Donation Exp "Tmura" | C22: =Warrants!C20 -> 9655.0902 | D22: Warrants - "Tmura"
A23: 3210 | B23: Options fund | C23: =-C22 -> -9655.0902
A25: 4010 | B25: 4010 Intercompany Income | C25: ='TP 2021'!C7*-1 -> -11046.827 | D25: Adding intercompany income
A26: 1410 | B26: 1410 Inter Company account | C26: =-C25 -> 11046.827
A29: =LEFT(B29,4) -> 3110 | B29: 3110 Series seed Preferred Stock | C29: =SUM(C30:C32)*-1 -> 46468.64 | D29: Reclassification- additional paid in dapital to share (par value)
A30: NEW4 | B30: Ordinary shares | C30: =-'Equity '!D11 -> -20105
A31: NEW5 | B31: Seed Round shares | C31: =-'Equity '!F6 -> -16000
A32: NEW6 | B32: Preferred A shares | C32: =-'Equity '!H7 -> -10363.64

Sheet Equity 
B2: Statement of Changes in Equity-
B4: CONS- USD
C5: Number of Ordinary shares | D5: Amount of Ordinary shares | E5: Number of Seed Preferred stock | F5: Amount of Seed Preferred stock | G5: Number of A Preferred shares | H5: Amount of A Preferred stock | I5: Issuance Costs | J5: Additional paid in capital | K5: Accumulated deficit | L5: Total
B6: Balance as at 31/12/2020 | C6: 2000000 | D6: 20000 | E6: 1600000 | F6: =E6*0.01 -> 16000 | G6: 0 | H6: 0 | I6: -85128 | J6: =7896662.25917829-I6 -> 7981790.3 | K6: -1248109 | L6: =D6+F6+I6+J6+K6 -> 6684553.3 | N6: =K6+1248109 -> 0
B7: Round A | G7: ='Investment 2021'!C11 -> 1036364 | H7: ='Investment 2021'!D11 -> 10363.64 | I7: ='Investment 2021'!B25*-1 -> -122963.78 | J7: ='Investment 2021'!F11 -> 14239634 | L7: =D7+H7+I7+J7+K7+F7 -> 14127034
B8: Stock-based compensation | F8: =E8/1000 -> 0 | J8: ='AJE INC'!C7*-1+'AJE INC'!C10*-1+'AJE INC'!C17*-1+'AJE INC'!C23*-1 -> 55942.738 | L8: =D8+H8+I8+J8+K8 -> 55942.738
B9: Options exercised | C9: ='Investment 2021'!C18 -> 10500 | D9: ='Investment 2021'!D18 -> 105 | J9: ='Investment 2021'!F18 -> 10367.5 | L9: =D9+H9+I9+J9+K9 -> 10472.5
B10: Loss for the year | K10: ='2021'!E43*-1 -> -2702097.7 | L10: =D10+H10+I10+J10+K10 -> -2702097.7
B11: Balance as at 31/12/2021 | C11: =SUM(C6:C10) -> 2010500 | D11: =SUM(D6:D10) -> 20105 | E11: =SUM(E6:E10) -> 1600000 | F11: =SUM(F6:F10) -> 16000 | G11: =SUM(G6:G10) -> 1036364 | H11: =SUM(H6:H10) -> 10363.64 | I11: =SUM(I6:I10) -> -208091.78 | J11: =SUM(J6:J10) -> 22287734 | ... L11: =SUM(L6:L10) -> 18175904
B14: Check | L14: =L11+SUM('2021'!E22:E30) -> 0.049178287
J16: =J7+I7*-1 -> 14362598

Sheet CF 
A2: תזרים מזומנים 2020 USD | N2: 44196 | O2: 44561
B3: 31.12.2020 | C3: שוטפת | E3: השקעה | F3: מימון | G3: העברות | H3: שינוי במזומן | I3: 31.12.2021 | J3: שינוי | K3: בדיקה | M3: Purchases | N3: 41186.38 | O3: ='2021'!E10 -> 214203
A4: Cash and cash equivalents | B4: 6801987.9 | H4: =I4-B4 -> 11417175 | I4: ='2021'!E5 -> 18219163 | J4: =I4-B4 -> 11417175 | K4: =J4-C4-E4-F4-G4-H4-D4 -> 0 | M4: Depreciation | N4: -7303.96 | O4: ='2021'!E11 -> -23340.34
A5: Restricted Cash | B5: 31111.515 | C5: =I5-B5 -> 1053.4952 | I5: ='2021'!E6 -> 32165.01 | J5: =I5-B5 -> 1053.4952 | K5: =J5-C5-E5-F5-G5-H5-D5 -> 0
A6: Accounts receivable | J6: =I6-B6 -> 0 | K6: =J6-C6-E6-F6-G6-H6-D6 -> 0
A7: Other account receivables and prepaid expenses | B7: 15055.01 | C7: =I7-B7 -> 45455.8 | I7: ='2021'!E8+'2021'!E9 -> 60510.81 | J7: =I7-B7 -> 45455.8 | K7: =J7-C7-E7-F7-G7-H7-D7 -> 0
A8: Fixed assets, net | B8: 33882.42 | C8: =O4-N4 -> -16036.38 | E8: =O3-N3 -> 173016.62 | I8: ='2021'!E10+'2021'!E11 -> 190862.66 | J8: =I8-B8 -> 156980.24 | K8: =J8-C8-E8-F8-G8-H8-D8 -> 0
A9: Trade payables | B9: -10200 | C9: =I9-B9 -> -44467 | I9: -54667 | J9: =I9-B9 -> -44467
A10: Acrrued expenses | B10: -34663 | C10: =I10-B10 -> 4575 | I10: -30088 | J10: =I10-B10 -> 4575 | K10: =J10-C10-E10-F10-G10-H10-D10 -> 0
A11: Other current liabilties | B11: -152620.66 | C11: =I11-B11 -> -89421.37 | I11: ='2021'!E17+'2021'!E18 -> -242042.03 | J11: =I11-B11 -> -89421.37 | K11: =J11-C11-E11-F11-G11-H11-D11 -> 0
A12: SAFE Liab | J12: =I12-B12 -> 0
A13: Ordinary shares | B13: -20000 | F13: =I13-B13 -> -105 | I13: =B13+'Investment 2021'!D18*-1 -> -20105 | J13: =I13-B13 -> -105 | K13: =J13-C13-E13-F13-G13-H13-D13 -> 0
A14: Preferred shares SEED | B14: -16000 | F14: =I14-B14 -> -10363.64 | I14: =B14+'Investment 2021'!D11*-1 -> -26363.64 | J14: =I14-B14 -> -10363.64 | K14: =J14-C14-E14-F14-G14-H14-D14 -> 0
A15: Receivable on account of shares | J15: =I15-B15 -> 0 | K15: =J15-C15-E15-F15-G15-H15-D15 -> 0
A16: Share based compensation | B16: -17790.692 | C16: =I16-B16 -> -55942.737 | I16: ='2021'!E27 -> -73733.428 | J16: =I16-B16 -> -55942.737 | K16: =J16-C16-E16-F16-G16-H16-D16 -> 0
A17: Additional paid in capital | B17: -7964000 | F17: =I17-B17 -> -14250001 | I17: ='2021'!E25 -> -22214001 | J17: =I17-B17 -> -14250001 | K17: =J17-C17-E17-F17-G17-H17-D17 -> 0
A18: Issuance Costs | B18: 85128.432 | F18: =I18-B18 -> 122963.35 | I18: ='2021'!E26 -> 208091.78 | J18: =I18-B18 -> 122963.35 | K18: =J18-C18-E18-F18-G18-H18-D18 -> 0
A19: Accumulated deficit | B19: 1248109.2 | C19: =I19-B19 -> 2702098 | I19: ='2021'!E29+'2021'!E30 -> 3950207.2 | J19: =I19-B19 -> 2702098 | K19: =J19-C19-E19-F19-G19-H19-D19 -> 0
I20: =E49+E50+E51 -> 0 | J20: =I20-B20 -> 0 | K20: =J20-C20-E20-F20-G20-H20-D20 -> 0
B21: =SUM(B4:B20) -> 0.11234837 | C21: =SUM(C4:C20) -> 2547314.8 | D21: =SUM(D4:D20) -> 0 | E21: =SUM(E4:E20) -> 173016.62 | F21: =SUM(F4:F20) -> -14137507 | G21: =SUM(G4:G20) -> 0 | H21: =SUM(H4:H20) -> 11417175 | I21: =SUM(I4:I20) -> -0.090000002 | ... K21: =SUM(K4:K20) -> 0
A27: Cash flows from operating activities: | C27: Cons USD
A29: Net loss | C29: ='2021'!E43*-1 -> -2702097.7
A30: Adjustments to reconcile net loss to net cash used in operating activities:
A31: Depreciation | C31: =-C8 -> 16036.38
A32: Share based compensation | C32: =-C16 -> 55942.737
A33: Changes in assets and liabilities:
A34: Increase in other accounts receivables and prepaid expenses | C34: =-C7 -> -45455.8
A35: Increase in Trade payables and acrrued expenses | C35: =-C10-C11 -> 84846.37
A36: Increase in other current liabilities
C37: =SUM(C31:C36) -> 111369.69
A39: Net cash used in operating activities | C39: =C29+C37 -> -2590728
A41: Cash flows from investing activities:
A42: Restricted cash | C42: =-C5 -> -1053.4952
A43: Purchase of property and equipment | C43: =-E8 -> -173016.62
A44: Net cash used in investing activities | C44: =C43+C42 -> -174070.12
A46: Cash flows from financing activities:
A47: Proceeds from issuance of Round A Preferred shares, net | C47: =-F17-F18 -> 14127038
A48: Preferred shares SEED | C48: =-F14-F13 -> 10468.64
A50: Net cash provided by financing activities | C50: =C47+C49+C48 -> 14137507
A52: Change in cash and cash equivalents | C52: =C39+C44+C50 -> 11372708
A53: Cash and cash equivalents at beginning of period | C53: =B4 -> 6801987.9
A54: Cash and cash equivalents at end of period | C54: =C52+C53 -> 18174696
A57: Supplemental disclosures of noncash activities:
A60: Fair Value of SAFE preferred A Shares | C60: =G12 -> 0

Sheet Allocation - G&A
A2: LTD | G2: LOC | H2: # EMP | I2: NIS | J2: USD
C3: ILS | D3: USD | G3: R&D | H3: 10 | I3: =$C$23*H3/$H$6 -> 256287.19 | J3: =$D$23*H3/$H$6 -> 78920.731
A4: 70008 | B4: ביטוח דירקטורים | C4: =SUMIF('TB LTD 2021'!B:B,'Allocation - G&A'!A4,'TB LTD 2021'!F:F) -> 12696.36 | D4: =SUMIF('TB LTD 2021'!B:B,'Allocation - G&A'!A4,'TB LTD 2021'!I:I) -> 3806.82 | G4: G&A | H4: 2 | I4: =$C$23*H4/$H$6 -> 51257.439 | J4: =$D$23*H4/$H$6 -> 15784.146
A5: 70010 | B5: מתנות עובדים | C5: =SUMIF('TB LTD 2021'!B:B,'Allocation - G&A'!A5,'TB LTD 2021'!F:F) -> 18983 | D5: =SUMIF('TB LTD 2021'!B:B,'Allocation - G&A'!A5,'TB LTD 2021'!I:I) -> 5821.41 | G5: Marketing | H5: 4 | I5: =$C$23*H5/$H$6 -> 102514.88 | J5: =$D$23*H5/$H$6 -> 31568.292
A6: 70011 | B6: שכר דירה | C6: =SUMIF('TB LTD 2021'!B:B,'Allocation - G&A'!A6,'TB LTD 2021'!F:F) -> 194210.24 | D6: =SUMIF('TB LTD 2021'!B:B,'Allocation - G&A'!A6,'TB LTD 2021'!I:I) -> 60343.81 | G6: Total | H6: =SUM(H3:H5) -> 16 | I6: =$C$23*H6/$H$6 -> 410059.51 | J6: =$D$23*H6/$H$6 -> 126273.17
A7: 70012 | B7: שליחויות והובלות | C7: =SUMIF('TB LTD 2021'!B:B,'Allocation - G&A'!A7,'TB LTD 2021'!F:F) -> 5429.96 | D7: =SUMIF('TB LTD 2021'!B:B,'Allocation - G&A'!A7,'TB LTD 2021'!I:I) -> 1707.64
A8: 70013 | B8: אינטרנט ותקשורת | C8: =SUMIF('TB LTD 2021'!B:B,'Allocation - G&A'!A8,'TB LTD 2021'!F:F) -> 5402 | D8: =SUMIF('TB LTD 2021'!B:B,'Allocation - G&A'!A8,'TB LTD 2021'!I:I) -> 1690.96
A9: 70014 | B9: דואר | C9: =SUMIF('TB LTD 2021'!B:B,'Allocation - G&A'!A9,'TB LTD 2021'!F:F) -> 140.3 | D9: =SUMIF('TB LTD 2021'!B:B,'Allocation - G&A'!A9,'TB LTD 2021'!I:I) -> 43.31
A10: 70015 | B10: טלפון | C10: =SUMIF('TB LTD 2021'!B:B,'Allocation - G&A'!A10,'TB LTD 2021'!F:F) -> 1799.39 | D10: =SUMIF('TB LTD 2021'!B:B,'Allocation - G&A'!A10,'TB LTD 2021'!I:I) -> 555.3
A11: 70016 | B11: כיבודים | C11: =SUMIF('TB LTD 2021'!B:B,'Allocation - G&A'!A11,'TB LTD 2021'!F:F) -> 33448.7 | D11: =SUMIF('TB LTD 2021'!B:B,'Allocation - G&A'!A11,'TB LTD 2021'!I:I) -> 10334.39
A12: 70017 | B12: אחזקת משרד | C12: =SUMIF('TB LTD 2021'!B:B,'Allocation - G&A'!A12,'TB LTD 2021'!F:F) -> 7388.66 | D12: =SUMIF('TB LTD 2021'!B:B,'Allocation - G&A'!A12,'TB LTD 2021'!I:I) -> 2304.51
A13: 70018 | B13: מיסי עירייה | C13: =SUMIF('TB LTD 2021'!B:B,'Allocation - G&A'!A13,'TB LTD 2021'!F:F) -> 40937.87 | D13: =SUMIF('TB LTD 2021'!B:B,'Allocation - G&A'!A13,'TB LTD 2021'!I:I) -> 12758.21
A14: 70020 | B14: חשמל | C14: =SUMIF('TB LTD 2021'!B:B,'Allocation - G&A'!A14,'TB LTD 2021'!F:F) -> 2744.33 | D14: =SUMIF('TB LTD 2021'!B:B,'Allocation - G&A'!A14,'TB LTD 2021'!I:I) -> 847.26
A15: 70027 | B15: אגרות | C15: =SUMIF('TB LTD 2021'!B:B,'Allocation - G&A'!A15,'TB LTD 2021'!F:F) -> 1505 | D15: =SUMIF('TB LTD 2021'!B:B,'Allocation - G&A'!A15,'TB LTD 2021'!I:I) -> 466.38
A16: 70028 | B16: חניה | C16: =SUMIF('TB LTD 2021'!B:B,'Allocation - G&A'!A16,'TB LTD 2021'!F:F) -> 7814.9 | D16: =SUMIF('TB LTD 2021'!B:B,'Allocation - G&A'!A16,'TB LTD 2021'!I:I) -> 2445.41
A17: 70033 | B17: נקיון | C17: =SUMIF('TB LTD 2021'!B:B,'Allocation - G&A'!A17,'TB LTD 2021'!F:F) -> 33923.87 | D17: =SUMIF('TB LTD 2021'!B:B,'Allocation - G&A'!A17,'TB LTD 2021'!I:I) -> 10483.5
A18: 74000 | B18: הוצאות פחת מחשבים ותוכנה | C18: =SUMIF('TB LTD 2021'!B:B,'Allocation - G&A'!A18,'TB LTD 2021'!F:F) -> 41785.95 | D18: =SUMIF('TB LTD 2021'!B:B,'Allocation - G&A'!A18,'TB LTD 2021'!I:I) -> 12127.58
... A21: 74003 | B21: הוצאות פחת שיפורים במושכר | C21: =SUMIF('TB LTD 2021'!B:B,'Allocation - G&A'!A21,'TB LTD 2021'!F:F) -> 6853.29 | D21: =SUMIF('TB LTD 2021'!B:B,'Allocation - G&A'!A21,'TB LTD 2021'!I:I) -> 2124.6
C23: =SUM(C4:C19) -> 410059.51 | D23: =SUM(D4:D19) -> 126273.17

Sheet FS
A1: Click here to enter input
A3: דוחות כספיים ליום 31 בדצמבר, 2020
A5: דוח על המצב הכספי
E8: ליום 31 בדצמבר,
E9: 2020 | G9: 2019
C10: באור | E10: אלפי ש"ח
A11: נכסים שוטפים
A13: מזומנים ושווי מזומנים | C13: =A300 -> ה. | E13: ='2021'!G5/1000 -> 2968.5043 | G13: 0
A14: מזומן משועבד | C14: =A309 -> ו. | E14: 0 | G14: 0
A15: פקדונות לזמן קצר | C15: =A313 -> ז. | E15: 0 | G15: 0
A16: לקוחות | E16: 0 | G16: 0
A17: הוצאות מראש | G17: 0
A18: חייבים ויתרות חובה | E18: ='2021'!G9/1000+'2021'!G8/1000 -> 157.7115 | G18: 0
A19: צדדים קשורים | C19: באור 12: - | E19: 0 | G19: 0
E21: =SUM(E13:E20) -> 3126.2158 | G21: =SUM(G13:G20) -> 0
A23: נכסים לא שוטפים
A25: פקדונות לזמן ארוך | E25: 0 | G25: 0
A26: רכוש קבוע | C26: =_Toc26607242 -> באור 3: - | E26: ='2021'!G10/1000+'2021'!G11/1000 -> 605.64504 | G26: 0
A27: צדדים קשורים | C27: באור 12: - | E27: 0 | G27: 0
E29: =SUM(E25:E28) -> 605.64504 | G29: =SUM(G25:G28) -> 0
A32: סה"כ נכסים | E32: =E21+E29-1 -> 3730.8608 | G32: =G21+G29 -> 0
A35: הבאורים המצורפים מהווים חלק בלתי נפרד מהדוחות הכספיים.
A37: דוחות על המצב הכספי
E40: ליום 31 בדצמבר,
E41: =E9 -> 2020 | G41: =G9 -> 2019
C42: באור | E42: אלפי ש"ח
A44: התחייבויות שוטפות
A45: התחייבויות לתאגידים בנקאיים | E45: 0 | G45: 0
A46: התחייבויות לספקים ולנותני שירותים | E46: =-('2021'!G15)/1000 -> -21.52196 | G46: 0
A47: זכאים ויתרות זכות | C47: =A502 -> באור 5: - | E47: =-(+'2021'!G16+'2021'!G17+'2021'!G18+'2021'!G19)/1000 -> 1000.2134 | G47: 0
A48: צדדים קשורים | C48: באור 12: - | E48: 0 | G48: 0
E50: =SUM(E45:E49) -> 978.69148 | G50: =SUM(G45:G49) -> 0
A51: התחייבויות לא שוטפות
A52: התחייבויות לתאגידים בנקאיים | C52: =A518 -> באור 6: - | E52: 0 | G52: 0
A53: התחייבויות בשל סיום יחסי עובד-מעביד, נטו | C53: =A531 -> באור 8: - | E53: 0 | G53: 0
A54: צדדים קשורים | C54: באור 12: - | E54: 0 | G54: 0
E56: =SUM(E52:E55) -> 0 | G56: =SUM(G52:G55) -> 0
A58: סך התחייבויות | E58: =E50+E56 -> 978.69148 | G58: =G50+G56 -> 0
A60: הלוואת בעלים המירה | E60: 0 | G60: 0
A62: הון עצמי
A63: הון מניות | C63: באור 10: - | E63: 0 | G63: 0
A64: פרמיה על מניות | C64: באור 10: - | E64: =-('2021'!G26+'2021'!#REF!+'2021'!G27)/1000 -> #REF! | G64: 0
A65: יתרת רווח (הפסד) | C65: באור 10: - | E65: ='2021'!G30/1000 -> 8843.6576 | G65: 0
A67: סך ההון העצמי | E67: =SUM(E63:E66) -> #REF! | G67: =SUM(G63:G66) -> 0
A69: סך התחייבויות והון עצמי | E69: =E67+E58 -> #REF! | G69: =G67+G58 -> 0
A73: הבאורים המצורפים מהווים חלק בלתי נפרד מהדוחות הכספיים.
A76: תאריך אישור הדוחות הכספיים | F76: דירקטור
A79: דוחות על הרווח הכולל
C82: לשנה שהסתיימה ביום
C83: 31 בדצמבר,
C84: =E41 -> 2020 | E84: =G41 -> 2019
C85: אלפי ש"ח
A87: הכנסות ממכירות | C87: 0 | E87: 0
A88: עלות המכירות | C88: 0 | E88: 0
A90: רווח (הפסד) גולמי | C90: =C87-C88 -> 0 | E90: =E87-E88 -> 0
A93: הוצאות מחקר ופיתוח, נטו | B93: באור 11: - | C93: ='2021'!G37/1000 -> 5316.2848 | E93: 0
A94: הוצאות מכירה ושיווק | B94: באור 11: - | C94: ='2021'!G38/1000 -> 761.00214 | E94: 0
A95: הוצאות הנהלה וכלליות | B95: באור 11: - | C95: ='2021'!G39/1000 -> 1479.4539 | E95: 0
A97: סה"כ הוצאות תפעוליות | C97: =SUM(C93:C96) -> 7556.7409 | E97: =SUM(E93:E96) -> 0
A99: רווח (הפסד) תפעולי | C99: =C90-C97 -> -7556.7409 | E99: =E90-E97 -> 0
A101: הוצאות מימון, נטו | C101: =-'2021'!G41/1000 -> -7.68839 | E101: 0
A103: רווח (הפסד) לפני מסים על ההכנסה | C103: =C99+C101 -> -7564.4292 | E103: =E99-E101 -> 0
A104: מסים על ההכנסה (הטבת מס) | C104: 0 | E104: 0
A106: רווח נקי (הפסד) | C106: =C103-C104 -> -7564.4292 | E106: =E103-E104 -> 0
A113: הבאורים המצורפים מהווים חלק בלתי נפרד מהדוחות הכספיים.
A115: דוחות על השינויים בהון העצמי
C119: הון מניות רגילות | E119: הון | G119: פרמיה על מניות | I119: יתרת | K119: סה"כ
E120: מניות בכורה | I120: רווח (הפסד)
C121: אלפי ש"ח
A123: יתרה ליום 1 בינואר, 2019 | C123: 0 | E123: 0 | G123: 0 | I123: 0 | K123: =SUM(C123:I123) -> 0
A124: רווח נקי (הפסד) | C124: - | E124: - | G124: - | I124: 0 | K124: =SUM(C124:I124) -> 0
A125: הנפקת מניות (בניכוי הוצאות הנפקה) | C125: 0 | E125: - | G125: 0 | I125: - | K125: =SUM(C125:I125) -> 0
A126: הנפקת מניות בכורה | C126: - | E126: 0 | G126: 0 | I126: - | K126: =SUM(C126:I126) -> 0
A127: מימוש אופציות למניות | C127: - | E127: - | G127: 0 | I127: - | K127: =SUM(C127:I127) -> 0
A128: עלות תשלום מבוסס מניות | C128: - | E128: - | G128: 0 | I128: - | K128: =SUM(C128:I128) -> 0
A130: יתרה ליום 31 בדצמבר, 2019 | C130: =SUM(C123:C128) -> 0 | E130: =SUM(E123:E128) -> 0 | G130: =SUM(G123:G128) -> 0 | I130: =SUM(I123:I128) -> 0 | K130: =SUM(K123:K128) -> 0
A132: רווח נקי (הפסד) | C132: - | E132: - | G132: - | I132: =-('2021'!G30)/1000 -> -8843.6576 | K132: =SUM(C132:I132) -> -8843.6576
A133: הנפקת מניות (בניכוי הוצאות הנפקה) | C133: 0 | E133: - | G133: =-('2021'!#REF!+'2021'!G26)/1000 -> #REF! | I133: - | K133: 16181
A134: עלות תשלום מבוסס מניות | C134: - | E134: - | G134: =-'2021'!G27/1000 -> 0 | I134: - | K134: 239
A136: יתרה ליום 31 בדצמבר, 2020 | C136: =SUM(C130:C134) -> 0 | E136: =SUM(E130:E134) -> 0 | G136: =SUM(G130:G134) -> #REF! | I136: =SUM(I130:I134) -> -8843.6576 | K136: =SUM(K130:K134) -> 7576.3424
A139: הבאורים והנספח המצורפים מהווים חלק בלתי נפרד מהדוחות הכספיים.
A141: דוחות על תזרימי המזומנים
C143: לשנה שהסתיימה ביום
C144: 31 בדצמבר,
C145: =C84 -> 2020 | E145: =E84 -> 2019
C146: אלפי ש"ח
A147: תזרימי מזומנים מפעילות שוטפת
A148: רווח נקי (הפסד) | C148: =-CF!V20/1000 -> -13345.315 | E148: 0
A149: פחת | C149: =-CF!P10/1000 -> 0 | E149: 0
A150: שינוי בהתחייבויות בשל סיום יחסי עובד-מעביד, נטו | E150: 0
A151: הפסד (רווח) הון מניירות ערך | C151: 0 | E151: 0
A152: הוצאות אופציות | C152: =-CF!P19/1000 -> #REF! | E152: 0
A153: שינוי בלקוחות | C153: 0 | E153: 0
A154: שינוי בחייבים ויתרות חובה | C154: =-CF!V9/1000-CF!P7/1000 -> -157.7115 | E154: 0
A155: שינוי במלאי | C155: 0 | E155: 0
A156: שינוי בהתחייבויות לספקים ולנותני שירותים | C156: =-CF!P13/1000-CF!P14/1000 -> 225.82242 | E156: 0
A157: שינוי בזכאים ויתרות זכות | C157: =-CF!P15/1000 -> 752.86906 | E157: 0
A159: מזומנים נטו שנבעו מפעילות (ששימשו לפעילות) שוטפת | C159: =SUM(C148:C158) -> #REF! | E159: =SUM(E148:E158) -> 0
A161: תזרימי מזומנים מפעילות השקעה
A162: רכישת רכוש קבוע | C162: =-CF!R10/1000 -> 0 | E162: 0
...

Sheet CF
A2: תזרים מזומנים טריברס 2020 USD | N2: תזרים מזומנים טריברס 2020 NIS
B3: 31.12.2019 | C3: שוטפת | D3: השקעה ב- INC | E3: השקעה | F3: מימון | G3: העברות | H3: שינוי במזומן | I3: 31.12.2020 | J3: שינוי | K3: בדיקה | O3: 31.12.2019 | P3: שוטפת | Q3: השקעה אפסלר | R3: השקעה | S3: מימון | T3: העברות | U3: שינוי במזומן | V3: 31.12.2020 | W3: שינוי | X3: בדיקה
A4: מזומנים ושווי מזומנים | H4: =I4-B4 -> 18219163 | I4: =C29 -> 18219163 | J4: =I4-B4 -> 18219163 | K4: =J4-C4-E4-F4-G4-H4-D4 -> 0 | N4: מזומנים ושווי מזומנים | U4: =V4-O4 -> 2968504.3 | V4: =E29 -> 2968504.3 | W4: =V4-O4 -> 2968504.3 | X4: =W4-P4-R4-S4-T4-U4-Q4 -> 0
A5: מזומן משועבד | E5: =I5-B5-D5 -> 32165.01 | I5: =C30 -> 32165.01 | J5: =I5-B5 -> 32165.01 | K5: =J5-C5-E5-F5-G5-H5-D5 -> 0 | N5: מזומן משועבד | R5: =V5-O5-Q5 -> 100033.18 | V5: =E30 -> 100033.18 | W5: =V5-O5 -> 100033.18 | X5: =W5-P5-R5-S5-T5-U5-Q5 -> 0
A6: לקוחות | C6: =I6-G6-B6 -> 0 | I6: =C31 -> 0 | J6: =I6-B6 -> 0 | K6: =J6-C6-E6-F6-G6-H6-D6 -> 0 | N6: לקוחות | P6: =V6-U6-O6 -> 0 | V6: =E31 -> 0 | W6: =V6-O6 -> 0 | X6: =W6-P6-R6-S6-T6-U6-Q6 -> 0
A7: חייבים אחרים | C7: =I7-G7-B7 -> 43827.32 | I7: =C33 -> 43827.32 | J7: =I7-B7 -> 43827.32 | K7: =J7-C7-E7-F7-G7-H7-D7 -> 0 | N7: חייבים אחרים | P7: =V7-U7-O7 -> 133234.8 | V7: =E33 -> 133234.8 | W7: =V7-O7 -> 133234.8 | X7: =W7-P7-R7-S7-T7-U7-Q7 -> 0
A8: Long term deposits | I8: =C36 -> 0 | J8: =I8-B8 -> 0 | K8: =J8-C8-E8-F8-G8-H8-D8 -> 0 | N8: Long term deposits | R8: =V8-O8 -> 0 | V8: =+E36 -> 0 | W8: =V8-O8 -> 0 | X8: =W8-P8-R8-S8-T8-U8-Q8 -> 0
A9: הוצאות מראש | C9: =I9-G9-B9 -> 16683.49 | I9: =C32 -> 16683.49 | J9: =I9-B9 -> 16683.49 | K9: =J9-C9-E9-F9-G9-H9-D9 -> 0 | N9: הוצאות מראש | P9: =V9-U9-O9 -> 24476.7 | V9: =E32 -> 24476.7 | W9: =V9-O9 -> 24476.7 | X9: =W9-P9-R9-S9-T9-U9-Q9 -> 0
A10: רכוש קבוע נטו | I10: =C34+C35 -> 190862.66 | J10: =I10-B10 -> 190862.66 | K10: =J10-C10-E10-F10-G10-H10-D10 -> 190862.66 | N10: רכוש קבוע נטו | P10: =W36 -> 0 | R10: =W30-W31 -> 0 | V10: =E34+E35 -> 605645.04 | W10: =V10-O10 -> 605645.04 | X10: =W10-P10-R10-S10-T10-U10-Q10 -> 605645.04
A11: נכסים בלתי מוחשיים | C11: =I11-G11-B11 -> 0 | I11: 0 | J11: =I11-B11 -> 0 | K11: =J11-C11-E11-F11-G11-H11-D11 -> 0 | N11: נכסים בלתי מוחשיים | P11: =V11-U11-O11 -> 0 | V11: 0 | W11: =V11-O11 -> 0 | X11: =W11-P11-R11-S11-T11-U11-Q11 -> 0
A12: Intercompany | I12: =C44 -> -0.31 | J12: =I12-B12 -> -0.31 | K12: =J12-C12-E12-F12-G12-H12-D12 -> -0.31 | N12: Intercompany | R12: =V12-O12 -> -16198518 | V12: =E44 -> -16198518 | W12: =V12-O12 -> -16198518 | X12: =W12-P12-R12-S12-T12-U12-Q12 -> 0
A13: ספקים ונותני שירותים | C13: =I13-G13-B13 -> -54667.22 | I13: =C39 -> -54667.22 | J13: =I13-B13 -> -54667.22 | K13: =J13-C13-E13-F13-G13-H13-D13 -> 0 | N13: ספקים ונותני שירותים | P13: =V13-U13-O13 -> 21521.96 | V13: =E39 -> 21521.96 | W13: =V13-O13 -> 21521.96 | X13: =W13-P13-R13-S13-T13-U13-Q13 -> 0
A14: הוצאות לשלם | C14: =I14-G14-B14 -> -30087.38 | I14: =C40 -> -30087.38 | J14: =I14-B14 -> -30087.38 | K14: =J14-C14-E14-F14-G14-H14-D14 -> 0 | N14: הוצאות לשלם | P14: =V14-U14-O14 -> -247344.38 | V14: =E40 -> -247344.38 | W14: =V14-O14 -> -247344.38 | X14: =W14-P14-R14-S14-T14-U14-Q14 -> 0
A15: זכאים ויתרות זכות | C15: =I15-G15-B15 -> -242042.03 | I15: =C41+C42+C43 -> -242042.03 | J15: =I15-B15 -> -242042.03 | K15: =J15-C15-E15-F15-G15-H15-D15 -> 0 | N15: זכאים ויתרות זכות | P15: =V15-U15-O15 -> -752869.06 | V15: =E41+E42+E43 -> -752869.06 | W15: =V15-O15 -> -752869.06 | X15: =W15-P15-R15-S15-T15-U15-Q15 -> 0
A16: Warrants | J16: =I16-B16 -> 0 | K16: =J16-C16-E16-F16-G16-H16-D16 -> 0 | N16: Warrants | W16: =V16-O16 -> 0 | X16: =W16-P16-R16-S16-T16-U16-Q16 -> 0
A17: הכנסות נדחות | J17: =I17-B17 -> 0 | K17: =J17-C17-E17-F17-G17-H17-D17 -> 0 | N17: הכנסות נדחות | W17: =V17-O17 -> 0 | X17: =W17-P17-R17-S17-T17-U17-Q17 -> 0
A18: הלוואות זמן ארוך + ז"ק | J18: =I18-B18 -> 0 | K18: =J18-C18-E18-F18-G18-H18-D18 -> 0 | N18: הלוואות זמן ארוך + ז"ק | W18: =V18-O18 -> 0 | X18: =W18-P18-R18-S18-T18-U18-Q18 -> 0
A19: פרמיה | C19: =I19-F19-B19 -> #REF! | I19: =C48+C49+C50 -> #REF! | J19: =I19-B19 -> #REF! | K19: =J19-C19-E19-F19-G19-H19-D19 -> #REF! | N19: פרמיה | P19: =V19-S19-O19 -> #REF! | S19: 0 | V19: =E48+E49+E50 -> #REF! | W19: =V19-O19 -> #REF! | X19: =W19-P19-R19-S19-T19-U19-Q19 -> #REF!
A20: עודפים | C20: =I20-B20 -> 3950207.2 | I20: =C53+C52 -> 3950207.2 | J20: =I20-B20 -> 3950207.2 | K20: =I20-C20-D20--E20-F20-G20-H20-B20 -> 0 | N20: עודפים | P20: =V20-O20 -> 13345315 | V20: =E53+E52 -> 13345315 | W20: =V20-O20 -> 13345315 | X20: =V20-P20-Q20--R20-S20-T20-U20-O20 -> 0
A21: הון מניות | F21: =I21-B21 -> 0 | J21: =I21-B21 -> 0 | K21: =J21-C21-E21-F21-G21-H21-D21 -> 0 | N21: הון מניות | S21: =V21-O21 -> 0 | W21: =V21-O21 -> 0 | X21: =W21-P21-R21-S21-T21-U21-Q21 -> 0
B22: =SUM(B4:B21) -> 0 | C22: =SUM(C4:C21) -> #REF! | D22: =SUM(D4:D21) -> 0 | E22: =SUM(E4:E21) -> 32165.01 | F22: =SUM(F4:F21) -> 0 | G22: =SUM(G4:G21) -> 0 | H22: =SUM(H4:H21) -> 18219163 | I22: =SUM(I4:I21) -> #REF! | ... K22: =SUM(K4:K21) -> #REF! | O22: =SUM(O4:O21) -> 0 | P22: =SUM(P4:P21) -> #REF! | Q22: =SUM(Q4:Q21) -> 0 | R22: =SUM(R4:R21) -> -16098484 | S22: =SUM(S4:S21) -> 0 | T22: =SUM(T4:T21) -> 0 | U22: =SUM(U4:U21) -> 2968504.3 | V22: =SUM(V4:V21) -> #REF! | ... X22: =SUM(X4:X21) -> #REF!
C24: 3965.79
C26: 2020
C27: Stoke CONS | E27: Stoke Ltd
C28: USD | E28: NIS | K28: רכוש קבוע | W28: רכוש קבוע
A29: 10 | B29: Cash | C29: ='2021'!E5 -> 18219163 | E29: ='2021'!G5 -> 2968504.3 | K29: 13833.08 | L29: 31.12.19 | W29: 49025.65 | X29: 31.12.19
A30: 11 | B30: Restricted Cash | C30: ='2021'!E6 -> 32165.01 | E30: ='2021'!G6 -> 100033.18 | L30: תוספות | X30: תוספות
A31: 12 | B31: Accounts Receivable | C31: ='2021'!E7 -> 0 | E31: ='2021'!G7 -> 0 | L31: גריעות | X31: גריעות
A32: 13 | B32: prepaid expenses | C32: ='2021'!E8 -> 16683.49 | E32: ='2021'!G8 -> 24476.7 | K32: =K29+K30-K31 -> 13833.08 | L32: 31.12.20 | W32: =W29+W30-W31 -> 49025.65 | X32: 31.12.20
A33: 14 | B33: Other current assets | C33: ='2021'!E9 -> 43827.32 | E33: ='2021'!G9 -> 133234.8 | K33: =K32-C34 -> -200369.92 | W33: =W32-E34 -> -635132.14
A34: 27 | B34: Fixed assets - Cost | C34: ='2021'!E10 -> 214203 | E34: ='2021'!G10 -> 684157.79 | K34: פחת נצבר | W34: פחת נצבר
A35: 28 | B35: Fixed assets - Accumulated Depreciation | C35: ='2021'!E11 -> -23340.34 | E35: ='2021'!G11 -> -78512.75 | K35: -1859.92 | L35: =L29 -> 31.12.19 | W35: -6639.15 | X35: =X29 -> 31.12.19
A36: 29 | B36: Long term deposits | C36: ='2021'!E12 -> 0 | E36: ='2021'!G12 -> 0 | L36: הוצאות פחת | X36: הוצאות פחת
C37: =SUM(C29:C36) -> 18502701 | E37: =SUM(E29:E36) -> 3831894 | L37: גריעות | X37: גריעות
K38: =K35+K36-K37 -> -1859.92 | L38: =L32 -> 31.12.20 | W38: =W35+W36-W37 -> -6639.15 | X38: =X32 -> 31.12.20
A39: 31 | B39: Trade payables | C39: ='2021'!E15 -> -54667.22 | E39: ='2021'!G15 -> 21521.96 | K39: =K38-C35 -> 21480.42 | W39: =W38-E35 -> 71873.6
A40: 32 | B40: Accrued expenses | C40: ='2021'!E16 -> -30087.38 | E40: ='2021'!G16 -> -247344.38
A41: 33 | B41: Employees and payroll accruals | C41: ='2021'!E17 -> -142655.32 | E41: ='2021'!G17 -> -443776.38
A42: 34 | B42: Employee institution | C42: ='2021'!E18 -> -99386.71 | E42: ='2021'!G18 -> -309092.68 | K42: Option fund | W42: Option fund
A43: 35 | B43: Other current liabilities | C43: ='2021'!E19 -> 0 | E43: ='2021'!G19 -> 0 | K43: -67755.671 | L43: =L35 -> 31.12.19 | W43: -240058.24 | X43: =X35 -> 31.12.19
A44: 36 | B44: Intercompany | C44: ='2021'!E20 -> -0.31 | E44: ='2021'!G20 -> -16198518 | K44: ='AJE LTD'!D9 -> -40267.021 | L44: הוצאות אופציות | W44: ='AJE LTD'!C9 -> -130034.29 | X44: הוצאות אופציות
A45: 37 | B45: Long term provisions | C45: ='2021'!E21 -> 0 | E45: ='2021'!G21 -> 0 | K45: =SUM(K43:K44) -> -108022.69 | L45: =L38 -> 31.12.20 | W45: =SUM(W43:W44) -> -370092.53 | X45: =X38 -> 31.12.20
A46: 40 | B46: Ordinary shares | C46: ='2021'!E24 -> -10363.64 | E46: ='2021'!G24 -> 0 | K46: =K45-C50 -> -34289.264 | W46: =W45-E50 -> -370092.53
A47: 41 | B47: Preferred A shares | C47: ='2021'!E25 -> -22214001 | E47: ='2021'!G25 -> 0
A48: 44 | B48: Issuance costs | C48: ='2021'!E26 -> 208091.78 | E48: ='2021'!G26 -> 0
A49: 45 | B49: Additional paid in capital | C49: ='2021'!#REF! -> #REF! | E49: ='2021'!#REF! -> #REF!
A50: 46 | B50: Option fund | C50: ='2021'!E27 -> -73733.428 | E50: ='2021'!G27 -> 0
A51: 47 | B51: Repurchaseable shares fund | C51: ='2021'!E28 -> 0 | E51: ='2021'!G28 -> 0
A52: 48 | B52: Accumulated deficit | C52: ='2021'!E29 -> 1248109.5 | E52: ='2021'!G29 -> 4501657.5
B53: Profit (loss) - for the period | C53: ='2021'!E30 -> 2702097.7 | E53: ='2021'!G30 -> 8843657.6
C54: =SUM(C39:C53) -> #REF! | E54: =SUM(E39:E53) -> #REF!
C55: =IF(ROUND(C54+C37,0)=0,"OK","CHECK") -> #REF! | E55: =IF(ROUND(E54+E37,0)=0,"OK","CHECK") -> #REF!
C57: =C37+C54 -> #REF!
A58: 51 | B58: Net Revenues | C58: ='2021'!E35 -> 0 | E58: ='2021'!G35 -> 1279228.3
A59: 52 | B59: Cost of Goods | C59: ='2021'!E36 -> 0 | E59: ='2021'!G36 -> 0
A60: 53 | B60: R&D expenses | C60: ='2021'!E37 -> 1649671 | E60: ='2021'!G37 -> 5316284.8
A61: 54 | B61: Marketing expenses | C61: ='2021'!E38 -> 446350.16 | E61: ='2021'!G38 -> 761002.14
A62: 55 | B62: G&A expenses | C62: ='2021'!E39 -> 616681.83 | E62: ='2021'!G39 -> 1479453.9
A63: 59 | B63: Sales expenses | C63: ='2021'!E40 -> 0 | E63: ='2021'!G40 -> 0
A64: 56 | B64: Financial expenses | C64: ='2021'!E41 -> -21684.35 | E64: ='2021'!G41 -> 7688.39
A65: 58 | B65: Income Tax | C65: ='2021'!E42 -> 11079.1 | E65: ='2021'!G42 -> 0
B66: Loss for the period | C66: =SUM(C58:C65) -> 2702097.7 | E66: =SUM(E58:E65) -> 8843657.6

Sheet Equity
B1: Common stock | D1: Preferred stock | F1: Additional paid in cpaital | G1: Accumulated deficit | H1: Total shareholders equity | I1: Check | L1: Common stock | N1: Preferred stock | P1: Additional paid in cpaital | Q1: Accumulated deficit | R1: Total shareholders equity | S1: Check
A2: ILS | B2: shares | C2: amount | D2: shares | E2: amount | K2: $ | L2: shares | M2: amount | N2: shares | O2: amount
A4: Balance as of December 31 ,2018 | B4: 0 | C4: 0 | D4: 0 | E4: 0 | F4: 0 | G4: 0 | H4: 0 | K4: Balance as of December 31 ,2018 | L4: 0 | M4: 0 | N4: 0 | O4: 0 | P4: 0 | Q4: 0 | R4: 0
A6: Option fund | F6: 240.05824 | H6: 240.05824 | K6: Option fund | P6: 67.755641 | R6: 67.755641
A8: Issue of shares | F8: 16292.371 | H8: 16292.371 | K8: Issue of shares | P8: 4500 | R8: 4500
A10: Issuance costs | F10: -111.20962 | H10: -111.20962 | K10: Issuance costs | P10: -30.91621 | R10: -30.91621
A12: Net loss for the year ending 31/12/19 | G12: -3943.5946 | H12: -3943.5946 | K12: Net loss for the year ending 31/12/19 | Q12: -924.92143 | R12: -924.92143
A14: Balance as of December 31 ,2019 | B14: 0 | C14: 0 | D14: 0 | E14: 0 | F14: 16421.22 | G14: -3943.5946 | H14: 12477.625 | K14: Balance as of December 31 ,2019 | L14: 0 | M14: 0 | N14: 0 | O14: 0 | P14: =SUM(P6:P13) -> 4536.8394 | Q14: =SUM(Q6:Q13) -> -924.92143 | R14: =P14+Q14+M14+N14 -> 3611.918
H16: -12477.625 | R16: 3611.918
H18: 0 | R18: 0
A21: Balance as of December 31 ,2019 | B21: =SUM(B4:B5) -> 0 | C21: =SUM(C4:C5) -> 0 | D21: =SUM(D4:D5) -> 0 | E21: =SUM(E4:E5) -> 0 | F21: 16421.22 | G21: -3943.5946 | H21: =G21+F21+E21+C21 -> 12477.625 | K21: Balance as of December 31 ,2019 | L21: =SUM(L4:L5) -> 0 | M21: =SUM(M4:M5) -> 0 | N21: =SUM(N4:N5) -> 0 | O21: =SUM(O4:O5) -> 0 | P21: 4536.8394 | Q21: -924.92143 | R21: 3611.918
A23: Option fund | F23: =-'AJE LTD'!C9/1000 -> 130.03429 | H23: =H6+F23 -> 370.09253 | I23: =H23+'2021'!G27/1000 -> 370.09253 | K23: Option fund | P23: =-'AJE LTD'!D9/1000 -> 40.267021 | R23: =R6+P23 -> 108.02266 | S23: =R23+'2021'!C27/1000 -> 108.02266
A25: Issue of shares | F25: =H25-H8 -> #REF! | H25: =-'2021'!#REF!/1000 -> #REF! | K25: Issue of shares | P25: =R25-R8 -> #REF! | R25: =-'2021'!#REF!/1000 -> #REF!
A27: Issuance costs | F27: =H27-H10 -> 111.20962 | H27: =-'2021'!G26/1000 -> 0 | K27: Issuance costs | P27: =R27-R10 -> 30.91621 | R27: =-'2021'!C26/1000 -> 0
A29: Net loss for the year ending 31/12/20 | G29: =-'2021'!G30/1000 -> -8843.6576 | H29: =G29+F29+E29+C29 -> -8843.6576 | K29: Net loss for the year ending 31/12/20 | Q29: =-'2021'!C30/1000 -> -2724.3093 | R29: =Q29+P29+O29+M29 -> -2724.3093
A31: Balance as of December 31 ,2020 | B31: =SUM(B21:B30) -> 0 | C31: =SUM(C21:C30) -> 0 | D31: =SUM(D21:D30) -> 0 | E31: =SUM(E21:E30) -> 0 | F31: =SUM(F21:F30) -> #REF! | G31: =SUM(G21:G30) -> -12787.252 | H31: =F31+G31+C31+D31 -> #REF! | K31: Balance as of December 31 ,2020 | L31: =SUM(L21:L30) -> 0 | M31: =SUM(M21:M30) -> 0 | N31: =SUM(N21:N30) -> 0 | O31: =SUM(O21:O30) -> 0 | P31: =SUM(P21:P30) -> #REF! | Q31: =SUM(Q21:Q30) -> -3649.2307 | R31: =P31+Q31+M31+N31 -> #REF!
H33: =SUM('2021'!G24:G30)/1000 -> 13345.315 | R33: =SUM('2021'!C24:C30)/1000 -> 3973.8319
H35: =H33+H31 -> #REF! | R35: =R33+R31 -> #REF!

Sheet Investment 2021
A2: Round A
A3: Date | B3: Investor name | C3: Number of preferred stock | D3: Par value | E3: Investment amount (USD) | F3: Additional paid in capital
A4: 44405 | B4: Dell Inc | C4: 581818 | D4: =C4*0.01 -> 5818.18 | E4: 7999997.5 | F4: =E4-D4 -> 7994179.3
A5: 44405 | B5: Norwest Venture Partners XV | C5: 218181 | D5: =C5*0.01 -> 2181.81 | E5: 3000000 | F5: =E5-D5 -> 2997818.2
A6: 44406 | B6: Zeev Ventures VII | C6: 218181 | D6: =C6*0.01 -> 2181.81 | E6: 3000000 | F6: =E6-D6 -> 2997818.2
A7: 44440 | B7: Avrom Gilbert | C7: 15273 | D7: =C7*0.01 -> 152.73 | E7: 210000 | F7: =E7-D7 -> 209847.27
A8: 44447 | B8: Micah Breakstone | C8: 728 | D8: =C8*0.01 -> 7.28 | E8: 10000 | F8: =E8-D8 -> 9992.72
A9: 44481 | B9: Mnor Family | C9: 1455 | D9: =C9*0.01 -> 14.55 | E9: 20000 | F9: =E9-D9 -> 19985.45
A10: 44452 | B10: Ocean Pacific Investment | C10: 728 | D10: =C10*0.01 -> 7.28 | E10: 10000 | F10: =E10-D10 -> 9992.72
C11: =SUM(C4:C10) -> 1036364 | D11: =SUM(D4:D10) -> 10363.64 | E11: =SUM(E4:E10) -> 14249998 | F11: =SUM(F4:F10) -> 14239634
A14: Options exercise
A15: Date of exercise | B15: Name | C15: Number of ordinary stock | D15: Par value | E15: amount (USD) | F15: Additional paid in capital
A16: 44551 | B16: Avrom Gilbert | C16: 8000 | D16: =C16*0.01 -> 80 | E16: 8000 | F16: =E16-D16 -> 7920
A17: 44559 | B17: Yael Rivkind | C17: 2500 | D17: =C17*0.01 -> 25 | E17: 2472.5 | F17: =E17-D17 -> 2447.5
C18: =SUM(C16:C17) -> 10500 | D18: =SUM(D16:D17) -> 105 | E18: =SUM(E16:E17) -> 10472.5 | F18: =SUM(F16:F17) -> 10367.5
A23: Issuance cost
A24: 44196 | B24: Diff | C24: 44561
A25: 85128 | B25: =C25-A25 -> 122963.78 | C25: ='TB INC'!F20 -> 208091.78

Sheet Warrants
A2: Date of signature | C2: 44522
A4: Current stock price | C4: 4.25
A5: Exercise price | C5: 1.26
A6: Risk-free rate of interest | C6: 0.0163
A7: Expected life (in years) | C7: 10
A8: Stock volatility | C8: 0.8
A10: d1 | C10: =(LN(C4/C5)+(C6+0.5*C8^2)*C7)/(C8*SQRT(C7)) -> 1.8099325
A11: d2 | C11: =C10-SQRT(C7)*C8 -> -0.71988964
A13: N(d1) | C13: =NORMSDIST(C10) -> 0.96484687
A14: N(d2) | C14: =NORMSDIST(C11) -> 0.23579647
A16: Black Scholes | C16: =C13*C4-C5*EXP(-C6*C7)*C14 -> 3.8481826
A18: Number of warrants | C18: 2509
A20: Total exp | C20: =C16*C18 -> 9655.0902

Sheet TP 2021
A2: TOTAL EXPENSES | C2: =SUM('TB INC'!F24:F60)-'TB INC'!F53-'TB INC'!F54-'TB INC'!F55-'TB INC'!F56-'TB INC'!F57-'TB INC'!D51-'TB INC'!D52 -> 367277.2
A3: COST + 10% | C3: 0.1
A4: TOTAL TP | C4: =C2*1.1 -> 404004.92
A5: intercompany income recorded | C5: =-'TB INC'!D23 -> 392958.09
A7: Diff | C7: =C4-C5 -> 11046.827
