Workbook

Sheet דוח התאמה למס
B2: Papaya Gaming LTD | C2: דוח התאמה 2021
B6: רווח לפני מס 2021 | E6: ='P&L LTD USD'!J122-'P&L LTD USD'!J120 -> -95997189
B8: תיאום הוצאות עודפות:
B9: מחקר ופיתוח - דחיית הוצאות | E9: ='R&D 20A'!G8+'R&D 20A'!G9+'R&D 20A'!H9 -> #N/A | F9: פריסה על פני 3 שנים
B10: מחקר ופיתוח - הכרה בהוצאות ש"ק | E10: ='R&D 20A'!F7+'R&D 20A'!F8 -> 2898754.6 | F10: בגין הוצאות שמקורן ב 2018-2019
A11: 23031 | B11: הוצאות בגין תשלום מבוסס מניות | E11: =VLOOKUP(A12,'TB LTD 12.22'!D:F,3,0) -> #N/A
A12: 20060 | B12: הוצאות בגין תשלום מבוסס מניות | E12: =VLOOKUP(A13,'TB LTD 12.22'!D:F,3,0) -> #N/A
A13: 20048 | B13: הוצאות בגין תשלום מבוסס מניות | E13: =VLOOKUP(A14,'TB LTD 12.22'!D:F,3,0) -> #N/A
A14: 90017 | B14: גידול בהפרשה לחופשה | E14: =VLOOKUP(A15,'TB LTD 12.22'!D:F,3,0) -> #N/A
A15: 90018 | B15: גידול בהפרשה להבראה | E15: =VLOOKUP(A16,'TB LTD 12.22'!D:F,3,0) -> #N/A
A16: 20024 | B16: ארוחות | E16: =VLOOKUP(A17,'TB LTD 12.22'!D:F,3,0) -> #N/A | F16: 100% מתואם
A17: ='[1]TB 12.2018'!C7 -> 20001 | B17: כיבודים
B18: עודפות
B19: רווחי אקוויטי | E19: =-'[2]FS ILS 12.20'!E72 -> #REF!
A20: 20039 | B20: תרומות | E20: =VLOOKUP(A20,'[2]TB LTD 12.20'!$D:$F,3,FALSE)-17586.4 -> #N/A
A21: 20035 | B21: קנסות | E21: =+VLOOKUP(A21,'[2]TB LTD 12.20'!$D:$F,3,FALSE) -> #N/A | F21: קנסות תנועה + מוסדות
E23: =SUM(E9:E21) -> #N/A
N24: כרטיס | O24: תאור | Q24: סה"כ הוצאה | R24: שויים | S24: הוצאה עודפת
B25: הפסד מועבר משנת 2019 | E25: -4245210 | N25: 20014 | O25: מצרכים וכיבודים | Q25: #REF! | S25: =+Q25*0.2 -> #VALUE!
N26: 20021 | O26: מתנות | P26: 90015 | Q26: #REF! | R26: #REF! | S26: =+Q26-R26 -> #VALUE!
B27: הפסד לצרכי מס - מועבר לשנת 2021 | E27: =E6+E23+E25 -> #N/A | F27: =-E27+E25 -> #N/A | N27: 20024 | O27: ארוחות | P27: 90012 | Q27: #REF! | R27: #REF! | S27: =+Q27-R27 -> #VALUE!
N28: 20036 | O28: אירוע חברה | Q28: #REF! | S28: =+Q28 -> #REF!
B29: תרומה להעברה לשנים הבאות לשם קבלת הזיכוי | E29: =+E20 -> #N/A | F29: =+E27-E29 -> #N/A | N29: 20041 | O29: מתנות לעובדים חד פעמי | Q29: #REF! | S29: =+Q29 -> #REF!
S30: =0.45*SUM(S25:S29) -> #VALUE!
C32: USD | D32: NIS | E32: שיעור המס לפי מפעל טכנולוגי מועדף (גישה שמרנית)
B33: נכס מס נדחה בגין הפסד להעברה | C33: =+D33/'[2]FS USD 12.20'!$I$1 -> #N/A | D33: =-E27*E33 -> #N/A | E33: 0.12
A34: 90017 | B34: נכס מס נדחה בגין הפרשה לחופשה | C34: #REF! | D34: =-VLOOKUP(A34,'[2]TB LTD 12.20'!$D:$F,3,FALSE)*$E$34 -> #N/A | E34: 0.12 | O34: התאמת מו"פ
A35: 90018 | B35: נכס מס נדחה בגין הפרשה להבראה | C35: #REF! | D35: =-VLOOKUP(A35,'[2]TB LTD 12.20'!$D:$F,3,FALSE)*$E$35 -> #N/A | E35: 0.12
B36: הוצאות מו״פ שנדחו | C36: =+D36/'[2]FS USD 12.20'!$I$1 -> #REF! | D36: =+SUM(M9:N10)*E36 -> 0 | E36: 0.12 | N36: הוצאות מו"פ | O36: =-'[2]FS ILS 12.20'!E60 -> #REF!
M38: 23012 | N38: הוצאות הפרשה להבראה מופ | O38: #REF!
M39: 23011 | N39: הוצאות חופשה מופ | O39: #REF!
M40: SBC Expenses R&D | N40: הוצאות בגין תשלום מבוסס מניות | O40: =-E11 -> #N/A
O41: =SUM(O36:O40) -> #REF!

Sheet Income WP
C1: January | D1: februay | E1: march | F1: April | G1: May | H1: June | I1: July | J1: August | K1: September | L1: October | M1: November | N1: December
B4: Net revenue | C4: Books
B6: Revenue -Revenue Worldpay | C6: -8464.236 | D6: -8214.9616 | E6: -7864.6015 | F6: -6635.6998 | G6: -6367.1782 | H6: -5679.5026 | I6: -6074.0722 | J6: -6044.8198 | K6: -5718.7637 | L6: -5812.9114 | M6: -5945.4744 | N6: -7092.0165 | O6: =SUM(C6:N6) -> -79914.238
B7: Revenue -Revenue Paypal IL | C7: -7708.4674 | D7: -8023.2407 | E7: -8567.4289 | F7: -2482.4601 | G7: -549.67162 | H7: -588.54806 | I7: -772.40202 | J7: -698.99656 | K7: -569.86207 | L7: -633.74312 | M7: -651.10238 | N7: -795.55018 | O7: =SUM(C7:N7) -> -32041.473
B8: Revenue -Revenue Paypal US | C8: -11.161 | D8: -15.068 | E8: -913.23003 | F8: -6763.3307 | G8: -8302.2735 | H8: -7566.9065 | I8: -8300.8356 | J8: -8661.674 | K8: -8403.418 | L8: -9039.249 | M8: -9231.405 | N8: -11230.575 | O8: =SUM(C8:N8) -> -78439.126
B9: Revenue -Revenue Cyber Source | C9: -10287.134 | D9: -9723.4638 | E9: -11979.491 | F9: -10840.921 | G9: -11149.886 | H9: -10416.312 | I9: -11524.237 | J9: -11540.062 | K9: -11056.225 | L9: -11555.783 | M9: -11900.453 | N9: -14063.502 | O9: =SUM(C9:N9) -> -136037.47
B10: Revenue - Braintree | C10: 0 | D10: -0.009 | E10: -668.6464 | F10: -1421.1699 | G10: -1898.0734 | H10: -2037.7415 | I10: -2256.9943 | J10: -2872.641 | K10: -2934.0622 | L10: -3108.4732 | M10: -3325.7385 | N10: -3863.4214 | O10: =SUM(C10:N10) -> -24386.971
B11: direct Sales tax | M11: 366 | N11: 1038.077 | O11: =SUM(C11:N11) -> 1404.077
B12: FX paypal | C12: -2.4 | D12: -18.6 | E12: -24.3 | F12: -23.6 | G12: -23.199 | H12: -23.6 | I12: -27.4 | J12: -24.9 | K12: -20.8 | L12: -23.1 | M12: -16.9 | N12: -20.6 | O12: =SUM(C12:N12) -> -249.399
B13: Revenue Sales Tax | C13: 997.217 | D13: 952.537 | E13: 1069.429 | F13: 940.664 | G13: 926.095 | H13: 878.436 | I13: 946.384 | J13: 929.883 | K13: 770.866 | L13: 855.649 | M13: 531 | N13: =30+181 -> 211 | O13: =SUM(C13:N13) -> 10009.16
B15: ='P&L LTD USD'!C8 -> withdrawals | C15: 316.551 | D15: 223.42657 | E15: 267.68417 | F15: 167.10198 | G15: 153.64264 | H15: 233.62136 | I15: 200.58034 | J15: 199.29227 | K15: 186.66177 | L15: 264.48114 | M15: 299.47245 | N15: 554.15426 | O15: ='P&L LTD USD'!F8/1000 -> 3066.6699
B16: ='P&L LTD USD'!C7 -> Net Cash | C16: 418.747 | D16: 411.425 | E16: 463.667 | F16: 414.138 | G16: 244.824 | H16: 421.944 | I16: 538.704 | J16: 431.387 | K16: 394.87727 | L16: 287.31728 | M16: 511.67244 | N16: 392.65548 | O16: ='P&L LTD USD'!F7/1000 -> 4931.3585
B17: ='P&L LTD USD'!C6 -> ads revenue | C17: -207.63259 | D17: -197.12699 | E17: -212.44853 | F17: -208.6662 | G17: -219.74986 | H17: -214.47608 | I17: -256.15022 | J17: -217.27895 | K17: -225.66554 | L17: -220.16938 | M17: -206.10497 | N17: -215.09991 | O17: ='P&L LTD USD'!F6/1000 -> -2600.5692
B19: Total income | O19: =SUM(O5:O17) -> -334257.98
O63: =-334239531.33/1000 -> -334239.53
N64: i/m | O64: =O19-O63 -> -18.44882
E129: ;

Sheet Exp By type
B4: Total revenue
C5: India | D5: INC | E5: LTD | F5: Total
B6: Ua | C6: =+SUMIFS('P&L India'!F:F,'P&L India'!A:A,'Exp By type'!B6) -> 0 | D6: =+SUMIFS('P&L INC'!F:F,'P&L INC'!A:A,'Exp By type'!B6) -> 24308066 | E6: =SUMIFS('P&L LTD USD'!F:F,'P&L LTD USD'!A:A,'Exp By type'!B6) -> 2.2524941e+08 | F6: =SUM(C6:E6) -> 2.4955748e+08
B7: Fee | C7: =+SUMIFS('P&L India'!F:F,'P&L India'!A:A,'Exp By type'!B7) -> 0 | D7: =+SUMIFS('P&L INC'!F:F,'P&L INC'!A:A,'Exp By type'!B7) -> 19761872 | E7: =SUMIFS('P&L LTD USD'!F:F,'P&L LTD USD'!A:A,'Exp By type'!B7) -> 0 | F7: =SUM(C7:E7) -> 19761872
B8: Payroll | C8: =+SUMIFS('P&L India'!F:F,'P&L India'!A:A,'Exp By type'!B8) -> 0 | D8: =+SUMIFS('P&L INC'!F:F,'P&L INC'!A:A,'Exp By type'!B8) -> 0 | E8: =SUMIFS('P&L LTD USD'!F:F,'P&L LTD USD'!A:A,'Exp By type'!B8) -> 19481623 | F8: =SUM(C8:E8) -> 19481623
B9: Options | C9: =+SUMIFS('P&L India'!F:F,'P&L India'!A:A,'Exp By type'!B9) -> 0 | D9: =+SUMIFS('P&L INC'!F:F,'P&L INC'!A:A,'Exp By type'!B9) -> 0 | E9: =SUMIFS('P&L LTD USD'!F:F,'P&L LTD USD'!A:A,'Exp By type'!B9) -> 185110.54 | F9: =SUM(C9:E9) -> 185110.54
B10: Overheads | C10: =+SUMIFS('P&L India'!F:F,'P&L India'!A:A,'Exp By type'!B10) -> 51073.93 | D10: =+SUMIFS('P&L INC'!F:F,'P&L INC'!A:A,'Exp By type'!B10) -> 244662.34 | E10: =SUMIFS('P&L LTD USD'!F:F,'P&L LTD USD'!A:A,'Exp By type'!B10) -> 15118489 | F10: =SUM(C10:E10) -> 15414226
B11: Financial expenses | C11: =+SUMIFS('P&L India'!F:F,'P&L India'!A:A,'Exp By type'!B11) -> 262.11 | D11: =+SUMIFS('P&L INC'!F:F,'P&L INC'!A:A,'Exp By type'!B11) -> 179789.7 | E11: =SUMIFS('P&L LTD USD'!F:F,'P&L LTD USD'!A:A,'Exp By type'!B11) -> 242412.35 | F11: =SUM(C11:E11) -> 422464.16
B12: Taxes | C12: =+SUMIFS('P&L India'!F:F,'P&L India'!A:A,'Exp By type'!B12) -> 0 | D12: =+SUMIFS('P&L INC'!F:F,'P&L INC'!A:A,'Exp By type'!B12) -> 89337.55 | E12: =SUMIFS('P&L LTD USD'!F:F,'P&L LTD USD'!A:A,'Exp By type'!B12) -> 3503498.7 | F12: =SUM(C12:E12) -> 3592836.3
B13: Ua Indirect | C13: =+SUMIFS('P&L India'!F:F,'P&L India'!A:A,'Exp By type'!B13) -> 0 | D13: =+SUMIFS('P&L INC'!F:F,'P&L INC'!A:A,'Exp By type'!B13) -> 587361.08 | E13: =SUMIFS('P&L LTD USD'!F:F,'P&L LTD USD'!A:A,'Exp By type'!B13) -> 2935151.9 | F13: =SUM(C13:E13) -> 3522513
B14: Depreciation | C14: =+SUMIFS('P&L India'!F:F,'P&L India'!A:A,'Exp By type'!B14) -> 0 | D14: =+SUMIFS('P&L INC'!F:F,'P&L INC'!A:A,'Exp By type'!B14) -> 0 | E14: =SUMIFS('P&L LTD USD'!F:F,'P&L LTD USD'!A:A,'Exp By type'!B14) -> 216788.83 | F14: =SUM(C14:E14) -> 216788.83
C15: =SUM(C6:C14) -> 51336.04 | D15: =SUM(D6:D14) -> 45171089 | E15: =SUM(E6:E14) -> 2.6693249e+08 | F15: =SUM(F6:F14) -> 3.1215491e+08
C16: ='P&L India'!F28 -> 51336.04 | D16: ='P&L INC'!F79 -> 0 | E16: ='P&L LTD USD'!F129 -> 2.6693249e+08
C17: =C15-C16 -> 0 | D17: =D15-D16 -> 45171089 | E17: =E15-E16 -> 0

Sheet Summary 
B4: Revenues | C4: 2022
B5: Revenues from commissions | C5: ='Income WP'!#REF! -> #REF!
B6: ADJ | C6: ='Income WP'!#REF!+'Income WP'!#REF! -> #REF!
B7: Total revenues | C7: =SUM(C5:C6) -> #REF!
B9: UA- Direct | C9: ='Exp By type'!F6/1000 -> 249557.48
B10: UA -Indirect | C10: ='Exp By type'!F13/1000 -> 3522.513
B11: Total Marketing | C11: =SUM(C9:C10) -> 253079.99
B13: GP | C13: =C7+C11 -> #REF!
B14: % | C14: =C13/C7 -> #REF!
B16: Clearing fees | C16: ='Exp By type'!F7/1000 -> 19761.872
B17: Payroll | C17: ='Exp By type'!F8/1000 -> 19481.623
B18: OverHeads | C18: ='Exp By type'!F10/1000 -> 15414.226
B20: EBITDA (Loss) | C20: =C13+C16+C17+C18 -> #REF!

Sheet FS
A1: 44926
A2: FS
A3: Papaya Gaming Ltd
A4: USD
A7: BS | F7: PL
C10: 44926 | H10: 44926 | I10: 44926
C11: Consolidated | H11: Consolidated | I11: Consolidated - K$
B14: CURRENT ASSETS | G14: Total Revenues | H14: ='P&L USD CONS'!L7 -> -3.3423953e+08 | I14: =H14/1000 -> -334239.53
A16: Short term deposit | B16: Cash | C16: =SUMIF('BS USD CONS '!B:B,FS!A16,'BS USD CONS '!M:M)+SUMIF('BS USD CONS '!B:B,FS!B16,'BS USD CONS '!M:M) -> 78468.185 | G16: Cost of revenues | H16: ='P&L USD CONS'!L9 -> 23057127 | I16: =H16/1000 -> 23057.127
A17: Related Party India | B17: Related Party | C17: =SUMIF('BS USD CONS '!B:B,FS!A17,'BS USD CONS '!M:M)+SUMIF('BS USD CONS '!B:B,FS!B17,'BS USD CONS '!M:M) -> -0.00025 | G17: Gross loss (profit) | H17: ='P&L USD CONS'!L11 -> -3.111824e+08 | I17: =H17/1000 -> -311182.4
B18: Account receivable | C18: =SUMIF('BS USD CONS '!B:B,FS!A18,'BS USD CONS '!M:M)+SUMIF('BS USD CONS '!B:B,FS!B18,'BS USD CONS '!M:M) -> 2668.2386
B19: Shareholders' loan | C19: =SUMIF('BS USD CONS '!B:B,FS!A19,'BS USD CONS '!M:M)+SUMIF('BS USD CONS '!B:B,FS!B19,'BS USD CONS '!M:M) -> 0
A20: Other accounts receivable | B20: Prepaid exepnses and other current assets | C20: =SUMIF('BS USD CONS '!B:B,FS!A20,'BS USD CONS '!M:M)+SUMIF('BS USD CONS '!B:B,FS!A21,'BS USD CONS '!M:M) -> 4289.8373 | G20: Research and development expenses, net | H20: ='P&L USD CONS'!L13 -> 20781725 | I20: =H20/1000 -> 20781.725
A21: Prepaid Expenses | C21: =SUM(C16:C20) -> 85426.261
B23: NON-CURRENT ASSETS | G23: Marketing expenses | H23: ='P&L USD CONS'!L15 -> 2.5604807e+08 | I23: =H23/1000 -> 256048.07
A25: Fixed assets, net | B25: Property and equipment, net | C25: =SUMIF('BS USD CONS '!B:B,FS!A25,'BS USD CONS '!M:M)+SUMIF('BS USD CONS '!B:B,FS!B25,'BS USD CONS '!M:M) -> 1659.0749
B26: ROA Assets | C26: =SUMIF('BS USD CONS '!B:B,FS!A26,'BS USD CONS '!M:M)+SUMIF('BS USD CONS '!B:B,FS!B26,'BS USD CONS '!M:M) -> 20186.267 | G26: General and administrative expenses | H26: ='P&L USD CONS'!L17 -> 8252686.3 | I26: =H26/1000 -> 8252.6863
A27: Reserve - Wordpay | B27: Restricted LT deposit | C27: =SUMIF('BS USD CONS '!B:B,FS!A27,'BS USD CONS '!M:M)+SUMIF('BS USD CONS '!B:B,FS!B27,'BS USD CONS '!M:M) -> 3667.2055
B28: Deferred tax assets | C28: =SUMIF('BS USD CONS '!B:B,FS!A28,'BS USD CONS '!M:M)+SUMIF('BS USD CONS '!B:B,FS!B28,'BS USD CONS '!M:M) -> 2030.2293
C29: =SUM(C25:C28) -> 27542.777
G30: Operating expenses | H30: ='P&L USD CONS'!L19 -> 2.8508248e+08 | I30: =H30/1000 -> 285082.48
B31: Total Assets | C31: =C29+C21 -> 112969.04
G32: Operating loss (profit) | H32: ='P&L USD CONS'!L21 -> -26099922 | I32: =H32/1000 -> -26099.922
B34: CURRENT LIABILITIES | G34: Financial expenses, net | H34: ='P&L USD CONS'!L23 -> 242674.46 | I34: =H34/1000 -> 242.67446
A36: Trade payables | B36: Account payables | C36: =SUMIF('BS USD CONS '!B:B,FS!A36,'BS USD CONS '!M:M)+SUMIF('BS USD CONS '!B:B,FS!B36,'BS USD CONS '!M:M) -> -8752.1494 | G36: TP Expenses | H36: ='P&L USD CONS'!L25 -> 0 | I36: =H36/1000 -> 0
A37: Loan-Short Term | B37: Current maurities of short term loan | C37: =SUMIF('BS USD CONS '!B:B,FS!A37,'BS USD CONS '!M:M)+SUMIF('BS USD CONS '!B:B,FS!B37,'BS USD CONS '!M:M) -> 0
B38: Contract liability | C38: =SUMIF('BS USD CONS '!B:B,FS!A38,'BS USD CONS '!M:M)+SUMIF('BS USD CONS '!B:B,FS!B38,'BS USD CONS '!M:M) -> -8960.3131 | G38: Equity | H38: ='P&L USD CONS'!L27 -> -12793.34 | I38: =H38/1000 -> -12.79334
B39: Related Party-AP | C39: =SUMIF('BS USD CONS '!B:B,FS!A39,'BS USD CONS '!M:M)+SUMIF('BS USD CONS '!B:B,FS!B39,'BS USD CONS '!M:M) -> 0
A40: Tax provision | B40: Warrant liability | C40: =SUMIF('BS USD CONS '!B:B,FS!B40,'BS USD CONS '!M:M) -> -1411.3574 | G40: loss before taxes | H40: ='P&L USD CONS'!L29 -> -25870040 | I40: =H40/1000 -> -25870.04
A41: Other accounts payable | B41: Other accounts payable and accrued expenses | C41: =SUMIF('BS USD CONS '!B:B,FS!A41,'BS USD CONS '!M:M)+SUMIF('BS USD CONS '!B:B,FS!A43,'BS USD CONS '!M:M)+SUMIF('BS USD CONS '!B:B,FS!A40,'BS USD CONS '!M:M)+SUMIF('BS USD CONS '!B:B,FS!A44,'BS USD CONS '!M:M)+SUMIF('BS USD CONS '!B:B,FS!A42,'BS USD CONS '!M:M) -> -35559.508
A42: Accrued expenses | C42: =SUM(C36:C41) -> -54683.328 | G42: Tax expenses | H42: ='P&L USD CONS'!L31 -> 3503498.7 | I42: =H42/1000 -> 3503.4987
A43: Sales Tax Provision
B44: ROA Liability | C44: =SUMIF('BS USD CONS '!B:B,FS!B44,'BS USD CONS '!M:M) -> 0 | G44: Net loss ( profit ) | H44: ='P&L USD CONS'!L33 -> -22366542 | I44: =H44/1000 -> -22366.542
B45: Shareholders | C45: =SUMIF('BS USD CONS '!B:B,FS!A45,'BS USD CONS '!M:M)+SUMIF('BS USD CONS '!B:B,FS!B45,'BS USD CONS '!M:M) -> 0
B46: Convertible Loan | C46: =SUMIF('BS USD CONS '!B:B,FS!A46,'BS USD CONS '!M:M)+SUMIF('BS USD CONS '!B:B,FS!B46,'BS USD CONS '!M:M) -> 0
C47: =SUM(C44:C46) -> 0
B49: Total liabilities | C49: =C47+C42 -> -54683.328
B51: SHAREHOLDERS' EQUITY
B53: Share capital - Ordinary Shares | C53: =SUMIF('BS USD CONS '!B:B,FS!A53,'BS USD CONS '!M:M)+SUMIF('BS USD CONS '!B:B,FS!B53,'BS USD CONS '!M:M) -> -0.69022
B54: Share capital - Preferred Seed-1 | C54: =SUMIF('BS USD CONS '!B:B,FS!A54,'BS USD CONS '!M:M)+SUMIF('BS USD CONS '!B:B,FS!B54,'BS USD CONS '!M:M) -> -0.191
B55: Share capital - Preferred Seed | C55: =SUMIF('BS USD CONS '!B:B,FS!A55,'BS USD CONS '!M:M)+SUMIF('BS USD CONS '!B:B,FS!B55,'BS USD CONS '!M:M) -> -0.04924
B56: Share premium | C56: =SUMIF('BS USD CONS '!B:B,FS!A56,'BS USD CONS '!M:M)+SUMIF('BS USD CONS '!B:B,FS!B56,'BS USD CONS '!M:M) -> -8818.4906
B57: Receivables for shares issued | C57: =SUMIF('BS USD CONS '!B:B,FS!A57,'BS USD CONS '!M:M)+SUMIF('BS USD CONS '!B:B,FS!B57,'BS USD CONS '!M:M) -> 0
A58: PL | B58: Accumulated deficit | C58: =SUMIF('BS USD CONS '!B:B,FS!A58,'BS USD CONS '!M:M)+SUMIF('BS USD CONS '!B:B,FS!B58,'BS USD CONS '!M:M) -> -26436.685
C59: =SUM(C53:C58) -> -35256.106
B61: Total Equity | C61: =C59+C49 -> -89939.434
B64: Check | C64: =C61+C31 -> 23029.604

Sheet FS Notes
A1: 44926
A2: FS Notes
A3: Papaya Gaming Ltd
A4: USD
B7: Note 3 - Property and Equipment, Net
F8: Signed FS
B9: Group | D9: 44926 | F9: 44561
B10: Computers and electronic equipment | D10: ='TB LTD 12.22'!G33/1000 -> -2.38178 | F10: 96
B11: Vehicles | D11: ='TB LTD 12.22'!G31/1000 -> 743.03846 | F11: 3
B12: Office furniture and equipment | D12: =('TB LTD 12.22'!G35+'TB LTD 12.22'!G40)/1000 -> -53.74139 | F12: 10
B13: Leasehold improvements | D13: ='TB LTD 12.22'!G36/1000 -> -10.63371 | F13: 3
D14: =SUM(D10:D13) -> 676.28158 | F14: =SUM(F10:F13) -> 112
B15: Less – accumulated depreciation | D15: =SUM('TB LTD 12.22'!G32,'TB LTD 12.22'!G34,'TB LTD 12.22'!G37,'TB LTD 12.22'!G38,'TB LTD 12.22'!G39)/1000-'AJE 2022'!H70/1000 -> 13533.105 | F15: -31
B16: Total property and equipment, net | D16: =SUM(D14:D15) -> 14209.386 | F16: =SUM(F14:F15) -> 81
B20: Note 5 - Other current Liabilities
F21: Signed FS
B22: Group | D22: 44926 | F22: 44561 | I22: Other current liabilities INC
B23: Accrued expenses | D23: =-'TB LTD 12.22'!G105/1000-(O25+O24+O26)/1000 -> 74800.143 | F23: 622 | I23: Entity | K23: Account | M23: 44561 | O23: 44926
B24: Payroll and related expenses | D24: =-SUM('TB LTD 12.22'!G19:G28)/1000 -> 18836.575 | F24: 372 | I24: INC | K24: SVB Commission | M24: -125276.67 | O24: -518442.74
B25: WHT | D25: =-'TB LTD 12.22'!G9/1000 -> -1056.9565 | F25: 0 | I25: INC | K25: WorldPay Commission | M25: 0 | O25: -35916.02
B26: Income tax payable | D26: =-O27/1000 -> 101.4614 | F26: 0 | I26: INC | K26: James Kong | M26: 0 | O26: -8333.33
B27: Sales Tax | D27: ='AJE 2022'!#REF!/1000 -> #REF! | F27: 0 | I27: INC | K27: Income tax payable | M27: 714 | O27: -101461.4
D28: =SUM(D23:D27) -> #REF! | F28: =SUM(F23:F27) -> 994
B31: Note 11 - Supplementary statements of operation information
F32: Signed FS
B33: a. Research and development expenses: | D33: 44926 | F33: 44561
B34: Payroll and related expenses | D34: =SUM('TB LTD 12.22'!G173,'TB LTD 12.22'!G187:G232,'TB LTD 12.22'!G249,'TB LTD 12.22'!G251,'TB LTD 12.22'!G253)/1000 -> 24333.964 | F34: 1089
B35: Computer Maintenance | D35: =('TB LTD 12.22'!G350)/1000 -> 52.92387 | F35: 159
B36: Software subscription | D36: =SUM('TB LTD 12.22'!G238,'TB LTD 12.22'!G241,'TB LTD 12.22'!G243:G244,'TB LTD 12.22'!G247,'TB LTD 12.22'!G250)/1000 -> 182.33229 | F36: 0
B37: Professional consulting | D37: =SUM('TB LTD 12.22'!G239+'TB LTD 12.22'!G240+'TB LTD 12.22'!G254+'TB LTD 12.22'!G236)/1000 -> 181.41188 | F37: 535
B38: Share-based compensation | D38: ='TB LTD 12.22'!G245/1000+'P&L LTD USD'!E49/1000 -> -57.85857 | F38: 370
B39: Hosting and Servers | D39: ='TB LTD 12.22'!G252/1000 -> 82.4095 | F39: 0
B40: Other | D40: =SUM('TB LTD 12.22'!G233,'TB LTD 12.22'!G234,'TB LTD 12.22'!G237,'TB LTD 12.22'!G242,'TB LTD 12.22'!G246,'TB LTD 12.22'!G248)/1000 -> 1734.4082 | F40: 144
D41: =SUM(D34:D40) -> 26509.591 | F41: =SUM(F34:F40) -> 2297
F43: Signed FS
B44: b. Marketing expenses: | D44: 44926 | F44: 44561
B45: Payroll and related expenses | D45: =SUM('TB LTD 12.22'!G255:G260,'TB LTD 12.22'!G262:G269,'TB LTD 12.22'!G279)/1000 -> 1780.7246 | F45: 314
B46: Marketing and Advertising | D46: =SUM('TB LTD 12.22'!G270,'TB LTD 12.22'!G273,'TB LTD 12.22'!G275:G277,'TB LTD 12.22'!G329)/1000 -> 162.14992 | F46: 12695
B47: Software subscription | D47: =SUM('TB LTD 12.22'!G271:G272,'TB LTD 12.22'!G280)/1000 -> 173.66855 | F47: 0
B48: Share-based compensation | D48: ='TB LTD 12.22'!G281/1000+'P&L LTD USD'!E74/1000 -> -31.70624 | F48: 0
B49: Other | D49: =SUM('TB LTD 12.22'!G274,,'TB LTD 12.22'!G282)/1000 -> 5.32135 | F49: 36
D50: =SUM(D45:D49) -> 2090.1582 | F50: =SUM(F45:F49) -> 13045
F52: Signed FS
B53: c. General and administrative expenses: | D53: 44926 | F53: 44561
B54: Payroll and related expenses | D54: =SUM('TB LTD 12.22'!G283:G297,'TB LTD 12.22'!G337,'TB LTD 12.22'!G347)/1000 -> 783.27467 | F54: 168
B55: Legal expenses | D55: ='TB LTD 12.22'!G340/1000 -> 228.04963 | F55: 297
B56: Professional services | D56: =SUM('TB LTD 12.22'!G336,'TB LTD 12.22'!G338:G339,'TB LTD 12.22'!G341,'TB LTD 12.22'!G344)/1000 -> 927.3114 | F56: 145
B57: Rent and maintenance | D57: =SUM('TB LTD 12.22'!G298,'TB LTD 12.22'!G302:G305)/1000 -> 2082.4744 | F57: 12
B58: Depreciation | D58: =SUM('TB LTD 12.22'!G306:G310,'TB LTD 12.22'!G315)/1000 -> 518.29219 | F58: 20
B59: Software subscription | D59: =SUM('TB LTD 12.22'!G342+'TB LTD 12.22'!G349+'TB LTD 12.22'!G351)/1000 -> 1212.3967 | F59: 0
B60: Share-based compensation | D60: ='TB LTD 12.22'!G332/1000 -> 0.45249 | F60: 58
B61: Other | D61: =SUM('TB LTD 12.22'!G235,'TB LTD 12.22'!G278,'TB LTD 12.22'!G299:G301,'TB LTD 12.22'!G311:G314,'TB LTD 12.22'!G316:G328,'TB LTD 12.22'!G330:G331,'TB LTD 12.22'!G333:G334,'TB LTD 12.22'!G343,'TB LTD 12.22'!G345:G346,'TB LTD 12.22'!G348)/1000 -> 4777.7621 | F61: 19 | G61: Including Allocation
D62: =SUM(D54:D61) -> 10530.014 | F62: =SUM(F54:F61) -> 719

Sheet BS USD CONS 
C3: 2022 | E3: 2022 | G3: 2022 | I3: Cons Company | K3: 2022 | M3: 2022
C4: LTD | E4: INC | G4: India | K4: Cons | M4: Cons
C5: USD | E5: USD | G5: USD | K5: USD | M5: $ In thousands
B6: CURRENT ASSETS
B8: Cash | C8: =SUMIF('BS LTD USD '!B:B,'BS USD CONS '!$B8,'BS LTD USD '!E:E) -> 23504184 | E8: =SUMIF('BS INC'!B:B,'BS USD CONS '!$B8,'BS INC'!E:E) -> 24693919 | G8: =SUMIF('BS India'!B:B,'BS USD CONS '!$B8,'BS India'!E:E) -> 0 | K8: =+E8+C8+I8+G8 -> 48198103 | M8: =K8/1000 -> 48198.103 | N8: =K8/1000 -> 48198.103
B9: Account receivable | C9: =SUMIF('BS LTD USD '!B:B,'BS USD CONS '!$B9,'BS LTD USD '!E:E) -> 2668238.6 | E9: =SUMIF('BS INC'!B:B,'BS USD CONS '!$B9,'BS INC'!E:E) -> 0 | G9: =SUMIF('BS India'!B:B,'BS USD CONS '!$B9,'BS India'!E:E) -> 0 | K9: =+E9+C9+I9+G9 -> 2668238.6 | M9: =K9/1000 -> 2668.2386 | N9: =K9/1000 -> 2668.2386
B10: Related Party | C10: =SUMIF('BS LTD USD '!B:B,'BS USD CONS '!$B10,'BS LTD USD '!E:E) -> 24505604 | E10: =SUMIF('BS INC'!B:B,'BS USD CONS '!$B10,'BS INC'!E:E) -> -24505604 | G10: =SUMIF('BS India'!B:B,'BS USD CONS '!$B10,'BS India'!E:E) -> 0 | K10: =+E10+C10+I10+G10 -> -0.25 | M10: =K10/1000 -> -0.00025
B11: Related Party India | C11: =SUMIF('BS LTD USD '!B:B,'BS USD CONS '!$B11,'BS LTD USD '!E:E) -> 29383.12 | E11: =SUMIF('BS INC'!B:B,'BS USD CONS '!$B11,'BS INC'!E:E) -> 0 | G11: =SUMIF('BS India'!B:B,'BS USD CONS '!$B11,'BS India'!E:E) -> -29383.12 | K11: =+E11+C11+I11+G11 -> 0 | M11: =K11/1000 -> 0
B12: Short term deposit | C12: =SUMIF('BS LTD USD '!B:B,'BS USD CONS '!$B12,'BS LTD USD '!E:E) -> 30270082 | E12: =SUMIF('BS INC'!B:B,'BS USD CONS '!$B12,'BS INC'!E:E) -> 0 | G12: =SUMIF('BS India'!B:B,'BS USD CONS '!$B12,'BS India'!E:E) -> 0 | K12: =+E12+C12+I12+G12 -> 30270082 | M12: =K12/1000 -> 30270.082 | N12: =K12/1000 -> 30270.082
B13: Shareholders' loan | C13: =SUMIF('BS LTD USD '!B:B,'BS USD CONS '!$B13,'BS LTD USD '!E:E) -> 0 | E13: =SUMIF('BS INC'!B:B,'BS USD CONS '!$B13,'BS INC'!E:E) -> 0 | G13: =SUMIF('BS India'!B:B,'BS USD CONS '!$B13,'BS India'!E:E) -> 0 | K13: =+E13+C13+I13+G13 -> 0 | M13: =K13/1000 -> 0
B14: Prepaid Expenses | C14: =SUMIF('BS LTD USD '!B:B,'BS USD CONS '!$B14,'BS LTD USD '!E:E) -> 611164.27 | E14: =SUMIF('BS INC'!B:B,'BS USD CONS '!$B14,'BS INC'!E:E) -> 0 | G14: =SUMIF('BS India'!B:B,'BS USD CONS '!$B14,'BS India'!E:E) -> 0 | K14: =+E14+C14+I14+G14 -> 611164.27 | M14: =K14/1000 -> 611.16427 | N14: =K14/1000 -> 611.16427
B15: Other accounts receivable | C15: =SUMIF('BS LTD USD '!B:B,'BS USD CONS '!$B15,'BS LTD USD '!E:E) -> 2592878.1 | E15: =SUMIF('BS INC'!B:B,'BS USD CONS '!$B15,'BS INC'!E:E) -> 1085652.4 | G15: =SUMIF('BS India'!B:B,'BS USD CONS '!$B15,'BS India'!E:E) -> 142.43 | K15: =+E15+C15+I15+G15 -> 3678673 | M15: =K15/1000 -> 3678.673 | N15: =K15/1000 -> 3678.673
C16: =SUM(C8:C15) -> 84181534 | E16: =SUM(E8:E15) -> 1273967.5 | G16: =SUM(G8:G15) -> -29240.69 | K16: =+E16+C16+G16 -> 85426261 | M16: =K16/1000 -> 85426.261 | N16: =K16/1000 -> 85426.261
B18: NON-CURRENT ASSETS
B20: Investment | C20: =SUMIF('BS LTD USD '!B:B,'BS USD CONS '!$B20,'BS LTD USD '!E:E) -> 310312.38 | E20: =SUMIF('BS INC'!B:B,'BS USD CONS '!$B20,'BS INC'!E:E) -> 0 | G20: =SUMIF('BS India'!B:B,'BS USD CONS '!$B20,'BS India'!E:E) -> 0 | I20: =-C20 -> -310312.38 | K20: =+E20+C20+I20+G20 -> 0 | M20: =K20/1000 -> 0
B21: ROA Assets | C21: =SUMIF('BS LTD USD '!B:B,'BS USD CONS '!$B21,'BS LTD USD '!E:E) -> 20186267 | E21: =SUMIF('BS INC'!B:B,'BS USD CONS '!$B21,'BS INC'!E:E) -> 0 | G21: =SUMIF('BS India'!B:B,'BS USD CONS '!$B21,'BS India'!E:E) -> 0 | K21: =+E21+C21+I21+G21 -> 20186267 | M21: =K21/1000 -> 20186.267 | N21: =K21/1000 -> 20186.267
B22: Restricted LT deposit | C22: =SUMIF('BS LTD USD '!B:B,'BS USD CONS '!$B22,'BS LTD USD '!E:E) -> 2467206.5 | E22: =SUMIF('BS INC'!B:B,'BS USD CONS '!$B22,'BS INC'!E:E) -> 1199999 | G22: =SUMIF('BS India'!B:B,'BS USD CONS '!$B22,'BS India'!E:E) -> 0 | K22: =+E22+C22+I22+G22 -> 3667205.5 | M22: =K22/1000 -> 3667.2055 | N22: =K22/1000 -> 3667.2055
B23: Deferred tax assets | C23: =SUMIF('BS LTD USD '!B:B,'BS USD CONS '!$B23,'BS LTD USD '!E:E) -> 2030229.3 | E23: =SUMIF('BS INC'!B:B,'BS USD CONS '!$B23,'BS INC'!E:E) -> 0 | G23: =SUMIF('BS India'!B:B,'BS USD CONS '!$B23,'BS India'!E:E) -> 0 | K23: =+E23+C23+I23+G23 -> 2030229.3 | M23: =K23/1000 -> 2030.2293 | N23: =K23/1000 -> 2030.2293
B24: Reserve - Wordpay | C24: =SUMIF('BS LTD USD '!B:B,'BS USD CONS '!$B24,'BS LTD USD '!E:E) -> 0 | E24: =SUMIF('BS INC'!B:B,'BS USD CONS '!$B24,'BS INC'!E:E) -> 0 | G24: =SUMIF('BS India'!B:B,'BS USD CONS '!$B24,'BS India'!E:E) -> 0 | K24: =+E24+C24+I24+G24 -> 0 | M24: =K24/1000 -> 0
B25: Fixed assets, net | C25: =SUMIF('BS LTD USD '!B:B,'BS USD CONS '!$B25,'BS LTD USD '!E:E) -> 1659074.9 | E25: =SUMIF('BS INC'!B:B,'BS USD CONS '!$B25,'BS INC'!E:E) -> 0 | G25: =SUMIF('BS India'!B:B,'BS USD CONS '!$B25,'BS India'!C:C) -> 0 | K25: =+E25+C25+I25+G25 -> 1659074.9 | M25: =K25/1000 -> 1659.0749 | N25: =K25/1000 -> 1659.0749
C26: =SUM(C20:C25) -> 26653090 | E26: =SUM(E20:E25) -> 1199999 | G26: =SUM(G20:G25) -> 0 | I26: =SUM(I20:I25) -> -310312.38 | K26: =SUM(K20:K25) -> 27542777 | M26: =K26/1000 -> 27542.777 | N26: =K26/1000 -> 27542.777
N27: =K27/1000 -> 0
B28: Total Assets | C28: =+C26+C16 -> 1.1083462e+08 | E28: =+E26+E16 -> 2473966.5 | G28: =+G26+G16 -> -29240.69 | I28: =+I26+I16 -> -310312.38 | K28: =K16+K26 -> 1.1296904e+08 | M28: =K28/1000 -> 112969.04 | N28: =K28/1000 -> 112969.04
B31: CURRENT LIABILITIES
B33: Trade payables | C33: =SUMIF('BS LTD USD '!B:B,'BS USD CONS '!$B33,'BS LTD USD '!E:E) -> -7799848.3 | E33: =SUMIF('BS INC'!B:B,'BS USD CONS '!$B33,'BS INC'!E:E) -> -952301.09 | G33: =SUMIF('BS India'!B:B,'BS USD CONS '!$B33,'BS India'!C:C) -> 0 | K33: =+E33+C33+I33+G33 -> -8752149.4 | M33: =K33/1000 -> -8752.1494 | N33: =K33/1000 -> -8752.1494
B34: Accrued Expenses | C34: =SUMIF('BS LTD USD '!B:B,'BS USD CONS '!$B34,'BS LTD USD '!E:E) -> -14333945 | E34: =SUMIF('BS INC'!B:B,'BS USD CONS '!$B34,'BS INC'!E:E) -> 0 | G34: =SUMIF('BS India'!B:B,'BS USD CONS '!$B34,'BS India'!C:C) -> 0 | K34: =+E34+C34+I34+G34 -> -14333945 | M34: =K34/1000 -> -14333.945 | N34: =K34/1000 -> -14333.945
B35: Loan-Short Term | C35: =SUMIF('BS LTD USD '!B:B,'BS USD CONS '!$B35,'BS LTD USD '!E:E) -> 0 | E35: =SUMIF('BS INC'!B:B,'BS USD CONS '!$B35,'BS INC'!E:E) -> 0 | G35: =SUMIF('BS India'!B:B,'BS USD CONS '!$B35,'BS India'!C:C) -> 0 | K35: =+E35+C35+I35+G35 -> 0 | M35: =K35/1000 -> 0 | N35: =K35/1000 -> 0
B36: Contract liability | C36: =SUMIF('BS LTD USD '!B:B,'BS USD CONS '!$B36,'BS LTD USD '!E:E) -> -8960313.1 | E36: =SUMIF('BS INC'!B:B,'BS USD CONS '!$B36,'BS INC'!E:E) -> 0 | G36: =SUMIF('BS India'!B:B,'BS USD CONS '!$B36,'BS India'!C:C) -> 0 | K36: =+E36+C36+I36+G36 -> -8960313.1 | M36: =K36/1000 -> -8960.3131 | N36: =K36/1000 -> -8960.3131
B37: Tax provision | C37: =SUMIF('BS LTD USD '!B:B,'BS USD CONS '!$B37,'BS LTD USD '!E:E) -> -4156792.7 | E37: =SUMIF('BS INC'!B:B,'BS USD CONS '!$B37,'BS INC'!E:E) -> 0 | G37: =SUMIF('BS India'!B:B,'BS USD CONS '!$B37,'BS India'!C:C) -> 0 | K37: =+E37+C37+I37+G37 -> -4156792.7 | M37: =K37/1000 -> -4156.7927 | N37: =K37/1000 -> -4156.7927
B38: Warrant liability | C38: =SUMIF('BS LTD USD '!B:B,'BS USD CONS '!$B38,'BS LTD USD '!E:E) -> -1411357.4 | E38: =SUMIF('BS INC'!B:B,'BS USD CONS '!$B38,'BS INC'!E:E) -> 0 | G38: =SUMIF('BS India'!B:B,'BS USD CONS '!$B38,'BS India'!C:C) -> 0 | K38: =+E38+C38+I38+G38 -> -1411357.4 | M38: =K38/1000 -> -1411.3574 | N38: =K38/1000 -> -1411.3574
B39: ROA Liability ST | C39: =SUMIF('BS LTD USD '!B:B,'BS USD CONS '!$B39,'BS LTD USD '!E:E) -> -958916.79 | E39: =SUMIF('BS INC'!B:B,'BS USD CONS '!$B39,'BS INC'!E:E) -> 0 | G39: =SUMIF('BS India'!B:B,'BS USD CONS '!$B39,'BS India'!C:C) -> 0 | K39: =+E39+C39+I39+G39 -> -958916.79 | M39: =K39/1000 -> -958.91679 | N39: =K39/1000 -> -958.91679
B40: ROA Liability LT | C40: =SUMIF('BS LTD USD '!B:B,'BS USD CONS '!$B40,'BS LTD USD '!E:E) -> -17832251 | K40: =+E40+C40+I40+G40 -> -17832251 | M40: =K40/1000 -> -17832.251 | N40: =K40/1000 -> -17832.251
B41: Sales Tax Provision | C41: =SUMIF('BS LTD USD '!B:B,'BS USD CONS '!$B41,'BS LTD USD '!E:E) -> -15835320 | E41: =SUMIF('BS INC'!B:B,'BS USD CONS '!$B41,'BS INC'!E:E) -> 0 | G41: =SUMIF('BS India'!B:B,'BS USD CONS '!$B41,'BS India'!C:C) -> 0 | K41: =+E41+C41+I41+G41 -> -15835320 | M41: =K41/1000 -> -15835.32 | N41: =K41/1000 -> -15835.32
B42: Employees payables | C42: =SUMIF('BS LTD USD '!B:B,'BS USD CONS '!$B42,'BS LTD USD '!E:E) -> -4238437.8 | E42: =SUMIF('BS INC'!B:B,'BS USD CONS '!$B42,'BS INC'!E:E) -> 0 | G42: =SUMIF('BS India'!B:B,'BS USD CONS '!$B42,'BS India'!C:C) -> 0 | K42: =+E42+C42+I42+G42 -> -4238437.8 | M42: =K42/1000 -> -4238.4378 | N42: =K42/1000 -> -4238.4378
B43: Deferred tax liability | C43: =SUMIF('BS LTD USD '!B:B,'BS USD CONS '!$B43,'BS LTD USD '!E:E) -> 0 | E43: =SUMIF('BS INC'!B:B,'BS USD CONS '!$B43,'BS INC'!E:E) -> 0 | G43: =SUMIF('BS India'!B:B,'BS USD CONS '!$B43,'BS India'!C:C) -> 0 | K43: =+E43+C43+I43+G43 -> 0 | M43: =K43/1000 -> 0 | N43: =K43/1000 -> 0
B44: Other accounts payable | C44: =SUMIF('BS LTD USD '!B:B,'BS USD CONS '!$B44,'BS LTD USD '!E:E) -> 0 | E44: =SUMIF('BS INC'!B:B,'BS USD CONS '!$B44,'BS INC'!E:E) -> -1211355.4 | G44: =SUMIF('BS India'!B:B,'BS USD CONS '!$B44,'BS India'!C:C) -> -22095.35 | K44: =+E44+C44+I44+G44 -> -1233450.8 | M44: =K44/1000 -> -1233.4507 | N44: =K44/1000 -> -1233.4507
C45: =SUM(C33:C44) -> -75527182 | E45: =SUM(E31:E44) -> -2163656.5 | G45: =SUM(G31:G44) -> -22095.35 | K45: =+E45+C45+G45 -> -77712934 | M45: =K45/1000 -> -77712.934 | N45: =K45/1000 -> -77712.934
N46: =K46/1000 -> 0
N47: =K47/1000 -> 0
B48: Total liabilities | C48: =+C45 -> -75527182 | E48: =+E45 -> -2163656.5 | G48: =+G45 -> -22095.35 | I48: =+I45 -> 0 | K48: =+E48+C48+G48 -> -77712934 | M48: =K48/1000 -> -77712.934 | N48: =K48/1000 -> -77712.934
N49: =K49/1000 -> 0
B50: SHAREHOLDERS' EQUITY | N50: =K50/1000 -> 0
N51: =K51/1000 -> 0
B52: Share capital - Ordinary Shares | C52: =SUMIF('BS LTD USD '!B:B,'BS USD CONS '!$B52,'BS LTD USD '!E:E) -> -690.22 | E52: =SUMIF('BS INC'!B:B,'BS USD CONS '!$B52,'BS INC'!E:E) -> 0 | G52: =SUMIF('BS India'!B:B,'BS USD CONS '!$B52,'BS India'!C:C) -> 0 | K52: =+E52+C52+I52+G52 -> -690.22 | M52: =K52/1000 -> -0.69022 | N52: =K52/1000 -> -0.69022
B53: Share capital - Preferred Seed-1 | C53: =SUMIF('BS LTD USD '!B:B,'BS USD CONS '!$B53,'BS LTD USD '!E:E) -> -191 | E53: =SUMIF('BS INC'!B:B,'BS USD CONS '!$B53,'BS INC'!E:E) -> 0 | G53: =SUMIF('BS India'!B:B,'BS USD CONS '!$B53,'BS India'!C:C) -> 0 | K53: =+E53+C53+I53+G53 -> -191 | M53: =K53/1000 -> -0.191 | N53: =K53/1000 -> -0.191
B54: Share capital - Preferred Seed | C54: =SUMIF('BS LTD USD '!B:B,'BS USD CONS '!$B54,'BS LTD USD '!E:E) -> -49.24 | E54: =SUMIF('BS INC'!B:B,'BS USD CONS '!$B54,'BS INC'!E:E) -> 0 | G54: =SUMIF('BS India'!B:B,'BS USD CONS '!$B54,'BS India'!C:C) -> 0 | K54: =+E54+C54+I54+G54 -> -49.24 | M54: =K54/1000 -> -0.04924 | N54: =K54/1000 -> -0.04924
B55: Share premium | C55: =SUMIF('BS LTD USD '!B:B,'BS USD CONS '!$B55,'BS LTD USD '!E:E) -> -8818490.6 | E55: =SUMIF('BS INC'!B:B,'BS USD CONS '!$B55,'BS INC'!E:E) -> 0 | G55: =SUMIF('BS India'!B:B,'BS USD CONS '!$B55,'BS India'!C:C) -> 0 | K55: =+E55+C55+I55+G55 -> -8818490.6 | M55: =K55/1000 -> -8818.4906 | N55: =K55/1000 -> -8818.4906
B56: Receivables for shares issued | C56: =SUMIF('BS LTD USD '!B:B,'BS USD CONS '!$B56,'BS LTD USD '!E:E) -> 0 | E56: =SUMIF('BS INC'!B:B,'BS USD CONS '!$B56,'BS INC'!E:E) -> 0 | G56: =SUMIF('BS India'!B:B,'BS USD CONS '!$B56,'BS India'!C:C) -> 0 | K56: =+E56+C56+I56+G56 -> 0 | M56: =K56/1000 -> 0 | N56: =K56/1000 -> 0
B57: Accumulated deficit | C57: =SUMIF('BS LTD USD '!B:B,'BS USD CONS '!$B57,'BS LTD USD '!E:E) -> -4082936.6 | E57: =SUMIF('BS INC'!B:B,'BS USD CONS '!$B57,'BS INC'!E:E) -> -297517.45 | G57: =SUMIF('BS India'!B:B,'BS USD CONS '!$B57,'BS India'!C:C) -> 0 | I57: =-E57 -> 297517.45 | K57: =+E57+C57+I57+G57 -> -4082936.6 | M57: =K57/1000 -> -4082.9366 | N57: =K57/1000 -> -4082.9366
B58: PL | C58: ='P&L LTD USD'!F122 -> -22405084 | E58: =SUMIF('BS INC'!B:B,'BS USD CONS '!$B58,'BS INC'!E:E) -> -12793.34 | G58: =SUMIF('BS India'!B:B,'BS USD CONS '!$B58,'BS India'!C:C) -> 51336.04 | I58: =-E58 -> 12793.34 | K58: =+E58+C58+I58+G58 -> -22353748 | M58: =K58/1000 -> -22353.748 | N58: =K58/1000 -> -22353.748
C59: =SUM(C52:C58) -> -35307442 | E59: =SUM(E52:E58) -> -310310.79 | G59: =SUM(G52:G58) -> 51336.04 | K59: =SUM(K52:K58) -> -35256106 | M59: =K59/1000 -> -35256.106 | N59: =K59/1000 -> -35256.106
K60: =+E60+C60 -> 0 | M60: =K60/1000 -> 0 | N60: =K60/1000 -> 0
C61: =C59+C48 -> -1.1083462e+08 | E61: =E59+E48 -> -2473967.3 | G61: =G59+G48 -> 29240.69 | K61: =K59+K48 -> -1.1296904e+08 | M61: =K61/1000 -> -112969.04 | N61: =K61/1000 -> -112969.04
C62: =+C61=-C28 -> FALSE | E62: =+E61=E28 -> FALSE | G62: =+G61=G28 -> FALSE | K62: =+K61+K28 -> -2.4099999 | M62: =K62/1000 -> -0.0024099999 | N62: =K62/1000 -> -0.0024099999
C63: =+C61+C28 -> -0.0099999905 | E63: =+E61+E28 -> -0.80999996 | G63: =+G61+G28 -> 0 | K63: =+E63+C63 -> -0.81999995 | M63: =K63/1000 -> -0.00081999995 | N63: =K63/1000 -> -0.00081999995
N64: =K64/1000 -> 0
N65: =K65/1000 -> 0
N66: =K66/1000 -> 0
N67: =K67/1000 -> 0
N68: =K68/1000 -> 0
N69: =K69/1000 -> 0
N70: =K70/1000 -> 0
N71: =K71/1000 -> 0
N72: =K72/1000 -> 0
N73: =K73/1000 -> 0
N74: =K74/1000 -> 0
N75: =K75/1000 -> 0
... N77: =K77/1000 -> 0

Sheet P&L USD CONS
D3: 2022 | F3: 2022 | H3: 2022 | J3: 2022 | L3: 2022 | N3: 2022
D4: LTD | F4: INC | H4: India | J4: Cons | L4: Cons | N4: Cons
D5: USD | F5: USD | H5: USD | J5: USD | L5: USD | N5: $ In thousands
B7: Total Revenues | D7: =SUMIF('P&L LTD USD'!C:C,B:B,'P&L LTD USD'!F:F) -> -3.3423953e+08 | F7: =SUMIF('P&L INC'!B:B,'P&L USD CONS'!$B:$B,'P&L INC'!F:F) -> -3.8458971e+08 | H7: =SUMIF('P&L India'!B:B,'P&L USD CONS'!$B:$B,'P&L India'!D:D) -> 0 | J7: =-F7 -> 3.8458971e+08 | L7: =(+F7+D7+H7+J7) -> -3.3423953e+08 | N7: =L7/1000 -> -334239.53
B9: Operations | D9: =SUMIF('P&L LTD USD'!C:C,B:B,'P&L LTD USD'!F:F) -> 23057127 | F9: =SUMIF('P&L INC'!B:B,'P&L USD CONS'!$B:$B,'P&L INC'!F:F) -> 19761872 | H9: =SUMIF('P&L India'!B:B,'P&L USD CONS'!$B:$B,'P&L India'!D:D) -> 0 | J9: =-F9 -> -19761872 | L9: =(+F9+D9+H9+J9) -> 23057127 | N9: =L9/1000 -> 23057.127
B11: Gross loss (profit) | D11: =D9+D7 -> -3.111824e+08 | F11: =F9+F7 -> -3.6482784e+08 | H11: =H9+H7 -> 0 | J11: =J9+J7 -> 3.6482784e+08 | L11: =L9+L7 -> -3.111824e+08 | N11: =N9+N7 -> -311182.4
B13: Research and development expenses, net | D13: =SUMIF('P&L LTD USD'!C:C,B:B,'P&L LTD USD'!F:F) -> 20781725 | F13: =SUMIF('P&L INC'!B:B,'P&L USD CONS'!$B:$B,'P&L INC'!F:F) -> 0 | H13: =-SUMIF('P&L India'!B:B,'P&L USD CONS'!$B:$B,'P&L India'!D:D) -> 0 | L13: =(+F13+D13+H13+J13) -> 20781725 | N13: =L13/1000 -> 20781.725
B15: Marketing expenses | D15: =SUMIF('P&L LTD USD'!C:C,B:B,'P&L LTD USD'!F:F) -> 2.5601775e+08 | F15: =SUMIF('P&L INC'!B:B,'P&L USD CONS'!$B:$B,'P&L INC'!F:F) -> 24957328 | H15: =SUMIF('P&L India'!B:B,'P&L USD CONS'!$B:$B,'P&L India'!D:D) -> 30322.73 | J15: =-F15 -> -24957328 | L15: =(+F15+D15+H15+J15) -> 2.5604807e+08 | N15: =L15/1000 -> 256048.07
B17: General and administrative expenses | D17: =SUMIF('P&L LTD USD'!C:C,B:B,'P&L LTD USD'!F:F) -> 8244728.4 | F17: =SUMIF('P&L INC'!B:B,'P&L USD CONS'!$B:$B,'P&L INC'!F:F) -> 182761.95 | H17: =SUMIF('P&L India'!B:B,'P&L USD CONS'!$B:$B,'P&L India'!D:D) -> 20751.2 | J17: =-F17*1.07 -> -195555.29 | L17: =(+F17+D17+H17+J17) -> 8252686.3 | N17: =L17/1000 -> 8252.6863 | O17: =J17+F17 -> -12793.337
B19: Operating expenses | D19: =+D17+D15+D13 -> 2.850442e+08 | F19: =+F17+F15+F13 -> 25140090 | H19: =+H17+H15+H13 -> 51073.93 | J19: =+J17+J15+J13 -> -25152883 | L19: =+L17+L15+L13 -> 2.8508248e+08 | N19: =+N17+N15+N13 -> 285082.48
B21: Operating loss (pprofit) | D21: =SUMIF('P&L LTD USD'!C:C,B:B,'P&L LTD USD'!F:F) -> -26138202 | F21: =F11+F19 -> -3.3968775e+08 | H21: =H11+H19 -> 51073.93 | J21: =J11+J19 -> 3.3967496e+08 | L21: =L11+L19 -> -26099922 | N21: =N19+N11 -> -26099.922
B23: Financial expenses, net | D23: =SUMIF('P&L LTD USD'!C:C,B:B,'P&L LTD USD'!F:F) -> 242412.35 | F23: =SUMIF('P&L INC'!B:B,'P&L USD CONS'!$B:$B,'P&L INC'!F:F) -> 179789.7 | H23: =SUMIF('P&L India'!B:B,'P&L USD CONS'!$B:$B,'P&L India'!D:D) -> 262.11 | J23: =-F23 -> -179789.7 | L23: =(+F23+D23+H23+J23) -> 242674.46 | N23: =L23/1000 -> 242.67446
B25: TP Expenses | D25: =SUMIF('P&L LTD USD'!C:C,B:B,'P&L LTD USD'!F:F) -> 0 | F25: =SUMIF('P&L INC'!B:B,'P&L USD CONS'!$B:$B,'P&L INC'!F:F) -> 3.3940583e+08 | H25: =SUMIF('P&L India'!B:B,'P&L USD CONS'!$B:$B,'P&L India'!D:D) -> 0 | J25: =-F25 -> -3.3940583e+08 | L25: =(+F25+D25+H25+J25) -> 0 | N25: =L25/1000 -> 0
B27: Equity | D27: =SUMIF('P&L LTD USD'!C:C,B:B,'P&L LTD USD'!F:F) -> -12793.34 | F27: =SUMIF('P&L INC'!B:B,'P&L USD CONS'!$B:$B,'P&L INC'!D:D) -> 0 | H27: =SUMIF('P&L India'!B:B,'P&L USD CONS'!$B:$B,'P&L India'!D:D) -> 0 | L27: =(+F27+D27+H27) -> -12793.34 | N27: =L27/1000 -> -12.79334
B29: loss before taxes | D29: =SUM(D21:D27) -> -25908583 | F29: =SUM(F21:F27) -> -102130.89 | H29: =SUM(H21:H27) -> 51336.04 | J29: =SUM(J21:J27) -> 89337.553 | L29: =SUM(L21:L27) -> -25870040 | N29: =SUM(N21:N27) -> -25870.04
B31: Tax expenses | D31: =SUMIF('P&L LTD USD'!C:C,B:B,'P&L LTD USD'!F:F) -> 3503498.7 | F31: =SUMIF('P&L INC'!B:B,'P&L USD CONS'!$B:$B,'P&L INC'!F:F) -> 89337.55 | H31: =SUMIF('P&L India'!B:B,'P&L USD CONS'!$B:$B,'P&L India'!D:D) -> 0 | J31: =-F31 -> -89337.55 | L31: =(+F31+D31+H31+J31) -> 3503498.7 | N31: =L31/1000 -> 3503.4987
B33: Net loss ( profit ) | D33: =+D29+D31 -> -22405084 | F33: =+F31+F29 -> -12793.34 | H33: =+H31+H29 -> 51336.04 | J33: =+J31+J29 -> 0.0034999967 | L33: =+L29+L31 -> -22366542 | N33: =+N29+N31 -> -22366.542
D34: =D33-'P&L LTD USD'!F122 -> 0 | F34: =F33-'P&L INC'!F51 -> -1.1990778e-08 | H34: ='P&L India'!D28-H33 -> 0
D35: =D9+D13+D15+D17+D23+D31 -> 3.1184724e+08 | F35: =F9+F13+F15+F17+F23+F31 -> 45171089 | H35: =H9+H13+H15+H17+H23+H31 -> 51336.04 | L35: =L9+L13+L15+L17+L23+L31 -> 3.1188578e+08 | N35: -21787.447
N36: =N35-N33 -> 579.09429

Sheet COA LTD
A1: חשבון | B1: תאור חשבון
A2: 10000 | B2: Leumi IL 568400 | C2: BS | D2: cash
A3: 10001 | B3: Leumi $ 568400 | C3: BS | D3: cash
A4: 10002 | B4: Leumi GBP 568400 | C4: BS | D4: cash
A5: 10003 | B5: Leumi EURO 568400 | C5: BS | D5: cash
A6: 10004 | B6: SVB LTD | C6: BS | D6: cash
A7: 10200 | B7: Bank Paypal LTD-USD | C7: BS | D7: cash
A8: 11004 | B8: Applovin | C8: BS | D8: Account receivable
A9: 11100 | B9: Account receivable | C9: BS | D9: Account receivable
A10: 12000 | B10: Papaya Gaming INC | C10: BS | D10: Related Party
A11: 13000 | B11: Vat D/C | C11: BS | D11: Other accounts receivable
A12: 13002 | B12: VAT input | C12: BS | D12: Other accounts receivable
A13: 13003 | B13: VAT Input FA | C13: BS | D13: Other accounts receivable
... A136: 51200 | B136: Premium | C136: BS | D136: Share premium
A137: 53000 | B137: Capital reserve for share-based Payment | C137: BS | D137: Other accounts receivable | E137: 0
A138: 54000 | B138: Accumulated deficit | C138: BS | D138: Accumulated deficit | E138: 0
A139: 60202000 | B139: Revenue - Revenue Worldpay IC | C139: PL | D139: Revenues | E139: Revenues
A140: 60202007 | B140: Revenue - Revenue Paypal IL IC | C140: PL | D140: Revenues | E140: Revenues
A141: 60202009 | B141: Revenue - Revenue Paypal US IC | C141: PL | D141: Revenues | E141: Revenues
A142: 60202016 | B142: Revenue - Revenue Cyber Source IC | C142: PL | D142: Revenues | E142: Revenues
A143: 60202023 | B143: Revenue - Revenue Braintree IC | C143: PL | D143: Revenues | E143: Revenues
A144: 60202101 | B144: Revenue - Israeli Customer | C144: PL | D144: Revenues | E144: Revenues
A145: 60202094 | B145: Revenue - Advertising income | C145: PL | D145: Revenues | E145: ads revenue
A146: 60202095 | B146: Revenue - Advertising income- VAT | C146: PL | D146: Revenues | E146: ads revenue
A147: 60202097 | B147: Revenue - Net cash Balance | C147: PL | D147: Revenues | E147: Net cash
A148: 60202098 | B148: Revenue - Self invoice Debit | C148: PL | D148: Revenues | E148: Revenues
A149: 60202099 | B149: Revenue - Self invoice Credit | C149: PL | D149: Revenues | E149: Revenues
A150: 60202100 | B150: Revenue - Withdrawals | C150: PL | D150: Revenues | E150: Withdrawals
... A154: 60203016 | B154: Revenue - Revenue Paypal Cyber Source Receiveab | C154: PL | D154: Revenues | E154: Revenues
A155: 60203094 | B155: Revenue - Revenue Advertising Receiveable | C155: PL | D155: Revenues | E155: ads revenue | F155: ;
A156: 70201200 | B156: Tax - Tax expenses current period | C156: PL | D156: Tax expenses | E156: Tax expenses
A157: 80010100 | B157: Operations Support- Base salary | C157: PL | D157: Operations | E157: Salary
A158: 80010101 | B158: Operations Support- Contractors as employees Sup | C158: PL | D158: Operations | E158: Salary
A159: 80010102 | B159: Operations Support- Options | C159: PL | D159: Operations | E159: option expenses
A160: 80010104 | B160: Operations Support- Bonus provision | C160: PL | D160: Operations | E160: Salary
A161: 80010105 | B161: Operations Support- Bonus-subcontractors | C161: PL | D161: Operations | E161: Salary
A162: 80010107 | B162: Operations Support- vacation provision | C162: PL | D162: Operations | E162: Salary
A163: 80010108 | B163: Operations Support- Social security | C163: PL | D163: Operations | E163: Salary
A164: 80010109 | B164: Operations Support- Pension | C164: PL | D164: Operations | E164: Salary
A165: 80010110 | B165: Operations Support- Education fund | C165: PL | D165: Operations | E165: Salary
A166: 80010111 | B166: Operations Support- Recuperation | C166: PL | D166: Operations | E166: Salary
A167: 80010112 | B167: Operations Support- Severance | C167: PL | D167: Operations | E167: Salary
... A424: 90201106 | B424: Financial exp - Cancellation balances | C424: PL | D424: Financial expenses, net | E424: Exchange rate
A425: 90019 | B425: הכנסות נדחות - מאזני | C425: BS | D425: Trade payables
A426: 10100 | B426: פקדון כנגד שעבוד זמן ארוך (לטובת מסגרת כ״א) | C426: BS | D426: Deposit
A427: 10101 | B427: Deposit | C427: BS | D427: Deposit
A428: 340000 | B428: טוטאל פינאנס בע"מ | C428: BS | D428: Trade payables
A429: 340026 | B429: ה.ס.פ. - הסעות ושליחויות | C429: BS | D429: Trade payables
A430: 340051 | B430: אטיאס אופיס קולקשיין בע״מ | C430: BS | D430: Trade payables
A431: 340056 | B431: גט טקסי סירוויס | C431: BS | D431: Trade payables
A432: 340058 | B432: וואלט אנטרפריזס ישראל | C432: BS | D432: Trade payables
A433: 340071 | B433: רמי לוי | C433: BS | D433: Trade payables
A434: 340084 | B434: ריסקיפייד בע"מ | C434: BS | D434: Trade payables
A435: 340105 | B435: ווייד אופס בע"מ | C435: BS | D435: Trade payables
A436: 340117 | B436: דבוסקין ייעוץ בע"מ | C436: BS | D436: Trade payables
... A504: 10005 | B504: SVB-MMA **6735 | C504: BS | D504: cash
A505: 80010113 | B505: Operations Support- Reserve refund | C505: PL | D505: Operations | E505: Salary
A506: 81020200 | B506: RnD Analytics- Professional Services | C506: PL | D506: Research and development expenses, net | E506: Professional Services
A507: 81200408 | B507: RnD - Office | C507: PL | D507: Research and development expenses, net | E507: Rent and related
A508: 81200601 | B508: RnD - Team bulilding | C508: PL | D508: Research and development expenses, net | E508: Welfare
A509: 83120201 | B509: G&A Finance- Audit | C509: PL | D509: General and administrative expenses | E509: Professional Services
A510: 83200209 | B510: G&A - Hekzev expenses | C510: PL | D510: General and administrative expenses | E510: Rent and related
A511: 83200601 | B511: G&A - Team bulilding | C511: PL | D511: General and administrative expenses | E511: Welfare
A512: 83140801 | B512: G&A G&A- DnO | C512: PL | D512: General and administrative expenses | E512: insurance
A513: 84200404 | B513: Allocation - electricity | C513: PL | D513: General and administrative expenses | E513: Allocation
A514: 84200407 | B514: Allocation - Parking | C514: PL | D514: General and administrative expenses | E514: Allocation
A515: 84200408 | B515: Allocation - Office | C515: PL | D515: General and administrative expenses | E515: Allocation
A516: 84200409 | B516: Allocation - Transportation | C516: PL | D516: General and administrative expenses | E516: Allocation
A517: 13001 | B517: Vat Output | C517: BS | D517: Other accounts payable
A518: 340202 | B518: גונון בת קול בע״מ | C518: BS | D518: Trade payables
A519: 340289 | B519: לאבס תל אביב בע"מ | C519: BS | D519: Trade payables
A520: 340316 | B520: שיפינג טו.גו. בע"מ | C520: BS | D520: Trade payables
A521: 340328 | B521: היי ביז בע"מ | C521: BS | D521: Trade payables
A522: 340330 | B522: פיתוח ארגוני פיאוסידי | C522: BS | D522: Trade payables
A523: 340342 | B523: איוונטהנדלר בע"מ | C523: BS | D523: Trade payables
A524: 340343 | B524: נחמקין שאול | C524: BS | D524: Trade payables
A525: 341017 | B525: Box UK | C525: BS | D525: Trade payables
A526: 341060 | B526: SignNow | C526: BS | D526: Trade payables
A527: 341077 | B527: Fluent | C527: BS | D527: Trade payables
A528: 341110 | B528: Dla Piper LLP | C528: BS | D528: Trade payables
... A536: 38300 | B536: Employee D/C | C536: BS | D536: Trade payables
A537: 22222 | B537: הפרשי שער
A538: 80010120 | B538: Operations Support- Gifts Value D | C538: PL | D538: Operations | E538: salary
A539: 80010121 | B539: Operations Support- Gifts Value C | C539: PL | D539: Operations | E539: salary
A540: 81020120 | B540: RnD Analytics- Gifts Value D | C540: PL | D540: Research and development expenses, net | E540: salary
A541: 81020121 | B541: RnD Analytics- Gifts Value C | C541: PL | D541: Research and development expenses, net | E541: salary
A542: 81030120 | B542: RnD Art- Gifts Value D | C542: PL | D542: Research and development expenses, net | E542: salary
A543: 81030121 | B543: RnD Art- Gifts Value C | C543: PL | D543: Research and development expenses, net | E543: salary
A544: 81040120 | B544: RnD Product- Gifts Value D | C544: PL | D544: Research and development expenses, net | E544: salary
A545: 81040121 | B545: RnD Product- Gifts Value C | C545: PL | D545: Research and development expenses, net | E545: salary
A546: 81050120 | B546: RnD Monetization- Gifts Value D | C546: PL | D546: Research and development expenses, net | E546: salary
A547: 81050121 | B547: RnD Monetization- Gifts Value C | C547: PL | D547: Research and development expenses, net | E547: salary
A548: 81060120 | B548: RnD Development- Gifts Value D | C548: PL | D548: Research and development expenses, net | E548: salary
A549: 81060121 | B549: RnD Development- Gifts Value C | C549: PL | D549: Research and development expenses, net | E549: salary
... A569: 90201105 | B569: Financial exp - Interest Income | C569: PL | D569: Financial expenses, net | E569: Loan interest
A570: 340002 | B570: דפוס אופסט ראובן | C570: BS | D570: Trade payables
A571: 80200404 | B571: Operations - electricity | C571: PL | D571: Operations | E571: Rent and related
A572: 80200407 | B572: Operations - Parking | C572: PL | D572: Operations | E572: Rent and related
A573: 80200408 | B573: Operations - Office | C573: PL | D573: Operations | E573: Rent and related
A574: 80200409 | B574: Operations - Transportation | C574: PL | D574: Operations | E574: Rent and related
...

Sheet FS Notes ILS
B3: Note 3 - חייבים ויתרות חובה
F4: Signed FS
B5: Group | D5: 44926 | F5: 44561
B6: מוסדות ממשלתיים | D6: =SUM('TB LTD 12.22'!F14:F16)/1000 -> 4373.887 | F6: 4413
B7: הוצאות מראש | D7: ='BS LTD USD '!K14/1000 -> 2150.687 | F7: 3162
B8: חייבים על חשבון מניות | D8: ='TB LTD 12.22'!F157/1000 -> 68.76185 | F8: 171
B9: חייבים בגין הקצב | D9: =SUM('TB LTD 12.22'!F17)/1000 -> 4679.8518 | F9: 0
B11: סה״כ | D11: =SUM(D6:D9) -> 11273.188 | F11: =SUM(F6:F9) -> 7746
D12: =D11-'BS LTD USD '!N14 -> 0
B14: Note 4 - רכוש קבוע נטו
F15: Signed FS
B16: Group | D16: 44926 | F16: 44561
B17: מחשבים וציוד אלקטרוני | D17: =SUM('TB LTD 12.22'!F30,'TB LTD 12.22'!F31)/1000 -> 3093.2701 | F17: 1308
B18: ריהוט וציוד משרדי | D18: =('TB LTD 12.22'!F27+'TB LTD 12.22'!F28)/1000 -> 2817.3151 | F18: 574
B19: שיפורים במושכר | D19: ='TB LTD 12.22'!F29/1000 -> 758.76923 | F19: 118
D20: =SUM(D17:D19) -> 6669.3544 | F20: =SUM(F17:F19) -> 2000
B22: בניכוי פחת שנצבר | D22: =SUM('TB LTD 12.22'!F33:F37)/1000 -> -1072.9372 | F22: -369
B24: סה״כ | D24: =SUM(D20:D22) -> 5596.4173 | F24: =SUM(F20:F22) -> 1631
D25: =D24-'BS LTD USD '!M23 -> 0
B26: הוצאות פחת | D26: 704 | F26: 268
B29: Note 4 - זכאים ויתרות זכות
F30: Signed FS
B31: Group | D31: 44926 | F31: 44561
B32: הוצאות לשלם | D32: =-'BS LTD USD '!M33 -> 50441.183 | F32: 33054
B33: מיסים לשלם | D33: =-'BS LTD USD '!M37-'BS LTD USD '!M36-SUM('TB LTD 12.22'!F36,'TB LTD 12.22'!F111,'TB LTD 12.22'!F38)/1000 -> 76401.737 | F33: 21536
B34: שכר | D34: =-SUM('TB LTD 12.22'!F19,'TB LTD 12.22'!F112,'TB LTD 12.22'!F116:F124)/1000 -> 53451.326 | F34: 2449
B36: סה״כ | D36: =SUM(D32:D34) -> 180294.25 | F36: =SUM(F32:F34) -> 57039
D37: =D36+'BS LTD USD '!N33 -> 44585.757

Sheet BS LTD USD 
B1: -17832251 | C1: USD -LTD | I1: ILS -LTD
C3: 44926 | E3: 44926 | I3: 44926 | K3: 44926
A4: Restricted | D4: JE | E4: AJE | J4: JE | K4: AJE
B6: CURRENT ASSETS
B8: Cash | C8: =SUMIF('TB LTD 12.22'!I:I,B8,'TB LTD 12.22'!G:G) -> 23504184 | E8: =C8+D8 -> 23504184 | I8: =SUMIF('TB LTD 12.22'!I:I,B8,'TB LTD 12.22'!F:F) -> 82711224 | K8: =I8+J8 -> 82711224 | L8: =K8/E8 -> 3.519 | M8: =K8/1000 -> 82711.224
B9: Account receivable | C9: =SUMIF('TB LTD 12.22'!I:I,B9,'TB LTD 12.22'!G:G) -> 2668238.6 | D9: ='AJE 2022'!G49 -> 0 | E9: =C9+D9 -> 2668238.6 | I9: =SUMIF('TB LTD 12.22'!I:I,B9,'TB LTD 12.22'!F:F) -> 9389531.7 | J9: ='AJE 2022'!J49 -> 0 | K9: =I9+J9 -> 9389531.7 | L9: =K9/E9 -> 3.519 | M9: =K9/1000 -> 9389.5317
B10: Related Party | C10: =SUMIF('TB LTD 12.22'!I:I,B10,'TB LTD 12.22'!G:G) -> 24505604 | D10: =-'AJE 2022'!H13-'AJE 2022'!H23-'AJE 2022'!H28-'AJE 2022'!H33+'AJE 2022'!G43-'AJE 2022'!H50 -> 0 | E10: =C10+D10 -> 24505604 | I10: =SUMIF('TB LTD 12.22'!I:I,B10,'TB LTD 12.22'!F:F) -> 86235220 | J10: =-'AJE 2022'!K13-'AJE 2022'!K23-'AJE 2022'!K28-'AJE 2022'!K33+'AJE 2022'!J43-'AJE 2022'!J49 -> 0 | K10: =I10+J10 -> 86235220 | L10: =K10/E10 -> 3.519 | M10: =K10/1000 -> 86235.22 | N10: =M10+M11 -> 86338.619 | O10: =E10*3.519 -> 86235220 | P10: =O10-K10 -> -0.003370136
B11: Related Party India | C11: =SUMIF('TB LTD 12.22'!I:I,B11,'TB LTD 12.22'!G:G) -> 29383.12 | E11: =C11+D11 -> 29383.12 | I11: =SUMIF('TB LTD 12.22'!I:I,B11,'TB LTD 12.22'!F:F) -> 103399.2 | K11: =I11+J11 -> 103399.2 | L11: =K11/E11 -> 3.519 | M11: =K11/1000 -> 103.3992
B12: Short term deposit | C12: =SUMIF('TB LTD 12.22'!I:I,B12,'TB LTD 12.22'!G:G) -> 30270082 | D12: ='AJE 2022'!H93 -> 0 | E12: =C12+D12 -> 30270082 | I12: =SUMIF('TB LTD 12.22'!I:I,B12,'TB LTD 12.22'!F:F) -> 106520419 | J12: ='AJE 2022'!K93 -> 0 | K12: =I12+J12 -> 106520419 | L12: =K12/E12 -> 3.519 | M12: =K12/1000 -> 106520.42
B13: Shareholders' loan | C13: =SUMIF('TB LTD 12.22'!I:I,B13,'TB LTD 12.22'!G:G) -> 0 | E13: =C13+D13 -> 0 | I13: =SUMIF('TB LTD 12.22'!I:I,B13,'TB LTD 12.22'!F:F) -> 0 | K13: =I13+J13 -> 0 | L13: =K13/E13 -> #DIV/0! | M13: =K13/1000 -> 0
B14: Prepaid Expenses | C14: =SUMIF('TB LTD 12.22'!I:I,B14,'TB LTD 12.22'!G:G) -> 611164.27 | D14: =-'AJE 2022'!H81 -> 0 | E14: =C14+D14 -> 611164.27 | I14: =SUMIF('TB LTD 12.22'!I:I,B14,'TB LTD 12.22'!F:F) -> 2150687 | J14: =-'AJE 2022'!K81 -> 0 | K14: =I14+J14 -> 2150687 | L14: =K14/E14 -> 3.519 | M14: =K14/1000 -> 2150.687 | N14: =M14+M15 -> 11273.188
B15: Other accounts receivable | C15: =SUMIF('TB LTD 12.22'!I:I,B15,'TB LTD 12.22'!G:G) -> 2592878.1 | E15: =C15+D15 -> 2592878.1 | I15: =SUMIF('TB LTD 12.22'!I:I,B15,'TB LTD 12.22'!F:F) -> 9122500.7 | K15: =I15+J15 -> 9122500.7 | L15: =K15/E15 -> 3.5182913 | M15: =K15/1000 -> 9122.5006
C16: =SUM(C8:C15) -> 84181534 | D16: =SUM(D8:D15) -> 0 | E16: =SUM(E8:E15) -> 84181534 | I16: =SUM(I8:I15) -> 2.9623298e+08 | J16: =SUM(J8:J15) -> 0 | K16: =SUM(K8:K15) -> 2.9623298e+08 | L16: =K16/E16 -> 3.5189782 | M16: =K16/1000 -> 296232.98 | O16: 297457
L17: =K17/E17 -> #DIV/0! | M17: =K17/1000 -> 0 | O17: 89523
B18: NON-CURRENT ASSETS | L18: =K18/E18 -> #DIV/0! | M18: =K18/1000 -> 0
L19: =K19/E19 -> #DIV/0! | M19: =K19/1000 -> 0
B20: Investment | C20: =SUMIF('TB LTD 12.22'!I:I,B20,'TB LTD 12.22'!G:G) -> 297519.04 | D20: =-'P&L INC'!F51 -> 12793.34 | E20: =C20+D20 -> 310312.38 | I20: =SUMIF('TB LTD 12.22'!I:I,B20,'TB LTD 12.22'!F:F) -> 970500.41 | J20: =-'P&L LTD USD'!K121 -> 42857.689 | K20: =I20+J20 -> 1013358.1 | L20: =K20/E20 -> 3.2656064 | M20: =K20/1000 -> 1013.3581
B21: Restricted LT deposit | C21: =SUMIF('TB LTD 12.22'!I:I,B21,'TB LTD 12.22'!G:G) -> 2467206.5 | E21: =C21+D21 -> 2467206.5 | I21: =SUMIF('TB LTD 12.22'!I:I,B21,'TB LTD 12.22'!F:F) -> 8682099.8 | K21: =I21+J21 -> 8682099.8 | L21: =K21/E21 -> 3.519 | M21: =K21/1000 -> 8682.0997
B22: ROA Assets | C22: =SUMIF('TB LTD 12.22'!I:I,B22,'TB LTD 12.22'!G:G) -> 20186267 | D22: ='AJE 2022'!G78 -> 0 | E22: =C22+D22 -> 20186267 | I22: =SUMIF('TB LTD 12.22'!I:I,B22,'TB LTD 12.22'!F:F) -> 71364452 | J22: ='AJE 2022'!J78 -> 0 | K22: =I22+J22 -> 71364452 | L22: =K22/E22 -> 3.5352971 | M22: =K22/1000 -> 71364.452
B23: Fixed assets, net | C23: =SUMIF('TB LTD 12.22'!I:I,B23,'TB LTD 12.22'!G:G) -> 1659074.9 | E23: =C23+D23 -> 1659074.9 | I23: =SUMIF('TB LTD 12.22'!I:I,B23,'TB LTD 12.22'!F:F) -> 5596417.2 | K23: =I23+J23 -> 5596417.2 | L23: =K23/E23 -> 3.3732155 | M23: =K23/1000 -> 5596.4173
B24: Deferred tax assets | C24: =SUMIF('TB LTD 12.22'!I:I,B24,'TB LTD 12.22'!G:G) -> 2030229.3 | D24: ='AJE 2022'!G56 -> 0 | E24: =C24+D24 -> 2030229.3 | I24: =SUMIF('TB LTD 12.22'!I:I,B24,'TB LTD 12.22'!F:F) -> 7144377 | J24: ='AJE 2022'!J56 -> 0 | K24: =I24+J24 -> 7144377 | L24: =K24/E24 -> 3.519 | M24: =K24/1000 -> 7144.377 | N24: =K24/3.519 -> 2030229.3 | O24: =N24-E24 -> -0.0048536519
C25: =SUM(C18:C24) -> 26640297 | D25: =SUM(D18:D24) -> 12793.34 | E25: =SUM(E18:E24) -> 26653090 | I25: =SUM(I18:I24) -> 93757846 | J25: =SUM(J18:J24) -> 42857.689 | K25: =SUM(K18:K24) -> 93800704 | L25: =K25/E25 -> 3.5193182 | M25: =K25/1000 -> 93800.704
L26: =K26/E26 -> #DIV/0! | M26: =K26/1000 -> 0
B27: Total Assets | C27: =+C25+C16 -> 1.1082183e+08 | D27: =+D25+D16 -> 12793.34 | E27: =+E25+E16 -> 1.1083462e+08 | I27: =+I25+I16 -> 3.8999083e+08 | J27: =+J25+J16 -> 42857.689 | K27: =+K25+K16 -> 3.9003369e+08 | L27: =K27/E27 -> 3.5190599 | M27: =K27/1000 -> 390033.69
L28: =K28/E28 -> #DIV/0! | M28: =K28/1000 -> 0
L29: =K29/E29 -> #DIV/0! | M29: =K29/1000 -> 0
B30: CURRENT LIABILITIES | L30: =K30/E30 -> #DIV/0! | M30: =K30/1000 -> 0
L31: =K31/E31 -> #DIV/0! | M31: =K31/1000 -> 0
B32: Trade payables | C32: =SUMIF('TB LTD 12.22'!I:I,B32,'TB LTD 12.22'!G:G) -> -7799848.3 | E32: =C32+D32 -> -7799848.3 | I32: =SUMIF('TB LTD 12.22'!I:I,B32,'TB LTD 12.22'!F:F) -> -27447666 | J32: =-'AJE 2022'!K36 -> 0 | K32: =I32+J32 -> -27447666 | L32: =K32/E32 -> 3.519 | M32: =K32/1000 -> -27447.666
B33: Accrued Expenses | C33: =SUMIF('TB LTD 12.22'!I:I,B33,'TB LTD 12.22'!G:G) -> -14333945 | D33: =-'AJE 2022'!H89 -> 0 | E33: =C33+D33 -> -14333945 | I33: =SUMIF('TB LTD 12.22'!I:I,B33,'TB LTD 12.22'!F:F) -> -50441183 | J33: =-'AJE 2022'!K89 -> 0 | K33: =I33+J33 -> -50441183 | L33: =K33/E33 -> 3.5190021 | M33: =K33/1000 -> -50441.183 | N33: =M33+M36+M37+M40+M38 -> -135708.49
B34: Loan-Short Term | C34: =SUMIF('TB LTD 12.22'!I:I,B34,'TB LTD 12.22'!G:G) -> 0 | E34: =C34+D34 -> 0 | I34: =SUMIF('TB LTD 12.22'!I:I,B34,'TB LTD 12.22'!F:F) -> 0 | K34: =I34+J34 -> 0 | L34: =K34/E34 -> #DIV/0! | M34: =K34/1000 -> 0
B35: Contract liability | C35: =SUMIF('TB LTD 12.22'!I:I,B35,'TB LTD 12.22'!G:G) -> -8960313.1 | E35: =C35+D35 -> -8960313.1 | I35: =SUMIF('TB LTD 12.22'!I:I,B35,'TB LTD 12.22'!F:F) -> -31531317 | J35: =-'AJE 2022'!K42 -> 0 | K35: =I35+J35 -> -31531317 | L35: =K35/E35 -> 3.5189973 | M35: =K35/1000 -> -31531.317
B36: Tax provision | C36: =SUMIF('TB LTD 12.22'!I:I,B36,'TB LTD 12.22'!G:G) -> -4203504.2 | D36: =-('AJE 2022'!G109-'AJE 2022'!H105) -> 46711.547 | E36: =C36+D36 -> -4156792.7 | I36: =SUMIF('TB LTD 12.22'!I:I,B36,'TB LTD 12.22'!F:F) -> -14792131 | J36: =-('AJE 2022'!J109-'AJE 2022'!K105) -> 164377.93 | K36: =I36+J36 -> -14627753 | L36: =K36/E36 -> 3.519 | M36: =K36/1000 -> -14627.753 | N36: =K36/3.519 -> -4156792.7 | O36: =N36-E36 -> -0.002790567
B37: Sales tax Provision | C37: =SUMIF('TB LTD 12.22'!I:I,B37,'TB LTD 12.22'!G:G) -> -15835320 | D37: =-'AJE 2022'!G43 -> 0 | E37: =C37+D37 -> -15835320 | I37: =SUMIF('TB LTD 12.22'!I:I,B37,'TB LTD 12.22'!F:F) -> -55724490 | J37: =-'AJE 2022'!K44 -> 0 | K37: =I37+J37 -> -55724490 | L37: =K37/E37 -> 3.519 | M37: =K37/1000 -> -55724.49 | N37: =E37*3.519 -> -55724490 | O37: =N37-K37 -> -0.4662
B38: Employees payables | C38: =SUMIF('TB LTD 12.22'!I:I,B38,'TB LTD 12.22'!G:G) -> -4238437.8 | E38: =C38+D38 -> -4238437.8 | I38: =SUMIF('TB LTD 12.22'!I:I,B38,'TB LTD 12.22'!F:F) -> -14915063 | K38: =I38+J38 -> -14915063 | L38: =K38/E38 -> 3.519 | M38: =K38/1000 -> -14915.063
B39: ROA Liability ST | C39: =SUMIF('TB LTD 12.22'!I:I,B39,'TB LTD 12.22'!G:G) -> -18791168 | D39: =--17832251.4423087 -> 17832251 | E39: =C39+D39 -> -958916.79 | I39: =SUMIF('TB LTD 12.22'!I:I,B39,'TB LTD 12.22'!F:F) -> -66126121 | J39: =62751693 -> 62751693 | K39: =I39+J39 -> -3374428 | L39: =K39/E39 -> 3.5189998 | M39: =K39/1000 -> -3374.428
B40: Other accounts payable | C40: =SUMIF('TB LTD 12.22'!I:I,B40,'TB LTD 12.22'!G:G) -> 0 | E40: =C40+D40 -> 0 | I40: =SUMIF('TB LTD 12.22'!I:I,B40,'TB LTD 12.22'!F:F) -> 0 | K40: =I40+J40 -> 0 | L40: =K40/E40 -> #DIV/0! | M40: =K40/1000 -> 0
B41: Warrant liability | C41: =SUMIF('TB LTD 12.22'!I:I,B41,'TB LTD 12.22'!G:G) -> -1411357.4 | E41: =C41+D41 -> -1411357.4 | I41: =SUMIF('TB LTD 12.22'!I:I,B41,'TB LTD 12.22'!F:F) -> -4966566.8 | K41: =I41+J41 -> -4966566.8 | L41: =K41/E41 -> 3.519 | M41: =K41/1000 -> -4966.5668
C42: =SUM(C32:C41) -> -75573894 | D42: =SUM(D32:D41) -> 17878963 | E42: =SUM(E32:E41) -> -57694931 | I42: =SUM(I32:I41) -> -265944538 | J42: =SUM(J32:J41) -> 62916071 | K42: =SUM(K32:K41) -> -2.0302847e+08 | L42: =K42/E42 -> 3.5190001 | M42: =K42/1000 -> -203028.47
L43: =K43/E43 -> #DIV/0!
B44: Loan-Long Term | C44: =SUMIF('TB LTD 12.22'!I:I,B44,'TB LTD 12.22'!G:G) -> 0 | E44: =C44+D44 -> 0 | I44: =SUMIF('TB LTD 12.22'!I:I,B44,'TB LTD 12.22'!F:F) -> 0 | K44: =I44+J44 -> 0 | L44: =K44/E44 -> #DIV/0! | M44: =K44/1000 -> 0
B45: ROA Liability LT | C45: =SUMIF('TB LTD 12.22'!I:I,B45,'TB LTD 12.22'!G:G) -> 0 | D45: -17832251 | E45: =C45+D45 -> -17832251 | I45: =SUMIF('TB LTD 12.22'!I:I,B45,'TB LTD 12.22'!F:F) -> 0 | J45: -62751693 | K45: =I45+J45 -> -62751693 | L45: =K45/E45 -> 3.519 | M45: =K45/1000 -> -62751.693
B46: Shareholders | C46: =SUMIF('TB LTD 12.22'!I:I,B46,'TB LTD 12.22'!G:G) -> 0 | E46: =C46+D46 -> 0 | I46: =SUMIF('TB LTD 12.22'!I:I,B46,'TB LTD 12.22'!F:F) -> 0 | K46: =I46+J46 -> 0 | L46: =K46/E46 -> #DIV/0! | M46: =K46/1000 -> 0
B47: Convertible Loan | C47: =SUMIF('TB LTD 12.22'!I:I,B47,'TB LTD 12.22'!G:G) -> 0 | E47: =C47+D47 -> 0 | I47: =SUMIF('TB LTD 12.22'!I:I,B47,'TB LTD 12.22'!F:F) -> 0 | K47: =I47+J47 -> 0 | L47: =K47/E47 -> #DIV/0! | M47: =K47/1000 -> 0
C48: =SUM(C44:C47) -> 0 | D48: =SUM(D44:D47) -> -17832251 | E48: =SUM(E44:E47) -> -17832251 | I48: =SUM(I44:I47) -> 0 | J48: =SUM(J44:J47) -> -62751693 | K48: =SUM(K44:K47) -> -62751693 | L48: =K48/E48 -> 3.519 | M48: =K48/1000 -> -62751.693
L49: =K49/E49 -> #DIV/0! | M49: =K49/1000 -> 0
B50: Total libiliaties | C50: =+C48+C42 -> -75573894 | D50: =+D48+D42 -> 46711.547 | E50: =+E48+E42 -> -75527182 | I50: =+I48+I42 -> -265944538 | J50: =+J48+J42 -> 164378.11 | K50: =+K48+K42 -> -2.6578016e+08 | L50: =K50/E50 -> 3.5190001 | M50: =K50/1000 -> -265780.16
L51: =K51/E51 -> #DIV/0! | M51: =K51/1000 -> 0
B52: SHAREHOLDERS' EQUITY | L52: =K52/E52 -> #DIV/0! | M52: =K52/1000 -> 0
L53: =K53/E53 -> #DIV/0! | M53: =K53/1000 -> 0
B54: Share capital - Ordinary Shares | C54: =SUMIF('TB LTD 12.22'!I:I,B54,'TB LTD 12.22'!G:G) -> -690.22 | E54: =C54+D54 -> -690.22 | I54: =SUMIF('TB LTD 12.22'!I:I,B54,'TB LTD 12.22'!F:F) -> -2417.02 | K54: =I54+J54 -> -2417.02 | L54: =K54/E54 -> 3.501811 | M54: =K54/1000 -> -2.41702 | N54: =SUM(M54:M57) -> -29790.977
B55: Share capital - Preferred Seed-1 | C55: =SUMIF('TB LTD 12.22'!I:I,B55,'TB LTD 12.22'!G:G) -> -191 | E55: =C55+D55 -> -191 | I55: =SUMIF('TB LTD 12.22'!I:I,B55,'TB LTD 12.22'!F:F) -> -651 | K55: =I55+J55 -> -651 | L55: =K55/E55 -> 3.408377 | M55: =K55/1000 -> -0.651
B56: Share capital - Preferred Seed | C56: =SUMIF('TB LTD 12.22'!I:I,B56,'TB LTD 12.22'!G:G) -> -49.24 | E56: =C56+D56 -> -49.24 | I56: =SUMIF('TB LTD 12.22'!I:I,B56,'TB LTD 12.22'!F:F) -> -169.46 | K56: =I56+J56 -> -169.46 | L56: =K56/E56 -> 3.441511 | M56: =K56/1000 -> -0.16946
B57: Share premium | C57: =SUMIF('TB LTD 12.22'!I:I,B57,'TB LTD 12.22'!G:G) -> -8818490.6 | D57: ='AJE 2022'!G40 -> 0 | E57: =C57+D57 -> -8818490.6 | I57: =SUMIF('TB LTD 12.22'!I:I,B57,'TB LTD 12.22'!F:F) -> -29787740 | J57: ='AJE 2022'!J40 -> 0 | K57: =I57+J57 -> -29787740 | L57: =K57/E57 -> 3.3778729 | M57: =K57/1000 -> -29787.74
B58: Receivables for shares issued | C58: =SUMIF('TB LTD 12.22'!I:I,B58,'TB LTD 12.22'!G:G) -> 0 | E58: =C58+D58 -> 0 | I58: =SUMIF('TB LTD 12.22'!I:I,B58,'TB LTD 12.22'!F:F) -> 0 | K58: =I58+J58 -> 0 | L58: =K58/E58 -> #DIV/0! | M58: =K58/1000 -> 0
B59: Accumulated deficit | C59: =SUMIF('TB LTD 12.22'!I:I,B59,'TB LTD 12.22'!G:G) -> -4082936.6 | E59: =C59+D59 -> -4082936.6 | I59: =SUMIF('TB LTD 12.22'!I:I,B59,'TB LTD 12.22'!F:F) -> -10468188 | K59: =I59+J59 -> -10468188 | L59: =K59/E59 -> 2.5638869 | M59: =K59/1000 -> -10468.188 | N59: =SUM(M59:M60) -> -94462.548
B60: PL | C60: ='P&L LTD USD'!D122 -> -22345579 | D60: =-D10-D57-D37-D9-D36-D24-D14-D22-D39-D33-D12-D45-D20 -> -59504.887 | E60: =C60+D60 -> -22405084 | F60: =E60-'P&L LTD USD'!F122 -> 0 | I60: ='P&L LTD USD'!J122 -> -83787125 | J60: =-J10-J57-J37-J9-J36-J24-J14-J22-J39-J33-J20-J12-J45 -> -207235.8 | K60: =I60+J60 -> -83994361 | L60: =K60/E60 -> 3.7488973 | M60: =K60/1000 -> -83994.361
C61: =SUM(C54:C60) -> -35247937 | D61: =SUM(D54:D60) -> -59504.887 | E61: =SUM(E54:E60) -> -35307442 | I61: =SUM(I54:I60) -> -1.2404629e+08 | J61: =SUM(J54:J60) -> -207235.8 | K61: =I61+J61 -> -1.2425353e+08 | L61: =K61/E61 -> 3.519188 | M61: =K61/1000 -> -124253.53
L62: =K62/E62 -> #DIV/0! | M62: =K62/1000 -> 0
C63: =C61+C50 -> -1.1082183e+08 | D63: =D61+D50 -> -12793.34 | E63: =E61+E50 -> -1.1083462e+08 | I63: =I61+I50 -> -3.8999083e+08 | J63: =J61+J50 -> -42857.689 | K63: =K61+K50 -> -3.9003369e+08 | L63: =K63/E63 -> 3.5190599 | M63: =K63/1000 -> -390033.69
C64: =+C63=-C27 -> FALSE | D64: =+D63=-D27 -> TRUE | E64: =+E63=-E27 -> FALSE | I64: =+I63=-I27 -> TRUE | J64: =+J63=-J27 -> FALSE | K64: =+K63=-K27 -> TRUE | L64: =K64/E64 -> #DIV/0! | M64: =K64/1000 -> 0.001
C65: =+C63+C27 -> -0.0099999905 | D65: =+D63+D27 -> 0 | E65: =+E63+E27 -> -0.0099999905 | I65: =+I63+I27 -> 0 | J65: =+J63+J27 -> -1.7316779e-09 | K65: =+K63+K27 -> 0 | L65: =K65/E65 -> 0 | M65: =K65/1000 -> 0

Sheet P&L LTD  USD
D1: USD -LTD | J1: ILS -LTD
D3: 2022 | F3: 2022 | J3: 2022 | L3: 2022
E4: JE | F4: AJE | J4: LTD | K4: JE | L4: AJE
B5: Revenues | C5: Revenues | D5: =SUMIFS('TB LTD 12.22'!G:G,'TB LTD 12.22'!I:I,$B5,'TB LTD 12.22'!J:J,$C5) -> -3.3963699e+08 | E5: ='AJE 2022'!G12+'AJE 2022'!G27 -> 0 | F5: =D5+E5 -> -3.3963699e+08 | G5: =SUM('P&L INC'!F12:F17) -> -3.3940583e+08 | J5: =SUMIFS('TB LTD 12.22'!F:F,'TB LTD 12.22'!I:I,$B5,'TB LTD 12.22'!J:J,$C5) -> -1.1480931e+09 | K5: ='AJE 2022'!J12+'AJE 2022'!J27 -> 0 | L5: =J5+K5 -> -1.1480931e+09
B6: Revenues | C6: ads revenue | D6: =SUMIFS('TB LTD 12.22'!G:G,'TB LTD 12.22'!I:I,$B6,'TB LTD 12.22'!J:J,$C6) -> -2600569.2 | F6: =D6+E6 -> -2600569.2 | G6: =F5-G5 -> -231159.39 | J6: =SUMIFS('TB LTD 12.22'!F:F,'TB LTD 12.22'!I:I,$B6,'TB LTD 12.22'!J:J,$C6) -> -8791096.3 | L6: =J6+K6 -> -8791096.3
B7: Revenues | C7: Net Cash | D7: =SUMIFS('TB LTD 12.22'!G:G,'TB LTD 12.22'!I:I,$B7,'TB LTD 12.22'!J:J,$C7) -> 4931358.5 | F7: =D7+E7 -> 4931358.5 | G7: 249578 | J7: =SUMIFS('TB LTD 12.22'!F:F,'TB LTD 12.22'!I:I,$B7,'TB LTD 12.22'!J:J,$C7) -> 16699482 | L7: =J7+K7 -> 16699482
B8: Revenues | C8: withdrawals | D8: =SUMIFS('TB LTD 12.22'!G:G,'TB LTD 12.22'!I:I,$B8,'TB LTD 12.22'!J:J,$C8) -> 3066670 | F8: =D8+E8 -> 3066670 | J8: =SUMIFS('TB LTD 12.22'!F:F,'TB LTD 12.22'!I:I,$B8,'TB LTD 12.22'!J:J,$C8) -> 10391330 | L8: =J8+K8 -> 10391330
B9: Revenues | C9: Hekzev | D9: =SUMIFS('TB LTD 12.22'!G:G,'TB LTD 12.22'!I:I,$B9,'TB LTD 12.22'!J:J,$C9) -> 0.0099999999 | F9: =D9+E9 -> 0.0099999999 | J9: =SUMIFS('TB LTD 12.22'!F:F,'TB LTD 12.22'!I:I,$B9,'TB LTD 12.22'!J:J,$C9) -> 0 | L9: =J9+K9 -> 0
B10: Revenues | C10: Total Revenues | D10: =SUM(D5:D8) -> -3.3423953e+08 | E10: =SUM(E5:E8) -> 0 | F10: =SUM(F5:F8) -> -3.3423953e+08 | J10: =SUM(J5:J8) -> -1.1297934e+09 | K10: =SUM(K5:K8) -> 0 | L10: =SUM(L5:L8) -> -1.1297934e+09 | N10: =L10/1000 -> -1129793.4
C12: Operations | D12: =SUM(D13:D31) -> 23057127 | E12: =SUM(E13:E31) -> 0 | F12: =SUM(F13:F31) -> 23057127 | J12: =SUM(J13:J31) -> 77948520 | K12: =SUM(K13:K31) -> 0 | L12: =SUM(L13:L31) -> 77948520 | N12: =L12/1000 -> 77948.52
A13: Payroll | B13: Operations | C13: Salary | D13: =SUMIFS('TB LTD 12.22'!G:G,'TB LTD 12.22'!I:I,$B13,'TB LTD 12.22'!J:J,$C13) -> 844546.94 | F13: =D13+E13 -> 844546.94 | J13: =SUMIFS('TB LTD 12.22'!F:F,'TB LTD 12.22'!I:I,$B13,'TB LTD 12.22'!J:J,$C13) -> 2852594.4 | L13: =J13+K13 -> 2852594.4
A14: Overheads | B14: Operations | C14: Professional Services | D14: =SUMIFS('TB LTD 12.22'!G:G,'TB LTD 12.22'!I:I,$B14,'TB LTD 12.22'!J:J,$C14) -> 321517.7 | F14: =D14+E14 -> 321517.7 | J14: =SUMIFS('TB LTD 12.22'!F:F,'TB LTD 12.22'!I:I,$B14,'TB LTD 12.22'!J:J,$C14) -> 1079539.9 | L14: =J14+K14 -> 1079539.9
A15: Overheads | B15: Operations | C15: Softwere subscription | D15: =SUMIFS('TB LTD 12.22'!G:G,'TB LTD 12.22'!I:I,$B15,'TB LTD 12.22'!J:J,$C15) -> 70434.95 | F15: =D15+E15 -> 70434.95 | J15: =SUMIFS('TB LTD 12.22'!F:F,'TB LTD 12.22'!I:I,$B15,'TB LTD 12.22'!J:J,$C15) -> 238667.82 | L15: =J15+K15 -> 238667.82
A16: Options | B16: Operations | C16: option expenses | D16: =SUMIFS('TB LTD 12.22'!G:G,'TB LTD 12.22'!I:I,$B16,'TB LTD 12.22'!J:J,$C16) -> 21106.66 | E16: ='AJE 2022'!G38 -> 0 | F16: =D16+E16 -> 21106.66 | J16: =SUMIFS('TB LTD 12.22'!F:F,'TB LTD 12.22'!I:I,$B16,'TB LTD 12.22'!J:J,$C16) -> 70070.51 | K16: ='AJE 2022'!J38 -> 0 | L16: =J16+K16 -> 70070.51
A17: Overheads | B17: Operations | C17: Rent and related | D17: =SUMIFS('TB LTD 12.22'!G:G,'TB LTD 12.22'!I:I,$B17,'TB LTD 12.22'!J:J,$C17) -> 114342.52 | F17: =D17+E17 -> 114342.52 | J17: =SUMIFS('TB LTD 12.22'!F:F,'TB LTD 12.22'!I:I,$B17,'TB LTD 12.22'!J:J,$C17) -> 392459.69 | L17: =J17+K17 -> 392459.69
A18: Depreciation | B18: Operations | C18: Depreciation | D18: =SUMIFS('TB LTD 12.22'!G:G,'TB LTD 12.22'!I:I,$B18,'TB LTD 12.22'!J:J,$C18) -> 16803.74 | F18: =D18+E18 -> 16803.74 | J18: =SUMIFS('TB LTD 12.22'!F:F,'TB LTD 12.22'!I:I,$B18,'TB LTD 12.22'!J:J,$C18) -> 54762.66 | L18: =J18+K18 -> 54762.66
A19: Overheads | B19: Operations | C19: Welfare | D19: =SUMIFS('TB LTD 12.22'!G:G,'TB LTD 12.22'!I:I,$B19,'TB LTD 12.22'!J:J,$C19) -> 1757.32 | F19: =D19+E19 -> 1757.32 | J19: =SUMIFS('TB LTD 12.22'!F:F,'TB LTD 12.22'!I:I,$B19,'TB LTD 12.22'!J:J,$C19) -> 6136 | L19: =J19+K19 -> 6136
A20: Overheads | B20: Operations | C20: Refreshments & Meals | D20: =SUMIFS('TB LTD 12.22'!G:G,'TB LTD 12.22'!I:I,$B20,'TB LTD 12.22'!J:J,$C20) -> 48346.67 | F20: =D20+E20 -> 48346.67 | J20: =SUMIFS('TB LTD 12.22'!F:F,'TB LTD 12.22'!I:I,$B20,'TB LTD 12.22'!J:J,$C20) -> 162032.54 | L20: =J20+K20 -> 162032.54
A21: Overheads | B21: Operations | C21: Benefits | D21: =SUMIFS('TB LTD 12.22'!G:G,'TB LTD 12.22'!I:I,$B21,'TB LTD 12.22'!J:J,$C21) -> 9171.54 | F21: =D21+E21 -> 9171.54 | J21: =SUMIFS('TB LTD 12.22'!F:F,'TB LTD 12.22'!I:I,$B21,'TB LTD 12.22'!J:J,$C21) -> 30310.62 | L21: =J21+K21 -> 30310.62
A22: Overheads | B22: Operations | C22: Company events | D22: =SUMIFS('TB LTD 12.22'!G:G,'TB LTD 12.22'!I:I,$B22,'TB LTD 12.22'!J:J,$C22) -> 52156.54 | F22: =D22+E22 -> 52156.54 | J22: =SUMIFS('TB LTD 12.22'!F:F,'TB LTD 12.22'!I:I,$B22,'TB LTD 12.22'!J:J,$C22) -> 174725.83 | L22: =J22+K22 -> 174725.83
A23: Overheads | B23: Operations | C23: Conferences and seminars | D23: =SUMIFS('TB LTD 12.22'!G:G,'TB LTD 12.22'!I:I,$B23,'TB LTD 12.22'!J:J,$C23) -> 1872.76 | F23: =D23+E23 -> 1872.76 | J23: =SUMIFS('TB LTD 12.22'!F:F,'TB LTD 12.22'!I:I,$B23,'TB LTD 12.22'!J:J,$C23) -> 6808.42 | L23: =J23+K23 -> 6808.42
A24: Overheads | B24: Operations | C24: Office exp | D24: =SUMIFS('TB LTD 12.22'!G:G,'TB LTD 12.22'!I:I,$B24,'TB LTD 12.22'!J:J,$C24) -> 0 | F24: =D24+E24 -> 0 | J24: =SUMIFS('TB LTD 12.22'!F:F,'TB LTD 12.22'!I:I,$B24,'TB LTD 12.22'!J:J,$C24) -> 0 | L24: =J24+K24 -> 0
A25: Overheads | B25: Operations | C25: Design | D25: =SUMIFS('TB LTD 12.22'!G:G,'TB LTD 12.22'!I:I,$B25,'TB LTD 12.22'!J:J,$C25) -> 2471.58 | F25: =D25+E25 -> 2471.58 | J25: =SUMIFS('TB LTD 12.22'!F:F,'TB LTD 12.22'!I:I,$B25,'TB LTD 12.22'!J:J,$C25) -> 8556.43 | L25: =J25+K25 -> 8556.43
A26: Overheads | B26: Operations | C26: Donation | D26: =SUMIFS('TB LTD 12.22'!G:G,'TB LTD 12.22'!I:I,$B26,'TB LTD 12.22'!J:J,$C26) -> 0 | F26: =D26+E26 -> 0 | J26: =SUMIFS('TB LTD 12.22'!F:F,'TB LTD 12.22'!I:I,$B26,'TB LTD 12.22'!J:J,$C26) -> 0 | L26: =J26+K26 -> 0
A27: Overheads | B27: Operations | C27: hosting | D27: =SUMIFS('TB LTD 12.22'!G:G,'TB LTD 12.22'!I:I,$B27,'TB LTD 12.22'!J:J,$C27) -> 1787545.2 | E27: =-'AJE 2022'!H67 -> 0 | F27: =D27+E27 -> 1787545.2 | J27: =SUMIFS('TB LTD 12.22'!F:F,'TB LTD 12.22'!I:I,$B27,'TB LTD 12.22'!J:J,$C27) -> 6216999.6 | K27: =-'AJE 2022'!J66 -> 0 | L27: =J27+K27 -> 6216999.6
A28: Overheads | B28: Operations | C28: insurance | D28: =SUMIFS('TB LTD 12.22'!G:G,'TB LTD 12.22'!I:I,$B28,'TB LTD 12.22'!J:J,$C28) -> 3082.15 | F28: =D28+E28 -> 3082.15 | J28: =SUMIFS('TB LTD 12.22'!F:F,'TB LTD 12.22'!I:I,$B28,'TB LTD 12.22'!J:J,$C28) -> 9998.95 | L28: =J28+K28 -> 9998.95
A29: Overheads | B29: Operations | C29: Fees and fines | D29: =SUMIFS('TB LTD 12.22'!G:G,'TB LTD 12.22'!I:I,$B29,'TB LTD 12.22'!J:J,$C29) -> 99.05 | F29: =D29+E29 -> 99.05 | J29: =SUMIFS('TB LTD 12.22'!F:F,'TB LTD 12.22'!I:I,$B29,'TB LTD 12.22'!J:J,$C29) -> 338.71 | L29: =J29+K29 -> 338.71
A30: Overheads | B30: Operations | C30: recruitment | D30: =SUMIFS('TB LTD 12.22'!G:G,'TB LTD 12.22'!I:I,$B30,'TB LTD 12.22'!J:J,$C30) -> 0 | F30: =D30+E30 -> 0 | J30: =SUMIFS('TB LTD 12.22'!F:F,'TB LTD 12.22'!I:I,$B30,'TB LTD 12.22'!J:J,$C30) -> 0 | L30: =J30+K30 -> 0
B31: Operations | C31: IC expenses | D31: =SUMIFS('TB LTD 12.22'!G:G,'TB LTD 12.22'!I:I,$B31,'TB LTD 12.22'!J:J,$C31) -> 19761872 | E31: ='AJE 2022'!G17 -> 0 | F31: =D31+E31 -> 19761872 | J31: =SUMIFS('TB LTD 12.22'!F:F,'TB LTD 12.22'!I:I,$B31,'TB LTD 12.22'!J:J,$C31) -> 66644518 | K31: ='AJE 2022'!J17 -> 0 | L31: =J31+K31 -> 66644518
C32: Gross loss (profit) | D32: =D10+D12 -> -3.111824e+08 | E32: =E10+E12 -> 0 | F32: =F10+F12 -> -3.111824e+08 | J32: =J10+J12 -> -1.0518449e+09 | K32: =K10+K12 -> 0 | L32: =L10+L12 -> -1.0518449e+09 | N32: =L32/1000 -> -1051844.9
C35: Research and development expenses, net | D35: =SUM(D36:D54) -> 20781725 | E35: =SUM(E36:E54) -> 0 | F35: =SUM(F36:F54) -> 20781725 | J35: =SUM(J36:J54) -> 70597716 | K35: =SUM(K36:K54) -> 0 | L35: =SUM(L36:L54) -> 70597716 | N35: =L35/1000 -> 70597.716
A36: Payroll | B36: Research and development expenses, net | C36: Salary | D36: =SUMIFS('TB LTD 12.22'!G:G,'TB LTD 12.22'!I:I,$B36,'TB LTD 12.22'!J:J,$C36) -> 13350033 | E36: ='AJE 2022'!G97-'AJE 2022'!G101 -> 0 | F36: =D36+E36 -> 13350033 | J36: =SUMIFS('TB LTD 12.22'!F:F,'TB LTD 12.22'!I:I,$B36,'TB LTD 12.22'!J:J,$C36) -> 45424826 | K36: ='AJE 2022'!K98-'AJE 2022'!J101 -> 0 | L36: =J36+K36 -> 45424826
A37: Overheads | B37: Research and development expenses, net | C37: Professional Services | D37: =SUMIFS('TB LTD 12.22'!G:G,'TB LTD 12.22'!I:I,$B37,'TB LTD 12.22'!J:J,$C37) -> 1119298.7 | F37: =D37+E37 -> 1119298.7 | J37: =SUMIFS('TB LTD 12.22'!F:F,'TB LTD 12.22'!I:I,$B37,'TB LTD 12.22'!J:J,$C37) -> 3777596 | L37: =J37+K37 -> 3777596
A38: Overheads | B38: Research and development expenses, net | C38: Softwere subscription | D38: =SUMIFS('TB LTD 12.22'!G:G,'TB LTD 12.22'!I:I,$B38,'TB LTD 12.22'!J:J,$C38) -> 1670933.7 | F38: =D38+E38 -> 1670933.7 | J38: =SUMIFS('TB LTD 12.22'!F:F,'TB LTD 12.22'!I:I,$B38,'TB LTD 12.22'!J:J,$C38) -> 5623468.9 | L38: =J38+K38 -> 5623468.9
A39: Options | B39: Research and development expenses, net | C39: option expenses | D39: =SUMIFS('TB LTD 12.22'!G:G,'TB LTD 12.22'!I:I,$B39,'TB LTD 12.22'!J:J,$C39) -> -39848.17 | E39: =-'AJE 2022'!H37 -> 0 | F39: =D39+E39 -> -39848.17 | J39: =SUMIFS('TB LTD 12.22'!F:F,'TB LTD 12.22'!I:I,$B39,'TB LTD 12.22'!J:J,$C39) -> -161997.48 | K39: =-'AJE 2022'!K37 -> 0 | L39: =J39+K39 -> -161997.48
A40: Overheads | B40: Research and development expenses, net | C40: Rent and related | D40: =SUMIFS('TB LTD 12.22'!G:G,'TB LTD 12.22'!I:I,$B40,'TB LTD 12.22'!J:J,$C40) -> 989386.59 | F40: =D40+E40 -> 989386.59 | J40: =SUMIFS('TB LTD 12.22'!F:F,'TB LTD 12.22'!I:I,$B40,'TB LTD 12.22'!J:J,$C40) -> 3423464.7 | L40: =J40+K40 -> 3423464.7
A41: Depreciation | B41: Research and development expenses, net | C41: Depreciation | D41: =SUMIFS('TB LTD 12.22'!G:G,'TB LTD 12.22'!I:I,$B41,'TB LTD 12.22'!J:J,$C41) -> 136688.74 | F41: =D41+E41 -> 136688.74 | J41: =SUMIFS('TB LTD 12.22'!F:F,'TB LTD 12.22'!I:I,$B41,'TB LTD 12.22'!J:J,$C41) -> 445711.95 | L41: =J41+K41 -> 445711.95
A42: Overheads | B42: Research and development expenses, net | C42: Welfare | D42: =SUMIFS('TB LTD 12.22'!G:G,'TB LTD 12.22'!I:I,$B42,'TB LTD 12.22'!J:J,$C42) -> 18024.67 | F42: =D42+E42 -> 18024.67 | J42: =SUMIFS('TB LTD 12.22'!F:F,'TB LTD 12.22'!I:I,$B42,'TB LTD 12.22'!J:J,$C42) -> 61677.9 | L42: =J42+K42 -> 61677.9
A43: Overheads | B43: Research and development expenses, net | C43: Refreshments & Meals | D43: =SUMIFS('TB LTD 12.22'!G:G,'TB LTD 12.22'!I:I,$B43,'TB LTD 12.22'!J:J,$C43) -> 392581.94 | F43: =D43+E43 -> 392581.94 | J43: =SUMIFS('TB LTD 12.22'!F:F,'TB LTD 12.22'!I:I,$B43,'TB LTD 12.22'!J:J,$C43) -> 1326297 | L43: =J43+K43 -> 1326297
A44: Overheads | B44: Research and development expenses, net | C44: Benefits | D44: =SUMIFS('TB LTD 12.22'!G:G,'TB LTD 12.22'!I:I,$B44,'TB LTD 12.22'!J:J,$C44) -> 76196.55 | F44: =D44+E44 -> 76196.55 | J44: =SUMIFS('TB LTD 12.22'!F:F,'TB LTD 12.22'!I:I,$B44,'TB LTD 12.22'!J:J,$C44) -> 255373.49 | L44: =J44+K44 -> 255373.49
A45: Overheads | B45: Research and development expenses, net | C45: Company events | D45: =SUMIFS('TB LTD 12.22'!G:G,'TB LTD 12.22'!I:I,$B45,'TB LTD 12.22'!J:J,$C45) -> 424207.54 | F45: =D45+E45 -> 424207.54 | J45: =SUMIFS('TB LTD 12.22'!F:F,'TB LTD 12.22'!I:I,$B45,'TB LTD 12.22'!J:J,$C45) -> 1431443.6 | L45: =J45+K45 -> 1431443.6
A46: Overheads | B46: Research and development expenses, net | C46: Conferences and seminars | D46: =SUMIFS('TB LTD 12.22'!G:G,'TB LTD 12.22'!I:I,$B46,'TB LTD 12.22'!J:J,$C46) -> 21837.15 | F46: =D46+E46 -> 21837.15 | J46: =SUMIFS('TB LTD 12.22'!F:F,'TB LTD 12.22'!I:I,$B46,'TB LTD 12.22'!J:J,$C46) -> 77653.32 | L46: =J46+K46 -> 77653.32
A47: Overheads | B47: Research and development expenses, net | C47: Donation | D47: =SUMIFS('TB LTD 12.22'!G:G,'TB LTD 12.22'!I:I,$B47,'TB LTD 12.22'!J:J,$C47) -> 0 | F47: =D47+E47 -> 0 | J47: =SUMIFS('TB LTD 12.22'!F:F,'TB LTD 12.22'!I:I,$B47,'TB LTD 12.22'!J:J,$C47) -> 0 | L47: =J47+K47 -> 0
A48: Overheads | B48: Research and development expenses, net | C48: travel | D48: =SUMIFS('TB LTD 12.22'!G:G,'TB LTD 12.22'!I:I,$B48,'TB LTD 12.22'!J:J,$C48) -> 2740 | F48: =D48+E48 -> 2740 | J48: =SUMIFS('TB LTD 12.22'!F:F,'TB LTD 12.22'!I:I,$B48,'TB LTD 12.22'!J:J,$C48) -> 9189.96 | L48: =J48+K48 -> 9189.96
A49: Overheads | B49: Research and development expenses, net | C49: hosting | D49: =SUMIFS('TB LTD 12.22'!G:G,'TB LTD 12.22'!I:I,$B49,'TB LTD 12.22'!J:J,$C49) -> 2292651.6 | E49: ='AJE 2022'!H67 -> 0 | F49: =D49+E49 -> 2292651.6 | J49: =SUMIFS('TB LTD 12.22'!F:F,'TB LTD 12.22'!I:I,$B49,'TB LTD 12.22'!J:J,$C49) -> 7796537 | K49: ='AJE 2022'!J66 -> 0 | L49: =J49+K49 -> 7796537
A50: Overheads | B50: Research and development expenses, net | C50: Design | D50: =SUMIFS('TB LTD 12.22'!G:G,'TB LTD 12.22'!I:I,$B50,'TB LTD 12.22'!J:J,$C50) -> 28002.55 | F50: =D50+E50 -> 28002.55 | J50: =SUMIFS('TB LTD 12.22'!F:F,'TB LTD 12.22'!I:I,$B50,'TB LTD 12.22'!J:J,$C50) -> 96897.68 | L50: =J50+K50 -> 96897.68
A51: Overheads | B51: Research and development expenses, net | C51: Office exp | D51: =SUMIFS('TB LTD 12.22'!G:G,'TB LTD 12.22'!I:I,$B51,'TB LTD 12.22'!J:J,$C51) -> 0 | F51: =D51+E51 -> 0 | J51: =SUMIFS('TB LTD 12.22'!F:F,'TB LTD 12.22'!I:I,$B51,'TB LTD 12.22'!J:J,$C51) -> 0 | L51: =J51+K51 -> 0
A52: Overheads | B52: Research and development expenses, net | C52: insurance | D52: =SUMIFS('TB LTD 12.22'!G:G,'TB LTD 12.22'!I:I,$B52,'TB LTD 12.22'!J:J,$C52) -> 25708.76 | F52: =D52+E52 -> 25708.76 | J52: =SUMIFS('TB LTD 12.22'!F:F,'TB LTD 12.22'!I:I,$B52,'TB LTD 12.22'!J:J,$C52) -> 83647.78 | L52: =J52+K52 -> 83647.78
A53: Overheads | B53: Research and development expenses, net | C53: Fees and fines | D53: =SUMIFS('TB LTD 12.22'!G:G,'TB LTD 12.22'!I:I,$B53,'TB LTD 12.22'!J:J,$C53) -> 973.72 | F53: =D53+E53 -> 973.72 | J53: =SUMIFS('TB LTD 12.22'!F:F,'TB LTD 12.22'!I:I,$B53,'TB LTD 12.22'!J:J,$C53) -> 3337.97 | L53: =J53+K53 -> 3337.97
A54: Overheads | B54: Research and development expenses, net | C54: recruitment | D54: =SUMIFS('TB LTD 12.22'!G:G,'TB LTD 12.22'!I:I,$B54,'TB LTD 12.22'!J:J,$C54) -> 272308.26 | F54: =D54+E54 -> 272308.26 | J54: =SUMIFS('TB LTD 12.22'!F:F,'TB LTD 12.22'!I:I,$B54,'TB LTD 12.22'!J:J,$C54) -> 922590.9 | L54: =J54+K54 -> 922590.9
C56: Marketing expenses | D56: =SUM(D57:D80) -> 2.5601775e+08 | E56: =SUM(E57:E80) -> 0 | F56: =SUM(F57:F80) -> 2.5601775e+08 | J56: =SUM(J57:J80) -> 8.6313586e+08 | K56: =SUM(K57:K80) -> 0 | L56: =SUM(L57:L80) -> 8.6313586e+08 | N56: =L56/1000 -> 863135.86
A57: Payroll | B57: Marketing expenses | C57: Salary | D57: =SUMIFS('TB LTD 12.22'!G:G,'TB LTD 12.22'!I:I,$B57,'TB LTD 12.22'!J:J,$C57) -> 2173718.7 | E57: ='AJE 2022'!G101 -> 0 | F57: =D57+E57 -> 2173718.7 | J57: =SUMIFS('TB LTD 12.22'!F:F,'TB LTD 12.22'!I:I,$B57,'TB LTD 12.22'!J:J,$C57) -> 7365858 | K57: ='AJE 2022'!J101 -> 0 | L57: =J57+K57 -> 7365858
A58: Overheads | B58: Marketing expenses | C58: Professional Services | D58: =SUMIFS('TB LTD 12.22'!G:G,'TB LTD 12.22'!I:I,$B58,'TB LTD 12.22'!J:J,$C58) -> 115313.87 | F58: =D58+E58 -> 115313.87 | J58: =SUMIFS('TB LTD 12.22'!F:F,'TB LTD 12.22'!I:I,$B58,'TB LTD 12.22'!J:J,$C58) -> 370618.51 | L58: =J58+K58 -> 370618.51
A59: Ua | B59: Marketing expenses | C59: User Acquisition | D59: =SUMIFS('TB LTD 12.22'!G:G,'TB LTD 12.22'!I:I,$B59,'TB LTD 12.22'!J:J,$C59) -> 2.2524941e+08 | F59: =D59+E59 -> 2.2524941e+08 | J59: =SUMIFS('TB LTD 12.22'!F:F,'TB LTD 12.22'!I:I,$B59,'TB LTD 12.22'!J:J,$C59) -> 7.5966812e+08 | L59: =J59+K59 -> 7.5966812e+08
A60: Ua Indirect | B60: Marketing expenses | C60: PR | D60: =SUMIFS('TB LTD 12.22'!G:G,'TB LTD 12.22'!I:I,$B60,'TB LTD 12.22'!J:J,$C60) -> 1690366.1 | F60: =D60+E60 -> 1690366.1 | J60: =SUMIFS('TB LTD 12.22'!F:F,'TB LTD 12.22'!I:I,$B60,'TB LTD 12.22'!J:J,$C60) -> 5731716.5 | L60: =J60+K60 -> 5731716.5
A61: Ua Indirect | B61: Marketing expenses | C61: Copywriting expenses | D61: =SUMIFS('TB LTD 12.22'!G:G,'TB LTD 12.22'!I:I,$B61,'TB LTD 12.22'!J:J,$C61) -> 0 | F61: =D61+E61 -> 0 | J61: =SUMIFS('TB LTD 12.22'!F:F,'TB LTD 12.22'!I:I,$B61,'TB LTD 12.22'!J:J,$C61) -> 0 | L61: =J61+K61 -> 0
A62: Ua Indirect | B62: Marketing expenses | C62: Softwere subscription | D62: =SUMIFS('TB LTD 12.22'!G:G,'TB LTD 12.22'!I:I,$B62,'TB LTD 12.22'!J:J,$C62) -> 1244785.9 | F62: =D62+E62 -> 1244785.9 | J62: =SUMIFS('TB LTD 12.22'!F:F,'TB LTD 12.22'!I:I,$B62,'TB LTD 12.22'!J:J,$C62) -> 4178354.5 | L62: =J62+K62 -> 4178354.5
A63: Options | B63: Marketing expenses | C63: option expenses | D63: =SUMIFS('TB LTD 12.22'!G:G,'TB LTD 12.22'!I:I,$B63,'TB LTD 12.22'!J:J,$C63) -> 45317.04 | E63: =-'AJE 2022'!H39 -> 0 | F63: =D63+E63 -> 45317.04 | J63: =SUMIFS('TB LTD 12.22'!F:F,'TB LTD 12.22'!I:I,$B63,'TB LTD 12.22'!J:J,$C63) -> 145013.25 | K63: =-'AJE 2022'!K39 -> 0 | L63: =J63+K63 -> 145013.25
A64: Overheads | B64: Marketing expenses | C64: Rent and related | D64: =SUMIFS('TB LTD 12.22'!G:G,'TB LTD 12.22'!I:I,$B64,'TB LTD 12.22'!J:J,$C64) -> 236043.48 | F64: =D64+E64 -> 236043.48 | J64: =SUMIFS('TB LTD 12.22'!F:F,'TB LTD 12.22'!I:I,$B64,'TB LTD 12.22'!J:J,$C64) -> 815217.65 | L64: =J64+K64 -> 815217.65
A65: Depreciation | B65: Marketing expenses | C65: Depreciation | D65: =SUMIFS('TB LTD 12.22'!G:G,'TB LTD 12.22'!I:I,$B65,'TB LTD 12.22'!J:J,$C65) -> 33124.83 | F65: =D65+E65 -> 33124.83 | J65: =SUMIFS('TB LTD 12.22'!F:F,'TB LTD 12.22'!I:I,$B65,'TB LTD 12.22'!J:J,$C65) -> 107986.72 | L65: =J65+K65 -> 107986.72
A66: Overheads | B66: Marketing expenses | C66: Welfare | D66: =SUMIFS('TB LTD 12.22'!G:G,'TB LTD 12.22'!I:I,$B66,'TB LTD 12.22'!J:J,$C66) -> 1262.26 | F66: =D66+E66 -> 1262.26 | J66: =SUMIFS('TB LTD 12.22'!F:F,'TB LTD 12.22'!I:I,$B66,'TB LTD 12.22'!J:J,$C66) -> 4182.8 | L66: =J66+K66 -> 4182.8
A67: Overheads | B67: Marketing expenses | C67: Refreshments & Meals | D67: =SUMIFS('TB LTD 12.22'!G:G,'TB LTD 12.22'!I:I,$B67,'TB LTD 12.22'!J:J,$C67) -> 94035.67 | F67: =D67+E67 -> 94035.67 | J67: =SUMIFS('TB LTD 12.22'!F:F,'TB LTD 12.22'!I:I,$B67,'TB LTD 12.22'!J:J,$C67) -> 317248.46 | L67: =J67+K67 -> 317248.46
A68: Overheads | B68: Marketing expenses | C68: Office exp | D68: =SUMIFS('TB LTD 12.22'!G:G,'TB LTD 12.22'!I:I,$B68,'TB LTD 12.22'!J:J,$C68) -> 0 | F68: =D68+E68 -> 0 | J68: =SUMIFS('TB LTD 12.22'!F:F,'TB LTD 12.22'!I:I,$B68,'TB LTD 12.22'!J:J,$C68) -> 0 | L68: =J68+K68 -> 0
A69: Overheads | B69: Marketing expenses | C69: Benefits | D69: =SUMIFS('TB LTD 12.22'!G:G,'TB LTD 12.22'!I:I,$B69,'TB LTD 12.22'!J:J,$C69) -> 17764 | F69: =D69+E69 -> 17764 | J69: =SUMIFS('TB LTD 12.22'!F:F,'TB LTD 12.22'!I:I,$B69,'TB LTD 12.22'!J:J,$C69) -> 59157.19 | L69: =J69+K69 -> 59157.19
A70: Overheads | B70: Marketing expenses | C70: Company events | D70: =SUMIFS('TB LTD 12.22'!G:G,'TB LTD 12.22'!I:I,$B70,'TB LTD 12.22'!J:J,$C70) -> 106943.14 | F70: =D70+E70 -> 106943.14 | J70: =SUMIFS('TB LTD 12.22'!F:F,'TB LTD 12.22'!I:I,$B70,'TB LTD 12.22'!J:J,$C70) -> 360812.2 | L70: =J70+K70 -> 360812.2
A71: Overheads | B71: Marketing expenses | C71: Conferences and seminars | D71: =SUMIFS('TB LTD 12.22'!G:G,'TB LTD 12.22'!I:I,$B71,'TB LTD 12.22'!J:J,$C71) -> 3325.12 | F71: =D71+E71 -> 3325.12 | J71: =SUMIFS('TB LTD 12.22'!F:F,'TB LTD 12.22'!I:I,$B71,'TB LTD 12.22'!J:J,$C71) -> 12110.43 | L71: =J71+K71 -> 12110.43
A72: Overheads | B72: Marketing expenses | C72: Donation | D72: =SUMIFS('TB LTD 12.22'!G:G,'TB LTD 12.22'!I:I,$B72,'TB LTD 12.22'!J:J,$C72) -> 0 | F72: =D72+E72 -> 0 | J72: =SUMIFS('TB LTD 12.22'!F:F,'TB LTD 12.22'!I:I,$B72,'TB LTD 12.22'!J:J,$C72) -> 0 | L72: =J72+K72 -> 0
A73: Overheads | B73: Marketing expenses | C73: Design | D73: =SUMIFS('TB LTD 12.22'!G:G,'TB LTD 12.22'!I:I,$B73,'TB LTD 12.22'!J:J,$C73) -> 6569.35 | F73: =D73+E73 -> 6569.35 | J73: =SUMIFS('TB LTD 12.22'!F:F,'TB LTD 12.22'!I:I,$B73,'TB LTD 12.22'!J:J,$C73) -> 22728.95 | L73: =J73+K73 -> 22728.95
A74: Overheads | B74: Marketing expenses | C74: travel | D74: =SUMIFS('TB LTD 12.22'!G:G,'TB LTD 12.22'!I:I,$B74,'TB LTD 12.22'!J:J,$C74) -> 1970.55 | F74: =D74+E74 -> 1970.55 | J74: =SUMIFS('TB LTD 12.22'!F:F,'TB LTD 12.22'!I:I,$B74,'TB LTD 12.22'!J:J,$C74) -> 6763.54 | L74: =J74+K74 -> 6763.54
A75: Overheads | B75: Marketing expenses | C75: hosting | D75: =SUMIFS('TB LTD 12.22'!G:G,'TB LTD 12.22'!I:I,$B75,'TB LTD 12.22'!J:J,$C75) -> 0 | F75: =D75+E75 -> 0 | J75: =SUMIFS('TB LTD 12.22'!F:F,'TB LTD 12.22'!I:I,$B75,'TB LTD 12.22'!J:J,$C75) -> 0 | L75: =J75+K75 -> 0
... A79: Overheads | B79: Marketing expenses | C79: Gift to Users | D79: =SUMIFS('TB LTD 12.22'!G:G,'TB LTD 12.22'!I:I,$B79,'TB LTD 12.22'!J:J,$C79) -> 21808.15 | F79: =D79+E79 -> 21808.15 | J79: =SUMIFS('TB LTD 12.22'!F:F,'TB LTD 12.22'!I:I,$B79,'TB LTD 12.22'!J:J,$C79) -> 75149.43 | L79: =J79+K79 -> 75149.43
B80: Marketing expenses | C80: IC expenses | D80: =SUMIFS('TB LTD 12.22'!G:G,'TB LTD 12.22'!I:I,$B80,'TB LTD 12.22'!J:J,$C80) -> 24957328 | F80: =D80+E80 -> 24957328 | J80: =SUMIFS('TB LTD 12.22'!F:F,'TB LTD 12.22'!I:I,$B80,'TB LTD 12.22'!J:J,$C80) -> 83833545 | L80: =J80+K80 -> 83833545
C82: General and administrative expenses | D82: =SUM(D83:D107) -> 8244728.4 | E82: =SUM(E83:E107) -> 0 | F82: =SUM(F83:F107) -> 8244728.4 | J82: =SUM(J83:J107) -> 28231935 | K82: =SUM(K83:K107) -> 0 | L82: =SUM(L83:L107) -> 28231935 | N82: =L82/1000 -> 28231.935
A83: Payroll | B83: General and administrative expenses | C83: Salary | D83: =SUMIFS('TB LTD 12.22'!G:G,'TB LTD 12.22'!I:I,$B83,'TB LTD 12.22'!J:J,$C83) -> 3113324.5 | E83: =-'AJE 2022'!G97 -> 0 | F83: =D83+E83 -> 3113324.5 | J83: =SUMIFS('TB LTD 12.22'!F:F,'TB LTD 12.22'!I:I,$B83,'TB LTD 12.22'!J:J,$C83) -> 10615546 | K83: =-'AJE 2022'!J97 -> 0 | L83: =J83+K83 -> 10615546
A84: Overheads | B84: General and administrative expenses | C84: Professional Services | D84: =SUMIFS('TB LTD 12.22'!G:G,'TB LTD 12.22'!I:I,$B84,'TB LTD 12.22'!J:J,$C84) -> 1393307.4 | F84: =D84+E84 -> 1393307.4 | J84: =SUMIFS('TB LTD 12.22'!F:F,'TB LTD 12.22'!I:I,$B84,'TB LTD 12.22'!J:J,$C84) -> 4792776.7 | L84: =J84+K84 -> 4792776.7
A85: Overheads | B85: General and administrative expenses | C85: Softwere subscription | D85: =SUMIFS('TB LTD 12.22'!G:G,'TB LTD 12.22'!I:I,$B85,'TB LTD 12.22'!J:J,$C85) -> 50814.44 | F85: =D85+E85 -> 50814.44 | J85: =SUMIFS('TB LTD 12.22'!F:F,'TB LTD 12.22'!I:I,$B85,'TB LTD 12.22'!J:J,$C85) -> 174686.63 | L85: =J85+K85 -> 174686.63
A86: Options | B86: General and administrative expenses | C86: option expenses | D86: =SUMIFS('TB LTD 12.22'!G:G,'TB LTD 12.22'!I:I,$B86,'TB LTD 12.22'!J:J,$C86) -> 158535.01 | E86: ='AJE 2022'!G36 -> 0 | F86: =D86+E86 -> 158535.01 | J86: =SUMIFS('TB LTD 12.22'!F:F,'TB LTD 12.22'!I:I,$B86,'TB LTD 12.22'!J:J,$C86) -> 528868.75 | K86: ='AJE 2022'!J36 -> 0 | L86: =J86+K86 -> 528868.75
A87: Overheads | B87: General and administrative expenses | C87: Rent and related | D87: =SUMIFS('TB LTD 12.22'!G:G,'TB LTD 12.22'!I:I,$B87,'TB LTD 12.22'!J:J,$C87) -> 174471.07 | E87: =-'AJE 2022'!H80 -> 0 | F87: =D87+E87 -> 174471.07 | J87: =SUMIFS('TB LTD 12.22'!F:F,'TB LTD 12.22'!I:I,$B87,'TB LTD 12.22'!J:J,$C87) -> 675328.11 | K87: =-'AJE 2022'!K80 -> 0 | L87: =J87+K87 -> 675328.11
A88: Depreciation | B88: General and administrative expenses | C88: Depreciation | D88: =SUMIFS('TB LTD 12.22'!G:G,'TB LTD 12.22'!I:I,$B88,'TB LTD 12.22'!J:J,$C88) -> 30171.52 | F88: =D88+E88 -> 30171.52 | J88: =SUMIFS('TB LTD 12.22'!F:F,'TB LTD 12.22'!I:I,$B88,'TB LTD 12.22'!J:J,$C88) -> 98394.26 | L88: =J88+K88 -> 98394.26
A89: Overheads | B89: General and administrative expenses | C89: Welfare | D89: =SUMIFS('TB LTD 12.22'!G:G,'TB LTD 12.22'!I:I,$B89,'TB LTD 12.22'!J:J,$C89) -> 20969.42 | F89: =D89+E89 -> 20969.42 | J89: =SUMIFS('TB LTD 12.22'!F:F,'TB LTD 12.22'!I:I,$B89,'TB LTD 12.22'!J:J,$C89) -> 71129.97 | L89: =J89+K89 -> 71129.97
A90: Overheads | B90: General and administrative expenses | C90: Refreshments & Meals | D90: =SUMIFS('TB LTD 12.22'!G:G,'TB LTD 12.22'!I:I,$B90,'TB LTD 12.22'!J:J,$C90) -> 99716.29 | F90: =D90+E90 -> 99716.29 | J90: =SUMIFS('TB LTD 12.22'!F:F,'TB LTD 12.22'!I:I,$B90,'TB LTD 12.22'!J:J,$C90) -> 337073.24 | L90: =J90+K90 -> 337073.24
A91: Overheads | B91: General and administrative expenses | C91: Benefits | D91: =SUMIFS('TB LTD 12.22'!G:G,'TB LTD 12.22'!I:I,$B91,'TB LTD 12.22'!J:J,$C91) -> 21579.97 | F91: =D91+E91 -> 21579.97 | J91: =SUMIFS('TB LTD 12.22'!F:F,'TB LTD 12.22'!I:I,$B91,'TB LTD 12.22'!J:J,$C91) -> 73077.03 | L91: =J91+K91 -> 73077.03
A92: Overheads | B92: General and administrative expenses | C92: Company events | D92: =SUMIFS('TB LTD 12.22'!G:G,'TB LTD 12.22'!I:I,$B92,'TB LTD 12.22'!J:J,$C92) -> 100410.54 | F92: =D92+E92 -> 100410.54 | J92: =SUMIFS('TB LTD 12.22'!F:F,'TB LTD 12.22'!I:I,$B92,'TB LTD 12.22'!J:J,$C92) -> 338802.02 | L92: =J92+K92 -> 338802.02
A93: Overheads | B93: General and administrative expenses | C93: Conferences and seminars | D93: =SUMIFS('TB LTD 12.22'!G:G,'TB LTD 12.22'!I:I,$B93,'TB LTD 12.22'!J:J,$C93) -> 5488.36 | F93: =D93+E93 -> 5488.36 | J93: =SUMIFS('TB LTD 12.22'!F:F,'TB LTD 12.22'!I:I,$B93,'TB LTD 12.22'!J:J,$C93) -> 18652.97 | L93: =J93+K93 -> 18652.97
A94: Overheads | B94: General and administrative expenses | C94: Donation | D94: =SUMIFS('TB LTD 12.22'!G:G,'TB LTD 12.22'!I:I,$B94,'TB LTD 12.22'!J:J,$C94) -> 359315.87 | F94: =D94+E94 -> 359315.87 | J94: =SUMIFS('TB LTD 12.22'!F:F,'TB LTD 12.22'!I:I,$B94,'TB LTD 12.22'!J:J,$C94) -> 1208109.6 | L94: =J94+K94 -> 1208109.6
A95: Overheads | B95: General and administrative expenses | C95: hosting | D95: =SUMIFS('TB LTD 12.22'!G:G,'TB LTD 12.22'!I:I,$B95,'TB LTD 12.22'!J:J,$C95) -> 0 | F95: =D95+E95 -> 0 | J95: =SUMIFS('TB LTD 12.22'!F:F,'TB LTD 12.22'!I:I,$B95,'TB LTD 12.22'!J:J,$C95) -> 0 | L95: =J95+K95 -> 0
A96: Overheads | B96: General and administrative expenses | C96: Office exp | D96: =SUMIFS('TB LTD 12.22'!G:G,'TB LTD 12.22'!I:I,$B96,'TB LTD 12.22'!J:J,$C96) -> 65698.04 | F96: =D96+E96 -> 65698.04 | J96: =SUMIFS('TB LTD 12.22'!F:F,'TB LTD 12.22'!I:I,$B96,'TB LTD 12.22'!J:J,$C96) -> 224892.89 | L96: =J96+K96 -> 224892.89
A97: Overheads | B97: General and administrative expenses | C97: insurance | D97: =SUMIFS('TB LTD 12.22'!G:G,'TB LTD 12.22'!I:I,$B97,'TB LTD 12.22'!J:J,$C97) -> 167873.21 | F97: =D97+E97 -> 167873.21 | J97: =SUMIFS('TB LTD 12.22'!F:F,'TB LTD 12.22'!I:I,$B97,'TB LTD 12.22'!J:J,$C97) -> 537325.07 | L97: =J97+K97 -> 537325.07
A98: Overheads | B98: General and administrative expenses | C98: recruitment | D98: =SUMIFS('TB LTD 12.22'!G:G,'TB LTD 12.22'!I:I,$B98,'TB LTD 12.22'!J:J,$C98) -> 2198.83 | F98: =D98+E98 -> 2198.83 | J98: =SUMIFS('TB LTD 12.22'!F:F,'TB LTD 12.22'!I:I,$B98,'TB LTD 12.22'!J:J,$C98) -> 7488.5 | L98: =J98+K98 -> 7488.5
A99: Overheads | B99: General and administrative expenses | C99: Design | D99: =SUMIFS('TB LTD 12.22'!G:G,'TB LTD 12.22'!I:I,$B99,'TB LTD 12.22'!J:J,$C99) -> 6569.36 | F99: =D99+E99 -> 6569.36 | J99: =SUMIFS('TB LTD 12.22'!F:F,'TB LTD 12.22'!I:I,$B99,'TB LTD 12.22'!J:J,$C99) -> 22728.95 | L99: =J99+K99 -> 22728.95
... A101: Overheads | B101: General and administrative expenses | C101: Gift to Users | D101: =SUMIFS('TB LTD 12.22'!G:G,'TB LTD 12.22'!I:I,$B101,'TB LTD 12.22'!J:J,$C101) -> 0 | F101: =D101+E101 -> 0 | J101: =SUMIFS('TB LTD 12.22'!F:F,'TB LTD 12.22'!I:I,$B101,'TB LTD 12.22'!J:J,$C101) -> 0 | L101: =J101+K101 -> 0
A102: Overheads | B102: General and administrative expenses | C102: Legal Law Suit | D102: =SUMIFS('TB LTD 12.22'!G:G,'TB LTD 12.22'!I:I,$B102,'TB LTD 12.22'!J:J,$C102) -> 0 | E102: ='AJE 2022'!G88 -> 0 | F102: =D102+E102 -> 0 | J102: =SUMIFS('TB LTD 12.22'!F:F,'TB LTD 12.22'!I:I,$B102,'TB LTD 12.22'!J:J,$C102) -> 0 | K102: ='AJE 2022'!J88 -> 0 | L102: =J102+K102 -> 0
A103: Overheads | B103: General and administrative expenses | C103: Legal | D103: =SUMIFS('TB LTD 12.22'!G:G,'TB LTD 12.22'!I:I,$B103,'TB LTD 12.22'!J:J,$C103) -> 1267685.2 | F103: =D103+E103 -> 1267685.2 | J103: =SUMIFS('TB LTD 12.22'!F:F,'TB LTD 12.22'!I:I,$B103,'TB LTD 12.22'!J:J,$C103) -> 4297812.8 | L103: =J103+K103 -> 4297812.8
A104: Overheads | B104: General and administrative expenses | C104: Fees and fines | D104: =SUMIFS('TB LTD 12.22'!G:G,'TB LTD 12.22'!I:I,$B104,'TB LTD 12.22'!J:J,$C104) -> 1000932.4 | F104: =D104+E104 -> 1000932.4 | J104: =SUMIFS('TB LTD 12.22'!F:F,'TB LTD 12.22'!I:I,$B104,'TB LTD 12.22'!J:J,$C104) -> 3522236.3 | L104: =J104+K104 -> 3522236.3
A105: Overheads | B105: General and administrative expenses | C105: Cash Back | D105: =SUMIFS('TB LTD 12.22'!G:G,'TB LTD 12.22'!I:I,$B105,'TB LTD 12.22'!J:J,$C105) -> -14370.75 | F105: =D105+E105 -> -14370.75 | J105: =SUMIFS('TB LTD 12.22'!F:F,'TB LTD 12.22'!I:I,$B105,'TB LTD 12.22'!J:J,$C105) -> -50172.89 | L105: =J105+K105 -> -50172.89
A106: Overheads | B106: General and administrative expenses | C106: Allocation | D106: =SUMIFS('TB LTD 12.22'!G:G,'TB LTD 12.22'!I:I,$B106,'TB LTD 12.22'!J:J,$C106) -> 1862.65 | F106: =D106+E106 -> 1862.65 | J106: =SUMIFS('TB LTD 12.22'!F:F,'TB LTD 12.22'!I:I,$B106,'TB LTD 12.22'!J:J,$C106) -> -2.87 | L106: =J106+K106 -> -2.87
B107: General and administrative expenses | C107: IC expenses | D107: =SUMIFS('TB LTD 12.22'!G:G,'TB LTD 12.22'!I:I,$B107,'TB LTD 12.22'!J:J,$C107) -> 195554.4 | E107: ='AJE 2022'!G22 -> 0 | F107: =D107+E107 -> 195554.4 | J107: =SUMIFS('TB LTD 12.22'!F:F,'TB LTD 12.22'!I:I,$B107,'TB LTD 12.22'!J:J,$C107) -> 659533.23 | K107: ='AJE 2022'!J22 -> 0 | L107: =J107+K107 -> 659533.23
C108: Operating expenses | D108: =D82+D56+D35 -> 2.850442e+08 | E108: =E82+E56+E35 -> 0 | F108: =F82+F56+F35 -> 2.850442e+08 | J108: =J82+J56+J35 -> 9.6196551e+08 | K108: =K82+K56+K35 -> 0 | L108: =L82+L56+L35 -> 9.6196551e+08 | N108: =L108/1000 -> 961965.51
C110: Operating loss (pprofit) | D110: =D108+D32 -> -26138202 | E110: =E108+E32 -> 0 | F110: =F108+F32 -> -26138202 | J110: =J108+J32 -> -89879369 | K110: =K108+K32 -> 0 | L110: =L108+L32 -> -89879369 | N110: =L110/1000 -> -89879.369
C112: Financial expenses, net | D112: =SUM(D113:D119) -> 242412.35 | E112: =SUM(E113:E119) -> 0 | F112: =SUM(F113:F119) -> 242412.35 | J112: =SUM(J113:J119) -> -6117819.7 | K112: =SUM(K113:K118) -> 0 | L112: =SUM(L113:L119) -> -6117819.7 | N112: =L112/1000 -> -6117.8197
...

Sheet TB LTD 12.22
A1: כותרת ראשית; | B1: כותרת משנה; | C1: סעיף; | D1: חשבון | E1: תאור החשבון | F1: יתרה בשקלים | G1: יתרה בדולרים | H1: סוג דוח | I1: מחלקה | J1: תת מחלקה
A2: Assets.1** | B2: Cash and Cash equivalent.10* | C2: Banks.100 | D2: 10000 | E2: Bank Leumi IL 568400 | F2: 4069321.5 | G2: 1156385.8 | H2: =VLOOKUP(D2,'COA LTD'!A:F,3,0) -> BS | I2: =VLOOKUP(D2,'COA LTD'!A:F,4,0) -> cash | J2: =VLOOKUP(D2,'COA LTD'!A:F,5,0) -> 0 | K2: =F2/G2 -> 3.519 | M2: 1
A3: Assets.1** | B3: Cash and Cash equivalent.10* | C3: Banks.100 | D3: 10001 | E3: Bank Leumi $ 568400 | F3: 5712873.2 | G3: 1623436.6 | H3: =VLOOKUP(D3,'COA LTD'!A:F,3,0) -> BS | I3: =VLOOKUP(D3,'COA LTD'!A:F,4,0) -> cash | J3: =VLOOKUP(D3,'COA LTD'!A:F,5,0) -> 0 | K3: =F3/G3 -> 3.519
A4: Assets.1** | B4: Cash and Cash equivalent.10* | C4: Banks.100 | D4: 10002 | E4: Bank Leumi GBP 568400 | F4: 3949.53 | G4: 1122.34 | H4: =VLOOKUP(D4,'COA LTD'!A:F,3,0) -> BS | I4: =VLOOKUP(D4,'COA LTD'!A:F,4,0) -> cash | J4: =VLOOKUP(D4,'COA LTD'!A:F,5,0) -> 0 | K4: =F4/G4 -> 3.5190138
A5: Assets.1** | B5: Cash and Cash equivalent.10* | C5: Banks.100 | D5: 10004 | E5: Bank SVB LTD **3838 | F5: 2900219.3 | G5: 824160.08 | H5: =VLOOKUP(D5,'COA LTD'!A:F,3,0) -> BS | I5: =VLOOKUP(D5,'COA LTD'!A:F,4,0) -> cash | J5: =VLOOKUP(D5,'COA LTD'!A:F,5,0) -> 0 | K5: =F5/G5 -> 3.519
A6: Assets.1** | B6: Cash and Cash equivalent.10* | C6: Banks.100 | D6: 10005 | E6: Bank SVB-MMA **6735 | F6: 68199313 | G6: 19380311 | H6: =VLOOKUP(D6,'COA LTD'!A:F,3,0) -> BS | I6: =VLOOKUP(D6,'COA LTD'!A:F,4,0) -> cash | J6: =VLOOKUP(D6,'COA LTD'!A:F,5,0) -> 0 | K6: =F6/G6 -> 3.519
A7: Assets.1** | B7: Cash and Cash equivalent.10* | C7: Banks.100 | D7: 10006 | E7: Bank SVB-COLLATERAL MMA **7997 | F7: 4962669.8 | G7: 1410250 | H7: =VLOOKUP(D7,'COA LTD'!A:F,3,0) -> BS | I7: =VLOOKUP(D7,'COA LTD'!A:F,4,0) -> Restricted LT deposit | J7: =VLOOKUP(D7,'COA LTD'!A:F,5,0) -> 0 | K7: =F7/G7 -> 3.519
A8: Assets.1** | B8: Cash and Cash equivalent.10* | C8: Deposit.101 | D8: 10102 | E8: Deposit bank leumi USD 30M | F8: 106520419 | G8: 30270082 | H8: =VLOOKUP(D8,'COA LTD'!A:F,3,0) -> BS | I8: =VLOOKUP(D8,'COA LTD'!A:F,4,0) -> Short term deposit | J8: =VLOOKUP(D8,'COA LTD'!A:F,5,0) -> 0 | K8: =F8/G8 -> 3.519
A9: Assets.1** | B9: Cash and Cash equivalent.10* | C9: Deposit.101 | D9: 10103 | E9: Deposit bank leumi NIS (SKY) | F9: 3719430 | G9: 1056956.5 | H9: =VLOOKUP(D9,'COA LTD'!A:F,3,0) -> BS | I9: =VLOOKUP(D9,'COA LTD'!A:F,4,0) -> Restricted LT deposit | J9: =VLOOKUP(D9,'COA LTD'!A:F,5,0) -> 0 | K9: =F9/G9 -> 3.519
A10: Assets.1** | B10: Cash and Cash equivalent.10* | C10: E-Wallet.102 | D10: 10200 | E10: Bank Paypal LTD-USD | F10: 1825547.2 | G10: 518768.73 | H10: =VLOOKUP(D10,'COA LTD'!A:F,3,0) -> BS | I10: =VLOOKUP(D10,'COA LTD'!A:F,4,0) -> cash | J10: =VLOOKUP(D10,'COA LTD'!A:F,5,0) -> 0 | K10: =F10/G10 -> 3.519
A11: Assets.1** | B11: Cash and Cash equivalent.10* | C11: E-Wallet.102 | D11: 10201 | E11: Mesh | F11: -948573.72 | G11: -269557.75 | H11: =VLOOKUP(D11,'COA LTD'!A:F,3,0) -> BS | I11: =VLOOKUP(D11,'COA LTD'!A:F,4,0) -> Accrued Expenses | J11: =VLOOKUP(D11,'COA LTD'!A:F,5,0) -> 0 | K11: =F11/G11 -> 3.519
A12: Assets.1** | B12: Trade receivable.11* | C12: Account receivable.111 | D12: 11100 | E12: Account receivable | F12: 9389531.7 | G12: 2668238.6 | H12: =VLOOKUP(D12,'COA LTD'!A:F,3,0) -> BS | I12: =VLOOKUP(D12,'COA LTD'!A:F,4,0) -> Account receivable | J12: =VLOOKUP(D12,'COA LTD'!A:F,5,0) -> 0 | K12: =F12/G12 -> 3.519
A13: Assets.1** | B13: Related party receivable.12* | C13: IC receivable.120 | D13: 12000 | E13: Papaya Gaming INC | F13: 1.8539152e+09 | G13: 5.2683013e+08 | H13: =VLOOKUP(D13,'COA LTD'!A:F,3,0) -> BS | I13: =VLOOKUP(D13,'COA LTD'!A:F,4,0) -> Related Party | J13: =VLOOKUP(D13,'COA LTD'!A:F,5,0) -> 0 | K13: =F13/G13 -> 3.519
A14: Assets.1** | B14: Other receivable.13* | C14: Authorities.130 | D14: 13000 | E14: Vat D/C (חו״ז מע״מ) | F14: 4717224.8 | G14: 1340501.5 | H14: =VLOOKUP(D14,'COA LTD'!A:F,3,0) -> BS | I14: =VLOOKUP(D14,'COA LTD'!A:F,4,0) -> Other accounts receivable | J14: =VLOOKUP(D14,'COA LTD'!A:F,5,0) -> 0 | K14: =F14/G14 -> 3.519
... A263: Department.8** | B263: R&D.81* | C263: RnD Payroll.81A | D263: 81030118 | E263: RnD Art- Meal value D | F263: 272105 | G263: 79953.47 | H263: =VLOOKUP(D263,'COA LTD'!A:F,3,0) -> PL | I263: =VLOOKUP(D263,'COA LTD'!A:F,4,0) -> Research and development expenses, net | J263: =VLOOKUP(D263,'COA LTD'!A:F,5,0) -> Salary | K263: =F263/G263 -> 3.4032919
A264: Department.8** | B264: R&D.81* | C264: RnD Payroll.81A | D264: 81030119 | E264: RnD Art- Meal value C | F264: -272105 | G264: -79953.47 | H264: =VLOOKUP(D264,'COA LTD'!A:F,3,0) -> PL | I264: =VLOOKUP(D264,'COA LTD'!A:F,4,0) -> Research and development expenses, net | J264: =VLOOKUP(D264,'COA LTD'!A:F,5,0) -> Salary | K264: =F264/G264 -> 3.4032919 | N264: option expenses
A265: Department.8** | B265: R&D.81* | C265: RnD Payroll.81A | D265: 81030120 | E265: RnD Art- Gifts Value D | F265: 39970 | G265: 11579.12 | H265: =VLOOKUP(D265,'COA LTD'!A:F,3,0) -> PL | I265: =VLOOKUP(D265,'COA LTD'!A:F,4,0) -> Research and development expenses, net | J265: =VLOOKUP(D265,'COA LTD'!A:F,5,0) -> salary | K265: =F265/G265 -> 3.4519031
A266: Department.8** | B266: R&D.81* | C266: RnD Payroll.81A | D266: 81030121 | E266: RnD Art- Gifts Value C | F266: -39970 | G266: -11579.12 | H266: =VLOOKUP(D266,'COA LTD'!A:F,3,0) -> PL | I266: =VLOOKUP(D266,'COA LTD'!A:F,4,0) -> Research and development expenses, net | J266: =VLOOKUP(D266,'COA LTD'!A:F,5,0) -> salary | K266: =F266/G266 -> 3.4519031
A267: Department.8** | B267: R&D.81* | C267: RnD Payroll.81A | D267: 81040100 | E267: RnD Product- Base salary | F267: 4688367 | G267: 1383435.8 | H267: =VLOOKUP(D267,'COA LTD'!A:F,3,0) -> PL | I267: =VLOOKUP(D267,'COA LTD'!A:F,4,0) -> Research and development expenses, net | J267: =VLOOKUP(D267,'COA LTD'!A:F,5,0) -> Salary | K267: =F267/G267 -> 3.3889299
A268: Department.8** | B268: R&D.81* | C268: RnD Payroll.81A | D268: 81040102 | E268: RnD Product- Options | F268: 164450.34 | G268: 54515.31 | H268: =VLOOKUP(D268,'COA LTD'!A:F,3,0) -> PL | I268: =VLOOKUP(D268,'COA LTD'!A:F,4,0) -> Research and development expenses, net | J268: =VLOOKUP(D268,'COA LTD'!A:F,5,0) -> option expenses | K268: =F268/G268 -> 3.01659
A269: Department.8** | B269: R&D.81* | C269: RnD Payroll.81A | D269: 81040104 | E269: RnD Product- Bonus provision | F269: 195096 | G269: 40495.54 | H269: =VLOOKUP(D269,'COA LTD'!A:F,3,0) -> PL | I269: =VLOOKUP(D269,'COA LTD'!A:F,4,0) -> Research and development expenses, net | J269: =VLOOKUP(D269,'COA LTD'!A:F,5,0) -> Salary | K269: =F269/G269 -> 4.8177157
A270: Department.8** | B270: R&D.81* | C270: RnD Payroll.81A | D270: 81040107 | E270: RnD Product- vacation provision | F270: 185139.2 | G270: 55284.9 | H270: =VLOOKUP(D270,'COA LTD'!A:F,3,0) -> PL | I270: =VLOOKUP(D270,'COA LTD'!A:F,4,0) -> Research and development expenses, net | J270: =VLOOKUP(D270,'COA LTD'!A:F,5,0) -> Salary | K270: =F270/G270 -> 3.3488204
A271: Department.8** | B271: R&D.81* | C271: RnD Payroll.81A | D271: 81040108 | E271: RnD Product- Social security | F271: 240655 | G271: 70819.14 | H271: =VLOOKUP(D271,'COA LTD'!A:F,3,0) -> PL | I271: =VLOOKUP(D271,'COA LTD'!A:F,4,0) -> Research and development expenses, net | J271: =VLOOKUP(D271,'COA LTD'!A:F,5,0) -> Salary | K271: =F271/G271 -> 3.3981633
A272: Department.8** | B272: R&D.81* | C272: RnD Payroll.81A | D272: 81040109 | E272: RnD Product- Pension | F272: 241909 | G272: 71143.17 | H272: =VLOOKUP(D272,'COA LTD'!A:F,3,0) -> PL | I272: =VLOOKUP(D272,'COA LTD'!A:F,4,0) -> Research and development expenses, net | J272: =VLOOKUP(D272,'COA LTD'!A:F,5,0) -> Salary | K272: =F272/G272 -> 3.4003124
A273: Department.8** | B273: R&D.81* | C273: RnD Payroll.81A | D273: 81040110 | E273: RnD Product- Education fund | F273: 125107 | G273: 36734.55 | H273: =VLOOKUP(D273,'COA LTD'!A:F,3,0) -> PL | I273: =VLOOKUP(D273,'COA LTD'!A:F,4,0) -> Research and development expenses, net | J273: =VLOOKUP(D273,'COA LTD'!A:F,5,0) -> Salary | K273: =F273/G273 -> 3.4057039
A274: Department.8** | B274: R&D.81* | C274: RnD Payroll.81A | D274: 81040111 | E274: RnD Product- Recuperation | F274: 3756.54 | G274: 1099.31 | H274: =VLOOKUP(D274,'COA LTD'!A:F,3,0) -> PL | I274: =VLOOKUP(D274,'COA LTD'!A:F,4,0) -> Research and development expenses, net | J274: =VLOOKUP(D274,'COA LTD'!A:F,5,0) -> Salary | K274: =F274/G274 -> 3.4171799
A275: Department.8** | B275: R&D.81* | C275: RnD Payroll.81A | D275: 81040112 | E275: RnD Product- Severance | F275: 275083 | G275: 80400.49 | H275: =VLOOKUP(D275,'COA LTD'!A:F,3,0) -> PL | I275: =VLOOKUP(D275,'COA LTD'!A:F,4,0) -> Research and development expenses, net | J275: =VLOOKUP(D275,'COA LTD'!A:F,5,0) -> Salary | K275: =F275/G275 -> 3.4214095
A276: Department.8** | B276: R&D.81* | C276: RnD Payroll.81A | D276: 81040114 | E276: RnD Product- Pension Value D | F276: 76072 | G276: 22283.03 | H276: =VLOOKUP(D276,'COA LTD'!A:F,3,0) -> PL | I276: =VLOOKUP(D276,'COA LTD'!A:F,4,0) -> Research and development expenses, net | J276: =VLOOKUP(D276,'COA LTD'!A:F,5,0) -> Salary | K276: =F276/G276 -> 3.4138984
... A623: Financial Expenses.9** | B623: Financial Expenses.90* | C623: Financial exp.90K | D623: 90201109 | E623: Financial exp - Currency difference GBP | F623: -55779.58 | G623: -58702.41 | H623: =VLOOKUP(D623,'COA LTD'!A:F,3,0) -> PL | I623: =VLOOKUP(D623,'COA LTD'!A:F,4,0) -> Financial expenses, net | J623: =VLOOKUP(D623,'COA LTD'!A:F,5,0) -> Exchange rate | K623: =F623/G623 -> 0.95020937

Sheet AJE 2022
M2: End of 2022 | N2: 3.519
F3: LTD | M3: Average 2022 | N3: 3.35 | T3: INC
S8: 1 | U8: Revenue Sales Tax | AA8: עדכון sales Tax
G9: חובה דולר | H9: זכות דולר | J9: חובה שקל | K9: זכות שקל | U9: Sales tax Provision
O11: תיקון משיכת sales tax
B12: הוצאת חשבונית | E12: 60203095 | F12: Revenue - Revenue Sales Tax | S12: 2 | U12: חו״ ז | AA12: עדכון sales Tax
F13: PAPAYA GAMING INC חוז | U13: IC exp | AC13: =14532619+4903754+V8-632066 -> 18804307
P15: ='AJE 2022'!J12+'AJE 2022'!J27 -> 0
P17: ='AJE 2022'!J38 -> 0 | S17: 3 | U17: חו״ז | AA17: תיקון פקודת איחוד
U18: IC Revenues
O21: תיקון פקודת איחוד | S21: 4 | U21: חו״ז | AA21: תיקון פקודת איחוד
F22: IC expenses G&N | U22: TP Expenses
F23: חו״ז
O26: תיקון פקודת איחוד | S26: 5 | U26: חו״ז | AA26: משיכת הוצ מימון + TAX B2B
D27: new | E27: Revenue - Revenue general | F27: IC revenure | U27: IC Revenues
F28: חו״ז
S30: 6 | U30: Sales tax Provision | AA30: העברת התחייבות למס לישראל
O31: TP משיכת הוצ מימון + TAX B2B | U31: חוז
F32: finance exp
F33: חו״ז
S34: 7 | U34: Other accounts receivable | AA34: העברת הכנסות לקבל לישראל
U35: חוז
F36: הוצ אופציות הנה״כ | O36: תיקון הוצ אופציות
F37: הוצ אופציות מו״פ
F38: הוצאות אופציות operation
F39: הוצאות אופציות מרקטינג | AA39: העברת הוצ לשלם של העמלות של הסולקים
E40: 51100 | F40: קרן הון תמ״מ
O42: התחייבות sales tax - העברה לישראל
F43: חוז
F44: Sales tax Provision
O48: העברת הכנסות לקבל - לישרא | U48: ='AJE 2022'!G12+'AJE 2022'!G27 -> 0
F49: Account receivable
F50: חוז
O54: עדכון מס נדחה
F55: Tax expenses
E56: 39000 | F56: Deferred tax liabilities
O58: עדכון הוצ מס
F59: Tax expenses
F60: Tax provision
O65: העברה של 11% נוספים של הוסטנג למו״פ .
F66: hosting r&d
F67: hosting Operetion
O77: העברת פקודות יומן של חכירות סקיי טאוור + איסרליש
E78: Debit | F78: ROA Asset
E79: Credit | F79: ROA Liabillity
E80: Debit | F80: Rent Expenses
E81: Credit | F81: Prepaid Expenses
E82: Debit | F82: Financial Expenses
O87: סגירת תביעה משפטית
E88: new 1 | F88: Legal LAWSUIT
F89: Acc expenses
O92: הכנסות לקבל פקדון 30M גלור
F93: הכנסות ריבית לקבל
F94: פקדון
O96: מיון שכר של אוריאל 33%
E97: איפה שהשכר של אנדרי ואלכס | F97: ח. הוצ שכר מופ
E98: איפה שרשום ההוצאות שכר של אוריאת | F98: ז. הוצ שכר הנה״כ
O100: מיון שכר של מוניטיזציה
E101: new 3 | F101: ח. הוצ מרקטינג
E102: new 2 | F102: ז הוצ שכר מיון מו״ פ
O104: עדכון הפרשה למס לאחר כל הפקודות הנוספות
F105: ז׳ - הוצאות מס | G105: =J105/N2 -> 0 | H105: =K105/N2 -> 70562.173 | K105: 248308.29
F106: ח׳ - הפרשה למס | G106: =H105 -> 70562.173 | H106: =G105 -> 0 | J106: =K105 -> 248308.29 | K106: =J105 -> 0
O108: עדכון הפרשה למס בגין 2021
F109: ח׳ - הוצ מס שנים קודמות | G109: =J109/$N$2 -> 23850.626 | J109: 83930.351
F110: ז. הפרשה למס | H110: =G109 -> 23850.626 | K110: =J109 -> 83930.351
H112: =-H105+G109 -> -46711.547 | K112: =-K105+J109 -> -164377.93
T118: ='AJE 2022'!K105-'AJE 2022'!K110 -> 164377.93

Sheet COA INC
A2: 10004 | B2: Bank SVB 80025 | C2: BS | D2: Cash
A3: 10101 | B3: Reserve Worldpay | C3: BS | D3: Deposit
A4: 10200 | B4: Bank Paypal INC | C4: BS | D4: Cash
A5: 11100 | B5: Other Accounts Receivable | C5: BS | D5: Other Accounts Receivable
A6: 12001 | B6: Papaya Gaming Ltd | C6: BS | D6: Related Party
A7: 35002 | B7: Due to/from Papaya Ltd | C7: BS | D7: Related Party
A8: 30000 | B8: Tax provision 2021 | C8: BS | D8: Other accounts payable
A9: 31006 | B9: Prepaid tax 2022 | C9: BS | D9: Other accounts payable
A10: 340001 | B10: Samsung | C10: BS | D10: Trade payables
A11: 340002 | B11: Google | C11: BS | D11: Trade payables
A12: 340003 | B12: Cybersource | C12: BS | D12: Trade payables
A13: 340004 | B13: D Young CO LLP | C13: BS | D13: Trade payables
... A18: 54000 | B18: Retained Earnings | C18: BS | D18: Accumulated deficit
A19: 60202096 | B19: Revenue -IC revenue | C19: PL | D19: Revenues | E19: Revenue -IC revenue
A20: 60202000 | B20: Revenue -Revenue Worldpay | C20: PL | D20: Revenues | E20: Revenue -Revenue Worldpay
A21: 60202007 | B21: Revenue -Revenue Paypal IL | C21: PL | D21: Revenues | E21: Revenue -Revenue Paypal IL
A22: 60202009 | B22: Revenue -Revenue Paypal US | C22: PL | D22: Revenues | E22: Revenue -Revenue Paypal US
A23: 60202016 | B23: Revenue -Revenue Cyber Source | C23: PL | D23: Revenues | E23: Revenue -Revenue Cyber Source
A24: 70201200 | B24: Tax -Tax expenses current period | C24: PL | D24: Tax expenses | E24: Tax expenses
A25: 80201300 | B25: Operations -Worldpay fees | C25: PL | D25: Operations | E25: Worldpay fees
A26: 80201307 | B26: Operations -Paypal fees | C26: PL | D26: Operations | E26: Paypal fees
A27: 80201309 | B27: Operations -Paypal US fees | C27: PL | D27: Operations | E27: Paypal US fees
A28: 80201316 | B28: Operations -Cybersource SVB fees | C28: PL | D28: Operations | E28: Cybersource SVB fees
A29: 80201400 | B29: Operations -IR VAT | C29: PL | D29: General and administrative expenses | E29: Vat
A30: 80201500 | B30: Operations - Worldpay CHB | C30: PL | D30: Operations | E30: Worldpay CHB
... A42: 90201104 | B42: Financial exp -epricing exp | C42: PL | D42: Financial expenses, net | E42: Exchange rate
A43: 340005 | B43: The Yard | C43: BS | D43: Trade payables
A44: 340007 | B44: VLP Law Group LLP | C44: BS | D44: Trade payables
A45: 340008 | B45: Keystone Law | C45: BS | D45: Trade payables
A46: 340009 | B46: CITY-YUWA PARTNERS | C46: BS | D46: Trade payables
A47: 340022 | B47: Tozzini, Freire, Teixeira e Silva | C47: BS | D47: Trade payables
A48: 60202023 | B48: Revenue -Revenue Braintree | C48: PL | D48: Revenues | E48: Revenue - Braintree
A49: 84200401 | B49: Allocation -rent | C49: PL | D49: General and administrative expenses | E49: Other expenses
A50: 90201102 | B50: Financial exp -Paypal Currency difference | C50: PL | D50: Financial expenses, net | E50: Exchange rate
A51: 80201323 | B51: Operations -Braintree fees | C51: PL | D51: Operations | E51: Braintree fees
A52: 80201509 | B52: Operations - Paypal US CHB | C52: PL | D52: Operations | E52: Paypal US CHB
A53: 83120203 | B53: G&A Finance -Tax Consulting | C53: PL | D53: General and administrative expenses | E53: Professional Services
A54: 10005 | B54: Bank SVB MMA 6754 | C54: BS | D54: Cash
A55: 10201 | B55: Bank Paypal INC-Transfer | C55: BS | D55: Cash
A56: 340011 | B56: Bryan Aarflot | C56: BS | D56: Trade payables
A57: 340012 | B57: Khaitan & Co | C57: BS | D57: Trade payables
A58: 80201523 | B58: Operations - Braintree CHB | C58: PL | D58: Operations | E58: Braintree CHB
A59: 90201103 | B59: Financial exp -Interest Income | C59: PL | D59: Financial expenses, net | E59: Income -interest
A60: 340023 | B60: ZwillGen PLLC | C60: BS | D60: Trade payables
A61: 80201304 | B61: Operations - Proccesing fees | C61: PL | D61: Operations | E61: Cybersource SVB fees
A62: 82110300 | B62: S&M Marketing- Saas | C62: PL | D62: Marketing expenses | E62: Softwere subscription
A63: 342001 | B63: Samsung | C63: BS | D63: Trade payables
A64: 342002 | B64: Google | C64: BS | D64: Trade payables
A65: 342003 | B65: Cybersource | C65: BS | D65: Trade payables
A66: 342004 | B66: D Young CO LLP | C66: BS | D66: Trade payables
A67: 342005 | B67: The Yard | C67: BS | D67: Trade payables
A68: 342006 | B68: LexOrbis | C68: BS | D68: Trade payables
A69: 342007 | B69: VLP Law Group LLP | C69: BS | D69: Trade payables
A70: 342008 | B70: Keystone Law | C70: BS | D70: Trade payables
A71: 342009 | B71: CITY-YUWA PARTNERS | C71: BS | D71: Trade payables
A72: 342011 | B72: Bryan Aarflot | C72: BS | D72: Trade payables
A73: 342012 | B73: Khaitan & Co | C73: BS | D73: Trade payables
A74: 342022 | B74: Tozzini, Freire, Teixeira e Silva | C74: BS | D74: Trade payables
A75: 342023 | B75: ZwillGen PLLC | C75: BS | D75: Trade payables
A76: 83120215 | B76: G&A Finance -Compliance | C76: PL | D76: General and administrative expenses | E76: Legal
A77: 83150207 | B77: G&A Legal -Compliance | C77: PL | D77: General and administrative expenses | E77: Legal
A78: 342013 | B78: KPMG | C78: BS | D78: Trade payables
A79: 83120214 | B79: G&A Finance- US tax reporting | C79: PL | D79: General and administrative expenses | E79: Professional Services
A80: 61202000 | B80: Revenue -Sales tax | C80: PL | D80: Revenues | E80: Revenue Sales Tax
A81: 31007 | B81: Sales Tax | C81: BS | D81: Sales Tax Provision
A82: 83150205 | B82: G&A Legal -Commercial | C82: PL | D82: General and administrative expenses | E82: Legal
A83: 10006 | B83: Bank SVB COLLATERAL MMA 7982 | C83: BS | D83: Deposit
A84: 342024 | B84: Envato | C84: BS | D84: Trade payables
A85: 342025 | B85: Poindexter Associates INC | C85: BS | D85: Trade payables
A86: 342026 | B86: Gaming Laboratories International | C86: BS | D86: Trade payables
A87: 70201201 | B87: Tax -Tax expenses Previous Years | C87: PL | D87: Tax expenses | E87: Tax expenses
A88: 82110904 | B88: S&M Marketing -UA Indirect PR | C88: PL | D88: Marketing expenses | E88: PR
F155: ;

Sheet BS INC
A2: Papaya gaming INC
C8: 2022 | D8: JE | E8: 2022
C9: INC | E9: INC
C10: USD | E10: USD
B11: CURRENT ASSETS
B13: Cash | C13: =SUMIF('TB INC 12.22'!I:I,'BS INC'!B13,'TB INC 12.22'!F:F) -> 24693919 | E13: =C13+D13 -> 24693919
B14: Account receivable | C14: =SUMIF('TB INC 12.22'!I:I,'BS INC'!B14,'TB INC 12.22'!F:F) -> 0 | E14: =C14+D14 -> 0
B15: Related Party | C15: =SUMIF('TB INC 12.22'!I:I,'BS INC'!B15,'TB INC 12.22'!F:F) -> -24505604 | D15: ='AJE 2022'!V12+'AJE 2022'!V17+'AJE 2022'!V21+'AJE 2022'!V26-'AJE 2022'!W31+'AJE 2022'!V35 -> 0 | E15: =C15+D15 -> -24505604
B16: Other accounts receivable | C16: =SUMIF('TB INC 12.22'!I:I,'BS INC'!B16,'TB INC 12.22'!F:F) -> 1085652.4 | D16: =-'AJE 2022'!V35 -> 0 | E16: =C16+D16 -> 1085652.4
C17: =SUM(C13:C16) -> 1273967.5 | E17: =SUM(E13:E16) -> 1273967.5
B20: Non CURRENT ASSETS
B22: Restricted LT deposit | C22: =SUMIF('TB INC 12.22'!I:I,'BS INC'!B22,'TB INC 12.22'!F:F) -> 1199999 | E22: =C22+D22 -> 1199999
B24: Total Assets | C24: =+C17+C22 -> 2473966.5 | E24: =+E17+E22 -> 2473966.5
B26: CURRENT LIABILITIES
B28: Trade payables | C28: =SUMIF('TB INC 12.22'!I:I,'BS INC'!B28,'TB INC 12.22'!F:F) -> -952301.09 | E28: =C28+D28 -> -952301.09
B29: Other accounts payable | C29: =SUMIF('TB INC 12.22'!I:I,'BS INC'!B29,'TB INC 12.22'!F:F) -> -1211355.4 | E29: =C29+D29 -> -1211355.4
B30: Sales Tax Provision | C30: =SUMIF('TB INC 12.22'!I:I,'BS INC'!B30,'TB INC 12.22'!F:F) -> 0 | D30: =-'P&L INC'!E17+'AJE 2022'!V30 -> 0 | E30: =C30+D30 -> 0
C31: =SUM(C28:C30) -> -2163656.5 | E31: =SUM(E28:E30) -> -2163656.5 | F31: =C30+11413446 -> 11413446
B34: Total libiliaties | C34: =+C31 -> -2163656.5 | E34: =+E31 -> -2163656.5
B36: SHAREHOLDERS' EQUITY
B38: Accumulated deficit | C38: =SUMIF('TB INC 12.22'!I:I,'BS INC'!B38,'TB INC 12.22'!F:F) -> -297517.45 | E38: =C38+D38 -> -297517.45
B39: PL | C39: ='P&L INC'!D51 -> -12793.34 | D39: ='P&L INC'!E42 -> 0 | E39: =C39+D39 -> -12793.34
C40: =SUM(C38:C39) -> -310310.79 | E40: =SUM(E38:E39) -> -310310.79
C42: =C40+C34 -> -2473967.3 | E42: =E40+E34 -> -2473967.3
C43: =+C42=-C24 -> FALSE | E43: =+E42=-E24 -> FALSE
C44: =+C42+C24 -> -0.80999996 | E44: =+E42+E24 -> -0.80999996

Sheet P&L INC
A2: Papaya gaming INC
D8: 2022 | E8: JE | F8: 2022
D9: INC | F9: INC
B11: Revenues | C11: Revenue -IC revenue | D11: =SUMIFS('TB INC 12.22'!F:F,'TB INC 12.22'!I:I,$B11,'TB INC 12.22'!J:J,$C11) -> -45183882 | E11: =-'AJE 2022'!W18-'AJE 2022'!V26 -> 0 | F11: =D11+E11 -> -45183882 | J11: =SUM(F12:F17) -> -3.3940583e+08 | K11: סה״כהכנסות אינק
B12: Revenues | C12: Revenue -Revenue Worldpay | D12: =SUMIFS('TB INC 12.22'!F:F,'TB INC 12.22'!I:I,$B12,'TB INC 12.22'!J:J,$C12) -> -79914238 | F12: =D12+E12 -> -79914238 | J12: =-(F38+F39) -> -3.3944901e+08 | K12: סה״כ הוצ באינק- כנגד משיכת הכנסה
B13: Revenues | C13: Revenue -Revenue Paypal IL | D13: =SUMIFS('TB INC 12.22'!F:F,'TB INC 12.22'!I:I,$B13,'TB INC 12.22'!J:J,$C13) -> -32041473 | F13: =D13+E13 -> -32041473 | J13: =J11-J12 -> 43181.59 | K13: GAP
B14: Revenues | C14: Revenue -Revenue Paypal US | D14: =SUMIFS('TB INC 12.22'!F:F,'TB INC 12.22'!I:I,$B14,'TB INC 12.22'!J:J,$C14) -> -78439126 | F14: =D14+E14 -> -78439126 | J14: =F38 -> 43181.59 | K14: VaT
B15: Revenues | C15: Revenue -Revenue Cyber Source | D15: =SUMIFS('TB INC 12.22'!F:F,'TB INC 12.22'!I:I,$B15,'TB INC 12.22'!J:J,$C15) -> -1.3603747e+08 | F15: =D15+E15 -> -1.3603747e+08 | J15: =J13-J14 -> -2.6222551e-08 | K15: I.M
B16: Revenues | C16: Revenue - Braintree | D16: =SUMIFS('TB INC 12.22'!F:F,'TB INC 12.22'!I:I,$B16,'TB INC 12.22'!J:J,$C16) -> -24386971 | F16: =D16+E16 -> -24386971 | J16: 31274.21
B17: Revenues | C17: Revenue Sales Tax | D17: =SUMIFS('TB INC 12.22'!F:F,'TB INC 12.22'!I:I,$B17,'TB INC 12.22'!J:J,$C17) -> 11413446 | E17: ='AJE 2022'!V8 -> 0 | F17: =D17+E17 -> 11413446 | G17: 11508311 | H17: =F17-G17 -> -94865
B18: Total Revenues | C18: Total income | D18: =SUM(D11:D17) -> -3.8458971e+08 | E18: =SUM(E11:E17) -> 0 | F18: =SUM(F11:F17) -> -3.8458971e+08
C20: Operations | D20: =SUM(D21:D25) -> 19761872 | E20: =SUM(E21:E25) -> 0 | F20: =SUM(F21:F25) -> 19761872
A21: FEE | B21: Operations | C21: Worldpay fees | D21: =SUMIFS('TB INC 12.22'!F:F,'TB INC 12.22'!I:I,$B21,'TB INC 12.22'!J:J,$C21) -> 4897335 | F21: =D21+E21 -> 4897335
A22: FEE | B22: Operations | C22: Paypal fees | D22: =SUMIFS('TB INC 12.22'!F:F,'TB INC 12.22'!I:I,$B22,'TB INC 12.22'!J:J,$C22) -> 2076066.5 | F22: =D22+E22 -> 2076066.5 | J22: =SUM(F12:F17) -> -3.3940583e+08 | K22: סה״כהכנסות אינק
A23: FEE | B23: Operations | C23: Paypal US fees | D23: =SUMIFS('TB INC 12.22'!F:F,'TB INC 12.22'!I:I,$B23,'TB INC 12.22'!J:J,$C23) -> 3479229.9 | F23: =D23+E23 -> 3479229.9 | J23: ='P&L LTD USD'!F5 -> -3.3963699e+08 | K23: סה״כ הכנסות בישראל
A24: FEE | B24: Operations | C24: Cybersource SVB fees | D24: =SUMIFS('TB INC 12.22'!F:F,'TB INC 12.22'!I:I,$B24,'TB INC 12.22'!J:J,$C24) -> 8169254 | F24: =D24+E24 -> 8169254 | J24: =J22-J23 -> 231159.39 | K24: GAP
A25: FEE | B25: Operations | C25: Braintree fees | D25: =SUMIFS('TB INC 12.22'!F:F,'TB INC 12.22'!I:I,$B25,'TB INC 12.22'!J:J,$C25) -> 1139986.4 | F25: =D25+E25 -> 1139986.4 | J25: 249578 | K25: FX
C26: Gross profit | D26: =D18+D20 -> -3.6482784e+08 | E26: =E18+E20 -> 0 | F26: =F18+F20 -> -3.6482784e+08 | J26: =J24-J25 -> -18418.61 | K26: I.M
C28: Marketing expenses | D28: =SUM(D29:D32) -> 24957328 | E28: =SUM(E29:E32) -> 0 | F28: =SUM(F29:F32) -> 24957328
A29: Overheads | B29: Marketing expenses | C29: Professional Services | D29: =SUMIFS('TB INC 12.22'!F:F,'TB INC 12.22'!I:I,$B29,'TB INC 12.22'!J:J,$C29) -> 61900.39 | F29: =D29+E29 -> 61900.39
A30: Ua | B30: Marketing expenses | C30: Ua | D30: =SUMIFS('TB INC 12.22'!F:F,'TB INC 12.22'!I:I,$B30,'TB INC 12.22'!J:J,$C30) -> 24308066 | F30: =D30+E30 -> 24308066
A31: Ua Indirect | B31: Marketing expenses | C31: Softwere subscription | D31: =SUMIFS('TB INC 12.22'!F:F,'TB INC 12.22'!I:I,$B31,'TB INC 12.22'!J:J,$C31) -> 581361.08 | F31: =D31+E31 -> 581361.08
A32: Ua Indirect | B32: Marketing expenses | C32: PR | D32: =SUMIFS('TB INC 12.22'!F:F,'TB INC 12.22'!I:I,$B32,'TB INC 12.22'!J:J,$C32) -> 6000 | F32: =D32+E32 -> 6000
J33: =F38+F39 -> 3.3944901e+08 | K33: סה״כ הוצאות IC ecp
C34: General and administrative expenses | D34: =SUM(D35:D38) -> 182761.95 | E34: =SUM(E35:E38) -> 0 | F34: =SUM(F35:F38) -> 182761.95 | G34: =F34*7% -> 12793.336 | J34: ='P&L LTD USD'!F5 -> -3.3963699e+08 | K34: סה״כ הכנסות בישראל
A35: Overheads | B35: General and administrative expenses | C35: Professional Services | D35: =SUMIFS('TB INC 12.22'!F:F,'TB INC 12.22'!I:I,$B35,'TB INC 12.22'!J:J,$C35) -> 64357.53 | F35: =D35+E35 -> 64357.53 | J35: =J33+J34 -> -187977.8 | K35: GAP
A36: Overheads | B36: General and administrative expenses | C36: Other expenses | D36: =SUMIFS('TB INC 12.22'!F:F,'TB INC 12.22'!I:I,$B36,'TB INC 12.22'!J:J,$C36) -> 550 | F36: =D36+E36 -> 550 | J36: =D38 -> 43181.59 | K36: VAT באינק מופיע בהוצ בישראל לא
A37: Overheads | B37: General and administrative expenses | C37: Legal | D37: =SUMIFS('TB INC 12.22'!F:F,'TB INC 12.22'!I:I,$B37,'TB INC 12.22'!J:J,$C37) -> 74672.83 | F37: =D37+E37 -> 74672.83 | J37: =-J25 -> -249578 | K37: FX בישראל מופיע בהכנסות באינק בהוצ מימון
A38: Overheads | B38: General and administrative expenses | C38: Vat | D38: =SUMIFS('TB INC 12.22'!F:F,'TB INC 12.22'!I:I,$B38,'TB INC 12.22'!J:J,$C38) -> 43181.59 | F38: =D38+E38 -> 43181.59 | G38: צריך להיות | H38: רשום | I38: 73679.806
B39: TP Expenses | C39: TP Expenses | D39: =SUMIFS('TB INC 12.22'!F:F,'TB INC 12.22'!I:I,$B39,'TB INC 12.22'!J:J,$C39) -> 3.3940583e+08 | E39: =-'AJE 2022'!V12-'AJE 2022'!W22 -> 0 | F39: =D39+E39 -> 3.3940583e+08 | G39: =F20+F28+(F35+F37+F36+F38)*1.07 -> 44914755 | H39: =D11 -> -45183882 | I39: =G39+H39 -> -269127.25 | J39: =J35-(J36+J37) -> 18418.61 | K39: I.M
C40: Operating expenses | D40: =D34+D28+D39 -> 3.6454592e+08 | E40: =E34+E28+E39 -> 0 | F40: =F34+F28+F39 -> 3.6454592e+08
J41: =+J39+J26 -> -2.6222551e-08
C42: Operating profit | D42: =D40+D26 -> -281920.59 | E42: =E40+E26 -> 0 | F42: =F40+F26 -> -281920.59 | G42: =F42-G34 -> -294713.93
C44: Financial expenses, net | D44: =SUM(D45:D48) -> 179789.7 | E44: =SUM(E45:E48) -> 0 | F44: =SUM(F45:F48) -> 179789.7
A45: Financial expenses | B45: Financial expenses, net | C45: Bank fees | D45: =SUMIFS('TB INC 12.22'!F:F,'TB INC 12.22'!I:I,$B45,'TB INC 12.22'!J:J,$C45) -> -19246.86 | F45: =D45+E45 -> -19246.86
A46: Financial expenses | B46: Financial expenses, net | C46: Income -interest | D46: =SUMIFS('TB INC 12.22'!F:F,'TB INC 12.22'!I:I,$B46,'TB INC 12.22'!J:J,$C46) -> -442911.25 | F46: =D46+E46 -> -442911.25
A47: Financial expenses | B47: Financial expenses, net | C47: Exchange rate | D47: =SUMIFS('TB INC 12.22'!F:F,'TB INC 12.22'!I:I,$B47,'TB INC 12.22'!J:J,$C47) -> 641947.81 | F47: =D47+E47 -> 641947.81
B48: Financial expenses, net | D48: =SUMIFS('TB INC 12.22'!F:F,'TB INC 12.22'!I:I,$B48,'TB INC 12.22'!J:J,$C48) -> 0 | F48: =D48+E48 -> 0
A49: Taxes | B49: Tax expenses | C49: Tax expenses | D49: =SUMIFS('TB INC 12.22'!F:F,'TB INC 12.22'!I:I,$B49,'TB INC 12.22'!J:J,$C49) -> 89337.55 | F49: =D49+E49 -> 89337.55 | G49: =F44+F49 -> 269127.25 | H49: 269127.25
C51: Net loss ( profit ) | D51: =+D42+D44+D49 -> -12793.34 | E51: =+E42+E44+E49 -> 0 | F51: =+F42+F44+F49 -> -12793.34
C53: Check | D53: -699975.26 | F53: -699975.26
D54: =D51-D53 -> 687181.92 | F54: =F51-F53 -> 687181.92
C56: COGs | D56: =SUM(D21:D25) -> 19761872 | F56: =SUM(F21:F25) -> 19761872
C57: G&A | D57: =SUM(D35:D38) -> 182761.95 | F57: =SUM(F35:F38) -> 182761.95
C58: Marketing | D58: =D28 -> 24957328 | F58: =F28 -> 24957328
C59: =C44 -> Financial expenses, net | D59: =D44 -> 179789.7 | F59: =F44 -> 179789.7
C60: =C49 -> Tax expenses | D60: =D49 -> 89337.55 | F60: =F49 -> 89337.55
C61: IC exo | D61: =D57*1.07+D58+D56+D59+D60 -> 45183882 | F61: =F57*1.07+F58+F56+F59+F60 -> 45183882
D62: =D61+D11 -> -0.0035000071 | F62: =F61+F11 -> -0.0035000071
C64: Total inc income | D64: =SUM(D12:D17) -> -3.3940583e+08 | F64: =SUM(F12:F17) -> -3.3940583e+08
C65: Total LTD income | D65: =(-D39-D38) -> -3.3944901e+08 | F65: =(-F39-F38) -> -3.3944901e+08 | G65: =F65-J23 -> 187977.8
D66: =D64-D65 -> 43181.59 | F66: =F64-F65 -> 43181.59
F69: Should Be | G69: Books
D70: Cogs | E70: =SUM(F21:F25) -> 19761872 | F70: =E70 -> 19761872 | G70: ='P&L LTD USD'!D31 -> 19761872 | H70: =F70-G70 -> 0.099999998 | I70: 5877.1767
D71: S&M | E71: =SUM(F29:F32) -> 24957328 | F71: =E71 -> 24957328 | G71: ='P&L LTD USD'!D80 -> 24957328 | H71: =F71-G71 -> -0.69000001 | I71: -0.69000001
D72: G&n | E72: =SUM(F35:F38) -> 182761.95 | F72: =SUM(F35:F37)*1.054 -> 147117.7 | G72: ='P&L LTD USD'!D107 -> 195554.4 | H72: =F72-G72 -> -48436.701 | I72: 70756.695
H74: =SUM(H70:H73) -> -48437.291 | I74: Diff

Sheet TB INC 12.22
A1: כותרת ראשית; | B1: כותרת משנה; | C1: סעיף; | D1: חשבון | E1: תאור החשבון | F1: יתרה בדולרים $ | G1: יתרה בדולר USD | H1: סוג דוח | I1: מחלקה | J1: תת מחלקה
A2: Assets.1** | B2: Cash and Cash equivalent.10* | C2: Banks.100 | D2: 10004 | E2: Bank SVB *7345 | F2: 3826808 | G2: 3826808 | H2: BS | I2: Cash
A3: Assets.1** | B3: Cash and Cash equivalent.10* | C3: Banks.100 | D3: 10005 | E3: Bank SVB MMA 6754 | F3: 17773792 | G3: 17773792 | H3: BS | I3: Cash
A4: Assets.1** | B4: Cash and Cash equivalent.10* | C4: Banks.100 | D4: 10006 | E4: Bank SVB COLLATERAL MMA 7982 | F4: 1000000 | G4: 1000000 | H4: BS | I4: Restricted LT deposit
A5: Assets.1** | B5: Cash and Cash equivalent.10* | C5: Deposit.101 | D5: 10101 | E5: Reserve Worldpay | F5: 199999 | G5: 199999 | H5: BS | I5: Restricted LT deposit
A6: Assets.1** | B6: Cash and Cash equivalent.10* | C6: E-Wallet.102 | D6: 10200 | E6: Bank Paypal INC | F6: 3093319.2 | G6: 3093319.2 | H6: BS | I6: Cash
A7: Assets.1** | B7: Trade receivable.11* | C7: Account receivable.111 | D7: 11100 | E7: Other Accounts Receivable | F7: -0.08 | G7: -0.08 | H7: BS | I7: Other Accounts Receivable
A8: Assets.1** | B8: Related party receivable.12* | C8: IC receivable.120 | D8: 12001 | E8: Papaya Gaming Ltd | F8: 74237451 | G8: 74237451 | H8: BS | I8: Related Party
A9: Assets.1** | B9: Related party receivable.12* | C9: IC receivable.120 | D9: 35002 | E9: Due to/from Papaya Ltd | F9: 4.2808709e+08 | G9: 4.2808709e+08 | H9: BS | I9: Related Party
A10: Liabilities.3** | B10: Tax provision.30* | C10: Tax provision.300 | D10: 30000 | E10: Tax provision 2021 | F10: -97699.4 | G10: -97699.4 | H10: BS | I10: Other accounts payable
A11: Liabilities.3** | B11: Prepaid taxes.31* | C11: Prepaid taxes.310 | D11: 31006 | E11: Prepaid tax 2022 | F11: 1085652.5 | G11: 1085652.5 | H11: BS | I11: Other Accounts Receivable
A12: Liabilities.3** | B12: Account payables.34* | C12: AP Local.340 | D12: 342002 | E12: Google | F12: -847437.74 | G12: -847437.74 | H12: BS | I12: Trade payables
A13: Liabilities.3** | B13: Account payables.34* | C13: AP Local.340 | D13: 342003 | E13: Cybersource | F13: -99421.88 | G13: -99421.88 | H13: BS | I13: Trade payables
... A17: Equity.5** | B17: Accumulated deficit.54* | C17: Accumulated deficit.540 | D17: 54000 | E17: Retained Earnings | F17: -297517.45 | G17: -297517.45 | H17: BS | I17: Accumulated deficit
A18: Revenues.6** | B18: Revenues.60* | C18: Revenue Revenue.60R | D18: 60202096 | E18: Revenue -IC revenue | F18: -45183882 | G18: -45183882 | H18: PL | I18: Revenues | J18: Revenue -IC revenue
A19: Revenues.6** | B19: Revenues.60* | C19: Revenue Revenue.60T | D19: 60202000 | E19: Revenue -Revenue Worldpay | F19: -79914238 | G19: -79914238 | H19: PL | I19: Revenues | J19: Revenue -Revenue Worldpay
A20: Revenues.6** | B20: Revenues.60* | C20: Revenue Revenue.60T | D20: 60202007 | E20: Revenue -Revenue Paypal IL | F20: -32041473 | G20: -32041473 | H20: PL | I20: Revenues | J20: Revenue -Revenue Paypal IL
A21: Revenues.6** | B21: Revenues.60* | C21: Revenue Revenue.60T | D21: 60202009 | E21: Revenue -Revenue Paypal US | F21: -78439126 | G21: -78439126 | H21: PL | I21: Revenues | J21: Revenue -Revenue Paypal US
A22: Revenues.6** | B22: Revenues.60* | C22: Revenue Revenue.60T | D22: 60202016 | E22: Revenue -Revenue Cyber Source | F22: -1.3603747e+08 | G22: -1.3603747e+08 | H22: PL | I22: Revenues | J22: Revenue -Revenue Cyber Source
A23: Revenues.6** | B23: Revenues.60* | C23: Revenue Revenue.60T | D23: 60202023 | E23: Revenue -Revenue Braintree | F23: -24386971 | G23: -24386971 | H23: PL | I23: Revenues | J23: Revenue - Braintree
A24: Revenues.6** | B24: *61.הוצאות יצור | C24: Revenue Revenue.61T | D24: 61202000 | E24: Revenue -Sales tax | F24: 11413446 | G24: 11413446 | H24: PL | I24: Revenues | J24: Revenue Sales Tax
A25: Tax.7** | B25: Tax Expenses.70* | C25: Tax Expenses.70L | D25: 70201200 | E25: Tax -Tax expenses current period | F25: 88915.55 | G25: 88915.55 | H25: PL | I25: Tax expenses | J25: Tax expenses
A26: Tax.7** | B26: Tax Expenses.70* | C26: Tax Expenses.70L | D26: 70201201 | E26: Tax -Tax expenses Previous Years | F26: 422 | G26: 422 | H26: PL | I26: Tax expenses | J26: Tax expenses
A27: Department.8** | B27: Operations.80* | C27: Operations Processing Fees.80M | D27: 80201300 | E27: Operations -Worldpay fees | F27: 4897335 | G27: 4897335 | H27: PL | I27: Operations | J27: Worldpay fees
A28: Department.8** | B28: Operations.80* | C28: Operations Processing Fees.80M | D28: 80201304 | E28: Operations - Proccesing fees-Cybersourse | F28: 976550.04 | G28: 976550.04 | H28: PL | I28: Operations | J28: Cybersource SVB fees
A29: Department.8** | B29: Operations.80* | C29: Operations Processing Fees.80M | D29: 80201307 | E29: Operations -Paypal fees | F29: 2076066.5 | G29: 2076066.5 | H29: PL | I29: Operations | J29: Paypal fees
... A54: .9** | B54: .90* | C54: Financial exp.90K | D54: 90201104 | E54: Financial exp -epricing exp | F54: 392088 | G54: 392088 | H54: PL | I54: Financial expenses, net | J54: Exchange rate

Sheet Tech Plant Check
C1: 2018 | D1: 2019 | E1: 2020 | G1: 2021
B2: Opening Balance | D2: =+C5 -> 299492.06 | E2: =+D5 -> 1188415 | G2: =+E5 -> 2792020
B3: Expected Loss (Revenue) | E3: =2173604.92192246-570000 -> 1603604.9 | G3: =-4850953*4 -> -19403812
B4: Carryforward losses | C4: =1076644/3.5949 -> 299492.06 | D4: =3168566/3.5645 -> 888922.99
B5: Ending Balance | C5: =+SUM(C2:C4) -> 299492.06 | D5: =+SUM(D2:D4) -> 1188415 | E5: =+SUM(E2:E4) -> 2792020 | G5: =+SUM(G2:G4) -> -16611792
B10: Requirements
B12: R&D Expenses test (7%/75M NIS) | C12: 2018 | D12: 2019 | E12: 2020 | F12: 2021
B13: Revenues | C13: 0 | D13: 866635 | E13: 15116394 | F13: =-'P&L USD CONS'!L7*1000 -> 3.3423953e+11 | K13: missing
B14: R&D Expenses | C14: 201051 | D14: 692900 | E14: 2297223 | F14: ='P&L USD CONS'!L13*1000 -> 20781725320 | J14: =I13*0.07 -> 0 | K14: =J14-I14 -> 0
B15: R&D Expenses\Revenues Ratio | D15: =+D14/D13 -> 0.79952921 | E15: =+E14/E13 -> 0.15196898 | F15: =+F14/F13 -> 0.062176144
B16: R&D Expenses\Revenues Ratio - 3Y AVG | E16: =+AVERAGE(C14:E14)/AVERAGE(C13:E13) -> 0.19966015 | F16: =+AVERAGE(D14:F14)/AVERAGE(D13:F13) -> 0.062182117 | K16: =J14/I13 -> #DIV/0!
B17: Missing R&D Expenses to reach the ratio | F17: =AVERAGE(D13:F13)*0.07 -> 7.7992953e+09
B18: R&D Expenses Non GAAP | F18: =AVERAGE(D14:F14) -> 6928238481 | J18: =+G18/0.04 -> 0 | K18: Break even point | L18: Net Income in 2022
F19: =F17-F18 -> 8.7105686e+08 | G19: =F19*3 -> 2.6131706e+09 | H19: missing exp | K19: Above this point Its better to Increase our R&D Spend to reach the ratio
B21: Investment from VC in USD | C21: 500000 | E21: 5748600
B22: AVERAGE NIS/USD Exchange rate | C22: 3.5949 | D22: 3.5645 | E22: 3.4424 | G22: 3.2549
B23: Investment - 8M NIS investment from VC | C23: =+C21*C22 -> 1797450 | E23: =+E21*E22 -> 19788981
K24: 993 | L24: ספטמבר R&D
B25: 25% Increase in AVG revenues Yearly | C25: 0 | D25: 0 | E25: =+E13/D13-1 -> 16.44263 | K25: -181 | L25: founder Bonus
K26: =-(150+86)/3.25 -> -72.615385 | L26: Emp Bonus
B27: 25% Increase in AVG number of employees + at least 50 employees
B28: Number of employees | C28: 3 | D28: 13 | E28: 33 | G28: 67 | H28: 13 | I28: =G28+H28 -> 80 | K28: =K24+K25+K26 -> 739.38462
B29: HC Increase ratio | C29: 0 | D29: =+D28/C28-1 -> 3.3333333 | E29: =+E28/D28-1 -> 1.5384615 | G29: =+G28/E28-1 -> 1.030303 | I29: =G29+H29 -> 1.030303
I30: =G30+H30 -> 0 | L30: רועי
B31: 20% of the Company's employees expenses listed as R&D or At least 200 Employees | I31: =G31+H31 -> 0 | K31: 3461 | L31: יולי V2
B32: R&D Payroll | C32: =(330825+326191)/C22 -> 182763.36 | D32: =449059+791642/$D$22 -> 671149.62 | E32: 1527152 | G32: 5994309 | I32: =G32+H32 -> 5994309
B33: R&D HC | C33: 2 | D33: 9 | E33: 23 | G33: 40 | H33: 6 | I33: =G33+H33 -> 46 | K33: =651*5 -> 3255 | L33: הערכה
B34: Total Payroll | C34: =+(142534+73203)+C32 -> 398500.36 | D34: =958816+791642/$D$22+358000/$D$22 -> 1281341.5 | E34: 2005609 | G34: 9020947 | I34: =G34+H34 -> 9020947
B35: Total HC | C35: =+C28 -> 3 | D35: =+D28 -> 13 | E35: =+E28 -> 33 | G35: =+G28 -> 67 | H35: 13 | I35: =G35+H35 -> 80
B36: R&D Payroll expenses ratio | C36: =+C32/C34 -> 0.45862784 | D36: =+D32/D34 -> 0.5237867 | E36: =+E32/E34 -> 0.76144054 | G36: =+G32/G34 -> 0.66448778 | I36: =G36+H36 -> 0.66448778
B37: R&D HC ratio | C37: =+C33/C35 -> 0.66666667 | D37: =+D33/D35 -> 0.69230769 | E37: =+E33/E35 -> 0.6969697 | G37: =+G33/G35 -> 0.59701493 | H37: =+H33/H35 -> 0.46153846 | I37: =G37+H37 -> 1.0585534 | K37: =K31+K33 -> 6716 | L37: סה״כ RD
B39: מפעל מועדף - תנאים | C39: 0.16
B40: מפעל תעשייתי - בית תכנה נחשב מפעל תעשייתי
B41: מפעל בר תחרות - רוב ההכנסות נובעות מייצוא
C44: 3.597 | D44: 3.5643 | E44: 3.4367 | G44: 3.5882
B45: R&D Expenses test (7%/75M NIS) | C45: 2018 | D45: 2019 | E45: 2020 | G45: 2021 - ytd 9.21 | H45: Oct-Dec 2021 estimeted | I45: Total 2021
B46: Revenues | D46: =D13*D44 -> 3088947.1 | E46: =E13*3.4367 -> 51950511 | G46: =G13*3.4367 -> 0 | H46: =17500000*3*G44 -> 188380500 | I46: =G46+H46 -> 188380500
B47: R&D Expenses | C47: =C14*C44 -> 723180.45 | D47: =D14*D44 -> 2469703.5 | E47: =E14*E44 -> 7894866.3 | G47: =G14*G44 -> 0 | H47: =(993000-200000)*3*G44 -> 8536327.8 | I47: =G47+H47 -> 8536327.8
B48: R&D Expenses\Revenues Ratio | D48: =+D47/D46 -> 0.79952921 | E48: =+E47/E46 -> 0.15196898 | G48: =+G47/G46 -> #DIV/0! | H48: =+H47/H46 -> 0.045314286 | I48: =+I47/I46 -> 0.045314286
B49: R&D Expenses\Revenues Ratio - 3Y AVG | E49: =+AVERAGE(C47:E47)/AVERAGE(C46:E46) -> 0.13430062 | G49: =+AVERAGE(D47:G47)/AVERAGE(D46:G46) -> 0.18831162 | H49: =+AVERAGE(E47:H47)/AVERAGE(E46:H46) -> 0.068369013 | I49: =+AVERAGE(G47:I47)/AVERAGE(G46:I46) -> 0.045314286
B50: Missing R&D Expenses to reach the ratio | G50: =0.07*SUM(D46:G46)-SUM(D47:G47) -> -6511807.7 | H50: =0.07*SUM(E46:H46)-SUM(E47:H47) -> 391976.7
J51: =+G50/0.04 -> -1.6279519e+08 | K51: Break even point | L51: Net Income in 2022
K52: Above this point Its better to Increase our R&D Spend to reach the ratio
B53: Investment from VC in USD | C53: 500000 | E53: 5748600
B54: AVERAGE NIS/USD Exchange rate | C54: 3.5949 | D54: 3.5645 | E54: 3.4424 | G54: 3.2549
B55: Investment - 8M NIS investment from VC | C55: =+C53*C54 -> 1797450 | E55: =+E53*E54 -> 19788981
B57: 25% Increase in AVG revenues Yearly | C57: 0 | D57: 0 | E57: =+E46/D46-1 -> 15.818194 | G57: =+G46/E46-1 -> -1
B59: 25% Increase in AVG number of employees + at least 50 employees
B60: Number of employees | C60: 3 | D60: 13 | E60: 33 | G60: 67 | H60: 13 | I60: =G60+H60 -> 80
B61: HC Increase ratio | C61: 0 | D61: =+D60/C60-1 -> 3.3333333 | E61: =+E60/D60-1 -> 1.5384615 | G61: =+G60/E60-1 -> 1.030303 | I61: =G61+H61 -> 1.030303
I62: =G62+H62 -> 0
B63: 20% of the Company's employees expenses listed as R&D or At least 200 Employees | I63: =G63+H63 -> 0
B64: R&D Payroll | C64: =(330825+326191)/C54 -> 182763.36 | D64: =449059+791642/$D$22 -> 671149.62 | E64: 1527152 | G64: 5994309 | I64: =G64+H64 -> 5994309
B65: R&D HC | C65: 2 | D65: 9 | E65: 23 | G65: 40 | H65: 6 | I65: =G65+H65 -> 46
B66: Total Payroll | C66: =+(142534+73203)+C64 -> 398500.36 | D66: =958816+791642/$D$22+358000/$D$22 -> 1281341.5 | E66: 2005609 | G66: 9020947 | I66: =G66+H66 -> 9020947
B67: Total HC | C67: =+C60 -> 3 | D67: =+D60 -> 13 | E67: =+E60 -> 33 | G67: =+G60 -> 67 | H67: 13 | I67: =G67+H67 -> 80
B68: R&D Payroll expenses ratio | C68: =+C64/C66 -> 0.45862784 | D68: =+D64/D66 -> 0.5237867 | E68: =+E64/E66 -> 0.76144054 | G68: =+G64/G66 -> 0.66448778 | I68: =G68+H68 -> 0.66448778
B69: R&D HC ratio | C69: =+C65/C67 -> 0.66666667 | D69: =+D65/D67 -> 0.69230769 | E69: =+E65/E67 -> 0.6969697 | G69: =+G65/G67 -> 0.59701493 | H69: =+H65/H67 -> 0.46153846 | I69: =G69+H69 -> 1.0585534
B71: מפעל מועדף - תנאים | C71: 0.16
B72: מפעל תעשייתי - בית תכנה נחשב מפעל תעשייתי
B73: מפעל בר תחרות - רוב ההכנסות נובעות מייצוא

Sheet R&D 20A
C1: 3 | D1: =+C1+1 -> 4 | E1: =+D1+1 -> 5 | F1: =+E1+1 -> 6 | G1: =+F1+1 -> 7 | H1: =+G1+1 -> 8 | I1: =+H1+1 -> 9
A3: Research and development expenses, net | D3: פריסת הוצאות מו"פ
B4: 2017 | C4: 2018 | D4: 2019 | E4: 2020 | F4: 2021 | G4: 2022 | H4: 2023 | I4: סך הוצאה
A5: 2017 | B5: =I5/3 -> 53630.333 | C5: =B5 -> 53630.333 | D5: =C5 -> 53630.333 | I5: 160891
A6: 2018 | C6: =I6/3 -> 241060.77 | D6: =C6 -> 241060.77 | E6: =D6 -> 241060.77 | I6: 723182.3
A7: 2019 | D7: =+$I$7/3 -> 813428.31 | E7: =+$I$7/3 -> 813428.31 | F7: =+$I$7/3 -> 813428.31 | I7: 2440284.9
A8: 2020 | E8: =+$I$8/3 -> 2085326.3 | F8: =+$I$8/3 -> 2085326.3 | G8: =+$I$8/3 -> 2085326.3 | I8: 6255979
A9: 2021 | F9: =+$I$9/3 -> #N/A | G9: =+$I$9/3 -> #N/A | H9: =+$I$9/3 -> #N/A | I9: =C21 -> #N/A
C16: 44531
A17: RND Expenses Adjustments | C17: ='P&L LTD USD'!J35 -> 70597716
A18: 23012 | B18: הוצאות הפרשה להבראה מופ | C18: =-VLOOKUP(A18,'TB LTD 12.22'!D:F,3,0) -> #N/A
A19: 23011 | B19: הוצאות חופשה מופ | C19: =-VLOOKUP(A19,'TB LTD 12.22'!D:F,3,0) -> #N/A
A20: 23031 | B20: הוצאות אופציות מחקר ופיתוח | C20: =-VLOOKUP(A20,'TB LTD 12.22'!D:F,3,0) -> #N/A
C21: =+SUM(C17:C20) -> #N/A

Sheet COA India
B2: 340000 | C2: HYPAETHRAL MEDIA PVT. LTD. | D2: BS | E2: Trade payables
B3: 340001 | C3: Ranjan Periwal | D3: BS | E3: Trade payables
B4: 35001 | C4: Papayagaming LTD | D4: BS | E4: Related Party India
B5: 36102 | C5: WHT Vendors | D5: BS | E5: Other accounts payable
B6: 83140200 | C6: G&A G&A- Professional Services | D6: PL | E6: General and administrative expenses | F6: Professional Services
B7: 83200401 | C7: G&A - rent | D7: PL | E7: General and administrative expenses | F7: Office exp
B8: 343000 | C8: HYPAETHRAL MEDIA PVT. LTD. | D8: BS | E8: Trade payables
B9: 343001 | C9: Ranjan Periwal | D9: BS | E9: Trade payables
B10: 35001 | C10: Papayagaming LTD | D10: BS | E10: Related Party India
B11: 14000 | C11: Prepaid Expenses | D11: BS | E11: Other accounts receivable
B12: 90201104 | C12: Financial exp - Currency difference | D12: PL | E12: Financial expenses, net | F12: Financial expenses
B13: 82110200 | C13: S&M Marketing- Professional Services | D13: PL | E13: Marketing expenses | F13: Professional Services
B14: 35002 | C14: Papayagaming LTD ($) D/C | D14: BS | E14: Related Party India
B15: 37101 | C15: Accrued Expenses | D15: BS | E15: Other accounts payable
B16: 83120201 | C16: G&A Finance- Audit | D16: PL | E16: General and administrative expenses | F16: Professional Services

Sheet BS India
A2: Papaya gaming India
C8: 2022 | D8: JE | E8: 2022
C9: India | E9: India
C10: USD | E10: USD
B11: CURRENT ASSETS
B13: Other accounts receivable | C13: =SUMIF('TB India 12.22'!I:I,B13,'TB India 12.22'!G:G) -> 142.43 | E13: =C13+D13 -> 142.43
C14: =SUM(C13:C13) -> 142.43 | E14: =SUM(E13:E13) -> 142.43
B16: Total Assets | C16: =+C14 -> 142.43 | E16: =+E14 -> 142.43
D17: \
B18: CURRENT LIABILITIES
B20: Related Party India | C20: =SUMIF('TB India 12.22'!I:I,B20,'TB India 12.22'!G:G) -> -29383.12 | E20: =C20+D20 -> -29383.12
B21: Other accounts payable | C21: =SUMIF('TB India 12.22'!I:I,B21,'TB India 12.22'!G:G) -> -22095.35 | E21: =C21+D21 -> -22095.35
C22: =SUM(C20:C21) -> -51478.47 | E22: =SUM(E20:E21) -> -51478.47
B24: Total libiliaties | C24: =+C22 -> -51478.47 | E24: =+E22 -> -51478.47
B26: SHAREHOLDERS' EQUITY
B28: PL | C28: ='P&L India'!D28 -> 51336.04 | E28: =C28+D28 -> 51336.04
C29: =SUM(C28:C28) -> 51336.04 | E29: =SUM(E28:E28) -> 51336.04
C31: =C29+C24 -> -142.43 | E31: =E29+E24 -> -142.43
C32: =+C31=-C16 -> TRUE | E32: =+E31=-E16 -> TRUE
C33: =+C31+C16 -> -2.8421709e-13 | E33: =+E31+E16 -> -2.8421709e-13

Sheet P&L India
A2: Papaya gaming India
D8: 2022 | E8: JE | F8: 2022
D9: India | F9: India
B11: Revenues | C11: Revenue | D11: =SUMIFS('TB India 12.22'!G:G,'TB India 12.22'!I:I,$B11,'TB India 12.22'!J:J,$C11) -> 0 | F11: =D11+E11 -> 0
C12: Gross profit | D12: =D11 -> 0 | F12: =F11 -> 0
C14: Marketing expenses | D14: =SUM(D15:D15) -> 30322.73 | F14: =SUM(F15:F15) -> 30322.73
A15: Overheads | B15: Marketing expenses | C15: Professional Services | D15: =SUMIFS('TB India 12.22'!G:G,'TB India 12.22'!I:I,$B15,'TB India 12.22'!J:J,$C15) -> 30322.73 | F15: =D15+E15 -> 30322.73
C17: General and administrative expenses | D17: =SUM(D18:D19) -> 20751.2 | F17: =SUM(F18:F19) -> 20751.2
A18: Overheads | B18: General and administrative expenses | C18: Professional Services | D18: =SUMIFS('TB India 12.22'!G:G,'TB India 12.22'!I:I,$B18,'TB India 12.22'!J:J,$C18) -> 20000 | F18: =D18+E18 -> 20000
A19: Overheads | B19: General and administrative expenses | C19: Office exp | D19: =SUMIFS('TB India 12.22'!G:G,'TB India 12.22'!I:I,$B19,'TB India 12.22'!J:J,$C19) -> 751.2 | F19: =D19+E19 -> 751.2
B20: TP Expenses | C20: TP Expenses | D20: =SUMIFS('TB India 12.22'!G:G,'TB India 12.22'!I:I,$B20,'TB India 12.22'!J:J,$C20) -> 0 | F20: =D20+E20 -> 0
C21: Operating expenses | D21: =D17+D14+D20 -> 51073.93 | F21: =F17+F14+F20 -> 51073.93
C23: Operating profit | D23: =D21+D12 -> 51073.93 | F23: =F21+F12 -> 51073.93
C25: Financial expenses, net | D25: =SUM(D26:D26) -> 262.11 | F25: =SUM(F26:F26) -> 262.11
A26: Financial expenses | B26: Financial expenses, net | C26: Financial expenses | D26: =SUMIFS('TB India 12.22'!G:G,'TB India 12.22'!I:I,$B26,'TB India 12.22'!J:J,$C26) -> 262.11 | F26: =D26+E26 -> 262.11
C28: Net loss ( profit ) | D28: =+D23+D25 -> 51336.04 | F28: =+F23+F25 -> 51336.04

Sheet TB India 12.22
A1: כותרת ראשית; | B1: כותרת משנה; | C1: סעיף; | D1: חשבון | E1: תאור החשבון | F1: יתרה ברופיה הודית | G1: יתרה בדולרים | H1: סוג דוח | I1: מחלקה | J1: תת מחלקה
A2: Assets.1** | B2: Prepaid Expenses.14* | C2: Prepaid Expenses.140 | D2: 14000 | E2: Prepaid Expenses | F2: 11800 | G2: 142.43 | H2: =VLOOKUP(D2,'COA India'!B:E,3,0) -> BS | I2: =VLOOKUP(D2,'COA India'!B:E,4,0) -> Other accounts receivable | J2: =VLOOKUP(D2,'COA India'!B:F,5,0) -> 0
A3: Liabilities.3** | B3: Related party payable.35* | C3: IC payable.350 | D3: 35002 | E3: Papayagaming LTD ($) D/C | F3: -2433088.2 | G3: -29383.12 | H3: =VLOOKUP(D3,'COA India'!B:E,3,0) -> BS | I3: =VLOOKUP(D3,'COA India'!B:E,4,0) -> Related Party India | J3: =VLOOKUP(D3,'COA India'!B:F,5,0) -> 0
A4: Liabilities.3** | B4: Other payables and accouted liabilittis.36* | C4: Other payables.361 | D4: 36102 | E4: WHT Vendors | F4: -200000 | G4: -2414 | H4: =VLOOKUP(D4,'COA India'!B:E,3,0) -> BS | I4: =VLOOKUP(D4,'COA India'!B:E,4,0) -> Other accounts payable | J4: =VLOOKUP(D4,'COA India'!B:F,5,0) -> 0
A5: Liabilities.3** | B5: Accrued Expenses.37* | C5: Accrued Expenses.371 | D5: 37101 | E5: Accrued Expenses | F5: -1630600 | G5: -19681.35 | H5: =VLOOKUP(D5,'COA India'!B:E,3,0) -> BS | I5: =VLOOKUP(D5,'COA India'!B:E,4,0) -> Other accounts payable | J5: =VLOOKUP(D5,'COA India'!B:F,5,0) -> 0
A6: Department.8** | B6: S&M.82* | C6: S&M Professional Services.82B | D6: 82110200 | E6: S&M Marketing- Professional Services | F6: 2360000 | G6: 30322.73 | H6: =VLOOKUP(D6,'COA India'!B:E,3,0) -> PL | I6: =VLOOKUP(D6,'COA India'!B:E,4,0) -> Marketing expenses | J6: =VLOOKUP(D6,'COA India'!B:F,5,0) -> Professional Services
A7: Department.8** | B7: G&A.83* | C7: G&A Professional Services.83B | D7: 83120201 | E7: G&A Finance- Audit | F7: 1630600 | G7: 20000 | H7: =VLOOKUP(D7,'COA India'!B:E,3,0) -> PL | I7: =VLOOKUP(D7,'COA India'!B:E,4,0) -> General and administrative expenses | J7: =VLOOKUP(D7,'COA India'!B:F,5,0) -> Professional Services
A8: Department.8** | B8: G&A.83* | C8: G&A Building.83D | D8: 83200401 | E8: G&A - rent | F8: 59000 | G8: 751.2 | H8: =VLOOKUP(D8,'COA India'!B:E,3,0) -> PL | I8: =VLOOKUP(D8,'COA India'!B:E,4,0) -> General and administrative expenses | J8: =VLOOKUP(D8,'COA India'!B:F,5,0) -> Office exp
A9: Financial Expenses.9** | B9: Financial Expenses.90* | C9: Financial exp.90K | D9: 90201104 | E9: Financial exp - Currency difference | F9: 202288.19 | G9: 262.11 | H9: =VLOOKUP(D9,'COA India'!B:E,3,0) -> PL | I9: =VLOOKUP(D9,'COA India'!B:E,4,0) -> Financial expenses, net | J9: =VLOOKUP(D9,'COA India'!B:F,5,0) -> Financial expenses

Sheet CF FS
A1: 44926
A2: Cash Flow
A3: Papaya Gaming Ltd
A4: USD
B7: Consolidated staements of cash flows 31/12/2022
B9: Operating activities | C9: USD | D9: USD in thousands
B10: Net Profit | C10: ='CF WP'!C41 -> 22353748 | D10: ='CF WP'!D41 -> 22354
B12: Depreciation | C12: ='CF WP'!C44 -> 215126.76 | D12: ='CF WP'!D44 -> 215
B13: Share based compensation | C13: ='CF WP'!C45 -> 185110.54 | D13: ='CF WP'!D45 -> 185
B14: Deffered tax liabilities | C14: ='CF WP'!C46 -> -1338238 | D14: ='CF WP'!D46 -> -1338
B15: Financial expenses (Fx) | C15: ='CF WP'!C47 -> 731369.94 | D15: ='CF WP'!D47 -> 731
B16: Changes in operating assets and liabilities:
B17: ='CF WP'!B48 -> Prepaid expenses and other current assets | C17: ='CF WP'!C48 -> -2188067.3 | D17: ='CF WP'!D48 -> -2188
B18: ='CF WP'!B49 -> Account receivable | C18: ='CF WP'!C49 -> -1472342.3 | D18: ='CF WP'!D49 -> -1472
B19: ='CF WP'!B50 -> Trade payables change | C19: ='CF WP'!C50 -> -4629842.7 | D19: ='CF WP'!D50 -> -4630
B20: ='CF WP'!B51 -> Other accounts payable and accrued expenses | C20: ='CF WP'!C51 -> 17074813 | D20: ='CF WP'!D51 -> 17075
B21: ='CF WP'!B52 -> Reserve - Wordpay | C21: ='CF WP'!C52 -> 199999 | D21: ='CF WP'!D52 -> 200
B22: ='CF WP'!B53 -> Contract liability change | C22: ='CF WP'!C53 -> 4931358.5 | D22: ='CF WP'!D53 -> 4931
B23: ='CF WP'!B54 -> Receivables for shares issued | C23: ='CF WP'!C54 -> 0 | D23: ='CF WP'!D54 -> 0
B24: ='CF WP'!B55 -> Operating lease ROU assets and liabilities, net | C24: ='CF WP'!C55 -> -19203588 | D24: ='CF WP'!D55 -> -19204
B26: ='CF WP'!B56 -> Interest received | C26: ='CF WP'!C56 -> 0 | D26: ='CF WP'!D56 -> 0
C27: ='CF WP'!C57 -> -5494300.9 | D27: ='CF WP'!D57 -> -5494
B29: Net cash provieded by (used in) operating activities | C29: ='CF WP'!C59 -> 16859447 | D29: ='CF WP'!D59 -> 16859
B31: Investing activities | C31: ='CF WP'!C61 -> 0 | D31: ='CF WP'!D61 -> 0
B32: Purchase of property and equipment | C32: ='CF WP'!C62 -> -1372173.1 | D32: ='CF WP'!D62 -> -1372
B33: Restricted LT deposit | C33: ='CF WP'!C63 -> -3667205.5 | D33: ='CF WP'!D63 -> -3667
B34: Shareholders | C34: ='CF WP'!C64 -> -500000 | D34: ='CF WP'!D64 -> -500
C35: ='CF WP'!C66 -> -5539378.6 | D35: ='CF WP'!D66 -> -5539
B37: Financing activities
B40: Options exercised | C40: ='CF WP'!C69 -> 18743.53 | D40: ='CF WP'!D69 -> 19
B41: Repayment of long term loan | C41: ='CF WP'!C70 -> -2566666.7 | D41: ='CF WP'!D70 -> -2567
C42: ='CF WP'!C71 -> -2547923.2 | D42: =SUM(D38:D41) -> -2548
B45: Cash Change | C45: ='CF WP'!C74 -> 8772145.6 | D45: ='CF WP'!D74 -> 8772
B46: Cash FX Change | C46: ='CF WP'!C75 -> -902714.25 | D46: ='CF WP'!D75 -> -903
B47: Cash O.B | C47: ='CF WP'!C76 -> 48531569 | D47: ='CF WP'!D76 -> 48532
B48: Cash C.B | C48: ='CF WP'!C77 -> 56401001 | D48: ='CF WP'!D77 -> 56401
B50: Check | C50: ='CF WP'!C79 -> -22067185 | D50: ='CF WP'!C79/1000 -> -22067.185
B52: ='CF WP'!B81 -> Shareholders loan | D52: ='CF WP'!C81/1000 -> 0
B53: ='CF WP'!B82 -> Interest Paid | D53: ='CF WP'!C82/1000 -> -115.34195
B54: ='CF WP'!B83 -> ASC842 Adoption | D54: ='CF WP'!C83/1000 -> 19064.116
B55: ='CF WP'!B84 -> Tax Paid | D55: ='CF WP'!C84/1000 -> -6382.8062

Sheet CF WP
A1: 44926
A2: Cash Flow
A3: Papaya Gaming Ltd
A4: USD
B5: Consolidated staements of cash flows
D6: $
A7: Ref | D7: 44561 | E7: Profit | F7: Operating activities | G7: Investing activities | H7: Financing activities | I7: Transfers | J7: Cash Change | K7: FX change | L7: 44926 | M7: Check
B8: Assets
B9: Cash | D9: 48531569 | J9: =L9-D9-K9 -> 30839330 | K9: =-C152-C155-C161-C166 -> -902714.25 | L9: ='BS USD CONS '!K8+'BS USD CONS '!K12 -> 78468185 | M9: =SUM(D9:K9)-L9 -> 0
B10: Account receivable | D10: 1196011.9 | F10: =L10-D10-K10 -> 1472342.3 | K10: =-C151 -> -115.58 | L10: ='BS USD CONS '!K9 -> 2668238.6 | M10: =SUM(D10:K10)-L10 -> 0
B11: Prepaid expenses and other current assets | D11: 2484721.1 | F11: =L11-D11-K11 -> 2188067.3 | K11: =-C159 -> -382951.06 | L11: ='BS USD CONS '!K14+'BS USD CONS '!K15 -> 4289837.3 | M11: =SUM(D11:K11)-L11 -> 0
B12: Related Party | D12: 0 | L12: ='BS USD CONS '!K10+'BS USD CONS '!K11 -> -0.25 | M12: =SUM(D12:K12)-L12 -> 0.25
A13: 8 | B13: ROA Assets | D13: 409121.67 | F13: =L13-I13-D13 -> 713029.57 | I13: 19064116 | L13: ='BS USD CONS '!K21 -> 20186267 | M13: =SUM(D13:K13)-L13 -> 0
A14: 1 | B14: Fixed assets, net | D14: 501895.3 | F14: =+D93-K14 -> -215126.76 | G14: =+D91 -> 1372173.1 | K14: =-C156 -> 133.27 | L14: ='BS USD CONS '!K25 -> 1659074.9 | M14: =SUM(D14:K14)-L14 -> 3.4924597e-09
B15: Deferred tax assets | D15: 939408.95 | F15: =L15-D15-K15 -> 1338238 | K15: =-C154 -> -247417.61 | L15: ='BS USD CONS '!K23 -> 2030229.3 | M15: =SUM(D15:K15)-L15 -> 0
B16: Restricted LT deposit | D16: 0 | G16: =L16-D16 -> 3667205.5 | L16: ='BS USD CONS '!K22 -> 3667205.5 | M16: =SUM(D16:K16)-L16 -> 0
B17: Reserve - Wordpay | D17: 199999 | F17: =L17-D17 -> -199999 | L17: ='BS USD CONS '!K24 -> 0 | M17: =SUM(D17:K17)-L17 -> 0
B19: Liabilities and Shareholders equity | D19: 54262727 | L19: =SUM(L9:L17) -> 1.1296904e+08
B20: Trade payables | D20: -13433835 | F20: =L20-D20-K20-I20 -> 4629842.7 | K20: =-C160 -> 51842.58 | L20: ='BS USD CONS '!K33 -> -8752149.4 | M20: =SUM(D20:K20)-L20 -> 0
B21: Other accounts payable and accrued expenses | D21: =-20587203.3903504-D22 -> -18990237 | F21: =L21-D21-K21-I21 -> -17074813 | K21: =-C157 -> 505541.3 | L21: ='BS USD CONS '!K34+'BS USD CONS '!K44+'BS USD CONS '!K41+'BS USD CONS '!K37 -> -35559508 | M21: =SUM(D21:K21)-L21 -> 0
B22: Warrant Liability | D22: -1596966.8 | K22: =-C158 -> 185609 | L22: ='BS USD CONS '!K38 -> -1411357.4 | M22: =SUM(D22:K22)-L22 -> -0.39
A23: 8 | B23: ROA Liability | D23: -385359.69 | F23: =L23-I23-D23 -> 18490559 | I23: =-I13 -> -19064116 | L23: ='BS USD CONS '!K39 -> -958916.79 | M23: =SUM(D23:K23)-L23 -> 0
B24: Contract liability | D24: -4087657 | F24: =L24-D24-K24 -> -4931358.5 | K24: =-C153 -> 58702.41 | L24: ='BS USD CONS '!K36 -> -8960313.1 | M24: =SUM(D24:K24)-L24 -> 0
A25: 2 | B25: Loan-Short term | D25: -2033334 | H25: =D103 -> 2033334 | L25: 0 | M25: =SUM(D25:K25)-L25 -> 0
A26: 3 | B26: Loan-Long term | D26: -533332.72 | H26: =D114 -> 533332.72 | L26: 0 | M26: =SUM(D26:K26)-L26 -> 0
B27: Shareholders | D27: -500000 | G27: =L27-D27-K27-H27 -> 500000 | L27: 0 | M27: =SUM(D27:K27)-L27 -> 0
A28: =A136 -> 6 | B28: Share capital - Ordinary Shares | D28: -418.92 | H28: =L28-D28-K28 -> -271.3 | L28: ='BS USD CONS '!K52 -> -690.22 | M28: =SUM(D28:K28)-L28 -> 0
B29: Share capital - Preferred Seed-1 | D29: -191 | L29: ='BS USD CONS '!K53 -> -191 | M29: =SUM(D29:K29)-L29 -> 0
B30: Share capital - Preferred Seed | D30: -49.24 | L30: ='BS USD CONS '!K54 -> -49.24 | M30: =SUM(D30:K30)-L30 -> 0
A31: =A122 -> 5 | B31: Share premium | D31: -8614908.1 | F31: =C127+C126 -> -185110.54 | H31: =C128 -> -18472.23 | L31: ='BS USD CONS '!K55 -> -8818490.6 | M31: =SUM(D31:K31)-L31 -> -0.3084867
B32: Receivables for shares issued | D32: 0 | L32: ='BS USD CONS '!K56 -> 0 | M32: =SUM(D32:K32)-L32 -> 0
B33: Accumulated deficit | D33: -4086439.6 | L33: ='BS USD CONS '!K57 -> -4082936.6 | M33: =SUM(D33:K33)-L33 -> -3503.0106
B34: PL | E34: =L34-K34 -> -22353748 | L34: ='BS USD CONS '!K58 -> -22353748 | M34: =SUM(D34:K34)-L34 -> 0
D36: -54262728 | E36: =SUM(E9:E35) -> -22353748 | F36: =SUM(F9:F35) -> 6225670.8 | G36: =SUM(G9:G35) -> 5539378.6 | H36: =SUM(H9:H35) -> 2547923.2 | I36: =SUM(I9:I35) -> 0 | J36: =SUM(J9:J35) -> 30839330 | K36: =SUM(K9:K35) -> -731369.94 | L36: =SUM(L20:L35) -> -90898351 | M36: =SUM(E36:K36) -> 22067185
D37: =+D36+D19 -> -1.21 | L37: =+L36+L19 -> 22070687
B38: Consolidated staements of cash flows 31/12/2022 | F38: =F36+C57+K36 -> 0 | G38: =G36+C66 -> 0 | H38: =H36+C71 -> 0
B40: Operating activities | G40: =D34+D33 -> -4086439.6
B41: Net Profit | C41: =-E34 -> 22353748 | D41: =+ROUND(C41/1000,0) -> 22354
A44: התאמה בגין הוצאות שלא במזומן | B44: Depreciation | C44: =-F14 -> 215126.76 | D44: =+ROUND(C44/1000,0) -> 215
A45: התאמה בגין הוצאות שלא במזומן | B45: Share based compensation | C45: =-SUM(C126:C127) -> 185110.54 | D45: =+ROUND(C45/1000,0) -> 185
A46: התאמה בגין הוצאות שלא במזומן | B46: Deffered tax liabilities | C46: =-F15 -> -1338238 | D46: =+ROUND(C46/1000,0) -> -1338 | F46: =SUM(F20:F21)/F36 -> -1.9989766
B47: Financial expenses (Fx) | C47: =-K36 -> 731369.94 | D47: =+ROUND(C47/1000,0) -> 731
B48: =B11 -> Prepaid expenses and other current assets | C48: =-F11 -> -2188067.3 | D48: =+ROUND(C48/1000,0) -> -2188
B49: =B10 -> Account receivable | C49: =-F10 -> -1472342.3 | D49: =+ROUND(C49/1000,0) -> -1472
B50: Trade payables change | C50: =-F20 -> -4629842.7 | D50: =+ROUND(C50/1000,0) -> -4630
B51: =B21 -> Other accounts payable and accrued expenses | C51: =-F21 -> 17074813 | D51: =+ROUND(C51/1000,0) -> 17075
B52: Reserve - Wordpay | C52: =-F17 -> 199999 | D52: =+ROUND(C52/1000,0) -> 200
B53: Contract liability change | C53: =-F24 -> 4931358.5 | D53: =+ROUND(C53/1000,0) -> 4931
B54: =B32 -> Receivables for shares issued | C54: =-F32 -> 0 | D54: =+ROUND(C54/1000,0) -> 0
B55: Operating lease ROU assets and liabilities, net | C55: =-F13-F23 -> -19203588 | D55: =+ROUND(C55/1000,0) -> -19204
B56: Interest received
C57: =SUM(C43:C56) -> -5494300.9 | D57: =+ROUND(C57/1000,0) -> -5494
B59: Net cash provieded by (used in) operating activities | C59: =C57+C41 -> 16859447 | D59: =+ROUND(C59/1000,0) -> 16859
B61: Investing activities
B62: Purchase of property and equipment | C62: =-G14 -> -1372173.1 | D62: =+ROUND(C62/1000,0) -> -1372
B63: Restricted LT deposit | C63: =-G16 -> -3667205.5 | D63: =+ROUND(C63/1000,0) -> -3667
B64: Shareholders | C64: =-G27 -> -500000 | D64: =+ROUND(C64/1000,0) -> -500
C66: =SUM(C62:C65) -> -5539378.6 | D66: =+ROUND(C66/1000,0) -> -5539
B67: Financing activities
B68: Proceeds from issuance of Ordinary Shares | D68: =+ROUND(C68/1000,0) -> 0
B69: =B128 -> Options exercised | C69: =-C139-C128 -> 18743.53 | D69: =+ROUND(C69/1000,0) -> 19
B70: Repayment of long term loan | C70: =-H26-H25 -> -2566666.7 | D70: =+ROUND(C70/1000,0) -> -2567
C71: =+SUM(C68:C70) -> -2547923.2 | D71: =+ROUND(C71/1000,0) -> -2548
B74: Cash Change | C74: =C66+C59+C71 -> 8772145.6 | D74: =+ROUND(C74/1000,0) -> 8772
B75: Cash FX Change | C75: =K9 -> -902714.25 | D75: =+ROUND(C75/1000,0) -> -903
B76: Cash O.B | C76: =D9 -> 48531569 | D76: =+ROUND(C76/1000,0) -> 48532
B77: Cash C.B | C77: =SUM(C74:C76) -> 56401001 | D77: =+ROUND(C77/1000,0) -> 56401
B79: Check | C79: =C77-L9 -> -22067185
B81: Shareholders loan | C81: =I20 -> 0 | D81: =C81/1000 -> 0
B82: Interest Paid | C82: ='P&L LTD USD'!D114 -> -115341.95 | D82: =C82/1000 -> -115.34195
B83: ASC842 Adoption | C83: =I13 -> 19064116 | D83: =C83/1000 -> 19064.116
B84: Tax Paid | C84: =SUM('TB LTD 12.22'!G38:G42) -> -6382806.2 | D84: =C84/1000 -> -6382.8062
B86: Notes:
A88: =A14 -> 1 | B88: FA. Roll Froward
C90: O.B | D90: =+D14 -> 501895.3
C91: Purchases | D91: =1371233.290241--939.802894705208 -> 1372173.1
C92: Disposals | D92: 0
C93: Depreciation | D93: -214993.49 | F93: -460.5617
C96: C.B | D96: =SUM(D90:D95) -> 1659074.9
C97: Check | D97: =+D96-L14 -> 3.7252903e-09
A99: =A25 -> 2 | B99: Short-Term Loan Roll Froward
C101: O.B | D101: =D25 -> -2033334
C102: Additional loan
C103: Payments | D103: =-D101 -> 2033334
C104: Interest (Accrual)
C107: C.B | D107: =SUM(D101:D106) -> 0
C108: Check | D108: =D107-L25 -> 0
A110: =A26 -> 3 | B110: Long-Term Loan Roll Froward
C112: O.B | D112: =D26 -> -533332.72
C113: Additional loan | D113: 0
C114: Payments | D114: =-D112 -> 533332.72
C115: FX | D115: 0
C118: C.B | D118: =SUM(D112:D117) -> 0
C119: Check | D119: =D118-L26 -> 0
A122: 5 | B122: Additional paid in capital Roll Forward
B124: O.B | C124: =D31 -> -8614908.1
B126: SBC Employees 2022 | C126: =-SUMIF('TB LTD 12.22'!$J:$J,"option expenses ",'TB LTD 12.22'!$G:$G)-'P&L LTD USD'!E16-'P&L LTD USD'!E39-'P&L LTD USD'!E63-'P&L LTD USD'!E86 -> -185110.54 | F126: 18472.23
B127: SBC Non Employees 2022
B128: Options exercised | C128: -18472.23
B133: C.B | C133: =SUM(C124:C131) -> -8818490.9
...

Sheet Changes in equity
A1: 44926
A2: Changes ion equity
A3: Papaya Gaming Ltd
A4: USD | B4: USD
C5: Preferred shares | E5: Ordinary Shares
C6: Number of shares | D6: Amount | E6: Number of shares | F6: Amount | G6: Additional paid- in capital | H6: Receivables on account of shares | I6: Accumulated deficit | J6: Total
B8: Balance as of December 31, 2021 | C8: 40926000 | D8: 120 | E8: 65488458 | F8: 157 | G8: =8615.0671284867-F8-D8 -> 8338.0671 | H8: 0 | I8: 4086.4747 | J8: 12701.542
B9: Issuance of Ordinary shares upon exerise of options | E9: 32812 | G9: =-'CF WP'!C128/1000 -> 18.47223 | J9: =SUM(G9:I9) -> 18.47223
B10: Stock base compensation | G10: =-('CF WP'!C126+'CF WP'!C127)/1000 -> 185.11054 | J10: =SUM(G10:I10) -> 185.11054
B11: Adjustment | H11: =-H8 -> 0 | J11: =SUM(G11:I11) -> 0
B12: Net Profit | I12: =-'P&L USD CONS'!N33 -> 22366.542 | J12: =SUM(G12:I12) -> 22366.542
B13: Balance as of December 31, 2022 | C13: =SUM(C8:C12) -> 40926000 | D13: =SUM(D8:D12) -> 120 | E13: =SUM(E8:E12) -> 65521270 | F13: =SUM(F8:F12) -> 157 | G13: =SUM(G8:G12) -> 8541.6499 | H13: =SUM(H8:H12) -> 0 | I13: =SUM(I8:I12) -> 26453.016 | J13: =SUM(G13:I13)+F13+D13 -> 35271.666 | K13: =SUM(J8:J12)-J13 -> 0
D14: * | F14: * | G14: =-'BS USD CONS '!M55-F13-D13 -> 8541.4906
G15: =G13-G14 -> 0.15930849
B22: ILS
C23: Preferred shares | E23: Ordinary Shares
C24: Number of shares | D24: Amount | E24: Number of shares | F24: Amount | G24: Additional paid- in capital | H24: Receivables on account of shares | I24: Accumulated deficit | J24: Total
B26: Balance as of December 31, 2021 | C26: 40926000 | D26: 409 | E26: 65488458 | F26: 605 | G26: =29146.2402057101-1013 -> 28133.24 | H26: 0 | I26: 9699.5922 | J26: 38845.832
B27: Issuance of Ordinary shares upon exerise of options | E27: =E9 -> 32812 | G27: =59499.05/1000 -> 59.49905 | J27: =SUM(G27:I27) -> 59.49905
B28: Stock base compensation | G28: =('P&L LTD USD'!L16+'P&L LTD USD'!L39+'P&L LTD USD'!L63+'P&L LTD USD'!L86)/1000 -> 581.95503 | J28: =SUM(G28:I28) -> 581.95503
B29: Adjustment | H29: =-H26 -> 0 | J29: =SUM(G29:I29) -> 0
B30: Net Profit | I30: =-'BS LTD USD '!K60/1000 -> 83994.361 | J30: =SUM(G30:I30) -> 83994.361
B31: Balance as of December 31, 2022 | C31: =SUM(C26:C30) -> 40926000 | D31: =SUM(D26:D30) -> 409 | E31: =SUM(E26:E30) -> 65521270 | F31: =SUM(F26:F30) -> 605 | G31: =SUM(G26:G30) -> 28774.694 | H31: 0 | I31: =SUM(I26:I30) -> 93693.953 | J31: =SUM(F31:I31)+D31 -> 123482.65
D32: * | F32: * | G32: =-('BS LTD USD '!K57)/1000-F31-D31 -> 28773.74 | H32: =-'BS LTD USD '!L57/1000 -> -0.0033778729 | J32: =SUM(J26:J30)-J31 -> -1
G33: =G31-G32 -> 0.95430571 | H33: =H31-H32 -> 0.0033778729
C34: =C26/500 -> 81852

Sheet Tech Plant Check ILS
C1: 2018 | D1: 2019 | E1: 2020 | G1: 2021
B2: Opening Balance | D2: =+C5 -> 299492.06 | E2: =+D5 -> 1188415 | G2: =+E5 -> 2792020
B3: Expected Loss (Revenue) | E3: =2173604.92192246-570000 -> 1603604.9 | G3: =-4850953*4 -> -19403812
B4: Carryforward losses | C4: =1076644/3.5949 -> 299492.06 | D4: =3168566/3.5645 -> 888922.99
B5: Ending Balance | C5: =+SUM(C2:C4) -> 299492.06 | D5: =+SUM(D2:D4) -> 1188415 | E5: =+SUM(E2:E4) -> 2792020 | G5: =+SUM(G2:G4) -> -16611792
B10: Requirements
B12: R&D Expenses test (7%/75M NIS) | C12: 2018 | D12: 2019 | E12: 2020 | F12: 2021
B13: Revenues | C13: 0 | D13: 3088948 | E13: 38427000 | F13: =-'P&L LTD USD'!L10 -> 1.1297934e+09 | K13: missing
B14: R&D Expenses | C14: 723182 | D14: 2469703 | E14: 7715000 | F14: ='P&L LTD USD'!L35 -> 70597716 | J14: =I13*0.07 -> 0 | K14: =J14-I14 -> 0
B15: R&D Expenses\Revenues Ratio | D15: =+D14/D13 -> 0.79952884 | E15: =+E14/E13 -> 0.20077029 | F15: =+F14/F13 -> 0.06248728
B16: R&D Expenses\Revenues Ratio - 3Y AVG | E16: =+AVERAGE(C14:E14)/AVERAGE(C13:E13) -> 0.26273963 | F16: =+AVERAGE(C14:E14)/AVERAGE(C13:E13) -> 0.26273963 | K16: =J14/I13 -> #DIV/0!
B17: 3 years revenues | F17: =AVERAGE(C13:E13)*0.07 -> 968705.45 | G17: =AVERAGE(F13)*0.07 -> 79085538
B18: 3 years rnd expenses | F18: =AVERAGE(C14:E14) -> 3635961.7 | G18: =AVERAGE(F14) -> 70597716 | J18: =+G18/0.04 -> 1.7649429e+09 | K18: Break even point | L18: Net Income in 2022
B19: rate | F19: =F17-F18 -> -2667256.2 | G19: =G17-G18 -> 8487821.8 | H19: =G19 -> 8487821.8 | I19: missing exp | K19: Above this point Its better to Increase our R&D Spend to reach the ratio
B22: Investment from VC in USD | C22: 500000 | E22: 5748600
B23: AVERAGE NIS/USD Exchange rate | C23: 3.5949 | D23: 3.5645 | E23: 3.4424 | G23: 3.2549
B24: Investment - 8M NIS investment from VC | C24: =+C22*C23 -> 1797450 | E24: =+E22*E23 -> 19788981
K25: 993 | L25: ספטמבר R&D
B26: 25% Increase in AVG revenues Yearly | C26: 0 | D26: 0 | E26: =+E13/D13-1 -> 11.440158 | K26: -181 | L26: founder Bonus
K27: =-(150+86)/3.25 -> -72.615385 | L27: Emp Bonus
B28: 25% Increase in AVG number of employees + at least 50 employees
B29: Number of employees | C29: 3 | D29: 13 | E29: 33 | G29: 67 | H29: 13 | I29: =G29+H29 -> 80 | K29: =K25+K26+K27 -> 739.38462
B30: HC Increase ratio | C30: 0 | D30: =+D29/C29-1 -> 3.3333333 | E30: =+E29/D29-1 -> 1.5384615 | G30: =+G29/E29-1 -> 1.030303 | I30: =G30+H30 -> 1.030303
I31: =G31+H31 -> 0 | L31: רועי
B32: 20% of the Company's employees expenses listed as R&D or At least 200 Employees | I32: =G32+H32 -> 0 | K32: 3461 | L32: יולי V2
B33: R&D Payroll | C33: =(330825+326191)/C23 -> 182763.36 | D33: =449059+791642/$D$23 -> 671149.62 | E33: 1527152 | G33: 5994309 | I33: =G33+H33 -> 5994309
B34: R&D HC | C34: 2 | D34: 9 | E34: 23 | G34: 40 | H34: 6 | I34: =G34+H34 -> 46 | K34: =651*5 -> 3255 | L34: הערכה
B35: Total Payroll | C35: =+(142534+73203)+C33 -> 398500.36 | D35: =958816+791642/$D$23+358000/$D$23 -> 1281341.5 | E35: 2005609 | G35: 9020947 | I35: =G35+H35 -> 9020947
B36: Total HC | C36: =+C29 -> 3 | D36: =+D29 -> 13 | E36: =+E29 -> 33 | G36: =+G29 -> 67 | H36: 13 | I36: =G36+H36 -> 80
B37: R&D Payroll expenses ratio | C37: =+C33/C35 -> 0.45862784 | D37: =+D33/D35 -> 0.5237867 | E37: =+E33/E35 -> 0.76144054 | G37: =+G33/G35 -> 0.66448778 | I37: =G37+H37 -> 0.66448778
B38: R&D HC ratio | C38: =+C34/C36 -> 0.66666667 | D38: =+D34/D36 -> 0.69230769 | E38: =+E34/E36 -> 0.6969697 | G38: =+G34/G36 -> 0.59701493 | H38: =+H34/H36 -> 0.46153846 | I38: =G38+H38 -> 1.0585534 | K38: =K32+K34 -> 6716 | L38: סה״כ RD
B40: מפעל מועדף - תנאים | C40: 0.16
B41: מפעל תעשייתי - בית תכנה נחשב מפעל תעשייתי
B42: מפעל בר תחרות - רוב ההכנסות נובעות מייצוא
C45: 3.597 | D45: 3.5643 | E45: 3.4367 | G45: 3.5882
B46: R&D Expenses test (7%/75M NIS) | C46: 2018 | D46: 2019 | E46: 2020 | G46: 2021 - ytd 9.21 | H46: Oct-Dec 2021 estimeted | I46: Total 2021
B47: Revenues | D47: =D13*D45 -> 11009937 | E47: =E13*3.4367 -> 1.3206207e+08 | G47: =G13*3.4367 -> 0 | H47: =17500000*3*G45 -> 188380500 | I47: =G47+H47 -> 188380500
B48: R&D Expenses | C48: =C14*C45 -> 2601285.7 | D48: =D14*D45 -> 8802762.4 | E48: =E14*E45 -> 26514140 | G48: =G14*G45 -> 0 | H48: =(993000-200000)*3*G45 -> 8536327.8 | I48: =G48+H48 -> 8536327.8
B49: R&D Expenses\Revenues Ratio | D49: =+D48/D47 -> 0.79952884 | E49: =+E48/E47 -> 0.20077029 | G49: =+G48/G47 -> #DIV/0! | H49: =+H48/H47 -> 0.045314286 | I49: =+I48/I47 -> 0.045314286
B50: R&D Expenses\Revenues Ratio - 3Y AVG | E50: =+AVERAGE(C48:E48)/AVERAGE(C47:E47) -> 0.1766858 | G50: =+AVERAGE(D48:G48)/AVERAGE(D47:G47) -> 0.24684705 | H50: =+AVERAGE(E48:H48)/AVERAGE(E47:H47) -> 0.10938144 | I50: =+AVERAGE(G48:I48)/AVERAGE(G47:I47) -> 0.045314286
B51: Missing R&D Expenses to reach the ratio | G51: =0.07*SUM(D47:G47)-SUM(D48:G48) -> -25301862 | H51: =0.07*SUM(E47:H47)-SUM(E48:H48) -> -12619488
J52: =+G51/0.04 -> -6.3254656e+08 | K52: Break even point | L52: Net Income in 2022
K53: Above this point Its better to Increase our R&D Spend to reach the ratio
B54: Investment from VC in USD | C54: 500000 | E54: 5748600
B55: AVERAGE NIS/USD Exchange rate | C55: 3.5949 | D55: 3.5645 | E55: 3.4424 | G55: 3.2549
B56: Investment - 8M NIS investment from VC | C56: =+C54*C55 -> 1797450 | E56: =+E54*E55 -> 19788981
B58: 25% Increase in AVG revenues Yearly | C58: 0 | D58: 0 | E58: =+E47/D47-1 -> 10.994807 | G58: =+G47/E47-1 -> -1
B60: 25% Increase in AVG number of employees + at least 50 employees
B61: Number of employees | C61: 3 | D61: 13 | E61: 33 | G61: 67 | H61: 13 | I61: =G61+H61 -> 80
B62: HC Increase ratio | C62: 0 | D62: =+D61/C61-1 -> 3.3333333 | E62: =+E61/D61-1 -> 1.5384615 | G62: =+G61/E61-1 -> 1.030303 | I62: =G62+H62 -> 1.030303
I63: =G63+H63 -> 0
B64: 20% of the Company's employees expenses listed as R&D or At least 200 Employees | I64: =G64+H64 -> 0
B65: R&D Payroll | C65: =(330825+326191)/C55 -> 182763.36 | D65: =449059+791642/$D$23 -> 671149.62 | E65: 1527152 | G65: 5994309 | I65: =G65+H65 -> 5994309
B66: R&D HC | C66: 2 | D66: 9 | E66: 23 | G66: 40 | H66: 6 | I66: =G66+H66 -> 46
B67: Total Payroll | C67: =+(142534+73203)+C65 -> 398500.36 | D67: =958816+791642/$D$23+358000/$D$23 -> 1281341.5 | E67: 2005609 | G67: 9020947 | I67: =G67+H67 -> 9020947
B68: Total HC | C68: =+C61 -> 3 | D68: =+D61 -> 13 | E68: =+E61 -> 33 | G68: =+G61 -> 67 | H68: 13 | I68: =G68+H68 -> 80
B69: R&D Payroll expenses ratio | C69: =+C65/C67 -> 0.45862784 | D69: =+D65/D67 -> 0.5237867 | E69: =+E65/E67 -> 0.76144054 | G69: =+G65/G67 -> 0.66448778 | I69: =G69+H69 -> 0.66448778
B70: R&D HC ratio | C70: =+C66/C68 -> 0.66666667 | D70: =+D66/D68 -> 0.69230769 | E70: =+E66/E68 -> 0.6969697 | G70: =+G66/G68 -> 0.59701493 | H70: =+H66/H68 -> 0.46153846 | I70: =G70+H70 -> 1.0585534
B72: מפעל מועדף - תנאים | C72: 0.16
B73: מפעל תעשייתי - בית תכנה נחשב מפעל תעשייתי
B74: מפעל בר תחרות - רוב ההכנסות נובעות מייצוא
