Workbook
Name ___thinkcellH0YAAAAAAAAAAAAAAbeHRFzlWE2uPyH9A6Q3vA: '[1]Master List technology spli EPC'!$A$94:$H$100
Name ___thinkcellH0YAAAAAAAAAAAAAs6d8nGaIbUK8FJH9dh7DkA: '[1]Master List technology spli EPC'!$A$118:$H$124
Name ___thinkcellhkMAAAAAAAAAAAAA57beSTVytE2I7JqSMJDRqw: '[2]Evaluations master list (order)'!$B$18:$J$29
Name ___thinkcellhkMAAAAAAAAAAAAA7gglqEXtAUuFGRX83IhJHg: '[2]Evaluations master list (order)'!$B$49:$J$60
Name ___thinkcellhkMAAAAAAAAAAAAAA1OlPiG7vUyRVcey.zE4.A: '[2]Order year by technology'!$A$53:$G$60
Name ___thinkcellhkMAAAAAAAAAAAAAE9cDjjT78EGiGoFzh4BoJQ: '[2]Evaluation installation p. year'!$B$18:$J$29
Name ___thinkcellhkMAAAAAAAAAAAAAEmg5knyxEkumYODT3xUZvQ: '[2]Order year by technology'!$A$92:$G$99
Name ___thinkcellhkMAAAAAAAAAAAAAOVPfM9XMWkyNTmxP7c1ogQ: '[2]arab countries market'!$A$19:$H$30
Name ___thinkcellhkMAAAAAAAAAAAAAr5FRo9lrKESOsRa6pwZ6Bg: '[2]arab countries market'!$A$38:$H$49
Name ___thinkcellhkMAAAAAAAAAAAAAzvzDuBaOvUalz8oQYLRn9w: '[2]Order year by technology'!$A$82:$G$89
Name ___thinkcellJ0YAAAAAAAAAAAAAxxe2w0vIYkSwqa8CViiJMQ: '[3]Alignment with E O'!$C$120:$L$123
Name ___thinkcellM0YAAAAAAAAAAAAAGuVyKWbgm0ejNwDEIyQmkA: [4]Mix!#REF!
Name ___thinkcellM0YAAAAAAAAAAAAAYIORGssyX0y.C0TzDAVkSg: '[5]MW CSP market old-new'!$X$28:$AE$39
Name ___thinkcellM0YAAAAAAAABAAAAtU6bd5Iu8kaYiGYthvGSMA: [4]Mix!#REF!
Name ___thinkcellM0YAAAAAAAADAAAATfJU.3Wkd0uyHxwS.whxcg: '[4]Grafics Base'!#REF!
Name ___thinkcellM0YAAAAAAAAEAAAACkePQ7R9WEyWVDXXuP7rxQ: [4]Mix!#REF!
Name ___thinkcellNUMAAAAAAAAAAAAAHgEoWX6oDE6.igFHPsGu1w: '[6]High Growth'!$C$79:$F$85
Name ___thinkcellNUMAAAAAAAAAAAAAIHAYpfVrAUez_kl9E5ssXw: '[6]High Growth'!$C$68:$I$75
Name ___thinkcellNUMAAAAAAAAAAAAAPY1DxDuJ5k.TTl.AC9jLcw: '[6]High Growth'!$I$79:$L$85
Name ___thinkcellNUMAAAAAAAAAAAAAqat2s5B2Vk.JDGESv5MRgg: '[6]High Growth'!$C$78:$L$85
Name ___thinkcellNUMAAAAAAAABAAAAuS77Vn0yBEGHmXJ23nirYg: '[6]High Growth'!$C$68:$I$75
Name ___thinkcellNUMAAAEAAAAGAAAAbzZc6A_Px0ee7cWD5d.4cg: '[7]Overview incentive schemes'!$AD$147:$AG$170
Name ___thinkcellNUMAAAEAAAAGAAAAODW1t7nePUuNNcMPfPA2PA: '[7] TWh targets'!$N$3:$Q$39
Name ___thinkcellNUMAAAEAAAAGAAAAX6Cf49KrXUi..OiyrcHesQ: '[7] TWh targets'!$N$3:$Q$37
Name ___thinkcellNUYAAAAAAAAAAAAA4yIzjySHZkKlh2BSSzfi7g: [8]ER_EVA_ROCE!#REF!
Name ___thinkcellPkYAAAAAAAABAAAACfCgeAUy_0SCaTmpBKZuCA: '[9]Technology Split'!#REF!
Name ___thinkcellw0UAAAAAAAAAAAAA3kbAzw87l0uvbu92dkE79A: '[2]Order year by technology'!$A$92:$E$99
Name ___thinkcellw0UAAAAAAAAAAAAAc8D3Alwu2k2l_67NaHwtMg: '[2]Order year by techn. EPC update'!$A$82:$E$89
Name ___thinkcellykUAAAAAAAABAAAA9r94OUzIGk6hKuNZuf3xQA: [10]Bilder!$B$169:$C$175
Name ___thinkcellykUAAAAAAAABAAAAlK5PatKEZUGah_xHFk7jrQ: [10]Bilder!$D$169:$E$175
Name ___thinkcellykUAAAAAAAABAAAAsYrXHDHqaUqmY0d3tALWZg: [10]Bilder!$F$169:$G$175
Name __DCF1: {"Back Page",#N/A,FALSE,"Front and Back"}
Name __FDS_HYPERLINK_TOGGLE_STATE__: "ON"
Name __q2: {"Total1",#N/A,FALSE,"Total Summary";"Risk1",#N/A,FALSE,"Risks"}
Name _1_???: 0.17
Name _1__xlfn.COUNTIFS: #NAME?
Name _BvA: [11]pswzParams!$J$1
Name _DAT3: '[12]Anl 0.5'!#REF!
Name _DCF1: {"Back Page",#N/A,FALSE,"Front and Back"}
Name _GSRATES_1: "CT300001Latest "
Name _GSRATES_2: "H20070129Latest USDEUR1000001"
Name _GSRATES_3: "H20060711Latest EURUSD1000001"
Name _GSRATES_4: "H20051206Latest USDEUR1000001"
Name _GSRATES_5: "H20060307Latest GBPEUR1000001"
Name _GSRATES_6: "H20060714Latest GBPUSD1000001"
Name _GSRATES_7: "CT30000119980930 "
Name _GSRATES_8: "CT30000119980630 "
Name _GSRATES_9: "CT30000119980331 "
Name _GSRATES_COUNT: 1
Name _newDAT3: '[12]Anl 0.5'!#REF!
Name _Order1: 255
Name _Order2: 255
Name _q2: {"Total1",#N/A,FALSE,"Total Summary";"Risk1",#N/A,FALSE,"Risks"}
Name _Regression_Int: 1
Name a: {#N/A,#N/A,FALSE,"מאזן בוחן";"כל_מאזן_בוחן",#N/A,FALSE,"מאזן בוחן"}
Name a: {#N/A,#N/A,FALSE,"מאזן בוחן";"כל_מאזן_בוחן",#N/A,FALSE,"מאזן בוחן"}
Name a: {#N/A,#N/A,FALSE,"מאזן בוחן";"כל_מאזן_בוחן",#N/A,FALSE,"מאזן בוחן"}
Name a: {#N/A,#N/A,FALSE,"מאזן בוחן";"כל_מאזן_בוחן",#N/A,FALSE,"מאזן בוחן"}
Name a: {#N/A,#N/A,FALSE,"מאזן בוחן";"כל_מאזן_בוחן",#N/A,FALSE,"מאזן בוחן"}
Name aa: {#N/A,#N/A,FALSE,"מאזן";#N/A,#N/A,FALSE,"רווהפ";#N/A,#N/A,FALSE,"שינויים בהון";#N/A,#N/A,FALSE,"תזרים";#N/A,#N/A,FALSE,"נספח - התאמות";#N/A,#N/A,FALSE,"ני""ע לתזרים";#N/A,#N/A,FALSE,"פירוטים לדוחות"}

Sheet BOD Slides
B2: 45047
B4: P&L Summary | D4: Q1 2023 | E4: Q2 2023 | F4: Q3 2023 | G4: Q4 2023 | I4: Q2 2022 | M4: 2023 YTD
B5: US K$ | D5: Actual | E5: Actual | F5: Actual | G5: Actual | I5: Actual | J5: Budget | K5: Variance | M5: Actual | N5: Budget | O5: Variance
B6: Revenues | D6: -37 | E6: =FS!M79/1000-D6 -> -1450.1293 | F6: 0 | G6: 0 | I6: ='Actual vs Budget'!I14/1000 -> #ERROR! | J6: 0 | K6: =J6-I6 -> #ERROR! | M6: =('Actual vs Budget'!N14)*0 -> #ERROR! | N6: ='Actual vs Budget'!O14/1000 -> 0 | O6: =(N6-M6)/1000 -> #ERROR!
B7: COS | D7: 45 | E7: =FS!M87/1000-D7 -> 36.17857 | F7: 0 | G7: 0 | I7: =A7 | J7: 0 | K7: =J7-I7 -> 0 | M7: =('Actual vs Budget'!N15)*0 -> #ERROR! | N7: ='Actual vs Budget'!J15/1000 -> 0 | O7: =(N7-M7)/1000 -> #ERROR! | Q7: 0
B8: Gross loss | D8: 8 | E8: =E6+E7 -> -1413.9507 | F8: 0 | G8: 0 | I8: =I6 -> #ERROR! | J8: 0 | K8: =J8-I8 -> #ERROR! | M8: =(M6-M7)/1000 -> #ERROR! | N8: =N6-N7 -> 0 | O8: =O6-O7 -> #ERROR!
B9: Gross Margin (%) | D9: -0.2 | E9: =E8/E6 -> 0.97505149 | F9: 0 | I9: 1 | J9: 0 | K9: =K8/K6 -> #ERROR! | M9: =M8/M6*1000 -> #ERROR! | N9: =N8/N6 -> #DIV/0! | O9: =O8/O6 -> #ERROR!
B11: R&D | D11: 793 | E11: =FS!M110/1000-D11 -> 2661.69 | F11: 0 | G11: 0 | I11: ='Actual vs Budget'!I19/1000 -> #ERROR! | J11: ='Actual vs Budget'!J19/1000 -> 0 | K11: =J11-I11 -> #ERROR! | M11: =('Actual vs Budget'!N19/1000)*0 -> #ERROR! | N11: ='Actual vs Budget'!O19/1000 -> 0 | O11: =N11-M11 -> #ERROR!
B12: Sales / Customer Success | D12: 297 | E12: =FS!M129/1000-D12 -> 529.39082 | F12: 0 | G12: 0 | I12: ='Actual vs Budget'!I20/1000 -> #ERROR! | J12: ='Actual vs Budget'!J20/1000 -> 0 | K12: =J12-I12 -> #ERROR! | M12: =('Actual vs Budget'!N20/1000)*0 -> #ERROR! | N12: ='Actual vs Budget'!O20/1000 -> 0 | O12: =N12-M12 -> #ERROR!
B13: Marketing | D13: 135 | E13: =FS!M146/1000-D13 -> 2086.9726 | F13: 0 | G13: 0 | I13: ='Actual vs Budget'!I21/1000 -> #ERROR! | J13: ='Actual vs Budget'!J21/1000 -> 0 | K13: =J13-I13 -> #ERROR! | M13: =('Actual vs Budget'!N21/1000)*0 -> #ERROR! | N13: ='Actual vs Budget'!O21/1000 -> 0 | O13: =N13-M13 -> #ERROR!
B14: G&A | D14: 245 | E14: =FS!M187/1000-D14 -> 699.52116 | F14: 0 | G14: 0 | I14: ='Actual vs Budget'!I22/1000 -> #ERROR! | J14: ='Actual vs Budget'!J22/1000 -> 0 | K14: =J14-I14 -> #ERROR! | M14: =('Actual vs Budget'!N22/1000)*0 -> #ERROR! | N14: ='Actual vs Budget'!O22/1000 -> 0 | O14: =N14-M14 -> #ERROR!
B15: Developer Experiance | D15: 250 | E15: =FS!M164/1000-D15 -> 445.27785 | F15: 0 | G15: 0 | I15: ='Actual vs Budget'!I23/1000 -> #ERROR! | J15: ='Actual vs Budget'!J23/1000 -> 0 | K15: =J15-I15 -> #ERROR! | M15: =('Actual vs Budget'!N23/1000)*0 -> #ERROR! | N15: ='Actual vs Budget'!O23/1000 -> 0 | O15: =N15-M15 -> #ERROR!
B16: OPEX | D16: 1719 | E16: =SUM(E11:E15) -> 6422.8525 | F16: =(SUM(F11:F15))*0 -> 0 | G16: 0 | I16: =SUM(I11:I15) -> #ERROR! | J16: =SUM(J11:J15) -> 0 | K16: =SUM(K11:K15) -> #ERROR! | M16: =SUM(M11:M15) -> #ERROR! | N16: =SUM(N11:N15) -> 0 | O16: =SUM(O11:O15) -> #ERROR!
B17: EBITDA | D17: 1727 | E17: =E8+E16 -> 5008.9017 | F17: =F8-F16 -> 0 | I17: =I8-I16 -> #ERROR! | J17: =J8-J16 -> 0 | K17: =K8-K16 -> #ERROR! | M17: =M8-M16 -> #ERROR! | N17: =N8-N16 -> 0 | O17: =O8-O16 -> #ERROR!
B20: HC Summary | D20: =D4 -> Q1 2023 | E20: =E4 -> Q2 2023 | F20: =F4 -> Q3 2023 | G20: =G4 -> Q4 2023 | I20: =I4 -> Q2 2022 | M20: =M4 -> 2023 YTD
D21: Actual | E21: Actual | F21: Actual | G21: Actual | I21: Actual | J21: Budget | K21: Variance | M21: Actual | N21: Budget | O21: Variance
B23: R&D | D23: 16 | E23: ='Actual vs Budget'!D39 -> 16 | F23: 0 | G23: 0 | I23: =E23 -> 16 | J23: ='Actual vs Budget'!J39 -> 0 | K23: =I23-J23 -> 16 | M23: ='Actual vs Budget'!N39 -> 0 | N23: ='Actual vs Budget'!O39 -> 0 | O23: =M23-N23 -> 0
B24: Sales / Customer Success | D24: 2 | E24: ='Actual vs Budget'!D40 -> 2 | F24: 0 | G24: 0 | I24: =E24 -> 2 | J24: ='Actual vs Budget'!J40 -> 0 | K24: =I24-J24 -> 2 | M24: ='Actual vs Budget'!N40 -> 0 | N24: ='Actual vs Budget'!O40 -> 0 | O24: =M24-N24 -> 0
B25: Marketing | D25: 2 | E25: ='Actual vs Budget'!D41 -> 2 | F25: 0 | G25: 0 | I25: =E25 -> 2 | J25: ='Actual vs Budget'!J41 -> 0 | K25: =I25-J25 -> 2 | M25: ='Actual vs Budget'!N41 -> 0 | N25: ='Actual vs Budget'!O41 -> 0 | O25: =M25-N25 -> 0
B26: G&A | D26: 3 | E26: ='Actual vs Budget'!D42 -> 3 | F26: 0 | G26: 0 | I26: =E26 -> 3 | J26: ='Actual vs Budget'!J42 -> 0 | K26: =I26-J26 -> 3 | M26: ='Actual vs Budget'!N42 -> 0 | N26: ='Actual vs Budget'!O42 -> 0 | O26: =M26-N26 -> 0
B27: Developer Experiance | D27: 4 | E27: ='Actual vs Budget'!D43 -> 1 | F27: 0 | G27: 0 | I27: =E27 -> 1 | J27: ='Actual vs Budget'!J43 -> 0 | K27: =I27-J27 -> 1 | M27: ='Actual vs Budget'!N43 -> 0 | N27: ='Actual vs Budget'!O43 -> 0 | O27: =M27-N27 -> 0
B28: Total HC | D28: 27 | E28: =SUM(E23:E27) -> 24 | F28: =SUM(F23:F27) -> 0 | G28: 0 | I28: =SUM(I23:I27) -> 24 | J28: =SUM(J23:J27) -> 0 | K28: =SUM(K23:K27) -> 24 | M28: =SUM(M23:M27) -> 0 | N28: =SUM(N23:N27) -> 0 | O28: =SUM(O23:O27) -> 0
B30: Cash Flow Summary - K USD | D30: =D20 -> Q1 2023 | E30: =E20 -> Q2 2023 | F30: =F20 -> Q3 2023 | G30: =G20 -> Q4 2023 | I30: =I4 -> Q2 2022 | M30: =M20 -> 2023 YTD
D31: Actual | E31: Actual | F31: Actual | G31: Actual | I31: Actual | J31: Budget | K31: Variance | M31: Actual | N31: Budget | O31: Variance
B33: Cash at Beginning of Period | D33: 12394000 | E33: =D38 -> 10584334 | F33: 0 | G33: 0 | I33: ='Actual vs Budget'!I28 -> #REF! | J33: ='Actual vs Budget'!J28 -> #REF! | K33: =J33-I33 -> #REF! | M33: 0 | N33: 0 | O33: 0
B34: Net Operating Cash Flow | D34: -1854276.9 | E34: -1060663 | F34: 0 | G34: 0 | I34: ='Actual vs Budget'!I29 -> #REF! | J34: ='Actual vs Budget'!J29 -> #REF! | K34: =J34-I34 -> #REF! | M34: 0 | N34: 0 | O34: 0
B35: Total Capital Expenditure | D35: -8308.4582 | E35: -2517.2308 | F35: 0 | G35: 0 | I35: ='Actual vs Budget'!I30 -> #REF! | J35: ='Actual vs Budget'!J30 -> #REF! | K35: =J35-I35 -> #REF! | M35: 0 | N35: 0 | O35: 0
B36: Equity financing | D36: 52919.46 | E36: -5794 | F36: 0 | G36: 0 | I36: ='Actual vs Budget'!I31 -> #REF! | J36: ='Actual vs Budget'!J31 -> #REF! | K36: =J36-I36 -> #REF! | M36: 0 | N36: 0 | O36: 0
B37: Net Cash Inflow / (Outflow) | D37: =SUM(D34:D36) -> -1809665.9 | E37: =SUM(E34:E36) -> -1068974.2 | F37: 0 | G37: 0 | I37: =SUM(I34:I36) -> #REF! | J37: =SUM(J34:J36) -> #REF! | K37: =J37-I37 -> #REF! | M37: 0 | N37: 0 | O37: 0
B38: Cash End Of Period | D38: =D33+D37 -> 10584334 | E38: =E33+E37 -> 9515359.8 | F38: 0 | G38: 0 | I38: =I37+I33 -> #REF! | J38: =J33+J37 -> #REF! | K38: =K33+K37 -> #REF! | M38: =M33+M37 -> 0 | N38: =N33+N37 -> 0 | O38: =O33+O37 -> 0
B41: Opex Breakdown by Type - K USD | D41: =D30 -> Q1 2023 | E41: =E30 -> Q2 2023 | F41: =F30 -> Q3 2023 | G41: =G30 -> Q4 2023 | I41: =I30 -> Q2 2022 | M41: =M30 -> 2023 YTD
D42: Actual | E42: Actual | F42: Actual | G42: Actual | I42: Actual | J42: Budget | K42: Variance | M42: Actual | N42: Budget | O42: Variance
B44: Payroll | D44: 1250 | E44: =(FS!M94+FS!M113+FS!M132+FS!M151+FS!M167)/1000-D44 -> 2932.1099 | F44: 0 | G44: 0 | I44: ='Actual vs Budget'!I48 -> #ERROR! | J44: ='Actual vs Budget'!J48 | K44: =J44-I44 -> #ERROR! | M44: 0 | N44: 0 | O44: 0
B45: Recruiting | D45: 1 | E45: =(FS!M182)/1000-D45 -> 53.89842 | F45: 0 | G45: 0 | I45: ='Actual vs Budget'!I49 -> #ERROR! | J45: ='Actual vs Budget'!J49 | K45: =J45-I45 -> #ERROR! | M45: 0 | N45: 0 | O45: 0
B46: Bonus | D46: 132 | E46: =(FS!M114+FS!M152)/1000-D46 -> 22.48174 | F46: 0 | G46: 0 | I46: ='Actual vs Budget'!I50 -> #ERROR! | J46: ='Actual vs Budget'!J50 | K46: =J46-I46 -> #ERROR! | M46: 0 | N46: 0 | O46: 0
B47: Tools | D47: 54 | E47: =(FS!M100+FS!M116+FS!M134+FS!M153+FS!M169)/1000-E49-D47 -> 194.21811 | F47: 0 | G47: 0 | I47: ='Actual vs Budget'!I51 -> #ERROR! | J47: ='Actual vs Budget'!J51 | K47: =J47-I47 -> #ERROR! | M47: 0 | N47: 0 | O47: 0
B48: Hosting | D48: 103 | E48: =(FS!M82+FS!M108)/1000-D48 -> 278.70183 | F48: 0 | G48: 0 | I48: ='Actual vs Budget'!I52 -> #ERROR! | J48: ='Actual vs Budget'!J52 | K48: =J48-I48 -> #ERROR! | M48: 0 | N48: 0 | O48: 0
B49: HUBSPOT + site ground | D49: 4 | E49: =1.6+1.4+1.4-D49 -> 0.4 | F49: 0 | G49: 0 | I49: ='Actual vs Budget'!I54 -> #ERROR! | J49: ='Actual vs Budget'!J54 | K49: =J49-I49 -> #ERROR! | M49: 0 | N49: 0 | O49: 0
B50: Consultant | D50: 40 | E50: =(FS!M98+FS!M135+FS!M154+FS!M168)/1000-D50 -> 637.54752 | F50: 0 | G50: 0 | I50: ='Actual vs Budget'!I55 -> #ERROR! | J50: ='Actual vs Budget'!J55 | K50: =J50-I50 -> #ERROR! | M50: 0 | N50: 0 | O50: 0
B51: Travel | D51: 29 | E51: =(FS!M97+FS!M118+FS!M137+FS!M155+FS!M172)/1000-D51 -> 106.51198 | F51: 0 | G51: 0 | I51: ='Actual vs Budget'!I56 -> #ERROR! | J51: ='Actual vs Budget'!J56 | K51: =J51-I51 -> #ERROR! | M51: 0 | N51: 0 | O51: 0
B52: Others | D52: 3 | E52: =(FS!M176+FS!M157+FS!M124+FS!M120+FS!MI99)/1000-D52 -> 4.9144 | F52: 0 | G52: 0 | I52: ='Actual vs Budget'!I57 | J52: ='Actual vs Budget'!J57 | K52: =J52-I52 -> 0 | M52: 0 | N52: 0 | O52: 0
B53: Commission | D53: - | E53: 0 | F53: 0 | G53: 0 | I53: ='Actual vs Budget'!I58 -> #ERROR! | J53: ='Actual vs Budget'!J58 | K53: =J53-I53 -> #ERROR! | M53: 0 | N53: 0 | O53: 0
B54: Marketing | D54: 0 | E54: =(FS!M141)/1000 -> 27.113638 | F54: 0 | G54: 0 | I54: ='Actual vs Budget'!I59 -> #ERROR! | J54: ='Actual vs Budget'!J59 | K54: =J54-I54 -> #ERROR! | M54: 0 | N54: 0 | O54: 0
B55: conference | D55: 23 | E55: =(FS!M126+FS!M143+FS!M161)/1000-D55 -> 168.9508 | F55: 0 | G55: 0 | M55: 0 | N55: 0 | O55: 0
B56: Rent & Utilities | D56: 24 | E56: =(FS!M174+FS!M175)/1000-D56 -> 78.60659 | F56: 0 | G56: 0 | M56: 0 | N56: 0 | O56: 0
B57: Welfare | D57: 23 | E57: =(FS!M178+FS!M179+FS!M180)/1000-D57 -> 14.79825 | F57: 0 | G57: 0 | M57: 0 | N57: 0 | O57: 0
B58: Professional | D58: 56 | E58: =(FS!M170+FS!M171)/1000-D58 -> 220.40434 | F58: 0 | G58: 0 | M58: 0 | N58: 0 | O58: 0
B59: IT | D59: - | E59: 0 | F59: 0 | G59: 0 | M59: 0 | N59: 0 | O59: 0
B60: Insurance | D60: 5 | E60: =(FS!M177)/1000-D60 -> 7.2506231 | F60: 0 | G60: 0 | I60: ='Actual vs Budget'!I60 -> #ERROR! | J60: ='Actual vs Budget'!J60 | K60: =J60-I60 -> #ERROR! | M60: 0 | N60: 0 | O60: 0
B61: Office exp. | D61: 8 | E61: =(FS!M173)/1000-D61 -> 53.361278 | F61: 0 | G61: 0 | I61: ='Actual vs Budget'!I61 -> #ERROR! | J61: ='Actual vs Budget'!J61 | K61: =J61-I61 -> #ERROR! | M61: 0 | N61: 0 | O61: 0
B62: Compliance | D62: - | E62: 0 | F62: 0 | G62: 0 | I62: ='Actual vs Budget'!I62 -> #ERROR! | J62: ='Actual vs Budget'!J62 | K62: =J62-I62 -> #ERROR! | M62: 0 | N62: 0 | O62: 0
B63: Training | D63: - | E63: 0 | F63: 0 | G63: 0 | I63: ='Actual vs Budget'!I63 | J63: ='Actual vs Budget'!J63 | K63: =J63-I63 -> 0 | M63: 0 | N63: 0 | O63: 0
B64: IN PERSOM MEETUPS | D64: 3 | E64: =FS!M156/1000-D64 -> -1.35622 | F64: 0 | G64: 0 | I64: ='Actual vs Budget'!I64 -> #ERROR! | J64: ='Actual vs Budget'!J64 | K64: =J64-I64 -> #ERROR! | M64: 0 | N64: 0 | O64: 0
B65: Taxes | D65: - | E65: 0 | F65: 0 | G65: 0 | I65: ='Actual vs Budget'!I65 -> #ERROR! | J65: ='Actual vs Budget'!J65 | K65: =J65-I65 -> #ERROR! | M65: 0 | N65: 0 | O65: 0
B66: Linkedin | D66: 12 | E66: =(FS!M139)/1000-D66 -> -11.93902 | F66: 0 | G66: 0 | I66: ='Actual vs Budget'!I66 | J66: ='Actual vs Budget'!J66 | K66: =J66-I66 -> 0 | M66: 0 | N66: 0 | O66: 0
B67: Depreciation | D67: -2 | E67: =(FS!M181)/1000-D67 -> 56.33761 | F67: 0 | G67: 0 | I67: ='Actual vs Budget'!I67 -> #ERROR! | J67: ='Actual vs Budget'!J67 | K67: =J67-I67 -> #ERROR! | M67: 0 | N67: 0 | O67: 0
B68: ='Actual vs Budget'!H72 -> Total Opex | D68: =SUM(D44:D67) -> 1768 | E68: =SUM(E44:E67) -> 4844.3118 | F68: =SUM(F44:F67) -> 0 | G68: =SUM(G44:G67) -> 0 | I68: =SUM(I44:I67) -> #ERROR! | J68: =SUM(J44:J67) -> 0 | K68: =SUM(K44:K67) -> #ERROR! | M68: 0 | N68: 0 | O68: 0
D69: =D70-D68 -> -4
D70: =D7+D16 -> 1764

Sheet Actual vs Budget
A2: Errors in this sheet: | H2: =#REF! -> #REF!
A3: =COUNTIF(D26:O26,"error")+COUNTIF(D35:O35,"error")+COUNTIF(D45:O45,"error")+COUNTIF(D73:O73,"error") -> 0 | C3: Actual vs Budget | H3: Actual vs Budget
A4: General errors in file:
A5: =A3+#REF!+#REF!+#REF!+#REF!+#REF!+#REF!+#REF!+#REF!+#REF! -> #REF!
A6: Scale | C6: Month $ | D6: 45047 | H6: ="Quarter "&$A$7 -> #REF! | I6: Q1-23 | M6: =$A$7&" YTD "&YEAR(month_of_report) -> #REF! | N6: 2023
A7: =#REF! -> #REF! | D7: Actual | E7: Budget | F7: Variance | I7: Actual | J7: Budget | K7: Variance | N7: Actual | O7: Budget | P7: Variance
A8: =IF(A7="$",1,IF(A7="$k",1000,1000000)) -> #REF! | C8: KPI | H8: =C8 -> KPI | M8: =H8 -> KPI
C9: KPI | H9: =C9 -> KPI | M9: =H9 -> KPI
C10: MRR | H10: =C10 -> MRR | M10: =H10 -> MRR
C11: ARR | H11: =C11 -> ARR | M11: =H11 -> ARR
C13: P&L Summary $ | H13: =C13 -> P&L Summary $ | M13: =H13 -> P&L Summary $
A14: 1 | C14: Revenues | D14: =-FS!#REF! -> #ERROR! | E14: 14792 | F14: =D14-E14 -> #ERROR! | H14: =C14 -> Revenues | I14: =D14 -> #ERROR! | K14: =IFERROR(INDEX(#REF!,MATCH($A14,#REF!,0),),0)/$A$8 -> #REF! | M14: =H14 -> Revenues | N14: =I14 -> #ERROR! | P14: =IFERROR(INDEX(#REF!,MATCH($A14,#REF!,0),),0)/$A$8 -> #REF!
A15: 2 | C15: Cost of Sales | D15: =FS!#REF! -> #ERROR! | E15: 8400 | F15: =D15-E15 -> #ERROR! | H15: =C15 -> Cost of Sales | I15: =D15 -> #ERROR! | K15: =IFERROR(INDEX(#REF!,MATCH($A15,#REF!,0),),0)/$A$8 -> #REF! | M15: =H15 -> Cost of Sales | N15: =I15 -> #ERROR! | P15: =IFERROR(INDEX(#REF!,MATCH($A15,#REF!,0),),0)/$A$8 -> #REF!
C16: Gross profit | D16: =D14-D15 -> #ERROR! | E16: 6392 | F16: =D16-E16 -> #ERROR! | H16: =C16 -> Gross profit | I16: =I14-I15 -> #ERROR! | J16: =J14-J15 -> 0 | K16: =K14+K15 -> #REF! | M16: =H16 -> Gross profit | N16: =N14-N15 -> #ERROR! | O16: =O14-O15 -> 0 | P16: =P14+P15 -> #REF!
C17: Gross margin | D17: =IFERROR(+D16/D14,0) -> 0 | E17: 0.43212547 | F17: =IFERROR(+F16/F14,0) -> 0 | H17: =C17 -> Gross margin | I17: =IFERROR(+I16/I14,0) -> 0 | J17: =IFERROR(+J16/J14,0) -> 0 | K17: =IFERROR(+K16/K14,0) -> 0 | M17: =H17 -> Gross margin | N17: =IFERROR(+N16/N14,0) -> 0 | O17: =IFERROR(+O16/O14,0) -> 0 | P17: =IFERROR(+P16/P14,0) -> 0
C18: Opex: | H18: =C18 -> Opex: | M18: =H18 -> Opex:
A19: =#REF! -> #REF! | C19: R&D | D19: =FS!#REF! -> #ERROR! | E19: 253251 | F19: =D19-E19 -> #ERROR! | H19: =C19 -> R&D | I19: =D19 -> #ERROR! | K19: =IFERROR(INDEX(#REF!,MATCH($A19,#REF!,0),),0)/$A$8 -> #REF! | M19: =H19 -> R&D | N19: =I19 -> #ERROR! | P19: =IFERROR(INDEX(#REF!,MATCH($A19,#REF!,0),),0)/$A$8 -> #REF!
A20: =#REF! -> #REF! | C20: Sales / Customer Success | D20: =FS!#REF! -> #ERROR! | E20: 67047 | F20: =D20-E20 -> #ERROR! | H20: =C20 -> Sales / Customer Success | I20: =D20 -> #ERROR! | K20: =IFERROR(INDEX(#REF!,MATCH($A20,#REF!,0),),0)/$A$8 -> #REF! | M20: =H20 -> Sales / Customer Success | N20: =I20 -> #ERROR! | P20: =IFERROR(INDEX(#REF!,MATCH($A20,#REF!,0),),0)/$A$8 -> #REF!
A21: =#REF! -> #REF! | C21: Marketing | D21: =FS!#REF! -> #ERROR! | E21: 40926.286 | F21: =D21-E21 -> #ERROR! | H21: =C21 -> Marketing | I21: =D21 -> #ERROR! | K21: =IFERROR(INDEX(#REF!,MATCH($A21,#REF!,0),),0)/$A$8 -> #REF! | M21: =H21 -> Marketing | N21: =I21 -> #ERROR! | P21: =IFERROR(INDEX(#REF!,MATCH($A21,#REF!,0),),0)/$A$8 -> #REF!
A22: =#REF! -> #REF! | C22: G&A | D22: =FS!#REF! -> #ERROR! | E22: 117416.08 | F22: =D22-E22 -> #ERROR! | H22: =C22 -> G&A | I22: =D22 -> #ERROR! | K22: =IFERROR(INDEX(#REF!,MATCH($A22,#REF!,0),),0)/$A$8 -> #REF! | M22: =H22 -> G&A | N22: =I22 -> #ERROR! | P22: =IFERROR(INDEX(#REF!,MATCH($A22,#REF!,0),),0)/$A$8 -> #REF!
A23: =#REF! -> #REF! | C23: Developer Experiance | D23: =FS!#REF! -> #ERROR! | E23: 62624.833 | F23: =D23-E23 -> #ERROR! | H23: =C23 -> Developer Experiance | I23: =D23 -> #ERROR! | K23: =IFERROR(INDEX(#REF!,MATCH($A23,#REF!,0),),0)/$A$8 -> #REF! | M23: =H23 -> Developer Experiance | N23: =I23 -> #ERROR! | P23: =IFERROR(INDEX(#REF!,MATCH($A23,#REF!,0),),0)/$A$8 -> #REF!
C24: Total OPEX | D24: =SUM(D19:D23) -> #ERROR! | E24: 585054.65 | F24: =D24-E24 -> #ERROR! | H24: =C24 -> Total OPEX | I24: =SUM(I19:I23) -> #ERROR! | J24: =SUM(J19:J23) -> 0 | K24: =SUM(K19:K23) -> #REF! | M24: =H24 -> Total OPEX | N24: =SUM(N19:N23) -> #ERROR! | O24: =SUM(O19:O23) -> 0 | P24: =SUM(P19:P23) -> #REF!
C25: EBITDA | D25: =D16-D24 -> #ERROR! | E25: -578662.65 | F25: =D25-E25 -> #ERROR! | H25: =C25 -> EBITDA | I25: =I16-I24 -> #ERROR! | J25: =J16-J24 -> 0 | K25: =K16+K24 -> #REF! | M25: =H25 -> EBITDA | N25: =N16-N24 -> #ERROR! | O25: =O16-O24 -> 0 | P25: =P16+P24 -> #REF!
I26: =IF(ROUND(I24*$A$8,0)=ROUND(#REF!,0),"","Error") -> #ERROR! | J26: =IF(ROUND(J24*$A$8,0)=ROUND(#REF!,0),"","Error") -> #REF! | N26: =IF(ROUND(N24*$A$8,0)=ROUND(#REF!,0),"","Error") -> #ERROR! | O26: =IF(ROUND(O24*$A$8,0)=ROUND(#REF!,0),"","Error") -> #REF!
C27: Cash flow $ | D27: =D7 -> Actual | E27: =E7 -> Budget | F27: =F7 -> Variance | H27: =C27 -> Cash flow $ | I27: =I7 -> Actual | J27: =J7 -> Budget | K27: =K7 -> Variance | M27: =H27 -> Cash flow $ | N27: =N7 -> Actual | O27: =O7 -> Budget | P27: =P7 -> Variance
C28: Cash at Beginning of Period | D28: 10006986 | E28: 9890000 | F28: =D28-E28 -> 116985.9 | H28: =C28 -> Cash at Beginning of Period | I28: =INDEX(#REF!,MATCH($C28,#REF!,0))/$A$8 -> #REF! | J28: =INDEX(#REF!,MATCH($C28,#REF!,0))/$A$8 -> #REF! | K28: =INDEX(#REF!,MATCH($C28,#REF!,0))/$A$8 -> #REF! | M28: =H28 -> Cash at Beginning of Period | N28: =INDEX(#REF!,MATCH($C28,#REF!,0))/$A$8 -> #REF! | O28: =INDEX(#REF!,MATCH($C28,#REF!,0))/$A$8 -> #REF! | P28: =INDEX(#REF!,MATCH($C28,#REF!,0))/$A$8 -> #REF!
C29: Net Operating Cash Flow | D29: -488560 | E29: -590921.32 | F29: =D29-E29 -> 102361.32 | H29: =C29 -> Net Operating Cash Flow | I29: =INDEX(#REF!,MATCH($C29,#REF!,0))/$A$8 -> #REF! | J29: =INDEX(#REF!,MATCH($C29,#REF!,0))/$A$8 -> #REF! | K29: =INDEX(#REF!,MATCH($C29,#REF!,0))/$A$8 -> #REF! | M29: =H29 -> Net Operating Cash Flow | N29: =INDEX(#REF!,MATCH($C29,#REF!,0))/$A$8 -> #REF! | O29: =INDEX(#REF!,MATCH($C29,#REF!,0))/$A$8 -> #REF! | P29: =INDEX(#REF!,MATCH($C29,#REF!,0))/$A$8 -> #REF! | R29: על פי תקציב חדש 6.23
C30: Total Capital Expenditure | D30: 0 | E30: 0 | F30: =D30-E30 -> 0 | H30: =C30 -> Total Capital Expenditure | I30: =INDEX(#REF!,MATCH($C30,#REF!,0))/$A$8 -> #REF! | J30: =INDEX(#REF!,MATCH($C30,#REF!,0))/$A$8 -> #REF! | K30: =INDEX(#REF!,MATCH($C30,#REF!,0))/$A$8 -> #REF! | M30: =H30 -> Total Capital Expenditure | N30: =INDEX(#REF!,MATCH($C30,#REF!,0))/$A$8 -> #REF! | O30: =INDEX(#REF!,MATCH($C30,#REF!,0))/$A$8 -> #REF! | P30: =INDEX(#REF!,MATCH($C30,#REF!,0))/$A$8 -> #REF!
C31: Total Financing | D31: -2979 | E31: 0 | F31: =D31-E31 -> -2979 | H31: =C31 -> Total Financing | I31: =INDEX(#REF!,MATCH($C31,#REF!,0))/$A$8 -> #REF! | J31: =INDEX(#REF!,MATCH($C31,#REF!,0))/$A$8 -> #REF! | K31: =INDEX(#REF!,MATCH($C31,#REF!,0))/$A$8 -> #REF! | M31: =H31 -> Total Financing | N31: =INDEX(#REF!,MATCH($C31,#REF!,0))/$A$8 -> #REF! | O31: =INDEX(#REF!,MATCH($C31,#REF!,0))/$A$8 -> #REF! | P31: =INDEX(#REF!,MATCH($C31,#REF!,0))/$A$8 -> #REF!
C32: Taxation Paid | D32: 0 | E32: 0 | F32: =D32-E32 -> 0 | H32: =C32 -> Taxation Paid | I32: =INDEX(#REF!,MATCH($C32,#REF!,0))/$A$8 -> #REF! | J32: =INDEX(#REF!,MATCH($C32,#REF!,0))/$A$8 -> #REF! | K32: =INDEX(#REF!,MATCH($C32,#REF!,0))/$A$8 -> #REF! | M32: =H32 -> Taxation Paid | N32: =INDEX(#REF!,MATCH($C32,#REF!,0))/$A$8 -> #REF! | O32: =INDEX(#REF!,MATCH($C32,#REF!,0))/$A$8 -> #REF! | P32: =INDEX(#REF!,MATCH($C32,#REF!,0))/$A$8 -> #REF!
C33: Net Cash Inflow / (Outflow) | D33: =SUM(D29:D32) -> -491539 | E33: =SUM(E29:E32) -> -590921.32 | F33: =D33-E33 -> 99382.316 | H33: =C33 -> Net Cash Inflow / (Outflow) | I33: =INDEX(#REF!,MATCH($C33,#REF!,0))/$A$8 -> #REF! | J33: =INDEX(#REF!,MATCH($C33,#REF!,0))/$A$8 -> #REF! | K33: =INDEX(#REF!,MATCH($C33,#REF!,0))/$A$8 -> #REF! | M33: =H33 -> Net Cash Inflow / (Outflow) | N33: =INDEX(#REF!,MATCH($C33,#REF!,0))/$A$8 -> #REF! | O33: =INDEX(#REF!,MATCH($C33,#REF!,0))/$A$8 -> #REF! | P33: =INDEX(#REF!,MATCH($C33,#REF!,0))/$A$8 -> #REF!
C34: Cash End Of Period | D34: =D28+D33 -> 9515446.9 | E34: =E28+E33 -> 9299078.7 | F34: =F28+F33 -> 216368.21 | H34: =C34 -> Cash End Of Period | I34: =INDEX(#REF!,MATCH($C34,#REF!,0))/$A$8 -> #REF! | J34: =INDEX(#REF!,MATCH($C34,#REF!,0))/$A$8 -> #REF! | K34: =INDEX(#REF!,MATCH($C34,#REF!,0))/$A$8 -> #REF! | M34: =H34 -> Cash End Of Period | N34: =INDEX(#REF!,MATCH($C34,#REF!,0))/$A$8 -> #REF! | O34: =INDEX(#REF!,MATCH($C34,#REF!,0))/$A$8 -> #REF! | P34: =INDEX(#REF!,MATCH($C34,#REF!,0))/$A$8 -> #REF!
I35: =IF(ROUND(I34*$A$8,0)=ROUND(#REF!,0),"","Error") -> #REF! | J35: =IF(ROUND(J34*$A$8,0)=ROUND(#REF!,0),"","Error") -> #REF! | N35: =IF(ROUND(N34*$A$8,0)=ROUND(#REF!,0),"","Error") -> #REF! | O35: =IF(ROUND(O34*$A$8,0)=ROUND(#REF!,0),"","Error") -> #REF!
C37: HC | D37: =D6 -> 45047 | H37: =C37 -> HC | I37: =I6 -> Q1-23 | M37: =H37 -> HC | N37: =N6 -> 2023
D38: =D7 -> Actual | E38: =E7 -> Budget | F38: =F7 -> Variance | I38: =I7 -> Actual | J38: =J7 -> Budget | K38: =K7 -> Variance | N38: =N7 -> Actual | O38: =O7 -> Budget | P38: =P7 -> Variance
A39: =#REF! -> #REF! | C39: =C19 -> R&D | D39: 16 | E39: 16 | F39: =D39-E39 -> 0 | H39: R&D | I39: =IFERROR(INDEX(#REF!,MATCH($A39,#REF!,0),),0) -> 0 | J39: =IFERROR(INDEX(#REF!,MATCH($A39,#REF!,0),),0) -> 0 | K39: =IFERROR(INDEX(#REF!,MATCH($A39,#REF!,0),),0) -> 0 | M39: =H39 -> R&D | N39: =IFERROR(INDEX(#REF!,MATCH($A39,#REF!,0),),0) -> 0 | O39: =IFERROR(INDEX(#REF!,MATCH($A39,#REF!,0),),0) -> 0 | P39: =IFERROR(INDEX(#REF!,MATCH($A39,#REF!,0),),0) -> 0
A40: =#REF! -> #REF! | C40: =C20 -> Sales / Customer Success | D40: 2 | E40: 2 | F40: =D40-E40 -> 0 | H40: Sales / Customer Success | I40: =IFERROR(INDEX(#REF!,MATCH($A40,#REF!,0),),0) -> 0 | J40: =IFERROR(INDEX(#REF!,MATCH($A40,#REF!,0),),0) -> 0 | K40: =IFERROR(INDEX(#REF!,MATCH($A40,#REF!,0),),0) -> 0 | M40: =H40 -> Sales / Customer Success | N40: =IFERROR(INDEX(#REF!,MATCH($A40,#REF!,0),),0) -> 0 | O40: =IFERROR(INDEX(#REF!,MATCH($A40,#REF!,0),),0) -> 0 | P40: =IFERROR(INDEX(#REF!,MATCH($A40,#REF!,0),),0) -> 0
A41: =#REF! -> #REF! | C41: =C21 -> Marketing | D41: 2 | E41: 2 | F41: =D41-E41 -> 0 | H41: Marketing | I41: =IFERROR(INDEX(#REF!,MATCH($A41,#REF!,0),),0) -> 0 | J41: =IFERROR(INDEX(#REF!,MATCH($A41,#REF!,0),),0) -> 0 | K41: =IFERROR(INDEX(#REF!,MATCH($A41,#REF!,0),),0) -> 0 | M41: =H41 -> Marketing | N41: =IFERROR(INDEX(#REF!,MATCH($A41,#REF!,0),),0) -> 0 | O41: =IFERROR(INDEX(#REF!,MATCH($A41,#REF!,0),),0) -> 0 | P41: =IFERROR(INDEX(#REF!,MATCH($A41,#REF!,0),),0) -> 0
A42: =#REF! -> #REF! | C42: =C22 -> G&A | D42: 3 | E42: 3 | F42: =D42-E42 -> 0 | H42: G&A | I42: =IFERROR(INDEX(#REF!,MATCH($A42,#REF!,0),),0) -> 0 | J42: =IFERROR(INDEX(#REF!,MATCH($A42,#REF!,0),),0) -> 0 | K42: =IFERROR(INDEX(#REF!,MATCH($A42,#REF!,0),),0) -> 0 | M42: =H42 -> G&A | N42: =IFERROR(INDEX(#REF!,MATCH($A42,#REF!,0),),0) -> 0 | O42: =IFERROR(INDEX(#REF!,MATCH($A42,#REF!,0),),0) -> 0 | P42: =IFERROR(INDEX(#REF!,MATCH($A42,#REF!,0),),0) -> 0
A43: =#REF! -> #REF! | C43: =C23 -> Developer Experiance | D43: 1 | E43: 1 | F43: =D43-E43 -> 0 | H43: Developer Experiance | I43: =IFERROR(INDEX(#REF!,MATCH($A43,#REF!,0),),0) -> 0 | J43: =IFERROR(INDEX(#REF!,MATCH($A43,#REF!,0),),0) -> 0 | K43: =IFERROR(INDEX(#REF!,MATCH($A43,#REF!,0),),0) -> 0 | M43: =H43 -> Developer Experiance | N43: =IFERROR(INDEX(#REF!,MATCH($A43,#REF!,0),),0) -> 0 | O43: =IFERROR(INDEX(#REF!,MATCH($A43,#REF!,0),),0) -> 0 | P43: =IFERROR(INDEX(#REF!,MATCH($A43,#REF!,0),),0) -> 0
C44: Total Headcount | D44: =SUM(D39:D43) -> 24 | E44: =SUM(E39:E43) -> 24 | F44: =D44-E44 -> 0 | H44: =C44 -> Total Headcount | I44: =SUM(I39:I43) -> 0 | J44: =SUM(J39:J43) -> 0 | K44: =SUM(K39:K43) -> 0 | M44: =H44 -> Total Headcount | N44: =SUM(N39:N43) -> 0 | O44: =SUM(O39:O43) -> 0 | P44: =SUM(P39:P43) -> 0
I45: =IF(ROUND(I44,0)=ROUND(#REF!,0),"","Error") -> #REF! | J45: =IF(ROUND(J44,0)=ROUND(#REF!,0),"","Error") -> #REF! | N45: =IF(ROUND(N44,0)=ROUND(#REF!,0),"","Error") -> #REF! | O45: =IF(ROUND(O44,0)=ROUND(#REF!,0),"","Error") -> #REF!
C46: Opex expense type $ | D46: =D6 -> 45047 | H46: =C46 -> Opex expense type $ | I46: =I6 -> Q1-23 | M46: =H46 -> Opex expense type $ | N46: =N6 -> 2023
D47: =D7 -> Actual | E47: =E7 -> Budget | F47: =F7 -> Variance | I47: =I7 -> Actual | J47: =J7 -> Budget | K47: =K7 -> Variance | N47: =N7 -> Actual | O47: =O7 -> Budget | P47: =P7 -> Variance
C48: Payroll | D48: =FS!#REF!+FS!#REF!+FS!#REF!+FS!#REF!+FS!#REF!+FS!#REF! -> #ERROR! | E48: 408606.9 | F48: =D48-E48 -> #ERROR! | H48: =#REF! -> #REF! | I48: =D48 -> #ERROR! | K48: =SUMIFS(#REF!,#REF!,$C48)/$A$8 -> #N/A | M48: =H48 -> #REF! | N48: =I48 -> #ERROR! | P48: =SUMIFS(#REF!,#REF!,$C48)/$A$8 -> #N/A
C49: Recruiting | D49: =FS!#REF! -> #ERROR! | E49: 0 | F49: =D49-E49 -> #ERROR! | H49: =C49 -> Recruiting | I49: =D49 -> #ERROR! | K49: =SUMIFS(#REF!,#REF!,$C49)/$A$8 -> #N/A | M49: =H49 -> Recruiting | N49: =I49 -> #ERROR! | P49: =SUMIFS(#REF!,#REF!,$C49)/$A$8 -> #N/A
C50: Bonus | D50: =FS!#REF! -> #ERROR! | F50: =D50-E50 -> #ERROR! | H50: =C50 -> Bonus | I50: =D50 -> #ERROR! | K50: =SUMIFS(#REF!,#REF!,$C50)/$A$8 -> #N/A | M50: =H50 -> Bonus | N50: =I50 -> #ERROR! | P50: =SUMIFS(#REF!,#REF!,$C50)/$A$8 -> #N/A
C51: Tools | D51: =FS!#REF!+FS!#REF!+FS!#REF!+FS!#REF!+FS!#REF!-D53 -> #ERROR! | E51: =(#REF!+#REF!+#REF!+#REF!+#REF!)*1000 -> #REF! | F51: =D51-E51 -> #ERROR! | H51: =C51 -> Tools | I51: =D51 -> #ERROR! | K51: =SUMIFS(#REF!,#REF!,$C51)/$A$8 -> #N/A | M51: =H51 -> Tools | N51: =I51 -> #ERROR! | P51: =SUMIFS(#REF!,#REF!,$C51)/$A$8 -> #N/A
C52: Hosting | D52: =FS!#REF!+FS!#REF! -> #ERROR! | E52: =(#REF!+#REF!)*1000 -> #REF! | F52: =D52-E52 -> #ERROR! | H52: =C52 -> Hosting | I52: =D52 -> #ERROR! | K52: =SUMIFS(#REF!,#REF!,$C52)/$A$8 -> #N/A | M52: =H52 -> Hosting | N52: =I52 -> #ERROR! | P52: =SUMIFS(#REF!,#REF!,$C52)/$A$8 -> #N/A
C53: HUBSPOT + site ground | D53: 1600 | E53: =#REF!*1000 -> #REF! | F53: =D53-E53 -> #REF! | H53: =C53 -> HUBSPOT + site ground | M53: =H53 -> HUBSPOT + site ground
C54: Consultant | D54: =FS!#REF!+FS!#REF!+FS!#REF!+FS!#REF! -> #ERROR! | E54: =(#REF!+#REF!+#REF!+#REF!+#REF!)*1000 -> #REF! | F54: =D54-E54 -> #ERROR! | H54: =C54 -> Consultant | I54: =D54 -> #ERROR! | K54: =SUMIFS(#REF!,#REF!,$C54)/$A$8 -> #N/A | M54: =H54 -> Consultant | N54: =I54 -> #ERROR! | P54: =SUMIFS(#REF!,#REF!,$C54)/$A$8 -> #N/A
C55: Travel | D55: =FS!#REF!+FS!#REF!+FS!#REF!+FS!#REF!+FS!#REF! -> #ERROR! | E55: =(#REF!+#REF!+#REF!+#REF!+#REF!)*1000 -> #REF! | F55: =D55-E55 -> #ERROR! | H55: =C55 -> Travel | I55: =D55 -> #ERROR! | K55: =SUMIFS(#REF!,#REF!,$C55)/$A$8 -> #N/A | M55: =H55 -> Travel | N55: =I55 -> #ERROR! | P55: =SUMIFS(#REF!,#REF!,$C55)/$A$8 -> #N/A
C56: Others | D56: =FS!#REF!+FS!#REF!+FS!#REF!+FS!#REF!+FS!#REF! -> #ERROR! | E56: =(#REF!+#REF!+#REF!+#REF!+#REF!+#REF!+#REF!)*1000 -> #REF! | F56: =D56-E56 -> #ERROR! | H56: =C56 -> Others | I56: =D56 -> #ERROR! | K56: =SUMIFS(#REF!,#REF!,$C56)/$A$8 -> #N/A | M56: =H56 -> Others | N56: =I56 -> #ERROR! | P56: =SUMIFS(#REF!,#REF!,$C56)/$A$8 -> #N/A
C57: Commission | F57: =D57-E57 -> 0 | H57: =C57 -> Commission | I57: =D57 | K57: =SUMIFS(#REF!,#REF!,$C57)/$A$8 -> #N/A | M57: =H57 -> Commission | N57: =I57 | P57: =SUMIFS(#REF!,#REF!,$C57)/$A$8 -> #N/A
C58: Marketing | D58: =FS!#REF! -> #ERROR! | F58: =D58-E58 -> #ERROR! | H58: =C58 -> Marketing | I58: =D58 -> #ERROR! | K58: =SUMIFS(#REF!,#REF!,$C58)/$A$8 -> #N/A | M58: =H58 -> Marketing | N58: =I58 -> #ERROR! | P58: =SUMIFS(#REF!,#REF!,$C58)/$A$8 -> #N/A
C59: conference | D59: =FS!#REF!+FS!#REF!+FS!#REF! -> #ERROR! | E59: =#REF!*1000 -> #REF! | F59: =D59-E59 -> #ERROR! | H59: =C59 -> conference | I59: =D59 -> #ERROR! | K59: =SUMIFS(#REF!,#REF!,$C59)/$A$8 -> #N/A | M59: =H59 -> conference | N59: =I59 -> #ERROR! | P59: =SUMIFS(#REF!,#REF!,$C59)/$A$8 -> #N/A
C60: Rent & Utilities | D60: =FS!#REF!+FS!#REF! -> #ERROR! | E60: =#REF!*1000 -> #REF! | F60: =D60-E60 -> #ERROR! | H60: =C60 -> Rent & Utilities | I60: =D60 -> #ERROR! | K60: =SUMIFS(#REF!,#REF!,$C60)/$A$8 -> #N/A | M60: =H60 -> Rent & Utilities | N60: =I60 -> #ERROR! | P60: =SUMIFS(#REF!,#REF!,$C60)/$A$8 -> #N/A
C61: Welfare | D61: =FS!#REF!+FS!#REF!+FS!#REF! -> #ERROR! | E61: =#REF!*1000 -> #REF! | F61: =D61-E61 -> #ERROR! | H61: =C61 -> Welfare | I61: =D61 -> #ERROR! | K61: =SUMIFS(#REF!,#REF!,$C61)/$A$8 -> #N/A | M61: =H61 -> Welfare | N61: =I61 -> #ERROR! | P61: =SUMIFS(#REF!,#REF!,$C61)/$A$8 -> #N/A
C62: Professional | D62: =FS!#REF!+FS!#REF! -> #ERROR! | E62: =(#REF!+#REF!+#REF!+#REF!+#REF!)*1000 -> #REF! | F62: =D62-E62 -> #ERROR! | H62: =C62 -> Professional | I62: =D62 -> #ERROR! | K62: =SUMIFS(#REF!,#REF!,$C62)/$A$8 -> #N/A | M62: =H62 -> Professional | N62: =I62 -> #ERROR! | P62: =SUMIFS(#REF!,#REF!,$C62)/$A$8 -> #N/A
C63: IT | F63: =D63-E63 -> 0 | H63: =C63 -> IT | I63: =D63 | K63: =SUMIFS(#REF!,#REF!,$C63)/$A$8 -> #N/A | M63: =H63 -> IT | N63: =I63 | P63: =SUMIFS(#REF!,#REF!,$C63)/$A$8 -> #N/A
C64: Insurance | D64: =FS!#REF! -> #ERROR! | E64: =#REF!*1000 -> #REF! | F64: =D64-E64 -> #ERROR! | H64: =C64 -> Insurance | I64: =D64 -> #ERROR! | K64: =SUMIFS(#REF!,#REF!,$C64)/$A$8 -> #N/A | M64: =H64 -> Insurance | N64: =I64 -> #ERROR! | P64: =SUMIFS(#REF!,#REF!,$C64)/$A$8 -> #N/A
C65: Office exp. | D65: =FS!#REF! -> #ERROR! | E65: =#REF!*1000 -> #REF! | F65: =D65-E65 -> #ERROR! | H65: =C65 -> Office exp. | I65: =D65 -> #ERROR! | K65: =SUMIFS(#REF!,#REF!,$C65)/$A$8 -> #N/A | M65: =H65 -> Office exp. | N65: =I65 -> #ERROR! | P65: =SUMIFS(#REF!,#REF!,$C65)/$A$8 -> #N/A
C66: Compliance | F66: =D66-E66 -> 0 | H66: =C66 -> Compliance | I66: =D66 | K66: =SUMIFS(#REF!,#REF!,$C66)/$A$8 -> #N/A | M66: =H66 -> Compliance | N66: =I66 | P66: =SUMIFS(#REF!,#REF!,$C66)/$A$8 -> #N/A
C67: IN PERSOM MEETUPS | D67: =FS!#REF! -> #ERROR! | E67: =#REF!*1000 -> #REF! | F67: =D67-E67 -> #ERROR! | H67: =C67 -> IN PERSOM MEETUPS | I67: =D67 -> #ERROR! | K67: =SUMIFS(#REF!,#REF!,$C67)/$A$8 -> #N/A | M67: =H67 -> IN PERSOM MEETUPS | N67: =I67 -> #ERROR! | P67: =SUMIFS(#REF!,#REF!,$C67)/$A$8 -> #N/A
C68: Team building | E68: =#REF! -> #REF! | F68: =D68-E68 -> #REF! | H68: =C68 -> Team building | I68: =D68 | K68: =SUMIFS(#REF!,#REF!,$C68)/$A$8 -> #N/A | M68: =H68 -> Team building | N68: =I68 | P68: =SUMIFS(#REF!,#REF!,$C68)/$A$8 -> #N/A
C69: Taxes | F69: =D69-E69 -> 0 | H69: =C69 -> Taxes | I69: =D69 | K69: =SUMIFS(#REF!,#REF!,$C69)/$A$8 -> #N/A | M69: =H69 -> Taxes | N69: =I69 | P69: =SUMIFS(#REF!,#REF!,$C69)/$A$8 -> #N/A
C70: Linkedin | D70: =FS!#REF! -> #ERROR! | E70: 0 | F70: =D70-E70 -> #ERROR! | H70: =C70 -> Linkedin | I70: =D70 -> #ERROR! | K70: =SUMIFS(#REF!,#REF!,$C70)/$A$8 -> #N/A | M70: =H70 -> Linkedin | N70: =I70 -> #ERROR! | P70: =SUMIFS(#REF!,#REF!,$C70)/$A$8 -> #N/A
C71: Depreciation | D71: =FS!#REF! -> #ERROR! | E71: 0 | F71: =D71-E71 -> #ERROR! | I71: =D71 -> #ERROR! | K71: =SUMIFS(#REF!,#REF!,$C71)/$A$8 -> #N/A | N71: =I71 -> #ERROR! | P71: =SUMIFS(#REF!,#REF!,$C71)/$A$8 -> #N/A
C72: Total Opex | D72: =SUM(D48:D71) -> #ERROR! | E72: =SUM(E48:E71) -> #REF! | F72: =D72-E72 -> #ERROR! | H72: =C72 -> Total Opex | I72: =SUM(I48:I71) -> #ERROR! | J72: =SUM(J48:J71) -> 0 | K72: =SUM(K48:K71) -> #N/A | M72: =H72 -> Total Opex | N72: =SUM(N48:N71) -> #ERROR! | O72: =SUM(O48:O71) -> 0 | P72: =SUM(P48:P71) -> #N/A
D73: =D72-D74 -> #ERROR! | E73: =E72-E74 -> #REF! | I73: =IF(ROUND(I72*$A$8,0)=ROUND(SUM(I15,I24)*$A$8,0),"","Error") -> #ERROR! | J73: =IF(ROUND(J72*$A$8,0)=ROUND(SUM(J15,J24)*$A$8,0),"","Error") -> #REF! | N73: =IF(ROUND(N72*$A$8,0)=ROUND(SUM(N15,N24)*$A$8,0),"","Error") -> #ERROR! | O73: =IF(ROUND(O72*$A$8,0)=ROUND(SUM(O15,O24)*$A$8,0),"","Error") -> #REF!
D74: =D24+D15 -> #ERROR! | E74: =(#REF!+#REF!)*1000 -> #REF!

Sheet Reports
K1: =A10 | P1: =K1 | U1: =P1
G2: Balance Sheets | L2: =G2 -> Balance Sheets | Q2: Statements of operations
G3: USD in thousands | L3: =G3 -> USD in thousands | Q3: =L3 -> USD in thousands
T4: DRAFT
J5: DRAFT | O5: DRAFT | T5: For the period ended
J6: =WP_LTD!C9 -> 44926 | O6: =J6 -> 44926 | T6: =O6 -> 44926
J7: UNAUDITED | O7: =J7 -> UNAUDITED | T7: =O7 -> UNAUDITED
G9: CURRENT ASSETS | L9: CURRENT LIABILITIES | Q9: Revenues | T9: =-ROUND(FS!M79/1000,0) -> 1487
A10: =+WP_LTD!B3 | G10: Cash and short term deposit | J10: =ROUND(FS!M11/1000,0) -> 1795 | L10: Trade payables | O10: =-ROUND(FS!M37/1000,0)+1 -> 117 | Q10: Cost of revenues | T10: =ROUND(FS!M87/1000,0) -> 81 | X10: =T10/T9 -> 0.054472091
G11: Short-term Deposits | J11: =ROUND(FS!M13/1000,0) -> 7600 | L11: Employees and related | O11: =-ROUND(FS!M38/1000,0) -> 312 | Q11: Gross Profit/(Loss) | T11: =T9-T10 -> 1406 | X11: =T11/T9 -> 0.94552791
G12: Other account receivable & prepaid expenses | J12: =ROUND((FS!M14+FS!M17)/1000,0) -> 129 | L12: Other current liabilities | O12: =-ROUND((FS!M39)/1000,0) -> 11
G13: Total current assets | J13: =SUM(J10:J12) -> 9524 | L13: Total current liabilities | O13: =SUM(O10:O12) -> 440 | Q13: Operation Expenses:
Q14: Research and Development | T14: =ROUND(FS!M110/1000,0) -> 3455 | X14: =T14/$T$17 -> 0.66111749
A15: Unaudited financial statements | G15: NON-CURRENT ASSETS | L15: NON-CURRENT LIABILITIES | Q15: Sales and Marketing | T15: =ROUND(FS!M129/1000,0) -> 826 | X15: =T15/$T$17 -> 0.15805587
G16: Long-term Deposits | J16: =ROUND(FS!M21/1000,0) -> 34 | L16: Convertible Loan | O16: =-ROUND(FS!M41/1000,0) -> 0 | Q16: General and Administrative | T16: =ROUND(FS!M187/1000,0) -> 945 | X16: =T16/$T$17 -> 0.18082664
A17: =WP_LTD!B4 -> As of Dec 31, 2022 | G17: Property and equipment, NET | J17: =ROUND(FS!M28/1000,0) -> 295 | L17: Total Non-current liabilities | O17: =O16 -> 0 | Q17: Total Operating expenses | T17: =SUM(T14:T16) -> 5226
G18: Total Non-current assets | J18: =SUM(J16:J17) -> 329
D19: DRAFT
L20: SHAREHOLDERS EQUITY/(DEFICIENCY) | Q20: Loss From Operations | T20: =T17-T11 -> 3820
L22: Share capital & Additional paid-in capital | O22: =-ROUND((FS!M56+FS!M61+FS!M62+FS!M64)/1000,0) -> 22801 | Q22: Financial Expenses/(income) | T22: =ROUND(FS!M193/1000,0)-1 -> -11
L23: Accumulated profit/(loss) | O23: =-ROUND((FS!M65+FS!M66)/1000,0) -> -10728 | Q23: Other Expenses / (Income) | T23: =ROUND(FS!M194/1000,0) -> 0
L24: Total Shareholder's Equity/(deficiency) | O24: =SUM(O22:O23) -> 12073 | Q24: Tax Expenses | T24: =ROUND(FS!M194/1000,0) -> 0
G27: Total Assets | J27: =J13+J18 -> 9853 | L27: Total Liability and shareholders equity | O27: =O13+O24+O17 -> 12513 | Q27: Net Loss | T27: =T20+T22+T24 -> 3809
M29: =J27-O27 -> -2660
G35: Page 1 | L35: Page 2 | Q35: Page 3
A37: Financial Solutions | Q37: Page 3

Sheet FS
B3: Financial Statements
B4: =WP_LTD!B4 -> As of Dec 31, 2022
B5: In NIS
C6: LTD | I6: INC | K6: AJE | M6: Consolidated | O6: 44926 | P6: Budget | Q6: ישראל | R6: אינק | S6: הערות
C7: IL | E7: $ | I7: $ | M7: $
B8: ASSETS
B10: Current assets
A11: 1 | B11: Cash and cash equivalents LTD | C11: =SUMIF(GL_LTD!$J:$J,A11,GL_LTD!$I:$I) -> 6315593.8 | E11: =SUMIF(GL_LTD!$J:$J,A11,GL_LTD!$G:$G) -> 1794712.6 | G11: =IFERROR(C11/E11,0) -> 3.519 | I11: =SUMIF(GL_INC!G:G,A11,GL_INC!F:F) -> 0 | M11: =SUM(E11+I11) -> 1794712.6 | O11: 9428530.8 | Q11: תקין
A12: 1.5 | B12: Cash and cash equivalents US | C12: =SUMIF(GL_LTD!$J:$J,A12,GL_LTD!$I:$I) -> 0 | E12: =SUMIF(GL_LTD!$J:$J,A12,GL_LTD!$G:$G) -> 0 | G12: =IFERROR(C12/E12,0) -> 0 | I12: =SUMIF(GL_INC!G:G,A12,GL_INC!F:F) -> 2966550.7 | M12: =SUM(E12+I12) -> 2966550.7 | O12: 2965550.7 | R12: תקין
A13: 2 | B13: Short-term Deposits | C13: =SUMIF(GL_LTD!$J:$J,A13,GL_LTD!$I:$I) -> 26744400 | E13: =SUMIF(GL_LTD!$J:$J,A13,GL_LTD!$G:$G) -> 7600000 | G13: =IFERROR(C13/E13,0) -> 3.519 | I13: =SUMIF(GL_INC!G:G,A13,GL_INC!F:F) -> 0 | M13: =SUM(E13+I13) -> 7600000 | Q13: תקין - ראה בדיקת מזומנים
A14: 5 | B14: Accounts Receivables | C14: =SUMIF(GL_LTD!$J:$J,A14,GL_LTD!$I:$I) -> 11691.9 | E14: =SUMIF(GL_LTD!$J:$J,A14,GL_LTD!$G:$G) -> 3300 | G14: =IFERROR(C14/E14,0) -> 3.543 | I14: =SUMIF(GL_INC!G:G,A14,GL_INC!F:F) -> 0 | M14: =SUM(E14+I14) -> 3300 | O14: 0 | Q14: תקין
A15: 6 | B15: Intercompany | C15: =SUMIF(GL_LTD!$J:$J,A15,GL_LTD!$I:$I) -> -6512491.1 | E15: =SUMIF(GL_LTD!$J:$J,A15,GL_LTD!$G:$G) -> -1850665.3 | G15: =IFERROR(C15/E15,0) -> 3.519 | I15: =SUMIF(GL_INC!G:G,A15,GL_INC!F:F) -> 19978310 | M15: =SUM(E15+I15) -> 18127645 | O15: 0
A16: 7.1 | B16: Prepaid expenses | C16: =SUMIF(GL_LTD!$J:$J,A16,GL_LTD!$I:$I) -> 199115.83 | E16: =SUMIF(GL_LTD!$J:$J,A16,GL_LTD!$G:$G) -> 58556.86 | G16: =IFERROR(C16/E16,0) -> 3.4003843 | I16: =SUMIF(GL_INC!G:G,A16,GL_INC!F:F) -> 19852.35 | M16: =SUM(E16+I16) -> 78409.21 | O16: 76421.53 | Q16: טיסות קינג 35 אלפד MARCH 2023 -CloserStill - 18K | R16: Gong - $9.3K
A17: 7 | B17: Other receivables | C17: =C222 -> 173018.36 | E17: =E222 -> 49176.387 | G17: =IFERROR(C17/E17,0) -> 3.518322 | I17: =I222 -> 76966.74 | M17: =SUM(E17+I17) -> 126143.13 | O17: 106017.44 | Q17: תקין | R17: Deposit Papaya - $56K | S17: לבדוק מיליון מניות של עינת ושל עוז כל אחד - מול מה נרשם?
G18: =IFERROR(C18/E18,0) -> 0 | I18: =SUMIF(GL_INC!G:G,A18,GL_INC!F:F) -> 0 | M18: =SUM(E18+I18) -> 0
B19: Total Current assets | C19: =SUM(C11:C18) -> 26931329 | E19: =SUM(E11:E18) -> 7655080.6 | G19: =IFERROR(C19/E19,0) -> 3.5180987 | I19: =SUM(I11:I18) -> 23041680 | M19: =SUM(M11:M18) -> 30696761 | O19: =SUM(O11:O17) -> 12576520
G20: =IFERROR(C20/E20,0) -> 0 | M20: =SUM(E20+I20) -> 0
A21: 20.1 | B21: Restricted deposit | C21: =SUMIF(GL_LTD!$J:$J,A21,GL_LTD!$I:$I) -> 120409.93 | E21: =SUMIF(GL_LTD!$J:$J,A21,GL_LTD!$G:$G) -> 34217.09 | G21: =IFERROR(C21/E21,0) -> 3.5189997 | I21: =SUMIF(GL_INC!G:G,A21,GL_INC!F:F) -> 0 | M21: =SUM(E21+I21) -> 34217.09 | Q21: תקין - ראה בדיקת מזומנים
A22: 20 | B22: Long term Assets | C22: =C21 -> 120409.93 | E22: =E21 -> 34217.09 | G22: =IFERROR(C22/E22,0) -> 3.5189997 | I22: =I21 -> 0 | M22: =M21 -> 34217.09
G23: =IFERROR(C23/E23,0) -> 0 | M23: =SUM(E23+I23) -> 0
G24: =IFERROR(C24/E24,0) -> 0 | M24: =SUM(E24+I24) -> 0
B25: Fixed assets | G25: =IFERROR(C25/E25,0) -> 0 | M25: =SUM(E25+I25) -> 0
A26: 21 | B26: Fixed assets | C26: =SUMIF(GL_LTD!$J:$J,A26,GL_LTD!$I:$I) -> 1160559.5 | E26: =SUMIF(GL_LTD!$J:$J,A26,GL_LTD!$G:$G) -> 359332.47 | G26: =IFERROR(C26/E26,0) -> 3.2297652 | I26: =SUMIF(GL_INC!G:G,A26,GL_INC!F:F) -> 12994.45 | M26: =SUM(E26+I26) -> 372326.92 | O26: 372326.89
A27: 22 | B27: Accumulated depreciation | C27: =SUMIF(GL_LTD!$J:$J,A27,GL_LTD!$I:$I) -> -249045.12 | E27: =SUMIF(GL_LTD!$J:$J,A27,GL_LTD!$G:$G) -> -75295.25 | G27: =IFERROR(C27/E27,0) -> 3.3075808 | I27: =SUMIF(GL_INC!G:G,A27,GL_INC!F:F) -> -2382.7 | M27: =SUM(E27+I27) -> -77677.95 | O27: -77677.95
B28: Total Fixed assets | C28: =SUM(C26:C27) -> 911514.4 | E28: =SUM(E26:E27) -> 284037.22 | G28: =IFERROR(C28/E28,0) -> 3.2091372 | I28: =SUM(I26:I27) -> 10611.75 | M28: =SUM(E28+I28) -> 294648.97 | O28: =SUM(O26:O27) -> 294648.94 | Q28: לבקש טופס פחת
G29: =IFERROR(C29/E29,0) -> 0 | M29: =SUM(E29+I29) -> 0
A30: 25 | B30: Other Assets | C30: =SUMIF(GL_LTD!$J:$J,A30,GL_LTD!$I:$I) -> 0 | E30: =SUMIF(GL_LTD!$J:$J,A30,GL_LTD!$G:$G) -> 0 | G30: =IFERROR(C30/E30,0) -> 0 | I30: =SUMIF(GL_INC!G:G,A30,GL_INC!F:F) -> 0 | M30: =SUM(E30+I30) -> 0
G31: =IFERROR(C31/E31,0) -> 0 | M31: =SUM(E31+I31) -> 0
B32: Total Assets | C32: =C28+C19+C30+C22 -> 27963253 | E32: =E28+E19+E30+E22 -> 7973334.9 | G32: =IFERROR(C32/E32,0) -> 3.5070963 | I32: =I28+I19+I30+I22 -> 23052292 | M32: =M28+M19+M30+M22 -> 31025627 | O32: =O28+O19+O30+O22 -> 12871169
G33: =IFERROR(C33/E33,0) -> 0 | M33: =SUM(E33+I33) -> 0
B34: LIABILITIES | G34: =IFERROR(C34/E34,0) -> 0 | M34: =SUM(E34+I34) -> 0
G35: =IFERROR(C35/E35,0) -> 0 | M35: =SUM(E35+I35) -> 0
B36: Current liabilities | G36: =IFERROR(C36/E36,0) -> 0 | M36: =SUM(E36+I36) -> 0
A37: 31 | B37: Accounts payables | C37: =C236 -> -337109.07 | E37: =E236 -> -95796.83 | G37: =IFERROR(C37/E37,0) -> 3.5190003 | I37: =I236 -> -20271.55 | M37: =SUM(E37+I37) -> -116068.38 | O37: -82839.51 | Q37: תקין
A38: 33 | B38: Employees and related | C38: =C229 -> -1100045.1 | E38: =E229 -> -312370.54 | G38: =IFERROR(C38/E38,0) -> 3.5216031 | I38: =I229 -> 0 | M38: =SUM(E38+I38) -> -312370.54 | O38: -310976.71 | Q38: תקין
A39: 34 | B39: Other current liabilities | C39: =SUMIF(GL_LTD!$J:$J,A39,GL_LTD!$I:$I) -> -30000 | E39: =SUMIF(GL_LTD!$J:$J,A39,GL_LTD!$G:$G) -> -8525.15 | G39: =IFERROR(C39/E39,0) -> 3.5189997 | I39: =SUMIF(GL_INC!G:G,A39,GL_INC!F:F) -> -2662.5 | M39: =SUM(E39+I39) -> -11187.65 | O39: -11187.65 | Q39: פקדון שכירות מהשוכר בייס לאבס
A40: 38 | B40: Accrued Expenses | C40: =SUMIF(GL_LTD!$J:$J,A40,GL_LTD!$I:$I) -> -464040.8 | E40: =SUMIF(GL_LTD!$J:$J,A40,GL_LTD!$G:$G) -> -131867.24 | G40: =IFERROR(C40/E40,0) -> 3.5189999 | I40: =SUMIF(GL_INC!G:G,A40,GL_INC!F:F) -> -142024 | M40: =SUM(E40+I40) -> -273891.24 | O40: -126218.42 | Q40: תקין
A41: 35 | B41: Shareholders liability | C41: =SUMIF(GL_LTD!$J:$J,A41,GL_LTD!$I:$I) -> 0 | E41: =SUMIF(GL_LTD!$J:$J,A41,GL_LTD!$G:$G) -> 0 | G41: =IFERROR(C41/E41,0) -> 0 | I41: =SUMIF(GL_INC!G:G,A41,GL_INC!F:F) -> 0 | M41: =SUM(E41+I41) -> 0 | O41: 0
A42: 37 | B42: Deferred revenues | C42: =SUMIF(GL_LTD!$J:$J,A42,GL_LTD!$I:$I) -> -2748.83 | E42: =SUMIF(GL_LTD!$J:$J,A42,GL_LTD!$G:$G) -> -1249.65 | G42: =IFERROR(C42/E42,0) -> 2.1996799 | I42: =SUMIF(GL_INC!G:G,A42,GL_INC!F:F) -> -77620.96 | M42: =SUM(E42+I42) -> -78870.61 | O42: -78870.61 | Q42: תקין | R42: תקין
A43: 36 | B43: Intercompany | C43: =SUMIF(GL_LTD!$J:$J,A43,GL_LTD!$I:$I) -> 0 | E43: =SUMIF(GL_LTD!$J:$J,A43,GL_LTD!$G:$G) -> 0 | G43: =IFERROR(C43/E43,0) -> 0 | I43: =SUMIF(GL_INC!G:G,A43,GL_INC!F:F) -> 0 | M43: =SUM(E43+I43) -> 0
B44: Total Current liabilities | C44: =SUM(C37:C43) -> -1933943.8 | E44: =SUM(E37:E43) -> -549809.41 | G44: =IFERROR(C44/E44,0) -> 3.5174803 | I44: =SUM(I37:I43) -> -242579.01 | M44: =SUM(M37:M43) -> -792388.42 | O44: =SUM(O37:O43) -> -610092.9
G45: =IFERROR(C45/E45,0) -> 0 | M45: =SUM(E45+I45) -> 0
B46: Long term liabilities | G46: =IFERROR(C46/E46,0) -> 0 | M46: =SUM(E46+I46) -> 0
A47: 40 | B47: Severance pay | C47: =SUMIF(GL_LTD!$J:$J,A47,GL_LTD!$I:$I) -> 0 | E47: =SUMIF(GL_LTD!$J:$J,A47,GL_LTD!$G:$G) -> 0 | G47: =IFERROR(C47/E47,0) -> 0 | I47: =SUMIF(GL_INC!G:G,A47,GL_INC!F:F) -> 0 | M47: =SUM(E47+I47) -> 0
A48: 41 | B48: Convertible Loans | C48: =SUMIF(GL_LTD!$J:$J,A48,GL_LTD!$I:$I) -> 0 | E48: =SUMIF(GL_LTD!$J:$J,A48,GL_LTD!$G:$G) -> 0 | G48: =IFERROR(C48/E48,0) -> 0 | I48: =SUMIF(GL_INC!G:G,A48,GL_INC!F:F) -> 0 | M48: =SUM(E48+I48) -> 0
A49: 43 | B49: Long Term deferred revenues | C49: =SUMIF(GL_LTD!$J:$J,A49,GL_LTD!$I:$I) -> 0 | E49: =SUMIF(GL_LTD!$J:$J,A49,GL_LTD!$G:$G) -> 0 | G49: =IFERROR(C49/E49,0) -> 0 | I49: =SUMIF(GL_INC!G:G,A49,GL_INC!F:F) -> 0 | M49: =SUM(E49+I49) -> 0
A50: 42 | B50: Shareholders liabilities | C50: =SUMIF(GL_LTD!$J:$J,A50,GL_LTD!$I:$I) -> 0 | E50: =SUMIF(GL_LTD!$J:$J,A50,GL_LTD!$G:$G) -> 0 | G50: =IFERROR(C50/E50,0) -> 0 | I50: =SUMIF(GL_INC!G:G,A50,GL_INC!F:F) -> 0 | M50: =SUM(E50+I50) -> 0
B51: Total long term liabilities | C51: =SUM(C47:C50) -> 0 | E51: =SUM(E47:E50) -> 0 | G51: =IFERROR(C51/E51,0) -> 0 | I51: =SUM(I47:I50) -> 0 | M51: =SUM(E51+I51) -> 0
G52: =IFERROR(C52/E52,0) -> 0 | M52: =SUM(E52+I52) -> 0
B53: Total Liabilities | C53: =C51+C44 -> -1933943.8 | E53: =E51+E44 -> -549809.41 | G53: =IFERROR(C53/E53,0) -> 3.5174803 | I53: =I51+I44 -> -242579.01 | M53: =M51+M44 -> -792388.42 | O53: =O51+O44 -> -610092.9
G54: =IFERROR(C54/E54,0) -> 0 | M54: =SUM(E54+I54) -> 0
B55: Shareholders’ deficiency | G55: =IFERROR(C55/E55,0) -> 0 | M55: =SUM(E55+I55) -> 0
A56: 50 | B56: Share capital | C56: =SUMIF(GL_LTD!$J:$J,A56,GL_LTD!$I:$I) -> 0 | E56: =SUMIF(GL_LTD!$J:$J,A56,GL_LTD!$G:$G) -> 0 | G56: =IFERROR(C56/E56,0) -> 0 | I56: =SUMIF(GL_INC!G:G,A56,GL_INC!F:F) -> 0 | M56: =SUM(E56+I56) -> 0
A57: 50.1 | B57: Series seed Preferred Stock | C57: =SUMIF(GL_LTD!$J:$J,A57,GL_LTD!$I:$I) -> 0 | E57: =SUMIF(GL_LTD!$J:$J,A57,GL_LTD!$G:$G) -> 0 | I57: =SUMIF(GL_INC!G:G,A57,GL_INC!F:F) -> 0 | M57: =SUM(E57+I57) -> 0
A58: 50.2 | B58: Series A Preferred Stock | C58: =SUMIF(GL_LTD!$J:$J,A58,GL_LTD!$I:$I) -> 0 | E58: =SUMIF(GL_LTD!$J:$J,A58,GL_LTD!$G:$G) -> 0 | I58: =SUMIF(GL_INC!G:G,A58,GL_INC!F:F) -> 0 | M58: =SUM(E58+I58) -> 0
A59: 50.3 | B59: Seed Round shares | C59: =SUMIF(GL_LTD!$J:$J,A59,GL_LTD!$I:$I) -> 0 | E59: =SUMIF(GL_LTD!$J:$J,A59,GL_LTD!$G:$G) -> 0 | I59: =SUMIF(GL_INC!G:G,A59,GL_INC!F:F) -> 0 | M59: =SUM(E59+I59) -> 0
A60: 50.4 | B60: Preferred A shares | C60: =SUMIF(GL_LTD!$J:$J,A60,GL_LTD!$I:$I) -> 0 | E60: =SUMIF(GL_LTD!$J:$J,A60,GL_LTD!$G:$G) -> 0 | I60: =SUMIF(GL_INC!G:G,A60,GL_INC!F:F) -> 0 | M60: =SUM(E60+I60) -> 0
A61: 51 | B61: Additional paid-in capital | C61: =SUMIF(GL_LTD!$J:$J,A61,GL_LTD!$I:$I) -> 0 | E61: =SUMIF(GL_LTD!$J:$J,A61,GL_LTD!$G:$G) -> 0 | G61: =IFERROR(C61/E61,0) -> 0 | I61: =SUMIF(GL_INC!G:G,A61,GL_INC!F:F) -> -23009114 | M61: =SUM(E61+I61) -> -23009114 | O61: -22989114 | R61: השקעה בסך של 120 אלף ועוד 535 אלף
A62: 56 | B62: Notes Receivable for shares issued | C62: =SUMIF(GL_LTD!$J:$J,A62,GL_LTD!$I:$I) -> 0 | E62: =SUMIF(GL_LTD!$J:$J,A62,GL_LTD!$G:$G) -> 0 | G62: =IFERROR(C62/E62,0) -> 0 | I62: =SUMIF(GL_INC!G:G,A62,GL_INC!F:F) -> 0 | M62: =SUM(E62+I62) -> 0
A63: 54 | B63: Stock compensation | C63: =SUMIF(GL_LTD!$J:$J,A63,GL_LTD!$I:$I) -> 0 | E63: =SUMIF(GL_LTD!$J:$J,A63,GL_LTD!$G:$G) -> 0 | G63: =IFERROR(C63/E63,0) -> 0 | I63: =SUMIF(GL_INC!G:G,A63,GL_INC!F:F) -> -32476.959 | M63: =SUM(E63+I63) -> -32476.959
A64: 55 | B64: Issuance expenses | C64: =SUMIF(GL_LTD!$J:$J,A64,GL_LTD!$I:$I) -> -0.4 | E64: =SUMIF(GL_LTD!$J:$J,A64,GL_LTD!$G:$G) -> 0.35 | G64: =IFERROR(C64/E64,0) -> -1.1428571 | I64: =SUMIF(GL_INC!G:G,A64,GL_INC!F:F) -> 208091.78 | M64: =SUM(E64+I64) -> 208092.13 | O64: 208092.13
A65: 52 | B65: Net Profit (loss) For the period | C65: =C199 -> 22748108 | E65: =E199 -> 6730288.5 | G65: =IFERROR(C65/E65,0) -> 3.3799604 | I65: =I199 -> 47411.659 | M65: =SUM(E65+I65) -> 6777700.1 | U65: בדיקת עודפים
A66: 53 | B66: Accumulated loss | C66: =SUMIF(GL_LTD!$J:$J,A66,GL_LTD!$I:$I) -> 13345316 | E66: =SUMIF(GL_LTD!$J:$J,A66,GL_LTD!$G:$G) -> 3973830.5 | G66: =IFERROR(C66/E66,0) -> 3.3583002 | I66: =SUMIF(GL_INC!G:G,A66,GL_INC!F:F) -> -23624.69 | M66: =SUM(E66+I66) -> 3950205.8 | O66: 10519946 | R66: תקין | V66: דוח חתום 31.12.20 -₪
B67: Total Shareholders’ deficiency | C67: =SUM(C56:C66) -> 36093424 | E67: =SUM(E56:E66) -> 10704119 | G67: =IFERROR(C67/E67,0) -> 3.371919 | I67: =SUM(I56:I66) -> -22809713 | M67: =SUM(M56:M66) -> -12105593 | O67: =SUM(O56:O66) -> -12261076 | U67: =C66 -> 13345316 | V67: הרכבה
G68: =IFERROR(C68/E68,0) -> 0 | M68: =SUM(E68+I68) -> 0 | U68: =U67-U66 -> 13345316 | V68: הפרש
B69: Total Passive | C69: =C67+C53 -> 34159480 | E69: =E67+E53 -> 10154310 | G69: =IFERROR(C69/E69,0) -> 3.3640376 | I69: =I67+I53 -> -23052292 | M69: =M67+M53 -> -12897982 | O69: =O67+O53 -> -12871169
G70: =IFERROR(C70/E70,0) -> 0 | M70: =SUM(E70+I70) -> 0 | V70: דוח חתום 31.12.20 -$
B71: CHECK! | C71: =C69+C32 -> 62122733 | E71: =E69+E32 -> 18127645 | G71: =IFERROR(C71/E71,0) -> 3.4269611 | I71: =I69+I32 -> 0 | M71: =SUM(E71+I71) -> 18127645 | O71: =SUM(G71+K71) -> 3.4269611 | R71: בונוס לוינו 4171 בחודש מאי | S71: להוסיף למייל שאלות לאסקלון | U71: =E66 -> 3973830.5 | V71: הרכבה
G72: =IFERROR(C72/E72,0) -> 0 | M72: =SUM(E72+I72) -> 0 | U72: =U71-U70 -> 3973830.5 | V72: הפרש
G73: =IFERROR(C73/E73,0) -> 0 | M73: =SUM(E73+I73) -> 0
G74: =IFERROR(C74/E74,0) -> 0 | M74: =SUM(E74+I74) -> 0 | V74: דוח חתום 31.12.20
B75: P&L | G75: =IFERROR(C75/E75,0) -> 0 | M75: =SUM(E75+I75) -> 0 | U75: =I66 -> -23624.69 | V75: הרכבה
G76: =IFERROR(C76/E76,0) -> 0 | M76: =SUM(E76+I76) -> 0 | U76: =U75-U74 -> -23624.69 | V76: הפרש
A77: 100 | B77: Revenues | C77: =SUMIF(GL_LTD!$J:$J,A77,GL_LTD!$I:$I) -> -59058.4 | E77: =SUMIF(GL_LTD!$J:$J,A77,GL_LTD!$G:$G) -> -17050 | G77: =IFERROR(C77/E77,0) -> 3.4638358 | I77: =SUMIF(GL_INC!G:G,A77,GL_INC!F:F) -> -32379.04 | M77: =SUM(E77+I77) -> -49429.04 | O77: -10417 | Q77: הכנס מהרצאה 3.3 אלפד ומלקוחות 13ת750 | R77: enigma -16,250 Lockheed Martin - 16,129
A78: 101 | B78: LRD Model | C78: =SUMIF(GL_LTD!$J:$J,A78,GL_LTD!$I:$I) -> 0 | E78: =SUMIF(GL_LTD!$J:$J,A78,GL_LTD!$G:$G) -> 0 | G78: =IFERROR(C78/E78,0) -> 0 | I78: =SUMIF(GL_INC!G:G,A78,GL_INC!F:F) -> -1437700.3 | K78: =-E78 -> 0 | M78: =SUM(E78+I78+K78) -> -1437700.3
B79: Total revenues | C79: =SUM(C77:C78) -> -59058.4 | E79: =SUM(E77:E78) -> -17050 | I79: =SUM(I77:I78) -> -1470079.3 | M79: =SUM(M77:M78) -> -1487129.3
G80: =IFERROR(C80/E80,0) -> 0 | M80: =SUM(E80+I80) -> 0
B81: Cost of revenues | G81: =IFERROR(C81/E81,0) -> 0 | M81: =SUM(E81+I81) -> 0
A82: 200 | B82: COS - AWS | C82: =SUMIF(GL_LTD!$J:$J,A82,GL_LTD!$I:$I) -> 282419.76 | E82: =SUMIF(GL_LTD!$J:$J,A82,GL_LTD!$G:$G) -> 81178.57 | G82: =IFERROR(C82/E82,0) -> 3.478994 | I82: =SUMIF(GL_INC!G:G,A82,GL_INC!F:F) -> 0 | M82: =SUM(E82+I82) -> 81178.57 | O82: 17961 | P82: 28560
A83: 201 | B83: Payroll & Related | C83: =SUMIF(GL_LTD!$J:$J,A83,GL_LTD!$I:$I) -> 0 | E83: =SUMIF(GL_LTD!$J:$J,A83,GL_LTD!$G:$G) -> 0 | G83: =IFERROR(C83/E83,0) -> 0 | I83: =SUMIF(GL_INC!G:G,A83,GL_INC!F:F) -> 0 | M83: =SUM(E83+I83) -> 0
A84: 204 | B84: T&E | C84: =SUMIF(GL_LTD!$J:$J,A84,GL_LTD!$I:$I) -> 0 | E84: =SUMIF(GL_LTD!$J:$J,A84,GL_LTD!$G:$G) -> 0 | G84: =IFERROR(C84/E84,0) -> 0 | I84: =SUMIF(GL_INC!G:G,A84,GL_INC!F:F) -> 0 | M84: =SUM(E84+I84) -> 0
A85: 202 | B85: Other Cost of revenues | C85: =SUMIF(GL_LTD!$J:$J,A85,GL_LTD!$I:$I) -> 0 | E85: =SUMIF(GL_LTD!$J:$J,A85,GL_LTD!$G:$G) -> 0 | G85: =IFERROR(C85/E85,0) -> 0 | I85: =SUMIF(GL_INC!G:G,A85,GL_INC!F:F) -> 0 | M85: =SUM(E85+I85) -> 0
A86: 203 | B86: Allocation of Overhead | C86: =SUMIF(GL_LTD!$J:$J,A86,GL_LTD!$I:$I) -> 0 | E86: =SUMIF(GL_LTD!$J:$J,A86,GL_LTD!$G:$G) -> 0 | G86: =IFERROR(C86/E86,0) -> 0 | I86: =SUMIF(GL_INC!G:G,A86,GL_INC!F:F) -> 0 | M86: =SUM(E86+I86) -> 0
B87: Total COGS expenses | C87: =SUM(C82:C86) -> 282419.76 | E87: =SUM(E82:E86) -> 81178.57 | G87: =IFERROR(C87/E87,0) -> 3.478994 | I87: =SUM(I82:I86) -> 0 | M87: =SUM(M80:M86) -> 81178.57 | O87: =SUM(O80:O86) -> 17961
G88: =IFERROR(C88/E88,0) -> 0 | M88: =SUM(E88+I88) -> 0
B89: Gross Profit | C89: =C79+C87 -> 223361.36 | E89: =E79+E87 -> 64128.57 | G89: =IFERROR(C89/E89,0) -> 3.4830242 | I89: =I79+I87 -> -1470079.3 | M89: =M79+M87 -> -1405950.8
G90: =IFERROR(C90/E90,0) -> 0 | M90: =SUM(E90+I90) -> 0
B91: Expenses | G91: =IFERROR(C91/E91,0) -> 0 | M91: =SUM(E91+I91) -> 0
G92: =IFERROR(C92/E92,0) -> 0 | M92: =SUM(E92+I92) -> 0
B93: R&D | G93: =IFERROR(C93/E93,0) -> 0 | M93: =SUM(E93+I93) -> 0
A94: 300 | B94: Payroll and related (r&d) | C94: =SUMIF(GL_LTD!$J:$J,A94,GL_LTD!$I:$I) -> 8482074.9 | E94: =SUMIF(GL_LTD!$J:$J,A94,GL_LTD!$G:$G) -> 2504687.6 | G94: =IFERROR(C94/E94,0) -> 3.3864802 | I94: =SUMIF(GL_INC!G:G,A94,GL_INC!F:F) -> 0 | M94: =SUM(E94+I94) -> 2504687.6 | O94: 234780 | P94: 243326.6
A95: 308 | B95: Recruting (R&D) | C95: =SUMIF(GL_LTD!$J:$J,A95,GL_LTD!$I:$I) -> 1215.77 | E95: =SUMIF(GL_LTD!$J:$J,A95,GL_LTD!$G:$G) -> 379.24 | G95: =IFERROR(C95/E95,0) -> 3.2058064 | I95: =SUMIF(GL_INC!G:G,A95,GL_INC!F:F) -> 23000 | M95: =SUM(E95+I95) -> 23379.24 | O95: 379 | P95: 1886 | T95: תקין
A96: 301 | B96: Expenses related to employees | C96: =SUMIF(GL_LTD!$J:$J,A96,GL_LTD!$I:$I) -> 368.8 | E96: =SUMIF(GL_LTD!$J:$J,A96,GL_LTD!$G:$G) -> 111.12 | G96: =IFERROR(C96/E96,0) -> 3.3189345 | I96: =SUMIF(GL_INC!G:G,A96,GL_INC!F:F) -> 0 | M96: =SUM(E96+I96) -> 111.12
A97: 303 | B97: Travel abroad | C97: =SUMIF(GL_LTD!$J:$J,A97,GL_LTD!$I:$I) -> 159019.35 | E97: =SUMIF(GL_LTD!$J:$J,A97,GL_LTD!$G:$G) -> 46979.23 | G97: =IFERROR(C97/E97,0) -> 3.3848863 | I97: =SUMIF(GL_INC!G:G,A97,GL_INC!F:F) -> 0 | M97: =SUM(E97+I97) -> 46979.23 | P97: 6000 | T97: דמי ביטול - 360 דולר
A98: 304 | B98: Consultants R&D | C98: =SUMIF(GL_LTD!$J:$J,A98,GL_LTD!$I:$I) -> 1032263.8 | E98: =SUMIF(GL_LTD!$J:$J,A98,GL_LTD!$G:$G) -> 307085.1 | G98: =IFERROR(C98/E98,0) -> 3.3614909 | I98: =SUMIF(GL_INC!G:G,A98,GL_INC!F:F) -> 0 | M98: =SUM(E98+I98) -> 307085.1 | O98: 17082 | P98: 2500 | T98: תקין
A99: 305 | B99: Other R&D expenses | C99: =SUMIF(GL_LTD!$J:$J,A99,GL_LTD!$I:$I) -> 0 | E99: =SUMIF(GL_LTD!$J:$J,A99,GL_LTD!$G:$G) -> 0 | G99: =IFERROR(C99/E99,0) -> 0 | I99: =SUMIF(GL_INC!G:G,A99,GL_INC!F:F) -> 0 | M99: =SUM(E99+I99) -> 0 | P99: 500
A100: 302 | B100: R&D Software | C100: =SUMIF(GL_LTD!$J:$J,A100,GL_LTD!$I:$I) -> 377422.87 | E100: =SUMIF(GL_LTD!$J:$J,A100,GL_LTD!$G:$G) -> 111355.71 | G100: =IFERROR(C100/E100,0) -> 3.3893446 | I100: =SUMIF(GL_INC!G:G,A100,GL_INC!F:F) -> 663 | M100: =SUM(E100+I100) -> 112018.71 | O100: 10945 | P100: 11500
A101: 323 | B101: Allocation to other departments | C101: =SUMIF(GL_LTD!$J:$J,A101,GL_LTD!$I:$I) -> 533869.57 | E101: =SUMIF(GL_LTD!$J:$J,A101,GL_LTD!$G:$G) -> 159905.79 | G101: =IFERROR(C101/E101,0) -> 3.3386506 | I101: =SUMIF(GL_INC!G:G,A101,GL_INC!F:F) -> 0 | M101: =SUM(E101+I101) -> 159905.79
A102: 312 | B102: R&D Development costs | C102: =SUMIF(GL_LTD!$J:$J,A102,GL_LTD!$I:$I) -> 0 | E102: =SUMIF(GL_LTD!$J:$J,A102,GL_LTD!$G:$G) -> 0 | G102: =IFERROR(C102/E102,0) -> 0 | I102: =SUMIF(GL_INC!G:G,A102,GL_INC!F:F) -> 0 | M102: =SUM(E102+I102) -> 0
A103: 309 | B103: Patents and Regulations | C103: =SUMIF(GL_LTD!$J:$J,A103,GL_LTD!$I:$I) -> 0 | E103: =SUMIF(GL_LTD!$J:$J,A103,GL_LTD!$G:$G) -> 0 | G103: =IFERROR(C103/E103,0) -> 0 | I103: =SUMIF(GL_INC!G:G,A103,GL_INC!F:F) -> 0 | M103: =SUM(E103+I103) -> 0
...

Sheet GL_LTD
C3: General Ledger | G3: =D85/E85 -> 3.519
C4: =WP_LTD!B4 -> As of Dec 31, 2022
B6: Account | C6: שם | D6: יתרה | E6: יתרה | F6: AJE | G6: Final Balance USD | H6: AJE | I6: Final Balance NIS | J6: FS Code | K6: FS Name | L6: BVA Code | M6: Check | P6: Exchange rate
F7: =SUMIF(AJE_LTD!$B:$B,B7,AJE_LTD!$D:$D) -> 0 | G7: =IF(E3="__________________"," ",IF(ISERROR(F7+E7),"",(F7+E7))) -> 0 | H7: =SUMIF(AJE_LTD!$B:$B,B7,AJE_LTD!$F:$F) -> 0 | I7: =IF(D3="__________________"," ",IF(ISERROR(H7+D7),"",(H7+D7))) -> 0 | J7: =IF(ISERROR(VLOOKUP(B7,Accounts_LTD!$B:$E,3,FALSE)),"",VLOOKUP(B7,Accounts_LTD!$B:$E,3,FALSE)) | K7: =IFERROR(IF(J7="","",VLOOKUP(J7,FS!$A$11:$B$241,2,FALSE)),"") | L7: =IFERROR(VLOOKUP(B7,Accounts_LTD!B:G,6,FALSE),"") | P7: =IF(G7=0," ",IF(G7="__________________"," ",ROUND(I7/G7,3)))
B8: PL0001 | C8: =VLOOKUP(B8,Accounts_LTD!B:C,2,0) -> קיזוז הכנסות שכירות | F8: =SUMIF(AJE_LTD!$B:$B,B8,AJE_LTD!$D:$D) -> 0 | G8: =IF(E4="__________________"," ",IF(ISERROR(F8+E8),"",(F8+E8))) -> 0 | H8: =SUMIF(AJE_LTD!$B:$B,B8,AJE_LTD!$F:$F) -> 0 | I8: =IF(D4="__________________"," ",IF(ISERROR(H8+D8),"",(H8+D8))) -> 0 | J8: =IF(ISERROR(VLOOKUP(B8,Accounts_LTD!$B:$E,3,FALSE)),"",VLOOKUP(B8,Accounts_LTD!$B:$E,3,FALSE)) -> 504 | K8: =IFERROR(IF(J8="","",VLOOKUP(J8,FS!$A$11:$B$241,2,FALSE)),"") -> Rent & Related expenses | L8: =IFERROR(VLOOKUP(B8,Accounts_LTD!B:G,6,FALSE),"") | P8: =IF(G8=0," ",IF(G8="__________________"," ",ROUND(I8/G8,3)))
B9: PL0002 | C9: מייד פיננסים | F9: =SUMIF(AJE_LTD!$B:$B,B9,AJE_LTD!$D:$D) -> 0 | G9: =IF(E5="__________________"," ",IF(ISERROR(F9+E9),"",(F9+E9))) -> 0 | H9: =SUMIF(AJE_LTD!$B:$B,B9,AJE_LTD!$F:$F) -> 0 | I9: =IF(D5="__________________"," ",IF(ISERROR(H9+D9),"",(H9+D9))) -> 0 | J9: =IF(ISERROR(VLOOKUP(B9,Accounts_LTD!$B:$E,3,FALSE)),"",VLOOKUP(B9,Accounts_LTD!$B:$E,3,FALSE)) -> 501 | K9: =IFERROR(IF(J9="","",VLOOKUP(J9,FS!$A$11:$B$241,2,FALSE)),"") -> Professional services LTD | L9: =IFERROR(VLOOKUP(B9,Accounts_LTD!B:G,6,FALSE),"") | P9: =IF(G9=0," ",IF(G9="__________________"," ",ROUND(I9/G9,3)))
B10: BS001 | C10: הכנסות לקבל | F10: =SUMIF(AJE_LTD!$B:$B,B10,AJE_LTD!$D:$D) -> 0 | G10: =IF(E6="__________________"," ",IF(ISERROR(F10+E10),"",(F10+E10))) -> 0 | H10: =SUMIF(AJE_LTD!$B:$B,B10,AJE_LTD!$F:$F) -> 0 | I10: =IF(D6="__________________"," ",IF(ISERROR(H10+D10),"",(H10+D10))) -> 0 | J10: =IF(ISERROR(VLOOKUP(B10,Accounts_LTD!$B:$E,3,FALSE)),"",VLOOKUP(B10,Accounts_LTD!$B:$E,3,FALSE)) -> 5 | K10: =IFERROR(IF(J10="","",VLOOKUP(J10,FS!$A$11:$B$241,2,FALSE)),"") -> Accounts Receivables | L10: =IFERROR(VLOOKUP(B10,Accounts_LTD!B:G,6,FALSE),"") | P10: =IF(G10=0," ",IF(G10="__________________"," ",ROUND(I10/G10,3))) | S10: BL00072
B11: PL0003 | C11: Azure (microsoft) | F11: =SUMIF(AJE_LTD!$B:$B,B11,AJE_LTD!$D:$D) -> 0 | G11: =IF(E7="__________________"," ",IF(ISERROR(F11+E11),"",(F11+E11))) -> 0 | H11: =SUMIF(AJE_LTD!$B:$B,B11,AJE_LTD!$F:$F) -> 0 | I11: =IF(D7="__________________"," ",IF(ISERROR(H11+D11),"",(H11+D11))) -> 0 | J11: =IF(ISERROR(VLOOKUP(B11,Accounts_LTD!$B:$E,3,FALSE)),"",VLOOKUP(B11,Accounts_LTD!$B:$E,3,FALSE)) -> 305 | K11: =IFERROR(IF(J11="","",VLOOKUP(J11,FS!$A$11:$B$241,2,FALSE)),"") -> Other R&D expenses | L11: =IFERROR(VLOOKUP(B11,Accounts_LTD!B:G,6,FALSE),"") | P11: =IF(G11=0," ",IF(G11="__________________"," ",ROUND(I11/G11,3)))
B12: BS0017 | C12: נסיעה עוז כץ 02-04/02/23 בריסל | F12: =SUMIF(AJE_LTD!$B:$B,B12,AJE_LTD!$D:$D) -> 0 | G12: =IF(E8="__________________"," ",IF(ISERROR(F12+E12),"",(F12+E12))) -> 0 | H12: =SUMIF(AJE_LTD!$B:$B,B12,AJE_LTD!$F:$F) -> 0 | I12: =IF(D8="__________________"," ",IF(ISERROR(H12+D12),"",(H12+D12))) -> 0 | J12: =IF(ISERROR(VLOOKUP(B12,Accounts_LTD!$B:$E,3,FALSE)),"",VLOOKUP(B12,Accounts_LTD!$B:$E,3,FALSE)) | K12: =IFERROR(IF(J12="","",VLOOKUP(J12,FS!$A$11:$B$241,2,FALSE)),"") | L12: =IFERROR(VLOOKUP(B12,Accounts_LTD!B:G,6,FALSE),"") | P12: =IF(G12=0," ",IF(G12="__________________"," ",ROUND(I12/G12,3)))
B13: PL0004 | C13: נקסטייג | F13: =SUMIF(AJE_LTD!$B:$B,B13,AJE_LTD!$D:$D) -> 0 | G13: =IF(E9="__________________"," ",IF(ISERROR(F13+E13),"",(F13+E13))) -> 0 | H13: =SUMIF(AJE_LTD!$B:$B,B13,AJE_LTD!$F:$F) -> 0 | I13: =IF(D9="__________________"," ",IF(ISERROR(H13+D13),"",(H13+D13))) -> 0 | J13: =IF(ISERROR(VLOOKUP(B13,Accounts_LTD!$B:$E,3,FALSE)),"",VLOOKUP(B13,Accounts_LTD!$B:$E,3,FALSE)) -> 501 | K13: =IFERROR(IF(J13="","",VLOOKUP(J13,FS!$A$11:$B$241,2,FALSE)),"") -> Professional services LTD | L13: =IFERROR(VLOOKUP(B13,Accounts_LTD!B:G,6,FALSE),"") | P13: =IF(G13=0," ",IF(G13="__________________"," ",ROUND(I13/G13,3)))
B14: PL0099 | F14: =SUMIF(AJE_LTD!$B:$B,B14,AJE_LTD!$D:$D) -> 0 | G14: =IF(E11="__________________"," ",IF(ISERROR(F14+E14),"",(F14+E14))) -> 0 | H14: =SUMIF(AJE_LTD!$B:$B,B14,AJE_LTD!$F:$F) -> 0 | I14: =IF(D11="__________________"," ",IF(ISERROR(H14+D14),"",(H14+D14))) -> 0 | J14: =IF(ISERROR(VLOOKUP(B14,Accounts_LTD!$B:$E,3,FALSE)),"",VLOOKUP(B14,Accounts_LTD!$B:$E,3,FALSE)) | K14: =IFERROR(IF(J14="","",VLOOKUP(J14,FS!$A$11:$B$241,2,FALSE)),"") | P14: =IF(G14=0," ",IF(G14="__________________"," ",ROUND(I14/G14,3)))
B15: PL113 | C15: אלוקציה למופ | F15: =SUMIF(AJE_LTD!$B:$B,B15,AJE_LTD!$D:$D) -> 159905.79 | G15: =IF(E12="__________________"," ",IF(ISERROR(F15+E15),"",(F15+E15))) -> 159905.79 | H15: =SUMIF(AJE_LTD!$B:$B,B15,AJE_LTD!$F:$F) -> 533869.57 | I15: =IF(D12="__________________"," ",IF(ISERROR(H15+D15),"",(H15+D15))) -> 533869.57 | J15: =IF(ISERROR(VLOOKUP(B15,Accounts_LTD!$B:$E,3,FALSE)),"",VLOOKUP(B15,Accounts_LTD!$B:$E,3,FALSE)) -> 323 | K15: =IFERROR(IF(J15="","",VLOOKUP(J15,FS!$A$11:$B$241,2,FALSE)),"") -> Allocation to other departments | P15: =IF(G15=0," ",IF(G15="__________________"," ",ROUND(I15/G15,3))) -> 3.339
B16: PL114 | C16: אלוקציה למרקטינג | F16: =SUMIF(AJE_LTD!$B:$B,B16,AJE_LTD!$D:$D) -> 10660.386 | G16: =IF(E13="__________________"," ",IF(ISERROR(F16+E16),"",(F16+E16))) -> 10660.386 | H16: =SUMIF(AJE_LTD!$B:$B,B16,AJE_LTD!$F:$F) -> 35591.305 | I16: =IF(D13="__________________"," ",IF(ISERROR(H16+D16),"",(H16+D16))) -> 35591.305 | J16: =IF(ISERROR(VLOOKUP(B16,Accounts_LTD!$B:$E,3,FALSE)),"",VLOOKUP(B16,Accounts_LTD!$B:$E,3,FALSE)) -> 812 | K16: =IFERROR(IF(J16="","",VLOOKUP(J16,FS!$A$11:$B$241,2,FALSE)),"") -> Allocation to other departments | L16: =IFERROR(VLOOKUP(B16,Accounts_LTD!B:G,6,FALSE),"") | P16: =IF(G16=0," ",IF(G16="__________________"," ",ROUND(I16/G16,3))) -> 3.339
B17: PL115 | C17: אלוקציה ל DEVEX | F17: =SUMIF(AJE_LTD!$B:$B,B17,AJE_LTD!$D:$D) -> 10660.386 | G17: =IF(E14="__________________"," ",IF(ISERROR(F17+E17),"",(F17+E17))) -> 10660.386 | H17: =SUMIF(AJE_LTD!$B:$B,B17,AJE_LTD!$F:$F) -> 35591.305 | I17: =IF(D14="__________________"," ",IF(ISERROR(H17+D17),"",(H17+D17))) -> 35591.305 | J17: =IF(ISERROR(VLOOKUP(B17,Accounts_LTD!$B:$E,3,FALSE)),"",VLOOKUP(B17,Accounts_LTD!$B:$E,3,FALSE)) -> 611 | K17: =IFERROR(IF(J17="","",VLOOKUP(J17,FS!$A$11:$B$241,2,FALSE)),"") -> Allocation to other departments | P17: =IF(G17=0," ",IF(G17="__________________"," ",ROUND(I17/G17,3))) -> 3.339
B18: PL116 | C18: אלוקציה מהנהכ | F18: =SUMIF(AJE_LTD!$B:$B,B18,AJE_LTD!$D:$D) -> -181226.57 | G18: =IF(E14="__________________"," ",IF(ISERROR(F18+E18),"",(F18+E18))) -> -181226.57 | H18: =SUMIF(AJE_LTD!$B:$B,B18,AJE_LTD!$F:$F) -> -605052.18 | I18: =IF(D14="__________________"," ",IF(ISERROR(H18+D18),"",(H18+D18))) -> -605052.18 | J18: =IF(ISERROR(VLOOKUP(B18,Accounts_LTD!$B:$E,3,FALSE)),"",VLOOKUP(B18,Accounts_LTD!$B:$E,3,FALSE)) -> 510 | K18: =IFERROR(IF(J18="","",VLOOKUP(J18,FS!$A$11:$B$241,2,FALSE)),"") -> Allocation to other departments | P18: =IF(G18=0," ",IF(G18="__________________"," ",ROUND(I18/G18,3))) -> 3.339
B19: PL0011 | C19: הוצ נסיעות DEVEX ל WELFARE | F19: =SUMIF(AJE_LTD!$B:$B,B19,AJE_LTD!$D:$D) -> 0 | G19: =IF(E15="__________________"," ",IF(ISERROR(F19+E19),"",(F19+E19))) -> 0 | H19: =SUMIF(AJE_LTD!$B:$B,B19,AJE_LTD!$F:$F) -> 0 | I19: =IF(D15="__________________"," ",IF(ISERROR(H19+D19),"",(H19+D19))) -> 0 | J19: =IF(ISERROR(VLOOKUP(B19,Accounts_LTD!$B:$E,3,FALSE)),"",VLOOKUP(B19,Accounts_LTD!$B:$E,3,FALSE)) -> 600 | K19: =IFERROR(IF(J19="","",VLOOKUP(J19,FS!$A$11:$B$241,2,FALSE)),"") -> Payroll and related (DevEx) | P19: =IF(G19=0," ",IF(G19="__________________"," ",ROUND(I19/G19,3)))
B20: PL0012 | C20: הוצ ארוחות G&A ל WELFARE | F20: =SUMIF(AJE_LTD!$B:$B,B20,AJE_LTD!$D:$D) -> 0 | G20: =IF(E16="__________________"," ",IF(ISERROR(F20+E20),"",(F20+E20))) -> 0 | H20: =SUMIF(AJE_LTD!$B:$B,B20,AJE_LTD!$F:$F) -> 0 | I20: =IF(D16="__________________"," ",IF(ISERROR(H20+D20),"",(H20+D20))) -> 0 | J20: =IF(ISERROR(VLOOKUP(B20,Accounts_LTD!$B:$E,3,FALSE)),"",VLOOKUP(B20,Accounts_LTD!$B:$E,3,FALSE)) -> 500 | K20: =IFERROR(IF(J20="","",VLOOKUP(J20,FS!$A$11:$B$241,2,FALSE)),"") -> Payroll and related (G&A) | P20: =IF(G20=0," ",IF(G20="__________________"," ",ROUND(I20/G20,3)))
B21: PL0013 | C21: הוצ נסיעות G&A ל WELFARE | F21: =SUMIF(AJE_LTD!$B:$B,B21,AJE_LTD!$D:$D) -> 0 | G21: =IF(E17="__________________"," ",IF(ISERROR(F21+E21),"",(F21+E21))) -> 0 | H21: =SUMIF(AJE_LTD!$B:$B,B21,AJE_LTD!$F:$F) -> 0 | I21: =IF(D17="__________________"," ",IF(ISERROR(H21+D21),"",(H21+D21))) -> 0 | J21: =IF(ISERROR(VLOOKUP(B21,Accounts_LTD!$B:$E,3,FALSE)),"",VLOOKUP(B21,Accounts_LTD!$B:$E,3,FALSE)) -> 500 | K21: =IFERROR(IF(J21="","",VLOOKUP(J21,FS!$A$11:$B$241,2,FALSE)),"") -> Payroll and related (G&A) | P21: =IF(G21=0," ",IF(G21="__________________"," ",ROUND(I21/G21,3)))
B22: PL0014 | C22: ארוחות WELFARE | F22: =SUMIF(AJE_LTD!$B:$B,B22,AJE_LTD!$D:$D) -> 0 | G22: =IF(E18="__________________"," ",IF(ISERROR(F22+E22),"",(F22+E22))) -> 0 | H22: =SUMIF(AJE_LTD!$B:$B,B22,AJE_LTD!$F:$F) -> 0 | I22: =IF(D18="__________________"," ",IF(ISERROR(H22+D22),"",(H22+D22))) -> 0 | J22: =IF(ISERROR(VLOOKUP(B22,Accounts_LTD!$B:$E,3,FALSE)),"",VLOOKUP(B22,Accounts_LTD!$B:$E,3,FALSE)) -> 508 | K22: =IFERROR(IF(J22="","",VLOOKUP(J22,FS!$A$11:$B$241,2,FALSE)),"") -> Welfare (Meals + transportation) | P22: =IF(G22=0," ",IF(G22="__________________"," ",ROUND(I22/G22,3)))
B23: PL0015 | C23: נסיעות WELFARE | F23: =SUMIF(AJE_LTD!$B:$B,B23,AJE_LTD!$D:$D) -> 0 | G23: =IF(E19="__________________"," ",IF(ISERROR(F23+E23),"",(F23+E23))) -> 0 | H23: =SUMIF(AJE_LTD!$B:$B,B23,AJE_LTD!$F:$F) -> 0 | I23: =IF(D19="__________________"," ",IF(ISERROR(H23+D23),"",(H23+D23))) -> 0 | J23: =IF(ISERROR(VLOOKUP(B23,Accounts_LTD!$B:$E,3,FALSE)),"",VLOOKUP(B23,Accounts_LTD!$B:$E,3,FALSE)) -> 508 | K23: =IFERROR(IF(J23="","",VLOOKUP(J23,FS!$A$11:$B$241,2,FALSE)),"") -> Welfare (Meals + transportation) | P23: =IF(G23=0," ",IF(G23="__________________"," ",ROUND(I23/G23,3)))
B24: 50500 | C24: נסיעה לארה"ב עוז כץ 11.10.21-15.10.21 | F24: =SUMIF(AJE_LTD!$B:$B,B24,AJE_LTD!$D:$D) -> 12386.42 | G24: =IF(E20="__________________"," ",IF(ISERROR(F24+E24),"",(F24+E24))) -> 12386.42 | H24: =SUMIF(AJE_LTD!$B:$B,B24,AJE_LTD!$F:$F) -> 43587.81 | I24: =IF(D20="__________________"," ",IF(ISERROR(H24+D24),"",(H24+D24))) -> 43587.81 | J24: =IF(ISERROR(VLOOKUP(B24,Accounts_LTD!$B:$E,3,FALSE)),"",VLOOKUP(B24,Accounts_LTD!$B:$E,3,FALSE)) -> 303 | K24: =IFERROR(IF(J24="","",VLOOKUP(J24,FS!$A$11:$B$241,2,FALSE)),"") -> Travel abroad | P24: =IF(G24=0," ",IF(G24="__________________"," ",ROUND(I24/G24,3))) -> 3.519
B25: PL51000 | C25: =VLOOKUP(B25,Accounts_LTD!B:C,2,0) -> #N/A | F25: =SUMIF(AJE_LTD!$B:$B,B25,AJE_LTD!$D:$D) -> 0 | G25: =IF(E21="__________________"," ",IF(ISERROR(F25+E25),"",(F25+E25))) -> 0 | H25: =SUMIF(AJE_LTD!$B:$B,B25,AJE_LTD!$F:$F) -> 0 | I25: =IF(D21="__________________"," ",IF(ISERROR(H25+D25),"",(H25+D25))) -> 0 | J25: =IF(ISERROR(VLOOKUP(B25,Accounts_LTD!$B:$E,3,FALSE)),"",VLOOKUP(B25,Accounts_LTD!$B:$E,3,FALSE)) | K25: =IFERROR(IF(J25="","",VLOOKUP(J25,FS!$A$11:$B$241,2,FALSE)),"") | P25: =IF(G25=0," ",IF(G25="__________________"," ",ROUND(I25/G25,3)))
B26: PL32300 | C26: =VLOOKUP(B26,Accounts_LTD!B:C,2,0) -> #N/A | F26: =SUMIF(AJE_LTD!$B:$B,B26,AJE_LTD!$D:$D) -> 0 | G26: =IF(E22="__________________"," ",IF(ISERROR(F26+E26),"",(F26+E26))) -> 0 | H26: =SUMIF(AJE_LTD!$B:$B,B26,AJE_LTD!$F:$F) -> 0 | I26: =IF(D22="__________________"," ",IF(ISERROR(H26+D26),"",(H26+D26))) -> 0 | J26: =IF(ISERROR(VLOOKUP(B26,Accounts_LTD!$B:$E,3,FALSE)),"",VLOOKUP(B26,Accounts_LTD!$B:$E,3,FALSE)) | K26: =IFERROR(IF(J26="","",VLOOKUP(J26,FS!$A$11:$B$241,2,FALSE)),"") | P26: =IF(G26=0," ",IF(G26="__________________"," ",ROUND(I26/G26,3)))
B27: BS002 | C27: מעמ ספקים | F27: =SUMIF(AJE_LTD!$B:$B,B27,AJE_LTD!$D:$D) -> 1897.1666 | G27: =IF(E23="__________________"," ",IF(ISERROR(F27+E27),"",(F27+E27))) -> 1897.1666 | H27: =SUMIF(AJE_LTD!$B:$B,B27,AJE_LTD!$F:$F) -> 6676.1238 | I27: =IF(D23="__________________"," ",IF(ISERROR(H27+D27),"",(H27+D27))) -> 6676.1238 | J27: =IF(ISERROR(VLOOKUP(B27,Accounts_LTD!$B:$E,3,FALSE)),"",VLOOKUP(B27,Accounts_LTD!$B:$E,3,FALSE)) -> 7.3 | K27: =IFERROR(IF(J27="","",VLOOKUP(J27,FS!$A$11:$B$241,2,FALSE)),"") -> Government Institutions | P27: =IF(G27=0," ",IF(G27="__________________"," ",ROUND(I27/G27,3))) -> 3.519
B28: 70039 | C28: הוצאות VANTA INC | F28: =SUMIF(AJE_LTD!$B:$B,B28,AJE_LTD!$D:$D) -> 0 | G28: =IF(E24="__________________"," ",IF(ISERROR(F28+E28),"",(F28+E28))) -> 0 | H28: =SUMIF(AJE_LTD!$B:$B,B28,AJE_LTD!$F:$F) -> 0 | I28: =IF(D24="__________________"," ",IF(ISERROR(H28+D28),"",(H28+D28))) -> 0 | J28: =IF(ISERROR(VLOOKUP(B28,Accounts_LTD!$B:$E,3,FALSE)),"",VLOOKUP(B28,Accounts_LTD!$B:$E,3,FALSE)) -> 511 | K28: =IFERROR(IF(J28="","",VLOOKUP(J28,FS!$A$11:$B$241,2,FALSE)),"") -> G&A Software | P28: =IF(G28=0," ",IF(G28="__________________"," ",ROUND(I28/G28,3)))
B29: BS510 | C29: Additional Paid-In Capital | F29: =SUMIF(AJE_LTD!$B:$B,B29,AJE_LTD!$D:$D) -> #ERROR! | G29: =IF(E25="__________________"," ",IF(ISERROR(F29+E29),"",(F29+E29))) | H29: =SUMIF(AJE_LTD!$B:$B,B29,AJE_LTD!$F:$F) -> #ERROR! | I29: =IF(D25="__________________"," ",IF(ISERROR(H29+D29),"",(H29+D29))) | J29: =IF(ISERROR(VLOOKUP(B29,Accounts_LTD!$B:$E,3,FALSE)),"",VLOOKUP(B29,Accounts_LTD!$B:$E,3,FALSE)) -> 51 | K29: =IFERROR(IF(J29="","",VLOOKUP(J29,FS!$A$11:$B$241,2,FALSE)),"") -> Additional paid-in capital | P29: =IF(G29=0," ",IF(G29="__________________"," ",ROUND(I29/G29,3))) -> #DIV/0!
C30: תוכנה וכילים TOOLS הנה"כ | F30: =SUMIF(AJE_LTD!$B:$B,B30,AJE_LTD!$D:$D) -> 0 | G30: =IF(E25="__________________"," ",IF(ISERROR(F30+E30),"",(F30+E30))) -> 0 | H30: =SUMIF(AJE_LTD!$B:$B,B30,AJE_LTD!$F:$F) -> 0 | I30: =IF(D25="__________________"," ",IF(ISERROR(H30+D30),"",(H30+D30))) -> 0 | J30: =IF(ISERROR(VLOOKUP(B30,Accounts_LTD!$B:$E,3,FALSE)),"",VLOOKUP(B30,Accounts_LTD!$B:$E,3,FALSE)) | K30: =IFERROR(IF(J30="","",VLOOKUP(J30,FS!$A$11:$B$241,2,FALSE)),"") | P30: =IF(G30=0," ",IF(G30="__________________"," ",ROUND(I30/G30,3)))
B31: PL112 | C31: Bonus DevEx | F31: =SUMIF(AJE_LTD!$B:$B,B31,AJE_LTD!$D:$D) -> 10116.51 | G31: =IF(E26="__________________"," ",IF(ISERROR(F31+E31),"",(F31+E31))) -> 10116.51 | H31: =SUMIF(AJE_LTD!$B:$B,B31,AJE_LTD!$F:$F) -> 35600 | I31: =IF(D26="__________________"," ",IF(ISERROR(H31+D31),"",(H31+D31))) -> 35600 | J31: =IF(ISERROR(VLOOKUP(B31,Accounts_LTD!$B:$E,3,FALSE)),"",VLOOKUP(B31,Accounts_LTD!$B:$E,3,FALSE)) -> 601 | K31: =IFERROR(IF(J31="","",VLOOKUP(J31,FS!$A$11:$B$241,2,FALSE)),"") -> Bonus DevEx | P31: =IF(G31=0," ",IF(G31="__________________"," ",ROUND(I31/G31,3))) -> 3.519
B32: PL117 | C32: אופציות- מו"פ | F32: =SUMIF(AJE_LTD!$B:$B,B32,AJE_LTD!$D:$D) -> #REF! | G32: =IF(E27="__________________"," ",IF(ISERROR(F32+E32),"",(F32+E32))) | H32: =SUMIF(AJE_LTD!$B:$B,B32,AJE_LTD!$F:$F) -> #REF! | I32: =IF(D27="__________________"," ",IF(ISERROR(H32+D32),"",(H32+D32))) | J32: =IF(ISERROR(VLOOKUP(B32,Accounts_LTD!$B:$E,3,FALSE)),"",VLOOKUP(B32,Accounts_LTD!$B:$E,3,FALSE)) -> 314 | K32: =IFERROR(IF(J32="","",VLOOKUP(J32,FS!$A$11:$B$241,2,FALSE)),"") -> Stock compensation exp - R&D | P32: =IF(G32=0," ",IF(G32="__________________"," ",ROUND(I32/G32,3))) -> #DIV/0!
B33: PL118 | C33: אופציות-הנה"כ | F33: =SUMIF(AJE_LTD!$B:$B,B33,AJE_LTD!$D:$D) -> #REF! | G33: =IF(E28="__________________"," ",IF(ISERROR(F33+E33),"",(F33+E33))) | H33: =SUMIF(AJE_LTD!$B:$B,B33,AJE_LTD!$F:$F) -> #REF! | I33: =IF(D28="__________________"," ",IF(ISERROR(H33+D33),"",(H33+D33))) | J33: =IF(ISERROR(VLOOKUP(B33,Accounts_LTD!$B:$E,3,FALSE)),"",VLOOKUP(B33,Accounts_LTD!$B:$E,3,FALSE)) -> 512 | K33: =IFERROR(IF(J33="","",VLOOKUP(J33,FS!$A$11:$B$241,2,FALSE)),"") -> Stock compensation exp - G&A | P33: =IF(G33=0," ",IF(G33="__________________"," ",ROUND(I33/G33,3))) -> #DIV/0!
B34: PL119 | C34: אופציות- מכירה ושיווק | F34: =SUMIF(AJE_LTD!$B:$B,B34,AJE_LTD!$D:$D) -> #REF! | G34: =IF(E30="__________________"," ",IF(ISERROR(F34+E34),"",(F34+E34))) | H34: =SUMIF(AJE_LTD!$B:$B,B34,AJE_LTD!$F:$F) -> #REF! | I34: =IF(D30="__________________"," ",IF(ISERROR(H34+D34),"",(H34+D34))) | J34: =IF(ISERROR(VLOOKUP(B34,Accounts_LTD!$B:$E,3,FALSE)),"",VLOOKUP(B34,Accounts_LTD!$B:$E,3,FALSE)) -> 813 | K34: =IFERROR(IF(J34="","",VLOOKUP(J34,FS!$A$11:$B$241,2,FALSE)),"") -> Stock compensation exp - marketing | P34: =IF(G34=0," ",IF(G34="__________________"," ",ROUND(I34/G34,3))) -> #DIV/0!
B35: BS200 | C35: קרן הון- אופציות | F35: =SUMIF(AJE_LTD!$B:$B,B35,AJE_LTD!$D:$D) -> #REF! | G35: =IF(E31="__________________"," ",IF(ISERROR(F35+E35),"",(F35+E35))) | H35: =SUMIF(AJE_LTD!$B:$B,B35,AJE_LTD!$F:$F) -> #REF! | I35: =IF(D31="__________________"," ",IF(ISERROR(H35+D35),"",(H35+D35))) | J35: =IF(ISERROR(VLOOKUP(B35,Accounts_LTD!$B:$E,3,FALSE)),"",VLOOKUP(B35,Accounts_LTD!$B:$E,3,FALSE)) -> 54 | K35: =IFERROR(IF(J35="","",VLOOKUP(J35,FS!$A$11:$B$241,2,FALSE)),"") -> Stock compensation | P35: =IF(G35=0," ",IF(G35="__________________"," ",ROUND(I35/G35,3))) -> #DIV/0!
B36: PL0019 | C36: =VLOOKUP(B36,Accounts_LTD!B:C,2,0) -> Michal Wosk Big Data & AI World UK 2023 07-10/03/23 | F36: =SUMIF(AJE_LTD!$B:$B,B36,AJE_LTD!$D:$D) -> 0 | G36: =IF(E27="__________________"," ",IF(ISERROR(F36+E36),"",(F36+E36))) -> 0 | H36: =SUMIF(AJE_LTD!$B:$B,B36,AJE_LTD!$F:$F) -> 0 | I36: =IF(D27="__________________"," ",IF(ISERROR(H36+D36),"",(H36+D36))) -> 0 | J36: =IF(ISERROR(VLOOKUP(B36,Accounts_LTD!$B:$E,3,FALSE)),"",VLOOKUP(B36,Accounts_LTD!$B:$E,3,FALSE)) -> 811 | K36: =IFERROR(IF(J36="","",VLOOKUP(J36,FS!$A$11:$B$241,2,FALSE)),"") -> Conference Expenses marketing | P36: =IF(G36=0," ",IF(G36="__________________"," ",ROUND(I36/G36,3)))
B37: 460001 | C37: =VLOOKUP(B37,Accounts_LTD!B:C,2,0) -> #N/A | F37: =SUMIF(AJE_LTD!$B:$B,B37,AJE_LTD!$D:$D) -> 0 | G37: =IF(E28="__________________"," ",IF(ISERROR(F37+E37),"",(F37+E37))) -> 0 | H37: =SUMIF(AJE_LTD!$B:$B,B37,AJE_LTD!$F:$F) -> 0 | I37: =IF(D28="__________________"," ",IF(ISERROR(H37+D37),"",(H37+D37))) -> 0 | J37: =IF(ISERROR(VLOOKUP(B37,Accounts_LTD!$B:$E,3,FALSE)),"",VLOOKUP(B37,Accounts_LTD!$B:$E,3,FALSE)) | K37: =IFERROR(IF(J37="","",VLOOKUP(J37,FS!$A$11:$B$241,2,FALSE)),"") | P37: =IF(G37=0," ",IF(G37="__________________"," ",ROUND(I37/G37,3)))
B38: PL0016 | C38: =VLOOKUP(B38,Accounts_LTD!B:C,2,0) -> יעוץ | F38: =SUMIF(AJE_LTD!$B:$B,B38,AJE_LTD!$D:$D) -> 0 | G38: =IF(E30="__________________"," ",IF(ISERROR(F38+E38),"",(F38+E38))) -> 0 | H38: =SUMIF(AJE_LTD!$B:$B,B38,AJE_LTD!$F:$F) -> 0 | I38: =IF(D30="__________________"," ",IF(ISERROR(H38+D38),"",(H38+D38))) -> 0 | J38: =IF(ISERROR(VLOOKUP(B38,Accounts_LTD!$B:$E,3,FALSE)),"",VLOOKUP(B38,Accounts_LTD!$B:$E,3,FALSE)) -> 501 | K38: =IFERROR(IF(J38="","",VLOOKUP(J38,FS!$A$11:$B$241,2,FALSE)),"") -> Professional services LTD
B39: =IF(IF(ISERROR(LEFT(C39,5)*1),"",(LEFT(C39,5)*1))<10000,"",IF(ISERROR(LEFT(C39,5)*1),"",(LEFT(C39,5)*1))) | F39: =SUMIF(AJE_LTD!$B:$B,B39,AJE_LTD!$D:$D) -> 0 | G39: =IF(E22="__________________"," ",IF(ISERROR(F39+E39),"",(F39+E39))) -> 0 | H39: =SUMIF(AJE_LTD!$B:$B,B39,AJE_LTD!$F:$F) -> 0 | I39: =IF(D22="__________________"," ",IF(ISERROR(H39+D39),"",(H39+D39))) -> 0 | J39: =IF(ISERROR(VLOOKUP(B39,Accounts_LTD!$B:$E,3,FALSE)),"",VLOOKUP(B39,Accounts_LTD!$B:$E,3,FALSE)) | K39: =IFERROR(IF(J39="","",VLOOKUP(J39,FS!$A$11:$B$241,2,FALSE)),"") | L39: =IFERROR(VLOOKUP(B39,Accounts_LTD!B:G,6,FALSE),"") | M39: =IF(and(B39<>"",J39=""),"Error","")
B40: חשבון | C40: תאור החשבון | D40: יתרה בשקלים | E40: יתרה בדולרים | F40: =SUMIF(AJE_LTD!$B:$B,B40,AJE_LTD!$D:$D) -> 0 | G40: =IF(E23="__________________"," ",IF(ISERROR(F40+E40),"",(F40+E40))) | H40: =SUMIF(AJE_LTD!$B:$B,B40,AJE_LTD!$F:$F) -> 0 | I40: =IF(D23="__________________"," ",IF(ISERROR(H40+D40),"",(H40+D40))) | J40: =IF(ISERROR(VLOOKUP(B40,Accounts_LTD!$B:$E,3,FALSE)),"",VLOOKUP(B40,Accounts_LTD!$B:$E,3,FALSE)) | K40: =IFERROR(IF(J40="","",VLOOKUP(J40,FS!$A$11:$B$241,2,FALSE)),"") | L40: =IFERROR(VLOOKUP(#REF!,Accounts_LTD!B:G,6,FALSE),"")
B41: 10000 | C41: בנק לאומי ש"ח | D41: 5716204.6 | E41: 1624383.2 | F41: =SUMIF(AJE_LTD!$B:$B,B41,AJE_LTD!$D:$D) -> 0 | G41: =IF(E24="__________________"," ",IF(ISERROR(F41+E41),"",(F41+E41))) -> 1624383.2 | H41: =SUMIF(AJE_LTD!$B:$B,B41,AJE_LTD!$F:$F) -> 0 | I41: =IF(D24="__________________"," ",IF(ISERROR(H41+D41),"",(H41+D41))) -> 5716204.6 | J41: =IF(ISERROR(VLOOKUP(B41,Accounts_LTD!$B:$E,3,FALSE)),"",VLOOKUP(B41,Accounts_LTD!$B:$E,3,FALSE)) -> 1 | K41: =IFERROR(IF(J41="","",VLOOKUP(J41,FS!$A$11:$B$241,2,FALSE)),"") -> Cash and cash equivalents LTD | L41: =IFERROR(VLOOKUP(B42,Accounts_LTD!B:G,6,FALSE),"") | P41: =IF(G41=0," ",IF(G41="__________________"," ",ROUND(I41/G41,3))) -> 3.519 | R41: =IF(E44>G42,0,1) -> 1 | S41: =E41-G41 -> 0 | U41: =D41-I41 -> 0
B42: 10001 | C42: בנק לאומי $ | D42: 586873.73 | E42: 166772.87 | F42: =SUMIF(AJE_LTD!$B:$B,B42,AJE_LTD!$D:$D) -> 0 | G42: =IF(E25="__________________"," ",IF(ISERROR(F42+E42),"",(F42+E42))) -> 166772.87 | H42: =SUMIF(AJE_LTD!$B:$B,B42,AJE_LTD!$F:$F) -> 0 | I42: =IF(D25="__________________"," ",IF(ISERROR(H42+D42),"",(H42+D42))) -> 586873.73 | J42: =IF(ISERROR(VLOOKUP(B42,Accounts_LTD!$B:$E,3,FALSE)),"",VLOOKUP(B42,Accounts_LTD!$B:$E,3,FALSE)) -> 1 | K42: =IFERROR(IF(J42="","",VLOOKUP(J42,FS!$A$11:$B$241,2,FALSE)),"") -> Cash and cash equivalents LTD | L42: =IFERROR(VLOOKUP(B43,Accounts_LTD!B:G,6,FALSE),"") | P42: =IF(G42=0," ",IF(G42="__________________"," ",ROUND(I42/G42,3))) -> 3.519 | R42: =IF(E45>G43,0,1) -> 1 | S42: =E42-G42 -> 0 | U42: =D42-I42 -> 0
B43: 10002 | C43: בנק לאומי דולר קנדי | D43: 11130.46 | E43: 3162.96 | F43: =SUMIF(AJE_LTD!$B:$B,B43,AJE_LTD!$D:$D) -> 0 | G43: =IF(E39="__________________"," ",IF(ISERROR(F43+E43),"",(F43+E43))) -> 3162.96 | H43: =SUMIF(AJE_LTD!$B:$B,B43,AJE_LTD!$F:$F) -> 0 | I43: =IF(D39="__________________"," ",IF(ISERROR(H43+D43),"",(H43+D43))) -> 11130.46 | J43: =IF(ISERROR(VLOOKUP(B43,Accounts_LTD!$B:$E,3,FALSE)),"",VLOOKUP(B43,Accounts_LTD!$B:$E,3,FALSE)) -> 1 | K43: =IFERROR(IF(J43="","",VLOOKUP(J43,FS!$A$11:$B$241,2,FALSE)),"") -> Cash and cash equivalents LTD | L43: =IFERROR(VLOOKUP(#REF!,Accounts_LTD!B:G,6,FALSE),"") | P43: =IF(G43=0," ",IF(G43="__________________"," ",ROUND(I43/G43,3))) -> 3.519 | R43: =IF(E46>G44,0,1) -> 1 | S43: =E43-G43 -> 0 | U43: =D43-I43 -> 0
B44: 10003 | C44: בנק לאומי אירו | D44: -18.99 | E44: -5.4 | F44: =SUMIF(AJE_LTD!$B:$B,B44,AJE_LTD!$D:$D) -> 0 | G44: =IF(E40="__________________"," ",IF(ISERROR(F44+E44),"",(F44+E44))) -> -5.4 | H44: =SUMIF(AJE_LTD!$B:$B,B44,AJE_LTD!$F:$F) -> 0 | I44: =IF(D40="__________________"," ",IF(ISERROR(H44+D44),"",(H44+D44))) -> -18.99 | J44: =IF(ISERROR(VLOOKUP(B44,Accounts_LTD!$B:$E,3,FALSE)),"",VLOOKUP(B44,Accounts_LTD!$B:$E,3,FALSE)) -> 1 | K44: =IFERROR(IF(J44="","",VLOOKUP(J44,FS!$A$11:$B$241,2,FALSE)),"") -> Cash and cash equivalents LTD | L44: =IFERROR(VLOOKUP(#REF!,Accounts_LTD!B:G,6,FALSE),"") | P44: =IF(G44=0," ",IF(G44="__________________"," ",ROUND(I44/G44,3))) -> 3.517 | R44: =IF(E47>G45,0,1) -> 0 | S44: =E44-G44 -> 0 | U44: =D44-I44 -> 0
B45: 10200 | C45: ויזה 1912 ש"ח | D45: -7835.27 | E45: -2226.56 | F45: =SUMIF(AJE_LTD!$B:$B,B45,AJE_LTD!$D:$D) -> 0 | G45: =IF(E41="__________________"," ",IF(ISERROR(F45+E45),"",(F45+E45))) -> -2226.56 | H45: =SUMIF(AJE_LTD!$B:$B,B45,AJE_LTD!$F:$F) -> 0 | I45: =IF(D41="__________________"," ",IF(ISERROR(H45+D45),"",(H45+D45))) -> -7835.27 | J45: =IF(ISERROR(VLOOKUP(B45,Accounts_LTD!$B:$E,3,FALSE)),"",VLOOKUP(B45,Accounts_LTD!$B:$E,3,FALSE)) -> 31.3 | K45: =IFERROR(IF(J45="","",VLOOKUP(J45,FS!$A$11:$B$241,2,FALSE)),"") -> Credit Cards | R45: =IF(E48>G46,0,1) -> 0 | S45: =E45-G45 -> 0 | U45: =D45-I45 -> 0
B46: 10201 | C46: ויזה 1912 $ | D46: -64959.23 | E46: -18459.57 | F46: =SUMIF(AJE_LTD!$B:$B,B46,AJE_LTD!$D:$D) -> 0 | G46: =IF(E42="__________________"," ",IF(ISERROR(F46+E46),"",(F46+E46))) -> -18459.57 | H46: =SUMIF(AJE_LTD!$B:$B,B46,AJE_LTD!$F:$F) -> 0 | I46: =IF(D42="__________________"," ",IF(ISERROR(H46+D46),"",(H46+D46))) -> -64959.23 | J46: =IF(ISERROR(VLOOKUP(B46,Accounts_LTD!$B:$E,3,FALSE)),"",VLOOKUP(B46,Accounts_LTD!$B:$E,3,FALSE)) -> 31.3 | K46: =IFERROR(IF(J46="","",VLOOKUP(J46,FS!$A$11:$B$241,2,FALSE)),"") -> Credit Cards | L46: =IFERROR(VLOOKUP(B47,Accounts_LTD!B:G,6,FALSE),"") | P46: =IF(G46=0," ",IF(G46="__________________"," ",ROUND(I46/G46,3))) -> 3.519 | R46: =IF(E49>G47,0,1) -> 0 | S46: =E46-G46 -> 0 | U46: =D46-I46 -> 0
B47: 10202 | C47: ויזה 1912 אירו | D47: -1302.33 | E47: -370.08 | F47: =SUMIF(AJE_LTD!$B:$B,B47,AJE_LTD!$D:$D) -> 0 | G47: =IF(E43="__________________"," ",IF(ISERROR(F47+E47),"",(F47+E47))) -> -370.08 | H47: =SUMIF(AJE_LTD!$B:$B,B47,AJE_LTD!$F:$F) -> 0 | I47: =IF(D43="__________________"," ",IF(ISERROR(H47+D47),"",(H47+D47))) -> -1302.33 | J47: =IF(ISERROR(VLOOKUP(B47,Accounts_LTD!$B:$E,3,FALSE)),"",VLOOKUP(B47,Accounts_LTD!$B:$E,3,FALSE)) -> 31.3 | K47: =IFERROR(IF(J47="","",VLOOKUP(J47,FS!$A$11:$B$241,2,FALSE)),"") -> Credit Cards | L47: =IFERROR(VLOOKUP(B48,Accounts_LTD!B:G,6,FALSE),"") | P47: =IF(G47=0," ",IF(G47="__________________"," ",ROUND(I47/G47,3))) -> 3.519 | R47: =IF(E50>G48,0,1) -> 1 | S47: =E47-G47 -> 0 | U47: =D47-I47 -> 0
B48: 10300 | C48: פקדון ש"ח בנק לאומי | D48: 120409.93 | E48: 34217.09 | F48: =SUMIF(AJE_LTD!$B:$B,B48,AJE_LTD!$D:$D) -> 0 | G48: =IF(E44="__________________"," ",IF(ISERROR(F48+E48),"",(F48+E48))) -> 34217.09 | H48: =SUMIF(AJE_LTD!$B:$B,B48,AJE_LTD!$F:$F) -> 0 | I48: =IF(D44="__________________"," ",IF(ISERROR(H48+D48),"",(H48+D48))) -> 120409.93 | J48: =IF(ISERROR(VLOOKUP(B48,Accounts_LTD!$B:$E,3,FALSE)),"",VLOOKUP(B48,Accounts_LTD!$B:$E,3,FALSE)) -> 20.1 | K48: =IFERROR(IF(J48="","",VLOOKUP(J48,FS!$A$11:$B$241,2,FALSE)),"") -> Restricted deposit | L48: =IFERROR(VLOOKUP(B49,Accounts_LTD!B:G,6,FALSE),"") | P48: =IF(G48=0," ",IF(G48="__________________"," ",ROUND(I48/G48,3))) -> 3.519 | R48: =IF(E51>G49,0,1) -> 1 | S48: =E48-G48 -> 0 | U48: =D48-I48 -> 0
B49: 10310 | C49: פקדון $ בנק לאומי | D49: 26744400 | E49: 7600000 | F49: =SUMIF(AJE_LTD!$B:$B,B49,AJE_LTD!$D:$D) -> 0 | G49: =IF(E45="__________________"," ",IF(ISERROR(F49+E49),"",(F49+E49))) -> 7600000 | H49: =SUMIF(AJE_LTD!$B:$B,B49,AJE_LTD!$F:$F) -> 0 | I49: =IF(D45="__________________"," ",IF(ISERROR(H49+D49),"",(H49+D49))) -> 26744400 | J49: =IF(ISERROR(VLOOKUP(B49,Accounts_LTD!$B:$E,3,FALSE)),"",VLOOKUP(B49,Accounts_LTD!$B:$E,3,FALSE)) -> 2 | K49: =IFERROR(IF(J49="","",VLOOKUP(J49,FS!$A$11:$B$241,2,FALSE)),"") -> Short-term Deposits | L49: =IFERROR(VLOOKUP(B50,Accounts_LTD!B:G,6,FALSE),"") | P49: =IF(G49=0," ",IF(G49="__________________"," ",ROUND(I49/G49,3))) -> 3.519 | R49: =IF(E52>G50,0,1) -> 0 | S49: =E49-G49 -> 0 | U49: =D49-I49 -> 0
B50: 10501 | C50: פקדון SOK WORKS | D50: 1404 | E50: 398.98 | F50: =SUMIF(AJE_LTD!$B:$B,B50,AJE_LTD!$D:$D) -> 0 | G50: =IF(E46="__________________"," ",IF(ISERROR(F50+E50),"",(F50+E50))) -> 398.98 | H50: =SUMIF(AJE_LTD!$B:$B,B50,AJE_LTD!$F:$F) -> 0 | I50: =IF(D46="__________________"," ",IF(ISERROR(H50+D50),"",(H50+D50))) -> 1404 | J50: =IF(ISERROR(VLOOKUP(B50,Accounts_LTD!$B:$E,3,FALSE)),"",VLOOKUP(B50,Accounts_LTD!$B:$E,3,FALSE)) -> 1 | K50: =IFERROR(IF(J50="","",VLOOKUP(J50,FS!$A$11:$B$241,2,FALSE)),"") -> Cash and cash equivalents LTD | L50: =IFERROR(VLOOKUP(#REF!,Accounts_LTD!B:G,6,FALSE),"") | P50: =IF(G50=0," ",IF(G50="__________________"," ",ROUND(I50/G50,3))) -> 3.519 | R50: =IF(E53>G51,0,1) -> 0 | S50: =E50-G50 -> 0 | U50: =D50-I50 -> 0
B51: 10604 | C51: O'Reilly Media, Inc. | D51: 11691.9 | E51: 3300 | F51: =SUMIF(AJE_LTD!$B:$B,B51,AJE_LTD!$D:$D) -> 0 | G51: =IF(E47="__________________"," ",IF(ISERROR(F51+E51),"",(F51+E51))) -> 3300 | H51: =SUMIF(AJE_LTD!$B:$B,B51,AJE_LTD!$F:$F) -> 0 | I51: =IF(D47="__________________"," ",IF(ISERROR(H51+D51),"",(H51+D51))) -> 11691.9 | J51: =IF(ISERROR(VLOOKUP(B51,Accounts_LTD!$B:$E,3,FALSE)),"",VLOOKUP(B51,Accounts_LTD!$B:$E,3,FALSE)) -> 5 | K51: =IFERROR(IF(J51="","",VLOOKUP(J51,FS!$A$11:$B$241,2,FALSE)),"") -> Accounts Receivables | L51: =IFERROR(VLOOKUP(B52,Accounts_LTD!B:G,6,FALSE),"") | P51: =IF(G51=0," ",IF(G51="__________________"," ",ROUND(I51/G51,3))) -> 3.543 | R51: =IF(E54>G52,0,1) -> 1 | S51: =E51-G51 -> 0 | U51: =D51-I51 -> 0
B52: 10800 | C52: הוצאות מראש | D52: 199115.83 | E52: 58556.86 | F52: =SUMIF(AJE_LTD!$B:$B,B52,AJE_LTD!$D:$D) -> 0 | G52: =IF(E48="__________________"," ",IF(ISERROR(F52+E52),"",(F52+E52))) -> 58556.86 | H52: =SUMIF(AJE_LTD!$B:$B,B52,AJE_LTD!$F:$F) -> 0 | I52: =IF(D48="__________________"," ",IF(ISERROR(H52+D52),"",(H52+D52))) -> 199115.83 | J52: =IF(ISERROR(VLOOKUP(B52,Accounts_LTD!$B:$E,3,FALSE)),"",VLOOKUP(B52,Accounts_LTD!$B:$E,3,FALSE)) -> 7.1 | K52: =IFERROR(IF(J52="","",VLOOKUP(J52,FS!$A$11:$B$241,2,FALSE)),"") -> Prepaid expenses | L52: =IFERROR(VLOOKUP(B53,Accounts_LTD!B:G,6,FALSE),"") | P52: =IF(G52=0," ",IF(G52="__________________"," ",ROUND(I52/G52,3))) -> 3.4 | R52: =IF(E55>G53,0,1) -> 1 | S52: =E52-G52 -> 0 | U52: =D52-I52 -> 0
B53: 15000 | C53: מחשבים ותוכנות | D53: 332570.48 | E53: 100775.74 | F53: =SUMIF(AJE_LTD!$B:$B,B53,AJE_LTD!$D:$D) -> 0 | G53: =IF(E49="__________________"," ",IF(ISERROR(F53+E53),"",(F53+E53))) -> 100775.74 | H53: =SUMIF(AJE_LTD!$B:$B,B53,AJE_LTD!$F:$F) -> 0 | I53: =IF(D49="__________________"," ",IF(ISERROR(H53+D53),"",(H53+D53))) -> 332570.48 | J53: =IF(ISERROR(VLOOKUP(B53,Accounts_LTD!$B:$E,3,FALSE)),"",VLOOKUP(B53,Accounts_LTD!$B:$E,3,FALSE)) -> 21 | K53: =IFERROR(IF(J53="","",VLOOKUP(J53,FS!$A$11:$B$241,2,FALSE)),"") -> Fixed assets | L53: =IFERROR(VLOOKUP(B54,Accounts_LTD!B:G,6,FALSE),"") | P53: =IF(G53=0," ",IF(G53="__________________"," ",ROUND(I53/G53,3))) -> 3.3 | R53: =IF(E56>G54,0,1) -> 0 | S53: =E53-G53 -> 0 | U53: =D53-I53 -> 0
B54: 15001 | C54: ריהוט וציוד | D54: 174714.82 | E54: 53938.52 | F54: =SUMIF(AJE_LTD!$B:$B,B54,AJE_LTD!$D:$D) -> 0 | G54: =IF(E50="__________________"," ",IF(ISERROR(F54+E54),"",(F54+E54))) -> 53938.52 | H54: =SUMIF(AJE_LTD!$B:$B,B54,AJE_LTD!$F:$F) -> 0 | I54: =IF(D50="__________________"," ",IF(ISERROR(H54+D54),"",(H54+D54))) -> 174714.82 | J54: =IF(ISERROR(VLOOKUP(B54,Accounts_LTD!$B:$E,3,FALSE)),"",VLOOKUP(B54,Accounts_LTD!$B:$E,3,FALSE)) -> 21 | K54: =IFERROR(IF(J54="","",VLOOKUP(J54,FS!$A$11:$B$241,2,FALSE)),"") -> Fixed assets | L54: =IFERROR(VLOOKUP(B55,Accounts_LTD!B:G,6,FALSE),"") | P54: =IF(G54=0," ",IF(G54="__________________"," ",ROUND(I54/G54,3))) -> 3.239 | R54: =IF(E57>G55,0,1) -> 1 | S54: =E54-G54 -> 0 | U54: =D54-I54 -> 0
B55: 15002 | C55: ציוד אלקטרוני | D55: 30031.33 | E55: 9173.77 | F55: =SUMIF(AJE_LTD!$B:$B,B55,AJE_LTD!$D:$D) -> 0 | G55: =IF(E51="__________________"," ",IF(ISERROR(F55+E55),"",(F55+E55))) -> 9173.77 | H55: =SUMIF(AJE_LTD!$B:$B,B55,AJE_LTD!$F:$F) -> 0 | I55: =IF(D51="__________________"," ",IF(ISERROR(H55+D55),"",(H55+D55))) -> 30031.33 | J55: =IF(ISERROR(VLOOKUP(B55,Accounts_LTD!$B:$E,3,FALSE)),"",VLOOKUP(B55,Accounts_LTD!$B:$E,3,FALSE)) -> 21 | K55: =IFERROR(IF(J55="","",VLOOKUP(J55,FS!$A$11:$B$241,2,FALSE)),"") -> Fixed assets | L55: =IFERROR(VLOOKUP(#REF!,Accounts_LTD!B:G,6,FALSE),"") | P55: =IF(G55=0," ",IF(G55="__________________"," ",ROUND(I55/G55,3))) -> 3.274 | R55: =IF(E58>G56,0,1) -> 1 | S55: =E55-G55 -> 0 | U55: =D55-I55 -> 0
B56: 15003 | C56: שיפורים במושכר | D56: 623242.89 | E56: 195444.44 | F56: =SUMIF(AJE_LTD!$B:$B,B56,AJE_LTD!$D:$D) -> 0 | G56: =IF(E52="__________________"," ",IF(ISERROR(F56+E56),"",(F56+E56))) -> 195444.44 | H56: =SUMIF(AJE_LTD!$B:$B,B56,AJE_LTD!$F:$F) -> 0 | I56: =IF(D52="__________________"," ",IF(ISERROR(H56+D56),"",(H56+D56))) -> 623242.89 | J56: =IF(ISERROR(VLOOKUP(B56,Accounts_LTD!$B:$E,3,FALSE)),"",VLOOKUP(B56,Accounts_LTD!$B:$E,3,FALSE)) -> 21 | K56: =IFERROR(IF(J56="","",VLOOKUP(J56,FS!$A$11:$B$241,2,FALSE)),"") -> Fixed assets | R56: =IF(E59>G57,0,1) -> 0 | S56: =E56-G56 -> 0 | U56: =D56-I56 -> 0
B57: 15100 | C57: פחת נצבר מחשבים | D57: -161847.48 | E57: -48143.28 | F57: =SUMIF(AJE_LTD!$B:$B,B57,AJE_LTD!$D:$D) -> 0 | G57: =IF(E53="__________________"," ",IF(ISERROR(F57+E57),"",(F57+E57))) -> -48143.28 | H57: =SUMIF(AJE_LTD!$B:$B,B57,AJE_LTD!$F:$F) -> 0 | I57: =IF(D53="__________________"," ",IF(ISERROR(H57+D57),"",(H57+D57))) -> -161847.48 | J57: =IF(ISERROR(VLOOKUP(B57,Accounts_LTD!$B:$E,3,FALSE)),"",VLOOKUP(B57,Accounts_LTD!$B:$E,3,FALSE)) -> 22 | K57: =IFERROR(IF(J57="","",VLOOKUP(J57,FS!$A$11:$B$241,2,FALSE)),"") -> Accumulated depreciation | L57: =IFERROR(VLOOKUP(B58,Accounts_LTD!B:G,6,FALSE),"") | P57: =IF(G57=0," ",IF(G57="__________________"," ",ROUND(I57/G57,3))) -> 3.362 | R57: =IF(E60>G58,0,1) -> 1 | S57: =E57-G57 -> 0 | U57: =D57-I57 -> 0
B58: 15101 | C58: פחת נצבר ריהוט וציוד | D58: -14202.87 | E58: -4331.73 | F58: =SUMIF(AJE_LTD!$B:$B,B58,AJE_LTD!$D:$D) -> 0 | G58: =IF(E54="__________________"," ",IF(ISERROR(F58+E58),"",(F58+E58))) -> -4331.73 | H58: =SUMIF(AJE_LTD!$B:$B,B58,AJE_LTD!$F:$F) -> 0 | I58: =IF(D54="__________________"," ",IF(ISERROR(H58+D58),"",(H58+D58))) -> -14202.87 | J58: =IF(ISERROR(VLOOKUP(B58,Accounts_LTD!$B:$E,3,FALSE)),"",VLOOKUP(B58,Accounts_LTD!$B:$E,3,FALSE)) -> 22 | K58: =IFERROR(IF(J58="","",VLOOKUP(J58,FS!$A$11:$B$241,2,FALSE)),"") -> Accumulated depreciation | L58: =IFERROR(VLOOKUP(B59,Accounts_LTD!B:G,6,FALSE),"") | P58: =IF(G58=0," ",IF(G58="__________________"," ",ROUND(I58/G58,3))) -> 3.279 | R58: =IF(E61>G59,0,1) -> 1 | S58: =E58-G58 -> 0 | U58: =D58-I58 -> 0
B59: 15102 | C59: פחת נצבר ציוד אלקטרוני | D59: -7065.24 | E59: -2145.57 | F59: =SUMIF(AJE_LTD!$B:$B,B59,AJE_LTD!$D:$D) -> 0 | G59: =IF(E55="__________________"," ",IF(ISERROR(F59+E59),"",(F59+E59))) -> -2145.57 | H59: =SUMIF(AJE_LTD!$B:$B,B59,AJE_LTD!$F:$F) -> 0 | I59: =IF(D55="__________________"," ",IF(ISERROR(H59+D59),"",(H59+D59))) -> -7065.24 | J59: =IF(ISERROR(VLOOKUP(B59,Accounts_LTD!$B:$E,3,FALSE)),"",VLOOKUP(B59,Accounts_LTD!$B:$E,3,FALSE)) -> 22 | K59: =IFERROR(IF(J59="","",VLOOKUP(J59,FS!$A$11:$B$241,2,FALSE)),"") -> Accumulated depreciation | L59: =IFERROR(VLOOKUP(B60,Accounts_LTD!B:G,6,FALSE),"") | P59: =IF(G59=0," ",IF(G59="__________________"," ",ROUND(I59/G59,3))) -> 3.293 | R59: =IF(E62>G60,0,1) -> 0 | S59: =E59-G59 -> 0 | U59: =D59-I59 -> 0
B60: 15103 | C60: פחת נצבר שפורים במושכר | D60: -65929.53 | E60: -20674.67 | F60: =SUMIF(AJE_LTD!$B:$B,B60,AJE_LTD!$D:$D) -> 0 | G60: =IF(E56="__________________"," ",IF(ISERROR(F60+E60),"",(F60+E60))) -> -20674.67 | H60: =SUMIF(AJE_LTD!$B:$B,B60,AJE_LTD!$F:$F) -> 0 | I60: =IF(D56="__________________"," ",IF(ISERROR(H60+D60),"",(H60+D60))) -> -65929.53 | J60: =IF(ISERROR(VLOOKUP(B60,Accounts_LTD!$B:$E,3,FALSE)),"",VLOOKUP(B60,Accounts_LTD!$B:$E,3,FALSE)) -> 22 | K60: =IFERROR(IF(J60="","",VLOOKUP(J60,FS!$A$11:$B$241,2,FALSE)),"") -> Accumulated depreciation | L60: =IFERROR(VLOOKUP(B61,Accounts_LTD!B:G,6,FALSE),"") | P60: =IF(G60=0," ",IF(G60="__________________"," ",ROUND(I60/G60,3))) -> 3.189 | R60: =IF(E63>G61,0,1) -> 0 | S60: =E60-G60 -> 0 | U60: =D60-I60 -> 0
B61: 200015 | C61: אספירקום מערכות בע"מ | D61: -17306.34 | E61: -4917.97 | F61: =SUMIF(AJE_LTD!$B:$B,B61,AJE_LTD!$D:$D) -> 0 | G61: =IF(E57="__________________"," ",IF(ISERROR(F61+E61),"",(F61+E61))) -> -4917.97 | H61: =SUMIF(AJE_LTD!$B:$B,B61,AJE_LTD!$F:$F) -> 0 | I61: =IF(D57="__________________"," ",IF(ISERROR(H61+D61),"",(H61+D61))) -> -17306.34 | J61: =IF(ISERROR(VLOOKUP(B61,Accounts_LTD!$B:$E,3,FALSE)),"",VLOOKUP(B61,Accounts_LTD!$B:$E,3,FALSE)) -> 31.1 | K61: =IFERROR(IF(J61="","",VLOOKUP(J61,FS!$A$11:$B$241,2,FALSE)),"") -> Trade Payables | L61: =IFERROR(VLOOKUP(B62,Accounts_LTD!B:G,6,FALSE),"") | P61: =IF(G61=0," ",IF(G61="__________________"," ",ROUND(I61/G61,3))) -> 3.519 | R61: =IF(E64>G62,0,1) -> 0 | S61: =E61-G61 -> 0 | U61: =D61-I61 -> 0
B62: 20002 | C62: חברת חשמל | D62: -1308.92 | E62: -371.96 | F62: =SUMIF(AJE_LTD!$B:$B,B62,AJE_LTD!$D:$D) -> 0 | G62: =IF(E58="__________________"," ",IF(ISERROR(F62+E62),"",(F62+E62))) -> -371.96 | H62: =SUMIF(AJE_LTD!$B:$B,B62,AJE_LTD!$F:$F) -> 0 | I62: =IF(D58="__________________"," ",IF(ISERROR(H62+D62),"",(H62+D62))) -> -1308.92 | J62: =IF(ISERROR(VLOOKUP(B62,Accounts_LTD!$B:$E,3,FALSE)),"",VLOOKUP(B62,Accounts_LTD!$B:$E,3,FALSE)) -> 31.1 | K62: =IFERROR(IF(J62="","",VLOOKUP(J62,FS!$A$11:$B$241,2,FALSE)),"") -> Trade Payables | L62: =IFERROR(VLOOKUP(B63,Accounts_LTD!B:G,6,FALSE),"") | P62: =IF(G62=0," ",IF(G62="__________________"," ",ROUND(I62/G62,3))) -> 3.519 | R62: =IF(E65>G63,0,1) -> 1 | S62: =E62-G62 -> 0 | U62: =D62-I62 -> 0
B63: 200023 | C63: חברת פרטנר תקשורת בע"מ | D63: -1505.1 | E63: -427.71 | F63: =SUMIF(AJE_LTD!$B:$B,B63,AJE_LTD!$D:$D) -> 0 | G63: =IF(E59="__________________"," ",IF(ISERROR(F63+E63),"",(F63+E63))) -> -427.71 | H63: =SUMIF(AJE_LTD!$B:$B,B63,AJE_LTD!$F:$F) -> 0 | I63: =IF(D59="__________________"," ",IF(ISERROR(H63+D63),"",(H63+D63))) -> -1505.1 | J63: =IF(ISERROR(VLOOKUP(B63,Accounts_LTD!$B:$E,3,FALSE)),"",VLOOKUP(B63,Accounts_LTD!$B:$E,3,FALSE)) -> 31.1 | K63: =IFERROR(IF(J63="","",VLOOKUP(J63,FS!$A$11:$B$241,2,FALSE)),"") -> Trade Payables | L63: =IFERROR(VLOOKUP(B64,Accounts_LTD!B:G,6,FALSE),"") | P63: =IF(G63=0," ",IF(G63="__________________"," ",ROUND(I63/G63,3))) -> 3.519 | R63: =IF(E66>G64,0,1) -> 0 | S63: =E63-G63 -> 0 | U63: =D63-I63 -> 0
B64: 200027 | C64: מגדל חברה לבטוח בע"מ | D64: 8563.51 | E64: 2433.51 | F64: =SUMIF(AJE_LTD!$B:$B,B64,AJE_LTD!$D:$D) -> -2433.51 | G64: =IF(E60="__________________"," ",IF(ISERROR(F64+E64),"",(F64+E64))) -> 0 | H64: =SUMIF(AJE_LTD!$B:$B,B64,AJE_LTD!$F:$F) -> -8563.51 | I64: =IF(D60="__________________"," ",IF(ISERROR(H64+D64),"",(H64+D64))) -> 0 | J64: =IF(ISERROR(VLOOKUP(B64,Accounts_LTD!$B:$E,3,FALSE)),"",VLOOKUP(B64,Accounts_LTD!$B:$E,3,FALSE)) -> 31.1 | K64: =IFERROR(IF(J64="","",VLOOKUP(J64,FS!$A$11:$B$241,2,FALSE)),"") -> Trade Payables | L64: =IFERROR(VLOOKUP(B65,Accounts_LTD!B:G,6,FALSE),"") | P64: =IF(G64=0," ",IF(G64="__________________"," ",ROUND(I64/G64,3))) | R64: =IF(E67>G65,0,1) -> 0 | S64: =E64-G64 -> 2433.51 | U64: =D64-I64 -> 8563.51
B65: 200058 | C65: רופטופ פרטנרס בע"מ | D65: -7809.75 | E65: -2219.31 | F65: =SUMIF(AJE_LTD!$B:$B,B65,AJE_LTD!$D:$D) -> 0 | G65: =IF(E61="__________________"," ",IF(ISERROR(F65+E65),"",(F65+E65))) -> -2219.31 | H65: =SUMIF(AJE_LTD!$B:$B,B65,AJE_LTD!$F:$F) -> 0 | I65: =IF(D61="__________________"," ",IF(ISERROR(H65+D65),"",(H65+D65))) -> -7809.75 | J65: =IF(ISERROR(VLOOKUP(B65,Accounts_LTD!$B:$E,3,FALSE)),"",VLOOKUP(B65,Accounts_LTD!$B:$E,3,FALSE)) -> 31.1 | K65: =IFERROR(IF(J65="","",VLOOKUP(J65,FS!$A$11:$B$241,2,FALSE)),"") -> Trade Payables | L65: =IFERROR(VLOOKUP(B66,Accounts_LTD!B:G,6,FALSE),"") | P65: =IF(G65=0," ",IF(G65="__________________"," ",ROUND(I65/G65,3))) -> 3.519 | R65: =IF(E68>G66,0,1) -> 0 | S65: =E65-G65 -> 0 | U65: =D65-I65 -> 0
B66: 200059 | C66: ג'יטי גט טקסי סרוויסס בע"מ | D66: 1204.3 | E66: 342.23 | F66: =SUMIF(AJE_LTD!$B:$B,B66,AJE_LTD!$D:$D) -> -342.23 | G66: =IF(E62="__________________"," ",IF(ISERROR(F66+E66),"",(F66+E66))) -> 0 | H66: =SUMIF(AJE_LTD!$B:$B,B66,AJE_LTD!$F:$F) -> -1204.3 | I66: =IF(D62="__________________"," ",IF(ISERROR(H66+D66),"",(H66+D66))) -> 0 | J66: =IF(ISERROR(VLOOKUP(B66,Accounts_LTD!$B:$E,3,FALSE)),"",VLOOKUP(B66,Accounts_LTD!$B:$E,3,FALSE)) -> 31.1 | K66: =IFERROR(IF(J66="","",VLOOKUP(J66,FS!$A$11:$B$241,2,FALSE)),"") -> Trade Payables | L66: =IFERROR(VLOOKUP(B67,Accounts_LTD!B:G,6,FALSE),"") | P66: =IF(G66=0," ",IF(G66="__________________"," ",ROUND(I66/G66,3))) | R66: =IF(E69>G67,0,1) -> 1 | S66: =E66-G66 -> 342.23 | U66: =D66-I66 -> 1204.3
B67: 200060 | C67: הפניקס חברה לביטוח בע"מ | D67: -3162.04 | E67: -898.56 | F67: =SUMIF(AJE_LTD!$B:$B,B67,AJE_LTD!$D:$D) -> 0 | G67: =IF(E63="__________________"," ",IF(ISERROR(F67+E67),"",(F67+E67))) -> -898.56 | H67: =SUMIF(AJE_LTD!$B:$B,B67,AJE_LTD!$F:$F) -> 0 | I67: =IF(D63="__________________"," ",IF(ISERROR(H67+D67),"",(H67+D67))) -> -3162.04 | J67: =IF(ISERROR(VLOOKUP(B67,Accounts_LTD!$B:$E,3,FALSE)),"",VLOOKUP(B67,Accounts_LTD!$B:$E,3,FALSE)) -> 31.1 | K67: =IFERROR(IF(J67="","",VLOOKUP(J67,FS!$A$11:$B$241,2,FALSE)),"") -> Trade Payables | L67: =IFERROR(VLOOKUP(B68,Accounts_LTD!B:G,6,FALSE),"") | P67: =IF(G67=0," ",IF(G67="__________________"," ",ROUND(I67/G67,3))) -> 3.519 | R67: =IF(E70>G68,0,1) -> 0 | S67: =E67-G67 -> 0 | U67: =D67-I67 -> 0
B68: 200065 | C68: קיי.אס.פי אקספרס בע"מ | D68: 989 | E68: 281.05 | F68: =SUMIF(AJE_LTD!$B:$B,B68,AJE_LTD!$D:$D) -> -281.05 | G68: =IF(E64="__________________"," ",IF(ISERROR(F68+E68),"",(F68+E68))) -> 0 | H68: =SUMIF(AJE_LTD!$B:$B,B68,AJE_LTD!$F:$F) -> -989 | I68: =IF(D64="__________________"," ",IF(ISERROR(H68+D68),"",(H68+D68))) -> 0 | J68: =IF(ISERROR(VLOOKUP(B68,Accounts_LTD!$B:$E,3,FALSE)),"",VLOOKUP(B68,Accounts_LTD!$B:$E,3,FALSE)) -> 31.1 | K68: =IFERROR(IF(J68="","",VLOOKUP(J68,FS!$A$11:$B$241,2,FALSE)),"") -> Trade Payables | L68: =IFERROR(VLOOKUP(B69,Accounts_LTD!B:G,6,FALSE),"") | P68: =IF(G68=0," ",IF(G68="__________________"," ",ROUND(I68/G68,3))) | R68: =IF(E71>G69,0,1) -> 0 | S68: =E68-G68 -> 281.05 | U68: =D68-I68 -> 989
... B75: 200166 | C75: קינג אקספרס בע"מ king Express | D75: -62922.43 | E75: -17880.77 | F75: =SUMIF(AJE_LTD!$B:$B,B75,AJE_LTD!$D:$D) -> 0 | G75: =IF(E71="__________________"," ",IF(ISERROR(F75+E75),"",(F75+E75))) -> -17880.77 | H75: =SUMIF(AJE_LTD!$B:$B,B75,AJE_LTD!$F:$F) -> 0 | I75: =IF(D71="__________________"," ",IF(ISERROR(H75+D75),"",(H75+D75))) -> -62922.43 | J75: =IF(ISERROR(VLOOKUP(B75,Accounts_LTD!$B:$E,3,FALSE)),"",VLOOKUP(B75,Accounts_LTD!$B:$E,3,FALSE)) -> 31.1 | K75: =IFERROR(IF(J75="","",VLOOKUP(J75,FS!$A$11:$B$241,2,FALSE)),"") -> Trade Payables | L75: =IFERROR(VLOOKUP(B76,Accounts_LTD!B:G,6,FALSE),"") | P75: =IF(G75=0," ",IF(G75="__________________"," ",ROUND(I75/G75,3))) -> 3.519 | R75: =IF(E78>G76,0,1) -> 1 | S75: =E75-G75 -> 0 | U75: =D75-I75 -> 0
B76: 200221 | C76: הולו דפוס דיגיטלי בע"מ | D76: 219 | E76: 62.23 | F76: =SUMIF(AJE_LTD!$B:$B,B76,AJE_LTD!$D:$D) -> -62.23 | G76: =IF(E72="__________________"," ",IF(ISERROR(F76+E76),"",(F76+E76))) -> 0 | H76: =SUMIF(AJE_LTD!$B:$B,B76,AJE_LTD!$F:$F) -> -219 | I76: =IF(D72="__________________"," ",IF(ISERROR(H76+D76),"",(H76+D76))) -> 0 | J76: =IF(ISERROR(VLOOKUP(B76,Accounts_LTD!$B:$E,3,FALSE)),"",VLOOKUP(B76,Accounts_LTD!$B:$E,3,FALSE)) -> 31.1 | K76: =IFERROR(IF(J76="","",VLOOKUP(J76,FS!$A$11:$B$241,2,FALSE)),"") -> Trade Payables | L76: =IFERROR(VLOOKUP(#REF!,Accounts_LTD!B:G,6,FALSE),"") | P76: =IF(G76=0," ",IF(G76="__________________"," ",ROUND(I76/G76,3))) | R76: =IF(E79>G77,0,1) -> 0 | S76: =E76-G76 -> 62.23 | U76: =D76-I76 -> 219
B77: 200258 | C77: אינפורמט מחשבים בע"מ | D77: -854.1 | E77: -242.71 | F77: =SUMIF(AJE_LTD!$B:$B,B77,AJE_LTD!$D:$D) -> 0 | G77: =IF(E73="__________________"," ",IF(ISERROR(F77+E77),"",(F77+E77))) -> -242.71 | H77: =SUMIF(AJE_LTD!$B:$B,B77,AJE_LTD!$F:$F) -> 0 | I77: =IF(D73="__________________"," ",IF(ISERROR(H77+D77),"",(H77+D77))) -> -854.1 | J77: =IF(ISERROR(VLOOKUP(B77,Accounts_LTD!$B:$E,3,FALSE)),"",VLOOKUP(B77,Accounts_LTD!$B:$E,3,FALSE)) -> 31.1 | K77: =IFERROR(IF(J77="","",VLOOKUP(J77,FS!$A$11:$B$241,2,FALSE)),"") -> Trade Payables | L77: =IFERROR(VLOOKUP(B78,Accounts_LTD!B:G,6,FALSE),"") | P77: =IF(G77=0," ",IF(G77="__________________"," ",ROUND(I77/G77,3))) -> 3.519 | R77: =IF(E80>G78,0,1) -> 0 | S77: =E77-G77 -> 0 | U77: =D77-I77 -> 0
B78: 200260 | C78: קלינקס אחזקות ושרותים בע"מ | D78: -6698 | E78: -1903.38 | F78: =SUMIF(AJE_LTD!$B:$B,B78,AJE_LTD!$D:$D) -> 0 | G78: =IF(E74="__________________"," ",IF(ISERROR(F78+E78),"",(F78+E78))) -> -1903.38 | H78: =SUMIF(AJE_LTD!$B:$B,B78,AJE_LTD!$F:$F) -> 0 | I78: =IF(D74="__________________"," ",IF(ISERROR(H78+D78),"",(H78+D78))) -> -6698 | J78: =IF(ISERROR(VLOOKUP(B78,Accounts_LTD!$B:$E,3,FALSE)),"",VLOOKUP(B78,Accounts_LTD!$B:$E,3,FALSE)) -> 31.1 | K78: =IFERROR(IF(J78="","",VLOOKUP(J78,FS!$A$11:$B$241,2,FALSE)),"") -> Trade Payables | L78: =IFERROR(VLOOKUP(B79,Accounts_LTD!B:G,6,FALSE),"") | P78: =IF(G78=0," ",IF(G78="__________________"," ",ROUND(I78/G78,3))) -> 3.519 | R78: =IF(E81>G79,0,1) -> 0 | S78: =E78-G78 -> 0 | U78: =D78-I78 -> 0
B79: 200005 | C79: ג'ט בריינס jetbrains | D79: 160.15 | E79: 45.51 | F79: =SUMIF(AJE_LTD!$B:$B,B79,AJE_LTD!$D:$D) -> -45.51 | G79: =IF(E75="__________________"," ",IF(ISERROR(F79+E79),"",(F79+E79))) -> 0 | H79: =SUMIF(AJE_LTD!$B:$B,B79,AJE_LTD!$F:$F) -> -160.15 | I79: =IF(D75="__________________"," ",IF(ISERROR(H79+D79),"",(H79+D79))) -> 0 | J79: =IF(ISERROR(VLOOKUP(B79,Accounts_LTD!$B:$E,3,FALSE)),"",VLOOKUP(B79,Accounts_LTD!$B:$E,3,FALSE)) -> 31.1 | K79: =IFERROR(IF(J79="","",VLOOKUP(J79,FS!$A$11:$B$241,2,FALSE)),"") -> Trade Payables | L79: =IFERROR(VLOOKUP(B80,Accounts_LTD!B:G,6,FALSE),"") | P79: =IF(G79=0," ",IF(G79="__________________"," ",ROUND(I79/G79,3))) | R79: =IF(E82>G80,0,1) -> 0 | S79: =E79-G79 -> 45.51 | U79: =D79-I79 -> 160.15
B80: 200008 | C80: GOOGLE | D80: -1338.31 | E80: -380.31 | F80: =SUMIF(AJE_LTD!$B:$B,B80,AJE_LTD!$D:$D) -> 0 | G80: =IF(E76="__________________"," ",IF(ISERROR(F80+E80),"",(F80+E80))) -> -380.31 | H80: =SUMIF(AJE_LTD!$B:$B,B80,AJE_LTD!$F:$F) -> 0 | I80: =IF(D76="__________________"," ",IF(ISERROR(H80+D80),"",(H80+D80))) -> -1338.31 | J80: =IF(ISERROR(VLOOKUP(B80,Accounts_LTD!$B:$E,3,FALSE)),"",VLOOKUP(B80,Accounts_LTD!$B:$E,3,FALSE)) -> 31.1 | K80: =IFERROR(IF(J80="","",VLOOKUP(J80,FS!$A$11:$B$241,2,FALSE)),"") -> Trade Payables | L80: =IFERROR(VLOOKUP(B81,Accounts_LTD!B:G,6,FALSE),"") | P80: =IF(G80=0," ",IF(G80="__________________"," ",ROUND(I80/G80,3))) -> 3.519 | R80: =IF(E83>G81,0,1) -> 0 | S80: =E80-G80 -> 0 | U80: =D80-I80 -> 0
B81: 200032 | C81: UNITED | D81: 26905.39 | E81: 7645.75 | F81: =SUMIF(AJE_LTD!$B:$B,B81,AJE_LTD!$D:$D) -> -7645.75 | G81: =IF(E77="__________________"," ",IF(ISERROR(F81+E81),"",(F81+E81))) -> 0 | H81: =SUMIF(AJE_LTD!$B:$B,B81,AJE_LTD!$F:$F) -> -26905.39 | I81: =IF(D77="__________________"," ",IF(ISERROR(H81+D81),"",(H81+D81))) -> 0 | J81: =IF(ISERROR(VLOOKUP(B81,Accounts_LTD!$B:$E,3,FALSE)),"",VLOOKUP(B81,Accounts_LTD!$B:$E,3,FALSE)) -> 31.1 | K81: =IFERROR(IF(J81="","",VLOOKUP(J81,FS!$A$11:$B$241,2,FALSE)),"") -> Trade Payables | L81: =IFERROR(VLOOKUP(B82,Accounts_LTD!B:G,6,FALSE),"") | P81: =IF(G81=0," ",IF(G81="__________________"," ",ROUND(I81/G81,3))) | R81: =IF(E84>G82,0,1) -> 0 | S81: =E81-G81 -> 7645.75 | U81: =D81-I81 -> 26905.39
B82: 200075 | C82: YOAST | D82: 16682.42 | E82: 4740.67 | F82: =SUMIF(AJE_LTD!$B:$B,B82,AJE_LTD!$D:$D) -> -4740.67 | G82: =IF(E78="__________________"," ",IF(ISERROR(F82+E82),"",(F82+E82))) -> 0 | H82: =SUMIF(AJE_LTD!$B:$B,B82,AJE_LTD!$F:$F) -> -16682.42 | I82: =IF(D78="__________________"," ",IF(ISERROR(H82+D82),"",(H82+D82))) -> 0 | J82: =IF(ISERROR(VLOOKUP(B82,Accounts_LTD!$B:$E,3,FALSE)),"",VLOOKUP(B82,Accounts_LTD!$B:$E,3,FALSE)) -> 31.1 | K82: =IFERROR(IF(J82="","",VLOOKUP(J82,FS!$A$11:$B$241,2,FALSE)),"") -> Trade Payables | L82: =IFERROR(VLOOKUP(B83,Accounts_LTD!B:G,6,FALSE),"") | P82: =IF(G82=0," ",IF(G82="__________________"," ",ROUND(I82/G82,3))) | R82: =IF(E85>G83,0,1) -> 0 | S82: =E82-G82 -> 4740.67 | U82: =D82-I82 -> 16682.42
B83: 200078 | C83: Upwork Global Inc | D83: 5394.63 | E83: 1533 | F83: =SUMIF(AJE_LTD!$B:$B,B83,AJE_LTD!$D:$D) -> -1533 | G83: =IF(E79="__________________"," ",IF(ISERROR(F83+E83),"",(F83+E83))) -> 0 | H83: =SUMIF(AJE_LTD!$B:$B,B83,AJE_LTD!$F:$F) -> -5394.63 | I83: =IF(D79="__________________"," ",IF(ISERROR(H83+D83),"",(H83+D83))) -> 0 | J83: =IF(ISERROR(VLOOKUP(B83,Accounts_LTD!$B:$E,3,FALSE)),"",VLOOKUP(B83,Accounts_LTD!$B:$E,3,FALSE)) -> 31.1 | K83: =IFERROR(IF(J83="","",VLOOKUP(J83,FS!$A$11:$B$241,2,FALSE)),"") -> Trade Payables | L83: =IFERROR(VLOOKUP(B84,Accounts_LTD!B:G,6,FALSE),"") | P83: =IF(G83=0," ",IF(G83="__________________"," ",ROUND(I83/G83,3))) | R83: =IF(E86>G84,0,1) -> 0 | S83: =E83-G83 -> 1533 | U83: =D83-I83 -> 5394.63
B84: 200087 | C84: DOCUSIGN | D84: 158.36 | E84: 45 | F84: =SUMIF(AJE_LTD!$B:$B,B84,AJE_LTD!$D:$D) -> -45 | G84: =IF(E80="__________________"," ",IF(ISERROR(F84+E84),"",(F84+E84))) -> 0 | H84: =SUMIF(AJE_LTD!$B:$B,B84,AJE_LTD!$F:$F) -> -158.36 | I84: =IF(D80="__________________"," ",IF(ISERROR(H84+D84),"",(H84+D84))) -> 0 | J84: =IF(ISERROR(VLOOKUP(B84,Accounts_LTD!$B:$E,3,FALSE)),"",VLOOKUP(B84,Accounts_LTD!$B:$E,3,FALSE)) -> 31.1 | K84: =IFERROR(IF(J84="","",VLOOKUP(J84,FS!$A$11:$B$241,2,FALSE)),"") -> Trade Payables | L84: =IFERROR(VLOOKUP(B85,Accounts_LTD!B:G,6,FALSE),"") | P84: =IF(G84=0," ",IF(G84="__________________"," ",ROUND(I84/G84,3))) | R84: =IF(E87>G85,0,1) -> 0 | S84: =E84-G84 -> 45 | U84: =D84-I84 -> 158.36
B85: 200094 | C85: Microsoft | D85: 5278.5 | E85: 1500 | F85: =SUMIF(AJE_LTD!$B:$B,B85,AJE_LTD!$D:$D) -> -1500 | G85: =IF(E81="__________________"," ",IF(ISERROR(F85+E85),"",(F85+E85))) -> 0 | H85: =SUMIF(AJE_LTD!$B:$B,B85,AJE_LTD!$F:$F) -> -5278.5 | I85: =IF(D81="__________________"," ",IF(ISERROR(H85+D85),"",(H85+D85))) -> 0 | J85: =IF(ISERROR(VLOOKUP(B85,Accounts_LTD!$B:$E,3,FALSE)),"",VLOOKUP(B85,Accounts_LTD!$B:$E,3,FALSE)) -> 31.1 | K85: =IFERROR(IF(J85="","",VLOOKUP(J85,FS!$A$11:$B$241,2,FALSE)),"") -> Trade Payables | L85: =IFERROR(VLOOKUP(B86,Accounts_LTD!B:G,6,FALSE),"") | P85: =IF(G85=0," ",IF(G85="__________________"," ",ROUND(I85/G85,3))) | R85: =IF(E88>G86,0,1) -> 0 | S85: =E85-G85 -> 1500 | U85: =D85-I85 -> 5278.5
B86: 200098 | C86: DATABRICKS INC | D86: 8369.73 | E86: 2378.44 | F86: =SUMIF(AJE_LTD!$B:$B,B86,AJE_LTD!$D:$D) -> -2378.44 | G86: =IF(E82="__________________"," ",IF(ISERROR(F86+E86),"",(F86+E86))) -> 0 | H86: =SUMIF(AJE_LTD!$B:$B,B86,AJE_LTD!$F:$F) -> -8369.73 | I86: =IF(D82="__________________"," ",IF(ISERROR(H86+D86),"",(H86+D86))) -> 0 | J86: =IF(ISERROR(VLOOKUP(B86,Accounts_LTD!$B:$E,3,FALSE)),"",VLOOKUP(B86,Accounts_LTD!$B:$E,3,FALSE)) -> 31.1 | K86: =IFERROR(IF(J86="","",VLOOKUP(J86,FS!$A$11:$B$241,2,FALSE)),"") -> Trade Payables | L86: =IFERROR(VLOOKUP(#REF!,Accounts_LTD!B:G,6,FALSE),"") | P86: =IF(G86=0," ",IF(G86="__________________"," ",ROUND(I86/G86,3))) | R86: =IF(E89>G87,0,1) -> 0 | S86: =E86-G86 -> 2378.44 | U86: =D86-I86 -> 8369.73
B87: 200127 | C87: JumpCloud Inc | D87: 1375.93 | E87: 391 | F87: =SUMIF(AJE_LTD!$B:$B,B87,AJE_LTD!$D:$D) -> -391 | G87: =IF(E83="__________________"," ",IF(ISERROR(F87+E87),"",(F87+E87))) -> 0 | H87: =SUMIF(AJE_LTD!$B:$B,B87,AJE_LTD!$F:$F) -> -1375.93 | I87: =IF(D83="__________________"," ",IF(ISERROR(H87+D87),"",(H87+D87))) -> 0 | J87: =IF(ISERROR(VLOOKUP(B87,Accounts_LTD!$B:$E,3,FALSE)),"",VLOOKUP(B87,Accounts_LTD!$B:$E,3,FALSE)) -> 31.1 | K87: =IFERROR(IF(J87="","",VLOOKUP(J87,FS!$A$11:$B$241,2,FALSE)),"") -> Trade Payables | L87: =IFERROR(VLOOKUP(B88,Accounts_LTD!B:G,6,FALSE),"") | P87: =IF(G87=0," ",IF(G87="__________________"," ",ROUND(I87/G87,3))) | R87: =IF(E90>G88,0,1) -> 1 | S87: =E87-G87 -> 391 | U87: =D87-I87 -> 1375.93
B88: 200131 | C88: INTERCONTINENTAL SAN | D88: 3092.54 | E88: 878.81 | F88: =SUMIF(AJE_LTD!$B:$B,B88,AJE_LTD!$D:$D) -> -878.81 | G88: =IF(E84="__________________"," ",IF(ISERROR(F88+E88),"",(F88+E88))) -> 0 | H88: =SUMIF(AJE_LTD!$B:$B,B88,AJE_LTD!$F:$F) -> -3092.54 | I88: =IF(D84="__________________"," ",IF(ISERROR(H88+D88),"",(H88+D88))) -> 0 | J88: =IF(ISERROR(VLOOKUP(B88,Accounts_LTD!$B:$E,3,FALSE)),"",VLOOKUP(B88,Accounts_LTD!$B:$E,3,FALSE)) -> 31.1 | K88: =IFERROR(IF(J88="","",VLOOKUP(J88,FS!$A$11:$B$241,2,FALSE)),"") -> Trade Payables | L88: =IFERROR(VLOOKUP(B89,Accounts_LTD!B:G,6,FALSE),"") | P88: =IF(G88=0," ",IF(G88="__________________"," ",ROUND(I88/G88,3))) | R88: =IF(E91>G89,0,1) -> 0 | S88: =E88-G88 -> 878.81 | U88: =D88-I88 -> 3092.54
B89: 200153 | C89: Brand24 Global Inc | D89: 1539.63 | E89: 437.52 | F89: =SUMIF(AJE_LTD!$B:$B,B89,AJE_LTD!$D:$D) -> -437.52 | G89: =IF(E85="__________________"," ",IF(ISERROR(F89+E89),"",(F89+E89))) -> 0 | H89: =SUMIF(AJE_LTD!$B:$B,B89,AJE_LTD!$F:$F) -> -1539.63 | I89: =IF(D85="__________________"," ",IF(ISERROR(H89+D89),"",(H89+D89))) -> 0 | J89: =IF(ISERROR(VLOOKUP(B89,Accounts_LTD!$B:$E,3,FALSE)),"",VLOOKUP(B89,Accounts_LTD!$B:$E,3,FALSE)) -> 31.1 | K89: =IFERROR(IF(J89="","",VLOOKUP(J89,FS!$A$11:$B$241,2,FALSE)),"") -> Trade Payables | L89: =IFERROR(VLOOKUP(B90,Accounts_LTD!B:G,6,FALSE),"") | P89: =IF(G89=0," ",IF(G89="__________________"," ",ROUND(I89/G89,3))) | R89: =IF(E92>G90,0,1) -> 0 | S89: =E89-G89 -> 437.52 | U89: =D89-I89 -> 1539.63
B90: 200161 | C90: Treeverse, Inc | D90: -5421463.2 | E90: -1540626.1 | F90: =SUMIF(AJE_LTD!$B:$B,B90,AJE_LTD!$D:$D) -> -310695.28 | G90: =IF(E86="__________________"," ",IF(ISERROR(F90+E90),"",(F90+E90))) -> -1851321.4 | H90: =SUMIF(AJE_LTD!$B:$B,B90,AJE_LTD!$F:$F) -> -1093336.7 | I90: =IF(D86="__________________"," ",IF(ISERROR(H90+D90),"",(H90+D90))) -> -6514799.9 | J90: =IF(ISERROR(VLOOKUP(B90,Accounts_LTD!$B:$E,3,FALSE)),"",VLOOKUP(B90,Accounts_LTD!$B:$E,3,FALSE)) -> 6 | K90: =IFERROR(IF(J90="","",VLOOKUP(J90,FS!$A$11:$B$241,2,FALSE)),"") -> Intercompany | L90: =IFERROR(VLOOKUP(B91,Accounts_LTD!B:G,6,FALSE),"") | P90: =IF(G90=0," ",IF(G90="__________________"," ",ROUND(I90/G90,3))) -> 3.519 | R90: =IF(E93>G91,0,1) -> 1 | S90: =E90-G90 -> 310695.28 | U90: =D90-I90 -> 1093336.7
B91: 200191 | C91: Shutterstock Ireland Ltd. | D91: 102.05 | E91: 29 | F91: =SUMIF(AJE_LTD!$B:$B,B91,AJE_LTD!$D:$D) -> -29 | G91: =IF(E87="__________________"," ",IF(ISERROR(F91+E91),"",(F91+E91))) -> 0 | H91: =SUMIF(AJE_LTD!$B:$B,B91,AJE_LTD!$F:$F) -> -102.05 | I91: =IF(D87="__________________"," ",IF(ISERROR(H91+D91),"",(H91+D91))) -> 0 | J91: =IF(ISERROR(VLOOKUP(B91,Accounts_LTD!$B:$E,3,FALSE)),"",VLOOKUP(B91,Accounts_LTD!$B:$E,3,FALSE)) -> 31.1 | K91: =IFERROR(IF(J91="","",VLOOKUP(J91,FS!$A$11:$B$241,2,FALSE)),"") -> Trade Payables | L91: =IFERROR(VLOOKUP(B92,Accounts_LTD!B:G,6,FALSE),"") | P91: =IF(G91=0," ",IF(G91="__________________"," ",ROUND(I91/G91,3))) | R91: =IF(E94>G92,0,1) -> 1 | S91: =E91-G91 -> 29 | U91: =D91-I91 -> 102.05
B92: 200240 | C92: Paddle | D92: -672.13 | E92: -191 | F92: =SUMIF(AJE_LTD!$B:$B,B92,AJE_LTD!$D:$D) -> 0 | G92: =IF(E88="__________________"," ",IF(ISERROR(F92+E92),"",(F92+E92))) -> -191 | H92: =SUMIF(AJE_LTD!$B:$B,B92,AJE_LTD!$F:$F) -> 0 | I92: =IF(D88="__________________"," ",IF(ISERROR(H92+D92),"",(H92+D92))) -> -672.13 | J92: =IF(ISERROR(VLOOKUP(B92,Accounts_LTD!$B:$E,3,FALSE)),"",VLOOKUP(B92,Accounts_LTD!$B:$E,3,FALSE)) -> 31.1 | K92: =IFERROR(IF(J92="","",VLOOKUP(J92,FS!$A$11:$B$241,2,FALSE)),"") -> Trade Payables | L92: =IFERROR(VLOOKUP(B93,Accounts_LTD!B:G,6,FALSE),"") | P92: =IF(G92=0," ",IF(G92="__________________"," ",ROUND(I92/G92,3))) -> 3.519 | R92: =IF(E95>G93,0,1) -> 0 | S92: =E92-G92 -> 0 | U92: =D92-I92 -> 0
B93: 200253 | C93: PARCELFORCE WORLDWIDE MILTON KEYNES | D93: -2096.34 | E93: -595.72 | F93: =SUMIF(AJE_LTD!$B:$B,B93,AJE_LTD!$D:$D) -> 0 | G93: =IF(E89="__________________"," ",IF(ISERROR(F93+E93),"",(F93+E93))) -> -595.72 | H93: =SUMIF(AJE_LTD!$B:$B,B93,AJE_LTD!$F:$F) -> 0 | I93: =IF(D89="__________________"," ",IF(ISERROR(H93+D93),"",(H93+D93))) -> -2096.34 | J93: =IF(ISERROR(VLOOKUP(B93,Accounts_LTD!$B:$E,3,FALSE)),"",VLOOKUP(B93,Accounts_LTD!$B:$E,3,FALSE)) -> 31.1 | K93: =IFERROR(IF(J93="","",VLOOKUP(J93,FS!$A$11:$B$241,2,FALSE)),"") -> Trade Payables | L93: =IFERROR(VLOOKUP(B94,Accounts_LTD!B:G,6,FALSE),"") | P93: =IF(G93=0," ",IF(G93="__________________"," ",ROUND(I93/G93,3))) -> 3.519 | R93: =IF(E96>G94,0,1) -> 1 | S93: =E93-G93 -> 0 | U93: =D93-I93 -> 0
B94: 200269 | C94: CloserStill Media Limited | D94: -63888.18 | E94: -18155.21 | F94: =SUMIF(AJE_LTD!$B:$B,B94,AJE_LTD!$D:$D) -> 0 | G94: =IF(E90="__________________"," ",IF(ISERROR(F94+E94),"",(F94+E94))) -> -18155.21 | H94: =SUMIF(AJE_LTD!$B:$B,B94,AJE_LTD!$F:$F) -> 0 | I94: =IF(D90="__________________"," ",IF(ISERROR(H94+D94),"",(H94+D94))) -> -63888.18 | J94: =IF(ISERROR(VLOOKUP(B94,Accounts_LTD!$B:$E,3,FALSE)),"",VLOOKUP(B94,Accounts_LTD!$B:$E,3,FALSE)) -> 31.1 | K94: =IFERROR(IF(J94="","",VLOOKUP(J94,FS!$A$11:$B$241,2,FALSE)),"") -> Trade Payables | L94: =IFERROR(VLOOKUP(B95,Accounts_LTD!B:G,6,FALSE),"") | P94: =IF(G94=0," ",IF(G94="__________________"," ",ROUND(I94/G94,3))) -> 3.519 | R94: =IF(E97>G95,0,1) -> 1 | S94: =E94-G94 -> 0 | U94: =D94-I94 -> 0
B95: 21001 | C95: Amazon | D95: 6078.37 | E95: 1727.3 | F95: =SUMIF(AJE_LTD!$B:$B,B95,AJE_LTD!$D:$D) -> -1727.3 | G95: =IF(E91="__________________"," ",IF(ISERROR(F95+E95),"",(F95+E95))) -> 0 | H95: =SUMIF(AJE_LTD!$B:$B,B95,AJE_LTD!$F:$F) -> -6078.37 | I95: =IF(D91="__________________"," ",IF(ISERROR(H95+D95),"",(H95+D95))) -> 0 | J95: =IF(ISERROR(VLOOKUP(B95,Accounts_LTD!$B:$E,3,FALSE)),"",VLOOKUP(B95,Accounts_LTD!$B:$E,3,FALSE)) -> 31.1 | K95: =IFERROR(IF(J95="","",VLOOKUP(J95,FS!$A$11:$B$241,2,FALSE)),"") -> Trade Payables | L95: =IFERROR(VLOOKUP(#REF!,Accounts_LTD!B:G,6,FALSE),"") | P95: =IF(G95=0," ",IF(G95="__________________"," ",ROUND(I95/G95,3))) | R95: =IF(E98>G96,0,1) -> 0 | S95: =E95-G95 -> 1727.3 | U95: =D95-I95 -> 6078.37
B96: 20200 | C96: הוצאות לשלם | D96: -382908.46 | E96: -108811.73 | F96: =SUMIF(AJE_LTD!$B:$B,B96,AJE_LTD!$D:$D) -> -23055.51 | G96: =IF(E92="__________________"," ",IF(ISERROR(F96+E96),"",(F96+E96))) -> -131867.24 | H96: =SUMIF(AJE_LTD!$B:$B,B96,AJE_LTD!$F:$F) -> -81132.341 | I96: =IF(D92="__________________"," ",IF(ISERROR(H96+D96),"",(H96+D96))) -> -464040.8 | J96: =IF(ISERROR(VLOOKUP(B96,Accounts_LTD!$B:$E,3,FALSE)),"",VLOOKUP(B96,Accounts_LTD!$B:$E,3,FALSE)) -> 38 | K96: =IFERROR(IF(J96="","",VLOOKUP(J96,FS!$A$11:$B$241,2,FALSE)),"") -> Accrued Expenses | L96: =IFERROR(VLOOKUP(#REF!,Accounts_LTD!B:G,6,FALSE),"") | P96: =IF(G96=0," ",IF(G96="__________________"," ",ROUND(I96/G96,3))) -> 3.519 | R96: =IF(E99>G97,0,1) -> 0 | S96: =E96-G96 -> 23055.51 | U96: =D96-I96 -> 81132.341
B97: 20401 | C97: מע'מ עסקאות | D97: -82317.27 | E97: -23392.23 | F97: =SUMIF(AJE_LTD!$B:$B,B97,AJE_LTD!$D:$D) -> 0 | G97: =IF(E93="__________________"," ",IF(ISERROR(F97+E97),"",(F97+E97))) -> -23392.23 | H97: =SUMIF(AJE_LTD!$B:$B,B97,AJE_LTD!$F:$F) -> 0 | I97: =IF(D93="__________________"," ",IF(ISERROR(H97+D97),"",(H97+D97))) -> -82317.27 | J97: =IF(ISERROR(VLOOKUP(B97,Accounts_LTD!$B:$E,3,FALSE)),"",VLOOKUP(B97,Accounts_LTD!$B:$E,3,FALSE)) -> 7.3 | K97: =IFERROR(IF(J97="","",VLOOKUP(J97,FS!$A$11:$B$241,2,FALSE)),"") -> Government Institutions | L97: =IFERROR(VLOOKUP(B98,Accounts_LTD!B:G,6,FALSE),"") | P97: =IF(G97=0," ",IF(G97="__________________"," ",ROUND(I97/G97,3))) -> 3.519 | R97: =IF(E100>G98,0,1) -> 1 | S97: =E97-G97 -> 0 | U97: =D97-I97 -> 0
B98: 20402 | C98: מע'מ תשומות | D98: 214511.14 | E98: 60957.98 | F98: =SUMIF(AJE_LTD!$B:$B,B98,AJE_LTD!$D:$D) -> 0 | G98: =IF(E94="__________________"," ",IF(ISERROR(F98+E98),"",(F98+E98))) -> 60957.98 | H98: =SUMIF(AJE_LTD!$B:$B,B98,AJE_LTD!$F:$F) -> 0 | I98: =IF(D94="__________________"," ",IF(ISERROR(H98+D98),"",(H98+D98))) -> 214511.14 | J98: =IF(ISERROR(VLOOKUP(B98,Accounts_LTD!$B:$E,3,FALSE)),"",VLOOKUP(B98,Accounts_LTD!$B:$E,3,FALSE)) -> 7.3 | K98: =IFERROR(IF(J98="","",VLOOKUP(J98,FS!$A$11:$B$241,2,FALSE)),"") -> Government Institutions | L98: =IFERROR(VLOOKUP(B99,Accounts_LTD!B:G,6,FALSE),"") | P98: =IF(G98=0," ",IF(G98="__________________"," ",ROUND(I98/G98,3))) -> 3.519 | R98: =IF(E101>G99,0,1) -> 0 | S98: =E98-G98 -> 0 | U98: =D98-I98 -> 0
B99: 20403 | C99: מע'מ תשומות לנכסים | D99: 4767.32 | E99: 1354.74 | F99: =SUMIF(AJE_LTD!$B:$B,B99,AJE_LTD!$D:$D) -> 0 | G99: =IF(E95="__________________"," ",IF(ISERROR(F99+E99),"",(F99+E99))) -> 1354.74 | H99: =SUMIF(AJE_LTD!$B:$B,B99,AJE_LTD!$F:$F) -> 0 | I99: =IF(D95="__________________"," ",IF(ISERROR(H99+D99),"",(H99+D99))) -> 4767.32 | J99: =IF(ISERROR(VLOOKUP(B99,Accounts_LTD!$B:$E,3,FALSE)),"",VLOOKUP(B99,Accounts_LTD!$B:$E,3,FALSE)) -> 7.3 | K99: =IFERROR(IF(J99="","",VLOOKUP(J99,FS!$A$11:$B$241,2,FALSE)),"") -> Government Institutions | L99: =IFERROR(VLOOKUP(B100,Accounts_LTD!B:G,6,FALSE),"") | P99: =IF(G99=0," ",IF(G99="__________________"," ",ROUND(I99/G99,3))) -> 3.519 | R99: =IF(E102>G100,0,1) -> 1 | S99: =E99-G99 -> 0 | U99: =D99-I99 -> 0
B100: 20405 | C100: מע"מ במקור (אינו משתתף בדוח מע"מ) | D100: -78917.27 | E100: -22426.06 | F100: =SUMIF(AJE_LTD!$B:$B,B100,AJE_LTD!$D:$D) -> 0 | G100: =IF(E96="__________________"," ",IF(ISERROR(F100+E100),"",(F100+E100))) -> -22426.06 | H100: =SUMIF(AJE_LTD!$B:$B,B100,AJE_LTD!$F:$F) -> 0 | I100: =IF(D96="__________________"," ",IF(ISERROR(H100+D100),"",(H100+D100))) -> -78917.27 | J100: =IF(ISERROR(VLOOKUP(B100,Accounts_LTD!$B:$E,3,FALSE)),"",VLOOKUP(B100,Accounts_LTD!$B:$E,3,FALSE)) -> 7.3 | K100: =IFERROR(IF(J100="","",VLOOKUP(J100,FS!$A$11:$B$241,2,FALSE)),"") -> Government Institutions | L100: =IFERROR(VLOOKUP(B101,Accounts_LTD!B:G,6,FALSE),"") | P100: =IF(G100=0," ",IF(G100="__________________"," ",ROUND(I100/G100,3))) -> 3.519 | R100: =IF(E103>G101,0,1) -> 1 | S100: =E100-G100 -> 0 | U100: =D100-I100 -> 0
B101: 20406 | C101: קיזוז מע"מ חשבונית עצמית (אינו משתתף בדוח מע"מ) | D101: 78917.27 | E101: 22426.06 | F101: =SUMIF(AJE_LTD!$B:$B,B101,AJE_LTD!$D:$D) -> 0 | G101: =IF(E97="__________________"," ",IF(ISERROR(F101+E101),"",(F101+E101))) -> 22426.06 | H101: =SUMIF(AJE_LTD!$B:$B,B101,AJE_LTD!$F:$F) -> 0 | I101: =IF(D97="__________________"," ",IF(ISERROR(H101+D101),"",(H101+D101))) -> 78917.27 | J101: =IF(ISERROR(VLOOKUP(B101,Accounts_LTD!$B:$E,3,FALSE)),"",VLOOKUP(B101,Accounts_LTD!$B:$E,3,FALSE)) -> 7.3 | K101: =IFERROR(IF(J101="","",VLOOKUP(J101,FS!$A$11:$B$241,2,FALSE)),"") -> Government Institutions | L101: =IFERROR(VLOOKUP(B102,Accounts_LTD!B:G,6,FALSE),"") | P101: =IF(G101=0," ",IF(G101="__________________"," ",ROUND(I101/G101,3))) -> 3.519 | R101: =IF(E104>G102,0,1) -> 0 | S101: =E101-G101 -> 0 | U101: =D101-I101 -> 0
B102: 20500 | C102: ביטוח לאומי ניכויים | D102: -145844 | E102: -41444.73 | F102: =SUMIF(AJE_LTD!$B:$B,B102,AJE_LTD!$D:$D) -> 0 | G102: =IF(E98="__________________"," ",IF(ISERROR(F102+E102),"",(F102+E102))) -> -41444.73 | H102: =SUMIF(AJE_LTD!$B:$B,B102,AJE_LTD!$F:$F) -> 0 | I102: =IF(D98="__________________"," ",IF(ISERROR(H102+D102),"",(H102+D102))) -> -145844 | J102: =IF(ISERROR(VLOOKUP(B102,Accounts_LTD!$B:$E,3,FALSE)),"",VLOOKUP(B102,Accounts_LTD!$B:$E,3,FALSE)) -> 33.3 | K102: =IFERROR(IF(J102="","",VLOOKUP(J102,FS!$A$11:$B$241,2,FALSE)),"") -> Accruals related to Employees | L102: =IFERROR(VLOOKUP(#REF!,Accounts_LTD!B:G,6,FALSE),"") | P102: =IF(G102=0," ",IF(G102="__________________"," ",ROUND(I102/G102,3))) -> 3.519 | R102: =IF(E105>G103,0,1) -> 0 | S102: =E102-G102 -> 0 | U102: =D102-I102 -> 0
B103: 20501 | C103: מס הכנסה ניכויים | D103: -225229 | E103: -64013.98 | F103: =SUMIF(AJE_LTD!$B:$B,B103,AJE_LTD!$D:$D) -> 0 | G103: =IF(E99="__________________"," ",IF(ISERROR(F103+E103),"",(F103+E103))) -> -64013.98 | H103: =SUMIF(AJE_LTD!$B:$B,B103,AJE_LTD!$F:$F) -> 0 | I103: =IF(D99="__________________"," ",IF(ISERROR(H103+D103),"",(H103+D103))) -> -225229 | J103: =IF(ISERROR(VLOOKUP(B103,Accounts_LTD!$B:$E,3,FALSE)),"",VLOOKUP(B103,Accounts_LTD!$B:$E,3,FALSE)) -> 33.3 | K103: =IFERROR(IF(J103="","",VLOOKUP(J103,FS!$A$11:$B$241,2,FALSE)),"") -> Accruals related to Employees | L103: =IFERROR(VLOOKUP(B104,Accounts_LTD!B:G,6,FALSE),"") | P103: =IF(G103=0," ",IF(G103="__________________"," ",ROUND(I103/G103,3))) -> 3.518 | R103: =IF(E106>G104,0,1) -> 0 | S103: =E103-G103 -> 0 | U103: =D103-I103 -> 0
B104: 20602 | C104: ניכוי מס במקור - ספקים | D104: -0.27 | E104: -0.08 | F104: =SUMIF(AJE_LTD!$B:$B,B104,AJE_LTD!$D:$D) -> 0 | G104: =IF(E100="__________________"," ",IF(ISERROR(F104+E104),"",(F104+E104))) -> -0.08 | H104: =SUMIF(AJE_LTD!$B:$B,B104,AJE_LTD!$F:$F) -> 0 | I104: =IF(D100="__________________"," ",IF(ISERROR(H104+D104),"",(H104+D104))) -> -0.27 | J104: =IF(ISERROR(VLOOKUP(B104,Accounts_LTD!$B:$E,3,FALSE)),"",VLOOKUP(B104,Accounts_LTD!$B:$E,3,FALSE)) -> 7.3 | K104: =IFERROR(IF(J104="","",VLOOKUP(J104,FS!$A$11:$B$241,2,FALSE)),"") -> Government Institutions | L104: =IFERROR(VLOOKUP(B105,Accounts_LTD!B:G,6,FALSE),"") | P104: =IF(G104=0," ",IF(G104="__________________"," ",ROUND(I104/G104,3))) -> 3.375 | R104: =IF(E107>G105,0,1) -> 0 | S104: =E104-G104 -> 0 | U104: =D104-I104 -> 0
B105: 20603 | C105: ניכוי מס במקור - לקוחות | D105: 2925 | E105: 831.2 | F105: =SUMIF(AJE_LTD!$B:$B,B105,AJE_LTD!$D:$D) -> 0 | G105: =IF(E101="__________________"," ",IF(ISERROR(F105+E105),"",(F105+E105))) -> 831.2 | H105: =SUMIF(AJE_LTD!$B:$B,B105,AJE_LTD!$F:$F) -> 0 | I105: =IF(D101="__________________"," ",IF(ISERROR(H105+D105),"",(H105+D105))) -> 2925 | J105: =IF(ISERROR(VLOOKUP(B105,Accounts_LTD!$B:$E,3,FALSE)),"",VLOOKUP(B105,Accounts_LTD!$B:$E,3,FALSE)) -> 7.3 | K105: =IFERROR(IF(J105="","",VLOOKUP(J105,FS!$A$11:$B$241,2,FALSE)),"") -> Government Institutions | L105: =IFERROR(VLOOKUP(B106,Accounts_LTD!B:G,6,FALSE),"") | P105: =IF(G105=0," ",IF(G105="__________________"," ",ROUND(I105/G105,3))) -> 3.519 | R105: =IF(E108>G106,0,1) -> 1 | S105: =E105-G105 -> 0 | U105: =D105-I105 -> 0
B106: 20604 | C106: ניכוי מס במקור - ריבית | D106: 6.32 | E106: 1.8 | F106: =SUMIF(AJE_LTD!$B:$B,B106,AJE_LTD!$D:$D) -> 0 | G106: =IF(E102="__________________"," ",IF(ISERROR(F106+E106),"",(F106+E106))) -> 1.8 | H106: =SUMIF(AJE_LTD!$B:$B,B106,AJE_LTD!$F:$F) -> 0 | I106: =IF(D102="__________________"," ",IF(ISERROR(H106+D106),"",(H106+D106))) -> 6.32 | J106: =IF(ISERROR(VLOOKUP(B106,Accounts_LTD!$B:$E,3,FALSE)),"",VLOOKUP(B106,Accounts_LTD!$B:$E,3,FALSE)) -> 7.3 | K106: =IFERROR(IF(J106="","",VLOOKUP(J106,FS!$A$11:$B$241,2,FALSE)),"") -> Government Institutions | L106: =IFERROR(VLOOKUP(B107,Accounts_LTD!B:G,6,FALSE),"") | P106: =IF(G106=0," ",IF(G106="__________________"," ",ROUND(I106/G106,3))) -> 3.511 | R106: =IF(E109>G107,0,1) -> 1 | S106: =E106-G106 -> 0 | U106: =D106-I106 -> 0
B107: 20606 | C107: מקדמות בגין עודפות 2021 | D107: 26450 | E107: 7525.81 | F107: =SUMIF(AJE_LTD!$B:$B,B107,AJE_LTD!$D:$D) -> 0 | G107: =IF(E103="__________________"," ",IF(ISERROR(F107+E107),"",(F107+E107))) -> 7525.81 | H107: =SUMIF(AJE_LTD!$B:$B,B107,AJE_LTD!$F:$F) -> 0 | I107: =IF(D103="__________________"," ",IF(ISERROR(H107+D107),"",(H107+D107))) -> 26450 | J107: =IF(ISERROR(VLOOKUP(B107,Accounts_LTD!$B:$E,3,FALSE)),"",VLOOKUP(B107,Accounts_LTD!$B:$E,3,FALSE)) -> 7.3 | K107: =IFERROR(IF(J107="","",VLOOKUP(J107,FS!$A$11:$B$241,2,FALSE)),"") -> Government Institutions | L107: =IFERROR(VLOOKUP(B108,Accounts_LTD!B:G,6,FALSE),"") | P107: =IF(G107=0," ",IF(G107="__________________"," ",ROUND(I107/G107,3))) -> 3.515 | R107: =IF(E110>G108,0,1) -> 0 | S107: =E107-G107 -> 0 | U107: =D107-I107 -> 0
B108: 20799 | C108: חו"ז גמל | D108: -214898 | E108: -61067.92 | F108: =SUMIF(AJE_LTD!$B:$B,B108,AJE_LTD!$D:$D) -> 0 | G108: =IF(E104="__________________"," ",IF(ISERROR(F108+E108),"",(F108+E108))) -> -61067.92 | H108: =SUMIF(AJE_LTD!$B:$B,B108,AJE_LTD!$F:$F) -> 0 | I108: =IF(D104="__________________"," ",IF(ISERROR(H108+D108),"",(H108+D108))) -> -214898 | J108: =IF(ISERROR(VLOOKUP(B108,Accounts_LTD!$B:$E,3,FALSE)),"",VLOOKUP(B108,Accounts_LTD!$B:$E,3,FALSE)) -> 33.3 | K108: =IFERROR(IF(J108="","",VLOOKUP(J108,FS!$A$11:$B$241,2,FALSE)),"") -> Accruals related to Employees | L108: =IFERROR(VLOOKUP(B109,Accounts_LTD!B:G,6,FALSE),"") | P108: =IF(G108=0," ",IF(G108="__________________"," ",ROUND(I108/G108,3))) -> 3.519 | R108: =IF(E111>G109,0,1) -> 0 | S108: =E108-G108 -> 0 | U108: =D108-I108 -> 0
B109: 20900 | C109: חו"ז עובדים | D109: -487277 | E109: -138470.3 | F109: =SUMIF(AJE_LTD!$B:$B,B109,AJE_LTD!$D:$D) -> 0 | G109: =IF(E105="__________________"," ",IF(ISERROR(F109+E109),"",(F109+E109))) -> -138470.3 | H109: =SUMIF(AJE_LTD!$B:$B,B109,AJE_LTD!$F:$F) -> 0 | I109: =IF(D105="__________________"," ",IF(ISERROR(H109+D109),"",(H109+D109))) -> -487277 | J109: =IF(ISERROR(VLOOKUP(B109,Accounts_LTD!$B:$E,3,FALSE)),"",VLOOKUP(B109,Accounts_LTD!$B:$E,3,FALSE)) -> 33.3 | K109: =IFERROR(IF(J109="","",VLOOKUP(J109,FS!$A$11:$B$241,2,FALSE)),"") -> Accruals related to Employees | L109: =IFERROR(VLOOKUP(B110,Accounts_LTD!B:G,6,FALSE),"") | P109: =IF(G109=0," ",IF(G109="__________________"," ",ROUND(I109/G109,3))) -> 3.519 | R109: =IF(E112>G110,0,1) -> 1 | S109: =E109-G109 -> 0 | U109: =D109-I109 -> 0
...

Sheet GL_INC
C3: General Ledger
C4: =WP_LTD!B4 -> As of Dec 31, 2022
A6: Account | B6: Account | C6: שם | D6: יתרה | E6: AJE | F6: Final Balance USD | G6: FS Code | H6: FS Name | I6: BVA Code | J6: Check
E7: =SUMIF(AJE_INC!B:B,B7,AJE_INC!D:D) -> 0 | F7: =IF(D3="__________________"," ",IF(ISERROR(E7+D7),"",(E7+D7))) -> 0 | G7: =IF(ISERROR(VLOOKUP(B7,Accounts_INC!$B:$E,3,FALSE)),"",VLOOKUP(B7,Accounts_INC!$B:$E,3,FALSE)) | H7: =IFERROR(IF(G7="","",VLOOKUP(G7,FS!$A$11:$B$241,2,FALSE)),"")
A8: PL001 | B8: PL001 | C8: =VLOOKUP(B8,Accounts_INC!B:C,2,0) -> #N/A | E8: =SUMIF(AJE_INC!B:B,B8,AJE_INC!D:D) -> 0 | F8: =IF(D4="__________________"," ",IF(ISERROR(E8+D8),"",(E8+D8))) -> 0 | G8: =IF(ISERROR(VLOOKUP(B8,Accounts_INC!$B:$E,3,FALSE)),"",VLOOKUP(B8,Accounts_INC!$B:$E,3,FALSE)) | H8: =IFERROR(IF(G8="","",VLOOKUP(G8,FS!$A$11:$B$241,2,FALSE)),"") | I8: =IFERROR(VLOOKUP(B8,Accounts_LTD!B:G,6,FALSE),"")
A9: BS11000 | B9: BS11000 | C9: =VLOOKUP(B9,Accounts_INC!B:C,2,0) -> #N/A | E9: =SUMIF(AJE_INC!B:B,B9,AJE_INC!D:D) -> 0 | F9: =IF(D5="__________________"," ",IF(ISERROR(E9+D9),"",(E9+D9))) -> 0 | G9: =IF(ISERROR(VLOOKUP(B9,Accounts_INC!$B:$E,3,FALSE)),"",VLOOKUP(B9,Accounts_INC!$B:$E,3,FALSE)) | H9: =IFERROR(IF(G9="","",VLOOKUP(G9,FS!$A$11:$B$241,2,FALSE)),"") | I9: =IFERROR(VLOOKUP(B9,Accounts_LTD!B:G,6,FALSE),"")
A10: 90003 | B10: 90003 | C10: =VLOOKUP(B10,Accounts_INC!B:C,2,0) -> #N/A | E10: =SUMIF(AJE_INC!B:B,B10,AJE_INC!D:D) -> 0 | F10: =IF(D6="__________________"," ",IF(ISERROR(E10+D10),"",(E10+D10))) -> 0 | G10: =IF(ISERROR(VLOOKUP(B10,Accounts_INC!$B:$E,3,FALSE)),"",VLOOKUP(B10,Accounts_INC!$B:$E,3,FALSE)) | H10: =IFERROR(IF(G10="","",VLOOKUP(G10,FS!$A$11:$B$241,2,FALSE)),"") | I10: =IFERROR(VLOOKUP(B10,Accounts_LTD!B:G,6,FALSE),"")
A11: BS99001 | B11: BS99001 | C11: =VLOOKUP(B11,Accounts_INC!B:C,2,0) -> #N/A | E11: =SUMIF(AJE_INC!B:B,B11,AJE_INC!D:D) -> 0 | F11: =IF(D7="__________________"," ",IF(ISERROR(E11+D11),"",(E11+D11))) -> 0 | G11: =IF(ISERROR(VLOOKUP(B11,Accounts_INC!$B:$E,3,FALSE)),"",VLOOKUP(B11,Accounts_INC!$B:$E,3,FALSE)) | H11: =IFERROR(IF(G11="","",VLOOKUP(G11,FS!$A$11:$B$241,2,FALSE)),"") | I11: =IFERROR(VLOOKUP(B11,Accounts_LTD!B:G,6,FALSE),"")
E12: =SUMIF(AJE_INC!B:B,B12,AJE_INC!D:D) -> 0 | F12: =IF(D8="__________________"," ",IF(ISERROR(E12+D12),"",(E12+D12))) -> 0 | G12: =IF(ISERROR(VLOOKUP(B12,Accounts_INC!$B:$E,3,FALSE)),"",VLOOKUP(B12,Accounts_INC!$B:$E,3,FALSE)) | H12: =IFERROR(IF(G12="","",VLOOKUP(G12,FS!$A$11:$B$241,2,FALSE)),"") | I12: =IFERROR(VLOOKUP(B12,Accounts_LTD!B:G,6,FALSE),"")
A13: PL008 | B13: PL008 | C13: =VLOOKUP(B13,Accounts_INC!B:C,2,0) -> #N/A | E13: =SUMIF(AJE_INC!B:B,B13,AJE_INC!D:D) -> 0 | F13: =IF(D10="__________________"," ",IF(ISERROR(E13+D13),"",(E13+D13))) -> 0 | G13: =IF(ISERROR(VLOOKUP(B13,Accounts_INC!$B:$E,3,FALSE)),"",VLOOKUP(B13,Accounts_INC!$B:$E,3,FALSE)) | H13: =IFERROR(IF(G13="","",VLOOKUP(G13,FS!$A$11:$B$241,2,FALSE)),"") | I13: =IFERROR(VLOOKUP(B13,Accounts_LTD!B:G,6,FALSE),"")
B14: PL111 | C14: Bonus Customer Success | E14: =SUMIF(AJE_INC!B:B,B14,AJE_INC!D:D) -> 117986 | F14: =IF(D11="__________________"," ",IF(ISERROR(E14+D14),"",(E14+D14))) -> 117986 | G14: =IF(ISERROR(VLOOKUP(B14,Accounts_INC!$B:$E,3,FALSE)),"",VLOOKUP(B14,Accounts_INC!$B:$E,3,FALSE)) -> 420 | H14: =IFERROR(IF(G14="","",VLOOKUP(G14,FS!$A$11:$B$241,2,FALSE)),"") -> Bonus Customer Success
B15: PL112 | C15: Bonus DevEx | E15: =SUMIF(AJE_INC!B:B,B15,AJE_INC!D:D) -> 13708 | F15: =IF(D12="__________________"," ",IF(ISERROR(E15+D15),"",(E15+D15))) -> 13708 | G15: =IF(ISERROR(VLOOKUP(B15,Accounts_INC!$B:$E,3,FALSE)),"",VLOOKUP(B15,Accounts_INC!$B:$E,3,FALSE)) -> 601 | H15: =IFERROR(IF(G15="","",VLOOKUP(G15,FS!$A$11:$B$241,2,FALSE)),"") -> Bonus DevEx
B16: PL113 | C16: =VLOOKUP(B16,Accounts_INC!B:C,2,0) -> Option Expenses | E16: =SUMIF(AJE_INC!B:B,B16,AJE_INC!D:D) -> 32476.959 | F16: =IF(D13="__________________"," ",IF(ISERROR(E16+D16),"",(E16+D16))) -> 32476.959 | G16: =IF(ISERROR(VLOOKUP(B16,Accounts_INC!$B:$E,3,FALSE)),"",VLOOKUP(B16,Accounts_INC!$B:$E,3,FALSE)) -> 400 | H16: =IFERROR(IF(G16="","",VLOOKUP(G16,FS!$A$11:$B$241,2,FALSE)),"") -> Payroll and related (Customer Success)
B17: BS114 | C17: =VLOOKUP(B17,Accounts_INC!B:C,2,0) -> Stock compensation | E17: =SUMIF(AJE_INC!B:B,B17,AJE_INC!D:D) -> -32476.959 | F17: =IF(D13="__________________"," ",IF(ISERROR(E17+D17),"",(E17+D17))) -> -32476.959 | G17: =IF(ISERROR(VLOOKUP(B17,Accounts_INC!$B:$E,3,FALSE)),"",VLOOKUP(B17,Accounts_INC!$B:$E,3,FALSE)) -> 54 | H17: =IFERROR(IF(G17="","",VLOOKUP(G17,FS!$A$11:$B$241,2,FALSE)),"") -> Stock compensation
E18: =SUMIF(AJE_INC!B:B,B18,AJE_INC!D:D) -> 0 | F18: =IF(D14="__________________"," ",IF(ISERROR(E18+D18),"",(E18+D18))) -> 0 | G18: =IF(ISERROR(VLOOKUP(B18,Accounts_INC!$B:$E,3,FALSE)),"",VLOOKUP(B18,Accounts_INC!$B:$E,3,FALSE)) | H18: =IFERROR(IF(G18="","",VLOOKUP(G18,FS!$A$11:$B$241,2,FALSE)),"")
E19: =SUMIF(AJE_INC!B:B,B19,AJE_INC!D:D) -> 0 | F19: =IF(D15="__________________"," ",IF(ISERROR(E19+D19),"",(E19+D19))) -> 0 | G19: =IF(ISERROR(VLOOKUP(B19,Accounts_INC!$B:$E,3,FALSE)),"",VLOOKUP(B19,Accounts_INC!$B:$E,3,FALSE)) | H19: =IFERROR(IF(G19="","",VLOOKUP(G19,FS!$A$11:$B$241,2,FALSE)),"") | I19: =IFERROR(VLOOKUP(B19,Accounts_LTD!B:G,6,FALSE),"")
E20: =SUMIF(AJE_INC!B:B,B20,AJE_INC!D:D) -> 0 | F20: =IF(D16="__________________"," ",IF(ISERROR(E20+D20),"",(E20+D20))) -> 0 | G20: =IF(ISERROR(VLOOKUP(B20,Accounts_INC!$B:$E,3,FALSE)),"",VLOOKUP(B20,Accounts_INC!$B:$E,3,FALSE)) | H20: =IFERROR(IF(G20="","",VLOOKUP(G20,FS!$A$11:$B$241,2,FALSE)),"")
E21: =SUMIF(AJE_INC!B:B,B21,AJE_INC!D:D) -> 0 | F21: =IF(D17="__________________"," ",IF(ISERROR(E21+D21),"",(E21+D21))) -> 0 | G21: =IF(ISERROR(VLOOKUP(B21,Accounts_INC!$B:$E,3,FALSE)),"",VLOOKUP(B21,Accounts_INC!$B:$E,3,FALSE)) | H21: =IFERROR(IF(G21="","",VLOOKUP(G21,FS!$A$11:$B$241,2,FALSE)),"")
E22: =SUMIF(AJE_INC!B:B,B22,AJE_INC!D:D) -> 0 | F22: =IF(D18="__________________"," ",IF(ISERROR(E22+D22),"",(E22+D22))) -> 0 | G22: =IF(ISERROR(VLOOKUP(B22,Accounts_INC!$B:$E,3,FALSE)),"",VLOOKUP(B22,Accounts_INC!$B:$E,3,FALSE)) | H22: =IFERROR(IF(G22="","",VLOOKUP(G22,FS!$A$11:$B$241,2,FALSE)),"")
E23: =SUMIF(AJE_INC!B:B,B23,AJE_INC!D:D) -> 0 | F23: =IF(D19="__________________"," ",IF(ISERROR(E23+D23),"",(E23+D23))) -> 0 | G23: =IF(ISERROR(VLOOKUP(B23,Accounts_INC!$B:$E,3,FALSE)),"",VLOOKUP(B23,Accounts_INC!$B:$E,3,FALSE)) | H23: =IFERROR(IF(G23="","",VLOOKUP(G23,FS!$A$11:$B$241,2,FALSE)),"")
E24: =SUMIF(AJE_INC!B:B,B24,AJE_INC!D:D) -> 0 | F24: =IF(D20="__________________"," ",IF(ISERROR(E24+D24),"",(E24+D24))) -> 0 | G24: =IF(ISERROR(VLOOKUP(B24,Accounts_INC!$B:$E,3,FALSE)),"",VLOOKUP(B24,Accounts_INC!$B:$E,3,FALSE)) | H24: =IFERROR(IF(G24="","",VLOOKUP(G24,FS!$A$11:$B$241,2,FALSE)),"")
E25: =SUMIF(AJE_INC!B:B,B25,AJE_INC!D:D) -> 0 | F25: =IF(D21="__________________"," ",IF(ISERROR(E25+D25),"",(E25+D25))) -> 0 | G25: =IF(ISERROR(VLOOKUP(B25,Accounts_INC!$B:$E,3,FALSE)),"",VLOOKUP(B25,Accounts_INC!$B:$E,3,FALSE)) | H25: =IFERROR(IF(G25="","",VLOOKUP(G25,FS!$A$11:$B$241,2,FALSE)),"")
E26: =SUMIF(AJE_INC!B:B,B26,AJE_INC!D:D) -> 0 | F26: =IF(D22="__________________"," ",IF(ISERROR(E26+D26),"",(E26+D26))) -> 0 | G26: =IF(ISERROR(VLOOKUP(B26,Accounts_INC!$B:$E,3,FALSE)),"",VLOOKUP(B26,Accounts_INC!$B:$E,3,FALSE)) | H26: =IFERROR(IF(G26="","",VLOOKUP(G26,FS!$A$11:$B$241,2,FALSE)),"")
E27: =SUMIF(AJE_INC!B:B,B27,AJE_INC!D:D) -> 0 | F27: =IF(D23="__________________"," ",IF(ISERROR(E27+D27),"",(E27+D27))) -> 0 | G27: =IF(ISERROR(VLOOKUP(B27,Accounts_INC!$B:$E,3,FALSE)),"",VLOOKUP(B27,Accounts_INC!$B:$E,3,FALSE)) | H27: =IFERROR(IF(G27="","",VLOOKUP(G27,FS!$A$11:$B$241,2,FALSE)),"")
E28: =SUMIF(AJE_INC!B:B,B28,AJE_INC!D:D) -> 0 | F28: =IF(D24="__________________"," ",IF(ISERROR(E28+D28),"",(E28+D28))) -> 0 | G28: =IF(ISERROR(VLOOKUP(B28,Accounts_INC!$B:$E,3,FALSE)),"",VLOOKUP(B28,Accounts_INC!$B:$E,3,FALSE)) | H28: =IFERROR(IF(G28="","",VLOOKUP(G28,FS!$A$11:$B$241,2,FALSE)),"")
B29: =IF(IF(ISERROR(LEFT(C29,5)*1),"",(LEFT(C29,5)*1))<10000,"",IF(ISERROR(LEFT(C29,5)*1),"",(LEFT(C29,5)*1))) | E29: =SUMIF(AJE_INC!B:B,B29,AJE_INC!D:D) -> 0 | F29: =IF(D25="__________________"," ",IF(ISERROR(E29+D29),"",(E29+D29))) -> 0 | G29: =IF(ISERROR(VLOOKUP(B29,Accounts_INC!$B:$E,3,FALSE)),"",VLOOKUP(B29,Accounts_INC!$B:$E,3,FALSE)) | H29: =IFERROR(IF(G29="","",VLOOKUP(G29,FS!$A$11:$B$241,2,FALSE)),"") | I29: =IFERROR(VLOOKUP(B29,Accounts_LTD!B:G,6,FALSE),"") | J29: =IF(and(B29<>"",G29=""),"Error","")
A30: חשבון | B30: חשבון | C30: תאור החשבון | D30: יתרה בדולרים | E30: =SUMIF(AJE_INC!B:B,B30,AJE_INC!D:D) -> 0 | F30: =IF(D26="__________________"," ",IF(ISERROR(E30+D30),"",(E30+D30))) | G30: =IF(ISERROR(VLOOKUP(B30,Accounts_INC!$B:$E,3,FALSE)),"",VLOOKUP(B30,Accounts_INC!$B:$E,3,FALSE)) | H30: =IFERROR(IF(G30="","",VLOOKUP(G30,FS!$A$11:$B$241,2,FALSE)),"") | I30: =IFERROR(VLOOKUP(#REF!,Accounts_LTD!B:G,6,FALSE),"")
A31: 1010 | B31: =LEFT(C31,4) -> 1010 | C31: 1010 Chase Checking:2986 Checking Leumi Activity - Deposit Accounts | D31: 326572.86 | E31: =SUMIF(AJE_INC!B:B,B31,AJE_INC!D:D) -> 0 | F31: =IF(D27="__________________"," ",IF(ISERROR(E31+D31),"",(E31+D31))) -> 326572.86 | G31: =IF(ISERROR(VLOOKUP(B31,Accounts_INC!$B:$E,3,FALSE)),"",VLOOKUP(B31,Accounts_INC!$B:$E,3,FALSE)) -> 1.5 | H31: =IFERROR(IF(G31="","",VLOOKUP(G31,FS!$A$11:$B$241,2,FALSE)),"") -> Cash and cash equivalents US | I31: =IFERROR(VLOOKUP(B32,Accounts_LTD!B:G,6,FALSE),"")
A32: 1020 | B32: =LEFT(C32,4) -> 1020 | C32: 1020 Chase Checking:TREEVERSE INC - BUSINESS MONEY MARKET | D32: 2548926.9 | E32: =SUMIF(AJE_INC!B:B,B32,AJE_INC!D:D) -> 0 | F32: =IF(D28="__________________"," ",IF(ISERROR(E32+D32),"",(E32+D32))) -> 2548926.9 | G32: =IF(ISERROR(VLOOKUP(B32,Accounts_INC!$B:$E,3,FALSE)),"",VLOOKUP(B32,Accounts_INC!$B:$E,3,FALSE)) -> 1.5 | H32: =IFERROR(IF(G32="","",VLOOKUP(G32,FS!$A$11:$B$241,2,FALSE)),"") -> Cash and cash equivalents US | I32: =IFERROR(VLOOKUP(B33,Accounts_LTD!B:G,6,FALSE),"")
A33: 1030 | B33: =LEFT(C33,4) -> 1030 | C33: 1030 Chase Checking:Time Deposit | D33: 20000 | E33: =SUMIF(AJE_INC!B:B,B33,AJE_INC!D:D) -> 0 | F33: =IF(D29="__________________"," ",IF(ISERROR(E33+D33),"",(E33+D33))) -> 20000 | G33: =IF(ISERROR(VLOOKUP(B33,Accounts_INC!$B:$E,3,FALSE)),"",VLOOKUP(B33,Accounts_INC!$B:$E,3,FALSE)) -> 1.5 | H33: =IFERROR(IF(G33="","",VLOOKUP(G33,FS!$A$11:$B$241,2,FALSE)),"") -> Cash and cash equivalents US | I33: =IFERROR(VLOOKUP(#REF!,Accounts_LTD!B:G,6,FALSE),"")
A34: 1015 | B34: =LEFT(C34,4) -> 1015 | C34: 1015 Euro Account | D34: 49098.39 | E34: =SUMIF(AJE_INC!B:B,B34,AJE_INC!D:D) -> 0 | F34: =IF(D30="__________________"," ",IF(ISERROR(E34+D34),"",(E34+D34))) -> 49098.39 | G34: =IF(ISERROR(VLOOKUP(B34,Accounts_INC!$B:$E,3,FALSE)),"",VLOOKUP(B34,Accounts_INC!$B:$E,3,FALSE)) -> 1.5 | H34: =IFERROR(IF(G34="","",VLOOKUP(G34,FS!$A$11:$B$241,2,FALSE)),"") -> Cash and cash equivalents US | I34: =IFERROR(VLOOKUP(#REF!,Accounts_LTD!B:G,6,FALSE),"")
A35: 1025 | B35: =LEFT(C35,4) -> 1025 | C35: 1025 CAD Account | D35: 952.6 | E35: =SUMIF(AJE_INC!B:B,B35,AJE_INC!D:D) -> 0 | F35: =IF(D31="__________________"," ",IF(ISERROR(E35+D35),"",(E35+D35))) -> 952.6 | G35: =IF(ISERROR(VLOOKUP(B35,Accounts_INC!$B:$E,3,FALSE)),"",VLOOKUP(B35,Accounts_INC!$B:$E,3,FALSE)) -> 1.5 | H35: =IFERROR(IF(G35="","",VLOOKUP(G35,FS!$A$11:$B$241,2,FALSE)),"") -> Cash and cash equivalents US
A36: 1100 | B36: =LEFT(C36,4) -> 1100 | C36: 1100 Accounts Receivable | D36: 0 | E36: =SUMIF(AJE_INC!B:B,B36,AJE_INC!D:D) -> 0 | F36: =IF(D32="__________________"," ",IF(ISERROR(E36+D36),"",(E36+D36))) -> 0 | G36: =IF(ISERROR(VLOOKUP(B36,Accounts_INC!$B:$E,3,FALSE)),"",VLOOKUP(B36,Accounts_INC!$B:$E,3,FALSE)) -> 5.1 | H36: =IFERROR(IF(G36="","",VLOOKUP(G36,FS!$A$11:$B$241,2,FALSE)),"") -> Trade receivables | I36: =IFERROR(VLOOKUP(#REF!,Accounts_LTD!B:G,6,FALSE),"")
A37: 1300 | B37: =LEFT(C37,4) -> 1300 | C37: 1300 Prepaid Expenses | D37: 19852.35 | E37: =SUMIF(AJE_INC!B:B,B37,AJE_INC!D:D) -> 0 | F37: =IF(D33="__________________"," ",IF(ISERROR(E37+D37),"",(E37+D37))) -> 19852.35 | G37: =IF(ISERROR(VLOOKUP(B37,Accounts_INC!$B:$E,3,FALSE)),"",VLOOKUP(B37,Accounts_INC!$B:$E,3,FALSE)) -> 7.1 | H37: =IFERROR(IF(G37="","",VLOOKUP(G37,FS!$A$11:$B$241,2,FALSE)),"") -> Prepaid expenses | I37: =IFERROR(VLOOKUP(B38,Accounts_LTD!B:G,6,FALSE),"")
A38: 1400 | B38: =LEFT(C38,4) -> 1400 | C38: 1400 Security Deposits | D38: 1000 | E38: =SUMIF(AJE_INC!B:B,B38,AJE_INC!D:D) -> 0 | F38: =IF(D34="__________________"," ",IF(ISERROR(E38+D38),"",(E38+D38))) -> 1000 | G38: =IF(ISERROR(VLOOKUP(B38,Accounts_INC!$B:$E,3,FALSE)),"",VLOOKUP(B38,Accounts_INC!$B:$E,3,FALSE)) -> 1.5 | H38: =IFERROR(IF(G38="","",VLOOKUP(G38,FS!$A$11:$B$241,2,FALSE)),"") -> Cash and cash equivalents US | I38: =IFERROR(VLOOKUP(B39,Accounts_LTD!B:G,6,FALSE),"")
A39: 1410 | B39: =LEFT(C39,4) -> 1410 | C39: 1410 Inter Company account | D39: 20008924 | E39: =SUMIF(AJE_INC!B:B,B39,AJE_INC!D:D) -> -30613.83 | F39: =IF(D35="__________________"," ",IF(ISERROR(E39+D39),"",(E39+D39))) -> 19978310 | G39: =IF(ISERROR(VLOOKUP(B39,Accounts_INC!$B:$E,3,FALSE)),"",VLOOKUP(B39,Accounts_INC!$B:$E,3,FALSE)) -> 6 | H39: =IFERROR(IF(G39="","",VLOOKUP(G39,FS!$A$11:$B$241,2,FALSE)),"") -> Intercompany | I39: =IFERROR(VLOOKUP(#REF!,Accounts_LTD!B:G,6,FALSE),"")
A40: 1420 | B40: =LEFT(C40,4) -> 1420 | C40: 1420 Advance to vendor | D40: 832.04 | E40: =SUMIF(AJE_INC!B:B,B40,AJE_INC!D:D) -> 0 | F40: =IF(D36="__________________"," ",IF(ISERROR(E40+D40),"",(E40+D40))) -> 832.04 | G40: =IF(ISERROR(VLOOKUP(B40,Accounts_INC!$B:$E,3,FALSE)),"",VLOOKUP(B40,Accounts_INC!$B:$E,3,FALSE)) -> 31.1 | H40: =IFERROR(IF(G40="","",VLOOKUP(G40,FS!$A$11:$B$241,2,FALSE)),"") -> Trade Payables | I40: =IFERROR(VLOOKUP(#REF!,Accounts_LTD!B:G,6,FALSE),"")
A41: 1430 | B41: =LEFT(C41,4) -> 1430 | C41: 1430 CC Deposit | D41: 20000 | E41: =SUMIF(AJE_INC!B:B,B41,AJE_INC!D:D) -> 0 | F41: =IF(D37="__________________"," ",IF(ISERROR(E41+D41),"",(E41+D41))) -> 20000 | G41: =IF(ISERROR(VLOOKUP(B41,Accounts_INC!$B:$E,3,FALSE)),"",VLOOKUP(B41,Accounts_INC!$B:$E,3,FALSE)) -> 1.5 | H41: =IFERROR(IF(G41="","",VLOOKUP(G41,FS!$A$11:$B$241,2,FALSE)),"") -> Cash and cash equivalents US | I41: =IFERROR(VLOOKUP(B42,Accounts_LTD!B:G,6,FALSE),"")
A42: 1500 | B42: =LEFT(C42,4) -> 1500 | C42: 1500 Employee Advance | D42: 1184.94 | E42: =SUMIF(AJE_INC!B:B,B42,AJE_INC!D:D) -> 0 | F42: =IF(D38="__________________"," ",IF(ISERROR(E42+D42),"",(E42+D42))) -> 1184.94 | G42: =IF(ISERROR(VLOOKUP(B42,Accounts_INC!$B:$E,3,FALSE)),"",VLOOKUP(B42,Accounts_INC!$B:$E,3,FALSE)) -> 7.4 | H42: =IFERROR(IF(G42="","",VLOOKUP(G42,FS!$A$11:$B$241,2,FALSE)),"") -> Other Receivables | I42: =IFERROR(VLOOKUP(B43,Accounts_LTD!B:G,6,FALSE),"")
A43: 1510 | B43: =LEFT(C43,4) -> 1510 | C43: 1510 Salary Deposit - DevEX hire | D43: 55781.8 | E43: =SUMIF(AJE_INC!B:B,B43,AJE_INC!D:D) -> 0 | F43: =IF(D39="__________________"," ",IF(ISERROR(E43+D43),"",(E43+D43))) -> 55781.8 | G43: =IF(ISERROR(VLOOKUP(B43,Accounts_INC!$B:$E,3,FALSE)),"",VLOOKUP(B43,Accounts_INC!$B:$E,3,FALSE)) -> 7.4 | H43: =IFERROR(IF(G43="","",VLOOKUP(G43,FS!$A$11:$B$241,2,FALSE)),"") -> Other Receivables | I43: =IFERROR(VLOOKUP(#REF!,Accounts_LTD!B:G,6,FALSE),"")
A44: 1601 | B44: =LEFT(C44,4) -> 1601 | C44: 1601 Fixed Assets:Fixed Asset Computers | D44: 12994.45 | E44: =SUMIF(AJE_INC!B:B,B44,AJE_INC!D:D) -> 0 | F44: =IF(D40="__________________"," ",IF(ISERROR(E44+D44),"",(E44+D44))) -> 12994.45 | G44: =IF(ISERROR(VLOOKUP(B44,Accounts_INC!$B:$E,3,FALSE)),"",VLOOKUP(B44,Accounts_INC!$B:$E,3,FALSE)) -> 21 | H44: =IFERROR(IF(G44="","",VLOOKUP(G44,FS!$A$11:$B$241,2,FALSE)),"") -> Fixed assets | I44: =IFERROR(VLOOKUP(#REF!,Accounts_LTD!B:G,6,FALSE),"")
A45: 1611 | B45: =LEFT(C45,4) -> 1611 | C45: 1611 Fixed Assets:Fixed Assets- Accumulated Depreciation:Accumulated Depreciation- Computers | D45: -2382.7 | E45: =SUMIF(AJE_INC!B:B,B45,AJE_INC!D:D) -> 0 | F45: =IF(D41="__________________"," ",IF(ISERROR(E45+D45),"",(E45+D45))) -> -2382.7 | G45: =IF(ISERROR(VLOOKUP(B45,Accounts_INC!$B:$E,3,FALSE)),"",VLOOKUP(B45,Accounts_INC!$B:$E,3,FALSE)) -> 22 | H45: =IFERROR(IF(G45="","",VLOOKUP(G45,FS!$A$11:$B$241,2,FALSE)),"") -> Accumulated depreciation
A46: 1700 | B46: =LEFT(C46,4) -> 1700 | C46: 1700 Other Receivables | D46: 20000 | E46: =SUMIF(AJE_INC!B:B,B46,AJE_INC!D:D) -> 0 | F46: =IF(D42="__________________"," ",IF(ISERROR(E46+D46),"",(E46+D46))) -> 20000 | G46: =IF(ISERROR(VLOOKUP(B46,Accounts_INC!$B:$E,3,FALSE)),"",VLOOKUP(B46,Accounts_INC!$B:$E,3,FALSE)) -> 7.4 | H46: =IFERROR(IF(G46="","",VLOOKUP(G46,FS!$A$11:$B$241,2,FALSE)),"") -> Other Receivables | I46: =IFERROR(VLOOKUP(B47,Accounts_LTD!B:G,6,FALSE),"")
A47: 2000 | B47: =LEFT(C47,4) -> 2000 | C47: 2000 Accounts Payable | D47: -3115 | E47: =SUMIF(AJE_INC!B:B,B47,AJE_INC!D:D) -> 0 | F47: =IF(D43="__________________"," ",IF(ISERROR(E47+D47),"",(E47+D47))) -> -3115 | G47: =IF(ISERROR(VLOOKUP(B47,Accounts_INC!$B:$E,3,FALSE)),"",VLOOKUP(B47,Accounts_INC!$B:$E,3,FALSE)) -> 31.1 | H47: =IFERROR(IF(G47="","",VLOOKUP(G47,FS!$A$11:$B$241,2,FALSE)),"") -> Trade Payables | I47: =IFERROR(VLOOKUP(B48,Accounts_LTD!B:G,6,FALSE),"")
A48: 2050 | B48: =LEFT(C48,4) -> 2050 | C48: 2050 Accounts Payable (A/P) - EUR | D48: -3429.34 | E48: =SUMIF(AJE_INC!B:B,B48,AJE_INC!D:D) -> 0 | F48: =IF(D44="__________________"," ",IF(ISERROR(E48+D48),"",(E48+D48))) -> -3429.34 | G48: =IF(ISERROR(VLOOKUP(B48,Accounts_INC!$B:$E,3,FALSE)),"",VLOOKUP(B48,Accounts_INC!$B:$E,3,FALSE)) -> 31.1 | H48: =IFERROR(IF(G48="","",VLOOKUP(G48,FS!$A$11:$B$241,2,FALSE)),"") -> Trade Payables | I48: =IFERROR(VLOOKUP(B49,Accounts_LTD!B:G,6,FALSE),"")
A49: Acco | B49: =LEFT(C49,4) -> Acco | C49: Accounts Payable (A/P) - GBP | D49: -2903.52 | E49: =SUMIF(AJE_INC!B:B,B49,AJE_INC!D:D) -> 0 | F49: =IF(D45="__________________"," ",IF(ISERROR(E49+D49),"",(E49+D49))) -> -2903.52 | G49: =IF(ISERROR(VLOOKUP(B49,Accounts_INC!$B:$E,3,FALSE)),"",VLOOKUP(B49,Accounts_INC!$B:$E,3,FALSE)) -> 31.1 | H49: =IFERROR(IF(G49="","",VLOOKUP(G49,FS!$A$11:$B$241,2,FALSE)),"") -> Trade Payables | I49: =IFERROR(VLOOKUP(B50,Accounts_LTD!B:G,6,FALSE),"")
A50: 2110 | B50: =LEFT(C50,4) -> 2110 | C50: 2110 Credit Card:Leumi Credit Card XXXX 6767 | D50: -11655.73 | E50: =SUMIF(AJE_INC!B:B,B50,AJE_INC!D:D) -> 0 | F50: =IF(D46="__________________"," ",IF(ISERROR(E50+D50),"",(E50+D50))) -> -11655.73 | G50: =IF(ISERROR(VLOOKUP(B50,Accounts_INC!$B:$E,3,FALSE)),"",VLOOKUP(B50,Accounts_INC!$B:$E,3,FALSE)) -> 31.3 | H50: =IFERROR(IF(G50="","",VLOOKUP(G50,FS!$A$11:$B$241,2,FALSE)),"") -> Credit Cards | I50: =IFERROR(VLOOKUP(#REF!,Accounts_LTD!B:G,6,FALSE),"")
A51: 2200 | B51: =LEFT(C51,4) -> 2200 | C51: 2200 Accrued Expenses | D51: -6775 | E51: =SUMIF(AJE_INC!B:B,B51,AJE_INC!D:D) -> -135249 | F51: =IF(D47="__________________"," ",IF(ISERROR(E51+D51),"",(E51+D51))) -> -142024 | G51: =IF(ISERROR(VLOOKUP(B51,Accounts_INC!$B:$E,3,FALSE)),"",VLOOKUP(B51,Accounts_INC!$B:$E,3,FALSE)) -> 38 | H51: =IFERROR(IF(G51="","",VLOOKUP(G51,FS!$A$11:$B$241,2,FALSE)),"") -> Accrued Expenses | I51: =IFERROR(VLOOKUP(#REF!,Accounts_LTD!B:G,6,FALSE),"")
A52: 2300 | B52: =LEFT(C52,4) -> 2300 | C52: 2300 Payroll Liabilities | D52: 0 | E52: =SUMIF(AJE_INC!B:B,B52,AJE_INC!D:D) -> 0 | F52: =IF(D48="__________________"," ",IF(ISERROR(E52+D52),"",(E52+D52))) -> 0 | G52: =IF(ISERROR(VLOOKUP(B52,Accounts_INC!$B:$E,3,FALSE)),"",VLOOKUP(B52,Accounts_INC!$B:$E,3,FALSE)) -> 33 | H52: =IFERROR(IF(G52="","",VLOOKUP(G52,FS!$A$11:$B$241,2,FALSE)),"") -> Employees and related | I52: =IFERROR(VLOOKUP(B53,Accounts_LTD!B:G,6,FALSE),"")
A53: 2350 | B53: =LEFT(C53,4) -> 2350 | C53: 2350 Deferred Revenue | D53: -77620.96 | E53: =SUMIF(AJE_INC!B:B,B53,AJE_INC!D:D) -> 0 | F53: =IF(D49="__________________"," ",IF(ISERROR(E53+D53),"",(E53+D53))) -> -77620.96 | G53: =IF(ISERROR(VLOOKUP(B53,Accounts_INC!$B:$E,3,FALSE)),"",VLOOKUP(B53,Accounts_INC!$B:$E,3,FALSE)) -> 37 | H53: =IFERROR(IF(G53="","",VLOOKUP(G53,FS!$A$11:$B$241,2,FALSE)),"") -> Deferred revenues | I53: =IFERROR(VLOOKUP(B54,Accounts_LTD!B:G,6,FALSE),"")
A54: 2450 | B54: =LEFT(C54,4) -> 2450 | C54: 2450 NY Sales Tax | D54: -2662.5 | E54: =SUMIF(AJE_INC!B:B,B54,AJE_INC!D:D) -> 0 | F54: =IF(D50="__________________"," ",IF(ISERROR(E54+D54),"",(E54+D54))) -> -2662.5 | G54: =IF(ISERROR(VLOOKUP(B54,Accounts_INC!$B:$E,3,FALSE)),"",VLOOKUP(B54,Accounts_INC!$B:$E,3,FALSE)) -> 34 | H54: =IFERROR(IF(G54="","",VLOOKUP(G54,FS!$A$11:$B$241,2,FALSE)),"") -> Other current liabilities | I54: =IFERROR(VLOOKUP(#REF!,Accounts_LTD!B:G,6,FALSE),"")
A55: 3100 | B55: =LEFT(C55,4) -> 3100 | C55: 3100 Common Stock | D55: -20105 | E55: =SUMIF(AJE_INC!B:B,B55,AJE_INC!D:D) -> 0 | F55: =IF(D51="__________________"," ",IF(ISERROR(E55+D55),"",(E55+D55))) -> -20105 | G55: =IF(ISERROR(VLOOKUP(B55,Accounts_INC!$B:$E,3,FALSE)),"",VLOOKUP(B55,Accounts_INC!$B:$E,3,FALSE)) -> 51 | H55: =IFERROR(IF(G55="","",VLOOKUP(G55,FS!$A$11:$B$241,2,FALSE)),"") -> Additional paid-in capital
A56: 3110 | B56: =LEFT(C56,4) -> 3110 | C56: 3110 Series seed Preferred Stock | D56: -7953531.4 | E56: =SUMIF(AJE_INC!B:B,B56,AJE_INC!D:D) -> 0 | F56: =IF(D52="__________________"," ",IF(ISERROR(E56+D56),"",(E56+D56))) -> -7953531.4 | G56: =IF(ISERROR(VLOOKUP(B56,Accounts_INC!$B:$E,3,FALSE)),"",VLOOKUP(B56,Accounts_INC!$B:$E,3,FALSE)) -> 51 | H56: =IFERROR(IF(G56="","",VLOOKUP(G56,FS!$A$11:$B$241,2,FALSE)),"") -> Additional paid-in capital | I56: =IFERROR(VLOOKUP(B57,Accounts_LTD!B:G,6,FALSE),"")
A57: 3120 | B57: =LEFT(C57,4) -> 3120 | C57: 3120 Additional Paid-In Capital | D57: -10367.5 | E57: =SUMIF(AJE_INC!B:B,B57,AJE_INC!D:D) -> 0 | F57: =IF(D53="__________________"," ",IF(ISERROR(E57+D57),"",(E57+D57))) -> -10367.5 | G57: =IF(ISERROR(VLOOKUP(B57,Accounts_INC!$B:$E,3,FALSE)),"",VLOOKUP(B57,Accounts_INC!$B:$E,3,FALSE)) -> 51 | H57: =IFERROR(IF(G57="","",VLOOKUP(G57,FS!$A$11:$B$241,2,FALSE)),"") -> Additional paid-in capital | I57: =IFERROR(VLOOKUP(B58,Accounts_LTD!B:G,6,FALSE),"")
A58: 3130 | B58: =LEFT(C58,4) -> 3130 | C58: 3130 Issuance Cost | D58: 208091.78 | E58: =SUMIF(AJE_INC!B:B,B58,AJE_INC!D:D) -> 0 | F58: =IF(D54="__________________"," ",IF(ISERROR(E58+D58),"",(E58+D58))) -> 208091.78 | G58: =IF(ISERROR(VLOOKUP(B58,Accounts_INC!$B:$E,3,FALSE)),"",VLOOKUP(B58,Accounts_INC!$B:$E,3,FALSE)) -> 55 | H58: =IFERROR(IF(G58="","",VLOOKUP(G58,FS!$A$11:$B$241,2,FALSE)),"") -> Issuance expenses | I58: =IFERROR(VLOOKUP(B59,Accounts_LTD!B:G,6,FALSE),"")
A59: 3140 | B59: =LEFT(C59,4) -> 3140 | C59: 3140 Series A Preferred Stock | D59: -14904908 | E59: =SUMIF(AJE_INC!B:B,B59,AJE_INC!D:D) -> 0 | F59: =IF(D55="__________________"," ",IF(ISERROR(E59+D59),"",(E59+D59))) -> -14904908 | G59: =IF(ISERROR(VLOOKUP(B59,Accounts_INC!$B:$E,3,FALSE)),"",VLOOKUP(B59,Accounts_INC!$B:$E,3,FALSE)) -> 51 | H59: =IFERROR(IF(G59="","",VLOOKUP(G59,FS!$A$11:$B$241,2,FALSE)),"") -> Additional paid-in capital | I59: =IFERROR(VLOOKUP(B60,Accounts_LTD!B:G,6,FALSE),"")
A60: 3200 | B60: =LEFT(C60,4) -> 3200 | C60: 3200 Retained Earnings | D60: -23624.69 | E60: =SUMIF(AJE_INC!B:B,B60,AJE_INC!D:D) -> 0 | F60: =IF(D56="__________________"," ",IF(ISERROR(E60+D60),"",(E60+D60))) -> -23624.69 | G60: =IF(ISERROR(VLOOKUP(B60,Accounts_INC!$B:$E,3,FALSE)),"",VLOOKUP(B60,Accounts_INC!$B:$E,3,FALSE)) -> 53 | H60: =IFERROR(IF(G60="","",VLOOKUP(G60,FS!$A$11:$B$241,2,FALSE)),"") -> Accumulated loss | I60: =IFERROR(VLOOKUP(#REF!,Accounts_LTD!B:G,6,FALSE),"")
A61: 3210 | B61: =LEFT(C61,4) -> 3210 | C61: 3210 Options Fund | D61: -73733.43 | E61: =SUMIF(AJE_INC!B:B,B61,AJE_INC!D:D) -> 0 | F61: =IF(D57="__________________"," ",IF(ISERROR(E61+D61),"",(E61+D61))) -> -73733.43 | G61: =IF(ISERROR(VLOOKUP(B61,Accounts_INC!$B:$E,3,FALSE)),"",VLOOKUP(B61,Accounts_INC!$B:$E,3,FALSE)) -> 51 | H61: =IFERROR(IF(G61="","",VLOOKUP(G61,FS!$A$11:$B$241,2,FALSE)),"") -> Additional paid-in capital | I61: =IFERROR(VLOOKUP(#REF!,Accounts_LTD!B:G,6,FALSE),"")
A62: 3212 | B62: =LEFT(C62,4) -> 3212 | C62: 3212 Ordinary shares | D62: -20105 | E62: =SUMIF(AJE_INC!B:B,B62,AJE_INC!D:D) -> 0 | F62: =IF(D58="__________________"," ",IF(ISERROR(E62+D62),"",(E62+D62))) -> -20105 | G62: =IF(ISERROR(VLOOKUP(B62,Accounts_INC!$B:$E,3,FALSE)),"",VLOOKUP(B62,Accounts_INC!$B:$E,3,FALSE)) -> 51 | H62: =IFERROR(IF(G62="","",VLOOKUP(G62,FS!$A$11:$B$241,2,FALSE)),"") -> Additional paid-in capital | I62: =IFERROR(VLOOKUP(B63,Accounts_LTD!B:G,6,FALSE),"")
A63: 3213 | B63: =LEFT(C63,4) -> 3213 | C63: 3213 Seed Round shares | D63: -16000 | E63: =SUMIF(AJE_INC!B:B,B63,AJE_INC!D:D) -> 0 | F63: =IF(D59="__________________"," ",IF(ISERROR(E63+D63),"",(E63+D63))) -> -16000 | G63: =IF(ISERROR(VLOOKUP(B63,Accounts_INC!$B:$E,3,FALSE)),"",VLOOKUP(B63,Accounts_INC!$B:$E,3,FALSE)) -> 51 | H63: =IFERROR(IF(G63="","",VLOOKUP(G63,FS!$A$11:$B$241,2,FALSE)),"") -> Additional paid-in capital | I63: =IFERROR(VLOOKUP(B64,Accounts_LTD!B:G,6,FALSE),"")
A64: 3214 | B64: =LEFT(C64,4) -> 3214 | C64: 3214 Preferred A shares | D64: -10363.64 | E64: =SUMIF(AJE_INC!B:B,B64,AJE_INC!D:D) -> 0 | F64: =IF(D60="__________________"," ",IF(ISERROR(E64+D64),"",(E64+D64))) -> -10363.64 | G64: =IF(ISERROR(VLOOKUP(B64,Accounts_INC!$B:$E,3,FALSE)),"",VLOOKUP(B64,Accounts_INC!$B:$E,3,FALSE)) -> 51 | H64: =IFERROR(IF(G64="","",VLOOKUP(G64,FS!$A$11:$B$241,2,FALSE)),"") -> Additional paid-in capital | I64: =IFERROR(VLOOKUP(#REF!,Accounts_LTD!B:G,6,FALSE),"")
A65: 4000 | B65: =LEFT(C65,4) -> 4000 | C65: 4000 Sales | D65: -32379.04 | E65: =SUMIF(AJE_INC!B:B,B65,AJE_INC!D:D) -> 0 | F65: =IF(D61="__________________"," ",IF(ISERROR(E65+D65),"",(E65+D65))) -> -32379.04 | G65: =IF(ISERROR(VLOOKUP(B65,Accounts_INC!$B:$E,3,FALSE)),"",VLOOKUP(B65,Accounts_INC!$B:$E,3,FALSE)) -> 100 | H65: =IFERROR(IF(G65="","",VLOOKUP(G65,FS!$A$11:$B$241,2,FALSE)),"") -> Revenues | I65: =IFERROR(VLOOKUP(#REF!,Accounts_LTD!B:G,6,FALSE),"")
A66: 4010 | B66: =LEFT(C66,4) -> 4010 | C66: 4010 Intercompany Income | D66: -1468314.1 | E66: =SUMIF(AJE_INC!B:B,B66,AJE_INC!D:D) -> 30613.83 | F66: =IF(D62="__________________"," ",IF(ISERROR(E66+D66),"",(E66+D66))) -> -1437700.3 | G66: =IF(ISERROR(VLOOKUP(B66,Accounts_INC!$B:$E,3,FALSE)),"",VLOOKUP(B66,Accounts_INC!$B:$E,3,FALSE)) -> 101 | H66: =IFERROR(IF(G66="","",VLOOKUP(G66,FS!$A$11:$B$241,2,FALSE)),"") -> LRD Model | N66: =VLOOKUP(B66,#REF!,3,0) -> #REF! | P66: =F66-N66 -> #REF! | Q66: =P66-N66 -> #REF!
A67: 6010 | B67: =LEFT(C67,4) -> 6010 | C67: 6010 Payroll Expenses:Gross Salary | D67: 247413.08 | E67: =SUMIF(AJE_INC!B:B,B67,AJE_INC!D:D) -> 0 | F67: =IF(D64="__________________"," ",IF(ISERROR(E67+D67),"",(E67+D67))) -> 247413.08 | G67: =IF(ISERROR(VLOOKUP(B67,Accounts_INC!$B:$E,3,FALSE)),"",VLOOKUP(B67,Accounts_INC!$B:$E,3,FALSE)) -> 400 | H67: =IFERROR(IF(G67="","",VLOOKUP(G67,FS!$A$11:$B$241,2,FALSE)),"") -> Payroll and related (Customer Success) | I67: =IFERROR(VLOOKUP(B68,Accounts_LTD!B:G,6,FALSE),"") | N67: =VLOOKUP(B67,#REF!,3,0) -> #REF! | P67: =F67-N67 -> #REF! | Q67: =P67-N67 -> #REF!
A68: 6011 | B68: =LEFT(C68,4) -> 6011 | C68: 6011 Payroll Expenses:Paul Sigman Salary expenses | D68: 103722.66 | E68: =SUMIF(AJE_INC!B:B,B68,AJE_INC!D:D) -> 0 | F68: =IF(D65="__________________"," ",IF(ISERROR(E68+D68),"",(E68+D68))) -> 103722.66 | G68: =IF(ISERROR(VLOOKUP(B68,Accounts_INC!$B:$E,3,FALSE)),"",VLOOKUP(B68,Accounts_INC!$B:$E,3,FALSE)) -> 400 | H68: =IFERROR(IF(G68="","",VLOOKUP(G68,FS!$A$11:$B$241,2,FALSE)),"") -> Payroll and related (Customer Success) | I68: =IFERROR(VLOOKUP(B69,Accounts_LTD!B:G,6,FALSE),"")
A69: 6012 | B69: =LEFT(C69,4) -> 6012 | C69: 6012 Payroll Expenses:Salary expenses - Developer Experience department | D69: 164345.94 | E69: =SUMIF(AJE_INC!B:B,B69,AJE_INC!D:D) -> 0 | F69: =IF(D66="__________________"," ",IF(ISERROR(E69+D69),"",(E69+D69))) -> 164345.94 | G69: =IF(ISERROR(VLOOKUP(B69,Accounts_INC!$B:$E,3,FALSE)),"",VLOOKUP(B69,Accounts_INC!$B:$E,3,FALSE)) -> 600 | H69: =IFERROR(IF(G69="","",VLOOKUP(G69,FS!$A$11:$B$241,2,FALSE)),"") -> Payroll and related (DevEx) | I69: =IFERROR(VLOOKUP(B70,Accounts_LTD!B:G,6,FALSE),"") | N69: =VLOOKUP(B69,#REF!,3,0) -> #REF! | P69: =F69-N69 -> #REF! | Q69: =P69-N69 -> #REF!
A70: 6013 | B70: =LEFT(C70,4) -> 6013 | C70: 6013 Payroll Expenses:Gross Salary - Customer success | D70: 123692.17 | E70: =SUMIF(AJE_INC!B:B,B70,AJE_INC!D:D) -> 0 | F70: =IF(D67="__________________"," ",IF(ISERROR(E70+D70),"",(E70+D70))) -> 123692.17 | G70: =IF(ISERROR(VLOOKUP(B70,Accounts_INC!$B:$E,3,FALSE)),"",VLOOKUP(B70,Accounts_INC!$B:$E,3,FALSE)) -> 400 | H70: =IFERROR(IF(G70="","",VLOOKUP(G70,FS!$A$11:$B$241,2,FALSE)),"") -> Payroll and related (Customer Success) | I70: =IFERROR(VLOOKUP(#REF!,Accounts_LTD!B:G,6,FALSE),"") | N70: =VLOOKUP(B70,#REF!,3,0) -> #REF! | P70: =F70-N70 -> #REF! | Q70: =P70-N70 -> #REF!
A71: 6020 | B71: =LEFT(C71,4) -> 6020 | C71: 6020 Payroll Expenses:Bonus | D71: 12671.23 | E71: =SUMIF(AJE_INC!B:B,B71,AJE_INC!D:D) -> 0 | F71: =IF(D67="__________________"," ",IF(ISERROR(E71+D71),"",(E71+D71))) -> 12671.23 | G71: =IF(ISERROR(VLOOKUP(B71,Accounts_INC!$B:$E,3,FALSE)),"",VLOOKUP(B71,Accounts_INC!$B:$E,3,FALSE)) -> 420 | H71: =IFERROR(IF(G71="","",VLOOKUP(G71,FS!$A$11:$B$241,2,FALSE)),"") -> Bonus Customer Success | I71: =IFERROR(VLOOKUP(#REF!,Accounts_LTD!B:G,6,FALSE),"")
A72: 6040 | B72: =LEFT(C72,4) -> 6040 | C72: 6040 Payroll Expenses:Payroll Taxes | D72: 19926.55 | E72: =SUMIF(AJE_INC!B:B,B72,AJE_INC!D:D) -> 0 | F72: =IF(D68="__________________"," ",IF(ISERROR(E72+D72),"",(E72+D72))) -> 19926.55 | G72: =IF(ISERROR(VLOOKUP(B72,Accounts_INC!$B:$E,3,FALSE)),"",VLOOKUP(B72,Accounts_INC!$B:$E,3,FALSE)) -> 400 | H72: =IFERROR(IF(G72="","",VLOOKUP(G72,FS!$A$11:$B$241,2,FALSE)),"") -> Payroll and related (Customer Success) | I72: =IFERROR(VLOOKUP(B73,Accounts_LTD!B:G,6,FALSE),"") | N72: =VLOOKUP(B72,#REF!,3,0) -> #REF! | P72: =F72-N72 -> #REF! | Q72: =P72-N72 -> #REF!
A73: 6041 | B73: =LEFT(C73,4) -> 6041 | C73: 6041 Payroll Expenses:Payroll taxes - Customer success | D73: 9555.09 | E73: =SUMIF(AJE_INC!B:B,B73,AJE_INC!D:D) -> 0 | F73: =IF(D69="__________________"," ",IF(ISERROR(E73+D73),"",(E73+D73))) -> 9555.09 | G73: =IF(ISERROR(VLOOKUP(B73,Accounts_INC!$B:$E,3,FALSE)),"",VLOOKUP(B73,Accounts_INC!$B:$E,3,FALSE)) -> 400 | H73: =IFERROR(IF(G73="","",VLOOKUP(G73,FS!$A$11:$B$241,2,FALSE)),"") -> Payroll and related (Customer Success) | I73: =IFERROR(VLOOKUP(B74,Accounts_LTD!B:G,6,FALSE),"")
A74: 6042 | B74: =LEFT(C74,4) -> 6042 | C74: 6042 Payroll Expenses:Payroll taxes - Developer Experience department | D74: 14099.2 | E74: =SUMIF(AJE_INC!B:B,B74,AJE_INC!D:D) -> 0 | F74: =IF(D70="__________________"," ",IF(ISERROR(E74+D74),"",(E74+D74))) -> 14099.2 | G74: =IF(ISERROR(VLOOKUP(B74,Accounts_INC!$B:$E,3,FALSE)),"",VLOOKUP(B74,Accounts_INC!$B:$E,3,FALSE)) -> 600 | H74: =IFERROR(IF(G74="","",VLOOKUP(G74,FS!$A$11:$B$241,2,FALSE)),"") -> Payroll and related (DevEx) | I74: =IFERROR(VLOOKUP(#REF!,Accounts_LTD!B:G,6,FALSE),"") | N74: =VLOOKUP(B74,#REF!,3,0) -> #REF! | P74: =F74-N74 -> #REF! | Q74: =P74-N74 -> #REF!
A75: 6050 | B75: =LEFT(C75,4) -> 6050 | C75: 6050 Payroll Expenses:Benefits | D75: 42045.44 | E75: =SUMIF(AJE_INC!B:B,B75,AJE_INC!D:D) -> 0 | F75: =IF(D71="__________________"," ",IF(ISERROR(E75+D75),"",(E75+D75))) -> 42045.44 | G75: =IF(ISERROR(VLOOKUP(B75,Accounts_INC!$B:$E,3,FALSE)),"",VLOOKUP(B75,Accounts_INC!$B:$E,3,FALSE)) -> 400 | H75: =IFERROR(IF(G75="","",VLOOKUP(G75,FS!$A$11:$B$241,2,FALSE)),"") -> Payroll and related (Customer Success) | I75: =IFERROR(VLOOKUP(#REF!,Accounts_LTD!B:G,6,FALSE),"") | N75: =VLOOKUP(B75,#REF!,3,0) -> #REF! | P75: =F75-N75 -> #REF! | Q75: =P75-N75 -> #REF!
A76: 6051 | B76: =LEFT(C76,4) -> 6051 | C76: 6051 Payroll Expenses:Payroll benefits - Developer Experience department | D76: 9843.33 | E76: =SUMIF(AJE_INC!B:B,B76,AJE_INC!D:D) -> 0 | F76: =IF(D72="__________________"," ",IF(ISERROR(E76+D76),"",(E76+D76))) -> 9843.33 | G76: =IF(ISERROR(VLOOKUP(B76,Accounts_INC!$B:$E,3,FALSE)),"",VLOOKUP(B76,Accounts_INC!$B:$E,3,FALSE)) -> 600 | H76: =IFERROR(IF(G76="","",VLOOKUP(G76,FS!$A$11:$B$241,2,FALSE)),"") -> Payroll and related (DevEx)
A77: 6052 | B77: =LEFT(C77,4) -> 6052 | C77: 6052 Payroll Expenses:Payroll Benefits - Customer success | D77: 16307.2 | E77: =SUMIF(AJE_INC!B:B,B77,AJE_INC!D:D) -> 0 | F77: =IF(D73="__________________"," ",IF(ISERROR(E77+D77),"",(E77+D77))) -> 16307.2 | G77: =IF(ISERROR(VLOOKUP(B77,Accounts_INC!$B:$E,3,FALSE)),"",VLOOKUP(B77,Accounts_INC!$B:$E,3,FALSE)) -> 400 | H77: =IFERROR(IF(G77="","",VLOOKUP(G77,FS!$A$11:$B$241,2,FALSE)),"") -> Payroll and related (Customer Success) | I77: =IFERROR(VLOOKUP(B78,Accounts_LTD!B:G,6,FALSE),"") | N77: =VLOOKUP(B77,#REF!,3,0) -> #REF! | P77: =F77-N77 -> #REF! | Q77: =P77-N77 -> #REF!
A78: 6060 | B78: =LEFT(C78,4) -> 6060 | C78: 6060 Payroll Expenses:Worker's Compensation | D78: 545.84 | E78: =SUMIF(AJE_INC!B:B,B78,AJE_INC!D:D) -> 0 | F78: =IF(D74="__________________"," ",IF(ISERROR(E78+D78),"",(E78+D78))) -> 545.84 | G78: =IF(ISERROR(VLOOKUP(B78,Accounts_INC!$B:$E,3,FALSE)),"",VLOOKUP(B78,Accounts_INC!$B:$E,3,FALSE)) -> 400 | H78: =IFERROR(IF(G78="","",VLOOKUP(G78,FS!$A$11:$B$241,2,FALSE)),"") -> Payroll and related (Customer Success) | I78: =IFERROR(VLOOKUP(B79,Accounts_LTD!B:G,6,FALSE),"") | N78: =VLOOKUP(B78,#REF!,3,0) -> #REF! | P78: =F78-N78 -> #REF! | Q78: =P78-N78 -> #REF!
A79: 6061 | B79: =LEFT(C79,4) -> 6061 | C79: 6061 Payroll Expenses:Worker's Compensation - Developer Experience department | D79: 690.93 | E79: =SUMIF(AJE_INC!B:B,B79,AJE_INC!D:D) -> 0 | F79: =IF(D75="__________________"," ",IF(ISERROR(E79+D79),"",(E79+D79))) -> 690.93 | G79: =IF(ISERROR(VLOOKUP(B79,Accounts_INC!$B:$E,3,FALSE)),"",VLOOKUP(B79,Accounts_INC!$B:$E,3,FALSE)) -> 600 | H79: =IFERROR(IF(G79="","",VLOOKUP(G79,FS!$A$11:$B$241,2,FALSE)),"") -> Payroll and related (DevEx) | I79: =IFERROR(VLOOKUP(B80,Accounts_LTD!B:G,6,FALSE),"")
A80: 6062 | B80: =LEFT(C80,4) -> 6062 | C80: 6062 Payroll Expenses:Worker's Compensation - Customer success | D80: 519.72 | E80: =SUMIF(AJE_INC!B:B,B80,AJE_INC!D:D) -> 0 | F80: =IF(D76="__________________"," ",IF(ISERROR(E80+D80),"",(E80+D80))) -> 519.72 | G80: =IF(ISERROR(VLOOKUP(B80,Accounts_INC!$B:$E,3,FALSE)),"",VLOOKUP(B80,Accounts_INC!$B:$E,3,FALSE)) -> 400 | H80: =IFERROR(IF(G80="","",VLOOKUP(G80,FS!$A$11:$B$241,2,FALSE)),"") -> Payroll and related (Customer Success) | I80: =IFERROR(VLOOKUP(B81,Accounts_LTD!B:G,6,FALSE),"") | N80: =VLOOKUP(B80,#REF!,3,0) -> #REF! | P80: =F80-N80 -> #REF! | Q80: =P80-N80 -> #REF!
A81: 6070 | B81: =LEFT(C81,4) -> 6070 | C81: 6070 Payroll Expenses:Relocation Expenses | D81: 4262.38 | E81: =SUMIF(AJE_INC!B:B,B81,AJE_INC!D:D) -> 0 | F81: =IF(D77="__________________"," ",IF(ISERROR(E81+D81),"",(E81+D81))) -> 4262.38 | G81: =IF(ISERROR(VLOOKUP(B81,Accounts_INC!$B:$E,3,FALSE)),"",VLOOKUP(B81,Accounts_INC!$B:$E,3,FALSE)) -> 400 | H81: =IFERROR(IF(G81="","",VLOOKUP(G81,FS!$A$11:$B$241,2,FALSE)),"") -> Payroll and related (Customer Success) | I81: =IFERROR(VLOOKUP(#REF!,Accounts_LTD!B:G,6,FALSE),"")
A82: 6090 | B82: =LEFT(C82,4) -> 6090 | C82: 6090 Payroll Expenses:Payroll Fees | D82: 2385 | E82: =SUMIF(AJE_INC!B:B,B82,AJE_INC!D:D) -> 0 | F82: =IF(D78="__________________"," ",IF(ISERROR(E82+D82),"",(E82+D82))) -> 2385 | G82: =IF(ISERROR(VLOOKUP(B82,Accounts_INC!$B:$E,3,FALSE)),"",VLOOKUP(B82,Accounts_INC!$B:$E,3,FALSE)) -> 400 | H82: =IFERROR(IF(G82="","",VLOOKUP(G82,FS!$A$11:$B$241,2,FALSE)),"") -> Payroll and related (Customer Success) | I82: =IFERROR(VLOOKUP(#REF!,Accounts_LTD!B:G,6,FALSE),"")
A83: 6091 | B83: =LEFT(C83,4) -> 6091 | C83: 6091 Payroll Expenses:Payroll fees - Developer Experience department | D83: 2087.5 | E83: =SUMIF(AJE_INC!B:B,B83,AJE_INC!D:D) -> 0 | F83: =IF(D79="__________________"," ",IF(ISERROR(E83+D83),"",(E83+D83))) -> 2087.5 | G83: =IF(ISERROR(VLOOKUP(B83,Accounts_INC!$B:$E,3,FALSE)),"",VLOOKUP(B83,Accounts_INC!$B:$E,3,FALSE)) -> 600 | H83: =IFERROR(IF(G83="","",VLOOKUP(G83,FS!$A$11:$B$241,2,FALSE)),"") -> Payroll and related (DevEx) | I83: =IFERROR(VLOOKUP(B84,Accounts_LTD!B:G,6,FALSE),"")
A84: 6092 | B84: =LEFT(C84,4) -> 6092 | C84: 6092 Payroll Expenses:Payroll Fees - Customer success | D84: 1007.5 | E84: =SUMIF(AJE_INC!B:B,B84,AJE_INC!D:D) -> 0 | F84: =IF(D80="__________________"," ",IF(ISERROR(E84+D84),"",(E84+D84))) -> 1007.5 | G84: =IF(ISERROR(VLOOKUP(B84,Accounts_INC!$B:$E,3,FALSE)),"",VLOOKUP(B84,Accounts_INC!$B:$E,3,FALSE)) -> 400 | H84: =IFERROR(IF(G84="","",VLOOKUP(G84,FS!$A$11:$B$241,2,FALSE)),"") -> Payroll and related (Customer Success) | I84: =IFERROR(VLOOKUP(B85,Accounts_LTD!B:G,6,FALSE),"")
A85: 6104 | B85: =LEFT(C85,4) -> 6104 | C85: 6104 General & Administrative Expenses:G&A Travel Abroad | D85: 119 | E85: =SUMIF(AJE_INC!B:B,B85,AJE_INC!D:D) -> 0 | F85: =IF(D81="__________________"," ",IF(ISERROR(E85+D85),"",(E85+D85))) -> 119 | G85: =IF(ISERROR(VLOOKUP(B85,Accounts_INC!$B:$E,3,FALSE)),"",VLOOKUP(B85,Accounts_INC!$B:$E,3,FALSE)) -> 503 | H85: =IFERROR(IF(G85="","",VLOOKUP(G85,FS!$A$11:$B$241,2,FALSE)),"") -> Office expenses & other | I85: =IFERROR(VLOOKUP(#REF!,Accounts_LTD!B:G,6,FALSE),"")
A86: 6109 | B86: =LEFT(C86,4) -> 6109 | C86: 6109 General & Administrative Expenses:409A Altshuler Shaham | D86: 1840 | E86: =SUMIF(AJE_INC!B:B,B86,AJE_INC!D:D) -> 0 | F86: =IF(D82="__________________"," ",IF(ISERROR(E86+D86),"",(E86+D86))) -> 1840 | G86: =IF(ISERROR(VLOOKUP(B86,Accounts_INC!$B:$E,3,FALSE)),"",VLOOKUP(B86,Accounts_INC!$B:$E,3,FALSE)) -> 501.5 | H86: =IFERROR(IF(G86="","",VLOOKUP(G86,FS!$A$11:$B$241,2,FALSE)),"") -> Professional services US | I86: =IFERROR(VLOOKUP(#REF!,Accounts_LTD!B:G,6,FALSE),"")
A87: 6110 | B87: =LEFT(C87,4) -> 6110 | C87: 6110 General & Administrative Expenses:G&A trust expenses - Altshuler Shaham | D87: 2000.3 | E87: =SUMIF(AJE_INC!B:B,B87,AJE_INC!D:D) -> 0 | F87: =IF(D83="__________________"," ",IF(ISERROR(E87+D87),"",(E87+D87))) -> 2000.3 | G87: =IF(ISERROR(VLOOKUP(B87,Accounts_INC!$B:$E,3,FALSE)),"",VLOOKUP(B87,Accounts_INC!$B:$E,3,FALSE)) -> 501.5 | H87: =IFERROR(IF(G87="","",VLOOKUP(G87,FS!$A$11:$B$241,2,FALSE)),"") -> Professional services US
A88: 6115 | B88: =LEFT(C88,4) -> 6115 | C88: 6115 General & Administrative Expenses:G&A - Recruiting | D88: 15696.56 | E88: =SUMIF(AJE_INC!B:B,B88,AJE_INC!D:D) -> 0 | F88: =IF(D84="__________________"," ",IF(ISERROR(E88+D88),"",(E88+D88))) -> 15696.56 | G88: =IF(ISERROR(VLOOKUP(B88,Accounts_INC!$B:$E,3,FALSE)),"",VLOOKUP(B88,Accounts_INC!$B:$E,3,FALSE)) -> 514 | H88: =IFERROR(IF(G88="","",VLOOKUP(G88,FS!$A$11:$B$241,2,FALSE)),"") -> Recruiting | I88: =IFERROR(VLOOKUP(B89,Accounts_LTD!B:G,6,FALSE),"")
A89: 6125 | B89: =LEFT(C89,4) -> 6125 | C89: 6125 General & Administrative Expenses:G&A - Setup Fee | D89: 653.03 | E89: =SUMIF(AJE_INC!B:B,B89,AJE_INC!D:D) -> 0 | F89: =IF(D85="__________________"," ",IF(ISERROR(E89+D89),"",(E89+D89))) -> 653.03 | G89: =IF(ISERROR(VLOOKUP(B89,Accounts_INC!$B:$E,3,FALSE)),"",VLOOKUP(B89,Accounts_INC!$B:$E,3,FALSE)) -> 503 | H89: =IFERROR(IF(G89="","",VLOOKUP(G89,FS!$A$11:$B$241,2,FALSE)),"") -> Office expenses & other | I89: =IFERROR(VLOOKUP(B90,Accounts_LTD!B:G,6,FALSE),"")
A90: 6135 | B90: =LEFT(C90,4) -> 6135 | C90: 6135 General & Administrative Expenses:G&A - Office Supplies/Expenses | D90: 805.82 | E90: =SUMIF(AJE_INC!B:B,B90,AJE_INC!D:D) -> 0 | F90: =IF(D86="__________________"," ",IF(ISERROR(E90+D90),"",(E90+D90))) -> 805.82 | G90: =IF(ISERROR(VLOOKUP(B90,Accounts_INC!$B:$E,3,FALSE)),"",VLOOKUP(B90,Accounts_INC!$B:$E,3,FALSE)) -> 503 | H90: =IFERROR(IF(G90="","",VLOOKUP(G90,FS!$A$11:$B$241,2,FALSE)),"") -> Office expenses & other | I90: =IFERROR(VLOOKUP(B91,Accounts_LTD!B:G,6,FALSE),"")
A91: 6145 | B91: =LEFT(C91,4) -> 6145 | C91: 6145 General & Administrative Expenses:G&A-Offsite | D91: 3134.02 | E91: =SUMIF(AJE_INC!B:B,B91,AJE_INC!D:D) -> 0 | F91: =IF(D87="__________________"," ",IF(ISERROR(E91+D91),"",(E91+D91))) -> 3134.02 | G91: =IF(ISERROR(VLOOKUP(B91,Accounts_INC!$B:$E,3,FALSE)),"",VLOOKUP(B91,Accounts_INC!$B:$E,3,FALSE)) -> 503 | H91: =IFERROR(IF(G91="","",VLOOKUP(G91,FS!$A$11:$B$241,2,FALSE)),"") -> Office expenses & other | I91: =IFERROR(VLOOKUP(B92,Accounts_LTD!B:G,6,FALSE),"")
A92: 6150 | B92: =LEFT(C92,4) -> 6150 | C92: 6150 General & Administrative Expenses:Property & General liability insurance | D92: 1080.64 | E92: =SUMIF(AJE_INC!B:B,B92,AJE_INC!D:D) -> 0 | F92: =IF(D88="__________________"," ",IF(ISERROR(E92+D92),"",(E92+D92))) -> 1080.64 | G92: =IF(ISERROR(VLOOKUP(B92,Accounts_INC!$B:$E,3,FALSE)),"",VLOOKUP(B92,Accounts_INC!$B:$E,3,FALSE)) -> 507 | H92: =IFERROR(IF(G92="","",VLOOKUP(G92,FS!$A$11:$B$241,2,FALSE)),"") -> Insurance | I92: =IFERROR(VLOOKUP(#REF!,Accounts_LTD!B:G,6,FALSE),"")
A93: 6160 | B93: =LEFT(C93,4) -> 6160 | C93: 6160 General & Administrative Expenses:D&O Insurance | D93: 6486.4 | E93: =SUMIF(AJE_INC!B:B,B93,AJE_INC!D:D) -> 0 | F93: =IF(D89="__________________"," ",IF(ISERROR(E93+D93),"",(E93+D93))) -> 6486.4 | G93: =IF(ISERROR(VLOOKUP(B93,Accounts_INC!$B:$E,3,FALSE)),"",VLOOKUP(B93,Accounts_INC!$B:$E,3,FALSE)) -> 507 | H93: =IFERROR(IF(G93="","",VLOOKUP(G93,FS!$A$11:$B$241,2,FALSE)),"") -> Insurance | I93: =IFERROR(VLOOKUP(#REF!,Accounts_LTD!B:G,6,FALSE),"")
A94: 6210 | B94: =LEFT(C94,4) -> 6210 | C94: 6210 Professional Services:Accounting Fee | D94: 6600 | E94: =SUMIF(AJE_INC!B:B,B94,AJE_INC!D:D) -> 0 | F94: =IF(D90="__________________"," ",IF(ISERROR(E94+D94),"",(E94+D94))) -> 6600 | G94: =IF(ISERROR(VLOOKUP(B94,Accounts_INC!$B:$E,3,FALSE)),"",VLOOKUP(B94,Accounts_INC!$B:$E,3,FALSE)) -> 501.5 | H94: =IFERROR(IF(G94="","",VLOOKUP(G94,FS!$A$11:$B$241,2,FALSE)),"") -> Professional services US | I94: =IFERROR(VLOOKUP(B95,Accounts_LTD!B:G,6,FALSE),"")
A95: 6221 | B95: =LEFT(C95,4) -> 6221 | C95: 6221 Professional Services:Audit expenses-EY | D95: 10000 | E95: =SUMIF(AJE_INC!B:B,B95,AJE_INC!D:D) -> 0 | F95: =IF(D91="__________________"," ",IF(ISERROR(E95+D95),"",(E95+D95))) -> 10000 | G95: =IF(ISERROR(VLOOKUP(B95,Accounts_INC!$B:$E,3,FALSE)),"",VLOOKUP(B95,Accounts_INC!$B:$E,3,FALSE)) -> 501.5 | H95: =IFERROR(IF(G95="","",VLOOKUP(G95,FS!$A$11:$B$241,2,FALSE)),"") -> Professional services US | I95: =IFERROR(VLOOKUP(B96,Accounts_LTD!B:G,6,FALSE),"")
A96: 6230 | B96: =LEFT(C96,4) -> 6230 | C96: 6230 Professional Services:Consulting Services | D96: 17198.9 | E96: =SUMIF(AJE_INC!B:B,B96,AJE_INC!D:D) -> 3555 | F96: =IF(D92="__________________"," ",IF(ISERROR(E96+D96),"",(E96+D96))) -> 20753.9 | G96: =IF(ISERROR(VLOOKUP(B96,Accounts_INC!$B:$E,3,FALSE)),"",VLOOKUP(B96,Accounts_INC!$B:$E,3,FALSE)) -> 501.5 | H96: =IFERROR(IF(G96="","",VLOOKUP(G96,FS!$A$11:$B$241,2,FALSE)),"") -> Professional services US | I96: =IFERROR(VLOOKUP(#REF!,Accounts_LTD!B:G,6,FALSE),"")
A97: 6240 | B97: =LEFT(C97,4) -> 6240 | C97: 6240 Professional Services:HR Services | D97: 1000 | E97: =SUMIF(AJE_INC!B:B,B97,AJE_INC!D:D) -> 0 | F97: =IF(D93="__________________"," ",IF(ISERROR(E97+D97),"",(E97+D97))) -> 1000 | G97: =IF(ISERROR(VLOOKUP(B97,Accounts_INC!$B:$E,3,FALSE)),"",VLOOKUP(B97,Accounts_INC!$B:$E,3,FALSE)) -> 501.5 | H97: =IFERROR(IF(G97="","",VLOOKUP(G97,FS!$A$11:$B$241,2,FALSE)),"") -> Professional services US | I97: =IFERROR(VLOOKUP(#REF!,Accounts_LTD!B:G,6,FALSE),"")
A98: 6260 | B98: =LEFT(C98,4) -> 6260 | C98: 6260 Professional Services:Recruitment Charges | D98: 43625 | E98: =SUMIF(AJE_INC!B:B,B98,AJE_INC!D:D) -> 0 | F98: =IF(D94="__________________"," ",IF(ISERROR(E98+D98),"",(E98+D98))) -> 43625 | G98: =IF(ISERROR(VLOOKUP(B98,Accounts_INC!$B:$E,3,FALSE)),"",VLOOKUP(B98,Accounts_INC!$B:$E,3,FALSE)) -> 615 | H98: =IFERROR(IF(G98="","",VLOOKUP(G98,FS!$A$11:$B$241,2,FALSE)),"") -> Recruting (DevEx)
A99: 6290 | B99: =LEFT(C99,4) -> 6290 | C99: 6290 Professional Services:Other Professional Services | D99: 1119.37 | E99: =SUMIF(AJE_INC!B:B,B99,AJE_INC!D:D) -> 0 | F99: =IF(D95="__________________"," ",IF(ISERROR(E99+D99),"",(E99+D99))) -> 1119.37 | G99: =IF(ISERROR(VLOOKUP(B99,Accounts_INC!$B:$E,3,FALSE)),"",VLOOKUP(B99,Accounts_INC!$B:$E,3,FALSE)) -> 501.5 | H99: =IFERROR(IF(G99="","",VLOOKUP(G99,FS!$A$11:$B$241,2,FALSE)),"") -> Professional services US | I99: =IFERROR(VLOOKUP(B100,Accounts_LTD!B:G,6,FALSE),"")
A100: 6291 | B100: =LEFT(C100,4) -> 6291 | C100: 6291 Developer Experience - Recruiting | D100: 35500 | E100: =SUMIF(AJE_INC!B:B,B100,AJE_INC!D:D) -> 0 | F100: =IF(D96="__________________"," ",IF(ISERROR(E100+D100),"",(E100+D100))) -> 35500 | G100: =IF(ISERROR(VLOOKUP(B100,Accounts_INC!$B:$E,3,FALSE)),"",VLOOKUP(B100,Accounts_INC!$B:$E,3,FALSE)) -> 615 | H100: =IFERROR(IF(G100="","",VLOOKUP(G100,FS!$A$11:$B$241,2,FALSE)),"") -> Recruting (DevEx) | I100: =IFERROR(VLOOKUP(B101,Accounts_LTD!B:G,6,FALSE),"")
A101: 6293 | B101: =LEFT(C101,4) -> 6293 | C101: 6293 Customer Success - Recruiting | D101: 50000 | E101: =SUMIF(AJE_INC!B:B,B101,AJE_INC!D:D) -> 0 | F101: =IF(D97="__________________"," ",IF(ISERROR(E101+D101),"",(E101+D101))) -> 50000 | G101: =IF(ISERROR(VLOOKUP(B101,Accounts_INC!$B:$E,3,FALSE)),"",VLOOKUP(B101,Accounts_INC!$B:$E,3,FALSE)) -> 415 | H101: =IFERROR(IF(G101="","",VLOOKUP(G101,FS!$A$11:$B$241,2,FALSE)),"") -> Recruting (Customer success) | I101: =IFERROR(VLOOKUP(B102,Accounts_LTD!B:G,6,FALSE),"")
A102: 6294 | B102: =LEFT(C102,4) -> 6294 | C102: 6294 R&D - Recruiting | D102: 23000 | E102: =SUMIF(AJE_INC!B:B,B102,AJE_INC!D:D) -> 0 | F102: =IF(D98="__________________"," ",IF(ISERROR(E102+D102),"",(E102+D102))) -> 23000 | G102: =IF(ISERROR(VLOOKUP(B102,Accounts_INC!$B:$E,3,FALSE)),"",VLOOKUP(B102,Accounts_INC!$B:$E,3,FALSE)) -> 308 | H102: =IFERROR(IF(G102="","",VLOOKUP(G102,FS!$A$11:$B$241,2,FALSE)),"") -> Recruting (R&D) | I102: =IFERROR(VLOOKUP(B103,Accounts_LTD!B:G,6,FALSE),"")
A103: 6310 | B103: =LEFT(C103,4) -> 6310 | C103: 6310 Travel & Entertainment:Airfare | D103: 7015.81 | E103: =SUMIF(AJE_INC!B:B,B103,AJE_INC!D:D) -> 0 | F103: =IF(D99="__________________"," ",IF(ISERROR(E103+D103),"",(E103+D103))) -> 7015.81 | G103: =IF(ISERROR(VLOOKUP(B103,Accounts_INC!$B:$E,3,FALSE)),"",VLOOKUP(B103,Accounts_INC!$B:$E,3,FALSE)) -> 804 | H103: =IFERROR(IF(G103="","",VLOOKUP(G103,FS!$A$11:$B$241,2,FALSE)),"") -> Travel abroad marketing | I103: =IFERROR(VLOOKUP(#REF!,Accounts_LTD!B:G,6,FALSE),"")
...

Sheet AJE_LTD
C3: Additional Jurnal Entries
C4: =WP_LTD!B4 -> As of Dec 31, 2022 | J4: FS check | K4: =FS!C71 -> 62122733 | L4: =FS!E71 -> 18127645
B6: Acc # | C6: Acc Name | D6: USD | F6: NIS | I6: GL | J6: AJE Check | K6: =SUM(D:D) -> #REF! | L6: =SUM(F:F) -> #REF! | M6: Acc # | N6: Acc #
C7: =IF(ISERROR(VLOOKUP(B7,Accounts_LTD!$B:$E,2,FALSE)),"",VLOOKUP(B7,Accounts_LTD!$B:$E,2,FALSE))
C8: =IF(ISERROR(VLOOKUP(B8,Accounts_LTD!$B:$E,2,FALSE)),"",VLOOKUP(B8,Accounts_LTD!$B:$E,2,FALSE))
B10: 65006 | C10: =VLOOKUP(B10,GL_LTD!B:C,2,0) -> הוצאות מחירי העברה IC EXPENSES | D10: 341309.11 | F10: =-F11 -> 1201066.8 | G10: רישום חשבונית בינחברתית 12/22 בספרי LTD
B11: 200161 | C11: =VLOOKUP(B11,GL_LTD!B:C,2,0) -> Treeverse, Inc | D11: =-D10 -> -341309.11 | F11: =D11*USD -> -1201066.8 | G11: רישום חשבונית בינחברתית 12/22 בספרי LTD
B13: 65006 | C13: =VLOOKUP(B13,GL_LTD!B:C,2,0) -> הוצאות מחירי העברה IC EXPENSES | D13: =-AJE_INC!D14 -> -30613.83 | F13: =-F14 -> -107730.07 | G13: איפוס LRD - משיכה מאינק
B14: 200161 | C14: =VLOOKUP(B14,GL_LTD!B:C,2,0) -> Treeverse, Inc | D14: =-D13 -> 30613.83 | F14: =D14*USD -> 107730.07 | G14: איפוס LRD - משיכה מאינק
B19: 200147 | C19: =VLOOKUP(B19,GL_LTD!B:C,2,0) -> מפתחים מובילים בהייטק בע"מ | D19: =-GL_LTD!E74 -> -7314.58 | F19: =-GL_LTD!D74 -> -25740 | G19: ספקים בחובה
B20: 50115 | C20: =VLOOKUP(B20,GL_LTD!B:C,2,0) -> הוצ יעוץ מפתחים -שימי וידר | D20: =-D19/1.17 -> 6251.7778 | F20: =-F19/1.17 -> 22000
B22: 200027 | C22: =VLOOKUP(B22,GL_LTD!B:C,2,0) -> מגדל חברה לבטוח בע"מ | D22: =-VLOOKUP(B22,GL_LTD!$B:$J,4,0) -> -2433.51 | F22: =-VLOOKUP(B22,GL_LTD!$B:$J,3,0) -> -8563.51
B23: 70007 | C23: =VLOOKUP(B23,GL_LTD!B:C,2,0) -> ביטוח עסק | D23: =-D22/1.17 -> 2079.9231 | F23: =-F22/1.17 -> 7319.2393
B25: 200059 | C25: =VLOOKUP(B25,GL_LTD!B:C,2,0) -> ג'יטי גט טקסי סרוויסס בע"מ | D25: =-VLOOKUP(B25,GL_LTD!$B:$J,4,0) -> -342.23 | F25: =-VLOOKUP(B25,GL_LTD!$B:$J,3,0) -> -1204.3
B26: 70034 | C26: =VLOOKUP(B26,GL_LTD!B:C,2,0) -> נסיעות תחבורה ומוניות | D26: =-D25/1.17 -> 292.50427 | F26: =-F25/1.17 -> 1029.3162
B28: 200065 | C28: =VLOOKUP(B28,GL_LTD!B:C,2,0) -> קיי.אס.פי אקספרס בע"מ | D28: =-VLOOKUP(B28,GL_LTD!$B:$J,4,0) -> -281.05 | F28: =-VLOOKUP(B28,GL_LTD!$B:$J,3,0) -> -989
B29: 70022 | C29: =VLOOKUP(B29,GL_LTD!B:C,2,0) -> אחזקת מחשב הנה"כ | D29: =-D28/1.17 -> 240.21368 | F29: =-F28/1.17 -> 845.29915
B31: 200099 | C31: =VLOOKUP(B31,GL_LTD!B:C,2,0) -> קיי.אס.פי. מחשבים (ראשון לציון) בע"מ | D31: =-VLOOKUP(B31,GL_LTD!$B:$J,4,0) -> -570.62 | F31: =-VLOOKUP(B31,GL_LTD!$B:$J,3,0) -> -2008
B32: 70022 | C32: =VLOOKUP(B32,GL_LTD!B:C,2,0) -> אחזקת מחשב הנה"כ | D32: =-D31/1.17 -> 487.7094 | F32: =-F31/1.17 -> 1716.2393
B34: 200111 | C34: =VLOOKUP(B34,GL_LTD!B:C,2,0) -> קיי.אס.פי מחשבים תל אביב בע"מ | D34: =-VLOOKUP(B34,GL_LTD!$B:$J,4,0) -> -519.75 | F34: =-VLOOKUP(B34,GL_LTD!$B:$J,3,0) -> -1829
B35: 70022 | C35: =VLOOKUP(B35,GL_LTD!B:C,2,0) -> אחזקת מחשב הנה"כ | D35: =-D34/1.17 -> 444.23077 | F35: =-F34/1.17 -> 1563.2479
B37: 200221 | C37: =VLOOKUP(B37,GL_LTD!B:C,2,0) -> הולו דפוס דיגיטלי בע"מ | D37: =-VLOOKUP(B37,GL_LTD!$B:$J,4,0) -> -62.23 | F37: =-VLOOKUP(B37,GL_LTD!$B:$J,3,0) -> -219
B38: 60009 | C38: =VLOOKUP(B38,GL_LTD!B:C,2,0) -> הוצMarkting Swag - Worldwide Buddies, Etsy and P | D38: =-D37/1.17 -> 53.188034 | F38: =-F37/1.17 -> 187.17949
B40: 200005 | C40: =VLOOKUP(B40,GL_LTD!B:C,2,0) -> ג'ט בריינס jetbrains | D40: =-VLOOKUP(B40,GL_LTD!$B:$J,4,0) -> -45.51 | F40: =-VLOOKUP(B40,GL_LTD!$B:$J,3,0) -> -160.15
B41: 50109 | C41: =VLOOKUP(B41,GL_LTD!B:C,2,0) -> תוכנה וכילים TOOLS מו"פ | D41: =-D40 -> 45.51 | F41: =-F40 -> 160.15
B43: 200078 | C43: =VLOOKUP(B43,GL_LTD!B:C,2,0) -> Upwork Global Inc | D43: =-VLOOKUP(B43,GL_LTD!$B:$J,4,0) -> -1533 | F43: =-VLOOKUP(B43,GL_LTD!$B:$J,3,0) -> -5394.63
B44: 60007 | C44: =VLOOKUP(B44,GL_LTD!B:C,2,0) -> הוצאות Marketing - Upwork expenses | D44: =-D43/1.17 -> 1310.2564 | F44: =-F43/1.17 -> 4610.7949
B46: 200087 | C46: =VLOOKUP(B46,GL_LTD!B:C,2,0) -> DOCUSIGN | D46: =-VLOOKUP(B46,GL_LTD!$B:$J,4,0) -> -45 | F46: =-VLOOKUP(B46,GL_LTD!$B:$J,3,0) -> -158.36
B47: 70047 | C47: =VLOOKUP(B47,GL_LTD!B:C,2,0) -> הוצ Docusign | D47: =-D46 -> 45 | F47: =-F46 -> 158.36
B49: 200094 | C49: =VLOOKUP(B49,GL_LTD!B:C,2,0) -> Microsoft | D49: =-VLOOKUP(B49,GL_LTD!$B:$J,4,0) -> -1500 | F49: =-VLOOKUP(B49,GL_LTD!$B:$J,3,0) -> -5278.5
B50: 70042 | C50: =VLOOKUP(B50,GL_LTD!B:C,2,0) -> תוכנה וכילים TOOLS הנה"כ | D50: =-D49 -> 1500 | F50: =-F49 -> 5278.5
B52: 200098 | C52: =VLOOKUP(B52,GL_LTD!B:C,2,0) -> DATABRICKS INC | D52: =-VLOOKUP(B52,GL_LTD!$B:$J,4,0) -> -2378.44 | F52: =-VLOOKUP(B52,GL_LTD!$B:$J,3,0) -> -8369.73
B53: 50109 | C53: =VLOOKUP(B53,GL_LTD!B:C,2,0) -> תוכנה וכילים TOOLS מו"פ | D53: =-D52 -> 2378.44 | F53: =-F52 -> 8369.73
B55: 200127 | C55: =VLOOKUP(B55,GL_LTD!B:C,2,0) -> JumpCloud Inc | D55: =-VLOOKUP(B55,GL_LTD!$B:$J,4,0) -> -391 | F55: =-VLOOKUP(B55,GL_LTD!$B:$J,3,0) -> -1375.93
B56: 50109 | C56: =VLOOKUP(B56,GL_LTD!B:C,2,0) -> תוכנה וכילים TOOLS מו"פ | D56: =-D55 -> 391 | F56: =-F55 -> 1375.93
B58: 200131 | C58: =VLOOKUP(B58,GL_LTD!B:C,2,0) -> INTERCONTINENTAL SAN | D58: =-VLOOKUP(B58,GL_LTD!$B:$J,4,0) -> -878.81 | F58: =-VLOOKUP(B58,GL_LTD!$B:$J,3,0) -> -3092.54
B59: 50503 | C59: =VLOOKUP(B59,GL_LTD!B:C,2,0) -> נסיעה לחול יונתן ארגוטן ניו יורק 20.4-06.6.22 | D59: =-D58 -> 878.81 | F59: =-F58 -> 3092.54
B61: 200153 | C61: =VLOOKUP(B61,GL_LTD!B:C,2,0) -> Brand24 Global Inc | D61: =-VLOOKUP(B61,GL_LTD!$B:$J,4,0) -> -437.52 | F61: =-VLOOKUP(B61,GL_LTD!$B:$J,3,0) -> -1539.63
B62: 67002 | C62: =VLOOKUP(B62,GL_LTD!B:C,2,0) -> כילים Developer Experience | D62: =-D61 -> 437.52 | F62: =-F61 -> 1539.63
B64: 200191 | C64: =VLOOKUP(B64,GL_LTD!B:C,2,0) -> Shutterstock Ireland Ltd. | D64: =-VLOOKUP(B64,GL_LTD!$B:$J,4,0) -> -29 | F64: =-VLOOKUP(B64,GL_LTD!$B:$J,3,0) -> -102.05
B65: 67002 | C65: =VLOOKUP(B65,GL_LTD!B:C,2,0) -> כילים Developer Experience | D65: =-D64 -> 29 | F65: =-F64 -> 102.05
B67: 21001 | C67: =VLOOKUP(B67,GL_LTD!B:C,2,0) -> Amazon | D67: =-VLOOKUP(B67,GL_LTD!$B:$J,4,0) -> -1727.3 | F67: =-VLOOKUP(B67,GL_LTD!$B:$J,3,0) -> -6078.37
B68: 70025 | C68: =VLOOKUP(B68,GL_LTD!B:C,2,0) -> ספרות מקצועית | D68: =-D67 -> 1727.3 | F68: =-F67 -> 6078.37
B70: BS002 | C70: =VLOOKUP(B70,GL_LTD!B:C,2,0) -> מעמ ספקים | D70: =-SUM(D19:D68) -> 1897.1666 | F70: =-SUM(F19:F68) -> 6676.1238
B72: 50115 | C72: =VLOOKUP(B72,GL_LTD!B:C,2,0) -> הוצ יעוץ מפתחים -שימי וידר | D72: -6811 | F72: =D72*USD -> -23967.909 | G72: ביטול הוצאה לשלם שנרשמה. במקום זה בוטל ספק בחובה
B73: 20200 | C73: =VLOOKUP(B73,GL_LTD!B:C,2,0) -> הוצאות לשלם | D73: =-D72 -> 6811 | F73: =-F72 -> 23967.909
B75: 200032 | C75: =VLOOKUP(B75,GL_LTD!B:C,2,0) -> UNITED | D75: =-GL_LTD!E81 -> -7645.75 | F75: =-GL_LTD!D81 -> -26905.39 | G75: ספקים בחובה - שניהם נסגרו מול כרטיס אחד אבל שניהם כנגד טיסות ישנות
B76: 200075 | C76: =VLOOKUP(B76,GL_LTD!B:C,2,0) -> YOAST | D76: =-GL_LTD!E82 -> -4740.67 | F76: =-GL_LTD!D82 -> -16682.42
B77: 50500 | C77: =VLOOKUP(B77,GL_LTD!B:C,2,0) -> נסיעה לארה"ב עוז כץ 11.10.21-15.10.21 | D77: =-D75-D76 -> 12386.42 | F77: =-F75-F76 -> 43587.81
B79: 40101 | C79: =VLOOKUP(B79,GL_LTD!B:C,2,0) -> הכנסות תחזוקה - חו"ל | D79: 4300 | F79: =D79*USD -> 15131.7 | G79: הוצאות טיסה לחול שנרשמו כהכנסות
B80: 40102 | C80: =VLOOKUP(B80,GL_LTD!B:C,2,0) -> הכנסות תחזוקה - חו"ל ללא למעמ | D80: =-D79 -> -4300 | F80: =-F79 -> -15131.7
B83: 50116 | C83: =VLOOKUP(B83,GL_LTD!B:C,2,0) -> הוצ איתי דויד MANITOBA contractor -Itay David | D83: 19750 | F83: =D83*USD -> 69500.25 | G83: שולם בינואר עבור דצמבר
B84: 20200 | C84: =VLOOKUP(B84,GL_LTD!B:C,2,0) -> הוצאות לשלם | D84: =-D83 -> -19750 | F84: =-F83 -> -69500.25
B87: PL112 | C87: =VLOOKUP(B87,GL_LTD!B:C,2,0) -> Bonus DevEx | D87: =F87/USD -> 10116.51 | F87: 35600 | G87: בונוס עדי עבור שנת 2022
B88: 20200 | C88: =VLOOKUP(B88,GL_LTD!B:C,2,0) -> הוצאות לשלם | D88: =F88/USD -> -10116.51 | F88: =-F87 -> -35600
B91: PL113 | C91: =VLOOKUP(B91,GL_LTD!B:C,2,0) -> אלוקציה למופ | D91: =WP_LTD!E314 -> 159905.79 | F91: =WP_LTD!D314 -> 533869.57 | G91: הוצאות אלוקציה
B92: PL114 | C92: =VLOOKUP(B92,GL_LTD!B:C,2,0) -> אלוקציה למרקטינג | D92: =WP_LTD!E316 -> 10660.386 | F92: =WP_LTD!D316 -> 35591.305
B93: PL115 | C93: =VLOOKUP(B93,GL_LTD!B:C,2,0) -> אלוקציה ל DEVEX | D93: =WP_LTD!E315 -> 10660.386 | F93: =WP_LTD!D315 -> 35591.305
B94: PL116 | C94: =VLOOKUP(B94,GL_LTD!B:C,2,0) -> אלוקציה מהנהכ | D94: =-SUM(D91:D93) -> -181226.57 | F94: =-SUM(F91:F93) -> -605052.18
B96: 20999 | C96: =VLOOKUP(B96,GL_LTD!B:C,2,0) -> עתודה להבראה | D96: =-SUM(D97:D99) -> -1835.1804 | F96: =-F97-F98 -> -6458 | G96: עתודה להבראה
B97: 51097 | C97: =VLOOKUP(B97,GL_LTD!B:C,2,0) -> הוצאות הפרשה להבראה מו"פ | D97: =F97/USD -> 1566.6382 | F97: 5513 | G97: התאמה ליתרה שרשמו נקסטייג לסוף דצמבר
B98: 71097 | C98: =VLOOKUP(B98,GL_LTD!B:C,2,0) -> הוצאות הפרשה להבראה הנהלה | D98: =F98/USD -> 268.5422 | F98: 945
B99: 65097 | C99: =VLOOKUP(B99,GL_LTD!B:C,2,0) -> הוצאות הפרשה להבראה Marketing | D99: =F99/USD -> 0
B101: PL117 | C101: =VLOOKUP(B101,GL_LTD!B:C,2,0) -> אופציות- מו"פ | D101: ='[75]2022 FAS 123 '!$V$59 -> #REF! | F101: =D101*AVR_USD -> #REF! | G101: הוצאות בגין אופציות
B102: PL118 | C102: =VLOOKUP(B102,GL_LTD!B:C,2,0) -> אופציות-הנה"כ | D102: ='[75]2022 FAS 123 '!$V$62 -> #REF! | F102: =D102*AVR_USD -> #REF!
B103: PL119 | C103: =VLOOKUP(B103,GL_LTD!B:C,2,0) -> אופציות- מכירה ושיווק | D103: ='[75]2022 FAS 123 '!$V$60 -> #REF! | F103: =D103*AVR_USD -> #REF!
B104: BS200 | C104: =VLOOKUP(B104,GL_LTD!B:C,2,0) -> קרן הון- אופציות | D104: =-SUM(D101:D103) -> #REF! | F104: =D104*AVR_USD -> #REF!
B106: BS510 | C106: =VLOOKUP(B106,GL_LTD!B:C,2,0) -> Additional Paid-In Capital | D106: =[76]DataSheet!$O$13176 -> #ERROR! | F106: =[77]DataSheet!$G$13177 -> #ERROR! | G106: מיון מחוז להשקעה בחברת בת LTD
B107: 20800 | C107: =VLOOKUP(B107,GL_LTD!B:C,2,0) -> TREEVERSE INC | D107: =-D106 -> #ERROR! | F107: =-F106 -> #ERROR!
B109: BS510 | C109: =VLOOKUP(B109,GL_LTD!B:C,2,0) -> Additional Paid-In Capital | D109: ='Shareholders Equity'!D23 -> 58765 | F109: ='Shareholders Equity'!C23 -> 191000 | G109: מיון יתרת פתיחה בין השקעה(פרמיה) לקרן הון אופציות
B110: BS200 | C110: =VLOOKUP(B110,GL_LTD!B:C,2,0) -> קרן הון- אופציות | D110: =-D109 -> -58765 | F110: =-F109 -> -191000 | G110: שייך ל 2021
B112: 20800 | C112: =VLOOKUP(B112,GL_LTD!B:C,2,0) -> TREEVERSE INC | D112: ='Shareholders Equity'!D26 | F112: =[76]DataSheet!$K$13182 -> #ERROR! | G112: ביטול הפרשי שער שנרשמו על השקעה (נרמו עבור השקעות של INC(
B113: 90002 | C113: =VLOOKUP(B113,GL_LTD!B:C,2,0) -> הפרשי שער | D113: =-D112 -> 0 | F113: =-F112 -> #ERROR!

Sheet CF
C2: Cash Flow $ | J2: check
C3: 44196 | D3: Cash | E3: Not Cash | F3: Operating | G3: Financing | H3: Investments | I3: 44561
A4: 1 | B4: Cash and cash equivalents | C4: 1026366.6 | D4: =I4-C4 -> 768346.03 | I4: =VLOOKUP(A4,FS!$A:$M,13,0) -> 1794712.6 | J4: =I4-C4-(SUM(D4:H4)) -> 0
A5: 2 | B5: Short-term Deposits | C5: 18664.59 | H5: =I5-C5 -> 7581335.4 | I5: =VLOOKUP(A5,FS!$A:$M,13,0) -> 7600000 | J5: =I5-C5-(SUM(D5:H5)) -> 0
A6: 5 | B6: Trade Receivables | C6: 5816.59 | F6: =I6-C6 -> -2516.59 | I6: =VLOOKUP(A6,FS!$A:$M,13,0) -> 3300 | J6: =I6-C6-(SUM(D6:H6)) -> 0
A7: 6 | B7: Intercompany | C7: 0 | I7: =VLOOKUP(A7,FS!$A:$M,13,0) -> 18127645 | J7: =I7-C7-(SUM(D7:H7)) -> 18127645
A8: 7 | B8: Receivables and prepaid expenses | C8: 89778.554 | F8: =I8-C8 -> 36364.573 | I8: =VLOOKUP(A8,FS!$A:$M,13,0) -> 126143.13 | J8: =I8-C8-(SUM(D8:H8)) -> 0
A9: 20.1 | B9: lease deposit | C9: 13917.95 | F9: =I9-C9 -> 20299.14 | I9: =VLOOKUP(A9,FS!$A:$M,13,0) -> 34217.09 | J9: =I9-C9-(SUM(D9:H9)) -> 0
A10: 21 | B10: Fixed assets | C10: 10159.29 | E10: =-N36 -> #ERROR! | H10: =I10-C10-E10 -> #ERROR! | I10: =VLOOKUP(A10,FS!$A:$M,13,0) -> 372326.92 | J10: =I10-C10-(SUM(D10:H10)) -> #ERROR!
A11: 22 | B11: Accumulated depreciation | C11: -8702.8198 | E11: =-N37 -> #ERROR! | F11: =I11-C11-E11 -> #ERROR! | I11: =VLOOKUP(A11,FS!$A:$M,13,0) -> -77677.95 | J11: =I11-C11-(SUM(D11:H11)) -> #ERROR!
A12: 31 | B12: Trade payables | C12: -48727.169 | F12: =I12-C12 -> -67341.211 | I12: =VLOOKUP(A12,FS!$A:$M,13,0) -> -116068.38 | J12: =I12-C12-(SUM(D12:H12)) -> 0
A13: 33 | B13: Employees and related | C13: -177924.59 | F13: =I13-C13 -> -134445.95 | I13: =VLOOKUP(A13,FS!$A:$M,13,0) -> -312370.54 | J13: =I13-C13-(SUM(D13:H13)) -> 0
A14: 34 | B14: Other current liabilities | C14: -52658.057 | F14: =I14-C14 -> 41470.407 | I14: =VLOOKUP(A14,FS!$A:$M,13,0) -> -11187.65 | J14: =I14-C14-(SUM(D14:H14)) -> 0
A15: 35 | B15: Shareholders liability | C15: 0 | I15: =VLOOKUP(A15,FS!$A:$M,13,0) -> 0 | J15: =I15-C15-(SUM(D15:H15)) -> 0
A16: 36 | B16: Intercompany | C16: 0 | I16: =VLOOKUP(A16,FS!$A:$M,13,0) -> 0 | J16: =I16-C16-(SUM(D16:H16)) -> 0
A17: 40 | B17: Severance pay | C17: 0 | I17: =VLOOKUP(A17,FS!$A:$M,13,0) -> 0 | J17: =I17-C17-(SUM(D17:H17)) -> 0
A18: 41 | B18: Convertible Loans | C18: 0 | I18: =VLOOKUP(A18,FS!$A:$M,13,0) -> 0 | J18: =I18-C18-(SUM(D18:H18)) -> 0
A19: 42 | B19: Shareholders liabilities | C19: 0 | I19: =VLOOKUP(A19,FS!$A:$M,13,0) -> 0 | J19: =I19-C19-(SUM(D19:H19)) -> 0
A20: 50 | B20: Share capital | C20: -1786.3465 | G20: =I20-C20 -> 1786.3465 | I20: =VLOOKUP(A20,FS!$A:$M,13,0) -> 0 | J20: =I20-C20-(SUM(D20:H20)) -> 0
A21: 50.1 | B21: Preferred A-1 Shares | C21: -540.57414 | G21: =I21-C21 -> 540.57414 | I21: =VLOOKUP(A21,FS!$A:$M,13,0) -> 0 | J21: =I21-C21-(SUM(D21:H21)) -> 0
A22: 50.2 | B22: Preferred A Shares | C22: -340.84488 | G22: =I22-C22 -> 340.84488 | I22: =VLOOKUP(A22,FS!$A:$M,13,0) -> 0 | J22: =I22-C22-(SUM(D22:H22)) -> 0
A23: 51 | B23: Additional paid-in capital | C23: -4902593.8 | G23: =I23-C23 -> -18106521 | I23: =VLOOKUP(A23,FS!$A:$M,13,0) -> -23009114 | J23: =I23-C23-(SUM(D23:H23)) -> 0
A24: 56 | B24: Notes Receivable for shares issued | C24: 75872.812 | G24: =I24-C24 -> -75872.812 | I24: =VLOOKUP(A24,FS!$A:$M,13,0) -> 0 | J24: =I24-C24-(SUM(D24:H24)) -> 0
A25: 54 | B25: Stock compensation | C25: 0 | F25: =I25-C25 -> -32476.959 | I25: =VLOOKUP(A25,FS!$A:$M,13,0) -> -32476.959 | J25: =I25-C25-(SUM(D25:H25)) -> 0
A26: 55 | B26: Issuance expenses | C26: 97935 | G26: =I26-C26 -> 110157.13 | I26: =VLOOKUP(A26,FS!$A:$M,13,0) -> 208092.13 | J26: =I26-C26-(SUM(D26:H26)) -> 0
A27: 52 | B27: Net Profit (loss) For the period | C27: 1816584.7 | F27: =I27-C27 -> 4961115.5 | I27: =VLOOKUP(A27,FS!$A:$M,13,0) -> 6777700.1 | J27: =I27-C27-(SUM(D27:H27)) -> 0
A28: 53 | B28: Accumulated loss | C28: 2038178.2 | F28: =I28-C28 -> 1912027.6 | I28: =VLOOKUP(A28,FS!$A:$M,13,0) -> 3950205.8 | J28: =I28-C28-(SUM(D28:H28)) -> 0
B30: Check | C30: =SUM(C4:C29) -> 4.6566129e-10 | D30: =SUM(D4:D29) -> 768346.03 | E30: =SUM(E4:E29) -> #ERROR! | F30: =SUM(F4:F29) -> #ERROR! | G30: =SUM(G4:G29) -> -18069569 | H30: =SUM(H4:H29) -> #ERROR! | I30: =SUM(I4:I29) -> 15435447
B35: Statements of cash flows | O35: גריעת רכוש קבוע:
N36: =-AJE_LTD!#REF! -> #ERROR! | O36: עלות
N37: =-AJE_LTD!#REF! -> #ERROR! | O37: פחנ"צ
B38: Cash flows - operating activities | N38: =AJE_LTD!#REF! -> #ERROR! | O38: תשלום
B40: Net loss for the period | D40: =-F27-F28 -> -6873143.1 | E40: =ROUND(D40/1000,0) -> -6873
B41: Adjustments to reconcile net loss to net cash used in operating activities: | E41: =ROUND(D41/1000,0) -> 0
B42: Items not involving cash flows: | E42: =ROUND(D42/1000,0) -> 0
B43: Depreciation | D43: =-F11 -> #ERROR! | E43: =ROUND(D43/1000,0) -> #ERROR!
B44: Beneficial conversion feature, net | E44: =ROUND(D44/1000,0) -> 0
B45: Changes in operating assets and liabilities: | E45: =ROUND(D45/1000,0) -> 0
B46: Decrease (Increase) in other current assets | D46: =-F8-F9-D47 -> -56663.713 | E46: =ROUND(D46/1000,0) -> -57
B47: Decrease (Increase) in Israel Innovation Authority | D47: =-GL_LTD!F105 -> 0 | E47: =ROUND(D47/1000,0) -> 0
B48: Decrease (Increase) in accounts receivable | D48: =-F6 -> 2516.59 | E48: =ROUND(D48/1000,0) -> 3
B49: Increase in trade accounts payable | D49: =-F12 -> 67341.211 | E49: =ROUND(D49/1000,0) -> 67
B50: Increase (Decrease) in other current liabilities | D50: =-F13-F14 -> 92975.543 | E50: =ROUND(D50/1000,0) -> 93
B51: Net cash used in operating activities | D51: =SUM(D40:D50) -> #ERROR! | E51: =ROUND(D51/1000,0) -> #ERROR!
E52: =ROUND(D52/1000,0) -> 0
B53: Cash flows - investing activity | E53: =ROUND(D53/1000,0) -> 0
B54: Deposits | D54: =-H5 -> -7581335.4 | E54: =ROUND(D54/1000,0) -> -7581
B55: Sale (Purchase) of property and equipment | D55: =-H10 -> #ERROR! | E55: =ROUND(D55/1000,0) -> #ERROR!
B56: Net cash used in investing activity | D56: =SUM(D54:D55) -> #ERROR! | E56: =ROUND(D56/1000,0) -> #ERROR!
E57: =ROUND(D57/1000,0) -> 0
E58: =ROUND(D58/1000,0) -> 0
B59: Cash flows - financing activities | E59: =ROUND(D59/1000,0) -> 0
B60: Issuance of Shares | D60: =-G20-G21-G22-G23-G24-G26 -> 18069569 | E60: =ROUND(D60/1000,0) -> 18070 | F60: =D60-#REF!-#REF!-#REF! -> #REF! | G60: בדיקה מול דוח על השינויים
B61: Receipt SAFE investment | E61: =ROUND(D61/1000,0) -> 0
B62: Receipt convertible security | E62: =ROUND(D62/1000,0) -> 0
B63: Net cash provided by financing activities | D63: =SUM(D60:D62) -> 18069569 | E63: =ROUND(D63/1000,0) -> 18070
E64: =ROUND(D64/1000,0) -> 0
E65: =ROUND(D65/1000,0) -> 0
B66: Increase (decrease) in cash, cash equivalents and restricted cash | D66: =D51+D56+D63 -> #ERROR! | E66: =ROUND(D66/1000,0) -> #ERROR!
B67: Cash, cash equivalents and restricted cash at beginning of period | D67: =C4 -> 1026366.6 | E67: =ROUND(D67/1000,0) -> 1026
E68: =ROUND(D68/1000,0) -> 0
B69: Cash, cash equivalents and restricted cash at end of period | D69: =I4 -> 1794712.6 | E69: =ROUND(D69/1000,0) -> 1795
D70: =D69-D67-D66 -> #ERROR! | E70: =ROUND(D70/1000,0) -> #ERROR!
B71: Supplemental disclosure of non-cash activities
B72: Conversion of SAFE and convertible loans into Shares
B73: Debtors on account of shares

Sheet TB INC

Sheet Shareholders Equity
B3: Ordinary shares | C3: Additional paid-in capital include share based | D3: Acumulated deficit | E3: Preferred | F3: total shareholders' equity
A4: Balance of 31/12/2021 | B4: 0 | C4: 14919518 | D4: =-FS!C66 -> -13345316 | F4: =SUM(B4:E4) -> 1574202.6 | I4: כןלל תשלום מבוסס מניות
A6: Convertible loan | F6: 0
A7: Additional paid-in capital | C7: 44289995 | F7: =SUM(B7:E7) -> 44289995
A8: Share capital adjustment | F8: 0 | H8: =SUM(F4:F10) -> 23827410
A9: Share based compensation | C9: 711321 | F9: =SUM(B9:E9) -> 711321 | I9: בדיקה
A10: Net loss | D10: =D12-D4 -> -22748108 | F10: =SUM(B10:E10) -> -22748108 | H10: =H8-F12 -> 0
A11: Issuance expenses | F11: 0
A12: Balance of 31/12/2022 | B12: 0 | C12: =SUM(C4:C9) -> 59920834 | D12: =-FS!C65-FS!C66 -> -36093424 | E12: 0 | F12: =SUM(B12:E12) -> 23827410
A14: Common share
A15: Preferred A shares
A16: Preferred B shares
A21: Share based compensation
C22: ILS | D22: $
A23: Balance of 31/12/2021 | C23: 191000 | D23: 58765 | F23: =C23/D23 -> 3.250234
A25: הבשלה | C25: =-AJE_LTD!F104 -> #REF! | D25: ='[75]2022 FAS 123 '!$V$63 -> #REF! | F25: שע"ח ממוצע
A27: Balance of 31/12/2022 | C27: =C23+C25 -> #REF! | D27: 302970.2
A36: Additional paid-in capital | C36: =C27-C12 -> #REF!
B44: צריך להיות | C44: ILS | D44: USD
D45: -18135902
D46: =D23 -> 58765 | E46: 2021
C47: =C12-C23 -> 59729834 | D47: =D45+D46 -> -18077137 | E47: סה"בדולרים

Sheet WP_LTD
B4: As of Dec 31, 2022
B6: USD= | C6: 3.519 | D6: Euro | E6: 3.753
B7: Average rate USD | C7: 3.3596 | D7: GBP | E7: 4.2376
B8: Month # | C8: 12 | D8: Cad | E8: 2.5966
B9: Date: | C9: 44926
B12: Cash and cash equivalents
B13: Account # | C13: Account Name | D13: TB NIS | E13: amount according to bank statement | F13: currency | G13: Difference
B14: 10000 | C14: =IF(ISERROR(VLOOKUP(B14,Accounts_LTD!$B:$E,2,FALSE)),"",VLOOKUP(B14,Accounts_LTD!$B:$E,2,FALSE)) -> בנק לאומי ש"ח | D14: =IF(ISERROR(VLOOKUP(B14,GL_LTD!$B:$I,8,FALSE)),0,VLOOKUP(B14,GL_LTD!$B:$I,8,FALSE)) -> 5716204.6 | E14: 5716204.6 | F14: NIS | G14: =D14-E14 -> 0 | H14: =D14/USD -> 1624383.2 | L14: 3.668
B15: 10001 | C15: =IF(ISERROR(VLOOKUP(B15,Accounts_LTD!$B:$E,2,FALSE)),"",VLOOKUP(B15,Accounts_LTD!$B:$E,2,FALSE)) -> בנק לאומי $ | D15: =IF(ISERROR(VLOOKUP(B15,GL_LTD!$B:$I,8,FALSE)),0,VLOOKUP(B15,GL_LTD!$B:$I,8,FALSE)) -> 586873.73 | E15: 586873.73 | F15: USD | G15: =D15-E15 -> 0 | H15: =D15/USD -> 166772.87
B16: 10300 | C16: =IF(ISERROR(VLOOKUP(B16,Accounts_LTD!$B:$E,2,FALSE)),"",VLOOKUP(B16,Accounts_LTD!$B:$E,2,FALSE)) -> פקדון ש"ח בנק לאומי | D16: =IF(ISERROR(VLOOKUP(B16,GL_LTD!$B:$I,8,FALSE)),0,VLOOKUP(B16,GL_LTD!$B:$I,8,FALSE)) -> 120409.93 | E16: 120409.93 | F16: NIS | G16: =D16-E16 -> 0 | H16: =D16/USD -> 34217.087
B17: 10310 | C17: =IF(ISERROR(VLOOKUP(B17,Accounts_LTD!$B:$E,2,FALSE)),"",VLOOKUP(B17,Accounts_LTD!$B:$E,2,FALSE)) -> פקדון $ בנק לאומי | D17: =IF(ISERROR(VLOOKUP(B17,GL_LTD!$B:$I,8,FALSE)),0,VLOOKUP(B17,GL_LTD!$B:$I,8,FALSE)) -> 26744400 | E17: 26744400 | F17: USD | G17: =D17-E17 -> 0 | H17: =D17/USD -> 7600000
B18: 10501 | C18: =IF(ISERROR(VLOOKUP(B18,Accounts_LTD!$B:$E,2,FALSE)),"",VLOOKUP(B18,Accounts_LTD!$B:$E,2,FALSE)) -> פקדון SOK WORKS | D18: =IF(ISERROR(VLOOKUP(B18,GL_LTD!$B:$I,8,FALSE)),0,VLOOKUP(B18,GL_LTD!$B:$I,8,FALSE)) -> 1404 | E18: 1404 | F18: USD | G18: =D18-E18 -> 0 | H18: =D18/USD -> 398.97698
B19: 10003 | C19: =IF(ISERROR(VLOOKUP(B19,Accounts_LTD!$B:$E,2,FALSE)),"",VLOOKUP(B19,Accounts_LTD!$B:$E,2,FALSE)) -> בנק לאומי אירו | D19: =IF(ISERROR(VLOOKUP(B19,GL_LTD!$B:$I,8,FALSE)),0,VLOOKUP(B19,GL_LTD!$B:$I,8,FALSE)) -> -18.99 | E19: -18.99 | F19: Euro | G19: =D19-E19 -> 0 | H19: =D19/USD -> -5.3964194
B20: 10002 | C20: =IF(ISERROR(VLOOKUP(B20,Accounts_LTD!$B:$E,2,FALSE)),"",VLOOKUP(B20,Accounts_LTD!$B:$E,2,FALSE)) -> בנק לאומי דולר קנדי | D20: =IF(ISERROR(VLOOKUP(B20,GL_LTD!$B:$I,8,FALSE)),0,VLOOKUP(B20,GL_LTD!$B:$I,8,FALSE)) -> 11130.46 | E20: 11130.46 | H20: =D20/USD -> 3162.9611
C21: =IF(ISERROR(VLOOKUP(B21,Accounts_LTD!$B:$E,2,FALSE)),"",VLOOKUP(B21,Accounts_LTD!$B:$E,2,FALSE)) | G21: =D21-E21 -> 0
D22: =SUM(D14:D21) -> 33180404 | E22: =SUM(E14:E21) -> 33180404 | G22: =SUM(G14:G19) -> 0 | H22: =SUM(H14:H21) -> 9428929.7
D23: =FS!C11 -> 6315593.8 | H23: =FS!E11 -> 1794712.6
C24: check | D24: =D22-D23 -> 26864810 | H24: =H22-H23 -> 7634217.1
B27: Prepaid expenses
B28: Account # | C28: Account Name | D28: AJE | F28: Details | G28: Amount USD | H28: Amount NIS | I28: Start | J28: End
D29: Amount USD | E29: Amount NIS
B30: 977001 | C30: =IF(ISERROR(VLOOKUP(B30,Accounts_LTD!$B:$E,2,FALSE)),"",VLOOKUP(B30,Accounts_LTD!$B:$E,2,FALSE)) | G30: 3244 | H30: 10611.12 | I30: 44400 | J30: 44764
C31: =IF(ISERROR(VLOOKUP(B31,Accounts_LTD!$B:$E,2,FALSE)),"",VLOOKUP(B31,Accounts_LTD!$B:$E,2,FALSE))
D32: =SUM(D30:D31) -> 0 | E32: =SUM(E30) -> 0
C34: CHECK | D34: =D32-FS!#REF! -> #ERROR! | E34: =E32-FS!#REF! -> #ERROR!
B37: Government Institutions
B38: Account # | C38: Account Name | D38: TB NIS | F38: Details
B39: 20400 | C39: מע'מ חו'ז | D39: =IF(ISERROR(VLOOKUP(B39,GL_LTD!$B:$I,8,FALSE)),0,VLOOKUP(B39,GL_LTD!$B:$I,8,FALSE)) -> 0
B40: 20401 | C40: מע'מ עסקאות | D40: =IF(ISERROR(VLOOKUP(B40,GL_LTD!$B:$I,8,FALSE)),0,VLOOKUP(B40,GL_LTD!$B:$I,8,FALSE)) -> -82317.27
B41: 20402 | C41: מע'מ תשומות | D41: =IF(ISERROR(VLOOKUP(B41,GL_LTD!$B:$I,8,FALSE)),0,VLOOKUP(B41,GL_LTD!$B:$I,8,FALSE)) -> 214511.14
B42: 20405 | C42: מע"מ במקור (אינו משתתף בדוח מע"מ) | D42: =IF(ISERROR(VLOOKUP(B42,GL_LTD!$B:$I,8,FALSE)),0,VLOOKUP(B42,GL_LTD!$B:$I,8,FALSE)) -> -78917.27
B43: 20602 | C43: ניכוי מס במקור - ספקים | D43: =IF(ISERROR(VLOOKUP(B43,GL_LTD!$B:$I,8,FALSE)),0,VLOOKUP(B43,GL_LTD!$B:$I,8,FALSE)) -> -0.27
B44: 20603 | C44: ניכוי מס במקור - לקוחות | D44: =IF(ISERROR(VLOOKUP(B44,GL_LTD!$B:$I,8,FALSE)),0,VLOOKUP(B44,GL_LTD!$B:$I,8,FALSE)) -> 2925
B45: 20604 | C45: ניכוי מס במקור - ריבית | D45: =IF(ISERROR(VLOOKUP(B45,GL_LTD!$B:$I,8,FALSE)),0,VLOOKUP(B45,GL_LTD!$B:$I,8,FALSE)) -> 6.32
B46: 20606 | C46: מקדמות בגין עודפות 2021 | D46: =IF(ISERROR(VLOOKUP(B46,GL_LTD!$B:$I,8,FALSE)),0,VLOOKUP(B46,GL_LTD!$B:$I,8,FALSE)) -> 26450
B47: 20607 | C47: מקדמות בגין עודפות 2022 | D47: =IF(ISERROR(VLOOKUP(B47,GL_LTD!$B:$I,8,FALSE)),0,VLOOKUP(B47,GL_LTD!$B:$I,8,FALSE)) -> 0
B48: 20406 | C48: קיזוז מע"מ חשבונית עצמית (אינו משתתף בדוח מע"מ) | D48: =IF(ISERROR(VLOOKUP(B48,GL_LTD!$B:$I,8,FALSE)),0,VLOOKUP(B48,GL_LTD!$B:$I,8,FALSE)) -> 78917.27
B49: BS002 | C49: =IF(ISERROR(VLOOKUP(B49,Accounts_LTD!$B:$E,2,FALSE)),"",VLOOKUP(B49,Accounts_LTD!$B:$E,2,FALSE)) -> מעמ ספקים | D49: =IF(ISERROR(VLOOKUP(B49,GL_LTD!$B:$I,8,FALSE)),0,VLOOKUP(B49,GL_LTD!$B:$I,8,FALSE)) -> 6676.1238
C50: =IF(ISERROR(VLOOKUP(B50,Accounts_LTD!$B:$E,2,FALSE)),"",VLOOKUP(B50,Accounts_LTD!$B:$E,2,FALSE)) | D50: =IF(ISERROR(VLOOKUP(B50,GL_LTD!$B:$I,8,FALSE)),0,VLOOKUP(B50,GL_LTD!$B:$I,8,FALSE)) -> 0
C51: =IF(ISERROR(VLOOKUP(B51,Accounts_LTD!$B:$E,2,FALSE)),"",VLOOKUP(B51,Accounts_LTD!$B:$E,2,FALSE)) | D51: =IF(ISERROR(VLOOKUP(B51,GL_LTD!$B:$I,8,FALSE)),0,VLOOKUP(B51,GL_LTD!$B:$I,8,FALSE)) -> 0
D52: =SUM(D39:D51) -> 168251.04
C54: CHECK | D54: =D52-FS!C218 -> -4767.32
B57: Fixed Assets
B58: Account # | C58: Account name | D58: Amount (NIS) | E58: Amount ($)
B60: 560001 | C60: =IF(ISERROR(VLOOKUP(B60,Accounts_LTD!$B:$E,2,FALSE)),"",VLOOKUP(B60,Accounts_LTD!$B:$E,2,FALSE)) | D60: =IF(ISERROR(VLOOKUP(B60,GL_LTD!$B:$I,8,FALSE)),0,VLOOKUP(B60,GL_LTD!$B:$I,8,FALSE)) -> 0 | E60: =IF(ISERROR(VLOOKUP(B60,GL_LTD!$B:$I,6,FALSE)),"",VLOOKUP(B60,GL_LTD!$B:$I,6,FALSE))
B61: 560003 | C61: =IF(ISERROR(VLOOKUP(B61,Accounts_LTD!$B:$E,2,FALSE)),"",VLOOKUP(B61,Accounts_LTD!$B:$E,2,FALSE)) | D61: =IF(ISERROR(VLOOKUP(B61,GL_LTD!$B:$I,8,FALSE)),0,VLOOKUP(B61,GL_LTD!$B:$I,8,FALSE)) -> 0 | E61: =IF(ISERROR(VLOOKUP(B61,GL_LTD!$B:$I,6,FALSE)),"",VLOOKUP(B61,GL_LTD!$B:$I,6,FALSE))
C62: =IF(ISERROR(VLOOKUP(B62,Accounts_LTD!$B:$E,2,FALSE)),"",VLOOKUP(B62,Accounts_LTD!$B:$E,2,FALSE)) | D62: =SUM(D60:D61) -> 0 | E62: =SUM(E60:E61) -> 0
B64: dep form | C64: סה" כ עלות | D64: =#REF! -> #REF! | E64: =#REF! -> #REF!
C65: CHECK | D65: =D62-D64 -> #REF! | E65: =E62-E64 -> #REF!
B67: 580001 | C67: =IF(ISERROR(VLOOKUP(B67,Accounts_LTD!$B:$E,2,FALSE)),"",VLOOKUP(B67,Accounts_LTD!$B:$E,2,FALSE)) | D67: =IF(ISERROR(VLOOKUP(B67,GL_LTD!$B:$I,8,FALSE)),0,VLOOKUP(B67,GL_LTD!$B:$I,8,FALSE)) -> 0 | E67: =IF(ISERROR(VLOOKUP(B67,GL_LTD!$B:$I,6,FALSE)),"",VLOOKUP(B67,GL_LTD!$B:$I,6,FALSE))
B68: 580003 | C68: =IF(ISERROR(VLOOKUP(B68,Accounts_LTD!$B:$E,2,FALSE)),"",VLOOKUP(B68,Accounts_LTD!$B:$E,2,FALSE)) | D68: =IF(ISERROR(VLOOKUP(B68,GL_LTD!$B:$I,8,FALSE)),0,VLOOKUP(B68,GL_LTD!$B:$I,8,FALSE)) -> 0 | E68: =IF(ISERROR(VLOOKUP(B68,GL_LTD!$B:$I,6,FALSE)),"",VLOOKUP(B68,GL_LTD!$B:$I,6,FALSE))
C69: =IF(ISERROR(VLOOKUP(B69,Accounts_LTD!$B:$E,2,FALSE)),"",VLOOKUP(B69,Accounts_LTD!$B:$E,2,FALSE)) | D69: =SUM(D67:D68) -> 0 | E69: =SUM(E67:E68) -> 0
B71: dep form | C71: סה"כ פחנ"צ | D71: =-#REF! -> #REF! | E71: =-#REF! -> #REF!
C72: CHECK | D72: =D69-D71 -> #REF! | E72: =E69-E71 -> #REF!
D74: AJE DEPRECIATION | E74: AJE DEPRECIATION
B75: 979504 | C75: הוצאות פחת מחשבים | D75: =#REF! -> #REF! | E75: =#REF! -> #REF!
B80: dep form | C80: עלות מופחתת | D80: =D64+D71 -> #REF! | E80: =E64+E71 -> #REF!
C82: CHECK | D82: =D80-FS!C28 -> #REF! | E82: =E80-FS!E28 -> #REF!
B85: Employee & related
B86: Account # | C86: Account name | D86: Amount (NIS) | E86: פק' משכורת | F86: Diff | G86: Comments
B87: 20500 | C87: ביטוח לאומי ניכויים | D87: =IF(ISERROR(VLOOKUP(B87,GL_LTD!$B:$I,8,FALSE)),0,VLOOKUP(B87,GL_LTD!$B:$I,8,FALSE)) -> -145844 | E87: 145844 | F87: =D87+E87 -> 0
B88: 20501 | C88: מס הכנסה ניכויים | D88: =IF(ISERROR(VLOOKUP(B88,GL_LTD!$B:$I,8,FALSE)),0,VLOOKUP(B88,GL_LTD!$B:$I,8,FALSE)) -> -225229 | E88: 225229 | F88: =D88+E88 -> 0
