Workbook
Name \0: #REF!
Name \a: #REF!
Name \B: #REF!
Name \C: '[1]טורים 98'!$HJ$154
Name \D: #REF!
Name \E: '[1]טורים 98'!$HJ$155
Name \F: #REF!
Name \G: #REF!
Name \H: #REF!
Name \I: #REF!
Name \J: #REF!
Name \K: #REF!
Name \L: #REF!
Name \M: #REF!
Name \M2: #REF!
Name \N: #REF!
Name \O: #REF!
Name \P: #REF!
Name \Q: '[1]טורים 98'!$HJ$127
Name \R: #REF!
Name \S: #REF!
Name \T: #REF!
Name \U: #REF!
Name \V: #REF!
Name \W: #REF!
Name \X: '[1]טורים 98'!$HJ$146
Name \Y: #REF!
Name \Z: #REF!
Name _____________YR5: '[2]T3.1 Comp Allocation-FY 99'!#REF!
Name ____________YR5: '[2]T3.1 Comp Allocation-FY 99'!#REF!
Name ___________YR5: '[2]T3.1 Comp Allocation-FY 99'!#REF!
Name __________YR5: '[2]T3.1 Comp Allocation-FY 99'!#REF!
Name _________YR5: '[2]T3.1 Comp Allocation-FY 99'!#REF!
Name ________YR5: '[2]T3.1 Comp Allocation-FY 99'!#REF!
Name ______YR5: '[2]T3.1 Comp Allocation-FY 99'!#REF!
Name ____YR5: '[2]T3.1 Comp Allocation-FY 99'!#REF!
Name ___A1: #N/A
Name ___A2: #N/A
Name ___A3: #N/A
Name ___A4: #N/A
Name ___A5: #N/A
Name ___A6: #N/A
Name ___A7: #N/A
Name ___fsi1: #REF!
Name ___fsi10: #REF!
Name ___fsi11: #REF!
Name ___fsi19: #REF!
Name ___fsi2: #REF!
Name ___fsi20: #REF!
Name ___fsi3: #REF!
Name ___fsi30: #REF!
Name ___fsi5: #REF!
Name ___HOA1: #N/A
Name ___HOA2: #N/A
Name ___HOA3: #N/A
Name ___HOA4: #N/A
Name ___HOA5: #N/A
Name ___HOA6: #N/A
Name ___HOA7: #N/A
Name ___ILF2000: #REF!

Sheet Index
A1: Entity # | B1: Entity | D1: Account # | E1: Accounts | G1: Sub-Account # | H1: Sub-Account | J1: Sub-Department # | K1: Sub-Department | M1: Entity # | N1: Entity | O1: TB # | P1: Account/Department | Q1: Account # | R1: Sub-Account | S1: Sub-Account # | T1: Sub-Department | U1: Sub-Department # | V1: GL # | X1: Entity # | Y1: Entity | Z1: TB # | AA1: Account/Department | AB1: Account # | AC1: Sub-Account | AD1: Sub-Account # | AE1: Sub-Department | AF1: Sub-Department # | AG1: GL #
A2: 1 | B2: Ltd | D2: 1 | E2: Cash and Cash Equivalents | G2: 100 | H2: Accrued Expenses | J2: 41 | K2: Dev | M2: =_xlfn.SINGLE(_xlfn.XLOOKUP(N2,B:B,A:A,0,0,1)) -> 1 | N2: Ltd | O2: 10002 | P2: Cash and Cash Equivalents | Q2: =_xlfn.SINGLE(_xlfn.XLOOKUP(P2,E:E,D:D,0,0,1)) -> 1 | S2: =_xlfn.SINGLE(_xlfn.XLOOKUP(R2,H:H,G:G,0,0,1)) -> 0 | U2: =_xlfn.SINGLE(_xlfn.XLOOKUP(T2,K:K,J:J,0,0,1)) -> 0 | V2: =M2&O2&Q2&S2&U2 -> 110002100 | X2: =_xlfn.SINGLE(_xlfn.XLOOKUP(Y2,B:B,A:A,0,0,1)) -> 2 | Y2: Inc | Z2: 10000 | AA2: Cash and Cash Equivalents | AB2: =_xlfn.SINGLE(_xlfn.XLOOKUP(AA2,E:E,D:D,0,0,1)) -> 1 | AD2: =_xlfn.SINGLE(_xlfn.XLOOKUP(AC2,H:H,G:G,0,0,1)) -> 0 | AF2: =_xlfn.SINGLE(_xlfn.XLOOKUP(AE2,K:K,J:J,0,0,1)) -> 0 | AG2: =X2&Z2&AB2&AD2&AF2 -> 210000100
A3: 2 | B3: Inc | D3: 2 | E3: Accounts Receivable | G3: 101 | H3: Channel Marketing | J3: 42 | K3: Product | M3: =_xlfn.SINGLE(_xlfn.XLOOKUP(N3,B:B,A:A,0,0,1)) -> 1 | N3: Ltd | O3: 10003 | P3: Cash and Cash Equivalents | Q3: =_xlfn.SINGLE(_xlfn.XLOOKUP(P3,E:E,D:D,0,0,1)) -> 1 | S3: =_xlfn.SINGLE(_xlfn.XLOOKUP(R3,H:H,G:G,0,0,1)) -> 0 | U3: =_xlfn.SINGLE(_xlfn.XLOOKUP(T3,K:K,J:J,0,0,1)) -> 0 | V3: =M3&O3&Q3&S3&U3 -> 110003100 | X3: =_xlfn.SINGLE(_xlfn.XLOOKUP(Y3,B:B,A:A,0,0,1)) -> 2 | Y3: Inc | Z3: 10005 | AA3: Cash and Cash Equivalents | AB3: =_xlfn.SINGLE(_xlfn.XLOOKUP(AA3,E:E,D:D,0,0,1)) -> 1 | AC3: Restricted Cash | AD3: =_xlfn.SINGLE(_xlfn.XLOOKUP(AC3,H:H,G:G,0,0,1)) -> 120 | AF3: =_xlfn.SINGLE(_xlfn.XLOOKUP(AE3,K:K,J:J,0,0,1)) -> 0 | AG3: =X3&Z3&AB3&AD3&AF3 -> 21000511200
D4: 3 | E4: Prepaid expenses and other receivable | G4: 102 | H4: Contractors & Services | J4: 43 | K4: Labs | M4: =_xlfn.SINGLE(_xlfn.XLOOKUP(N4,B:B,A:A,0,0,1)) -> 1 | N4: Ltd | O4: 10004 | P4: Cash and Cash Equivalents | Q4: =_xlfn.SINGLE(_xlfn.XLOOKUP(P4,E:E,D:D,0,0,1)) -> 1 | S4: =_xlfn.SINGLE(_xlfn.XLOOKUP(R4,H:H,G:G,0,0,1)) -> 0 | U4: =_xlfn.SINGLE(_xlfn.XLOOKUP(T4,K:K,J:J,0,0,1)) -> 0 | V4: =M4&O4&Q4&S4&U4 -> 110004100 | X4: =_xlfn.SINGLE(_xlfn.XLOOKUP(Y4,B:B,A:A,0,0,1)) -> 2 | Y4: Inc | Z4: 10010 | AA4: Cash and Cash Equivalents | AB4: =_xlfn.SINGLE(_xlfn.XLOOKUP(AA4,E:E,D:D,0,0,1)) -> 1 | AC4: Short Term Deposits | AD4: =_xlfn.SINGLE(_xlfn.XLOOKUP(AC4,H:H,G:G,0,0,1)) -> 122 | AF4: =_xlfn.SINGLE(_xlfn.XLOOKUP(AE4,K:K,J:J,0,0,1)) -> 0 | AG4: =X4&Z4&AB4&AD4&AF4 -> 21001011220
D5: 4 | E5: Fixed Assets | G5: 103 | H5: Credit Cards | M5: =_xlfn.SINGLE(_xlfn.XLOOKUP(N5,B:B,A:A,0,0,1)) -> 1 | N5: Ltd | O5: 10007 | P5: Cash and Cash Equivalents | Q5: =_xlfn.SINGLE(_xlfn.XLOOKUP(P5,E:E,D:D,0,0,1)) -> 1 | S5: =_xlfn.SINGLE(_xlfn.XLOOKUP(R5,H:H,G:G,0,0,1)) -> 0 | U5: =_xlfn.SINGLE(_xlfn.XLOOKUP(T5,K:K,J:J,0,0,1)) -> 0 | V5: =M5&O5&Q5&S5&U5 -> 110007100 | X5: =_xlfn.SINGLE(_xlfn.XLOOKUP(Y5,B:B,A:A,0,0,1)) -> 2 | Y5: Inc | Z5: 10011 | AA5: Cash and Cash Equivalents | AB5: =_xlfn.SINGLE(_xlfn.XLOOKUP(AA5,E:E,D:D,0,0,1)) -> 1 | AC5: Short Term Deposits | AD5: =_xlfn.SINGLE(_xlfn.XLOOKUP(AC5,H:H,G:G,0,0,1)) -> 122 | AF5: =_xlfn.SINGLE(_xlfn.XLOOKUP(AE5,K:K,J:J,0,0,1)) -> 0 | AG5: =X5&Z5&AB5&AD5&AF5 -> 21001111220
D6: 5 | E6: Intercompany | G6: 104 | H6: Deposits | M6: =_xlfn.SINGLE(_xlfn.XLOOKUP(N6,B:B,A:A,0,0,1)) -> 1 | N6: Ltd | O6: 10008 | P6: Prepaid expenses and other receivable | Q6: =_xlfn.SINGLE(_xlfn.XLOOKUP(P6,E:E,D:D,0,0,1)) -> 3 | R6: Deposits | S6: =_xlfn.SINGLE(_xlfn.XLOOKUP(R6,H:H,G:G,0,0,1)) -> 104 | U6: =_xlfn.SINGLE(_xlfn.XLOOKUP(T6,K:K,J:J,0,0,1)) -> 0 | V6: =M6&O6&Q6&S6&U6 -> 11000831040 | X6: =_xlfn.SINGLE(_xlfn.XLOOKUP(Y6,B:B,A:A,0,0,1)) -> 2 | Y6: Inc | Z6: 10999 | AA6: Overhead | AB6: =_xlfn.SINGLE(_xlfn.XLOOKUP(AA6,E:E,D:D,0,0,1)) -> 99 | AD6: =_xlfn.SINGLE(_xlfn.XLOOKUP(AC6,H:H,G:G,0,0,1)) -> 0 | AF6: =_xlfn.SINGLE(_xlfn.XLOOKUP(AE6,K:K,J:J,0,0,1)) -> 0 | AG6: =X6&Z6&AB6&AD6&AF6 -> 2109999900
D7: 6 | E7: Accounts Payable | G7: 105 | H7: Digital Marketing | M7: =_xlfn.SINGLE(_xlfn.XLOOKUP(N7,B:B,A:A,0,0,1)) -> 1 | N7: Ltd | O7: 10012 | P7: Prepaid expenses and other receivable | Q7: =_xlfn.SINGLE(_xlfn.XLOOKUP(P7,E:E,D:D,0,0,1)) -> 3 | R7: Deposits | S7: =_xlfn.SINGLE(_xlfn.XLOOKUP(R7,H:H,G:G,0,0,1)) -> 104 | U7: =_xlfn.SINGLE(_xlfn.XLOOKUP(T7,K:K,J:J,0,0,1)) -> 0 | V7: =M7&O7&Q7&S7&U7 -> 11001231040 | X7: =_xlfn.SINGLE(_xlfn.XLOOKUP(Y7,B:B,A:A,0,0,1)) -> 2 | Y7: Inc | Z7: 11000 | AA7: Accounts Receivable | AB7: =_xlfn.SINGLE(_xlfn.XLOOKUP(AA7,E:E,D:D,0,0,1)) -> 2 | AD7: =_xlfn.SINGLE(_xlfn.XLOOKUP(AC7,H:H,G:G,0,0,1)) -> 0 | AF7: =_xlfn.SINGLE(_xlfn.XLOOKUP(AE7,K:K,J:J,0,0,1)) -> 0 | AG7: =X7&Z7&AB7&AD7&AF7 -> 211000200
D8: 7 | E8: Accrued expenses and other payable | G8: 106 | H8: Events & Conferences | M8: =_xlfn.SINGLE(_xlfn.XLOOKUP(N8,B:B,A:A,0,0,1)) -> 1 | N8: Ltd | O8: 10013 | P8: Prepaid expenses and other receivable | Q8: =_xlfn.SINGLE(_xlfn.XLOOKUP(P8,E:E,D:D,0,0,1)) -> 3 | R8: Deposits | S8: =_xlfn.SINGLE(_xlfn.XLOOKUP(R8,H:H,G:G,0,0,1)) -> 104 | U8: =_xlfn.SINGLE(_xlfn.XLOOKUP(T8,K:K,J:J,0,0,1)) -> 0 | V8: =M8&O8&Q8&S8&U8 -> 11001331040 | X8: =_xlfn.SINGLE(_xlfn.XLOOKUP(Y8,B:B,A:A,0,0,1)) -> 2 | Y8: Inc | Z8: 12500 | AA8: Prepaid expenses and other receivable | AB8: =_xlfn.SINGLE(_xlfn.XLOOKUP(AA8,E:E,D:D,0,0,1)) -> 3 | AC8: Prepaid Expenses | AD8: =_xlfn.SINGLE(_xlfn.XLOOKUP(AC8,H:H,G:G,0,0,1)) -> 118 | AF8: =_xlfn.SINGLE(_xlfn.XLOOKUP(AE8,K:K,J:J,0,0,1)) -> 0 | AG8: =X8&Z8&AB8&AD8&AF8 -> 21250031180
D9: 8 | E9: Employees Payable | G9: 107 | H9: Field Marketing | M9: =_xlfn.SINGLE(_xlfn.XLOOKUP(N9,B:B,A:A,0,0,1)) -> 1 | N9: Ltd | O9: 10014 | P9: Cash and Cash Equivalents | Q9: =_xlfn.SINGLE(_xlfn.XLOOKUP(P9,E:E,D:D,0,0,1)) -> 1 | S9: =_xlfn.SINGLE(_xlfn.XLOOKUP(R9,H:H,G:G,0,0,1)) -> 0 | U9: =_xlfn.SINGLE(_xlfn.XLOOKUP(T9,K:K,J:J,0,0,1)) -> 0 | V9: =M9&O9&Q9&S9&U9 -> 110014100 | X9: =_xlfn.SINGLE(_xlfn.XLOOKUP(Y9,B:B,A:A,0,0,1)) -> 2 | Y9: Inc | Z9: 12505 | AA9: Prepaid expenses and other receivable | AB9: =_xlfn.SINGLE(_xlfn.XLOOKUP(AA9,E:E,D:D,0,0,1)) -> 3 | AC9: Prepaid Expenses | AD9: =_xlfn.SINGLE(_xlfn.XLOOKUP(AC9,H:H,G:G,0,0,1)) -> 118 | AF9: =_xlfn.SINGLE(_xlfn.XLOOKUP(AE9,K:K,J:J,0,0,1)) -> 0 | AG9: =X9&Z9&AB9&AD9&AF9 -> 21250531180
D10: 9 | E10: Deferred Revenue | G10: 108 | H10: Hosting | M10: =_xlfn.SINGLE(_xlfn.XLOOKUP(N10,B:B,A:A,0,0,1)) -> 1 | N10: Ltd | O10: 10016 | P10: Cash and Cash Equivalents | Q10: =_xlfn.SINGLE(_xlfn.XLOOKUP(P10,E:E,D:D,0,0,1)) -> 1 | R10: Short Term deposits | S10: =_xlfn.SINGLE(_xlfn.XLOOKUP(R10,H:H,G:G,0,0,1)) -> 122 | U10: =_xlfn.SINGLE(_xlfn.XLOOKUP(T10,K:K,J:J,0,0,1)) -> 0 | V10: =M10&O10&Q10&S10&U10 -> 11001611220 | X10: =_xlfn.SINGLE(_xlfn.XLOOKUP(Y10,B:B,A:A,0,0,1)) -> 2 | Y10: Inc | Z10: 12510 | AA10: Prepaid expenses and other receivable | AB10: =_xlfn.SINGLE(_xlfn.XLOOKUP(AA10,E:E,D:D,0,0,1)) -> 3 | AC10: Prepaid Expenses | AD10: =_xlfn.SINGLE(_xlfn.XLOOKUP(AC10,H:H,G:G,0,0,1)) -> 118 | AF10: =_xlfn.SINGLE(_xlfn.XLOOKUP(AE10,K:K,J:J,0,0,1)) -> 0 | AG10: =X10&Z10&AB10&AD10&AF10 -> 21251031180
D11: 10 | E11: Capital Stock | G11: 109 | H11: Institutions | M11: =_xlfn.SINGLE(_xlfn.XLOOKUP(N11,B:B,A:A,0,0,1)) -> 1 | N11: Ltd | O11: 10017 | P11: Prepaid expenses and other receivable | Q11: =_xlfn.SINGLE(_xlfn.XLOOKUP(P11,E:E,D:D,0,0,1)) -> 3 | R11: Deposits | S11: =_xlfn.SINGLE(_xlfn.XLOOKUP(R11,H:H,G:G,0,0,1)) -> 104 | U11: =_xlfn.SINGLE(_xlfn.XLOOKUP(T11,K:K,J:J,0,0,1)) -> 0 | V11: =M11&O11&Q11&S11&U11 -> 11001731040 | X11: =_xlfn.SINGLE(_xlfn.XLOOKUP(Y11,B:B,A:A,0,0,1)) -> 2 | Y11: Inc | Z11: 12515 | AA11: Prepaid expenses and other receivable | AB11: =_xlfn.SINGLE(_xlfn.XLOOKUP(AA11,E:E,D:D,0,0,1)) -> 3 | AC11: Prepaid Expenses | AD11: =_xlfn.SINGLE(_xlfn.XLOOKUP(AC11,H:H,G:G,0,0,1)) -> 118 | AF11: =_xlfn.SINGLE(_xlfn.XLOOKUP(AE11,K:K,J:J,0,0,1)) -> 0 | AG11: =X11&Z11&AB11&AD11&AF11 -> 21251531180
D12: 11 | E12: Additional Paid In Capital | G12: 110 | H12: Legal Services | M12: =_xlfn.SINGLE(_xlfn.XLOOKUP(N12,B:B,A:A,0,0,1)) -> 1 | N12: Ltd | O12: 10018 | P12: Prepaid expenses and other receivable | Q12: =_xlfn.SINGLE(_xlfn.XLOOKUP(P12,E:E,D:D,0,0,1)) -> 3 | R12: Deposits | S12: =_xlfn.SINGLE(_xlfn.XLOOKUP(R12,H:H,G:G,0,0,1)) -> 104 | U12: =_xlfn.SINGLE(_xlfn.XLOOKUP(T12,K:K,J:J,0,0,1)) -> 0 | V12: =M12&O12&Q12&S12&U12 -> 11001831040 | X12: =_xlfn.SINGLE(_xlfn.XLOOKUP(Y12,B:B,A:A,0,0,1)) -> 2 | Y12: Inc | Z12: 12516 | AA12: Prepaid expenses and other receivable | AB12: =_xlfn.SINGLE(_xlfn.XLOOKUP(AA12,E:E,D:D,0,0,1)) -> 3 | AC12: Prepaid R&D exp. | AD12: =_xlfn.SINGLE(_xlfn.XLOOKUP(AC12,H:H,G:G,0,0,1)) -> 129 | AF12: =_xlfn.SINGLE(_xlfn.XLOOKUP(AE12,K:K,J:J,0,0,1)) -> 0 | AG12: =X12&Z12&AB12&AD12&AF12 -> 21251631290
D13: 12 | E13: Accumulated Comprehensive Income | G13: 111 | H13: Other Finance | M13: =_xlfn.SINGLE(_xlfn.XLOOKUP(N13,B:B,A:A,0,0,1)) -> 1 | N13: Ltd | O13: 10019 | P13: Prepaid expenses and other receivable | Q13: =_xlfn.SINGLE(_xlfn.XLOOKUP(P13,E:E,D:D,0,0,1)) -> 3 | R13: Deposits | S13: =_xlfn.SINGLE(_xlfn.XLOOKUP(R13,H:H,G:G,0,0,1)) -> 104 | U13: =_xlfn.SINGLE(_xlfn.XLOOKUP(T13,K:K,J:J,0,0,1)) -> 0 | V13: =M13&O13&Q13&S13&U13 -> 11001931040 | X13: =_xlfn.SINGLE(_xlfn.XLOOKUP(Y13,B:B,A:A,0,0,1)) -> 2 | Y13: Inc | Z13: 16000 | AA13: Intercompany | AB13: =_xlfn.SINGLE(_xlfn.XLOOKUP(AA13,E:E,D:D,0,0,1)) -> 5 | AD13: =_xlfn.SINGLE(_xlfn.XLOOKUP(AC13,H:H,G:G,0,0,1)) -> 0 | AF13: =_xlfn.SINGLE(_xlfn.XLOOKUP(AE13,K:K,J:J,0,0,1)) -> 0 | AG13: =X13&Z13&AB13&AD13&AF13 -> 216000500
D14: 13 | E14: Retained Loss | G14: 112 | H14: Other HR | M14: =_xlfn.SINGLE(_xlfn.XLOOKUP(N14,B:B,A:A,0,0,1)) -> 1 | N14: Ltd | O14: 10020 | P14: Prepaid expenses and other receivable | Q14: =_xlfn.SINGLE(_xlfn.XLOOKUP(P14,E:E,D:D,0,0,1)) -> 3 | R14: Deposits | S14: =_xlfn.SINGLE(_xlfn.XLOOKUP(R14,H:H,G:G,0,0,1)) -> 104 | U14: =_xlfn.SINGLE(_xlfn.XLOOKUP(T14,K:K,J:J,0,0,1)) -> 0 | V14: =M14&O14&Q14&S14&U14 -> 11002031040 | X14: =_xlfn.SINGLE(_xlfn.XLOOKUP(Y14,B:B,A:A,0,0,1)) -> 2 | Y14: Inc | Z14: 16025 | AA14: Intercompany | AB14: =_xlfn.SINGLE(_xlfn.XLOOKUP(AA14,E:E,D:D,0,0,1)) -> 5 | AD14: =_xlfn.SINGLE(_xlfn.XLOOKUP(AC14,H:H,G:G,0,0,1)) -> 0 | AF14: =_xlfn.SINGLE(_xlfn.XLOOKUP(AE14,K:K,J:J,0,0,1)) -> 0 | AG14: =X14&Z14&AB14&AD14&AF14 -> 216025500
D15: 14 | E15: Other long term liabilities | G15: 113 | H15: Other Marketing | M15: =_xlfn.SINGLE(_xlfn.XLOOKUP(N15,B:B,A:A,0,0,1)) -> 1 | N15: Ltd | O15: 10023 | P15: Cash and Cash Equivalents | Q15: =_xlfn.SINGLE(_xlfn.XLOOKUP(P15,E:E,D:D,0,0,1)) -> 1 | S15: =_xlfn.SINGLE(_xlfn.XLOOKUP(R15,H:H,G:G,0,0,1)) -> 0 | U15: =_xlfn.SINGLE(_xlfn.XLOOKUP(T15,K:K,J:J,0,0,1)) -> 0 | V15: =M15&O15&Q15&S15&U15 -> 110023100 | X15: =_xlfn.SINGLE(_xlfn.XLOOKUP(Y15,B:B,A:A,0,0,1)) -> 2 | Y15: Inc | Z15: 16030 | AA15: Capital Stock | AB15: =_xlfn.SINGLE(_xlfn.XLOOKUP(AA15,E:E,D:D,0,0,1)) -> 10 | AD15: =_xlfn.SINGLE(_xlfn.XLOOKUP(AC15,H:H,G:G,0,0,1)) -> 0 | AF15: =_xlfn.SINGLE(_xlfn.XLOOKUP(AE15,K:K,J:J,0,0,1)) -> 0 | AG15: =X15&Z15&AB15&AD15&AF15 -> 2160301000
D16: 15 | E16: Long term deferred revenue | G16: 114 | H16: Other R&D | M16: =_xlfn.SINGLE(_xlfn.XLOOKUP(N16,B:B,A:A,0,0,1)) -> 1 | N16: Ltd | O16: 10024 | P16: Cash and Cash Equivalents | Q16: =_xlfn.SINGLE(_xlfn.XLOOKUP(P16,E:E,D:D,0,0,1)) -> 1 | S16: =_xlfn.SINGLE(_xlfn.XLOOKUP(R16,H:H,G:G,0,0,1)) -> 0 | U16: =_xlfn.SINGLE(_xlfn.XLOOKUP(T16,K:K,J:J,0,0,1)) -> 0 | V16: =M16&O16&Q16&S16&U16 -> 110024100 | X16: =_xlfn.SINGLE(_xlfn.XLOOKUP(Y16,B:B,A:A,0,0,1)) -> 2 | Y16: Inc | Z16: 16050 | AA16: Intercompany | AB16: =_xlfn.SINGLE(_xlfn.XLOOKUP(AA16,E:E,D:D,0,0,1)) -> 5 | AD16: =_xlfn.SINGLE(_xlfn.XLOOKUP(AC16,H:H,G:G,0,0,1)) -> 0 | AF16: =_xlfn.SINGLE(_xlfn.XLOOKUP(AE16,K:K,J:J,0,0,1)) -> 0 | AG16: =X16&Z16&AB16&AD16&AF16 -> 216050500
D17: 16 | E17: Current Right-of-use asset | G17: 115 | H17: Patent | M17: =_xlfn.SINGLE(_xlfn.XLOOKUP(N17,B:B,A:A,0,0,1)) -> 1 | N17: Ltd | O17: 10025 | P17: Cash and Cash Equivalents | Q17: =_xlfn.SINGLE(_xlfn.XLOOKUP(P17,E:E,D:D,0,0,1)) -> 1 | S17: =_xlfn.SINGLE(_xlfn.XLOOKUP(R17,H:H,G:G,0,0,1)) -> 0 | U17: =_xlfn.SINGLE(_xlfn.XLOOKUP(T17,K:K,J:J,0,0,1)) -> 0 | V17: =M17&O17&Q17&S17&U17 -> 110025100 | X17: =_xlfn.SINGLE(_xlfn.XLOOKUP(Y17,B:B,A:A,0,0,1)) -> 2 | Y17: Inc | Z17: 20000 | AA17: Accounts Payable | AB17: =_xlfn.SINGLE(_xlfn.XLOOKUP(AA17,E:E,D:D,0,0,1)) -> 6 | AD17: =_xlfn.SINGLE(_xlfn.XLOOKUP(AC17,H:H,G:G,0,0,1)) -> 0 | AF17: =_xlfn.SINGLE(_xlfn.XLOOKUP(AE17,K:K,J:J,0,0,1)) -> 0 | AG17: =X17&Z17&AB17&AD17&AF17 -> 220000600
D18: 17 | E18: Long-term Right-of-use asset | G18: 116 | H18: Payroll & Payroll related | M18: =_xlfn.SINGLE(_xlfn.XLOOKUP(N18,B:B,A:A,0,0,1)) -> 1 | N18: Ltd | O18: 11001 | P18: Cash and Cash Equivalents | Q18: =_xlfn.SINGLE(_xlfn.XLOOKUP(P18,E:E,D:D,0,0,1)) -> 1 | S18: =_xlfn.SINGLE(_xlfn.XLOOKUP(R18,H:H,G:G,0,0,1)) -> 0 | U18: =_xlfn.SINGLE(_xlfn.XLOOKUP(T18,K:K,J:J,0,0,1)) -> 0 | V18: =M18&O18&Q18&S18&U18 -> 111001100 | X18: =_xlfn.SINGLE(_xlfn.XLOOKUP(Y18,B:B,A:A,0,0,1)) -> 2 | Y18: Inc | Z18: 20105 | AA18: Accounts Payable | AB18: =_xlfn.SINGLE(_xlfn.XLOOKUP(AA18,E:E,D:D,0,0,1)) -> 6 | AC18: Credit Cards | AD18: =_xlfn.SINGLE(_xlfn.XLOOKUP(AC18,H:H,G:G,0,0,1)) -> 103 | AF18: =_xlfn.SINGLE(_xlfn.XLOOKUP(AE18,K:K,J:J,0,0,1)) -> 0 | AG18: =X18&Z18&AB18&AD18&AF18 -> 22010561030
D19: 18 | E19: Current Lease liability | G19: 117 | H19: Prepaid Commissions | M19: =_xlfn.SINGLE(_xlfn.XLOOKUP(N19,B:B,A:A,0,0,1)) -> 1 | N19: Ltd | O19: 11002 | P19: Cash and Cash Equivalents | Q19: =_xlfn.SINGLE(_xlfn.XLOOKUP(P19,E:E,D:D,0,0,1)) -> 1 | S19: =_xlfn.SINGLE(_xlfn.XLOOKUP(R19,H:H,G:G,0,0,1)) -> 0 | U19: =_xlfn.SINGLE(_xlfn.XLOOKUP(T19,K:K,J:J,0,0,1)) -> 0 | V19: =M19&O19&Q19&S19&U19 -> 111002100 | X19: =_xlfn.SINGLE(_xlfn.XLOOKUP(Y19,B:B,A:A,0,0,1)) -> 2 | Y19: Inc | Z19: 21010 | AA19: Employees Payable | AB19: =_xlfn.SINGLE(_xlfn.XLOOKUP(AA19,E:E,D:D,0,0,1)) -> 8 | AD19: =_xlfn.SINGLE(_xlfn.XLOOKUP(AC19,H:H,G:G,0,0,1)) -> 0 | AF19: =_xlfn.SINGLE(_xlfn.XLOOKUP(AE19,K:K,J:J,0,0,1)) -> 0 | AG19: =X19&Z19&AB19&AD19&AF19 -> 221010800
D20: 19 | E20: Long-term Lease liability | G20: 118 | H20: Prepaid Expenses | M20: =_xlfn.SINGLE(_xlfn.XLOOKUP(N20,B:B,A:A,0,0,1)) -> 1 | N20: Ltd | O20: 11010 | P20: Cash and Cash Equivalents | Q20: =_xlfn.SINGLE(_xlfn.XLOOKUP(P20,E:E,D:D,0,0,1)) -> 1 | S20: =_xlfn.SINGLE(_xlfn.XLOOKUP(R20,H:H,G:G,0,0,1)) -> 0 | U20: =_xlfn.SINGLE(_xlfn.XLOOKUP(T20,K:K,J:J,0,0,1)) -> 0 | V20: =M20&O20&Q20&S20&U20 -> 111010100 | X20: =_xlfn.SINGLE(_xlfn.XLOOKUP(Y20,B:B,A:A,0,0,1)) -> 2 | Y20: Inc | Z20: 21020 | AA20: Employees Payable | AB20: =_xlfn.SINGLE(_xlfn.XLOOKUP(AA20,E:E,D:D,0,0,1)) -> 8 | AD20: =_xlfn.SINGLE(_xlfn.XLOOKUP(AC20,H:H,G:G,0,0,1)) -> 0 | AF20: =_xlfn.SINGLE(_xlfn.XLOOKUP(AE20,K:K,J:J,0,0,1)) -> 0 | AG20: =X20&Z20&AB20&AD20&AF20 -> 221020800
D21: 20 | E21: Revenue | G21: 119 | H21: Recruiting | M21: =_xlfn.SINGLE(_xlfn.XLOOKUP(N21,B:B,A:A,0,0,1)) -> 1 | N21: Ltd | O21: 11011 | P21: Cash and Cash Equivalents | Q21: =_xlfn.SINGLE(_xlfn.XLOOKUP(P21,E:E,D:D,0,0,1)) -> 1 | S21: =_xlfn.SINGLE(_xlfn.XLOOKUP(R21,H:H,G:G,0,0,1)) -> 0 | U21: =_xlfn.SINGLE(_xlfn.XLOOKUP(T21,K:K,J:J,0,0,1)) -> 0 | V21: =M21&O21&Q21&S21&U21 -> 111011100 | X21: =_xlfn.SINGLE(_xlfn.XLOOKUP(Y21,B:B,A:A,0,0,1)) -> 2 | Y21: Inc | Z21: 21025 | AA21: Employees Payable | AB21: =_xlfn.SINGLE(_xlfn.XLOOKUP(AA21,E:E,D:D,0,0,1)) -> 8 | AD21: =_xlfn.SINGLE(_xlfn.XLOOKUP(AC21,H:H,G:G,0,0,1)) -> 0 | AF21: =_xlfn.SINGLE(_xlfn.XLOOKUP(AE21,K:K,J:J,0,0,1)) -> 0 | AG21: =X21&Z21&AB21&AD21&AF21 -> 221025800
D22: 30 | E22: Cost of Sales | G22: 120 | H22: Restricted Cash | M22: =_xlfn.SINGLE(_xlfn.XLOOKUP(N22,B:B,A:A,0,0,1)) -> 1 | N22: Ltd | O22: 11012 | P22: Cash and Cash Equivalents | Q22: =_xlfn.SINGLE(_xlfn.XLOOKUP(P22,E:E,D:D,0,0,1)) -> 1 | S22: =_xlfn.SINGLE(_xlfn.XLOOKUP(R22,H:H,G:G,0,0,1)) -> 0 | U22: =_xlfn.SINGLE(_xlfn.XLOOKUP(T22,K:K,J:J,0,0,1)) -> 0 | V22: =M22&O22&Q22&S22&U22 -> 111012100 | X22: =_xlfn.SINGLE(_xlfn.XLOOKUP(Y22,B:B,A:A,0,0,1)) -> 2 | Y22: Inc | Z22: 21030 | AA22: Accrued expenses and other payable | AB22: =_xlfn.SINGLE(_xlfn.XLOOKUP(AA22,E:E,D:D,0,0,1)) -> 7 | AD22: =_xlfn.SINGLE(_xlfn.XLOOKUP(AC22,H:H,G:G,0,0,1)) -> 0 | AF22: =_xlfn.SINGLE(_xlfn.XLOOKUP(AE22,K:K,J:J,0,0,1)) -> 0 | AG22: =X22&Z22&AB22&AD22&AF22 -> 221030700
D23: 40 | E23: R&D | G23: 121 | H23: Security | M23: =_xlfn.SINGLE(_xlfn.XLOOKUP(N23,B:B,A:A,0,0,1)) -> 1 | N23: Ltd | O23: 11013 | P23: Cash and Cash Equivalents | Q23: =_xlfn.SINGLE(_xlfn.XLOOKUP(P23,E:E,D:D,0,0,1)) -> 1 | S23: =_xlfn.SINGLE(_xlfn.XLOOKUP(R23,H:H,G:G,0,0,1)) -> 0 | U23: =_xlfn.SINGLE(_xlfn.XLOOKUP(T23,K:K,J:J,0,0,1)) -> 0 | V23: =M23&O23&Q23&S23&U23 -> 111013100 | X23: =_xlfn.SINGLE(_xlfn.XLOOKUP(Y23,B:B,A:A,0,0,1)) -> 2 | Y23: Inc | Z23: 22005 | AA23: Deferred Revenue | AB23: =_xlfn.SINGLE(_xlfn.XLOOKUP(AA23,E:E,D:D,0,0,1)) -> 9 | AD23: =_xlfn.SINGLE(_xlfn.XLOOKUP(AC23,H:H,G:G,0,0,1)) -> 0 | AF23: =_xlfn.SINGLE(_xlfn.XLOOKUP(AE23,K:K,J:J,0,0,1)) -> 0 | AG23: =X23&Z23&AB23&AD23&AF23 -> 222005900
D24: 50 | E24: Sales | G24: 122 | H24: Short Term deposits | M24: =_xlfn.SINGLE(_xlfn.XLOOKUP(N24,B:B,A:A,0,0,1)) -> 1 | N24: Ltd | O24: 11014 | P24: Cash and Cash Equivalents | Q24: =_xlfn.SINGLE(_xlfn.XLOOKUP(P24,E:E,D:D,0,0,1)) -> 1 | S24: =_xlfn.SINGLE(_xlfn.XLOOKUP(R24,H:H,G:G,0,0,1)) -> 0 | U24: =_xlfn.SINGLE(_xlfn.XLOOKUP(T24,K:K,J:J,0,0,1)) -> 0 | V24: =M24&O24&Q24&S24&U24 -> 111014100 | X24: 2 | Y24: Inc | Z24: 27100 | AA24: Long term deferred revenue | AB24: =_xlfn.SINGLE(_xlfn.XLOOKUP(AA24,E:E,D:D,0,0,1)) -> 15 | AD24: 0 | AF24: 0 | AG24: =X24&Z24&AB24&AD24&AF24 -> 2271001500
D25: 60 | E25: Marketing | G25: 123 | H25: Software | M25: =_xlfn.SINGLE(_xlfn.XLOOKUP(N25,B:B,A:A,0,0,1)) -> 1 | N25: Ltd | O25: 21002 | P25: Accounts Payable | Q25: =_xlfn.SINGLE(_xlfn.XLOOKUP(P25,E:E,D:D,0,0,1)) -> 6 | R25: Credit Cards | S25: =_xlfn.SINGLE(_xlfn.XLOOKUP(R25,H:H,G:G,0,0,1)) -> 103 | U25: =_xlfn.SINGLE(_xlfn.XLOOKUP(T25,K:K,J:J,0,0,1)) -> 0 | V25: =M25&O25&Q25&S25&U25 -> 12100261030 | X25: =_xlfn.SINGLE(_xlfn.XLOOKUP(Y25,B:B,A:A,0,0,1)) -> 2 | Y25: Inc | Z25: 24000 | AA25: Employees Payable | AB25: =_xlfn.SINGLE(_xlfn.XLOOKUP(AA25,E:E,D:D,0,0,1)) -> 8 | AD25: =_xlfn.SINGLE(_xlfn.XLOOKUP(AC25,H:H,G:G,0,0,1)) -> 0 | AF25: =_xlfn.SINGLE(_xlfn.XLOOKUP(AE25,K:K,J:J,0,0,1)) -> 0 | AG25: =X25&Z25&AB25&AD25&AF25 -> 224000800
D26: 70 | E26: G&A | G26: 124 | H26: T&E | M26: =_xlfn.SINGLE(_xlfn.XLOOKUP(N26,B:B,A:A,0,0,1)) -> 1 | N26: Ltd | O26: 21003 | P26: Accounts Payable | Q26: =_xlfn.SINGLE(_xlfn.XLOOKUP(P26,E:E,D:D,0,0,1)) -> 6 | R26: Credit Cards | S26: =_xlfn.SINGLE(_xlfn.XLOOKUP(R26,H:H,G:G,0,0,1)) -> 103 | U26: =_xlfn.SINGLE(_xlfn.XLOOKUP(T26,K:K,J:J,0,0,1)) -> 0 | V26: =M26&O26&Q26&S26&U26 -> 12100361030 | X26: =_xlfn.SINGLE(_xlfn.XLOOKUP(Y26,B:B,A:A,0,0,1)) -> 2 | Y26: Inc | Z26: 24017 | AA26: Employees Payable | AB26: =_xlfn.SINGLE(_xlfn.XLOOKUP(AA26,E:E,D:D,0,0,1)) -> 8 | AD26: =_xlfn.SINGLE(_xlfn.XLOOKUP(AC26,H:H,G:G,0,0,1)) -> 0 | AF26: =_xlfn.SINGLE(_xlfn.XLOOKUP(AE26,K:K,J:J,0,0,1)) -> 0 | AG26: =X26&Z26&AB26&AD26&AF26 -> 224017800
D27: 80 | E27: Other | G27: 125 | H27: Other Sales | M27: =_xlfn.SINGLE(_xlfn.XLOOKUP(N27,B:B,A:A,0,0,1)) -> 1 | N27: Ltd | O27: 21006 | P27: Accounts Payable | Q27: =_xlfn.SINGLE(_xlfn.XLOOKUP(P27,E:E,D:D,0,0,1)) -> 6 | R27: Credit Cards | S27: =_xlfn.SINGLE(_xlfn.XLOOKUP(R27,H:H,G:G,0,0,1)) -> 103 | U27: =_xlfn.SINGLE(_xlfn.XLOOKUP(T27,K:K,J:J,0,0,1)) -> 0 | V27: =M27&O27&Q27&S27&U27 -> 12100661030 | X27: =_xlfn.SINGLE(_xlfn.XLOOKUP(Y27,B:B,A:A,0,0,1)) -> 2 | Y27: Inc | Z27: 24018 | AA27: Employees Payable | AB27: =_xlfn.SINGLE(_xlfn.XLOOKUP(AA27,E:E,D:D,0,0,1)) -> 8 | AD27: =_xlfn.SINGLE(_xlfn.XLOOKUP(AC27,H:H,G:G,0,0,1)) -> 0 | AF27: =_xlfn.SINGLE(_xlfn.XLOOKUP(AE27,K:K,J:J,0,0,1)) -> 0 | AG27: =X27&Z27&AB27&AD27&AF27 -> 224018800
D28: 90 | E28: Finance | G28: 126 | H28: Referral Fees | M28: =_xlfn.SINGLE(_xlfn.XLOOKUP(N28,B:B,A:A,0,0,1)) -> 1 | N28: Ltd | O28: 21007 | P28: Accounts Payable | Q28: =_xlfn.SINGLE(_xlfn.XLOOKUP(P28,E:E,D:D,0,0,1)) -> 6 | R28: Credit Cards | S28: =_xlfn.SINGLE(_xlfn.XLOOKUP(R28,H:H,G:G,0,0,1)) -> 103 | U28: =_xlfn.SINGLE(_xlfn.XLOOKUP(T28,K:K,J:J,0,0,1)) -> 0 | V28: =M28&O28&Q28&S28&U28 -> 12100761030 | X28: =_xlfn.SINGLE(_xlfn.XLOOKUP(Y28,B:B,A:A,0,0,1)) -> 2 | Y28: Inc | Z28: 25503 | AA28: Accrued expenses and other payable | AB28: =_xlfn.SINGLE(_xlfn.XLOOKUP(AA28,E:E,D:D,0,0,1)) -> 7 | AC28: Institutions | AD28: =_xlfn.SINGLE(_xlfn.XLOOKUP(AC28,H:H,G:G,0,0,1)) -> 109 | AF28: =_xlfn.SINGLE(_xlfn.XLOOKUP(AE28,K:K,J:J,0,0,1)) -> 0 | AG28: =X28&Z28&AB28&AD28&AF28 -> 22550371090
D29: 88 | E29: Tax | G29: 127 | H29: Other CoS | M29: =_xlfn.SINGLE(_xlfn.XLOOKUP(N29,B:B,A:A,0,0,1)) -> 1 | N29: Ltd | O29: 21008 | P29: Accounts Payable | Q29: =_xlfn.SINGLE(_xlfn.XLOOKUP(P29,E:E,D:D,0,0,1)) -> 6 | R29: Credit Cards | S29: =_xlfn.SINGLE(_xlfn.XLOOKUP(R29,H:H,G:G,0,0,1)) -> 103 | U29: =_xlfn.SINGLE(_xlfn.XLOOKUP(T29,K:K,J:J,0,0,1)) -> 0 | V29: =M29&O29&Q29&S29&U29 -> 12100861030 | X29: =_xlfn.SINGLE(_xlfn.XLOOKUP(Y29,B:B,A:A,0,0,1)) -> 2 | Y29: Inc | Z29: 25504 | AA29: Accrued expenses and other payable | AB29: =_xlfn.SINGLE(_xlfn.XLOOKUP(AA29,E:E,D:D,0,0,1)) -> 7 | AC29: Institutions | AD29: =_xlfn.SINGLE(_xlfn.XLOOKUP(AC29,H:H,G:G,0,0,1)) -> 109 | AF29: =_xlfn.SINGLE(_xlfn.XLOOKUP(AE29,K:K,J:J,0,0,1)) -> 0 | AG29: =X29&Z29&AB29&AD29&AF29 -> 22550471090
D30: 99 | E30: Overhead | G30: 128 | H30: Other G&A | M30: =_xlfn.SINGLE(_xlfn.XLOOKUP(N30,B:B,A:A,0,0,1)) -> 1 | N30: Ltd | O30: 21009 | P30: Accounts Payable | Q30: =_xlfn.SINGLE(_xlfn.XLOOKUP(P30,E:E,D:D,0,0,1)) -> 6 | R30: Credit Cards | S30: =_xlfn.SINGLE(_xlfn.XLOOKUP(R30,H:H,G:G,0,0,1)) -> 103 | U30: =_xlfn.SINGLE(_xlfn.XLOOKUP(T30,K:K,J:J,0,0,1)) -> 0 | V30: =M30&O30&Q30&S30&U30 -> 12100961030 | X30: =_xlfn.SINGLE(_xlfn.XLOOKUP(Y30,B:B,A:A,0,0,1)) -> 2 | Y30: Inc | Z30: 25505 | AA30: Accrued expenses and other payable | AB30: =_xlfn.SINGLE(_xlfn.XLOOKUP(AA30,E:E,D:D,0,0,1)) -> 7 | AC30: Institutions | AD30: =_xlfn.SINGLE(_xlfn.XLOOKUP(AC30,H:H,G:G,0,0,1)) -> 109 | AF30: =_xlfn.SINGLE(_xlfn.XLOOKUP(AE30,K:K,J:J,0,0,1)) -> 0 | AG30: =X30&Z30&AB30&AD30&AF30 -> 22550571090
G31: 129 | H31: Prepaid R&D exp. | M31: =_xlfn.SINGLE(_xlfn.XLOOKUP(N31,B:B,A:A,0,0,1)) -> 1 | N31: Ltd | O31: 21010 | P31: Accounts Payable | Q31: =_xlfn.SINGLE(_xlfn.XLOOKUP(P31,E:E,D:D,0,0,1)) -> 6 | R31: Credit Cards | S31: =_xlfn.SINGLE(_xlfn.XLOOKUP(R31,H:H,G:G,0,0,1)) -> 103 | U31: =_xlfn.SINGLE(_xlfn.XLOOKUP(T31,K:K,J:J,0,0,1)) -> 0 | V31: =M31&O31&Q31&S31&U31 -> 12101061030 | X31: =_xlfn.SINGLE(_xlfn.XLOOKUP(Y31,B:B,A:A,0,0,1)) -> 2 | Y31: Inc | Z31: 25506 | AA31: Accrued expenses and other payable | AB31: =_xlfn.SINGLE(_xlfn.XLOOKUP(AA31,E:E,D:D,0,0,1)) -> 7 | AC31: Institutions | AD31: =_xlfn.SINGLE(_xlfn.XLOOKUP(AC31,H:H,G:G,0,0,1)) -> 109 | AF31: =_xlfn.SINGLE(_xlfn.XLOOKUP(AE31,K:K,J:J,0,0,1)) -> 0 | AG31: =X31&Z31&AB31&AD31&AF31 -> 22550671090
M32: =_xlfn.SINGLE(_xlfn.XLOOKUP(N32,B:B,A:A,0,0,1)) -> 1 | N32: Ltd | O32: 21011 | P32: Accounts Payable | Q32: =_xlfn.SINGLE(_xlfn.XLOOKUP(P32,E:E,D:D,0,0,1)) -> 6 | R32: Credit Cards | S32: =_xlfn.SINGLE(_xlfn.XLOOKUP(R32,H:H,G:G,0,0,1)) -> 103 | U32: =_xlfn.SINGLE(_xlfn.XLOOKUP(T32,K:K,J:J,0,0,1)) -> 0 | V32: =M32&O32&Q32&S32&U32 -> 12101161030 | X32: =_xlfn.SINGLE(_xlfn.XLOOKUP(Y32,B:B,A:A,0,0,1)) -> 2 | Y32: Inc | Z32: 25507 | AA32: Accrued expenses and other payable | AB32: =_xlfn.SINGLE(_xlfn.XLOOKUP(AA32,E:E,D:D,0,0,1)) -> 7 | AC32: Institutions | AD32: =_xlfn.SINGLE(_xlfn.XLOOKUP(AC32,H:H,G:G,0,0,1)) -> 109 | AF32: =_xlfn.SINGLE(_xlfn.XLOOKUP(AE32,K:K,J:J,0,0,1)) -> 0 | AG32: =X32&Z32&AB32&AD32&AF32 -> 22550771090
M33: =_xlfn.SINGLE(_xlfn.XLOOKUP(N33,B:B,A:A,0,0,1)) -> 1 | N33: Ltd | O33: 21014 | P33: Accounts Payable | Q33: =_xlfn.SINGLE(_xlfn.XLOOKUP(P33,E:E,D:D,0,0,1)) -> 6 | R33: Credit Cards | S33: =_xlfn.SINGLE(_xlfn.XLOOKUP(R33,H:H,G:G,0,0,1)) -> 103 | U33: =_xlfn.SINGLE(_xlfn.XLOOKUP(T33,K:K,J:J,0,0,1)) -> 0 | V33: =M33&O33&Q33&S33&U33 -> 12101461030 | X33: =_xlfn.SINGLE(_xlfn.XLOOKUP(Y33,B:B,A:A,0,0,1)) -> 2 | Y33: Inc | Z33: 25508 | AA33: Accrued expenses and other payable | AB33: =_xlfn.SINGLE(_xlfn.XLOOKUP(AA33,E:E,D:D,0,0,1)) -> 7 | AC33: Institutions | AD33: =_xlfn.SINGLE(_xlfn.XLOOKUP(AC33,H:H,G:G,0,0,1)) -> 109 | AF33: =_xlfn.SINGLE(_xlfn.XLOOKUP(AE33,K:K,J:J,0,0,1)) -> 0 | AG33: =X33&Z33&AB33&AD33&AF33 -> 22550871090
M34: =_xlfn.SINGLE(_xlfn.XLOOKUP(N34,B:B,A:A,0,0,1)) -> 1 | N34: Ltd | O34: 21015 | P34: Accounts Payable | Q34: =_xlfn.SINGLE(_xlfn.XLOOKUP(P34,E:E,D:D,0,0,1)) -> 6 | R34: Credit Cards | S34: =_xlfn.SINGLE(_xlfn.XLOOKUP(R34,H:H,G:G,0,0,1)) -> 103 | U34: =_xlfn.SINGLE(_xlfn.XLOOKUP(T34,K:K,J:J,0,0,1)) -> 0 | V34: =M34&O34&Q34&S34&U34 -> 12101561030 | X34: =_xlfn.SINGLE(_xlfn.XLOOKUP(Y34,B:B,A:A,0,0,1)) -> 2 | Y34: Inc | Z34: 25509 | AA34: Accrued expenses and other payable | AB34: =_xlfn.SINGLE(_xlfn.XLOOKUP(AA34,E:E,D:D,0,0,1)) -> 7 | AC34: Institutions | AD34: =_xlfn.SINGLE(_xlfn.XLOOKUP(AC34,H:H,G:G,0,0,1)) -> 109 | AF34: =_xlfn.SINGLE(_xlfn.XLOOKUP(AE34,K:K,J:J,0,0,1)) -> 0 | AG34: =X34&Z34&AB34&AD34&AF34 -> 22550971090
M35: =_xlfn.SINGLE(_xlfn.XLOOKUP(N35,B:B,A:A,0,0,1)) -> 1 | N35: Ltd | O35: 21020 | P35: Accounts Payable | Q35: =_xlfn.SINGLE(_xlfn.XLOOKUP(P35,E:E,D:D,0,0,1)) -> 6 | R35: Credit Cards | S35: =_xlfn.SINGLE(_xlfn.XLOOKUP(R35,H:H,G:G,0,0,1)) -> 103 | U35: =_xlfn.SINGLE(_xlfn.XLOOKUP(T35,K:K,J:J,0,0,1)) -> 0 | V35: =M35&O35&Q35&S35&U35 -> 12102061030 | X35: =_xlfn.SINGLE(_xlfn.XLOOKUP(Y35,B:B,A:A,0,0,1)) -> 2 | Y35: Inc | Z35: 25510 | AA35: Accrued expenses and other payable | AB35: =_xlfn.SINGLE(_xlfn.XLOOKUP(AA35,E:E,D:D,0,0,1)) -> 7 | AC35: Institutions | AD35: =_xlfn.SINGLE(_xlfn.XLOOKUP(AC35,H:H,G:G,0,0,1)) -> 109 | AF35: =_xlfn.SINGLE(_xlfn.XLOOKUP(AE35,K:K,J:J,0,0,1)) -> 0 | AG35: =X35&Z35&AB35&AD35&AF35 -> 22551071090
M36: =_xlfn.SINGLE(_xlfn.XLOOKUP(N36,B:B,A:A,0,0,1)) -> 1 | N36: Ltd | O36: 22260 | P36: Accounts Receivable | Q36: =_xlfn.SINGLE(_xlfn.XLOOKUP(P36,E:E,D:D,0,0,1)) -> 2 | S36: =_xlfn.SINGLE(_xlfn.XLOOKUP(R36,H:H,G:G,0,0,1)) -> 0 | U36: =_xlfn.SINGLE(_xlfn.XLOOKUP(T36,K:K,J:J,0,0,1)) -> 0 | V36: =M36&O36&Q36&S36&U36 -> 122260200 | X36: =_xlfn.SINGLE(_xlfn.XLOOKUP(Y36,B:B,A:A,0,0,1)) -> 2 | Y36: Inc | Z36: 25511 | AA36: Accrued expenses and other payable | AB36: =_xlfn.SINGLE(_xlfn.XLOOKUP(AA36,E:E,D:D,0,0,1)) -> 7 | AC36: Institutions | AD36: =_xlfn.SINGLE(_xlfn.XLOOKUP(AC36,H:H,G:G,0,0,1)) -> 109 | AF36: =_xlfn.SINGLE(_xlfn.XLOOKUP(AE36,K:K,J:J,0,0,1)) -> 0 | AG36: =X36&Z36&AB36&AD36&AF36 -> 22551171090
M37: =_xlfn.SINGLE(_xlfn.XLOOKUP(N37,B:B,A:A,0,0,1)) -> 1 | N37: Ltd | O37: 22263 | P37: Accounts Receivable | Q37: =_xlfn.SINGLE(_xlfn.XLOOKUP(P37,E:E,D:D,0,0,1)) -> 2 | S37: =_xlfn.SINGLE(_xlfn.XLOOKUP(R37,H:H,G:G,0,0,1)) -> 0 | U37: =_xlfn.SINGLE(_xlfn.XLOOKUP(T37,K:K,J:J,0,0,1)) -> 0 | V37: =M37&O37&Q37&S37&U37 -> 122263200 | X37: =_xlfn.SINGLE(_xlfn.XLOOKUP(Y37,B:B,A:A,0,0,1)) -> 2 | Y37: Inc | Z37: 25512 | AA37: Accrued expenses and other payable | AB37: =_xlfn.SINGLE(_xlfn.XLOOKUP(AA37,E:E,D:D,0,0,1)) -> 7 | AC37: Institutions | AD37: =_xlfn.SINGLE(_xlfn.XLOOKUP(AC37,H:H,G:G,0,0,1)) -> 109 | AF37: =_xlfn.SINGLE(_xlfn.XLOOKUP(AE37,K:K,J:J,0,0,1)) -> 0 | AG37: =X37&Z37&AB37&AD37&AF37 -> 22551271090
M38: =_xlfn.SINGLE(_xlfn.XLOOKUP(N38,B:B,A:A,0,0,1)) -> 1 | N38: Ltd | O38: 22264 | P38: Accounts Receivable | Q38: =_xlfn.SINGLE(_xlfn.XLOOKUP(P38,E:E,D:D,0,0,1)) -> 2 | S38: =_xlfn.SINGLE(_xlfn.XLOOKUP(R38,H:H,G:G,0,0,1)) -> 0 | U38: =_xlfn.SINGLE(_xlfn.XLOOKUP(T38,K:K,J:J,0,0,1)) -> 0 | V38: =M38&O38&Q38&S38&U38 -> 122264200 | X38: =_xlfn.SINGLE(_xlfn.XLOOKUP(Y38,B:B,A:A,0,0,1)) -> 2 | Y38: Inc | Z38: 25513 | AA38: Accrued expenses and other payable | AB38: =_xlfn.SINGLE(_xlfn.XLOOKUP(AA38,E:E,D:D,0,0,1)) -> 7 | AC38: Institutions | AD38: =_xlfn.SINGLE(_xlfn.XLOOKUP(AC38,H:H,G:G,0,0,1)) -> 109 | AF38: =_xlfn.SINGLE(_xlfn.XLOOKUP(AE38,K:K,J:J,0,0,1)) -> 0 | AG38: =X38&Z38&AB38&AD38&AF38 -> 22551371090
M39: =_xlfn.SINGLE(_xlfn.XLOOKUP(N39,B:B,A:A,0,0,1)) -> 1 | N39: Ltd | O39: 22268 | P39: Accounts Receivable | Q39: =_xlfn.SINGLE(_xlfn.XLOOKUP(P39,E:E,D:D,0,0,1)) -> 2 | S39: =_xlfn.SINGLE(_xlfn.XLOOKUP(R39,H:H,G:G,0,0,1)) -> 0 | U39: =_xlfn.SINGLE(_xlfn.XLOOKUP(T39,K:K,J:J,0,0,1)) -> 0 | V39: =M39&O39&Q39&S39&U39 -> 122268200 | X39: =_xlfn.SINGLE(_xlfn.XLOOKUP(Y39,B:B,A:A,0,0,1)) -> 2 | Y39: Inc | Z39: 27020 | AA39: Employees Payable | AB39: =_xlfn.SINGLE(_xlfn.XLOOKUP(AA39,E:E,D:D,0,0,1)) -> 8 | AD39: =_xlfn.SINGLE(_xlfn.XLOOKUP(AC39,H:H,G:G,0,0,1)) -> 0 | AF39: =_xlfn.SINGLE(_xlfn.XLOOKUP(AE39,K:K,J:J,0,0,1)) -> 0 | AG39: =X39&Z39&AB39&AD39&AF39 -> 227020800
M40: =_xlfn.SINGLE(_xlfn.XLOOKUP(N40,B:B,A:A,0,0,1)) -> 1 | N40: Ltd | O40: 22270 | P40: Accounts Receivable | Q40: =_xlfn.SINGLE(_xlfn.XLOOKUP(P40,E:E,D:D,0,0,1)) -> 2 | S40: =_xlfn.SINGLE(_xlfn.XLOOKUP(R40,H:H,G:G,0,0,1)) -> 0 | U40: =_xlfn.SINGLE(_xlfn.XLOOKUP(T40,K:K,J:J,0,0,1)) -> 0 | V40: =M40&O40&Q40&S40&U40 -> 122270200 | X40: =_xlfn.SINGLE(_xlfn.XLOOKUP(Y40,B:B,A:A,0,0,1)) -> 2 | Y40: Inc | Z40: 30000 | AA40: Capital Stock | AB40: =_xlfn.SINGLE(_xlfn.XLOOKUP(AA40,E:E,D:D,0,0,1)) -> 10 | AD40: =_xlfn.SINGLE(_xlfn.XLOOKUP(AC40,H:H,G:G,0,0,1)) -> 0 | AF40: =_xlfn.SINGLE(_xlfn.XLOOKUP(AE40,K:K,J:J,0,0,1)) -> 0 | AG40: =X40&Z40&AB40&AD40&AF40 -> 2300001000
M41: =_xlfn.SINGLE(_xlfn.XLOOKUP(N41,B:B,A:A,0,0,1)) -> 1 | N41: Ltd | O41: 22272 | P41: Accounts Receivable | Q41: =_xlfn.SINGLE(_xlfn.XLOOKUP(P41,E:E,D:D,0,0,1)) -> 2 | S41: =_xlfn.SINGLE(_xlfn.XLOOKUP(R41,H:H,G:G,0,0,1)) -> 0 | U41: =_xlfn.SINGLE(_xlfn.XLOOKUP(T41,K:K,J:J,0,0,1)) -> 0 | V41: =M41&O41&Q41&S41&U41 -> 122272200 | X41: =_xlfn.SINGLE(_xlfn.XLOOKUP(Y41,B:B,A:A,0,0,1)) -> 2 | Y41: Inc | Z41: 30010 | AA41: Capital Stock | AB41: =_xlfn.SINGLE(_xlfn.XLOOKUP(AA41,E:E,D:D,0,0,1)) -> 10 | AD41: =_xlfn.SINGLE(_xlfn.XLOOKUP(AC41,H:H,G:G,0,0,1)) -> 0 | AF41: =_xlfn.SINGLE(_xlfn.XLOOKUP(AE41,K:K,J:J,0,0,1)) -> 0 | AG41: =X41&Z41&AB41&AD41&AF41 -> 2300101000
M42: =_xlfn.SINGLE(_xlfn.XLOOKUP(N42,B:B,A:A,0,0,1)) -> 1 | N42: Ltd | O42: 22277 | P42: Accounts Receivable | Q42: =_xlfn.SINGLE(_xlfn.XLOOKUP(P42,E:E,D:D,0,0,1)) -> 2 | S42: =_xlfn.SINGLE(_xlfn.XLOOKUP(R42,H:H,G:G,0,0,1)) -> 0 | U42: =_xlfn.SINGLE(_xlfn.XLOOKUP(T42,K:K,J:J,0,0,1)) -> 0 | V42: =M42&O42&Q42&S42&U42 -> 122277200 | X42: =_xlfn.SINGLE(_xlfn.XLOOKUP(Y42,B:B,A:A,0,0,1)) -> 2 | Y42: Inc | Z42: 30011 | AA42: Capital Stock | AB42: =_xlfn.SINGLE(_xlfn.XLOOKUP(AA42,E:E,D:D,0,0,1)) -> 10 | AD42: =_xlfn.SINGLE(_xlfn.XLOOKUP(AC42,H:H,G:G,0,0,1)) -> 0 | AF42: =_xlfn.SINGLE(_xlfn.XLOOKUP(AE42,K:K,J:J,0,0,1)) -> 0 | AG42: =X42&Z42&AB42&AD42&AF42 -> 2300111000
M43: =_xlfn.SINGLE(_xlfn.XLOOKUP(N43,B:B,A:A,0,0,1)) -> 1 | N43: Ltd | O43: 22280 | P43: Accounts Receivable | Q43: =_xlfn.SINGLE(_xlfn.XLOOKUP(P43,E:E,D:D,0,0,1)) -> 2 | S43: =_xlfn.SINGLE(_xlfn.XLOOKUP(R43,H:H,G:G,0,0,1)) -> 0 | U43: =_xlfn.SINGLE(_xlfn.XLOOKUP(T43,K:K,J:J,0,0,1)) -> 0 | V43: =M43&O43&Q43&S43&U43 -> 122280200 | X43: =_xlfn.SINGLE(_xlfn.XLOOKUP(Y43,B:B,A:A,0,0,1)) -> 2 | Y43: Inc | Z43: 30012 | AA43: Capital Stock | AB43: =_xlfn.SINGLE(_xlfn.XLOOKUP(AA43,E:E,D:D,0,0,1)) -> 10 | AD43: =_xlfn.SINGLE(_xlfn.XLOOKUP(AC43,H:H,G:G,0,0,1)) -> 0 | AF43: =_xlfn.SINGLE(_xlfn.XLOOKUP(AE43,K:K,J:J,0,0,1)) -> 0 | AG43: =X43&Z43&AB43&AD43&AF43 -> 2300121000
M44: =_xlfn.SINGLE(_xlfn.XLOOKUP(N44,B:B,A:A,0,0,1)) -> 1 | N44: Ltd | O44: 22288 | P44: Accounts Receivable | Q44: =_xlfn.SINGLE(_xlfn.XLOOKUP(P44,E:E,D:D,0,0,1)) -> 2 | S44: =_xlfn.SINGLE(_xlfn.XLOOKUP(R44,H:H,G:G,0,0,1)) -> 0 | U44: =_xlfn.SINGLE(_xlfn.XLOOKUP(T44,K:K,J:J,0,0,1)) -> 0 | V44: =M44&O44&Q44&S44&U44 -> 122288200 | X44: =_xlfn.SINGLE(_xlfn.XLOOKUP(Y44,B:B,A:A,0,0,1)) -> 2 | Y44: Inc | Z44: 30013 | AA44: Capital Stock | AB44: =_xlfn.SINGLE(_xlfn.XLOOKUP(AA44,E:E,D:D,0,0,1)) -> 10 | AD44: =_xlfn.SINGLE(_xlfn.XLOOKUP(AC44,H:H,G:G,0,0,1)) -> 0 | AF44: =_xlfn.SINGLE(_xlfn.XLOOKUP(AE44,K:K,J:J,0,0,1)) -> 0 | AG44: =X44&Z44&AB44&AD44&AF44 -> 2300131000
M45: =_xlfn.SINGLE(_xlfn.XLOOKUP(N45,B:B,A:A,0,0,1)) -> 1 | N45: Ltd | O45: 22292 | P45: Accounts Receivable | Q45: =_xlfn.SINGLE(_xlfn.XLOOKUP(P45,E:E,D:D,0,0,1)) -> 2 | S45: =_xlfn.SINGLE(_xlfn.XLOOKUP(R45,H:H,G:G,0,0,1)) -> 0 | U45: =_xlfn.SINGLE(_xlfn.XLOOKUP(T45,K:K,J:J,0,0,1)) -> 0 | V45: =M45&O45&Q45&S45&U45 -> 122292200 | X45: =_xlfn.SINGLE(_xlfn.XLOOKUP(Y45,B:B,A:A,0,0,1)) -> 2 | Y45: Inc | Z45: 30014 | AA45: Capital Stock | AB45: =_xlfn.SINGLE(_xlfn.XLOOKUP(AA45,E:E,D:D,0,0,1)) -> 10 | AD45: =_xlfn.SINGLE(_xlfn.XLOOKUP(AC45,H:H,G:G,0,0,1)) -> 0 | AF45: =_xlfn.SINGLE(_xlfn.XLOOKUP(AE45,K:K,J:J,0,0,1)) -> 0 | AG45: =X45&Z45&AB45&AD45&AF45 -> 2300141000
M46: =_xlfn.SINGLE(_xlfn.XLOOKUP(N46,B:B,A:A,0,0,1)) -> 1 | N46: Ltd | O46: 22299 | P46: Accounts Receivable | Q46: =_xlfn.SINGLE(_xlfn.XLOOKUP(P46,E:E,D:D,0,0,1)) -> 2 | S46: =_xlfn.SINGLE(_xlfn.XLOOKUP(R46,H:H,G:G,0,0,1)) -> 0 | U46: =_xlfn.SINGLE(_xlfn.XLOOKUP(T46,K:K,J:J,0,0,1)) -> 0 | V46: =M46&O46&Q46&S46&U46 -> 122299200 | X46: =_xlfn.SINGLE(_xlfn.XLOOKUP(Y46,B:B,A:A,0,0,1)) -> 2 | Y46: Inc | Z46: 30050 | AA46: Additional Paid In Capital | AB46: =_xlfn.SINGLE(_xlfn.XLOOKUP(AA46,E:E,D:D,0,0,1)) -> 11 | AD46: =_xlfn.SINGLE(_xlfn.XLOOKUP(AC46,H:H,G:G,0,0,1)) -> 0 | AF46: =_xlfn.SINGLE(_xlfn.XLOOKUP(AE46,K:K,J:J,0,0,1)) -> 0 | AG46: =X46&Z46&AB46&AD46&AF46 -> 2300501100
M47: =_xlfn.SINGLE(_xlfn.XLOOKUP(N47,B:B,A:A,0,0,1)) -> 1 | N47: Ltd | O47: 22306 | P47: Accounts Receivable | Q47: =_xlfn.SINGLE(_xlfn.XLOOKUP(P47,E:E,D:D,0,0,1)) -> 2 | S47: =_xlfn.SINGLE(_xlfn.XLOOKUP(R47,H:H,G:G,0,0,1)) -> 0 | U47: =_xlfn.SINGLE(_xlfn.XLOOKUP(T47,K:K,J:J,0,0,1)) -> 0 | V47: =M47&O47&Q47&S47&U47 -> 122306200 | X47: =_xlfn.SINGLE(_xlfn.XLOOKUP(Y47,B:B,A:A,0,0,1)) -> 2 | Y47: Inc | Z47: 30090 | AA47: Additional Paid In Capital | AB47: =_xlfn.SINGLE(_xlfn.XLOOKUP(AA47,E:E,D:D,0,0,1)) -> 11 | AD47: =_xlfn.SINGLE(_xlfn.XLOOKUP(AC47,H:H,G:G,0,0,1)) -> 0 | AF47: =_xlfn.SINGLE(_xlfn.XLOOKUP(AE47,K:K,J:J,0,0,1)) -> 0 | AG47: =X47&Z47&AB47&AD47&AF47 -> 2300901100
M48: =_xlfn.SINGLE(_xlfn.XLOOKUP(N48,B:B,A:A,0,0,1)) -> 1 | N48: Ltd | O48: 22307 | P48: Accounts Receivable | Q48: =_xlfn.SINGLE(_xlfn.XLOOKUP(P48,E:E,D:D,0,0,1)) -> 2 | S48: =_xlfn.SINGLE(_xlfn.XLOOKUP(R48,H:H,G:G,0,0,1)) -> 0 | U48: =_xlfn.SINGLE(_xlfn.XLOOKUP(T48,K:K,J:J,0,0,1)) -> 0 | V48: =M48&O48&Q48&S48&U48 -> 122307200 | X48: =_xlfn.SINGLE(_xlfn.XLOOKUP(Y48,B:B,A:A,0,0,1)) -> 2 | Y48: Inc | Z48: 30091 | AA48: Additional Paid In Capital | AB48: =_xlfn.SINGLE(_xlfn.XLOOKUP(AA48,E:E,D:D,0,0,1)) -> 11 | AD48: =_xlfn.SINGLE(_xlfn.XLOOKUP(AC48,H:H,G:G,0,0,1)) -> 0 | AF48: =_xlfn.SINGLE(_xlfn.XLOOKUP(AE48,K:K,J:J,0,0,1)) -> 0 | AG48: =X48&Z48&AB48&AD48&AF48 -> 2300911100
M49: =_xlfn.SINGLE(_xlfn.XLOOKUP(N49,B:B,A:A,0,0,1)) -> 1 | N49: Ltd | O49: 22308 | P49: Accounts Receivable | Q49: =_xlfn.SINGLE(_xlfn.XLOOKUP(P49,E:E,D:D,0,0,1)) -> 2 | S49: =_xlfn.SINGLE(_xlfn.XLOOKUP(R49,H:H,G:G,0,0,1)) -> 0 | U49: =_xlfn.SINGLE(_xlfn.XLOOKUP(T49,K:K,J:J,0,0,1)) -> 0 | V49: =M49&O49&Q49&S49&U49 -> 122308200 | X49: =_xlfn.SINGLE(_xlfn.XLOOKUP(Y49,B:B,A:A,0,0,1)) -> 2 | Y49: Inc | Z49: 35000 | AA49: Retained Loss | AB49: =_xlfn.SINGLE(_xlfn.XLOOKUP(AA49,E:E,D:D,0,0,1)) -> 13 | AD49: =_xlfn.SINGLE(_xlfn.XLOOKUP(AC49,H:H,G:G,0,0,1)) -> 0 | AF49: =_xlfn.SINGLE(_xlfn.XLOOKUP(AE49,K:K,J:J,0,0,1)) -> 0 | AG49: =X49&Z49&AB49&AD49&AF49 -> 2350001300
M50: =_xlfn.SINGLE(_xlfn.XLOOKUP(N50,B:B,A:A,0,0,1)) -> 1 | N50: Ltd | O50: 35002 | P50: Prepaid expenses and other receivable | Q50: =_xlfn.SINGLE(_xlfn.XLOOKUP(P50,E:E,D:D,0,0,1)) -> 3 | R50: Prepaid Expenses | S50: =_xlfn.SINGLE(_xlfn.XLOOKUP(R50,H:H,G:G,0,0,1)) -> 118 | U50: =_xlfn.SINGLE(_xlfn.XLOOKUP(T50,K:K,J:J,0,0,1)) -> 0 | V50: =M50&O50&Q50&S50&U50 -> 13500231180 | X50: =_xlfn.SINGLE(_xlfn.XLOOKUP(Y50,B:B,A:A,0,0,1)) -> 2 | Y50: Inc | Z50: 35001 | AA50: Retained Loss | AB50: =_xlfn.SINGLE(_xlfn.XLOOKUP(AA50,E:E,D:D,0,0,1)) -> 13 | AD50: =_xlfn.SINGLE(_xlfn.XLOOKUP(AC50,H:H,G:G,0,0,1)) -> 0 | AF50: =_xlfn.SINGLE(_xlfn.XLOOKUP(AE50,K:K,J:J,0,0,1)) -> 0 | AG50: =X50&Z50&AB50&AD50&AF50 -> 2350011300
M51: =_xlfn.SINGLE(_xlfn.XLOOKUP(N51,B:B,A:A,0,0,1)) -> 1 | N51: Ltd | O51: 35011 | P51: Prepaid expenses and other receivable | Q51: =_xlfn.SINGLE(_xlfn.XLOOKUP(P51,E:E,D:D,0,0,1)) -> 3 | R51: Prepaid Commissions | S51: =_xlfn.SINGLE(_xlfn.XLOOKUP(R51,H:H,G:G,0,0,1)) -> 117 | U51: =_xlfn.SINGLE(_xlfn.XLOOKUP(T51,K:K,J:J,0,0,1)) -> 0 | V51: =M51&O51&Q51&S51&U51 -> 13501131170 | X51: =_xlfn.SINGLE(_xlfn.XLOOKUP(Y51,B:B,A:A,0,0,1)) -> 2 | Y51: Inc | Z51: 40000 | AA51: Revenue | AB51: =_xlfn.SINGLE(_xlfn.XLOOKUP(AA51,E:E,D:D,0,0,1)) -> 20 | AD51: =_xlfn.SINGLE(_xlfn.XLOOKUP(AC51,H:H,G:G,0,0,1)) -> 0 | AF51: =_xlfn.SINGLE(_xlfn.XLOOKUP(AE51,K:K,J:J,0,0,1)) -> 0 | AG51: =X51&Z51&AB51&AD51&AF51 -> 2400002000
M52: =_xlfn.SINGLE(_xlfn.XLOOKUP(N52,B:B,A:A,0,0,1)) -> 1 | N52: Ltd | O52: 35012 | P52: Prepaid expenses and other receivable | Q52: =_xlfn.SINGLE(_xlfn.XLOOKUP(P52,E:E,D:D,0,0,1)) -> 3 | R52: Prepaid R&D exp. | S52: =_xlfn.SINGLE(_xlfn.XLOOKUP(R52,H:H,G:G,0,0,1)) -> 129 | U52: =_xlfn.SINGLE(_xlfn.XLOOKUP(T52,K:K,J:J,0,0,1)) -> 0 | V52: =M52&O52&Q52&S52&U52 -> 13501231290 | X52: =_xlfn.SINGLE(_xlfn.XLOOKUP(Y52,B:B,A:A,0,0,1)) -> 2 | Y52: Inc | Z52: 70005 | AA52: Sales | AB52: =_xlfn.SINGLE(_xlfn.XLOOKUP(AA52,E:E,D:D,0,0,1)) -> 50 | AC52: Payroll & Payroll related | AD52: =_xlfn.SINGLE(_xlfn.XLOOKUP(AC52,H:H,G:G,0,0,1)) -> 116 | AF52: =_xlfn.SINGLE(_xlfn.XLOOKUP(AE52,K:K,J:J,0,0,1)) -> 0 | AG52: =X52&Z52&AB52&AD52&AF52 -> 270005501160
M53: =_xlfn.SINGLE(_xlfn.XLOOKUP(N53,B:B,A:A,0,0,1)) -> 1 | N53: Ltd | O53: 15600 | P53: Fixed Assets | Q53: =_xlfn.SINGLE(_xlfn.XLOOKUP(P53,E:E,D:D,0,0,1)) -> 4 | S53: =_xlfn.SINGLE(_xlfn.XLOOKUP(R53,H:H,G:G,0,0,1)) -> 0 | U53: =_xlfn.SINGLE(_xlfn.XLOOKUP(T53,K:K,J:J,0,0,1)) -> 0 | V53: =M53&O53&Q53&S53&U53 -> 115600400 | X53: =_xlfn.SINGLE(_xlfn.XLOOKUP(Y53,B:B,A:A,0,0,1)) -> 2 | Y53: Inc | Z53: 70010 | AA53: Sales | AB53: =_xlfn.SINGLE(_xlfn.XLOOKUP(AA53,E:E,D:D,0,0,1)) -> 50 | AC53: Payroll & Payroll related | AD53: =_xlfn.SINGLE(_xlfn.XLOOKUP(AC53,H:H,G:G,0,0,1)) -> 116 | AF53: =_xlfn.SINGLE(_xlfn.XLOOKUP(AE53,K:K,J:J,0,0,1)) -> 0 | AG53: =X53&Z53&AB53&AD53&AF53 -> 270010501160
M54: =_xlfn.SINGLE(_xlfn.XLOOKUP(N54,B:B,A:A,0,0,1)) -> 1 | N54: Ltd | O54: 15900 | P54: Fixed Assets | Q54: =_xlfn.SINGLE(_xlfn.XLOOKUP(P54,E:E,D:D,0,0,1)) -> 4 | S54: =_xlfn.SINGLE(_xlfn.XLOOKUP(R54,H:H,G:G,0,0,1)) -> 0 | U54: =_xlfn.SINGLE(_xlfn.XLOOKUP(T54,K:K,J:J,0,0,1)) -> 0 | V54: =M54&O54&Q54&S54&U54 -> 115900400 | X54: =_xlfn.SINGLE(_xlfn.XLOOKUP(Y54,B:B,A:A,0,0,1)) -> 2 | Y54: Inc | Z54: 70015 | AA54: Sales | AB54: =_xlfn.SINGLE(_xlfn.XLOOKUP(AA54,E:E,D:D,0,0,1)) -> 50 | AC54: Payroll & Payroll related | AD54: =_xlfn.SINGLE(_xlfn.XLOOKUP(AC54,H:H,G:G,0,0,1)) -> 116 | AF54: =_xlfn.SINGLE(_xlfn.XLOOKUP(AE54,K:K,J:J,0,0,1)) -> 0 | AG54: =X54&Z54&AB54&AD54&AF54 -> 270015501160
M55: =_xlfn.SINGLE(_xlfn.XLOOKUP(N55,B:B,A:A,0,0,1)) -> 1 | N55: Ltd | O55: 15901 | P55: Fixed Assets | Q55: =_xlfn.SINGLE(_xlfn.XLOOKUP(P55,E:E,D:D,0,0,1)) -> 4 | S55: =_xlfn.SINGLE(_xlfn.XLOOKUP(R55,H:H,G:G,0,0,1)) -> 0 | U55: =_xlfn.SINGLE(_xlfn.XLOOKUP(T55,K:K,J:J,0,0,1)) -> 0 | V55: =M55&O55&Q55&S55&U55 -> 115901400 | X55: =_xlfn.SINGLE(_xlfn.XLOOKUP(Y55,B:B,A:A,0,0,1)) -> 2 | Y55: Inc | Z55: 70020 | AA55: Sales | AB55: =_xlfn.SINGLE(_xlfn.XLOOKUP(AA55,E:E,D:D,0,0,1)) -> 50 | AC55: Payroll & Payroll related | AD55: =_xlfn.SINGLE(_xlfn.XLOOKUP(AC55,H:H,G:G,0,0,1)) -> 116 | AF55: =_xlfn.SINGLE(_xlfn.XLOOKUP(AE55,K:K,J:J,0,0,1)) -> 0 | AG55: =X55&Z55&AB55&AD55&AF55 -> 270020501160
M56: =_xlfn.SINGLE(_xlfn.XLOOKUP(N56,B:B,A:A,0,0,1)) -> 1 | N56: Ltd | O56: 15902 | P56: Fixed Assets | Q56: =_xlfn.SINGLE(_xlfn.XLOOKUP(P56,E:E,D:D,0,0,1)) -> 4 | S56: =_xlfn.SINGLE(_xlfn.XLOOKUP(R56,H:H,G:G,0,0,1)) -> 0 | U56: =_xlfn.SINGLE(_xlfn.XLOOKUP(T56,K:K,J:J,0,0,1)) -> 0 | V56: =M56&O56&Q56&S56&U56 -> 115902400 | X56: =_xlfn.SINGLE(_xlfn.XLOOKUP(Y56,B:B,A:A,0,0,1)) -> 2 | Y56: Inc | Z56: 70024 | AA56: Sales | AB56: =_xlfn.SINGLE(_xlfn.XLOOKUP(AA56,E:E,D:D,0,0,1)) -> 50 | AC56: Payroll & Payroll related | AD56: =_xlfn.SINGLE(_xlfn.XLOOKUP(AC56,H:H,G:G,0,0,1)) -> 116 | AF56: =_xlfn.SINGLE(_xlfn.XLOOKUP(AE56,K:K,J:J,0,0,1)) -> 0 | AG56: =X56&Z56&AB56&AD56&AF56 -> 270024501160
M57: =_xlfn.SINGLE(_xlfn.XLOOKUP(N57,B:B,A:A,0,0,1)) -> 1 | N57: Ltd | O57: 15905 | P57: Fixed Assets | Q57: =_xlfn.SINGLE(_xlfn.XLOOKUP(P57,E:E,D:D,0,0,1)) -> 4 | S57: =_xlfn.SINGLE(_xlfn.XLOOKUP(R57,H:H,G:G,0,0,1)) -> 0 | U57: =_xlfn.SINGLE(_xlfn.XLOOKUP(T57,K:K,J:J,0,0,1)) -> 0 | V57: =M57&O57&Q57&S57&U57 -> 115905400 | X57: =_xlfn.SINGLE(_xlfn.XLOOKUP(Y57,B:B,A:A,0,0,1)) -> 2 | Y57: Inc | Z57: 70025 | AA57: Sales | AB57: =_xlfn.SINGLE(_xlfn.XLOOKUP(AA57,E:E,D:D,0,0,1)) -> 50 | AC57: Payroll & Payroll related | AD57: =_xlfn.SINGLE(_xlfn.XLOOKUP(AC57,H:H,G:G,0,0,1)) -> 116 | AF57: =_xlfn.SINGLE(_xlfn.XLOOKUP(AE57,K:K,J:J,0,0,1)) -> 0 | AG57: =X57&Z57&AB57&AD57&AF57 -> 270025501160
M58: =_xlfn.SINGLE(_xlfn.XLOOKUP(N58,B:B,A:A,0,0,1)) -> 1 | N58: Ltd | O58: 15906 | P58: Fixed Assets | Q58: =_xlfn.SINGLE(_xlfn.XLOOKUP(P58,E:E,D:D,0,0,1)) -> 4 | S58: =_xlfn.SINGLE(_xlfn.XLOOKUP(R58,H:H,G:G,0,0,1)) -> 0 | U58: =_xlfn.SINGLE(_xlfn.XLOOKUP(T58,K:K,J:J,0,0,1)) -> 0 | V58: =M58&O58&Q58&S58&U58 -> 115906400 | X58: =_xlfn.SINGLE(_xlfn.XLOOKUP(Y58,B:B,A:A,0,0,1)) -> 2 | Y58: Inc | Z58: 70030 | AA58: Sales | AB58: =_xlfn.SINGLE(_xlfn.XLOOKUP(AA58,E:E,D:D,0,0,1)) -> 50 | AC58: Payroll & Payroll related | AD58: =_xlfn.SINGLE(_xlfn.XLOOKUP(AC58,H:H,G:G,0,0,1)) -> 116 | AF58: =_xlfn.SINGLE(_xlfn.XLOOKUP(AE58,K:K,J:J,0,0,1)) -> 0 | AG58: =X58&Z58&AB58&AD58&AF58 -> 270030501160
M59: =_xlfn.SINGLE(_xlfn.XLOOKUP(N59,B:B,A:A,0,0,1)) -> 1 | N59: Ltd | O59: 15910 | P59: Fixed Assets | Q59: =_xlfn.SINGLE(_xlfn.XLOOKUP(P59,E:E,D:D,0,0,1)) -> 4 | S59: =_xlfn.SINGLE(_xlfn.XLOOKUP(R59,H:H,G:G,0,0,1)) -> 0 | U59: =_xlfn.SINGLE(_xlfn.XLOOKUP(T59,K:K,J:J,0,0,1)) -> 0 | V59: =M59&O59&Q59&S59&U59 -> 115910400 | X59: =_xlfn.SINGLE(_xlfn.XLOOKUP(Y59,B:B,A:A,0,0,1)) -> 2 | Y59: Inc | Z59: 70035 | AA59: Sales | AB59: =_xlfn.SINGLE(_xlfn.XLOOKUP(AA59,E:E,D:D,0,0,1)) -> 50 | AC59: Payroll & Payroll related | AD59: =_xlfn.SINGLE(_xlfn.XLOOKUP(AC59,H:H,G:G,0,0,1)) -> 116 | AF59: =_xlfn.SINGLE(_xlfn.XLOOKUP(AE59,K:K,J:J,0,0,1)) -> 0 | AG59: =X59&Z59&AB59&AD59&AF59 -> 270035501160
M60: =_xlfn.SINGLE(_xlfn.XLOOKUP(N60,B:B,A:A,0,0,1)) -> 1 | N60: Ltd | O60: 15911 | P60: Fixed Assets | Q60: =_xlfn.SINGLE(_xlfn.XLOOKUP(P60,E:E,D:D,0,0,1)) -> 4 | S60: =_xlfn.SINGLE(_xlfn.XLOOKUP(R60,H:H,G:G,0,0,1)) -> 0 | U60: =_xlfn.SINGLE(_xlfn.XLOOKUP(T60,K:K,J:J,0,0,1)) -> 0 | V60: =M60&O60&Q60&S60&U60 -> 115911400 | X60: =_xlfn.SINGLE(_xlfn.XLOOKUP(Y60,B:B,A:A,0,0,1)) -> 2 | Y60: Inc | Z60: 70040 | AA60: Sales | AB60: =_xlfn.SINGLE(_xlfn.XLOOKUP(AA60,E:E,D:D,0,0,1)) -> 50 | AC60: T&E | AD60: =_xlfn.SINGLE(_xlfn.XLOOKUP(AC60,H:H,G:G,0,0,1)) -> 124 | AF60: =_xlfn.SINGLE(_xlfn.XLOOKUP(AE60,K:K,J:J,0,0,1)) -> 0 | AG60: =X60&Z60&AB60&AD60&AF60 -> 270040501240
M61: =_xlfn.SINGLE(_xlfn.XLOOKUP(N61,B:B,A:A,0,0,1)) -> 1 | N61: Ltd | O61: 15912 | P61: Fixed Assets | Q61: =_xlfn.SINGLE(_xlfn.XLOOKUP(P61,E:E,D:D,0,0,1)) -> 4 | S61: =_xlfn.SINGLE(_xlfn.XLOOKUP(R61,H:H,G:G,0,0,1)) -> 0 | U61: =_xlfn.SINGLE(_xlfn.XLOOKUP(T61,K:K,J:J,0,0,1)) -> 0 | V61: =M61&O61&Q61&S61&U61 -> 115912400 | X61: =_xlfn.SINGLE(_xlfn.XLOOKUP(Y61,B:B,A:A,0,0,1)) -> 2 | Y61: Inc | Z61: 70050 | AA61: Sales | AB61: =_xlfn.SINGLE(_xlfn.XLOOKUP(AA61,E:E,D:D,0,0,1)) -> 50 | AC61: T&E | AD61: =_xlfn.SINGLE(_xlfn.XLOOKUP(AC61,H:H,G:G,0,0,1)) -> 124 | AF61: =_xlfn.SINGLE(_xlfn.XLOOKUP(AE61,K:K,J:J,0,0,1)) -> 0 | AG61: =X61&Z61&AB61&AD61&AF61 -> 270050501240
M62: =_xlfn.SINGLE(_xlfn.XLOOKUP(N62,B:B,A:A,0,0,1)) -> 1 | N62: Ltd | O62: 15913 | P62: Fixed Assets | Q62: =_xlfn.SINGLE(_xlfn.XLOOKUP(P62,E:E,D:D,0,0,1)) -> 4 | S62: =_xlfn.SINGLE(_xlfn.XLOOKUP(R62,H:H,G:G,0,0,1)) -> 0 | U62: =_xlfn.SINGLE(_xlfn.XLOOKUP(T62,K:K,J:J,0,0,1)) -> 0 | V62: =M62&O62&Q62&S62&U62 -> 115913400 | X62: =_xlfn.SINGLE(_xlfn.XLOOKUP(Y62,B:B,A:A,0,0,1)) -> 2 | Y62: Inc | Z62: 70055 | AA62: Sales | AB62: =_xlfn.SINGLE(_xlfn.XLOOKUP(AA62,E:E,D:D,0,0,1)) -> 50 | AC62: T&E | AD62: =_xlfn.SINGLE(_xlfn.XLOOKUP(AC62,H:H,G:G,0,0,1)) -> 124 | AF62: =_xlfn.SINGLE(_xlfn.XLOOKUP(AE62,K:K,J:J,0,0,1)) -> 0 | AG62: =X62&Z62&AB62&AD62&AF62 -> 270055501240
M63: =_xlfn.SINGLE(_xlfn.XLOOKUP(N63,B:B,A:A,0,0,1)) -> 1 | N63: Ltd | O63: 15914 | P63: Fixed Assets | Q63: =_xlfn.SINGLE(_xlfn.XLOOKUP(P63,E:E,D:D,0,0,1)) -> 4 | S63: =_xlfn.SINGLE(_xlfn.XLOOKUP(R63,H:H,G:G,0,0,1)) -> 0 | U63: =_xlfn.SINGLE(_xlfn.XLOOKUP(T63,K:K,J:J,0,0,1)) -> 0 | V63: =M63&O63&Q63&S63&U63 -> 115914400 | X63: =_xlfn.SINGLE(_xlfn.XLOOKUP(Y63,B:B,A:A,0,0,1)) -> 2 | Y63: Inc | Z63: 70060 | AA63: Sales | AB63: =_xlfn.SINGLE(_xlfn.XLOOKUP(AA63,E:E,D:D,0,0,1)) -> 50 | AC63: T&E | AD63: =_xlfn.SINGLE(_xlfn.XLOOKUP(AC63,H:H,G:G,0,0,1)) -> 124 | AF63: =_xlfn.SINGLE(_xlfn.XLOOKUP(AE63,K:K,J:J,0,0,1)) -> 0 | AG63: =X63&Z63&AB63&AD63&AF63 -> 270060501240
M64: =_xlfn.SINGLE(_xlfn.XLOOKUP(N64,B:B,A:A,0,0,1)) -> 1 | N64: Ltd | O64: 35000 | P64: Accrued expenses and other payable | Q64: =_xlfn.SINGLE(_xlfn.XLOOKUP(P64,E:E,D:D,0,0,1)) -> 7 | R64: Accrued Expenses | S64: =_xlfn.SINGLE(_xlfn.XLOOKUP(R64,H:H,G:G,0,0,1)) -> 100 | U64: =_xlfn.SINGLE(_xlfn.XLOOKUP(T64,K:K,J:J,0,0,1)) -> 0 | V64: 13500071000 | X64: =_xlfn.SINGLE(_xlfn.XLOOKUP(Y64,B:B,A:A,0,0,1)) -> 2 | Y64: Inc | Z64: 70065 | AA64: Sales | AB64: =_xlfn.SINGLE(_xlfn.XLOOKUP(AA64,E:E,D:D,0,0,1)) -> 50 | AC64: Other Sales | AD64: =_xlfn.SINGLE(_xlfn.XLOOKUP(AC64,H:H,G:G,0,0,1)) -> 125 | AF64: =_xlfn.SINGLE(_xlfn.XLOOKUP(AE64,K:K,J:J,0,0,1)) -> 0 | AG64: =X64&Z64&AB64&AD64&AF64 -> 270065501250
M65: =_xlfn.SINGLE(_xlfn.XLOOKUP(N65,B:B,A:A,0,0,1)) -> 1 | N65: Ltd | O65: 35001 | P65: Accrued expenses and other payable | Q65: =_xlfn.SINGLE(_xlfn.XLOOKUP(P65,E:E,D:D,0,0,1)) -> 7 | R65: Accrued Expenses | S65: =_xlfn.SINGLE(_xlfn.XLOOKUP(R65,H:H,G:G,0,0,1)) -> 100 | U65: =_xlfn.SINGLE(_xlfn.XLOOKUP(T65,K:K,J:J,0,0,1)) -> 0 | V65: =M65&O65&Q65&S65&U65 -> 13500171000 | X65: =_xlfn.SINGLE(_xlfn.XLOOKUP(Y65,B:B,A:A,0,0,1)) -> 2 | Y65: Inc | Z65: 70070 | AA65: Sales | AB65: =_xlfn.SINGLE(_xlfn.XLOOKUP(AA65,E:E,D:D,0,0,1)) -> 50 | AC65: Other Sales | AD65: =_xlfn.SINGLE(_xlfn.XLOOKUP(AC65,H:H,G:G,0,0,1)) -> 125 | AF65: =_xlfn.SINGLE(_xlfn.XLOOKUP(AE65,K:K,J:J,0,0,1)) -> 0 | AG65: =X65&Z65&AB65&AD65&AF65 -> 270070501250
M66: =_xlfn.SINGLE(_xlfn.XLOOKUP(N66,B:B,A:A,0,0,1)) -> 1 | N66: Ltd | O66: 35006 | P66: Accrued expenses and other payable | Q66: =_xlfn.SINGLE(_xlfn.XLOOKUP(P66,E:E,D:D,0,0,1)) -> 7 | R66: Accrued Expenses | S66: =_xlfn.SINGLE(_xlfn.XLOOKUP(R66,H:H,G:G,0,0,1)) -> 100 | U66: =_xlfn.SINGLE(_xlfn.XLOOKUP(T66,K:K,J:J,0,0,1)) -> 0 | V66: =M66&O66&Q66&S66&U66 -> 13500671000 | X66: =_xlfn.SINGLE(_xlfn.XLOOKUP(Y66,B:B,A:A,0,0,1)) -> 2 | Y66: Inc | Z66: 70076 | AA66: Sales | AB66: =_xlfn.SINGLE(_xlfn.XLOOKUP(AA66,E:E,D:D,0,0,1)) -> 50 | AC66: Software | AD66: =_xlfn.SINGLE(_xlfn.XLOOKUP(AC66,H:H,G:G,0,0,1)) -> 123 | AF66: =_xlfn.SINGLE(_xlfn.XLOOKUP(AE66,K:K,J:J,0,0,1)) -> 0 | AG66: =X66&Z66&AB66&AD66&AF66 -> 270076501230
M67: =_xlfn.SINGLE(_xlfn.XLOOKUP(N67,B:B,A:A,0,0,1)) -> 1 | N67: Ltd | O67: 35008 | P67: Employees Payable | Q67: =_xlfn.SINGLE(_xlfn.XLOOKUP(P67,E:E,D:D,0,0,1)) -> 8 | S67: =_xlfn.SINGLE(_xlfn.XLOOKUP(R67,H:H,G:G,0,0,1)) -> 0 | U67: =_xlfn.SINGLE(_xlfn.XLOOKUP(T67,K:K,J:J,0,0,1)) -> 0 | V67: =M67&O67&Q67&S67&U67 -> 135008800 | X67: =_xlfn.SINGLE(_xlfn.XLOOKUP(Y67,B:B,A:A,0,0,1)) -> 2 | Y67: Inc | Z67: 70091 | AA67: Sales | AB67: =_xlfn.SINGLE(_xlfn.XLOOKUP(AA67,E:E,D:D,0,0,1)) -> 50 | AC67: Software | AD67: =_xlfn.SINGLE(_xlfn.XLOOKUP(AC67,H:H,G:G,0,0,1)) -> 123 | AF67: =_xlfn.SINGLE(_xlfn.XLOOKUP(AE67,K:K,J:J,0,0,1)) -> 0 | AG67: =X67&Z67&AB67&AD67&AF67 -> 270091501230
M68: =_xlfn.SINGLE(_xlfn.XLOOKUP(N68,B:B,A:A,0,0,1)) -> 1 | N68: Ltd | O68: 35009 | P68: Employees Payable | Q68: =_xlfn.SINGLE(_xlfn.XLOOKUP(P68,E:E,D:D,0,0,1)) -> 8 | S68: =_xlfn.SINGLE(_xlfn.XLOOKUP(R68,H:H,G:G,0,0,1)) -> 0 | U68: =_xlfn.SINGLE(_xlfn.XLOOKUP(T68,K:K,J:J,0,0,1)) -> 0 | V68: =M68&O68&Q68&S68&U68 -> 135009800 | X68: =_xlfn.SINGLE(_xlfn.XLOOKUP(Y68,B:B,A:A,0,0,1)) -> 2 | Y68: Inc | Z68: 70095 | AA68: Overhead | AB68: =_xlfn.SINGLE(_xlfn.XLOOKUP(AA68,E:E,D:D,0,0,1)) -> 99 | AD68: =_xlfn.SINGLE(_xlfn.XLOOKUP(AC68,H:H,G:G,0,0,1)) -> 0 | AF68: =_xlfn.SINGLE(_xlfn.XLOOKUP(AE68,K:K,J:J,0,0,1)) -> 0 | AG68: =X68&Z68&AB68&AD68&AF68 -> 2700959900
M69: =_xlfn.SINGLE(_xlfn.XLOOKUP(N69,B:B,A:A,0,0,1)) -> 1 | N69: Ltd | O69: 35010 | P69: Deferred Revenue | Q69: =_xlfn.SINGLE(_xlfn.XLOOKUP(P69,E:E,D:D,0,0,1)) -> 9 | S69: =_xlfn.SINGLE(_xlfn.XLOOKUP(R69,H:H,G:G,0,0,1)) -> 0 | U69: =_xlfn.SINGLE(_xlfn.XLOOKUP(T69,K:K,J:J,0,0,1)) -> 0 | V69: =M69&O69&Q69&S69&U69 -> 135010900 | X69: =_xlfn.SINGLE(_xlfn.XLOOKUP(Y69,B:B,A:A,0,0,1)) -> 2 | Y69: Inc | Z69: 70100 | AA69: Sales | AB69: =_xlfn.SINGLE(_xlfn.XLOOKUP(AA69,E:E,D:D,0,0,1)) -> 50 | AC69: Recruiting | AD69: =_xlfn.SINGLE(_xlfn.XLOOKUP(AC69,H:H,G:G,0,0,1)) -> 119 | AF69: =_xlfn.SINGLE(_xlfn.XLOOKUP(AE69,K:K,J:J,0,0,1)) -> 0 | AG69: =X69&Z69&AB69&AD69&AF69 -> 270100501190
M70: =_xlfn.SINGLE(_xlfn.XLOOKUP(N70,B:B,A:A,0,0,1)) -> 1 | N70: Ltd | O70: 35016 | P70: Employees Payable | Q70: =_xlfn.SINGLE(_xlfn.XLOOKUP(P70,E:E,D:D,0,0,1)) -> 8 | S70: =_xlfn.SINGLE(_xlfn.XLOOKUP(R70,H:H,G:G,0,0,1)) -> 0 | U70: =_xlfn.SINGLE(_xlfn.XLOOKUP(T70,K:K,J:J,0,0,1)) -> 0 | V70: =M70&O70&Q70&S70&U70 -> 135016800 | X70: =_xlfn.SINGLE(_xlfn.XLOOKUP(Y70,B:B,A:A,0,0,1)) -> 2 | Y70: Inc | Z70: 70105 | AA70: Sales | AB70: =_xlfn.SINGLE(_xlfn.XLOOKUP(AA70,E:E,D:D,0,0,1)) -> 50 | AC70: Referral Fees | AD70: =_xlfn.SINGLE(_xlfn.XLOOKUP(AC70,H:H,G:G,0,0,1)) -> 126 | AF70: =_xlfn.SINGLE(_xlfn.XLOOKUP(AE70,K:K,J:J,0,0,1)) -> 0 | AG70: =X70&Z70&AB70&AD70&AF70 -> 270105501260
M71: =_xlfn.SINGLE(_xlfn.XLOOKUP(N71,B:B,A:A,0,0,1)) -> 1 | N71: Ltd | O71: 35017 | P71: Employees Payable | Q71: =_xlfn.SINGLE(_xlfn.XLOOKUP(P71,E:E,D:D,0,0,1)) -> 8 | S71: =_xlfn.SINGLE(_xlfn.XLOOKUP(R71,H:H,G:G,0,0,1)) -> 0 | U71: =_xlfn.SINGLE(_xlfn.XLOOKUP(T71,K:K,J:J,0,0,1)) -> 0 | V71: =M71&O71&Q71&S71&U71 -> 135017800 | X71: =_xlfn.SINGLE(_xlfn.XLOOKUP(Y71,B:B,A:A,0,0,1)) -> 2 | Y71: Inc | Z71: 72005 | AA71: Marketing | AB71: =_xlfn.SINGLE(_xlfn.XLOOKUP(AA71,E:E,D:D,0,0,1)) -> 60 | AC71: Payroll & Payroll related | AD71: =_xlfn.SINGLE(_xlfn.XLOOKUP(AC71,H:H,G:G,0,0,1)) -> 116 | AF71: =_xlfn.SINGLE(_xlfn.XLOOKUP(AE71,K:K,J:J,0,0,1)) -> 0 | AG71: =X71&Z71&AB71&AD71&AF71 -> 272005601160
M72: =_xlfn.SINGLE(_xlfn.XLOOKUP(N72,B:B,A:A,0,0,1)) -> 1 | N72: Ltd | O72: 30002 | P72: Accounts Payable | Q72: =_xlfn.SINGLE(_xlfn.XLOOKUP(P72,E:E,D:D,0,0,1)) -> 6 | S72: =_xlfn.SINGLE(_xlfn.XLOOKUP(R72,H:H,G:G,0,0,1)) -> 0 | U72: =_xlfn.SINGLE(_xlfn.XLOOKUP(T72,K:K,J:J,0,0,1)) -> 0 | V72: =M72&O72&Q72&S72&U72 -> 130002600 | X72: =_xlfn.SINGLE(_xlfn.XLOOKUP(Y72,B:B,A:A,0,0,1)) -> 2 | Y72: Inc | Z72: 72010 | AA72: Marketing | AB72: =_xlfn.SINGLE(_xlfn.XLOOKUP(AA72,E:E,D:D,0,0,1)) -> 60 | AC72: Payroll & Payroll related | AD72: =_xlfn.SINGLE(_xlfn.XLOOKUP(AC72,H:H,G:G,0,0,1)) -> 116 | AF72: =_xlfn.SINGLE(_xlfn.XLOOKUP(AE72,K:K,J:J,0,0,1)) -> 0 | AG72: =X72&Z72&AB72&AD72&AF72 -> 272010601160
M73: =_xlfn.SINGLE(_xlfn.XLOOKUP(N73,B:B,A:A,0,0,1)) -> 1 | N73: Ltd | O73: 30018 | P73: Accounts Payable | Q73: =_xlfn.SINGLE(_xlfn.XLOOKUP(P73,E:E,D:D,0,0,1)) -> 6 | S73: =_xlfn.SINGLE(_xlfn.XLOOKUP(R73,H:H,G:G,0,0,1)) -> 0 | U73: =_xlfn.SINGLE(_xlfn.XLOOKUP(T73,K:K,J:J,0,0,1)) -> 0 | V73: =M73&O73&Q73&S73&U73 -> 130018600 | X73: =_xlfn.SINGLE(_xlfn.XLOOKUP(Y73,B:B,A:A,0,0,1)) -> 2 | Y73: Inc | Z73: 72020 | AA73: Marketing | AB73: =_xlfn.SINGLE(_xlfn.XLOOKUP(AA73,E:E,D:D,0,0,1)) -> 60 | AC73: Payroll & Payroll related | AD73: =_xlfn.SINGLE(_xlfn.XLOOKUP(AC73,H:H,G:G,0,0,1)) -> 116 | AF73: =_xlfn.SINGLE(_xlfn.XLOOKUP(AE73,K:K,J:J,0,0,1)) -> 0 | AG73: =X73&Z73&AB73&AD73&AF73 -> 272020601160
M74: =_xlfn.SINGLE(_xlfn.XLOOKUP(N74,B:B,A:A,0,0,1)) -> 1 | N74: Ltd | O74: 30021 | P74: Accounts Payable | Q74: =_xlfn.SINGLE(_xlfn.XLOOKUP(P74,E:E,D:D,0,0,1)) -> 6 | S74: =_xlfn.SINGLE(_xlfn.XLOOKUP(R74,H:H,G:G,0,0,1)) -> 0 | U74: =_xlfn.SINGLE(_xlfn.XLOOKUP(T74,K:K,J:J,0,0,1)) -> 0 | V74: =M74&O74&Q74&S74&U74 -> 130021600 | X74: =_xlfn.SINGLE(_xlfn.XLOOKUP(Y74,B:B,A:A,0,0,1)) -> 2 | Y74: Inc | Z74: 72024 | AA74: Marketing | AB74: =_xlfn.SINGLE(_xlfn.XLOOKUP(AA74,E:E,D:D,0,0,1)) -> 60 | AC74: Payroll & Payroll related | AD74: =_xlfn.SINGLE(_xlfn.XLOOKUP(AC74,H:H,G:G,0,0,1)) -> 116 | AF74: =_xlfn.SINGLE(_xlfn.XLOOKUP(AE74,K:K,J:J,0,0,1)) -> 0 | AG74: =X74&Z74&AB74&AD74&AF74 -> 272024601160
M75: =_xlfn.SINGLE(_xlfn.XLOOKUP(N75,B:B,A:A,0,0,1)) -> 1 | N75: Ltd | O75: 30028 | P75: Accounts Payable | Q75: =_xlfn.SINGLE(_xlfn.XLOOKUP(P75,E:E,D:D,0,0,1)) -> 6 | S75: =_xlfn.SINGLE(_xlfn.XLOOKUP(R75,H:H,G:G,0,0,1)) -> 0 | U75: =_xlfn.SINGLE(_xlfn.XLOOKUP(T75,K:K,J:J,0,0,1)) -> 0 | V75: =M75&O75&Q75&S75&U75 -> 130028600 | X75: =_xlfn.SINGLE(_xlfn.XLOOKUP(Y75,B:B,A:A,0,0,1)) -> 2 | Y75: Inc | Z75: 72025 | AA75: Marketing | AB75: =_xlfn.SINGLE(_xlfn.XLOOKUP(AA75,E:E,D:D,0,0,1)) -> 60 | AC75: Payroll & Payroll related | AD75: =_xlfn.SINGLE(_xlfn.XLOOKUP(AC75,H:H,G:G,0,0,1)) -> 116 | AF75: =_xlfn.SINGLE(_xlfn.XLOOKUP(AE75,K:K,J:J,0,0,1)) -> 0 | AG75: =X75&Z75&AB75&AD75&AF75 -> 272025601160
M76: =_xlfn.SINGLE(_xlfn.XLOOKUP(N76,B:B,A:A,0,0,1)) -> 1 | N76: Ltd | O76: 30033 | P76: Accounts Payable | Q76: =_xlfn.SINGLE(_xlfn.XLOOKUP(P76,E:E,D:D,0,0,1)) -> 6 | S76: =_xlfn.SINGLE(_xlfn.XLOOKUP(R76,H:H,G:G,0,0,1)) -> 0 | U76: =_xlfn.SINGLE(_xlfn.XLOOKUP(T76,K:K,J:J,0,0,1)) -> 0 | V76: =M76&O76&Q76&S76&U76 -> 130033600 | X76: =_xlfn.SINGLE(_xlfn.XLOOKUP(Y76,B:B,A:A,0,0,1)) -> 2 | Y76: Inc | Z76: 72030 | AA76: Marketing | AB76: =_xlfn.SINGLE(_xlfn.XLOOKUP(AA76,E:E,D:D,0,0,1)) -> 60 | AC76: Payroll & Payroll related | AD76: =_xlfn.SINGLE(_xlfn.XLOOKUP(AC76,H:H,G:G,0,0,1)) -> 116 | AF76: =_xlfn.SINGLE(_xlfn.XLOOKUP(AE76,K:K,J:J,0,0,1)) -> 0 | AG76: =X76&Z76&AB76&AD76&AF76 -> 272030601160
M77: =_xlfn.SINGLE(_xlfn.XLOOKUP(N77,B:B,A:A,0,0,1)) -> 1 | N77: Ltd | O77: 30036 | P77: Accounts Payable | Q77: =_xlfn.SINGLE(_xlfn.XLOOKUP(P77,E:E,D:D,0,0,1)) -> 6 | S77: =_xlfn.SINGLE(_xlfn.XLOOKUP(R77,H:H,G:G,0,0,1)) -> 0 | U77: =_xlfn.SINGLE(_xlfn.XLOOKUP(T77,K:K,J:J,0,0,1)) -> 0 | V77: =M77&O77&Q77&S77&U77 -> 130036600 | X77: =_xlfn.SINGLE(_xlfn.XLOOKUP(Y77,B:B,A:A,0,0,1)) -> 2 | Y77: Inc | Z77: 72040 | AA77: Marketing | AB77: =_xlfn.SINGLE(_xlfn.XLOOKUP(AA77,E:E,D:D,0,0,1)) -> 60 | AC77: T&E | AD77: =_xlfn.SINGLE(_xlfn.XLOOKUP(AC77,H:H,G:G,0,0,1)) -> 124 | AF77: =_xlfn.SINGLE(_xlfn.XLOOKUP(AE77,K:K,J:J,0,0,1)) -> 0 | AG77: =X77&Z77&AB77&AD77&AF77 -> 272040601240
M78: =_xlfn.SINGLE(_xlfn.XLOOKUP(N78,B:B,A:A,0,0,1)) -> 1 | N78: Ltd | O78: 30043 | P78: Accounts Payable | Q78: =_xlfn.SINGLE(_xlfn.XLOOKUP(P78,E:E,D:D,0,0,1)) -> 6 | S78: =_xlfn.SINGLE(_xlfn.XLOOKUP(R78,H:H,G:G,0,0,1)) -> 0 | U78: =_xlfn.SINGLE(_xlfn.XLOOKUP(T78,K:K,J:J,0,0,1)) -> 0 | V78: =M78&O78&Q78&S78&U78 -> 130043600 | X78: =_xlfn.SINGLE(_xlfn.XLOOKUP(Y78,B:B,A:A,0,0,1)) -> 2 | Y78: Inc | Z78: 72070 | AA78: Marketing | AB78: =_xlfn.SINGLE(_xlfn.XLOOKUP(AA78,E:E,D:D,0,0,1)) -> 60 | AC78: Other Marketing | AD78: =_xlfn.SINGLE(_xlfn.XLOOKUP(AC78,H:H,G:G,0,0,1)) -> 113 | AF78: =_xlfn.SINGLE(_xlfn.XLOOKUP(AE78,K:K,J:J,0,0,1)) -> 0 | AG78: =X78&Z78&AB78&AD78&AF78 -> 272070601130
M79: =_xlfn.SINGLE(_xlfn.XLOOKUP(N79,B:B,A:A,0,0,1)) -> 1 | N79: Ltd | O79: 30044 | P79: Accounts Payable | Q79: =_xlfn.SINGLE(_xlfn.XLOOKUP(P79,E:E,D:D,0,0,1)) -> 6 | S79: =_xlfn.SINGLE(_xlfn.XLOOKUP(R79,H:H,G:G,0,0,1)) -> 0 | U79: =_xlfn.SINGLE(_xlfn.XLOOKUP(T79,K:K,J:J,0,0,1)) -> 0 | V79: =M79&O79&Q79&S79&U79 -> 130044600 | X79: =_xlfn.SINGLE(_xlfn.XLOOKUP(Y79,B:B,A:A,0,0,1)) -> 2 | Y79: Inc | Z79: 72080 | AA79: Marketing | AB79: =_xlfn.SINGLE(_xlfn.XLOOKUP(AA79,E:E,D:D,0,0,1)) -> 60 | AC79: Other Marketing | AD79: =_xlfn.SINGLE(_xlfn.XLOOKUP(AC79,H:H,G:G,0,0,1)) -> 113 | AF79: =_xlfn.SINGLE(_xlfn.XLOOKUP(AE79,K:K,J:J,0,0,1)) -> 0 | AG79: =X79&Z79&AB79&AD79&AF79 -> 272080601130
M80: =_xlfn.SINGLE(_xlfn.XLOOKUP(N80,B:B,A:A,0,0,1)) -> 1 | N80: Ltd | O80: 30046 | P80: Accounts Payable | Q80: =_xlfn.SINGLE(_xlfn.XLOOKUP(P80,E:E,D:D,0,0,1)) -> 6 | S80: =_xlfn.SINGLE(_xlfn.XLOOKUP(R80,H:H,G:G,0,0,1)) -> 0 | U80: =_xlfn.SINGLE(_xlfn.XLOOKUP(T80,K:K,J:J,0,0,1)) -> 0 | V80: =M80&O80&Q80&S80&U80 -> 130046600 | X80: =_xlfn.SINGLE(_xlfn.XLOOKUP(Y80,B:B,A:A,0,0,1)) -> 2 | Y80: Inc | Z80: 72200 | AA80: Marketing | AB80: =_xlfn.SINGLE(_xlfn.XLOOKUP(AA80,E:E,D:D,0,0,1)) -> 60 | AC80: Other Marketing | AD80: =_xlfn.SINGLE(_xlfn.XLOOKUP(AC80,H:H,G:G,0,0,1)) -> 113 | AF80: =_xlfn.SINGLE(_xlfn.XLOOKUP(AE80,K:K,J:J,0,0,1)) -> 0 | AG80: =X80&Z80&AB80&AD80&AF80 -> 272200601130
... M101: =_xlfn.SINGLE(_xlfn.XLOOKUP(N101,B:B,A:A,0,0,1)) -> 1 | N101: Ltd | O101: 30242 | P101: Accounts Payable | Q101: =_xlfn.SINGLE(_xlfn.XLOOKUP(P101,E:E,D:D,0,0,1)) -> 6 | S101: =_xlfn.SINGLE(_xlfn.XLOOKUP(R101,H:H,G:G,0,0,1)) -> 0 | U101: =_xlfn.SINGLE(_xlfn.XLOOKUP(T101,K:K,J:J,0,0,1)) -> 0 | V101: =M101&O101&Q101&S101&U101 -> 130242600 | X101: =_xlfn.SINGLE(_xlfn.XLOOKUP(Y101,B:B,A:A,0,0,1)) -> 2 | Y101: Inc | Z101: 80040 | AA101: G&A | AB101: =_xlfn.SINGLE(_xlfn.XLOOKUP(AA101,E:E,D:D,0,0,1)) -> 70 | AC101: T&E | AD101: =_xlfn.SINGLE(_xlfn.XLOOKUP(AC101,H:H,G:G,0,0,1)) -> 124 | AF101: =_xlfn.SINGLE(_xlfn.XLOOKUP(AE101,K:K,J:J,0,0,1)) -> 0 | AG101: =X101&Z101&AB101&AD101&AF101 -> 280040701240
M102: =_xlfn.SINGLE(_xlfn.XLOOKUP(N102,B:B,A:A,0,0,1)) -> 1 | N102: Ltd | O102: 30245 | P102: Accounts Payable | Q102: =_xlfn.SINGLE(_xlfn.XLOOKUP(P102,E:E,D:D,0,0,1)) -> 6 | S102: =_xlfn.SINGLE(_xlfn.XLOOKUP(R102,H:H,G:G,0,0,1)) -> 0 | U102: =_xlfn.SINGLE(_xlfn.XLOOKUP(T102,K:K,J:J,0,0,1)) -> 0 | V102: =M102&O102&Q102&S102&U102 -> 130245600 | X102: =_xlfn.SINGLE(_xlfn.XLOOKUP(Y102,B:B,A:A,0,0,1)) -> 2 | Y102: Inc | Z102: 80061 | AA102: Overhead | AB102: =_xlfn.SINGLE(_xlfn.XLOOKUP(AA102,E:E,D:D,0,0,1)) -> 99 | AD102: =_xlfn.SINGLE(_xlfn.XLOOKUP(AC102,H:H,G:G,0,0,1)) -> 0 | AF102: =_xlfn.SINGLE(_xlfn.XLOOKUP(AE102,K:K,J:J,0,0,1)) -> 0 | AG102: =X102&Z102&AB102&AD102&AF102 -> 2800619900
M103: =_xlfn.SINGLE(_xlfn.XLOOKUP(N103,B:B,A:A,0,0,1)) -> 1 | N103: Ltd | O103: 30250 | P103: Accounts Payable | Q103: =_xlfn.SINGLE(_xlfn.XLOOKUP(P103,E:E,D:D,0,0,1)) -> 6 | S103: =_xlfn.SINGLE(_xlfn.XLOOKUP(R103,H:H,G:G,0,0,1)) -> 0 | U103: =_xlfn.SINGLE(_xlfn.XLOOKUP(T103,K:K,J:J,0,0,1)) -> 0 | V103: =M103&O103&Q103&S103&U103 -> 130250600 | X103: =_xlfn.SINGLE(_xlfn.XLOOKUP(Y103,B:B,A:A,0,0,1)) -> 2 | Y103: Inc | Z103: 80080 | AA103: G&A | AB103: =_xlfn.SINGLE(_xlfn.XLOOKUP(AA103,E:E,D:D,0,0,1)) -> 70 | AD103: =_xlfn.SINGLE(_xlfn.XLOOKUP(AC103,H:H,G:G,0,0,1)) -> 0 | AF103: =_xlfn.SINGLE(_xlfn.XLOOKUP(AE103,K:K,J:J,0,0,1)) -> 0 | AG103: =X103&Z103&AB103&AD103&AF103 -> 2800807000
M104: =_xlfn.SINGLE(_xlfn.XLOOKUP(N104,B:B,A:A,0,0,1)) -> 1 | N104: Ltd | O104: 30258 | P104: Accounts Payable | Q104: =_xlfn.SINGLE(_xlfn.XLOOKUP(P104,E:E,D:D,0,0,1)) -> 6 | S104: =_xlfn.SINGLE(_xlfn.XLOOKUP(R104,H:H,G:G,0,0,1)) -> 0 | U104: =_xlfn.SINGLE(_xlfn.XLOOKUP(T104,K:K,J:J,0,0,1)) -> 0 | V104: =M104&O104&Q104&S104&U104 -> 130258600 | X104: =_xlfn.SINGLE(_xlfn.XLOOKUP(Y104,B:B,A:A,0,0,1)) -> 2 | Y104: Inc | Z104: 80095 | AA104: Overhead | AB104: =_xlfn.SINGLE(_xlfn.XLOOKUP(AA104,E:E,D:D,0,0,1)) -> 99 | AD104: =_xlfn.SINGLE(_xlfn.XLOOKUP(AC104,H:H,G:G,0,0,1)) -> 0 | AF104: =_xlfn.SINGLE(_xlfn.XLOOKUP(AE104,K:K,J:J,0,0,1)) -> 0 | AG104: =X104&Z104&AB104&AD104&AF104 -> 2800959900
M105: =_xlfn.SINGLE(_xlfn.XLOOKUP(N105,B:B,A:A,0,0,1)) -> 1 | N105: Ltd | O105: 30268 | P105: Accounts Payable | Q105: =_xlfn.SINGLE(_xlfn.XLOOKUP(P105,E:E,D:D,0,0,1)) -> 6 | S105: =_xlfn.SINGLE(_xlfn.XLOOKUP(R105,H:H,G:G,0,0,1)) -> 0 | U105: =_xlfn.SINGLE(_xlfn.XLOOKUP(T105,K:K,J:J,0,0,1)) -> 0 | V105: =M105&O105&Q105&S105&U105 -> 130268600 | X105: =_xlfn.SINGLE(_xlfn.XLOOKUP(Y105,B:B,A:A,0,0,1)) -> 2 | Y105: Inc | Z105: 80110 | AA105: Overhead | AB105: =_xlfn.SINGLE(_xlfn.XLOOKUP(AA105,E:E,D:D,0,0,1)) -> 99 | AD105: =_xlfn.SINGLE(_xlfn.XLOOKUP(AC105,H:H,G:G,0,0,1)) -> 0 | AF105: =_xlfn.SINGLE(_xlfn.XLOOKUP(AE105,K:K,J:J,0,0,1)) -> 0 | AG105: =X105&Z105&AB105&AD105&AF105 -> 2801109900
M106: =_xlfn.SINGLE(_xlfn.XLOOKUP(N106,B:B,A:A,0,0,1)) -> 1 | N106: Ltd | O106: 30274 | P106: Accounts Payable | Q106: =_xlfn.SINGLE(_xlfn.XLOOKUP(P106,E:E,D:D,0,0,1)) -> 6 | S106: =_xlfn.SINGLE(_xlfn.XLOOKUP(R106,H:H,G:G,0,0,1)) -> 0 | U106: =_xlfn.SINGLE(_xlfn.XLOOKUP(T106,K:K,J:J,0,0,1)) -> 0 | V106: =M106&O106&Q106&S106&U106 -> 130274600 | X106: =_xlfn.SINGLE(_xlfn.XLOOKUP(Y106,B:B,A:A,0,0,1)) -> 2 | Y106: Inc | Z106: 80210 | AA106: G&A | AB106: =_xlfn.SINGLE(_xlfn.XLOOKUP(AA106,E:E,D:D,0,0,1)) -> 70 | AC106: Contractors & Services | AD106: =_xlfn.SINGLE(_xlfn.XLOOKUP(AC106,H:H,G:G,0,0,1)) -> 102 | AF106: =_xlfn.SINGLE(_xlfn.XLOOKUP(AE106,K:K,J:J,0,0,1)) -> 0 | AG106: =X106&Z106&AB106&AD106&AF106 -> 280210701020
M107: =_xlfn.SINGLE(_xlfn.XLOOKUP(N107,B:B,A:A,0,0,1)) -> 1 | N107: Ltd | O107: 30289 | P107: Accounts Payable | Q107: =_xlfn.SINGLE(_xlfn.XLOOKUP(P107,E:E,D:D,0,0,1)) -> 6 | S107: =_xlfn.SINGLE(_xlfn.XLOOKUP(R107,H:H,G:G,0,0,1)) -> 0 | U107: =_xlfn.SINGLE(_xlfn.XLOOKUP(T107,K:K,J:J,0,0,1)) -> 0 | V107: =M107&O107&Q107&S107&U107 -> 130289600 | X107: =_xlfn.SINGLE(_xlfn.XLOOKUP(Y107,B:B,A:A,0,0,1)) -> 2 | Y107: Inc | Z107: 80220 | AA107: G&A | AB107: =_xlfn.SINGLE(_xlfn.XLOOKUP(AA107,E:E,D:D,0,0,1)) -> 70 | AC107: Contractors & Services | AD107: =_xlfn.SINGLE(_xlfn.XLOOKUP(AC107,H:H,G:G,0,0,1)) -> 102 | AF107: =_xlfn.SINGLE(_xlfn.XLOOKUP(AE107,K:K,J:J,0,0,1)) -> 0 | AG107: =X107&Z107&AB107&AD107&AF107 -> 280220701020
M108: =_xlfn.SINGLE(_xlfn.XLOOKUP(N108,B:B,A:A,0,0,1)) -> 1 | N108: Ltd | O108: 30299 | P108: Accounts Payable | Q108: =_xlfn.SINGLE(_xlfn.XLOOKUP(P108,E:E,D:D,0,0,1)) -> 6 | S108: =_xlfn.SINGLE(_xlfn.XLOOKUP(R108,H:H,G:G,0,0,1)) -> 0 | U108: =_xlfn.SINGLE(_xlfn.XLOOKUP(T108,K:K,J:J,0,0,1)) -> 0 | V108: =M108&O108&Q108&S108&U108 -> 130299600 | X108: =_xlfn.SINGLE(_xlfn.XLOOKUP(Y108,B:B,A:A,0,0,1)) -> 2 | Y108: Inc | Z108: 80250 | AA108: Overhead | AB108: =_xlfn.SINGLE(_xlfn.XLOOKUP(AA108,E:E,D:D,0,0,1)) -> 99 | AD108: =_xlfn.SINGLE(_xlfn.XLOOKUP(AC108,H:H,G:G,0,0,1)) -> 0 | AF108: =_xlfn.SINGLE(_xlfn.XLOOKUP(AE108,K:K,J:J,0,0,1)) -> 0 | AG108: =X108&Z108&AB108&AD108&AF108 -> 2802509900
M109: =_xlfn.SINGLE(_xlfn.XLOOKUP(N109,B:B,A:A,0,0,1)) -> 1 | N109: Ltd | O109: 30301 | P109: Accounts Payable | Q109: =_xlfn.SINGLE(_xlfn.XLOOKUP(P109,E:E,D:D,0,0,1)) -> 6 | S109: =_xlfn.SINGLE(_xlfn.XLOOKUP(R109,H:H,G:G,0,0,1)) -> 0 | U109: =_xlfn.SINGLE(_xlfn.XLOOKUP(T109,K:K,J:J,0,0,1)) -> 0 | V109: =M109&O109&Q109&S109&U109 -> 130301600 | X109: =_xlfn.SINGLE(_xlfn.XLOOKUP(Y109,B:B,A:A,0,0,1)) -> 2 | Y109: Inc | Z109: 80260 | AA109: G&A | AB109: =_xlfn.SINGLE(_xlfn.XLOOKUP(AA109,E:E,D:D,0,0,1)) -> 70 | AD109: =_xlfn.SINGLE(_xlfn.XLOOKUP(AC109,H:H,G:G,0,0,1)) -> 0 | AF109: =_xlfn.SINGLE(_xlfn.XLOOKUP(AE109,K:K,J:J,0,0,1)) -> 0 | AG109: =X109&Z109&AB109&AD109&AF109 -> 2802607000
M110: =_xlfn.SINGLE(_xlfn.XLOOKUP(N110,B:B,A:A,0,0,1)) -> 1 | N110: Ltd | O110: 30306 | P110: Accounts Payable | Q110: =_xlfn.SINGLE(_xlfn.XLOOKUP(P110,E:E,D:D,0,0,1)) -> 6 | S110: =_xlfn.SINGLE(_xlfn.XLOOKUP(R110,H:H,G:G,0,0,1)) -> 0 | U110: =_xlfn.SINGLE(_xlfn.XLOOKUP(T110,K:K,J:J,0,0,1)) -> 0 | V110: =M110&O110&Q110&S110&U110 -> 130306600 | X110: =_xlfn.SINGLE(_xlfn.XLOOKUP(Y110,B:B,A:A,0,0,1)) -> 2 | Y110: Inc | Z110: 80261 | AA110: Overhead | AB110: =_xlfn.SINGLE(_xlfn.XLOOKUP(AA110,E:E,D:D,0,0,1)) -> 99 | AD110: =_xlfn.SINGLE(_xlfn.XLOOKUP(AC110,H:H,G:G,0,0,1)) -> 0 | AF110: =_xlfn.SINGLE(_xlfn.XLOOKUP(AE110,K:K,J:J,0,0,1)) -> 0 | AG110: =X110&Z110&AB110&AD110&AF110 -> 2802619900
M111: =_xlfn.SINGLE(_xlfn.XLOOKUP(N111,B:B,A:A,0,0,1)) -> 1 | N111: Ltd | O111: 30312 | P111: Accounts Payable | Q111: =_xlfn.SINGLE(_xlfn.XLOOKUP(P111,E:E,D:D,0,0,1)) -> 6 | S111: =_xlfn.SINGLE(_xlfn.XLOOKUP(R111,H:H,G:G,0,0,1)) -> 0 | U111: =_xlfn.SINGLE(_xlfn.XLOOKUP(T111,K:K,J:J,0,0,1)) -> 0 | V111: =M111&O111&Q111&S111&U111 -> 130312600 | X111: =_xlfn.SINGLE(_xlfn.XLOOKUP(Y111,B:B,A:A,0,0,1)) -> 2 | Y111: Inc | Z111: 91000 | AA111: Finance | AB111: =_xlfn.SINGLE(_xlfn.XLOOKUP(AA111,E:E,D:D,0,0,1)) -> 90 | AD111: =_xlfn.SINGLE(_xlfn.XLOOKUP(AC111,H:H,G:G,0,0,1)) -> 0 | AF111: =_xlfn.SINGLE(_xlfn.XLOOKUP(AE111,K:K,J:J,0,0,1)) -> 0 | AG111: =X111&Z111&AB111&AD111&AF111 -> 2910009000
M112: =_xlfn.SINGLE(_xlfn.XLOOKUP(N112,B:B,A:A,0,0,1)) -> 1 | N112: Ltd | O112: 30318 | P112: Accounts Payable | Q112: =_xlfn.SINGLE(_xlfn.XLOOKUP(P112,E:E,D:D,0,0,1)) -> 6 | S112: =_xlfn.SINGLE(_xlfn.XLOOKUP(R112,H:H,G:G,0,0,1)) -> 0 | U112: =_xlfn.SINGLE(_xlfn.XLOOKUP(T112,K:K,J:J,0,0,1)) -> 0 | V112: =M112&O112&Q112&S112&U112 -> 130318600 | X112: =_xlfn.SINGLE(_xlfn.XLOOKUP(Y112,B:B,A:A,0,0,1)) -> 2 | Y112: Inc | Z112: 80255 | AA112: Finance | AB112: =_xlfn.SINGLE(_xlfn.XLOOKUP(AA112,E:E,D:D,0,0,1)) -> 90 | AD112: =_xlfn.SINGLE(_xlfn.XLOOKUP(AC112,H:H,G:G,0,0,1)) -> 0 | AF112: =_xlfn.SINGLE(_xlfn.XLOOKUP(AE112,K:K,J:J,0,0,1)) -> 0 | AG112: =X112&Z112&AB112&AD112&AF112 -> 2802559000
M113: =_xlfn.SINGLE(_xlfn.XLOOKUP(N113,B:B,A:A,0,0,1)) -> 1 | N113: Ltd | O113: 30329 | P113: Accounts Payable | Q113: =_xlfn.SINGLE(_xlfn.XLOOKUP(P113,E:E,D:D,0,0,1)) -> 6 | S113: =_xlfn.SINGLE(_xlfn.XLOOKUP(R113,H:H,G:G,0,0,1)) -> 0 | U113: =_xlfn.SINGLE(_xlfn.XLOOKUP(T113,K:K,J:J,0,0,1)) -> 0 | V113: =M113&O113&Q113&S113&U113 -> 130329600 | X113: =_xlfn.SINGLE(_xlfn.XLOOKUP(Y113,B:B,A:A,0,0,1)) -> 2 | Y113: Inc | Z113: 21000 | AA113: Employees Payable | AB113: =_xlfn.SINGLE(_xlfn.XLOOKUP(AA113,E:E,D:D,0,0,1)) -> 8 | AC113: 0 | AD113: =_xlfn.SINGLE(_xlfn.XLOOKUP(AC113,H:H,G:G,0,0,1)) -> 0 | AE113: 0 | AF113: =_xlfn.SINGLE(_xlfn.XLOOKUP(AE113,K:K,J:J,0,0,1)) -> 0 | AG113: =X113&Z113&AB113&AD113&AF113 -> 221000800
M114: =_xlfn.SINGLE(_xlfn.XLOOKUP(N114,B:B,A:A,0,0,1)) -> 1 | N114: Ltd | O114: 30331 | P114: Accounts Payable | Q114: =_xlfn.SINGLE(_xlfn.XLOOKUP(P114,E:E,D:D,0,0,1)) -> 6 | S114: =_xlfn.SINGLE(_xlfn.XLOOKUP(R114,H:H,G:G,0,0,1)) -> 0 | U114: =_xlfn.SINGLE(_xlfn.XLOOKUP(T114,K:K,J:J,0,0,1)) -> 0 | V114: =M114&O114&Q114&S114&U114 -> 130331600 | X114: =_xlfn.SINGLE(_xlfn.XLOOKUP(Y114,B:B,A:A,0,0,1)) -> 2 | Y114: Inc | Z114: 21016 | AA114: Employees Payable | AB114: =_xlfn.SINGLE(_xlfn.XLOOKUP(AA114,E:E,D:D,0,0,1)) -> 8 | AC114: 0 | AD114: =_xlfn.SINGLE(_xlfn.XLOOKUP(AC114,H:H,G:G,0,0,1)) -> 0 | AE114: 0 | AF114: =_xlfn.SINGLE(_xlfn.XLOOKUP(AE114,K:K,J:J,0,0,1)) -> 0 | AG114: =X114&Z114&AB114&AD114&AF114 -> 221016800
M115: =_xlfn.SINGLE(_xlfn.XLOOKUP(N115,B:B,A:A,0,0,1)) -> 1 | N115: Ltd | O115: 30347 | P115: Accounts Payable | Q115: =_xlfn.SINGLE(_xlfn.XLOOKUP(P115,E:E,D:D,0,0,1)) -> 6 | S115: =_xlfn.SINGLE(_xlfn.XLOOKUP(R115,H:H,G:G,0,0,1)) -> 0 | U115: =_xlfn.SINGLE(_xlfn.XLOOKUP(T115,K:K,J:J,0,0,1)) -> 0 | V115: =M115&O115&Q115&S115&U115 -> 130347600 | X115: =_xlfn.SINGLE(_xlfn.XLOOKUP(Y115,B:B,A:A,0,0,1)) -> 2 | Y115: Inc | Z115: 25501 | AA115: Accrued expenses and other payable | AB115: =_xlfn.SINGLE(_xlfn.XLOOKUP(AA115,E:E,D:D,0,0,1)) -> 7 | AC115: Institutions | AD115: =_xlfn.SINGLE(_xlfn.XLOOKUP(AC115,H:H,G:G,0,0,1)) -> 109 | AE115: 0 | AF115: =_xlfn.SINGLE(_xlfn.XLOOKUP(AE115,K:K,J:J,0,0,1)) -> 0 | AG115: =X115&Z115&AB115&AD115&AF115 -> 22550171090
M116: =_xlfn.SINGLE(_xlfn.XLOOKUP(N116,B:B,A:A,0,0,1)) -> 1 | N116: Ltd | O116: 30348 | P116: Accounts Payable | Q116: =_xlfn.SINGLE(_xlfn.XLOOKUP(P116,E:E,D:D,0,0,1)) -> 6 | S116: =_xlfn.SINGLE(_xlfn.XLOOKUP(R116,H:H,G:G,0,0,1)) -> 0 | U116: =_xlfn.SINGLE(_xlfn.XLOOKUP(T116,K:K,J:J,0,0,1)) -> 0 | V116: =M116&O116&Q116&S116&U116 -> 130348600 | X116: =_xlfn.SINGLE(_xlfn.XLOOKUP(Y116,B:B,A:A,0,0,1)) -> 2 | Y116: Inc | Z116: 60070 | AA116: R&D | AB116: =_xlfn.SINGLE(_xlfn.XLOOKUP(AA116,E:E,D:D,0,0,1)) -> 40 | AC116: Payroll & Payroll related | AD116: =_xlfn.SINGLE(_xlfn.XLOOKUP(AC116,H:H,G:G,0,0,1)) -> 116 | AE116: Product | AF116: =_xlfn.SINGLE(_xlfn.XLOOKUP(AE116,K:K,J:J,0,0,1)) -> 42 | AG116: =X116&Z116&AB116&AD116&AF116 -> 2600704011642
M117: =_xlfn.SINGLE(_xlfn.XLOOKUP(N117,B:B,A:A,0,0,1)) -> 1 | N117: Ltd | O117: 30350 | P117: Accounts Payable | Q117: =_xlfn.SINGLE(_xlfn.XLOOKUP(P117,E:E,D:D,0,0,1)) -> 6 | S117: =_xlfn.SINGLE(_xlfn.XLOOKUP(R117,H:H,G:G,0,0,1)) -> 0 | U117: =_xlfn.SINGLE(_xlfn.XLOOKUP(T117,K:K,J:J,0,0,1)) -> 0 | V117: =M117&O117&Q117&S117&U117 -> 130350600 | X117: =_xlfn.SINGLE(_xlfn.XLOOKUP(Y117,B:B,A:A,0,0,1)) -> 2 | Y117: Inc | Z117: 70017 | AA117: Sales | AB117: =_xlfn.SINGLE(_xlfn.XLOOKUP(AA117,E:E,D:D,0,0,1)) -> 50 | AC117: Payroll & Payroll related | AD117: =_xlfn.SINGLE(_xlfn.XLOOKUP(AC117,H:H,G:G,0,0,1)) -> 116 | AE117: 0 | AF117: =_xlfn.SINGLE(_xlfn.XLOOKUP(AE117,K:K,J:J,0,0,1)) -> 0 | AG117: =X117&Z117&AB117&AD117&AF117 -> 270017501160
M118: =_xlfn.SINGLE(_xlfn.XLOOKUP(N118,B:B,A:A,0,0,1)) -> 1 | N118: Ltd | O118: 30359 | P118: Accounts Payable | Q118: =_xlfn.SINGLE(_xlfn.XLOOKUP(P118,E:E,D:D,0,0,1)) -> 6 | S118: =_xlfn.SINGLE(_xlfn.XLOOKUP(R118,H:H,G:G,0,0,1)) -> 0 | U118: =_xlfn.SINGLE(_xlfn.XLOOKUP(T118,K:K,J:J,0,0,1)) -> 0 | V118: =M118&O118&Q118&S118&U118 -> 130359600 | X118: =_xlfn.SINGLE(_xlfn.XLOOKUP(Y118,B:B,A:A,0,0,1)) -> 2 | Y118: Inc | Z118: 70045 | AA118: Sales | AB118: =_xlfn.SINGLE(_xlfn.XLOOKUP(AA118,E:E,D:D,0,0,1)) -> 50 | AC118: T&E | AD118: =_xlfn.SINGLE(_xlfn.XLOOKUP(AC118,H:H,G:G,0,0,1)) -> 124 | AE118: 0 | AF118: =_xlfn.SINGLE(_xlfn.XLOOKUP(AE118,K:K,J:J,0,0,1)) -> 0 | AG118: =X118&Z118&AB118&AD118&AF118 -> 270045501240
M119: =_xlfn.SINGLE(_xlfn.XLOOKUP(N119,B:B,A:A,0,0,1)) -> 1 | N119: Ltd | O119: 30362 | P119: Accounts Payable | Q119: =_xlfn.SINGLE(_xlfn.XLOOKUP(P119,E:E,D:D,0,0,1)) -> 6 | S119: =_xlfn.SINGLE(_xlfn.XLOOKUP(R119,H:H,G:G,0,0,1)) -> 0 | U119: =_xlfn.SINGLE(_xlfn.XLOOKUP(T119,K:K,J:J,0,0,1)) -> 0 | V119: =M119&O119&Q119&S119&U119 -> 130362600 | X119: =_xlfn.SINGLE(_xlfn.XLOOKUP(Y119,B:B,A:A,0,0,1)) -> 2 | Y119: Inc | Z119: 70075 | AA119: Sales | AB119: =_xlfn.SINGLE(_xlfn.XLOOKUP(AA119,E:E,D:D,0,0,1)) -> 50 | AC119: T&E | AD119: =_xlfn.SINGLE(_xlfn.XLOOKUP(AC119,H:H,G:G,0,0,1)) -> 124 | AE119: 0 | AF119: =_xlfn.SINGLE(_xlfn.XLOOKUP(AE119,K:K,J:J,0,0,1)) -> 0 | AG119: =X119&Z119&AB119&AD119&AF119 -> 270075501240
M120: =_xlfn.SINGLE(_xlfn.XLOOKUP(N120,B:B,A:A,0,0,1)) -> 1 | N120: Ltd | O120: 30364 | P120: Accounts Payable | Q120: =_xlfn.SINGLE(_xlfn.XLOOKUP(P120,E:E,D:D,0,0,1)) -> 6 | S120: =_xlfn.SINGLE(_xlfn.XLOOKUP(R120,H:H,G:G,0,0,1)) -> 0 | U120: =_xlfn.SINGLE(_xlfn.XLOOKUP(T120,K:K,J:J,0,0,1)) -> 0 | V120: =M120&O120&Q120&S120&U120 -> 130364600 | X120: =_xlfn.SINGLE(_xlfn.XLOOKUP(Y120,B:B,A:A,0,0,1)) -> 2 | Y120: Inc | Z120: 72015 | AA120: Marketing | AB120: =_xlfn.SINGLE(_xlfn.XLOOKUP(AA120,E:E,D:D,0,0,1)) -> 60 | AC120: Payroll & Payroll related | AD120: =_xlfn.SINGLE(_xlfn.XLOOKUP(AC120,H:H,G:G,0,0,1)) -> 116 | AE120: 0 | AF120: =_xlfn.SINGLE(_xlfn.XLOOKUP(AE120,K:K,J:J,0,0,1)) -> 0 | AG120: =X120&Z120&AB120&AD120&AF120 -> 272015601160
...

Sheet GL 12.22
A1: =SUM(L:L) -> 2.5494955e-08 | I1: YTD 2022
A2: Account Index | B2: FS Account | C2: Entity | D2: GL Account # | E2: Account Name | F2: Sub Account | G2: Sub Department | I2: Balance in USD | J2: AJE | K2: Allocation | L2: Balance | M2: Con. entry | N2: Reported balance (consolidated)
A3: =_xlfn.XLOOKUP($B3,Index!$E:$E,Index!$D:$D,) -> 1 | B3: =IF($C3="Ltd",_xlfn.XLOOKUP($D3,Index!$V:$V,Index!$P:$P,),_xlfn.XLOOKUP($D3,Index!$AG:$AG,Index!$AA:$AA,)) -> Cash and Cash Equivalents | C3: =IF(LEFT(D3)="1","Ltd","Inc") -> Ltd | D3: 110004100 | E3: =_xlfn.XLOOKUP(_xlfn.NUMBERVALUE(MID(D3,2,5)),'TB LTD 12.22'!$E:$E,'TB LTD 12.22'!$F:$F,) -> פקדון אשראי 1 1670001+3000001 | F3: =IF(C3="Ltd",_xlfn.XLOOKUP(D3,Index!V:V,Index!R:R,),_xlfn.XLOOKUP(D3,Index!AG:AG,Index!AC:AC,)) -> 0 | G3: =IF(C3="Ltd",_xlfn.XLOOKUP(D3,Index!V:V,Index!T:T,),_xlfn.XLOOKUP(D3,Index!AG:AG,Index!AE:AE,)) -> 0 | I3: =_xlfn.XLOOKUP(_xlfn.NUMBERVALUE(MID(D3,2,5)),'TB LTD 12.22'!E:E,'TB LTD 12.22'!H:H,0,0,1) -> 202311.56 | J3: =SUMIF(AJE!$E:$E,D3,AJE!$H:$H) -> 0 | K3: =SUMIF(AJE!$Q:$Q,D3,AJE!$T:$T) -> 0 | L3: =I3+J3+K3 -> 202311.56 | M3: =SUMIF(AJE!$AB:$AB,D3,AJE!$AE:$AE) -> 0 | N3: =L3+M3 -> 202311.56 | R3: =L3*3.519 -> 711934.38
A4: =_xlfn.XLOOKUP($B4,Index!$E:$E,Index!$D:$D,) -> 1 | B4: =IF($C4="Ltd",_xlfn.XLOOKUP($D4,Index!$V:$V,Index!$P:$P,),_xlfn.XLOOKUP($D4,Index!$AG:$AG,Index!$AA:$AA,)) -> Cash and Cash Equivalents | C4: =IF(LEFT(D4)="1","Ltd","Inc") -> Ltd | D4: 110007100 | E4: =_xlfn.XLOOKUP(_xlfn.NUMBERVALUE(MID(D4,2,5)),'TB LTD 12.22'!$E:$E,'TB LTD 12.22'!$F:$F,) -> פקדון דולרי 356924992 | F4: =IF(C4="Ltd",_xlfn.XLOOKUP(D4,Index!V:V,Index!R:R,),_xlfn.XLOOKUP(D4,Index!AG:AG,Index!AC:AC,)) -> 0 | G4: =IF(C4="Ltd",_xlfn.XLOOKUP(D4,Index!V:V,Index!T:T,),_xlfn.XLOOKUP(D4,Index!AG:AG,Index!AE:AE,)) -> 0 | I4: =_xlfn.XLOOKUP(_xlfn.NUMBERVALUE(MID(D4,2,5)),'TB LTD 12.22'!E:E,'TB LTD 12.22'!H:H,0,0,1) -> 5075011.6 | J4: =SUMIF(AJE!$E:$E,D4,AJE!$H:$H) -> 0 | K4: =SUMIF(AJE!$Q:$Q,D4,AJE!$T:$T) -> 0 | L4: =I4+J4+K4 -> 5075011.6 | M4: =SUMIF(AJE!$AB:$AB,D4,AJE!$AE:$AE) -> 0 | N4: =L4+M4 -> 5075011.6 | R4: =L4*3.519 -> 17858966
A5: =_xlfn.XLOOKUP($B5,Index!$E:$E,Index!$D:$D,) -> 3 | B5: =IF($C5="Ltd",_xlfn.XLOOKUP($D5,Index!$V:$V,Index!$P:$P,),_xlfn.XLOOKUP($D5,Index!$AG:$AG,Index!$AA:$AA,)) -> Prepaid expenses and other receivable | C5: =IF(LEFT(D5)="1","Ltd","Inc") -> Ltd | D5: 11000831040 | E5: =_xlfn.XLOOKUP(_xlfn.NUMBERVALUE(MID(D5,2,5)),'TB LTD 12.22'!$E:$E,'TB LTD 12.22'!$F:$F,) -> Deposit Papaya Global USD כללי עד 8.22 | F5: =IF(C5="Ltd",_xlfn.XLOOKUP(D5,Index!V:V,Index!R:R,),_xlfn.XLOOKUP(D5,Index!AG:AG,Index!AC:AC,)) -> Deposits | G5: =IF(C5="Ltd",_xlfn.XLOOKUP(D5,Index!V:V,Index!T:T,),_xlfn.XLOOKUP(D5,Index!AG:AG,Index!AE:AE,)) -> 0 | I5: =_xlfn.XLOOKUP(_xlfn.NUMBERVALUE(MID(D5,2,5)),'TB LTD 12.22'!E:E,'TB LTD 12.22'!H:H,0,0,1) -> 398459.46 | J5: =SUMIF(AJE!$E:$E,D5,AJE!$H:$H) -> 0 | K5: =SUMIF(AJE!$Q:$Q,D5,AJE!$T:$T) -> 0 | L5: =I5+J5+K5 -> 398459.46 | M5: =SUMIF(AJE!$AB:$AB,D5,AJE!$AE:$AE) -> 0 | N5: =L5+M5 -> 398459.46
A6: =_xlfn.XLOOKUP($B6,Index!$E:$E,Index!$D:$D,) -> 3 | B6: =IF($C6="Ltd",_xlfn.XLOOKUP($D6,Index!$V:$V,Index!$P:$P,),_xlfn.XLOOKUP($D6,Index!$AG:$AG,Index!$AA:$AA,)) -> Prepaid expenses and other receivable | C6: =IF(LEFT(D6)="1","Ltd","Inc") -> Ltd | D6: 11001231040 | E6: =_xlfn.XLOOKUP(_xlfn.NUMBERVALUE(MID(D6,2,5)),'TB LTD 12.22'!$E:$E,'TB LTD 12.22'!$F:$F,) -> פקדון שכ"ד שותפות נכסי הארבעה | F6: =IF(C6="Ltd",_xlfn.XLOOKUP(D6,Index!V:V,Index!R:R,),_xlfn.XLOOKUP(D6,Index!AG:AG,Index!AC:AC,)) -> Deposits | G6: =IF(C6="Ltd",_xlfn.XLOOKUP(D6,Index!V:V,Index!T:T,),_xlfn.XLOOKUP(D6,Index!AG:AG,Index!AE:AE,)) -> 0 | I6: =_xlfn.XLOOKUP(_xlfn.NUMBERVALUE(MID(D6,2,5)),'TB LTD 12.22'!E:E,'TB LTD 12.22'!H:H,0,0,1) -> 20940.49 | J6: =SUMIF(AJE!$E:$E,D6,AJE!$H:$H) -> 0 | K6: =SUMIF(AJE!$Q:$Q,D6,AJE!$T:$T) -> 0 | L6: =I6+J6+K6 -> 20940.49 | M6: =SUMIF(AJE!$AB:$AB,D6,AJE!$AE:$AE) -> 0 | N6: =L6+M6 -> 20940.49
A7: =_xlfn.XLOOKUP($B7,Index!$E:$E,Index!$D:$D,) -> 3 | B7: =IF($C7="Ltd",_xlfn.XLOOKUP($D7,Index!$V:$V,Index!$P:$P,),_xlfn.XLOOKUP($D7,Index!$AG:$AG,Index!$AA:$AA,)) -> Prepaid expenses and other receivable | C7: =IF(LEFT(D7)="1","Ltd","Inc") -> Ltd | D7: 11001331040 | E7: =_xlfn.XLOOKUP(_xlfn.NUMBERVALUE(MID(D7,2,5)),'TB LTD 12.22'!$E:$E,'TB LTD 12.22'!$F:$F,) -> פקדון שכ"ד GEGR LTD | F7: =IF(C7="Ltd",_xlfn.XLOOKUP(D7,Index!V:V,Index!R:R,),_xlfn.XLOOKUP(D7,Index!AG:AG,Index!AC:AC,)) -> Deposits | G7: =IF(C7="Ltd",_xlfn.XLOOKUP(D7,Index!V:V,Index!T:T,),_xlfn.XLOOKUP(D7,Index!AG:AG,Index!AE:AE,)) -> 0 | I7: =_xlfn.XLOOKUP(_xlfn.NUMBERVALUE(MID(D7,2,5)),'TB LTD 12.22'!E:E,'TB LTD 12.22'!H:H,0,0,1) -> 272833.76 | J7: =SUMIF(AJE!$E:$E,D7,AJE!$H:$H) -> 0 | K7: =SUMIF(AJE!$Q:$Q,D7,AJE!$T:$T) -> 0 | L7: =I7+J7+K7 -> 272833.76 | M7: =SUMIF(AJE!$AB:$AB,D7,AJE!$AE:$AE) -> 0 | N7: =L7+M7 -> 272833.76
A8: =_xlfn.XLOOKUP($B8,Index!$E:$E,Index!$D:$D,) -> 1 | B8: =IF($C8="Ltd",_xlfn.XLOOKUP($D8,Index!$V:$V,Index!$P:$P,),_xlfn.XLOOKUP($D8,Index!$AG:$AG,Index!$AA:$AA,)) -> Cash and Cash Equivalents | C8: =IF(LEFT(D8)="1","Ltd","Inc") -> Ltd | D8: 110014100 | E8: =_xlfn.XLOOKUP(_xlfn.NUMBERVALUE(MID(D8,2,5)),'TB LTD 12.22'!$E:$E,'TB LTD 12.22'!$F:$F,) -> פקדון אשראי 2 1230001 | F8: =IF(C8="Ltd",_xlfn.XLOOKUP(D8,Index!V:V,Index!R:R,),_xlfn.XLOOKUP(D8,Index!AG:AG,Index!AC:AC,)) -> 0 | G8: =IF(C8="Ltd",_xlfn.XLOOKUP(D8,Index!V:V,Index!T:T,),_xlfn.XLOOKUP(D8,Index!AG:AG,Index!AE:AE,)) -> 0 | I8: =_xlfn.XLOOKUP(_xlfn.NUMBERVALUE(MID(D8,2,5)),'TB LTD 12.22'!E:E,'TB LTD 12.22'!H:H,0,0,1) -> 19732.15 | J8: =SUMIF(AJE!$E:$E,D8,AJE!$H:$H) -> 0 | K8: =SUMIF(AJE!$Q:$Q,D8,AJE!$T:$T) -> 0 | L8: =I8+J8+K8 -> 19732.15 | M8: =SUMIF(AJE!$AB:$AB,D8,AJE!$AE:$AE) -> 0 | N8: =L8+M8 -> 19732.15 | R8: =L8*3.519 -> 69437.436
A9: =_xlfn.XLOOKUP($B9,Index!$E:$E,Index!$D:$D,) -> 1 | B9: =IF($C9="Ltd",_xlfn.XLOOKUP($D9,Index!$V:$V,Index!$P:$P,),_xlfn.XLOOKUP($D9,Index!$AG:$AG,Index!$AA:$AA,)) -> Cash and Cash Equivalents | C9: =IF(LEFT(D9)="1","Ltd","Inc") -> Ltd | D9: 11001611220 | E9: =_xlfn.XLOOKUP(_xlfn.NUMBERVALUE(MID(D9,2,5)),'TB LTD 12.22'!$E:$E,'TB LTD 12.22'!$F:$F,) -> פקדון דולרי | F9: =IF(C9="Ltd",_xlfn.XLOOKUP(D9,Index!V:V,Index!R:R,),_xlfn.XLOOKUP(D9,Index!AG:AG,Index!AC:AC,)) -> Short Term deposits | G9: =IF(C9="Ltd",_xlfn.XLOOKUP(D9,Index!V:V,Index!T:T,),_xlfn.XLOOKUP(D9,Index!AG:AG,Index!AE:AE,)) -> 0 | I9: =_xlfn.XLOOKUP(_xlfn.NUMBERVALUE(MID(D9,2,5)),'TB LTD 12.22'!E:E,'TB LTD 12.22'!H:H,0,0,1) -> 10166887 | J9: =SUMIF(AJE!$E:$E,D9,AJE!$H:$H) -> 0 | K9: =SUMIF(AJE!$Q:$Q,D9,AJE!$T:$T) -> 0 | L9: =I9+J9+K9 -> 10166887 | M9: =SUMIF(AJE!$AB:$AB,D9,AJE!$AE:$AE) -> 0 | N9: =L9+M9 -> 10166887 | R9: =L9*3.519 -> 35777276
A10: =_xlfn.XLOOKUP($B10,Index!$E:$E,Index!$D:$D,) -> 3 | B10: =IF($C10="Ltd",_xlfn.XLOOKUP($D10,Index!$V:$V,Index!$P:$P,),_xlfn.XLOOKUP($D10,Index!$AG:$AG,Index!$AA:$AA,)) -> Prepaid expenses and other receivable | C10: =IF(LEFT(D10)="1","Ltd","Inc") -> Ltd | D10: 11001731040 | E10: =_xlfn.XLOOKUP(_xlfn.NUMBERVALUE(MID(D10,2,5)),'TB LTD 12.22'!$E:$E,'TB LTD 12.22'!$F:$F,) -> Deposit Papaya Global EUR | F10: =IF(C10="Ltd",_xlfn.XLOOKUP(D10,Index!V:V,Index!R:R,),_xlfn.XLOOKUP(D10,Index!AG:AG,Index!AC:AC,)) -> Deposits | G10: =IF(C10="Ltd",_xlfn.XLOOKUP(D10,Index!V:V,Index!T:T,),_xlfn.XLOOKUP(D10,Index!AG:AG,Index!AE:AE,)) -> 0 | I10: =_xlfn.XLOOKUP(_xlfn.NUMBERVALUE(MID(D10,2,5)),'TB LTD 12.22'!E:E,'TB LTD 12.22'!H:H,0,0,1) -> 92428.98 | J10: =SUMIF(AJE!$E:$E,D10,AJE!$H:$H) -> 0 | K10: =SUMIF(AJE!$Q:$Q,D10,AJE!$T:$T) -> 0 | L10: =I10+J10+K10 -> 92428.98 | M10: =SUMIF(AJE!$AB:$AB,D10,AJE!$AE:$AE) -> 0 | N10: =L10+M10 -> 92428.98
A11: =_xlfn.XLOOKUP($B11,Index!$E:$E,Index!$D:$D,) -> 3 | B11: =IF($C11="Ltd",_xlfn.XLOOKUP($D11,Index!$V:$V,Index!$P:$P,),_xlfn.XLOOKUP($D11,Index!$AG:$AG,Index!$AA:$AA,)) -> Prepaid expenses and other receivable | C11: =IF(LEFT(D11)="1","Ltd","Inc") -> Ltd | D11: 11001831040 | E11: =_xlfn.XLOOKUP(_xlfn.NUMBERVALUE(MID(D11,2,5)),'TB LTD 12.22'!$E:$E,'TB LTD 12.22'!$F:$F,) -> Deposit Papaya Global GBP | F11: =IF(C11="Ltd",_xlfn.XLOOKUP(D11,Index!V:V,Index!R:R,),_xlfn.XLOOKUP(D11,Index!AG:AG,Index!AC:AC,)) -> Deposits | G11: =IF(C11="Ltd",_xlfn.XLOOKUP(D11,Index!V:V,Index!T:T,),_xlfn.XLOOKUP(D11,Index!AG:AG,Index!AE:AE,)) -> 0 | I11: =_xlfn.XLOOKUP(_xlfn.NUMBERVALUE(MID(D11,2,5)),'TB LTD 12.22'!E:E,'TB LTD 12.22'!H:H,0,0,1) -> 28298.83 | J11: =SUMIF(AJE!$E:$E,D11,AJE!$H:$H) -> 0 | K11: =SUMIF(AJE!$Q:$Q,D11,AJE!$T:$T) -> 0 | L11: =I11+J11+K11 -> 28298.83 | M11: =SUMIF(AJE!$AB:$AB,D11,AJE!$AE:$AE) -> 0 | N11: =L11+M11 -> 28298.83
A12: =_xlfn.XLOOKUP($B12,Index!$E:$E,Index!$D:$D,) -> 3 | B12: =IF($C12="Ltd",_xlfn.XLOOKUP($D12,Index!$V:$V,Index!$P:$P,),_xlfn.XLOOKUP($D12,Index!$AG:$AG,Index!$AA:$AA,)) -> Prepaid expenses and other receivable | C12: =IF(LEFT(D12)="1","Ltd","Inc") -> Ltd | D12: 11001931040 | E12: =_xlfn.XLOOKUP(_xlfn.NUMBERVALUE(MID(D12,2,5)),'TB LTD 12.22'!$E:$E,'TB LTD 12.22'!$F:$F,) -> Deposit Papaya Global SGD | F12: =IF(C12="Ltd",_xlfn.XLOOKUP(D12,Index!V:V,Index!R:R,),_xlfn.XLOOKUP(D12,Index!AG:AG,Index!AC:AC,)) -> Deposits | G12: =IF(C12="Ltd",_xlfn.XLOOKUP(D12,Index!V:V,Index!T:T,),_xlfn.XLOOKUP(D12,Index!AG:AG,Index!AE:AE,)) -> 0 | I12: =_xlfn.XLOOKUP(_xlfn.NUMBERVALUE(MID(D12,2,5)),'TB LTD 12.22'!E:E,'TB LTD 12.22'!H:H,0,0,1) -> 22336.74 | J12: =SUMIF(AJE!$E:$E,D12,AJE!$H:$H) -> 0 | K12: =SUMIF(AJE!$Q:$Q,D12,AJE!$T:$T) -> 0 | L12: =I12+J12+K12 -> 22336.74 | M12: =SUMIF(AJE!$AB:$AB,D12,AJE!$AE:$AE) -> 0 | N12: =L12+M12 -> 22336.74
A13: =_xlfn.XLOOKUP($B13,Index!$E:$E,Index!$D:$D,) -> 3 | B13: =IF($C13="Ltd",_xlfn.XLOOKUP($D13,Index!$V:$V,Index!$P:$P,),_xlfn.XLOOKUP($D13,Index!$AG:$AG,Index!$AA:$AA,)) -> Prepaid expenses and other receivable | C13: =IF(LEFT(D13)="1","Ltd","Inc") -> Ltd | D13: 11002031040 | E13: =_xlfn.XLOOKUP(_xlfn.NUMBERVALUE(MID(D13,2,5)),'TB LTD 12.22'!$E:$E,'TB LTD 12.22'!$F:$F,) -> Deposit Papaya Global AUD | F13: =IF(C13="Ltd",_xlfn.XLOOKUP(D13,Index!V:V,Index!R:R,),_xlfn.XLOOKUP(D13,Index!AG:AG,Index!AC:AC,)) -> Deposits | G13: =IF(C13="Ltd",_xlfn.XLOOKUP(D13,Index!V:V,Index!T:T,),_xlfn.XLOOKUP(D13,Index!AG:AG,Index!AE:AE,)) -> 0 | I13: =_xlfn.XLOOKUP(_xlfn.NUMBERVALUE(MID(D13,2,5)),'TB LTD 12.22'!E:E,'TB LTD 12.22'!H:H,0,0,1) -> 46548.47 | J13: =SUMIF(AJE!$E:$E,D13,AJE!$H:$H) -> 0 | K13: =SUMIF(AJE!$Q:$Q,D13,AJE!$T:$T) -> 0 | L13: =I13+J13+K13 -> 46548.47 | M13: =SUMIF(AJE!$AB:$AB,D13,AJE!$AE:$AE) -> 0 | N13: =L13+M13 -> 46548.47
A14: =_xlfn.XLOOKUP($B14,Index!$E:$E,Index!$D:$D,) -> 1 | B14: =IF($C14="Ltd",_xlfn.XLOOKUP($D14,Index!$V:$V,Index!$P:$P,),_xlfn.XLOOKUP($D14,Index!$AG:$AG,Index!$AA:$AA,)) -> Cash and Cash Equivalents | C14: =IF(LEFT(D14)="1","Ltd","Inc") -> Ltd | D14: 110023100 | E14: =_xlfn.XLOOKUP(_xlfn.NUMBERVALUE(MID(D14,2,5)),'TB LTD 12.22'!$E:$E,'TB LTD 12.22'!$F:$F,) -> פקדון שווה מזומנים עד 3 חודשים | F14: =IF(C14="Ltd",_xlfn.XLOOKUP(D14,Index!V:V,Index!R:R,),_xlfn.XLOOKUP(D14,Index!AG:AG,Index!AC:AC,)) -> 0 | G14: =IF(C14="Ltd",_xlfn.XLOOKUP(D14,Index!V:V,Index!T:T,),_xlfn.XLOOKUP(D14,Index!AG:AG,Index!AE:AE,)) -> 0 | I14: =_xlfn.XLOOKUP(_xlfn.NUMBERVALUE(MID(D14,2,5)),'TB LTD 12.22'!E:E,'TB LTD 12.22'!H:H,0,0,1) -> 2847895.3 | J14: =SUMIF(AJE!$E:$E,D14,AJE!$H:$H) -> 0 | K14: =SUMIF(AJE!$Q:$Q,D14,AJE!$T:$T) -> 0 | L14: =I14+J14+K14 -> 2847895.3 | M14: =SUMIF(AJE!$AB:$AB,D14,AJE!$AE:$AE) -> 0 | N14: =L14+M14 -> 2847895.3 | R14: =L14*3.519 -> 10021744
A15: =_xlfn.XLOOKUP($B15,Index!$E:$E,Index!$D:$D,) -> 1 | B15: =IF($C15="Ltd",_xlfn.XLOOKUP($D15,Index!$V:$V,Index!$P:$P,),_xlfn.XLOOKUP($D15,Index!$AG:$AG,Index!$AA:$AA,)) -> Cash and Cash Equivalents | C15: =IF(LEFT(D15)="1","Ltd","Inc") -> Ltd | D15: 110024100 | E15: =_xlfn.XLOOKUP(_xlfn.NUMBERVALUE(MID(D15,2,5)),'TB LTD 12.22'!$E:$E,'TB LTD 12.22'!$F:$F,) -> פקדון דולרי 357119482 6.12תאריך פתיחה | F15: =IF(C15="Ltd",_xlfn.XLOOKUP(D15,Index!V:V,Index!R:R,),_xlfn.XLOOKUP(D15,Index!AG:AG,Index!AC:AC,)) -> 0 | G15: =IF(C15="Ltd",_xlfn.XLOOKUP(D15,Index!V:V,Index!T:T,),_xlfn.XLOOKUP(D15,Index!AG:AG,Index!AE:AE,)) -> 0 | I15: =_xlfn.XLOOKUP(_xlfn.NUMBERVALUE(MID(D15,2,5)),'TB LTD 12.22'!E:E,'TB LTD 12.22'!H:H,0,0,1) -> 3010935.4 | J15: =SUMIF(AJE!$E:$E,D15,AJE!$H:$H) -> 0 | K15: =SUMIF(AJE!$Q:$Q,D15,AJE!$T:$T) -> 0 | L15: =I15+J15+K15 -> 3010935.4 | M15: =SUMIF(AJE!$AB:$AB,D15,AJE!$AE:$AE) -> 0 | N15: =L15+M15 -> 3010935.4 | R15: =L15*3.519 -> 10595482
A16: =_xlfn.XLOOKUP($B16,Index!$E:$E,Index!$D:$D,) -> 1 | B16: =IF($C16="Ltd",_xlfn.XLOOKUP($D16,Index!$V:$V,Index!$P:$P,),_xlfn.XLOOKUP($D16,Index!$AG:$AG,Index!$AA:$AA,)) -> Cash and Cash Equivalents | C16: =IF(LEFT(D16)="1","Ltd","Inc") -> Ltd | D16: 110025100 | E16: =_xlfn.XLOOKUP(_xlfn.NUMBERVALUE(MID(D16,2,5)),'TB LTD 12.22'!$E:$E,'TB LTD 12.22'!$F:$F,) -> פקדון דולרי 357119493 6.12תאריך פתיחה | F16: =IF(C16="Ltd",_xlfn.XLOOKUP(D16,Index!V:V,Index!R:R,),_xlfn.XLOOKUP(D16,Index!AG:AG,Index!AC:AC,)) -> 0 | G16: =IF(C16="Ltd",_xlfn.XLOOKUP(D16,Index!V:V,Index!T:T,),_xlfn.XLOOKUP(D16,Index!AG:AG,Index!AE:AE,)) -> 0 | I16: =_xlfn.XLOOKUP(_xlfn.NUMBERVALUE(MID(D16,2,5)),'TB LTD 12.22'!E:E,'TB LTD 12.22'!H:H,0,0,1) -> 4015429 | J16: =SUMIF(AJE!$E:$E,D16,AJE!$H:$H) -> 0 | K16: =SUMIF(AJE!$Q:$Q,D16,AJE!$T:$T) -> 0 | L16: =I16+J16+K16 -> 4015429 | M16: =SUMIF(AJE!$AB:$AB,D16,AJE!$AE:$AE) -> 0 | N16: =L16+M16 -> 4015429 | R16: =L16*3.519 -> 14130295
A17: =_xlfn.XLOOKUP($B17,Index!$E:$E,Index!$D:$D,) -> 1 | B17: =IF($C17="Ltd",_xlfn.XLOOKUP($D17,Index!$V:$V,Index!$P:$P,),_xlfn.XLOOKUP($D17,Index!$AG:$AG,Index!$AA:$AA,)) -> Cash and Cash Equivalents | C17: =IF(LEFT(D17)="1","Ltd","Inc") -> Ltd | D17: 111001100 | E17: =_xlfn.XLOOKUP(_xlfn.NUMBERVALUE(MID(D17,2,5)),'TB LTD 12.22'!$E:$E,'TB LTD 12.22'!$F:$F,) -> בנק הפועלים ש"ח חדש | F17: =IF(C17="Ltd",_xlfn.XLOOKUP(D17,Index!V:V,Index!R:R,),_xlfn.XLOOKUP(D17,Index!AG:AG,Index!AC:AC,)) -> 0 | G17: =IF(C17="Ltd",_xlfn.XLOOKUP(D17,Index!V:V,Index!T:T,),_xlfn.XLOOKUP(D17,Index!AG:AG,Index!AE:AE,)) -> 0 | I17: =_xlfn.XLOOKUP(_xlfn.NUMBERVALUE(MID(D17,2,5)),'TB LTD 12.22'!E:E,'TB LTD 12.22'!H:H,0,0,1) -> 4710236.8 | J17: =SUMIF(AJE!$E:$E,D17,AJE!$H:$H) -> 0 | K17: =SUMIF(AJE!$Q:$Q,D17,AJE!$T:$T) -> 0 | L17: =I17+J17+K17 -> 4710236.8 | M17: =SUMIF(AJE!$AB:$AB,D17,AJE!$AE:$AE) -> 0 | N17: =L17+M17 -> 4710236.8 | R17: =L17*3.519 -> 16575323
A18: =_xlfn.XLOOKUP($B18,Index!$E:$E,Index!$D:$D,) -> 1 | B18: =IF($C18="Ltd",_xlfn.XLOOKUP($D18,Index!$V:$V,Index!$P:$P,),_xlfn.XLOOKUP($D18,Index!$AG:$AG,Index!$AA:$AA,)) -> Cash and Cash Equivalents | C18: =IF(LEFT(D18)="1","Ltd","Inc") -> Ltd | D18: 111002100 | E18: =_xlfn.XLOOKUP(_xlfn.NUMBERVALUE(MID(D18,2,5)),'TB LTD 12.22'!$E:$E,'TB LTD 12.22'!$F:$F,) -> בנק הפועלים $ חדש | F18: =IF(C18="Ltd",_xlfn.XLOOKUP(D18,Index!V:V,Index!R:R,),_xlfn.XLOOKUP(D18,Index!AG:AG,Index!AC:AC,)) -> 0 | G18: =IF(C18="Ltd",_xlfn.XLOOKUP(D18,Index!V:V,Index!T:T,),_xlfn.XLOOKUP(D18,Index!AG:AG,Index!AE:AE,)) -> 0 | I18: =_xlfn.XLOOKUP(_xlfn.NUMBERVALUE(MID(D18,2,5)),'TB LTD 12.22'!E:E,'TB LTD 12.22'!H:H,0,0,1) -> 833462.03 | J18: =SUMIF(AJE!$E:$E,D18,AJE!$H:$H) -> 0 | K18: =SUMIF(AJE!$Q:$Q,D18,AJE!$T:$T) -> 0 | L18: =I18+J18+K18 -> 833462.03 | M18: =SUMIF(AJE!$AB:$AB,D18,AJE!$AE:$AE) -> 0 | N18: =L18+M18 -> 833462.03 | R18: =L18*3.519 -> 2932952.9
A19: =_xlfn.XLOOKUP($B19,Index!$E:$E,Index!$D:$D,) -> 1 | B19: =IF($C19="Ltd",_xlfn.XLOOKUP($D19,Index!$V:$V,Index!$P:$P,),_xlfn.XLOOKUP($D19,Index!$AG:$AG,Index!$AA:$AA,)) -> Cash and Cash Equivalents | C19: =IF(LEFT(D19)="1","Ltd","Inc") -> Ltd | D19: 111010100 | E19: =_xlfn.XLOOKUP(_xlfn.NUMBERVALUE(MID(D19,2,5)),'TB LTD 12.22'!$E:$E,'TB LTD 12.22'!$F:$F,) -> בנק הפועלים EUR יורו חדש | F19: =IF(C19="Ltd",_xlfn.XLOOKUP(D19,Index!V:V,Index!R:R,),_xlfn.XLOOKUP(D19,Index!AG:AG,Index!AC:AC,)) -> 0 | G19: =IF(C19="Ltd",_xlfn.XLOOKUP(D19,Index!V:V,Index!T:T,),_xlfn.XLOOKUP(D19,Index!AG:AG,Index!AE:AE,)) -> 0 | I19: =_xlfn.XLOOKUP(_xlfn.NUMBERVALUE(MID(D19,2,5)),'TB LTD 12.22'!E:E,'TB LTD 12.22'!H:H,0,0,1) -> 299801.79 | J19: =SUMIF(AJE!$E:$E,D19,AJE!$H:$H) -> 0 | K19: =SUMIF(AJE!$Q:$Q,D19,AJE!$T:$T) -> 0 | L19: =I19+J19+K19 -> 299801.79 | M19: =SUMIF(AJE!$AB:$AB,D19,AJE!$AE:$AE) -> 0 | N19: =L19+M19 -> 299801.79 | R19: =L19*3.519 -> 1055002.5
A20: =_xlfn.XLOOKUP($B20,Index!$E:$E,Index!$D:$D,) -> 1 | B20: =IF($C20="Ltd",_xlfn.XLOOKUP($D20,Index!$V:$V,Index!$P:$P,),_xlfn.XLOOKUP($D20,Index!$AG:$AG,Index!$AA:$AA,)) -> Cash and Cash Equivalents | C20: =IF(LEFT(D20)="1","Ltd","Inc") -> Ltd | D20: 111011100 | E20: =_xlfn.XLOOKUP(_xlfn.NUMBERVALUE(MID(D20,2,5)),'TB LTD 12.22'!$E:$E,'TB LTD 12.22'!$F:$F,) -> בנק פועלים GBP לירה שטרלינג חדש | F20: =IF(C20="Ltd",_xlfn.XLOOKUP(D20,Index!V:V,Index!R:R,),_xlfn.XLOOKUP(D20,Index!AG:AG,Index!AC:AC,)) -> 0 | G20: =IF(C20="Ltd",_xlfn.XLOOKUP(D20,Index!V:V,Index!T:T,),_xlfn.XLOOKUP(D20,Index!AG:AG,Index!AE:AE,)) -> 0 | I20: =_xlfn.XLOOKUP(_xlfn.NUMBERVALUE(MID(D20,2,5)),'TB LTD 12.22'!E:E,'TB LTD 12.22'!H:H,0,0,1) -> 415656.53 | J20: =SUMIF(AJE!$E:$E,D20,AJE!$H:$H) -> 0 | K20: =SUMIF(AJE!$Q:$Q,D20,AJE!$T:$T) -> 0 | L20: =I20+J20+K20 -> 415656.53 | M20: =SUMIF(AJE!$AB:$AB,D20,AJE!$AE:$AE) -> 0 | N20: =L20+M20 -> 415656.53 | R20: =L20*3.519 -> 1462695.3
A21: =_xlfn.XLOOKUP($B21,Index!$E:$E,Index!$D:$D,) -> 1 | B21: =IF($C21="Ltd",_xlfn.XLOOKUP($D21,Index!$V:$V,Index!$P:$P,),_xlfn.XLOOKUP($D21,Index!$AG:$AG,Index!$AA:$AA,)) -> Cash and Cash Equivalents | C21: =IF(LEFT(D21)="1","Ltd","Inc") -> Ltd | D21: 111012100 | E21: =_xlfn.XLOOKUP(_xlfn.NUMBERVALUE(MID(D21,2,5)),'TB LTD 12.22'!$E:$E,'TB LTD 12.22'!$F:$F,) -> בנק הפועלים AUD | F21: =IF(C21="Ltd",_xlfn.XLOOKUP(D21,Index!V:V,Index!R:R,),_xlfn.XLOOKUP(D21,Index!AG:AG,Index!AC:AC,)) -> 0 | G21: =IF(C21="Ltd",_xlfn.XLOOKUP(D21,Index!V:V,Index!T:T,),_xlfn.XLOOKUP(D21,Index!AG:AG,Index!AE:AE,)) -> 0 | I21: =_xlfn.XLOOKUP(_xlfn.NUMBERVALUE(MID(D21,2,5)),'TB LTD 12.22'!E:E,'TB LTD 12.22'!H:H,0,0,1) -> 220454.23 | J21: =SUMIF(AJE!$E:$E,D21,AJE!$H:$H) -> 0 | K21: =SUMIF(AJE!$Q:$Q,D21,AJE!$T:$T) -> 0 | L21: =I21+J21+K21 -> 220454.23 | M21: =SUMIF(AJE!$AB:$AB,D21,AJE!$AE:$AE) -> 0 | N21: =L21+M21 -> 220454.23 | R21: =L21*3.519 -> 775778.44
A22: =_xlfn.XLOOKUP($B22,Index!$E:$E,Index!$D:$D,) -> 1 | B22: =IF($C22="Ltd",_xlfn.XLOOKUP($D22,Index!$V:$V,Index!$P:$P,),_xlfn.XLOOKUP($D22,Index!$AG:$AG,Index!$AA:$AA,)) -> Cash and Cash Equivalents | C22: =IF(LEFT(D22)="1","Ltd","Inc") -> Ltd | D22: 111013100 | E22: =_xlfn.XLOOKUP(_xlfn.NUMBERVALUE(MID(D22,2,5)),'TB LTD 12.22'!$E:$E,'TB LTD 12.22'!$F:$F,) -> בנק הפועלים SGD | F22: =IF(C22="Ltd",_xlfn.XLOOKUP(D22,Index!V:V,Index!R:R,),_xlfn.XLOOKUP(D22,Index!AG:AG,Index!AC:AC,)) -> 0 | G22: =IF(C22="Ltd",_xlfn.XLOOKUP(D22,Index!V:V,Index!T:T,),_xlfn.XLOOKUP(D22,Index!AG:AG,Index!AE:AE,)) -> 0 | I22: =_xlfn.XLOOKUP(_xlfn.NUMBERVALUE(MID(D22,2,5)),'TB LTD 12.22'!E:E,'TB LTD 12.22'!H:H,0,0,1) -> 478724.33 | J22: =SUMIF(AJE!$E:$E,D22,AJE!$H:$H) -> 0 | K22: =SUMIF(AJE!$Q:$Q,D22,AJE!$T:$T) -> 0 | L22: =I22+J22+K22 -> 478724.33 | M22: =SUMIF(AJE!$AB:$AB,D22,AJE!$AE:$AE) -> 0 | N22: =L22+M22 -> 478724.33 | R22: =L22*3.519 -> 1684630.9
A23: =_xlfn.XLOOKUP($B23,Index!$E:$E,Index!$D:$D,) -> 1 | B23: =IF($C23="Ltd",_xlfn.XLOOKUP($D23,Index!$V:$V,Index!$P:$P,),_xlfn.XLOOKUP($D23,Index!$AG:$AG,Index!$AA:$AA,)) -> Cash and Cash Equivalents | C23: =IF(LEFT(D23)="1","Ltd","Inc") -> Ltd | D23: 111014100 | E23: =_xlfn.XLOOKUP(_xlfn.NUMBERVALUE(MID(D23,2,5)),'TB LTD 12.22'!$E:$E,'TB LTD 12.22'!$F:$F,) -> בנק SVB USD | F23: =IF(C23="Ltd",_xlfn.XLOOKUP(D23,Index!V:V,Index!R:R,),_xlfn.XLOOKUP(D23,Index!AG:AG,Index!AC:AC,)) -> 0 | G23: =IF(C23="Ltd",_xlfn.XLOOKUP(D23,Index!V:V,Index!T:T,),_xlfn.XLOOKUP(D23,Index!AG:AG,Index!AE:AE,)) -> 0 | I23: =_xlfn.XLOOKUP(_xlfn.NUMBERVALUE(MID(D23,2,5)),'TB LTD 12.22'!E:E,'TB LTD 12.22'!H:H,0,0,1) -> 1000000 | J23: =SUMIF(AJE!$E:$E,D23,AJE!$H:$H) -> 0 | K23: =SUMIF(AJE!$Q:$Q,D23,AJE!$T:$T) -> 0 | L23: =I23+J23+K23 -> 1000000 | M23: =SUMIF(AJE!$AB:$AB,D23,AJE!$AE:$AE) -> 0 | N23: =L23+M23 -> 1000000 | R23: =L23*3.519 -> 3519000
A24: =_xlfn.XLOOKUP($B24,Index!$E:$E,Index!$D:$D,) -> 6 | B24: =IF($C24="Ltd",_xlfn.XLOOKUP($D24,Index!$V:$V,Index!$P:$P,),_xlfn.XLOOKUP($D24,Index!$AG:$AG,Index!$AA:$AA,)) -> Accounts Payable | C24: =IF(LEFT(D24)="1","Ltd","Inc") -> Ltd | D24: 12100261030 | E24: =_xlfn.XLOOKUP(_xlfn.NUMBERVALUE(MID(D24,2,5)),'TB LTD 12.22'!$E:$E,'TB LTD 12.22'!$F:$F,) -> ישראכרט 0237 הד | F24: =IF(C24="Ltd",_xlfn.XLOOKUP(D24,Index!V:V,Index!R:R,),_xlfn.XLOOKUP(D24,Index!AG:AG,Index!AC:AC,)) -> Credit Cards | G24: =IF(C24="Ltd",_xlfn.XLOOKUP(D24,Index!V:V,Index!T:T,),_xlfn.XLOOKUP(D24,Index!AG:AG,Index!AE:AE,)) -> 0 | I24: =_xlfn.XLOOKUP(_xlfn.NUMBERVALUE(MID(D24,2,5)),'TB LTD 12.22'!E:E,'TB LTD 12.22'!H:H,0,0,1) -> -318.2 | J24: =SUMIF(AJE!$E:$E,D24,AJE!$H:$H) -> 0 | K24: =SUMIF(AJE!$Q:$Q,D24,AJE!$T:$T) -> 0 | L24: =I24+J24+K24 -> -318.2 | M24: =SUMIF(AJE!$AB:$AB,D24,AJE!$AE:$AE) -> 0 | N24: =L24+M24 -> -318.2
A25: =_xlfn.XLOOKUP($B25,Index!$E:$E,Index!$D:$D,) -> 6 | B25: =IF($C25="Ltd",_xlfn.XLOOKUP($D25,Index!$V:$V,Index!$P:$P,),_xlfn.XLOOKUP($D25,Index!$AG:$AG,Index!$AA:$AA,)) -> Accounts Payable | C25: =IF(LEFT(D25)="1","Ltd","Inc") -> Ltd | D25: 12100361030 | E25: =_xlfn.XLOOKUP(_xlfn.NUMBERVALUE(MID(D25,2,5)),'TB LTD 12.22'!$E:$E,'TB LTD 12.22'!$F:$F,) -> ישראכרט 4510 ירון | F25: =IF(C25="Ltd",_xlfn.XLOOKUP(D25,Index!V:V,Index!R:R,),_xlfn.XLOOKUP(D25,Index!AG:AG,Index!AC:AC,)) -> Credit Cards | G25: =IF(C25="Ltd",_xlfn.XLOOKUP(D25,Index!V:V,Index!T:T,),_xlfn.XLOOKUP(D25,Index!AG:AG,Index!AE:AE,)) -> 0 | I25: =_xlfn.XLOOKUP(_xlfn.NUMBERVALUE(MID(D25,2,5)),'TB LTD 12.22'!E:E,'TB LTD 12.22'!H:H,0,0,1) -> -69.35 | J25: =SUMIF(AJE!$E:$E,D25,AJE!$H:$H) -> 0 | K25: =SUMIF(AJE!$Q:$Q,D25,AJE!$T:$T) -> 0 | L25: =I25+J25+K25 -> -69.35 | M25: =SUMIF(AJE!$AB:$AB,D25,AJE!$AE:$AE) -> 0 | N25: =L25+M25 -> -69.35
A26: =_xlfn.XLOOKUP($B26,Index!$E:$E,Index!$D:$D,) -> 6 | B26: =IF($C26="Ltd",_xlfn.XLOOKUP($D26,Index!$V:$V,Index!$P:$P,),_xlfn.XLOOKUP($D26,Index!$AG:$AG,Index!$AA:$AA,)) -> Accounts Payable | C26: =IF(LEFT(D26)="1","Ltd","Inc") -> Ltd | D26: 12100661030 | E26: =_xlfn.XLOOKUP(_xlfn.NUMBERVALUE(MID(D26,2,5)),'TB LTD 12.22'!$E:$E,'TB LTD 12.22'!$F:$F,) -> ישרכארט ירון 4510 $ | F26: =IF(C26="Ltd",_xlfn.XLOOKUP(D26,Index!V:V,Index!R:R,),_xlfn.XLOOKUP(D26,Index!AG:AG,Index!AC:AC,)) -> Credit Cards | G26: =IF(C26="Ltd",_xlfn.XLOOKUP(D26,Index!V:V,Index!T:T,),_xlfn.XLOOKUP(D26,Index!AG:AG,Index!AE:AE,)) -> 0 | I26: =_xlfn.XLOOKUP(_xlfn.NUMBERVALUE(MID(D26,2,5)),'TB LTD 12.22'!E:E,'TB LTD 12.22'!H:H,0,0,1) -> -66.11 | J26: =SUMIF(AJE!$E:$E,D26,AJE!$H:$H) -> 0 | K26: =SUMIF(AJE!$Q:$Q,D26,AJE!$T:$T) -> 0 | L26: =I26+J26+K26 -> -66.11 | M26: =SUMIF(AJE!$AB:$AB,D26,AJE!$AE:$AE) -> 0 | N26: =L26+M26 -> -66.11
A27: =_xlfn.XLOOKUP($B27,Index!$E:$E,Index!$D:$D,) -> 6 | B27: =IF($C27="Ltd",_xlfn.XLOOKUP($D27,Index!$V:$V,Index!$P:$P,),_xlfn.XLOOKUP($D27,Index!$AG:$AG,Index!$AA:$AA,)) -> Accounts Payable | C27: =IF(LEFT(D27)="1","Ltd","Inc") -> Ltd | D27: 12100761030 | E27: =_xlfn.XLOOKUP(_xlfn.NUMBERVALUE(MID(D27,2,5)),'TB LTD 12.22'!$E:$E,'TB LTD 12.22'!$F:$F,) -> ישראכרט הד 0237 $ | F27: =IF(C27="Ltd",_xlfn.XLOOKUP(D27,Index!V:V,Index!R:R,),_xlfn.XLOOKUP(D27,Index!AG:AG,Index!AC:AC,)) -> Credit Cards | G27: =IF(C27="Ltd",_xlfn.XLOOKUP(D27,Index!V:V,Index!T:T,),_xlfn.XLOOKUP(D27,Index!AG:AG,Index!AE:AE,)) -> 0 | I27: =_xlfn.XLOOKUP(_xlfn.NUMBERVALUE(MID(D27,2,5)),'TB LTD 12.22'!E:E,'TB LTD 12.22'!H:H,0,0,1) -> -1534.11 | J27: =SUMIF(AJE!$E:$E,D27,AJE!$H:$H) -> 0 | K27: =SUMIF(AJE!$Q:$Q,D27,AJE!$T:$T) -> 0 | L27: =I27+J27+K27 -> -1534.11 | M27: =SUMIF(AJE!$AB:$AB,D27,AJE!$AE:$AE) -> 0 | N27: =L27+M27 -> -1534.11
A28: =_xlfn.XLOOKUP($B28,Index!$E:$E,Index!$D:$D,) -> 6 | B28: =IF($C28="Ltd",_xlfn.XLOOKUP($D28,Index!$V:$V,Index!$P:$P,),_xlfn.XLOOKUP($D28,Index!$AG:$AG,Index!$AA:$AA,)) -> Accounts Payable | C28: =IF(LEFT(D28)="1","Ltd","Inc") -> Ltd | D28: 12100861030 | E28: =_xlfn.XLOOKUP(_xlfn.NUMBERVALUE(MID(D28,2,5)),'TB LTD 12.22'!$E:$E,'TB LTD 12.22'!$F:$F,) -> ישראכרט 1943 | F28: =IF(C28="Ltd",_xlfn.XLOOKUP(D28,Index!V:V,Index!R:R,),_xlfn.XLOOKUP(D28,Index!AG:AG,Index!AC:AC,)) -> Credit Cards | G28: =IF(C28="Ltd",_xlfn.XLOOKUP(D28,Index!V:V,Index!T:T,),_xlfn.XLOOKUP(D28,Index!AG:AG,Index!AE:AE,)) -> 0 | I28: =_xlfn.XLOOKUP(_xlfn.NUMBERVALUE(MID(D28,2,5)),'TB LTD 12.22'!E:E,'TB LTD 12.22'!H:H,0,0,1) -> -9691.33 | J28: =SUMIF(AJE!$E:$E,D28,AJE!$H:$H) -> 0 | K28: =SUMIF(AJE!$Q:$Q,D28,AJE!$T:$T) -> 0 | L28: =I28+J28+K28 -> -9691.33 | M28: =SUMIF(AJE!$AB:$AB,D28,AJE!$AE:$AE) -> 0 | N28: =L28+M28 -> -9691.33
A29: =_xlfn.XLOOKUP($B29,Index!$E:$E,Index!$D:$D,) -> 6 | B29: =IF($C29="Ltd",_xlfn.XLOOKUP($D29,Index!$V:$V,Index!$P:$P,),_xlfn.XLOOKUP($D29,Index!$AG:$AG,Index!$AA:$AA,)) -> Accounts Payable | C29: =IF(LEFT(D29)="1","Ltd","Inc") -> Ltd | D29: 12100961030 | E29: =_xlfn.XLOOKUP(_xlfn.NUMBERVALUE(MID(D29,2,5)),'TB LTD 12.22'!$E:$E,'TB LTD 12.22'!$F:$F,) -> ישראכרט 1943 $ | F29: =IF(C29="Ltd",_xlfn.XLOOKUP(D29,Index!V:V,Index!R:R,),_xlfn.XLOOKUP(D29,Index!AG:AG,Index!AC:AC,)) -> Credit Cards | G29: =IF(C29="Ltd",_xlfn.XLOOKUP(D29,Index!V:V,Index!T:T,),_xlfn.XLOOKUP(D29,Index!AG:AG,Index!AE:AE,)) -> 0 | I29: =_xlfn.XLOOKUP(_xlfn.NUMBERVALUE(MID(D29,2,5)),'TB LTD 12.22'!E:E,'TB LTD 12.22'!H:H,0,0,1) -> -8574.42 | J29: =SUMIF(AJE!$E:$E,D29,AJE!$H:$H) -> 0 | K29: =SUMIF(AJE!$Q:$Q,D29,AJE!$T:$T) -> 0 | L29: =I29+J29+K29 -> -8574.42 | M29: =SUMIF(AJE!$AB:$AB,D29,AJE!$AE:$AE) -> 0 | N29: =L29+M29 -> -8574.42
A30: =_xlfn.XLOOKUP($B30,Index!$E:$E,Index!$D:$D,) -> 6 | B30: =IF($C30="Ltd",_xlfn.XLOOKUP($D30,Index!$V:$V,Index!$P:$P,),_xlfn.XLOOKUP($D30,Index!$AG:$AG,Index!$AA:$AA,)) -> Accounts Payable | C30: =IF(LEFT(D30)="1","Ltd","Inc") -> Ltd | D30: 12101061030 | E30: =_xlfn.XLOOKUP(_xlfn.NUMBERVALUE(MID(D30,2,5)),'TB LTD 12.22'!$E:$E,'TB LTD 12.22'!$F:$F,) -> ישראכרט 1943 EUR | F30: =IF(C30="Ltd",_xlfn.XLOOKUP(D30,Index!V:V,Index!R:R,),_xlfn.XLOOKUP(D30,Index!AG:AG,Index!AC:AC,)) -> Credit Cards | G30: =IF(C30="Ltd",_xlfn.XLOOKUP(D30,Index!V:V,Index!T:T,),_xlfn.XLOOKUP(D30,Index!AG:AG,Index!AE:AE,)) -> 0 | I30: =_xlfn.XLOOKUP(_xlfn.NUMBERVALUE(MID(D30,2,5)),'TB LTD 12.22'!E:E,'TB LTD 12.22'!H:H,0,0,1) -> -438.8 | J30: =SUMIF(AJE!$E:$E,D30,AJE!$H:$H) -> 0 | K30: =SUMIF(AJE!$Q:$Q,D30,AJE!$T:$T) -> 0 | L30: =I30+J30+K30 -> -438.8 | M30: =SUMIF(AJE!$AB:$AB,D30,AJE!$AE:$AE) -> 0 | N30: =L30+M30 -> -438.8
A31: =_xlfn.XLOOKUP($B31,Index!$E:$E,Index!$D:$D,) -> 6 | B31: =IF($C31="Ltd",_xlfn.XLOOKUP($D31,Index!$V:$V,Index!$P:$P,),_xlfn.XLOOKUP($D31,Index!$AG:$AG,Index!$AA:$AA,)) -> Accounts Payable | C31: =IF(LEFT(D31)="1","Ltd","Inc") -> Ltd | D31: 12101161030 | E31: =_xlfn.XLOOKUP(_xlfn.NUMBERVALUE(MID(D31,2,5)),'TB LTD 12.22'!$E:$E,'TB LTD 12.22'!$F:$F,) -> מסטרקרד 5930 | F31: =IF(C31="Ltd",_xlfn.XLOOKUP(D31,Index!V:V,Index!R:R,),_xlfn.XLOOKUP(D31,Index!AG:AG,Index!AC:AC,)) -> Credit Cards | G31: =IF(C31="Ltd",_xlfn.XLOOKUP(D31,Index!V:V,Index!T:T,),_xlfn.XLOOKUP(D31,Index!AG:AG,Index!AE:AE,)) -> 0 | I31: =_xlfn.XLOOKUP(_xlfn.NUMBERVALUE(MID(D31,2,5)),'TB LTD 12.22'!E:E,'TB LTD 12.22'!H:H,0,0,1) -> -3947.88 | J31: =SUMIF(AJE!$E:$E,D31,AJE!$H:$H) -> 0 | K31: =SUMIF(AJE!$Q:$Q,D31,AJE!$T:$T) -> 0 | L31: =I31+J31+K31 -> -3947.88 | M31: =SUMIF(AJE!$AB:$AB,D31,AJE!$AE:$AE) -> 0 | N31: =L31+M31 -> -3947.88
A32: =_xlfn.XLOOKUP($B32,Index!$E:$E,Index!$D:$D,) -> 6 | B32: =IF($C32="Ltd",_xlfn.XLOOKUP($D32,Index!$V:$V,Index!$P:$P,),_xlfn.XLOOKUP($D32,Index!$AG:$AG,Index!$AA:$AA,)) -> Accounts Payable | C32: =IF(LEFT(D32)="1","Ltd","Inc") -> Ltd | D32: 12101361030 | E32: =_xlfn.XLOOKUP(_xlfn.NUMBERVALUE(MID(D32,2,5)),'TB LTD 12.22'!$E:$E,'TB LTD 12.22'!$F:$F,) -> מסטרקרד 5930 $ | F32: =IF(C32="Ltd",_xlfn.XLOOKUP(D32,Index!V:V,Index!R:R,),_xlfn.XLOOKUP(D32,Index!AG:AG,Index!AC:AC,)) -> Credit Cards | G32: =IF(C32="Ltd",_xlfn.XLOOKUP(D32,Index!V:V,Index!T:T,),_xlfn.XLOOKUP(D32,Index!AG:AG,Index!AE:AE,)) -> 0 | I32: =_xlfn.XLOOKUP(_xlfn.NUMBERVALUE(MID(D32,2,5)),'TB LTD 12.22'!E:E,'TB LTD 12.22'!H:H,0,0,1) -> -349.31 | J32: =SUMIF(AJE!$E:$E,D32,AJE!$H:$H) -> 0 | K32: =SUMIF(AJE!$Q:$Q,D32,AJE!$T:$T) -> 0 | L32: =I32+J32+K32 -> -349.31 | M32: =SUMIF(AJE!$AB:$AB,D32,AJE!$AE:$AE) -> 0 | N32: =L32+M32 -> -349.31
A33: =_xlfn.XLOOKUP($B33,Index!$E:$E,Index!$D:$D,) -> 6 | B33: =IF($C33="Ltd",_xlfn.XLOOKUP($D33,Index!$V:$V,Index!$P:$P,),_xlfn.XLOOKUP($D33,Index!$AG:$AG,Index!$AA:$AA,)) -> Accounts Payable | C33: =IF(LEFT(D33)="1","Ltd","Inc") -> Ltd | D33: 12101461030 | E33: =_xlfn.XLOOKUP(_xlfn.NUMBERVALUE(MID(D33,2,5)),'TB LTD 12.22'!$E:$E,'TB LTD 12.22'!$F:$F,) -> ישראכרט 1243 $ | F33: =IF(C33="Ltd",_xlfn.XLOOKUP(D33,Index!V:V,Index!R:R,),_xlfn.XLOOKUP(D33,Index!AG:AG,Index!AC:AC,)) -> Credit Cards | G33: =IF(C33="Ltd",_xlfn.XLOOKUP(D33,Index!V:V,Index!T:T,),_xlfn.XLOOKUP(D33,Index!AG:AG,Index!AE:AE,)) -> 0 | I33: =_xlfn.XLOOKUP(_xlfn.NUMBERVALUE(MID(D33,2,5)),'TB LTD 12.22'!E:E,'TB LTD 12.22'!H:H,0,0,1) -> -2500 | J33: =SUMIF(AJE!$E:$E,D33,AJE!$H:$H) -> 0 | K33: =SUMIF(AJE!$Q:$Q,D33,AJE!$T:$T) -> 0 | L33: =I33+J33+K33 -> -2500 | M33: =SUMIF(AJE!$AB:$AB,D33,AJE!$AE:$AE) -> 0 | N33: =L33+M33 -> -2500
A34: =_xlfn.XLOOKUP($B34,Index!$E:$E,Index!$D:$D,) -> 6 | B34: =IF($C34="Ltd",_xlfn.XLOOKUP($D34,Index!$V:$V,Index!$P:$P,),_xlfn.XLOOKUP($D34,Index!$AG:$AG,Index!$AA:$AA,)) -> Accounts Payable | C34: =IF(LEFT(D34)="1","Ltd","Inc") -> Ltd | D34: 12101561030 | E34: =_xlfn.XLOOKUP(_xlfn.NUMBERVALUE(MID(D34,2,5)),'TB LTD 12.22'!$E:$E,'TB LTD 12.22'!$F:$F,) -> מסטרקרד 5948 | F34: =IF(C34="Ltd",_xlfn.XLOOKUP(D34,Index!V:V,Index!R:R,),_xlfn.XLOOKUP(D34,Index!AG:AG,Index!AC:AC,)) -> Credit Cards | G34: =IF(C34="Ltd",_xlfn.XLOOKUP(D34,Index!V:V,Index!T:T,),_xlfn.XLOOKUP(D34,Index!AG:AG,Index!AE:AE,)) -> 0 | I34: =_xlfn.XLOOKUP(_xlfn.NUMBERVALUE(MID(D34,2,5)),'TB LTD 12.22'!E:E,'TB LTD 12.22'!H:H,0,0,1) -> -6385.22 | J34: =SUMIF(AJE!$E:$E,D34,AJE!$H:$H) -> 0 | K34: =SUMIF(AJE!$Q:$Q,D34,AJE!$T:$T) -> 0 | L34: =I34+J34+K34 -> -6385.22 | M34: =SUMIF(AJE!$AB:$AB,D34,AJE!$AE:$AE) -> 0 | N34: =L34+M34 -> -6385.22
A35: =_xlfn.XLOOKUP($B35,Index!$E:$E,Index!$D:$D,) -> 6 | B35: =IF($C35="Ltd",_xlfn.XLOOKUP($D35,Index!$V:$V,Index!$P:$P,),_xlfn.XLOOKUP($D35,Index!$AG:$AG,Index!$AA:$AA,)) -> Accounts Payable | C35: =IF(LEFT(D35)="1","Ltd","Inc") -> Ltd | D35: 12102061030 | E35: =_xlfn.XLOOKUP(_xlfn.NUMBERVALUE(MID(D35,2,5)),'TB LTD 12.22'!$E:$E,'TB LTD 12.22'!$F:$F,) -> ישראכרט ירון 6892 שח | F35: =IF(C35="Ltd",_xlfn.XLOOKUP(D35,Index!V:V,Index!R:R,),_xlfn.XLOOKUP(D35,Index!AG:AG,Index!AC:AC,)) -> Credit Cards | G35: =IF(C35="Ltd",_xlfn.XLOOKUP(D35,Index!V:V,Index!T:T,),_xlfn.XLOOKUP(D35,Index!AG:AG,Index!AE:AE,)) -> 0 | I35: =_xlfn.XLOOKUP(_xlfn.NUMBERVALUE(MID(D35,2,5)),'TB LTD 12.22'!E:E,'TB LTD 12.22'!H:H,0,0,1) -> -253.62 | J35: =SUMIF(AJE!$E:$E,D35,AJE!$H:$H) -> 0 | K35: =SUMIF(AJE!$Q:$Q,D35,AJE!$T:$T) -> 0 | L35: =I35+J35+K35 -> -253.62 | M35: =SUMIF(AJE!$AB:$AB,D35,AJE!$AE:$AE) -> 0 | N35: =L35+M35 -> -253.62
... A283: =_xlfn.XLOOKUP($B283,Index!$E:$E,Index!$D:$D,) -> 99 | B283: =IF($C283="Ltd",_xlfn.XLOOKUP($D283,Index!$V:$V,Index!$P:$P,),_xlfn.XLOOKUP($D283,Index!$AG:$AG,Index!$AA:$AA,)) -> Overhead | C283: =IF(LEFT(D283)="1","Ltd","Inc") -> Ltd | D283: 1650169900 | E283: =_xlfn.XLOOKUP(_xlfn.NUMBERVALUE(MID(D283,2,5)),'TB LTD 12.22'!$E:$E,'TB LTD 12.22'!$F:$F,) -> כיבודים | F283: =IF(C283="Ltd",_xlfn.XLOOKUP(D283,Index!V:V,Index!R:R,),_xlfn.XLOOKUP(D283,Index!AG:AG,Index!AC:AC,)) -> 0 | G283: =IF(C283="Ltd",_xlfn.XLOOKUP(D283,Index!V:V,Index!T:T,),_xlfn.XLOOKUP(D283,Index!AG:AG,Index!AE:AE,)) -> 0 | I283: =_xlfn.XLOOKUP(_xlfn.NUMBERVALUE(MID(D283,2,5)),'TB LTD 12.22'!E:E,'TB LTD 12.22'!H:H,0,0,1) -> 40798.86 | J283: =SUMIF(AJE!$E:$E,D283,AJE!$H:$H) -> 0 | K283: =SUMIF(AJE!$Q:$Q,D283,AJE!$T:$T) -> -40798.86 | L283: =I283+J283+K283 -> 0 | M283: =SUMIF(AJE!$AB:$AB,D283,AJE!$AE:$AE) -> 0 | N283: =L283+M283 -> 0
A284: =_xlfn.XLOOKUP($B284,Index!$E:$E,Index!$D:$D,) -> 99 | B284: =IF($C284="Ltd",_xlfn.XLOOKUP($D284,Index!$V:$V,Index!$P:$P,),_xlfn.XLOOKUP($D284,Index!$AG:$AG,Index!$AA:$AA,)) -> Overhead | C284: =IF(LEFT(D284)="1","Ltd","Inc") -> Ltd | D284: 165016L9900 | E284: =_xlfn.XLOOKUP((MID(D284,2,6)),'TB LTD 12.22'!$E:$E,'TB LTD 12.22'!$F:$F,) -> כיבודים לא מוכר | F284: =IF(C284="Ltd",_xlfn.XLOOKUP(D284,Index!V:V,Index!R:R,),_xlfn.XLOOKUP(D284,Index!AG:AG,Index!AC:AC,)) -> 0 | G284: =IF(C284="Ltd",_xlfn.XLOOKUP(D284,Index!V:V,Index!T:T,),_xlfn.XLOOKUP(D284,Index!AG:AG,Index!AE:AE,)) -> 0 | I284: =_xlfn.XLOOKUP((MID(D284,2,6)),'TB LTD 12.22'!E:E,'TB LTD 12.22'!H:H,0,0,1) -> 31188.71 | J284: =SUMIF(AJE!$E:$E,D284,AJE!$H:$H) -> 0 | K284: =SUMIF(AJE!$Q:$Q,D284,AJE!$T:$T) -> -31188.71 | L284: =I284+J284+K284 -> 0 | M284: =SUMIF(AJE!$AB:$AB,D284,AJE!$AE:$AE) -> 0 | N284: =L284+M284 -> 0
A285: =_xlfn.XLOOKUP($B285,Index!$E:$E,Index!$D:$D,) -> 99 | B285: =IF($C285="Ltd",_xlfn.XLOOKUP($D285,Index!$V:$V,Index!$P:$P,),_xlfn.XLOOKUP($D285,Index!$AG:$AG,Index!$AA:$AA,)) -> Overhead | C285: =IF(LEFT(D285)="1","Ltd","Inc") -> Ltd | D285: 1650179900 | E285: =_xlfn.XLOOKUP(_xlfn.NUMBERVALUE(MID(D285,2,5)),'TB LTD 12.22'!$E:$E,'TB LTD 12.22'!$F:$F,) -> מתנות לעובדי ישראל | F285: =IF(C285="Ltd",_xlfn.XLOOKUP(D285,Index!V:V,Index!R:R,),_xlfn.XLOOKUP(D285,Index!AG:AG,Index!AC:AC,)) -> 0 | G285: =IF(C285="Ltd",_xlfn.XLOOKUP(D285,Index!V:V,Index!T:T,),_xlfn.XLOOKUP(D285,Index!AG:AG,Index!AE:AE,)) -> 0 | I285: =_xlfn.XLOOKUP(_xlfn.NUMBERVALUE(MID(D285,2,5)),'TB LTD 12.22'!E:E,'TB LTD 12.22'!H:H,0,0,1) -> 126978.38 | J285: =SUMIF(AJE!$E:$E,D285,AJE!$H:$H) -> 0 | K285: =SUMIF(AJE!$Q:$Q,D285,AJE!$T:$T) -> -126978.38 | L285: =I285+J285+K285 -> 0 | M285: =SUMIF(AJE!$AB:$AB,D285,AJE!$AE:$AE) -> 0 | N285: =L285+M285 -> 0
A286: =_xlfn.XLOOKUP($B286,Index!$E:$E,Index!$D:$D,) -> 99 | B286: =IF($C286="Ltd",_xlfn.XLOOKUP($D286,Index!$V:$V,Index!$P:$P,),_xlfn.XLOOKUP($D286,Index!$AG:$AG,Index!$AA:$AA,)) -> Overhead | C286: =IF(LEFT(D286)="1","Ltd","Inc") -> Ltd | D286: 1650209900 | E286: =_xlfn.XLOOKUP(_xlfn.NUMBERVALUE(MID(D286,2,5)),'TB LTD 12.22'!$E:$E,'TB LTD 12.22'!$F:$F,) -> אגרות | F286: =IF(C286="Ltd",_xlfn.XLOOKUP(D286,Index!V:V,Index!R:R,),_xlfn.XLOOKUP(D286,Index!AG:AG,Index!AC:AC,)) -> 0 | G286: =IF(C286="Ltd",_xlfn.XLOOKUP(D286,Index!V:V,Index!T:T,),_xlfn.XLOOKUP(D286,Index!AG:AG,Index!AE:AE,)) -> 0 | I286: =_xlfn.XLOOKUP(_xlfn.NUMBERVALUE(MID(D286,2,5)),'TB LTD 12.22'!E:E,'TB LTD 12.22'!H:H,0,0,1) -> 385.53 | J286: =SUMIF(AJE!$E:$E,D286,AJE!$H:$H) -> 0 | K286: =SUMIF(AJE!$Q:$Q,D286,AJE!$T:$T) -> -385.53 | L286: =I286+J286+K286 -> 0 | M286: =SUMIF(AJE!$AB:$AB,D286,AJE!$AE:$AE) -> 0 | N286: =L286+M286 -> 0
A287: =_xlfn.XLOOKUP($B287,Index!$E:$E,Index!$D:$D,) -> 99 | B287: =IF($C287="Ltd",_xlfn.XLOOKUP($D287,Index!$V:$V,Index!$P:$P,),_xlfn.XLOOKUP($D287,Index!$AG:$AG,Index!$AA:$AA,)) -> Overhead | C287: =IF(LEFT(D287)="1","Ltd","Inc") -> Ltd | D287: 1650219900 | E287: =_xlfn.XLOOKUP(_xlfn.NUMBERVALUE(MID(D287,2,5)),'TB LTD 12.22'!$E:$E,'TB LTD 12.22'!$F:$F,) -> גיבוש ורווחה וימי כיף עובדים | F287: =IF(C287="Ltd",_xlfn.XLOOKUP(D287,Index!V:V,Index!R:R,),_xlfn.XLOOKUP(D287,Index!AG:AG,Index!AC:AC,)) -> 0 | G287: =IF(C287="Ltd",_xlfn.XLOOKUP(D287,Index!V:V,Index!T:T,),_xlfn.XLOOKUP(D287,Index!AG:AG,Index!AE:AE,)) -> 0 | I287: =_xlfn.XLOOKUP(_xlfn.NUMBERVALUE(MID(D287,2,5)),'TB LTD 12.22'!E:E,'TB LTD 12.22'!H:H,0,0,1) -> 118369.7 | J287: =SUMIF(AJE!$E:$E,D287,AJE!$H:$H) -> 0 | K287: =SUMIF(AJE!$Q:$Q,D287,AJE!$T:$T) -> -118369.7 | L287: =I287+J287+K287 -> 0 | M287: =SUMIF(AJE!$AB:$AB,D287,AJE!$AE:$AE) -> 0 | N287: =L287+M287 -> 0
A288: =_xlfn.XLOOKUP($B288,Index!$E:$E,Index!$D:$D,) -> 70 | B288: =IF($C288="Ltd",_xlfn.XLOOKUP($D288,Index!$V:$V,Index!$P:$P,),_xlfn.XLOOKUP($D288,Index!$AG:$AG,Index!$AA:$AA,)) -> G&A | C288: =IF(LEFT(D288)="1","Ltd","Inc") -> Ltd | D288: 165030701120 | E288: =_xlfn.XLOOKUP(_xlfn.NUMBERVALUE(MID(D288,2,5)),'TB LTD 12.22'!$E:$E,'TB LTD 12.22'!$F:$F,) -> יעוץ ושירותי HR | F288: =IF(C288="Ltd",_xlfn.XLOOKUP(D288,Index!V:V,Index!R:R,),_xlfn.XLOOKUP(D288,Index!AG:AG,Index!AC:AC,)) -> Other HR | G288: =IF(C288="Ltd",_xlfn.XLOOKUP(D288,Index!V:V,Index!T:T,),_xlfn.XLOOKUP(D288,Index!AG:AG,Index!AE:AE,)) -> 0 | I288: =_xlfn.XLOOKUP(_xlfn.NUMBERVALUE(MID(D288,2,5)),'TB LTD 12.22'!E:E,'TB LTD 12.22'!H:H,0,0,1) -> 25411.28 | J288: =SUMIF(AJE!$E:$E,D288,AJE!$H:$H) -> 0 | K288: =SUMIF(AJE!$Q:$Q,D288,AJE!$T:$T) -> 0 | L288: =I288+J288+K288 -> 25411.28 | M288: =SUMIF(AJE!$AB:$AB,D288,AJE!$AE:$AE) -> 0 | N288: =L288+M288 -> 25411.28
A289: =_xlfn.XLOOKUP($B289,Index!$E:$E,Index!$D:$D,) -> 70 | B289: =IF($C289="Ltd",_xlfn.XLOOKUP($D289,Index!$V:$V,Index!$P:$P,),_xlfn.XLOOKUP($D289,Index!$AG:$AG,Index!$AA:$AA,)) -> G&A | C289: =IF(LEFT(D289)="1","Ltd","Inc") -> Ltd | D289: 165032701230 | E289: =_xlfn.XLOOKUP(_xlfn.NUMBERVALUE(MID(D289,2,5)),'TB LTD 12.22'!$E:$E,'TB LTD 12.22'!$F:$F,) -> IT licenses G&A | F289: =IF(C289="Ltd",_xlfn.XLOOKUP(D289,Index!V:V,Index!R:R,),_xlfn.XLOOKUP(D289,Index!AG:AG,Index!AC:AC,)) -> Software | G289: =IF(C289="Ltd",_xlfn.XLOOKUP(D289,Index!V:V,Index!T:T,),_xlfn.XLOOKUP(D289,Index!AG:AG,Index!AE:AE,)) -> 0 | I289: =_xlfn.XLOOKUP(_xlfn.NUMBERVALUE(MID(D289,2,5)),'TB LTD 12.22'!E:E,'TB LTD 12.22'!H:H,0,0,1) -> 171664.6 | J289: =SUMIF(AJE!$E:$E,D289,AJE!$H:$H) -> 0 | K289: =SUMIF(AJE!$Q:$Q,D289,AJE!$T:$T) -> 0 | L289: =I289+J289+K289 -> 171664.6 | M289: =SUMIF(AJE!$AB:$AB,D289,AJE!$AE:$AE) -> 0 | N289: =L289+M289 -> 171664.6
A290: =_xlfn.XLOOKUP($B290,Index!$E:$E,Index!$D:$D,) -> 70 | B290: =IF($C290="Ltd",_xlfn.XLOOKUP($D290,Index!$V:$V,Index!$P:$P,),_xlfn.XLOOKUP($D290,Index!$AG:$AG,Index!$AA:$AA,)) -> G&A | C290: =IF(LEFT(D290)="1","Ltd","Inc") -> Ltd | D290: 165060701230 | E290: =_xlfn.XLOOKUP(_xlfn.NUMBERVALUE(MID(D290,2,5)),'TB LTD 12.22'!$E:$E,'TB LTD 12.22'!$F:$F,) -> IT equipment G&A | F290: =IF(C290="Ltd",_xlfn.XLOOKUP(D290,Index!V:V,Index!R:R,),_xlfn.XLOOKUP(D290,Index!AG:AG,Index!AC:AC,)) -> Software | G290: =IF(C290="Ltd",_xlfn.XLOOKUP(D290,Index!V:V,Index!T:T,),_xlfn.XLOOKUP(D290,Index!AG:AG,Index!AE:AE,)) -> 0 | I290: =_xlfn.XLOOKUP(_xlfn.NUMBERVALUE(MID(D290,2,5)),'TB LTD 12.22'!E:E,'TB LTD 12.22'!H:H,0,0,1) -> 58942.95 | J290: =SUMIF(AJE!$E:$E,D290,AJE!$H:$H) -> 0 | K290: =SUMIF(AJE!$Q:$Q,D290,AJE!$T:$T) -> 0 | L290: =I290+J290+K290 -> 58942.95 | M290: =SUMIF(AJE!$AB:$AB,D290,AJE!$AE:$AE) -> 0 | N290: =L290+M290 -> 58942.95
A291: =_xlfn.XLOOKUP($B291,Index!$E:$E,Index!$D:$D,) -> 70 | B291: =IF($C291="Ltd",_xlfn.XLOOKUP($D291,Index!$V:$V,Index!$P:$P,),_xlfn.XLOOKUP($D291,Index!$AG:$AG,Index!$AA:$AA,)) -> G&A | C291: =IF(LEFT(D291)="1","Ltd","Inc") -> Ltd | D291: 165068701230 | E291: =_xlfn.XLOOKUP(_xlfn.NUMBERVALUE(MID(D291,2,5)),'TB LTD 12.22'!$E:$E,'TB LTD 12.22'!$F:$F,) -> Software and tools G&A for finance | F291: =IF(C291="Ltd",_xlfn.XLOOKUP(D291,Index!V:V,Index!R:R,),_xlfn.XLOOKUP(D291,Index!AG:AG,Index!AC:AC,)) -> Software | G291: =IF(C291="Ltd",_xlfn.XLOOKUP(D291,Index!V:V,Index!T:T,),_xlfn.XLOOKUP(D291,Index!AG:AG,Index!AE:AE,)) -> 0 | I291: =_xlfn.XLOOKUP(_xlfn.NUMBERVALUE(MID(D291,2,5)),'TB LTD 12.22'!E:E,'TB LTD 12.22'!H:H,0,0,1) -> 52400.16 | J291: =SUMIF(AJE!$E:$E,D291,AJE!$H:$H) -> 0 | K291: =SUMIF(AJE!$Q:$Q,D291,AJE!$T:$T) -> 0 | L291: =I291+J291+K291 -> 52400.16 | M291: =SUMIF(AJE!$AB:$AB,D291,AJE!$AE:$AE) -> 0 | N291: =L291+M291 -> 52400.16
A292: =_xlfn.XLOOKUP($B292,Index!$E:$E,Index!$D:$D,) -> 70 | B292: =IF($C292="Ltd",_xlfn.XLOOKUP($D292,Index!$V:$V,Index!$P:$P,),_xlfn.XLOOKUP($D292,Index!$AG:$AG,Index!$AA:$AA,)) -> G&A | C292: =IF(LEFT(D292)="1","Ltd","Inc") -> Ltd | D292: 165079701230 | E292: =_xlfn.XLOOKUP(_xlfn.NUMBERVALUE(MID(D292,2,5)),'TB LTD 12.22'!$E:$E,'TB LTD 12.22'!$F:$F,) -> Software and tools G&A for HR | F292: =IF(C292="Ltd",_xlfn.XLOOKUP(D292,Index!V:V,Index!R:R,),_xlfn.XLOOKUP(D292,Index!AG:AG,Index!AC:AC,)) -> Software | G292: =IF(C292="Ltd",_xlfn.XLOOKUP(D292,Index!V:V,Index!T:T,),_xlfn.XLOOKUP(D292,Index!AG:AG,Index!AE:AE,)) -> 0 | I292: =_xlfn.XLOOKUP(_xlfn.NUMBERVALUE(MID(D292,2,5)),'TB LTD 12.22'!E:E,'TB LTD 12.22'!H:H,0,0,1) -> 11043.72 | J292: =SUMIF(AJE!$E:$E,D292,AJE!$H:$H) -> 0 | K292: =SUMIF(AJE!$Q:$Q,D292,AJE!$T:$T) -> 0 | L292: =I292+J292+K292 -> 11043.72 | M292: =SUMIF(AJE!$AB:$AB,D292,AJE!$AE:$AE) -> 0 | N292: =L292+M292 -> 11043.72
A293: =_xlfn.XLOOKUP($B293,Index!$E:$E,Index!$D:$D,) -> 70 | B293: =IF($C293="Ltd",_xlfn.XLOOKUP($D293,Index!$V:$V,Index!$P:$P,),_xlfn.XLOOKUP($D293,Index!$AG:$AG,Index!$AA:$AA,)) -> G&A | C293: =IF(LEFT(D293)="1","Ltd","Inc") -> Ltd | D293: 165069701230 | E293: =_xlfn.XLOOKUP(_xlfn.NUMBERVALUE(MID(D293,2,5)),'TB LTD 12.22'!$E:$E,'TB LTD 12.22'!$F:$F,) -> Training G&A | F293: =IF(C293="Ltd",_xlfn.XLOOKUP(D293,Index!V:V,Index!R:R,),_xlfn.XLOOKUP(D293,Index!AG:AG,Index!AC:AC,)) -> Software | G293: =IF(C293="Ltd",_xlfn.XLOOKUP(D293,Index!V:V,Index!T:T,),_xlfn.XLOOKUP(D293,Index!AG:AG,Index!AE:AE,)) -> 0 | I293: =_xlfn.XLOOKUP(_xlfn.NUMBERVALUE(MID(D293,2,5)),'TB LTD 12.22'!E:E,'TB LTD 12.22'!H:H,0,0,1) -> 720 | J293: =SUMIF(AJE!$E:$E,D293,AJE!$H:$H) -> 0 | K293: =SUMIF(AJE!$Q:$Q,D293,AJE!$T:$T) -> 0 | L293: =I293+J293+K293 -> 720 | M293: =SUMIF(AJE!$AB:$AB,D293,AJE!$AE:$AE) -> 0 | N293: =L293+M293 -> 720
A294: =_xlfn.XLOOKUP($B294,Index!$E:$E,Index!$D:$D,) -> 70 | B294: =IF($C294="Ltd",_xlfn.XLOOKUP($D294,Index!$V:$V,Index!$P:$P,),_xlfn.XLOOKUP($D294,Index!$AG:$AG,Index!$AA:$AA,)) -> G&A | C294: =IF(LEFT(D294)="1","Ltd","Inc") -> Ltd | D294: 165084701120 | E294: =_xlfn.XLOOKUP(_xlfn.NUMBERVALUE(MID(D294,2,5)),'TB LTD 12.22'!$E:$E,'TB LTD 12.22'!$F:$F,) -> HR Awareness | F294: =IF(C294="Ltd",_xlfn.XLOOKUP(D294,Index!V:V,Index!R:R,),_xlfn.XLOOKUP(D294,Index!AG:AG,Index!AC:AC,)) -> Other HR | G294: =IF(C294="Ltd",_xlfn.XLOOKUP(D294,Index!V:V,Index!T:T,),_xlfn.XLOOKUP(D294,Index!AG:AG,Index!AE:AE,)) -> 0 | I294: =_xlfn.XLOOKUP(_xlfn.NUMBERVALUE(MID(D294,2,5)),'TB LTD 12.22'!E:E,'TB LTD 12.22'!H:H,0,0,1) -> 10061 | J294: =SUMIF(AJE!$E:$E,D294,AJE!$H:$H) -> 0 | K294: =SUMIF(AJE!$Q:$Q,D294,AJE!$T:$T) -> 0 | L294: =I294+J294+K294 -> 10061 | M294: =SUMIF(AJE!$AB:$AB,D294,AJE!$AE:$AE) -> 0 | N294: =L294+M294 -> 10061
A295: =_xlfn.XLOOKUP($B295,Index!$E:$E,Index!$D:$D,) -> 70 | B295: =IF($C295="Ltd",_xlfn.XLOOKUP($D295,Index!$V:$V,Index!$P:$P,),_xlfn.XLOOKUP($D295,Index!$AG:$AG,Index!$AA:$AA,)) -> G&A | C295: =IF(LEFT(D295)="1","Ltd","Inc") -> Ltd | D295: 165202701120 | E295: =_xlfn.XLOOKUP(_xlfn.NUMBERVALUE(MID(D295,2,5)),'TB LTD 12.22'!$E:$E,'TB LTD 12.22'!$F:$F,) -> Field Hr Support (prints, giveaways) | F295: =IF(C295="Ltd",_xlfn.XLOOKUP(D295,Index!V:V,Index!R:R,),_xlfn.XLOOKUP(D295,Index!AG:AG,Index!AC:AC,)) -> Other HR | G295: =IF(C295="Ltd",_xlfn.XLOOKUP(D295,Index!V:V,Index!T:T,),_xlfn.XLOOKUP(D295,Index!AG:AG,Index!AE:AE,)) -> 0 | I295: =_xlfn.XLOOKUP(_xlfn.NUMBERVALUE(MID(D295,2,5)),'TB LTD 12.22'!E:E,'TB LTD 12.22'!H:H,0,0,1) -> 6142.12 | J295: =SUMIF(AJE!$E:$E,D295,AJE!$H:$H) -> 0 | K295: =SUMIF(AJE!$Q:$Q,D295,AJE!$T:$T) -> 0 | L295: =I295+J295+K295 -> 6142.12 | M295: =SUMIF(AJE!$AB:$AB,D295,AJE!$AE:$AE) -> 0 | N295: =L295+M295 -> 6142.12
A296: =_xlfn.XLOOKUP($B296,Index!$E:$E,Index!$D:$D,) -> 99 | B296: =IF($C296="Ltd",_xlfn.XLOOKUP($D296,Index!$V:$V,Index!$P:$P,),_xlfn.XLOOKUP($D296,Index!$AG:$AG,Index!$AA:$AA,)) -> Overhead | C296: =IF(LEFT(D296)="1","Ltd","Inc") -> Ltd | D296: 1670079900 | E296: =_xlfn.XLOOKUP(_xlfn.NUMBERVALUE(MID(D296,2,5)),'TB LTD 12.22'!$E:$E,'TB LTD 12.22'!$F:$F,) -> דמי ניהול פנסיונים | F296: =IF(C296="Ltd",_xlfn.XLOOKUP(D296,Index!V:V,Index!R:R,),_xlfn.XLOOKUP(D296,Index!AG:AG,Index!AC:AC,)) -> 0 | G296: =IF(C296="Ltd",_xlfn.XLOOKUP(D296,Index!V:V,Index!T:T,),_xlfn.XLOOKUP(D296,Index!AG:AG,Index!AE:AE,)) -> 0 | I296: =_xlfn.XLOOKUP(_xlfn.NUMBERVALUE(MID(D296,2,5)),'TB LTD 12.22'!E:E,'TB LTD 12.22'!H:H,0,0,1) -> 12142.32 | J296: =SUMIF(AJE!$E:$E,D296,AJE!$H:$H) -> 0 | K296: =SUMIF(AJE!$Q:$Q,D296,AJE!$T:$T) -> -12142.32 | L296: =I296+J296+K296 -> 0 | M296: =SUMIF(AJE!$AB:$AB,D296,AJE!$AE:$AE) -> 0 | N296: =L296+M296 -> 0
... A337: =_xlfn.XLOOKUP($B337,Index!$E:$E,Index!$D:$D,) -> 40 | B337: =IF($C337="Ltd",_xlfn.XLOOKUP($D337,Index!$V:$V,Index!$P:$P,),_xlfn.XLOOKUP($D337,Index!$AG:$AG,Index!$AA:$AA,)) -> R&D | C337: =IF(LEFT(D337)="1","Ltd","Inc") -> Ltd | D337: 1106444012443 | E337: =_xlfn.XLOOKUP(_xlfn.NUMBERVALUE(MID(D337,2,5)),'TB LTD 12.22'!$E:$E,'TB LTD 12.22'!$F:$F,) -> Yaron Singapore 26.11.3.12.22 | F337: =IF(C337="Ltd",_xlfn.XLOOKUP(D337,Index!V:V,Index!R:R,),_xlfn.XLOOKUP(D337,Index!AG:AG,Index!AC:AC,)) -> T&E | G337: =IF(C337="Ltd",_xlfn.XLOOKUP(D337,Index!V:V,Index!T:T,),_xlfn.XLOOKUP(D337,Index!AG:AG,Index!AE:AE,)) -> Labs | I337: =_xlfn.XLOOKUP(_xlfn.NUMBERVALUE(MID(D337,2,5)),'TB LTD 12.22'!E:E,'TB LTD 12.22'!H:H,0,0,1) -> 5619.68 | J337: =SUMIF(AJE!$E:$E,D337,AJE!$H:$H) -> 0 | K337: =SUMIF(AJE!$Q:$Q,D337,AJE!$T:$T) -> 0 | L337: =I337+J337+K337 -> 5619.68 | M337: =SUMIF(AJE!$AB:$AB,D337,AJE!$AE:$AE) -> 0 | N337: =L337+M337 -> 5619.68
A338: =_xlfn.XLOOKUP($B338,Index!$E:$E,Index!$D:$D,) -> 40 | B338: =IF($C338="Ltd",_xlfn.XLOOKUP($D338,Index!$V:$V,Index!$P:$P,),_xlfn.XLOOKUP($D338,Index!$AG:$AG,Index!$AA:$AA,)) -> R&D | C338: =IF(LEFT(D338)="1","Ltd","Inc") -> Ltd | D338: 192644012441 | E338: =_xlfn.XLOOKUP(_xlfn.NUMBERVALUE(MID(D338,2,4)),'TB LTD 12.22'!$E:$E,'TB LTD 12.22'!$F:$F,) -> Hadas Sason USA 20.11-3.12.22 | F338: =IF(C338="Ltd",_xlfn.XLOOKUP(D338,Index!V:V,Index!R:R,),_xlfn.XLOOKUP(D338,Index!AG:AG,Index!AC:AC,)) -> T&E | G338: =IF(C338="Ltd",_xlfn.XLOOKUP(D338,Index!V:V,Index!T:T,),_xlfn.XLOOKUP(D338,Index!AG:AG,Index!AE:AE,)) -> Dev | I338: =_xlfn.XLOOKUP(_xlfn.NUMBERVALUE(MID(D338,2,4)),'TB LTD 12.22'!E:E,'TB LTD 12.22'!H:H,0,0,1) -> 2625 | J338: =SUMIF(AJE!$E:$E,D338,AJE!$H:$H) -> 0 | K338: =SUMIF(AJE!$Q:$Q,D338,AJE!$T:$T) -> 0 | L338: =I338+J338+K338 -> 2625 | M338: =SUMIF(AJE!$AB:$AB,D338,AJE!$AE:$AE) -> 0 | N338: =L338+M338 -> 2625
A339: =_xlfn.XLOOKUP($B339,Index!$E:$E,Index!$D:$D,) -> 60 | B339: =IF($C339="Ltd",_xlfn.XLOOKUP($D339,Index!$V:$V,Index!$P:$P,),_xlfn.XLOOKUP($D339,Index!$AG:$AG,Index!$AA:$AA,)) -> Marketing | C339: =IF(LEFT(D339)="1","Ltd","Inc") -> Ltd | D339: 19854601240 | E339: =_xlfn.XLOOKUP(_xlfn.NUMBERVALUE(MID(D339,2,4)),'TB LTD 12.22'!$E:$E,'TB LTD 12.22'!$F:$F,) -> Federica Manasse Singapore 16.10-2.11.22 | F339: =IF(C339="Ltd",_xlfn.XLOOKUP(D339,Index!V:V,Index!R:R,),_xlfn.XLOOKUP(D339,Index!AG:AG,Index!AC:AC,)) -> T&E | G339: =IF(C339="Ltd",_xlfn.XLOOKUP(D339,Index!V:V,Index!T:T,),_xlfn.XLOOKUP(D339,Index!AG:AG,Index!AE:AE,)) -> 0 | I339: =_xlfn.XLOOKUP(_xlfn.NUMBERVALUE(MID(D339,2,4)),'TB LTD 12.22'!E:E,'TB LTD 12.22'!H:H,0,0,1) -> 1609 | J339: =SUMIF(AJE!$E:$E,D339,AJE!$H:$H) -> 0 | K339: =SUMIF(AJE!$Q:$Q,D339,AJE!$T:$T) -> 0 | L339: =I339+J339+K339 -> 1609 | M339: =SUMIF(AJE!$AB:$AB,D339,AJE!$AE:$AE) -> 0 | N339: =L339+M339 -> 1609
A340: =_xlfn.XLOOKUP($B340,Index!$E:$E,Index!$D:$D,) -> 40 | B340: =IF($C340="Ltd",_xlfn.XLOOKUP($D340,Index!$V:$V,Index!$P:$P,),_xlfn.XLOOKUP($D340,Index!$AG:$AG,Index!$AA:$AA,)) -> R&D | C340: =IF(LEFT(D340)="1","Ltd","Inc") -> Ltd | D340: 1650184010242 | E340: =_xlfn.XLOOKUP(_xlfn.NUMBERVALUE(MID(D340,2,5)),'TB LTD 12.22'!$E:$E,'TB LTD 12.22'!$F:$F,) -> UX/UI product design | F340: =IF(C340="Ltd",_xlfn.XLOOKUP(D340,Index!V:V,Index!R:R,),_xlfn.XLOOKUP(D340,Index!AG:AG,Index!AC:AC,)) -> Contractors & Services | G340: =IF(C340="Ltd",_xlfn.XLOOKUP(D340,Index!V:V,Index!T:T,),_xlfn.XLOOKUP(D340,Index!AG:AG,Index!AE:AE,)) -> Product | I340: =_xlfn.XLOOKUP(_xlfn.NUMBERVALUE(MID(D340,2,5)),'TB LTD 12.22'!E:E,'TB LTD 12.22'!H:H,0,0,1) -> 35505.27 | J340: =SUMIF(AJE!$E:$E,D340,AJE!$H:$H) -> 0 | K340: =SUMIF(AJE!$Q:$Q,D340,AJE!$T:$T) -> 0 | L340: =I340+J340+K340 -> 35505.27 | M340: =SUMIF(AJE!$AB:$AB,D340,AJE!$AE:$AE) -> 0 | N340: =L340+M340 -> 35505.27
A341: =_xlfn.XLOOKUP($B341,Index!$E:$E,Index!$D:$D,) -> 70 | B341: =IF($C341="Ltd",_xlfn.XLOOKUP($D341,Index!$V:$V,Index!$P:$P,),_xlfn.XLOOKUP($D341,Index!$AG:$AG,Index!$AA:$AA,)) -> G&A | C341: =IF(LEFT(D341)="1","Ltd","Inc") -> Ltd | D341: 165022701150 | E341: =_xlfn.XLOOKUP(_xlfn.NUMBERVALUE(MID(D341,2,5)),'TB LTD 12.22'!$E:$E,'TB LTD 12.22'!$F:$F,) -> פטנטים | F341: =IF(C341="Ltd",_xlfn.XLOOKUP(D341,Index!V:V,Index!R:R,),_xlfn.XLOOKUP(D341,Index!AG:AG,Index!AC:AC,)) -> Patent | G341: =IF(C341="Ltd",_xlfn.XLOOKUP(D341,Index!V:V,Index!T:T,),_xlfn.XLOOKUP(D341,Index!AG:AG,Index!AE:AE,)) -> 0 | I341: =_xlfn.XLOOKUP(_xlfn.NUMBERVALUE(MID(D341,2,5)),'TB LTD 12.22'!E:E,'TB LTD 12.22'!H:H,0,0,1) -> 15835.71 | J341: =SUMIF(AJE!$E:$E,D341,AJE!$H:$H) -> 0 | K341: =SUMIF(AJE!$Q:$Q,D341,AJE!$T:$T) -> 0 | L341: =I341+J341+K341 -> 15835.71 | M341: =SUMIF(AJE!$AB:$AB,D341,AJE!$AE:$AE) -> 0 | N341: =L341+M341 -> 15835.71
A342: =_xlfn.XLOOKUP($B342,Index!$E:$E,Index!$D:$D,) -> 40 | B342: =IF($C342="Ltd",_xlfn.XLOOKUP($D342,Index!$V:$V,Index!$P:$P,),_xlfn.XLOOKUP($D342,Index!$AG:$AG,Index!$AA:$AA,)) -> R&D | C342: =IF(LEFT(D342)="1","Ltd","Inc") -> Ltd | D342: 1650364010241 | E342: =_xlfn.XLOOKUP(_xlfn.NUMBERVALUE(MID(D342,2,5)),'TB LTD 12.22'!$E:$E,'TB LTD 12.22'!$F:$F,) -> קבלני פיתוח R&D | F342: =IF(C342="Ltd",_xlfn.XLOOKUP(D342,Index!V:V,Index!R:R,),_xlfn.XLOOKUP(D342,Index!AG:AG,Index!AC:AC,)) -> Contractors & Services | G342: =IF(C342="Ltd",_xlfn.XLOOKUP(D342,Index!V:V,Index!T:T,),_xlfn.XLOOKUP(D342,Index!AG:AG,Index!AE:AE,)) -> Dev | I342: =_xlfn.XLOOKUP(_xlfn.NUMBERVALUE(MID(D342,2,5)),'TB LTD 12.22'!E:E,'TB LTD 12.22'!H:H,0,0,1) -> 12956.8 | J342: =SUMIF(AJE!$E:$E,D342,AJE!$H:$H) -> 0 | K342: =SUMIF(AJE!$Q:$Q,D342,AJE!$T:$T) -> 0 | L342: =I342+J342+K342 -> 12956.8 | M342: =SUMIF(AJE!$AB:$AB,D342,AJE!$AE:$AE) -> 0 | N342: =L342+M342 -> 12956.8
A343: =_xlfn.XLOOKUP($B343,Index!$E:$E,Index!$D:$D,) -> 70 | B343: =IF($C343="Ltd",_xlfn.XLOOKUP($D343,Index!$V:$V,Index!$P:$P,),_xlfn.XLOOKUP($D343,Index!$AG:$AG,Index!$AA:$AA,)) -> G&A | C343: =IF(LEFT(D343)="1","Ltd","Inc") -> Ltd | D343: 165043701210 | E343: =_xlfn.XLOOKUP(_xlfn.NUMBERVALUE(MID(D343,2,5)),'TB LTD 12.22'!$E:$E,'TB LTD 12.22'!$F:$F,) -> Compliance & penetration testing | F343: =IF(C343="Ltd",_xlfn.XLOOKUP(D343,Index!V:V,Index!R:R,),_xlfn.XLOOKUP(D343,Index!AG:AG,Index!AC:AC,)) -> Security | G343: =IF(C343="Ltd",_xlfn.XLOOKUP(D343,Index!V:V,Index!T:T,),_xlfn.XLOOKUP(D343,Index!AG:AG,Index!AE:AE,)) -> 0 | I343: =_xlfn.XLOOKUP(_xlfn.NUMBERVALUE(MID(D343,2,5)),'TB LTD 12.22'!E:E,'TB LTD 12.22'!H:H,0,0,1) -> 4398.91 | J343: =SUMIF(AJE!$E:$E,D343,AJE!$H:$H) -> 0 | K343: =SUMIF(AJE!$Q:$Q,D343,AJE!$T:$T) -> 0 | L343: =I343+J343+K343 -> 4398.91 | M343: =SUMIF(AJE!$AB:$AB,D343,AJE!$AE:$AE) -> 0 | N343: =L343+M343 -> 4398.91
A344: =_xlfn.XLOOKUP($B344,Index!$E:$E,Index!$D:$D,) -> 40 | B344: =IF($C344="Ltd",_xlfn.XLOOKUP($D344,Index!$V:$V,Index!$P:$P,),_xlfn.XLOOKUP($D344,Index!$AG:$AG,Index!$AA:$AA,)) -> R&D | C344: =IF(LEFT(D344)="1","Ltd","Inc") -> Ltd | D344: 165044401230 | E344: =_xlfn.XLOOKUP(_xlfn.NUMBERVALUE(MID(D344,2,5)),'TB LTD 12.22'!$E:$E,'TB LTD 12.22'!$F:$F,) -> Software tools R&D | F344: =IF(C344="Ltd",_xlfn.XLOOKUP(D344,Index!V:V,Index!R:R,),_xlfn.XLOOKUP(D344,Index!AG:AG,Index!AC:AC,)) -> Software | G344: =IF(C344="Ltd",_xlfn.XLOOKUP(D344,Index!V:V,Index!T:T,),_xlfn.XLOOKUP(D344,Index!AG:AG,Index!AE:AE,)) -> 0 | I344: =_xlfn.XLOOKUP(_xlfn.NUMBERVALUE(MID(D344,2,5)),'TB LTD 12.22'!E:E,'TB LTD 12.22'!H:H,0,0,1) -> 102905.97 | J344: =SUMIF(AJE!$E:$E,D344,AJE!$H:$H) -> 0 | K344: =SUMIF(AJE!$Q:$Q,D344,AJE!$T:$T) -> 0 | L344: =I344+J344+K344 -> 102905.97 | M344: =SUMIF(AJE!$AB:$AB,D344,AJE!$AE:$AE) -> 0 | N344: =L344+M344 -> 102905.97
A345: =_xlfn.XLOOKUP($B345,Index!$E:$E,Index!$D:$D,) -> 40 | B345: =IF($C345="Ltd",_xlfn.XLOOKUP($D345,Index!$V:$V,Index!$P:$P,),_xlfn.XLOOKUP($D345,Index!$AG:$AG,Index!$AA:$AA,)) -> R&D | C345: =IF(LEFT(D345)="1","Ltd","Inc") -> Ltd | D345: 165047401080 | E345: =_xlfn.XLOOKUP(_xlfn.NUMBERVALUE(MID(D345,2,5)),'TB LTD 12.22'!$E:$E,'TB LTD 12.22'!$F:$F,) -> Cloud hosting R&D | F345: =IF(C345="Ltd",_xlfn.XLOOKUP(D345,Index!V:V,Index!R:R,),_xlfn.XLOOKUP(D345,Index!AG:AG,Index!AC:AC,)) -> Hosting | G345: =IF(C345="Ltd",_xlfn.XLOOKUP(D345,Index!V:V,Index!T:T,),_xlfn.XLOOKUP(D345,Index!AG:AG,Index!AE:AE,)) -> 0 | I345: =_xlfn.XLOOKUP(_xlfn.NUMBERVALUE(MID(D345,2,5)),'TB LTD 12.22'!E:E,'TB LTD 12.22'!H:H,0,0,1) -> 693995.07 | J345: =SUMIF(AJE!$E:$E,D345,AJE!$H:$H) -> 0 | K345: =SUMIF(AJE!$Q:$Q,D345,AJE!$T:$T) -> 0 | L345: =I345+J345+K345 -> 693995.07 | M345: =SUMIF(AJE!$AB:$AB,D345,AJE!$AE:$AE) -> 0 | N345: =L345+M345 -> 693995.07
A346: =_xlfn.XLOOKUP($B346,Index!$E:$E,Index!$D:$D,) -> 40 | B346: =IF($C346="Ltd",_xlfn.XLOOKUP($D346,Index!$V:$V,Index!$P:$P,),_xlfn.XLOOKUP($D346,Index!$AG:$AG,Index!$AA:$AA,)) -> R&D | C346: =IF(LEFT(D346)="1","Ltd","Inc") -> Ltd | D346: 165071401140 | E346: =_xlfn.XLOOKUP(_xlfn.NUMBERVALUE(MID(D346,2,5)),'TB LTD 12.22'!$E:$E,'TB LTD 12.22'!$F:$F,) -> VP Budget R&D Rotem Team outing | F346: =IF(C346="Ltd",_xlfn.XLOOKUP(D346,Index!V:V,Index!R:R,),_xlfn.XLOOKUP(D346,Index!AG:AG,Index!AC:AC,)) -> Other R&D | G346: =IF(C346="Ltd",_xlfn.XLOOKUP(D346,Index!V:V,Index!T:T,),_xlfn.XLOOKUP(D346,Index!AG:AG,Index!AE:AE,)) -> 0 | I346: =_xlfn.XLOOKUP(_xlfn.NUMBERVALUE(MID(D346,2,5)),'TB LTD 12.22'!E:E,'TB LTD 12.22'!H:H,0,0,1) -> 2662.78 | J346: =SUMIF(AJE!$E:$E,D346,AJE!$H:$H) -> 0 | K346: =SUMIF(AJE!$Q:$Q,D346,AJE!$T:$T) -> 0 | L346: =I346+J346+K346 -> 2662.78 | M346: =SUMIF(AJE!$AB:$AB,D346,AJE!$AE:$AE) -> 0 | N346: =L346+M346 -> 2662.78
A347: =_xlfn.XLOOKUP($B347,Index!$E:$E,Index!$D:$D,) -> 40 | B347: =IF($C347="Ltd",_xlfn.XLOOKUP($D347,Index!$V:$V,Index!$P:$P,),_xlfn.XLOOKUP($D347,Index!$AG:$AG,Index!$AA:$AA,)) -> R&D | C347: =IF(LEFT(D347)="1","Ltd","Inc") -> Ltd | D347: 165081401230 | E347: =_xlfn.XLOOKUP(_xlfn.NUMBERVALUE(MID(D347,2,5)),'TB LTD 12.22'!$E:$E,'TB LTD 12.22'!$F:$F,) -> Frontegg services | F347: =IF(C347="Ltd",_xlfn.XLOOKUP(D347,Index!V:V,Index!R:R,),_xlfn.XLOOKUP(D347,Index!AG:AG,Index!AC:AC,)) -> Software | G347: =IF(C347="Ltd",_xlfn.XLOOKUP(D347,Index!V:V,Index!T:T,),_xlfn.XLOOKUP(D347,Index!AG:AG,Index!AE:AE,)) -> 0 | I347: =_xlfn.XLOOKUP(_xlfn.NUMBERVALUE(MID(D347,2,5)),'TB LTD 12.22'!E:E,'TB LTD 12.22'!H:H,0,0,1) -> 1016.59 | J347: =SUMIF(AJE!$E:$E,D347,AJE!$H:$H) -> 0 | K347: =SUMIF(AJE!$Q:$Q,D347,AJE!$T:$T) -> 0 | L347: =I347+J347+K347 -> 1016.59 | M347: =SUMIF(AJE!$AB:$AB,D347,AJE!$AE:$AE) -> 0 | N347: =L347+M347 -> 1016.59
A348: =_xlfn.XLOOKUP($B348,Index!$E:$E,Index!$D:$D,) -> 40 | B348: =IF($C348="Ltd",_xlfn.XLOOKUP($D348,Index!$V:$V,Index!$P:$P,),_xlfn.XLOOKUP($D348,Index!$AG:$AG,Index!$AA:$AA,)) -> R&D | C348: =IF(LEFT(D348)="1","Ltd","Inc") -> Ltd | D348: 165086401190 | E348: =_xlfn.XLOOKUP(_xlfn.NUMBERVALUE(MID(D348,2,5)),'TB LTD 12.22'!$E:$E,'TB LTD 12.22'!$F:$F,) -> הוצ גיוס HR R&D HR recruting | F348: =IF(C348="Ltd",_xlfn.XLOOKUP(D348,Index!V:V,Index!R:R,),_xlfn.XLOOKUP(D348,Index!AG:AG,Index!AC:AC,)) -> Recruiting | G348: =IF(C348="Ltd",_xlfn.XLOOKUP(D348,Index!V:V,Index!T:T,),_xlfn.XLOOKUP(D348,Index!AG:AG,Index!AE:AE,)) -> 0 | I348: =_xlfn.XLOOKUP(_xlfn.NUMBERVALUE(MID(D348,2,5)),'TB LTD 12.22'!E:E,'TB LTD 12.22'!H:H,0,0,1) -> 48330.64 | J348: =SUMIF(AJE!$E:$E,D348,AJE!$H:$H) -> 0 | K348: =SUMIF(AJE!$Q:$Q,D348,AJE!$T:$T) -> 0 | L348: =I348+J348+K348 -> 48330.64 | M348: =SUMIF(AJE!$AB:$AB,D348,AJE!$AE:$AE) -> 0 | N348: =L348+M348 -> 48330.64
A349: =_xlfn.XLOOKUP($B349,Index!$E:$E,Index!$D:$D,) -> 40 | B349: =IF($C349="Ltd",_xlfn.XLOOKUP($D349,Index!$V:$V,Index!$P:$P,),_xlfn.XLOOKUP($D349,Index!$AG:$AG,Index!$AA:$AA,)) -> R&D | C349: =IF(LEFT(D349)="1","Ltd","Inc") -> Ltd | D349: 165087401020 | E349: =_xlfn.XLOOKUP(_xlfn.NUMBERVALUE(MID(D349,2,5)),'TB LTD 12.22'!$E:$E,'TB LTD 12.22'!$F:$F,) -> עיצוב ואנימציה R&D | F349: =IF(C349="Ltd",_xlfn.XLOOKUP(D349,Index!V:V,Index!R:R,),_xlfn.XLOOKUP(D349,Index!AG:AG,Index!AC:AC,)) -> Contractors & Services | G349: =IF(C349="Ltd",_xlfn.XLOOKUP(D349,Index!V:V,Index!T:T,),_xlfn.XLOOKUP(D349,Index!AG:AG,Index!AE:AE,)) -> 0 | I349: =_xlfn.XLOOKUP(_xlfn.NUMBERVALUE(MID(D349,2,5)),'TB LTD 12.22'!E:E,'TB LTD 12.22'!H:H,0,0,1) -> 1351.04 | J349: =SUMIF(AJE!$E:$E,D349,AJE!$H:$H) -> 0 | K349: =SUMIF(AJE!$Q:$Q,D349,AJE!$T:$T) -> 0 | L349: =I349+J349+K349 -> 1351.04 | M349: =SUMIF(AJE!$AB:$AB,D349,AJE!$AE:$AE) -> 0 | N349: =L349+M349 -> 1351.04
A350: =_xlfn.XLOOKUP($B350,Index!$E:$E,Index!$D:$D,) -> 40 | B350: =IF($C350="Ltd",_xlfn.XLOOKUP($D350,Index!$V:$V,Index!$P:$P,),_xlfn.XLOOKUP($D350,Index!$AG:$AG,Index!$AA:$AA,)) -> R&D | C350: =IF(LEFT(D350)="1","Ltd","Inc") -> Ltd | D350: 161600401160 | E350: =_xlfn.XLOOKUP(_xlfn.NUMBERVALUE(MID(D350,2,5)),'TB LTD 12.22'!$E:$E,'TB LTD 12.22'!$F:$F,) -> הוצ שכר מוצר | F350: =IF(C350="Ltd",_xlfn.XLOOKUP(D350,Index!V:V,Index!R:R,),_xlfn.XLOOKUP(D350,Index!AG:AG,Index!AC:AC,)) -> Payroll & Payroll related | G350: =IF(C350="Ltd",_xlfn.XLOOKUP(D350,Index!V:V,Index!T:T,),_xlfn.XLOOKUP(D350,Index!AG:AG,Index!AE:AE,)) -> 0 | I350: =_xlfn.XLOOKUP(_xlfn.NUMBERVALUE(MID(D350,2,5)),'TB LTD 12.22'!E:E,'TB LTD 12.22'!H:H,0,0,1) -> 895136.45 | J350: =SUMIF(AJE!$E:$E,D350,AJE!$H:$H) -> 0 | K350: =SUMIF(AJE!$Q:$Q,D350,AJE!$T:$T) -> 0 | L350: =I350+J350+K350 -> 895136.45 | M350: =SUMIF(AJE!$AB:$AB,D350,AJE!$AE:$AE) -> 0 | N350: =L350+M350 -> 895136.45
A351: =_xlfn.XLOOKUP($B351,Index!$E:$E,Index!$D:$D,) -> 40 | B351: =IF($C351="Ltd",_xlfn.XLOOKUP($D351,Index!$V:$V,Index!$P:$P,),_xlfn.XLOOKUP($D351,Index!$AG:$AG,Index!$AA:$AA,)) -> R&D | C351: =IF(LEFT(D351)="1","Ltd","Inc") -> Ltd | D351: 161602401160 | E351: =_xlfn.XLOOKUP(_xlfn.NUMBERVALUE(MID(D351,2,5)),'TB LTD 12.22'!$E:$E,'TB LTD 12.22'!$F:$F,) -> הוצ ביטוח לאומי מוצר | F351: =IF(C351="Ltd",_xlfn.XLOOKUP(D351,Index!V:V,Index!R:R,),_xlfn.XLOOKUP(D351,Index!AG:AG,Index!AC:AC,)) -> Payroll & Payroll related | G351: =IF(C351="Ltd",_xlfn.XLOOKUP(D351,Index!V:V,Index!T:T,),_xlfn.XLOOKUP(D351,Index!AG:AG,Index!AE:AE,)) -> 0 | I351: =_xlfn.XLOOKUP(_xlfn.NUMBERVALUE(MID(D351,2,5)),'TB LTD 12.22'!E:E,'TB LTD 12.22'!H:H,0,0,1) -> 60934.06 | J351: =SUMIF(AJE!$E:$E,D351,AJE!$H:$H) -> 0 | K351: =SUMIF(AJE!$Q:$Q,D351,AJE!$T:$T) -> 0 | L351: =I351+J351+K351 -> 60934.06 | M351: =SUMIF(AJE!$AB:$AB,D351,AJE!$AE:$AE) -> 0 | N351: =L351+M351 -> 60934.06
... A382: =_xlfn.XLOOKUP($B382,Index!$E:$E,Index!$D:$D,) -> 40 | B382: =IF($C382="Ltd",_xlfn.XLOOKUP($D382,Index!$V:$V,Index!$P:$P,),_xlfn.XLOOKUP($D382,Index!$AG:$AG,Index!$AA:$AA,)) -> R&D | C382: =IF(LEFT(D382)="1","Ltd","Inc") -> Ltd | D382: 162606401160 | E382: =_xlfn.XLOOKUP(_xlfn.NUMBERVALUE(MID(D382,2,5)),'TB LTD 12.22'!$E:$E,'TB LTD 12.22'!$F:$F,) -> שונות מעביד - לאבס | F382: =IF(C382="Ltd",_xlfn.XLOOKUP(D382,Index!V:V,Index!R:R,),_xlfn.XLOOKUP(D382,Index!AG:AG,Index!AC:AC,)) -> Payroll & Payroll related | G382: =IF(C382="Ltd",_xlfn.XLOOKUP(D382,Index!V:V,Index!T:T,),_xlfn.XLOOKUP(D382,Index!AG:AG,Index!AE:AE,)) -> 0 | I382: =_xlfn.XLOOKUP(_xlfn.NUMBERVALUE(MID(D382,2,5)),'TB LTD 12.22'!E:E,'TB LTD 12.22'!H:H,0,0,1) -> 1703.89 | J382: =SUMIF(AJE!$E:$E,D382,AJE!$H:$H) -> 0 | K382: =SUMIF(AJE!$Q:$Q,D382,AJE!$T:$T) -> 0 | L382: =I382+J382+K382 -> 1703.89 | M382: =SUMIF(AJE!$AB:$AB,D382,AJE!$AE:$AE) -> 0 | N382: =L382+M382 -> 1703.89
A383: =_xlfn.XLOOKUP($B383,Index!$E:$E,Index!$D:$D,) -> 30 | B383: =IF($C383="Ltd",_xlfn.XLOOKUP($D383,Index!$V:$V,Index!$P:$P,),_xlfn.XLOOKUP($D383,Index!$AG:$AG,Index!$AA:$AA,)) -> Cost of Sales | C383: =IF(LEFT(D383)="1","Ltd","Inc") -> Ltd | D383: 1999993000 | E383: Overhead Allocation - CoS | F383: =IF(C383="Ltd",_xlfn.XLOOKUP(D383,Index!V:V,Index!R:R,),_xlfn.XLOOKUP(D383,Index!AG:AG,Index!AC:AC,)) -> Overhead Allocation - CoS | G383: =IF(C383="Ltd",_xlfn.XLOOKUP(D383,Index!V:V,Index!T:T,),_xlfn.XLOOKUP(D383,Index!AG:AG,Index!AE:AE,)) -> 0 | I383: 0 | J383: =SUMIF(AJE!$E:$E,D383,AJE!$H:$H) -> 0 | K383: =SUMIF(AJE!$Q:$Q,D383,AJE!$T:$T) -> 191221.27 | L383: =I383+J383+K383 -> 191221.27 | M383: =SUMIF(AJE!$AB:$AB,D383,AJE!$AE:$AE) -> 0 | N383: =L383+M383 -> 191221.27
A384: =_xlfn.XLOOKUP($B384,Index!$E:$E,Index!$D:$D,) -> 40 | B384: =IF($C384="Ltd",_xlfn.XLOOKUP($D384,Index!$V:$V,Index!$P:$P,),_xlfn.XLOOKUP($D384,Index!$AG:$AG,Index!$AA:$AA,)) -> R&D | C384: =IF(LEFT(D384)="1","Ltd","Inc") -> Ltd | D384: 1999994000 | E384: Overhead Allocation - R&D | F384: =IF(C384="Ltd",_xlfn.XLOOKUP(D384,Index!V:V,Index!R:R,),_xlfn.XLOOKUP(D384,Index!AG:AG,Index!AC:AC,)) -> Overhead Allocation - R&D | G384: =IF(C384="Ltd",_xlfn.XLOOKUP(D384,Index!V:V,Index!T:T,),_xlfn.XLOOKUP(D384,Index!AG:AG,Index!AE:AE,)) -> 0 | I384: 0 | J384: =SUMIF(AJE!$E:$E,D384,AJE!$H:$H) -> 0 | K384: =SUMIF(AJE!$Q:$Q,D384,AJE!$T:$T) -> 1140610.7 | L384: =I384+J384+K384 -> 1140610.7 | M384: =SUMIF(AJE!$AB:$AB,D384,AJE!$AE:$AE) -> 0 | N384: =L384+M384 -> 1140610.7
A385: =_xlfn.XLOOKUP($B385,Index!$E:$E,Index!$D:$D,) -> 50 | B385: =IF($C385="Ltd",_xlfn.XLOOKUP($D385,Index!$V:$V,Index!$P:$P,),_xlfn.XLOOKUP($D385,Index!$AG:$AG,Index!$AA:$AA,)) -> Sales | C385: =IF(LEFT(D385)="1","Ltd","Inc") -> Ltd | D385: 1999995000 | E385: Overhead Allocation - Sales | F385: =IF(C385="Ltd",_xlfn.XLOOKUP(D385,Index!V:V,Index!R:R,),_xlfn.XLOOKUP(D385,Index!AG:AG,Index!AC:AC,)) -> Overhead Allocation - Sales | G385: =IF(C385="Ltd",_xlfn.XLOOKUP(D385,Index!V:V,Index!T:T,),_xlfn.XLOOKUP(D385,Index!AG:AG,Index!AE:AE,)) -> 0 | I385: 0 | J385: =SUMIF(AJE!$E:$E,D385,AJE!$H:$H) -> 0 | K385: =SUMIF(AJE!$Q:$Q,D385,AJE!$T:$T) -> 96498.301 | L385: =I385+J385+K385 -> 96498.301 | M385: =SUMIF(AJE!$AB:$AB,D385,AJE!$AE:$AE) -> 0 | N385: =L385+M385 -> 96498.301
A386: =_xlfn.XLOOKUP($B386,Index!$E:$E,Index!$D:$D,) -> 60 | B386: =IF($C386="Ltd",_xlfn.XLOOKUP($D386,Index!$V:$V,Index!$P:$P,),_xlfn.XLOOKUP($D386,Index!$AG:$AG,Index!$AA:$AA,)) -> Marketing | C386: =IF(LEFT(D386)="1","Ltd","Inc") -> Ltd | D386: 1999996000 | E386: Overhead Allocation - Marketing | F386: =IF(C386="Ltd",_xlfn.XLOOKUP(D386,Index!V:V,Index!R:R,),_xlfn.XLOOKUP(D386,Index!AG:AG,Index!AC:AC,)) -> Overhead Allocation - Marketing | G386: =IF(C386="Ltd",_xlfn.XLOOKUP(D386,Index!V:V,Index!T:T,),_xlfn.XLOOKUP(D386,Index!AG:AG,Index!AE:AE,)) -> 0 | I386: 0 | J386: =SUMIF(AJE!$E:$E,D386,AJE!$H:$H) -> 0 | K386: =SUMIF(AJE!$Q:$Q,D386,AJE!$T:$T) -> 150786.89 | L386: =I386+J386+K386 -> 150786.89 | M386: =SUMIF(AJE!$AB:$AB,D386,AJE!$AE:$AE) -> 0 | N386: =L386+M386 -> 150786.89
A387: =_xlfn.XLOOKUP($B387,Index!$E:$E,Index!$D:$D,) -> 70 | B387: =IF($C387="Ltd",_xlfn.XLOOKUP($D387,Index!$V:$V,Index!$P:$P,),_xlfn.XLOOKUP($D387,Index!$AG:$AG,Index!$AA:$AA,)) -> G&A | C387: =IF(LEFT(D387)="1","Ltd","Inc") -> Ltd | D387: 1999997000 | E387: Overhead Allocation - G&A | F387: =IF(C387="Ltd",_xlfn.XLOOKUP(D387,Index!V:V,Index!R:R,),_xlfn.XLOOKUP(D387,Index!AG:AG,Index!AC:AC,)) -> Overhead Allocation - G&A | G387: =IF(C387="Ltd",_xlfn.XLOOKUP(D387,Index!V:V,Index!T:T,),_xlfn.XLOOKUP(D387,Index!AG:AG,Index!AE:AE,)) -> 0 | I387: 0 | J387: =SUMIF(AJE!$E:$E,D387,AJE!$H:$H) -> 0 | K387: =SUMIF(AJE!$Q:$Q,D387,AJE!$T:$T) -> 362811.85 | L387: =I387+J387+K387 -> 362811.85 | M387: =SUMIF(AJE!$AB:$AB,D387,AJE!$AE:$AE) -> 0 | N387: =L387+M387 -> 362811.85
A388: =_xlfn.XLOOKUP($B388,Index!$E:$E,Index!$D:$D,) -> 2 | B388: =IF($C388="Ltd",_xlfn.XLOOKUP($D388,Index!$V:$V,Index!$P:$P,),_xlfn.XLOOKUP($D388,Index!$AG:$AG,Index!$AA:$AA,)) -> Accounts Receivable | C388: =IF(LEFT(D388)="1","Ltd","Inc") -> Ltd | D388: 122285200 | E388: =_xlfn.XLOOKUP(_xlfn.NUMBERVALUE(MID(D388,2,5)),'TB LTD 12.22'!$E:$E,'TB LTD 12.22'!$F:$F,) -> Magellan Netzwerke GmbH | F388: =IF(C388="Ltd",_xlfn.XLOOKUP(D388,Index!V:V,Index!R:R,),_xlfn.XLOOKUP(D388,Index!AG:AG,Index!AC:AC,)) -> 0 | G388: =IF(C388="Ltd",_xlfn.XLOOKUP(D388,Index!V:V,Index!T:T,),_xlfn.XLOOKUP(D388,Index!AG:AG,Index!AE:AE,)) -> 0 | I388: =_xlfn.XLOOKUP(_xlfn.NUMBERVALUE(MID(D388,2,5)),'TB LTD 12.22'!E:E,'TB LTD 12.22'!H:H,0,0,1) -> 129329.12 | J388: =SUMIF(AJE!$E:$E,D388,AJE!$H:$H) -> 0 | K388: =SUMIF(AJE!$Q:$Q,D388,AJE!$T:$T) -> 0 | L388: =I388+J388+K388 -> 129329.12 | M388: =SUMIF(AJE!$AB:$AB,D388,AJE!$AE:$AE) -> 0 | N388: =L388+M388 -> 129329.12
A389: =_xlfn.XLOOKUP($B389,Index!$E:$E,Index!$D:$D,) -> 6 | B389: =IF($C389="Ltd",_xlfn.XLOOKUP($D389,Index!$V:$V,Index!$P:$P,),_xlfn.XLOOKUP($D389,Index!$AG:$AG,Index!$AA:$AA,)) -> Accounts Payable | C389: =IF(LEFT(D389)="1","Ltd","Inc") -> Ltd | D389: 132125600 | E389: =_xlfn.XLOOKUP(_xlfn.NUMBERVALUE(MID(D389,2,5)),'TB LTD 12.22'!$E:$E,'TB LTD 12.22'!$F:$F,) -> ס.ב. ספורט בשרון בעמ | F389: =IF(C389="Ltd",_xlfn.XLOOKUP(D389,Index!V:V,Index!R:R,),_xlfn.XLOOKUP(D389,Index!AG:AG,Index!AC:AC,)) -> 0 | G389: =IF(C389="Ltd",_xlfn.XLOOKUP(D389,Index!V:V,Index!T:T,),_xlfn.XLOOKUP(D389,Index!AG:AG,Index!AE:AE,)) -> 0 | I389: =_xlfn.XLOOKUP(_xlfn.NUMBERVALUE(MID(D389,2,5)),'TB LTD 12.22'!E:E,'TB LTD 12.22'!H:H,0,0,1) -> -426.26 | J389: =SUMIF(AJE!$E:$E,D389,AJE!$H:$H) -> 0 | K389: =SUMIF(AJE!$Q:$Q,D389,AJE!$T:$T) -> 0 | L389: =I389+J389+K389 -> -426.26 | M389: =SUMIF(AJE!$AB:$AB,D389,AJE!$AE:$AE) -> 0 | N389: =L389+M389 -> -426.26
A390: =_xlfn.XLOOKUP($B390,Index!$E:$E,Index!$D:$D,) -> 6 | B390: =IF($C390="Ltd",_xlfn.XLOOKUP($D390,Index!$V:$V,Index!$P:$P,),_xlfn.XLOOKUP($D390,Index!$AG:$AG,Index!$AA:$AA,)) -> Accounts Payable | C390: =IF(LEFT(D390)="1","Ltd","Inc") -> Ltd | D390: 132143600 | E390: =_xlfn.XLOOKUP(_xlfn.NUMBERVALUE(MID(D390,2,5)),'TB LTD 12.22'!$E:$E,'TB LTD 12.22'!$F:$F,) -> כנען דפוס בע"מ | F390: =IF(C390="Ltd",_xlfn.XLOOKUP(D390,Index!V:V,Index!R:R,),_xlfn.XLOOKUP(D390,Index!AG:AG,Index!AC:AC,)) -> 0 | G390: =IF(C390="Ltd",_xlfn.XLOOKUP(D390,Index!V:V,Index!T:T,),_xlfn.XLOOKUP(D390,Index!AG:AG,Index!AE:AE,)) -> 0 | I390: =_xlfn.XLOOKUP(_xlfn.NUMBERVALUE(MID(D390,2,5)),'TB LTD 12.22'!E:E,'TB LTD 12.22'!H:H,0,0,1) -> -182.72 | J390: =SUMIF(AJE!$E:$E,D390,AJE!$H:$H) -> 0 | K390: =SUMIF(AJE!$Q:$Q,D390,AJE!$T:$T) -> 0 | L390: =I390+J390+K390 -> -182.72 | M390: =SUMIF(AJE!$AB:$AB,D390,AJE!$AE:$AE) -> 0 | N390: =L390+M390 -> -182.72
A391: =_xlfn.XLOOKUP($B391,Index!$E:$E,Index!$D:$D,) -> 6 | B391: =IF($C391="Ltd",_xlfn.XLOOKUP($D391,Index!$V:$V,Index!$P:$P,),_xlfn.XLOOKUP($D391,Index!$AG:$AG,Index!$AA:$AA,)) -> Accounts Payable | C391: =IF(LEFT(D391)="1","Ltd","Inc") -> Ltd | D391: 132165600 | E391: =_xlfn.XLOOKUP(_xlfn.NUMBERVALUE(MID(D391,2,5)),'TB LTD 12.22'!$E:$E,'TB LTD 12.22'!$F:$F,) -> אימפקט אורלי שוורץ | F391: =IF(C391="Ltd",_xlfn.XLOOKUP(D391,Index!V:V,Index!R:R,),_xlfn.XLOOKUP(D391,Index!AG:AG,Index!AC:AC,)) -> 0 | G391: =IF(C391="Ltd",_xlfn.XLOOKUP(D391,Index!V:V,Index!T:T,),_xlfn.XLOOKUP(D391,Index!AG:AG,Index!AE:AE,)) -> 0 | I391: =_xlfn.XLOOKUP(_xlfn.NUMBERVALUE(MID(D391,2,5)),'TB LTD 12.22'!E:E,'TB LTD 12.22'!H:H,0,0,1) -> -30382.1 | J391: =SUMIF(AJE!$E:$E,D391,AJE!$H:$H) -> 0 | K391: =SUMIF(AJE!$Q:$Q,D391,AJE!$T:$T) -> 0 | L391: =I391+J391+K391 -> -30382.1 | M391: =SUMIF(AJE!$AB:$AB,D391,AJE!$AE:$AE) -> 0 | N391: =L391+M391 -> -30382.1
A392: =_xlfn.XLOOKUP($B392,Index!$E:$E,Index!$D:$D,) -> 6 | B392: =IF($C392="Ltd",_xlfn.XLOOKUP($D392,Index!$V:$V,Index!$P:$P,),_xlfn.XLOOKUP($D392,Index!$AG:$AG,Index!$AA:$AA,)) -> Accounts Payable | C392: =IF(LEFT(D392)="1","Ltd","Inc") -> Ltd | D392: 131005600 | E392: =_xlfn.XLOOKUP(_xlfn.NUMBERVALUE(MID(D392,2,5)),'TB LTD 12.22'!$E:$E,'TB LTD 12.22'!$F:$F,) -> Atlassian | F392: =IF(C392="Ltd",_xlfn.XLOOKUP(D392,Index!V:V,Index!R:R,),_xlfn.XLOOKUP(D392,Index!AG:AG,Index!AC:AC,)) -> 0 | G392: =IF(C392="Ltd",_xlfn.XLOOKUP(D392,Index!V:V,Index!T:T,),_xlfn.XLOOKUP(D392,Index!AG:AG,Index!AE:AE,)) -> 0 | I392: =_xlfn.XLOOKUP(_xlfn.NUMBERVALUE(MID(D392,2,5)),'TB LTD 12.22'!E:E,'TB LTD 12.22'!H:H,0,0,1) -> 6301.3 | J392: =SUMIF(AJE!$E:$E,D392,AJE!$H:$H) -> 0 | K392: =SUMIF(AJE!$Q:$Q,D392,AJE!$T:$T) -> 0 | L392: =I392+J392+K392 -> 6301.3 | M392: =SUMIF(AJE!$AB:$AB,D392,AJE!$AE:$AE) -> 0 | N392: =L392+M392 -> 6301.3
A393: =_xlfn.XLOOKUP($B393,Index!$E:$E,Index!$D:$D,) -> 6 | B393: =IF($C393="Ltd",_xlfn.XLOOKUP($D393,Index!$V:$V,Index!$P:$P,),_xlfn.XLOOKUP($D393,Index!$AG:$AG,Index!$AA:$AA,)) -> Accounts Payable | C393: =IF(LEFT(D393)="1","Ltd","Inc") -> Ltd | D393: 132084600 | E393: =_xlfn.XLOOKUP(_xlfn.NUMBERVALUE(MID(D393,2,5)),'TB LTD 12.22'!$E:$E,'TB LTD 12.22'!$F:$F,) -> Information Synergies | F393: =IF(C393="Ltd",_xlfn.XLOOKUP(D393,Index!V:V,Index!R:R,),_xlfn.XLOOKUP(D393,Index!AG:AG,Index!AC:AC,)) -> 0 | G393: =IF(C393="Ltd",_xlfn.XLOOKUP(D393,Index!V:V,Index!T:T,),_xlfn.XLOOKUP(D393,Index!AG:AG,Index!AE:AE,)) -> 0 | I393: =_xlfn.XLOOKUP(_xlfn.NUMBERVALUE(MID(D393,2,5)),'TB LTD 12.22'!E:E,'TB LTD 12.22'!H:H,0,0,1) -> -15000 | J393: =SUMIF(AJE!$E:$E,D393,AJE!$H:$H) -> 0 | K393: =SUMIF(AJE!$Q:$Q,D393,AJE!$T:$T) -> 0 | L393: =I393+J393+K393 -> -15000 | M393: =SUMIF(AJE!$AB:$AB,D393,AJE!$AE:$AE) -> 0 | N393: =L393+M393 -> -15000
A394: =_xlfn.XLOOKUP($B394,Index!$E:$E,Index!$D:$D,) -> 40 | B394: =IF($C394="Ltd",_xlfn.XLOOKUP($D394,Index!$V:$V,Index!$P:$P,),_xlfn.XLOOKUP($D394,Index!$AG:$AG,Index!$AA:$AA,)) -> R&D | C394: =IF(LEFT(D394)="1","Ltd","Inc") -> Ltd | D394: 1620104011641 | E394: =_xlfn.XLOOKUP(_xlfn.NUMBERVALUE(MID(D394,2,5)),'TB LTD 12.22'!$E:$E,'TB LTD 12.22'!$F:$F,) -> זק.השתלמות פיתוח | F394: =IF(C394="Ltd",_xlfn.XLOOKUP(D394,Index!V:V,Index!R:R,),_xlfn.XLOOKUP(D394,Index!AG:AG,Index!AC:AC,)) -> Payroll & Payroll related | G394: =IF(C394="Ltd",_xlfn.XLOOKUP(D394,Index!V:V,Index!T:T,),_xlfn.XLOOKUP(D394,Index!AG:AG,Index!AE:AE,)) -> Dev | I394: =_xlfn.XLOOKUP(_xlfn.NUMBERVALUE(MID(D394,2,5)),'TB LTD 12.22'!E:E,'TB LTD 12.22'!H:H,0,0,1) -> 2730.15 | J394: =SUMIF(AJE!$E:$E,D394,AJE!$H:$H) -> 0 | K394: =SUMIF(AJE!$Q:$Q,D394,AJE!$T:$T) -> 0 | L394: =I394+J394+K394 -> 2730.15 | M394: =SUMIF(AJE!$AB:$AB,D394,AJE!$AE:$AE) -> 0 | N394: =L394+M394 -> 2730.15
A395: =_xlfn.XLOOKUP($B395,Index!$E:$E,Index!$D:$D,) -> 50 | B395: =IF($C395="Ltd",_xlfn.XLOOKUP($D395,Index!$V:$V,Index!$P:$P,),_xlfn.XLOOKUP($D395,Index!$AG:$AG,Index!$AA:$AA,)) -> Sales | C395: =IF(LEFT(D395)="1","Ltd","Inc") -> Ltd | D395: 165082501190 | E395: =_xlfn.XLOOKUP(_xlfn.NUMBERVALUE(MID(D395,2,5)),'TB LTD 12.22'!$E:$E,'TB LTD 12.22'!$F:$F,) -> HR recruting -sales APAC | F395: =IF(C395="Ltd",_xlfn.XLOOKUP(D395,Index!V:V,Index!R:R,),_xlfn.XLOOKUP(D395,Index!AG:AG,Index!AC:AC,)) -> Recruiting | G395: =IF(C395="Ltd",_xlfn.XLOOKUP(D395,Index!V:V,Index!T:T,),_xlfn.XLOOKUP(D395,Index!AG:AG,Index!AE:AE,)) -> 0 | I395: =_xlfn.XLOOKUP(_xlfn.NUMBERVALUE(MID(D395,2,5)),'TB LTD 12.22'!E:E,'TB LTD 12.22'!H:H,0,0,1) -> 35263.81 | J395: =SUMIF(AJE!$E:$E,D395,AJE!$H:$H) -> 0 | K395: =SUMIF(AJE!$Q:$Q,D395,AJE!$T:$T) -> 0 | L395: =I395+J395+K395 -> 35263.81 | M395: =SUMIF(AJE!$AB:$AB,D395,AJE!$AE:$AE) -> 0 | N395: =L395+M395 -> 35263.81
A396: =_xlfn.XLOOKUP($B396,Index!$E:$E,Index!$D:$D,) -> 50 | B396: =IF($C396="Ltd",_xlfn.XLOOKUP($D396,Index!$V:$V,Index!$P:$P,),_xlfn.XLOOKUP($D396,Index!$AG:$AG,Index!$AA:$AA,)) -> Sales | C396: =IF(LEFT(D396)="1","Ltd","Inc") -> Ltd | D396: 165083501190 | E396: =_xlfn.XLOOKUP(_xlfn.NUMBERVALUE(MID(D396,2,5)),'TB LTD 12.22'!$E:$E,'TB LTD 12.22'!$F:$F,) -> HR recruting- sales EMEA | F396: =IF(C396="Ltd",_xlfn.XLOOKUP(D396,Index!V:V,Index!R:R,),_xlfn.XLOOKUP(D396,Index!AG:AG,Index!AC:AC,)) -> Recruiting | G396: =IF(C396="Ltd",_xlfn.XLOOKUP(D396,Index!V:V,Index!T:T,),_xlfn.XLOOKUP(D396,Index!AG:AG,Index!AE:AE,)) -> 0 | I396: =_xlfn.XLOOKUP(_xlfn.NUMBERVALUE(MID(D396,2,5)),'TB LTD 12.22'!E:E,'TB LTD 12.22'!H:H,0,0,1) -> 52334.06 | J396: =SUMIF(AJE!$E:$E,D396,AJE!$H:$H) -> 0 | K396: =SUMIF(AJE!$Q:$Q,D396,AJE!$T:$T) -> 0 | L396: =I396+J396+K396 -> 52334.06 | M396: =SUMIF(AJE!$AB:$AB,D396,AJE!$AE:$AE) -> 0 | N396: =L396+M396 -> 52334.06
A397: =_xlfn.XLOOKUP($B397,Index!$E:$E,Index!$D:$D,) -> 99 | B397: =IF($C397="Ltd",_xlfn.XLOOKUP($D397,Index!$V:$V,Index!$P:$P,),_xlfn.XLOOKUP($D397,Index!$AG:$AG,Index!$AA:$AA,)) -> Overhead | C397: =IF(LEFT(D397)="1","Ltd","Inc") -> Ltd | D397: 1670359900 | E397: =_xlfn.XLOOKUP(_xlfn.NUMBERVALUE(MID(D397,2,5)),'TB LTD 12.22'!$E:$E,'TB LTD 12.22'!$F:$F,) -> שכירות משרדים אוסטרליה | F397: =IF(C397="Ltd",_xlfn.XLOOKUP(D397,Index!V:V,Index!R:R,),_xlfn.XLOOKUP(D397,Index!AG:AG,Index!AC:AC,)) -> 0 | G397: =IF(C397="Ltd",_xlfn.XLOOKUP(D397,Index!V:V,Index!T:T,),_xlfn.XLOOKUP(D397,Index!AG:AG,Index!AE:AE,)) -> 0 | I397: =_xlfn.XLOOKUP(_xlfn.NUMBERVALUE(MID(D397,2,5)),'TB LTD 12.22'!E:E,'TB LTD 12.22'!H:H,0,0,1) -> 6147.76 | J397: =SUMIF(AJE!$E:$E,D397,AJE!$H:$H) -> 0 | K397: =SUMIF(AJE!$Q:$Q,D397,AJE!$T:$T) -> -6147.76 | L397: =I397+J397+K397 -> 0 | M397: =SUMIF(AJE!$AB:$AB,D397,AJE!$AE:$AE) -> 0 | N397: =L397+M397 -> 0
A398: =_xlfn.XLOOKUP($B398,Index!$E:$E,Index!$D:$D,) -> 60 | B398: =IF($C398="Ltd",_xlfn.XLOOKUP($D398,Index!$V:$V,Index!$P:$P,),_xlfn.XLOOKUP($D398,Index!$AG:$AG,Index!$AA:$AA,)) -> Marketing | C398: =IF(LEFT(D398)="1","Ltd","Inc") -> Ltd | D398: 151102601160 | E398: =_xlfn.XLOOKUP(_xlfn.NUMBERVALUE(MID(D398,2,5)),'TB LTD 12.22'!$E:$E,'TB LTD 12.22'!$F:$F,) -> Papaya M Reimbursement Exp | F398: =IF(C398="Ltd",_xlfn.XLOOKUP(D398,Index!V:V,Index!R:R,),_xlfn.XLOOKUP(D398,Index!AG:AG,Index!AC:AC,)) -> Payroll & Payroll related | G398: =IF(C398="Ltd",_xlfn.XLOOKUP(D398,Index!V:V,Index!T:T,),_xlfn.XLOOKUP(D398,Index!AG:AG,Index!AE:AE,)) -> 0 | I398: =_xlfn.XLOOKUP(_xlfn.NUMBERVALUE(MID(D398,2,5)),'TB LTD 12.22'!E:E,'TB LTD 12.22'!H:H,0,0,1) -> 4992.02 | J398: =SUMIF(AJE!$E:$E,D398,AJE!$H:$H) -> 0 | K398: =SUMIF(AJE!$Q:$Q,D398,AJE!$T:$T) -> 0 | L398: =I398+J398+K398 -> 4992.02 | M398: =SUMIF(AJE!$AB:$AB,D398,AJE!$AE:$AE) -> 0 | N398: =L398+M398 -> 4992.02
A399: =_xlfn.XLOOKUP($B399,Index!$E:$E,Index!$D:$D,) -> 70 | B399: =IF($C399="Ltd",_xlfn.XLOOKUP($D399,Index!$V:$V,Index!$P:$P,),_xlfn.XLOOKUP($D399,Index!$AG:$AG,Index!$AA:$AA,)) -> G&A | C399: =IF(LEFT(D399)="1","Ltd","Inc") -> Ltd | D399: 165038701110 | E399: =_xlfn.XLOOKUP(_xlfn.NUMBERVALUE(MID(D399,2,5)),'TB LTD 12.22'!$E:$E,'TB LTD 12.22'!$F:$F,) -> מתנות לספקים/ לקוחות/לרגל אירוע מיוחד | F399: =IF(C399="Ltd",_xlfn.XLOOKUP(D399,Index!V:V,Index!R:R,),_xlfn.XLOOKUP(D399,Index!AG:AG,Index!AC:AC,)) -> Other Finance | G399: =IF(C399="Ltd",_xlfn.XLOOKUP(D399,Index!V:V,Index!T:T,),_xlfn.XLOOKUP(D399,Index!AG:AG,Index!AE:AE,)) -> 0 | I399: =_xlfn.XLOOKUP(_xlfn.NUMBERVALUE(MID(D399,2,5)),'TB LTD 12.22'!E:E,'TB LTD 12.22'!H:H,0,0,1) -> 6377.31 | J399: =SUMIF(AJE!$E:$E,D399,AJE!$H:$H) -> 0 | K399: =SUMIF(AJE!$Q:$Q,D399,AJE!$T:$T) -> 0 | L399: =I399+J399+K399 -> 6377.31 | M399: =SUMIF(AJE!$AB:$AB,D399,AJE!$AE:$AE) -> 0 | N399: =L399+M399 -> 6377.31
... A404: =_xlfn.XLOOKUP($B404,Index!$E:$E,Index!$D:$D,) -> 60 | B404: =IF($C404="Ltd",_xlfn.XLOOKUP($D404,Index!$V:$V,Index!$P:$P,),_xlfn.XLOOKUP($D404,Index!$AG:$AG,Index!$AA:$AA,)) -> Marketing | C404: =IF(LEFT(D404)="1","Ltd","Inc") -> Ltd | D404: 165220601240 | E404: =_xlfn.XLOOKUP(_xlfn.NUMBERVALUE(MID(D404,2,5)),'TB LTD 12.22'!$E:$E,'TB LTD 12.22'!$F:$F,) -> Visa General | F404: =IF(C404="Ltd",_xlfn.XLOOKUP(D404,Index!V:V,Index!R:R,),_xlfn.XLOOKUP(D404,Index!AG:AG,Index!AC:AC,)) -> T&E | G404: =IF(C404="Ltd",_xlfn.XLOOKUP(D404,Index!V:V,Index!T:T,),_xlfn.XLOOKUP(D404,Index!AG:AG,Index!AE:AE,)) -> 0 | I404: =_xlfn.XLOOKUP(_xlfn.NUMBERVALUE(MID(D404,2,5)),'TB LTD 12.22'!E:E,'TB LTD 12.22'!H:H,0,0,1) -> 857.79 | J404: =SUMIF(AJE!$E:$E,D404,AJE!$H:$H) -> 0 | K404: =SUMIF(AJE!$Q:$Q,D404,AJE!$T:$T) -> 0 | L404: =I404+J404+K404 -> 857.79 | M404: =SUMIF(AJE!$AB:$AB,D404,AJE!$AE:$AE) -> 0 | N404: =L404+M404 -> 857.79
A405: =_xlfn.XLOOKUP($B405,Index!$E:$E,Index!$D:$D,) -> 40 | B405: =IF($C405="Ltd",_xlfn.XLOOKUP($D405,Index!$V:$V,Index!$P:$P,),_xlfn.XLOOKUP($D405,Index!$AG:$AG,Index!$AA:$AA,)) -> R&D | C405: =IF(LEFT(D405)="1","Ltd","Inc") -> Ltd | D405: 197574012441 | E405: =_xlfn.XLOOKUP(_xlfn.NUMBERVALUE(MID(D405,2,4)),'TB LTD 12.22'!$E:$E,'TB LTD 12.22'!$F:$F,) -> Miki Tsivion USA 20.11-3.12.22 | F405: =IF(C405="Ltd",_xlfn.XLOOKUP(D405,Index!V:V,Index!R:R,),_xlfn.XLOOKUP(D405,Index!AG:AG,Index!AC:AC,)) -> T&E | G405: =IF(C405="Ltd",_xlfn.XLOOKUP(D405,Index!V:V,Index!T:T,),_xlfn.XLOOKUP(D405,Index!AG:AG,Index!AE:AE,)) -> Dev | I405: =_xlfn.XLOOKUP(_xlfn.NUMBERVALUE(MID(D405,2,4)),'TB LTD 12.22'!E:E,'TB LTD 12.22'!H:H,0,0,1) -> 2199.22 | J405: =SUMIF(AJE!$E:$E,D405,AJE!$H:$H) -> 0 | K405: =SUMIF(AJE!$Q:$Q,D405,AJE!$T:$T) -> 0 | L405: =I405+J405+K405 -> 2199.22 | M405: =SUMIF(AJE!$AB:$AB,D405,AJE!$AE:$AE) -> 0 | N405: =L405+M405 -> 2199.22
A406: =_xlfn.XLOOKUP($B406,Index!$E:$E,Index!$D:$D,) -> 60 | B406: =IF($C406="Ltd",_xlfn.XLOOKUP($D406,Index!$V:$V,Index!$P:$P,),_xlfn.XLOOKUP($D406,Index!$AG:$AG,Index!$AA:$AA,)) -> Marketing | C406: =IF(LEFT(D406)="1","Ltd","Inc") -> Ltd | D406: 165056601130 | E406: =_xlfn.XLOOKUP(_xlfn.NUMBERVALUE(MID(D406,2,5)),'TB LTD 12.22'!$E:$E,'TB LTD 12.22'!$F:$F,) -> Roadshows local sales events | F406: =IF(C406="Ltd",_xlfn.XLOOKUP(D406,Index!V:V,Index!R:R,),_xlfn.XLOOKUP(D406,Index!AG:AG,Index!AC:AC,)) -> Other Marketing | G406: =IF(C406="Ltd",_xlfn.XLOOKUP(D406,Index!V:V,Index!T:T,),_xlfn.XLOOKUP(D406,Index!AG:AG,Index!AE:AE,)) -> 0 | I406: =_xlfn.XLOOKUP(_xlfn.NUMBERVALUE(MID(D406,2,5)),'TB LTD 12.22'!E:E,'TB LTD 12.22'!H:H,0,0,1) -> 227.43 | J406: =SUMIF(AJE!$E:$E,D406,AJE!$H:$H) -> 0 | K406: =SUMIF(AJE!$Q:$Q,D406,AJE!$T:$T) -> 0 | L406: =I406+J406+K406 -> 227.43 | M406: =SUMIF(AJE!$AB:$AB,D406,AJE!$AE:$AE) -> 0 | N406: =L406+M406 -> 227.43
A407: =_xlfn.XLOOKUP($B407,Index!$E:$E,Index!$D:$D,) -> 50 | B407: =IF($C407="Ltd",_xlfn.XLOOKUP($D407,Index!$V:$V,Index!$P:$P,),_xlfn.XLOOKUP($D407,Index!$AG:$AG,Index!$AA:$AA,)) -> Sales | C407: =IF(LEFT(D407)="1","Ltd","Inc") -> Ltd | D407: 165057501160 | E407: =_xlfn.XLOOKUP(_xlfn.NUMBERVALUE(MID(D407,2,5)),'TB LTD 12.22'!$E:$E,'TB LTD 12.22'!$F:$F,) -> Outsourcing sales | F407: =IF(C407="Ltd",_xlfn.XLOOKUP(D407,Index!V:V,Index!R:R,),_xlfn.XLOOKUP(D407,Index!AG:AG,Index!AC:AC,)) -> Payroll & Payroll related | G407: =IF(C407="Ltd",_xlfn.XLOOKUP(D407,Index!V:V,Index!T:T,),_xlfn.XLOOKUP(D407,Index!AG:AG,Index!AE:AE,)) -> 0 | I407: =_xlfn.XLOOKUP(_xlfn.NUMBERVALUE(MID(D407,2,5)),'TB LTD 12.22'!E:E,'TB LTD 12.22'!H:H,0,0,1) -> 62082 | J407: =SUMIF(AJE!$E:$E,D407,AJE!$H:$H) -> 0 | K407: =SUMIF(AJE!$Q:$Q,D407,AJE!$T:$T) -> 0 | L407: =I407+J407+K407 -> 62082 | M407: =SUMIF(AJE!$AB:$AB,D407,AJE!$AE:$AE) -> 0 | N407: =L407+M407 -> 62082
A408: =_xlfn.XLOOKUP($B408,Index!$E:$E,Index!$D:$D,) -> 50 | B408: =IF($C408="Ltd",_xlfn.XLOOKUP($D408,Index!$V:$V,Index!$P:$P,),_xlfn.XLOOKUP($D408,Index!$AG:$AG,Index!$AA:$AA,)) -> Sales | C408: =IF(LEFT(D408)="1","Ltd","Inc") -> Ltd | D408: 167038501230 | E408: =_xlfn.XLOOKUP(_xlfn.NUMBERVALUE(MID(D408,2,5)),'TB LTD 12.22'!$E:$E,'TB LTD 12.22'!$F:$F,) -> Linkedin - Sales Navigator | F408: =IF(C408="Ltd",_xlfn.XLOOKUP(D408,Index!V:V,Index!R:R,),_xlfn.XLOOKUP(D408,Index!AG:AG,Index!AC:AC,)) -> Software | G408: =IF(C408="Ltd",_xlfn.XLOOKUP(D408,Index!V:V,Index!T:T,),_xlfn.XLOOKUP(D408,Index!AG:AG,Index!AE:AE,)) -> 0 | I408: =_xlfn.XLOOKUP(_xlfn.NUMBERVALUE(MID(D408,2,5)),'TB LTD 12.22'!E:E,'TB LTD 12.22'!H:H,0,0,1) -> 7938.9 | J408: =SUMIF(AJE!$E:$E,D408,AJE!$H:$H) -> 0 | K408: =SUMIF(AJE!$Q:$Q,D408,AJE!$T:$T) -> 0 | L408: =I408+J408+K408 -> 7938.9 | M408: =SUMIF(AJE!$AB:$AB,D408,AJE!$AE:$AE) -> 0 | N408: =L408+M408 -> 7938.9
A409: =_xlfn.XLOOKUP($B409,Index!$E:$E,Index!$D:$D,) -> 2 | B409: =IF($C409="Ltd",_xlfn.XLOOKUP($D409,Index!$V:$V,Index!$P:$P,),_xlfn.XLOOKUP($D409,Index!$AG:$AG,Index!$AA:$AA,)) -> Accounts Receivable | C409: =IF(LEFT(D409)="1","Ltd","Inc") -> Ltd | D409: 122298200 | E409: =_xlfn.XLOOKUP(_xlfn.NUMBERVALUE(MID(D409,2,5)),'TB LTD 12.22'!$E:$E,'TB LTD 12.22'!$F:$F,) -> Softcat Plc | F409: =IF(C409="Ltd",_xlfn.XLOOKUP(D409,Index!V:V,Index!R:R,),_xlfn.XLOOKUP(D409,Index!AG:AG,Index!AC:AC,)) -> 0 | G409: =IF(C409="Ltd",_xlfn.XLOOKUP(D409,Index!V:V,Index!T:T,),_xlfn.XLOOKUP(D409,Index!AG:AG,Index!AE:AE,)) -> 0 | I409: =_xlfn.XLOOKUP(_xlfn.NUMBERVALUE(MID(D409,2,5)),'TB LTD 12.22'!E:E,'TB LTD 12.22'!H:H,0,0,1) -> 163649.34 | J409: =SUMIF(AJE!$E:$E,D409,AJE!$H:$H) -> 0 | K409: =SUMIF(AJE!$Q:$Q,D409,AJE!$T:$T) -> 0 | L409: =I409+J409+K409 -> 163649.34 | M409: =SUMIF(AJE!$AB:$AB,D409,AJE!$AE:$AE) -> 0 | N409: =L409+M409 -> 163649.34
A410: =_xlfn.XLOOKUP($B410,Index!$E:$E,Index!$D:$D,) -> 2 | B410: =IF($C410="Ltd",_xlfn.XLOOKUP($D410,Index!$V:$V,Index!$P:$P,),_xlfn.XLOOKUP($D410,Index!$AG:$AG,Index!$AA:$AA,)) -> Accounts Receivable | C410: =IF(LEFT(D410)="1","Ltd","Inc") -> Ltd | D410: 122303200 | E410: =_xlfn.XLOOKUP(_xlfn.NUMBERVALUE(MID(D410,2,5)),'TB LTD 12.22'!$E:$E,'TB LTD 12.22'!$F:$F,) -> BlueFort Security Ltd | F410: =IF(C410="Ltd",_xlfn.XLOOKUP(D410,Index!V:V,Index!R:R,),_xlfn.XLOOKUP(D410,Index!AG:AG,Index!AC:AC,)) -> 0 | G410: =IF(C410="Ltd",_xlfn.XLOOKUP(D410,Index!V:V,Index!T:T,),_xlfn.XLOOKUP(D410,Index!AG:AG,Index!AE:AE,)) -> 0 | I410: =_xlfn.XLOOKUP(_xlfn.NUMBERVALUE(MID(D410,2,5)),'TB LTD 12.22'!E:E,'TB LTD 12.22'!H:H,0,0,1) -> 38546.46 | J410: =SUMIF(AJE!$E:$E,D410,AJE!$H:$H) -> 0 | K410: =SUMIF(AJE!$Q:$Q,D410,AJE!$T:$T) -> 0 | L410: =I410+J410+K410 -> 38546.46 | M410: =SUMIF(AJE!$AB:$AB,D410,AJE!$AE:$AE) -> 0 | N410: =L410+M410 -> 38546.46
A411: =_xlfn.XLOOKUP($B411,Index!$E:$E,Index!$D:$D,) -> 6 | B411: =IF($C411="Ltd",_xlfn.XLOOKUP($D411,Index!$V:$V,Index!$P:$P,),_xlfn.XLOOKUP($D411,Index!$AG:$AG,Index!$AA:$AA,)) -> Accounts Payable | C411: =IF(LEFT(D411)="1","Ltd","Inc") -> Ltd | D411: 130130600 | E411: =_xlfn.XLOOKUP(_xlfn.NUMBERVALUE(MID(D411,2,5)),'TB LTD 12.22'!$E:$E,'TB LTD 12.22'!$F:$F,) -> מיטב ציוד משרדי | F411: =IF(C411="Ltd",_xlfn.XLOOKUP(D411,Index!V:V,Index!R:R,),_xlfn.XLOOKUP(D411,Index!AG:AG,Index!AC:AC,)) -> 0 | G411: =IF(C411="Ltd",_xlfn.XLOOKUP(D411,Index!V:V,Index!T:T,),_xlfn.XLOOKUP(D411,Index!AG:AG,Index!AE:AE,)) -> 0 | I411: =_xlfn.XLOOKUP(_xlfn.NUMBERVALUE(MID(D411,2,5)),'TB LTD 12.22'!E:E,'TB LTD 12.22'!H:H,0,0,1) -> 282.13 | J411: =SUMIF(AJE!$E:$E,D411,AJE!$H:$H) -> 0 | K411: =SUMIF(AJE!$Q:$Q,D411,AJE!$T:$T) -> 0 | L411: =I411+J411+K411 -> 282.13 | M411: =SUMIF(AJE!$AB:$AB,D411,AJE!$AE:$AE) -> 0 | N411: =L411+M411 -> 282.13
A412: =_xlfn.XLOOKUP($B412,Index!$E:$E,Index!$D:$D,) -> 6 | B412: =IF($C412="Ltd",_xlfn.XLOOKUP($D412,Index!$V:$V,Index!$P:$P,),_xlfn.XLOOKUP($D412,Index!$AG:$AG,Index!$AA:$AA,)) -> Accounts Payable | C412: =IF(LEFT(D412)="1","Ltd","Inc") -> Ltd | D412: 130236600 | E412: =_xlfn.XLOOKUP(_xlfn.NUMBERVALUE(MID(D412,2,5)),'TB LTD 12.22'!$E:$E,'TB LTD 12.22'!$F:$F,) -> מכון התקנים הישראלי | F412: =IF(C412="Ltd",_xlfn.XLOOKUP(D412,Index!V:V,Index!R:R,),_xlfn.XLOOKUP(D412,Index!AG:AG,Index!AC:AC,)) -> 0 | G412: =IF(C412="Ltd",_xlfn.XLOOKUP(D412,Index!V:V,Index!T:T,),_xlfn.XLOOKUP(D412,Index!AG:AG,Index!AE:AE,)) -> 0 | I412: =_xlfn.XLOOKUP(_xlfn.NUMBERVALUE(MID(D412,2,5)),'TB LTD 12.22'!E:E,'TB LTD 12.22'!H:H,0,0,1) -> -2189.71 | J412: =SUMIF(AJE!$E:$E,D412,AJE!$H:$H) -> 0 | K412: =SUMIF(AJE!$Q:$Q,D412,AJE!$T:$T) -> 0 | L412: =I412+J412+K412 -> -2189.71 | M412: =SUMIF(AJE!$AB:$AB,D412,AJE!$AE:$AE) -> 0 | N412: =L412+M412 -> -2189.71
A413: =_xlfn.XLOOKUP($B413,Index!$E:$E,Index!$D:$D,) -> 6 | B413: =IF($C413="Ltd",_xlfn.XLOOKUP($D413,Index!$V:$V,Index!$P:$P,),_xlfn.XLOOKUP($D413,Index!$AG:$AG,Index!$AA:$AA,)) -> Accounts Payable | C413: =IF(LEFT(D413)="1","Ltd","Inc") -> Ltd | D413: 131075600 | E413: =_xlfn.XLOOKUP(_xlfn.NUMBERVALUE(MID(D413,2,5)),'TB LTD 12.22'!$E:$E,'TB LTD 12.22'!$F:$F,) -> Zendesk INC | F413: =IF(C413="Ltd",_xlfn.XLOOKUP(D413,Index!V:V,Index!R:R,),_xlfn.XLOOKUP(D413,Index!AG:AG,Index!AC:AC,)) -> 0 | G413: =IF(C413="Ltd",_xlfn.XLOOKUP(D413,Index!V:V,Index!T:T,),_xlfn.XLOOKUP(D413,Index!AG:AG,Index!AE:AE,)) -> 0 | I413: =_xlfn.XLOOKUP(_xlfn.NUMBERVALUE(MID(D413,2,5)),'TB LTD 12.22'!E:E,'TB LTD 12.22'!H:H,0,0,1) -> 54.54 | J413: =SUMIF(AJE!$E:$E,D413,AJE!$H:$H) -> 0 | K413: =SUMIF(AJE!$Q:$Q,D413,AJE!$T:$T) -> 0 | L413: =I413+J413+K413 -> 54.54 | M413: =SUMIF(AJE!$AB:$AB,D413,AJE!$AE:$AE) -> 0 | N413: =L413+M413 -> 54.54
A414: =_xlfn.XLOOKUP($B414,Index!$E:$E,Index!$D:$D,) -> 6 | B414: =IF($C414="Ltd",_xlfn.XLOOKUP($D414,Index!$V:$V,Index!$P:$P,),_xlfn.XLOOKUP($D414,Index!$AG:$AG,Index!$AA:$AA,)) -> Accounts Payable | C414: =IF(LEFT(D414)="1","Ltd","Inc") -> Ltd | D414: 131089600 | E414: =_xlfn.XLOOKUP(_xlfn.NUMBERVALUE(MID(D414,2,5)),'TB LTD 12.22'!$E:$E,'TB LTD 12.22'!$F:$F,) -> SkyTap | F414: =IF(C414="Ltd",_xlfn.XLOOKUP(D414,Index!V:V,Index!R:R,),_xlfn.XLOOKUP(D414,Index!AG:AG,Index!AC:AC,)) -> 0 | G414: =IF(C414="Ltd",_xlfn.XLOOKUP(D414,Index!V:V,Index!T:T,),_xlfn.XLOOKUP(D414,Index!AG:AG,Index!AE:AE,)) -> 0 | I414: =_xlfn.XLOOKUP(_xlfn.NUMBERVALUE(MID(D414,2,5)),'TB LTD 12.22'!E:E,'TB LTD 12.22'!H:H,0,0,1) -> -4163.49 | J414: =SUMIF(AJE!$E:$E,D414,AJE!$H:$H) -> 0 | K414: =SUMIF(AJE!$Q:$Q,D414,AJE!$T:$T) -> 0 | L414: =I414+J414+K414 -> -4163.49 | M414: =SUMIF(AJE!$AB:$AB,D414,AJE!$AE:$AE) -> 0 | N414: =L414+M414 -> -4163.49
A415: =_xlfn.XLOOKUP($B415,Index!$E:$E,Index!$D:$D,) -> 6 | B415: =IF($C415="Ltd",_xlfn.XLOOKUP($D415,Index!$V:$V,Index!$P:$P,),_xlfn.XLOOKUP($D415,Index!$AG:$AG,Index!$AA:$AA,)) -> Accounts Payable | C415: =IF(LEFT(D415)="1","Ltd","Inc") -> Ltd | D415: 131198600 | E415: =_xlfn.XLOOKUP(_xlfn.NUMBERVALUE(MID(D415,2,5)),'TB LTD 12.22'!$E:$E,'TB LTD 12.22'!$F:$F,) -> Gartner Australasia Pty Limited | F415: =IF(C415="Ltd",_xlfn.XLOOKUP(D415,Index!V:V,Index!R:R,),_xlfn.XLOOKUP(D415,Index!AG:AG,Index!AC:AC,)) -> 0 | G415: =IF(C415="Ltd",_xlfn.XLOOKUP(D415,Index!V:V,Index!T:T,),_xlfn.XLOOKUP(D415,Index!AG:AG,Index!AE:AE,)) -> 0 | I415: =_xlfn.XLOOKUP(_xlfn.NUMBERVALUE(MID(D415,2,5)),'TB LTD 12.22'!E:E,'TB LTD 12.22'!H:H,0,0,1) -> -18537.84 | J415: =SUMIF(AJE!$E:$E,D415,AJE!$H:$H) -> 0 | K415: =SUMIF(AJE!$Q:$Q,D415,AJE!$T:$T) -> 0 | L415: =I415+J415+K415 -> -18537.84 | M415: =SUMIF(AJE!$AB:$AB,D415,AJE!$AE:$AE) -> 0 | N415: =L415+M415 -> -18537.84
A416: =_xlfn.XLOOKUP($B416,Index!$E:$E,Index!$D:$D,) -> 6 | B416: =IF($C416="Ltd",_xlfn.XLOOKUP($D416,Index!$V:$V,Index!$P:$P,),_xlfn.XLOOKUP($D416,Index!$AG:$AG,Index!$AA:$AA,)) -> Accounts Payable | C416: =IF(LEFT(D416)="1","Ltd","Inc") -> Ltd | D416: 132046600 | E416: =_xlfn.XLOOKUP(_xlfn.NUMBERVALUE(MID(D416,2,5)),'TB LTD 12.22'!$E:$E,'TB LTD 12.22'!$F:$F,) -> Pepper Marketing PTY LTD | F416: =IF(C416="Ltd",_xlfn.XLOOKUP(D416,Index!V:V,Index!R:R,),_xlfn.XLOOKUP(D416,Index!AG:AG,Index!AC:AC,)) -> 0 | G416: =IF(C416="Ltd",_xlfn.XLOOKUP(D416,Index!V:V,Index!T:T,),_xlfn.XLOOKUP(D416,Index!AG:AG,Index!AE:AE,)) -> 0 | I416: =_xlfn.XLOOKUP(_xlfn.NUMBERVALUE(MID(D416,2,5)),'TB LTD 12.22'!E:E,'TB LTD 12.22'!H:H,0,0,1) -> -11959.9 | J416: =SUMIF(AJE!$E:$E,D416,AJE!$H:$H) -> 0 | K416: =SUMIF(AJE!$Q:$Q,D416,AJE!$T:$T) -> 0 | L416: =I416+J416+K416 -> -11959.9 | M416: =SUMIF(AJE!$AB:$AB,D416,AJE!$AE:$AE) -> 0 | N416: =L416+M416 -> -11959.9
A417: =_xlfn.XLOOKUP($B417,Index!$E:$E,Index!$D:$D,) -> 6 | B417: =IF($C417="Ltd",_xlfn.XLOOKUP($D417,Index!$V:$V,Index!$P:$P,),_xlfn.XLOOKUP($D417,Index!$AG:$AG,Index!$AA:$AA,)) -> Accounts Payable | C417: =IF(LEFT(D417)="1","Ltd","Inc") -> Ltd | D417: 132151600 | E417: =_xlfn.XLOOKUP(_xlfn.NUMBERVALUE(MID(D417,2,5)),'TB LTD 12.22'!$E:$E,'TB LTD 12.22'!$F:$F,) -> Cloburnie Pty Ltd | F417: =IF(C417="Ltd",_xlfn.XLOOKUP(D417,Index!V:V,Index!R:R,),_xlfn.XLOOKUP(D417,Index!AG:AG,Index!AC:AC,)) -> 0 | G417: =IF(C417="Ltd",_xlfn.XLOOKUP(D417,Index!V:V,Index!T:T,),_xlfn.XLOOKUP(D417,Index!AG:AG,Index!AE:AE,)) -> 0 | I417: =_xlfn.XLOOKUP(_xlfn.NUMBERVALUE(MID(D417,2,5)),'TB LTD 12.22'!E:E,'TB LTD 12.22'!H:H,0,0,1) -> -1097.25 | J417: =SUMIF(AJE!$E:$E,D417,AJE!$H:$H) -> 0 | K417: =SUMIF(AJE!$Q:$Q,D417,AJE!$T:$T) -> 0 | L417: =I417+J417+K417 -> -1097.25 | M417: =SUMIF(AJE!$AB:$AB,D417,AJE!$AE:$AE) -> 0 | N417: =L417+M417 -> -1097.25
... A427: =_xlfn.XLOOKUP($B427,Index!$E:$E,Index!$D:$D,) -> 70 | B427: =IF($C427="Ltd",_xlfn.XLOOKUP($D427,Index!$V:$V,Index!$P:$P,),_xlfn.XLOOKUP($D427,Index!$AG:$AG,Index!$AA:$AA,)) -> G&A | C427: =IF(LEFT(D427)="1","Ltd","Inc") -> Ltd | D427: 110645701240 | E427: =_xlfn.XLOOKUP(_xlfn.NUMBERVALUE(MID(D427,2,5)),'TB LTD 12.22'!$E:$E,'TB LTD 12.22'!$F:$F,) -> Hed Kovetz UK 14-16.11.22 | F427: =IF(C427="Ltd",_xlfn.XLOOKUP(D427,Index!V:V,Index!R:R,),_xlfn.XLOOKUP(D427,Index!AG:AG,Index!AC:AC,)) -> T&E | G427: =IF(C427="Ltd",_xlfn.XLOOKUP(D427,Index!V:V,Index!T:T,),_xlfn.XLOOKUP(D427,Index!AG:AG,Index!AE:AE,)) -> 0 | I427: =_xlfn.XLOOKUP(_xlfn.NUMBERVALUE(MID(D427,2,5)),'TB LTD 12.22'!E:E,'TB LTD 12.22'!H:H,0,0,1) -> 1475 | J427: =SUMIF(AJE!$E:$E,D427,AJE!$H:$H) -> 0 | K427: =SUMIF(AJE!$Q:$Q,D427,AJE!$T:$T) -> 0 | L427: =I427+J427+K427 -> 1475 | M427: =SUMIF(AJE!$AB:$AB,D427,AJE!$AE:$AE) -> 0 | N427: =L427+M427 -> 1475
A428: =_xlfn.XLOOKUP($B428,Index!$E:$E,Index!$D:$D,) -> 70 | B428: =IF($C428="Ltd",_xlfn.XLOOKUP($D428,Index!$V:$V,Index!$P:$P,),_xlfn.XLOOKUP($D428,Index!$AG:$AG,Index!$AA:$AA,)) -> G&A | C428: =IF(LEFT(D428)="1","Ltd","Inc") -> Ltd | D428: 19855701240 | E428: =_xlfn.XLOOKUP(_xlfn.NUMBERVALUE(MID(D428,2,4)),'TB LTD 12.22'!$E:$E,'TB LTD 12.22'!$F:$F,) -> Hed Kovetz Australia 15-18.10.22 | F428: =IF(C428="Ltd",_xlfn.XLOOKUP(D428,Index!V:V,Index!R:R,),_xlfn.XLOOKUP(D428,Index!AG:AG,Index!AC:AC,)) -> T&E | G428: =IF(C428="Ltd",_xlfn.XLOOKUP(D428,Index!V:V,Index!T:T,),_xlfn.XLOOKUP(D428,Index!AG:AG,Index!AE:AE,)) -> 0 | I428: =_xlfn.XLOOKUP(_xlfn.NUMBERVALUE(MID(D428,2,4)),'TB LTD 12.22'!E:E,'TB LTD 12.22'!H:H,0,0,1) -> 10771.39 | J428: =SUMIF(AJE!$E:$E,D428,AJE!$H:$H) -> 0 | K428: =SUMIF(AJE!$Q:$Q,D428,AJE!$T:$T) -> 0 | L428: =I428+J428+K428 -> 10771.39 | M428: =SUMIF(AJE!$AB:$AB,D428,AJE!$AE:$AE) -> 0 | N428: =L428+M428 -> 10771.39
A429: =_xlfn.XLOOKUP($B429,Index!$E:$E,Index!$D:$D,) -> 60 | B429: =IF($C429="Ltd",_xlfn.XLOOKUP($D429,Index!$V:$V,Index!$P:$P,),_xlfn.XLOOKUP($D429,Index!$AG:$AG,Index!$AA:$AA,)) -> Marketing | C429: =IF(LEFT(D429)="1","Ltd","Inc") -> Ltd | D429: 165073601050 | E429: =_xlfn.XLOOKUP(_xlfn.NUMBERVALUE(MID(D429,2,5)),'TB LTD 12.22'!$E:$E,'TB LTD 12.22'!$F:$F,) -> Digital Marketing - global | F429: =IF(C429="Ltd",_xlfn.XLOOKUP(D429,Index!V:V,Index!R:R,),_xlfn.XLOOKUP(D429,Index!AG:AG,Index!AC:AC,)) -> Digital Marketing | G429: =IF(C429="Ltd",_xlfn.XLOOKUP(D429,Index!V:V,Index!T:T,),_xlfn.XLOOKUP(D429,Index!AG:AG,Index!AE:AE,)) -> 0 | I429: =_xlfn.XLOOKUP(_xlfn.NUMBERVALUE(MID(D429,2,5)),'TB LTD 12.22'!E:E,'TB LTD 12.22'!H:H,0,0,1) -> 30820.66 | J429: =SUMIF(AJE!$E:$E,D429,AJE!$H:$H) -> 0 | K429: =SUMIF(AJE!$Q:$Q,D429,AJE!$T:$T) -> 0 | L429: =I429+J429+K429 -> 30820.66 | M429: =SUMIF(AJE!$AB:$AB,D429,AJE!$AE:$AE) -> 0 | N429: =L429+M429 -> 30820.66
A430: =_xlfn.XLOOKUP($B430,Index!$E:$E,Index!$D:$D,) -> 60 | B430: =IF($C430="Ltd",_xlfn.XLOOKUP($D430,Index!$V:$V,Index!$P:$P,),_xlfn.XLOOKUP($D430,Index!$AG:$AG,Index!$AA:$AA,)) -> Marketing | C430: =IF(LEFT(D430)="1","Ltd","Inc") -> Ltd | D430: 167026601050 | E430: =_xlfn.XLOOKUP(_xlfn.NUMBERVALUE(MID(D430,2,5)),'TB LTD 12.22'!$E:$E,'TB LTD 12.22'!$F:$F,) -> Google Services | F430: =IF(C430="Ltd",_xlfn.XLOOKUP(D430,Index!V:V,Index!R:R,),_xlfn.XLOOKUP(D430,Index!AG:AG,Index!AC:AC,)) -> Digital Marketing | G430: =IF(C430="Ltd",_xlfn.XLOOKUP(D430,Index!V:V,Index!T:T,),_xlfn.XLOOKUP(D430,Index!AG:AG,Index!AE:AE,)) -> 0 | I430: =_xlfn.XLOOKUP(_xlfn.NUMBERVALUE(MID(D430,2,5)),'TB LTD 12.22'!E:E,'TB LTD 12.22'!H:H,0,0,1) -> 136940.79 | J430: =SUMIF(AJE!$E:$E,D430,AJE!$H:$H) -> 0 | K430: =SUMIF(AJE!$Q:$Q,D430,AJE!$T:$T) -> 0 | L430: =I430+J430+K430 -> 136940.79 | M430: =SUMIF(AJE!$AB:$AB,D430,AJE!$AE:$AE) -> 0 | N430: =L430+M430 -> 136940.79
...

Sheet P&L
C2: =G2 -> 12.22 | E2: =C2 -> 12.22 | G2: 12.22 | I2: V10 | O2: Diff
C3: Ltd Solo | E3: Inc Solo | G3: Consolidated | I3: Ltd Solo | K3: Inc Solo | M3: Consolidated | O3: Ltd Solo | Q3: Inc Solo | S3: Consolidated
A5: 20 | B5: Revenue | C5: =-SUMIFS('GL 12.22'!$L:$L,'GL 12.22'!$A:$A,A5,'GL 12.22'!$C:$C,"=LTD") -> 3801680.7 | E5: =-SUMIFS('GL 12.22'!$L:$L,'GL 12.22'!$A:$A,A5,'GL 12.22'!$C:$C,"=INC") -> 11509034 | G5: =-SUMIF('GL 12.22'!$A:$A,A5,'GL 12.22'!$N:$N) -> 9644604.2 | I5: 3801680.7 | K5: 11509034 | M5: 9644604.2 | O5: =C5-I5 -> 0 | Q5: =E5-K5 -> 0 | S5: =G5-M5 -> 0
A6: 30 | B6: Cost of Sales | C6: =SUMIFS('GL 12.22'!$L:$L,'GL 12.22'!$A:$A,A6,'GL 12.22'!$C:$C,"=LTD") -> 7040238.7 | E6: =SUMIFS('GL 12.22'!$L:$L,'GL 12.22'!$A:$A,A6,'GL 12.22'!$C:$C,"=INC") -> 1365559 | G6: =SUMIF('GL 12.22'!$A:$A,A6,'GL 12.22'!$N:$N) -> 3443936.4 | I6: 7027264.3 | K6: 1361933.5 | M6: 3427336.5 | O6: =C6-I6 -> 12974.397 | Q6: =E6-K6 -> 3625.514 | S6: =G6-M6 -> 16599.911
B7: Gross Margin | C7: =C5-C6 -> -3238558 | E7: =E5-E6 -> 10143475 | G7: =G5-G6 -> 6200667.8 | I7: -3225583.6 | K7: 10147101 | M7: 6217267.7 | O7: =C7-I7 -> -12974.397 | Q7: =E7-K7 -> -3625.514 | S7: =G7-M7 -> -16599.911
O8: =C8-I8 -> 0 | Q8: =E8-K8 -> 0 | S8: =G8-M8 -> 0
O9: =C9-I9 -> 0 | Q9: =E9-K9 -> 0 | S9: =G9-M9 -> 0
A10: 40 | B10: R&D | C10: =SUMIFS('GL 12.22'!$L:$L,'GL 12.22'!$A:$A,A10,'GL 12.22'!$C:$C,"=LTD") -> 10788080 | E10: =SUMIFS('GL 12.22'!$L:$L,'GL 12.22'!$A:$A,A10,'GL 12.22'!$C:$C,"=INC") -> -0.19 | G10: =SUMIF('GL 12.22'!$A:$A,A10,'GL 12.22'!$N:$N) -> 10788080 | I10: 10788080 | K10: -0.19 | M10: 10788080 | O10: =C10-I10 -> 0 | Q10: =E10-K10 -> 0 | S10: =G10-M10 -> 0
A11: 50 | B11: Sales | C11: =SUMIFS('GL 12.22'!$L:$L,'GL 12.22'!$A:$A,A11,'GL 12.22'!$C:$C,"=LTD") -> 6654578.7 | E11: =SUMIFS('GL 12.22'!$L:$L,'GL 12.22'!$A:$A,A11,'GL 12.22'!$C:$C,"=INC") -> 7502165.3 | G11: =SUMIF('GL 12.22'!$A:$A,A11,'GL 12.22'!$N:$N) -> 13711791 | I11: 6443527.9 | K11: 7468650.4 | M11: 13467225 | O11: =C11-I11 -> 211050.83 | Q11: =E11-K11 -> 33514.969 | S11: =G11-M11 -> 244565.79
A12: 60 | B12: Marketing | C12: =SUMIFS('GL 12.22'!$L:$L,'GL 12.22'!$A:$A,A12,'GL 12.22'!$C:$C,"=LTD") -> 3076604.8 | E12: =SUMIFS('GL 12.22'!$L:$L,'GL 12.22'!$A:$A,A12,'GL 12.22'!$C:$C,"=INC") -> 1638623.3 | G12: =SUMIF('GL 12.22'!$A:$A,A12,'GL 12.22'!$N:$N) -> 4455931.8 | I12: 3076604.8 | K12: 1638623.3 | M12: 4455931.8 | O12: =C12-I12 -> 0 | Q12: =E12-K12 -> 0 | S12: =G12-M12 -> 0
A13: 70 | B13: G&A | C13: =SUMIFS('GL 12.22'!$L:$L,'GL 12.22'!$A:$A,A13,'GL 12.22'!$C:$C,"=LTD") -> 3338312.4 | E13: =SUMIFS('GL 12.22'!$L:$L,'GL 12.22'!$A:$A,A13,'GL 12.22'!$C:$C,"=INC")+SUMIFS('GL 12.22'!$L:$L,'GL 12.22'!$A:$A,A25,'GL 12.22'!$C:$C,"=INC") -> 948923.23 | G13: =SUMIF('GL 12.22'!$A:$A,A13,'GL 12.22'!$N:$N)+SUMIF('GL 12.22'!$A:$A,A25,'GL 12.22'!$N:$N) -> 4287235.6 | I13: 3338312.4 | K13: 948923.23 | M13: 4287235.6 | O13: =C13-I13 -> 0 | Q13: =E13-K13 -> 0 | S13: =G13-M13 -> 0
C14: =SUM(C10:C13) -> 23857576 | E14: =SUM(E10:E13) -> 10089712 | G14: =SUM(G10:G13) -> 33243038 | I14: 23646525 | K14: 10056197 | M14: 32998472 | O14: =C14-I14 -> 211050.83 | Q14: =E14-K14 -> 33514.969 | S14: =G14-M14 -> 244565.79
O15: =C15-I15 -> 0 | Q15: =E15-K15 -> 0 | S15: =G15-M15 -> 0
A16: 99 | B16: Overhead | C16: =SUMIFS('GL 12.22'!$L:$L,'GL 12.22'!$A:$A,A16,'GL 12.22'!$C:$C,"=LTD") -> 0 | E16: =SUMIFS('GL 12.22'!$L:$L,'GL 12.22'!$A:$A,A16,'GL 12.22'!$C:$C,"=INC") -> 0 | G16: =-SUMIF('GL 12.22'!$A:$A,A16,'GL 12.22'!$N:$N) -> 0 | I16: 0 | K16: 0 | M16: 0 | O16: =C16-I16 -> 0 | Q16: =E16-K16 -> 0 | S16: =G16-M16 -> 0
O17: =C17-I17 -> 0 | Q17: =E17-K17 -> 0 | S17: =G17-M17 -> 0
B18: Operating Margin | C18: =C7-C14-C16 -> -27096134 | E18: =E7-E14-E16 -> 53763.794 | G18: =G7-G14-G16 -> -27042370 | I18: -26872108 | K18: 90904.277 | M18: -26781204 | O18: =C18-I18 -> -224025.22 | Q18: =E18-K18 -> -37140.483 | S18: =G18-M18 -> -261165.71
C19: =C18/C5 -> -7.1274091 | E19: =E18/E5 -> 0.0046714426 | G19: =G18/G5 -> -2.8038859 | I19: -7.0684812 | K19: 0.0078985146 | M19: -2.776807 | O19: =C19-I19 -> -0.058927943 | Q19: =E19-K19 -> -0.003227072 | S19: =G19-M19 -> -0.027078945
O20: =C20-I20 -> 0 | Q20: =E20-K20 -> 0 | S20: =G20-M20 -> 0
A21: 80 | B21: Other | C21: =SUMIFS('GL 12.22'!$L:$L,'GL 12.22'!$A:$A,A21,'GL 12.22'!$C:$C,"=LTD") -> 0 | E21: =SUMIFS('GL 12.22'!$L:$L,'GL 12.22'!$A:$A,A21,'GL 12.22'!$C:$C,"=INC") -> 0 | G21: =SUMIF('GL 12.22'!$A:$A,A21,'GL 12.22'!$L:$L) -> 0 | I21: 0 | K21: 0 | M21: 0 | O21: =C21-I21 -> 0 | Q21: =E21-K21 -> 0 | S21: =G21-M21 -> 0
O22: =C22-I22 -> 0 | Q22: =E22-K22 -> 0 | S22: =G22-M22 -> 0
A23: 90 | B23: Finance | C23: =SUMIFS('GL 12.22'!$L:$L,'GL 12.22'!$A:$A,A23,'GL 12.22'!$C:$C,"=LTD") -> -2905.87 | E23: =SUMIFS('GL 12.22'!$L:$L,'GL 12.22'!$A:$A,A23,'GL 12.22'!$C:$C,"=INC") -> -203176.12 | G23: =SUMIF('GL 12.22'!$A:$A,A23,'GL 12.22'!$N:$N) -> -206081.99 | I23: -2905.87 | K23: -203176.12 | M23: -206081.99 | O23: =C23-I23 -> 0 | Q23: =E23-K23 -> 0 | S23: =G23-M23 -> 0
O24: =C24-I24 -> 0 | Q24: =E24-K24 -> 0 | S24: =G24-M24 -> 0
A25: 88 | B25: Tax | C25: =SUMIFS('GL 12.22'!$L:$L,'GL 12.22'!$A:$A,A25,'GL 12.22'!$C:$C,"=LTD") -> 0 | E25: 0 | G25: 0 | I25: 0 | K25: 0 | M25: 0 | O25: =C25-I25 -> 0 | Q25: =E25-K25 -> 0 | S25: =G25-M25 -> 0
O26: =C26-I26 -> 0 | Q26: =E26-K26 -> 0 | S26: =G26-M26 -> 0
B27: Net Income | C27: =C18-C21-C23-C25 -> -27093228 | E27: =E18-E21-E23-E25 -> 256939.91 | G27: =G18-G21-G23-G25 -> -26836288 | I27: -26869203 | K27: 294080.4 | M27: -26575122 | O27: =C27-I27 -> -224025.22 | Q27: =E27-K27 -> -37140.483 | S27: =G27-M27 -> -261165.71
C28: =C27/C5 -> -7.1266448 | E28: =E27/E5 -> 0.022325062 | G28: =G27/G5 -> -2.7825183 | I28: -7.0677168 | K28: 0.025552135 | M28: -2.7554394

Sheet BS
C2: =G2 -> 44926 | E2: =C2 -> 44926 | G2: 44926 | I2: V10 | O2: Diff
C3: Ltd Solo | E3: Inc Solo | G3: Consolidated | I3: Ltd Solo | K3: Inc Solo | M3: Consolidated | O3: Ltd Solo | Q3: Inc Solo | S3: Consolidated
A5: 1 | B5: Cash and Cash Equivalents | C5: =SUMIFS('GL 12.22'!$L:$L,'GL 12.22'!$A:$A,$A5,'GL 12.22'!$C:$C,"Ltd") -> 33296538 | E5: =SUMIFS('GL 12.22'!$L:$L,'GL 12.22'!$A:$A,$A5,'GL 12.22'!$C:$C,"Inc") -> 16726555 | G5: =SUMIF('GL 12.22'!$A:$A,A5,'GL 12.22'!$N:$N) -> 50023093 | I5: 33296538 | K5: 16726555 | M5: 50023093 | O5: =C5-I5 -> 0 | Q5: =E5-K5 -> 0 | S5: =G5-M5 -> 0
A6: 2 | B6: Accounts Receivable | C6: =SUMIFS('GL 12.22'!$L:$L,'GL 12.22'!$A:$A,$A6,'GL 12.22'!$C:$C,"Ltd") -> 2628437.3 | E6: =SUMIFS('GL 12.22'!$L:$L,'GL 12.22'!$A:$A,$A6,'GL 12.22'!$C:$C,"Inc") -> 1727688.7 | G6: =SUMIF('GL 12.22'!$A:$A,A6,'GL 12.22'!$N:$N) -> 4356126 | I6: 2628437.3 | K6: 1727688.7 | M6: 4356126 | O6: =C6-I6 -> 0 | Q6: =E6-K6 -> 0 | S6: =G6-M6 -> 0
A7: 3 | B7: Prepaid Expenses and Other Receivable | C7: =SUMIFS('GL 12.22'!$L:$L,'GL 12.22'!$A:$A,$A7,'GL 12.22'!$C:$C,"Ltd") -> 3907599.5 | E7: =SUMIFS('GL 12.22'!$L:$L,'GL 12.22'!$A:$A,$A7,'GL 12.22'!$C:$C,"Inc") -> 3269439.4 | G7: =SUMIF('GL 12.22'!$A:$A,A7,'GL 12.22'!$N:$N) -> 7177038.9 | I7: 3907599.5 | K7: 3269439.4 | M7: 7177038.9 | O7: =C7-I7 -> 0 | Q7: =E7-K7 -> 0 | S7: =G7-M7 -> 0
A8: 16 | B8: Right-of-use asset | C8: =SUMIFS('GL 12.22'!$L:$L,'GL 12.22'!$A:$A,$A8,'GL 12.22'!$C:$C,"Ltd") -> 978652.28 | E8: =SUMIFS('GL 12.22'!$L:$L,'GL 12.22'!$A:$A,$A8,'GL 12.22'!$C:$C,"Inc") -> 0 | G8: =SUMIF('GL 12.22'!$A:$A,A8,'GL 12.22'!$N:$N) -> 978652.28 | I8: 978652.28 | K8: 0 | M8: 978652.28 | O8: =C8-I8 -> 0 | Q8: =E8-K8 -> 0 | S8: =G8-M8 -> 0
A9: 5 | B9: Intercompany | C9: =SUMIFS('GL 12.22'!$L:$L,'GL 12.22'!$A:$A,$A9,'GL 12.22'!$C:$C,"Ltd") -> -92047294 | E9: =SUMIFS('GL 12.22'!$L:$L,'GL 12.22'!$A:$A,$A9,'GL 12.22'!$C:$C,"Inc") -> 54344528 | G9: =SUMIF('GL 12.22'!$A:$A,A9,'GL 12.22'!$N:$N) -> -0.22000001 | I9: -92047294 | K9: 54344528 | M9: -0.22000001 | O9: =C9-I9 -> 0 | Q9: =E9-K9 -> 0 | S9: =G9-M9 -> 0
C10: =SUM(C5:C9) -> -51236067 | E10: =SUM(E5:E9) -> 76068211 | G10: =SUM(G5:G9) -> 62534910 | I10: -51236067 | K10: 76068211 | M10: 62534910 | O10: =C10-I10 -> 0 | Q10: =E10-K10 -> 0 | S10: =G10-M10 -> 0
A12: 4 | B12: Fixed Assets | C12: =SUMIFS('GL 12.22'!$L:$L,'GL 12.22'!$A:$A,$A12,'GL 12.22'!$C:$C,"Ltd") -> 575033.88 | E12: =SUMIFS('GL 12.22'!$L:$L,'GL 12.22'!$A:$A,$A12,'GL 12.22'!$C:$C,"Inc") -> 0 | G12: =SUMIF('GL 12.22'!$A:$A,A12,'GL 12.22'!$N:$N) -> 575033.88 | I12: 575033.88 | K12: 0 | M12: 575033.88 | O12: =C12-I12 -> 0 | Q12: =E12-K12 -> 0 | S12: =G12-M12 -> 0
A13: 17 | B13: Long-term Right-of-use asset | C13: =SUMIFS('GL 12.22'!$L:$L,'GL 12.22'!$A:$A,$A13,'GL 12.22'!$C:$C,"Ltd") -> 2201963.3 | E13: =SUMIFS('GL 12.22'!$L:$L,'GL 12.22'!$A:$A,$A13,'GL 12.22'!$C:$C,"Inc") -> 0 | G13: =SUMIF('GL 12.22'!$A:$A,A13,'GL 12.22'!$N:$N) -> 2201963.3 | I13: 2201963.3 | K13: 0 | M13: 2201963.3 | O13: =C13-I13 -> 0 | Q13: =E13-K13 -> 0 | S13: =G13-M13 -> 0
C14: =C12+C13 -> 2776997.1 | E14: =E12+E13 -> 0 | G14: =G12+G13 -> 2776997.1 | I14: 2776997.1 | K14: 0 | M14: 2776997.1 | O14: =C14-I14 -> 0 | Q14: =E14-K14 -> 0 | S14: =G14-M14 -> 0
C16: =C10+C14 -> -48459070 | E16: =E10+E14 -> 76068211 | G16: =G10+G14 -> 65311907 | I16: -48459070 | K16: 76068211 | M16: 65311907 | O16: =C16-I16 -> 0 | Q16: =E16-K16 -> 0 | S16: =G16-M16 -> 0
A18: 6 | B18: Accounts Payable | C18: =SUMIFS('GL 12.22'!$L:$L,'GL 12.22'!$A:$A,$A18,'GL 12.22'!$C:$C,"Ltd") -> -857637.01 | E18: =SUMIFS('GL 12.22'!$L:$L,'GL 12.22'!$A:$A,$A18,'GL 12.22'!$C:$C,"Inc") -> -193889.46 | G18: =SUMIF('GL 12.22'!$A:$A,A18,'GL 12.22'!$N:$N) -> -1051526.5 | I18: -857637.01 | K18: -193889.46 | M18: -1051526.5 | O18: =C18-I18 -> 0 | Q18: =E18-K18 -> 0 | S18: =G18-M18 -> 0
A19: 7 | B19: Accrues Expenses and Other Payable | C19: =SUMIFS('GL 12.22'!$L:$L,'GL 12.22'!$A:$A,$A19,'GL 12.22'!$C:$C,"Ltd") -> -455091.61 | E19: =SUMIFS('GL 12.22'!$L:$L,'GL 12.22'!$A:$A,$A19,'GL 12.22'!$C:$C,"Inc") -> -142741.29 | G19: =SUMIF('GL 12.22'!$A:$A,A19,'GL 12.22'!$N:$N) -> -597832.9 | I19: -455091.61 | K19: -142741.29 | M19: -597832.9 | O19: =C19-I19 -> 0 | Q19: =E19-K19 -> 0 | S19: =G19-M19 -> 0
A20: 8 | B20: Employees Payable | C20: =SUMIFS('GL 12.22'!$L:$L,'GL 12.22'!$A:$A,$A20,'GL 12.22'!$C:$C,"Ltd") -> -3283620.8 | E20: =SUMIFS('GL 12.22'!$L:$L,'GL 12.22'!$A:$A,$A20,'GL 12.22'!$C:$C,"Inc") -> -1205090.4 | G20: =SUMIF('GL 12.22'!$A:$A,A20,'GL 12.22'!$N:$N) -> -4488711.3 | I20: -3059595.6 | K20: -1167950 | M20: -4227545.6 | O20: =C20-I20 -> -224025.22 | Q20: =E20-K20 -> -37140.483 | S20: =G20-M20 -> -261165.71
A21: 18 | B21: Current Lease liability | C21: =SUMIFS('GL 12.22'!$L:$L,'GL 12.22'!$A:$A,$A21,'GL 12.22'!$C:$C,"Ltd") -> -1064637.7 | E21: =SUMIFS('GL 12.22'!$L:$L,'GL 12.22'!$A:$A,$A21,'GL 12.22'!$C:$C,"Inc") -> 0 | G21: =SUMIF('GL 12.22'!$A:$A,A21,'GL 12.22'!$N:$N) -> -1064637.7 | I21: -1064637.7 | K21: 0 | M21: -1064637.7 | O21: =C21-I21 -> 0 | Q21: =E21-K21 -> 0 | S21: =G21-M21 -> 0
A22: 9 | B22: Deferred Revenue | C22: =SUMIFS('GL 12.22'!$L:$L,'GL 12.22'!$A:$A,$A22,'GL 12.22'!$C:$C,"Ltd") -> -4515227.9 | E22: =SUMIFS('GL 12.22'!$L:$L,'GL 12.22'!$A:$A,$A22,'GL 12.22'!$C:$C,"Inc") -> -5616818.4 | G22: =SUMIF('GL 12.22'!$A:$A,A22,'GL 12.22'!$N:$N) -> -10132046 | I22: -4515227.9 | K22: -5616818.4 | M22: -10132046 | O22: =C22-I22 -> 0 | Q22: =E22-K22 -> 0 | S22: =G22-M22 -> 0
C23: =SUM(C18:C22) -> -10176215 | E23: =SUM(E18:E22) -> -7158539.6 | G23: =SUM(G18:G22) -> -17334755 | I23: -9952189.9 | K23: -7121399.1 | M23: -17073589 | O23: =C23-I23 -> -224025.22 | Q23: =E23-K23 -> -37140.483 | S23: =G23-M23 -> -261165.71
A25: 14 | B25: Other Long Term Liabilities | C25: =SUMIFS('GL 12.22'!$L:$L,'GL 12.22'!$A:$A,$A25,'GL 12.22'!$C:$C,"Ltd") -> 0 | E25: =SUMIFS('GL 12.22'!$L:$L,'GL 12.22'!$A:$A,$A25,'GL 12.22'!$C:$C,"Inc") -> -548875.83 | G25: =SUMIF('GL 12.22'!$A:$A,A25,'GL 12.22'!$N:$N) -> -548875.83 | I25: 0 | K25: -548875.83 | M25: -548875.83 | O25: =C25-I25 -> 0 | Q25: =E25-K25 -> 0 | S25: =G25-M25 -> 0
A26: 19 | B26: Long-term Lease liability | C26: =SUMIFS('GL 12.22'!$L:$L,'GL 12.22'!$A:$A,$A26,'GL 12.22'!$C:$C,"Ltd") -> -1940868.1 | E26: =SUMIFS('GL 12.22'!$L:$L,'GL 12.22'!$A:$A,$A26,'GL 12.22'!$C:$C,"Inc") -> 0 | G26: =SUMIF('GL 12.22'!$A:$A,A26,'GL 12.22'!$N:$N) -> -1940868.1 | I26: -1940868.1 | K26: 0 | M26: -1940868.1 | O26: =C26-I26 -> 0 | Q26: =E26-K26 -> 0 | S26: =G26-M26 -> 0
A27: 15 | B27: Long term deferred revenue | C27: =SUMIFS('GL 12.22'!$L:$L,'GL 12.22'!$A:$A,$A27,'GL 12.22'!$C:$C,"Ltd") -> -1336920.2 | E27: =SUMIFS('GL 12.22'!$L:$L,'GL 12.22'!$A:$A,$A27,'GL 12.22'!$C:$C,"Inc") -> -2696365 | G27: =SUMIF('GL 12.22'!$A:$A,A27,'GL 12.22'!$N:$N) -> -4033285.2 | I27: -1336920.2 | K27: -2696365 | M27: -4033285.2 | O27: =C27-I27 -> 0 | Q27: =E27-K27 -> 0 | S27: =G27-M27 -> 0
C28: =SUM(C25:C27) -> -3277788.3 | E28: =SUM(E25:E27) -> -3245240.8 | G28: =SUM(G25:G27) -> -6523029.1 | I28: -3277788.3 | K28: -3245240.8 | M28: -6523029.1 | O28: =C28-I28 -> 0 | Q28: =E28-K28 -> 0 | S28: =G28-M28 -> 0
A30: 10 | B30: Capital Stock | C30: =SUMIFS('GL 12.22'!$L:$L,'GL 12.22'!$A:$A,$A30,'GL 12.22'!$C:$C,"Ltd") -> -3046161 | E30: =SUMIFS('GL 12.22'!$L:$L,'GL 12.22'!$A:$A,$A30,'GL 12.22'!$C:$C,"Inc") -> 2816040.6 | G30: =SUMIF('GL 12.22'!$A:$A,A30,'GL 12.22'!$N:$N) -> -230120.42 | I30: -3046161 | K30: 2816040.6 | M30: -230120.42 | O30: =C30-I30 -> 0 | Q30: =E30-K30 -> 0 | S30: =G30-M30 -> 0
A31: 11 | B31: Additional Paid In Capital | C31: =SUMIFS('GL 12.22'!$L:$L,'GL 12.22'!$A:$A,$A31,'GL 12.22'!$C:$C,"Ltd") -> 0 | E31: =SUMIFS('GL 12.22'!$L:$L,'GL 12.22'!$A:$A,$A31,'GL 12.22'!$C:$C,"Inc") -> -1.0816314e+08 | G31: =SUMIF('GL 12.22'!$A:$A,A31,'GL 12.22'!$N:$N) -> -1.0816314e+08 | I31: 0 | K31: -1.0816314e+08 | M31: -1.0816314e+08 | O31: =C31-I31 -> 0 | Q31: =E31-K31 -> 0 | S31: =G31-M31 -> 0
A32: 12 | B32: Accumulated Comprehensive Income | C32: =SUMIFS('GL 12.22'!$L:$L,'GL 12.22'!$A:$A,$A32,'GL 12.22'!$C:$C,"Ltd") -> 0 | E32: =SUMIFS('GL 12.22'!$L:$L,'GL 12.22'!$A:$A,$A32,'GL 12.22'!$C:$C,"Inc") -> 0 | I32: 0 | K32: 0
A33: 13 | B33: Retained Loss | C33: =SUMIFS('GL 12.22'!$L:$L,'GL 12.22'!$A:$A,$A33,'GL 12.22'!$C:$C,"Ltd")-'P&L'!C27 -> 64959234 | E33: =SUMIFS('GL 12.22'!$L:$L,'GL 12.22'!$A:$A,$A33,'GL 12.22'!$C:$C,"Inc")-'P&L'!E27 -> 39682669 | G33: =SUMIF('GL 12.22'!$A:$A,A33,'GL 12.22'!$N:$N)-'P&L'!G27 -> 66939138 | I33: 64735209 | K33: 39645529 | M33: 66677972 | O33: =C33-I33 -> 224025.22 | Q33: =E33-K33 -> 37140.483 | S33: =G33-M33 -> 261165.71
C34: =SUM(C30:C33) -> 61913073 | E34: =SUM(E30:E33) -> -65664431 | G34: =SUM(G30:G33) -> -41454123 | I34: 61689048 | K34: -65701571 | M34: -41715289 | O34: =C34-I34 -> 224025.22 | Q34: =E34-K34 -> 37140.483 | S34: =G34-M34 -> 261165.71
C36: =C23+C34+C28 -> 48459070 | E36: =E23+E34+E28 -> -76068211 | G36: =G23+G34+G28 -> -65311907 | I36: 48459070 | K36: -76068211 | M36: -65311907 | O36: =C36-I36 -> 0 | Q36: =E36-K36 -> 0 | S36: =G36-M36 -> 0
C37: =C16+C36 -> 0 | E37: =E16+E36 -> 0 | G37: =G16+G36 -> 0

Sheet AJE
B1: 12.22 | N1: 12.22 - Allocations | Y1: 12.22 - Consolidation | AL1: פקודות שכבר נרשמו בספרים
B2: # | C2: Description | D2: Entity | E2: GL Account # | F2: TB Account # | G2: Account Name | H2: Balance in USD | N2: # | O2: Description | P2: Entity | Q2: GL Account # | R2: TB Account # | S2: Account Name | T2: Balance in USD | Y2: # | Z2: Description | AA2: Entity | AB2: GL Account # | AC2: TB Account # | AD2: Account Name | AE2: Balance in USD | AL2: # | AM2: Description | AN2: Entity | AO2: GL Account # | AP2: TB Account # | AQ2: Account Name | AR2: Balance in USD
O3: LTD OH Allocation - Step 1 | P3: =IF(LEFT(Q3,1)="1","LTD","INC") -> LTD | Q3: 1670369900 | R3: =_xlfn.NUMBERVALUE(MID(Q3,2,5)) -> 67036 | S3: =IF(P3="LTD",_xlfn.XLOOKUP(R3,'TB LTD 12.22'!$E:$E,'TB LTD 12.22'!$F:$F,),_xlfn.XLOOKUP(AJE!R3,'TB INC 12.22'!$B:$B,'TB INC 12.22'!$C:$C,)) -> שכירות משרדים סינגפור | T3: =-(_xlfn.XLOOKUP(Q3,'GL 12.22'!$D:$D,'GL 12.22'!$I:$I,)+_xlfn.XLOOKUP(Q3,'GL 12.22'!$D:$D,'GL 12.22'!$J:$J,)) -> -12025.7 | Y3: 1 | Z3: IC | AA3: =IF(LEFT(AB3,1)="1","LTD","INC") -> INC | AB3: 216050500 | AC3: =_xlfn.NUMBERVALUE(MID(AB3,2,5)) -> 16050 | AD3: =IF(AA3="LTD",_xlfn.XLOOKUP(AC3,'TB LTD 12.22'!$E:$E,'TB LTD 12.22'!$F:$F,),_xlfn.XLOOKUP(AJE!AC3,'TB INC 12.22'!$B:$B,'TB INC 12.22'!$C:$C,)) -> 16050 LTD Investement - Equity Loss | AE3: 37702765
B4: 1 | C4: Issuance costs fix | D4: =IF(LEFT(E4,1)="1","LTD","INC") -> INC | E4: 2300901100 | F4: =_xlfn.NUMBERVALUE(MID(E4,2,5)) -> 30090 | G4: =IF(D4="LTD",_xlfn.XLOOKUP(F4,'TB LTD 12.22'!$E:$E,'TB LTD 12.22'!$F:$F,),_xlfn.XLOOKUP(AJE!F4,'TB INC 12.22'!$B:$B,'TB INC 12.22'!$C:$C,)) -> 30090 Additional Paid In Capital | H4: 2000 | P4: =IF(LEFT(Q4,1)="1","LTD","INC") -> LTD | Q4: 1650059900 | R4: =_xlfn.NUMBERVALUE(MID(Q4,2,5)) -> 65005 | S4: =IF(P4="LTD",_xlfn.XLOOKUP(R4,'TB LTD 12.22'!$E:$E,'TB LTD 12.22'!$F:$F,),_xlfn.XLOOKUP(AJE!R4,'TB INC 12.22'!$B:$B,'TB INC 12.22'!$C:$C,)) -> נסיעות | T4: =-(_xlfn.XLOOKUP(Q4,'GL 12.22'!$D:$D,'GL 12.22'!$I:$I,)+_xlfn.XLOOKUP(Q4,'GL 12.22'!$D:$D,'GL 12.22'!$J:$J,)) -> -11869.77 | AA4: =IF(LEFT(AB4,1)="1","LTD","INC") -> INC | AB4: 2350001300 | AC4: =_xlfn.NUMBERVALUE(MID(AB4,2,5)) -> 35000 | AD4: =IF(AA4="LTD",_xlfn.XLOOKUP(AC4,'TB LTD 12.22'!$E:$E,'TB LTD 12.22'!$F:$F,),_xlfn.XLOOKUP(AJE!AC4,'TB INC 12.22'!$B:$B,'TB INC 12.22'!$C:$C,)) -> 35000 Retained Earnings | AE4: =-AE3 -> -37702765 | AL4: 1 | AM4: SBC | AN4: LTD | AO4: 160312301160 | AP4: 60312 | AQ4: COS תשלום מבוסס מניות | AR4: 34797.078
D5: =IF(LEFT(E5,1)="1","LTD","INC") -> INC | E5: 280220701020 | F5: =_xlfn.NUMBERVALUE(MID(E5,2,5)) -> 80220 | G5: =IF(D5="LTD",_xlfn.XLOOKUP(F5,'TB LTD 12.22'!$E:$E,'TB LTD 12.22'!$F:$F,),_xlfn.XLOOKUP(AJE!F5,'TB INC 12.22'!$B:$B,'TB INC 12.22'!$C:$C,)) -> 80220 General and Administrative:Professional Fees:Consulting | H5: =-H4 -> -2000 | P5: =IF(LEFT(Q5,1)="1","LTD","INC") -> LTD | Q5: 1650069900 | R5: =_xlfn.NUMBERVALUE(MID(Q5,2,5)) -> 65006 | S5: =IF(P5="LTD",_xlfn.XLOOKUP(R5,'TB LTD 12.22'!$E:$E,'TB LTD 12.22'!$F:$F,),_xlfn.XLOOKUP(AJE!R5,'TB INC 12.22'!$B:$B,'TB INC 12.22'!$C:$C,)) -> ארוחות עובדים | T5: =-(_xlfn.XLOOKUP(Q5,'GL 12.22'!$D:$D,'GL 12.22'!$I:$I,)+_xlfn.XLOOKUP(Q5,'GL 12.22'!$D:$D,'GL 12.22'!$J:$J,)) -> -328933.13 | AN5: LTD | AO5: 161117401160 | AP5: 61117 | AQ5: תשלום מבוסס מניות פיתוח | AR5: 750232.16
P6: =IF(LEFT(Q6,1)="1","LTD","INC") -> LTD | Q6: 1650079900 | R6: =_xlfn.NUMBERVALUE(MID(Q6,2,5)) -> 65007 | S6: =IF(P6="LTD",_xlfn.XLOOKUP(R6,'TB LTD 12.22'!$E:$E,'TB LTD 12.22'!$F:$F,),_xlfn.XLOOKUP(AJE!R6,'TB INC 12.22'!$B:$B,'TB INC 12.22'!$C:$C,)) -> חניות | T6: =-(_xlfn.XLOOKUP(Q6,'GL 12.22'!$D:$D,'GL 12.22'!$I:$I,)+_xlfn.XLOOKUP(Q6,'GL 12.22'!$D:$D,'GL 12.22'!$J:$J,)) -> -80167.88 | Y6: 2 | Z6: TP | AA6: =IF(LEFT(AB6,1)="1","LTD","INC") -> INC | AB6: 2400502000 | AC6: =_xlfn.NUMBERVALUE(MID(AB6,2,5)) -> 40050 | AD6: =IF(AA6="LTD",_xlfn.XLOOKUP(AC6,'TB LTD 12.22'!$E:$E,'TB LTD 12.22'!$F:$F,),_xlfn.XLOOKUP(AJE!AC6,'TB INC 12.22'!$B:$B,'TB INC 12.22'!$C:$C,)) -> 40050 Intercompany Revenue | AE6: =5666110.81477924+0.19 -> 5666111 | AN6: LTD | AO6: 161317501160 | AP6: 61317 | AQ6: תשלום מבוסס מניות מכירות | AR6: 92826.96
B7: 2 | C7: Deferred Revenue | D7: =IF(LEFT(E7,1)="1","LTD","INC") -> INC | E7: 212105300 | F7: =_xlfn.NUMBERVALUE(MID(E7,2,5)) -> 12105 | G7: =IF(D7="LTD",_xlfn.XLOOKUP(F7,'TB LTD 12.22'!$E:$E,'TB LTD 12.22'!$F:$F,),_xlfn.XLOOKUP(AJE!F7,'TB INC 12.22'!$B:$B,'TB INC 12.22'!$C:$C,)) -> 12105 Accrued Unbilled Revenue | H7: -324225 | P7: =IF(LEFT(Q7,1)="1","LTD","INC") -> LTD | Q7: 1650169900 | R7: =_xlfn.NUMBERVALUE(MID(Q7,2,5)) -> 65016 | S7: =IF(P7="LTD",_xlfn.XLOOKUP(R7,'TB LTD 12.22'!$E:$E,'TB LTD 12.22'!$F:$F,),_xlfn.XLOOKUP(AJE!R7,'TB INC 12.22'!$B:$B,'TB INC 12.22'!$C:$C,)) -> כיבודים | T7: =-(_xlfn.XLOOKUP(Q7,'GL 12.22'!$D:$D,'GL 12.22'!$I:$I,)+_xlfn.XLOOKUP(Q7,'GL 12.22'!$D:$D,'GL 12.22'!$J:$J,)) -> -40798.86 | AA7: =IF(LEFT(AB7,1)="1","LTD","INC") -> INC | AB7: 216000500 | AC7: =_xlfn.NUMBERVALUE(MID(AB7,2,5)) -> 16000 | AD7: =IF(AA7="LTD",_xlfn.XLOOKUP(AC7,'TB LTD 12.22'!$E:$E,'TB LTD 12.22'!$F:$F,),_xlfn.XLOOKUP(AJE!AC7,'TB INC 12.22'!$B:$B,'TB INC 12.22'!$C:$C,)) -> 16000 Intercompany Silverfort LTD | AE7: =-AE6 -> -5666111 | AN7: LTD | AO7: 160912601160 | AP7: 60912 | AQ7: תשלום מבוסס מניות שיווק | AR7: 20995.023
C8: ביטול הפקודה | D8: =IF(LEFT(E8,1)="1","LTD","INC") -> INC | E8: 222005900 | F8: =_xlfn.NUMBERVALUE(MID(E8,2,5)) -> 22005 | G8: =IF(D8="LTD",_xlfn.XLOOKUP(F8,'TB LTD 12.22'!$E:$E,'TB LTD 12.22'!$F:$F,),_xlfn.XLOOKUP(AJE!F8,'TB INC 12.22'!$B:$B,'TB INC 12.22'!$C:$C,)) -> 22005 Deferred Revenue:Software Sales | H8: =-H7 -> 324225 | P8: =IF(LEFT(Q8,1)="1","LTD","INC") -> LTD | Q8: 165016L9900 | R8: =_xlfn.NUMBERVALUE(MID(Q8,2,5)) -> 65016 | S8: =IF(P8="LTD",_xlfn.XLOOKUP(R8,'TB LTD 12.22'!$E:$E,'TB LTD 12.22'!$F:$F,),_xlfn.XLOOKUP(AJE!R8,'TB INC 12.22'!$B:$B,'TB INC 12.22'!$C:$C,)) -> כיבודים | T8: =-(_xlfn.XLOOKUP(Q8,'GL 12.22'!$D:$D,'GL 12.22'!$I:$I,)+_xlfn.XLOOKUP(Q8,'GL 12.22'!$D:$D,'GL 12.22'!$J:$J,)) -> -31188.71 | AN8: LTD | AO8: 161021701160 | AP8: 61021 | AQ8: תשלום מבוסס מניות הנהלה | AR8: 601515.33
P9: =IF(LEFT(Q9,1)="1","LTD","INC") -> LTD | Q9: 1650179900 | R9: =_xlfn.NUMBERVALUE(MID(Q9,2,5)) -> 65017 | S9: =IF(P9="LTD",_xlfn.XLOOKUP(R9,'TB LTD 12.22'!$E:$E,'TB LTD 12.22'!$F:$F,),_xlfn.XLOOKUP(AJE!R9,'TB INC 12.22'!$B:$B,'TB INC 12.22'!$C:$C,)) -> מתנות לעובדי ישראל | T9: =-(_xlfn.XLOOKUP(Q9,'GL 12.22'!$D:$D,'GL 12.22'!$I:$I,)+_xlfn.XLOOKUP(Q9,'GL 12.22'!$D:$D,'GL 12.22'!$J:$J,)) -> -126978.38 | AA9: =IF(LEFT(AB9,1)="1","LTD","INC") -> LTD | AB9: 180001500 | AC9: =_xlfn.NUMBERVALUE(MID(AB9,2,5)) -> 80001 | AD9: =IF(AA9="LTD",_xlfn.XLOOKUP(AC9,'TB LTD 12.22'!$E:$E,'TB LTD 12.22'!$F:$F,),_xlfn.XLOOKUP(AJE!AC9,'TB INC 12.22'!$B:$B,'TB INC 12.22'!$C:$C,)) -> Silverfort INC | AE9: =-AE7 -> 5666111 | AN9: LTD | AO9: 180004500 | AP9: 80004 | AQ9: Silverfort INC Share-based Compensation | AR9: -1500366.6
B10: 3 | C10: LTD Rev Adj | D10: =IF(LEFT(E10,1)="1","LTD",IF(LEFT(#REF!,1)="2","INC"," ")) -> LTD | E10: 1500042000 | F10: =_xlfn.NUMBERVALUE(MID(E10,2,5)) -> 50004 | G10: =IF(D10="LTD",_xlfn.XLOOKUP(F10,'TB LTD 12.22'!$E:$E,'TB LTD 12.22'!$F:$F,),_xlfn.XLOOKUP(AJE!F10,'TB INC 12.22'!$B:$B,'TB INC 12.22'!$C:$C,)) -> הכנסות מחו"ל | H10: =-K12 -> -1442.8459 | J10: should be | K10: 3809869.7 | P10: =IF(LEFT(Q10,1)="1","LTD","INC") -> LTD | Q10: 1650209900 | R10: =_xlfn.NUMBERVALUE(MID(Q10,2,5)) -> 65020 | S10: =IF(P10="LTD",_xlfn.XLOOKUP(R10,'TB LTD 12.22'!$E:$E,'TB LTD 12.22'!$F:$F,),_xlfn.XLOOKUP(AJE!R10,'TB INC 12.22'!$B:$B,'TB INC 12.22'!$C:$C,)) -> אגרות | T10: =-(_xlfn.XLOOKUP(Q10,'GL 12.22'!$D:$D,'GL 12.22'!$I:$I,)+_xlfn.XLOOKUP(Q10,'GL 12.22'!$D:$D,'GL 12.22'!$J:$J,)) -> -385.53 | AA10: =IF(LEFT(AB10,1)="1","LTD","INC") -> LTD | AB10: 1603103000 | AC10: =_xlfn.NUMBERVALUE(MID(AB10,2,5)) -> 60310 | AD10: =IF(AA10="LTD",_xlfn.XLOOKUP(AC10,'TB LTD 12.22'!$E:$E,'TB LTD 12.22'!$F:$F,),_xlfn.XLOOKUP(AJE!AC10,'TB INC 12.22'!$B:$B,'TB INC 12.22'!$C:$C,)) -> TP Cost of Sales | AE10: =-4961861.12584347-0.19 -> -4961861.3
D11: =IF(LEFT(E11,1)="1","LTD",IF(LEFT(#REF!,1)="2","INC"," ")) -> LTD | E11: 135010900 | F11: =_xlfn.NUMBERVALUE(MID(E11,2,5)) -> 35010 | G11: =IF(D11="LTD",_xlfn.XLOOKUP(F11,'TB LTD 12.22'!$E:$E,'TB LTD 12.22'!$F:$F,),_xlfn.XLOOKUP(AJE!F11,'TB INC 12.22'!$B:$B,'TB INC 12.22'!$C:$C,)) -> הכנסות מראש- ביקורת | H11: =-H10 -> 1442.8459 | J11: books | K11: ='TB LTD 12.22'!H316+'TB LTD 12.22'!H317 -> -3808426.8 | P11: =IF(LEFT(Q11,1)="1","LTD","INC") -> LTD | Q11: 1650219900 | R11: =_xlfn.NUMBERVALUE(MID(Q11,2,5)) -> 65021 | S11: =IF(P11="LTD",_xlfn.XLOOKUP(R11,'TB LTD 12.22'!$E:$E,'TB LTD 12.22'!$F:$F,),_xlfn.XLOOKUP(AJE!R11,'TB INC 12.22'!$B:$B,'TB INC 12.22'!$C:$C,)) -> גיבוש ורווחה וימי כיף עובדים | T11: =-(_xlfn.XLOOKUP(Q11,'GL 12.22'!$D:$D,'GL 12.22'!$I:$I,)+_xlfn.XLOOKUP(Q11,'GL 12.22'!$D:$D,'GL 12.22'!$J:$J,)) -> -118369.7 | AA11: =IF(LEFT(AB11,1)="1","LTD","INC") -> LTD | AB11: 1625165000 | AC11: =_xlfn.NUMBERVALUE(MID(AB11,2,5)) -> 62516 | AD11: =IF(AA11="LTD",_xlfn.XLOOKUP(AC11,'TB LTD 12.22'!$E:$E,'TB LTD 12.22'!$F:$F,),_xlfn.XLOOKUP(AJE!AC11,'TB INC 12.22'!$B:$B,'TB INC 12.22'!$C:$C,)) -> TP Sales | AE11: -444953.46 | AN11: INC | AO11: 275110301160 | AP11: 75110 | AQ11: 75110 Client Services:SBC | AR11: 20512.708
K12: =K10+K11 -> 1442.8459 | P12: =IF(LEFT(Q12,1)="1","LTD","INC") -> LTD | Q12: 1670079900 | R12: =_xlfn.NUMBERVALUE(MID(Q12,2,5)) -> 67007 | S12: =IF(P12="LTD",_xlfn.XLOOKUP(R12,'TB LTD 12.22'!$E:$E,'TB LTD 12.22'!$F:$F,),_xlfn.XLOOKUP(AJE!R12,'TB INC 12.22'!$B:$B,'TB INC 12.22'!$C:$C,)) -> דמי ניהול פנסיונים | T12: =-(_xlfn.XLOOKUP(Q12,'GL 12.22'!$D:$D,'GL 12.22'!$I:$I,)+_xlfn.XLOOKUP(Q12,'GL 12.22'!$D:$D,'GL 12.22'!$J:$J,)) -> -12142.32 | AA12: =IF(LEFT(AB12,1)="1","LTD","INC") -> LTD | AB12: 1625156000 | AC12: =_xlfn.NUMBERVALUE(MID(AB12,2,5)) -> 62515 | AD12: =IF(AA12="LTD",_xlfn.XLOOKUP(AC12,'TB LTD 12.22'!$E:$E,'TB LTD 12.22'!$F:$F,),_xlfn.XLOOKUP(AJE!AC12,'TB INC 12.22'!$B:$B,'TB INC 12.22'!$C:$C,)) -> TP Marketing | AE12: -259296.23 | AN12: INC | AO12: 270110501160 | AP12: 70110 | AQ12: 70110 Sales:SBC | AR12: 368800.64
B13: 4 | C13: AON | D13: =IF(LEFT(E13,1)="1","LTD",IF(LEFT(#REF!,1)="2","INC"," ")) -> LTD | E13: 1500042000 | F13: =_xlfn.NUMBERVALUE(MID(E13,2,5)) -> 50004 | G13: =IF(D13="LTD",_xlfn.XLOOKUP(F13,'TB LTD 12.22'!$E:$E,'TB LTD 12.22'!$F:$F,),_xlfn.XLOOKUP(AJE!F13,'TB INC 12.22'!$B:$B,'TB INC 12.22'!$C:$C,)) -> הכנסות מחו"ל | H13: 8189 | P13: =IF(LEFT(Q13,1)="1","LTD","INC") -> LTD | Q13: 1670379900 | R13: =_xlfn.NUMBERVALUE(MID(Q13,2,5)) -> 67037 | S13: =IF(P13="LTD",_xlfn.XLOOKUP(R13,'TB LTD 12.22'!$E:$E,'TB LTD 12.22'!$F:$F,),_xlfn.XLOOKUP(AJE!R13,'TB INC 12.22'!$B:$B,'TB INC 12.22'!$C:$C,)) -> השכרת חדרים | T13: =-(_xlfn.XLOOKUP(Q13,'GL 12.22'!$D:$D,'GL 12.22'!$I:$I,)+_xlfn.XLOOKUP(Q13,'GL 12.22'!$D:$D,'GL 12.22'!$J:$J,)) -> -1746.49 | AN13: INC | AO13: 272110601160 | AP13: 72110 | AQ13: 72110 Marketing:SBC | AR13: 114524.51
D14: =IF(LEFT(E14,1)="1","LTD",IF(LEFT(#REF!,1)="2","INC"," ")) -> LTD | E14: 165039301260 | F14: =_xlfn.NUMBERVALUE(MID(E14,2,5)) -> 65039 | G14: =IF(D14="LTD",_xlfn.XLOOKUP(F14,'TB LTD 12.22'!$E:$E,'TB LTD 12.22'!$F:$F,),_xlfn.XLOOKUP(AJE!F14,'TB INC 12.22'!$B:$B,'TB INC 12.22'!$C:$C,)) -> Referral Fee | H14: =-H13 -> -8189 | P14: =IF(LEFT(Q14,1)="1","LTD","INC") -> LTD | Q14: 1650019900 | R14: =_xlfn.NUMBERVALUE(MID(Q14,2,5)) -> 65001 | S14: =IF(P14="LTD",_xlfn.XLOOKUP(R14,'TB LTD 12.22'!$E:$E,'TB LTD 12.22'!$F:$F,),_xlfn.XLOOKUP(AJE!R14,'TB INC 12.22'!$B:$B,'TB INC 12.22'!$C:$C,)) -> אחזקת משרד | T14: =-(_xlfn.XLOOKUP(Q14,'GL 12.22'!$D:$D,'GL 12.22'!$I:$I,)+_xlfn.XLOOKUP(Q14,'GL 12.22'!$D:$D,'GL 12.22'!$J:$J,)) -> -150503.06 | Y14: 3 | Z14: IC elimination | AA14: =IF(LEFT(AB14,1)="1","LTD","INC") -> LTD | AB14: 180004500 | AC14: =_xlfn.NUMBERVALUE(MID(AB14,2,5)) -> 80004 | AD14: =IF(AA14="LTD",_xlfn.XLOOKUP(AC14,'TB LTD 12.22'!$E:$E,'TB LTD 12.22'!$F:$F,),_xlfn.XLOOKUP(AJE!AC14,'TB INC 12.22'!$B:$B,'TB INC 12.22'!$C:$C,)) -> Silverfort INC Share-based Compensation | AE14: 1500366.6 | AN14: INC | AO14: 280130701160 | AP14: 80130 | AQ14: 80130 General and Administrative: SBC | AR14: 29400.111
P15: =IF(LEFT(Q15,1)="1","LTD","INC") -> LTD | Q15: 1650039900 | R15: =_xlfn.NUMBERVALUE(MID(Q15,2,5)) -> 65003 | S15: =IF(P15="LTD",_xlfn.XLOOKUP(R15,'TB LTD 12.22'!$E:$E,'TB LTD 12.22'!$F:$F,),_xlfn.XLOOKUP(AJE!R15,'TB INC 12.22'!$B:$B,'TB INC 12.22'!$C:$C,)) -> שכירות משרד קומה 26 | T15: =-(_xlfn.XLOOKUP(Q15,'GL 12.22'!$D:$D,'GL 12.22'!$I:$I,)+_xlfn.XLOOKUP(Q15,'GL 12.22'!$D:$D,'GL 12.22'!$J:$J,)) -> -419988.17 | Z15: Ltd SBC | AA15: =IF(LEFT(AB15,1)="1","LTD","INC") -> INC | AB15: 2160301000 | AC15: =_xlfn.NUMBERVALUE(MID(AB15,2,5)) -> 16030 | AD15: =IF(AA15="LTD",_xlfn.XLOOKUP(AC15,'TB LTD 12.22'!$E:$E,'TB LTD 12.22'!$F:$F,),_xlfn.XLOOKUP(AJE!AC15,'TB INC 12.22'!$B:$B,'TB INC 12.22'!$C:$C,)) -> 16030 Option Investment in LTD | AE15: =-AE14 -> -1500366.6 | AN15: INC | AO15: 2300911100 | AP15: 30091 | AQ15: 30091 Additional Paid In capital - Options | AR15: -533237.96
D16: =IF(LEFT(E16,1)="1","LTD",IF(LEFT(#REF!,1)="2","INC"," ")) -> LTD | E16: 135010900 | F16: =_xlfn.NUMBERVALUE(MID(E16,2,5)) -> 35010 | G16: =IF(D16="LTD",_xlfn.XLOOKUP(F16,'TB LTD 12.22'!$E:$E,'TB LTD 12.22'!$F:$F,),_xlfn.XLOOKUP(AJE!F16,'TB INC 12.22'!$B:$B,'TB INC 12.22'!$C:$C,)) -> הכנסות מראש- ביקורת | H16: 67266 | P16: =IF(LEFT(Q16,1)="1","LTD","INC") -> LTD | Q16: 1650049900 | R16: =_xlfn.NUMBERVALUE(MID(Q16,2,5)) -> 65004 | S16: =IF(P16="LTD",_xlfn.XLOOKUP(R16,'TB LTD 12.22'!$E:$E,'TB LTD 12.22'!$F:$F,),_xlfn.XLOOKUP(AJE!R16,'TB INC 12.22'!$B:$B,'TB INC 12.22'!$C:$C,)) -> צרכי משרד | T16: =-(_xlfn.XLOOKUP(Q16,'GL 12.22'!$D:$D,'GL 12.22'!$I:$I,)+_xlfn.XLOOKUP(Q16,'GL 12.22'!$D:$D,'GL 12.22'!$J:$J,)) -> -17297.06
D17: =IF(LEFT(E17,1)="1","LTD",IF(LEFT(#REF!,1)="2","INC"," ")) -> LTD | E17: 165039301260 | F17: =_xlfn.NUMBERVALUE(MID(E17,2,5)) -> 65039 | G17: =IF(D17="LTD",_xlfn.XLOOKUP(F17,'TB LTD 12.22'!$E:$E,'TB LTD 12.22'!$F:$F,),_xlfn.XLOOKUP(AJE!F17,'TB INC 12.22'!$B:$B,'TB INC 12.22'!$C:$C,)) -> Referral Fee | H17: =-H16 -> -67266 | P17: =IF(LEFT(Q17,1)="1","LTD","INC") -> LTD | Q17: 1650339900 | R17: =_xlfn.NUMBERVALUE(MID(Q17,2,5)) -> 65033 | S17: =IF(P17="LTD",_xlfn.XLOOKUP(R17,'TB LTD 12.22'!$E:$E,'TB LTD 12.22'!$F:$F,),_xlfn.XLOOKUP(AJE!R17,'TB INC 12.22'!$B:$B,'TB INC 12.22'!$C:$C,)) -> תקשורת (אינטרנט) | T17: =-(_xlfn.XLOOKUP(Q17,'GL 12.22'!$D:$D,'GL 12.22'!$I:$I,)+_xlfn.XLOOKUP(Q17,'GL 12.22'!$D:$D,'GL 12.22'!$J:$J,)) -> -30281.55 | AN17: INC | AO17: 2160301000 | AP17: 16030 | AQ17: 16030 Option Investment in LTD | AR17: 1500366.6
P18: =IF(LEFT(Q18,1)="1","LTD","INC") -> LTD | Q18: 1652159900 | R18: =_xlfn.NUMBERVALUE(MID(Q18,2,5)) -> 65215 | S18: =IF(P18="LTD",_xlfn.XLOOKUP(R18,'TB LTD 12.22'!$E:$E,'TB LTD 12.22'!$F:$F,),_xlfn.XLOOKUP(AJE!R18,'TB INC 12.22'!$B:$B,'TB INC 12.22'!$C:$C,)) -> ארנונה | T18: =-(_xlfn.XLOOKUP(Q18,'GL 12.22'!$D:$D,'GL 12.22'!$I:$I,)+_xlfn.XLOOKUP(Q18,'GL 12.22'!$D:$D,'GL 12.22'!$J:$J,)) -> -18618.43 | AN18: INC | AO18: 2300911100 | AP18: 30091 | AQ18: 30091 Additional Paid In capital - Options | AR18: -1500366.6
D19: =IF(LEFT(E19,1)="1","LTD",IF(LEFT(#REF!,1)="2","INC"," ")) -> LTD | E19: 13500071000 | F19: =_xlfn.NUMBERVALUE(MID(E19,2,5)) -> 35000 | G19: =IF(D19="LTD",_xlfn.XLOOKUP(F19,'TB LTD 12.22'!$E:$E,'TB LTD 12.22'!$F:$F,),_xlfn.XLOOKUP(AJE!F19,'TB INC 12.22'!$B:$B,'TB INC 12.22'!$C:$C,)) -> הוצאות לשלם | H19: =-(H13+H16) -> -75455 | P19: =IF(LEFT(Q19,1)="1","LTD","INC") -> LTD | Q19: 1670149900 | R19: =_xlfn.NUMBERVALUE(MID(Q19,2,5)) -> 67014 | S19: =IF(P19="LTD",_xlfn.XLOOKUP(R19,'TB LTD 12.22'!$E:$E,'TB LTD 12.22'!$F:$F,),_xlfn.XLOOKUP(AJE!R19,'TB INC 12.22'!$B:$B,'TB INC 12.22'!$C:$C,)) -> חשמל | T19: =-(_xlfn.XLOOKUP(Q19,'GL 12.22'!$D:$D,'GL 12.22'!$I:$I,)+_xlfn.XLOOKUP(Q19,'GL 12.22'!$D:$D,'GL 12.22'!$J:$J,)) -> -10593.65
D20: =IF(LEFT(E20,1)="1","LTD",IF(LEFT(#REF!,1)="2","INC"," ")) -> LTD | E20: 165039301260 | F20: =_xlfn.NUMBERVALUE(MID(E20,2,5)) -> 65039 | G20: =IF(D20="LTD",_xlfn.XLOOKUP(F20,'TB LTD 12.22'!$E:$E,'TB LTD 12.22'!$F:$F,),_xlfn.XLOOKUP(AJE!F20,'TB INC 12.22'!$B:$B,'TB INC 12.22'!$C:$C,)) -> Referral Fee | H20: =-H19 -> 75455 | P20: =IF(LEFT(Q20,1)="1","LTD","INC") -> LTD | Q20: 1670399900 | R20: =_xlfn.NUMBERVALUE(MID(Q20,2,5)) -> 67039 | S20: =IF(P20="LTD",_xlfn.XLOOKUP(R20,'TB LTD 12.22'!$E:$E,'TB LTD 12.22'!$F:$F,),_xlfn.XLOOKUP(AJE!R20,'TB INC 12.22'!$B:$B,'TB INC 12.22'!$C:$C,)) -> שכ"ד קומה 27 | T20: =-(_xlfn.XLOOKUP(Q20,'GL 12.22'!$D:$D,'GL 12.22'!$I:$I,)+_xlfn.XLOOKUP(Q20,'GL 12.22'!$D:$D,'GL 12.22'!$J:$J,)) -> -117557.9
P21: =IF(LEFT(Q21,1)="1","LTD","INC") -> LTD | Q21: 1670359900 | R21: =_xlfn.NUMBERVALUE(MID(Q21,2,5)) -> 67035 | S21: =IF(P21="LTD",_xlfn.XLOOKUP(R21,'TB LTD 12.22'!$E:$E,'TB LTD 12.22'!$F:$F,),_xlfn.XLOOKUP(AJE!R21,'TB INC 12.22'!$B:$B,'TB INC 12.22'!$C:$C,)) -> שכירות משרדים אוסטרליה | T21: =-(_xlfn.XLOOKUP(Q21,'GL 12.22'!$D:$D,'GL 12.22'!$I:$I,)+_xlfn.XLOOKUP(Q21,'GL 12.22'!$D:$D,'GL 12.22'!$J:$J,)) -> -6147.76 | AL21: 2 | AM21: TP | AN21: INC | AO21: 2400102000 | AP21: 40010 | AQ21: 40010 IC revenue | AR21: -5666110.8
B22: 5 | C22: INC Rev Adj | D22: =IF(LEFT(E22,1)="1","LTD","INC") -> INC | E22: 2400002000 | F22: =_xlfn.NUMBERVALUE(MID(E22,2,5)) -> 40000 | G22: =IF(D22="INC",VLOOKUP(_xlfn.NUMBERVALUE(F22),'[196]TB INC 02.23'!$B:$C,2,0),VLOOKUP(F22,'[196]TB LTD 02.23'!$E:$F,2,0)) -> 40000 Software Sales | H22: =-K24 -> 6792.0628 | J22: should be | K22: 5842923.5 | P22: =IF(LEFT(Q22,1)="1","LTD","INC") -> LTD | Q22: 167011991160 | R22: =_xlfn.NUMBERVALUE(MID(Q22,2,5)) -> 67011 | S22: =IF(P22="LTD",_xlfn.XLOOKUP(R22,'TB LTD 12.22'!$E:$E,'TB LTD 12.22'!$F:$F,),_xlfn.XLOOKUP(AJE!R22,'TB INC 12.22'!$B:$B,'TB INC 12.22'!$C:$C,)) -> החזר מילואים | T22: =-(_xlfn.XLOOKUP(Q22,'GL 12.22'!$D:$D,'GL 12.22'!$I:$I,)+_xlfn.XLOOKUP(Q22,'GL 12.22'!$D:$D,'GL 12.22'!$J:$J,)) -> 10554.94 | AN22: INC | AO22: 216000500 | AP22: 16000 | AQ22: 16000 Intercompany Silverfort LTD | AR22: 5666110.8
D23: =IF(LEFT(E23,1)="1","LTD","INC") -> INC | E23: 222005900 | F23: =_xlfn.NUMBERVALUE(MID(E23,2,5)) -> 22005 | G23: =IF(D23="INC",VLOOKUP(_xlfn.NUMBERVALUE(F23),'[196]TB INC 02.23'!$B:$C,2,0),VLOOKUP(F23,'[196]TB LTD 02.23'!$E:$F,2,0)) -> 22005 Deferred Revenue:Software Sales | H23: =-H22 -> -6792.0628 | J23: books | K23: ='TB INC 12.22'!F53 -> -5849715.5 | P23: =IF(LEFT(Q23,1)="1","LTD","INC") -> LTD | Q23: 1650289900 | R23: =_xlfn.NUMBERVALUE(MID(Q23,2,5)) -> 65028 | S23: =IF(P23="LTD",_xlfn.XLOOKUP(R23,'TB LTD 12.22'!$E:$E,'TB LTD 12.22'!$F:$F,),_xlfn.XLOOKUP(AJE!R23,'TB INC 12.22'!$B:$B,'TB INC 12.22'!$C:$C,)) -> אירוח אורחים מחו"ל | T23: =-(_xlfn.XLOOKUP(Q23,'GL 12.22'!$D:$D,'GL 12.22'!$I:$I,)+_xlfn.XLOOKUP(Q23,'GL 12.22'!$D:$D,'GL 12.22'!$J:$J,)) -> -3845.17
K24: =K22+K23 -> -6792.0628 | P24: =IF(LEFT(Q24,1)="1","LTD","INC") -> LTD | Q24: 1650619900 | R24: =_xlfn.NUMBERVALUE(MID(Q24,2,5)) -> 65061 | S24: =IF(P24="LTD",_xlfn.XLOOKUP(R24,'TB LTD 12.22'!$E:$E,'TB LTD 12.22'!$F:$F,),_xlfn.XLOOKUP(AJE!R24,'TB INC 12.22'!$B:$B,'TB INC 12.22'!$C:$C,)) -> ניהול אופציות ומניות Trust & Stock Admin | T24: =-(_xlfn.XLOOKUP(Q24,'GL 12.22'!$D:$D,'GL 12.22'!$I:$I,)+_xlfn.XLOOKUP(Q24,'GL 12.22'!$D:$D,'GL 12.22'!$J:$J,)) -> -5644.03 | AN24: LTD | AO24: 180001500 | AP24: 80001 | AQ24: Silverfort INC | AR24: -5666110.8
B25: 6 | C25: Lease asset classification | D25: =IF(LEFT(E25,1)="1","LTD",IF(LEFT(#REF!,1)="2","INC"," ")) -> LTD | E25: 1250301600 | F25: =_xlfn.NUMBERVALUE(MID(E25,2,5)) -> 25030 | G25: =IF(D25="LTD",_xlfn.XLOOKUP(F25,'TB LTD 12.22'!$E:$E,'TB LTD 12.22'!$F:$F,),_xlfn.XLOOKUP(AJE!F25,'TB INC 12.22'!$B:$B,'TB INC 12.22'!$C:$C,)) -> Right-of-use asset | H25: -2201963.3 | P25: =IF(LEFT(Q25,1)="1","LTD","INC") -> LTD | Q25: 1670229900 | R25: =_xlfn.NUMBERVALUE(MID(Q25,2,5)) -> 67022 | S25: =IF(P25="LTD",_xlfn.XLOOKUP(R25,'TB LTD 12.22'!$E:$E,'TB LTD 12.22'!$F:$F,),_xlfn.XLOOKUP(AJE!R25,'TB INC 12.22'!$B:$B,'TB INC 12.22'!$C:$C,)) -> QBR/SKO IL (Kikoff Sales) 2021-22 | T25: =-(_xlfn.XLOOKUP(Q25,'GL 12.22'!$D:$D,'GL 12.22'!$I:$I,)+_xlfn.XLOOKUP(Q25,'GL 12.22'!$D:$D,'GL 12.22'!$J:$J,)) -> -37504.93 | AN25: LTD | AO25: 1601003000 | AP25: 60100 | AQ25: TP Cost of Sales | AR25: 4961861.1
